Workbook
Name Autor_Jesus_Tassarolo: "Modelo financiero de embudos · creado por Jesús Tassarolo · TooAudience · youtube.com/@JesusTassaroloSinFiltro"

Sheet Inicio
B1: © Jesús Tassarolo · TooAudience · youtube.com/@JesusTassaroloSinFiltro · uso personal; no redistribuir modificado
B2: Modelo financiero · Embudo low-ticket con bumps y upsells
B3: Anuncios → página de ventas (VSL) → checkout → producto principal + bumps + OTOs + ascenso
B5: Para qué sirve este modelo
B6: Es el modelo financiero de un embudo de venta directa: anuncios que llevan a una página de ventas con video (VSL), un producto principal de precio bajo y una escalera de bumps, OTOs y un programa de ascenso. Con tus números (o con el ejemplo cargado) te dice cuánto vale cada visita que comprás con publicidad, hasta cuánto podés pagar por visita y por cada etapa siguiente, cuánto invertir para una meta de ventas, cuánta caja necesitás y qué palanca mejora más la ganancia.
B7: La unidad que comprás es la visita a la página. El número que manda es la diferencia entre lo que deja cada comprador sumando toda la escalera (AOV neto) y lo que te cuesta conseguirlo (CPA).
B9: Cómo usarlo en 6 pasos
B10: 1. Andá a Supuestos y reemplazá el ejemplo por tus números. Si todavía no tenés datos, dejá el escenario en 1 (conservador) y usá Benchmarks como referencia.
B11: 2. Mirá Resumen: ganancia del mes, ROAS, el techo y el objetivo de costo por visita, y el semáforo. Después Embudo: todos los pasos en orden con cuántos pasan, qué porcentaje se pierde y cuánto cuesta cada paso.
B12: 3. Abrí Escenarios para ver qué pasa si cambia el precio, la conversión o el costo. Las celdas amarillas de cada tabla se pueden cambiar.
B13: 4. Abrí Sensibilidad para saber qué variable conviene trabajar primero.
B14: 5. Antes de invertir, mirá Proyección 12 meses: la caja necesaria es la plata que tenés que tener para no frenar la pauta mientras cobrás. Si da 0, el embudo se autofinancia.
... B46: Este modelo se comparte para que lo uses con tus números. Si lo compartís, dejá esta línea: es la forma de saber de dónde salió.

Sheet Resumen
B1: © Jesús Tassarolo · TooAudience · youtube.com/@JesusTassaroloSinFiltro · uso personal; no redistribuir modificado
B2: Resumen: lo que hay que mirar
B3: Todo sale de Modelo con los supuestos del escenario en uso. Cambiá Supuestos y esto se actualiza.
B5: Indicador | C5: Valor | D5: Qué significa
B6: Resultado del mes
B7: Ganancia del período | C7: ='Modelo'!$C$41 | D7: Cash neto menos costos y menos inversión. Lo que queda.
B8: ROAS sobre cash neto | C8: ='Modelo'!$C$43 | D8: Cada dólar invertido vuelve como esto, ya neto.
B9: ROAS sobre facturado | C9: ='Modelo'!$C$42 | D9: Sobre facturado. Se infla con cuotas y comisiones: no decidas con este.
B10: Ventas del producto principal | C10: ='Modelo'!$C$10 | D10: Ventas del producto principal por mes.
B11: Unit economics
B12: Facturado por comprador (AOV) | C12: ='Modelo'!$C$30 | D12: Facturado por comprador sumando toda la escalera.
B13: Costo por comprador (CPA) | C13: ='Modelo'!$C$12 | D13: Lo que te cuesta cada comprador.
B14: AOV neto − CPA (lo que queda por comprador) | C14: ='Modelo'!$C$54 | D14: Si es negativo, cada venta pierde plata.
B15: Valor neto por visita | C15: ='Modelo'!$C$47 | D15: Lo que vale una visita en cash neto.
B16: Las dos caras de cada número
B17: Costo por visita | C17: ='Modelo'!$C$7 | D17: Lo que pagás por cada visita.
B18: Ganancia por visita | C18: ='Modelo'!$C$60 | D18: Lo que te queda por cada visita después de todo. La métrica más valiosa del embudo.
B19: Costo por cliente (CPA) | C19: ='Modelo'!$C$12 | D19: Lo que pagás por cada comprador.
B20: Ganancia por cliente | C20: ='Modelo'!$C$62 | D20: Lo que te queda por cada comprador después de todo.
B21: Order value (AOV) | C21: ='Modelo'!$C$30 | D21: Facturado por comprador con toda la escalera.
B22: Order value neto (AOV neto) | C22: ='Modelo'!$C$53 | D22: Lo mismo después de comisiones, reembolsos y costos por unidad.
B23: Hasta cuánto pagar
B24: Techo de costo por visita (break-even) | C24: ='Modelo'!$C$48 | D24: Costo por visita donde no ganás ni perdés.
B25: Objetivo de costo por visita | C25: ='Modelo'!$C$49 | D25: A este costo o menos estás en verde.
B26: Techo de costo por comprador (CPA máximo) | C26: ='Modelo'!$C$51 | D26: CPA máximo si lo demás se mantiene.
B27: Semáforo del costo por visita actual | C27: ='Modelo'!$C$56 | D27: Tu costo por visita actual contra techo y objetivo.
B28: Cuánto invertir y cuánta caja
B29: Inversión necesaria para la meta de ventas (al costo actual) | C29: ='Modelo'!$C$57 | D29: Para llegar a la meta de ventas de Supuestos, al costo actual.
B30: Caja que hay que tener (peor momento de la proyección) | C30: ='Proyección 12 meses'!$C$18 | D30: Si da 0, el embudo se autofinancia: cada mes cobra más de lo que invierte.
B31: Saldo mínimo de caja con tu caja inicial | C31: ='Proyección 12 meses'!$C$19 | D31: Si es negativo, la caja inicial no alcanza.
B32: Ganancia acumulada en 12 meses | C32: ='Proyección 12 meses'!$C$20 | D32: Con la inversión creciendo según el supuesto.
B34: Recomendación según el semáforo | C34: =IF('Modelo'!$C$56="VERDE","Sostener o subir un escalón (+25 %) y medir 7 días",IF('Modelo'!$C$56="AMARILLO","No subir. Si el costo está bien, el ROAS no llega al objetivo: mirá Sensibilidad. Si no, revisar en orden: CPM, creativo, página",IF('Modelo'!$C$56="ROJO","Bajar un escalón (−25 %) y arreglar antes de volver a subir","")))
B36: Modelo financiero de embudos · creado por Jesús Tassarolo · TooAudience · youtube.com/@JesusTassaroloSinFiltro · v1.2 · octubre 2026

Sheet Embudo
B1: © Jesús Tassarolo · TooAudience · youtube.com/@JesusTassaroloSinFiltro · uso personal; no redistribuir modificado
B2: Embudo: todos los pasos, cuántos pasan y, por cada uno, qué pagás, qué te queda y hasta cuánto podrías pagar
B3: Cada fila es un paso del embudo en orden. '% que pasa' compara con el paso anterior (o con el que dice la nota). Tres números por paso: lo que pagás hoy por cada uno (inversión ÷ cantidad), lo que te queda por cada uno (ganancia ÷ cantidad) y lo máximo que podrías pagar (el techo: lo que cada uno genera en cash neto). Techo = costo + ganancia + fijos repartidos.
B5: Paso | C5: Cantidad | D5: % que pasa | E5: % acumulado | F5: Costo por paso (pagás hoy) | G5: Ganancia por paso (te queda) | H5: Techo por paso (máximo a pagar) | I5: Qué se paga acá / cómo se lee
B6: Visitas a la página de ventas (VSL) | C6: ='Modelo'!$C$8 | D6: — | E6: =IF('Modelo'!$C$8=0,0,'Modelo'!$C$8/'Modelo'!$C$8) | F6: =IF('Modelo'!$C$8=0,0,'Supuestos'!$C$8*1/'Modelo'!$C$8) | G6: =IF('Modelo'!$C$8=0,0,'Modelo'!$C$41*1/'Modelo'!$C$8) | H6: =IF('Modelo'!$C$8=0,0,'Modelo'!$C$47*'Modelo'!$C$8*1/'Modelo'!$C$8) | I6: La unidad que compra la pauta. Costo por visita.
B7: Abren el checkout | C7: ='Modelo'!$C$9 | D7: =IF('Modelo'!$C$8=0,0,'Modelo'!$C$9/'Modelo'!$C$8) | E7: =IF('Modelo'!$C$8=0,0,'Modelo'!$C$9/'Modelo'!$C$8) | F7: =IF('Modelo'!$C$9=0,0,'Supuestos'!$C$8*1/'Modelo'!$C$9) | G7: =IF('Modelo'!$C$9=0,0,'Modelo'!$C$41*1/'Modelo'!$C$9) | H7: =IF('Modelo'!$C$9=0,0,'Modelo'!$C$47*'Modelo'!$C$8*1/'Modelo'!$C$9) | I7: Costo por checkout. Si se pierde mucho acá, es la VSL.
B8: Compran el producto principal | C8: ='Modelo'!$C$10 | D8: =IF('Modelo'!$C$9=0,0,'Modelo'!$C$10/'Modelo'!$C$9) | E8: =IF('Modelo'!$C$8=0,0,'Modelo'!$C$10/'Modelo'!$C$8) | F8: =IF('Modelo'!$C$10=0,0,'Supuestos'!$C$8*1/'Modelo'!$C$10) | G8: =IF('Modelo'!$C$10=0,0,'Modelo'!$C$41*1/'Modelo'!$C$10) | H8: =IF('Modelo'!$C$10=0,0,'Modelo'!$C$47*'Modelo'!$C$8*1/'Modelo'!$C$10) | I8: CPA: costo por comprador. Si se pierde mucho acá, es el checkout o la oferta.
B9: Toman el bump 1 | C9: ='Modelo'!$C$15 | D9: =IF('Modelo'!$C$10=0,0,'Modelo'!$C$15/'Modelo'!$C$10) | E9: =IF('Modelo'!$C$8=0,0,'Modelo'!$C$15/'Modelo'!$C$8) | F9: sin costo propio | G9: — | H9: — | I9: Sobre compradores del principal. Se pagó con el CPA; suma al AOV.
B10: Toman el bump 2 | C10: ='Modelo'!$C$17 | D10: =IF('Modelo'!$C$10=0,0,'Modelo'!$C$17/'Modelo'!$C$10) | E10: =IF('Modelo'!$C$8=0,0,'Modelo'!$C$17/'Modelo'!$C$8) | F10: sin costo propio | G10: — | H10: — | I10: Sobre compradores del principal.
B11: Toman la OTO 1 | C11: ='Modelo'!$C$19 | D11: =IF('Modelo'!$C$10=0,0,'Modelo'!$C$19/'Modelo'!$C$10) | E11: =IF('Modelo'!$C$8=0,0,'Modelo'!$C$19/'Modelo'!$C$8) | F11: sin costo propio | G11: — | H11: — | I11: Página 1 después del pago.
B12: Toman la OTO 2 | C12: ='Modelo'!$C$21 | D12: =IF('Modelo'!$C$10=0,0,'Modelo'!$C$21/'Modelo'!$C$10) | E12: =IF('Modelo'!$C$8=0,0,'Modelo'!$C$21/'Modelo'!$C$8) | F12: sin costo propio | G12: — | H12: — | I12: Página 2 (downsell de la OTO 1).
B13: Toman la OTO 3 | C13: ='Modelo'!$C$23 | D13: =IF('Modelo'!$C$10=0,0,'Modelo'!$C$23/'Modelo'!$C$10) | E13: =IF('Modelo'!$C$8=0,0,'Modelo'!$C$23/'Modelo'!$C$8) | F13: sin costo propio | G13: — | H13: — | I13: Página 3.
B14: Toman la OTO 4 | C14: ='Modelo'!$C$25 | D14: =IF('Modelo'!$C$10=0,0,'Modelo'!$C$25/'Modelo'!$C$10) | E14: =IF('Modelo'!$C$8=0,0,'Modelo'!$C$25/'Modelo'!$C$8) | F14: sin costo propio | G14: — | H14: — | I14: Página 4.
B15: Ascienden al programa | C15: ='Modelo'!$C$27 | D15: =IF('Modelo'!$C$10=0,0,'Modelo'!$C$27/'Modelo'!$C$10) | E15: =IF('Modelo'!$C$8=0,0,'Modelo'!$C$27/'Modelo'!$C$8) | F15: sin costo propio | G15: — | H15: — | I15: Sobre compradores del principal. El AOV neto resultante contra el CPA es lo que decide el embudo.
B17: Comprobalo con la fila de la unidad: costo + ganancia + fijos repartidos = techo | F17: =F6 | G17: =G6 | H17: =F6+G6+'Supuestos'!$C$37/'Modelo'!$C$8 | I17: Techo = costo + ganancia + fijos ÷ unidades. Lo que falta entre (costo + ganancia) y el techo son los costos fijos repartidos entre las unidades.
B18: Cómo se lee
B19: Cantidad: cuántas acciones o personas hubo en ese paso con los supuestos del escenario en uso.
B20: % que pasa: de los que estaban en el paso anterior (o en el paso que indica la nota), cuántos llegan a este. % acumulado: cuántos llegan a este paso por cada 100 unidades que compra la pauta.
B21: Costo por paso: inversión ÷ cantidad. Es lo que te está costando hoy cada persona que llega a ese paso.
B22: Ganancia por paso: ganancia del período ÷ cantidad. Lo que te queda por cada persona de ese paso después de pagar la pauta, las comisiones, los reembolsos y los fijos. La ganancia por visita es la métrica más valiosa del embudo: resume todo lo que pasa después.
B23: Techo por paso: lo que cada persona de ese paso genera en cash neto (cash neto menos costos por unidad, dividido por la cantidad). Es lo máximo que podrías pagar por ese paso antes de que la ganancia llegue a cero, si lo demás se mantiene. Por eso siempre es mayor que la ganancia: techo = costo + ganancia + fijos repartidos.
B24: Los bumps, las OTOs y la ascensión no tienen costo propio: se pagan con el CPA del comprador principal y se miden por lo que suman al AOV.

Sheet Supuestos
B1: © Jesús Tassarolo · TooAudience · youtube.com/@JesusTassaroloSinFiltro · uso personal; no redistribuir modificado
B2: Supuestos
B3: Celdas amarillas = las editás vos. Celdas azules = se calculan solas. Cada fila dice en qué unidad va y de dónde sale el valor del ejemplo.
B5: Supuesto | C5: Valor en uso | D5: Conservador | E5: Base | F5: Optimista | G5: Unidad | H5: Nota / fuente del ejemplo
B6: Escenario en uso (1 = conservador · 2 = base · 3 = optimista) | C6: 2 | G6: 1 / 2 / 3 | H6: Cambia todas las filas que tienen tres valores. Si una fila no tiene tres valores, se usa el de 'Valor en uso'.
B7: 1. Inversión y tráfico
B8: Inversión en publicidad por mes | C8: 9000 | G8: USD / mes | H8: El ejemplo invierte 300 USD por día.
B9: Costo por visita a la página de ventas (VSL) | C9: =IF('Supuestos'!$C$6=1,D9,IF('Supuestos'!$C$6=2,E9,F9)) | D9: 0.4 | E9: 0.3 | F9: 0.22 | G9: USD / visita | H9: Lo que pagás por cada persona que llega a la página. En tráfico frío hispano se mueve entre 0,20 y 0,50.
B11: 2. Conversión de la página de ventas
B12: % de visitas que llegan al checkout | C12: =IF('Supuestos'!$C$6=1,D12,IF('Supuestos'!$C$6=2,E12,F12)) | D12: 0.025 | E12: 0.035 | F12: 0.045 | G12: % | H12: Visitas que tocan 'comprar' y abren el checkout.
B13: % de checkouts que terminan en compra | C13: =IF('Supuestos'!$C$6=1,D13,IF('Supuestos'!$C$6=2,E13,F13)) | D13: 0.2 | E13: 0.26 | F13: 0.3 | G13: % | H13: Checkouts que pagan.
B15: 3. Escalera: producto principal → bumps 1 y 2 → OTO 1 a 4 → ascensión (precio y % sobre compradores del principal)
B16: Producto principal: precio | C16: 37 | G16: USD | H16: El producto que vende la VSL. Todo lo demás se mide como % de sus compradores.
B17: Bump 1: precio | C17: 17 | G17: USD | H17: Oferta extra en el checkout del principal (una casilla). % sobre compradores del principal.
B18: Bump 1: % de compradores que lo toman | C18: =IF('Supuestos'!$C$6=1,D18,IF('Supuestos'!$C$6=2,E18,F18)) | D18: 0.18 | E18: 0.25 | F18: 0.35 | G18: %
B19: Bump 2: precio | C19: 17 | G19: USD | H19: Segundo bump en el mismo checkout. Rinde algo menos que el primero.
B20: Bump 2: % de compradores que lo toman | C20: =IF('Supuestos'!$C$6=1,D20,IF('Supuestos'!$C$6=2,E20,F20)) | D20: 0.12 | E20: 0.18 | F20: 0.25 | G20: %
B21: OTO 1: precio | C21: 47 | G21: USD | H21: Página 1 después del pago: el primer upsell. % sobre compradores del principal.
B22: OTO 1: % de compradores que lo toman | C22: =IF('Supuestos'!$C$6=1,D22,IF('Supuestos'!$C$6=2,E22,F22)) | D22: 0.07 | E22: 0.1 | F22: 0.14 | G22: %
B23: OTO 2: precio | C23: 17 | G23: USD | H23: Página 2: suele ser el downsell de la OTO 1 (más barato). El % va sobre todos los compradores, para simplificar.
B24: OTO 2: % de compradores que lo toman | C24: =IF('Supuestos'!$C$6=1,D24,IF('Supuestos'!$C$6=2,E24,F24)) | D24: 0.04 | E24: 0.06 | F24: 0.09 | G24: %
B25: OTO 3: precio | C25: 97 | G25: USD | H25: Página 3: el segundo upsell.
B26: OTO 3: % de compradores que lo toman | C26: =IF('Supuestos'!$C$6=1,D26,IF('Supuestos'!$C$6=2,E26,F26)) | D26: 0.02 | E26: 0.03 | F26: 0.05 | G26: %
B27: OTO 4: precio | C27: 27 | G27: USD | H27: Página 4: el downsell del segundo upsell.
B28: OTO 4: % de compradores que lo toman | C28: =IF('Supuestos'!$C$6=1,D28,IF('Supuestos'!$C$6=2,E28,F28)) | D28: 0.03 | E28: 0.04 | F28: 0.06 | G28: %
B29: Ascensión (programa de mayor valor): precio | C29: 297 | G29: USD | H29: El upsell de ascensión: el programa que se vende después del embudo, por checkout o por llamada. % sobre compradores del principal.
B30: Ascensión (programa de mayor valor): % de compradores que lo toman | C30: =IF('Supuestos'!$C$6=1,D30,IF('Supuestos'!$C$6=2,E30,F30)) | D30: 0.01 | E30: 0.02 | F30: 0.04 | G30: %
B32: 4. Costos
B33: Comisión de la pasarela o plataforma de pago | C33: 0.1 | G33: % del cash | H33: Hotmart, Stripe, Mercado Pago: lo que se queda la plataforma.
B34: Comisión del equipo de ventas | C34: 0 | G34: % del cash | H34: Sobre el cash cobrado. En este embudo no hay llamadas: 0 %.
B35: Reembolsos y contracargos | C35: 0.05 | G35: % del cash | H35: 5 % es normal en productos digitales. Más de 10 % es un problema de oferta o de expectativa.
B36: Costos por visita (herramientas, WhatsApp, IA) | C36: 0 | G36: USD / visita | H36: Costos que crecen con el volumen. En venta directa suele ser 0.
B37: Costos fijos por mes | C37: 1500 | G37: USD / mes | H37: Equipo, herramientas, edición: lo que pagás aunque no vendas.
B39: 5. Cobranza
B40: % del facturado que entra en el mes 1 | C40: 1 | G40: % | H40: Pago único digital: 100 % en el mes 1.
B41: % que entra en el mes 2 | C41: 0 | G41: % | H41: Cuotas o pagos diferidos.
B42: % que entra en el mes 3 | C42: 0 | G42: % | H42: Los tres deben sumar 100 %.
B44: 6. Objetivos y proyección
B45: ROAS objetivo sobre cash neto | C45: 2 | G45: x | H45: El retorno mínimo que querés por cada dólar invertido, después de comisiones y reembolsos. Entra en el semáforo: sin llegar a este ROAS no hay verde.
B46: Margen de seguridad | C46: 0.3 | G46: % | H46: Colchón entre el techo (donde no ganás ni perdés) y el objetivo. 30 % es el estándar que usamos.
B47: Meta de ventas del producto principal | C47: 500 | G47: ventas / mes | H47: Para calcular cuánto invertir.
B48: Crecimiento de la inversión por mes (proyección) | C48: 0.1 | G48: % / mes | H48: Cuánto sube la inversión cada mes en la proyección. 10 % por mes es un ritmo prudente; más de 25 % suele encarecer el CPM.
B49: Caja inicial | C49: 5000 | G49: USD | H49: Con cuánta plata arrancás. La proyección te dice si alcanza.

Sheet Modelo
B1: © Jesús Tassarolo · TooAudience · youtube.com/@JesusTassaroloSinFiltro · uso personal; no redistribuir modificado
B2: Modelo: la cadena completa del embudo
B3: Cada fila es una etapa o un resultado. No se edita: todo sale de Supuestos. La columna de la derecha dice cómo se calcula.
B5: Etapa / resultado | C5: Valor | D5: Cómo se calcula
B6: Tráfico y unidades
B7: Costo por visita (unidad de adquisición) | C7: ='Supuestos'!$C$9 | D7: El supuesto 'costo por visita'.
B8: Visitas a la página de ventas | C8: =IF('Modelo'!$C$7=0,0,'Supuestos'!$C$8/'Modelo'!$C$7) | D8: Inversión ÷ costo por visita.
B9: Checkouts iniciados | C9: ='Modelo'!$C$8*'Supuestos'!$C$12 | D9: Visitas × % que llega al checkout.
B10: Ventas del producto principal | C10: ='Modelo'!$C$9*'Supuestos'!$C$13 | D10: Checkouts × % que compra.
B11: % de visitas que compran | C11: =IF('Modelo'!$C$8=0,0,'Modelo'!$C$10/'Modelo'!$C$8) | D11: Ventas ÷ visitas. Las dos conversiones multiplicadas.
B12: Costo por comprador (CPA) | C12: =IF('Modelo'!$C$10=0,0,'Supuestos'!$C$8/'Modelo'!$C$10) | D12: Inversión ÷ ventas del principal.
B13: Facturación por producto
B14: Facturado: producto principal | C14: ='Modelo'!$C$10*'Supuestos'!$C$16 | D14: Ventas × precio.
B15: Ventas: Bump 1 | C15: ='Modelo'!$C$10*'Supuestos'!$C$18 | D15: Compradores del principal × % que lo toma.
B16: Facturado: Bump 1 | C16: ='Modelo'!$C$15*'Supuestos'!$C$17 | D16: Ventas × precio.
B17: Ventas: Bump 2 | C17: ='Modelo'!$C$10*'Supuestos'!$C$20 | D17: Compradores del principal × % que lo toma.
B18: Facturado: Bump 2 | C18: ='Modelo'!$C$17*'Supuestos'!$C$19 | D18: Ventas × precio.
B19: Ventas: OTO 1 | C19: ='Modelo'!$C$10*'Supuestos'!$C$22 | D19: Compradores del principal × % que lo toma.
B20: Facturado: OTO 1 | C20: ='Modelo'!$C$19*'Supuestos'!$C$21 | D20: Ventas × precio.
B21: Ventas: OTO 2 | C21: ='Modelo'!$C$10*'Supuestos'!$C$24 | D21: Compradores del principal × % que lo toma.
B22: Facturado: OTO 2 | C22: ='Modelo'!$C$21*'Supuestos'!$C$23 | D22: Ventas × precio.
B23: Ventas: OTO 3 | C23: ='Modelo'!$C$10*'Supuestos'!$C$26 | D23: Compradores del principal × % que lo toma.
B24: Facturado: OTO 3 | C24: ='Modelo'!$C$23*'Supuestos'!$C$25 | D24: Ventas × precio.
B25: Ventas: OTO 4 | C25: ='Modelo'!$C$10*'Supuestos'!$C$28 | D25: Compradores del principal × % que lo toma.
B26: Facturado: OTO 4 | C26: ='Modelo'!$C$25*'Supuestos'!$C$27 | D26: Ventas × precio.
B27: Ventas: Ascensión (programa de mayor valor) | C27: ='Modelo'!$C$10*'Supuestos'!$C$30 | D27: Compradores del principal × % que lo toma.
B28: Facturado: Ascensión (programa de mayor valor) | C28: ='Modelo'!$C$27*'Supuestos'!$C$29 | D28: Ventas × precio.
B29: Facturado total | C29: ='Modelo'!$C$14+'Modelo'!$C$16+'Modelo'!$C$18+'Modelo'!$C$20+'Modelo'!$C$22+'Modelo'!$C$24+'Modelo'!$C$26+'Modelo'!$C$28 | D29: Suma de todos los productos.
B30: Facturado por comprador (AOV) | C30: =IF('Modelo'!$C$10=0,0,'Modelo'!$C$29/'Modelo'!$C$10) | D30: Facturado total ÷ ventas del principal.
B31: AOV ÷ precio del principal | C31: =IF('Supuestos'!$C$16=0,0,'Modelo'!$C$30/'Supuestos'!$C$16) | D31: Cuánto multiplica la escalera al precio del front.
B32: Ventas del principal por visita (para la proyección) | C32: =IF('Modelo'!$C$8=0,0,'Modelo'!$C$10/'Modelo'!$C$8) | D32: Igual a '% de visitas que compran'.
B33: Facturado por visita | C33: =IF('Modelo'!$C$8=0,0,'Modelo'!$C$29/'Modelo'!$C$8) | D33: Facturado total ÷ visitas.
B34: Cash, costos y ganancia del período
B35: Cash a cobrar (facturado × cobranza completa) | C35: ='Modelo'!$C$29*('Supuestos'!$C$40+'Supuestos'!$C$41+'Supuestos'!$C$42) | D35: Facturado × (mes 1 + mes 2 + mes 3). Si la cobranza suma 100 %, es igual al facturado.
B36: Cash que entra en el primer mes | C36: ='Modelo'!$C$29*'Supuestos'!$C$40 | D36: Facturado × % del mes 1.
B37: Comisiones (pasarela + ventas) | C37: ='Modelo'!$C$35*('Supuestos'!$C$33+'Supuestos'!$C$34) | D37: Cash × (pasarela + equipo de ventas).
B38: Reembolsos | C38: ='Modelo'!$C$35*'Supuestos'!$C$35 | D38: Cash × % de reembolsos.
B39: Cash neto | C39: ='Modelo'!$C$35*(1-'Supuestos'!$C$33-'Supuestos'!$C$34-'Supuestos'!$C$35) | D39: Cash − comisiones − reembolsos. La base de verdad.
B40: Costos por visita (herramientas, WhatsApp, IA) | C40: ='Modelo'!$C$8*'Supuestos'!$C$36 | D40: Visitas × costo por visita.
B41: Ganancia del período | C41: ='Modelo'!$C$39-'Modelo'!$C$40-'Supuestos'!$C$37-'Supuestos'!$C$8 | D41: Cash neto − costos por unidad − fijos − inversión.
B42: ROAS sobre facturado | C42: =IF('Supuestos'!$C$8=0,0,'Modelo'!$C$29/'Supuestos'!$C$8) | D42: Facturado ÷ inversión. El número que más se infla: no decidas con este.
B43: ROAS sobre cash neto | C43: =IF('Supuestos'!$C$8=0,0,'Modelo'!$C$39/'Supuestos'!$C$8) | D43: Cash neto ÷ inversión. Con este se decide.
B44: Margen sobre cash | C44: =IF('Modelo'!$C$35=0,0,'Modelo'!$C$41/'Modelo'!$C$35) | D44: Ganancia ÷ cash.
B45: ¿Cumple el ROAS objetivo? | C45: =IF('Modelo'!$C$43>='Supuestos'!$C$45,"SÍ","NO") | D45: ROAS sobre cash neto contra el objetivo de Supuestos.
B46: Cuánto vale cada unidad y hasta cuánto pagar
B47: Valor neto por visita | C47: =IF('Modelo'!$C$8=0,0,('Modelo'!$C$39-'Modelo'!$C$40)/'Modelo'!$C$8) | D47: (Cash neto − costos por unidad) ÷ visitas. Lo que vale una visita.
B48: Techo de costo por visita (break-even) | C48: ='Modelo'!$C$47 | D48: Igual al valor neto por visita: pagando esto no ganás ni perdés.
B49: Objetivo de costo por visita | C49: ='Modelo'!$C$48/(1+'Supuestos'!$C$46) | D49: Techo ÷ (1 + margen de seguridad).
B50: Techo de costo por checkout | C50: =IF('Supuestos'!$C$12=0,0,'Modelo'!$C$47/'Supuestos'!$C$12) | D50: Valor por visita ÷ % que llega al checkout.
B51: Techo de costo por comprador (CPA máximo) | C51: =IF('Modelo'!$C$11=0,0,'Modelo'!$C$47/'Modelo'!$C$11) | D51: Valor por visita ÷ % de visitas que compran.
B52: Objetivo de CPA | C52: ='Modelo'!$C$51/(1+'Supuestos'!$C$46) | D52: CPA máximo ÷ (1 + margen de seguridad).
B53: Cash neto por comprador (AOV neto) | C53: =IF('Modelo'!$C$10=0,0,('Modelo'!$C$39-'Modelo'!$C$40)/'Modelo'!$C$10) | D53: Lo que deja cada comprador después de comisiones y reembolsos.
B54: AOV neto − CPA (lo que queda por comprador) | C54: ='Modelo'!$C$53-'Modelo'!$C$12 | D54: Si es negativo, perdés plata con cada venta.
B55: Semáforo y cuánto invertir
B56: Semáforo del costo por visita actual | C56: =IF('Modelo'!$C$7>'Modelo'!$C$48,"ROJO",IF(AND('Modelo'!$C$7<='Modelo'!$C$49,'Modelo'!$C$43>='Supuestos'!$C$45),"VERDE","AMARILLO")) | D56: Rojo: costo > techo. Verde: costo ≤ objetivo y ROAS sobre cash neto ≥ objetivo. Amarillo: el resto.
B57: Inversión necesaria para la meta de ventas (al costo actual) | C57: =IF('Modelo'!$C$11=0,"inalcanzable con estos supuestos",'Supuestos'!$C$47/'Modelo'!$C$11*'Modelo'!$C$7) | D57: Meta ÷ % de visitas que compran × costo por visita.
B58: Inversión para la meta al costo objetivo (lo máximo que conviene pagar) | C58: =IF('Modelo'!$C$11=0,"inalcanzable con estos supuestos",'Supuestos'!$C$47/'Modelo'!$C$11*'Modelo'!$C$49) | D58: Lo mismo, al costo objetivo.
B59: Ganancia por paso (las dos caras de cada número: costo por X y ganancia por X)
B60: Ganancia por visita | C60: =IF('Modelo'!$C$8=0,0,'Modelo'!$C$41/'Modelo'!$C$8) | D60: Ganancia del período ÷ visitas. La métrica más valiosa del embudo: resume todo lo que pasa después de la página. Su par es el costo por visita.
B61: Ganancia por checkout | C61: =IF('Modelo'!$C$9=0,0,'Modelo'!$C$41/'Modelo'!$C$9) | D61: Ganancia del período ÷ checkouts. Su par es el costo por checkout.
B62: Ganancia por cliente | C62: =IF('Modelo'!$C$10=0,0,'Modelo'!$C$41/'Modelo'!$C$10) | D62: Ganancia del período ÷ compradores del principal. Su par es el CPA; la diferencia entre AOV neto y CPA es lo que queda por cliente antes de fijos.

Sheet Escenarios
B1: © Jesús Tassarolo · TooAudience · youtube.com/@JesusTassaroloSinFiltro · uso personal; no redistribuir modificado
B2: Escenarios: qué pasa si cambian el precio, la conversión o el costo
B3: Las celdas amarillas de cada tabla (fila y columna) se pueden cambiar. Verde = ganancia, amarillo = cerca del cero, rojo = pérdida. Todo lo demás queda como en Supuestos.
B5: Umbral de 'cerca del cero' (inversión × margen de seguridad) | C5: ='Supuestos'!$C$8*'Supuestos'!$C$46
B7: Precio del producto principal × % de checkouts que compran → ganancia del mes
B8: Subir el precio suele bajar la conversión: la tabla muestra qué combinación gana.
B9: Precio ↓ / % checkout → compra → | C9: 0.18 | D9: 0.22 | E9: 0.26 | F9: 0.3 | G9: 0.34
B10: 27 | C10: =((((((((IF(('Supuestos'!$C$9)=0,0,'Supuestos'!$C$8/('Supuestos'!$C$9)))*'Supuestos'!$C$12)*C$9)*$B10)+(((((IF(('Supuestos'!$C$9)=0,0,'Supuestos'!$C$8/('Supuestos'!$C$9)))*'Supuestos'!$C$12)*C$9)*'Supuestos'!$C$18)*'Supuestos'!$C$17)+(((((IF(('Supuestos'!$C$9)=0,0,'Supuestos'!$C$8/('Supuestos'!$C$9)))*'Supuestos'!$C$12)*C$9)*'Supuestos'!$C$20)*'Supuestos'!$C$19)+(((((IF(('Supuestos'!$C$9)=0,0,'Supuestos'!$C$8/('Supuestos'!$C$9)))*'Supuestos'!$C$12)*C$9)*'Supuestos'!$C$22)*'Supuestos'!$C$21)+(((((IF(('Supuestos'!$C$9)=0,0,'Supuestos'!$C$8/('Supuestos'!$C$9)))*'Supuestos'!$C$12)*C$9)*'Supuestos'!$C$24)*'Supuestos'!$C$23)+(((((IF(('Supuestos'!$C$9)=0,0,'Supuestos'!$C$8/('Supuestos'!$C$9)))*'Supuestos'!$C$12)*C$9)*'Supuestos'!$C$26)*'Supuestos'!$C$25)+(((((IF(('Supuestos'!$C$9)=0,0,'Supuestos'!$C$8/('Supuestos'!$C$9)))*'Supuestos'!$C$12)*C$9)*'Supuestos'!$C$28)*'Supuestos'!$C$27)+(((((IF(('Supuestos'!$C$9)=0,0,'Supuestos'!$C$8/('Supuestos'!$C$9)))*'Supuestos'!$C$12)*C$9)*'Supuestos'!$C$30)*'Supuestos'!$C$29))*('Supuestos'!$C$40+'Supuestos'!$C$41+'Supuestos'!$C$42))*(1-'Supuestos'!$C$33-'Supuestos'!$C$34-'Supuestos'!$C$35))-((IF(('Supuestos'!$C$9)=0,0,'Supuestos'!$C$8/('Supuestos'!$C$9)))*'Supuestos'!$C$36)-'Supuestos'!$C$37-'Supuestos'!$C$8) | D10: =((((((((IF(('Supuestos'!$C$9)=0,0,'Supuestos'!$C$8/('Supuestos'!$C$9)))*'Supuestos'!$C$12)*D$9)*$B10)+(((((IF(('Supuestos'!$C$9)=0,0,'Supuestos'!$C$8/('Supuestos'!$C$9)))*'Supuestos'!$C$12)*D$9)*'Supuestos'!$C$18)*'Supuestos'!$C$17)+(((((IF(('Supuestos'!$C$9)=0,0,'Supuestos'!$C$8/('Supuestos'!$C$9)))*'Supuestos'!$C$12)*D$9)*'Supuestos'!$C$20)*'Supuestos'!$C$19)+(((((IF(('Supuestos'!$C$9)=0,0,'Supuestos'!$C$8/('Supuestos'!$C$9)))*'Supuestos'!$C$12)*D$9)*'Supuestos'!$C$22)*'Supuestos'!$C$21)+(((((IF(('Supuestos'!$C$9)=0,0,'Supuestos'!$C$8/('Supuestos'!$C$9)))*'Supuestos'!$C$12)*D$9)*'Supuestos'!$C$24)*'Supuestos'!$C$23)+(((((IF(('Supuestos'!$C$9)=0,0,'Supuestos'!$C$8/('Supuestos'!$C$9)))*'Supuestos'!$C$12)*D$9)*'Supuestos'!$C$26)*'Supuestos'!$C$25)+(((((IF(('Supuestos'!$C$9)=0,0,'Supuestos'!$C$8/('Supuestos'!$C$9)))*'Supuestos'!$C$12)*D$9)*'Supuestos'!$C$28)*'Supuestos'!$C$27)+(((((IF(('Supuestos'!$C$9)=0,0,'Supuestos'!$C$8/('Supuestos'!$C$9)))*'Supuestos'!$C$12)*D$9)*'Supuestos'!$C$30)*'Supuestos'!$C$29))*('Supuestos'!$C$40+'Supuestos'!$C$41+'Supuestos'!$C$42))*(1-'Supuestos'!$C$33-'Supuestos'!$C$34-'Supuestos'!$C$35))-((IF(('Supuestos'!$C$9)=0,0,'Supuestos'!$C$8/('Supuestos'!$C$9)))*'Supuestos'!$C$36)-'Supuestos'!$C$37-'Supuestos'!$C$8) | E10: =((((((((IF(('Supuestos'!$C$9)=0,0,'Supuestos'!$C$8/('Supuestos'!$C$9)))*'Supuestos'!$C$12)*E$9)*$B10)+(((((IF(('Supuestos'!$C$9)=0,0,'Supuestos'!$C$8/('Supuestos'!$C$9)))*'Supuestos'!$C$12)*E$9)*'Supuestos'!$C$18)*'Supuestos'!$C$17)+(((((IF(('Supuestos'!$C$9)=0,0,'Supuestos'!$C$8/('Supuestos'!$C$9)))*'Supuestos'!$C$12)*E$9)*'Supuestos'!$C$20)*'Supuestos'!$C$19)+(((((IF(('Supuestos'!$C$9)=0,0,'Supuestos'!$C$8/('Supuestos'!$C$9)))*'Supuestos'!$C$12)*E$9)*'Supuestos'!$C$22)*'Supuestos'!$C$21)+(((((IF(('Supuestos'!$C$9)=0,0,'Supuestos'!$C$8/('Supuestos'!$C$9)))*'Supuestos'!$C$12)*E$9)*'Supuestos'!$C$24)*'Supuestos'!$C$23)+(((((IF(('Supuestos'!$C$9)=0,0,'Supuestos'!$C$8/('Supuestos'!$C$9)))*'Supuestos'!$C$12)*E$9)*'Supuestos'!$C$26)*'Supuestos'!$C$25)+(((((IF(('Supuestos'!$C$9)=0,0,'Supuestos'!$C$8/('Supuestos'!$C$9)))*'Supuestos'!$C$12)*E$9)*'Supuestos'!$C$28)*'Supuestos'!$C$27)+(((((IF(('Supuestos'!$C$9)=0,0,'Supuestos'!$C$8/('Supuestos'!$C$9)))*'Supuestos'!$C$12)*E$9)*'Supuestos'!$C$30)*'Supuestos'!$C$29))*('Supuestos'!$C$40+'Supuestos'!$C$41+'Supuestos'!$C$42))*(1-'Supuestos'!$C$33-'Supuestos'!$C$34-'Supuestos'!$C$35))-((IF(('Supuestos'!$C$9)=0,0,'Supuestos'!$C$8/('Supuestos'!$C$9)))*'Supuestos'!$C$36)-'Supuestos'!$C$37-'Supuestos'!$C$8) | F10: =((((((((IF(('Supuestos'!$C$9)=0,0,'Supuestos'!$C$8/('Supuestos'!$C$9)))*'Supuestos'!$C$12)*F$9)*$B10)+(((((IF(('Supuestos'!$C$9)=0,0,'Supuestos'!$C$8/('Supuestos'!$C$9)))*'Supuestos'!$C$12)*F$9)*'Supuestos'!$C$18)*'Supuestos'!$C$17)+(((((IF(('Supuestos'!$C$9)=0,0,'Supuestos'!$C$8/('Supuestos'!$C$9)))*'Supuestos'!$C$12)*F$9)*'Supuestos'!$C$20)*'Supuestos'!$C$19)+(((((IF(('Supuestos'!$C$9)=0,0,'Supuestos'!$C$8/('Supuestos'!$C$9)))*'Supuestos'!$C$12)*F$9)*'Supuestos'!$C$22)*'Supuestos'!$C$21)+(((((IF(('Supuestos'!$C$9)=0,0,'Supuestos'!$C$8/('Supuestos'!$C$9)))*'Supuestos'!$C$12)*F$9)*'Supuestos'!$C$24)*'Supuestos'!$C$23)+(((((IF(('Supuestos'!$C$9)=0,0,'Supuestos'!$C$8/('Supuestos'!$C$9)))*'Supuestos'!$C$12)*F$9)*'Supuestos'!$C$26)*'Supuestos'!$C$25)+(((((IF(('Supuestos'!$C$9)=0,0,'Supuestos'!$C$8/('Supuestos'!$C$9)))*'Supuestos'!$C$12)*F$9)*'Supuestos'!$C$28)*'Supuestos'!$C$27)+(((((IF(('Supuestos'!$C$9)=0,0,'Supuestos'!$C$8/('Supuestos'!$C$9)))*'Supuestos'!$C$12)*F$9)*'Supuestos'!$C$30)*'Supuestos'!$C$29))*('Supuestos'!$C$40+'Supuestos'!$C$41+'Supuestos'!$C$42))*(1-'Supuestos'!$C$33-'Supuestos'!$C$34-'Supuestos'!$C$35))-((IF(('Supuestos'!$C$9)=0,0,'Supuestos'!$C$8/('Supuestos'!$C$9)))*'Supuestos'!$C$36)-'Supuestos'!$C$37-'Supuestos'!$C$8) | G10: =((((((((IF(('Supuestos'!$C$9)=0,0,'Supuestos'!$C$8/('Supuestos'!$C$9)))*'Supuestos'!$C$12)*G$9)*$B10)+(((((IF(('Supuestos'!$C$9)=0,0,'Supuestos'!$C$8/('Supuestos'!$C$9)))*'Supuestos'!$C$12)*G$9)*'Supuestos'!$C$18)*'Supuestos'!$C$17)+(((((IF(('Supuestos'!$C$9)=0,0,'Supuestos'!$C$8/('Supuestos'!$C$9)))*'Supuestos'!$C$12)*G$9)*'Supuestos'!$C$20)*'Supuestos'!$C$19)+(((((IF(('Supuestos'!$C$9)=0,0,'Supuestos'!$C$8/('Supuestos'!$C$9)))*'Supuestos'!$C$12)*G$9)*'Supuestos'!$C$22)*'Supuestos'!$C$21)+(((((IF(('Supuestos'!$C$9)=0,0,'Supuestos'!$C$8/('Supuestos'!$C$9)))*'Supuestos'!$C$12)*G$9)*'Supuestos'!$C$24)*'Supuestos'!$C$23)+(((((IF(('Supuestos'!$C$9)=0,0,'Supuestos'!$C$8/('Supuestos'!$C$9)))*'Supuestos'!$C$12)*G$9)*'Supuestos'!$C$26)*'Supuestos'!$C$25)+(((((IF(('Supuestos'!$C$9)=0,0,'Supuestos'!$C$8/('Supuestos'!$C$9)))*'Supuestos'!$C$12)*G$9)*'Supuestos'!$C$28)*'Supuestos'!$C$27)+(((((IF(('Supuestos'!$C$9)=0,0,'Supuestos'!$C$8/('Supuestos'!$C$9)))*'Supuestos'!$C$12)*G$9)*'Supuestos'!$C$30)*'Supuestos'!$C$29))*('Supuestos'!$C$40+'Supuestos'!$C$41+'Supuestos'!$C$42))*(1-'Supuestos'!$C$33-'Supuestos'!$C$34-'Supuestos'!$C$35))-((IF(('Supuestos'!$C$9)=0,0,'Supuestos'!$C$8/('Supuestos'!$C$9)))*'Supuestos'!$C$36)-'Supuestos'!$C$37-'Supuestos'!$C$8)
B11: 37 | C11: =((((((((IF(('Supuestos'!$C$9)=0,0,'Supuestos'!$C$8/('Supuestos'!$C$9)))*'Supuestos'!$C$12)*C$9)*$B11)+(((((IF(('Supuestos'!$C$9)=0,0,'Supuestos'!$C$8/('Supuestos'!$C$9)))*'Supuestos'!$C$12)*C$9)*'Supuestos'!$C$18)*'Supuestos'!$C$17)+(((((IF(('Supuestos'!$C$9)=0,0,'Supuestos'!$C$8/('Supuestos'!$C$9)))*'Supuestos'!$C$12)*C$9)*'Supuestos'!$C$20)*'Supuestos'!$C$19)+(((((IF(('Supuestos'!$C$9)=0,0,'Supuestos'!$C$8/('Supuestos'!$C$9)))*'Supuestos'!$C$12)*C$9)*'Supuestos'!$C$22)*'Supuestos'!$C$21)+(((((IF(('Supuestos'!$C$9)=0,0,'Supuestos'!$C$8/('Supuestos'!$C$9)))*'Supuestos'!$C$12)*C$9)*'Supuestos'!$C$24)*'Supuestos'!$C$23)+(((((IF(('Supuestos'!$C$9)=0,0,'Supuestos'!$C$8/('Supuestos'!$C$9)))*'Supuestos'!$C$12)*C$9)*'Supuestos'!$C$26)*'Supuestos'!$C$25)+(((((IF(('Supuestos'!$C$9)=0,0,'Supuestos'!$C$8/('Supuestos'!$C$9)))*'Supuestos'!$C$12)*C$9)*'Supuestos'!$C$28)*'Supuestos'!$C$27)+(((((IF(('Supuestos'!$C$9)=0,0,'Supuestos'!$C$8/('Supuestos'!$C$9)))*'Supuestos'!$C$12)*C$9)*'Supuestos'!$C$30)*'Supuestos'!$C$29))*('Supuestos'!$C$40+'Supuestos'!$C$41+'Supuestos'!$C$42))*(1-'Supuestos'!$C$33-'Supuestos'!$C$34-'Supuestos'!$C$35))-((IF(('Supuestos'!$C$9)=0,0,'Supuestos'!$C$8/('Supuestos'!$C$9)))*'Supuestos'!$C$36)-'Supuestos'!$C$37-'Supuestos'!$C$8) | D11: =((((((((IF(('Supuestos'!$C$9)=0,0,'Supuestos'!$C$8/('Supuestos'!$C$9)))*'Supuestos'!$C$12)*D$9)*$B11)+(((((IF(('Supuestos'!$C$9)=0,0,'Supuestos'!$C$8/('Supuestos'!$C$9)))*'Supuestos'!$C$12)*D$9)*'Supuestos'!$C$18)*'Supuestos'!$C$17)+(((((IF(('Supuestos'!$C$9)=0,0,'Supuestos'!$C$8/('Supuestos'!$C$9)))*'Supuestos'!$C$12)*D$9)*'Supuestos'!$C$20)*'Supuestos'!$C$19)+(((((IF(('Supuestos'!$C$9)=0,0,'Supuestos'!$C$8/('Supuestos'!$C$9)))*'Supuestos'!$C$12)*D$9)*'Supuestos'!$C$22)*'Supuestos'!$C$21)+(((((IF(('Supuestos'!$C$9)=0,0,'Supuestos'!$C$8/('Supuestos'!$C$9)))*'Supuestos'!$C$12)*D$9)*'Supuestos'!$C$24)*'Supuestos'!$C$23)+(((((IF(('Supuestos'!$C$9)=0,0,'Supuestos'!$C$8/('Supuestos'!$C$9)))*'Supuestos'!$C$12)*D$9)*'Supuestos'!$C$26)*'Supuestos'!$C$25)+(((((IF(('Supuestos'!$C$9)=0,0,'Supuestos'!$C$8/('Supuestos'!$C$9)))*'Supuestos'!$C$12)*D$9)*'Supuestos'!$C$28)*'Supuestos'!$C$27)+(((((IF(('Supuestos'!$C$9)=0,0,'Supuestos'!$C$8/('Supuestos'!$C$9)))*'Supuestos'!$C$12)*D$9)*'Supuestos'!$C$30)*'Supuestos'!$C$29))*('Supuestos'!$C$40+'Supuestos'!$C$41+'Supuestos'!$C$42))*(1-'Supuestos'!$C$33-'Supuestos'!$C$34-'Supuestos'!$C$35))-((IF(('Supuestos'!$C$9)=0,0,'Supuestos'!$C$8/('Supuestos'!$C$9)))*'Supuestos'!$C$36)-'Supuestos'!$C$37-'Supuestos'!$C$8) | E11: =((((((((IF(('Supuestos'!$C$9)=0,0,'Supuestos'!$C$8/('Supuestos'!$C$9)))*'Supuestos'!$C$12)*E$9)*$B11)+(((((IF(('Supuestos'!$C$9)=0,0,'Supuestos'!$C$8/('Supuestos'!$C$9)))*'Supuestos'!$C$12)*E$9)*'Supuestos'!$C$18)*'Supuestos'!$C$17)+(((((IF(('Supuestos'!$C$9)=0,0,'Supuestos'!$C$8/('Supuestos'!$C$9)))*'Supuestos'!$C$12)*E$9)*'Supuestos'!$C$20)*'Supuestos'!$C$19)+(((((IF(('Supuestos'!$C$9)=0,0,'Supuestos'!$C$8/('Supuestos'!$C$9)))*'Supuestos'!$C$12)*E$9)*'Supuestos'!$C$22)*'Supuestos'!$C$21)+(((((IF(('Supuestos'!$C$9)=0,0,'Supuestos'!$C$8/('Supuestos'!$C$9)))*'Supuestos'!$C$12)*E$9)*'Supuestos'!$C$24)*'Supuestos'!$C$23)+(((((IF(('Supuestos'!$C$9)=0,0,'Supuestos'!$C$8/('Supuestos'!$C$9)))*'Supuestos'!$C$12)*E$9)*'Supuestos'!$C$26)*'Supuestos'!$C$25)+(((((IF(('Supuestos'!$C$9)=0,0,'Supuestos'!$C$8/('Supuestos'!$C$9)))*'Supuestos'!$C$12)*E$9)*'Supuestos'!$C$28)*'Supuestos'!$C$27)+(((((IF(('Supuestos'!$C$9)=0,0,'Supuestos'!$C$8/('Supuestos'!$C$9)))*'Supuestos'!$C$12)*E$9)*'Supuestos'!$C$30)*'Supuestos'!$C$29))*('Supuestos'!$C$40+'Supuestos'!$C$41+'Supuestos'!$C$42))*(1-'Supuestos'!$C$33-'Supuestos'!$C$34-'Supuestos'!$C$35))-((IF(('Supuestos'!$C$9)=0,0,'Supuestos'!$C$8/('Supuestos'!$C$9)))*'Supuestos'!$C$36)-'Supuestos'!$C$37-'Supuestos'!$C$8) | F11: =((((((((IF(('Supuestos'!$C$9)=0,0,'Supuestos'!$C$8/('Supuestos'!$C$9)))*'Supuestos'!$C$12)*F$9)*$B11)+(((((IF(('Supuestos'!$C$9)=0,0,'Supuestos'!$C$8/('Supuestos'!$C$9)))*'Supuestos'!$C$12)*F$9)*'Supuestos'!$C$18)*'Supuestos'!$C$17)+(((((IF(('Supuestos'!$C$9)=0,0,'Supuestos'!$C$8/('Supuestos'!$C$9)))*'Supuestos'!$C$12)*F$9)*'Supuestos'!$C$20)*'Supuestos'!$C$19)+(((((IF(('Supuestos'!$C$9)=0,0,'Supuestos'!$C$8/('Supuestos'!$C$9)))*'Supuestos'!$C$12)*F$9)*'Supuestos'!$C$22)*'Supuestos'!$C$21)+(((((IF(('Supuestos'!$C$9)=0,0,'Supuestos'!$C$8/('Supuestos'!$C$9)))*'Supuestos'!$C$12)*F$9)*'Supuestos'!$C$24)*'Supuestos'!$C$23)+(((((IF(('Supuestos'!$C$9)=0,0,'Supuestos'!$C$8/('Supuestos'!$C$9)))*'Supuestos'!$C$12)*F$9)*'Supuestos'!$C$26)*'Supuestos'!$C$25)+(((((IF(('Supuestos'!$C$9)=0,0,'Supuestos'!$C$8/('Supuestos'!$C$9)))*'Supuestos'!$C$12)*F$9)*'Supuestos'!$C$28)*'Supuestos'!$C$27)+(((((IF(('Supuestos'!$C$9)=0,0,'Supuestos'!$C$8/('Supuestos'!$C$9)))*'Supuestos'!$C$12)*F$9)*'Supuestos'!$C$30)*'Supuestos'!$C$29))*('Supuestos'!$C$40+'Supuestos'!$C$41+'Supuestos'!$C$42))*(1-'Supuestos'!$C$33-'Supuestos'!$C$34-'Supuestos'!$C$35))-((IF(('Supuestos'!$C$9)=0,0,'Supuestos'!$C$8/('Supuestos'!$C$9)))*'Supuestos'!$C$36)-'Supuestos'!$C$37-'Supuestos'!$C$8) | G11: =((((((((IF(('Supuestos'!$C$9)=0,0,'Supuestos'!$C$8/('Supuestos'!$C$9)))*'Supuestos'!$C$12)*G$9)*$B11)+(((((IF(('Supuestos'!$C$9)=0,0,'Supuestos'!$C$8/('Supuestos'!$C$9)))*'Supuestos'!$C$12)*G$9)*'Supuestos'!$C$18)*'Supuestos'!$C$17)+(((((IF(('Supuestos'!$C$9)=0,0,'Supuestos'!$C$8/('Supuestos'!$C$9)))*'Supuestos'!$C$12)*G$9)*'Supuestos'!$C$20)*'Supuestos'!$C$19)+(((((IF(('Supuestos'!$C$9)=0,0,'Supuestos'!$C$8/('Supuestos'!$C$9)))*'Supuestos'!$C$12)*G$9)*'Supuestos'!$C$22)*'Supuestos'!$C$21)+(((((IF(('Supuestos'!$C$9)=0,0,'Supuestos'!$C$8/('Supuestos'!$C$9)))*'Supuestos'!$C$12)*G$9)*'Supuestos'!$C$24)*'Supuestos'!$C$23)+(((((IF(('Supuestos'!$C$9)=0,0,'Supuestos'!$C$8/('Supuestos'!$C$9)))*'Supuestos'!$C$12)*G$9)*'Supuestos'!$C$26)*'Supuestos'!$C$25)+(((((IF(('Supuestos'!$C$9)=0,0,'Supuestos'!$C$8/('Supuestos'!$C$9)))*'Supuestos'!$C$12)*G$9)*'Supuestos'!$C$28)*'Supuestos'!$C$27)+(((((IF(('Supuestos'!$C$9)=0,0,'Supuestos'!$C$8/('Supuestos'!$C$9)))*'Supuestos'!$C$12)*G$9)*'Supuestos'!$C$30)*'Supuestos'!$C$29))*('Supuestos'!$C$40+'Supuestos'!$C$41+'Supuestos'!$C$42))*(1-'Supuestos'!$C$33-'Supuestos'!$C$34-'Supuestos'!$C$35))-((IF(('Supuestos'!$C$9)=0,0,'Supuestos'!$C$8/('Supuestos'!$C$9)))*'Supuestos'!$C$36)-'Supuestos'!$C$37-'Supuestos'!$C$8)
B12: 47 | C12: =((((((((IF(('Supuestos'!$C$9)=0,0,'Supuestos'!$C$8/('Supuestos'!$C$9)))*'Supuestos'!$C$12)*C$9)*$B12)+(((((IF(('Supuestos'!$C$9)=0,0,'Supuestos'!$C$8/('Supuestos'!$C$9)))*'Supuestos'!$C$12)*C$9)*'Supuestos'!$C$18)*'Supuestos'!$C$17)+(((((IF(('Supuestos'!$C$9)=0,0,'Supuestos'!$C$8/('Supuestos'!$C$9)))*'Supuestos'!$C$12)*C$9)*'Supuestos'!$C$20)*'Supuestos'!$C$19)+(((((IF(('Supuestos'!$C$9)=0,0,'Supuestos'!$C$8/('Supuestos'!$C$9)))*'Supuestos'!$C$12)*C$9)*'Supuestos'!$C$22)*'Supuestos'!$C$21)+(((((IF(('Supuestos'!$C$9)=0,0,'Supuestos'!$C$8/('Supuestos'!$C$9)))*'Supuestos'!$C$12)*C$9)*'Supuestos'!$C$24)*'Supuestos'!$C$23)+(((((IF(('Supuestos'!$C$9)=0,0,'Supuestos'!$C$8/('Supuestos'!$C$9)))*'Supuestos'!$C$12)*C$9)*'Supuestos'!$C$26)*'Supuestos'!$C$25)+(((((IF(('Supuestos'!$C$9)=0,0,'Supuestos'!$C$8/('Supuestos'!$C$9)))*'Supuestos'!$C$12)*C$9)*'Supuestos'!$C$28)*'Supuestos'!$C$27)+(((((IF(('Supuestos'!$C$9)=0,0,'Supuestos'!$C$8/('Supuestos'!$C$9)))*'Supuestos'!$C$12)*C$9)*'Supuestos'!$C$30)*'Supuestos'!$C$29))*('Supuestos'!$C$40+'Supuestos'!$C$41+'Supuestos'!$C$42))*(1-'Supuestos'!$C$33-'Supuestos'!$C$34-'Supuestos'!$C$35))-((IF(('Supuestos'!$C$9)=0,0,'Supuestos'!$C$8/('Supuestos'!$C$9)))*'Supuestos'!$C$36)-'Supuestos'!$C$37-'Supuestos'!$C$8) | D12: =((((((((IF(('Supuestos'!$C$9)=0,0,'Supuestos'!$C$8/('Supuestos'!$C$9)))*'Supuestos'!$C$12)*D$9)*$B12)+(((((IF(('Supuestos'!$C$9)=0,0,'Supuestos'!$C$8/('Supuestos'!$C$9)))*'Supuestos'!$C$12)*D$9)*'Supuestos'!$C$18)*'Supuestos'!$C$17)+(((((IF(('Supuestos'!$C$9)=0,0,'Supuestos'!$C$8/('Supuestos'!$C$9)))*'Supuestos'!$C$12)*D$9)*'Supuestos'!$C$20)*'Supuestos'!$C$19)+(((((IF(('Supuestos'!$C$9)=0,0,'Supuestos'!$C$8/('Supuestos'!$C$9)))*'Supuestos'!$C$12)*D$9)*'Supuestos'!$C$22)*'Supuestos'!$C$21)+(((((IF(('Supuestos'!$C$9)=0,0,'Supuestos'!$C$8/('Supuestos'!$C$9)))*'Supuestos'!$C$12)*D$9)*'Supuestos'!$C$24)*'Supuestos'!$C$23)+(((((IF(('Supuestos'!$C$9)=0,0,'Supuestos'!$C$8/('Supuestos'!$C$9)))*'Supuestos'!$C$12)*D$9)*'Supuestos'!$C$26)*'Supuestos'!$C$25)+(((((IF(('Supuestos'!$C$9)=0,0,'Supuestos'!$C$8/('Supuestos'!$C$9)))*'Supuestos'!$C$12)*D$9)*'Supuestos'!$C$28)*'Supuestos'!$C$27)+(((((IF(('Supuestos'!$C$9)=0,0,'Supuestos'!$C$8/('Supuestos'!$C$9)))*'Supuestos'!$C$12)*D$9)*'Supuestos'!$C$30)*'Supuestos'!$C$29))*('Supuestos'!$C$40+'Supuestos'!$C$41+'Supuestos'!$C$42))*(1-'Supuestos'!$C$33-'Supuestos'!$C$34-'Supuestos'!$C$35))-((IF(('Supuestos'!$C$9)=0,0,'Supuestos'!$C$8/('Supuestos'!$C$9)))*'Supuestos'!$C$36)-'Supuestos'!$C$37-'Supuestos'!$C$8) | E12: =((((((((IF(('Supuestos'!$C$9)=0,0,'Supuestos'!$C$8/('Supuestos'!$C$9)))*'Supuestos'!$C$12)*E$9)*$B12)+(((((IF(('Supuestos'!$C$9)=0,0,'Supuestos'!$C$8/('Supuestos'!$C$9)))*'Supuestos'!$C$12)*E$9)*'Supuestos'!$C$18)*'Supuestos'!$C$17)+(((((IF(('Supuestos'!$C$9)=0,0,'Supuestos'!$C$8/('Supuestos'!$C$9)))*'Supuestos'!$C$12)*E$9)*'Supuestos'!$C$20)*'Supuestos'!$C$19)+(((((IF(('Supuestos'!$C$9)=0,0,'Supuestos'!$C$8/('Supuestos'!$C$9)))*'Supuestos'!$C$12)*E$9)*'Supuestos'!$C$22)*'Supuestos'!$C$21)+(((((IF(('Supuestos'!$C$9)=0,0,'Supuestos'!$C$8/('Supuestos'!$C$9)))*'Supuestos'!$C$12)*E$9)*'Supuestos'!$C$24)*'Supuestos'!$C$23)+(((((IF(('Supuestos'!$C$9)=0,0,'Supuestos'!$C$8/('Supuestos'!$C$9)))*'Supuestos'!$C$12)*E$9)*'Supuestos'!$C$26)*'Supuestos'!$C$25)+(((((IF(('Supuestos'!$C$9)=0,0,'Supuestos'!$C$8/('Supuestos'!$C$9)))*'Supuestos'!$C$12)*E$9)*'Supuestos'!$C$28)*'Supuestos'!$C$27)+(((((IF(('Supuestos'!$C$9)=0,0,'Supuestos'!$C$8/('Supuestos'!$C$9)))*'Supuestos'!$C$12)*E$9)*'Supuestos'!$C$30)*'Supuestos'!$C$29))*('Supuestos'!$C$40+'Supuestos'!$C$41+'Supuestos'!$C$42))*(1-'Supuestos'!$C$33-'Supuestos'!$C$34-'Supuestos'!$C$35))-((IF(('Supuestos'!$C$9)=0,0,'Supuestos'!$C$8/('Supuestos'!$C$9)))*'Supuestos'!$C$36)-'Supuestos'!$C$37-'Supuestos'!$C$8) | F12: =((((((((IF(('Supuestos'!$C$9)=0,0,'Supuestos'!$C$8/('Supuestos'!$C$9)))*'Supuestos'!$C$12)*F$9)*$B12)+(((((IF(('Supuestos'!$C$9)=0,0,'Supuestos'!$C$8/('Supuestos'!$C$9)))*'Supuestos'!$C$12)*F$9)*'Supuestos'!$C$18)*'Supuestos'!$C$17)+(((((IF(('Supuestos'!$C$9)=0,0,'Supuestos'!$C$8/('Supuestos'!$C$9)))*'Supuestos'!$C$12)*F$9)*'Supuestos'!$C$20)*'Supuestos'!$C$19)+(((((IF(('Supuestos'!$C$9)=0,0,'Supuestos'!$C$8/('Supuestos'!$C$9)))*'Supuestos'!$C$12)*F$9)*'Supuestos'!$C$22)*'Supuestos'!$C$21)+(((((IF(('Supuestos'!$C$9)=0,0,'Supuestos'!$C$8/('Supuestos'!$C$9)))*'Supuestos'!$C$12)*F$9)*'Supuestos'!$C$24)*'Supuestos'!$C$23)+(((((IF(('Supuestos'!$C$9)=0,0,'Supuestos'!$C$8/('Supuestos'!$C$9)))*'Supuestos'!$C$12)*F$9)*'Supuestos'!$C$26)*'Supuestos'!$C$25)+(((((IF(('Supuestos'!$C$9)=0,0,'Supuestos'!$C$8/('Supuestos'!$C$9)))*'Supuestos'!$C$12)*F$9)*'Supuestos'!$C$28)*'Supuestos'!$C$27)+(((((IF(('Supuestos'!$C$9)=0,0,'Supuestos'!$C$8/('Supuestos'!$C$9)))*'Supuestos'!$C$12)*F$9)*'Supuestos'!$C$30)*'Supuestos'!$C$29))*('Supuestos'!$C$40+'Supuestos'!$C$41+'Supuestos'!$C$42))*(1-'Supuestos'!$C$33-'Supuestos'!$C$34-'Supuestos'!$C$35))-((IF(('Supuestos'!$C$9)=0,0,'Supuestos'!$C$8/('Supuestos'!$C$9)))*'Supuestos'!$C$36)-'Supuestos'!$C$37-'Supuestos'!$C$8) | G12: =((((((((IF(('Supuestos'!$C$9)=0,0,'Supuestos'!$C$8/('Supuestos'!$C$9)))*'Supuestos'!$C$12)*G$9)*$B12)+(((((IF(('Supuestos'!$C$9)=0,0,'Supuestos'!$C$8/('Supuestos'!$C$9)))*'Supuestos'!$C$12)*G$9)*'Supuestos'!$C$18)*'Supuestos'!$C$17)+(((((IF(('Supuestos'!$C$9)=0,0,'Supuestos'!$C$8/('Supuestos'!$C$9)))*'Supuestos'!$C$12)*G$9)*'Supuestos'!$C$20)*'Supuestos'!$C$19)+(((((IF(('Supuestos'!$C$9)=0,0,'Supuestos'!$C$8/('Supuestos'!$C$9)))*'Supuestos'!$C$12)*G$9)*'Supuestos'!$C$22)*'Supuestos'!$C$21)+(((((IF(('Supuestos'!$C$9)=0,0,'Supuestos'!$C$8/('Supuestos'!$C$9)))*'Supuestos'!$C$12)*G$9)*'Supuestos'!$C$24)*'Supuestos'!$C$23)+(((((IF(('Supuestos'!$C$9)=0,0,'Supuestos'!$C$8/('Supuestos'!$C$9)))*'Supuestos'!$C$12)*G$9)*'Supuestos'!$C$26)*'Supuestos'!$C$25)+(((((IF(('Supuestos'!$C$9)=0,0,'Supuestos'!$C$8/('Supuestos'!$C$9)))*'Supuestos'!$C$12)*G$9)*'Supuestos'!$C$28)*'Supuestos'!$C$27)+(((((IF(('Supuestos'!$C$9)=0,0,'Supuestos'!$C$8/('Supuestos'!$C$9)))*'Supuestos'!$C$12)*G$9)*'Supuestos'!$C$30)*'Supuestos'!$C$29))*('Supuestos'!$C$40+'Supuestos'!$C$41+'Supuestos'!$C$42))*(1-'Supuestos'!$C$33-'Supuestos'!$C$34-'Supuestos'!$C$35))-((IF(('Supuestos'!$C$9)=0,0,'Supuestos'!$C$8/('Supuestos'!$C$9)))*'Supuestos'!$C$36)-'Supuestos'!$C$37-'Supuestos'!$C$8)
B13: 67 | C13: =((((((((IF(('Supuestos'!$C$9)=0,0,'Supuestos'!$C$8/('Supuestos'!$C$9)))*'Supuestos'!$C$12)*C$9)*$B13)+(((((IF(('Supuestos'!$C$9)=0,0,'Supuestos'!$C$8/('Supuestos'!$C$9)))*'Supuestos'!$C$12)*C$9)*'Supuestos'!$C$18)*'Supuestos'!$C$17)+(((((IF(('Supuestos'!$C$9)=0,0,'Supuestos'!$C$8/('Supuestos'!$C$9)))*'Supuestos'!$C$12)*C$9)*'Supuestos'!$C$20)*'Supuestos'!$C$19)+(((((IF(('Supuestos'!$C$9)=0,0,'Supuestos'!$C$8/('Supuestos'!$C$9)))*'Supuestos'!$C$12)*C$9)*'Supuestos'!$C$22)*'Supuestos'!$C$21)+(((((IF(('Supuestos'!$C$9)=0,0,'Supuestos'!$C$8/('Supuestos'!$C$9)))*'Supuestos'!$C$12)*C$9)*'Supuestos'!$C$24)*'Supuestos'!$C$23)+(((((IF(('Supuestos'!$C$9)=0,0,'Supuestos'!$C$8/('Supuestos'!$C$9)))*'Supuestos'!$C$12)*C$9)*'Supuestos'!$C$26)*'Supuestos'!$C$25)+(((((IF(('Supuestos'!$C$9)=0,0,'Supuestos'!$C$8/('Supuestos'!$C$9)))*'Supuestos'!$C$12)*C$9)*'Supuestos'!$C$28)*'Supuestos'!$C$27)+(((((IF(('Supuestos'!$C$9)=0,0,'Supuestos'!$C$8/('Supuestos'!$C$9)))*'Supuestos'!$C$12)*C$9)*'Supuestos'!$C$30)*'Supuestos'!$C$29))*('Supuestos'!$C$40+'Supuestos'!$C$41+'Supuestos'!$C$42))*(1-'Supuestos'!$C$33-'Supuestos'!$C$34-'Supuestos'!$C$35))-((IF(('Supuestos'!$C$9)=0,0,'Supuestos'!$C$8/('Supuestos'!$C$9)))*'Supuestos'!$C$36)-'Supuestos'!$C$37-'Supuestos'!$C$8) | D13: =((((((((IF(('Supuestos'!$C$9)=0,0,'Supuestos'!$C$8/('Supuestos'!$C$9)))*'Supuestos'!$C$12)*D$9)*$B13)+(((((IF(('Supuestos'!$C$9)=0,0,'Supuestos'!$C$8/('Supuestos'!$C$9)))*'Supuestos'!$C$12)*D$9)*'Supuestos'!$C$18)*'Supuestos'!$C$17)+(((((IF(('Supuestos'!$C$9)=0,0,'Supuestos'!$C$8/('Supuestos'!$C$9)))*'Supuestos'!$C$12)*D$9)*'Supuestos'!$C$20)*'Supuestos'!$C$19)+(((((IF(('Supuestos'!$C$9)=0,0,'Supuestos'!$C$8/('Supuestos'!$C$9)))*'Supuestos'!$C$12)*D$9)*'Supuestos'!$C$22)*'Supuestos'!$C$21)+(((((IF(('Supuestos'!$C$9)=0,0,'Supuestos'!$C$8/('Supuestos'!$C$9)))*'Supuestos'!$C$12)*D$9)*'Supuestos'!$C$24)*'Supuestos'!$C$23)+(((((IF(('Supuestos'!$C$9)=0,0,'Supuestos'!$C$8/('Supuestos'!$C$9)))*'Supuestos'!$C$12)*D$9)*'Supuestos'!$C$26)*'Supuestos'!$C$25)+(((((IF(('Supuestos'!$C$9)=0,0,'Supuestos'!$C$8/('Supuestos'!$C$9)))*'Supuestos'!$C$12)*D$9)*'Supuestos'!$C$28)*'Supuestos'!$C$27)+(((((IF(('Supuestos'!$C$9)=0,0,'Supuestos'!$C$8/('Supuestos'!$C$9)))*'Supuestos'!$C$12)*D$9)*'Supuestos'!$C$30)*'Supuestos'!$C$29))*('Supuestos'!$C$40+'Supuestos'!$C$41+'Supuestos'!$C$42))*(1-'Supuestos'!$C$33-'Supuestos'!$C$34-'Supuestos'!$C$35))-((IF(('Supuestos'!$C$9)=0,0,'Supuestos'!$C$8/('Supuestos'!$C$9)))*'Supuestos'!$C$36)-'Supuestos'!$C$37-'Supuestos'!$C$8) | E13: =((((((((IF(('Supuestos'!$C$9)=0,0,'Supuestos'!$C$8/('Supuestos'!$C$9)))*'Supuestos'!$C$12)*E$9)*$B13)+(((((IF(('Supuestos'!$C$9)=0,0,'Supuestos'!$C$8/('Supuestos'!$C$9)))*'Supuestos'!$C$12)*E$9)*'Supuestos'!$C$18)*'Supuestos'!$C$17)+(((((IF(('Supuestos'!$C$9)=0,0,'Supuestos'!$C$8/('Supuestos'!$C$9)))*'Supuestos'!$C$12)*E$9)*'Supuestos'!$C$20)*'Supuestos'!$C$19)+(((((IF(('Supuestos'!$C$9)=0,0,'Supuestos'!$C$8/('Supuestos'!$C$9)))*'Supuestos'!$C$12)*E$9)*'Supuestos'!$C$22)*'Supuestos'!$C$21)+(((((IF(('Supuestos'!$C$9)=0,0,'Supuestos'!$C$8/('Supuestos'!$C$9)))*'Supuestos'!$C$12)*E$9)*'Supuestos'!$C$24)*'Supuestos'!$C$23)+(((((IF(('Supuestos'!$C$9)=0,0,'Supuestos'!$C$8/('Supuestos'!$C$9)))*'Supuestos'!$C$12)*E$9)*'Supuestos'!$C$26)*'Supuestos'!$C$25)+(((((IF(('Supuestos'!$C$9)=0,0,'Supuestos'!$C$8/('Supuestos'!$C$9)))*'Supuestos'!$C$12)*E$9)*'Supuestos'!$C$28)*'Supuestos'!$C$27)+(((((IF(('Supuestos'!$C$9)=0,0,'Supuestos'!$C$8/('Supuestos'!$C$9)))*'Supuestos'!$C$12)*E$9)*'Supuestos'!$C$30)*'Supuestos'!$C$29))*('Supuestos'!$C$40+'Supuestos'!$C$41+'Supuestos'!$C$42))*(1-'Supuestos'!$C$33-'Supuestos'!$C$34-'Supuestos'!$C$35))-((IF(('Supuestos'!$C$9)=0,0,'Supuestos'!$C$8/('Supuestos'!$C$9)))*'Supuestos'!$C$36)-'Supuestos'!$C$37-'Supuestos'!$C$8) | F13: =((((((((IF(('Supuestos'!$C$9)=0,0,'Supuestos'!$C$8/('Supuestos'!$C$9)))*'Supuestos'!$C$12)*F$9)*$B13)+(((((IF(('Supuestos'!$C$9)=0,0,'Supuestos'!$C$8/('Supuestos'!$C$9)))*'Supuestos'!$C$12)*F$9)*'Supuestos'!$C$18)*'Supuestos'!$C$17)+(((((IF(('Supuestos'!$C$9)=0,0,'Supuestos'!$C$8/('Supuestos'!$C$9)))*'Supuestos'!$C$12)*F$9)*'Supuestos'!$C$20)*'Supuestos'!$C$19)+(((((IF(('Supuestos'!$C$9)=0,0,'Supuestos'!$C$8/('Supuestos'!$C$9)))*'Supuestos'!$C$12)*F$9)*'Supuestos'!$C$22)*'Supuestos'!$C$21)+(((((IF(('Supuestos'!$C$9)=0,0,'Supuestos'!$C$8/('Supuestos'!$C$9)))*'Supuestos'!$C$12)*F$9)*'Supuestos'!$C$24)*'Supuestos'!$C$23)+(((((IF(('Supuestos'!$C$9)=0,0,'Supuestos'!$C$8/('Supuestos'!$C$9)))*'Supuestos'!$C$12)*F$9)*'Supuestos'!$C$26)*'Supuestos'!$C$25)+(((((IF(('Supuestos'!$C$9)=0,0,'Supuestos'!$C$8/('Supuestos'!$C$9)))*'Supuestos'!$C$12)*F$9)*'Supuestos'!$C$28)*'Supuestos'!$C$27)+(((((IF(('Supuestos'!$C$9)=0,0,'Supuestos'!$C$8/('Supuestos'!$C$9)))*'Supuestos'!$C$12)*F$9)*'Supuestos'!$C$30)*'Supuestos'!$C$29))*('Supuestos'!$C$40+'Supuestos'!$C$41+'Supuestos'!$C$42))*(1-'Supuestos'!$C$33-'Supuestos'!$C$34-'Supuestos'!$C$35))-((IF(('Supuestos'!$C$9)=0,0,'Supuestos'!$C$8/('Supuestos'!$C$9)))*'Supuestos'!$C$36)-'Supuestos'!$C$37-'Supuestos'!$C$8) | G13: =((((((((IF(('Supuestos'!$C$9)=0,0,'Supuestos'!$C$8/('Supuestos'!$C$9)))*'Supuestos'!$C$12)*G$9)*$B13)+(((((IF(('Supuestos'!$C$9)=0,0,'Supuestos'!$C$8/('Supuestos'!$C$9)))*'Supuestos'!$C$12)*G$9)*'Supuestos'!$C$18)*'Supuestos'!$C$17)+(((((IF(('Supuestos'!$C$9)=0,0,'Supuestos'!$C$8/('Supuestos'!$C$9)))*'Supuestos'!$C$12)*G$9)*'Supuestos'!$C$20)*'Supuestos'!$C$19)+(((((IF(('Supuestos'!$C$9)=0,0,'Supuestos'!$C$8/('Supuestos'!$C$9)))*'Supuestos'!$C$12)*G$9)*'Supuestos'!$C$22)*'Supuestos'!$C$21)+(((((IF(('Supuestos'!$C$9)=0,0,'Supuestos'!$C$8/('Supuestos'!$C$9)))*'Supuestos'!$C$12)*G$9)*'Supuestos'!$C$24)*'Supuestos'!$C$23)+(((((IF(('Supuestos'!$C$9)=0,0,'Supuestos'!$C$8/('Supuestos'!$C$9)))*'Supuestos'!$C$12)*G$9)*'Supuestos'!$C$26)*'Supuestos'!$C$25)+(((((IF(('Supuestos'!$C$9)=0,0,'Supuestos'!$C$8/('Supuestos'!$C$9)))*'Supuestos'!$C$12)*G$9)*'Supuestos'!$C$28)*'Supuestos'!$C$27)+(((((IF(('Supuestos'!$C$9)=0,0,'Supuestos'!$C$8/('Supuestos'!$C$9)))*'Supuestos'!$C$12)*G$9)*'Supuestos'!$C$30)*'Supuestos'!$C$29))*('Supuestos'!$C$40+'Supuestos'!$C$41+'Supuestos'!$C$42))*(1-'Supuestos'!$C$33-'Supuestos'!$C$34-'Supuestos'!$C$35))-((IF(('Supuestos'!$C$9)=0,0,'Supuestos'!$C$8/('Supuestos'!$C$9)))*'Supuestos'!$C$36)-'Supuestos'!$C$37-'Supuestos'!$C$8)
B14: 97 | C14: =((((((((IF(('Supuestos'!$C$9)=0,0,'Supuestos'!$C$8/('Supuestos'!$C$9)))*'Supuestos'!$C$12)*C$9)*$B14)+(((((IF(('Supuestos'!$C$9)=0,0,'Supuestos'!$C$8/('Supuestos'!$C$9)))*'Supuestos'!$C$12)*C$9)*'Supuestos'!$C$18)*'Supuestos'!$C$17)+(((((IF(('Supuestos'!$C$9)=0,0,'Supuestos'!$C$8/('Supuestos'!$C$9)))*'Supuestos'!$C$12)*C$9)*'Supuestos'!$C$20)*'Supuestos'!$C$19)+(((((IF(('Supuestos'!$C$9)=0,0,'Supuestos'!$C$8/('Supuestos'!$C$9)))*'Supuestos'!$C$12)*C$9)*'Supuestos'!$C$22)*'Supuestos'!$C$21)+(((((IF(('Supuestos'!$C$9)=0,0,'Supuestos'!$C$8/('Supuestos'!$C$9)))*'Supuestos'!$C$12)*C$9)*'Supuestos'!$C$24)*'Supuestos'!$C$23)+(((((IF(('Supuestos'!$C$9)=0,0,'Supuestos'!$C$8/('Supuestos'!$C$9)))*'Supuestos'!$C$12)*C$9)*'Supuestos'!$C$26)*'Supuestos'!$C$25)+(((((IF(('Supuestos'!$C$9)=0,0,'Supuestos'!$C$8/('Supuestos'!$C$9)))*'Supuestos'!$C$12)*C$9)*'Supuestos'!$C$28)*'Supuestos'!$C$27)+(((((IF(('Supuestos'!$C$9)=0,0,'Supuestos'!$C$8/('Supuestos'!$C$9)))*'Supuestos'!$C$12)*C$9)*'Supuestos'!$C$30)*'Supuestos'!$C$29))*('Supuestos'!$C$40+'Supuestos'!$C$41+'Supuestos'!$C$42))*(1-'Supuestos'!$C$33-'Supuestos'!$C$34-'Supuestos'!$C$35))-((IF(('Supuestos'!$C$9)=0,0,'Supuestos'!$C$8/('Supuestos'!$C$9)))*'Supuestos'!$C$36)-'Supuestos'!$C$37-'Supuestos'!$C$8) | D14: =((((((((IF(('Supuestos'!$C$9)=0,0,'Supuestos'!$C$8/('Supuestos'!$C$9)))*'Supuestos'!$C$12)*D$9)*$B14)+(((((IF(('Supuestos'!$C$9)=0,0,'Supuestos'!$C$8/('Supuestos'!$C$9)))*'Supuestos'!$C$12)*D$9)*'Supuestos'!$C$18)*'Supuestos'!$C$17)+(((((IF(('Supuestos'!$C$9)=0,0,'Supuestos'!$C$8/('Supuestos'!$C$9)))*'Supuestos'!$C$12)*D$9)*'Supuestos'!$C$20)*'Supuestos'!$C$19)+(((((IF(('Supuestos'!$C$9)=0,0,'Supuestos'!$C$8/('Supuestos'!$C$9)))*'Supuestos'!$C$12)*D$9)*'Supuestos'!$C$22)*'Supuestos'!$C$21)+(((((IF(('Supuestos'!$C$9)=0,0,'Supuestos'!$C$8/('Supuestos'!$C$9)))*'Supuestos'!$C$12)*D$9)*'Supuestos'!$C$24)*'Supuestos'!$C$23)+(((((IF(('Supuestos'!$C$9)=0,0,'Supuestos'!$C$8/('Supuestos'!$C$9)))*'Supuestos'!$C$12)*D$9)*'Supuestos'!$C$26)*'Supuestos'!$C$25)+(((((IF(('Supuestos'!$C$9)=0,0,'Supuestos'!$C$8/('Supuestos'!$C$9)))*'Supuestos'!$C$12)*D$9)*'Supuestos'!$C$28)*'Supuestos'!$C$27)+(((((IF(('Supuestos'!$C$9)=0,0,'Supuestos'!$C$8/('Supuestos'!$C$9)))*'Supuestos'!$C$12)*D$9)*'Supuestos'!$C$30)*'Supuestos'!$C$29))*('Supuestos'!$C$40+'Supuestos'!$C$41+'Supuestos'!$C$42))*(1-'Supuestos'!$C$33-'Supuestos'!$C$34-'Supuestos'!$C$35))-((IF(('Supuestos'!$C$9)=0,0,'Supuestos'!$C$8/('Supuestos'!$C$9)))*'Supuestos'!$C$36)-'Supuestos'!$C$37-'Supuestos'!$C$8) | E14: =((((((((IF(('Supuestos'!$C$9)=0,0,'Supuestos'!$C$8/('Supuestos'!$C$9)))*'Supuestos'!$C$12)*E$9)*$B14)+(((((IF(('Supuestos'!$C$9)=0,0,'Supuestos'!$C$8/('Supuestos'!$C$9)))*'Supuestos'!$C$12)*E$9)*'Supuestos'!$C$18)*'Supuestos'!$C$17)+(((((IF(('Supuestos'!$C$9)=0,0,'Supuestos'!$C$8/('Supuestos'!$C$9)))*'Supuestos'!$C$12)*E$9)*'Supuestos'!$C$20)*'Supuestos'!$C$19)+(((((IF(('Supuestos'!$C$9)=0,0,'Supuestos'!$C$8/('Supuestos'!$C$9)))*'Supuestos'!$C$12)*E$9)*'Supuestos'!$C$22)*'Supuestos'!$C$21)+(((((IF(('Supuestos'!$C$9)=0,0,'Supuestos'!$C$8/('Supuestos'!$C$9)))*'Supuestos'!$C$12)*E$9)*'Supuestos'!$C$24)*'Supuestos'!$C$23)+(((((IF(('Supuestos'!$C$9)=0,0,'Supuestos'!$C$8/('Supuestos'!$C$9)))*'Supuestos'!$C$12)*E$9)*'Supuestos'!$C$26)*'Supuestos'!$C$25)+(((((IF(('Supuestos'!$C$9)=0,0,'Supuestos'!$C$8/('Supuestos'!$C$9)))*'Supuestos'!$C$12)*E$9)*'Supuestos'!$C$28)*'Supuestos'!$C$27)+(((((IF(('Supuestos'!$C$9)=0,0,'Supuestos'!$C$8/('Supuestos'!$C$9)))*'Supuestos'!$C$12)*E$9)*'Supuestos'!$C$30)*'Supuestos'!$C$29))*('Supuestos'!$C$40+'Supuestos'!$C$41+'Supuestos'!$C$42))*(1-'Supuestos'!$C$33-'Supuestos'!$C$34-'Supuestos'!$C$35))-((IF(('Supuestos'!$C$9)=0,0,'Supuestos'!$C$8/('Supuestos'!$C$9)))*'Supuestos'!$C$36)-'Supuestos'!$C$37-'Supuestos'!$C$8) | F14: =((((((((IF(('Supuestos'!$C$9)=0,0,'Supuestos'!$C$8/('Supuestos'!$C$9)))*'Supuestos'!$C$12)*F$9)*$B14)+(((((IF(('Supuestos'!$C$9)=0,0,'Supuestos'!$C$8/('Supuestos'!$C$9)))*'Supuestos'!$C$12)*F$9)*'Supuestos'!$C$18)*'Supuestos'!$C$17)+(((((IF(('Supuestos'!$C$9)=0,0,'Supuestos'!$C$8/('Supuestos'!$C$9)))*'Supuestos'!$C$12)*F$9)*'Supuestos'!$C$20)*'Supuestos'!$C$19)+(((((IF(('Supuestos'!$C$9)=0,0,'Supuestos'!$C$8/('Supuestos'!$C$9)))*'Supuestos'!$C$12)*F$9)*'Supuestos'!$C$22)*'Supuestos'!$C$21)+(((((IF(('Supuestos'!$C$9)=0,0,'Supuestos'!$C$8/('Supuestos'!$C$9)))*'Supuestos'!$C$12)*F$9)*'Supuestos'!$C$24)*'Supuestos'!$C$23)+(((((IF(('Supuestos'!$C$9)=0,0,'Supuestos'!$C$8/('Supuestos'!$C$9)))*'Supuestos'!$C$12)*F$9)*'Supuestos'!$C$26)*'Supuestos'!$C$25)+(((((IF(('Supuestos'!$C$9)=0,0,'Supuestos'!$C$8/('Supuestos'!$C$9)))*'Supuestos'!$C$12)*F$9)*'Supuestos'!$C$28)*'Supuestos'!$C$27)+(((((IF(('Supuestos'!$C$9)=0,0,'Supuestos'!$C$8/('Supuestos'!$C$9)))*'Supuestos'!$C$12)*F$9)*'Supuestos'!$C$30)*'Supuestos'!$C$29))*('Supuestos'!$C$40+'Supuestos'!$C$41+'Supuestos'!$C$42))*(1-'Supuestos'!$C$33-'Supuestos'!$C$34-'Supuestos'!$C$35))-((IF(('Supuestos'!$C$9)=0,0,'Supuestos'!$C$8/('Supuestos'!$C$9)))*'Supuestos'!$C$36)-'Supuestos'!$C$37-'Supuestos'!$C$8) | G14: =((((((((IF(('Supuestos'!$C$9)=0,0,'Supuestos'!$C$8/('Supuestos'!$C$9)))*'Supuestos'!$C$12)*G$9)*$B14)+(((((IF(('Supuestos'!$C$9)=0,0,'Supuestos'!$C$8/('Supuestos'!$C$9)))*'Supuestos'!$C$12)*G$9)*'Supuestos'!$C$18)*'Supuestos'!$C$17)+(((((IF(('Supuestos'!$C$9)=0,0,'Supuestos'!$C$8/('Supuestos'!$C$9)))*'Supuestos'!$C$12)*G$9)*'Supuestos'!$C$20)*'Supuestos'!$C$19)+(((((IF(('Supuestos'!$C$9)=0,0,'Supuestos'!$C$8/('Supuestos'!$C$9)))*'Supuestos'!$C$12)*G$9)*'Supuestos'!$C$22)*'Supuestos'!$C$21)+(((((IF(('Supuestos'!$C$9)=0,0,'Supuestos'!$C$8/('Supuestos'!$C$9)))*'Supuestos'!$C$12)*G$9)*'Supuestos'!$C$24)*'Supuestos'!$C$23)+(((((IF(('Supuestos'!$C$9)=0,0,'Supuestos'!$C$8/('Supuestos'!$C$9)))*'Supuestos'!$C$12)*G$9)*'Supuestos'!$C$26)*'Supuestos'!$C$25)+(((((IF(('Supuestos'!$C$9)=0,0,'Supuestos'!$C$8/('Supuestos'!$C$9)))*'Supuestos'!$C$12)*G$9)*'Supuestos'!$C$28)*'Supuestos'!$C$27)+(((((IF(('Supuestos'!$C$9)=0,0,'Supuestos'!$C$8/('Supuestos'!$C$9)))*'Supuestos'!$C$12)*G$9)*'Supuestos'!$C$30)*'Supuestos'!$C$29))*('Supuestos'!$C$40+'Supuestos'!$C$41+'Supuestos'!$C$42))*(1-'Supuestos'!$C$33-'Supuestos'!$C$34-'Supuestos'!$C$35))-((IF(('Supuestos'!$C$9)=0,0,'Supuestos'!$C$8/('Supuestos'!$C$9)))*'Supuestos'!$C$36)-'Supuestos'!$C$37-'Supuestos'!$C$8)
B17: Costo por visita × % de visitas que llegan al checkout → ganancia del mes
B18: La tabla del tráfico: cuánto podés pagar por visita según lo que convierte la página.
B19: Costo por visita ↓ / % visita → checkout → | C19: 0.02 | D19: 0.025 | E19: 0.03 | F19: 0.035 | G19: 0.04 | H19: 0.05
B20: 0.15 | C20: =((((((((IF($B20=0,0,'Supuestos'!$C$8/$B20))*C$19)*'Supuestos'!$C$13)*'Supuestos'!$C$16)+(((((IF($B20=0,0,'Supuestos'!$C$8/$B20))*C$19)*'Supuestos'!$C$13)*'Supuestos'!$C$18)*'Supuestos'!$C$17)+(((((IF($B20=0,0,'Supuestos'!$C$8/$B20))*C$19)*'Supuestos'!$C$13)*'Supuestos'!$C$20)*'Supuestos'!$C$19)+(((((IF($B20=0,0,'Supuestos'!$C$8/$B20))*C$19)*'Supuestos'!$C$13)*'Supuestos'!$C$22)*'Supuestos'!$C$21)+(((((IF($B20=0,0,'Supuestos'!$C$8/$B20))*C$19)*'Supuestos'!$C$13)*'Supuestos'!$C$24)*'Supuestos'!$C$23)+(((((IF($B20=0,0,'Supuestos'!$C$8/$B20))*C$19)*'Supuestos'!$C$13)*'Supuestos'!$C$26)*'Supuestos'!$C$25)+(((((IF($B20=0,0,'Supuestos'!$C$8/$B20))*C$19)*'Supuestos'!$C$13)*'Supuestos'!$C$28)*'Supuestos'!$C$27)+(((((IF($B20=0,0,'Supuestos'!$C$8/$B20))*C$19)*'Supuestos'!$C$13)*'Supuestos'!$C$30)*'Supuestos'!$C$29))*('Supuestos'!$C$40+'Supuestos'!$C$41+'Supuestos'!$C$42))*(1-'Supuestos'!$C$33-'Supuestos'!$C$34-'Supuestos'!$C$35))-((IF($B20=0,0,'Supuestos'!$C$8/$B20))*'Supuestos'!$C$36)-'Supuestos'!$C$37-'Supuestos'!$C$8) | D20: =((((((((IF($B20=0,0,'Supuestos'!$C$8/$B20))*D$19)*'Supuestos'!$C$13)*'Supuestos'!$C$16)+(((((IF($B20=0,0,'Supuestos'!$C$8/$B20))*D$19)*'Supuestos'!$C$13)*'Supuestos'!$C$18)*'Supuestos'!$C$17)+(((((IF($B20=0,0,'Supuestos'!$C$8/$B20))*D$19)*'Supuestos'!$C$13)*'Supuestos'!$C$20)*'Supuestos'!$C$19)+(((((IF($B20=0,0,'Supuestos'!$C$8/$B20))*D$19)*'Supuestos'!$C$13)*'Supuestos'!$C$22)*'Supuestos'!$C$21)+(((((IF($B20=0,0,'Supuestos'!$C$8/$B20))*D$19)*'Supuestos'!$C$13)*'Supuestos'!$C$24)*'Supuestos'!$C$23)+(((((IF($B20=0,0,'Supuestos'!$C$8/$B20))*D$19)*'Supuestos'!$C$13)*'Supuestos'!$C$26)*'Supuestos'!$C$25)+(((((IF($B20=0,0,'Supuestos'!$C$8/$B20))*D$19)*'Supuestos'!$C$13)*'Supuestos'!$C$28)*'Supuestos'!$C$27)+(((((IF($B20=0,0,'Supuestos'!$C$8/$B20))*D$19)*'Supuestos'!$C$13)*'Supuestos'!$C$30)*'Supuestos'!$C$29))*('Supuestos'!$C$40+'Supuestos'!$C$41+'Supuestos'!$C$42))*(1-'Supuestos'!$C$33-'Supuestos'!$C$34-'Supuestos'!$C$35))-((IF($B20=0,0,'Supuestos'!$C$8/$B20))*'Supuestos'!$C$36)-'Supuestos'!$C$37-'Supuestos'!$C$8) | E20: =((((((((IF($B20=0,0,'Supuestos'!$C$8/$B20))*E$19)*'Supuestos'!$C$13)*'Supuestos'!$C$16)+(((((IF($B20=0,0,'Supuestos'!$C$8/$B20))*E$19)*'Supuestos'!$C$13)*'Supuestos'!$C$18)*'Supuestos'!$C$17)+(((((IF($B20=0,0,'Supuestos'!$C$8/$B20))*E$19)*'Supuestos'!$C$13)*'Supuestos'!$C$20)*'Supuestos'!$C$19)+(((((IF($B20=0,0,'Supuestos'!$C$8/$B20))*E$19)*'Supuestos'!$C$13)*'Supuestos'!$C$22)*'Supuestos'!$C$21)+(((((IF($B20=0,0,'Supuestos'!$C$8/$B20))*E$19)*'Supuestos'!$C$13)*'Supuestos'!$C$24)*'Supuestos'!$C$23)+(((((IF($B20=0,0,'Supuestos'!$C$8/$B20))*E$19)*'Supuestos'!$C$13)*'Supuestos'!$C$26)*'Supuestos'!$C$25)+(((((IF($B20=0,0,'Supuestos'!$C$8/$B20))*E$19)*'Supuestos'!$C$13)*'Supuestos'!$C$28)*'Supuestos'!$C$27)+(((((IF($B20=0,0,'Supuestos'!$C$8/$B20))*E$19)*'Supuestos'!$C$13)*'Supuestos'!$C$30)*'Supuestos'!$C$29))*('Supuestos'!$C$40+'Supuestos'!$C$41+'Supuestos'!$C$42))*(1-'Supuestos'!$C$33-'Supuestos'!$C$34-'Supuestos'!$C$35))-((IF($B20=0,0,'Supuestos'!$C$8/$B20))*'Supuestos'!$C$36)-'Supuestos'!$C$37-'Supuestos'!$C$8) | F20: =((((((((IF($B20=0,0,'Supuestos'!$C$8/$B20))*F$19)*'Supuestos'!$C$13)*'Supuestos'!$C$16)+(((((IF($B20=0,0,'Supuestos'!$C$8/$B20))*F$19)*'Supuestos'!$C$13)*'Supuestos'!$C$18)*'Supuestos'!$C$17)+(((((IF($B20=0,0,'Supuestos'!$C$8/$B20))*F$19)*'Supuestos'!$C$13)*'Supuestos'!$C$20)*'Supuestos'!$C$19)+(((((IF($B20=0,0,'Supuestos'!$C$8/$B20))*F$19)*'Supuestos'!$C$13)*'Supuestos'!$C$22)*'Supuestos'!$C$21)+(((((IF($B20=0,0,'Supuestos'!$C$8/$B20))*F$19)*'Supuestos'!$C$13)*'Supuestos'!$C$24)*'Supuestos'!$C$23)+(((((IF($B20=0,0,'Supuestos'!$C$8/$B20))*F$19)*'Supuestos'!$C$13)*'Supuestos'!$C$26)*'Supuestos'!$C$25)+(((((IF($B20=0,0,'Supuestos'!$C$8/$B20))*F$19)*'Supuestos'!$C$13)*'Supuestos'!$C$28)*'Supuestos'!$C$27)+(((((IF($B20=0,0,'Supuestos'!$C$8/$B20))*F$19)*'Supuestos'!$C$13)*'Supuestos'!$C$30)*'Supuestos'!$C$29))*('Supuestos'!$C$40+'Supuestos'!$C$41+'Supuestos'!$C$42))*(1-'Supuestos'!$C$33-'Supuestos'!$C$34-'Supuestos'!$C$35))-((IF($B20=0,0,'Supuestos'!$C$8/$B20))*'Supuestos'!$C$36)-'Supuestos'!$C$37-'Supuestos'!$C$8) | G20: =((((((((IF($B20=0,0,'Supuestos'!$C$8/$B20))*G$19)*'Supuestos'!$C$13)*'Supuestos'!$C$16)+(((((IF($B20=0,0,'Supuestos'!$C$8/$B20))*G$19)*'Supuestos'!$C$13)*'Supuestos'!$C$18)*'Supuestos'!$C$17)+(((((IF($B20=0,0,'Supuestos'!$C$8/$B20))*G$19)*'Supuestos'!$C$13)*'Supuestos'!$C$20)*'Supuestos'!$C$19)+(((((IF($B20=0,0,'Supuestos'!$C$8/$B20))*G$19)*'Supuestos'!$C$13)*'Supuestos'!$C$22)*'Supuestos'!$C$21)+(((((IF($B20=0,0,'Supuestos'!$C$8/$B20))*G$19)*'Supuestos'!$C$13)*'Supuestos'!$C$24)*'Supuestos'!$C$23)+(((((IF($B20=0,0,'Supuestos'!$C$8/$B20))*G$19)*'Supuestos'!$C$13)*'Supuestos'!$C$26)*'Supuestos'!$C$25)+(((((IF($B20=0,0,'Supuestos'!$C$8/$B20))*G$19)*'Supuestos'!$C$13)*'Supuestos'!$C$28)*'Supuestos'!$C$27)+(((((IF($B20=0,0,'Supuestos'!$C$8/$B20))*G$19)*'Supuestos'!$C$13)*'Supuestos'!$C$30)*'Supuestos'!$C$29))*('Supuestos'!$C$40+'Supuestos'!$C$41+'Supuestos'!$C$42))*(1-'Supuestos'!$C$33-'Supuestos'!$C$34-'Supuestos'!$C$35))-((IF($B20=0,0,'Supuestos'!$C$8/$B20))*'Supuestos'!$C$36)-'Supuestos'!$C$37-'Supuestos'!$C$8) | H20: =((((((((IF($B20=0,0,'Supuestos'!$C$8/$B20))*H$19)*'Supuestos'!$C$13)*'Supuestos'!$C$16)+(((((IF($B20=0,0,'Supuestos'!$C$8/$B20))*H$19)*'Supuestos'!$C$13)*'Supuestos'!$C$18)*'Supuestos'!$C$17)+(((((IF($B20=0,0,'Supuestos'!$C$8/$B20))*H$19)*'Supuestos'!$C$13)*'Supuestos'!$C$20)*'Supuestos'!$C$19)+(((((IF($B20=0,0,'Supuestos'!$C$8/$B20))*H$19)*'Supuestos'!$C$13)*'Supuestos'!$C$22)*'Supuestos'!$C$21)+(((((IF($B20=0,0,'Supuestos'!$C$8/$B20))*H$19)*'Supuestos'!$C$13)*'Supuestos'!$C$24)*'Supuestos'!$C$23)+(((((IF($B20=0,0,'Supuestos'!$C$8/$B20))*H$19)*'Supuestos'!$C$13)*'Supuestos'!$C$26)*'Supuestos'!$C$25)+(((((IF($B20=0,0,'Supuestos'!$C$8/$B20))*H$19)*'Supuestos'!$C$13)*'Supuestos'!$C$28)*'Supuestos'!$C$27)+(((((IF($B20=0,0,'Supuestos'!$C$8/$B20))*H$19)*'Supuestos'!$C$13)*'Supuestos'!$C$30)*'Supuestos'!$C$29))*('Supuestos'!$C$40+'Supuestos'!$C$41+'Supuestos'!$C$42))*(1-'Supuestos'!$C$33-'Supuestos'!$C$34-'Supuestos'!$C$35))-((IF($B20=0,0,'Supuestos'!$C$8/$B20))*'Supuestos'!$C$36)-'Supuestos'!$C$37-'Supuestos'!$C$8)
B21: 0.2 | C21: =((((((((IF($B21=0,0,'Supuestos'!$C$8/$B21))*C$19)*'Supuestos'!$C$13)*'Supuestos'!$C$16)+(((((IF($B21=0,0,'Supuestos'!$C$8/$B21))*C$19)*'Supuestos'!$C$13)*'Supuestos'!$C$18)*'Supuestos'!$C$17)+(((((IF($B21=0,0,'Supuestos'!$C$8/$B21))*C$19)*'Supuestos'!$C$13)*'Supuestos'!$C$20)*'Supuestos'!$C$19)+(((((IF($B21=0,0,'Supuestos'!$C$8/$B21))*C$19)*'Supuestos'!$C$13)*'Supuestos'!$C$22)*'Supuestos'!$C$21)+(((((IF($B21=0,0,'Supuestos'!$C$8/$B21))*C$19)*'Supuestos'!$C$13)*'Supuestos'!$C$24)*'Supuestos'!$C$23)+(((((IF($B21=0,0,'Supuestos'!$C$8/$B21))*C$19)*'Supuestos'!$C$13)*'Supuestos'!$C$26)*'Supuestos'!$C$25)+(((((IF($B21=0,0,'Supuestos'!$C$8/$B21))*C$19)*'Supuestos'!$C$13)*'Supuestos'!$C$28)*'Supuestos'!$C$27)+(((((IF($B21=0,0,'Supuestos'!$C$8/$B21))*C$19)*'Supuestos'!$C$13)*'Supuestos'!$C$30)*'Supuestos'!$C$29))*('Supuestos'!$C$40+'Supuestos'!$C$41+'Supuestos'!$C$42))*(1-'Supuestos'!$C$33-'Supuestos'!$C$34-'Supuestos'!$C$35))-((IF($B21=0,0,'Supuestos'!$C$8/$B21))*'Supuestos'!$C$36)-'Supuestos'!$C$37-'Supuestos'!$C$8) | D21: =((((((((IF($B21=0,0,'Supuestos'!$C$8/$B21))*D$19)*'Supuestos'!$C$13)*'Supuestos'!$C$16)+(((((IF($B21=0,0,'Supuestos'!$C$8/$B21))*D$19)*'Supuestos'!$C$13)*'Supuestos'!$C$18)*'Supuestos'!$C$17)+(((((IF($B21=0,0,'Supuestos'!$C$8/$B21))*D$19)*'Supuestos'!$C$13)*'Supuestos'!$C$20)*'Supuestos'!$C$19)+(((((IF($B21=0,0,'Supuestos'!$C$8/$B21))*D$19)*'Supuestos'!$C$13)*'Supuestos'!$C$22)*'Supuestos'!$C$21)+(((((IF($B21=0,0,'Supuestos'!$C$8/$B21))*D$19)*'Supuestos'!$C$13)*'Supuestos'!$C$24)*'Supuestos'!$C$23)+(((((IF($B21=0,0,'Supuestos'!$C$8/$B21))*D$19)*'Supuestos'!$C$13)*'Supuestos'!$C$26)*'Supuestos'!$C$25)+(((((IF($B21=0,0,'Supuestos'!$C$8/$B21))*D$19)*'Supuestos'!$C$13)*'Supuestos'!$C$28)*'Supuestos'!$C$27)+(((((IF($B21=0,0,'Supuestos'!$C$8/$B21))*D$19)*'Supuestos'!$C$13)*'Supuestos'!$C$30)*'Supuestos'!$C$29))*('Supuestos'!$C$40+'Supuestos'!$C$41+'Supuestos'!$C$42))*(1-'Supuestos'!$C$33-'Supuestos'!$C$34-'Supuestos'!$C$35))-((IF($B21=0,0,'Supuestos'!$C$8/$B21))*'Supuestos'!$C$36)-'Supuestos'!$C$37-'Supuestos'!$C$8) | E21: =((((((((IF($B21=0,0,'Supuestos'!$C$8/$B21))*E$19)*'Supuestos'!$C$13)*'Supuestos'!$C$16)+(((((IF($B21=0,0,'Supuestos'!$C$8/$B21))*E$19)*'Supuestos'!$C$13)*'Supuestos'!$C$18)*'Supuestos'!$C$17)+(((((IF($B21=0,0,'Supuestos'!$C$8/$B21))*E$19)*'Supuestos'!$C$13)*'Supuestos'!$C$20)*'Supuestos'!$C$19)+(((((IF($B21=0,0,'Supuestos'!$C$8/$B21))*E$19)*'Supuestos'!$C$13)*'Supuestos'!$C$22)*'Supuestos'!$C$21)+(((((IF($B21=0,0,'Supuestos'!$C$8/$B21))*E$19)*'Supuestos'!$C$13)*'Supuestos'!$C$24)*'Supuestos'!$C$23)+(((((IF($B21=0,0,'Supuestos'!$C$8/$B21))*E$19)*'Supuestos'!$C$13)*'Supuestos'!$C$26)*'Supuestos'!$C$25)+(((((IF($B21=0,0,'Supuestos'!$C$8/$B21))*E$19)*'Supuestos'!$C$13)*'Supuestos'!$C$28)*'Supuestos'!$C$27)+(((((IF($B21=0,0,'Supuestos'!$C$8/$B21))*E$19)*'Supuestos'!$C$13)*'Supuestos'!$C$30)*'Supuestos'!$C$29))*('Supuestos'!$C$40+'Supuestos'!$C$41+'Supuestos'!$C$42))*(1-'Supuestos'!$C$33-'Supuestos'!$C$34-'Supuestos'!$C$35))-((IF($B21=0,0,'Supuestos'!$C$8/$B21))*'Supuestos'!$C$36)-'Supuestos'!$C$37-'Supuestos'!$C$8) | F21: =((((((((IF($B21=0,0,'Supuestos'!$C$8/$B21))*F$19)*'Supuestos'!$C$13)*'Supuestos'!$C$16)+(((((IF($B21=0,0,'Supuestos'!$C$8/$B21))*F$19)*'Supuestos'!$C$13)*'Supuestos'!$C$18)*'Supuestos'!$C$17)+(((((IF($B21=0,0,'Supuestos'!$C$8/$B21))*F$19)*'Supuestos'!$C$13)*'Supuestos'!$C$20)*'Supuestos'!$C$19)+(((((IF($B21=0,0,'Supuestos'!$C$8/$B21))*F$19)*'Supuestos'!$C$13)*'Supuestos'!$C$22)*'Supuestos'!$C$21)+(((((IF($B21=0,0,'Supuestos'!$C$8/$B21))*F$19)*'Supuestos'!$C$13)*'Supuestos'!$C$24)*'Supuestos'!$C$23)+(((((IF($B21=0,0,'Supuestos'!$C$8/$B21))*F$19)*'Supuestos'!$C$13)*'Supuestos'!$C$26)*'Supuestos'!$C$25)+(((((IF($B21=0,0,'Supuestos'!$C$8/$B21))*F$19)*'Supuestos'!$C$13)*'Supuestos'!$C$28)*'Supuestos'!$C$27)+(((((IF($B21=0,0,'Supuestos'!$C$8/$B21))*F$19)*'Supuestos'!$C$13)*'Supuestos'!$C$30)*'Supuestos'!$C$29))*('Supuestos'!$C$40+'Supuestos'!$C$41+'Supuestos'!$C$42))*(1-'Supuestos'!$C$33-'Supuestos'!$C$34-'Supuestos'!$C$35))-((IF($B21=0,0,'Supuestos'!$C$8/$B21))*'Supuestos'!$C$36)-'Supuestos'!$C$37-'Supuestos'!$C$8) | G21: =((((((((IF($B21=0,0,'Supuestos'!$C$8/$B21))*G$19)*'Supuestos'!$C$13)*'Supuestos'!$C$16)+(((((IF($B21=0,0,'Supuestos'!$C$8/$B21))*G$19)*'Supuestos'!$C$13)*'Supuestos'!$C$18)*'Supuestos'!$C$17)+(((((IF($B21=0,0,'Supuestos'!$C$8/$B21))*G$19)*'Supuestos'!$C$13)*'Supuestos'!$C$20)*'Supuestos'!$C$19)+(((((IF($B21=0,0,'Supuestos'!$C$8/$B21))*G$19)*'Supuestos'!$C$13)*'Supuestos'!$C$22)*'Supuestos'!$C$21)+(((((IF($B21=0,0,'Supuestos'!$C$8/$B21))*G$19)*'Supuestos'!$C$13)*'Supuestos'!$C$24)*'Supuestos'!$C$23)+(((((IF($B21=0,0,'Supuestos'!$C$8/$B21))*G$19)*'Supuestos'!$C$13)*'Supuestos'!$C$26)*'Supuestos'!$C$25)+(((((IF($B21=0,0,'Supuestos'!$C$8/$B21))*G$19)*'Supuestos'!$C$13)*'Supuestos'!$C$28)*'Supuestos'!$C$27)+(((((IF($B21=0,0,'Supuestos'!$C$8/$B21))*G$19)*'Supuestos'!$C$13)*'Supuestos'!$C$30)*'Supuestos'!$C$29))*('Supuestos'!$C$40+'Supuestos'!$C$41+'Supuestos'!$C$42))*(1-'Supuestos'!$C$33-'Supuestos'!$C$34-'Supuestos'!$C$35))-((IF($B21=0,0,'Supuestos'!$C$8/$B21))*'Supuestos'!$C$36)-'Supuestos'!$C$37-'Supuestos'!$C$8) | H21: =((((((((IF($B21=0,0,'Supuestos'!$C$8/$B21))*H$19)*'Supuestos'!$C$13)*'Supuestos'!$C$16)+(((((IF($B21=0,0,'Supuestos'!$C$8/$B21))*H$19)*'Supuestos'!$C$13)*'Supuestos'!$C$18)*'Supuestos'!$C$17)+(((((IF($B21=0,0,'Supuestos'!$C$8/$B21))*H$19)*'Supuestos'!$C$13)*'Supuestos'!$C$20)*'Supuestos'!$C$19)+(((((IF($B21=0,0,'Supuestos'!$C$8/$B21))*H$19)*'Supuestos'!$C$13)*'Supuestos'!$C$22)*'Supuestos'!$C$21)+(((((IF($B21=0,0,'Supuestos'!$C$8/$B21))*H$19)*'Supuestos'!$C$13)*'Supuestos'!$C$24)*'Supuestos'!$C$23)+(((((IF($B21=0,0,'Supuestos'!$C$8/$B21))*H$19)*'Supuestos'!$C$13)*'Supuestos'!$C$26)*'Supuestos'!$C$25)+(((((IF($B21=0,0,'Supuestos'!$C$8/$B21))*H$19)*'Supuestos'!$C$13)*'Supuestos'!$C$28)*'Supuestos'!$C$27)+(((((IF($B21=0,0,'Supuestos'!$C$8/$B21))*H$19)*'Supuestos'!$C$13)*'Supuestos'!$C$30)*'Supuestos'!$C$29))*('Supuestos'!$C$40+'Supuestos'!$C$41+'Supuestos'!$C$42))*(1-'Supuestos'!$C$33-'Supuestos'!$C$34-'Supuestos'!$C$35))-((IF($B21=0,0,'Supuestos'!$C$8/$B21))*'Supuestos'!$C$36)-'Supuestos'!$C$37-'Supuestos'!$C$8)
B22: 0.25 | C22: =((((((((IF($B22=0,0,'Supuestos'!$C$8/$B22))*C$19)*'Supuestos'!$C$13)*'Supuestos'!$C$16)+(((((IF($B22=0,0,'Supuestos'!$C$8/$B22))*C$19)*'Supuestos'!$C$13)*'Supuestos'!$C$18)*'Supuestos'!$C$17)+(((((IF($B22=0,0,'Supuestos'!$C$8/$B22))*C$19)*'Supuestos'!$C$13)*'Supuestos'!$C$20)*'Supuestos'!$C$19)+(((((IF($B22=0,0,'Supuestos'!$C$8/$B22))*C$19)*'Supuestos'!$C$13)*'Supuestos'!$C$22)*'Supuestos'!$C$21)+(((((IF($B22=0,0,'Supuestos'!$C$8/$B22))*C$19)*'Supuestos'!$C$13)*'Supuestos'!$C$24)*'Supuestos'!$C$23)+(((((IF($B22=0,0,'Supuestos'!$C$8/$B22))*C$19)*'Supuestos'!$C$13)*'Supuestos'!$C$26)*'Supuestos'!$C$25)+(((((IF($B22=0,0,'Supuestos'!$C$8/$B22))*C$19)*'Supuestos'!$C$13)*'Supuestos'!$C$28)*'Supuestos'!$C$27)+(((((IF($B22=0,0,'Supuestos'!$C$8/$B22))*C$19)*'Supuestos'!$C$13)*'Supuestos'!$C$30)*'Supuestos'!$C$29))*('Supuestos'!$C$40+'Supuestos'!$C$41+'Supuestos'!$C$42))*(1-'Supuestos'!$C$33-'Supuestos'!$C$34-'Supuestos'!$C$35))-((IF($B22=0,0,'Supuestos'!$C$8/$B22))*'Supuestos'!$C$36)-'Supuestos'!$C$37-'Supuestos'!$C$8) | D22: =((((((((IF($B22=0,0,'Supuestos'!$C$8/$B22))*D$19)*'Supuestos'!$C$13)*'Supuestos'!$C$16)+(((((IF($B22=0,0,'Supuestos'!$C$8/$B22))*D$19)*'Supuestos'!$C$13)*'Supuestos'!$C$18)*'Supuestos'!$C$17)+(((((IF($B22=0,0,'Supuestos'!$C$8/$B22))*D$19)*'Supuestos'!$C$13)*'Supuestos'!$C$20)*'Supuestos'!$C$19)+(((((IF($B22=0,0,'Supuestos'!$C$8/$B22))*D$19)*'Supuestos'!$C$13)*'Supuestos'!$C$22)*'Supuestos'!$C$21)+(((((IF($B22=0,0,'Supuestos'!$C$8/$B22))*D$19)*'Supuestos'!$C$13)*'Supuestos'!$C$24)*'Supuestos'!$C$23)+(((((IF($B22=0,0,'Supuestos'!$C$8/$B22))*D$19)*'Supuestos'!$C$13)*'Supuestos'!$C$26)*'Supuestos'!$C$25)+(((((IF($B22=0,0,'Supuestos'!$C$8/$B22))*D$19)*'Supuestos'!$C$13)*'Supuestos'!$C$28)*'Supuestos'!$C$27)+(((((IF($B22=0,0,'Supuestos'!$C$8/$B22))*D$19)*'Supuestos'!$C$13)*'Supuestos'!$C$30)*'Supuestos'!$C$29))*('Supuestos'!$C$40+'Supuestos'!$C$41+'Supuestos'!$C$42))*(1-'Supuestos'!$C$33-'Supuestos'!$C$34-'Supuestos'!$C$35))-((IF($B22=0,0,'Supuestos'!$C$8/$B22))*'Supuestos'!$C$36)-'Supuestos'!$C$37-'Supuestos'!$C$8) | E22: =((((((((IF($B22=0,0,'Supuestos'!$C$8/$B22))*E$19)*'Supuestos'!$C$13)*'Supuestos'!$C$16)+(((((IF($B22=0,0,'Supuestos'!$C$8/$B22))*E$19)*'Supuestos'!$C$13)*'Supuestos'!$C$18)*'Supuestos'!$C$17)+(((((IF($B22=0,0,'Supuestos'!$C$8/$B22))*E$19)*'Supuestos'!$C$13)*'Supuestos'!$C$20)*'Supuestos'!$C$19)+(((((IF($B22=0,0,'Supuestos'!$C$8/$B22))*E$19)*'Supuestos'!$C$13)*'Supuestos'!$C$22)*'Supuestos'!$C$21)+(((((IF($B22=0,0,'Supuestos'!$C$8/$B22))*E$19)*'Supuestos'!$C$13)*'Supuestos'!$C$24)*'Supuestos'!$C$23)+(((((IF($B22=0,0,'Supuestos'!$C$8/$B22))*E$19)*'Supuestos'!$C$13)*'Supuestos'!$C$26)*'Supuestos'!$C$25)+(((((IF($B22=0,0,'Supuestos'!$C$8/$B22))*E$19)*'Supuestos'!$C$13)*'Supuestos'!$C$28)*'Supuestos'!$C$27)+(((((IF($B22=0,0,'Supuestos'!$C$8/$B22))*E$19)*'Supuestos'!$C$13)*'Supuestos'!$C$30)*'Supuestos'!$C$29))*('Supuestos'!$C$40+'Supuestos'!$C$41+'Supuestos'!$C$42))*(1-'Supuestos'!$C$33-'Supuestos'!$C$34-'Supuestos'!$C$35))-((IF($B22=0,0,'Supuestos'!$C$8/$B22))*'Supuestos'!$C$36)-'Supuestos'!$C$37-'Supuestos'!$C$8) | F22: =((((((((IF($B22=0,0,'Supuestos'!$C$8/$B22))*F$19)*'Supuestos'!$C$13)*'Supuestos'!$C$16)+(((((IF($B22=0,0,'Supuestos'!$C$8/$B22))*F$19)*'Supuestos'!$C$13)*'Supuestos'!$C$18)*'Supuestos'!$C$17)+(((((IF($B22=0,0,'Supuestos'!$C$8/$B22))*F$19)*'Supuestos'!$C$13)*'Supuestos'!$C$20)*'Supuestos'!$C$19)+(((((IF($B22=0,0,'Supuestos'!$C$8/$B22))*F$19)*'Supuestos'!$C$13)*'Supuestos'!$C$22)*'Supuestos'!$C$21)+(((((IF($B22=0,0,'Supuestos'!$C$8/$B22))*F$19)*'Supuestos'!$C$13)*'Supuestos'!$C$24)*'Supuestos'!$C$23)+(((((IF($B22=0,0,'Supuestos'!$C$8/$B22))*F$19)*'Supuestos'!$C$13)*'Supuestos'!$C$26)*'Supuestos'!$C$25)+(((((IF($B22=0,0,'Supuestos'!$C$8/$B22))*F$19)*'Supuestos'!$C$13)*'Supuestos'!$C$28)*'Supuestos'!$C$27)+(((((IF($B22=0,0,'Supuestos'!$C$8/$B22))*F$19)*'Supuestos'!$C$13)*'Supuestos'!$C$30)*'Supuestos'!$C$29))*('Supuestos'!$C$40+'Supuestos'!$C$41+'Supuestos'!$C$42))*(1-'Supuestos'!$C$33-'Supuestos'!$C$34-'Supuestos'!$C$35))-((IF($B22=0,0,'Supuestos'!$C$8/$B22))*'Supuestos'!$C$36)-'Supuestos'!$C$37-'Supuestos'!$C$8) | G22: =((((((((IF($B22=0,0,'Supuestos'!$C$8/$B22))*G$19)*'Supuestos'!$C$13)*'Supuestos'!$C$16)+(((((IF($B22=0,0,'Supuestos'!$C$8/$B22))*G$19)*'Supuestos'!$C$13)*'Supuestos'!$C$18)*'Supuestos'!$C$17)+(((((IF($B22=0,0,'Supuestos'!$C$8/$B22))*G$19)*'Supuestos'!$C$13)*'Supuestos'!$C$20)*'Supuestos'!$C$19)+(((((IF($B22=0,0,'Supuestos'!$C$8/$B22))*G$19)*'Supuestos'!$C$13)*'Supuestos'!$C$22)*'Supuestos'!$C$21)+(((((IF($B22=0,0,'Supuestos'!$C$8/$B22))*G$19)*'Supuestos'!$C$13)*'Supuestos'!$C$24)*'Supuestos'!$C$23)+(((((IF($B22=0,0,'Supuestos'!$C$8/$B22))*G$19)*'Supuestos'!$C$13)*'Supuestos'!$C$26)*'Supuestos'!$C$25)+(((((IF($B22=0,0,'Supuestos'!$C$8/$B22))*G$19)*'Supuestos'!$C$13)*'Supuestos'!$C$28)*'Supuestos'!$C$27)+(((((IF($B22=0,0,'Supuestos'!$C$8/$B22))*G$19)*'Supuestos'!$C$13)*'Supuestos'!$C$30)*'Supuestos'!$C$29))*('Supuestos'!$C$40+'Supuestos'!$C$41+'Supuestos'!$C$42))*(1-'Supuestos'!$C$33-'Supuestos'!$C$34-'Supuestos'!$C$35))-((IF($B22=0,0,'Supuestos'!$C$8/$B22))*'Supuestos'!$C$36)-'Supuestos'!$C$37-'Supuestos'!$C$8) | H22: =((((((((IF($B22=0,0,'Supuestos'!$C$8/$B22))*H$19)*'Supuestos'!$C$13)*'Supuestos'!$C$16)+(((((IF($B22=0,0,'Supuestos'!$C$8/$B22))*H$19)*'Supuestos'!$C$13)*'Supuestos'!$C$18)*'Supuestos'!$C$17)+(((((IF($B22=0,0,'Supuestos'!$C$8/$B22))*H$19)*'Supuestos'!$C$13)*'Supuestos'!$C$20)*'Supuestos'!$C$19)+(((((IF($B22=0,0,'Supuestos'!$C$8/$B22))*H$19)*'Supuestos'!$C$13)*'Supuestos'!$C$22)*'Supuestos'!$C$21)+(((((IF($B22=0,0,'Supuestos'!$C$8/$B22))*H$19)*'Supuestos'!$C$13)*'Supuestos'!$C$24)*'Supuestos'!$C$23)+(((((IF($B22=0,0,'Supuestos'!$C$8/$B22))*H$19)*'Supuestos'!$C$13)*'Supuestos'!$C$26)*'Supuestos'!$C$25)+(((((IF($B22=0,0,'Supuestos'!$C$8/$B22))*H$19)*'Supuestos'!$C$13)*'Supuestos'!$C$28)*'Supuestos'!$C$27)+(((((IF($B22=0,0,'Supuestos'!$C$8/$B22))*H$19)*'Supuestos'!$C$13)*'Supuestos'!$C$30)*'Supuestos'!$C$29))*('Supuestos'!$C$40+'Supuestos'!$C$41+'Supuestos'!$C$42))*(1-'Supuestos'!$C$33-'Supuestos'!$C$34-'Supuestos'!$C$35))-((IF($B22=0,0,'Supuestos'!$C$8/$B22))*'Supuestos'!$C$36)-'Supuestos'!$C$37-'Supuestos'!$C$8)
B23: 0.3 | C23: =((((((((IF($B23=0,0,'Supuestos'!$C$8/$B23))*C$19)*'Supuestos'!$C$13)*'Supuestos'!$C$16)+(((((IF($B23=0,0,'Supuestos'!$C$8/$B23))*C$19)*'Supuestos'!$C$13)*'Supuestos'!$C$18)*'Supuestos'!$C$17)+(((((IF($B23=0,0,'Supuestos'!$C$8/$B23))*C$19)*'Supuestos'!$C$13)*'Supuestos'!$C$20)*'Supuestos'!$C$19)+(((((IF($B23=0,0,'Supuestos'!$C$8/$B23))*C$19)*'Supuestos'!$C$13)*'Supuestos'!$C$22)*'Supuestos'!$C$21)+(((((IF($B23=0,0,'Supuestos'!$C$8/$B23))*C$19)*'Supuestos'!$C$13)*'Supuestos'!$C$24)*'Supuestos'!$C$23)+(((((IF($B23=0,0,'Supuestos'!$C$8/$B23))*C$19)*'Supuestos'!$C$13)*'Supuestos'!$C$26)*'Supuestos'!$C$25)+(((((IF($B23=0,0,'Supuestos'!$C$8/$B23))*C$19)*'Supuestos'!$C$13)*'Supuestos'!$C$28)*'Supuestos'!$C$27)+(((((IF($B23=0,0,'Supuestos'!$C$8/$B23))*C$19)*'Supuestos'!$C$13)*'Supuestos'!$C$30)*'Supuestos'!$C$29))*('Supuestos'!$C$40+'Supuestos'!$C$41+'Supuestos'!$C$42))*(1-'Supuestos'!$C$33-'Supuestos'!$C$34-'Supuestos'!$C$35))-((IF($B23=0,0,'Supuestos'!$C$8/$B23))*'Supuestos'!$C$36)-'Supuestos'!$C$37-'Supuestos'!$C$8) | D23: =((((((((IF($B23=0,0,'Supuestos'!$C$8/$B23))*D$19)*'Supuestos'!$C$13)*'Supuestos'!$C$16)+(((((IF($B23=0,0,'Supuestos'!$C$8/$B23))*D$19)*'Supuestos'!$C$13)*'Supuestos'!$C$18)*'Supuestos'!$C$17)+(((((IF($B23=0,0,'Supuestos'!$C$8/$B23))*D$19)*'Supuestos'!$C$13)*'Supuestos'!$C$20)*'Supuestos'!$C$19)+(((((IF($B23=0,0,'Supuestos'!$C$8/$B23))*D$19)*'Supuestos'!$C$13)*'Supuestos'!$C$22)*'Supuestos'!$C$21)+(((((IF($B23=0,0,'Supuestos'!$C$8/$B23))*D$19)*'Supuestos'!$C$13)*'Supuestos'!$C$24)*'Supuestos'!$C$23)+(((((IF($B23=0,0,'Supuestos'!$C$8/$B23))*D$19)*'Supuestos'!$C$13)*'Supuestos'!$C$26)*'Supuestos'!$C$25)+(((((IF($B23=0,0,'Supuestos'!$C$8/$B23))*D$19)*'Supuestos'!$C$13)*'Supuestos'!$C$28)*'Supuestos'!$C$27)+(((((IF($B23=0,0,'Supuestos'!$C$8/$B23))*D$19)*'Supuestos'!$C$13)*'Supuestos'!$C$30)*'Supuestos'!$C$29))*('Supuestos'!$C$40+'Supuestos'!$C$41+'Supuestos'!$C$42))*(1-'Supuestos'!$C$33-'Supuestos'!$C$34-'Supuestos'!$C$35))-((IF($B23=0,0,'Supuestos'!$C$8/$B23))*'Supuestos'!$C$36)-'Supuestos'!$C$37-'Supuestos'!$C$8) | E23: =((((((((IF($B23=0,0,'Supuestos'!$C$8/$B23))*E$19)*'Supuestos'!$C$13)*'Supuestos'!$C$16)+(((((IF($B23=0,0,'Supuestos'!$C$8/$B23))*E$19)*'Supuestos'!$C$13)*'Supuestos'!$C$18)*'Supuestos'!$C$17)+(((((IF($B23=0,0,'Supuestos'!$C$8/$B23))*E$19)*'Supuestos'!$C$13)*'Supuestos'!$C$20)*'Supuestos'!$C$19)+(((((IF($B23=0,0,'Supuestos'!$C$8/$B23))*E$19)*'Supuestos'!$C$13)*'Supuestos'!$C$22)*'Supuestos'!$C$21)+(((((IF($B23=0,0,'Supuestos'!$C$8/$B23))*E$19)*'Supuestos'!$C$13)*'Supuestos'!$C$24)*'Supuestos'!$C$23)+(((((IF($B23=0,0,'Supuestos'!$C$8/$B23))*E$19)*'Supuestos'!$C$13)*'Supuestos'!$C$26)*'Supuestos'!$C$25)+(((((IF($B23=0,0,'Supuestos'!$C$8/$B23))*E$19)*'Supuestos'!$C$13)*'Supuestos'!$C$28)*'Supuestos'!$C$27)+(((((IF($B23=0,0,'Supuestos'!$C$8/$B23))*E$19)*'Supuestos'!$C$13)*'Supuestos'!$C$30)*'Supuestos'!$C$29))*('Supuestos'!$C$40+'Supuestos'!$C$41+'Supuestos'!$C$42))*(1-'Supuestos'!$C$33-'Supuestos'!$C$34-'Supuestos'!$C$35))-((IF($B23=0,0,'Supuestos'!$C$8/$B23))*'Supuestos'!$C$36)-'Supuestos'!$C$37-'Supuestos'!$C$8) | F23: =((((((((IF($B23=0,0,'Supuestos'!$C$8/$B23))*F$19)*'Supuestos'!$C$13)*'Supuestos'!$C$16)+(((((IF($B23=0,0,'Supuestos'!$C$8/$B23))*F$19)*'Supuestos'!$C$13)*'Supuestos'!$C$18)*'Supuestos'!$C$17)+(((((IF($B23=0,0,'Supuestos'!$C$8/$B23))*F$19)*'Supuestos'!$C$13)*'Supuestos'!$C$20)*'Supuestos'!$C$19)+(((((IF($B23=0,0,'Supuestos'!$C$8/$B23))*F$19)*'Supuestos'!$C$13)*'Supuestos'!$C$22)*'Supuestos'!$C$21)+(((((IF($B23=0,0,'Supuestos'!$C$8/$B23))*F$19)*'Supuestos'!$C$13)*'Supuestos'!$C$24)*'Supuestos'!$C$23)+(((((IF($B23=0,0,'Supuestos'!$C$8/$B23))*F$19)*'Supuestos'!$C$13)*'Supuestos'!$C$26)*'Supuestos'!$C$25)+(((((IF($B23=0,0,'Supuestos'!$C$8/$B23))*F$19)*'Supuestos'!$C$13)*'Supuestos'!$C$28)*'Supuestos'!$C$27)+(((((IF($B23=0,0,'Supuestos'!$C$8/$B23))*F$19)*'Supuestos'!$C$13)*'Supuestos'!$C$30)*'Supuestos'!$C$29))*('Supuestos'!$C$40+'Supuestos'!$C$41+'Supuestos'!$C$42))*(1-'Supuestos'!$C$33-'Supuestos'!$C$34-'Supuestos'!$C$35))-((IF($B23=0,0,'Supuestos'!$C$8/$B23))*'Supuestos'!$C$36)-'Supuestos'!$C$37-'Supuestos'!$C$8) | G23: =((((((((IF($B23=0,0,'Supuestos'!$C$8/$B23))*G$19)*'Supuestos'!$C$13)*'Supuestos'!$C$16)+(((((IF($B23=0,0,'Supuestos'!$C$8/$B23))*G$19)*'Supuestos'!$C$13)*'Supuestos'!$C$18)*'Supuestos'!$C$17)+(((((IF($B23=0,0,'Supuestos'!$C$8/$B23))*G$19)*'Supuestos'!$C$13)*'Supuestos'!$C$20)*'Supuestos'!$C$19)+(((((IF($B23=0,0,'Supuestos'!$C$8/$B23))*G$19)*'Supuestos'!$C$13)*'Supuestos'!$C$22)*'Supuestos'!$C$21)+(((((IF($B23=0,0,'Supuestos'!$C$8/$B23))*G$19)*'Supuestos'!$C$13)*'Supuestos'!$C$24)*'Supuestos'!$C$23)+(((((IF($B23=0,0,'Supuestos'!$C$8/$B23))*G$19)*'Supuestos'!$C$13)*'Supuestos'!$C$26)*'Supuestos'!$C$25)+(((((IF($B23=0,0,'Supuestos'!$C$8/$B23))*G$19)*'Supuestos'!$C$13)*'Supuestos'!$C$28)*'Supuestos'!$C$27)+(((((IF($B23=0,0,'Supuestos'!$C$8/$B23))*G$19)*'Supuestos'!$C$13)*'Supuestos'!$C$30)*'Supuestos'!$C$29))*('Supuestos'!$C$40+'Supuestos'!$C$41+'Supuestos'!$C$42))*(1-'Supuestos'!$C$33-'Supuestos'!$C$34-'Supuestos'!$C$35))-((IF($B23=0,0,'Supuestos'!$C$8/$B23))*'Supuestos'!$C$36)-'Supuestos'!$C$37-'Supuestos'!$C$8) | H23: =((((((((IF($B23=0,0,'Supuestos'!$C$8/$B23))*H$19)*'Supuestos'!$C$13)*'Supuestos'!$C$16)+(((((IF($B23=0,0,'Supuestos'!$C$8/$B23))*H$19)*'Supuestos'!$C$13)*'Supuestos'!$C$18)*'Supuestos'!$C$17)+(((((IF($B23=0,0,'Supuestos'!$C$8/$B23))*H$19)*'Supuestos'!$C$13)*'Supuestos'!$C$20)*'Supuestos'!$C$19)+(((((IF($B23=0,0,'Supuestos'!$C$8/$B23))*H$19)*'Supuestos'!$C$13)*'Supuestos'!$C$22)*'Supuestos'!$C$21)+(((((IF($B23=0,0,'Supuestos'!$C$8/$B23))*H$19)*'Supuestos'!$C$13)*'Supuestos'!$C$24)*'Supuestos'!$C$23)+(((((IF($B23=0,0,'Supuestos'!$C$8/$B23))*H$19)*'Supuestos'!$C$13)*'Supuestos'!$C$26)*'Supuestos'!$C$25)+(((((IF($B23=0,0,'Supuestos'!$C$8/$B23))*H$19)*'Supuestos'!$C$13)*'Supuestos'!$C$28)*'Supuestos'!$C$27)+(((((IF($B23=0,0,'Supuestos'!$C$8/$B23))*H$19)*'Supuestos'!$C$13)*'Supuestos'!$C$30)*'Supuestos'!$C$29))*('Supuestos'!$C$40+'Supuestos'!$C$41+'Supuestos'!$C$42))*(1-'Supuestos'!$C$33-'Supuestos'!$C$34-'Supuestos'!$C$35))-((IF($B23=0,0,'Supuestos'!$C$8/$B23))*'Supuestos'!$C$36)-'Supuestos'!$C$37-'Supuestos'!$C$8)
B24: 0.4 | C24: =((((((((IF($B24=0,0,'Supuestos'!$C$8/$B24))*C$19)*'Supuestos'!$C$13)*'Supuestos'!$C$16)+(((((IF($B24=0,0,'Supuestos'!$C$8/$B24))*C$19)*'Supuestos'!$C$13)*'Supuestos'!$C$18)*'Supuestos'!$C$17)+(((((IF($B24=0,0,'Supuestos'!$C$8/$B24))*C$19)*'Supuestos'!$C$13)*'Supuestos'!$C$20)*'Supuestos'!$C$19)+(((((IF($B24=0,0,'Supuestos'!$C$8/$B24))*C$19)*'Supuestos'!$C$13)*'Supuestos'!$C$22)*'Supuestos'!$C$21)+(((((IF($B24=0,0,'Supuestos'!$C$8/$B24))*C$19)*'Supuestos'!$C$13)*'Supuestos'!$C$24)*'Supuestos'!$C$23)+(((((IF($B24=0,0,'Supuestos'!$C$8/$B24))*C$19)*'Supuestos'!$C$13)*'Supuestos'!$C$26)*'Supuestos'!$C$25)+(((((IF($B24=0,0,'Supuestos'!$C$8/$B24))*C$19)*'Supuestos'!$C$13)*'Supuestos'!$C$28)*'Supuestos'!$C$27)+(((((IF($B24=0,0,'Supuestos'!$C$8/$B24))*C$19)*'Supuestos'!$C$13)*'Supuestos'!$C$30)*'Supuestos'!$C$29))*('Supuestos'!$C$40+'Supuestos'!$C$41+'Supuestos'!$C$42))*(1-'Supuestos'!$C$33-'Supuestos'!$C$34-'Supuestos'!$C$35))-((IF($B24=0,0,'Supuestos'!$C$8/$B24))*'Supuestos'!$C$36)-'Supuestos'!$C$37-'Supuestos'!$C$8) | D24: =((((((((IF($B24=0,0,'Supuestos'!$C$8/$B24))*D$19)*'Supuestos'!$C$13)*'Supuestos'!$C$16)+(((((IF($B24=0,0,'Supuestos'!$C$8/$B24))*D$19)*'Supuestos'!$C$13)*'Supuestos'!$C$18)*'Supuestos'!$C$17)+(((((IF($B24=0,0,'Supuestos'!$C$8/$B24))*D$19)*'Supuestos'!$C$13)*'Supuestos'!$C$20)*'Supuestos'!$C$19)+(((((IF($B24=0,0,'Supuestos'!$C$8/$B24))*D$19)*'Supuestos'!$C$13)*'Supuestos'!$C$22)*'Supuestos'!$C$21)+(((((IF($B24=0,0,'Supuestos'!$C$8/$B24))*D$19)*'Supuestos'!$C$13)*'Supuestos'!$C$24)*'Supuestos'!$C$23)+(((((IF($B24=0,0,'Supuestos'!$C$8/$B24))*D$19)*'Supuestos'!$C$13)*'Supuestos'!$C$26)*'Supuestos'!$C$25)+(((((IF($B24=0,0,'Supuestos'!$C$8/$B24))*D$19)*'Supuestos'!$C$13)*'Supuestos'!$C$28)*'Supuestos'!$C$27)+(((((IF($B24=0,0,'Supuestos'!$C$8/$B24))*D$19)*'Supuestos'!$C$13)*'Supuestos'!$C$30)*'Supuestos'!$C$29))*('Supuestos'!$C$40+'Supuestos'!$C$41+'Supuestos'!$C$42))*(1-'Supuestos'!$C$33-'Supuestos'!$C$34-'Supuestos'!$C$35))-((IF($B24=0,0,'Supuestos'!$C$8/$B24))*'Supuestos'!$C$36)-'Supuestos'!$C$37-'Supuestos'!$C$8) | E24: =((((((((IF($B24=0,0,'Supuestos'!$C$8/$B24))*E$19)*'Supuestos'!$C$13)*'Supuestos'!$C$16)+(((((IF($B24=0,0,'Supuestos'!$C$8/$B24))*E$19)*'Supuestos'!$C$13)*'Supuestos'!$C$18)*'Supuestos'!$C$17)+(((((IF($B24=0,0,'Supuestos'!$C$8/$B24))*E$19)*'Supuestos'!$C$13)*'Supuestos'!$C$20)*'Supuestos'!$C$19)+(((((IF($B24=0,0,'Supuestos'!$C$8/$B24))*E$19)*'Supuestos'!$C$13)*'Supuestos'!$C$22)*'Supuestos'!$C$21)+(((((IF($B24=0,0,'Supuestos'!$C$8/$B24))*E$19)*'Supuestos'!$C$13)*'Supuestos'!$C$24)*'Supuestos'!$C$23)+(((((IF($B24=0,0,'Supuestos'!$C$8/$B24))*E$19)*'Supuestos'!$C$13)*'Supuestos'!$C$26)*'Supuestos'!$C$25)+(((((IF($B24=0,0,'Supuestos'!$C$8/$B24))*E$19)*'Supuestos'!$C$13)*'Supuestos'!$C$28)*'Supuestos'!$C$27)+(((((IF($B24=0,0,'Supuestos'!$C$8/$B24))*E$19)*'Supuestos'!$C$13)*'Supuestos'!$C$30)*'Supuestos'!$C$29))*('Supuestos'!$C$40+'Supuestos'!$C$41+'Supuestos'!$C$42))*(1-'Supuestos'!$C$33-'Supuestos'!$C$34-'Supuestos'!$C$35))-((IF($B24=0,0,'Supuestos'!$C$8/$B24))*'Supuestos'!$C$36)-'Supuestos'!$C$37-'Supuestos'!$C$8) | F24: =((((((((IF($B24=0,0,'Supuestos'!$C$8/$B24))*F$19)*'Supuestos'!$C$13)*'Supuestos'!$C$16)+(((((IF($B24=0,0,'Supuestos'!$C$8/$B24))*F$19)*'Supuestos'!$C$13)*'Supuestos'!$C$18)*'Supuestos'!$C$17)+(((((IF($B24=0,0,'Supuestos'!$C$8/$B24))*F$19)*'Supuestos'!$C$13)*'Supuestos'!$C$20)*'Supuestos'!$C$19)+(((((IF($B24=0,0,'Supuestos'!$C$8/$B24))*F$19)*'Supuestos'!$C$13)*'Supuestos'!$C$22)*'Supuestos'!$C$21)+(((((IF($B24=0,0,'Supuestos'!$C$8/$B24))*F$19)*'Supuestos'!$C$13)*'Supuestos'!$C$24)*'Supuestos'!$C$23)+(((((IF($B24=0,0,'Supuestos'!$C$8/$B24))*F$19)*'Supuestos'!$C$13)*'Supuestos'!$C$26)*'Supuestos'!$C$25)+(((((IF($B24=0,0,'Supuestos'!$C$8/$B24))*F$19)*'Supuestos'!$C$13)*'Supuestos'!$C$28)*'Supuestos'!$C$27)+(((((IF($B24=0,0,'Supuestos'!$C$8/$B24))*F$19)*'Supuestos'!$C$13)*'Supuestos'!$C$30)*'Supuestos'!$C$29))*('Supuestos'!$C$40+'Supuestos'!$C$41+'Supuestos'!$C$42))*(1-'Supuestos'!$C$33-'Supuestos'!$C$34-'Supuestos'!$C$35))-((IF($B24=0,0,'Supuestos'!$C$8/$B24))*'Supuestos'!$C$36)-'Supuestos'!$C$37-'Supuestos'!$C$8) | G24: =((((((((IF($B24=0,0,'Supuestos'!$C$8/$B24))*G$19)*'Supuestos'!$C$13)*'Supuestos'!$C$16)+(((((IF($B24=0,0,'Supuestos'!$C$8/$B24))*G$19)*'Supuestos'!$C$13)*'Supuestos'!$C$18)*'Supuestos'!$C$17)+(((((IF($B24=0,0,'Supuestos'!$C$8/$B24))*G$19)*'Supuestos'!$C$13)*'Supuestos'!$C$20)*'Supuestos'!$C$19)+(((((IF($B24=0,0,'Supuestos'!$C$8/$B24))*G$19)*'Supuestos'!$C$13)*'Supuestos'!$C$22)*'Supuestos'!$C$21)+(((((IF($B24=0,0,'Supuestos'!$C$8/$B24))*G$19)*'Supuestos'!$C$13)*'Supuestos'!$C$24)*'Supuestos'!$C$23)+(((((IF($B24=0,0,'Supuestos'!$C$8/$B24))*G$19)*'Supuestos'!$C$13)*'Supuestos'!$C$26)*'Supuestos'!$C$25)+(((((IF($B24=0,0,'Supuestos'!$C$8/$B24))*G$19)*'Supuestos'!$C$13)*'Supuestos'!$C$28)*'Supuestos'!$C$27)+(((((IF($B24=0,0,'Supuestos'!$C$8/$B24))*G$19)*'Supuestos'!$C$13)*'Supuestos'!$C$30)*'Supuestos'!$C$29))*('Supuestos'!$C$40+'Supuestos'!$C$41+'Supuestos'!$C$42))*(1-'Supuestos'!$C$33-'Supuestos'!$C$34-'Supuestos'!$C$35))-((IF($B24=0,0,'Supuestos'!$C$8/$B24))*'Supuestos'!$C$36)-'Supuestos'!$C$37-'Supuestos'!$C$8) | H24: =((((((((IF($B24=0,0,'Supuestos'!$C$8/$B24))*H$19)*'Supuestos'!$C$13)*'Supuestos'!$C$16)+(((((IF($B24=0,0,'Supuestos'!$C$8/$B24))*H$19)*'Supuestos'!$C$13)*'Supuestos'!$C$18)*'Supuestos'!$C$17)+(((((IF($B24=0,0,'Supuestos'!$C$8/$B24))*H$19)*'Supuestos'!$C$13)*'Supuestos'!$C$20)*'Supuestos'!$C$19)+(((((IF($B24=0,0,'Supuestos'!$C$8/$B24))*H$19)*'Supuestos'!$C$13)*'Supuestos'!$C$22)*'Supuestos'!$C$21)+(((((IF($B24=0,0,'Supuestos'!$C$8/$B24))*H$19)*'Supuestos'!$C$13)*'Supuestos'!$C$24)*'Supuestos'!$C$23)+(((((IF($B24=0,0,'Supuestos'!$C$8/$B24))*H$19)*'Supuestos'!$C$13)*'Supuestos'!$C$26)*'Supuestos'!$C$25)+(((((IF($B24=0,0,'Supuestos'!$C$8/$B24))*H$19)*'Supuestos'!$C$13)*'Supuestos'!$C$28)*'Supuestos'!$C$27)+(((((IF($B24=0,0,'Supuestos'!$C$8/$B24))*H$19)*'Supuestos'!$C$13)*'Supuestos'!$C$30)*'Supuestos'!$C$29))*('Supuestos'!$C$40+'Supuestos'!$C$41+'Supuestos'!$C$42))*(1-'Supuestos'!$C$33-'Supuestos'!$C$34-'Supuestos'!$C$35))-((IF($B24=0,0,'Supuestos'!$C$8/$B24))*'Supuestos'!$C$36)-'Supuestos'!$C$37-'Supuestos'!$C$8)
B25: 0.5 | C25: =((((((((IF($B25=0,0,'Supuestos'!$C$8/$B25))*C$19)*'Supuestos'!$C$13)*'Supuestos'!$C$16)+(((((IF($B25=0,0,'Supuestos'!$C$8/$B25))*C$19)*'Supuestos'!$C$13)*'Supuestos'!$C$18)*'Supuestos'!$C$17)+(((((IF($B25=0,0,'Supuestos'!$C$8/$B25))*C$19)*'Supuestos'!$C$13)*'Supuestos'!$C$20)*'Supuestos'!$C$19)+(((((IF($B25=0,0,'Supuestos'!$C$8/$B25))*C$19)*'Supuestos'!$C$13)*'Supuestos'!$C$22)*'Supuestos'!$C$21)+(((((IF($B25=0,0,'Supuestos'!$C$8/$B25))*C$19)*'Supuestos'!$C$13)*'Supuestos'!$C$24)*'Supuestos'!$C$23)+(((((IF($B25=0,0,'Supuestos'!$C$8/$B25))*C$19)*'Supuestos'!$C$13)*'Supuestos'!$C$26)*'Supuestos'!$C$25)+(((((IF($B25=0,0,'Supuestos'!$C$8/$B25))*C$19)*'Supuestos'!$C$13)*'Supuestos'!$C$28)*'Supuestos'!$C$27)+(((((IF($B25=0,0,'Supuestos'!$C$8/$B25))*C$19)*'Supuestos'!$C$13)*'Supuestos'!$C$30)*'Supuestos'!$C$29))*('Supuestos'!$C$40+'Supuestos'!$C$41+'Supuestos'!$C$42))*(1-'Supuestos'!$C$33-'Supuestos'!$C$34-'Supuestos'!$C$35))-((IF($B25=0,0,'Supuestos'!$C$8/$B25))*'Supuestos'!$C$36)-'Supuestos'!$C$37-'Supuestos'!$C$8) | D25: =((((((((IF($B25=0,0,'Supuestos'!$C$8/$B25))*D$19)*'Supuestos'!$C$13)*'Supuestos'!$C$16)+(((((IF($B25=0,0,'Supuestos'!$C$8/$B25))*D$19)*'Supuestos'!$C$13)*'Supuestos'!$C$18)*'Supuestos'!$C$17)+(((((IF($B25=0,0,'Supuestos'!$C$8/$B25))*D$19)*'Supuestos'!$C$13)*'Supuestos'!$C$20)*'Supuestos'!$C$19)+(((((IF($B25=0,0,'Supuestos'!$C$8/$B25))*D$19)*'Supuestos'!$C$13)*'Supuestos'!$C$22)*'Supuestos'!$C$21)+(((((IF($B25=0,0,'Supuestos'!$C$8/$B25))*D$19)*'Supuestos'!$C$13)*'Supuestos'!$C$24)*'Supuestos'!$C$23)+(((((IF($B25=0,0,'Supuestos'!$C$8/$B25))*D$19)*'Supuestos'!$C$13)*'Supuestos'!$C$26)*'Supuestos'!$C$25)+(((((IF($B25=0,0,'Supuestos'!$C$8/$B25))*D$19)*'Supuestos'!$C$13)*'Supuestos'!$C$28)*'Supuestos'!$C$27)+(((((IF($B25=0,0,'Supuestos'!$C$8/$B25))*D$19)*'Supuestos'!$C$13)*'Supuestos'!$C$30)*'Supuestos'!$C$29))*('Supuestos'!$C$40+'Supuestos'!$C$41+'Supuestos'!$C$42))*(1-'Supuestos'!$C$33-'Supuestos'!$C$34-'Supuestos'!$C$35))-((IF($B25=0,0,'Supuestos'!$C$8/$B25))*'Supuestos'!$C$36)-'Supuestos'!$C$37-'Supuestos'!$C$8) | E25: =((((((((IF($B25=0,0,'Supuestos'!$C$8/$B25))*E$19)*'Supuestos'!$C$13)*'Supuestos'!$C$16)+(((((IF($B25=0,0,'Supuestos'!$C$8/$B25))*E$19)*'Supuestos'!$C$13)*'Supuestos'!$C$18)*'Supuestos'!$C$17)+(((((IF($B25=0,0,'Supuestos'!$C$8/$B25))*E$19)*'Supuestos'!$C$13)*'Supuestos'!$C$20)*'Supuestos'!$C$19)+(((((IF($B25=0,0,'Supuestos'!$C$8/$B25))*E$19)*'Supuestos'!$C$13)*'Supuestos'!$C$22)*'Supuestos'!$C$21)+(((((IF($B25=0,0,'Supuestos'!$C$8/$B25))*E$19)*'Supuestos'!$C$13)*'Supuestos'!$C$24)*'Supuestos'!$C$23)+(((((IF($B25=0,0,'Supuestos'!$C$8/$B25))*E$19)*'Supuestos'!$C$13)*'Supuestos'!$C$26)*'Supuestos'!$C$25)+(((((IF($B25=0,0,'Supuestos'!$C$8/$B25))*E$19)*'Supuestos'!$C$13)*'Supuestos'!$C$28)*'Supuestos'!$C$27)+(((((IF($B25=0,0,'Supuestos'!$C$8/$B25))*E$19)*'Supuestos'!$C$13)*'Supuestos'!$C$30)*'Supuestos'!$C$29))*('Supuestos'!$C$40+'Supuestos'!$C$41+'Supuestos'!$C$42))*(1-'Supuestos'!$C$33-'Supuestos'!$C$34-'Supuestos'!$C$35))-((IF($B25=0,0,'Supuestos'!$C$8/$B25))*'Supuestos'!$C$36)-'Supuestos'!$C$37-'Supuestos'!$C$8) | F25: =((((((((IF($B25=0,0,'Supuestos'!$C$8/$B25))*F$19)*'Supuestos'!$C$13)*'Supuestos'!$C$16)+(((((IF($B25=0,0,'Supuestos'!$C$8/$B25))*F$19)*'Supuestos'!$C$13)*'Supuestos'!$C$18)*'Supuestos'!$C$17)+(((((IF($B25=0,0,'Supuestos'!$C$8/$B25))*F$19)*'Supuestos'!$C$13)*'Supuestos'!$C$20)*'Supuestos'!$C$19)+(((((IF($B25=0,0,'Supuestos'!$C$8/$B25))*F$19)*'Supuestos'!$C$13)*'Supuestos'!$C$22)*'Supuestos'!$C$21)+(((((IF($B25=0,0,'Supuestos'!$C$8/$B25))*F$19)*'Supuestos'!$C$13)*'Supuestos'!$C$24)*'Supuestos'!$C$23)+(((((IF($B25=0,0,'Supuestos'!$C$8/$B25))*F$19)*'Supuestos'!$C$13)*'Supuestos'!$C$26)*'Supuestos'!$C$25)+(((((IF($B25=0,0,'Supuestos'!$C$8/$B25))*F$19)*'Supuestos'!$C$13)*'Supuestos'!$C$28)*'Supuestos'!$C$27)+(((((IF($B25=0,0,'Supuestos'!$C$8/$B25))*F$19)*'Supuestos'!$C$13)*'Supuestos'!$C$30)*'Supuestos'!$C$29))*('Supuestos'!$C$40+'Supuestos'!$C$41+'Supuestos'!$C$42))*(1-'Supuestos'!$C$33-'Supuestos'!$C$34-'Supuestos'!$C$35))-((IF($B25=0,0,'Supuestos'!$C$8/$B25))*'Supuestos'!$C$36)-'Supuestos'!$C$37-'Supuestos'!$C$8) | G25: =((((((((IF($B25=0,0,'Supuestos'!$C$8/$B25))*G$19)*'Supuestos'!$C$13)*'Supuestos'!$C$16)+(((((IF($B25=0,0,'Supuestos'!$C$8/$B25))*G$19)*'Supuestos'!$C$13)*'Supuestos'!$C$18)*'Supuestos'!$C$17)+(((((IF($B25=0,0,'Supuestos'!$C$8/$B25))*G$19)*'Supuestos'!$C$13)*'Supuestos'!$C$20)*'Supuestos'!$C$19)+(((((IF($B25=0,0,'Supuestos'!$C$8/$B25))*G$19)*'Supuestos'!$C$13)*'Supuestos'!$C$22)*'Supuestos'!$C$21)+(((((IF($B25=0,0,'Supuestos'!$C$8/$B25))*G$19)*'Supuestos'!$C$13)*'Supuestos'!$C$24)*'Supuestos'!$C$23)+(((((IF($B25=0,0,'Supuestos'!$C$8/$B25))*G$19)*'Supuestos'!$C$13)*'Supuestos'!$C$26)*'Supuestos'!$C$25)+(((((IF($B25=0,0,'Supuestos'!$C$8/$B25))*G$19)*'Supuestos'!$C$13)*'Supuestos'!$C$28)*'Supuestos'!$C$27)+(((((IF($B25=0,0,'Supuestos'!$C$8/$B25))*G$19)*'Supuestos'!$C$13)*'Supuestos'!$C$30)*'Supuestos'!$C$29))*('Supuestos'!$C$40+'Supuestos'!$C$41+'Supuestos'!$C$42))*(1-'Supuestos'!$C$33-'Supuestos'!$C$34-'Supuestos'!$C$35))-((IF($B25=0,0,'Supuestos'!$C$8/$B25))*'Supuestos'!$C$36)-'Supuestos'!$C$37-'Supuestos'!$C$8) | H25: =((((((((IF($B25=0,0,'Supuestos'!$C$8/$B25))*H$19)*'Supuestos'!$C$13)*'Supuestos'!$C$16)+(((((IF($B25=0,0,'Supuestos'!$C$8/$B25))*H$19)*'Supuestos'!$C$13)*'Supuestos'!$C$18)*'Supuestos'!$C$17)+(((((IF($B25=0,0,'Supuestos'!$C$8/$B25))*H$19)*'Supuestos'!$C$13)*'Supuestos'!$C$20)*'Supuestos'!$C$19)+(((((IF($B25=0,0,'Supuestos'!$C$8/$B25))*H$19)*'Supuestos'!$C$13)*'Supuestos'!$C$22)*'Supuestos'!$C$21)+(((((IF($B25=0,0,'Supuestos'!$C$8/$B25))*H$19)*'Supuestos'!$C$13)*'Supuestos'!$C$24)*'Supuestos'!$C$23)+(((((IF($B25=0,0,'Supuestos'!$C$8/$B25))*H$19)*'Supuestos'!$C$13)*'Supuestos'!$C$26)*'Supuestos'!$C$25)+(((((IF($B25=0,0,'Supuestos'!$C$8/$B25))*H$19)*'Supuestos'!$C$13)*'Supuestos'!$C$28)*'Supuestos'!$C$27)+(((((IF($B25=0,0,'Supuestos'!$C$8/$B25))*H$19)*'Supuestos'!$C$13)*'Supuestos'!$C$30)*'Supuestos'!$C$29))*('Supuestos'!$C$40+'Supuestos'!$C$41+'Supuestos'!$C$42))*(1-'Supuestos'!$C$33-'Supuestos'!$C$34-'Supuestos'!$C$35))-((IF($B25=0,0,'Supuestos'!$C$8/$B25))*'Supuestos'!$C$36)-'Supuestos'!$C$37-'Supuestos'!$C$8)
B26: 0.6 | C26: =((((((((IF($B26=0,0,'Supuestos'!$C$8/$B26))*C$19)*'Supuestos'!$C$13)*'Supuestos'!$C$16)+(((((IF($B26=0,0,'Supuestos'!$C$8/$B26))*C$19)*'Supuestos'!$C$13)*'Supuestos'!$C$18)*'Supuestos'!$C$17)+(((((IF($B26=0,0,'Supuestos'!$C$8/$B26))*C$19)*'Supuestos'!$C$13)*'Supuestos'!$C$20)*'Supuestos'!$C$19)+(((((IF($B26=0,0,'Supuestos'!$C$8/$B26))*C$19)*'Supuestos'!$C$13)*'Supuestos'!$C$22)*'Supuestos'!$C$21)+(((((IF($B26=0,0,'Supuestos'!$C$8/$B26))*C$19)*'Supuestos'!$C$13)*'Supuestos'!$C$24)*'Supuestos'!$C$23)+(((((IF($B26=0,0,'Supuestos'!$C$8/$B26))*C$19)*'Supuestos'!$C$13)*'Supuestos'!$C$26)*'Supuestos'!$C$25)+(((((IF($B26=0,0,'Supuestos'!$C$8/$B26))*C$19)*'Supuestos'!$C$13)*'Supuestos'!$C$28)*'Supuestos'!$C$27)+(((((IF($B26=0,0,'Supuestos'!$C$8/$B26))*C$19)*'Supuestos'!$C$13)*'Supuestos'!$C$30)*'Supuestos'!$C$29))*('Supuestos'!$C$40+'Supuestos'!$C$41+'Supuestos'!$C$42))*(1-'Supuestos'!$C$33-'Supuestos'!$C$34-'Supuestos'!$C$35))-((IF($B26=0,0,'Supuestos'!$C$8/$B26))*'Supuestos'!$C$36)-'Supuestos'!$C$37-'Supuestos'!$C$8) | D26: =((((((((IF($B26=0,0,'Supuestos'!$C$8/$B26))*D$19)*'Supuestos'!$C$13)*'Supuestos'!$C$16)+(((((IF($B26=0,0,'Supuestos'!$C$8/$B26))*D$19)*'Supuestos'!$C$13)*'Supuestos'!$C$18)*'Supuestos'!$C$17)+(((((IF($B26=0,0,'Supuestos'!$C$8/$B26))*D$19)*'Supuestos'!$C$13)*'Supuestos'!$C$20)*'Supuestos'!$C$19)+(((((IF($B26=0,0,'Supuestos'!$C$8/$B26))*D$19)*'Supuestos'!$C$13)*'Supuestos'!$C$22)*'Supuestos'!$C$21)+(((((IF($B26=0,0,'Supuestos'!$C$8/$B26))*D$19)*'Supuestos'!$C$13)*'Supuestos'!$C$24)*'Supuestos'!$C$23)+(((((IF($B26=0,0,'Supuestos'!$C$8/$B26))*D$19)*'Supuestos'!$C$13)*'Supuestos'!$C$26)*'Supuestos'!$C$25)+(((((IF($B26=0,0,'Supuestos'!$C$8/$B26))*D$19)*'Supuestos'!$C$13)*'Supuestos'!$C$28)*'Supuestos'!$C$27)+(((((IF($B26=0,0,'Supuestos'!$C$8/$B26))*D$19)*'Supuestos'!$C$13)*'Supuestos'!$C$30)*'Supuestos'!$C$29))*('Supuestos'!$C$40+'Supuestos'!$C$41+'Supuestos'!$C$42))*(1-'Supuestos'!$C$33-'Supuestos'!$C$34-'Supuestos'!$C$35))-((IF($B26=0,0,'Supuestos'!$C$8/$B26))*'Supuestos'!$C$36)-'Supuestos'!$C$37-'Supuestos'!$C$8) | E26: =((((((((IF($B26=0,0,'Supuestos'!$C$8/$B26))*E$19)*'Supuestos'!$C$13)*'Supuestos'!$C$16)+(((((IF($B26=0,0,'Supuestos'!$C$8/$B26))*E$19)*'Supuestos'!$C$13)*'Supuestos'!$C$18)*'Supuestos'!$C$17)+(((((IF($B26=0,0,'Supuestos'!$C$8/$B26))*E$19)*'Supuestos'!$C$13)*'Supuestos'!$C$20)*'Supuestos'!$C$19)+(((((IF($B26=0,0,'Supuestos'!$C$8/$B26))*E$19)*'Supuestos'!$C$13)*'Supuestos'!$C$22)*'Supuestos'!$C$21)+(((((IF($B26=0,0,'Supuestos'!$C$8/$B26))*E$19)*'Supuestos'!$C$13)*'Supuestos'!$C$24)*'Supuestos'!$C$23)+(((((IF($B26=0,0,'Supuestos'!$C$8/$B26))*E$19)*'Supuestos'!$C$13)*'Supuestos'!$C$26)*'Supuestos'!$C$25)+(((((IF($B26=0,0,'Supuestos'!$C$8/$B26))*E$19)*'Supuestos'!$C$13)*'Supuestos'!$C$28)*'Supuestos'!$C$27)+(((((IF($B26=0,0,'Supuestos'!$C$8/$B26))*E$19)*'Supuestos'!$C$13)*'Supuestos'!$C$30)*'Supuestos'!$C$29))*('Supuestos'!$C$40+'Supuestos'!$C$41+'Supuestos'!$C$42))*(1-'Supuestos'!$C$33-'Supuestos'!$C$34-'Supuestos'!$C$35))-((IF($B26=0,0,'Supuestos'!$C$8/$B26))*'Supuestos'!$C$36)-'Supuestos'!$C$37-'Supuestos'!$C$8) | F26: =((((((((IF($B26=0,0,'Supuestos'!$C$8/$B26))*F$19)*'Supuestos'!$C$13)*'Supuestos'!$C$16)+(((((IF($B26=0,0,'Supuestos'!$C$8/$B26))*F$19)*'Supuestos'!$C$13)*'Supuestos'!$C$18)*'Supuestos'!$C$17)+(((((IF($B26=0,0,'Supuestos'!$C$8/$B26))*F$19)*'Supuestos'!$C$13)*'Supuestos'!$C$20)*'Supuestos'!$C$19)+(((((IF($B26=0,0,'Supuestos'!$C$8/$B26))*F$19)*'Supuestos'!$C$13)*'Supuestos'!$C$22)*'Supuestos'!$C$21)+(((((IF($B26=0,0,'Supuestos'!$C$8/$B26))*F$19)*'Supuestos'!$C$13)*'Supuestos'!$C$24)*'Supuestos'!$C$23)+(((((IF($B26=0,0,'Supuestos'!$C$8/$B26))*F$19)*'Supuestos'!$C$13)*'Supuestos'!$C$26)*'Supuestos'!$C$25)+(((((IF($B26=0,0,'Supuestos'!$C$8/$B26))*F$19)*'Supuestos'!$C$13)*'Supuestos'!$C$28)*'Supuestos'!$C$27)+(((((IF($B26=0,0,'Supuestos'!$C$8/$B26))*F$19)*'Supuestos'!$C$13)*'Supuestos'!$C$30)*'Supuestos'!$C$29))*('Supuestos'!$C$40+'Supuestos'!$C$41+'Supuestos'!$C$42))*(1-'Supuestos'!$C$33-'Supuestos'!$C$34-'Supuestos'!$C$35))-((IF($B26=0,0,'Supuestos'!$C$8/$B26))*'Supuestos'!$C$36)-'Supuestos'!$C$37-'Supuestos'!$C$8) | G26: =((((((((IF($B26=0,0,'Supuestos'!$C$8/$B26))*G$19)*'Supuestos'!$C$13)*'Supuestos'!$C$16)+(((((IF($B26=0,0,'Supuestos'!$C$8/$B26))*G$19)*'Supuestos'!$C$13)*'Supuestos'!$C$18)*'Supuestos'!$C$17)+(((((IF($B26=0,0,'Supuestos'!$C$8/$B26))*G$19)*'Supuestos'!$C$13)*'Supuestos'!$C$20)*'Supuestos'!$C$19)+(((((IF($B26=0,0,'Supuestos'!$C$8/$B26))*G$19)*'Supuestos'!$C$13)*'Supuestos'!$C$22)*'Supuestos'!$C$21)+(((((IF($B26=0,0,'Supuestos'!$C$8/$B26))*G$19)*'Supuestos'!$C$13)*'Supuestos'!$C$24)*'Supuestos'!$C$23)+(((((IF($B26=0,0,'Supuestos'!$C$8/$B26))*G$19)*'Supuestos'!$C$13)*'Supuestos'!$C$26)*'Supuestos'!$C$25)+(((((IF($B26=0,0,'Supuestos'!$C$8/$B26))*G$19)*'Supuestos'!$C$13)*'Supuestos'!$C$28)*'Supuestos'!$C$27)+(((((IF($B26=0,0,'Supuestos'!$C$8/$B26))*G$19)*'Supuestos'!$C$13)*'Supuestos'!$C$30)*'Supuestos'!$C$29))*('Supuestos'!$C$40+'Supuestos'!$C$41+'Supuestos'!$C$42))*(1-'Supuestos'!$C$33-'Supuestos'!$C$34-'Supuestos'!$C$35))-((IF($B26=0,0,'Supuestos'!$C$8/$B26))*'Supuestos'!$C$36)-'Supuestos'!$C$37-'Supuestos'!$C$8) | H26: =((((((((IF($B26=0,0,'Supuestos'!$C$8/$B26))*H$19)*'Supuestos'!$C$13)*'Supuestos'!$C$16)+(((((IF($B26=0,0,'Supuestos'!$C$8/$B26))*H$19)*'Supuestos'!$C$13)*'Supuestos'!$C$18)*'Supuestos'!$C$17)+(((((IF($B26=0,0,'Supuestos'!$C$8/$B26))*H$19)*'Supuestos'!$C$13)*'Supuestos'!$C$20)*'Supuestos'!$C$19)+(((((IF($B26=0,0,'Supuestos'!$C$8/$B26))*H$19)*'Supuestos'!$C$13)*'Supuestos'!$C$22)*'Supuestos'!$C$21)+(((((IF($B26=0,0,'Supuestos'!$C$8/$B26))*H$19)*'Supuestos'!$C$13)*'Supuestos'!$C$24)*'Supuestos'!$C$23)+(((((IF($B26=0,0,'Supuestos'!$C$8/$B26))*H$19)*'Supuestos'!$C$13)*'Supuestos'!$C$26)*'Supuestos'!$C$25)+(((((IF($B26=0,0,'Supuestos'!$C$8/$B26))*H$19)*'Supuestos'!$C$13)*'Supuestos'!$C$28)*'Supuestos'!$C$27)+(((((IF($B26=0,0,'Supuestos'!$C$8/$B26))*H$19)*'Supuestos'!$C$13)*'Supuestos'!$C$30)*'Supuestos'!$C$29))*('Supuestos'!$C$40+'Supuestos'!$C$41+'Supuestos'!$C$42))*(1-'Supuestos'!$C$33-'Supuestos'!$C$34-'Supuestos'!$C$35))-((IF($B26=0,0,'Supuestos'!$C$8/$B26))*'Supuestos'!$C$36)-'Supuestos'!$C$37-'Supuestos'!$C$8)
B29: Cuánto invertir para una facturación objetivo, según el ROAS que querés
B30: Inversión = facturación ÷ ROAS. Debajo: cuántas visitas hacen falta y cuánto podés pagar por cada una.
B31: Facturación objetivo ↓ / ROAS objetivo → | C31: 1.5 | D31: 2 | E31: 2.5 | F31: 3 | G31: 4
B32: 10000 | C32: =$B32/C$31 | D32: =$B32/D$31 | E32: =$B32/E$31 | F32: =$B32/F$31 | G32: =$B32/G$31
B33: 20000 | C33: =$B33/C$31 | D33: =$B33/D$31 | E33: =$B33/E$31 | F33: =$B33/F$31 | G33: =$B33/G$31
B34: 30000 | C34: =$B34/C$31 | D34: =$B34/D$31 | E34: =$B34/E$31 | F34: =$B34/F$31 | G34: =$B34/G$31
B35: 50000 | C35: =$B35/C$31 | D35: =$B35/D$31 | E35: =$B35/E$31 | F35: =$B35/F$31 | G35: =$B35/G$31
B36: 100000 | C36: =$B36/C$31 | D36: =$B36/D$31 | E36: =$B36/E$31 | F36: =$B36/F$31 | G36: =$B36/G$31
B37: Cantidad de visitas necesaria para esa facturación
B38: =$B32 | C38: =IF('Modelo'!$C$33=0,"inalcanzable",$B32/'Modelo'!$C$33)
B39: =$B33 | C39: =IF('Modelo'!$C$33=0,"inalcanzable",$B33/'Modelo'!$C$33)
B40: =$B34 | C40: =IF('Modelo'!$C$33=0,"inalcanzable",$B34/'Modelo'!$C$33)
B41: =$B35 | C41: =IF('Modelo'!$C$33=0,"inalcanzable",$B35/'Modelo'!$C$33)
B42: =$B36 | C42: =IF('Modelo'!$C$33=0,"inalcanzable",$B36/'Modelo'!$C$33)
B44: Costo máximo por visita para cumplir cada ROAS (sobre facturado)
C45: 1.5 | D45: 2 | E45: 2.5 | F45: 3 | G45: 4
B46: Costo máximo (facturado por unidad ÷ ROAS) | C46: =IF(C45=0,0,'Modelo'!$C$33/C45) | D46: =IF(D45=0,0,'Modelo'!$C$33/D45) | E46: =IF(E45=0,0,'Modelo'!$C$33/E45) | F46: =IF(F45=0,0,'Modelo'!$C$33/F45) | G46: =IF(G45=0,0,'Modelo'!$C$33/G45)
B47: Sobre cash neto, el techo real está en Modelo (ya descuenta comisiones y reembolsos).
B50: Guardarraíl: el ROAS mínimo que tiene que dar cada nivel de inversión para que subir valga la pena
B51: Parte de tu inversión y tu ROAS actuales. Cada dólar extra tiene que devolver al menos 1,3 neto. Si al subir un escalón el ROAS real queda por debajo del mínimo de esa fila, volvé al escalón anterior.
B52: Nivel de inversión | C52: Inversión del período | D52: ROAS mínimo (cash neto) | E52: Ganancia mínima
B53: actual | C53: ='Supuestos'!$C$8*1.0 | D53: =IF(C53=0,0,('Supuestos'!$C$8*'Modelo'!$C$43+1.3*(C53-'Supuestos'!$C$8))/C53) | E53: =C53*(D53-1)
B54: × 1.25 | C54: ='Supuestos'!$C$8*1.25 | D54: =IF(C54=0,0,('Supuestos'!$C$8*'Modelo'!$C$43+1.3*(C54-'Supuestos'!$C$8))/C54) | E54: =C54*(D54-1)
B55: × 1.5 | C55: ='Supuestos'!$C$8*1.5 | D55: =IF(C55=0,0,('Supuestos'!$C$8*'Modelo'!$C$43+1.3*(C55-'Supuestos'!$C$8))/C55) | E55: =C55*(D55-1)
B56: × 2 | C56: ='Supuestos'!$C$8*2.0 | D56: =IF(C56=0,0,('Supuestos'!$C$8*'Modelo'!$C$43+1.3*(C56-'Supuestos'!$C$8))/C56) | E56: =C56*(D56-1)
B57: × 3 | C57: ='Supuestos'!$C$8*3.0 | D57: =IF(C57=0,0,('Supuestos'!$C$8*'Modelo'!$C$43+1.3*(C57-'Supuestos'!$C$8))/C57) | E57: =C57*(D57-1)

Sheet Sensibilidad
B1: © Jesús Tassarolo · TooAudience · youtube.com/@JesusTassaroloSinFiltro · uso personal; no redistribuir modificado
B2: Sensibilidad: qué palanca mueve más la ganancia
B3: Cada fila mejora una sola variable un 10 % (o baja un costo un 10 %) y recalcula la ganancia del período. El ranking dice qué conviene trabajar primero.
B5: Palanca | C5: Cambio | D5: Ganancia nueva | E5: Diferencia | F5: Dif. % | G5: Ranking
B6: Ganancia del período con los supuestos actuales | D6: ='Modelo'!$C$41
B7: Costo por visita 10 % más barato (mejor creativo o público) | C7: −10 % | D7: =((((((((IF((('Supuestos'!$C$9*0.9))=0,0,'Supuestos'!$C$8/(('Supuestos'!$C$9*0.9))))*'Supuestos'!$C$12)*'Supuestos'!$C$13)*'Supuestos'!$C$16)+(((((IF((('Supuestos'!$C$9*0.9))=0,0,'Supuestos'!$C$8/(('Supuestos'!$C$9*0.9))))*'Supuestos'!$C$12)*'Supuestos'!$C$13)*'Supuestos'!$C$18)*'Supuestos'!$C$17)+(((((IF((('Supuestos'!$C$9*0.9))=0,0,'Supuestos'!$C$8/(('Supuestos'!$C$9*0.9))))*'Supuestos'!$C$12)*'Supuestos'!$C$13)*'Supuestos'!$C$20)*'Supuestos'!$C$19)+(((((IF((('Supuestos'!$C$9*0.9))=0,0,'Supuestos'!$C$8/(('Supuestos'!$C$9*0.9))))*'Supuestos'!$C$12)*'Supuestos'!$C$13)*'Supuestos'!$C$22)*'Supuestos'!$C$21)+(((((IF((('Supuestos'!$C$9*0.9))=0,0,'Supuestos'!$C$8/(('Supuestos'!$C$9*0.9))))*'Supuestos'!$C$12)*'Supuestos'!$C$13)*'Supuestos'!$C$24)*'Supuestos'!$C$23)+(((((IF((('Supuestos'!$C$9*0.9))=0,0,'Supuestos'!$C$8/(('Supuestos'!$C$9*0.9))))*'Supuestos'!$C$12)*'Supuestos'!$C$13)*'Supuestos'!$C$26)*'Supuestos'!$C$25)+(((((IF((('Supuestos'!$C$9*0.9))=0,0,'Supuestos'!$C$8/(('Supuestos'!$C$9*0.9))))*'Supuestos'!$C$12)*'Supuestos'!$C$13)*'Supuestos'!$C$28)*'Supuestos'!$C$27)+(((((IF((('Supuestos'!$C$9*0.9))=0,0,'Supuestos'!$C$8/(('Supuestos'!$C$9*0.9))))*'Supuestos'!$C$12)*'Supuestos'!$C$13)*'Supuestos'!$C$30)*'Supuestos'!$C$29))*('Supuestos'!$C$40+'Supuestos'!$C$41+'Supuestos'!$C$42))*(1-'Supuestos'!$C$33-'Supuestos'!$C$34-'Supuestos'!$C$35))-((IF((('Supuestos'!$C$9*0.9))=0,0,'Supuestos'!$C$8/(('Supuestos'!$C$9*0.9))))*'Supuestos'!$C$36)-'Supuestos'!$C$37-'Supuestos'!$C$8) | E7: =D7-$D$6 | F7: =IF($D$6=0,0,E7/ABS($D$6)) | G7: =RANK(E7,$E$7:$E$14)
B8: 10 % más visitas al checkout (mejor VSL) | C8: +10 % | D8: =((((((((IF(('Supuestos'!$C$9)=0,0,'Supuestos'!$C$8/('Supuestos'!$C$9)))*('Supuestos'!$C$12*1.1))*'Supuestos'!$C$13)*'Supuestos'!$C$16)+(((((IF(('Supuestos'!$C$9)=0,0,'Supuestos'!$C$8/('Supuestos'!$C$9)))*('Supuestos'!$C$12*1.1))*'Supuestos'!$C$13)*'Supuestos'!$C$18)*'Supuestos'!$C$17)+(((((IF(('Supuestos'!$C$9)=0,0,'Supuestos'!$C$8/('Supuestos'!$C$9)))*('Supuestos'!$C$12*1.1))*'Supuestos'!$C$13)*'Supuestos'!$C$20)*'Supuestos'!$C$19)+(((((IF(('Supuestos'!$C$9)=0,0,'Supuestos'!$C$8/('Supuestos'!$C$9)))*('Supuestos'!$C$12*1.1))*'Supuestos'!$C$13)*'Supuestos'!$C$22)*'Supuestos'!$C$21)+(((((IF(('Supuestos'!$C$9)=0,0,'Supuestos'!$C$8/('Supuestos'!$C$9)))*('Supuestos'!$C$12*1.1))*'Supuestos'!$C$13)*'Supuestos'!$C$24)*'Supuestos'!$C$23)+(((((IF(('Supuestos'!$C$9)=0,0,'Supuestos'!$C$8/('Supuestos'!$C$9)))*('Supuestos'!$C$12*1.1))*'Supuestos'!$C$13)*'Supuestos'!$C$26)*'Supuestos'!$C$25)+(((((IF(('Supuestos'!$C$9)=0,0,'Supuestos'!$C$8/('Supuestos'!$C$9)))*('Supuestos'!$C$12*1.1))*'Supuestos'!$C$13)*'Supuestos'!$C$28)*'Supuestos'!$C$27)+(((((IF(('Supuestos'!$C$9)=0,0,'Supuestos'!$C$8/('Supuestos'!$C$9)))*('Supuestos'!$C$12*1.1))*'Supuestos'!$C$13)*'Supuestos'!$C$30)*'Supuestos'!$C$29))*('Supuestos'!$C$40+'Supuestos'!$C$41+'Supuestos'!$C$42))*(1-'Supuestos'!$C$33-'Supuestos'!$C$34-'Supuestos'!$C$35))-((IF(('Supuestos'!$C$9)=0,0,'Supuestos'!$C$8/('Supuestos'!$C$9)))*'Supuestos'!$C$36)-'Supuestos'!$C$37-'Supuestos'!$C$8) | E8: =D8-$D$6 | F8: =IF($D$6=0,0,E8/ABS($D$6)) | G8: =RANK(E8,$E$7:$E$14)
B9: 10 % más checkouts que compran (mejor checkout y oferta) | C9: +10 % | D9: =((((((((IF(('Supuestos'!$C$9)=0,0,'Supuestos'!$C$8/('Supuestos'!$C$9)))*'Supuestos'!$C$12)*('Supuestos'!$C$13*1.1))*'Supuestos'!$C$16)+(((((IF(('Supuestos'!$C$9)=0,0,'Supuestos'!$C$8/('Supuestos'!$C$9)))*'Supuestos'!$C$12)*('Supuestos'!$C$13*1.1))*'Supuestos'!$C$18)*'Supuestos'!$C$17)+(((((IF(('Supuestos'!$C$9)=0,0,'Supuestos'!$C$8/('Supuestos'!$C$9)))*'Supuestos'!$C$12)*('Supuestos'!$C$13*1.1))*'Supuestos'!$C$20)*'Supuestos'!$C$19)+(((((IF(('Supuestos'!$C$9)=0,0,'Supuestos'!$C$8/('Supuestos'!$C$9)))*'Supuestos'!$C$12)*('Supuestos'!$C$13*1.1))*'Supuestos'!$C$22)*'Supuestos'!$C$21)+(((((IF(('Supuestos'!$C$9)=0,0,'Supuestos'!$C$8/('Supuestos'!$C$9)))*'Supuestos'!$C$12)*('Supuestos'!$C$13*1.1))*'Supuestos'!$C$24)*'Supuestos'!$C$23)+(((((IF(('Supuestos'!$C$9)=0,0,'Supuestos'!$C$8/('Supuestos'!$C$9)))*'Supuestos'!$C$12)*('Supuestos'!$C$13*1.1))*'Supuestos'!$C$26)*'Supuestos'!$C$25)+(((((IF(('Supuestos'!$C$9)=0,0,'Supuestos'!$C$8/('Supuestos'!$C$9)))*'Supuestos'!$C$12)*('Supuestos'!$C$13*1.1))*'Supuestos'!$C$28)*'Supuestos'!$C$27)+(((((IF(('Supuestos'!$C$9)=0,0,'Supuestos'!$C$8/('Supuestos'!$C$9)))*'Supuestos'!$C$12)*('Supuestos'!$C$13*1.1))*'Supuestos'!$C$30)*'Supuestos'!$C$29))*('Supuestos'!$C$40+'Supuestos'!$C$41+'Supuestos'!$C$42))*(1-'Supuestos'!$C$33-'Supuestos'!$C$34-'Supuestos'!$C$35))-((IF(('Supuestos'!$C$9)=0,0,'Supuestos'!$C$8/('Supuestos'!$C$9)))*'Supuestos'!$C$36)-'Supuestos'!$C$37-'Supuestos'!$C$8) | E9: =D9-$D$6 | F9: =IF($D$6=0,0,E9/ABS($D$6)) | G9: =RANK(E9,$E$7:$E$14)
B10: Precio del principal 10 % más alto (misma conversión) | C10: +10 % | D10: =((((((((IF(('Supuestos'!$C$9)=0,0,'Supuestos'!$C$8/('Supuestos'!$C$9)))*'Supuestos'!$C$12)*'Supuestos'!$C$13)*('Supuestos'!$C$16*1.1))+(((((IF(('Supuestos'!$C$9)=0,0,'Supuestos'!$C$8/('Supuestos'!$C$9)))*'Supuestos'!$C$12)*'Supuestos'!$C$13)*'Supuestos'!$C$18)*'Supuestos'!$C$17)+(((((IF(('Supuestos'!$C$9)=0,0,'Supuestos'!$C$8/('Supuestos'!$C$9)))*'Supuestos'!$C$12)*'Supuestos'!$C$13)*'Supuestos'!$C$20)*'Supuestos'!$C$19)+(((((IF(('Supuestos'!$C$9)=0,0,'Supuestos'!$C$8/('Supuestos'!$C$9)))*'Supuestos'!$C$12)*'Supuestos'!$C$13)*'Supuestos'!$C$22)*'Supuestos'!$C$21)+(((((IF(('Supuestos'!$C$9)=0,0,'Supuestos'!$C$8/('Supuestos'!$C$9)))*'Supuestos'!$C$12)*'Supuestos'!$C$13)*'Supuestos'!$C$24)*'Supuestos'!$C$23)+(((((IF(('Supuestos'!$C$9)=0,0,'Supuestos'!$C$8/('Supuestos'!$C$9)))*'Supuestos'!$C$12)*'Supuestos'!$C$13)*'Supuestos'!$C$26)*'Supuestos'!$C$25)+(((((IF(('Supuestos'!$C$9)=0,0,'Supuestos'!$C$8/('Supuestos'!$C$9)))*'Supuestos'!$C$12)*'Supuestos'!$C$13)*'Supuestos'!$C$28)*'Supuestos'!$C$27)+(((((IF(('Supuestos'!$C$9)=0,0,'Supuestos'!$C$8/('Supuestos'!$C$9)))*'Supuestos'!$C$12)*'Supuestos'!$C$13)*'Supuestos'!$C$30)*'Supuestos'!$C$29))*('Supuestos'!$C$40+'Supuestos'!$C$41+'Supuestos'!$C$42))*(1-'Supuestos'!$C$33-'Supuestos'!$C$34-'Supuestos'!$C$35))-((IF(('Supuestos'!$C$9)=0,0,'Supuestos'!$C$8/('Supuestos'!$C$9)))*'Supuestos'!$C$36)-'Supuestos'!$C$37-'Supuestos'!$C$8) | E10: =D10-$D$6 | F10: =IF($D$6=0,0,E10/ABS($D$6)) | G10: =RANK(E10,$E$7:$E$14)
B11: Bump 1 tomado 10 % más | C11: +10 % | D11: =((((((((IF(('Supuestos'!$C$9)=0,0,'Supuestos'!$C$8/('Supuestos'!$C$9)))*'Supuestos'!$C$12)*'Supuestos'!$C$13)*'Supuestos'!$C$16)+(((((IF(('Supuestos'!$C$9)=0,0,'Supuestos'!$C$8/('Supuestos'!$C$9)))*'Supuestos'!$C$12)*'Supuestos'!$C$13)*('Supuestos'!$C$18*1.1))*'Supuestos'!$C$17)+(((((IF(('Supuestos'!$C$9)=0,0,'Supuestos'!$C$8/('Supuestos'!$C$9)))*'Supuestos'!$C$12)*'Supuestos'!$C$13)*'Supuestos'!$C$20)*'Supuestos'!$C$19)+(((((IF(('Supuestos'!$C$9)=0,0,'Supuestos'!$C$8/('Supuestos'!$C$9)))*'Supuestos'!$C$12)*'Supuestos'!$C$13)*'Supuestos'!$C$22)*'Supuestos'!$C$21)+(((((IF(('Supuestos'!$C$9)=0,0,'Supuestos'!$C$8/('Supuestos'!$C$9)))*'Supuestos'!$C$12)*'Supuestos'!$C$13)*'Supuestos'!$C$24)*'Supuestos'!$C$23)+(((((IF(('Supuestos'!$C$9)=0,0,'Supuestos'!$C$8/('Supuestos'!$C$9)))*'Supuestos'!$C$12)*'Supuestos'!$C$13)*'Supuestos'!$C$26)*'Supuestos'!$C$25)+(((((IF(('Supuestos'!$C$9)=0,0,'Supuestos'!$C$8/('Supuestos'!$C$9)))*'Supuestos'!$C$12)*'Supuestos'!$C$13)*'Supuestos'!$C$28)*'Supuestos'!$C$27)+(((((IF(('Supuestos'!$C$9)=0,0,'Supuestos'!$C$8/('Supuestos'!$C$9)))*'Supuestos'!$C$12)*'Supuestos'!$C$13)*'Supuestos'!$C$30)*'Supuestos'!$C$29))*('Supuestos'!$C$40+'Supuestos'!$C$41+'Supuestos'!$C$42))*(1-'Supuestos'!$C$33-'Supuestos'!$C$34-'Supuestos'!$C$35))-((IF(('Supuestos'!$C$9)=0,0,'Supuestos'!$C$8/('Supuestos'!$C$9)))*'Supuestos'!$C$36)-'Supuestos'!$C$37-'Supuestos'!$C$8) | E11: =D11-$D$6 | F11: =IF($D$6=0,0,E11/ABS($D$6)) | G11: =RANK(E11,$E$7:$E$14)
B12: OTO 1 tomada 10 % más | C12: +10 % | D12: =((((((((IF(('Supuestos'!$C$9)=0,0,'Supuestos'!$C$8/('Supuestos'!$C$9)))*'Supuestos'!$C$12)*'Supuestos'!$C$13)*'Supuestos'!$C$16)+(((((IF(('Supuestos'!$C$9)=0,0,'Supuestos'!$C$8/('Supuestos'!$C$9)))*'Supuestos'!$C$12)*'Supuestos'!$C$13)*'Supuestos'!$C$18)*'Supuestos'!$C$17)+(((((IF(('Supuestos'!$C$9)=0,0,'Supuestos'!$C$8/('Supuestos'!$C$9)))*'Supuestos'!$C$12)*'Supuestos'!$C$13)*'Supuestos'!$C$20)*'Supuestos'!$C$19)+(((((IF(('Supuestos'!$C$9)=0,0,'Supuestos'!$C$8/('Supuestos'!$C$9)))*'Supuestos'!$C$12)*'Supuestos'!$C$13)*('Supuestos'!$C$22*1.1))*'Supuestos'!$C$21)+(((((IF(('Supuestos'!$C$9)=0,0,'Supuestos'!$C$8/('Supuestos'!$C$9)))*'Supuestos'!$C$12)*'Supuestos'!$C$13)*'Supuestos'!$C$24)*'Supuestos'!$C$23)+(((((IF(('Supuestos'!$C$9)=0,0,'Supuestos'!$C$8/('Supuestos'!$C$9)))*'Supuestos'!$C$12)*'Supuestos'!$C$13)*'Supuestos'!$C$26)*'Supuestos'!$C$25)+(((((IF(('Supuestos'!$C$9)=0,0,'Supuestos'!$C$8/('Supuestos'!$C$9)))*'Supuestos'!$C$12)*'Supuestos'!$C$13)*'Supuestos'!$C$28)*'Supuestos'!$C$27)+(((((IF(('Supuestos'!$C$9)=0,0,'Supuestos'!$C$8/('Supuestos'!$C$9)))*'Supuestos'!$C$12)*'Supuestos'!$C$13)*'Supuestos'!$C$30)*'Supuestos'!$C$29))*('Supuestos'!$C$40+'Supuestos'!$C$41+'Supuestos'!$C$42))*(1-'Supuestos'!$C$33-'Supuestos'!$C$34-'Supuestos'!$C$35))-((IF(('Supuestos'!$C$9)=0,0,'Supuestos'!$C$8/('Supuestos'!$C$9)))*'Supuestos'!$C$36)-'Supuestos'!$C$37-'Supuestos'!$C$8) | E12: =D12-$D$6 | F12: =IF($D$6=0,0,E12/ABS($D$6)) | G12: =RANK(E12,$E$7:$E$14)
B13: Ascensión al programa 10 % más alta | C13: +10 % | D13: =((((((((IF(('Supuestos'!$C$9)=0,0,'Supuestos'!$C$8/('Supuestos'!$C$9)))*'Supuestos'!$C$12)*'Supuestos'!$C$13)*'Supuestos'!$C$16)+(((((IF(('Supuestos'!$C$9)=0,0,'Supuestos'!$C$8/('Supuestos'!$C$9)))*'Supuestos'!$C$12)*'Supuestos'!$C$13)*'Supuestos'!$C$18)*'Supuestos'!$C$17)+(((((IF(('Supuestos'!$C$9)=0,0,'Supuestos'!$C$8/('Supuestos'!$C$9)))*'Supuestos'!$C$12)*'Supuestos'!$C$13)*'Supuestos'!$C$20)*'Supuestos'!$C$19)+(((((IF(('Supuestos'!$C$9)=0,0,'Supuestos'!$C$8/('Supuestos'!$C$9)))*'Supuestos'!$C$12)*'Supuestos'!$C$13)*'Supuestos'!$C$22)*'Supuestos'!$C$21)+(((((IF(('Supuestos'!$C$9)=0,0,'Supuestos'!$C$8/('Supuestos'!$C$9)))*'Supuestos'!$C$12)*'Supuestos'!$C$13)*'Supuestos'!$C$24)*'Supuestos'!$C$23)+(((((IF(('Supuestos'!$C$9)=0,0,'Supuestos'!$C$8/('Supuestos'!$C$9)))*'Supuestos'!$C$12)*'Supuestos'!$C$13)*'Supuestos'!$C$26)*'Supuestos'!$C$25)+(((((IF(('Supuestos'!$C$9)=0,0,'Supuestos'!$C$8/('Supuestos'!$C$9)))*'Supuestos'!$C$12)*'Supuestos'!$C$13)*'Supuestos'!$C$28)*'Supuestos'!$C$27)+(((((IF(('Supuestos'!$C$9)=0,0,'Supuestos'!$C$8/('Supuestos'!$C$9)))*'Supuestos'!$C$12)*'Supuestos'!$C$13)*('Supuestos'!$C$30*1.1))*'Supuestos'!$C$29))*('Supuestos'!$C$40+'Supuestos'!$C$41+'Supuestos'!$C$42))*(1-'Supuestos'!$C$33-'Supuestos'!$C$34-'Supuestos'!$C$35))-((IF(('Supuestos'!$C$9)=0,0,'Supuestos'!$C$8/('Supuestos'!$C$9)))*'Supuestos'!$C$36)-'Supuestos'!$C$37-'Supuestos'!$C$8) | E13: =D13-$D$6 | F13: =IF($D$6=0,0,E13/ABS($D$6)) | G13: =RANK(E13,$E$7:$E$14)
B14: Reembolsos 10 % más bajos | C14: −10 % | D14: =((((((((IF(('Supuestos'!$C$9)=0,0,'Supuestos'!$C$8/('Supuestos'!$C$9)))*'Supuestos'!$C$12)*'Supuestos'!$C$13)*'Supuestos'!$C$16)+(((((IF(('Supuestos'!$C$9)=0,0,'Supuestos'!$C$8/('Supuestos'!$C$9)))*'Supuestos'!$C$12)*'Supuestos'!$C$13)*'Supuestos'!$C$18)*'Supuestos'!$C$17)+(((((IF(('Supuestos'!$C$9)=0,0,'Supuestos'!$C$8/('Supuestos'!$C$9)))*'Supuestos'!$C$12)*'Supuestos'!$C$13)*'Supuestos'!$C$20)*'Supuestos'!$C$19)+(((((IF(('Supuestos'!$C$9)=0,0,'Supuestos'!$C$8/('Supuestos'!$C$9)))*'Supuestos'!$C$12)*'Supuestos'!$C$13)*'Supuestos'!$C$22)*'Supuestos'!$C$21)+(((((IF(('Supuestos'!$C$9)=0,0,'Supuestos'!$C$8/('Supuestos'!$C$9)))*'Supuestos'!$C$12)*'Supuestos'!$C$13)*'Supuestos'!$C$24)*'Supuestos'!$C$23)+(((((IF(('Supuestos'!$C$9)=0,0,'Supuestos'!$C$8/('Supuestos'!$C$9)))*'Supuestos'!$C$12)*'Supuestos'!$C$13)*'Supuestos'!$C$26)*'Supuestos'!$C$25)+(((((IF(('Supuestos'!$C$9)=0,0,'Supuestos'!$C$8/('Supuestos'!$C$9)))*'Supuestos'!$C$12)*'Supuestos'!$C$13)*'Supuestos'!$C$28)*'Supuestos'!$C$27)+(((((IF(('Supuestos'!$C$9)=0,0,'Supuestos'!$C$8/('Supuestos'!$C$9)))*'Supuestos'!$C$12)*'Supuestos'!$C$13)*'Supuestos'!$C$30)*'Supuestos'!$C$29))*('Supuestos'!$C$40+'Supuestos'!$C$41+'Supuestos'!$C$42))*(1-'Supuestos'!$C$33-'Supuestos'!$C$34-('Supuestos'!$C$35*0.9)))-((IF(('Supuestos'!$C$9)=0,0,'Supuestos'!$C$8/('Supuestos'!$C$9)))*'Supuestos'!$C$36)-'Supuestos'!$C$37-'Supuestos'!$C$8) | E14: =D14-$D$6 | F14: =IF($D$6=0,0,E14/ABS($D$6)) | G14: =RANK(E14,$E$7:$E$14)

Sheet Proyección 12 meses
B1: © Jesús Tassarolo · TooAudience · youtube.com/@JesusTassaroloSinFiltro · uso personal; no redistribuir modificado
B2: Proyección a 12 meses y caja
B3: La inversión crece cada mes según el supuesto de crecimiento. El cash entra según la curva de cobranza (mes 1 / 2 / 3). La ganancia acumulada muestra cuánto dinero hace falta para sostener la pauta.
B5: Concepto | C5: Mes 1 | D5: Mes 2 | E5: Mes 3 | F5: Mes 4 | G5: Mes 5 | H5: Mes 6 | I5: Mes 7 | J5: Mes 8 | K5: Mes 9 | L5: Mes 10 | M5: Mes 11 | N5: Mes 12 | O5: Total
B6: Inversión en publicidad del mes | C6: ='Supuestos'!$C$8*1 | D6: =C6*(1+'Supuestos'!$C$48) | E6: =D6*(1+'Supuestos'!$C$48) | F6: =E6*(1+'Supuestos'!$C$48) | G6: =F6*(1+'Supuestos'!$C$48) | H6: =G6*(1+'Supuestos'!$C$48) | I6: =H6*(1+'Supuestos'!$C$48) | J6: =I6*(1+'Supuestos'!$C$48) | K6: =J6*(1+'Supuestos'!$C$48) | ... N6: =M6*(1+'Supuestos'!$C$48) | O6: =SUM(C6:N6)
B7: Visitas compradas | C7: =IF('Modelo'!$C$7=0,0,C6/'Modelo'!$C$7) | D7: =IF('Modelo'!$C$7=0,0,D6/'Modelo'!$C$7) | E7: =IF('Modelo'!$C$7=0,0,E6/'Modelo'!$C$7) | F7: =IF('Modelo'!$C$7=0,0,F6/'Modelo'!$C$7) | G7: =IF('Modelo'!$C$7=0,0,G6/'Modelo'!$C$7) | H7: =IF('Modelo'!$C$7=0,0,H6/'Modelo'!$C$7) | I7: =IF('Modelo'!$C$7=0,0,I6/'Modelo'!$C$7) | J7: =IF('Modelo'!$C$7=0,0,J6/'Modelo'!$C$7) | ... N7: =IF('Modelo'!$C$7=0,0,N6/'Modelo'!$C$7) | O7: =SUM(C7:N7)
B8: Ventas del producto principal | C8: =C7*'Modelo'!$C$32 | D8: =D7*'Modelo'!$C$32 | E8: =E7*'Modelo'!$C$32 | F8: =F7*'Modelo'!$C$32 | G8: =G7*'Modelo'!$C$32 | H8: =H7*'Modelo'!$C$32 | I8: =I7*'Modelo'!$C$32 | J8: =J7*'Modelo'!$C$32 | ... N8: =N7*'Modelo'!$C$32 | O8: =SUM(C8:N8)
B9: Facturado (todos los productos) | C9: =C7*'Modelo'!$C$33 | D9: =D7*'Modelo'!$C$33 | E9: =E7*'Modelo'!$C$33 | F9: =F7*'Modelo'!$C$33 | G9: =G7*'Modelo'!$C$33 | H9: =H7*'Modelo'!$C$33 | I9: =I7*'Modelo'!$C$33 | J9: =J7*'Modelo'!$C$33 | ... N9: =N7*'Modelo'!$C$33 | O9: =SUM(C9:N9)
B10: Cash cobrado en el mes | C10: =C9*'Supuestos'!$C$40 | D10: =D9*'Supuestos'!$C$40+C9*'Supuestos'!$C$41 | E10: =E9*'Supuestos'!$C$40+D9*'Supuestos'!$C$41+C9*'Supuestos'!$C$42 | F10: =F9*'Supuestos'!$C$40+E9*'Supuestos'!$C$41+D9*'Supuestos'!$C$42 | G10: =G9*'Supuestos'!$C$40+F9*'Supuestos'!$C$41+E9*'Supuestos'!$C$42 | H10: =H9*'Supuestos'!$C$40+G9*'Supuestos'!$C$41+F9*'Supuestos'!$C$42 | I10: =I9*'Supuestos'!$C$40+H9*'Supuestos'!$C$41+G9*'Supuestos'!$C$42 | J10: =J9*'Supuestos'!$C$40+I9*'Supuestos'!$C$41+H9*'Supuestos'!$C$42 | K10: =K9*'Supuestos'!$C$40+J9*'Supuestos'!$C$41+I9*'Supuestos'!$C$42 | L10: =L9*'Supuestos'!$C$40+K9*'Supuestos'!$C$41+J9*'Supuestos'!$C$42 | ... N10: =N9*'Supuestos'!$C$40+M9*'Supuestos'!$C$41+L9*'Supuestos'!$C$42 | O10: =SUM(C10:N10)
B11: Comisiones y reembolsos | C11: =C10*('Supuestos'!$C$33+'Supuestos'!$C$34+'Supuestos'!$C$35) | D11: =D10*('Supuestos'!$C$33+'Supuestos'!$C$34+'Supuestos'!$C$35) | E11: =E10*('Supuestos'!$C$33+'Supuestos'!$C$34+'Supuestos'!$C$35) | F11: =F10*('Supuestos'!$C$33+'Supuestos'!$C$34+'Supuestos'!$C$35) | G11: =G10*('Supuestos'!$C$33+'Supuestos'!$C$34+'Supuestos'!$C$35) | H11: =H10*('Supuestos'!$C$33+'Supuestos'!$C$34+'Supuestos'!$C$35) | I11: =I10*('Supuestos'!$C$33+'Supuestos'!$C$34+'Supuestos'!$C$35) | J11: =J10*('Supuestos'!$C$33+'Supuestos'!$C$34+'Supuestos'!$C$35) | ... N11: =N10*('Supuestos'!$C$33+'Supuestos'!$C$34+'Supuestos'!$C$35) | O11: =SUM(C11:N11)
B12: Costos por unidad (herramientas, WhatsApp, IA) | C12: =C7*'Supuestos'!$C$36 | D12: =D7*'Supuestos'!$C$36 | E12: =E7*'Supuestos'!$C$36 | F12: =F7*'Supuestos'!$C$36 | G12: =G7*'Supuestos'!$C$36 | H12: =H7*'Supuestos'!$C$36 | I12: =I7*'Supuestos'!$C$36 | J12: =J7*'Supuestos'!$C$36 | ... N12: =N7*'Supuestos'!$C$36 | O12: =SUM(C12:N12)
B13: Costos fijos del mes | C13: ='Supuestos'!$C$37*1 | D13: ='Supuestos'!$C$37*1 | E13: ='Supuestos'!$C$37*1 | F13: ='Supuestos'!$C$37*1 | G13: ='Supuestos'!$C$37*1 | H13: ='Supuestos'!$C$37*1 | I13: ='Supuestos'!$C$37*1 | J13: ='Supuestos'!$C$37*1 | ... N13: ='Supuestos'!$C$37*1 | O13: =SUM(C13:N13)
B14: Ganancia de caja del mes | C14: =C10-C11-C12-C13-C6 | D14: =D10-D11-D12-D13-D6 | E14: =E10-E11-E12-E13-E6 | F14: =F10-F11-F12-F13-F6 | G14: =G10-G11-G12-G13-G6 | H14: =H10-H11-H12-H13-H6 | I14: =I10-I11-I12-I13-I6 | J14: =J10-J11-J12-J13-J6 | ... N14: =N10-N11-N12-N13-N6 | O14: =SUM(C14:N14)
B15: Ganancia de caja acumulada (desde cero) | C15: =C14 | D15: =C15+D14 | E15: =D15+E14 | F15: =E15+F14 | G15: =F15+G14 | H15: =G15+H14 | I15: =H15+I14 | J15: =I15+J14 | K15: =J15+K14 | ... N15: =M15+N14
B16: Saldo de caja (caja inicial + ganancia acumulada) | C16: ='Supuestos'!$C$49+C15 | D16: ='Supuestos'!$C$49+D15 | E16: ='Supuestos'!$C$49+E15 | F16: ='Supuestos'!$C$49+F15 | G16: ='Supuestos'!$C$49+G15 | H16: ='Supuestos'!$C$49+H15 | I16: ='Supuestos'!$C$49+I15 | J16: ='Supuestos'!$C$49+J15 | ... N16: ='Supuestos'!$C$49+N15
B18: Caja necesaria para no frenar la pauta (el peor momento de la ganancia acumulada) | C18: =MAX(0,-MIN(C15:N15))
B19: Saldo mínimo de caja con tu caja inicial | C19: =MIN(C16:N16)
B20: Ganancia de caja acumulada en 12 meses | C20: =O14

Sheet Seguimiento
B1: © Jesús Tassarolo · TooAudience · youtube.com/@JesusTassaroloSinFiltro · uso personal; no redistribuir modificado
B2: Seguimiento: una columna por mes
B3: Cargá los datos reales en las celdas amarillas. El semáforo compara tu costo real por visita con el techo móvil (lo que rindieron tus últimas 4 columnas) y con el techo del modelo.
B5: Dato | C5: Mes 1 | D5: Mes 2 | E5: Mes 3 | F5: Mes 4 | G5: Mes 5 | H5: Mes 6 | I5: Mes 7 | J5: Mes 8 | K5: Mes 9 | L5: Mes 10 | M5: Mes 11 | N5: Mes 12 | O5: Promedio | P5: Máximo | Q5: Mínimo
B6: Datos que cargás
B7: Inversión en publicidad | C7: 9000 | D7: 9500 | E7: 10500 | O7: =IF(COUNT(C7:N7)=0,"",AVERAGE(C7:N7)) | P7: =IF(COUNT(C7:N7)=0,"",MAX(C7:N7)) | Q7: =IF(COUNT(C7:N7)=0,"",MIN(C7:N7))
B8: Visitas a la página | C8: 30000 | D8: 30200 | E8: 29000 | O8: =IF(COUNT(C8:N8)=0,"",AVERAGE(C8:N8)) | P8: =IF(COUNT(C8:N8)=0,"",MAX(C8:N8)) | Q8: =IF(COUNT(C8:N8)=0,"",MIN(C8:N8))
B9: Checkouts iniciados | C9: 1050 | D9: 1030 | E9: 980 | O9: =IF(COUNT(C9:N9)=0,"",AVERAGE(C9:N9)) | P9: =IF(COUNT(C9:N9)=0,"",MAX(C9:N9)) | Q9: =IF(COUNT(C9:N9)=0,"",MIN(C9:N9))
B10: Ventas del producto principal | C10: 273 | D10: 262 | E10: 240 | O10: =IF(COUNT(C10:N10)=0,"",AVERAGE(C10:N10)) | P10: =IF(COUNT(C10:N10)=0,"",MAX(C10:N10)) | Q10: =IF(COUNT(C10:N10)=0,"",MIN(C10:N10))
B11: Ventas de bumps (1 + 2) | C11: 117 | D11: 110 | E11: 95 | O11: =IF(COUNT(C11:N11)=0,"",AVERAGE(C11:N11)) | P11: =IF(COUNT(C11:N11)=0,"",MAX(C11:N11)) | Q11: =IF(COUNT(C11:N11)=0,"",MIN(C11:N11))
B12: Ventas de OTOs (1 a 4) | C12: 63 | D12: 58 | E12: 52 | O12: =IF(COUNT(C12:N12)=0,"",AVERAGE(C12:N12)) | P12: =IF(COUNT(C12:N12)=0,"",MAX(C12:N12)) | Q12: =IF(COUNT(C12:N12)=0,"",MIN(C12:N12))
B13: Ventas de la ascensión (programa) | C13: 5 | D13: 6 | E13: 4 | O13: =IF(COUNT(C13:N13)=0,"",AVERAGE(C13:N13)) | P13: =IF(COUNT(C13:N13)=0,"",MAX(C13:N13)) | Q13: =IF(COUNT(C13:N13)=0,"",MIN(C13:N13))
B14: Facturado del mes (a precio de lista) | C14: 15900 | D14: 15400 | E14: 13700 | O14: =IF(COUNT(C14:N14)=0,"",AVERAGE(C14:N14)) | P14: =IF(COUNT(C14:N14)=0,"",MAX(C14:N14)) | Q14: =IF(COUNT(C14:N14)=0,"",MIN(C14:N14))
B15: Cash cobrado en el mes | C15: 15900 | D15: 15400 | E15: 13700 | O15: =IF(COUNT(C15:N15)=0,"",AVERAGE(C15:N15)) | P15: =IF(COUNT(C15:N15)=0,"",MAX(C15:N15)) | Q15: =IF(COUNT(C15:N15)=0,"",MIN(C15:N15))
B16: Lo que calcula el modelo
B17: Costo por visita real | C17: =IF(COUNT(C7:C15)<9,"",IF(C8=0,0,C7/C8)) | D17: =IF(COUNT(D7:D15)<9,"",IF(D8=0,0,D7/D8)) | E17: =IF(COUNT(E7:E15)<9,"",IF(E8=0,0,E7/E8)) | F17: =IF(COUNT(F7:F15)<9,"",IF(F8=0,0,F7/F8)) | G17: =IF(COUNT(G7:G15)<9,"",IF(G8=0,0,G7/G8)) | H17: =IF(COUNT(H7:H15)<9,"",IF(H8=0,0,H7/H8)) | I17: =IF(COUNT(I7:I15)<9,"",IF(I8=0,0,I7/I8)) | J17: =IF(COUNT(J7:J15)<9,"",IF(J8=0,0,J7/J8)) | ... N17: =IF(COUNT(N7:N15)<9,"",IF(N8=0,0,N7/N8)) | O17: =IF(COUNT(C17:N17)=0,"",AVERAGE(C17:N17)) | P17: =IF(COUNT(C17:N17)=0,"",MAX(C17:N17)) | Q17: =IF(COUNT(C17:N17)=0,"",MIN(C17:N17))
B18: % visitas → checkout | C18: =IF(COUNT(C7:C15)<9,"",IF(C8=0,0,C9/C8)) | D18: =IF(COUNT(D7:D15)<9,"",IF(D8=0,0,D9/D8)) | E18: =IF(COUNT(E7:E15)<9,"",IF(E8=0,0,E9/E8)) | F18: =IF(COUNT(F7:F15)<9,"",IF(F8=0,0,F9/F8)) | G18: =IF(COUNT(G7:G15)<9,"",IF(G8=0,0,G9/G8)) | H18: =IF(COUNT(H7:H15)<9,"",IF(H8=0,0,H9/H8)) | I18: =IF(COUNT(I7:I15)<9,"",IF(I8=0,0,I9/I8)) | J18: =IF(COUNT(J7:J15)<9,"",IF(J8=0,0,J9/J8)) | ... N18: =IF(COUNT(N7:N15)<9,"",IF(N8=0,0,N9/N8)) | O18: =IF(COUNT(C18:N18)=0,"",AVERAGE(C18:N18)) | P18: =IF(COUNT(C18:N18)=0,"",MAX(C18:N18)) | Q18: =IF(COUNT(C18:N18)=0,"",MIN(C18:N18))
B19: % checkout → compra | C19: =IF(COUNT(C7:C15)<9,"",IF(C9=0,0,C10/C9)) | D19: =IF(COUNT(D7:D15)<9,"",IF(D9=0,0,D10/D9)) | E19: =IF(COUNT(E7:E15)<9,"",IF(E9=0,0,E10/E9)) | F19: =IF(COUNT(F7:F15)<9,"",IF(F9=0,0,F10/F9)) | G19: =IF(COUNT(G7:G15)<9,"",IF(G9=0,0,G10/G9)) | H19: =IF(COUNT(H7:H15)<9,"",IF(H9=0,0,H10/H9)) | I19: =IF(COUNT(I7:I15)<9,"",IF(I9=0,0,I10/I9)) | J19: =IF(COUNT(J7:J15)<9,"",IF(J9=0,0,J10/J9)) | ... N19: =IF(COUNT(N7:N15)<9,"",IF(N9=0,0,N10/N9)) | O19: =IF(COUNT(C19:N19)=0,"",AVERAGE(C19:N19)) | P19: =IF(COUNT(C19:N19)=0,"",MAX(C19:N19)) | Q19: =IF(COUNT(C19:N19)=0,"",MIN(C19:N19))
B20: CPA real | C20: =IF(COUNT(C7:C15)<9,"",IF(C10=0,0,C7/C10)) | D20: =IF(COUNT(D7:D15)<9,"",IF(D10=0,0,D7/D10)) | E20: =IF(COUNT(E7:E15)<9,"",IF(E10=0,0,E7/E10)) | F20: =IF(COUNT(F7:F15)<9,"",IF(F10=0,0,F7/F10)) | G20: =IF(COUNT(G7:G15)<9,"",IF(G10=0,0,G7/G10)) | H20: =IF(COUNT(H7:H15)<9,"",IF(H10=0,0,H7/H10)) | I20: =IF(COUNT(I7:I15)<9,"",IF(I10=0,0,I7/I10)) | J20: =IF(COUNT(J7:J15)<9,"",IF(J10=0,0,J7/J10)) | ... N20: =IF(COUNT(N7:N15)<9,"",IF(N10=0,0,N7/N10)) | O20: =IF(COUNT(C20:N20)=0,"",AVERAGE(C20:N20)) | P20: =IF(COUNT(C20:N20)=0,"",MAX(C20:N20)) | Q20: =IF(COUNT(C20:N20)=0,"",MIN(C20:N20))
B21: Cash por comprador | C21: =IF(COUNT(C7:C15)<9,"",IF(C10=0,0,C15/C10)) | D21: =IF(COUNT(D7:D15)<9,"",IF(D10=0,0,D15/D10)) | E21: =IF(COUNT(E7:E15)<9,"",IF(E10=0,0,E15/E10)) | F21: =IF(COUNT(F7:F15)<9,"",IF(F10=0,0,F15/F10)) | G21: =IF(COUNT(G7:G15)<9,"",IF(G10=0,0,G15/G10)) | H21: =IF(COUNT(H7:H15)<9,"",IF(H10=0,0,H15/H10)) | I21: =IF(COUNT(I7:I15)<9,"",IF(I10=0,0,I15/I10)) | J21: =IF(COUNT(J7:J15)<9,"",IF(J10=0,0,J15/J10)) | ... N21: =IF(COUNT(N7:N15)<9,"",IF(N10=0,0,N15/N10)) | O21: =IF(COUNT(C21:N21)=0,"",AVERAGE(C21:N21)) | P21: =IF(COUNT(C21:N21)=0,"",MAX(C21:N21)) | Q21: =IF(COUNT(C21:N21)=0,"",MIN(C21:N21))
B22: Valor neto por unidad real (sobre facturado, cobranza completa) | C22: =IF(COUNT(C7:C15)<9,"",IF(C8=0,0,(C14*(1-'Supuestos'!$C$33-'Supuestos'!$C$34-'Supuestos'!$C$35)-C8*'Supuestos'!$C$36)/C8)) | D22: =IF(COUNT(D7:D15)<9,"",IF(D8=0,0,(D14*(1-'Supuestos'!$C$33-'Supuestos'!$C$34-'Supuestos'!$C$35)-D8*'Supuestos'!$C$36)/D8)) | E22: =IF(COUNT(E7:E15)<9,"",IF(E8=0,0,(E14*(1-'Supuestos'!$C$33-'Supuestos'!$C$34-'Supuestos'!$C$35)-E8*'Supuestos'!$C$36)/E8)) | F22: =IF(COUNT(F7:F15)<9,"",IF(F8=0,0,(F14*(1-'Supuestos'!$C$33-'Supuestos'!$C$34-'Supuestos'!$C$35)-F8*'Supuestos'!$C$36)/F8)) | G22: =IF(COUNT(G7:G15)<9,"",IF(G8=0,0,(G14*(1-'Supuestos'!$C$33-'Supuestos'!$C$34-'Supuestos'!$C$35)-G8*'Supuestos'!$C$36)/G8)) | H22: =IF(COUNT(H7:H15)<9,"",IF(H8=0,0,(H14*(1-'Supuestos'!$C$33-'Supuestos'!$C$34-'Supuestos'!$C$35)-H8*'Supuestos'!$C$36)/H8)) | I22: =IF(COUNT(I7:I15)<9,"",IF(I8=0,0,(I14*(1-'Supuestos'!$C$33-'Supuestos'!$C$34-'Supuestos'!$C$35)-I8*'Supuestos'!$C$36)/I8)) | J22: =IF(COUNT(J7:J15)<9,"",IF(J8=0,0,(J14*(1-'Supuestos'!$C$33-'Supuestos'!$C$34-'Supuestos'!$C$35)-J8*'Supuestos'!$C$36)/J8)) | ... N22: =IF(COUNT(N7:N15)<9,"",IF(N8=0,0,(N14*(1-'Supuestos'!$C$33-'Supuestos'!$C$34-'Supuestos'!$C$35)-N8*'Supuestos'!$C$36)/N8)) | O22: =IF(COUNT(C22:N22)=0,"",AVERAGE(C22:N22)) | P22: =IF(COUNT(C22:N22)=0,"",MAX(C22:N22)) | Q22: =IF(COUNT(C22:N22)=0,"",MIN(C22:N22))
B23: Ganancia del período al completar la cobranza | C23: =IF(COUNT(C7:C15)<9,"",C14*(1-'Supuestos'!$C$33-'Supuestos'!$C$34-'Supuestos'!$C$35)-C8*'Supuestos'!$C$36-'Supuestos'!$C$37-C7) | D23: =IF(COUNT(D7:D15)<9,"",D14*(1-'Supuestos'!$C$33-'Supuestos'!$C$34-'Supuestos'!$C$35)-D8*'Supuestos'!$C$36-'Supuestos'!$C$37-D7) | E23: =IF(COUNT(E7:E15)<9,"",E14*(1-'Supuestos'!$C$33-'Supuestos'!$C$34-'Supuestos'!$C$35)-E8*'Supuestos'!$C$36-'Supuestos'!$C$37-E7) | F23: =IF(COUNT(F7:F15)<9,"",F14*(1-'Supuestos'!$C$33-'Supuestos'!$C$34-'Supuestos'!$C$35)-F8*'Supuestos'!$C$36-'Supuestos'!$C$37-F7) | G23: =IF(COUNT(G7:G15)<9,"",G14*(1-'Supuestos'!$C$33-'Supuestos'!$C$34-'Supuestos'!$C$35)-G8*'Supuestos'!$C$36-'Supuestos'!$C$37-G7) | H23: =IF(COUNT(H7:H15)<9,"",H14*(1-'Supuestos'!$C$33-'Supuestos'!$C$34-'Supuestos'!$C$35)-H8*'Supuestos'!$C$36-'Supuestos'!$C$37-H7) | I23: =IF(COUNT(I7:I15)<9,"",I14*(1-'Supuestos'!$C$33-'Supuestos'!$C$34-'Supuestos'!$C$35)-I8*'Supuestos'!$C$36-'Supuestos'!$C$37-I7) | J23: =IF(COUNT(J7:J15)<9,"",J14*(1-'Supuestos'!$C$33-'Supuestos'!$C$34-'Supuestos'!$C$35)-J8*'Supuestos'!$C$36-'Supuestos'!$C$37-J7) | ... N23: =IF(COUNT(N7:N15)<9,"",N14*(1-'Supuestos'!$C$33-'Supuestos'!$C$34-'Supuestos'!$C$35)-N8*'Supuestos'!$C$36-'Supuestos'!$C$37-N7) | O23: =IF(COUNT(C23:N23)=0,"",AVERAGE(C23:N23)) | P23: =IF(COUNT(C23:N23)=0,"",MAX(C23:N23)) | Q23: =IF(COUNT(C23:N23)=0,"",MIN(C23:N23))
B24: Ganancia de caja del período (con lo cobrado hasta ahora) | C24: =IF(COUNT(C7:C15)<9,"",C15*(1-'Supuestos'!$C$33-'Supuestos'!$C$34-'Supuestos'!$C$35)-C8*'Supuestos'!$C$36-'Supuestos'!$C$37-C7) | D24: =IF(COUNT(D7:D15)<9,"",D15*(1-'Supuestos'!$C$33-'Supuestos'!$C$34-'Supuestos'!$C$35)-D8*'Supuestos'!$C$36-'Supuestos'!$C$37-D7) | E24: =IF(COUNT(E7:E15)<9,"",E15*(1-'Supuestos'!$C$33-'Supuestos'!$C$34-'Supuestos'!$C$35)-E8*'Supuestos'!$C$36-'Supuestos'!$C$37-E7) | F24: =IF(COUNT(F7:F15)<9,"",F15*(1-'Supuestos'!$C$33-'Supuestos'!$C$34-'Supuestos'!$C$35)-F8*'Supuestos'!$C$36-'Supuestos'!$C$37-F7) | G24: =IF(COUNT(G7:G15)<9,"",G15*(1-'Supuestos'!$C$33-'Supuestos'!$C$34-'Supuestos'!$C$35)-G8*'Supuestos'!$C$36-'Supuestos'!$C$37-G7) | H24: =IF(COUNT(H7:H15)<9,"",H15*(1-'Supuestos'!$C$33-'Supuestos'!$C$34-'Supuestos'!$C$35)-H8*'Supuestos'!$C$36-'Supuestos'!$C$37-H7) | I24: =IF(COUNT(I7:I15)<9,"",I15*(1-'Supuestos'!$C$33-'Supuestos'!$C$34-'Supuestos'!$C$35)-I8*'Supuestos'!$C$36-'Supuestos'!$C$37-I7) | J24: =IF(COUNT(J7:J15)<9,"",J15*(1-'Supuestos'!$C$33-'Supuestos'!$C$34-'Supuestos'!$C$35)-J8*'Supuestos'!$C$36-'Supuestos'!$C$37-J7) | ... N24: =IF(COUNT(N7:N15)<9,"",N15*(1-'Supuestos'!$C$33-'Supuestos'!$C$34-'Supuestos'!$C$35)-N8*'Supuestos'!$C$36-'Supuestos'!$C$37-N7) | O24: =IF(COUNT(C24:N24)=0,"",AVERAGE(C24:N24)) | P24: =IF(COUNT(C24:N24)=0,"",MAX(C24:N24)) | Q24: =IF(COUNT(C24:N24)=0,"",MIN(C24:N24))
B25: Ganancia por unidad real (ganancia ÷ unidades) | C25: =IF(COUNT(C7:C15)<9,"",IF(C8=0,0,(C14*(1-'Supuestos'!$C$33-'Supuestos'!$C$34-'Supuestos'!$C$35)-C8*'Supuestos'!$C$36-'Supuestos'!$C$37-C7)/C8)) | D25: =IF(COUNT(D7:D15)<9,"",IF(D8=0,0,(D14*(1-'Supuestos'!$C$33-'Supuestos'!$C$34-'Supuestos'!$C$35)-D8*'Supuestos'!$C$36-'Supuestos'!$C$37-D7)/D8)) | E25: =IF(COUNT(E7:E15)<9,"",IF(E8=0,0,(E14*(1-'Supuestos'!$C$33-'Supuestos'!$C$34-'Supuestos'!$C$35)-E8*'Supuestos'!$C$36-'Supuestos'!$C$37-E7)/E8)) | F25: =IF(COUNT(F7:F15)<9,"",IF(F8=0,0,(F14*(1-'Supuestos'!$C$33-'Supuestos'!$C$34-'Supuestos'!$C$35)-F8*'Supuestos'!$C$36-'Supuestos'!$C$37-F7)/F8)) | G25: =IF(COUNT(G7:G15)<9,"",IF(G8=0,0,(G14*(1-'Supuestos'!$C$33-'Supuestos'!$C$34-'Supuestos'!$C$35)-G8*'Supuestos'!$C$36-'Supuestos'!$C$37-G7)/G8)) | H25: =IF(COUNT(H7:H15)<9,"",IF(H8=0,0,(H14*(1-'Supuestos'!$C$33-'Supuestos'!$C$34-'Supuestos'!$C$35)-H8*'Supuestos'!$C$36-'Supuestos'!$C$37-H7)/H8)) | I25: =IF(COUNT(I7:I15)<9,"",IF(I8=0,0,(I14*(1-'Supuestos'!$C$33-'Supuestos'!$C$34-'Supuestos'!$C$35)-I8*'Supuestos'!$C$36-'Supuestos'!$C$37-I7)/I8)) | J25: =IF(COUNT(J7:J15)<9,"",IF(J8=0,0,(J14*(1-'Supuestos'!$C$33-'Supuestos'!$C$34-'Supuestos'!$C$35)-J8*'Supuestos'!$C$36-'Supuestos'!$C$37-J7)/J8)) | ... N25: =IF(COUNT(N7:N15)<9,"",IF(N8=0,0,(N14*(1-'Supuestos'!$C$33-'Supuestos'!$C$34-'Supuestos'!$C$35)-N8*'Supuestos'!$C$36-'Supuestos'!$C$37-N7)/N8)) | O25: =IF(COUNT(C25:N25)=0,"",AVERAGE(C25:N25)) | P25: =IF(COUNT(C25:N25)=0,"",MAX(C25:N25)) | Q25: =IF(COUNT(C25:N25)=0,"",MIN(C25:N25))
B26: ROAS sobre cash neto (cobranza completa) | C26: =IF(COUNT(C7:C15)<9,"",IF(C7=0,0,C14*(1-'Supuestos'!$C$33-'Supuestos'!$C$34-'Supuestos'!$C$35)/C7)) | D26: =IF(COUNT(D7:D15)<9,"",IF(D7=0,0,D14*(1-'Supuestos'!$C$33-'Supuestos'!$C$34-'Supuestos'!$C$35)/D7)) | E26: =IF(COUNT(E7:E15)<9,"",IF(E7=0,0,E14*(1-'Supuestos'!$C$33-'Supuestos'!$C$34-'Supuestos'!$C$35)/E7)) | F26: =IF(COUNT(F7:F15)<9,"",IF(F7=0,0,F14*(1-'Supuestos'!$C$33-'Supuestos'!$C$34-'Supuestos'!$C$35)/F7)) | G26: =IF(COUNT(G7:G15)<9,"",IF(G7=0,0,G14*(1-'Supuestos'!$C$33-'Supuestos'!$C$34-'Supuestos'!$C$35)/G7)) | H26: =IF(COUNT(H7:H15)<9,"",IF(H7=0,0,H14*(1-'Supuestos'!$C$33-'Supuestos'!$C$34-'Supuestos'!$C$35)/H7)) | I26: =IF(COUNT(I7:I15)<9,"",IF(I7=0,0,I14*(1-'Supuestos'!$C$33-'Supuestos'!$C$34-'Supuestos'!$C$35)/I7)) | J26: =IF(COUNT(J7:J15)<9,"",IF(J7=0,0,J14*(1-'Supuestos'!$C$33-'Supuestos'!$C$34-'Supuestos'!$C$35)/J7)) | ... N26: =IF(COUNT(N7:N15)<9,"",IF(N7=0,0,N14*(1-'Supuestos'!$C$33-'Supuestos'!$C$34-'Supuestos'!$C$35)/N7)) | O26: =IF(COUNT(C26:N26)=0,"",AVERAGE(C26:N26)) | P26: =IF(COUNT(C26:N26)=0,"",MAX(C26:N26)) | Q26: =IF(COUNT(C26:N26)=0,"",MIN(C26:N26))
B27: ROAS de caja (cobrado hasta ahora) | C27: =IF(COUNT(C7:C15)<9,"",IF(C7=0,0,C15*(1-'Supuestos'!$C$33-'Supuestos'!$C$34-'Supuestos'!$C$35)/C7)) | D27: =IF(COUNT(D7:D15)<9,"",IF(D7=0,0,D15*(1-'Supuestos'!$C$33-'Supuestos'!$C$34-'Supuestos'!$C$35)/D7)) | E27: =IF(COUNT(E7:E15)<9,"",IF(E7=0,0,E15*(1-'Supuestos'!$C$33-'Supuestos'!$C$34-'Supuestos'!$C$35)/E7)) | F27: =IF(COUNT(F7:F15)<9,"",IF(F7=0,0,F15*(1-'Supuestos'!$C$33-'Supuestos'!$C$34-'Supuestos'!$C$35)/F7)) | G27: =IF(COUNT(G7:G15)<9,"",IF(G7=0,0,G15*(1-'Supuestos'!$C$33-'Supuestos'!$C$34-'Supuestos'!$C$35)/G7)) | H27: =IF(COUNT(H7:H15)<9,"",IF(H7=0,0,H15*(1-'Supuestos'!$C$33-'Supuestos'!$C$34-'Supuestos'!$C$35)/H7)) | I27: =IF(COUNT(I7:I15)<9,"",IF(I7=0,0,I15*(1-'Supuestos'!$C$33-'Supuestos'!$C$34-'Supuestos'!$C$35)/I7)) | J27: =IF(COUNT(J7:J15)<9,"",IF(J7=0,0,J15*(1-'Supuestos'!$C$33-'Supuestos'!$C$34-'Supuestos'!$C$35)/J7)) | ... N27: =IF(COUNT(N7:N15)<9,"",IF(N7=0,0,N15*(1-'Supuestos'!$C$33-'Supuestos'!$C$34-'Supuestos'!$C$35)/N7)) | O27: =IF(COUNT(C27:N27)=0,"",AVERAGE(C27:N27)) | P27: =IF(COUNT(C27:N27)=0,"",MAX(C27:N27)) | Q27: =IF(COUNT(C27:N27)=0,"",MIN(C27:N27))
B28: Techo móvil (mediana de tus últimas 4 columnas; al inicio, el del modelo) | C28: =IF(COUNT(C7:C15)<9,"",'Modelo'!$C$48) | D28: =IF(COUNT(D7:D15)<9,"",IF(COUNT(C22:C22)>0,MEDIAN(C22:C22),'Modelo'!$C$48)) | E28: =IF(COUNT(E7:E15)<9,"",IF(COUNT(C22:D22)>0,MEDIAN(C22:D22),'Modelo'!$C$48)) | F28: =IF(COUNT(F7:F15)<9,"",IF(COUNT(C22:E22)>0,MEDIAN(C22:E22),'Modelo'!$C$48)) | G28: =IF(COUNT(G7:G15)<9,"",IF(COUNT(C22:F22)>0,MEDIAN(C22:F22),'Modelo'!$C$48)) | H28: =IF(COUNT(H7:H15)<9,"",IF(COUNT(D22:G22)>0,MEDIAN(D22:G22),'Modelo'!$C$48)) | I28: =IF(COUNT(I7:I15)<9,"",IF(COUNT(E22:H22)>0,MEDIAN(E22:H22),'Modelo'!$C$48)) | J28: =IF(COUNT(J7:J15)<9,"",IF(COUNT(F22:I22)>0,MEDIAN(F22:I22),'Modelo'!$C$48)) | K28: =IF(COUNT(K7:K15)<9,"",IF(COUNT(G22:J22)>0,MEDIAN(G22:J22),'Modelo'!$C$48)) | L28: =IF(COUNT(L7:L15)<9,"",IF(COUNT(H22:K22)>0,MEDIAN(H22:K22),'Modelo'!$C$48)) | M28: =IF(COUNT(M7:M15)<9,"",IF(COUNT(I22:L22)>0,MEDIAN(I22:L22),'Modelo'!$C$48)) | N28: =IF(COUNT(N7:N15)<9,"",IF(COUNT(J22:M22)>0,MEDIAN(J22:M22),'Modelo'!$C$48)) | O28: =IF(COUNT(C28:N28)=0,"",AVERAGE(C28:N28)) | P28: =IF(COUNT(C28:N28)=0,"",MAX(C28:N28)) | Q28: =IF(COUNT(C28:N28)=0,"",MIN(C28:N28))
B29: Semáforo (costo por unidad contra el techo móvil, y ROAS contra el objetivo) | C29: =IF(COUNT(C7:C15)<9,"",IF(C17>C28,"ROJO",IF(AND(C17<=C28/(1+'Supuestos'!$C$46),C26>='Supuestos'!$C$45),"VERDE","AMARILLO"))) | D29: =IF(COUNT(D7:D15)<9,"",IF(D17>D28,"ROJO",IF(AND(D17<=D28/(1+'Supuestos'!$C$46),D26>='Supuestos'!$C$45),"VERDE","AMARILLO"))) | E29: =IF(COUNT(E7:E15)<9,"",IF(E17>E28,"ROJO",IF(AND(E17<=E28/(1+'Supuestos'!$C$46),E26>='Supuestos'!$C$45),"VERDE","AMARILLO"))) | F29: =IF(COUNT(F7:F15)<9,"",IF(F17>F28,"ROJO",IF(AND(F17<=F28/(1+'Supuestos'!$C$46),F26>='Supuestos'!$C$45),"VERDE","AMARILLO"))) | G29: =IF(COUNT(G7:G15)<9,"",IF(G17>G28,"ROJO",IF(AND(G17<=G28/(1+'Supuestos'!$C$46),G26>='Supuestos'!$C$45),"VERDE","AMARILLO"))) | H29: =IF(COUNT(H7:H15)<9,"",IF(H17>H28,"ROJO",IF(AND(H17<=H28/(1+'Supuestos'!$C$46),H26>='Supuestos'!$C$45),"VERDE","AMARILLO"))) | I29: =IF(COUNT(I7:I15)<9,"",IF(I17>I28,"ROJO",IF(AND(I17<=I28/(1+'Supuestos'!$C$46),I26>='Supuestos'!$C$45),"VERDE","AMARILLO"))) | J29: =IF(COUNT(J7:J15)<9,"",IF(J17>J28,"ROJO",IF(AND(J17<=J28/(1+'Supuestos'!$C$46),J26>='Supuestos'!$C$45),"VERDE","AMARILLO"))) | ... N29: =IF(COUNT(N7:N15)<9,"",IF(N17>N28,"ROJO",IF(AND(N17<=N28/(1+'Supuestos'!$C$46),N26>='Supuestos'!$C$45),"VERDE","AMARILLO")))

Sheet Benchmarks
B1: © Jesús Tassarolo · TooAudience · youtube.com/@JesusTassaroloSinFiltro · uso personal; no redistribuir modificado
B2: Benchmarks: contra qué comparar tus números
B3: Valores de referencia para tráfico frío en español. Son orden de magnitud, no objetivo: tus propios datos de Seguimiento mandan.
B5: Métrica | C5: Malo | D5: Aceptable | E5: Bueno | F5: Ganador | G5: Tu valor (Modelo) | H5: Fuente / nota
B6: Costo por visita a la VSL (USD) | C6: >0,60 | D6: 0,35 a 0,60 | E6: 0,20 a 0,35 | F6: <0,20 | G6: ='Modelo'!$C$7 | H6: Embudos hispanos de venta directa a tráfico frío, 2025 a 2026.
B7: % visitas → checkout | C7: <2 % | D7: 2 a 3 % | E7: 3 a 5 % | F7: >5 % | G7: ='Supuestos'!$C$12 | H7: Idem.
B8: % checkout → compra | C8: <15 % | D8: 15 a 22 % | E8: 22 a 30 % | F8: >30 % | G8: ='Supuestos'!$C$13 | H8: Idem.
B9: % visitas → compra | C9: <0,5 % | D9: 0,5 a 0,9 % | E9: 0,9 a 1,5 % | F9: >1,5 % | G9: ='Modelo'!$C$11 | H9: Idem.
B10: Bump 1 tomado (% de compradores) | C10: <15 % | D10: 15 a 25 % | E10: 25 a 35 % | F10: >35 % | G10: ='Supuestos'!$C$18 | H10: Mercado USA: 30 a 40 % (SamCart, sobre miles de millones procesados). Hispano: 17 a 25 % es lo común.
B11: OTO 1 tomada (% de compradores) | C11: <5 % | D11: 5 a 9 % | E11: 9 a 14 % | F11: >14 % | G11: ='Supuestos'!$C$22 | H11: Mercado: 8 a 18 % en info-productos.
B12: Ascensión al programa (% de compradores) | C12: <1 % | D12: 1 a 2 % | E12: 2 a 4 % | F12: >4 % | G12: ='Supuestos'!$C$30 | H12: Ascenso front → programa de 300 a 1.000 USD.
B13: AOV ÷ precio del principal | C13: <1,2 | D13: 1,2 a 1,4 | E13: 1,4 a 1,7 | F13: >1,7 | G13: ='Modelo'!$C$31 | H13: Cuánto multiplica la escalera.
B14: ROAS sobre cash neto | C14: <1,2 | D14: 1,2 a 1,6 | E14: 1,6 a 2,5 | F14: >2,5 | G14: ='Modelo'!$C$43 | H14: Tráfico frío. Con backend por llamada sube.
B15: Reembolsos | C15: >10 % | D15: 7 a 10 % | E15: 4 a 7 % | F15: <4 % | G15: ='Supuestos'!$C$35 | H15: Más de 10 % es un problema de oferta.

Sheet Glosario
B1: © Jesús Tassarolo · TooAudience · youtube.com/@JesusTassaroloSinFiltro · uso personal; no redistribuir modificado
B2: Glosario
B3: Los términos que usa este modelo, en el orden del embudo.
B5: Término | C5: Qué es | D5: Dónde aparece
B6: CPM | C6: Costo por mil impresiones: lo que cobra la plataforma de anuncios por mostrar el aviso mil veces. | D6: Supuestos
B7: CTR | C7: Porcentaje de impresiones que terminan en clic al enlace. | D7: Supuestos
B8: Clic → visita | C8: Porcentaje de clics que llegan a cargar la página. Siempre menor a 100 % (cierran antes de que cargue). | D8: Supuestos
B9: Unidad de adquisición | C9: Lo que compra la publicidad en este embudo (visita, registro o entrada). Todo el modelo se mide por unidad. | D9: Modelo
B10: Costo por unidad | C10: Inversión dividida por unidades compradas: costo por visita, CPL (costo por lead o registro) o costo por entrada. | D10: Modelo, Seguimiento
B11: Conversión | C11: Porcentaje que pasa de una etapa a la siguiente. Las conversiones se multiplican: 15 % × 14 % × 44 % = 0,9 %. | D11: Supuestos, Modelo
B12: Show rate | C12: Porcentaje de registrados (o compradores) que asisten en vivo. El replay se cuenta aparte. | D12: Supuestos
B13: Bump | C13: Oferta extra en el mismo checkout, con una casilla. Se mide como % de los compradores. | D13: Supuestos
B14: OTO / upsell | C14: Oferta que aparece después de pagar (one-time offer). Downsell: la oferta más barata para quien rechaza la OTO. | D14: Supuestos
B15: Backend | C15: Producto de mayor valor que se vende después del primero, por ascenso o por llamada. | D15: Supuestos
B16: AOV | C16: Facturado promedio por comprador del producto principal, sumando toda la escalera. | D16: Modelo
... B41: Ascensión | C41: El upsell de mayor valor que se ofrece después del embudo (un programa de 300 a 1.000 USD), por checkout o por llamada. | D41: Supuestos

Sheet Chequeos
B1: © Jesús Tassarolo · TooAudience · youtube.com/@JesusTassaroloSinFiltro · uso personal; no redistribuir modificado
B2: Chequeos: el modelo se revisa solo
B3: Si alguna fila dice REVISAR, hay un supuesto fuera de rango o un dato inconsistente.
B5: Chequeo | C5: Estado | D5: Qué revisar
B6: Ninguna celda con error en Modelo | C6: =IF(ISERROR(SUM('Modelo'!C5:C160)),"REVISAR","OK") | D6: Si dice REVISAR, hay un #DIV/0! o #REF!: casi siempre un supuesto en 0 o una fila borrada.
B7: Ninguna celda con error en Embudo | C7: =IF(ISERROR(SUM('Embudo'!C5:H60)),"REVISAR","OK") | D7: Si dice REVISAR, hay un #DIV/0! o #REF!: casi siempre un supuesto en 0 o una fila borrada.
B8: Ninguna celda con error en Resumen | C8: =IF(ISERROR(SUM('Resumen'!C5:C60)),"REVISAR","OK") | D8: Si dice REVISAR, hay un #DIV/0! o #REF!: casi siempre un supuesto en 0 o una fila borrada.
B9: Ninguna celda con error en Proyección 12 meses | C9: =IF(ISERROR(SUM('Proyección 12 meses'!C5:O40)),"REVISAR","OK") | D9: Si dice REVISAR, hay un #DIV/0! o #REF!: casi siempre un supuesto en 0 o una fila borrada.
B10: Ninguna celda con error en Escenarios | C10: =IF(ISERROR(SUM('Escenarios'!C5:L120)),"REVISAR","OK") | D10: Si dice REVISAR, hay un #DIV/0! o #REF!: casi siempre un supuesto en 0 o una fila borrada.
B11: Ninguna celda con error en Seguimiento | C11: =IF(ISERROR(SUM('Seguimiento'!C5:Q80)),"REVISAR","OK") | D11: Si dice REVISAR, hay un #DIV/0! o #REF!: casi siempre un supuesto en 0 o una fila borrada.
B12: Los supuestos de tráfico son mayores a cero | C12: =IF(AND('Supuestos'!$C$9>0,'Supuestos'!$C$12>0,'Supuestos'!$C$13>0),"OK","REVISAR") | D12: Con un 0 en el tráfico o en la conversión de la página no hay unidades y el modelo no dice nada.
B13: La curva de cobranza suma 100 % | C13: =IF(ABS('Supuestos'!$C$40+'Supuestos'!$C$41+'Supuestos'!$C$42-1)<0.001,"OK","REVISAR") | D13: Supuestos → cobranza mes 1 + mes 2 + mes 3 = 100 %.
B14: Comisiones + reembolsos menores al 60 % | C14: =IF(('Supuestos'!$C$33+'Supuestos'!$C$34+'Supuestos'!$C$35)<0.6,"OK","REVISAR") | D14: Si suman más, revisá los porcentajes.
B15: El escenario en uso es 1, 2 o 3 | C15: =IF(OR('Supuestos'!$C$6=1,'Supuestos'!$C$6=2,'Supuestos'!$C$6=3),"OK","REVISAR") | D15: Supuestos → celda 'Escenario en uso'.
B16: La inversión es mayor a cero | C16: =IF('Supuestos'!$C$8>0,"OK","REVISAR")
B17: La meta de ventas es alcanzable (hay conversión a venta) | C17: =IF('Modelo'!$C$11>0,"OK","REVISAR") | D17: Con conversión a venta en 0, la inversión para la meta dice 'inalcanzable con estos supuestos'.
B18: Las conversiones están entre 0 y 100 % | C18: =IF(AND('Supuestos'!$C$12>=0,'Supuestos'!$C$12<=1,'Supuestos'!$C$13>=0,'Supuestos'!$C$13<=1,'Supuestos'!$C$18>=0,'Supuestos'!$C$18<=1,'Supuestos'!$C$20>=0,'Supuestos'!$C$20<=1,'Supuestos'!$C$22>=0,'Supuestos'!$C$22<=1,'Supuestos'!$C$24>=0,'Supuestos'!$C$24<=1,'Supuestos'!$C$26>=0,'Supuestos'!$C$26<=1,'Supuestos'!$C$28>=0,'Supuestos'!$C$28<=1,'Supuestos'!$C$30>=0,'Supuestos'!$C$30<=1),"OK","REVISAR") | D18: Un 25 % se escribe 25 % (o 0,25), no 25.
B19: El margen de seguridad está entre 0 y 100 % | C19: =IF(AND('Supuestos'!$C$46>=0,'Supuestos'!$C$46<=1),"OK","REVISAR")
B20: El crecimiento mensual está entre −50 % y 100 % | C20: =IF(AND('Supuestos'!$C$48>=-0.5,'Supuestos'!$C$48<=1),"OK","REVISAR") | D20: Más de 100 % por mes no es realista para una proyección.
B21: La cadena es decreciente (cada etapa tiene menos gente que la anterior) | C21: =IF(AND('Modelo'!$C$9<='Modelo'!$C$8,'Modelo'!$C$10<='Modelo'!$C$9),"OK","REVISAR") | D21: Si falla, alguna conversión está por encima de 100 %.
B23: Estado general del modelo | C23: =IF(COUNTIF(C6:C21,"REVISAR")=0,"OK","REVISAR")

Sheet Licencia
B2: Autoría y licencia
B4: Modelo financiero · Embudo low-ticket con bumps y upsells
B5: Modelo financiero de embudos · creado por Jesús Tassarolo · TooAudience · youtube.com/@JesusTassaroloSinFiltro
B6: v1.2 · octubre 2026
B8: Licencia Creative Commons BY-NC-ND 4.0: podés usar este archivo con tus números y compartirlo tal cual, citando al autor. No podés venderlo, modificar su estructura para redistribuirlo ni quitar la línea de autoría.
B10: Este archivo, sus fórmulas, sus umbrales y su método son obra de Jesús Tassarolo (TooAudience). Si lo compartís, compartilo entero y con esta hoja.
B11: Canal: youtube.com/@JesusTassaroloSinFiltro
