Workbook

Sheet Inicio
B2: Modelo financiero · Embudo de webinar gratuito
B3: Anuncios → landing de registro → grupo de WhatsApp → webinar en vivo y replay → oferta + bump + programa superior
B5: Para qué sirve este modelo
B6: Es el modelo financiero de un embudo de webinar gratuito: anuncios que llevan a una landing de registro, un grupo de WhatsApp, un webinar en vivo (con replay) donde se presenta una oferta, y un programa superior que se vende después. Con tus números (o con el ejemplo cargado) te dice cuánto vale cada registro que comprás con publicidad, hasta cuánto podés pagar por registro y por cada etapa siguiente, cuánto invertir para una meta de ventas, cuánta caja necesitás y qué palanca mejora más la ganancia.
B7: La unidad que comprás es el registro (lead). El número que manda es el valor neto por registro contra el costo por registro (CPL real y CPL calificado). Después, escalón por escalón: costo por persona en el grupo, costo por asistente en vivo, costo por solicitud y cierre, cada uno con su cantidad y su porcentaje.
B9: Cómo usarlo en 6 pasos
B10: 1. Andá a Supuestos y reemplazá el ejemplo por tus números. Si todavía no tenés datos, dejá el escenario en 1 (conservador) y usá Benchmarks como referencia.
B11: 2. Mirá Resumen: ganancia del lanzamiento, ROAS, el techo y el objetivo de costo por registro, y el semáforo. Después Embudo: todos los pasos en orden con cuántos pasan, qué porcentaje se pierde y cuánto cuesta cada paso.
B12: 3. Abrí Escenarios para ver qué pasa si cambia el precio, la conversión o el costo. Las celdas amarillas de cada tabla se pueden cambiar.
B13: 4. Abrí Sensibilidad para saber qué variable conviene trabajar primero.
B14: 5. Antes de invertir, mirá Proyección 12 meses: la caja necesaria es la plata que tenés que tener para no frenar la pauta mientras cobrás. Si da 0, el embudo se autofinancia.
B15: 6. Cuando el embudo esté andando, completá una columna de Seguimiento por lanzamiento. El semáforo te dice si estás pagando de más por cada registro.
... B46: Este modelo se comparte para que lo uses con tus números. Si lo compartís, dejá esta línea: es la forma de saber de dónde salió.

Sheet Resumen
B2: Resumen: lo que hay que mirar
B3: Todo sale de Modelo con los supuestos del escenario en uso. Cambiá Supuestos y esto se actualiza.
B5: Indicador | C5: Valor | D5: Qué significa
B6: Resultado del lanzamiento
B7: Ganancia del período | C7: ='Modelo'!$C$45 | D7: Cash neto menos costos y menos inversión.
B8: ROAS sobre cash neto | C8: ='Modelo'!$C$47 | D8: Cada dólar invertido vuelve como esto, ya neto.
B9: ROAS sobre facturado | C9: ='Modelo'!$C$46 | D9: Sobre facturado. No decidas con este.
B10: Registros (leads) | C10: ='Modelo'!$C$11 | D10: Registros que compra la pauta.
B11: Asistentes en vivo | C11: ='Modelo'!$C$17 | D11: Asistentes en vivo.
B12: Ventas de la oferta | C12: ='Modelo'!$C$26 | D12: Ventas de la oferta (vivo + replay).
B13: Unit economics
B14: Costo por registro (CPL) | C14: ='Modelo'!$C$10 | D14: CPL real: inversión ÷ registros.
B15: Costo por registro calificado (CPL calificado) | C15: ='Modelo'!$C$13 | D15: CPL calificado: inversión ÷ registros que califican.
B16: Costo por persona en el grupo | C16: ='Modelo'!$C$16 | D16: Lo que te cuesta cada persona que entra al grupo.
B17: Valor neto por registro | C17: ='Modelo'!$C$51 | D17: Lo que vale un registro en cash neto.
B18: Costo por asistente en vivo | C18: ='Modelo'!$C$19 | D18: Lo que te cuesta cada persona que asiste en vivo.
B19: Las dos caras de cada número
B20: Ganancia por visita | C20: ='Modelo'!$C$66 | D20: Lo que te queda por cada visita a la landing. La métrica más valiosa del embudo.
B21: Ganancia por clic | C21: ='Modelo'!$C$67 | D21: Lo que te queda por cada clic. Su par es el costo por clic (Embudo).
B22: Ganancia por lead | C22: ='Modelo'!$C$68 | D22: Lo que te queda por cada registro. Su par es el CPL.
B23: Ganancia por cliente | C23: ='Modelo'!$C$71 | D23: Lo que te queda por cada comprador. Su par es el CPA.
B24: Order value (AOV) | C24: ='Modelo'!$C$35 | D24: Facturado por comprador con bump y programa.
B25: Order value neto (AOV neto) | C25: ='Modelo'!$C$65 | D25: Lo mismo después de comisiones, reembolsos y costos por registro.
B26: Solicitudes (total) | C26: ='Modelo'!$C$23 | D26: Formularios de compra, aplicaciones o pedidos de hablar con un vendedor.
B27: Costo por solicitud | C27: ='Modelo'!$C$25 | D27: Lo que te cuesta cada solicitud.
B28: Costo por comprador (CPA) | C28: ='Modelo'!$C$28 | D28: Lo que te cuesta cada comprador.
B29: Hasta cuánto pagar
B30: Techo de CPL (break-even) | C30: ='Modelo'!$C$52 | D30: CPL donde no ganás ni perdés.
B31: Objetivo de CPL | C31: ='Modelo'!$C$53 | D31: A este CPL o menos estás en verde.
B32: Techo de costo por asistente en vivo | C32: ='Modelo'!$C$55 | D32: Costo máximo por asistente en vivo.
B33: Techo de costo por solicitud | C33: ='Modelo'!$C$57 | D33: Costo máximo por solicitud.
B34: Techo de costo por comprador (CPA máximo) | C34: ='Modelo'!$C$58 | D34: CPA máximo si lo demás se mantiene.
B35: Semáforo del CPL actual | C35: ='Modelo'!$C$61 | D35: Tu CPL actual contra techo y objetivo.
B36: Cuánto invertir y cuánta caja
B37: Inversión necesaria para la meta de ventas (al CPL actual) | C37: ='Modelo'!$C$62 | D37: Para la meta de ventas de Supuestos, al CPL actual.
B38: Caja que hay que tener (peor momento de la proyección) | C38: ='Proyección 12 meses'!$C$18 | D38: Si da 0, el embudo se autofinancia: cada mes cobra más de lo que invierte.
B39: Saldo mínimo de caja con tu caja inicial | C39: ='Proyección 12 meses'!$C$19 | D39: Si es negativo, la caja inicial no alcanza.
B40: Ganancia acumulada en 12 meses | C40: ='Proyección 12 meses'!$C$20 | D40: Con la inversión creciendo según el supuesto.
B42: Recomendación según el semáforo | C42: =IF('Modelo'!$C$61="VERDE","Sostener o subir un escalón (+25 %) y medir 7 días",IF('Modelo'!$C$61="AMARILLO","No subir. Si el costo está bien, el ROAS no llega al objetivo: mirá Sensibilidad. Si no, revisar en orden: CPM, creativo, página",IF('Modelo'!$C$61="ROJO","Bajar un escalón (−25 %) y arreglar antes de volver a subir","")))
B44: Modelo financiero de embudos · creado por Jesús Tassarolo · TooAudience · youtube.com/@JesusTassaroloSinFiltro · v1.2 · octubre 2026

Sheet Embudo
B2: Embudo: todos los pasos, cuántos pasan y, por cada uno, qué pagás, qué te queda y hasta cuánto podrías pagar
B3: Cada fila es un paso del embudo en orden. '% que pasa' compara con el paso anterior (o con el que dice la nota). Tres números por paso: lo que pagás hoy por cada uno (inversión ÷ cantidad), lo que te queda por cada uno (ganancia ÷ cantidad) y lo máximo que podrías pagar (el techo: lo que cada uno genera en cash neto). Techo = costo + ganancia + fijos repartidos.
B5: Paso | C5: Cantidad | D5: % que pasa | E5: % acumulado | F5: Costo por paso (pagás hoy) | G5: Ganancia por paso (te queda) | H5: Techo por paso (máximo a pagar) | I5: Qué se paga acá / cómo se lee
B6: Impresiones del anuncio (por mil) | C6: ='Modelo'!$C$7 | D6: — | E6: — | F6: =IF('Modelo'!$C$7=0,0,'Supuestos'!$C$8*1000/'Modelo'!$C$7) | G6: =IF('Modelo'!$C$7=0,0,'Modelo'!$C$45*1000/'Modelo'!$C$7) | H6: =IF('Modelo'!$C$7=0,0,'Modelo'!$C$51*'Modelo'!$C$11*1000/'Modelo'!$C$7) | I6: Costo por mil impresiones (CPM) y CPM máximo. Palancas: público, frecuencia, horario.
B7: Clics al enlace | C7: ='Modelo'!$C$8 | D7: =IF('Modelo'!$C$7=0,0,'Modelo'!$C$8/'Modelo'!$C$7) | E7: — | F7: =IF('Modelo'!$C$8=0,0,'Supuestos'!$C$8*1/'Modelo'!$C$8) | G7: =IF('Modelo'!$C$8=0,0,'Modelo'!$C$45*1/'Modelo'!$C$8) | H7: =IF('Modelo'!$C$8=0,0,'Modelo'!$C$51*'Modelo'!$C$11*1/'Modelo'!$C$8) | I7: Costo por clic. Palanca: el creativo (CTR).
B8: Visitas a la landing | C8: ='Modelo'!$C$9 | D8: =IF('Modelo'!$C$8=0,0,'Modelo'!$C$9/'Modelo'!$C$8) | E8: — | F8: =IF('Modelo'!$C$9=0,0,'Supuestos'!$C$8*1/'Modelo'!$C$9) | G8: =IF('Modelo'!$C$9=0,0,'Modelo'!$C$45*1/'Modelo'!$C$9) | H8: =IF('Modelo'!$C$9=0,0,'Modelo'!$C$51*'Modelo'!$C$11*1/'Modelo'!$C$9) | I8: Costo por visita. Palanca: velocidad de carga, enlace correcto.
B9: Registros (leads) | C9: ='Modelo'!$C$11 | D9: =IF('Modelo'!$C$9=0,0,'Modelo'!$C$11/'Modelo'!$C$9) | E9: =IF('Modelo'!$C$11=0,0,'Modelo'!$C$11/'Modelo'!$C$11) | F9: =IF('Modelo'!$C$11=0,0,'Supuestos'!$C$8*1/'Modelo'!$C$11) | G9: =IF('Modelo'!$C$11=0,0,'Modelo'!$C$45*1/'Modelo'!$C$11) | H9: =IF('Modelo'!$C$11=0,0,'Modelo'!$C$51*'Modelo'!$C$11*1/'Modelo'!$C$11) | I9: CPL real. Palanca: promesa y formulario del landing.
B10: Registros calificados | C10: ='Modelo'!$C$12 | D10: =IF('Modelo'!$C$11=0,0,'Modelo'!$C$12/'Modelo'!$C$11) | E10: =IF('Modelo'!$C$11=0,0,'Modelo'!$C$12/'Modelo'!$C$11) | F10: =IF('Modelo'!$C$12=0,0,'Supuestos'!$C$8*1/'Modelo'!$C$12) | G10: =IF('Modelo'!$C$12=0,0,'Modelo'!$C$45*1/'Modelo'!$C$12) | H10: =IF('Modelo'!$C$12=0,0,'Modelo'!$C$51*'Modelo'!$C$11*1/'Modelo'!$C$12) | I10: CPL calificado. Sobre registros.
B11: Entran al grupo de WhatsApp | C11: ='Modelo'!$C$15 | D11: =IF('Modelo'!$C$11=0,0,'Modelo'!$C$15/'Modelo'!$C$11) | E11: =IF('Modelo'!$C$11=0,0,'Modelo'!$C$15/'Modelo'!$C$11) | F11: =IF('Modelo'!$C$15=0,0,'Supuestos'!$C$8*1/'Modelo'!$C$15) | G11: =IF('Modelo'!$C$15=0,0,'Modelo'!$C$45*1/'Modelo'!$C$15) | H11: =IF('Modelo'!$C$15=0,0,'Modelo'!$C$51*'Modelo'!$C$11*1/'Modelo'!$C$15) | I11: Costo por persona en el grupo. Sobre registros.
B12: Asisten en vivo | C12: ='Modelo'!$C$17 | D12: =IF('Modelo'!$C$11=0,0,'Modelo'!$C$17/'Modelo'!$C$11) | E12: =IF('Modelo'!$C$11=0,0,'Modelo'!$C$17/'Modelo'!$C$11) | F12: =IF('Modelo'!$C$17=0,0,'Supuestos'!$C$8*1/'Modelo'!$C$17) | G12: =IF('Modelo'!$C$17=0,0,'Modelo'!$C$45*1/'Modelo'!$C$17) | H12: =IF('Modelo'!$C$17=0,0,'Modelo'!$C$51*'Modelo'!$C$11*1/'Modelo'!$C$17) | I12: Costo por asistente en vivo. Sobre registros. Palancas: recordatorios, grupo, horario.
B13: Ven el replay | C13: ='Modelo'!$C$18 | D13: =IF('Modelo'!$C$11=0,0,'Modelo'!$C$18/'Modelo'!$C$11) | E13: =IF('Modelo'!$C$11=0,0,'Modelo'!$C$18/'Modelo'!$C$11) | F13: =IF('Modelo'!$C$18=0,0,'Supuestos'!$C$8*1/'Modelo'!$C$18) | G13: =IF('Modelo'!$C$18=0,0,'Modelo'!$C$45*1/'Modelo'!$C$18) | H13: =IF('Modelo'!$C$18=0,0,'Modelo'!$C$51*'Modelo'!$C$11*1/'Modelo'!$C$18) | I13: Costo por persona que vio el replay. Sobre registros.
B14: Solicitan, de los que estuvieron en vivo | C14: ='Modelo'!$C$21 | D14: =IF('Modelo'!$C$17=0,0,'Modelo'!$C$21/'Modelo'!$C$17) | E14: =IF('Modelo'!$C$11=0,0,'Modelo'!$C$21/'Modelo'!$C$11) | F14: =IF('Modelo'!$C$21=0,0,'Supuestos'!$C$8*1/'Modelo'!$C$21) | G14: =IF('Modelo'!$C$21=0,0,'Modelo'!$C$45*1/'Modelo'!$C$21) | H14: =IF('Modelo'!$C$21=0,0,'Modelo'!$C$51*'Modelo'!$C$11*1/'Modelo'!$C$21) | I14: Formulario de compra, aplicación o vendedor. Sobre asistentes en vivo. Palancas: oferta, pitch.
B15: Solicitan, de los que vieron el replay | C15: ='Modelo'!$C$22 | D15: =IF('Modelo'!$C$18=0,0,'Modelo'!$C$22/'Modelo'!$C$18) | E15: =IF('Modelo'!$C$11=0,0,'Modelo'!$C$22/'Modelo'!$C$11) | F15: =IF('Modelo'!$C$22=0,0,'Supuestos'!$C$8*1/'Modelo'!$C$22) | G15: =IF('Modelo'!$C$22=0,0,'Modelo'!$C$45*1/'Modelo'!$C$22) | H15: =IF('Modelo'!$C$22=0,0,'Modelo'!$C$51*'Modelo'!$C$11*1/'Modelo'!$C$22) | I15: Sobre los que vieron el replay.
B16: Solicitudes (total) | C16: ='Modelo'!$C$23 | D16: =IF('Modelo'!$C$11=0,0,'Modelo'!$C$23/'Modelo'!$C$11) | E16: =IF('Modelo'!$C$11=0,0,'Modelo'!$C$23/'Modelo'!$C$11) | F16: =IF('Modelo'!$C$23=0,0,'Supuestos'!$C$8*1/'Modelo'!$C$23) | G16: =IF('Modelo'!$C$23=0,0,'Modelo'!$C$45*1/'Modelo'!$C$23) | H16: =IF('Modelo'!$C$23=0,0,'Modelo'!$C$51*'Modelo'!$C$11*1/'Modelo'!$C$23) | I16: Costo por solicitud. Sobre registros.
B17: Compran la oferta | C17: ='Modelo'!$C$26 | D17: =IF('Modelo'!$C$23=0,0,'Modelo'!$C$26/'Modelo'!$C$23) | E17: =IF('Modelo'!$C$11=0,0,'Modelo'!$C$26/'Modelo'!$C$11) | F17: =IF('Modelo'!$C$26=0,0,'Supuestos'!$C$8*1/'Modelo'!$C$26) | G17: =IF('Modelo'!$C$26=0,0,'Modelo'!$C$45*1/'Modelo'!$C$26) | H17: =IF('Modelo'!$C$26=0,0,'Modelo'!$C$51*'Modelo'!$C$11*1/'Modelo'!$C$26) | I17: CPA: costo por comprador. Sobre solicitudes (cierre). Palancas: seguimiento, vendedor, forma de pago.
B18: Toman el bump | C18: ='Modelo'!$C$30 | D18: =IF('Modelo'!$C$26=0,0,'Modelo'!$C$30/'Modelo'!$C$26) | E18: =IF('Modelo'!$C$11=0,0,'Modelo'!$C$30/'Modelo'!$C$11) | F18: sin costo propio | G18: — | H18: — | I18: Sobre compradores. Se pagó con el CPA; suma al AOV.
B19: Pasan al programa superior | C19: ='Modelo'!$C$32 | D19: =IF('Modelo'!$C$26=0,0,'Modelo'!$C$32/'Modelo'!$C$26) | E19: =IF('Modelo'!$C$11=0,0,'Modelo'!$C$32/'Modelo'!$C$11) | F19: sin costo propio | G19: — | H19: — | I19: Sobre compradores.
B21: Comprobalo con la fila de la unidad: costo + ganancia + fijos repartidos = techo | F21: =F9 | G21: =G9 | H21: =F9+G9+'Supuestos'!$C$38/'Modelo'!$C$11 | I21: Techo = costo + ganancia + fijos ÷ unidades. Lo que falta entre (costo + ganancia) y el techo son los costos fijos repartidos entre las unidades.
B22: Cómo se lee
B23: Cantidad: cuántas acciones o personas hubo en ese paso con los supuestos del escenario en uso.
B24: % que pasa: de los que estaban en el paso anterior (o en el paso que indica la nota), cuántos llegan a este. % acumulado: cuántos llegan a este paso por cada 100 unidades que compra la pauta.
B25: Costo por paso: inversión ÷ cantidad. Es lo que te está costando hoy cada persona que llega a ese paso.
B26: Ganancia por paso: ganancia del período ÷ cantidad. Lo que te queda por cada persona de ese paso después de pagar la pauta, las comisiones, los reembolsos y los fijos. La ganancia por visita es la métrica más valiosa del embudo: resume todo lo que pasa después.
B27: Techo por paso: lo que cada persona de ese paso genera en cash neto (cash neto menos costos por unidad, dividido por la cantidad). Es lo máximo que podrías pagar por ese paso antes de que la ganancia llegue a cero, si lo demás se mantiene. Por eso siempre es mayor que la ganancia: techo = costo + ganancia + fijos repartidos.
B28: Los bumps, las OTOs y la ascensión no tienen costo propio: se pagan con el CPA del comprador principal y se miden por lo que suman al AOV.

Sheet Supuestos
B2: Supuestos
B3: Celdas amarillas = las editás vos. Celdas azules = se calculan solas. Cada fila dice en qué unidad va y de dónde sale el valor del ejemplo.
B5: Supuesto | C5: Valor en uso | D5: Conservador | E5: Base | F5: Optimista | G5: Unidad | H5: Nota / fuente del ejemplo
B6: Escenario en uso (1 = conservador · 2 = base · 3 = optimista) | C6: 2 | G6: 1 / 2 / 3 | H6: Cambia todas las filas que tienen tres valores. Si una fila no tiene tres valores, se usa el de 'Valor en uso'.
B7: 1. Inversión y tráfico
B8: Inversión en publicidad por lanzamiento | C8: 6000 | G8: USD / lanzamiento | H8: Un lanzamiento = un ciclo de captación + webinar + venta (en el ejemplo, una semana).
B9: Lanzamientos por mes (para la proyección) | C9: 4 | G9: lanzamientos / mes | H9: Cuántos lanzamientos como este hacés por mes. La proyección multiplica inversión, costos fijos y ventas por este número.
B10: CPM (costo por mil impresiones) | C10: =IF('Supuestos'!$C$6=1,D10,IF('Supuestos'!$C$6=2,E10,F10)) | D10: 6 | E10: 4.5 | F10: 3.5 | G10: USD | H10: Lo que cobra Meta por mil impresiones. Hispano: 3 a 7.
B11: CTR al enlace | C11: =IF('Supuestos'!$C$6=1,D11,IF('Supuestos'!$C$6=2,E11,F11)) | D11: 0.016 | E11: 0.022 | F11: 0.03 | G11: % | H11: Clics en el enlace ÷ impresiones.
B12: % de clics que cargan la landing | C12: 0.9 | G12: % | H12: Siempre menor a 100 %: una parte cierra antes de que cargue.
B14: 2. Landing de registro
B15: % de visitas que se registran | C15: =IF('Supuestos'!$C$6=1,D15,IF('Supuestos'!$C$6=2,E15,F15)) | D15: 0.18 | E15: 0.23 | F15: 0.3 | G15: % | H15: La conversión del landing. Con nombre + WhatsApp: 20 a 30 %.
B16: % de registros que califican (si el formulario tiene una pregunta que califica) | C16: =IF('Supuestos'!$C$6=1,D16,IF('Supuestos'!$C$6=2,E16,F16)) | D16: 0.5 | E16: 0.6 | F16: 0.7 | G16: % | H16: Si no calificás en el formulario, poné 100 %. Sirve para ver el CPL calificado además del CPL real.
B18: 3. Grupo de WhatsApp y asistencia
B19: % de registrados que entran al grupo de WhatsApp | C19: =IF('Supuestos'!$C$6=1,D19,IF('Supuestos'!$C$6=2,E19,F19)) | D19: 0.55 | E19: 0.67 | F19: 0.78 | G19: % | H19: Si no usás grupo, poné 0 %: no afecta las ventas en este modelo, solo el techo por persona en el grupo.
B20: % de registrados que asisten en vivo | C20: =IF('Supuestos'!$C$6=1,D20,IF('Supuestos'!$C$6=2,E20,F20)) | D20: 0.11 | E20: 0.15 | F20: 0.2 | G20: % | H20: Tráfico frío hispano: 10 a 20 %. En B2B USA promedia 33 %.
B21: % de registrados que ven el replay | C21: =IF('Supuestos'!$C$6=1,D21,IF('Supuestos'!$C$6=2,E21,F21)) | D21: 0.4 | E21: 0.55 | F21: 0.7 | G21: % | H21: Sin contar a los que fueron en vivo.
B23: 4. Oferta y escalera
B24: Oferta del webinar: precio | C24: 297 | G24: USD | H24: El producto que se presenta en el webinar.
B25: % de asistentes en vivo que solicitan (formulario de compra, de aplicación o hablar con un vendedor) | C25: =IF('Supuestos'!$C$6=1,D25,IF('Supuestos'!$C$6=2,E25,F25)) | D25: 0.06 | E25: 0.1 | F25: 0.15 | G25: % | H25: La solicitud es lo que pasa en el webinar cuando se presenta la oferta. Incluye la ventana de 72 h.
B26: % de los que ven el replay que solicitan | C26: =IF('Supuestos'!$C$6=1,D26,IF('Supuestos'!$C$6=2,E26,F26)) | D26: 0.012 | E26: 0.025 | F26: 0.04 | G26: % | H26: Mucho menor que en vivo.
B27: % de solicitudes que terminan en compra | C27: =IF('Supuestos'!$C$6=1,D27,IF('Supuestos'!$C$6=2,E27,F27)) | D27: 0.3 | E27: 0.4 | F27: 0.5 | G27: % | H27: Con compra directa en el formulario suele ser alto; con vendedor o aplicación, 30 a 50 %.
B28: Bump en el checkout: precio | C28: 47 | G28: USD | H28: Oferta extra con una casilla en el checkout.
B29: Bump: % de compradores que lo toman | C29: =IF('Supuestos'!$C$6=1,D29,IF('Supuestos'!$C$6=2,E29,F29)) | D29: 0.12 | E29: 0.2 | F29: 0.3 | G29: %
B30: Programa superior: precio | C30: 997 | G30: USD | H30: Se vende después de la oferta, por llamada o por ascenso.
B31: Programa superior: % de compradores que lo toman | C31: =IF('Supuestos'!$C$6=1,D31,IF('Supuestos'!$C$6=2,E31,F31)) | D31: 0.03 | E31: 0.05 | F31: 0.08 | G31: % | H31: Sobre compradores de la oferta.
B33: 5. Costos
B34: Comisión de la pasarela o plataforma de pago | C34: 0.1 | G34: % del cash | H34: Hotmart, Stripe, Mercado Pago: lo que se queda la plataforma.
B35: Comisión del equipo de ventas | C35: 0 | G35: % del cash | H35: Sobre el cash cobrado. Si vendés el programa superior por llamada, poné acá la comisión del closer (10 a 15 % de esa parte).
B36: Reembolsos y contracargos | C36: 0.05 | G36: % del cash | H36: 5 % es normal en productos digitales. Más de 10 % es un problema de oferta o de expectativa.
B37: Costos por registro (herramientas, WhatsApp, IA) | C37: 0.1 | G37: USD / registro | H37: WhatsApp API, email, IA: lo que pagás por cada registro.
B38: Costos fijos por lanzamiento | C38: 1200 | G38: USD / lanzamiento | H38: Equipo, herramientas, edición: lo que pagás aunque no vendas.
B40: 6. Cobranza
B41: % del facturado que entra en el mes 1 | C41: 0.7 | G41: % | H41: Con cuotas, el 70 % entra el primer mes y el resto en los dos siguientes.
B42: % que entra en el mes 2 | C42: 0.15 | G42: % | H42: Cuotas o pagos diferidos.
B43: % que entra en el mes 3 | C43: 0.15 | G43: % | H43: Los tres deben sumar 100 %.
B45: 7. Objetivos y proyección
B46: ROAS objetivo sobre cash neto | C46: 2 | G46: x | H46: El retorno mínimo que querés por cada dólar invertido, después de comisiones y reembolsos. Entra en el semáforo: sin llegar a este ROAS no hay verde.
B47: Margen de seguridad | C47: 0.3 | G47: % | H47: Colchón entre el techo (donde no ganás ni perdés) y el objetivo. 30 % es el estándar que usamos.
B48: Meta de ventas del producto principal | C48: 60 | G48: ventas / lanzamiento | H48: Para calcular cuánto invertir.
B49: Crecimiento de la inversión por mes (proyección) | C49: 0.1 | G49: % / mes | H49: Cuánto sube la inversión cada mes en la proyección. 10 % por mes es un ritmo prudente; más de 25 % suele encarecer el CPM.
B50: Caja inicial | C50: 5000 | G50: USD | H50: Con cuánta plata arrancás. La proyección te dice si alcanza.

Sheet Modelo
B2: Modelo: la cadena completa del embudo
B3: Cada fila es una etapa o un resultado. No se edita: todo sale de Supuestos. La columna de la derecha dice cómo se calcula.
B5: Etapa / resultado | C5: Valor | D5: Cómo se calcula
B6: Tráfico y registros
B7: Impresiones | C7: =IF('Supuestos'!$C$10=0,0,'Supuestos'!$C$8/'Supuestos'!$C$10*1000) | D7: Inversión ÷ CPM × 1.000.
B8: Clics al enlace | C8: ='Modelo'!$C$7*'Supuestos'!$C$11 | D8: Impresiones × CTR.
B9: Visitas a la landing | C9: ='Modelo'!$C$8*'Supuestos'!$C$12 | D9: Clics × % que carga.
B10: Costo por registro (CPL) | C10: =IF('Supuestos'!$C$11*'Supuestos'!$C$12*'Supuestos'!$C$15=0,0,'Supuestos'!$C$10/1000/('Supuestos'!$C$11*'Supuestos'!$C$12*'Supuestos'!$C$15)) | D10: CPM ÷ 1.000 ÷ (CTR × clic→visita × conversión del landing).
B11: Registros (leads) | C11: =IF('Modelo'!$C$10=0,0,'Supuestos'!$C$8/'Modelo'!$C$10) | D11: Inversión ÷ CPL.
B12: Registros calificados | C12: ='Modelo'!$C$11*'Supuestos'!$C$16 | D12: Registros × % que califica.
B13: Costo por registro calificado (CPL calificado) | C13: =IF('Modelo'!$C$12=0,0,'Supuestos'!$C$8/'Modelo'!$C$12) | D13: Inversión ÷ registros calificados.
B14: Grupo y asistencia
B15: Personas en el grupo de WhatsApp | C15: ='Modelo'!$C$11*'Supuestos'!$C$19 | D15: Registros × % que entra.
B16: Costo por persona en el grupo | C16: =IF('Modelo'!$C$15=0,0,'Supuestos'!$C$8/'Modelo'!$C$15) | D16: Inversión ÷ personas en el grupo.
B17: Asistentes en vivo | C17: ='Modelo'!$C$11*'Supuestos'!$C$20 | D17: Registros × show rate en vivo.
B18: Vieron el replay | C18: ='Modelo'!$C$11*'Supuestos'!$C$21 | D18: Registros × % que ve el replay.
B19: Costo por asistente en vivo | C19: =IF('Modelo'!$C$17=0,0,'Supuestos'!$C$8/'Modelo'!$C$17) | D19: Inversión ÷ asistentes en vivo.
B20: Solicitudes (formulario de compra, aplicación o vendedor), ventas y facturación
B21: Solicitudes: en vivo | C21: ='Modelo'!$C$17*'Supuestos'!$C$25 | D21: Asistentes en vivo × % que solicita.
B22: Solicitudes: replay | C22: ='Modelo'!$C$18*'Supuestos'!$C$26 | D22: Replay × % que solicita.
B23: Solicitudes (total) | C23: ='Modelo'!$C$21+'Modelo'!$C$22 | D23: En vivo + replay.
B24: % de registros que solicitan | C24: =IF('Modelo'!$C$11=0,0,'Modelo'!$C$23/'Modelo'!$C$11) | D24: Solicitudes ÷ registros.
B25: Costo por solicitud | C25: =IF('Modelo'!$C$23=0,0,'Supuestos'!$C$8/'Modelo'!$C$23) | D25: Inversión ÷ solicitudes.
B26: Ventas de la oferta | C26: ='Modelo'!$C$23*'Supuestos'!$C$27 | D26: Solicitudes × % que termina en compra.
B27: % de registros que compran | C27: =IF('Modelo'!$C$11=0,0,'Modelo'!$C$26/'Modelo'!$C$11) | D27: Ventas ÷ registros.
B28: Costo por comprador (CPA) | C28: =IF('Modelo'!$C$26=0,0,'Supuestos'!$C$8/'Modelo'!$C$26) | D28: Inversión ÷ ventas de la oferta.
B29: Facturado: oferta | C29: ='Modelo'!$C$26*'Supuestos'!$C$24 | D29: Ventas × precio.
B30: Ventas: bump | C30: ='Modelo'!$C$26*'Supuestos'!$C$29 | D30: Compradores × % que lo toma.
B31: Facturado: bump | C31: ='Modelo'!$C$30*'Supuestos'!$C$28 | D31: Ventas × precio.
B32: Ventas: programa superior | C32: ='Modelo'!$C$26*'Supuestos'!$C$31 | D32: Compradores × % que asciende.
B33: Facturado: programa superior | C33: ='Modelo'!$C$32*'Supuestos'!$C$30 | D33: Ventas × precio.
B34: Facturado total | C34: ='Modelo'!$C$29+'Modelo'!$C$31+'Modelo'!$C$33 | D34: Oferta + bump + programa.
B35: Facturado por comprador (AOV) | C35: =IF('Modelo'!$C$26=0,0,'Modelo'!$C$34/'Modelo'!$C$26) | D35: Facturado ÷ ventas de la oferta.
B36: Ventas de la oferta por registro (para la proyección) | C36: =IF('Modelo'!$C$11=0,0,'Modelo'!$C$26/'Modelo'!$C$11) | D36: Igual a '% de registros que compran'.
B37: Facturado por registro | C37: =IF('Modelo'!$C$11=0,0,'Modelo'!$C$34/'Modelo'!$C$11) | D37: Facturado ÷ registros.
B38: Cash, costos y ganancia del período
B39: Cash a cobrar (facturado × cobranza completa) | C39: ='Modelo'!$C$34*('Supuestos'!$C$41+'Supuestos'!$C$42+'Supuestos'!$C$43) | D39: Facturado × (mes 1 + mes 2 + mes 3). Si la cobranza suma 100 %, es igual al facturado.
B40: Cash que entra en el primer mes | C40: ='Modelo'!$C$34*'Supuestos'!$C$41 | D40: Facturado × % del mes 1.
B41: Comisiones (pasarela + ventas) | C41: ='Modelo'!$C$39*('Supuestos'!$C$34+'Supuestos'!$C$35) | D41: Cash × (pasarela + equipo de ventas).
B42: Reembolsos | C42: ='Modelo'!$C$39*'Supuestos'!$C$36 | D42: Cash × % de reembolsos.
B43: Cash neto | C43: ='Modelo'!$C$39*(1-'Supuestos'!$C$34-'Supuestos'!$C$35-'Supuestos'!$C$36) | D43: Cash − comisiones − reembolsos. La base de verdad.
B44: Costos por registro (herramientas, WhatsApp, IA) | C44: ='Modelo'!$C$11*'Supuestos'!$C$37 | D44: Registros × costo por registro.
B45: Ganancia del período | C45: ='Modelo'!$C$43-'Modelo'!$C$44-'Supuestos'!$C$38-'Supuestos'!$C$8 | D45: Cash neto − costos por unidad − fijos − inversión.
B46: ROAS sobre facturado | C46: =IF('Supuestos'!$C$8=0,0,'Modelo'!$C$34/'Supuestos'!$C$8) | D46: Facturado ÷ inversión. El número que más se infla: no decidas con este.
B47: ROAS sobre cash neto | C47: =IF('Supuestos'!$C$8=0,0,'Modelo'!$C$43/'Supuestos'!$C$8) | D47: Cash neto ÷ inversión. Con este se decide.
B48: Margen sobre cash | C48: =IF('Modelo'!$C$39=0,0,'Modelo'!$C$45/'Modelo'!$C$39) | D48: Ganancia ÷ cash.
B49: ¿Cumple el ROAS objetivo? | C49: =IF('Modelo'!$C$47>='Supuestos'!$C$46,"SÍ","NO") | D49: ROAS sobre cash neto contra el objetivo de Supuestos.
B50: Cuánto vale cada registro y hasta cuánto pagar
B51: Valor neto por registro | C51: =IF('Modelo'!$C$11=0,0,('Modelo'!$C$43-'Modelo'!$C$44)/'Modelo'!$C$11) | D51: (Cash neto − costos por registro) ÷ registros.
B52: Techo de CPL (break-even) | C52: ='Modelo'!$C$51 | D52: Igual al valor neto por registro.
B53: Objetivo de CPL | C53: ='Modelo'!$C$52/(1+'Supuestos'!$C$47) | D53: Techo ÷ (1 + margen de seguridad).
B54: Techo de costo por persona en el grupo | C54: =IF('Supuestos'!$C$19=0,0,'Modelo'!$C$51/'Supuestos'!$C$19) | D54: Valor por registro ÷ % que entra al grupo.
B55: Techo de costo por asistente en vivo | C55: =IF('Supuestos'!$C$20=0,0,'Modelo'!$C$51/'Supuestos'!$C$20) | D55: Valor por registro ÷ show rate.
B56: Techo de CPL calificado | C56: =IF('Supuestos'!$C$16=0,0,'Modelo'!$C$51/'Supuestos'!$C$16) | D56: Valor por registro ÷ % que califica.
B57: Techo de costo por solicitud | C57: =IF('Modelo'!$C$23=0,0,'Modelo'!$C$51*'Modelo'!$C$11/'Modelo'!$C$23) | D57: Valor total ÷ solicitudes.
B58: Techo de costo por comprador (CPA máximo) | C58: =IF('Modelo'!$C$27=0,0,'Modelo'!$C$51/'Modelo'!$C$27) | D58: Valor por registro ÷ % de registros que compran.
B59: Objetivo de CPA | C59: ='Modelo'!$C$58/(1+'Supuestos'!$C$47) | D59: CPA máximo ÷ (1 + margen de seguridad).
B60: Semáforo y cuánto invertir
B61: Semáforo del CPL actual | C61: =IF('Modelo'!$C$10>'Modelo'!$C$52,"ROJO",IF(AND('Modelo'!$C$10<='Modelo'!$C$53,'Modelo'!$C$47>='Supuestos'!$C$46),"VERDE","AMARILLO")) | D61: Rojo: costo > techo. Verde: costo ≤ objetivo y ROAS sobre cash neto ≥ objetivo. Amarillo: el resto.
B62: Inversión necesaria para la meta de ventas (al CPL actual) | C62: =IF('Modelo'!$C$27=0,"inalcanzable con estos supuestos",'Supuestos'!$C$48/'Modelo'!$C$27*'Modelo'!$C$10) | D62: Meta ÷ % de registros que compran × CPL.
B63: Inversión para la meta al CPL objetivo (lo máximo que conviene pagar) | C63: =IF('Modelo'!$C$27=0,"inalcanzable con estos supuestos",'Supuestos'!$C$48/'Modelo'!$C$27*'Modelo'!$C$53) | D63: Lo mismo, al CPL objetivo.
B64: Ganancia por paso (las dos caras de cada número: costo por X y ganancia por X)
B65: Cash neto por comprador (AOV neto) | C65: =IF('Modelo'!$C$26=0,0,('Modelo'!$C$43-'Modelo'!$C$44)/'Modelo'!$C$26) | D65: Lo que deja cada comprador del principal después de comisiones, reembolsos y costos por unidad. Su par es el CPA.
B66: Ganancia por visita | C66: =IF('Modelo'!$C$9=0,0,'Modelo'!$C$45/'Modelo'!$C$9) | D66: Ganancia del período ÷ visitas a la landing. La métrica más valiosa: resume todo lo que pasa después de la página. Su par es el costo por visita.
B67: Ganancia por clic | C67: =IF('Modelo'!$C$8=0,0,'Modelo'!$C$45/'Modelo'!$C$8) | D67: Ganancia del período ÷ clics. Su par es el costo por clic.
B68: Ganancia por lead | C68: =IF('Modelo'!$C$11=0,0,'Modelo'!$C$45/'Modelo'!$C$11) | D68: Ganancia del período ÷ registros. Su par es el CPL.
B69: Ganancia por asistente en vivo | C69: =IF('Modelo'!$C$17=0,0,'Modelo'!$C$45/'Modelo'!$C$17) | D69: Ganancia del período ÷ asistente en vivos. Su par es el costo por asistente en vivo.
B70: Ganancia por solicitud | C70: =IF('Modelo'!$C$23=0,0,'Modelo'!$C$45/'Modelo'!$C$23) | D70: Ganancia del período ÷ solicituds. Su par es el costo por solicitud.
B71: Ganancia por cliente | C71: =IF('Modelo'!$C$26=0,0,'Modelo'!$C$45/'Modelo'!$C$26) | D71: Ganancia del período ÷ compradores. Su par es el CPA.

Sheet Escenarios
B2: Escenarios: qué pasa si cambian el precio, la conversión o el costo
B3: Las celdas amarillas de cada tabla (fila y columna) se pueden cambiar. Verde = ganancia, amarillo = cerca del cero, rojo = pérdida. Todo lo demás queda como en Supuestos.
B5: Umbral de 'cerca del cero' (inversión × margen de seguridad) | C5: ='Supuestos'!$C$8*'Supuestos'!$C$47
B7: Precio de la oferta × % de solicitudes que terminan en compra → ganancia del lanzamiento
B8: A más precio, menos cierre: la tabla muestra qué combinación gana.
B9: Precio ↓ / % solicitud → compra → | C9: 0.25 | D9: 0.3 | E9: 0.4 | F9: 0.5 | G9: 0.6
B10: 97 | C10: =((((((((((IF((IF('Supuestos'!$C$11*'Supuestos'!$C$12*'Supuestos'!$C$15=0,0,'Supuestos'!$C$10/1000/('Supuestos'!$C$11*'Supuestos'!$C$12*'Supuestos'!$C$15)))=0,0,'Supuestos'!$C$8/(IF('Supuestos'!$C$11*'Supuestos'!$C$12*'Supuestos'!$C$15=0,0,'Supuestos'!$C$10/1000/('Supuestos'!$C$11*'Supuestos'!$C$12*'Supuestos'!$C$15)))))*'Supuestos'!$C$20)*'Supuestos'!$C$25)+(((IF((IF('Supuestos'!$C$11*'Supuestos'!$C$12*'Supuestos'!$C$15=0,0,'Supuestos'!$C$10/1000/('Supuestos'!$C$11*'Supuestos'!$C$12*'Supuestos'!$C$15)))=0,0,'Supuestos'!$C$8/(IF('Supuestos'!$C$11*'Supuestos'!$C$12*'Supuestos'!$C$15=0,0,'Supuestos'!$C$10/1000/('Supuestos'!$C$11*'Supuestos'!$C$12*'Supuestos'!$C$15)))))*'Supuestos'!$C$21)*'Supuestos'!$C$26))*C$9)*$B10)+(((((((IF((IF('Supuestos'!$C$11*'Supuestos'!$C$12*'Supuestos'!$C$15=0,0,'Supuestos'!$C$10/1000/('Supuestos'!$C$11*'Supuestos'!$C$12*'Supuestos'!$C$15)))=0,0,'Supuestos'!$C$8/(IF('Supuestos'!$C$11*'Supuestos'!$C$12*'Supuestos'!$C$15=0,0,'Supuestos'!$C$10/1000/('Supuestos'!$C$11*'Supuestos'!$C$12*'Supuestos'!$C$15)))))*'Supuestos'!$C$20)*'Supuestos'!$C$25)+(((IF((IF('Supuestos'!$C$11*'Supuestos'!$C$12*'Supuestos'!$C$15=0,0,'Supuestos'!$C$10/1000/('Supuestos'!$C$11*'Supuestos'!$C$12*'Supuestos'!$C$15)))=0,0,'Supuestos'!$C$8/(IF('Supuestos'!$C$11*'Supuestos'!$C$12*'Supuestos'!$C$15=0,0,'Supuestos'!$C$10/1000/('Supuestos'!$C$11*'Supuestos'!$C$12*'Supuestos'!$C$15)))))*'Supuestos'!$C$21)*'Supuestos'!$C$26))*C$9)*'Supuestos'!$C$29)*'Supuestos'!$C$28)+(((((((IF((IF('Supuestos'!$C$11*'Supuestos'!$C$12*'Supuestos'!$C$15=0,0,'Supuestos'!$C$10/1000/('Supuestos'!$C$11*'Supuestos'!$C$12*'Supuestos'!$C$15)))=0,0,'Supuestos'!$C$8/(IF('Supuestos'!$C$11*'Supuestos'!$C$12*'Supuestos'!$C$15=0,0,'Supuestos'!$C$10/1000/('Supuestos'!$C$11*'Supuestos'!$C$12*'Supuestos'!$C$15)))))*'Supuestos'!$C$20)*'Supuestos'!$C$25)+(((IF((IF('Supuestos'!$C$11*'Supuestos'!$C$12*'Supuestos'!$C$15=0,0,'Supuestos'!$C$10/1000/('Supuestos'!$C$11*'Supuestos'!$C$12*'Supuestos'!$C$15)))=0,0,'Supuestos'!$C$8/(IF('Supuestos'!$C$11*'Supuestos'!$C$12*'Supuestos'!$C$15=0,0,'Supuestos'!$C$10/1000/('Supuestos'!$C$11*'Supuestos'!$C$12*'Supuestos'!$C$15)))))*'Supuestos'!$C$21)*'Supuestos'!$C$26))*C$9)*'Supuestos'!$C$31)*'Supuestos'!$C$30))*('Supuestos'!$C$41+'Supuestos'!$C$42+'Supuestos'!$C$43))*(1-'Supuestos'!$C$34-'Supuestos'!$C$35-'Supuestos'!$C$36))-((IF((IF('Supuestos'!$C$11*'Supuestos'!$C$12*'Supuestos'!$C$15=0,0,'Supuestos'!$C$10/1000/('Supuestos'!$C$11*'Supuestos'!$C$12*'Supuestos'!$C$15)))=0,0,'Supuestos'!$C$8/(IF('Supuestos'!$C$11*'Supuestos'!$C$12*'Supuestos'!$C$15=0,0,'Supuestos'!$C$10/1000/('Supuestos'!$C$11*'Supuestos'!$C$12*'Supuestos'!$C$15)))))*'Supuestos'!$C$37)-'Supuestos'!$C$38-'Supuestos'!$C$8) | D10: =((((((((((IF((IF('Supuestos'!$C$11*'Supuestos'!$C$12*'Supuestos'!$C$15=0,0,'Supuestos'!$C$10/1000/('Supuestos'!$C$11*'Supuestos'!$C$12*'Supuestos'!$C$15)))=0,0,'Supuestos'!$C$8/(IF('Supuestos'!$C$11*'Supuestos'!$C$12*'Supuestos'!$C$15=0,0,'Supuestos'!$C$10/1000/('Supuestos'!$C$11*'Supuestos'!$C$12*'Supuestos'!$C$15)))))*'Supuestos'!$C$20)*'Supuestos'!$C$25)+(((IF((IF('Supuestos'!$C$11*'Supuestos'!$C$12*'Supuestos'!$C$15=0,0,'Supuestos'!$C$10/1000/('Supuestos'!$C$11*'Supuestos'!$C$12*'Supuestos'!$C$15)))=0,0,'Supuestos'!$C$8/(IF('Supuestos'!$C$11*'Supuestos'!$C$12*'Supuestos'!$C$15=0,0,'Supuestos'!$C$10/1000/('Supuestos'!$C$11*'Supuestos'!$C$12*'Supuestos'!$C$15)))))*'Supuestos'!$C$21)*'Supuestos'!$C$26))*D$9)*$B10)+(((((((IF((IF('Supuestos'!$C$11*'Supuestos'!$C$12*'Supuestos'!$C$15=0,0,'Supuestos'!$C$10/1000/('Supuestos'!$C$11*'Supuestos'!$C$12*'Supuestos'!$C$15)))=0,0,'Supuestos'!$C$8/(IF('Supuestos'!$C$11*'Supuestos'!$C$12*'Supuestos'!$C$15=0,0,'Supuestos'!$C$10/1000/('Supuestos'!$C$11*'Supuestos'!$C$12*'Supuestos'!$C$15)))))*'Supuestos'!$C$20)*'Supuestos'!$C$25)+(((IF((IF('Supuestos'!$C$11*'Supuestos'!$C$12*'Supuestos'!$C$15=0,0,'Supuestos'!$C$10/1000/('Supuestos'!$C$11*'Supuestos'!$C$12*'Supuestos'!$C$15)))=0,0,'Supuestos'!$C$8/(IF('Supuestos'!$C$11*'Supuestos'!$C$12*'Supuestos'!$C$15=0,0,'Supuestos'!$C$10/1000/('Supuestos'!$C$11*'Supuestos'!$C$12*'Supuestos'!$C$15)))))*'Supuestos'!$C$21)*'Supuestos'!$C$26))*D$9)*'Supuestos'!$C$29)*'Supuestos'!$C$28)+(((((((IF((IF('Supuestos'!$C$11*'Supuestos'!$C$12*'Supuestos'!$C$15=0,0,'Supuestos'!$C$10/1000/('Supuestos'!$C$11*'Supuestos'!$C$12*'Supuestos'!$C$15)))=0,0,'Supuestos'!$C$8/(IF('Supuestos'!$C$11*'Supuestos'!$C$12*'Supuestos'!$C$15=0,0,'Supuestos'!$C$10/1000/('Supuestos'!$C$11*'Supuestos'!$C$12*'Supuestos'!$C$15)))))*'Supuestos'!$C$20)*'Supuestos'!$C$25)+(((IF((IF('Supuestos'!$C$11*'Supuestos'!$C$12*'Supuestos'!$C$15=0,0,'Supuestos'!$C$10/1000/('Supuestos'!$C$11*'Supuestos'!$C$12*'Supuestos'!$C$15)))=0,0,'Supuestos'!$C$8/(IF('Supuestos'!$C$11*'Supuestos'!$C$12*'Supuestos'!$C$15=0,0,'Supuestos'!$C$10/1000/('Supuestos'!$C$11*'Supuestos'!$C$12*'Supuestos'!$C$15)))))*'Supuestos'!$C$21)*'Supuestos'!$C$26))*D$9)*'Supuestos'!$C$31)*'Supuestos'!$C$30))*('Supuestos'!$C$41+'Supuestos'!$C$42+'Supuestos'!$C$43))*(1-'Supuestos'!$C$34-'Supuestos'!$C$35-'Supuestos'!$C$36))-((IF((IF('Supuestos'!$C$11*'Supuestos'!$C$12*'Supuestos'!$C$15=0,0,'Supuestos'!$C$10/1000/('Supuestos'!$C$11*'Supuestos'!$C$12*'Supuestos'!$C$15)))=0,0,'Supuestos'!$C$8/(IF('Supuestos'!$C$11*'Supuestos'!$C$12*'Supuestos'!$C$15=0,0,'Supuestos'!$C$10/1000/('Supuestos'!$C$11*'Supuestos'!$C$12*'Supuestos'!$C$15)))))*'Supuestos'!$C$37)-'Supuestos'!$C$38-'Supuestos'!$C$8) | E10: =((((((((((IF((IF('Supuestos'!$C$11*'Supuestos'!$C$12*'Supuestos'!$C$15=0,0,'Supuestos'!$C$10/1000/('Supuestos'!$C$11*'Supuestos'!$C$12*'Supuestos'!$C$15)))=0,0,'Supuestos'!$C$8/(IF('Supuestos'!$C$11*'Supuestos'!$C$12*'Supuestos'!$C$15=0,0,'Supuestos'!$C$10/1000/('Supuestos'!$C$11*'Supuestos'!$C$12*'Supuestos'!$C$15)))))*'Supuestos'!$C$20)*'Supuestos'!$C$25)+(((IF((IF('Supuestos'!$C$11*'Supuestos'!$C$12*'Supuestos'!$C$15=0,0,'Supuestos'!$C$10/1000/('Supuestos'!$C$11*'Supuestos'!$C$12*'Supuestos'!$C$15)))=0,0,'Supuestos'!$C$8/(IF('Supuestos'!$C$11*'Supuestos'!$C$12*'Supuestos'!$C$15=0,0,'Supuestos'!$C$10/1000/('Supuestos'!$C$11*'Supuestos'!$C$12*'Supuestos'!$C$15)))))*'Supuestos'!$C$21)*'Supuestos'!$C$26))*E$9)*$B10)+(((((((IF((IF('Supuestos'!$C$11*'Supuestos'!$C$12*'Supuestos'!$C$15=0,0,'Supuestos'!$C$10/1000/('Supuestos'!$C$11*'Supuestos'!$C$12*'Supuestos'!$C$15)))=0,0,'Supuestos'!$C$8/(IF('Supuestos'!$C$11*'Supuestos'!$C$12*'Supuestos'!$C$15=0,0,'Supuestos'!$C$10/1000/('Supuestos'!$C$11*'Supuestos'!$C$12*'Supuestos'!$C$15)))))*'Supuestos'!$C$20)*'Supuestos'!$C$25)+(((IF((IF('Supuestos'!$C$11*'Supuestos'!$C$12*'Supuestos'!$C$15=0,0,'Supuestos'!$C$10/1000/('Supuestos'!$C$11*'Supuestos'!$C$12*'Supuestos'!$C$15)))=0,0,'Supuestos'!$C$8/(IF('Supuestos'!$C$11*'Supuestos'!$C$12*'Supuestos'!$C$15=0,0,'Supuestos'!$C$10/1000/('Supuestos'!$C$11*'Supuestos'!$C$12*'Supuestos'!$C$15)))))*'Supuestos'!$C$21)*'Supuestos'!$C$26))*E$9)*'Supuestos'!$C$29)*'Supuestos'!$C$28)+(((((((IF((IF('Supuestos'!$C$11*'Supuestos'!$C$12*'Supuestos'!$C$15=0,0,'Supuestos'!$C$10/1000/('Supuestos'!$C$11*'Supuestos'!$C$12*'Supuestos'!$C$15)))=0,0,'Supuestos'!$C$8/(IF('Supuestos'!$C$11*'Supuestos'!$C$12*'Supuestos'!$C$15=0,0,'Supuestos'!$C$10/1000/('Supuestos'!$C$11*'Supuestos'!$C$12*'Supuestos'!$C$15)))))*'Supuestos'!$C$20)*'Supuestos'!$C$25)+(((IF((IF('Supuestos'!$C$11*'Supuestos'!$C$12*'Supuestos'!$C$15=0,0,'Supuestos'!$C$10/1000/('Supuestos'!$C$11*'Supuestos'!$C$12*'Supuestos'!$C$15)))=0,0,'Supuestos'!$C$8/(IF('Supuestos'!$C$11*'Supuestos'!$C$12*'Supuestos'!$C$15=0,0,'Supuestos'!$C$10/1000/('Supuestos'!$C$11*'Supuestos'!$C$12*'Supuestos'!$C$15)))))*'Supuestos'!$C$21)*'Supuestos'!$C$26))*E$9)*'Supuestos'!$C$31)*'Supuestos'!$C$30))*('Supuestos'!$C$41+'Supuestos'!$C$42+'Supuestos'!$C$43))*(1-'Supuestos'!$C$34-'Supuestos'!$C$35-'Supuestos'!$C$36))-((IF((IF('Supuestos'!$C$11*'Supuestos'!$C$12*'Supuestos'!$C$15=0,0,'Supuestos'!$C$10/1000/('Supuestos'!$C$11*'Supuestos'!$C$12*'Supuestos'!$C$15)))=0,0,'Supuestos'!$C$8/(IF('Supuestos'!$C$11*'Supuestos'!$C$12*'Supuestos'!$C$15=0,0,'Supuestos'!$C$10/1000/('Supuestos'!$C$11*'Supuestos'!$C$12*'Supuestos'!$C$15)))))*'Supuestos'!$C$37)-'Supuestos'!$C$38-'Supuestos'!$C$8) | F10: =((((((((((IF((IF('Supuestos'!$C$11*'Supuestos'!$C$12*'Supuestos'!$C$15=0,0,'Supuestos'!$C$10/1000/('Supuestos'!$C$11*'Supuestos'!$C$12*'Supuestos'!$C$15)))=0,0,'Supuestos'!$C$8/(IF('Supuestos'!$C$11*'Supuestos'!$C$12*'Supuestos'!$C$15=0,0,'Supuestos'!$C$10/1000/('Supuestos'!$C$11*'Supuestos'!$C$12*'Supuestos'!$C$15)))))*'Supuestos'!$C$20)*'Supuestos'!$C$25)+(((IF((IF('Supuestos'!$C$11*'Supuestos'!$C$12*'Supuestos'!$C$15=0,0,'Supuestos'!$C$10/1000/('Supuestos'!$C$11*'Supuestos'!$C$12*'Supuestos'!$C$15)))=0,0,'Supuestos'!$C$8/(IF('Supuestos'!$C$11*'Supuestos'!$C$12*'Supuestos'!$C$15=0,0,'Supuestos'!$C$10/1000/('Supuestos'!$C$11*'Supuestos'!$C$12*'Supuestos'!$C$15)))))*'Supuestos'!$C$21)*'Supuestos'!$C$26))*F$9)*$B10)+(((((((IF((IF('Supuestos'!$C$11*'Supuestos'!$C$12*'Supuestos'!$C$15=0,0,'Supuestos'!$C$10/1000/('Supuestos'!$C$11*'Supuestos'!$C$12*'Supuestos'!$C$15)))=0,0,'Supuestos'!$C$8/(IF('Supuestos'!$C$11*'Supuestos'!$C$12*'Supuestos'!$C$15=0,0,'Supuestos'!$C$10/1000/('Supuestos'!$C$11*'Supuestos'!$C$12*'Supuestos'!$C$15)))))*'Supuestos'!$C$20)*'Supuestos'!$C$25)+(((IF((IF('Supuestos'!$C$11*'Supuestos'!$C$12*'Supuestos'!$C$15=0,0,'Supuestos'!$C$10/1000/('Supuestos'!$C$11*'Supuestos'!$C$12*'Supuestos'!$C$15)))=0,0,'Supuestos'!$C$8/(IF('Supuestos'!$C$11*'Supuestos'!$C$12*'Supuestos'!$C$15=0,0,'Supuestos'!$C$10/1000/('Supuestos'!$C$11*'Supuestos'!$C$12*'Supuestos'!$C$15)))))*'Supuestos'!$C$21)*'Supuestos'!$C$26))*F$9)*'Supuestos'!$C$29)*'Supuestos'!$C$28)+(((((((IF((IF('Supuestos'!$C$11*'Supuestos'!$C$12*'Supuestos'!$C$15=0,0,'Supuestos'!$C$10/1000/('Supuestos'!$C$11*'Supuestos'!$C$12*'Supuestos'!$C$15)))=0,0,'Supuestos'!$C$8/(IF('Supuestos'!$C$11*'Supuestos'!$C$12*'Supuestos'!$C$15=0,0,'Supuestos'!$C$10/1000/('Supuestos'!$C$11*'Supuestos'!$C$12*'Supuestos'!$C$15)))))*'Supuestos'!$C$20)*'Supuestos'!$C$25)+(((IF((IF('Supuestos'!$C$11*'Supuestos'!$C$12*'Supuestos'!$C$15=0,0,'Supuestos'!$C$10/1000/('Supuestos'!$C$11*'Supuestos'!$C$12*'Supuestos'!$C$15)))=0,0,'Supuestos'!$C$8/(IF('Supuestos'!$C$11*'Supuestos'!$C$12*'Supuestos'!$C$15=0,0,'Supuestos'!$C$10/1000/('Supuestos'!$C$11*'Supuestos'!$C$12*'Supuestos'!$C$15)))))*'Supuestos'!$C$21)*'Supuestos'!$C$26))*F$9)*'Supuestos'!$C$31)*'Supuestos'!$C$30))*('Supuestos'!$C$41+'Supuestos'!$C$42+'Supuestos'!$C$43))*(1-'Supuestos'!$C$34-'Supuestos'!$C$35-'Supuestos'!$C$36))-((IF((IF('Supuestos'!$C$11*'Supuestos'!$C$12*'Supuestos'!$C$15=0,0,'Supuestos'!$C$10/1000/('Supuestos'!$C$11*'Supuestos'!$C$12*'Supuestos'!$C$15)))=0,0,'Supuestos'!$C$8/(IF('Supuestos'!$C$11*'Supuestos'!$C$12*'Supuestos'!$C$15=0,0,'Supuestos'!$C$10/1000/('Supuestos'!$C$11*'Supuestos'!$C$12*'Supuestos'!$C$15)))))*'Supuestos'!$C$37)-'Supuestos'!$C$38-'Supuestos'!$C$8) | G10: =((((((((((IF((IF('Supuestos'!$C$11*'Supuestos'!$C$12*'Supuestos'!$C$15=0,0,'Supuestos'!$C$10/1000/('Supuestos'!$C$11*'Supuestos'!$C$12*'Supuestos'!$C$15)))=0,0,'Supuestos'!$C$8/(IF('Supuestos'!$C$11*'Supuestos'!$C$12*'Supuestos'!$C$15=0,0,'Supuestos'!$C$10/1000/('Supuestos'!$C$11*'Supuestos'!$C$12*'Supuestos'!$C$15)))))*'Supuestos'!$C$20)*'Supuestos'!$C$25)+(((IF((IF('Supuestos'!$C$11*'Supuestos'!$C$12*'Supuestos'!$C$15=0,0,'Supuestos'!$C$10/1000/('Supuestos'!$C$11*'Supuestos'!$C$12*'Supuestos'!$C$15)))=0,0,'Supuestos'!$C$8/(IF('Supuestos'!$C$11*'Supuestos'!$C$12*'Supuestos'!$C$15=0,0,'Supuestos'!$C$10/1000/('Supuestos'!$C$11*'Supuestos'!$C$12*'Supuestos'!$C$15)))))*'Supuestos'!$C$21)*'Supuestos'!$C$26))*G$9)*$B10)+(((((((IF((IF('Supuestos'!$C$11*'Supuestos'!$C$12*'Supuestos'!$C$15=0,0,'Supuestos'!$C$10/1000/('Supuestos'!$C$11*'Supuestos'!$C$12*'Supuestos'!$C$15)))=0,0,'Supuestos'!$C$8/(IF('Supuestos'!$C$11*'Supuestos'!$C$12*'Supuestos'!$C$15=0,0,'Supuestos'!$C$10/1000/('Supuestos'!$C$11*'Supuestos'!$C$12*'Supuestos'!$C$15)))))*'Supuestos'!$C$20)*'Supuestos'!$C$25)+(((IF((IF('Supuestos'!$C$11*'Supuestos'!$C$12*'Supuestos'!$C$15=0,0,'Supuestos'!$C$10/1000/('Supuestos'!$C$11*'Supuestos'!$C$12*'Supuestos'!$C$15)))=0,0,'Supuestos'!$C$8/(IF('Supuestos'!$C$11*'Supuestos'!$C$12*'Supuestos'!$C$15=0,0,'Supuestos'!$C$10/1000/('Supuestos'!$C$11*'Supuestos'!$C$12*'Supuestos'!$C$15)))))*'Supuestos'!$C$21)*'Supuestos'!$C$26))*G$9)*'Supuestos'!$C$29)*'Supuestos'!$C$28)+(((((((IF((IF('Supuestos'!$C$11*'Supuestos'!$C$12*'Supuestos'!$C$15=0,0,'Supuestos'!$C$10/1000/('Supuestos'!$C$11*'Supuestos'!$C$12*'Supuestos'!$C$15)))=0,0,'Supuestos'!$C$8/(IF('Supuestos'!$C$11*'Supuestos'!$C$12*'Supuestos'!$C$15=0,0,'Supuestos'!$C$10/1000/('Supuestos'!$C$11*'Supuestos'!$C$12*'Supuestos'!$C$15)))))*'Supuestos'!$C$20)*'Supuestos'!$C$25)+(((IF((IF('Supuestos'!$C$11*'Supuestos'!$C$12*'Supuestos'!$C$15=0,0,'Supuestos'!$C$10/1000/('Supuestos'!$C$11*'Supuestos'!$C$12*'Supuestos'!$C$15)))=0,0,'Supuestos'!$C$8/(IF('Supuestos'!$C$11*'Supuestos'!$C$12*'Supuestos'!$C$15=0,0,'Supuestos'!$C$10/1000/('Supuestos'!$C$11*'Supuestos'!$C$12*'Supuestos'!$C$15)))))*'Supuestos'!$C$21)*'Supuestos'!$C$26))*G$9)*'Supuestos'!$C$31)*'Supuestos'!$C$30))*('Supuestos'!$C$41+'Supuestos'!$C$42+'Supuestos'!$C$43))*(1-'Supuestos'!$C$34-'Supuestos'!$C$35-'Supuestos'!$C$36))-((IF((IF('Supuestos'!$C$11*'Supuestos'!$C$12*'Supuestos'!$C$15=0,0,'Supuestos'!$C$10/1000/('Supuestos'!$C$11*'Supuestos'!$C$12*'Supuestos'!$C$15)))=0,0,'Supuestos'!$C$8/(IF('Supuestos'!$C$11*'Supuestos'!$C$12*'Supuestos'!$C$15=0,0,'Supuestos'!$C$10/1000/('Supuestos'!$C$11*'Supuestos'!$C$12*'Supuestos'!$C$15)))))*'Supuestos'!$C$37)-'Supuestos'!$C$38-'Supuestos'!$C$8)
B11: 197 | C11: =((((((((((IF((IF('Supuestos'!$C$11*'Supuestos'!$C$12*'Supuestos'!$C$15=0,0,'Supuestos'!$C$10/1000/('Supuestos'!$C$11*'Supuestos'!$C$12*'Supuestos'!$C$15)))=0,0,'Supuestos'!$C$8/(IF('Supuestos'!$C$11*'Supuestos'!$C$12*'Supuestos'!$C$15=0,0,'Supuestos'!$C$10/1000/('Supuestos'!$C$11*'Supuestos'!$C$12*'Supuestos'!$C$15)))))*'Supuestos'!$C$20)*'Supuestos'!$C$25)+(((IF((IF('Supuestos'!$C$11*'Supuestos'!$C$12*'Supuestos'!$C$15=0,0,'Supuestos'!$C$10/1000/('Supuestos'!$C$11*'Supuestos'!$C$12*'Supuestos'!$C$15)))=0,0,'Supuestos'!$C$8/(IF('Supuestos'!$C$11*'Supuestos'!$C$12*'Supuestos'!$C$15=0,0,'Supuestos'!$C$10/1000/('Supuestos'!$C$11*'Supuestos'!$C$12*'Supuestos'!$C$15)))))*'Supuestos'!$C$21)*'Supuestos'!$C$26))*C$9)*$B11)+(((((((IF((IF('Supuestos'!$C$11*'Supuestos'!$C$12*'Supuestos'!$C$15=0,0,'Supuestos'!$C$10/1000/('Supuestos'!$C$11*'Supuestos'!$C$12*'Supuestos'!$C$15)))=0,0,'Supuestos'!$C$8/(IF('Supuestos'!$C$11*'Supuestos'!$C$12*'Supuestos'!$C$15=0,0,'Supuestos'!$C$10/1000/('Supuestos'!$C$11*'Supuestos'!$C$12*'Supuestos'!$C$15)))))*'Supuestos'!$C$20)*'Supuestos'!$C$25)+(((IF((IF('Supuestos'!$C$11*'Supuestos'!$C$12*'Supuestos'!$C$15=0,0,'Supuestos'!$C$10/1000/('Supuestos'!$C$11*'Supuestos'!$C$12*'Supuestos'!$C$15)))=0,0,'Supuestos'!$C$8/(IF('Supuestos'!$C$11*'Supuestos'!$C$12*'Supuestos'!$C$15=0,0,'Supuestos'!$C$10/1000/('Supuestos'!$C$11*'Supuestos'!$C$12*'Supuestos'!$C$15)))))*'Supuestos'!$C$21)*'Supuestos'!$C$26))*C$9)*'Supuestos'!$C$29)*'Supuestos'!$C$28)+(((((((IF((IF('Supuestos'!$C$11*'Supuestos'!$C$12*'Supuestos'!$C$15=0,0,'Supuestos'!$C$10/1000/('Supuestos'!$C$11*'Supuestos'!$C$12*'Supuestos'!$C$15)))=0,0,'Supuestos'!$C$8/(IF('Supuestos'!$C$11*'Supuestos'!$C$12*'Supuestos'!$C$15=0,0,'Supuestos'!$C$10/1000/('Supuestos'!$C$11*'Supuestos'!$C$12*'Supuestos'!$C$15)))))*'Supuestos'!$C$20)*'Supuestos'!$C$25)+(((IF((IF('Supuestos'!$C$11*'Supuestos'!$C$12*'Supuestos'!$C$15=0,0,'Supuestos'!$C$10/1000/('Supuestos'!$C$11*'Supuestos'!$C$12*'Supuestos'!$C$15)))=0,0,'Supuestos'!$C$8/(IF('Supuestos'!$C$11*'Supuestos'!$C$12*'Supuestos'!$C$15=0,0,'Supuestos'!$C$10/1000/('Supuestos'!$C$11*'Supuestos'!$C$12*'Supuestos'!$C$15)))))*'Supuestos'!$C$21)*'Supuestos'!$C$26))*C$9)*'Supuestos'!$C$31)*'Supuestos'!$C$30))*('Supuestos'!$C$41+'Supuestos'!$C$42+'Supuestos'!$C$43))*(1-'Supuestos'!$C$34-'Supuestos'!$C$35-'Supuestos'!$C$36))-((IF((IF('Supuestos'!$C$11*'Supuestos'!$C$12*'Supuestos'!$C$15=0,0,'Supuestos'!$C$10/1000/('Supuestos'!$C$11*'Supuestos'!$C$12*'Supuestos'!$C$15)))=0,0,'Supuestos'!$C$8/(IF('Supuestos'!$C$11*'Supuestos'!$C$12*'Supuestos'!$C$15=0,0,'Supuestos'!$C$10/1000/('Supuestos'!$C$11*'Supuestos'!$C$12*'Supuestos'!$C$15)))))*'Supuestos'!$C$37)-'Supuestos'!$C$38-'Supuestos'!$C$8) | D11: =((((((((((IF((IF('Supuestos'!$C$11*'Supuestos'!$C$12*'Supuestos'!$C$15=0,0,'Supuestos'!$C$10/1000/('Supuestos'!$C$11*'Supuestos'!$C$12*'Supuestos'!$C$15)))=0,0,'Supuestos'!$C$8/(IF('Supuestos'!$C$11*'Supuestos'!$C$12*'Supuestos'!$C$15=0,0,'Supuestos'!$C$10/1000/('Supuestos'!$C$11*'Supuestos'!$C$12*'Supuestos'!$C$15)))))*'Supuestos'!$C$20)*'Supuestos'!$C$25)+(((IF((IF('Supuestos'!$C$11*'Supuestos'!$C$12*'Supuestos'!$C$15=0,0,'Supuestos'!$C$10/1000/('Supuestos'!$C$11*'Supuestos'!$C$12*'Supuestos'!$C$15)))=0,0,'Supuestos'!$C$8/(IF('Supuestos'!$C$11*'Supuestos'!$C$12*'Supuestos'!$C$15=0,0,'Supuestos'!$C$10/1000/('Supuestos'!$C$11*'Supuestos'!$C$12*'Supuestos'!$C$15)))))*'Supuestos'!$C$21)*'Supuestos'!$C$26))*D$9)*$B11)+(((((((IF((IF('Supuestos'!$C$11*'Supuestos'!$C$12*'Supuestos'!$C$15=0,0,'Supuestos'!$C$10/1000/('Supuestos'!$C$11*'Supuestos'!$C$12*'Supuestos'!$C$15)))=0,0,'Supuestos'!$C$8/(IF('Supuestos'!$C$11*'Supuestos'!$C$12*'Supuestos'!$C$15=0,0,'Supuestos'!$C$10/1000/('Supuestos'!$C$11*'Supuestos'!$C$12*'Supuestos'!$C$15)))))*'Supuestos'!$C$20)*'Supuestos'!$C$25)+(((IF((IF('Supuestos'!$C$11*'Supuestos'!$C$12*'Supuestos'!$C$15=0,0,'Supuestos'!$C$10/1000/('Supuestos'!$C$11*'Supuestos'!$C$12*'Supuestos'!$C$15)))=0,0,'Supuestos'!$C$8/(IF('Supuestos'!$C$11*'Supuestos'!$C$12*'Supuestos'!$C$15=0,0,'Supuestos'!$C$10/1000/('Supuestos'!$C$11*'Supuestos'!$C$12*'Supuestos'!$C$15)))))*'Supuestos'!$C$21)*'Supuestos'!$C$26))*D$9)*'Supuestos'!$C$29)*'Supuestos'!$C$28)+(((((((IF((IF('Supuestos'!$C$11*'Supuestos'!$C$12*'Supuestos'!$C$15=0,0,'Supuestos'!$C$10/1000/('Supuestos'!$C$11*'Supuestos'!$C$12*'Supuestos'!$C$15)))=0,0,'Supuestos'!$C$8/(IF('Supuestos'!$C$11*'Supuestos'!$C$12*'Supuestos'!$C$15=0,0,'Supuestos'!$C$10/1000/('Supuestos'!$C$11*'Supuestos'!$C$12*'Supuestos'!$C$15)))))*'Supuestos'!$C$20)*'Supuestos'!$C$25)+(((IF((IF('Supuestos'!$C$11*'Supuestos'!$C$12*'Supuestos'!$C$15=0,0,'Supuestos'!$C$10/1000/('Supuestos'!$C$11*'Supuestos'!$C$12*'Supuestos'!$C$15)))=0,0,'Supuestos'!$C$8/(IF('Supuestos'!$C$11*'Supuestos'!$C$12*'Supuestos'!$C$15=0,0,'Supuestos'!$C$10/1000/('Supuestos'!$C$11*'Supuestos'!$C$12*'Supuestos'!$C$15)))))*'Supuestos'!$C$21)*'Supuestos'!$C$26))*D$9)*'Supuestos'!$C$31)*'Supuestos'!$C$30))*('Supuestos'!$C$41+'Supuestos'!$C$42+'Supuestos'!$C$43))*(1-'Supuestos'!$C$34-'Supuestos'!$C$35-'Supuestos'!$C$36))-((IF((IF('Supuestos'!$C$11*'Supuestos'!$C$12*'Supuestos'!$C$15=0,0,'Supuestos'!$C$10/1000/('Supuestos'!$C$11*'Supuestos'!$C$12*'Supuestos'!$C$15)))=0,0,'Supuestos'!$C$8/(IF('Supuestos'!$C$11*'Supuestos'!$C$12*'Supuestos'!$C$15=0,0,'Supuestos'!$C$10/1000/('Supuestos'!$C$11*'Supuestos'!$C$12*'Supuestos'!$C$15)))))*'Supuestos'!$C$37)-'Supuestos'!$C$38-'Supuestos'!$C$8) | E11: =((((((((((IF((IF('Supuestos'!$C$11*'Supuestos'!$C$12*'Supuestos'!$C$15=0,0,'Supuestos'!$C$10/1000/('Supuestos'!$C$11*'Supuestos'!$C$12*'Supuestos'!$C$15)))=0,0,'Supuestos'!$C$8/(IF('Supuestos'!$C$11*'Supuestos'!$C$12*'Supuestos'!$C$15=0,0,'Supuestos'!$C$10/1000/('Supuestos'!$C$11*'Supuestos'!$C$12*'Supuestos'!$C$15)))))*'Supuestos'!$C$20)*'Supuestos'!$C$25)+(((IF((IF('Supuestos'!$C$11*'Supuestos'!$C$12*'Supuestos'!$C$15=0,0,'Supuestos'!$C$10/1000/('Supuestos'!$C$11*'Supuestos'!$C$12*'Supuestos'!$C$15)))=0,0,'Supuestos'!$C$8/(IF('Supuestos'!$C$11*'Supuestos'!$C$12*'Supuestos'!$C$15=0,0,'Supuestos'!$C$10/1000/('Supuestos'!$C$11*'Supuestos'!$C$12*'Supuestos'!$C$15)))))*'Supuestos'!$C$21)*'Supuestos'!$C$26))*E$9)*$B11)+(((((((IF((IF('Supuestos'!$C$11*'Supuestos'!$C$12*'Supuestos'!$C$15=0,0,'Supuestos'!$C$10/1000/('Supuestos'!$C$11*'Supuestos'!$C$12*'Supuestos'!$C$15)))=0,0,'Supuestos'!$C$8/(IF('Supuestos'!$C$11*'Supuestos'!$C$12*'Supuestos'!$C$15=0,0,'Supuestos'!$C$10/1000/('Supuestos'!$C$11*'Supuestos'!$C$12*'Supuestos'!$C$15)))))*'Supuestos'!$C$20)*'Supuestos'!$C$25)+(((IF((IF('Supuestos'!$C$11*'Supuestos'!$C$12*'Supuestos'!$C$15=0,0,'Supuestos'!$C$10/1000/('Supuestos'!$C$11*'Supuestos'!$C$12*'Supuestos'!$C$15)))=0,0,'Supuestos'!$C$8/(IF('Supuestos'!$C$11*'Supuestos'!$C$12*'Supuestos'!$C$15=0,0,'Supuestos'!$C$10/1000/('Supuestos'!$C$11*'Supuestos'!$C$12*'Supuestos'!$C$15)))))*'Supuestos'!$C$21)*'Supuestos'!$C$26))*E$9)*'Supuestos'!$C$29)*'Supuestos'!$C$28)+(((((((IF((IF('Supuestos'!$C$11*'Supuestos'!$C$12*'Supuestos'!$C$15=0,0,'Supuestos'!$C$10/1000/('Supuestos'!$C$11*'Supuestos'!$C$12*'Supuestos'!$C$15)))=0,0,'Supuestos'!$C$8/(IF('Supuestos'!$C$11*'Supuestos'!$C$12*'Supuestos'!$C$15=0,0,'Supuestos'!$C$10/1000/('Supuestos'!$C$11*'Supuestos'!$C$12*'Supuestos'!$C$15)))))*'Supuestos'!$C$20)*'Supuestos'!$C$25)+(((IF((IF('Supuestos'!$C$11*'Supuestos'!$C$12*'Supuestos'!$C$15=0,0,'Supuestos'!$C$10/1000/('Supuestos'!$C$11*'Supuestos'!$C$12*'Supuestos'!$C$15)))=0,0,'Supuestos'!$C$8/(IF('Supuestos'!$C$11*'Supuestos'!$C$12*'Supuestos'!$C$15=0,0,'Supuestos'!$C$10/1000/('Supuestos'!$C$11*'Supuestos'!$C$12*'Supuestos'!$C$15)))))*'Supuestos'!$C$21)*'Supuestos'!$C$26))*E$9)*'Supuestos'!$C$31)*'Supuestos'!$C$30))*('Supuestos'!$C$41+'Supuestos'!$C$42+'Supuestos'!$C$43))*(1-'Supuestos'!$C$34-'Supuestos'!$C$35-'Supuestos'!$C$36))-((IF((IF('Supuestos'!$C$11*'Supuestos'!$C$12*'Supuestos'!$C$15=0,0,'Supuestos'!$C$10/1000/('Supuestos'!$C$11*'Supuestos'!$C$12*'Supuestos'!$C$15)))=0,0,'Supuestos'!$C$8/(IF('Supuestos'!$C$11*'Supuestos'!$C$12*'Supuestos'!$C$15=0,0,'Supuestos'!$C$10/1000/('Supuestos'!$C$11*'Supuestos'!$C$12*'Supuestos'!$C$15)))))*'Supuestos'!$C$37)-'Supuestos'!$C$38-'Supuestos'!$C$8) | F11: =((((((((((IF((IF('Supuestos'!$C$11*'Supuestos'!$C$12*'Supuestos'!$C$15=0,0,'Supuestos'!$C$10/1000/('Supuestos'!$C$11*'Supuestos'!$C$12*'Supuestos'!$C$15)))=0,0,'Supuestos'!$C$8/(IF('Supuestos'!$C$11*'Supuestos'!$C$12*'Supuestos'!$C$15=0,0,'Supuestos'!$C$10/1000/('Supuestos'!$C$11*'Supuestos'!$C$12*'Supuestos'!$C$15)))))*'Supuestos'!$C$20)*'Supuestos'!$C$25)+(((IF((IF('Supuestos'!$C$11*'Supuestos'!$C$12*'Supuestos'!$C$15=0,0,'Supuestos'!$C$10/1000/('Supuestos'!$C$11*'Supuestos'!$C$12*'Supuestos'!$C$15)))=0,0,'Supuestos'!$C$8/(IF('Supuestos'!$C$11*'Supuestos'!$C$12*'Supuestos'!$C$15=0,0,'Supuestos'!$C$10/1000/('Supuestos'!$C$11*'Supuestos'!$C$12*'Supuestos'!$C$15)))))*'Supuestos'!$C$21)*'Supuestos'!$C$26))*F$9)*$B11)+(((((((IF((IF('Supuestos'!$C$11*'Supuestos'!$C$12*'Supuestos'!$C$15=0,0,'Supuestos'!$C$10/1000/('Supuestos'!$C$11*'Supuestos'!$C$12*'Supuestos'!$C$15)))=0,0,'Supuestos'!$C$8/(IF('Supuestos'!$C$11*'Supuestos'!$C$12*'Supuestos'!$C$15=0,0,'Supuestos'!$C$10/1000/('Supuestos'!$C$11*'Supuestos'!$C$12*'Supuestos'!$C$15)))))*'Supuestos'!$C$20)*'Supuestos'!$C$25)+(((IF((IF('Supuestos'!$C$11*'Supuestos'!$C$12*'Supuestos'!$C$15=0,0,'Supuestos'!$C$10/1000/('Supuestos'!$C$11*'Supuestos'!$C$12*'Supuestos'!$C$15)))=0,0,'Supuestos'!$C$8/(IF('Supuestos'!$C$11*'Supuestos'!$C$12*'Supuestos'!$C$15=0,0,'Supuestos'!$C$10/1000/('Supuestos'!$C$11*'Supuestos'!$C$12*'Supuestos'!$C$15)))))*'Supuestos'!$C$21)*'Supuestos'!$C$26))*F$9)*'Supuestos'!$C$29)*'Supuestos'!$C$28)+(((((((IF((IF('Supuestos'!$C$11*'Supuestos'!$C$12*'Supuestos'!$C$15=0,0,'Supuestos'!$C$10/1000/('Supuestos'!$C$11*'Supuestos'!$C$12*'Supuestos'!$C$15)))=0,0,'Supuestos'!$C$8/(IF('Supuestos'!$C$11*'Supuestos'!$C$12*'Supuestos'!$C$15=0,0,'Supuestos'!$C$10/1000/('Supuestos'!$C$11*'Supuestos'!$C$12*'Supuestos'!$C$15)))))*'Supuestos'!$C$20)*'Supuestos'!$C$25)+(((IF((IF('Supuestos'!$C$11*'Supuestos'!$C$12*'Supuestos'!$C$15=0,0,'Supuestos'!$C$10/1000/('Supuestos'!$C$11*'Supuestos'!$C$12*'Supuestos'!$C$15)))=0,0,'Supuestos'!$C$8/(IF('Supuestos'!$C$11*'Supuestos'!$C$12*'Supuestos'!$C$15=0,0,'Supuestos'!$C$10/1000/('Supuestos'!$C$11*'Supuestos'!$C$12*'Supuestos'!$C$15)))))*'Supuestos'!$C$21)*'Supuestos'!$C$26))*F$9)*'Supuestos'!$C$31)*'Supuestos'!$C$30))*('Supuestos'!$C$41+'Supuestos'!$C$42+'Supuestos'!$C$43))*(1-'Supuestos'!$C$34-'Supuestos'!$C$35-'Supuestos'!$C$36))-((IF((IF('Supuestos'!$C$11*'Supuestos'!$C$12*'Supuestos'!$C$15=0,0,'Supuestos'!$C$10/1000/('Supuestos'!$C$11*'Supuestos'!$C$12*'Supuestos'!$C$15)))=0,0,'Supuestos'!$C$8/(IF('Supuestos'!$C$11*'Supuestos'!$C$12*'Supuestos'!$C$15=0,0,'Supuestos'!$C$10/1000/('Supuestos'!$C$11*'Supuestos'!$C$12*'Supuestos'!$C$15)))))*'Supuestos'!$C$37)-'Supuestos'!$C$38-'Supuestos'!$C$8) | G11: =((((((((((IF((IF('Supuestos'!$C$11*'Supuestos'!$C$12*'Supuestos'!$C$15=0,0,'Supuestos'!$C$10/1000/('Supuestos'!$C$11*'Supuestos'!$C$12*'Supuestos'!$C$15)))=0,0,'Supuestos'!$C$8/(IF('Supuestos'!$C$11*'Supuestos'!$C$12*'Supuestos'!$C$15=0,0,'Supuestos'!$C$10/1000/('Supuestos'!$C$11*'Supuestos'!$C$12*'Supuestos'!$C$15)))))*'Supuestos'!$C$20)*'Supuestos'!$C$25)+(((IF((IF('Supuestos'!$C$11*'Supuestos'!$C$12*'Supuestos'!$C$15=0,0,'Supuestos'!$C$10/1000/('Supuestos'!$C$11*'Supuestos'!$C$12*'Supuestos'!$C$15)))=0,0,'Supuestos'!$C$8/(IF('Supuestos'!$C$11*'Supuestos'!$C$12*'Supuestos'!$C$15=0,0,'Supuestos'!$C$10/1000/('Supuestos'!$C$11*'Supuestos'!$C$12*'Supuestos'!$C$15)))))*'Supuestos'!$C$21)*'Supuestos'!$C$26))*G$9)*$B11)+(((((((IF((IF('Supuestos'!$C$11*'Supuestos'!$C$12*'Supuestos'!$C$15=0,0,'Supuestos'!$C$10/1000/('Supuestos'!$C$11*'Supuestos'!$C$12*'Supuestos'!$C$15)))=0,0,'Supuestos'!$C$8/(IF('Supuestos'!$C$11*'Supuestos'!$C$12*'Supuestos'!$C$15=0,0,'Supuestos'!$C$10/1000/('Supuestos'!$C$11*'Supuestos'!$C$12*'Supuestos'!$C$15)))))*'Supuestos'!$C$20)*'Supuestos'!$C$25)+(((IF((IF('Supuestos'!$C$11*'Supuestos'!$C$12*'Supuestos'!$C$15=0,0,'Supuestos'!$C$10/1000/('Supuestos'!$C$11*'Supuestos'!$C$12*'Supuestos'!$C$15)))=0,0,'Supuestos'!$C$8/(IF('Supuestos'!$C$11*'Supuestos'!$C$12*'Supuestos'!$C$15=0,0,'Supuestos'!$C$10/1000/('Supuestos'!$C$11*'Supuestos'!$C$12*'Supuestos'!$C$15)))))*'Supuestos'!$C$21)*'Supuestos'!$C$26))*G$9)*'Supuestos'!$C$29)*'Supuestos'!$C$28)+(((((((IF((IF('Supuestos'!$C$11*'Supuestos'!$C$12*'Supuestos'!$C$15=0,0,'Supuestos'!$C$10/1000/('Supuestos'!$C$11*'Supuestos'!$C$12*'Supuestos'!$C$15)))=0,0,'Supuestos'!$C$8/(IF('Supuestos'!$C$11*'Supuestos'!$C$12*'Supuestos'!$C$15=0,0,'Supuestos'!$C$10/1000/('Supuestos'!$C$11*'Supuestos'!$C$12*'Supuestos'!$C$15)))))*'Supuestos'!$C$20)*'Supuestos'!$C$25)+(((IF((IF('Supuestos'!$C$11*'Supuestos'!$C$12*'Supuestos'!$C$15=0,0,'Supuestos'!$C$10/1000/('Supuestos'!$C$11*'Supuestos'!$C$12*'Supuestos'!$C$15)))=0,0,'Supuestos'!$C$8/(IF('Supuestos'!$C$11*'Supuestos'!$C$12*'Supuestos'!$C$15=0,0,'Supuestos'!$C$10/1000/('Supuestos'!$C$11*'Supuestos'!$C$12*'Supuestos'!$C$15)))))*'Supuestos'!$C$21)*'Supuestos'!$C$26))*G$9)*'Supuestos'!$C$31)*'Supuestos'!$C$30))*('Supuestos'!$C$41+'Supuestos'!$C$42+'Supuestos'!$C$43))*(1-'Supuestos'!$C$34-'Supuestos'!$C$35-'Supuestos'!$C$36))-((IF((IF('Supuestos'!$C$11*'Supuestos'!$C$12*'Supuestos'!$C$15=0,0,'Supuestos'!$C$10/1000/('Supuestos'!$C$11*'Supuestos'!$C$12*'Supuestos'!$C$15)))=0,0,'Supuestos'!$C$8/(IF('Supuestos'!$C$11*'Supuestos'!$C$12*'Supuestos'!$C$15=0,0,'Supuestos'!$C$10/1000/('Supuestos'!$C$11*'Supuestos'!$C$12*'Supuestos'!$C$15)))))*'Supuestos'!$C$37)-'Supuestos'!$C$38-'Supuestos'!$C$8)
B12: 297 | C12: =((((((((((IF((IF('Supuestos'!$C$11*'Supuestos'!$C$12*'Supuestos'!$C$15=0,0,'Supuestos'!$C$10/1000/('Supuestos'!$C$11*'Supuestos'!$C$12*'Supuestos'!$C$15)))=0,0,'Supuestos'!$C$8/(IF('Supuestos'!$C$11*'Supuestos'!$C$12*'Supuestos'!$C$15=0,0,'Supuestos'!$C$10/1000/('Supuestos'!$C$11*'Supuestos'!$C$12*'Supuestos'!$C$15)))))*'Supuestos'!$C$20)*'Supuestos'!$C$25)+(((IF((IF('Supuestos'!$C$11*'Supuestos'!$C$12*'Supuestos'!$C$15=0,0,'Supuestos'!$C$10/1000/('Supuestos'!$C$11*'Supuestos'!$C$12*'Supuestos'!$C$15)))=0,0,'Supuestos'!$C$8/(IF('Supuestos'!$C$11*'Supuestos'!$C$12*'Supuestos'!$C$15=0,0,'Supuestos'!$C$10/1000/('Supuestos'!$C$11*'Supuestos'!$C$12*'Supuestos'!$C$15)))))*'Supuestos'!$C$21)*'Supuestos'!$C$26))*C$9)*$B12)+(((((((IF((IF('Supuestos'!$C$11*'Supuestos'!$C$12*'Supuestos'!$C$15=0,0,'Supuestos'!$C$10/1000/('Supuestos'!$C$11*'Supuestos'!$C$12*'Supuestos'!$C$15)))=0,0,'Supuestos'!$C$8/(IF('Supuestos'!$C$11*'Supuestos'!$C$12*'Supuestos'!$C$15=0,0,'Supuestos'!$C$10/1000/('Supuestos'!$C$11*'Supuestos'!$C$12*'Supuestos'!$C$15)))))*'Supuestos'!$C$20)*'Supuestos'!$C$25)+(((IF((IF('Supuestos'!$C$11*'Supuestos'!$C$12*'Supuestos'!$C$15=0,0,'Supuestos'!$C$10/1000/('Supuestos'!$C$11*'Supuestos'!$C$12*'Supuestos'!$C$15)))=0,0,'Supuestos'!$C$8/(IF('Supuestos'!$C$11*'Supuestos'!$C$12*'Supuestos'!$C$15=0,0,'Supuestos'!$C$10/1000/('Supuestos'!$C$11*'Supuestos'!$C$12*'Supuestos'!$C$15)))))*'Supuestos'!$C$21)*'Supuestos'!$C$26))*C$9)*'Supuestos'!$C$29)*'Supuestos'!$C$28)+(((((((IF((IF('Supuestos'!$C$11*'Supuestos'!$C$12*'Supuestos'!$C$15=0,0,'Supuestos'!$C$10/1000/('Supuestos'!$C$11*'Supuestos'!$C$12*'Supuestos'!$C$15)))=0,0,'Supuestos'!$C$8/(IF('Supuestos'!$C$11*'Supuestos'!$C$12*'Supuestos'!$C$15=0,0,'Supuestos'!$C$10/1000/('Supuestos'!$C$11*'Supuestos'!$C$12*'Supuestos'!$C$15)))))*'Supuestos'!$C$20)*'Supuestos'!$C$25)+(((IF((IF('Supuestos'!$C$11*'Supuestos'!$C$12*'Supuestos'!$C$15=0,0,'Supuestos'!$C$10/1000/('Supuestos'!$C$11*'Supuestos'!$C$12*'Supuestos'!$C$15)))=0,0,'Supuestos'!$C$8/(IF('Supuestos'!$C$11*'Supuestos'!$C$12*'Supuestos'!$C$15=0,0,'Supuestos'!$C$10/1000/('Supuestos'!$C$11*'Supuestos'!$C$12*'Supuestos'!$C$15)))))*'Supuestos'!$C$21)*'Supuestos'!$C$26))*C$9)*'Supuestos'!$C$31)*'Supuestos'!$C$30))*('Supuestos'!$C$41+'Supuestos'!$C$42+'Supuestos'!$C$43))*(1-'Supuestos'!$C$34-'Supuestos'!$C$35-'Supuestos'!$C$36))-((IF((IF('Supuestos'!$C$11*'Supuestos'!$C$12*'Supuestos'!$C$15=0,0,'Supuestos'!$C$10/1000/('Supuestos'!$C$11*'Supuestos'!$C$12*'Supuestos'!$C$15)))=0,0,'Supuestos'!$C$8/(IF('Supuestos'!$C$11*'Supuestos'!$C$12*'Supuestos'!$C$15=0,0,'Supuestos'!$C$10/1000/('Supuestos'!$C$11*'Supuestos'!$C$12*'Supuestos'!$C$15)))))*'Supuestos'!$C$37)-'Supuestos'!$C$38-'Supuestos'!$C$8) | D12: =((((((((((IF((IF('Supuestos'!$C$11*'Supuestos'!$C$12*'Supuestos'!$C$15=0,0,'Supuestos'!$C$10/1000/('Supuestos'!$C$11*'Supuestos'!$C$12*'Supuestos'!$C$15)))=0,0,'Supuestos'!$C$8/(IF('Supuestos'!$C$11*'Supuestos'!$C$12*'Supuestos'!$C$15=0,0,'Supuestos'!$C$10/1000/('Supuestos'!$C$11*'Supuestos'!$C$12*'Supuestos'!$C$15)))))*'Supuestos'!$C$20)*'Supuestos'!$C$25)+(((IF((IF('Supuestos'!$C$11*'Supuestos'!$C$12*'Supuestos'!$C$15=0,0,'Supuestos'!$C$10/1000/('Supuestos'!$C$11*'Supuestos'!$C$12*'Supuestos'!$C$15)))=0,0,'Supuestos'!$C$8/(IF('Supuestos'!$C$11*'Supuestos'!$C$12*'Supuestos'!$C$15=0,0,'Supuestos'!$C$10/1000/('Supuestos'!$C$11*'Supuestos'!$C$12*'Supuestos'!$C$15)))))*'Supuestos'!$C$21)*'Supuestos'!$C$26))*D$9)*$B12)+(((((((IF((IF('Supuestos'!$C$11*'Supuestos'!$C$12*'Supuestos'!$C$15=0,0,'Supuestos'!$C$10/1000/('Supuestos'!$C$11*'Supuestos'!$C$12*'Supuestos'!$C$15)))=0,0,'Supuestos'!$C$8/(IF('Supuestos'!$C$11*'Supuestos'!$C$12*'Supuestos'!$C$15=0,0,'Supuestos'!$C$10/1000/('Supuestos'!$C$11*'Supuestos'!$C$12*'Supuestos'!$C$15)))))*'Supuestos'!$C$20)*'Supuestos'!$C$25)+(((IF((IF('Supuestos'!$C$11*'Supuestos'!$C$12*'Supuestos'!$C$15=0,0,'Supuestos'!$C$10/1000/('Supuestos'!$C$11*'Supuestos'!$C$12*'Supuestos'!$C$15)))=0,0,'Supuestos'!$C$8/(IF('Supuestos'!$C$11*'Supuestos'!$C$12*'Supuestos'!$C$15=0,0,'Supuestos'!$C$10/1000/('Supuestos'!$C$11*'Supuestos'!$C$12*'Supuestos'!$C$15)))))*'Supuestos'!$C$21)*'Supuestos'!$C$26))*D$9)*'Supuestos'!$C$29)*'Supuestos'!$C$28)+(((((((IF((IF('Supuestos'!$C$11*'Supuestos'!$C$12*'Supuestos'!$C$15=0,0,'Supuestos'!$C$10/1000/('Supuestos'!$C$11*'Supuestos'!$C$12*'Supuestos'!$C$15)))=0,0,'Supuestos'!$C$8/(IF('Supuestos'!$C$11*'Supuestos'!$C$12*'Supuestos'!$C$15=0,0,'Supuestos'!$C$10/1000/('Supuestos'!$C$11*'Supuestos'!$C$12*'Supuestos'!$C$15)))))*'Supuestos'!$C$20)*'Supuestos'!$C$25)+(((IF((IF('Supuestos'!$C$11*'Supuestos'!$C$12*'Supuestos'!$C$15=0,0,'Supuestos'!$C$10/1000/('Supuestos'!$C$11*'Supuestos'!$C$12*'Supuestos'!$C$15)))=0,0,'Supuestos'!$C$8/(IF('Supuestos'!$C$11*'Supuestos'!$C$12*'Supuestos'!$C$15=0,0,'Supuestos'!$C$10/1000/('Supuestos'!$C$11*'Supuestos'!$C$12*'Supuestos'!$C$15)))))*'Supuestos'!$C$21)*'Supuestos'!$C$26))*D$9)*'Supuestos'!$C$31)*'Supuestos'!$C$30))*('Supuestos'!$C$41+'Supuestos'!$C$42+'Supuestos'!$C$43))*(1-'Supuestos'!$C$34-'Supuestos'!$C$35-'Supuestos'!$C$36))-((IF((IF('Supuestos'!$C$11*'Supuestos'!$C$12*'Supuestos'!$C$15=0,0,'Supuestos'!$C$10/1000/('Supuestos'!$C$11*'Supuestos'!$C$12*'Supuestos'!$C$15)))=0,0,'Supuestos'!$C$8/(IF('Supuestos'!$C$11*'Supuestos'!$C$12*'Supuestos'!$C$15=0,0,'Supuestos'!$C$10/1000/('Supuestos'!$C$11*'Supuestos'!$C$12*'Supuestos'!$C$15)))))*'Supuestos'!$C$37)-'Supuestos'!$C$38-'Supuestos'!$C$8) | E12: =((((((((((IF((IF('Supuestos'!$C$11*'Supuestos'!$C$12*'Supuestos'!$C$15=0,0,'Supuestos'!$C$10/1000/('Supuestos'!$C$11*'Supuestos'!$C$12*'Supuestos'!$C$15)))=0,0,'Supuestos'!$C$8/(IF('Supuestos'!$C$11*'Supuestos'!$C$12*'Supuestos'!$C$15=0,0,'Supuestos'!$C$10/1000/('Supuestos'!$C$11*'Supuestos'!$C$12*'Supuestos'!$C$15)))))*'Supuestos'!$C$20)*'Supuestos'!$C$25)+(((IF((IF('Supuestos'!$C$11*'Supuestos'!$C$12*'Supuestos'!$C$15=0,0,'Supuestos'!$C$10/1000/('Supuestos'!$C$11*'Supuestos'!$C$12*'Supuestos'!$C$15)))=0,0,'Supuestos'!$C$8/(IF('Supuestos'!$C$11*'Supuestos'!$C$12*'Supuestos'!$C$15=0,0,'Supuestos'!$C$10/1000/('Supuestos'!$C$11*'Supuestos'!$C$12*'Supuestos'!$C$15)))))*'Supuestos'!$C$21)*'Supuestos'!$C$26))*E$9)*$B12)+(((((((IF((IF('Supuestos'!$C$11*'Supuestos'!$C$12*'Supuestos'!$C$15=0,0,'Supuestos'!$C$10/1000/('Supuestos'!$C$11*'Supuestos'!$C$12*'Supuestos'!$C$15)))=0,0,'Supuestos'!$C$8/(IF('Supuestos'!$C$11*'Supuestos'!$C$12*'Supuestos'!$C$15=0,0,'Supuestos'!$C$10/1000/('Supuestos'!$C$11*'Supuestos'!$C$12*'Supuestos'!$C$15)))))*'Supuestos'!$C$20)*'Supuestos'!$C$25)+(((IF((IF('Supuestos'!$C$11*'Supuestos'!$C$12*'Supuestos'!$C$15=0,0,'Supuestos'!$C$10/1000/('Supuestos'!$C$11*'Supuestos'!$C$12*'Supuestos'!$C$15)))=0,0,'Supuestos'!$C$8/(IF('Supuestos'!$C$11*'Supuestos'!$C$12*'Supuestos'!$C$15=0,0,'Supuestos'!$C$10/1000/('Supuestos'!$C$11*'Supuestos'!$C$12*'Supuestos'!$C$15)))))*'Supuestos'!$C$21)*'Supuestos'!$C$26))*E$9)*'Supuestos'!$C$29)*'Supuestos'!$C$28)+(((((((IF((IF('Supuestos'!$C$11*'Supuestos'!$C$12*'Supuestos'!$C$15=0,0,'Supuestos'!$C$10/1000/('Supuestos'!$C$11*'Supuestos'!$C$12*'Supuestos'!$C$15)))=0,0,'Supuestos'!$C$8/(IF('Supuestos'!$C$11*'Supuestos'!$C$12*'Supuestos'!$C$15=0,0,'Supuestos'!$C$10/1000/('Supuestos'!$C$11*'Supuestos'!$C$12*'Supuestos'!$C$15)))))*'Supuestos'!$C$20)*'Supuestos'!$C$25)+(((IF((IF('Supuestos'!$C$11*'Supuestos'!$C$12*'Supuestos'!$C$15=0,0,'Supuestos'!$C$10/1000/('Supuestos'!$C$11*'Supuestos'!$C$12*'Supuestos'!$C$15)))=0,0,'Supuestos'!$C$8/(IF('Supuestos'!$C$11*'Supuestos'!$C$12*'Supuestos'!$C$15=0,0,'Supuestos'!$C$10/1000/('Supuestos'!$C$11*'Supuestos'!$C$12*'Supuestos'!$C$15)))))*'Supuestos'!$C$21)*'Supuestos'!$C$26))*E$9)*'Supuestos'!$C$31)*'Supuestos'!$C$30))*('Supuestos'!$C$41+'Supuestos'!$C$42+'Supuestos'!$C$43))*(1-'Supuestos'!$C$34-'Supuestos'!$C$35-'Supuestos'!$C$36))-((IF((IF('Supuestos'!$C$11*'Supuestos'!$C$12*'Supuestos'!$C$15=0,0,'Supuestos'!$C$10/1000/('Supuestos'!$C$11*'Supuestos'!$C$12*'Supuestos'!$C$15)))=0,0,'Supuestos'!$C$8/(IF('Supuestos'!$C$11*'Supuestos'!$C$12*'Supuestos'!$C$15=0,0,'Supuestos'!$C$10/1000/('Supuestos'!$C$11*'Supuestos'!$C$12*'Supuestos'!$C$15)))))*'Supuestos'!$C$37)-'Supuestos'!$C$38-'Supuestos'!$C$8) | F12: =((((((((((IF((IF('Supuestos'!$C$11*'Supuestos'!$C$12*'Supuestos'!$C$15=0,0,'Supuestos'!$C$10/1000/('Supuestos'!$C$11*'Supuestos'!$C$12*'Supuestos'!$C$15)))=0,0,'Supuestos'!$C$8/(IF('Supuestos'!$C$11*'Supuestos'!$C$12*'Supuestos'!$C$15=0,0,'Supuestos'!$C$10/1000/('Supuestos'!$C$11*'Supuestos'!$C$12*'Supuestos'!$C$15)))))*'Supuestos'!$C$20)*'Supuestos'!$C$25)+(((IF((IF('Supuestos'!$C$11*'Supuestos'!$C$12*'Supuestos'!$C$15=0,0,'Supuestos'!$C$10/1000/('Supuestos'!$C$11*'Supuestos'!$C$12*'Supuestos'!$C$15)))=0,0,'Supuestos'!$C$8/(IF('Supuestos'!$C$11*'Supuestos'!$C$12*'Supuestos'!$C$15=0,0,'Supuestos'!$C$10/1000/('Supuestos'!$C$11*'Supuestos'!$C$12*'Supuestos'!$C$15)))))*'Supuestos'!$C$21)*'Supuestos'!$C$26))*F$9)*$B12)+(((((((IF((IF('Supuestos'!$C$11*'Supuestos'!$C$12*'Supuestos'!$C$15=0,0,'Supuestos'!$C$10/1000/('Supuestos'!$C$11*'Supuestos'!$C$12*'Supuestos'!$C$15)))=0,0,'Supuestos'!$C$8/(IF('Supuestos'!$C$11*'Supuestos'!$C$12*'Supuestos'!$C$15=0,0,'Supuestos'!$C$10/1000/('Supuestos'!$C$11*'Supuestos'!$C$12*'Supuestos'!$C$15)))))*'Supuestos'!$C$20)*'Supuestos'!$C$25)+(((IF((IF('Supuestos'!$C$11*'Supuestos'!$C$12*'Supuestos'!$C$15=0,0,'Supuestos'!$C$10/1000/('Supuestos'!$C$11*'Supuestos'!$C$12*'Supuestos'!$C$15)))=0,0,'Supuestos'!$C$8/(IF('Supuestos'!$C$11*'Supuestos'!$C$12*'Supuestos'!$C$15=0,0,'Supuestos'!$C$10/1000/('Supuestos'!$C$11*'Supuestos'!$C$12*'Supuestos'!$C$15)))))*'Supuestos'!$C$21)*'Supuestos'!$C$26))*F$9)*'Supuestos'!$C$29)*'Supuestos'!$C$28)+(((((((IF((IF('Supuestos'!$C$11*'Supuestos'!$C$12*'Supuestos'!$C$15=0,0,'Supuestos'!$C$10/1000/('Supuestos'!$C$11*'Supuestos'!$C$12*'Supuestos'!$C$15)))=0,0,'Supuestos'!$C$8/(IF('Supuestos'!$C$11*'Supuestos'!$C$12*'Supuestos'!$C$15=0,0,'Supuestos'!$C$10/1000/('Supuestos'!$C$11*'Supuestos'!$C$12*'Supuestos'!$C$15)))))*'Supuestos'!$C$20)*'Supuestos'!$C$25)+(((IF((IF('Supuestos'!$C$11*'Supuestos'!$C$12*'Supuestos'!$C$15=0,0,'Supuestos'!$C$10/1000/('Supuestos'!$C$11*'Supuestos'!$C$12*'Supuestos'!$C$15)))=0,0,'Supuestos'!$C$8/(IF('Supuestos'!$C$11*'Supuestos'!$C$12*'Supuestos'!$C$15=0,0,'Supuestos'!$C$10/1000/('Supuestos'!$C$11*'Supuestos'!$C$12*'Supuestos'!$C$15)))))*'Supuestos'!$C$21)*'Supuestos'!$C$26))*F$9)*'Supuestos'!$C$31)*'Supuestos'!$C$30))*('Supuestos'!$C$41+'Supuestos'!$C$42+'Supuestos'!$C$43))*(1-'Supuestos'!$C$34-'Supuestos'!$C$35-'Supuestos'!$C$36))-((IF((IF('Supuestos'!$C$11*'Supuestos'!$C$12*'Supuestos'!$C$15=0,0,'Supuestos'!$C$10/1000/('Supuestos'!$C$11*'Supuestos'!$C$12*'Supuestos'!$C$15)))=0,0,'Supuestos'!$C$8/(IF('Supuestos'!$C$11*'Supuestos'!$C$12*'Supuestos'!$C$15=0,0,'Supuestos'!$C$10/1000/('Supuestos'!$C$11*'Supuestos'!$C$12*'Supuestos'!$C$15)))))*'Supuestos'!$C$37)-'Supuestos'!$C$38-'Supuestos'!$C$8) | G12: =((((((((((IF((IF('Supuestos'!$C$11*'Supuestos'!$C$12*'Supuestos'!$C$15=0,0,'Supuestos'!$C$10/1000/('Supuestos'!$C$11*'Supuestos'!$C$12*'Supuestos'!$C$15)))=0,0,'Supuestos'!$C$8/(IF('Supuestos'!$C$11*'Supuestos'!$C$12*'Supuestos'!$C$15=0,0,'Supuestos'!$C$10/1000/('Supuestos'!$C$11*'Supuestos'!$C$12*'Supuestos'!$C$15)))))*'Supuestos'!$C$20)*'Supuestos'!$C$25)+(((IF((IF('Supuestos'!$C$11*'Supuestos'!$C$12*'Supuestos'!$C$15=0,0,'Supuestos'!$C$10/1000/('Supuestos'!$C$11*'Supuestos'!$C$12*'Supuestos'!$C$15)))=0,0,'Supuestos'!$C$8/(IF('Supuestos'!$C$11*'Supuestos'!$C$12*'Supuestos'!$C$15=0,0,'Supuestos'!$C$10/1000/('Supuestos'!$C$11*'Supuestos'!$C$12*'Supuestos'!$C$15)))))*'Supuestos'!$C$21)*'Supuestos'!$C$26))*G$9)*$B12)+(((((((IF((IF('Supuestos'!$C$11*'Supuestos'!$C$12*'Supuestos'!$C$15=0,0,'Supuestos'!$C$10/1000/('Supuestos'!$C$11*'Supuestos'!$C$12*'Supuestos'!$C$15)))=0,0,'Supuestos'!$C$8/(IF('Supuestos'!$C$11*'Supuestos'!$C$12*'Supuestos'!$C$15=0,0,'Supuestos'!$C$10/1000/('Supuestos'!$C$11*'Supuestos'!$C$12*'Supuestos'!$C$15)))))*'Supuestos'!$C$20)*'Supuestos'!$C$25)+(((IF((IF('Supuestos'!$C$11*'Supuestos'!$C$12*'Supuestos'!$C$15=0,0,'Supuestos'!$C$10/1000/('Supuestos'!$C$11*'Supuestos'!$C$12*'Supuestos'!$C$15)))=0,0,'Supuestos'!$C$8/(IF('Supuestos'!$C$11*'Supuestos'!$C$12*'Supuestos'!$C$15=0,0,'Supuestos'!$C$10/1000/('Supuestos'!$C$11*'Supuestos'!$C$12*'Supuestos'!$C$15)))))*'Supuestos'!$C$21)*'Supuestos'!$C$26))*G$9)*'Supuestos'!$C$29)*'Supuestos'!$C$28)+(((((((IF((IF('Supuestos'!$C$11*'Supuestos'!$C$12*'Supuestos'!$C$15=0,0,'Supuestos'!$C$10/1000/('Supuestos'!$C$11*'Supuestos'!$C$12*'Supuestos'!$C$15)))=0,0,'Supuestos'!$C$8/(IF('Supuestos'!$C$11*'Supuestos'!$C$12*'Supuestos'!$C$15=0,0,'Supuestos'!$C$10/1000/('Supuestos'!$C$11*'Supuestos'!$C$12*'Supuestos'!$C$15)))))*'Supuestos'!$C$20)*'Supuestos'!$C$25)+(((IF((IF('Supuestos'!$C$11*'Supuestos'!$C$12*'Supuestos'!$C$15=0,0,'Supuestos'!$C$10/1000/('Supuestos'!$C$11*'Supuestos'!$C$12*'Supuestos'!$C$15)))=0,0,'Supuestos'!$C$8/(IF('Supuestos'!$C$11*'Supuestos'!$C$12*'Supuestos'!$C$15=0,0,'Supuestos'!$C$10/1000/('Supuestos'!$C$11*'Supuestos'!$C$12*'Supuestos'!$C$15)))))*'Supuestos'!$C$21)*'Supuestos'!$C$26))*G$9)*'Supuestos'!$C$31)*'Supuestos'!$C$30))*('Supuestos'!$C$41+'Supuestos'!$C$42+'Supuestos'!$C$43))*(1-'Supuestos'!$C$34-'Supuestos'!$C$35-'Supuestos'!$C$36))-((IF((IF('Supuestos'!$C$11*'Supuestos'!$C$12*'Supuestos'!$C$15=0,0,'Supuestos'!$C$10/1000/('Supuestos'!$C$11*'Supuestos'!$C$12*'Supuestos'!$C$15)))=0,0,'Supuestos'!$C$8/(IF('Supuestos'!$C$11*'Supuestos'!$C$12*'Supuestos'!$C$15=0,0,'Supuestos'!$C$10/1000/('Supuestos'!$C$11*'Supuestos'!$C$12*'Supuestos'!$C$15)))))*'Supuestos'!$C$37)-'Supuestos'!$C$38-'Supuestos'!$C$8)
B13: 497 | C13: =((((((((((IF((IF('Supuestos'!$C$11*'Supuestos'!$C$12*'Supuestos'!$C$15=0,0,'Supuestos'!$C$10/1000/('Supuestos'!$C$11*'Supuestos'!$C$12*'Supuestos'!$C$15)))=0,0,'Supuestos'!$C$8/(IF('Supuestos'!$C$11*'Supuestos'!$C$12*'Supuestos'!$C$15=0,0,'Supuestos'!$C$10/1000/('Supuestos'!$C$11*'Supuestos'!$C$12*'Supuestos'!$C$15)))))*'Supuestos'!$C$20)*'Supuestos'!$C$25)+(((IF((IF('Supuestos'!$C$11*'Supuestos'!$C$12*'Supuestos'!$C$15=0,0,'Supuestos'!$C$10/1000/('Supuestos'!$C$11*'Supuestos'!$C$12*'Supuestos'!$C$15)))=0,0,'Supuestos'!$C$8/(IF('Supuestos'!$C$11*'Supuestos'!$C$12*'Supuestos'!$C$15=0,0,'Supuestos'!$C$10/1000/('Supuestos'!$C$11*'Supuestos'!$C$12*'Supuestos'!$C$15)))))*'Supuestos'!$C$21)*'Supuestos'!$C$26))*C$9)*$B13)+(((((((IF((IF('Supuestos'!$C$11*'Supuestos'!$C$12*'Supuestos'!$C$15=0,0,'Supuestos'!$C$10/1000/('Supuestos'!$C$11*'Supuestos'!$C$12*'Supuestos'!$C$15)))=0,0,'Supuestos'!$C$8/(IF('Supuestos'!$C$11*'Supuestos'!$C$12*'Supuestos'!$C$15=0,0,'Supuestos'!$C$10/1000/('Supuestos'!$C$11*'Supuestos'!$C$12*'Supuestos'!$C$15)))))*'Supuestos'!$C$20)*'Supuestos'!$C$25)+(((IF((IF('Supuestos'!$C$11*'Supuestos'!$C$12*'Supuestos'!$C$15=0,0,'Supuestos'!$C$10/1000/('Supuestos'!$C$11*'Supuestos'!$C$12*'Supuestos'!$C$15)))=0,0,'Supuestos'!$C$8/(IF('Supuestos'!$C$11*'Supuestos'!$C$12*'Supuestos'!$C$15=0,0,'Supuestos'!$C$10/1000/('Supuestos'!$C$11*'Supuestos'!$C$12*'Supuestos'!$C$15)))))*'Supuestos'!$C$21)*'Supuestos'!$C$26))*C$9)*'Supuestos'!$C$29)*'Supuestos'!$C$28)+(((((((IF((IF('Supuestos'!$C$11*'Supuestos'!$C$12*'Supuestos'!$C$15=0,0,'Supuestos'!$C$10/1000/('Supuestos'!$C$11*'Supuestos'!$C$12*'Supuestos'!$C$15)))=0,0,'Supuestos'!$C$8/(IF('Supuestos'!$C$11*'Supuestos'!$C$12*'Supuestos'!$C$15=0,0,'Supuestos'!$C$10/1000/('Supuestos'!$C$11*'Supuestos'!$C$12*'Supuestos'!$C$15)))))*'Supuestos'!$C$20)*'Supuestos'!$C$25)+(((IF((IF('Supuestos'!$C$11*'Supuestos'!$C$12*'Supuestos'!$C$15=0,0,'Supuestos'!$C$10/1000/('Supuestos'!$C$11*'Supuestos'!$C$12*'Supuestos'!$C$15)))=0,0,'Supuestos'!$C$8/(IF('Supuestos'!$C$11*'Supuestos'!$C$12*'Supuestos'!$C$15=0,0,'Supuestos'!$C$10/1000/('Supuestos'!$C$11*'Supuestos'!$C$12*'Supuestos'!$C$15)))))*'Supuestos'!$C$21)*'Supuestos'!$C$26))*C$9)*'Supuestos'!$C$31)*'Supuestos'!$C$30))*('Supuestos'!$C$41+'Supuestos'!$C$42+'Supuestos'!$C$43))*(1-'Supuestos'!$C$34-'Supuestos'!$C$35-'Supuestos'!$C$36))-((IF((IF('Supuestos'!$C$11*'Supuestos'!$C$12*'Supuestos'!$C$15=0,0,'Supuestos'!$C$10/1000/('Supuestos'!$C$11*'Supuestos'!$C$12*'Supuestos'!$C$15)))=0,0,'Supuestos'!$C$8/(IF('Supuestos'!$C$11*'Supuestos'!$C$12*'Supuestos'!$C$15=0,0,'Supuestos'!$C$10/1000/('Supuestos'!$C$11*'Supuestos'!$C$12*'Supuestos'!$C$15)))))*'Supuestos'!$C$37)-'Supuestos'!$C$38-'Supuestos'!$C$8) | D13: =((((((((((IF((IF('Supuestos'!$C$11*'Supuestos'!$C$12*'Supuestos'!$C$15=0,0,'Supuestos'!$C$10/1000/('Supuestos'!$C$11*'Supuestos'!$C$12*'Supuestos'!$C$15)))=0,0,'Supuestos'!$C$8/(IF('Supuestos'!$C$11*'Supuestos'!$C$12*'Supuestos'!$C$15=0,0,'Supuestos'!$C$10/1000/('Supuestos'!$C$11*'Supuestos'!$C$12*'Supuestos'!$C$15)))))*'Supuestos'!$C$20)*'Supuestos'!$C$25)+(((IF((IF('Supuestos'!$C$11*'Supuestos'!$C$12*'Supuestos'!$C$15=0,0,'Supuestos'!$C$10/1000/('Supuestos'!$C$11*'Supuestos'!$C$12*'Supuestos'!$C$15)))=0,0,'Supuestos'!$C$8/(IF('Supuestos'!$C$11*'Supuestos'!$C$12*'Supuestos'!$C$15=0,0,'Supuestos'!$C$10/1000/('Supuestos'!$C$11*'Supuestos'!$C$12*'Supuestos'!$C$15)))))*'Supuestos'!$C$21)*'Supuestos'!$C$26))*D$9)*$B13)+(((((((IF((IF('Supuestos'!$C$11*'Supuestos'!$C$12*'Supuestos'!$C$15=0,0,'Supuestos'!$C$10/1000/('Supuestos'!$C$11*'Supuestos'!$C$12*'Supuestos'!$C$15)))=0,0,'Supuestos'!$C$8/(IF('Supuestos'!$C$11*'Supuestos'!$C$12*'Supuestos'!$C$15=0,0,'Supuestos'!$C$10/1000/('Supuestos'!$C$11*'Supuestos'!$C$12*'Supuestos'!$C$15)))))*'Supuestos'!$C$20)*'Supuestos'!$C$25)+(((IF((IF('Supuestos'!$C$11*'Supuestos'!$C$12*'Supuestos'!$C$15=0,0,'Supuestos'!$C$10/1000/('Supuestos'!$C$11*'Supuestos'!$C$12*'Supuestos'!$C$15)))=0,0,'Supuestos'!$C$8/(IF('Supuestos'!$C$11*'Supuestos'!$C$12*'Supuestos'!$C$15=0,0,'Supuestos'!$C$10/1000/('Supuestos'!$C$11*'Supuestos'!$C$12*'Supuestos'!$C$15)))))*'Supuestos'!$C$21)*'Supuestos'!$C$26))*D$9)*'Supuestos'!$C$29)*'Supuestos'!$C$28)+(((((((IF((IF('Supuestos'!$C$11*'Supuestos'!$C$12*'Supuestos'!$C$15=0,0,'Supuestos'!$C$10/1000/('Supuestos'!$C$11*'Supuestos'!$C$12*'Supuestos'!$C$15)))=0,0,'Supuestos'!$C$8/(IF('Supuestos'!$C$11*'Supuestos'!$C$12*'Supuestos'!$C$15=0,0,'Supuestos'!$C$10/1000/('Supuestos'!$C$11*'Supuestos'!$C$12*'Supuestos'!$C$15)))))*'Supuestos'!$C$20)*'Supuestos'!$C$25)+(((IF((IF('Supuestos'!$C$11*'Supuestos'!$C$12*'Supuestos'!$C$15=0,0,'Supuestos'!$C$10/1000/('Supuestos'!$C$11*'Supuestos'!$C$12*'Supuestos'!$C$15)))=0,0,'Supuestos'!$C$8/(IF('Supuestos'!$C$11*'Supuestos'!$C$12*'Supuestos'!$C$15=0,0,'Supuestos'!$C$10/1000/('Supuestos'!$C$11*'Supuestos'!$C$12*'Supuestos'!$C$15)))))*'Supuestos'!$C$21)*'Supuestos'!$C$26))*D$9)*'Supuestos'!$C$31)*'Supuestos'!$C$30))*('Supuestos'!$C$41+'Supuestos'!$C$42+'Supuestos'!$C$43))*(1-'Supuestos'!$C$34-'Supuestos'!$C$35-'Supuestos'!$C$36))-((IF((IF('Supuestos'!$C$11*'Supuestos'!$C$12*'Supuestos'!$C$15=0,0,'Supuestos'!$C$10/1000/('Supuestos'!$C$11*'Supuestos'!$C$12*'Supuestos'!$C$15)))=0,0,'Supuestos'!$C$8/(IF('Supuestos'!$C$11*'Supuestos'!$C$12*'Supuestos'!$C$15=0,0,'Supuestos'!$C$10/1000/('Supuestos'!$C$11*'Supuestos'!$C$12*'Supuestos'!$C$15)))))*'Supuestos'!$C$37)-'Supuestos'!$C$38-'Supuestos'!$C$8) | E13: =((((((((((IF((IF('Supuestos'!$C$11*'Supuestos'!$C$12*'Supuestos'!$C$15=0,0,'Supuestos'!$C$10/1000/('Supuestos'!$C$11*'Supuestos'!$C$12*'Supuestos'!$C$15)))=0,0,'Supuestos'!$C$8/(IF('Supuestos'!$C$11*'Supuestos'!$C$12*'Supuestos'!$C$15=0,0,'Supuestos'!$C$10/1000/('Supuestos'!$C$11*'Supuestos'!$C$12*'Supuestos'!$C$15)))))*'Supuestos'!$C$20)*'Supuestos'!$C$25)+(((IF((IF('Supuestos'!$C$11*'Supuestos'!$C$12*'Supuestos'!$C$15=0,0,'Supuestos'!$C$10/1000/('Supuestos'!$C$11*'Supuestos'!$C$12*'Supuestos'!$C$15)))=0,0,'Supuestos'!$C$8/(IF('Supuestos'!$C$11*'Supuestos'!$C$12*'Supuestos'!$C$15=0,0,'Supuestos'!$C$10/1000/('Supuestos'!$C$11*'Supuestos'!$C$12*'Supuestos'!$C$15)))))*'Supuestos'!$C$21)*'Supuestos'!$C$26))*E$9)*$B13)+(((((((IF((IF('Supuestos'!$C$11*'Supuestos'!$C$12*'Supuestos'!$C$15=0,0,'Supuestos'!$C$10/1000/('Supuestos'!$C$11*'Supuestos'!$C$12*'Supuestos'!$C$15)))=0,0,'Supuestos'!$C$8/(IF('Supuestos'!$C$11*'Supuestos'!$C$12*'Supuestos'!$C$15=0,0,'Supuestos'!$C$10/1000/('Supuestos'!$C$11*'Supuestos'!$C$12*'Supuestos'!$C$15)))))*'Supuestos'!$C$20)*'Supuestos'!$C$25)+(((IF((IF('Supuestos'!$C$11*'Supuestos'!$C$12*'Supuestos'!$C$15=0,0,'Supuestos'!$C$10/1000/('Supuestos'!$C$11*'Supuestos'!$C$12*'Supuestos'!$C$15)))=0,0,'Supuestos'!$C$8/(IF('Supuestos'!$C$11*'Supuestos'!$C$12*'Supuestos'!$C$15=0,0,'Supuestos'!$C$10/1000/('Supuestos'!$C$11*'Supuestos'!$C$12*'Supuestos'!$C$15)))))*'Supuestos'!$C$21)*'Supuestos'!$C$26))*E$9)*'Supuestos'!$C$29)*'Supuestos'!$C$28)+(((((((IF((IF('Supuestos'!$C$11*'Supuestos'!$C$12*'Supuestos'!$C$15=0,0,'Supuestos'!$C$10/1000/('Supuestos'!$C$11*'Supuestos'!$C$12*'Supuestos'!$C$15)))=0,0,'Supuestos'!$C$8/(IF('Supuestos'!$C$11*'Supuestos'!$C$12*'Supuestos'!$C$15=0,0,'Supuestos'!$C$10/1000/('Supuestos'!$C$11*'Supuestos'!$C$12*'Supuestos'!$C$15)))))*'Supuestos'!$C$20)*'Supuestos'!$C$25)+(((IF((IF('Supuestos'!$C$11*'Supuestos'!$C$12*'Supuestos'!$C$15=0,0,'Supuestos'!$C$10/1000/('Supuestos'!$C$11*'Supuestos'!$C$12*'Supuestos'!$C$15)))=0,0,'Supuestos'!$C$8/(IF('Supuestos'!$C$11*'Supuestos'!$C$12*'Supuestos'!$C$15=0,0,'Supuestos'!$C$10/1000/('Supuestos'!$C$11*'Supuestos'!$C$12*'Supuestos'!$C$15)))))*'Supuestos'!$C$21)*'Supuestos'!$C$26))*E$9)*'Supuestos'!$C$31)*'Supuestos'!$C$30))*('Supuestos'!$C$41+'Supuestos'!$C$42+'Supuestos'!$C$43))*(1-'Supuestos'!$C$34-'Supuestos'!$C$35-'Supuestos'!$C$36))-((IF((IF('Supuestos'!$C$11*'Supuestos'!$C$12*'Supuestos'!$C$15=0,0,'Supuestos'!$C$10/1000/('Supuestos'!$C$11*'Supuestos'!$C$12*'Supuestos'!$C$15)))=0,0,'Supuestos'!$C$8/(IF('Supuestos'!$C$11*'Supuestos'!$C$12*'Supuestos'!$C$15=0,0,'Supuestos'!$C$10/1000/('Supuestos'!$C$11*'Supuestos'!$C$12*'Supuestos'!$C$15)))))*'Supuestos'!$C$37)-'Supuestos'!$C$38-'Supuestos'!$C$8) | F13: =((((((((((IF((IF('Supuestos'!$C$11*'Supuestos'!$C$12*'Supuestos'!$C$15=0,0,'Supuestos'!$C$10/1000/('Supuestos'!$C$11*'Supuestos'!$C$12*'Supuestos'!$C$15)))=0,0,'Supuestos'!$C$8/(IF('Supuestos'!$C$11*'Supuestos'!$C$12*'Supuestos'!$C$15=0,0,'Supuestos'!$C$10/1000/('Supuestos'!$C$11*'Supuestos'!$C$12*'Supuestos'!$C$15)))))*'Supuestos'!$C$20)*'Supuestos'!$C$25)+(((IF((IF('Supuestos'!$C$11*'Supuestos'!$C$12*'Supuestos'!$C$15=0,0,'Supuestos'!$C$10/1000/('Supuestos'!$C$11*'Supuestos'!$C$12*'Supuestos'!$C$15)))=0,0,'Supuestos'!$C$8/(IF('Supuestos'!$C$11*'Supuestos'!$C$12*'Supuestos'!$C$15=0,0,'Supuestos'!$C$10/1000/('Supuestos'!$C$11*'Supuestos'!$C$12*'Supuestos'!$C$15)))))*'Supuestos'!$C$21)*'Supuestos'!$C$26))*F$9)*$B13)+(((((((IF((IF('Supuestos'!$C$11*'Supuestos'!$C$12*'Supuestos'!$C$15=0,0,'Supuestos'!$C$10/1000/('Supuestos'!$C$11*'Supuestos'!$C$12*'Supuestos'!$C$15)))=0,0,'Supuestos'!$C$8/(IF('Supuestos'!$C$11*'Supuestos'!$C$12*'Supuestos'!$C$15=0,0,'Supuestos'!$C$10/1000/('Supuestos'!$C$11*'Supuestos'!$C$12*'Supuestos'!$C$15)))))*'Supuestos'!$C$20)*'Supuestos'!$C$25)+(((IF((IF('Supuestos'!$C$11*'Supuestos'!$C$12*'Supuestos'!$C$15=0,0,'Supuestos'!$C$10/1000/('Supuestos'!$C$11*'Supuestos'!$C$12*'Supuestos'!$C$15)))=0,0,'Supuestos'!$C$8/(IF('Supuestos'!$C$11*'Supuestos'!$C$12*'Supuestos'!$C$15=0,0,'Supuestos'!$C$10/1000/('Supuestos'!$C$11*'Supuestos'!$C$12*'Supuestos'!$C$15)))))*'Supuestos'!$C$21)*'Supuestos'!$C$26))*F$9)*'Supuestos'!$C$29)*'Supuestos'!$C$28)+(((((((IF((IF('Supuestos'!$C$11*'Supuestos'!$C$12*'Supuestos'!$C$15=0,0,'Supuestos'!$C$10/1000/('Supuestos'!$C$11*'Supuestos'!$C$12*'Supuestos'!$C$15)))=0,0,'Supuestos'!$C$8/(IF('Supuestos'!$C$11*'Supuestos'!$C$12*'Supuestos'!$C$15=0,0,'Supuestos'!$C$10/1000/('Supuestos'!$C$11*'Supuestos'!$C$12*'Supuestos'!$C$15)))))*'Supuestos'!$C$20)*'Supuestos'!$C$25)+(((IF((IF('Supuestos'!$C$11*'Supuestos'!$C$12*'Supuestos'!$C$15=0,0,'Supuestos'!$C$10/1000/('Supuestos'!$C$11*'Supuestos'!$C$12*'Supuestos'!$C$15)))=0,0,'Supuestos'!$C$8/(IF('Supuestos'!$C$11*'Supuestos'!$C$12*'Supuestos'!$C$15=0,0,'Supuestos'!$C$10/1000/('Supuestos'!$C$11*'Supuestos'!$C$12*'Supuestos'!$C$15)))))*'Supuestos'!$C$21)*'Supuestos'!$C$26))*F$9)*'Supuestos'!$C$31)*'Supuestos'!$C$30))*('Supuestos'!$C$41+'Supuestos'!$C$42+'Supuestos'!$C$43))*(1-'Supuestos'!$C$34-'Supuestos'!$C$35-'Supuestos'!$C$36))-((IF((IF('Supuestos'!$C$11*'Supuestos'!$C$12*'Supuestos'!$C$15=0,0,'Supuestos'!$C$10/1000/('Supuestos'!$C$11*'Supuestos'!$C$12*'Supuestos'!$C$15)))=0,0,'Supuestos'!$C$8/(IF('Supuestos'!$C$11*'Supuestos'!$C$12*'Supuestos'!$C$15=0,0,'Supuestos'!$C$10/1000/('Supuestos'!$C$11*'Supuestos'!$C$12*'Supuestos'!$C$15)))))*'Supuestos'!$C$37)-'Supuestos'!$C$38-'Supuestos'!$C$8) | G13: =((((((((((IF((IF('Supuestos'!$C$11*'Supuestos'!$C$12*'Supuestos'!$C$15=0,0,'Supuestos'!$C$10/1000/('Supuestos'!$C$11*'Supuestos'!$C$12*'Supuestos'!$C$15)))=0,0,'Supuestos'!$C$8/(IF('Supuestos'!$C$11*'Supuestos'!$C$12*'Supuestos'!$C$15=0,0,'Supuestos'!$C$10/1000/('Supuestos'!$C$11*'Supuestos'!$C$12*'Supuestos'!$C$15)))))*'Supuestos'!$C$20)*'Supuestos'!$C$25)+(((IF((IF('Supuestos'!$C$11*'Supuestos'!$C$12*'Supuestos'!$C$15=0,0,'Supuestos'!$C$10/1000/('Supuestos'!$C$11*'Supuestos'!$C$12*'Supuestos'!$C$15)))=0,0,'Supuestos'!$C$8/(IF('Supuestos'!$C$11*'Supuestos'!$C$12*'Supuestos'!$C$15=0,0,'Supuestos'!$C$10/1000/('Supuestos'!$C$11*'Supuestos'!$C$12*'Supuestos'!$C$15)))))*'Supuestos'!$C$21)*'Supuestos'!$C$26))*G$9)*$B13)+(((((((IF((IF('Supuestos'!$C$11*'Supuestos'!$C$12*'Supuestos'!$C$15=0,0,'Supuestos'!$C$10/1000/('Supuestos'!$C$11*'Supuestos'!$C$12*'Supuestos'!$C$15)))=0,0,'Supuestos'!$C$8/(IF('Supuestos'!$C$11*'Supuestos'!$C$12*'Supuestos'!$C$15=0,0,'Supuestos'!$C$10/1000/('Supuestos'!$C$11*'Supuestos'!$C$12*'Supuestos'!$C$15)))))*'Supuestos'!$C$20)*'Supuestos'!$C$25)+(((IF((IF('Supuestos'!$C$11*'Supuestos'!$C$12*'Supuestos'!$C$15=0,0,'Supuestos'!$C$10/1000/('Supuestos'!$C$11*'Supuestos'!$C$12*'Supuestos'!$C$15)))=0,0,'Supuestos'!$C$8/(IF('Supuestos'!$C$11*'Supuestos'!$C$12*'Supuestos'!$C$15=0,0,'Supuestos'!$C$10/1000/('Supuestos'!$C$11*'Supuestos'!$C$12*'Supuestos'!$C$15)))))*'Supuestos'!$C$21)*'Supuestos'!$C$26))*G$9)*'Supuestos'!$C$29)*'Supuestos'!$C$28)+(((((((IF((IF('Supuestos'!$C$11*'Supuestos'!$C$12*'Supuestos'!$C$15=0,0,'Supuestos'!$C$10/1000/('Supuestos'!$C$11*'Supuestos'!$C$12*'Supuestos'!$C$15)))=0,0,'Supuestos'!$C$8/(IF('Supuestos'!$C$11*'Supuestos'!$C$12*'Supuestos'!$C$15=0,0,'Supuestos'!$C$10/1000/('Supuestos'!$C$11*'Supuestos'!$C$12*'Supuestos'!$C$15)))))*'Supuestos'!$C$20)*'Supuestos'!$C$25)+(((IF((IF('Supuestos'!$C$11*'Supuestos'!$C$12*'Supuestos'!$C$15=0,0,'Supuestos'!$C$10/1000/('Supuestos'!$C$11*'Supuestos'!$C$12*'Supuestos'!$C$15)))=0,0,'Supuestos'!$C$8/(IF('Supuestos'!$C$11*'Supuestos'!$C$12*'Supuestos'!$C$15=0,0,'Supuestos'!$C$10/1000/('Supuestos'!$C$11*'Supuestos'!$C$12*'Supuestos'!$C$15)))))*'Supuestos'!$C$21)*'Supuestos'!$C$26))*G$9)*'Supuestos'!$C$31)*'Supuestos'!$C$30))*('Supuestos'!$C$41+'Supuestos'!$C$42+'Supuestos'!$C$43))*(1-'Supuestos'!$C$34-'Supuestos'!$C$35-'Supuestos'!$C$36))-((IF((IF('Supuestos'!$C$11*'Supuestos'!$C$12*'Supuestos'!$C$15=0,0,'Supuestos'!$C$10/1000/('Supuestos'!$C$11*'Supuestos'!$C$12*'Supuestos'!$C$15)))=0,0,'Supuestos'!$C$8/(IF('Supuestos'!$C$11*'Supuestos'!$C$12*'Supuestos'!$C$15=0,0,'Supuestos'!$C$10/1000/('Supuestos'!$C$11*'Supuestos'!$C$12*'Supuestos'!$C$15)))))*'Supuestos'!$C$37)-'Supuestos'!$C$38-'Supuestos'!$C$8)
B14: 997 | C14: =((((((((((IF((IF('Supuestos'!$C$11*'Supuestos'!$C$12*'Supuestos'!$C$15=0,0,'Supuestos'!$C$10/1000/('Supuestos'!$C$11*'Supuestos'!$C$12*'Supuestos'!$C$15)))=0,0,'Supuestos'!$C$8/(IF('Supuestos'!$C$11*'Supuestos'!$C$12*'Supuestos'!$C$15=0,0,'Supuestos'!$C$10/1000/('Supuestos'!$C$11*'Supuestos'!$C$12*'Supuestos'!$C$15)))))*'Supuestos'!$C$20)*'Supuestos'!$C$25)+(((IF((IF('Supuestos'!$C$11*'Supuestos'!$C$12*'Supuestos'!$C$15=0,0,'Supuestos'!$C$10/1000/('Supuestos'!$C$11*'Supuestos'!$C$12*'Supuestos'!$C$15)))=0,0,'Supuestos'!$C$8/(IF('Supuestos'!$C$11*'Supuestos'!$C$12*'Supuestos'!$C$15=0,0,'Supuestos'!$C$10/1000/('Supuestos'!$C$11*'Supuestos'!$C$12*'Supuestos'!$C$15)))))*'Supuestos'!$C$21)*'Supuestos'!$C$26))*C$9)*$B14)+(((((((IF((IF('Supuestos'!$C$11*'Supuestos'!$C$12*'Supuestos'!$C$15=0,0,'Supuestos'!$C$10/1000/('Supuestos'!$C$11*'Supuestos'!$C$12*'Supuestos'!$C$15)))=0,0,'Supuestos'!$C$8/(IF('Supuestos'!$C$11*'Supuestos'!$C$12*'Supuestos'!$C$15=0,0,'Supuestos'!$C$10/1000/('Supuestos'!$C$11*'Supuestos'!$C$12*'Supuestos'!$C$15)))))*'Supuestos'!$C$20)*'Supuestos'!$C$25)+(((IF((IF('Supuestos'!$C$11*'Supuestos'!$C$12*'Supuestos'!$C$15=0,0,'Supuestos'!$C$10/1000/('Supuestos'!$C$11*'Supuestos'!$C$12*'Supuestos'!$C$15)))=0,0,'Supuestos'!$C$8/(IF('Supuestos'!$C$11*'Supuestos'!$C$12*'Supuestos'!$C$15=0,0,'Supuestos'!$C$10/1000/('Supuestos'!$C$11*'Supuestos'!$C$12*'Supuestos'!$C$15)))))*'Supuestos'!$C$21)*'Supuestos'!$C$26))*C$9)*'Supuestos'!$C$29)*'Supuestos'!$C$28)+(((((((IF((IF('Supuestos'!$C$11*'Supuestos'!$C$12*'Supuestos'!$C$15=0,0,'Supuestos'!$C$10/1000/('Supuestos'!$C$11*'Supuestos'!$C$12*'Supuestos'!$C$15)))=0,0,'Supuestos'!$C$8/(IF('Supuestos'!$C$11*'Supuestos'!$C$12*'Supuestos'!$C$15=0,0,'Supuestos'!$C$10/1000/('Supuestos'!$C$11*'Supuestos'!$C$12*'Supuestos'!$C$15)))))*'Supuestos'!$C$20)*'Supuestos'!$C$25)+(((IF((IF('Supuestos'!$C$11*'Supuestos'!$C$12*'Supuestos'!$C$15=0,0,'Supuestos'!$C$10/1000/('Supuestos'!$C$11*'Supuestos'!$C$12*'Supuestos'!$C$15)))=0,0,'Supuestos'!$C$8/(IF('Supuestos'!$C$11*'Supuestos'!$C$12*'Supuestos'!$C$15=0,0,'Supuestos'!$C$10/1000/('Supuestos'!$C$11*'Supuestos'!$C$12*'Supuestos'!$C$15)))))*'Supuestos'!$C$21)*'Supuestos'!$C$26))*C$9)*'Supuestos'!$C$31)*'Supuestos'!$C$30))*('Supuestos'!$C$41+'Supuestos'!$C$42+'Supuestos'!$C$43))*(1-'Supuestos'!$C$34-'Supuestos'!$C$35-'Supuestos'!$C$36))-((IF((IF('Supuestos'!$C$11*'Supuestos'!$C$12*'Supuestos'!$C$15=0,0,'Supuestos'!$C$10/1000/('Supuestos'!$C$11*'Supuestos'!$C$12*'Supuestos'!$C$15)))=0,0,'Supuestos'!$C$8/(IF('Supuestos'!$C$11*'Supuestos'!$C$12*'Supuestos'!$C$15=0,0,'Supuestos'!$C$10/1000/('Supuestos'!$C$11*'Supuestos'!$C$12*'Supuestos'!$C$15)))))*'Supuestos'!$C$37)-'Supuestos'!$C$38-'Supuestos'!$C$8) | D14: =((((((((((IF((IF('Supuestos'!$C$11*'Supuestos'!$C$12*'Supuestos'!$C$15=0,0,'Supuestos'!$C$10/1000/('Supuestos'!$C$11*'Supuestos'!$C$12*'Supuestos'!$C$15)))=0,0,'Supuestos'!$C$8/(IF('Supuestos'!$C$11*'Supuestos'!$C$12*'Supuestos'!$C$15=0,0,'Supuestos'!$C$10/1000/('Supuestos'!$C$11*'Supuestos'!$C$12*'Supuestos'!$C$15)))))*'Supuestos'!$C$20)*'Supuestos'!$C$25)+(((IF((IF('Supuestos'!$C$11*'Supuestos'!$C$12*'Supuestos'!$C$15=0,0,'Supuestos'!$C$10/1000/('Supuestos'!$C$11*'Supuestos'!$C$12*'Supuestos'!$C$15)))=0,0,'Supuestos'!$C$8/(IF('Supuestos'!$C$11*'Supuestos'!$C$12*'Supuestos'!$C$15=0,0,'Supuestos'!$C$10/1000/('Supuestos'!$C$11*'Supuestos'!$C$12*'Supuestos'!$C$15)))))*'Supuestos'!$C$21)*'Supuestos'!$C$26))*D$9)*$B14)+(((((((IF((IF('Supuestos'!$C$11*'Supuestos'!$C$12*'Supuestos'!$C$15=0,0,'Supuestos'!$C$10/1000/('Supuestos'!$C$11*'Supuestos'!$C$12*'Supuestos'!$C$15)))=0,0,'Supuestos'!$C$8/(IF('Supuestos'!$C$11*'Supuestos'!$C$12*'Supuestos'!$C$15=0,0,'Supuestos'!$C$10/1000/('Supuestos'!$C$11*'Supuestos'!$C$12*'Supuestos'!$C$15)))))*'Supuestos'!$C$20)*'Supuestos'!$C$25)+(((IF((IF('Supuestos'!$C$11*'Supuestos'!$C$12*'Supuestos'!$C$15=0,0,'Supuestos'!$C$10/1000/('Supuestos'!$C$11*'Supuestos'!$C$12*'Supuestos'!$C$15)))=0,0,'Supuestos'!$C$8/(IF('Supuestos'!$C$11*'Supuestos'!$C$12*'Supuestos'!$C$15=0,0,'Supuestos'!$C$10/1000/('Supuestos'!$C$11*'Supuestos'!$C$12*'Supuestos'!$C$15)))))*'Supuestos'!$C$21)*'Supuestos'!$C$26))*D$9)*'Supuestos'!$C$29)*'Supuestos'!$C$28)+(((((((IF((IF('Supuestos'!$C$11*'Supuestos'!$C$12*'Supuestos'!$C$15=0,0,'Supuestos'!$C$10/1000/('Supuestos'!$C$11*'Supuestos'!$C$12*'Supuestos'!$C$15)))=0,0,'Supuestos'!$C$8/(IF('Supuestos'!$C$11*'Supuestos'!$C$12*'Supuestos'!$C$15=0,0,'Supuestos'!$C$10/1000/('Supuestos'!$C$11*'Supuestos'!$C$12*'Supuestos'!$C$15)))))*'Supuestos'!$C$20)*'Supuestos'!$C$25)+(((IF((IF('Supuestos'!$C$11*'Supuestos'!$C$12*'Supuestos'!$C$15=0,0,'Supuestos'!$C$10/1000/('Supuestos'!$C$11*'Supuestos'!$C$12*'Supuestos'!$C$15)))=0,0,'Supuestos'!$C$8/(IF('Supuestos'!$C$11*'Supuestos'!$C$12*'Supuestos'!$C$15=0,0,'Supuestos'!$C$10/1000/('Supuestos'!$C$11*'Supuestos'!$C$12*'Supuestos'!$C$15)))))*'Supuestos'!$C$21)*'Supuestos'!$C$26))*D$9)*'Supuestos'!$C$31)*'Supuestos'!$C$30))*('Supuestos'!$C$41+'Supuestos'!$C$42+'Supuestos'!$C$43))*(1-'Supuestos'!$C$34-'Supuestos'!$C$35-'Supuestos'!$C$36))-((IF((IF('Supuestos'!$C$11*'Supuestos'!$C$12*'Supuestos'!$C$15=0,0,'Supuestos'!$C$10/1000/('Supuestos'!$C$11*'Supuestos'!$C$12*'Supuestos'!$C$15)))=0,0,'Supuestos'!$C$8/(IF('Supuestos'!$C$11*'Supuestos'!$C$12*'Supuestos'!$C$15=0,0,'Supuestos'!$C$10/1000/('Supuestos'!$C$11*'Supuestos'!$C$12*'Supuestos'!$C$15)))))*'Supuestos'!$C$37)-'Supuestos'!$C$38-'Supuestos'!$C$8) | E14: =((((((((((IF((IF('Supuestos'!$C$11*'Supuestos'!$C$12*'Supuestos'!$C$15=0,0,'Supuestos'!$C$10/1000/('Supuestos'!$C$11*'Supuestos'!$C$12*'Supuestos'!$C$15)))=0,0,'Supuestos'!$C$8/(IF('Supuestos'!$C$11*'Supuestos'!$C$12*'Supuestos'!$C$15=0,0,'Supuestos'!$C$10/1000/('Supuestos'!$C$11*'Supuestos'!$C$12*'Supuestos'!$C$15)))))*'Supuestos'!$C$20)*'Supuestos'!$C$25)+(((IF((IF('Supuestos'!$C$11*'Supuestos'!$C$12*'Supuestos'!$C$15=0,0,'Supuestos'!$C$10/1000/('Supuestos'!$C$11*'Supuestos'!$C$12*'Supuestos'!$C$15)))=0,0,'Supuestos'!$C$8/(IF('Supuestos'!$C$11*'Supuestos'!$C$12*'Supuestos'!$C$15=0,0,'Supuestos'!$C$10/1000/('Supuestos'!$C$11*'Supuestos'!$C$12*'Supuestos'!$C$15)))))*'Supuestos'!$C$21)*'Supuestos'!$C$26))*E$9)*$B14)+(((((((IF((IF('Supuestos'!$C$11*'Supuestos'!$C$12*'Supuestos'!$C$15=0,0,'Supuestos'!$C$10/1000/('Supuestos'!$C$11*'Supuestos'!$C$12*'Supuestos'!$C$15)))=0,0,'Supuestos'!$C$8/(IF('Supuestos'!$C$11*'Supuestos'!$C$12*'Supuestos'!$C$15=0,0,'Supuestos'!$C$10/1000/('Supuestos'!$C$11*'Supuestos'!$C$12*'Supuestos'!$C$15)))))*'Supuestos'!$C$20)*'Supuestos'!$C$25)+(((IF((IF('Supuestos'!$C$11*'Supuestos'!$C$12*'Supuestos'!$C$15=0,0,'Supuestos'!$C$10/1000/('Supuestos'!$C$11*'Supuestos'!$C$12*'Supuestos'!$C$15)))=0,0,'Supuestos'!$C$8/(IF('Supuestos'!$C$11*'Supuestos'!$C$12*'Supuestos'!$C$15=0,0,'Supuestos'!$C$10/1000/('Supuestos'!$C$11*'Supuestos'!$C$12*'Supuestos'!$C$15)))))*'Supuestos'!$C$21)*'Supuestos'!$C$26))*E$9)*'Supuestos'!$C$29)*'Supuestos'!$C$28)+(((((((IF((IF('Supuestos'!$C$11*'Supuestos'!$C$12*'Supuestos'!$C$15=0,0,'Supuestos'!$C$10/1000/('Supuestos'!$C$11*'Supuestos'!$C$12*'Supuestos'!$C$15)))=0,0,'Supuestos'!$C$8/(IF('Supuestos'!$C$11*'Supuestos'!$C$12*'Supuestos'!$C$15=0,0,'Supuestos'!$C$10/1000/('Supuestos'!$C$11*'Supuestos'!$C$12*'Supuestos'!$C$15)))))*'Supuestos'!$C$20)*'Supuestos'!$C$25)+(((IF((IF('Supuestos'!$C$11*'Supuestos'!$C$12*'Supuestos'!$C$15=0,0,'Supuestos'!$C$10/1000/('Supuestos'!$C$11*'Supuestos'!$C$12*'Supuestos'!$C$15)))=0,0,'Supuestos'!$C$8/(IF('Supuestos'!$C$11*'Supuestos'!$C$12*'Supuestos'!$C$15=0,0,'Supuestos'!$C$10/1000/('Supuestos'!$C$11*'Supuestos'!$C$12*'Supuestos'!$C$15)))))*'Supuestos'!$C$21)*'Supuestos'!$C$26))*E$9)*'Supuestos'!$C$31)*'Supuestos'!$C$30))*('Supuestos'!$C$41+'Supuestos'!$C$42+'Supuestos'!$C$43))*(1-'Supuestos'!$C$34-'Supuestos'!$C$35-'Supuestos'!$C$36))-((IF((IF('Supuestos'!$C$11*'Supuestos'!$C$12*'Supuestos'!$C$15=0,0,'Supuestos'!$C$10/1000/('Supuestos'!$C$11*'Supuestos'!$C$12*'Supuestos'!$C$15)))=0,0,'Supuestos'!$C$8/(IF('Supuestos'!$C$11*'Supuestos'!$C$12*'Supuestos'!$C$15=0,0,'Supuestos'!$C$10/1000/('Supuestos'!$C$11*'Supuestos'!$C$12*'Supuestos'!$C$15)))))*'Supuestos'!$C$37)-'Supuestos'!$C$38-'Supuestos'!$C$8) | F14: =((((((((((IF((IF('Supuestos'!$C$11*'Supuestos'!$C$12*'Supuestos'!$C$15=0,0,'Supuestos'!$C$10/1000/('Supuestos'!$C$11*'Supuestos'!$C$12*'Supuestos'!$C$15)))=0,0,'Supuestos'!$C$8/(IF('Supuestos'!$C$11*'Supuestos'!$C$12*'Supuestos'!$C$15=0,0,'Supuestos'!$C$10/1000/('Supuestos'!$C$11*'Supuestos'!$C$12*'Supuestos'!$C$15)))))*'Supuestos'!$C$20)*'Supuestos'!$C$25)+(((IF((IF('Supuestos'!$C$11*'Supuestos'!$C$12*'Supuestos'!$C$15=0,0,'Supuestos'!$C$10/1000/('Supuestos'!$C$11*'Supuestos'!$C$12*'Supuestos'!$C$15)))=0,0,'Supuestos'!$C$8/(IF('Supuestos'!$C$11*'Supuestos'!$C$12*'Supuestos'!$C$15=0,0,'Supuestos'!$C$10/1000/('Supuestos'!$C$11*'Supuestos'!$C$12*'Supuestos'!$C$15)))))*'Supuestos'!$C$21)*'Supuestos'!$C$26))*F$9)*$B14)+(((((((IF((IF('Supuestos'!$C$11*'Supuestos'!$C$12*'Supuestos'!$C$15=0,0,'Supuestos'!$C$10/1000/('Supuestos'!$C$11*'Supuestos'!$C$12*'Supuestos'!$C$15)))=0,0,'Supuestos'!$C$8/(IF('Supuestos'!$C$11*'Supuestos'!$C$12*'Supuestos'!$C$15=0,0,'Supuestos'!$C$10/1000/('Supuestos'!$C$11*'Supuestos'!$C$12*'Supuestos'!$C$15)))))*'Supuestos'!$C$20)*'Supuestos'!$C$25)+(((IF((IF('Supuestos'!$C$11*'Supuestos'!$C$12*'Supuestos'!$C$15=0,0,'Supuestos'!$C$10/1000/('Supuestos'!$C$11*'Supuestos'!$C$12*'Supuestos'!$C$15)))=0,0,'Supuestos'!$C$8/(IF('Supuestos'!$C$11*'Supuestos'!$C$12*'Supuestos'!$C$15=0,0,'Supuestos'!$C$10/1000/('Supuestos'!$C$11*'Supuestos'!$C$12*'Supuestos'!$C$15)))))*'Supuestos'!$C$21)*'Supuestos'!$C$26))*F$9)*'Supuestos'!$C$29)*'Supuestos'!$C$28)+(((((((IF((IF('Supuestos'!$C$11*'Supuestos'!$C$12*'Supuestos'!$C$15=0,0,'Supuestos'!$C$10/1000/('Supuestos'!$C$11*'Supuestos'!$C$12*'Supuestos'!$C$15)))=0,0,'Supuestos'!$C$8/(IF('Supuestos'!$C$11*'Supuestos'!$C$12*'Supuestos'!$C$15=0,0,'Supuestos'!$C$10/1000/('Supuestos'!$C$11*'Supuestos'!$C$12*'Supuestos'!$C$15)))))*'Supuestos'!$C$20)*'Supuestos'!$C$25)+(((IF((IF('Supuestos'!$C$11*'Supuestos'!$C$12*'Supuestos'!$C$15=0,0,'Supuestos'!$C$10/1000/('Supuestos'!$C$11*'Supuestos'!$C$12*'Supuestos'!$C$15)))=0,0,'Supuestos'!$C$8/(IF('Supuestos'!$C$11*'Supuestos'!$C$12*'Supuestos'!$C$15=0,0,'Supuestos'!$C$10/1000/('Supuestos'!$C$11*'Supuestos'!$C$12*'Supuestos'!$C$15)))))*'Supuestos'!$C$21)*'Supuestos'!$C$26))*F$9)*'Supuestos'!$C$31)*'Supuestos'!$C$30))*('Supuestos'!$C$41+'Supuestos'!$C$42+'Supuestos'!$C$43))*(1-'Supuestos'!$C$34-'Supuestos'!$C$35-'Supuestos'!$C$36))-((IF((IF('Supuestos'!$C$11*'Supuestos'!$C$12*'Supuestos'!$C$15=0,0,'Supuestos'!$C$10/1000/('Supuestos'!$C$11*'Supuestos'!$C$12*'Supuestos'!$C$15)))=0,0,'Supuestos'!$C$8/(IF('Supuestos'!$C$11*'Supuestos'!$C$12*'Supuestos'!$C$15=0,0,'Supuestos'!$C$10/1000/('Supuestos'!$C$11*'Supuestos'!$C$12*'Supuestos'!$C$15)))))*'Supuestos'!$C$37)-'Supuestos'!$C$38-'Supuestos'!$C$8) | G14: =((((((((((IF((IF('Supuestos'!$C$11*'Supuestos'!$C$12*'Supuestos'!$C$15=0,0,'Supuestos'!$C$10/1000/('Supuestos'!$C$11*'Supuestos'!$C$12*'Supuestos'!$C$15)))=0,0,'Supuestos'!$C$8/(IF('Supuestos'!$C$11*'Supuestos'!$C$12*'Supuestos'!$C$15=0,0,'Supuestos'!$C$10/1000/('Supuestos'!$C$11*'Supuestos'!$C$12*'Supuestos'!$C$15)))))*'Supuestos'!$C$20)*'Supuestos'!$C$25)+(((IF((IF('Supuestos'!$C$11*'Supuestos'!$C$12*'Supuestos'!$C$15=0,0,'Supuestos'!$C$10/1000/('Supuestos'!$C$11*'Supuestos'!$C$12*'Supuestos'!$C$15)))=0,0,'Supuestos'!$C$8/(IF('Supuestos'!$C$11*'Supuestos'!$C$12*'Supuestos'!$C$15=0,0,'Supuestos'!$C$10/1000/('Supuestos'!$C$11*'Supuestos'!$C$12*'Supuestos'!$C$15)))))*'Supuestos'!$C$21)*'Supuestos'!$C$26))*G$9)*$B14)+(((((((IF((IF('Supuestos'!$C$11*'Supuestos'!$C$12*'Supuestos'!$C$15=0,0,'Supuestos'!$C$10/1000/('Supuestos'!$C$11*'Supuestos'!$C$12*'Supuestos'!$C$15)))=0,0,'Supuestos'!$C$8/(IF('Supuestos'!$C$11*'Supuestos'!$C$12*'Supuestos'!$C$15=0,0,'Supuestos'!$C$10/1000/('Supuestos'!$C$11*'Supuestos'!$C$12*'Supuestos'!$C$15)))))*'Supuestos'!$C$20)*'Supuestos'!$C$25)+(((IF((IF('Supuestos'!$C$11*'Supuestos'!$C$12*'Supuestos'!$C$15=0,0,'Supuestos'!$C$10/1000/('Supuestos'!$C$11*'Supuestos'!$C$12*'Supuestos'!$C$15)))=0,0,'Supuestos'!$C$8/(IF('Supuestos'!$C$11*'Supuestos'!$C$12*'Supuestos'!$C$15=0,0,'Supuestos'!$C$10/1000/('Supuestos'!$C$11*'Supuestos'!$C$12*'Supuestos'!$C$15)))))*'Supuestos'!$C$21)*'Supuestos'!$C$26))*G$9)*'Supuestos'!$C$29)*'Supuestos'!$C$28)+(((((((IF((IF('Supuestos'!$C$11*'Supuestos'!$C$12*'Supuestos'!$C$15=0,0,'Supuestos'!$C$10/1000/('Supuestos'!$C$11*'Supuestos'!$C$12*'Supuestos'!$C$15)))=0,0,'Supuestos'!$C$8/(IF('Supuestos'!$C$11*'Supuestos'!$C$12*'Supuestos'!$C$15=0,0,'Supuestos'!$C$10/1000/('Supuestos'!$C$11*'Supuestos'!$C$12*'Supuestos'!$C$15)))))*'Supuestos'!$C$20)*'Supuestos'!$C$25)+(((IF((IF('Supuestos'!$C$11*'Supuestos'!$C$12*'Supuestos'!$C$15=0,0,'Supuestos'!$C$10/1000/('Supuestos'!$C$11*'Supuestos'!$C$12*'Supuestos'!$C$15)))=0,0,'Supuestos'!$C$8/(IF('Supuestos'!$C$11*'Supuestos'!$C$12*'Supuestos'!$C$15=0,0,'Supuestos'!$C$10/1000/('Supuestos'!$C$11*'Supuestos'!$C$12*'Supuestos'!$C$15)))))*'Supuestos'!$C$21)*'Supuestos'!$C$26))*G$9)*'Supuestos'!$C$31)*'Supuestos'!$C$30))*('Supuestos'!$C$41+'Supuestos'!$C$42+'Supuestos'!$C$43))*(1-'Supuestos'!$C$34-'Supuestos'!$C$35-'Supuestos'!$C$36))-((IF((IF('Supuestos'!$C$11*'Supuestos'!$C$12*'Supuestos'!$C$15=0,0,'Supuestos'!$C$10/1000/('Supuestos'!$C$11*'Supuestos'!$C$12*'Supuestos'!$C$15)))=0,0,'Supuestos'!$C$8/(IF('Supuestos'!$C$11*'Supuestos'!$C$12*'Supuestos'!$C$15=0,0,'Supuestos'!$C$10/1000/('Supuestos'!$C$11*'Supuestos'!$C$12*'Supuestos'!$C$15)))))*'Supuestos'!$C$37)-'Supuestos'!$C$38-'Supuestos'!$C$8)
B17: CPL × % de asistentes en vivo que solicitan → ganancia del lanzamiento
B18: La tabla del tráfico: hasta qué CPL seguís ganando según lo que mueve el webinar.
B19: CPL ↓ / % en vivo que solicita → | C19: 0.05 | D19: 0.08 | E19: 0.1 | F19: 0.12 | G19: 0.15 | H19: 0.2
B20: 0.5 | C20: =((((((((((IF($B20=0,0,'Supuestos'!$C$8/$B20))*'Supuestos'!$C$20)*C$19)+(((IF($B20=0,0,'Supuestos'!$C$8/$B20))*'Supuestos'!$C$21)*'Supuestos'!$C$26))*'Supuestos'!$C$27)*'Supuestos'!$C$24)+(((((((IF($B20=0,0,'Supuestos'!$C$8/$B20))*'Supuestos'!$C$20)*C$19)+(((IF($B20=0,0,'Supuestos'!$C$8/$B20))*'Supuestos'!$C$21)*'Supuestos'!$C$26))*'Supuestos'!$C$27)*'Supuestos'!$C$29)*'Supuestos'!$C$28)+(((((((IF($B20=0,0,'Supuestos'!$C$8/$B20))*'Supuestos'!$C$20)*C$19)+(((IF($B20=0,0,'Supuestos'!$C$8/$B20))*'Supuestos'!$C$21)*'Supuestos'!$C$26))*'Supuestos'!$C$27)*'Supuestos'!$C$31)*'Supuestos'!$C$30))*('Supuestos'!$C$41+'Supuestos'!$C$42+'Supuestos'!$C$43))*(1-'Supuestos'!$C$34-'Supuestos'!$C$35-'Supuestos'!$C$36))-((IF($B20=0,0,'Supuestos'!$C$8/$B20))*'Supuestos'!$C$37)-'Supuestos'!$C$38-'Supuestos'!$C$8) | D20: =((((((((((IF($B20=0,0,'Supuestos'!$C$8/$B20))*'Supuestos'!$C$20)*D$19)+(((IF($B20=0,0,'Supuestos'!$C$8/$B20))*'Supuestos'!$C$21)*'Supuestos'!$C$26))*'Supuestos'!$C$27)*'Supuestos'!$C$24)+(((((((IF($B20=0,0,'Supuestos'!$C$8/$B20))*'Supuestos'!$C$20)*D$19)+(((IF($B20=0,0,'Supuestos'!$C$8/$B20))*'Supuestos'!$C$21)*'Supuestos'!$C$26))*'Supuestos'!$C$27)*'Supuestos'!$C$29)*'Supuestos'!$C$28)+(((((((IF($B20=0,0,'Supuestos'!$C$8/$B20))*'Supuestos'!$C$20)*D$19)+(((IF($B20=0,0,'Supuestos'!$C$8/$B20))*'Supuestos'!$C$21)*'Supuestos'!$C$26))*'Supuestos'!$C$27)*'Supuestos'!$C$31)*'Supuestos'!$C$30))*('Supuestos'!$C$41+'Supuestos'!$C$42+'Supuestos'!$C$43))*(1-'Supuestos'!$C$34-'Supuestos'!$C$35-'Supuestos'!$C$36))-((IF($B20=0,0,'Supuestos'!$C$8/$B20))*'Supuestos'!$C$37)-'Supuestos'!$C$38-'Supuestos'!$C$8) | E20: =((((((((((IF($B20=0,0,'Supuestos'!$C$8/$B20))*'Supuestos'!$C$20)*E$19)+(((IF($B20=0,0,'Supuestos'!$C$8/$B20))*'Supuestos'!$C$21)*'Supuestos'!$C$26))*'Supuestos'!$C$27)*'Supuestos'!$C$24)+(((((((IF($B20=0,0,'Supuestos'!$C$8/$B20))*'Supuestos'!$C$20)*E$19)+(((IF($B20=0,0,'Supuestos'!$C$8/$B20))*'Supuestos'!$C$21)*'Supuestos'!$C$26))*'Supuestos'!$C$27)*'Supuestos'!$C$29)*'Supuestos'!$C$28)+(((((((IF($B20=0,0,'Supuestos'!$C$8/$B20))*'Supuestos'!$C$20)*E$19)+(((IF($B20=0,0,'Supuestos'!$C$8/$B20))*'Supuestos'!$C$21)*'Supuestos'!$C$26))*'Supuestos'!$C$27)*'Supuestos'!$C$31)*'Supuestos'!$C$30))*('Supuestos'!$C$41+'Supuestos'!$C$42+'Supuestos'!$C$43))*(1-'Supuestos'!$C$34-'Supuestos'!$C$35-'Supuestos'!$C$36))-((IF($B20=0,0,'Supuestos'!$C$8/$B20))*'Supuestos'!$C$37)-'Supuestos'!$C$38-'Supuestos'!$C$8) | F20: =((((((((((IF($B20=0,0,'Supuestos'!$C$8/$B20))*'Supuestos'!$C$20)*F$19)+(((IF($B20=0,0,'Supuestos'!$C$8/$B20))*'Supuestos'!$C$21)*'Supuestos'!$C$26))*'Supuestos'!$C$27)*'Supuestos'!$C$24)+(((((((IF($B20=0,0,'Supuestos'!$C$8/$B20))*'Supuestos'!$C$20)*F$19)+(((IF($B20=0,0,'Supuestos'!$C$8/$B20))*'Supuestos'!$C$21)*'Supuestos'!$C$26))*'Supuestos'!$C$27)*'Supuestos'!$C$29)*'Supuestos'!$C$28)+(((((((IF($B20=0,0,'Supuestos'!$C$8/$B20))*'Supuestos'!$C$20)*F$19)+(((IF($B20=0,0,'Supuestos'!$C$8/$B20))*'Supuestos'!$C$21)*'Supuestos'!$C$26))*'Supuestos'!$C$27)*'Supuestos'!$C$31)*'Supuestos'!$C$30))*('Supuestos'!$C$41+'Supuestos'!$C$42+'Supuestos'!$C$43))*(1-'Supuestos'!$C$34-'Supuestos'!$C$35-'Supuestos'!$C$36))-((IF($B20=0,0,'Supuestos'!$C$8/$B20))*'Supuestos'!$C$37)-'Supuestos'!$C$38-'Supuestos'!$C$8) | G20: =((((((((((IF($B20=0,0,'Supuestos'!$C$8/$B20))*'Supuestos'!$C$20)*G$19)+(((IF($B20=0,0,'Supuestos'!$C$8/$B20))*'Supuestos'!$C$21)*'Supuestos'!$C$26))*'Supuestos'!$C$27)*'Supuestos'!$C$24)+(((((((IF($B20=0,0,'Supuestos'!$C$8/$B20))*'Supuestos'!$C$20)*G$19)+(((IF($B20=0,0,'Supuestos'!$C$8/$B20))*'Supuestos'!$C$21)*'Supuestos'!$C$26))*'Supuestos'!$C$27)*'Supuestos'!$C$29)*'Supuestos'!$C$28)+(((((((IF($B20=0,0,'Supuestos'!$C$8/$B20))*'Supuestos'!$C$20)*G$19)+(((IF($B20=0,0,'Supuestos'!$C$8/$B20))*'Supuestos'!$C$21)*'Supuestos'!$C$26))*'Supuestos'!$C$27)*'Supuestos'!$C$31)*'Supuestos'!$C$30))*('Supuestos'!$C$41+'Supuestos'!$C$42+'Supuestos'!$C$43))*(1-'Supuestos'!$C$34-'Supuestos'!$C$35-'Supuestos'!$C$36))-((IF($B20=0,0,'Supuestos'!$C$8/$B20))*'Supuestos'!$C$37)-'Supuestos'!$C$38-'Supuestos'!$C$8) | H20: =((((((((((IF($B20=0,0,'Supuestos'!$C$8/$B20))*'Supuestos'!$C$20)*H$19)+(((IF($B20=0,0,'Supuestos'!$C$8/$B20))*'Supuestos'!$C$21)*'Supuestos'!$C$26))*'Supuestos'!$C$27)*'Supuestos'!$C$24)+(((((((IF($B20=0,0,'Supuestos'!$C$8/$B20))*'Supuestos'!$C$20)*H$19)+(((IF($B20=0,0,'Supuestos'!$C$8/$B20))*'Supuestos'!$C$21)*'Supuestos'!$C$26))*'Supuestos'!$C$27)*'Supuestos'!$C$29)*'Supuestos'!$C$28)+(((((((IF($B20=0,0,'Supuestos'!$C$8/$B20))*'Supuestos'!$C$20)*H$19)+(((IF($B20=0,0,'Supuestos'!$C$8/$B20))*'Supuestos'!$C$21)*'Supuestos'!$C$26))*'Supuestos'!$C$27)*'Supuestos'!$C$31)*'Supuestos'!$C$30))*('Supuestos'!$C$41+'Supuestos'!$C$42+'Supuestos'!$C$43))*(1-'Supuestos'!$C$34-'Supuestos'!$C$35-'Supuestos'!$C$36))-((IF($B20=0,0,'Supuestos'!$C$8/$B20))*'Supuestos'!$C$37)-'Supuestos'!$C$38-'Supuestos'!$C$8)
B21: 1 | C21: =((((((((((IF($B21=0,0,'Supuestos'!$C$8/$B21))*'Supuestos'!$C$20)*C$19)+(((IF($B21=0,0,'Supuestos'!$C$8/$B21))*'Supuestos'!$C$21)*'Supuestos'!$C$26))*'Supuestos'!$C$27)*'Supuestos'!$C$24)+(((((((IF($B21=0,0,'Supuestos'!$C$8/$B21))*'Supuestos'!$C$20)*C$19)+(((IF($B21=0,0,'Supuestos'!$C$8/$B21))*'Supuestos'!$C$21)*'Supuestos'!$C$26))*'Supuestos'!$C$27)*'Supuestos'!$C$29)*'Supuestos'!$C$28)+(((((((IF($B21=0,0,'Supuestos'!$C$8/$B21))*'Supuestos'!$C$20)*C$19)+(((IF($B21=0,0,'Supuestos'!$C$8/$B21))*'Supuestos'!$C$21)*'Supuestos'!$C$26))*'Supuestos'!$C$27)*'Supuestos'!$C$31)*'Supuestos'!$C$30))*('Supuestos'!$C$41+'Supuestos'!$C$42+'Supuestos'!$C$43))*(1-'Supuestos'!$C$34-'Supuestos'!$C$35-'Supuestos'!$C$36))-((IF($B21=0,0,'Supuestos'!$C$8/$B21))*'Supuestos'!$C$37)-'Supuestos'!$C$38-'Supuestos'!$C$8) | D21: =((((((((((IF($B21=0,0,'Supuestos'!$C$8/$B21))*'Supuestos'!$C$20)*D$19)+(((IF($B21=0,0,'Supuestos'!$C$8/$B21))*'Supuestos'!$C$21)*'Supuestos'!$C$26))*'Supuestos'!$C$27)*'Supuestos'!$C$24)+(((((((IF($B21=0,0,'Supuestos'!$C$8/$B21))*'Supuestos'!$C$20)*D$19)+(((IF($B21=0,0,'Supuestos'!$C$8/$B21))*'Supuestos'!$C$21)*'Supuestos'!$C$26))*'Supuestos'!$C$27)*'Supuestos'!$C$29)*'Supuestos'!$C$28)+(((((((IF($B21=0,0,'Supuestos'!$C$8/$B21))*'Supuestos'!$C$20)*D$19)+(((IF($B21=0,0,'Supuestos'!$C$8/$B21))*'Supuestos'!$C$21)*'Supuestos'!$C$26))*'Supuestos'!$C$27)*'Supuestos'!$C$31)*'Supuestos'!$C$30))*('Supuestos'!$C$41+'Supuestos'!$C$42+'Supuestos'!$C$43))*(1-'Supuestos'!$C$34-'Supuestos'!$C$35-'Supuestos'!$C$36))-((IF($B21=0,0,'Supuestos'!$C$8/$B21))*'Supuestos'!$C$37)-'Supuestos'!$C$38-'Supuestos'!$C$8) | E21: =((((((((((IF($B21=0,0,'Supuestos'!$C$8/$B21))*'Supuestos'!$C$20)*E$19)+(((IF($B21=0,0,'Supuestos'!$C$8/$B21))*'Supuestos'!$C$21)*'Supuestos'!$C$26))*'Supuestos'!$C$27)*'Supuestos'!$C$24)+(((((((IF($B21=0,0,'Supuestos'!$C$8/$B21))*'Supuestos'!$C$20)*E$19)+(((IF($B21=0,0,'Supuestos'!$C$8/$B21))*'Supuestos'!$C$21)*'Supuestos'!$C$26))*'Supuestos'!$C$27)*'Supuestos'!$C$29)*'Supuestos'!$C$28)+(((((((IF($B21=0,0,'Supuestos'!$C$8/$B21))*'Supuestos'!$C$20)*E$19)+(((IF($B21=0,0,'Supuestos'!$C$8/$B21))*'Supuestos'!$C$21)*'Supuestos'!$C$26))*'Supuestos'!$C$27)*'Supuestos'!$C$31)*'Supuestos'!$C$30))*('Supuestos'!$C$41+'Supuestos'!$C$42+'Supuestos'!$C$43))*(1-'Supuestos'!$C$34-'Supuestos'!$C$35-'Supuestos'!$C$36))-((IF($B21=0,0,'Supuestos'!$C$8/$B21))*'Supuestos'!$C$37)-'Supuestos'!$C$38-'Supuestos'!$C$8) | F21: =((((((((((IF($B21=0,0,'Supuestos'!$C$8/$B21))*'Supuestos'!$C$20)*F$19)+(((IF($B21=0,0,'Supuestos'!$C$8/$B21))*'Supuestos'!$C$21)*'Supuestos'!$C$26))*'Supuestos'!$C$27)*'Supuestos'!$C$24)+(((((((IF($B21=0,0,'Supuestos'!$C$8/$B21))*'Supuestos'!$C$20)*F$19)+(((IF($B21=0,0,'Supuestos'!$C$8/$B21))*'Supuestos'!$C$21)*'Supuestos'!$C$26))*'Supuestos'!$C$27)*'Supuestos'!$C$29)*'Supuestos'!$C$28)+(((((((IF($B21=0,0,'Supuestos'!$C$8/$B21))*'Supuestos'!$C$20)*F$19)+(((IF($B21=0,0,'Supuestos'!$C$8/$B21))*'Supuestos'!$C$21)*'Supuestos'!$C$26))*'Supuestos'!$C$27)*'Supuestos'!$C$31)*'Supuestos'!$C$30))*('Supuestos'!$C$41+'Supuestos'!$C$42+'Supuestos'!$C$43))*(1-'Supuestos'!$C$34-'Supuestos'!$C$35-'Supuestos'!$C$36))-((IF($B21=0,0,'Supuestos'!$C$8/$B21))*'Supuestos'!$C$37)-'Supuestos'!$C$38-'Supuestos'!$C$8) | G21: =((((((((((IF($B21=0,0,'Supuestos'!$C$8/$B21))*'Supuestos'!$C$20)*G$19)+(((IF($B21=0,0,'Supuestos'!$C$8/$B21))*'Supuestos'!$C$21)*'Supuestos'!$C$26))*'Supuestos'!$C$27)*'Supuestos'!$C$24)+(((((((IF($B21=0,0,'Supuestos'!$C$8/$B21))*'Supuestos'!$C$20)*G$19)+(((IF($B21=0,0,'Supuestos'!$C$8/$B21))*'Supuestos'!$C$21)*'Supuestos'!$C$26))*'Supuestos'!$C$27)*'Supuestos'!$C$29)*'Supuestos'!$C$28)+(((((((IF($B21=0,0,'Supuestos'!$C$8/$B21))*'Supuestos'!$C$20)*G$19)+(((IF($B21=0,0,'Supuestos'!$C$8/$B21))*'Supuestos'!$C$21)*'Supuestos'!$C$26))*'Supuestos'!$C$27)*'Supuestos'!$C$31)*'Supuestos'!$C$30))*('Supuestos'!$C$41+'Supuestos'!$C$42+'Supuestos'!$C$43))*(1-'Supuestos'!$C$34-'Supuestos'!$C$35-'Supuestos'!$C$36))-((IF($B21=0,0,'Supuestos'!$C$8/$B21))*'Supuestos'!$C$37)-'Supuestos'!$C$38-'Supuestos'!$C$8) | H21: =((((((((((IF($B21=0,0,'Supuestos'!$C$8/$B21))*'Supuestos'!$C$20)*H$19)+(((IF($B21=0,0,'Supuestos'!$C$8/$B21))*'Supuestos'!$C$21)*'Supuestos'!$C$26))*'Supuestos'!$C$27)*'Supuestos'!$C$24)+(((((((IF($B21=0,0,'Supuestos'!$C$8/$B21))*'Supuestos'!$C$20)*H$19)+(((IF($B21=0,0,'Supuestos'!$C$8/$B21))*'Supuestos'!$C$21)*'Supuestos'!$C$26))*'Supuestos'!$C$27)*'Supuestos'!$C$29)*'Supuestos'!$C$28)+(((((((IF($B21=0,0,'Supuestos'!$C$8/$B21))*'Supuestos'!$C$20)*H$19)+(((IF($B21=0,0,'Supuestos'!$C$8/$B21))*'Supuestos'!$C$21)*'Supuestos'!$C$26))*'Supuestos'!$C$27)*'Supuestos'!$C$31)*'Supuestos'!$C$30))*('Supuestos'!$C$41+'Supuestos'!$C$42+'Supuestos'!$C$43))*(1-'Supuestos'!$C$34-'Supuestos'!$C$35-'Supuestos'!$C$36))-((IF($B21=0,0,'Supuestos'!$C$8/$B21))*'Supuestos'!$C$37)-'Supuestos'!$C$38-'Supuestos'!$C$8)
B22: 1.5 | C22: =((((((((((IF($B22=0,0,'Supuestos'!$C$8/$B22))*'Supuestos'!$C$20)*C$19)+(((IF($B22=0,0,'Supuestos'!$C$8/$B22))*'Supuestos'!$C$21)*'Supuestos'!$C$26))*'Supuestos'!$C$27)*'Supuestos'!$C$24)+(((((((IF($B22=0,0,'Supuestos'!$C$8/$B22))*'Supuestos'!$C$20)*C$19)+(((IF($B22=0,0,'Supuestos'!$C$8/$B22))*'Supuestos'!$C$21)*'Supuestos'!$C$26))*'Supuestos'!$C$27)*'Supuestos'!$C$29)*'Supuestos'!$C$28)+(((((((IF($B22=0,0,'Supuestos'!$C$8/$B22))*'Supuestos'!$C$20)*C$19)+(((IF($B22=0,0,'Supuestos'!$C$8/$B22))*'Supuestos'!$C$21)*'Supuestos'!$C$26))*'Supuestos'!$C$27)*'Supuestos'!$C$31)*'Supuestos'!$C$30))*('Supuestos'!$C$41+'Supuestos'!$C$42+'Supuestos'!$C$43))*(1-'Supuestos'!$C$34-'Supuestos'!$C$35-'Supuestos'!$C$36))-((IF($B22=0,0,'Supuestos'!$C$8/$B22))*'Supuestos'!$C$37)-'Supuestos'!$C$38-'Supuestos'!$C$8) | D22: =((((((((((IF($B22=0,0,'Supuestos'!$C$8/$B22))*'Supuestos'!$C$20)*D$19)+(((IF($B22=0,0,'Supuestos'!$C$8/$B22))*'Supuestos'!$C$21)*'Supuestos'!$C$26))*'Supuestos'!$C$27)*'Supuestos'!$C$24)+(((((((IF($B22=0,0,'Supuestos'!$C$8/$B22))*'Supuestos'!$C$20)*D$19)+(((IF($B22=0,0,'Supuestos'!$C$8/$B22))*'Supuestos'!$C$21)*'Supuestos'!$C$26))*'Supuestos'!$C$27)*'Supuestos'!$C$29)*'Supuestos'!$C$28)+(((((((IF($B22=0,0,'Supuestos'!$C$8/$B22))*'Supuestos'!$C$20)*D$19)+(((IF($B22=0,0,'Supuestos'!$C$8/$B22))*'Supuestos'!$C$21)*'Supuestos'!$C$26))*'Supuestos'!$C$27)*'Supuestos'!$C$31)*'Supuestos'!$C$30))*('Supuestos'!$C$41+'Supuestos'!$C$42+'Supuestos'!$C$43))*(1-'Supuestos'!$C$34-'Supuestos'!$C$35-'Supuestos'!$C$36))-((IF($B22=0,0,'Supuestos'!$C$8/$B22))*'Supuestos'!$C$37)-'Supuestos'!$C$38-'Supuestos'!$C$8) | E22: =((((((((((IF($B22=0,0,'Supuestos'!$C$8/$B22))*'Supuestos'!$C$20)*E$19)+(((IF($B22=0,0,'Supuestos'!$C$8/$B22))*'Supuestos'!$C$21)*'Supuestos'!$C$26))*'Supuestos'!$C$27)*'Supuestos'!$C$24)+(((((((IF($B22=0,0,'Supuestos'!$C$8/$B22))*'Supuestos'!$C$20)*E$19)+(((IF($B22=0,0,'Supuestos'!$C$8/$B22))*'Supuestos'!$C$21)*'Supuestos'!$C$26))*'Supuestos'!$C$27)*'Supuestos'!$C$29)*'Supuestos'!$C$28)+(((((((IF($B22=0,0,'Supuestos'!$C$8/$B22))*'Supuestos'!$C$20)*E$19)+(((IF($B22=0,0,'Supuestos'!$C$8/$B22))*'Supuestos'!$C$21)*'Supuestos'!$C$26))*'Supuestos'!$C$27)*'Supuestos'!$C$31)*'Supuestos'!$C$30))*('Supuestos'!$C$41+'Supuestos'!$C$42+'Supuestos'!$C$43))*(1-'Supuestos'!$C$34-'Supuestos'!$C$35-'Supuestos'!$C$36))-((IF($B22=0,0,'Supuestos'!$C$8/$B22))*'Supuestos'!$C$37)-'Supuestos'!$C$38-'Supuestos'!$C$8) | F22: =((((((((((IF($B22=0,0,'Supuestos'!$C$8/$B22))*'Supuestos'!$C$20)*F$19)+(((IF($B22=0,0,'Supuestos'!$C$8/$B22))*'Supuestos'!$C$21)*'Supuestos'!$C$26))*'Supuestos'!$C$27)*'Supuestos'!$C$24)+(((((((IF($B22=0,0,'Supuestos'!$C$8/$B22))*'Supuestos'!$C$20)*F$19)+(((IF($B22=0,0,'Supuestos'!$C$8/$B22))*'Supuestos'!$C$21)*'Supuestos'!$C$26))*'Supuestos'!$C$27)*'Supuestos'!$C$29)*'Supuestos'!$C$28)+(((((((IF($B22=0,0,'Supuestos'!$C$8/$B22))*'Supuestos'!$C$20)*F$19)+(((IF($B22=0,0,'Supuestos'!$C$8/$B22))*'Supuestos'!$C$21)*'Supuestos'!$C$26))*'Supuestos'!$C$27)*'Supuestos'!$C$31)*'Supuestos'!$C$30))*('Supuestos'!$C$41+'Supuestos'!$C$42+'Supuestos'!$C$43))*(1-'Supuestos'!$C$34-'Supuestos'!$C$35-'Supuestos'!$C$36))-((IF($B22=0,0,'Supuestos'!$C$8/$B22))*'Supuestos'!$C$37)-'Supuestos'!$C$38-'Supuestos'!$C$8) | G22: =((((((((((IF($B22=0,0,'Supuestos'!$C$8/$B22))*'Supuestos'!$C$20)*G$19)+(((IF($B22=0,0,'Supuestos'!$C$8/$B22))*'Supuestos'!$C$21)*'Supuestos'!$C$26))*'Supuestos'!$C$27)*'Supuestos'!$C$24)+(((((((IF($B22=0,0,'Supuestos'!$C$8/$B22))*'Supuestos'!$C$20)*G$19)+(((IF($B22=0,0,'Supuestos'!$C$8/$B22))*'Supuestos'!$C$21)*'Supuestos'!$C$26))*'Supuestos'!$C$27)*'Supuestos'!$C$29)*'Supuestos'!$C$28)+(((((((IF($B22=0,0,'Supuestos'!$C$8/$B22))*'Supuestos'!$C$20)*G$19)+(((IF($B22=0,0,'Supuestos'!$C$8/$B22))*'Supuestos'!$C$21)*'Supuestos'!$C$26))*'Supuestos'!$C$27)*'Supuestos'!$C$31)*'Supuestos'!$C$30))*('Supuestos'!$C$41+'Supuestos'!$C$42+'Supuestos'!$C$43))*(1-'Supuestos'!$C$34-'Supuestos'!$C$35-'Supuestos'!$C$36))-((IF($B22=0,0,'Supuestos'!$C$8/$B22))*'Supuestos'!$C$37)-'Supuestos'!$C$38-'Supuestos'!$C$8) | H22: =((((((((((IF($B22=0,0,'Supuestos'!$C$8/$B22))*'Supuestos'!$C$20)*H$19)+(((IF($B22=0,0,'Supuestos'!$C$8/$B22))*'Supuestos'!$C$21)*'Supuestos'!$C$26))*'Supuestos'!$C$27)*'Supuestos'!$C$24)+(((((((IF($B22=0,0,'Supuestos'!$C$8/$B22))*'Supuestos'!$C$20)*H$19)+(((IF($B22=0,0,'Supuestos'!$C$8/$B22))*'Supuestos'!$C$21)*'Supuestos'!$C$26))*'Supuestos'!$C$27)*'Supuestos'!$C$29)*'Supuestos'!$C$28)+(((((((IF($B22=0,0,'Supuestos'!$C$8/$B22))*'Supuestos'!$C$20)*H$19)+(((IF($B22=0,0,'Supuestos'!$C$8/$B22))*'Supuestos'!$C$21)*'Supuestos'!$C$26))*'Supuestos'!$C$27)*'Supuestos'!$C$31)*'Supuestos'!$C$30))*('Supuestos'!$C$41+'Supuestos'!$C$42+'Supuestos'!$C$43))*(1-'Supuestos'!$C$34-'Supuestos'!$C$35-'Supuestos'!$C$36))-((IF($B22=0,0,'Supuestos'!$C$8/$B22))*'Supuestos'!$C$37)-'Supuestos'!$C$38-'Supuestos'!$C$8)
B23: 2 | C23: =((((((((((IF($B23=0,0,'Supuestos'!$C$8/$B23))*'Supuestos'!$C$20)*C$19)+(((IF($B23=0,0,'Supuestos'!$C$8/$B23))*'Supuestos'!$C$21)*'Supuestos'!$C$26))*'Supuestos'!$C$27)*'Supuestos'!$C$24)+(((((((IF($B23=0,0,'Supuestos'!$C$8/$B23))*'Supuestos'!$C$20)*C$19)+(((IF($B23=0,0,'Supuestos'!$C$8/$B23))*'Supuestos'!$C$21)*'Supuestos'!$C$26))*'Supuestos'!$C$27)*'Supuestos'!$C$29)*'Supuestos'!$C$28)+(((((((IF($B23=0,0,'Supuestos'!$C$8/$B23))*'Supuestos'!$C$20)*C$19)+(((IF($B23=0,0,'Supuestos'!$C$8/$B23))*'Supuestos'!$C$21)*'Supuestos'!$C$26))*'Supuestos'!$C$27)*'Supuestos'!$C$31)*'Supuestos'!$C$30))*('Supuestos'!$C$41+'Supuestos'!$C$42+'Supuestos'!$C$43))*(1-'Supuestos'!$C$34-'Supuestos'!$C$35-'Supuestos'!$C$36))-((IF($B23=0,0,'Supuestos'!$C$8/$B23))*'Supuestos'!$C$37)-'Supuestos'!$C$38-'Supuestos'!$C$8) | D23: =((((((((((IF($B23=0,0,'Supuestos'!$C$8/$B23))*'Supuestos'!$C$20)*D$19)+(((IF($B23=0,0,'Supuestos'!$C$8/$B23))*'Supuestos'!$C$21)*'Supuestos'!$C$26))*'Supuestos'!$C$27)*'Supuestos'!$C$24)+(((((((IF($B23=0,0,'Supuestos'!$C$8/$B23))*'Supuestos'!$C$20)*D$19)+(((IF($B23=0,0,'Supuestos'!$C$8/$B23))*'Supuestos'!$C$21)*'Supuestos'!$C$26))*'Supuestos'!$C$27)*'Supuestos'!$C$29)*'Supuestos'!$C$28)+(((((((IF($B23=0,0,'Supuestos'!$C$8/$B23))*'Supuestos'!$C$20)*D$19)+(((IF($B23=0,0,'Supuestos'!$C$8/$B23))*'Supuestos'!$C$21)*'Supuestos'!$C$26))*'Supuestos'!$C$27)*'Supuestos'!$C$31)*'Supuestos'!$C$30))*('Supuestos'!$C$41+'Supuestos'!$C$42+'Supuestos'!$C$43))*(1-'Supuestos'!$C$34-'Supuestos'!$C$35-'Supuestos'!$C$36))-((IF($B23=0,0,'Supuestos'!$C$8/$B23))*'Supuestos'!$C$37)-'Supuestos'!$C$38-'Supuestos'!$C$8) | E23: =((((((((((IF($B23=0,0,'Supuestos'!$C$8/$B23))*'Supuestos'!$C$20)*E$19)+(((IF($B23=0,0,'Supuestos'!$C$8/$B23))*'Supuestos'!$C$21)*'Supuestos'!$C$26))*'Supuestos'!$C$27)*'Supuestos'!$C$24)+(((((((IF($B23=0,0,'Supuestos'!$C$8/$B23))*'Supuestos'!$C$20)*E$19)+(((IF($B23=0,0,'Supuestos'!$C$8/$B23))*'Supuestos'!$C$21)*'Supuestos'!$C$26))*'Supuestos'!$C$27)*'Supuestos'!$C$29)*'Supuestos'!$C$28)+(((((((IF($B23=0,0,'Supuestos'!$C$8/$B23))*'Supuestos'!$C$20)*E$19)+(((IF($B23=0,0,'Supuestos'!$C$8/$B23))*'Supuestos'!$C$21)*'Supuestos'!$C$26))*'Supuestos'!$C$27)*'Supuestos'!$C$31)*'Supuestos'!$C$30))*('Supuestos'!$C$41+'Supuestos'!$C$42+'Supuestos'!$C$43))*(1-'Supuestos'!$C$34-'Supuestos'!$C$35-'Supuestos'!$C$36))-((IF($B23=0,0,'Supuestos'!$C$8/$B23))*'Supuestos'!$C$37)-'Supuestos'!$C$38-'Supuestos'!$C$8) | F23: =((((((((((IF($B23=0,0,'Supuestos'!$C$8/$B23))*'Supuestos'!$C$20)*F$19)+(((IF($B23=0,0,'Supuestos'!$C$8/$B23))*'Supuestos'!$C$21)*'Supuestos'!$C$26))*'Supuestos'!$C$27)*'Supuestos'!$C$24)+(((((((IF($B23=0,0,'Supuestos'!$C$8/$B23))*'Supuestos'!$C$20)*F$19)+(((IF($B23=0,0,'Supuestos'!$C$8/$B23))*'Supuestos'!$C$21)*'Supuestos'!$C$26))*'Supuestos'!$C$27)*'Supuestos'!$C$29)*'Supuestos'!$C$28)+(((((((IF($B23=0,0,'Supuestos'!$C$8/$B23))*'Supuestos'!$C$20)*F$19)+(((IF($B23=0,0,'Supuestos'!$C$8/$B23))*'Supuestos'!$C$21)*'Supuestos'!$C$26))*'Supuestos'!$C$27)*'Supuestos'!$C$31)*'Supuestos'!$C$30))*('Supuestos'!$C$41+'Supuestos'!$C$42+'Supuestos'!$C$43))*(1-'Supuestos'!$C$34-'Supuestos'!$C$35-'Supuestos'!$C$36))-((IF($B23=0,0,'Supuestos'!$C$8/$B23))*'Supuestos'!$C$37)-'Supuestos'!$C$38-'Supuestos'!$C$8) | G23: =((((((((((IF($B23=0,0,'Supuestos'!$C$8/$B23))*'Supuestos'!$C$20)*G$19)+(((IF($B23=0,0,'Supuestos'!$C$8/$B23))*'Supuestos'!$C$21)*'Supuestos'!$C$26))*'Supuestos'!$C$27)*'Supuestos'!$C$24)+(((((((IF($B23=0,0,'Supuestos'!$C$8/$B23))*'Supuestos'!$C$20)*G$19)+(((IF($B23=0,0,'Supuestos'!$C$8/$B23))*'Supuestos'!$C$21)*'Supuestos'!$C$26))*'Supuestos'!$C$27)*'Supuestos'!$C$29)*'Supuestos'!$C$28)+(((((((IF($B23=0,0,'Supuestos'!$C$8/$B23))*'Supuestos'!$C$20)*G$19)+(((IF($B23=0,0,'Supuestos'!$C$8/$B23))*'Supuestos'!$C$21)*'Supuestos'!$C$26))*'Supuestos'!$C$27)*'Supuestos'!$C$31)*'Supuestos'!$C$30))*('Supuestos'!$C$41+'Supuestos'!$C$42+'Supuestos'!$C$43))*(1-'Supuestos'!$C$34-'Supuestos'!$C$35-'Supuestos'!$C$36))-((IF($B23=0,0,'Supuestos'!$C$8/$B23))*'Supuestos'!$C$37)-'Supuestos'!$C$38-'Supuestos'!$C$8) | H23: =((((((((((IF($B23=0,0,'Supuestos'!$C$8/$B23))*'Supuestos'!$C$20)*H$19)+(((IF($B23=0,0,'Supuestos'!$C$8/$B23))*'Supuestos'!$C$21)*'Supuestos'!$C$26))*'Supuestos'!$C$27)*'Supuestos'!$C$24)+(((((((IF($B23=0,0,'Supuestos'!$C$8/$B23))*'Supuestos'!$C$20)*H$19)+(((IF($B23=0,0,'Supuestos'!$C$8/$B23))*'Supuestos'!$C$21)*'Supuestos'!$C$26))*'Supuestos'!$C$27)*'Supuestos'!$C$29)*'Supuestos'!$C$28)+(((((((IF($B23=0,0,'Supuestos'!$C$8/$B23))*'Supuestos'!$C$20)*H$19)+(((IF($B23=0,0,'Supuestos'!$C$8/$B23))*'Supuestos'!$C$21)*'Supuestos'!$C$26))*'Supuestos'!$C$27)*'Supuestos'!$C$31)*'Supuestos'!$C$30))*('Supuestos'!$C$41+'Supuestos'!$C$42+'Supuestos'!$C$43))*(1-'Supuestos'!$C$34-'Supuestos'!$C$35-'Supuestos'!$C$36))-((IF($B23=0,0,'Supuestos'!$C$8/$B23))*'Supuestos'!$C$37)-'Supuestos'!$C$38-'Supuestos'!$C$8)
B24: 3 | C24: =((((((((((IF($B24=0,0,'Supuestos'!$C$8/$B24))*'Supuestos'!$C$20)*C$19)+(((IF($B24=0,0,'Supuestos'!$C$8/$B24))*'Supuestos'!$C$21)*'Supuestos'!$C$26))*'Supuestos'!$C$27)*'Supuestos'!$C$24)+(((((((IF($B24=0,0,'Supuestos'!$C$8/$B24))*'Supuestos'!$C$20)*C$19)+(((IF($B24=0,0,'Supuestos'!$C$8/$B24))*'Supuestos'!$C$21)*'Supuestos'!$C$26))*'Supuestos'!$C$27)*'Supuestos'!$C$29)*'Supuestos'!$C$28)+(((((((IF($B24=0,0,'Supuestos'!$C$8/$B24))*'Supuestos'!$C$20)*C$19)+(((IF($B24=0,0,'Supuestos'!$C$8/$B24))*'Supuestos'!$C$21)*'Supuestos'!$C$26))*'Supuestos'!$C$27)*'Supuestos'!$C$31)*'Supuestos'!$C$30))*('Supuestos'!$C$41+'Supuestos'!$C$42+'Supuestos'!$C$43))*(1-'Supuestos'!$C$34-'Supuestos'!$C$35-'Supuestos'!$C$36))-((IF($B24=0,0,'Supuestos'!$C$8/$B24))*'Supuestos'!$C$37)-'Supuestos'!$C$38-'Supuestos'!$C$8) | D24: =((((((((((IF($B24=0,0,'Supuestos'!$C$8/$B24))*'Supuestos'!$C$20)*D$19)+(((IF($B24=0,0,'Supuestos'!$C$8/$B24))*'Supuestos'!$C$21)*'Supuestos'!$C$26))*'Supuestos'!$C$27)*'Supuestos'!$C$24)+(((((((IF($B24=0,0,'Supuestos'!$C$8/$B24))*'Supuestos'!$C$20)*D$19)+(((IF($B24=0,0,'Supuestos'!$C$8/$B24))*'Supuestos'!$C$21)*'Supuestos'!$C$26))*'Supuestos'!$C$27)*'Supuestos'!$C$29)*'Supuestos'!$C$28)+(((((((IF($B24=0,0,'Supuestos'!$C$8/$B24))*'Supuestos'!$C$20)*D$19)+(((IF($B24=0,0,'Supuestos'!$C$8/$B24))*'Supuestos'!$C$21)*'Supuestos'!$C$26))*'Supuestos'!$C$27)*'Supuestos'!$C$31)*'Supuestos'!$C$30))*('Supuestos'!$C$41+'Supuestos'!$C$42+'Supuestos'!$C$43))*(1-'Supuestos'!$C$34-'Supuestos'!$C$35-'Supuestos'!$C$36))-((IF($B24=0,0,'Supuestos'!$C$8/$B24))*'Supuestos'!$C$37)-'Supuestos'!$C$38-'Supuestos'!$C$8) | E24: =((((((((((IF($B24=0,0,'Supuestos'!$C$8/$B24))*'Supuestos'!$C$20)*E$19)+(((IF($B24=0,0,'Supuestos'!$C$8/$B24))*'Supuestos'!$C$21)*'Supuestos'!$C$26))*'Supuestos'!$C$27)*'Supuestos'!$C$24)+(((((((IF($B24=0,0,'Supuestos'!$C$8/$B24))*'Supuestos'!$C$20)*E$19)+(((IF($B24=0,0,'Supuestos'!$C$8/$B24))*'Supuestos'!$C$21)*'Supuestos'!$C$26))*'Supuestos'!$C$27)*'Supuestos'!$C$29)*'Supuestos'!$C$28)+(((((((IF($B24=0,0,'Supuestos'!$C$8/$B24))*'Supuestos'!$C$20)*E$19)+(((IF($B24=0,0,'Supuestos'!$C$8/$B24))*'Supuestos'!$C$21)*'Supuestos'!$C$26))*'Supuestos'!$C$27)*'Supuestos'!$C$31)*'Supuestos'!$C$30))*('Supuestos'!$C$41+'Supuestos'!$C$42+'Supuestos'!$C$43))*(1-'Supuestos'!$C$34-'Supuestos'!$C$35-'Supuestos'!$C$36))-((IF($B24=0,0,'Supuestos'!$C$8/$B24))*'Supuestos'!$C$37)-'Supuestos'!$C$38-'Supuestos'!$C$8) | F24: =((((((((((IF($B24=0,0,'Supuestos'!$C$8/$B24))*'Supuestos'!$C$20)*F$19)+(((IF($B24=0,0,'Supuestos'!$C$8/$B24))*'Supuestos'!$C$21)*'Supuestos'!$C$26))*'Supuestos'!$C$27)*'Supuestos'!$C$24)+(((((((IF($B24=0,0,'Supuestos'!$C$8/$B24))*'Supuestos'!$C$20)*F$19)+(((IF($B24=0,0,'Supuestos'!$C$8/$B24))*'Supuestos'!$C$21)*'Supuestos'!$C$26))*'Supuestos'!$C$27)*'Supuestos'!$C$29)*'Supuestos'!$C$28)+(((((((IF($B24=0,0,'Supuestos'!$C$8/$B24))*'Supuestos'!$C$20)*F$19)+(((IF($B24=0,0,'Supuestos'!$C$8/$B24))*'Supuestos'!$C$21)*'Supuestos'!$C$26))*'Supuestos'!$C$27)*'Supuestos'!$C$31)*'Supuestos'!$C$30))*('Supuestos'!$C$41+'Supuestos'!$C$42+'Supuestos'!$C$43))*(1-'Supuestos'!$C$34-'Supuestos'!$C$35-'Supuestos'!$C$36))-((IF($B24=0,0,'Supuestos'!$C$8/$B24))*'Supuestos'!$C$37)-'Supuestos'!$C$38-'Supuestos'!$C$8) | G24: =((((((((((IF($B24=0,0,'Supuestos'!$C$8/$B24))*'Supuestos'!$C$20)*G$19)+(((IF($B24=0,0,'Supuestos'!$C$8/$B24))*'Supuestos'!$C$21)*'Supuestos'!$C$26))*'Supuestos'!$C$27)*'Supuestos'!$C$24)+(((((((IF($B24=0,0,'Supuestos'!$C$8/$B24))*'Supuestos'!$C$20)*G$19)+(((IF($B24=0,0,'Supuestos'!$C$8/$B24))*'Supuestos'!$C$21)*'Supuestos'!$C$26))*'Supuestos'!$C$27)*'Supuestos'!$C$29)*'Supuestos'!$C$28)+(((((((IF($B24=0,0,'Supuestos'!$C$8/$B24))*'Supuestos'!$C$20)*G$19)+(((IF($B24=0,0,'Supuestos'!$C$8/$B24))*'Supuestos'!$C$21)*'Supuestos'!$C$26))*'Supuestos'!$C$27)*'Supuestos'!$C$31)*'Supuestos'!$C$30))*('Supuestos'!$C$41+'Supuestos'!$C$42+'Supuestos'!$C$43))*(1-'Supuestos'!$C$34-'Supuestos'!$C$35-'Supuestos'!$C$36))-((IF($B24=0,0,'Supuestos'!$C$8/$B24))*'Supuestos'!$C$37)-'Supuestos'!$C$38-'Supuestos'!$C$8) | H24: =((((((((((IF($B24=0,0,'Supuestos'!$C$8/$B24))*'Supuestos'!$C$20)*H$19)+(((IF($B24=0,0,'Supuestos'!$C$8/$B24))*'Supuestos'!$C$21)*'Supuestos'!$C$26))*'Supuestos'!$C$27)*'Supuestos'!$C$24)+(((((((IF($B24=0,0,'Supuestos'!$C$8/$B24))*'Supuestos'!$C$20)*H$19)+(((IF($B24=0,0,'Supuestos'!$C$8/$B24))*'Supuestos'!$C$21)*'Supuestos'!$C$26))*'Supuestos'!$C$27)*'Supuestos'!$C$29)*'Supuestos'!$C$28)+(((((((IF($B24=0,0,'Supuestos'!$C$8/$B24))*'Supuestos'!$C$20)*H$19)+(((IF($B24=0,0,'Supuestos'!$C$8/$B24))*'Supuestos'!$C$21)*'Supuestos'!$C$26))*'Supuestos'!$C$27)*'Supuestos'!$C$31)*'Supuestos'!$C$30))*('Supuestos'!$C$41+'Supuestos'!$C$42+'Supuestos'!$C$43))*(1-'Supuestos'!$C$34-'Supuestos'!$C$35-'Supuestos'!$C$36))-((IF($B24=0,0,'Supuestos'!$C$8/$B24))*'Supuestos'!$C$37)-'Supuestos'!$C$38-'Supuestos'!$C$8)
B25: 4 | C25: =((((((((((IF($B25=0,0,'Supuestos'!$C$8/$B25))*'Supuestos'!$C$20)*C$19)+(((IF($B25=0,0,'Supuestos'!$C$8/$B25))*'Supuestos'!$C$21)*'Supuestos'!$C$26))*'Supuestos'!$C$27)*'Supuestos'!$C$24)+(((((((IF($B25=0,0,'Supuestos'!$C$8/$B25))*'Supuestos'!$C$20)*C$19)+(((IF($B25=0,0,'Supuestos'!$C$8/$B25))*'Supuestos'!$C$21)*'Supuestos'!$C$26))*'Supuestos'!$C$27)*'Supuestos'!$C$29)*'Supuestos'!$C$28)+(((((((IF($B25=0,0,'Supuestos'!$C$8/$B25))*'Supuestos'!$C$20)*C$19)+(((IF($B25=0,0,'Supuestos'!$C$8/$B25))*'Supuestos'!$C$21)*'Supuestos'!$C$26))*'Supuestos'!$C$27)*'Supuestos'!$C$31)*'Supuestos'!$C$30))*('Supuestos'!$C$41+'Supuestos'!$C$42+'Supuestos'!$C$43))*(1-'Supuestos'!$C$34-'Supuestos'!$C$35-'Supuestos'!$C$36))-((IF($B25=0,0,'Supuestos'!$C$8/$B25))*'Supuestos'!$C$37)-'Supuestos'!$C$38-'Supuestos'!$C$8) | D25: =((((((((((IF($B25=0,0,'Supuestos'!$C$8/$B25))*'Supuestos'!$C$20)*D$19)+(((IF($B25=0,0,'Supuestos'!$C$8/$B25))*'Supuestos'!$C$21)*'Supuestos'!$C$26))*'Supuestos'!$C$27)*'Supuestos'!$C$24)+(((((((IF($B25=0,0,'Supuestos'!$C$8/$B25))*'Supuestos'!$C$20)*D$19)+(((IF($B25=0,0,'Supuestos'!$C$8/$B25))*'Supuestos'!$C$21)*'Supuestos'!$C$26))*'Supuestos'!$C$27)*'Supuestos'!$C$29)*'Supuestos'!$C$28)+(((((((IF($B25=0,0,'Supuestos'!$C$8/$B25))*'Supuestos'!$C$20)*D$19)+(((IF($B25=0,0,'Supuestos'!$C$8/$B25))*'Supuestos'!$C$21)*'Supuestos'!$C$26))*'Supuestos'!$C$27)*'Supuestos'!$C$31)*'Supuestos'!$C$30))*('Supuestos'!$C$41+'Supuestos'!$C$42+'Supuestos'!$C$43))*(1-'Supuestos'!$C$34-'Supuestos'!$C$35-'Supuestos'!$C$36))-((IF($B25=0,0,'Supuestos'!$C$8/$B25))*'Supuestos'!$C$37)-'Supuestos'!$C$38-'Supuestos'!$C$8) | E25: =((((((((((IF($B25=0,0,'Supuestos'!$C$8/$B25))*'Supuestos'!$C$20)*E$19)+(((IF($B25=0,0,'Supuestos'!$C$8/$B25))*'Supuestos'!$C$21)*'Supuestos'!$C$26))*'Supuestos'!$C$27)*'Supuestos'!$C$24)+(((((((IF($B25=0,0,'Supuestos'!$C$8/$B25))*'Supuestos'!$C$20)*E$19)+(((IF($B25=0,0,'Supuestos'!$C$8/$B25))*'Supuestos'!$C$21)*'Supuestos'!$C$26))*'Supuestos'!$C$27)*'Supuestos'!$C$29)*'Supuestos'!$C$28)+(((((((IF($B25=0,0,'Supuestos'!$C$8/$B25))*'Supuestos'!$C$20)*E$19)+(((IF($B25=0,0,'Supuestos'!$C$8/$B25))*'Supuestos'!$C$21)*'Supuestos'!$C$26))*'Supuestos'!$C$27)*'Supuestos'!$C$31)*'Supuestos'!$C$30))*('Supuestos'!$C$41+'Supuestos'!$C$42+'Supuestos'!$C$43))*(1-'Supuestos'!$C$34-'Supuestos'!$C$35-'Supuestos'!$C$36))-((IF($B25=0,0,'Supuestos'!$C$8/$B25))*'Supuestos'!$C$37)-'Supuestos'!$C$38-'Supuestos'!$C$8) | F25: =((((((((((IF($B25=0,0,'Supuestos'!$C$8/$B25))*'Supuestos'!$C$20)*F$19)+(((IF($B25=0,0,'Supuestos'!$C$8/$B25))*'Supuestos'!$C$21)*'Supuestos'!$C$26))*'Supuestos'!$C$27)*'Supuestos'!$C$24)+(((((((IF($B25=0,0,'Supuestos'!$C$8/$B25))*'Supuestos'!$C$20)*F$19)+(((IF($B25=0,0,'Supuestos'!$C$8/$B25))*'Supuestos'!$C$21)*'Supuestos'!$C$26))*'Supuestos'!$C$27)*'Supuestos'!$C$29)*'Supuestos'!$C$28)+(((((((IF($B25=0,0,'Supuestos'!$C$8/$B25))*'Supuestos'!$C$20)*F$19)+(((IF($B25=0,0,'Supuestos'!$C$8/$B25))*'Supuestos'!$C$21)*'Supuestos'!$C$26))*'Supuestos'!$C$27)*'Supuestos'!$C$31)*'Supuestos'!$C$30))*('Supuestos'!$C$41+'Supuestos'!$C$42+'Supuestos'!$C$43))*(1-'Supuestos'!$C$34-'Supuestos'!$C$35-'Supuestos'!$C$36))-((IF($B25=0,0,'Supuestos'!$C$8/$B25))*'Supuestos'!$C$37)-'Supuestos'!$C$38-'Supuestos'!$C$8) | G25: =((((((((((IF($B25=0,0,'Supuestos'!$C$8/$B25))*'Supuestos'!$C$20)*G$19)+(((IF($B25=0,0,'Supuestos'!$C$8/$B25))*'Supuestos'!$C$21)*'Supuestos'!$C$26))*'Supuestos'!$C$27)*'Supuestos'!$C$24)+(((((((IF($B25=0,0,'Supuestos'!$C$8/$B25))*'Supuestos'!$C$20)*G$19)+(((IF($B25=0,0,'Supuestos'!$C$8/$B25))*'Supuestos'!$C$21)*'Supuestos'!$C$26))*'Supuestos'!$C$27)*'Supuestos'!$C$29)*'Supuestos'!$C$28)+(((((((IF($B25=0,0,'Supuestos'!$C$8/$B25))*'Supuestos'!$C$20)*G$19)+(((IF($B25=0,0,'Supuestos'!$C$8/$B25))*'Supuestos'!$C$21)*'Supuestos'!$C$26))*'Supuestos'!$C$27)*'Supuestos'!$C$31)*'Supuestos'!$C$30))*('Supuestos'!$C$41+'Supuestos'!$C$42+'Supuestos'!$C$43))*(1-'Supuestos'!$C$34-'Supuestos'!$C$35-'Supuestos'!$C$36))-((IF($B25=0,0,'Supuestos'!$C$8/$B25))*'Supuestos'!$C$37)-'Supuestos'!$C$38-'Supuestos'!$C$8) | H25: =((((((((((IF($B25=0,0,'Supuestos'!$C$8/$B25))*'Supuestos'!$C$20)*H$19)+(((IF($B25=0,0,'Supuestos'!$C$8/$B25))*'Supuestos'!$C$21)*'Supuestos'!$C$26))*'Supuestos'!$C$27)*'Supuestos'!$C$24)+(((((((IF($B25=0,0,'Supuestos'!$C$8/$B25))*'Supuestos'!$C$20)*H$19)+(((IF($B25=0,0,'Supuestos'!$C$8/$B25))*'Supuestos'!$C$21)*'Supuestos'!$C$26))*'Supuestos'!$C$27)*'Supuestos'!$C$29)*'Supuestos'!$C$28)+(((((((IF($B25=0,0,'Supuestos'!$C$8/$B25))*'Supuestos'!$C$20)*H$19)+(((IF($B25=0,0,'Supuestos'!$C$8/$B25))*'Supuestos'!$C$21)*'Supuestos'!$C$26))*'Supuestos'!$C$27)*'Supuestos'!$C$31)*'Supuestos'!$C$30))*('Supuestos'!$C$41+'Supuestos'!$C$42+'Supuestos'!$C$43))*(1-'Supuestos'!$C$34-'Supuestos'!$C$35-'Supuestos'!$C$36))-((IF($B25=0,0,'Supuestos'!$C$8/$B25))*'Supuestos'!$C$37)-'Supuestos'!$C$38-'Supuestos'!$C$8)
B26: 6 | C26: =((((((((((IF($B26=0,0,'Supuestos'!$C$8/$B26))*'Supuestos'!$C$20)*C$19)+(((IF($B26=0,0,'Supuestos'!$C$8/$B26))*'Supuestos'!$C$21)*'Supuestos'!$C$26))*'Supuestos'!$C$27)*'Supuestos'!$C$24)+(((((((IF($B26=0,0,'Supuestos'!$C$8/$B26))*'Supuestos'!$C$20)*C$19)+(((IF($B26=0,0,'Supuestos'!$C$8/$B26))*'Supuestos'!$C$21)*'Supuestos'!$C$26))*'Supuestos'!$C$27)*'Supuestos'!$C$29)*'Supuestos'!$C$28)+(((((((IF($B26=0,0,'Supuestos'!$C$8/$B26))*'Supuestos'!$C$20)*C$19)+(((IF($B26=0,0,'Supuestos'!$C$8/$B26))*'Supuestos'!$C$21)*'Supuestos'!$C$26))*'Supuestos'!$C$27)*'Supuestos'!$C$31)*'Supuestos'!$C$30))*('Supuestos'!$C$41+'Supuestos'!$C$42+'Supuestos'!$C$43))*(1-'Supuestos'!$C$34-'Supuestos'!$C$35-'Supuestos'!$C$36))-((IF($B26=0,0,'Supuestos'!$C$8/$B26))*'Supuestos'!$C$37)-'Supuestos'!$C$38-'Supuestos'!$C$8) | D26: =((((((((((IF($B26=0,0,'Supuestos'!$C$8/$B26))*'Supuestos'!$C$20)*D$19)+(((IF($B26=0,0,'Supuestos'!$C$8/$B26))*'Supuestos'!$C$21)*'Supuestos'!$C$26))*'Supuestos'!$C$27)*'Supuestos'!$C$24)+(((((((IF($B26=0,0,'Supuestos'!$C$8/$B26))*'Supuestos'!$C$20)*D$19)+(((IF($B26=0,0,'Supuestos'!$C$8/$B26))*'Supuestos'!$C$21)*'Supuestos'!$C$26))*'Supuestos'!$C$27)*'Supuestos'!$C$29)*'Supuestos'!$C$28)+(((((((IF($B26=0,0,'Supuestos'!$C$8/$B26))*'Supuestos'!$C$20)*D$19)+(((IF($B26=0,0,'Supuestos'!$C$8/$B26))*'Supuestos'!$C$21)*'Supuestos'!$C$26))*'Supuestos'!$C$27)*'Supuestos'!$C$31)*'Supuestos'!$C$30))*('Supuestos'!$C$41+'Supuestos'!$C$42+'Supuestos'!$C$43))*(1-'Supuestos'!$C$34-'Supuestos'!$C$35-'Supuestos'!$C$36))-((IF($B26=0,0,'Supuestos'!$C$8/$B26))*'Supuestos'!$C$37)-'Supuestos'!$C$38-'Supuestos'!$C$8) | E26: =((((((((((IF($B26=0,0,'Supuestos'!$C$8/$B26))*'Supuestos'!$C$20)*E$19)+(((IF($B26=0,0,'Supuestos'!$C$8/$B26))*'Supuestos'!$C$21)*'Supuestos'!$C$26))*'Supuestos'!$C$27)*'Supuestos'!$C$24)+(((((((IF($B26=0,0,'Supuestos'!$C$8/$B26))*'Supuestos'!$C$20)*E$19)+(((IF($B26=0,0,'Supuestos'!$C$8/$B26))*'Supuestos'!$C$21)*'Supuestos'!$C$26))*'Supuestos'!$C$27)*'Supuestos'!$C$29)*'Supuestos'!$C$28)+(((((((IF($B26=0,0,'Supuestos'!$C$8/$B26))*'Supuestos'!$C$20)*E$19)+(((IF($B26=0,0,'Supuestos'!$C$8/$B26))*'Supuestos'!$C$21)*'Supuestos'!$C$26))*'Supuestos'!$C$27)*'Supuestos'!$C$31)*'Supuestos'!$C$30))*('Supuestos'!$C$41+'Supuestos'!$C$42+'Supuestos'!$C$43))*(1-'Supuestos'!$C$34-'Supuestos'!$C$35-'Supuestos'!$C$36))-((IF($B26=0,0,'Supuestos'!$C$8/$B26))*'Supuestos'!$C$37)-'Supuestos'!$C$38-'Supuestos'!$C$8) | F26: =((((((((((IF($B26=0,0,'Supuestos'!$C$8/$B26))*'Supuestos'!$C$20)*F$19)+(((IF($B26=0,0,'Supuestos'!$C$8/$B26))*'Supuestos'!$C$21)*'Supuestos'!$C$26))*'Supuestos'!$C$27)*'Supuestos'!$C$24)+(((((((IF($B26=0,0,'Supuestos'!$C$8/$B26))*'Supuestos'!$C$20)*F$19)+(((IF($B26=0,0,'Supuestos'!$C$8/$B26))*'Supuestos'!$C$21)*'Supuestos'!$C$26))*'Supuestos'!$C$27)*'Supuestos'!$C$29)*'Supuestos'!$C$28)+(((((((IF($B26=0,0,'Supuestos'!$C$8/$B26))*'Supuestos'!$C$20)*F$19)+(((IF($B26=0,0,'Supuestos'!$C$8/$B26))*'Supuestos'!$C$21)*'Supuestos'!$C$26))*'Supuestos'!$C$27)*'Supuestos'!$C$31)*'Supuestos'!$C$30))*('Supuestos'!$C$41+'Supuestos'!$C$42+'Supuestos'!$C$43))*(1-'Supuestos'!$C$34-'Supuestos'!$C$35-'Supuestos'!$C$36))-((IF($B26=0,0,'Supuestos'!$C$8/$B26))*'Supuestos'!$C$37)-'Supuestos'!$C$38-'Supuestos'!$C$8) | G26: =((((((((((IF($B26=0,0,'Supuestos'!$C$8/$B26))*'Supuestos'!$C$20)*G$19)+(((IF($B26=0,0,'Supuestos'!$C$8/$B26))*'Supuestos'!$C$21)*'Supuestos'!$C$26))*'Supuestos'!$C$27)*'Supuestos'!$C$24)+(((((((IF($B26=0,0,'Supuestos'!$C$8/$B26))*'Supuestos'!$C$20)*G$19)+(((IF($B26=0,0,'Supuestos'!$C$8/$B26))*'Supuestos'!$C$21)*'Supuestos'!$C$26))*'Supuestos'!$C$27)*'Supuestos'!$C$29)*'Supuestos'!$C$28)+(((((((IF($B26=0,0,'Supuestos'!$C$8/$B26))*'Supuestos'!$C$20)*G$19)+(((IF($B26=0,0,'Supuestos'!$C$8/$B26))*'Supuestos'!$C$21)*'Supuestos'!$C$26))*'Supuestos'!$C$27)*'Supuestos'!$C$31)*'Supuestos'!$C$30))*('Supuestos'!$C$41+'Supuestos'!$C$42+'Supuestos'!$C$43))*(1-'Supuestos'!$C$34-'Supuestos'!$C$35-'Supuestos'!$C$36))-((IF($B26=0,0,'Supuestos'!$C$8/$B26))*'Supuestos'!$C$37)-'Supuestos'!$C$38-'Supuestos'!$C$8) | H26: =((((((((((IF($B26=0,0,'Supuestos'!$C$8/$B26))*'Supuestos'!$C$20)*H$19)+(((IF($B26=0,0,'Supuestos'!$C$8/$B26))*'Supuestos'!$C$21)*'Supuestos'!$C$26))*'Supuestos'!$C$27)*'Supuestos'!$C$24)+(((((((IF($B26=0,0,'Supuestos'!$C$8/$B26))*'Supuestos'!$C$20)*H$19)+(((IF($B26=0,0,'Supuestos'!$C$8/$B26))*'Supuestos'!$C$21)*'Supuestos'!$C$26))*'Supuestos'!$C$27)*'Supuestos'!$C$29)*'Supuestos'!$C$28)+(((((((IF($B26=0,0,'Supuestos'!$C$8/$B26))*'Supuestos'!$C$20)*H$19)+(((IF($B26=0,0,'Supuestos'!$C$8/$B26))*'Supuestos'!$C$21)*'Supuestos'!$C$26))*'Supuestos'!$C$27)*'Supuestos'!$C$31)*'Supuestos'!$C$30))*('Supuestos'!$C$41+'Supuestos'!$C$42+'Supuestos'!$C$43))*(1-'Supuestos'!$C$34-'Supuestos'!$C$35-'Supuestos'!$C$36))-((IF($B26=0,0,'Supuestos'!$C$8/$B26))*'Supuestos'!$C$37)-'Supuestos'!$C$38-'Supuestos'!$C$8)
B29: Cuánto invertir para una facturación objetivo por lanzamiento, según el ROAS que querés
B30: Inversión = facturación ÷ ROAS. Debajo: cuántos registros hacen falta y cuánto podés pagar por cada uno.
B31: Facturación objetivo ↓ / ROAS objetivo → | C31: 1.5 | D31: 2 | E31: 2.5 | F31: 3 | G31: 4
B32: 5000 | C32: =$B32/C$31 | D32: =$B32/D$31 | E32: =$B32/E$31 | F32: =$B32/F$31 | G32: =$B32/G$31
B33: 10000 | C33: =$B33/C$31 | D33: =$B33/D$31 | E33: =$B33/E$31 | F33: =$B33/F$31 | G33: =$B33/G$31
B34: 20000 | C34: =$B34/C$31 | D34: =$B34/D$31 | E34: =$B34/E$31 | F34: =$B34/F$31 | G34: =$B34/G$31
B35: 30000 | C35: =$B35/C$31 | D35: =$B35/D$31 | E35: =$B35/E$31 | F35: =$B35/F$31 | G35: =$B35/G$31
B36: 50000 | C36: =$B36/C$31 | D36: =$B36/D$31 | E36: =$B36/E$31 | F36: =$B36/F$31 | G36: =$B36/G$31
B37: Cantidad de registros necesaria para esa facturación
B38: =$B32 | C38: =IF('Modelo'!$C$37=0,"inalcanzable",$B32/'Modelo'!$C$37)
B39: =$B33 | C39: =IF('Modelo'!$C$37=0,"inalcanzable",$B33/'Modelo'!$C$37)
B40: =$B34 | C40: =IF('Modelo'!$C$37=0,"inalcanzable",$B34/'Modelo'!$C$37)
B41: =$B35 | C41: =IF('Modelo'!$C$37=0,"inalcanzable",$B35/'Modelo'!$C$37)
B42: =$B36 | C42: =IF('Modelo'!$C$37=0,"inalcanzable",$B36/'Modelo'!$C$37)
B44: Costo máximo por registro para cumplir cada ROAS (sobre facturado)
C45: 1.5 | D45: 2 | E45: 2.5 | F45: 3 | G45: 4
B46: Costo máximo (facturado por unidad ÷ ROAS) | C46: =IF(C45=0,0,'Modelo'!$C$37/C45) | D46: =IF(D45=0,0,'Modelo'!$C$37/D45) | E46: =IF(E45=0,0,'Modelo'!$C$37/E45) | F46: =IF(F45=0,0,'Modelo'!$C$37/F45) | G46: =IF(G45=0,0,'Modelo'!$C$37/G45)
B47: Sobre cash neto, el techo real está en Modelo (ya descuenta comisiones y reembolsos).
B50: Guardarraíl: el ROAS mínimo que tiene que dar cada nivel de inversión para que subir valga la pena
B51: Parte de tu inversión y tu ROAS actuales. Cada dólar extra tiene que devolver al menos 1,3 neto. Si al subir un escalón el ROAS real queda por debajo del mínimo de esa fila, volvé al escalón anterior.
B52: Nivel de inversión | C52: Inversión del período | D52: ROAS mínimo (cash neto) | E52: Ganancia mínima
B53: actual | C53: ='Supuestos'!$C$8*1.0 | D53: =IF(C53=0,0,('Supuestos'!$C$8*'Modelo'!$C$47+1.3*(C53-'Supuestos'!$C$8))/C53) | E53: =C53*(D53-1)
B54: × 1.25 | C54: ='Supuestos'!$C$8*1.25 | D54: =IF(C54=0,0,('Supuestos'!$C$8*'Modelo'!$C$47+1.3*(C54-'Supuestos'!$C$8))/C54) | E54: =C54*(D54-1)
B55: × 1.5 | C55: ='Supuestos'!$C$8*1.5 | D55: =IF(C55=0,0,('Supuestos'!$C$8*'Modelo'!$C$47+1.3*(C55-'Supuestos'!$C$8))/C55) | E55: =C55*(D55-1)
B56: × 2 | C56: ='Supuestos'!$C$8*2.0 | D56: =IF(C56=0,0,('Supuestos'!$C$8*'Modelo'!$C$47+1.3*(C56-'Supuestos'!$C$8))/C56) | E56: =C56*(D56-1)
B57: × 3 | C57: ='Supuestos'!$C$8*3.0 | D57: =IF(C57=0,0,('Supuestos'!$C$8*'Modelo'!$C$47+1.3*(C57-'Supuestos'!$C$8))/C57) | E57: =C57*(D57-1)

Sheet Sensibilidad
B2: Sensibilidad: qué palanca mueve más la ganancia
B3: Cada fila mejora una sola variable un 10 % (o baja un costo un 10 %) y recalcula la ganancia del período. El ranking dice qué conviene trabajar primero.
B5: Palanca | C5: Cambio | D5: Ganancia nueva | E5: Diferencia | F5: Dif. % | G5: Ranking
B6: Ganancia del período con los supuestos actuales | D6: ='Modelo'!$C$45
B7: CPM 10 % más barato (público, frecuencia, horario) | C7: −10 % | D7: =((((((((((IF((IF('Supuestos'!$C$11*'Supuestos'!$C$12*'Supuestos'!$C$15=0,0,('Supuestos'!$C$10*0.9)/1000/('Supuestos'!$C$11*'Supuestos'!$C$12*'Supuestos'!$C$15)))=0,0,'Supuestos'!$C$8/(IF('Supuestos'!$C$11*'Supuestos'!$C$12*'Supuestos'!$C$15=0,0,('Supuestos'!$C$10*0.9)/1000/('Supuestos'!$C$11*'Supuestos'!$C$12*'Supuestos'!$C$15)))))*'Supuestos'!$C$20)*'Supuestos'!$C$25)+(((IF((IF('Supuestos'!$C$11*'Supuestos'!$C$12*'Supuestos'!$C$15=0,0,('Supuestos'!$C$10*0.9)/1000/('Supuestos'!$C$11*'Supuestos'!$C$12*'Supuestos'!$C$15)))=0,0,'Supuestos'!$C$8/(IF('Supuestos'!$C$11*'Supuestos'!$C$12*'Supuestos'!$C$15=0,0,('Supuestos'!$C$10*0.9)/1000/('Supuestos'!$C$11*'Supuestos'!$C$12*'Supuestos'!$C$15)))))*'Supuestos'!$C$21)*'Supuestos'!$C$26))*'Supuestos'!$C$27)*'Supuestos'!$C$24)+(((((((IF((IF('Supuestos'!$C$11*'Supuestos'!$C$12*'Supuestos'!$C$15=0,0,('Supuestos'!$C$10*0.9)/1000/('Supuestos'!$C$11*'Supuestos'!$C$12*'Supuestos'!$C$15)))=0,0,'Supuestos'!$C$8/(IF('Supuestos'!$C$11*'Supuestos'!$C$12*'Supuestos'!$C$15=0,0,('Supuestos'!$C$10*0.9)/1000/('Supuestos'!$C$11*'Supuestos'!$C$12*'Supuestos'!$C$15)))))*'Supuestos'!$C$20)*'Supuestos'!$C$25)+(((IF((IF('Supuestos'!$C$11*'Supuestos'!$C$12*'Supuestos'!$C$15=0,0,('Supuestos'!$C$10*0.9)/1000/('Supuestos'!$C$11*'Supuestos'!$C$12*'Supuestos'!$C$15)))=0,0,'Supuestos'!$C$8/(IF('Supuestos'!$C$11*'Supuestos'!$C$12*'Supuestos'!$C$15=0,0,('Supuestos'!$C$10*0.9)/1000/('Supuestos'!$C$11*'Supuestos'!$C$12*'Supuestos'!$C$15)))))*'Supuestos'!$C$21)*'Supuestos'!$C$26))*'Supuestos'!$C$27)*'Supuestos'!$C$29)*'Supuestos'!$C$28)+(((((((IF((IF('Supuestos'!$C$11*'Supuestos'!$C$12*'Supuestos'!$C$15=0,0,('Supuestos'!$C$10*0.9)/1000/('Supuestos'!$C$11*'Supuestos'!$C$12*'Supuestos'!$C$15)))=0,0,'Supuestos'!$C$8/(IF('Supuestos'!$C$11*'Supuestos'!$C$12*'Supuestos'!$C$15=0,0,('Supuestos'!$C$10*0.9)/1000/('Supuestos'!$C$11*'Supuestos'!$C$12*'Supuestos'!$C$15)))))*'Supuestos'!$C$20)*'Supuestos'!$C$25)+(((IF((IF('Supuestos'!$C$11*'Supuestos'!$C$12*'Supuestos'!$C$15=0,0,('Supuestos'!$C$10*0.9)/1000/('Supuestos'!$C$11*'Supuestos'!$C$12*'Supuestos'!$C$15)))=0,0,'Supuestos'!$C$8/(IF('Supuestos'!$C$11*'Supuestos'!$C$12*'Supuestos'!$C$15=0,0,('Supuestos'!$C$10*0.9)/1000/('Supuestos'!$C$11*'Supuestos'!$C$12*'Supuestos'!$C$15)))))*'Supuestos'!$C$21)*'Supuestos'!$C$26))*'Supuestos'!$C$27)*'Supuestos'!$C$31)*'Supuestos'!$C$30))*('Supuestos'!$C$41+'Supuestos'!$C$42+'Supuestos'!$C$43))*(1-'Supuestos'!$C$34-'Supuestos'!$C$35-'Supuestos'!$C$36))-((IF((IF('Supuestos'!$C$11*'Supuestos'!$C$12*'Supuestos'!$C$15=0,0,('Supuestos'!$C$10*0.9)/1000/('Supuestos'!$C$11*'Supuestos'!$C$12*'Supuestos'!$C$15)))=0,0,'Supuestos'!$C$8/(IF('Supuestos'!$C$11*'Supuestos'!$C$12*'Supuestos'!$C$15=0,0,('Supuestos'!$C$10*0.9)/1000/('Supuestos'!$C$11*'Supuestos'!$C$12*'Supuestos'!$C$15)))))*'Supuestos'!$C$37)-'Supuestos'!$C$38-'Supuestos'!$C$8) | E7: =D7-$D$6 | F7: =IF($D$6=0,0,E7/ABS($D$6)) | G7: =RANK(E7,$E$7:$E$15)
B8: CTR 10 % más alto (mejor creativo) | C8: +10 % | D8: =((((((((((IF((IF(('Supuestos'!$C$11*1.1)*'Supuestos'!$C$12*'Supuestos'!$C$15=0,0,'Supuestos'!$C$10/1000/(('Supuestos'!$C$11*1.1)*'Supuestos'!$C$12*'Supuestos'!$C$15)))=0,0,'Supuestos'!$C$8/(IF(('Supuestos'!$C$11*1.1)*'Supuestos'!$C$12*'Supuestos'!$C$15=0,0,'Supuestos'!$C$10/1000/(('Supuestos'!$C$11*1.1)*'Supuestos'!$C$12*'Supuestos'!$C$15)))))*'Supuestos'!$C$20)*'Supuestos'!$C$25)+(((IF((IF(('Supuestos'!$C$11*1.1)*'Supuestos'!$C$12*'Supuestos'!$C$15=0,0,'Supuestos'!$C$10/1000/(('Supuestos'!$C$11*1.1)*'Supuestos'!$C$12*'Supuestos'!$C$15)))=0,0,'Supuestos'!$C$8/(IF(('Supuestos'!$C$11*1.1)*'Supuestos'!$C$12*'Supuestos'!$C$15=0,0,'Supuestos'!$C$10/1000/(('Supuestos'!$C$11*1.1)*'Supuestos'!$C$12*'Supuestos'!$C$15)))))*'Supuestos'!$C$21)*'Supuestos'!$C$26))*'Supuestos'!$C$27)*'Supuestos'!$C$24)+(((((((IF((IF(('Supuestos'!$C$11*1.1)*'Supuestos'!$C$12*'Supuestos'!$C$15=0,0,'Supuestos'!$C$10/1000/(('Supuestos'!$C$11*1.1)*'Supuestos'!$C$12*'Supuestos'!$C$15)))=0,0,'Supuestos'!$C$8/(IF(('Supuestos'!$C$11*1.1)*'Supuestos'!$C$12*'Supuestos'!$C$15=0,0,'Supuestos'!$C$10/1000/(('Supuestos'!$C$11*1.1)*'Supuestos'!$C$12*'Supuestos'!$C$15)))))*'Supuestos'!$C$20)*'Supuestos'!$C$25)+(((IF((IF(('Supuestos'!$C$11*1.1)*'Supuestos'!$C$12*'Supuestos'!$C$15=0,0,'Supuestos'!$C$10/1000/(('Supuestos'!$C$11*1.1)*'Supuestos'!$C$12*'Supuestos'!$C$15)))=0,0,'Supuestos'!$C$8/(IF(('Supuestos'!$C$11*1.1)*'Supuestos'!$C$12*'Supuestos'!$C$15=0,0,'Supuestos'!$C$10/1000/(('Supuestos'!$C$11*1.1)*'Supuestos'!$C$12*'Supuestos'!$C$15)))))*'Supuestos'!$C$21)*'Supuestos'!$C$26))*'Supuestos'!$C$27)*'Supuestos'!$C$29)*'Supuestos'!$C$28)+(((((((IF((IF(('Supuestos'!$C$11*1.1)*'Supuestos'!$C$12*'Supuestos'!$C$15=0,0,'Supuestos'!$C$10/1000/(('Supuestos'!$C$11*1.1)*'Supuestos'!$C$12*'Supuestos'!$C$15)))=0,0,'Supuestos'!$C$8/(IF(('Supuestos'!$C$11*1.1)*'Supuestos'!$C$12*'Supuestos'!$C$15=0,0,'Supuestos'!$C$10/1000/(('Supuestos'!$C$11*1.1)*'Supuestos'!$C$12*'Supuestos'!$C$15)))))*'Supuestos'!$C$20)*'Supuestos'!$C$25)+(((IF((IF(('Supuestos'!$C$11*1.1)*'Supuestos'!$C$12*'Supuestos'!$C$15=0,0,'Supuestos'!$C$10/1000/(('Supuestos'!$C$11*1.1)*'Supuestos'!$C$12*'Supuestos'!$C$15)))=0,0,'Supuestos'!$C$8/(IF(('Supuestos'!$C$11*1.1)*'Supuestos'!$C$12*'Supuestos'!$C$15=0,0,'Supuestos'!$C$10/1000/(('Supuestos'!$C$11*1.1)*'Supuestos'!$C$12*'Supuestos'!$C$15)))))*'Supuestos'!$C$21)*'Supuestos'!$C$26))*'Supuestos'!$C$27)*'Supuestos'!$C$31)*'Supuestos'!$C$30))*('Supuestos'!$C$41+'Supuestos'!$C$42+'Supuestos'!$C$43))*(1-'Supuestos'!$C$34-'Supuestos'!$C$35-'Supuestos'!$C$36))-((IF((IF(('Supuestos'!$C$11*1.1)*'Supuestos'!$C$12*'Supuestos'!$C$15=0,0,'Supuestos'!$C$10/1000/(('Supuestos'!$C$11*1.1)*'Supuestos'!$C$12*'Supuestos'!$C$15)))=0,0,'Supuestos'!$C$8/(IF(('Supuestos'!$C$11*1.1)*'Supuestos'!$C$12*'Supuestos'!$C$15=0,0,'Supuestos'!$C$10/1000/(('Supuestos'!$C$11*1.1)*'Supuestos'!$C$12*'Supuestos'!$C$15)))))*'Supuestos'!$C$37)-'Supuestos'!$C$38-'Supuestos'!$C$8) | E8: =D8-$D$6 | F8: =IF($D$6=0,0,E8/ABS($D$6)) | G8: =RANK(E8,$E$7:$E$15)
B9: Landing 10 % más conversión | C9: +10 % | D9: =((((((((((IF((IF('Supuestos'!$C$11*'Supuestos'!$C$12*('Supuestos'!$C$15*1.1)=0,0,'Supuestos'!$C$10/1000/('Supuestos'!$C$11*'Supuestos'!$C$12*('Supuestos'!$C$15*1.1))))=0,0,'Supuestos'!$C$8/(IF('Supuestos'!$C$11*'Supuestos'!$C$12*('Supuestos'!$C$15*1.1)=0,0,'Supuestos'!$C$10/1000/('Supuestos'!$C$11*'Supuestos'!$C$12*('Supuestos'!$C$15*1.1))))))*'Supuestos'!$C$20)*'Supuestos'!$C$25)+(((IF((IF('Supuestos'!$C$11*'Supuestos'!$C$12*('Supuestos'!$C$15*1.1)=0,0,'Supuestos'!$C$10/1000/('Supuestos'!$C$11*'Supuestos'!$C$12*('Supuestos'!$C$15*1.1))))=0,0,'Supuestos'!$C$8/(IF('Supuestos'!$C$11*'Supuestos'!$C$12*('Supuestos'!$C$15*1.1)=0,0,'Supuestos'!$C$10/1000/('Supuestos'!$C$11*'Supuestos'!$C$12*('Supuestos'!$C$15*1.1))))))*'Supuestos'!$C$21)*'Supuestos'!$C$26))*'Supuestos'!$C$27)*'Supuestos'!$C$24)+(((((((IF((IF('Supuestos'!$C$11*'Supuestos'!$C$12*('Supuestos'!$C$15*1.1)=0,0,'Supuestos'!$C$10/1000/('Supuestos'!$C$11*'Supuestos'!$C$12*('Supuestos'!$C$15*1.1))))=0,0,'Supuestos'!$C$8/(IF('Supuestos'!$C$11*'Supuestos'!$C$12*('Supuestos'!$C$15*1.1)=0,0,'Supuestos'!$C$10/1000/('Supuestos'!$C$11*'Supuestos'!$C$12*('Supuestos'!$C$15*1.1))))))*'Supuestos'!$C$20)*'Supuestos'!$C$25)+(((IF((IF('Supuestos'!$C$11*'Supuestos'!$C$12*('Supuestos'!$C$15*1.1)=0,0,'Supuestos'!$C$10/1000/('Supuestos'!$C$11*'Supuestos'!$C$12*('Supuestos'!$C$15*1.1))))=0,0,'Supuestos'!$C$8/(IF('Supuestos'!$C$11*'Supuestos'!$C$12*('Supuestos'!$C$15*1.1)=0,0,'Supuestos'!$C$10/1000/('Supuestos'!$C$11*'Supuestos'!$C$12*('Supuestos'!$C$15*1.1))))))*'Supuestos'!$C$21)*'Supuestos'!$C$26))*'Supuestos'!$C$27)*'Supuestos'!$C$29)*'Supuestos'!$C$28)+(((((((IF((IF('Supuestos'!$C$11*'Supuestos'!$C$12*('Supuestos'!$C$15*1.1)=0,0,'Supuestos'!$C$10/1000/('Supuestos'!$C$11*'Supuestos'!$C$12*('Supuestos'!$C$15*1.1))))=0,0,'Supuestos'!$C$8/(IF('Supuestos'!$C$11*'Supuestos'!$C$12*('Supuestos'!$C$15*1.1)=0,0,'Supuestos'!$C$10/1000/('Supuestos'!$C$11*'Supuestos'!$C$12*('Supuestos'!$C$15*1.1))))))*'Supuestos'!$C$20)*'Supuestos'!$C$25)+(((IF((IF('Supuestos'!$C$11*'Supuestos'!$C$12*('Supuestos'!$C$15*1.1)=0,0,'Supuestos'!$C$10/1000/('Supuestos'!$C$11*'Supuestos'!$C$12*('Supuestos'!$C$15*1.1))))=0,0,'Supuestos'!$C$8/(IF('Supuestos'!$C$11*'Supuestos'!$C$12*('Supuestos'!$C$15*1.1)=0,0,'Supuestos'!$C$10/1000/('Supuestos'!$C$11*'Supuestos'!$C$12*('Supuestos'!$C$15*1.1))))))*'Supuestos'!$C$21)*'Supuestos'!$C$26))*'Supuestos'!$C$27)*'Supuestos'!$C$31)*'Supuestos'!$C$30))*('Supuestos'!$C$41+'Supuestos'!$C$42+'Supuestos'!$C$43))*(1-'Supuestos'!$C$34-'Supuestos'!$C$35-'Supuestos'!$C$36))-((IF((IF('Supuestos'!$C$11*'Supuestos'!$C$12*('Supuestos'!$C$15*1.1)=0,0,'Supuestos'!$C$10/1000/('Supuestos'!$C$11*'Supuestos'!$C$12*('Supuestos'!$C$15*1.1))))=0,0,'Supuestos'!$C$8/(IF('Supuestos'!$C$11*'Supuestos'!$C$12*('Supuestos'!$C$15*1.1)=0,0,'Supuestos'!$C$10/1000/('Supuestos'!$C$11*'Supuestos'!$C$12*('Supuestos'!$C$15*1.1))))))*'Supuestos'!$C$37)-'Supuestos'!$C$38-'Supuestos'!$C$8) | E9: =D9-$D$6 | F9: =IF($D$6=0,0,E9/ABS($D$6)) | G9: =RANK(E9,$E$7:$E$15)
B10: Show rate en vivo 10 % más alto (recordatorios, grupo, horario) | C10: +10 % | D10: =((((((((((IF((IF('Supuestos'!$C$11*'Supuestos'!$C$12*'Supuestos'!$C$15=0,0,'Supuestos'!$C$10/1000/('Supuestos'!$C$11*'Supuestos'!$C$12*'Supuestos'!$C$15)))=0,0,'Supuestos'!$C$8/(IF('Supuestos'!$C$11*'Supuestos'!$C$12*'Supuestos'!$C$15=0,0,'Supuestos'!$C$10/1000/('Supuestos'!$C$11*'Supuestos'!$C$12*'Supuestos'!$C$15)))))*('Supuestos'!$C$20*1.1))*'Supuestos'!$C$25)+(((IF((IF('Supuestos'!$C$11*'Supuestos'!$C$12*'Supuestos'!$C$15=0,0,'Supuestos'!$C$10/1000/('Supuestos'!$C$11*'Supuestos'!$C$12*'Supuestos'!$C$15)))=0,0,'Supuestos'!$C$8/(IF('Supuestos'!$C$11*'Supuestos'!$C$12*'Supuestos'!$C$15=0,0,'Supuestos'!$C$10/1000/('Supuestos'!$C$11*'Supuestos'!$C$12*'Supuestos'!$C$15)))))*'Supuestos'!$C$21)*'Supuestos'!$C$26))*'Supuestos'!$C$27)*'Supuestos'!$C$24)+(((((((IF((IF('Supuestos'!$C$11*'Supuestos'!$C$12*'Supuestos'!$C$15=0,0,'Supuestos'!$C$10/1000/('Supuestos'!$C$11*'Supuestos'!$C$12*'Supuestos'!$C$15)))=0,0,'Supuestos'!$C$8/(IF('Supuestos'!$C$11*'Supuestos'!$C$12*'Supuestos'!$C$15=0,0,'Supuestos'!$C$10/1000/('Supuestos'!$C$11*'Supuestos'!$C$12*'Supuestos'!$C$15)))))*('Supuestos'!$C$20*1.1))*'Supuestos'!$C$25)+(((IF((IF('Supuestos'!$C$11*'Supuestos'!$C$12*'Supuestos'!$C$15=0,0,'Supuestos'!$C$10/1000/('Supuestos'!$C$11*'Supuestos'!$C$12*'Supuestos'!$C$15)))=0,0,'Supuestos'!$C$8/(IF('Supuestos'!$C$11*'Supuestos'!$C$12*'Supuestos'!$C$15=0,0,'Supuestos'!$C$10/1000/('Supuestos'!$C$11*'Supuestos'!$C$12*'Supuestos'!$C$15)))))*'Supuestos'!$C$21)*'Supuestos'!$C$26))*'Supuestos'!$C$27)*'Supuestos'!$C$29)*'Supuestos'!$C$28)+(((((((IF((IF('Supuestos'!$C$11*'Supuestos'!$C$12*'Supuestos'!$C$15=0,0,'Supuestos'!$C$10/1000/('Supuestos'!$C$11*'Supuestos'!$C$12*'Supuestos'!$C$15)))=0,0,'Supuestos'!$C$8/(IF('Supuestos'!$C$11*'Supuestos'!$C$12*'Supuestos'!$C$15=0,0,'Supuestos'!$C$10/1000/('Supuestos'!$C$11*'Supuestos'!$C$12*'Supuestos'!$C$15)))))*('Supuestos'!$C$20*1.1))*'Supuestos'!$C$25)+(((IF((IF('Supuestos'!$C$11*'Supuestos'!$C$12*'Supuestos'!$C$15=0,0,'Supuestos'!$C$10/1000/('Supuestos'!$C$11*'Supuestos'!$C$12*'Supuestos'!$C$15)))=0,0,'Supuestos'!$C$8/(IF('Supuestos'!$C$11*'Supuestos'!$C$12*'Supuestos'!$C$15=0,0,'Supuestos'!$C$10/1000/('Supuestos'!$C$11*'Supuestos'!$C$12*'Supuestos'!$C$15)))))*'Supuestos'!$C$21)*'Supuestos'!$C$26))*'Supuestos'!$C$27)*'Supuestos'!$C$31)*'Supuestos'!$C$30))*('Supuestos'!$C$41+'Supuestos'!$C$42+'Supuestos'!$C$43))*(1-'Supuestos'!$C$34-'Supuestos'!$C$35-'Supuestos'!$C$36))-((IF((IF('Supuestos'!$C$11*'Supuestos'!$C$12*'Supuestos'!$C$15=0,0,'Supuestos'!$C$10/1000/('Supuestos'!$C$11*'Supuestos'!$C$12*'Supuestos'!$C$15)))=0,0,'Supuestos'!$C$8/(IF('Supuestos'!$C$11*'Supuestos'!$C$12*'Supuestos'!$C$15=0,0,'Supuestos'!$C$10/1000/('Supuestos'!$C$11*'Supuestos'!$C$12*'Supuestos'!$C$15)))))*'Supuestos'!$C$37)-'Supuestos'!$C$38-'Supuestos'!$C$8) | E10: =D10-$D$6 | F10: =IF($D$6=0,0,E10/ABS($D$6)) | G10: =RANK(E10,$E$7:$E$15)
B11: 10 % más asistentes en vivo que solicitan (oferta, pitch) | C11: +10 % | D11: =((((((((((IF((IF('Supuestos'!$C$11*'Supuestos'!$C$12*'Supuestos'!$C$15=0,0,'Supuestos'!$C$10/1000/('Supuestos'!$C$11*'Supuestos'!$C$12*'Supuestos'!$C$15)))=0,0,'Supuestos'!$C$8/(IF('Supuestos'!$C$11*'Supuestos'!$C$12*'Supuestos'!$C$15=0,0,'Supuestos'!$C$10/1000/('Supuestos'!$C$11*'Supuestos'!$C$12*'Supuestos'!$C$15)))))*'Supuestos'!$C$20)*('Supuestos'!$C$25*1.1))+(((IF((IF('Supuestos'!$C$11*'Supuestos'!$C$12*'Supuestos'!$C$15=0,0,'Supuestos'!$C$10/1000/('Supuestos'!$C$11*'Supuestos'!$C$12*'Supuestos'!$C$15)))=0,0,'Supuestos'!$C$8/(IF('Supuestos'!$C$11*'Supuestos'!$C$12*'Supuestos'!$C$15=0,0,'Supuestos'!$C$10/1000/('Supuestos'!$C$11*'Supuestos'!$C$12*'Supuestos'!$C$15)))))*'Supuestos'!$C$21)*'Supuestos'!$C$26))*'Supuestos'!$C$27)*'Supuestos'!$C$24)+(((((((IF((IF('Supuestos'!$C$11*'Supuestos'!$C$12*'Supuestos'!$C$15=0,0,'Supuestos'!$C$10/1000/('Supuestos'!$C$11*'Supuestos'!$C$12*'Supuestos'!$C$15)))=0,0,'Supuestos'!$C$8/(IF('Supuestos'!$C$11*'Supuestos'!$C$12*'Supuestos'!$C$15=0,0,'Supuestos'!$C$10/1000/('Supuestos'!$C$11*'Supuestos'!$C$12*'Supuestos'!$C$15)))))*'Supuestos'!$C$20)*('Supuestos'!$C$25*1.1))+(((IF((IF('Supuestos'!$C$11*'Supuestos'!$C$12*'Supuestos'!$C$15=0,0,'Supuestos'!$C$10/1000/('Supuestos'!$C$11*'Supuestos'!$C$12*'Supuestos'!$C$15)))=0,0,'Supuestos'!$C$8/(IF('Supuestos'!$C$11*'Supuestos'!$C$12*'Supuestos'!$C$15=0,0,'Supuestos'!$C$10/1000/('Supuestos'!$C$11*'Supuestos'!$C$12*'Supuestos'!$C$15)))))*'Supuestos'!$C$21)*'Supuestos'!$C$26))*'Supuestos'!$C$27)*'Supuestos'!$C$29)*'Supuestos'!$C$28)+(((((((IF((IF('Supuestos'!$C$11*'Supuestos'!$C$12*'Supuestos'!$C$15=0,0,'Supuestos'!$C$10/1000/('Supuestos'!$C$11*'Supuestos'!$C$12*'Supuestos'!$C$15)))=0,0,'Supuestos'!$C$8/(IF('Supuestos'!$C$11*'Supuestos'!$C$12*'Supuestos'!$C$15=0,0,'Supuestos'!$C$10/1000/('Supuestos'!$C$11*'Supuestos'!$C$12*'Supuestos'!$C$15)))))*'Supuestos'!$C$20)*('Supuestos'!$C$25*1.1))+(((IF((IF('Supuestos'!$C$11*'Supuestos'!$C$12*'Supuestos'!$C$15=0,0,'Supuestos'!$C$10/1000/('Supuestos'!$C$11*'Supuestos'!$C$12*'Supuestos'!$C$15)))=0,0,'Supuestos'!$C$8/(IF('Supuestos'!$C$11*'Supuestos'!$C$12*'Supuestos'!$C$15=0,0,'Supuestos'!$C$10/1000/('Supuestos'!$C$11*'Supuestos'!$C$12*'Supuestos'!$C$15)))))*'Supuestos'!$C$21)*'Supuestos'!$C$26))*'Supuestos'!$C$27)*'Supuestos'!$C$31)*'Supuestos'!$C$30))*('Supuestos'!$C$41+'Supuestos'!$C$42+'Supuestos'!$C$43))*(1-'Supuestos'!$C$34-'Supuestos'!$C$35-'Supuestos'!$C$36))-((IF((IF('Supuestos'!$C$11*'Supuestos'!$C$12*'Supuestos'!$C$15=0,0,'Supuestos'!$C$10/1000/('Supuestos'!$C$11*'Supuestos'!$C$12*'Supuestos'!$C$15)))=0,0,'Supuestos'!$C$8/(IF('Supuestos'!$C$11*'Supuestos'!$C$12*'Supuestos'!$C$15=0,0,'Supuestos'!$C$10/1000/('Supuestos'!$C$11*'Supuestos'!$C$12*'Supuestos'!$C$15)))))*'Supuestos'!$C$37)-'Supuestos'!$C$38-'Supuestos'!$C$8) | E11: =D11-$D$6 | F11: =IF($D$6=0,0,E11/ABS($D$6)) | G11: =RANK(E11,$E$7:$E$15)
B12: 10 % más solicitudes que terminan en compra (seguimiento, vendedor) | C12: +10 % | D12: =((((((((((IF((IF('Supuestos'!$C$11*'Supuestos'!$C$12*'Supuestos'!$C$15=0,0,'Supuestos'!$C$10/1000/('Supuestos'!$C$11*'Supuestos'!$C$12*'Supuestos'!$C$15)))=0,0,'Supuestos'!$C$8/(IF('Supuestos'!$C$11*'Supuestos'!$C$12*'Supuestos'!$C$15=0,0,'Supuestos'!$C$10/1000/('Supuestos'!$C$11*'Supuestos'!$C$12*'Supuestos'!$C$15)))))*'Supuestos'!$C$20)*'Supuestos'!$C$25)+(((IF((IF('Supuestos'!$C$11*'Supuestos'!$C$12*'Supuestos'!$C$15=0,0,'Supuestos'!$C$10/1000/('Supuestos'!$C$11*'Supuestos'!$C$12*'Supuestos'!$C$15)))=0,0,'Supuestos'!$C$8/(IF('Supuestos'!$C$11*'Supuestos'!$C$12*'Supuestos'!$C$15=0,0,'Supuestos'!$C$10/1000/('Supuestos'!$C$11*'Supuestos'!$C$12*'Supuestos'!$C$15)))))*'Supuestos'!$C$21)*'Supuestos'!$C$26))*('Supuestos'!$C$27*1.1))*'Supuestos'!$C$24)+(((((((IF((IF('Supuestos'!$C$11*'Supuestos'!$C$12*'Supuestos'!$C$15=0,0,'Supuestos'!$C$10/1000/('Supuestos'!$C$11*'Supuestos'!$C$12*'Supuestos'!$C$15)))=0,0,'Supuestos'!$C$8/(IF('Supuestos'!$C$11*'Supuestos'!$C$12*'Supuestos'!$C$15=0,0,'Supuestos'!$C$10/1000/('Supuestos'!$C$11*'Supuestos'!$C$12*'Supuestos'!$C$15)))))*'Supuestos'!$C$20)*'Supuestos'!$C$25)+(((IF((IF('Supuestos'!$C$11*'Supuestos'!$C$12*'Supuestos'!$C$15=0,0,'Supuestos'!$C$10/1000/('Supuestos'!$C$11*'Supuestos'!$C$12*'Supuestos'!$C$15)))=0,0,'Supuestos'!$C$8/(IF('Supuestos'!$C$11*'Supuestos'!$C$12*'Supuestos'!$C$15=0,0,'Supuestos'!$C$10/1000/('Supuestos'!$C$11*'Supuestos'!$C$12*'Supuestos'!$C$15)))))*'Supuestos'!$C$21)*'Supuestos'!$C$26))*('Supuestos'!$C$27*1.1))*'Supuestos'!$C$29)*'Supuestos'!$C$28)+(((((((IF((IF('Supuestos'!$C$11*'Supuestos'!$C$12*'Supuestos'!$C$15=0,0,'Supuestos'!$C$10/1000/('Supuestos'!$C$11*'Supuestos'!$C$12*'Supuestos'!$C$15)))=0,0,'Supuestos'!$C$8/(IF('Supuestos'!$C$11*'Supuestos'!$C$12*'Supuestos'!$C$15=0,0,'Supuestos'!$C$10/1000/('Supuestos'!$C$11*'Supuestos'!$C$12*'Supuestos'!$C$15)))))*'Supuestos'!$C$20)*'Supuestos'!$C$25)+(((IF((IF('Supuestos'!$C$11*'Supuestos'!$C$12*'Supuestos'!$C$15=0,0,'Supuestos'!$C$10/1000/('Supuestos'!$C$11*'Supuestos'!$C$12*'Supuestos'!$C$15)))=0,0,'Supuestos'!$C$8/(IF('Supuestos'!$C$11*'Supuestos'!$C$12*'Supuestos'!$C$15=0,0,'Supuestos'!$C$10/1000/('Supuestos'!$C$11*'Supuestos'!$C$12*'Supuestos'!$C$15)))))*'Supuestos'!$C$21)*'Supuestos'!$C$26))*('Supuestos'!$C$27*1.1))*'Supuestos'!$C$31)*'Supuestos'!$C$30))*('Supuestos'!$C$41+'Supuestos'!$C$42+'Supuestos'!$C$43))*(1-'Supuestos'!$C$34-'Supuestos'!$C$35-'Supuestos'!$C$36))-((IF((IF('Supuestos'!$C$11*'Supuestos'!$C$12*'Supuestos'!$C$15=0,0,'Supuestos'!$C$10/1000/('Supuestos'!$C$11*'Supuestos'!$C$12*'Supuestos'!$C$15)))=0,0,'Supuestos'!$C$8/(IF('Supuestos'!$C$11*'Supuestos'!$C$12*'Supuestos'!$C$15=0,0,'Supuestos'!$C$10/1000/('Supuestos'!$C$11*'Supuestos'!$C$12*'Supuestos'!$C$15)))))*'Supuestos'!$C$37)-'Supuestos'!$C$38-'Supuestos'!$C$8) | E12: =D12-$D$6 | F12: =IF($D$6=0,0,E12/ABS($D$6)) | G12: =RANK(E12,$E$7:$E$15)
B13: Precio de la oferta 10 % más alto (misma conversión) | C13: +10 % | D13: =((((((((((IF((IF('Supuestos'!$C$11*'Supuestos'!$C$12*'Supuestos'!$C$15=0,0,'Supuestos'!$C$10/1000/('Supuestos'!$C$11*'Supuestos'!$C$12*'Supuestos'!$C$15)))=0,0,'Supuestos'!$C$8/(IF('Supuestos'!$C$11*'Supuestos'!$C$12*'Supuestos'!$C$15=0,0,'Supuestos'!$C$10/1000/('Supuestos'!$C$11*'Supuestos'!$C$12*'Supuestos'!$C$15)))))*'Supuestos'!$C$20)*'Supuestos'!$C$25)+(((IF((IF('Supuestos'!$C$11*'Supuestos'!$C$12*'Supuestos'!$C$15=0,0,'Supuestos'!$C$10/1000/('Supuestos'!$C$11*'Supuestos'!$C$12*'Supuestos'!$C$15)))=0,0,'Supuestos'!$C$8/(IF('Supuestos'!$C$11*'Supuestos'!$C$12*'Supuestos'!$C$15=0,0,'Supuestos'!$C$10/1000/('Supuestos'!$C$11*'Supuestos'!$C$12*'Supuestos'!$C$15)))))*'Supuestos'!$C$21)*'Supuestos'!$C$26))*'Supuestos'!$C$27)*('Supuestos'!$C$24*1.1))+(((((((IF((IF('Supuestos'!$C$11*'Supuestos'!$C$12*'Supuestos'!$C$15=0,0,'Supuestos'!$C$10/1000/('Supuestos'!$C$11*'Supuestos'!$C$12*'Supuestos'!$C$15)))=0,0,'Supuestos'!$C$8/(IF('Supuestos'!$C$11*'Supuestos'!$C$12*'Supuestos'!$C$15=0,0,'Supuestos'!$C$10/1000/('Supuestos'!$C$11*'Supuestos'!$C$12*'Supuestos'!$C$15)))))*'Supuestos'!$C$20)*'Supuestos'!$C$25)+(((IF((IF('Supuestos'!$C$11*'Supuestos'!$C$12*'Supuestos'!$C$15=0,0,'Supuestos'!$C$10/1000/('Supuestos'!$C$11*'Supuestos'!$C$12*'Supuestos'!$C$15)))=0,0,'Supuestos'!$C$8/(IF('Supuestos'!$C$11*'Supuestos'!$C$12*'Supuestos'!$C$15=0,0,'Supuestos'!$C$10/1000/('Supuestos'!$C$11*'Supuestos'!$C$12*'Supuestos'!$C$15)))))*'Supuestos'!$C$21)*'Supuestos'!$C$26))*'Supuestos'!$C$27)*'Supuestos'!$C$29)*'Supuestos'!$C$28)+(((((((IF((IF('Supuestos'!$C$11*'Supuestos'!$C$12*'Supuestos'!$C$15=0,0,'Supuestos'!$C$10/1000/('Supuestos'!$C$11*'Supuestos'!$C$12*'Supuestos'!$C$15)))=0,0,'Supuestos'!$C$8/(IF('Supuestos'!$C$11*'Supuestos'!$C$12*'Supuestos'!$C$15=0,0,'Supuestos'!$C$10/1000/('Supuestos'!$C$11*'Supuestos'!$C$12*'Supuestos'!$C$15)))))*'Supuestos'!$C$20)*'Supuestos'!$C$25)+(((IF((IF('Supuestos'!$C$11*'Supuestos'!$C$12*'Supuestos'!$C$15=0,0,'Supuestos'!$C$10/1000/('Supuestos'!$C$11*'Supuestos'!$C$12*'Supuestos'!$C$15)))=0,0,'Supuestos'!$C$8/(IF('Supuestos'!$C$11*'Supuestos'!$C$12*'Supuestos'!$C$15=0,0,'Supuestos'!$C$10/1000/('Supuestos'!$C$11*'Supuestos'!$C$12*'Supuestos'!$C$15)))))*'Supuestos'!$C$21)*'Supuestos'!$C$26))*'Supuestos'!$C$27)*'Supuestos'!$C$31)*'Supuestos'!$C$30))*('Supuestos'!$C$41+'Supuestos'!$C$42+'Supuestos'!$C$43))*(1-'Supuestos'!$C$34-'Supuestos'!$C$35-'Supuestos'!$C$36))-((IF((IF('Supuestos'!$C$11*'Supuestos'!$C$12*'Supuestos'!$C$15=0,0,'Supuestos'!$C$10/1000/('Supuestos'!$C$11*'Supuestos'!$C$12*'Supuestos'!$C$15)))=0,0,'Supuestos'!$C$8/(IF('Supuestos'!$C$11*'Supuestos'!$C$12*'Supuestos'!$C$15=0,0,'Supuestos'!$C$10/1000/('Supuestos'!$C$11*'Supuestos'!$C$12*'Supuestos'!$C$15)))))*'Supuestos'!$C$37)-'Supuestos'!$C$38-'Supuestos'!$C$8) | E13: =D13-$D$6 | F13: =IF($D$6=0,0,E13/ABS($D$6)) | G13: =RANK(E13,$E$7:$E$15)
B14: Bump tomado 10 % más | C14: +10 % | D14: =((((((((((IF((IF('Supuestos'!$C$11*'Supuestos'!$C$12*'Supuestos'!$C$15=0,0,'Supuestos'!$C$10/1000/('Supuestos'!$C$11*'Supuestos'!$C$12*'Supuestos'!$C$15)))=0,0,'Supuestos'!$C$8/(IF('Supuestos'!$C$11*'Supuestos'!$C$12*'Supuestos'!$C$15=0,0,'Supuestos'!$C$10/1000/('Supuestos'!$C$11*'Supuestos'!$C$12*'Supuestos'!$C$15)))))*'Supuestos'!$C$20)*'Supuestos'!$C$25)+(((IF((IF('Supuestos'!$C$11*'Supuestos'!$C$12*'Supuestos'!$C$15=0,0,'Supuestos'!$C$10/1000/('Supuestos'!$C$11*'Supuestos'!$C$12*'Supuestos'!$C$15)))=0,0,'Supuestos'!$C$8/(IF('Supuestos'!$C$11*'Supuestos'!$C$12*'Supuestos'!$C$15=0,0,'Supuestos'!$C$10/1000/('Supuestos'!$C$11*'Supuestos'!$C$12*'Supuestos'!$C$15)))))*'Supuestos'!$C$21)*'Supuestos'!$C$26))*'Supuestos'!$C$27)*'Supuestos'!$C$24)+(((((((IF((IF('Supuestos'!$C$11*'Supuestos'!$C$12*'Supuestos'!$C$15=0,0,'Supuestos'!$C$10/1000/('Supuestos'!$C$11*'Supuestos'!$C$12*'Supuestos'!$C$15)))=0,0,'Supuestos'!$C$8/(IF('Supuestos'!$C$11*'Supuestos'!$C$12*'Supuestos'!$C$15=0,0,'Supuestos'!$C$10/1000/('Supuestos'!$C$11*'Supuestos'!$C$12*'Supuestos'!$C$15)))))*'Supuestos'!$C$20)*'Supuestos'!$C$25)+(((IF((IF('Supuestos'!$C$11*'Supuestos'!$C$12*'Supuestos'!$C$15=0,0,'Supuestos'!$C$10/1000/('Supuestos'!$C$11*'Supuestos'!$C$12*'Supuestos'!$C$15)))=0,0,'Supuestos'!$C$8/(IF('Supuestos'!$C$11*'Supuestos'!$C$12*'Supuestos'!$C$15=0,0,'Supuestos'!$C$10/1000/('Supuestos'!$C$11*'Supuestos'!$C$12*'Supuestos'!$C$15)))))*'Supuestos'!$C$21)*'Supuestos'!$C$26))*'Supuestos'!$C$27)*('Supuestos'!$C$29*1.1))*'Supuestos'!$C$28)+(((((((IF((IF('Supuestos'!$C$11*'Supuestos'!$C$12*'Supuestos'!$C$15=0,0,'Supuestos'!$C$10/1000/('Supuestos'!$C$11*'Supuestos'!$C$12*'Supuestos'!$C$15)))=0,0,'Supuestos'!$C$8/(IF('Supuestos'!$C$11*'Supuestos'!$C$12*'Supuestos'!$C$15=0,0,'Supuestos'!$C$10/1000/('Supuestos'!$C$11*'Supuestos'!$C$12*'Supuestos'!$C$15)))))*'Supuestos'!$C$20)*'Supuestos'!$C$25)+(((IF((IF('Supuestos'!$C$11*'Supuestos'!$C$12*'Supuestos'!$C$15=0,0,'Supuestos'!$C$10/1000/('Supuestos'!$C$11*'Supuestos'!$C$12*'Supuestos'!$C$15)))=0,0,'Supuestos'!$C$8/(IF('Supuestos'!$C$11*'Supuestos'!$C$12*'Supuestos'!$C$15=0,0,'Supuestos'!$C$10/1000/('Supuestos'!$C$11*'Supuestos'!$C$12*'Supuestos'!$C$15)))))*'Supuestos'!$C$21)*'Supuestos'!$C$26))*'Supuestos'!$C$27)*'Supuestos'!$C$31)*'Supuestos'!$C$30))*('Supuestos'!$C$41+'Supuestos'!$C$42+'Supuestos'!$C$43))*(1-'Supuestos'!$C$34-'Supuestos'!$C$35-'Supuestos'!$C$36))-((IF((IF('Supuestos'!$C$11*'Supuestos'!$C$12*'Supuestos'!$C$15=0,0,'Supuestos'!$C$10/1000/('Supuestos'!$C$11*'Supuestos'!$C$12*'Supuestos'!$C$15)))=0,0,'Supuestos'!$C$8/(IF('Supuestos'!$C$11*'Supuestos'!$C$12*'Supuestos'!$C$15=0,0,'Supuestos'!$C$10/1000/('Supuestos'!$C$11*'Supuestos'!$C$12*'Supuestos'!$C$15)))))*'Supuestos'!$C$37)-'Supuestos'!$C$38-'Supuestos'!$C$8) | E14: =D14-$D$6 | F14: =IF($D$6=0,0,E14/ABS($D$6)) | G14: =RANK(E14,$E$7:$E$15)
B15: Programa superior 10 % más tomado | C15: +10 % | D15: =((((((((((IF((IF('Supuestos'!$C$11*'Supuestos'!$C$12*'Supuestos'!$C$15=0,0,'Supuestos'!$C$10/1000/('Supuestos'!$C$11*'Supuestos'!$C$12*'Supuestos'!$C$15)))=0,0,'Supuestos'!$C$8/(IF('Supuestos'!$C$11*'Supuestos'!$C$12*'Supuestos'!$C$15=0,0,'Supuestos'!$C$10/1000/('Supuestos'!$C$11*'Supuestos'!$C$12*'Supuestos'!$C$15)))))*'Supuestos'!$C$20)*'Supuestos'!$C$25)+(((IF((IF('Supuestos'!$C$11*'Supuestos'!$C$12*'Supuestos'!$C$15=0,0,'Supuestos'!$C$10/1000/('Supuestos'!$C$11*'Supuestos'!$C$12*'Supuestos'!$C$15)))=0,0,'Supuestos'!$C$8/(IF('Supuestos'!$C$11*'Supuestos'!$C$12*'Supuestos'!$C$15=0,0,'Supuestos'!$C$10/1000/('Supuestos'!$C$11*'Supuestos'!$C$12*'Supuestos'!$C$15)))))*'Supuestos'!$C$21)*'Supuestos'!$C$26))*'Supuestos'!$C$27)*'Supuestos'!$C$24)+(((((((IF((IF('Supuestos'!$C$11*'Supuestos'!$C$12*'Supuestos'!$C$15=0,0,'Supuestos'!$C$10/1000/('Supuestos'!$C$11*'Supuestos'!$C$12*'Supuestos'!$C$15)))=0,0,'Supuestos'!$C$8/(IF('Supuestos'!$C$11*'Supuestos'!$C$12*'Supuestos'!$C$15=0,0,'Supuestos'!$C$10/1000/('Supuestos'!$C$11*'Supuestos'!$C$12*'Supuestos'!$C$15)))))*'Supuestos'!$C$20)*'Supuestos'!$C$25)+(((IF((IF('Supuestos'!$C$11*'Supuestos'!$C$12*'Supuestos'!$C$15=0,0,'Supuestos'!$C$10/1000/('Supuestos'!$C$11*'Supuestos'!$C$12*'Supuestos'!$C$15)))=0,0,'Supuestos'!$C$8/(IF('Supuestos'!$C$11*'Supuestos'!$C$12*'Supuestos'!$C$15=0,0,'Supuestos'!$C$10/1000/('Supuestos'!$C$11*'Supuestos'!$C$12*'Supuestos'!$C$15)))))*'Supuestos'!$C$21)*'Supuestos'!$C$26))*'Supuestos'!$C$27)*'Supuestos'!$C$29)*'Supuestos'!$C$28)+(((((((IF((IF('Supuestos'!$C$11*'Supuestos'!$C$12*'Supuestos'!$C$15=0,0,'Supuestos'!$C$10/1000/('Supuestos'!$C$11*'Supuestos'!$C$12*'Supuestos'!$C$15)))=0,0,'Supuestos'!$C$8/(IF('Supuestos'!$C$11*'Supuestos'!$C$12*'Supuestos'!$C$15=0,0,'Supuestos'!$C$10/1000/('Supuestos'!$C$11*'Supuestos'!$C$12*'Supuestos'!$C$15)))))*'Supuestos'!$C$20)*'Supuestos'!$C$25)+(((IF((IF('Supuestos'!$C$11*'Supuestos'!$C$12*'Supuestos'!$C$15=0,0,'Supuestos'!$C$10/1000/('Supuestos'!$C$11*'Supuestos'!$C$12*'Supuestos'!$C$15)))=0,0,'Supuestos'!$C$8/(IF('Supuestos'!$C$11*'Supuestos'!$C$12*'Supuestos'!$C$15=0,0,'Supuestos'!$C$10/1000/('Supuestos'!$C$11*'Supuestos'!$C$12*'Supuestos'!$C$15)))))*'Supuestos'!$C$21)*'Supuestos'!$C$26))*'Supuestos'!$C$27)*('Supuestos'!$C$31*1.1))*'Supuestos'!$C$30))*('Supuestos'!$C$41+'Supuestos'!$C$42+'Supuestos'!$C$43))*(1-'Supuestos'!$C$34-'Supuestos'!$C$35-'Supuestos'!$C$36))-((IF((IF('Supuestos'!$C$11*'Supuestos'!$C$12*'Supuestos'!$C$15=0,0,'Supuestos'!$C$10/1000/('Supuestos'!$C$11*'Supuestos'!$C$12*'Supuestos'!$C$15)))=0,0,'Supuestos'!$C$8/(IF('Supuestos'!$C$11*'Supuestos'!$C$12*'Supuestos'!$C$15=0,0,'Supuestos'!$C$10/1000/('Supuestos'!$C$11*'Supuestos'!$C$12*'Supuestos'!$C$15)))))*'Supuestos'!$C$37)-'Supuestos'!$C$38-'Supuestos'!$C$8) | E15: =D15-$D$6 | F15: =IF($D$6=0,0,E15/ABS($D$6)) | G15: =RANK(E15,$E$7:$E$15)

Sheet Proyección 12 meses
B2: Proyección a 12 meses y caja
B3: La inversión crece cada mes según el supuesto de crecimiento. El cash entra según la curva de cobranza (mes 1 / 2 / 3). La ganancia acumulada muestra cuánto dinero hace falta para sostener la pauta. Cada mes multiplica inversión, costos fijos y ventas por los lanzamientos por mes de Supuestos.
B5: Concepto | C5: Mes 1 | D5: Mes 2 | E5: Mes 3 | F5: Mes 4 | G5: Mes 5 | H5: Mes 6 | I5: Mes 7 | J5: Mes 8 | K5: Mes 9 | L5: Mes 10 | M5: Mes 11 | N5: Mes 12 | O5: Total
B6: Inversión en publicidad del mes | C6: ='Supuestos'!$C$8*'Supuestos'!$C$9 | D6: =C6*(1+'Supuestos'!$C$49) | E6: =D6*(1+'Supuestos'!$C$49) | F6: =E6*(1+'Supuestos'!$C$49) | G6: =F6*(1+'Supuestos'!$C$49) | H6: =G6*(1+'Supuestos'!$C$49) | I6: =H6*(1+'Supuestos'!$C$49) | J6: =I6*(1+'Supuestos'!$C$49) | K6: =J6*(1+'Supuestos'!$C$49) | ... N6: =M6*(1+'Supuestos'!$C$49) | O6: =SUM(C6:N6)
B7: Registros compradas | C7: =IF('Modelo'!$C$10=0,0,C6/'Modelo'!$C$10) | D7: =IF('Modelo'!$C$10=0,0,D6/'Modelo'!$C$10) | E7: =IF('Modelo'!$C$10=0,0,E6/'Modelo'!$C$10) | F7: =IF('Modelo'!$C$10=0,0,F6/'Modelo'!$C$10) | G7: =IF('Modelo'!$C$10=0,0,G6/'Modelo'!$C$10) | H7: =IF('Modelo'!$C$10=0,0,H6/'Modelo'!$C$10) | I7: =IF('Modelo'!$C$10=0,0,I6/'Modelo'!$C$10) | J7: =IF('Modelo'!$C$10=0,0,J6/'Modelo'!$C$10) | ... N7: =IF('Modelo'!$C$10=0,0,N6/'Modelo'!$C$10) | O7: =SUM(C7:N7)
B8: Ventas del producto principal | C8: =C7*'Modelo'!$C$36 | D8: =D7*'Modelo'!$C$36 | E8: =E7*'Modelo'!$C$36 | F8: =F7*'Modelo'!$C$36 | G8: =G7*'Modelo'!$C$36 | H8: =H7*'Modelo'!$C$36 | I8: =I7*'Modelo'!$C$36 | J8: =J7*'Modelo'!$C$36 | ... N8: =N7*'Modelo'!$C$36 | O8: =SUM(C8:N8)
B9: Facturado (todos los productos) | C9: =C7*'Modelo'!$C$37 | D9: =D7*'Modelo'!$C$37 | E9: =E7*'Modelo'!$C$37 | F9: =F7*'Modelo'!$C$37 | G9: =G7*'Modelo'!$C$37 | H9: =H7*'Modelo'!$C$37 | I9: =I7*'Modelo'!$C$37 | J9: =J7*'Modelo'!$C$37 | ... N9: =N7*'Modelo'!$C$37 | O9: =SUM(C9:N9)
B10: Cash cobrado en el mes | C10: =C9*'Supuestos'!$C$41 | D10: =D9*'Supuestos'!$C$41+C9*'Supuestos'!$C$42 | E10: =E9*'Supuestos'!$C$41+D9*'Supuestos'!$C$42+C9*'Supuestos'!$C$43 | F10: =F9*'Supuestos'!$C$41+E9*'Supuestos'!$C$42+D9*'Supuestos'!$C$43 | G10: =G9*'Supuestos'!$C$41+F9*'Supuestos'!$C$42+E9*'Supuestos'!$C$43 | H10: =H9*'Supuestos'!$C$41+G9*'Supuestos'!$C$42+F9*'Supuestos'!$C$43 | I10: =I9*'Supuestos'!$C$41+H9*'Supuestos'!$C$42+G9*'Supuestos'!$C$43 | J10: =J9*'Supuestos'!$C$41+I9*'Supuestos'!$C$42+H9*'Supuestos'!$C$43 | K10: =K9*'Supuestos'!$C$41+J9*'Supuestos'!$C$42+I9*'Supuestos'!$C$43 | L10: =L9*'Supuestos'!$C$41+K9*'Supuestos'!$C$42+J9*'Supuestos'!$C$43 | ... N10: =N9*'Supuestos'!$C$41+M9*'Supuestos'!$C$42+L9*'Supuestos'!$C$43 | O10: =SUM(C10:N10)
B11: Comisiones y reembolsos | C11: =C10*('Supuestos'!$C$34+'Supuestos'!$C$35+'Supuestos'!$C$36) | D11: =D10*('Supuestos'!$C$34+'Supuestos'!$C$35+'Supuestos'!$C$36) | E11: =E10*('Supuestos'!$C$34+'Supuestos'!$C$35+'Supuestos'!$C$36) | F11: =F10*('Supuestos'!$C$34+'Supuestos'!$C$35+'Supuestos'!$C$36) | G11: =G10*('Supuestos'!$C$34+'Supuestos'!$C$35+'Supuestos'!$C$36) | H11: =H10*('Supuestos'!$C$34+'Supuestos'!$C$35+'Supuestos'!$C$36) | I11: =I10*('Supuestos'!$C$34+'Supuestos'!$C$35+'Supuestos'!$C$36) | J11: =J10*('Supuestos'!$C$34+'Supuestos'!$C$35+'Supuestos'!$C$36) | ... N11: =N10*('Supuestos'!$C$34+'Supuestos'!$C$35+'Supuestos'!$C$36) | O11: =SUM(C11:N11)
B12: Costos por unidad (herramientas, WhatsApp, IA) | C12: =C7*'Supuestos'!$C$37 | D12: =D7*'Supuestos'!$C$37 | E12: =E7*'Supuestos'!$C$37 | F12: =F7*'Supuestos'!$C$37 | G12: =G7*'Supuestos'!$C$37 | H12: =H7*'Supuestos'!$C$37 | I12: =I7*'Supuestos'!$C$37 | J12: =J7*'Supuestos'!$C$37 | ... N12: =N7*'Supuestos'!$C$37 | O12: =SUM(C12:N12)
B13: Costos fijos del mes | C13: ='Supuestos'!$C$38*'Supuestos'!$C$9 | D13: ='Supuestos'!$C$38*'Supuestos'!$C$9 | E13: ='Supuestos'!$C$38*'Supuestos'!$C$9 | F13: ='Supuestos'!$C$38*'Supuestos'!$C$9 | G13: ='Supuestos'!$C$38*'Supuestos'!$C$9 | H13: ='Supuestos'!$C$38*'Supuestos'!$C$9 | I13: ='Supuestos'!$C$38*'Supuestos'!$C$9 | J13: ='Supuestos'!$C$38*'Supuestos'!$C$9 | ... N13: ='Supuestos'!$C$38*'Supuestos'!$C$9 | O13: =SUM(C13:N13)
B14: Ganancia de caja del mes | C14: =C10-C11-C12-C13-C6 | D14: =D10-D11-D12-D13-D6 | E14: =E10-E11-E12-E13-E6 | F14: =F10-F11-F12-F13-F6 | G14: =G10-G11-G12-G13-G6 | H14: =H10-H11-H12-H13-H6 | I14: =I10-I11-I12-I13-I6 | J14: =J10-J11-J12-J13-J6 | ... N14: =N10-N11-N12-N13-N6 | O14: =SUM(C14:N14)
B15: Ganancia de caja acumulada (desde cero) | C15: =C14 | D15: =C15+D14 | E15: =D15+E14 | F15: =E15+F14 | G15: =F15+G14 | H15: =G15+H14 | I15: =H15+I14 | J15: =I15+J14 | K15: =J15+K14 | ... N15: =M15+N14
B16: Saldo de caja (caja inicial + ganancia acumulada) | C16: ='Supuestos'!$C$50+C15 | D16: ='Supuestos'!$C$50+D15 | E16: ='Supuestos'!$C$50+E15 | F16: ='Supuestos'!$C$50+F15 | G16: ='Supuestos'!$C$50+G15 | H16: ='Supuestos'!$C$50+H15 | I16: ='Supuestos'!$C$50+I15 | J16: ='Supuestos'!$C$50+J15 | ... N16: ='Supuestos'!$C$50+N15
B18: Caja necesaria para no frenar la pauta (el peor momento de la ganancia acumulada) | C18: =MAX(0,-MIN(C15:N15))
B19: Saldo mínimo de caja con tu caja inicial | C19: =MIN(C16:N16)
B20: Ganancia de caja acumulada en 12 meses | C20: =O14

Sheet Seguimiento
B2: Seguimiento: una columna por lanzamiento
B3: Cargá los datos reales en las celdas amarillas. El semáforo compara tu costo real por registro con el techo móvil (lo que rindieron tus últimas 4 columnas) y con el techo del modelo.
B5: Dato | C5: Lanzamiento 1 | D5: Lanzamiento 2 | E5: Lanzamiento 3 | F5: Lanzamiento 4 | G5: Lanzamiento 5 | H5: Lanzamiento 6 | I5: Lanzamiento 7 | J5: Lanzamiento 8 | K5: Lanzamiento 9 | L5: Lanzamiento 10 | M5: Lanzamiento 11 | N5: Lanzamiento 12 | O5: Promedio | P5: Máximo | Q5: Mínimo
B6: Datos que cargás
B7: Inversión en publicidad | C7: 6000 | D7: 6500 | E7: 7200 | O7: =IF(COUNT(C7:N7)=0,"",AVERAGE(C7:N7)) | P7: =IF(COUNT(C7:N7)=0,"",MAX(C7:N7)) | Q7: =IF(COUNT(C7:N7)=0,"",MIN(C7:N7))
B8: Registros | C8: 5900 | D8: 6100 | E8: 6300 | O8: =IF(COUNT(C8:N8)=0,"",AVERAGE(C8:N8)) | P8: =IF(COUNT(C8:N8)=0,"",MAX(C8:N8)) | Q8: =IF(COUNT(C8:N8)=0,"",MIN(C8:N8))
B9: Registros calificados | C9: 3540 | D9: 3660 | E9: 3780 | O9: =IF(COUNT(C9:N9)=0,"",AVERAGE(C9:N9)) | P9: =IF(COUNT(C9:N9)=0,"",MAX(C9:N9)) | Q9: =IF(COUNT(C9:N9)=0,"",MIN(C9:N9))
B10: Entraron al grupo | C10: 3950 | D10: 4100 | E10: 4150 | O10: =IF(COUNT(C10:N10)=0,"",AVERAGE(C10:N10)) | P10: =IF(COUNT(C10:N10)=0,"",MAX(C10:N10)) | Q10: =IF(COUNT(C10:N10)=0,"",MIN(C10:N10))
B11: Asistentes en vivo | C11: 890 | D11: 900 | E11: 960 | O11: =IF(COUNT(C11:N11)=0,"",AVERAGE(C11:N11)) | P11: =IF(COUNT(C11:N11)=0,"",MAX(C11:N11)) | Q11: =IF(COUNT(C11:N11)=0,"",MIN(C11:N11))
B12: Vieron el replay | C12: 3250 | D12: 3400 | E12: 3500 | O12: =IF(COUNT(C12:N12)=0,"",AVERAGE(C12:N12)) | P12: =IF(COUNT(C12:N12)=0,"",MAX(C12:N12)) | Q12: =IF(COUNT(C12:N12)=0,"",MIN(C12:N12))
B13: Solicitudes (formulario de compra, aplicación o vendedor) | C13: 170 | D13: 165 | E13: 180 | O13: =IF(COUNT(C13:N13)=0,"",AVERAGE(C13:N13)) | P13: =IF(COUNT(C13:N13)=0,"",MAX(C13:N13)) | Q13: =IF(COUNT(C13:N13)=0,"",MIN(C13:N13))
B14: Ventas de la oferta | C14: 68 | D14: 66 | E14: 72 | O14: =IF(COUNT(C14:N14)=0,"",AVERAGE(C14:N14)) | P14: =IF(COUNT(C14:N14)=0,"",MAX(C14:N14)) | Q14: =IF(COUNT(C14:N14)=0,"",MIN(C14:N14))
B15: Ventas del bump | C15: 14 | D15: 13 | E15: 15 | O15: =IF(COUNT(C15:N15)=0,"",AVERAGE(C15:N15)) | P15: =IF(COUNT(C15:N15)=0,"",MAX(C15:N15)) | Q15: =IF(COUNT(C15:N15)=0,"",MIN(C15:N15))
B16: Ventas del programa superior | C16: 3 | D16: 4 | E16: 3 | O16: =IF(COUNT(C16:N16)=0,"",AVERAGE(C16:N16)) | P16: =IF(COUNT(C16:N16)=0,"",MAX(C16:N16)) | Q16: =IF(COUNT(C16:N16)=0,"",MIN(C16:N16))
B17: Facturado del lanzamiento (a precio de lista, con cuotas por cobrar) | C17: 23800 | D17: 23400 | E17: 25500 | O17: =IF(COUNT(C17:N17)=0,"",AVERAGE(C17:N17)) | P17: =IF(COUNT(C17:N17)=0,"",MAX(C17:N17)) | Q17: =IF(COUNT(C17:N17)=0,"",MIN(C17:N17))
B18: Cash cobrado hasta ahora de ese lanzamiento | C18: 16700 | D18: 16400 | E18: 17900 | O18: =IF(COUNT(C18:N18)=0,"",AVERAGE(C18:N18)) | P18: =IF(COUNT(C18:N18)=0,"",MAX(C18:N18)) | Q18: =IF(COUNT(C18:N18)=0,"",MIN(C18:N18))
B19: Lo que calcula el modelo
B20: CPL real | C20: =IF(COUNT(C7:C18)<12,"",IF(C8=0,0,C7/C8)) | D20: =IF(COUNT(D7:D18)<12,"",IF(D8=0,0,D7/D8)) | E20: =IF(COUNT(E7:E18)<12,"",IF(E8=0,0,E7/E8)) | F20: =IF(COUNT(F7:F18)<12,"",IF(F8=0,0,F7/F8)) | G20: =IF(COUNT(G7:G18)<12,"",IF(G8=0,0,G7/G8)) | H20: =IF(COUNT(H7:H18)<12,"",IF(H8=0,0,H7/H8)) | I20: =IF(COUNT(I7:I18)<12,"",IF(I8=0,0,I7/I8)) | J20: =IF(COUNT(J7:J18)<12,"",IF(J8=0,0,J7/J8)) | ... N20: =IF(COUNT(N7:N18)<12,"",IF(N8=0,0,N7/N8)) | O20: =IF(COUNT(C20:N20)=0,"",AVERAGE(C20:N20)) | P20: =IF(COUNT(C20:N20)=0,"",MAX(C20:N20)) | Q20: =IF(COUNT(C20:N20)=0,"",MIN(C20:N20))
B21: % registro → grupo | C21: =IF(COUNT(C7:C18)<12,"",IF(C8=0,0,C10/C8)) | D21: =IF(COUNT(D7:D18)<12,"",IF(D8=0,0,D10/D8)) | E21: =IF(COUNT(E7:E18)<12,"",IF(E8=0,0,E10/E8)) | F21: =IF(COUNT(F7:F18)<12,"",IF(F8=0,0,F10/F8)) | G21: =IF(COUNT(G7:G18)<12,"",IF(G8=0,0,G10/G8)) | H21: =IF(COUNT(H7:H18)<12,"",IF(H8=0,0,H10/H8)) | I21: =IF(COUNT(I7:I18)<12,"",IF(I8=0,0,I10/I8)) | J21: =IF(COUNT(J7:J18)<12,"",IF(J8=0,0,J10/J8)) | ... N21: =IF(COUNT(N7:N18)<12,"",IF(N8=0,0,N10/N8)) | O21: =IF(COUNT(C21:N21)=0,"",AVERAGE(C21:N21)) | P21: =IF(COUNT(C21:N21)=0,"",MAX(C21:N21)) | Q21: =IF(COUNT(C21:N21)=0,"",MIN(C21:N21))
B22: % registro → en vivo | C22: =IF(COUNT(C7:C18)<12,"",IF(C8=0,0,C11/C8)) | D22: =IF(COUNT(D7:D18)<12,"",IF(D8=0,0,D11/D8)) | E22: =IF(COUNT(E7:E18)<12,"",IF(E8=0,0,E11/E8)) | F22: =IF(COUNT(F7:F18)<12,"",IF(F8=0,0,F11/F8)) | G22: =IF(COUNT(G7:G18)<12,"",IF(G8=0,0,G11/G8)) | H22: =IF(COUNT(H7:H18)<12,"",IF(H8=0,0,H11/H8)) | I22: =IF(COUNT(I7:I18)<12,"",IF(I8=0,0,I11/I8)) | J22: =IF(COUNT(J7:J18)<12,"",IF(J8=0,0,J11/J8)) | ... N22: =IF(COUNT(N7:N18)<12,"",IF(N8=0,0,N11/N8)) | O22: =IF(COUNT(C22:N22)=0,"",AVERAGE(C22:N22)) | P22: =IF(COUNT(C22:N22)=0,"",MAX(C22:N22)) | Q22: =IF(COUNT(C22:N22)=0,"",MIN(C22:N22))
B23: Ventas ÷ asistentes en vivo | C23: =IF(COUNT(C7:C18)<12,"",IF(C11=0,0,C14/C11)) | D23: =IF(COUNT(D7:D18)<12,"",IF(D11=0,0,D14/D11)) | E23: =IF(COUNT(E7:E18)<12,"",IF(E11=0,0,E14/E11)) | F23: =IF(COUNT(F7:F18)<12,"",IF(F11=0,0,F14/F11)) | G23: =IF(COUNT(G7:G18)<12,"",IF(G11=0,0,G14/G11)) | H23: =IF(COUNT(H7:H18)<12,"",IF(H11=0,0,H14/H11)) | I23: =IF(COUNT(I7:I18)<12,"",IF(I11=0,0,I14/I11)) | J23: =IF(COUNT(J7:J18)<12,"",IF(J11=0,0,J14/J11)) | ... N23: =IF(COUNT(N7:N18)<12,"",IF(N11=0,0,N14/N11)) | O23: =IF(COUNT(C23:N23)=0,"",AVERAGE(C23:N23)) | P23: =IF(COUNT(C23:N23)=0,"",MAX(C23:N23)) | Q23: =IF(COUNT(C23:N23)=0,"",MIN(C23:N23))
B24: % registro → compra | C24: =IF(COUNT(C7:C18)<12,"",IF(C8=0,0,C14/C8)) | D24: =IF(COUNT(D7:D18)<12,"",IF(D8=0,0,D14/D8)) | E24: =IF(COUNT(E7:E18)<12,"",IF(E8=0,0,E14/E8)) | F24: =IF(COUNT(F7:F18)<12,"",IF(F8=0,0,F14/F8)) | G24: =IF(COUNT(G7:G18)<12,"",IF(G8=0,0,G14/G8)) | H24: =IF(COUNT(H7:H18)<12,"",IF(H8=0,0,H14/H8)) | I24: =IF(COUNT(I7:I18)<12,"",IF(I8=0,0,I14/I8)) | J24: =IF(COUNT(J7:J18)<12,"",IF(J8=0,0,J14/J8)) | ... N24: =IF(COUNT(N7:N18)<12,"",IF(N8=0,0,N14/N8)) | O24: =IF(COUNT(C24:N24)=0,"",AVERAGE(C24:N24)) | P24: =IF(COUNT(C24:N24)=0,"",MAX(C24:N24)) | Q24: =IF(COUNT(C24:N24)=0,"",MIN(C24:N24))
B25: CPA real | C25: =IF(COUNT(C7:C18)<12,"",IF(C14=0,0,C7/C14)) | D25: =IF(COUNT(D7:D18)<12,"",IF(D14=0,0,D7/D14)) | E25: =IF(COUNT(E7:E18)<12,"",IF(E14=0,0,E7/E14)) | F25: =IF(COUNT(F7:F18)<12,"",IF(F14=0,0,F7/F14)) | G25: =IF(COUNT(G7:G18)<12,"",IF(G14=0,0,G7/G14)) | H25: =IF(COUNT(H7:H18)<12,"",IF(H14=0,0,H7/H14)) | I25: =IF(COUNT(I7:I18)<12,"",IF(I14=0,0,I7/I14)) | J25: =IF(COUNT(J7:J18)<12,"",IF(J14=0,0,J7/J14)) | ... N25: =IF(COUNT(N7:N18)<12,"",IF(N14=0,0,N7/N14)) | O25: =IF(COUNT(C25:N25)=0,"",AVERAGE(C25:N25)) | P25: =IF(COUNT(C25:N25)=0,"",MAX(C25:N25)) | Q25: =IF(COUNT(C25:N25)=0,"",MIN(C25:N25))
B26: Costo por asistente en vivo | C26: =IF(COUNT(C7:C18)<12,"",IF(C11=0,0,C7/C11)) | D26: =IF(COUNT(D7:D18)<12,"",IF(D11=0,0,D7/D11)) | E26: =IF(COUNT(E7:E18)<12,"",IF(E11=0,0,E7/E11)) | F26: =IF(COUNT(F7:F18)<12,"",IF(F11=0,0,F7/F11)) | G26: =IF(COUNT(G7:G18)<12,"",IF(G11=0,0,G7/G11)) | H26: =IF(COUNT(H7:H18)<12,"",IF(H11=0,0,H7/H11)) | I26: =IF(COUNT(I7:I18)<12,"",IF(I11=0,0,I7/I11)) | J26: =IF(COUNT(J7:J18)<12,"",IF(J11=0,0,J7/J11)) | ... N26: =IF(COUNT(N7:N18)<12,"",IF(N11=0,0,N7/N11)) | O26: =IF(COUNT(C26:N26)=0,"",AVERAGE(C26:N26)) | P26: =IF(COUNT(C26:N26)=0,"",MAX(C26:N26)) | Q26: =IF(COUNT(C26:N26)=0,"",MIN(C26:N26))
B27: CPL calificado | C27: =IF(COUNT(C7:C18)<12,"",IF(C9=0,0,C7/C9)) | D27: =IF(COUNT(D7:D18)<12,"",IF(D9=0,0,D7/D9)) | E27: =IF(COUNT(E7:E18)<12,"",IF(E9=0,0,E7/E9)) | F27: =IF(COUNT(F7:F18)<12,"",IF(F9=0,0,F7/F9)) | G27: =IF(COUNT(G7:G18)<12,"",IF(G9=0,0,G7/G9)) | H27: =IF(COUNT(H7:H18)<12,"",IF(H9=0,0,H7/H9)) | I27: =IF(COUNT(I7:I18)<12,"",IF(I9=0,0,I7/I9)) | J27: =IF(COUNT(J7:J18)<12,"",IF(J9=0,0,J7/J9)) | ... N27: =IF(COUNT(N7:N18)<12,"",IF(N9=0,0,N7/N9)) | O27: =IF(COUNT(C27:N27)=0,"",AVERAGE(C27:N27)) | P27: =IF(COUNT(C27:N27)=0,"",MAX(C27:N27)) | Q27: =IF(COUNT(C27:N27)=0,"",MIN(C27:N27))
B28: Costo por persona en el grupo | C28: =IF(COUNT(C7:C18)<12,"",IF(C10=0,0,C7/C10)) | D28: =IF(COUNT(D7:D18)<12,"",IF(D10=0,0,D7/D10)) | E28: =IF(COUNT(E7:E18)<12,"",IF(E10=0,0,E7/E10)) | F28: =IF(COUNT(F7:F18)<12,"",IF(F10=0,0,F7/F10)) | G28: =IF(COUNT(G7:G18)<12,"",IF(G10=0,0,G7/G10)) | H28: =IF(COUNT(H7:H18)<12,"",IF(H10=0,0,H7/H10)) | I28: =IF(COUNT(I7:I18)<12,"",IF(I10=0,0,I7/I10)) | J28: =IF(COUNT(J7:J18)<12,"",IF(J10=0,0,J7/J10)) | ... N28: =IF(COUNT(N7:N18)<12,"",IF(N10=0,0,N7/N10)) | O28: =IF(COUNT(C28:N28)=0,"",AVERAGE(C28:N28)) | P28: =IF(COUNT(C28:N28)=0,"",MAX(C28:N28)) | Q28: =IF(COUNT(C28:N28)=0,"",MIN(C28:N28))
B29: % en vivo → solicitud | C29: =IF(COUNT(C7:C18)<12,"",IF(C11=0,0,C13/C11)) | D29: =IF(COUNT(D7:D18)<12,"",IF(D11=0,0,D13/D11)) | E29: =IF(COUNT(E7:E18)<12,"",IF(E11=0,0,E13/E11)) | F29: =IF(COUNT(F7:F18)<12,"",IF(F11=0,0,F13/F11)) | G29: =IF(COUNT(G7:G18)<12,"",IF(G11=0,0,G13/G11)) | H29: =IF(COUNT(H7:H18)<12,"",IF(H11=0,0,H13/H11)) | I29: =IF(COUNT(I7:I18)<12,"",IF(I11=0,0,I13/I11)) | J29: =IF(COUNT(J7:J18)<12,"",IF(J11=0,0,J13/J11)) | ... N29: =IF(COUNT(N7:N18)<12,"",IF(N11=0,0,N13/N11)) | O29: =IF(COUNT(C29:N29)=0,"",AVERAGE(C29:N29)) | P29: =IF(COUNT(C29:N29)=0,"",MAX(C29:N29)) | Q29: =IF(COUNT(C29:N29)=0,"",MIN(C29:N29))
B30: Costo por solicitud | C30: =IF(COUNT(C7:C18)<12,"",IF(C13=0,0,C7/C13)) | D30: =IF(COUNT(D7:D18)<12,"",IF(D13=0,0,D7/D13)) | E30: =IF(COUNT(E7:E18)<12,"",IF(E13=0,0,E7/E13)) | F30: =IF(COUNT(F7:F18)<12,"",IF(F13=0,0,F7/F13)) | G30: =IF(COUNT(G7:G18)<12,"",IF(G13=0,0,G7/G13)) | H30: =IF(COUNT(H7:H18)<12,"",IF(H13=0,0,H7/H13)) | I30: =IF(COUNT(I7:I18)<12,"",IF(I13=0,0,I7/I13)) | J30: =IF(COUNT(J7:J18)<12,"",IF(J13=0,0,J7/J13)) | ... N30: =IF(COUNT(N7:N18)<12,"",IF(N13=0,0,N7/N13)) | O30: =IF(COUNT(C30:N30)=0,"",AVERAGE(C30:N30)) | P30: =IF(COUNT(C30:N30)=0,"",MAX(C30:N30)) | Q30: =IF(COUNT(C30:N30)=0,"",MIN(C30:N30))
B31: % solicitud → compra | C31: =IF(COUNT(C7:C18)<12,"",IF(C13=0,0,C14/C13)) | D31: =IF(COUNT(D7:D18)<12,"",IF(D13=0,0,D14/D13)) | E31: =IF(COUNT(E7:E18)<12,"",IF(E13=0,0,E14/E13)) | F31: =IF(COUNT(F7:F18)<12,"",IF(F13=0,0,F14/F13)) | G31: =IF(COUNT(G7:G18)<12,"",IF(G13=0,0,G14/G13)) | H31: =IF(COUNT(H7:H18)<12,"",IF(H13=0,0,H14/H13)) | I31: =IF(COUNT(I7:I18)<12,"",IF(I13=0,0,I14/I13)) | J31: =IF(COUNT(J7:J18)<12,"",IF(J13=0,0,J14/J13)) | ... N31: =IF(COUNT(N7:N18)<12,"",IF(N13=0,0,N14/N13)) | O31: =IF(COUNT(C31:N31)=0,"",AVERAGE(C31:N31)) | P31: =IF(COUNT(C31:N31)=0,"",MAX(C31:N31)) | Q31: =IF(COUNT(C31:N31)=0,"",MIN(C31:N31))
B32: Valor neto por unidad real (sobre facturado, cobranza completa) | C32: =IF(COUNT(C7:C18)<12,"",IF(C8=0,0,(C17*(1-'Supuestos'!$C$34-'Supuestos'!$C$35-'Supuestos'!$C$36)-C8*'Supuestos'!$C$37)/C8)) | D32: =IF(COUNT(D7:D18)<12,"",IF(D8=0,0,(D17*(1-'Supuestos'!$C$34-'Supuestos'!$C$35-'Supuestos'!$C$36)-D8*'Supuestos'!$C$37)/D8)) | E32: =IF(COUNT(E7:E18)<12,"",IF(E8=0,0,(E17*(1-'Supuestos'!$C$34-'Supuestos'!$C$35-'Supuestos'!$C$36)-E8*'Supuestos'!$C$37)/E8)) | F32: =IF(COUNT(F7:F18)<12,"",IF(F8=0,0,(F17*(1-'Supuestos'!$C$34-'Supuestos'!$C$35-'Supuestos'!$C$36)-F8*'Supuestos'!$C$37)/F8)) | G32: =IF(COUNT(G7:G18)<12,"",IF(G8=0,0,(G17*(1-'Supuestos'!$C$34-'Supuestos'!$C$35-'Supuestos'!$C$36)-G8*'Supuestos'!$C$37)/G8)) | H32: =IF(COUNT(H7:H18)<12,"",IF(H8=0,0,(H17*(1-'Supuestos'!$C$34-'Supuestos'!$C$35-'Supuestos'!$C$36)-H8*'Supuestos'!$C$37)/H8)) | I32: =IF(COUNT(I7:I18)<12,"",IF(I8=0,0,(I17*(1-'Supuestos'!$C$34-'Supuestos'!$C$35-'Supuestos'!$C$36)-I8*'Supuestos'!$C$37)/I8)) | J32: =IF(COUNT(J7:J18)<12,"",IF(J8=0,0,(J17*(1-'Supuestos'!$C$34-'Supuestos'!$C$35-'Supuestos'!$C$36)-J8*'Supuestos'!$C$37)/J8)) | ... N32: =IF(COUNT(N7:N18)<12,"",IF(N8=0,0,(N17*(1-'Supuestos'!$C$34-'Supuestos'!$C$35-'Supuestos'!$C$36)-N8*'Supuestos'!$C$37)/N8)) | O32: =IF(COUNT(C32:N32)=0,"",AVERAGE(C32:N32)) | P32: =IF(COUNT(C32:N32)=0,"",MAX(C32:N32)) | Q32: =IF(COUNT(C32:N32)=0,"",MIN(C32:N32))
B33: Ganancia del período al completar la cobranza | C33: =IF(COUNT(C7:C18)<12,"",C17*(1-'Supuestos'!$C$34-'Supuestos'!$C$35-'Supuestos'!$C$36)-C8*'Supuestos'!$C$37-'Supuestos'!$C$38-C7) | D33: =IF(COUNT(D7:D18)<12,"",D17*(1-'Supuestos'!$C$34-'Supuestos'!$C$35-'Supuestos'!$C$36)-D8*'Supuestos'!$C$37-'Supuestos'!$C$38-D7) | E33: =IF(COUNT(E7:E18)<12,"",E17*(1-'Supuestos'!$C$34-'Supuestos'!$C$35-'Supuestos'!$C$36)-E8*'Supuestos'!$C$37-'Supuestos'!$C$38-E7) | F33: =IF(COUNT(F7:F18)<12,"",F17*(1-'Supuestos'!$C$34-'Supuestos'!$C$35-'Supuestos'!$C$36)-F8*'Supuestos'!$C$37-'Supuestos'!$C$38-F7) | G33: =IF(COUNT(G7:G18)<12,"",G17*(1-'Supuestos'!$C$34-'Supuestos'!$C$35-'Supuestos'!$C$36)-G8*'Supuestos'!$C$37-'Supuestos'!$C$38-G7) | H33: =IF(COUNT(H7:H18)<12,"",H17*(1-'Supuestos'!$C$34-'Supuestos'!$C$35-'Supuestos'!$C$36)-H8*'Supuestos'!$C$37-'Supuestos'!$C$38-H7) | I33: =IF(COUNT(I7:I18)<12,"",I17*(1-'Supuestos'!$C$34-'Supuestos'!$C$35-'Supuestos'!$C$36)-I8*'Supuestos'!$C$37-'Supuestos'!$C$38-I7) | J33: =IF(COUNT(J7:J18)<12,"",J17*(1-'Supuestos'!$C$34-'Supuestos'!$C$35-'Supuestos'!$C$36)-J8*'Supuestos'!$C$37-'Supuestos'!$C$38-J7) | ... N33: =IF(COUNT(N7:N18)<12,"",N17*(1-'Supuestos'!$C$34-'Supuestos'!$C$35-'Supuestos'!$C$36)-N8*'Supuestos'!$C$37-'Supuestos'!$C$38-N7) | O33: =IF(COUNT(C33:N33)=0,"",AVERAGE(C33:N33)) | P33: =IF(COUNT(C33:N33)=0,"",MAX(C33:N33)) | Q33: =IF(COUNT(C33:N33)=0,"",MIN(C33:N33))
B34: Ganancia de caja del período (con lo cobrado hasta ahora) | C34: =IF(COUNT(C7:C18)<12,"",C18*(1-'Supuestos'!$C$34-'Supuestos'!$C$35-'Supuestos'!$C$36)-C8*'Supuestos'!$C$37-'Supuestos'!$C$38-C7) | D34: =IF(COUNT(D7:D18)<12,"",D18*(1-'Supuestos'!$C$34-'Supuestos'!$C$35-'Supuestos'!$C$36)-D8*'Supuestos'!$C$37-'Supuestos'!$C$38-D7) | E34: =IF(COUNT(E7:E18)<12,"",E18*(1-'Supuestos'!$C$34-'Supuestos'!$C$35-'Supuestos'!$C$36)-E8*'Supuestos'!$C$37-'Supuestos'!$C$38-E7) | F34: =IF(COUNT(F7:F18)<12,"",F18*(1-'Supuestos'!$C$34-'Supuestos'!$C$35-'Supuestos'!$C$36)-F8*'Supuestos'!$C$37-'Supuestos'!$C$38-F7) | G34: =IF(COUNT(G7:G18)<12,"",G18*(1-'Supuestos'!$C$34-'Supuestos'!$C$35-'Supuestos'!$C$36)-G8*'Supuestos'!$C$37-'Supuestos'!$C$38-G7) | H34: =IF(COUNT(H7:H18)<12,"",H18*(1-'Supuestos'!$C$34-'Supuestos'!$C$35-'Supuestos'!$C$36)-H8*'Supuestos'!$C$37-'Supuestos'!$C$38-H7) | I34: =IF(COUNT(I7:I18)<12,"",I18*(1-'Supuestos'!$C$34-'Supuestos'!$C$35-'Supuestos'!$C$36)-I8*'Supuestos'!$C$37-'Supuestos'!$C$38-I7) | J34: =IF(COUNT(J7:J18)<12,"",J18*(1-'Supuestos'!$C$34-'Supuestos'!$C$35-'Supuestos'!$C$36)-J8*'Supuestos'!$C$37-'Supuestos'!$C$38-J7) | ... N34: =IF(COUNT(N7:N18)<12,"",N18*(1-'Supuestos'!$C$34-'Supuestos'!$C$35-'Supuestos'!$C$36)-N8*'Supuestos'!$C$37-'Supuestos'!$C$38-N7) | O34: =IF(COUNT(C34:N34)=0,"",AVERAGE(C34:N34)) | P34: =IF(COUNT(C34:N34)=0,"",MAX(C34:N34)) | Q34: =IF(COUNT(C34:N34)=0,"",MIN(C34:N34))
B35: Ganancia por unidad real (ganancia ÷ unidades) | C35: =IF(COUNT(C7:C18)<12,"",IF(C8=0,0,(C17*(1-'Supuestos'!$C$34-'Supuestos'!$C$35-'Supuestos'!$C$36)-C8*'Supuestos'!$C$37-'Supuestos'!$C$38-C7)/C8)) | D35: =IF(COUNT(D7:D18)<12,"",IF(D8=0,0,(D17*(1-'Supuestos'!$C$34-'Supuestos'!$C$35-'Supuestos'!$C$36)-D8*'Supuestos'!$C$37-'Supuestos'!$C$38-D7)/D8)) | E35: =IF(COUNT(E7:E18)<12,"",IF(E8=0,0,(E17*(1-'Supuestos'!$C$34-'Supuestos'!$C$35-'Supuestos'!$C$36)-E8*'Supuestos'!$C$37-'Supuestos'!$C$38-E7)/E8)) | F35: =IF(COUNT(F7:F18)<12,"",IF(F8=0,0,(F17*(1-'Supuestos'!$C$34-'Supuestos'!$C$35-'Supuestos'!$C$36)-F8*'Supuestos'!$C$37-'Supuestos'!$C$38-F7)/F8)) | G35: =IF(COUNT(G7:G18)<12,"",IF(G8=0,0,(G17*(1-'Supuestos'!$C$34-'Supuestos'!$C$35-'Supuestos'!$C$36)-G8*'Supuestos'!$C$37-'Supuestos'!$C$38-G7)/G8)) | H35: =IF(COUNT(H7:H18)<12,"",IF(H8=0,0,(H17*(1-'Supuestos'!$C$34-'Supuestos'!$C$35-'Supuestos'!$C$36)-H8*'Supuestos'!$C$37-'Supuestos'!$C$38-H7)/H8)) | I35: =IF(COUNT(I7:I18)<12,"",IF(I8=0,0,(I17*(1-'Supuestos'!$C$34-'Supuestos'!$C$35-'Supuestos'!$C$36)-I8*'Supuestos'!$C$37-'Supuestos'!$C$38-I7)/I8)) | J35: =IF(COUNT(J7:J18)<12,"",IF(J8=0,0,(J17*(1-'Supuestos'!$C$34-'Supuestos'!$C$35-'Supuestos'!$C$36)-J8*'Supuestos'!$C$37-'Supuestos'!$C$38-J7)/J8)) | ... N35: =IF(COUNT(N7:N18)<12,"",IF(N8=0,0,(N17*(1-'Supuestos'!$C$34-'Supuestos'!$C$35-'Supuestos'!$C$36)-N8*'Supuestos'!$C$37-'Supuestos'!$C$38-N7)/N8)) | O35: =IF(COUNT(C35:N35)=0,"",AVERAGE(C35:N35)) | P35: =IF(COUNT(C35:N35)=0,"",MAX(C35:N35)) | Q35: =IF(COUNT(C35:N35)=0,"",MIN(C35:N35))
B36: ROAS sobre cash neto (cobranza completa) | C36: =IF(COUNT(C7:C18)<12,"",IF(C7=0,0,C17*(1-'Supuestos'!$C$34-'Supuestos'!$C$35-'Supuestos'!$C$36)/C7)) | D36: =IF(COUNT(D7:D18)<12,"",IF(D7=0,0,D17*(1-'Supuestos'!$C$34-'Supuestos'!$C$35-'Supuestos'!$C$36)/D7)) | E36: =IF(COUNT(E7:E18)<12,"",IF(E7=0,0,E17*(1-'Supuestos'!$C$34-'Supuestos'!$C$35-'Supuestos'!$C$36)/E7)) | F36: =IF(COUNT(F7:F18)<12,"",IF(F7=0,0,F17*(1-'Supuestos'!$C$34-'Supuestos'!$C$35-'Supuestos'!$C$36)/F7)) | G36: =IF(COUNT(G7:G18)<12,"",IF(G7=0,0,G17*(1-'Supuestos'!$C$34-'Supuestos'!$C$35-'Supuestos'!$C$36)/G7)) | H36: =IF(COUNT(H7:H18)<12,"",IF(H7=0,0,H17*(1-'Supuestos'!$C$34-'Supuestos'!$C$35-'Supuestos'!$C$36)/H7)) | I36: =IF(COUNT(I7:I18)<12,"",IF(I7=0,0,I17*(1-'Supuestos'!$C$34-'Supuestos'!$C$35-'Supuestos'!$C$36)/I7)) | J36: =IF(COUNT(J7:J18)<12,"",IF(J7=0,0,J17*(1-'Supuestos'!$C$34-'Supuestos'!$C$35-'Supuestos'!$C$36)/J7)) | ... N36: =IF(COUNT(N7:N18)<12,"",IF(N7=0,0,N17*(1-'Supuestos'!$C$34-'Supuestos'!$C$35-'Supuestos'!$C$36)/N7)) | O36: =IF(COUNT(C36:N36)=0,"",AVERAGE(C36:N36)) | P36: =IF(COUNT(C36:N36)=0,"",MAX(C36:N36)) | Q36: =IF(COUNT(C36:N36)=0,"",MIN(C36:N36))
B37: ROAS de caja (cobrado hasta ahora) | C37: =IF(COUNT(C7:C18)<12,"",IF(C7=0,0,C18*(1-'Supuestos'!$C$34-'Supuestos'!$C$35-'Supuestos'!$C$36)/C7)) | D37: =IF(COUNT(D7:D18)<12,"",IF(D7=0,0,D18*(1-'Supuestos'!$C$34-'Supuestos'!$C$35-'Supuestos'!$C$36)/D7)) | E37: =IF(COUNT(E7:E18)<12,"",IF(E7=0,0,E18*(1-'Supuestos'!$C$34-'Supuestos'!$C$35-'Supuestos'!$C$36)/E7)) | F37: =IF(COUNT(F7:F18)<12,"",IF(F7=0,0,F18*(1-'Supuestos'!$C$34-'Supuestos'!$C$35-'Supuestos'!$C$36)/F7)) | G37: =IF(COUNT(G7:G18)<12,"",IF(G7=0,0,G18*(1-'Supuestos'!$C$34-'Supuestos'!$C$35-'Supuestos'!$C$36)/G7)) | H37: =IF(COUNT(H7:H18)<12,"",IF(H7=0,0,H18*(1-'Supuestos'!$C$34-'Supuestos'!$C$35-'Supuestos'!$C$36)/H7)) | I37: =IF(COUNT(I7:I18)<12,"",IF(I7=0,0,I18*(1-'Supuestos'!$C$34-'Supuestos'!$C$35-'Supuestos'!$C$36)/I7)) | J37: =IF(COUNT(J7:J18)<12,"",IF(J7=0,0,J18*(1-'Supuestos'!$C$34-'Supuestos'!$C$35-'Supuestos'!$C$36)/J7)) | ... N37: =IF(COUNT(N7:N18)<12,"",IF(N7=0,0,N18*(1-'Supuestos'!$C$34-'Supuestos'!$C$35-'Supuestos'!$C$36)/N7)) | O37: =IF(COUNT(C37:N37)=0,"",AVERAGE(C37:N37)) | P37: =IF(COUNT(C37:N37)=0,"",MAX(C37:N37)) | Q37: =IF(COUNT(C37:N37)=0,"",MIN(C37:N37))
B38: Techo móvil (mediana de tus últimas 4 columnas; al inicio, el del modelo) | C38: =IF(COUNT(C7:C18)<12,"",'Modelo'!$C$52) | D38: =IF(COUNT(D7:D18)<12,"",IF(COUNT(C32:C32)>0,MEDIAN(C32:C32),'Modelo'!$C$52)) | E38: =IF(COUNT(E7:E18)<12,"",IF(COUNT(C32:D32)>0,MEDIAN(C32:D32),'Modelo'!$C$52)) | F38: =IF(COUNT(F7:F18)<12,"",IF(COUNT(C32:E32)>0,MEDIAN(C32:E32),'Modelo'!$C$52)) | G38: =IF(COUNT(G7:G18)<12,"",IF(COUNT(C32:F32)>0,MEDIAN(C32:F32),'Modelo'!$C$52)) | H38: =IF(COUNT(H7:H18)<12,"",IF(COUNT(D32:G32)>0,MEDIAN(D32:G32),'Modelo'!$C$52)) | I38: =IF(COUNT(I7:I18)<12,"",IF(COUNT(E32:H32)>0,MEDIAN(E32:H32),'Modelo'!$C$52)) | J38: =IF(COUNT(J7:J18)<12,"",IF(COUNT(F32:I32)>0,MEDIAN(F32:I32),'Modelo'!$C$52)) | K38: =IF(COUNT(K7:K18)<12,"",IF(COUNT(G32:J32)>0,MEDIAN(G32:J32),'Modelo'!$C$52)) | L38: =IF(COUNT(L7:L18)<12,"",IF(COUNT(H32:K32)>0,MEDIAN(H32:K32),'Modelo'!$C$52)) | M38: =IF(COUNT(M7:M18)<12,"",IF(COUNT(I32:L32)>0,MEDIAN(I32:L32),'Modelo'!$C$52)) | N38: =IF(COUNT(N7:N18)<12,"",IF(COUNT(J32:M32)>0,MEDIAN(J32:M32),'Modelo'!$C$52)) | O38: =IF(COUNT(C38:N38)=0,"",AVERAGE(C38:N38)) | P38: =IF(COUNT(C38:N38)=0,"",MAX(C38:N38)) | Q38: =IF(COUNT(C38:N38)=0,"",MIN(C38:N38))
B39: Semáforo (costo por unidad contra el techo móvil, y ROAS contra el objetivo) | C39: =IF(COUNT(C7:C18)<12,"",IF(C20>C38,"ROJO",IF(AND(C20<=C38/(1+'Supuestos'!$C$47),C36>='Supuestos'!$C$46),"VERDE","AMARILLO"))) | D39: =IF(COUNT(D7:D18)<12,"",IF(D20>D38,"ROJO",IF(AND(D20<=D38/(1+'Supuestos'!$C$47),D36>='Supuestos'!$C$46),"VERDE","AMARILLO"))) | E39: =IF(COUNT(E7:E18)<12,"",IF(E20>E38,"ROJO",IF(AND(E20<=E38/(1+'Supuestos'!$C$47),E36>='Supuestos'!$C$46),"VERDE","AMARILLO"))) | F39: =IF(COUNT(F7:F18)<12,"",IF(F20>F38,"ROJO",IF(AND(F20<=F38/(1+'Supuestos'!$C$47),F36>='Supuestos'!$C$46),"VERDE","AMARILLO"))) | G39: =IF(COUNT(G7:G18)<12,"",IF(G20>G38,"ROJO",IF(AND(G20<=G38/(1+'Supuestos'!$C$47),G36>='Supuestos'!$C$46),"VERDE","AMARILLO"))) | H39: =IF(COUNT(H7:H18)<12,"",IF(H20>H38,"ROJO",IF(AND(H20<=H38/(1+'Supuestos'!$C$47),H36>='Supuestos'!$C$46),"VERDE","AMARILLO"))) | I39: =IF(COUNT(I7:I18)<12,"",IF(I20>I38,"ROJO",IF(AND(I20<=I38/(1+'Supuestos'!$C$47),I36>='Supuestos'!$C$46),"VERDE","AMARILLO"))) | J39: =IF(COUNT(J7:J18)<12,"",IF(J20>J38,"ROJO",IF(AND(J20<=J38/(1+'Supuestos'!$C$47),J36>='Supuestos'!$C$46),"VERDE","AMARILLO"))) | ... N39: =IF(COUNT(N7:N18)<12,"",IF(N20>N38,"ROJO",IF(AND(N20<=N38/(1+'Supuestos'!$C$47),N36>='Supuestos'!$C$46),"VERDE","AMARILLO")))

Sheet Benchmarks
B2: Benchmarks: contra qué comparar tus números
B3: Valores de referencia para tráfico frío en español. Son orden de magnitud, no objetivo: tus propios datos de Seguimiento mandan.
B5: Métrica | C5: Malo | D5: Aceptable | E5: Bueno | F5: Ganador | G5: Tu valor (Modelo) | H5: Fuente / nota
B6: CPL (USD) | C6: >3,00 | D6: 1,50 a 3,00 | E6: 0,80 a 1,50 | F6: <0,80 | G6: ='Modelo'!$C$10 | H6: Webinars gratuitos hispanos a tráfico frío, 2025 a 2026. Un agregador LATAM cita 0,50 a 3 para webinar (fuente débil).
B7: % visitas → registro (landing) | C7: <15 % | D7: 15 a 22 % | E7: 22 a 30 % | F7: >30 % | G7: ='Supuestos'!$C$15 | H7: Con nombre + WhatsApp. Con solo email sube.
B8: % registro → grupo de WhatsApp | C8: <50 % | D8: 50 a 65 % | E8: 65 a 80 % | F8: >80 % | G8: ='Supuestos'!$C$19 | H8: Depende de cuán directo sea el botón al grupo.
B9: % registro → en vivo | C9: <10 % | D9: 10 a 15 % | E9: 15 a 22 % | F9: >22 % | G9: ='Supuestos'!$C$20 | H9: Hispano tráfico frío. En B2B USA el promedio es 33 % (Goldcast 2025, 19.531 webinars).
B10: % registro → replay | C10: <40 % | D10: 40 a 60 % | E10: 60 a 80 % | F10: >80 % | G10: ='Supuestos'!$C$21 | H10: Con bot de WhatsApp que manda el replay.
B11: % registros que califican | C11: <40 % | D11: 40 a 55 % | E11: 55 a 70 % | F11: >70 % | G11: ='Supuestos'!$C$16 | H11: Depende de la pregunta que califica.
B12: Costo por persona en el grupo (USD) | C12: >3,00 | D12: 1,80 a 3,00 | E12: 1,00 a 1,80 | F12: <1,00 | G12: ='Modelo'!$C$16 | H12: Webinars hispanos 2026: mediana cerca de 1,60.
B13: % asistentes en vivo que solicitan | C13: <5 % | D13: 5 a 10 % | E13: 10 a 15 % | F13: >15 % | G13: ='Supuestos'!$C$25 | H13: Formulario de compra o aplicación presentado en el webinar. Hispano: 10 a 15 % de los asistentes en vivo.
B14: Costo por solicitud (USD) | C14: >150 | D14: 80 a 150 | E14: 40 a 80 | F14: <40 | G14: ='Modelo'!$C$25 | H14: Webinars de llamada hispanos: mediana cerca de 80.
B15: % solicitud → compra | C15: <25 % | D15: 25 a 40 % | E15: 40 a 55 % | F15: >55 % | G15: ='Supuestos'!$C$27 | H15: Con vendedor: 40 a 60 %. Compra directa en el formulario: más alto.
B16: % registro → compra | C16: <0,6 % | D16: 0,6 a 1 % | E16: 1 a 1,5 % | F16: >1,5 % | G16: ='Modelo'!$C$27 | H16: El producto de todas las conversiones.
B17: Costo por asistente en vivo (USD) | C17: >15 | D17: 8 a 15 | E17: 5 a 8 | F17: <5 | G17: ='Modelo'!$C$19
B18: ROAS sobre cash neto | C18: <1,2 | D18: 1,2 a 1,8 | E18: 1,8 a 2,5 | F18: >2,5 | G18: ='Modelo'!$C$47 | H18: Por lanzamiento, cobranza completa.

Sheet Glosario
B2: Glosario
B3: Los términos que usa este modelo, en el orden del embudo.
B5: Término | C5: Qué es | D5: Dónde aparece
B6: CPM | C6: Costo por mil impresiones: lo que cobra la plataforma de anuncios por mostrar el aviso mil veces. | D6: Supuestos
B7: CTR | C7: Porcentaje de impresiones que terminan en clic al enlace. | D7: Supuestos
B8: Clic → visita | C8: Porcentaje de clics que llegan a cargar la página. Siempre menor a 100 % (cierran antes de que cargue). | D8: Supuestos
B9: Unidad de adquisición | C9: Lo que compra la publicidad en este embudo (visita, registro o entrada). Todo el modelo se mide por unidad. | D9: Modelo
B10: Costo por unidad | C10: Inversión dividida por unidades compradas: costo por visita, CPL (costo por lead o registro) o costo por entrada. | D10: Modelo, Seguimiento
B11: Conversión | C11: Porcentaje que pasa de una etapa a la siguiente. Las conversiones se multiplican: 15 % × 14 % × 44 % = 0,9 %. | D11: Supuestos, Modelo
B12: Show rate | C12: Porcentaje de registrados (o compradores) que asisten en vivo. El replay se cuenta aparte. | D12: Supuestos
B13: Bump | C13: Oferta extra en el mismo checkout, con una casilla. Se mide como % de los compradores. | D13: Supuestos
B14: OTO / upsell | C14: Oferta que aparece después de pagar (one-time offer). Downsell: la oferta más barata para quien rechaza la OTO. | D14: Supuestos
B15: Backend | C15: Producto de mayor valor que se vende después del primero, por ascenso o por llamada. | D15: Supuestos
B16: AOV | C16: Facturado promedio por comprador del producto principal, sumando toda la escalera. | D16: Modelo
... B43: Registro calificado | C43: Registro que pasa la pregunta que califica en el formulario. Da el CPL calificado, además del CPL real. | D43: Modelo

Sheet Chequeos
B2: Chequeos: el modelo se revisa solo
B3: Si alguna fila dice REVISAR, hay un supuesto fuera de rango o un dato inconsistente.
B5: Chequeo | C5: Estado | D5: Qué revisar
B6: Ninguna celda con error en Modelo | C6: =IF(ISERROR(SUM('Modelo'!C5:C160)),"REVISAR","OK") | D6: Si dice REVISAR, hay un #DIV/0! o #REF!: casi siempre un supuesto en 0 o una fila borrada.
B7: Ninguna celda con error en Embudo | C7: =IF(ISERROR(SUM('Embudo'!C5:H60)),"REVISAR","OK") | D7: Si dice REVISAR, hay un #DIV/0! o #REF!: casi siempre un supuesto en 0 o una fila borrada.
B8: Ninguna celda con error en Resumen | C8: =IF(ISERROR(SUM('Resumen'!C5:C60)),"REVISAR","OK") | D8: Si dice REVISAR, hay un #DIV/0! o #REF!: casi siempre un supuesto en 0 o una fila borrada.
B9: Ninguna celda con error en Proyección 12 meses | C9: =IF(ISERROR(SUM('Proyección 12 meses'!C5:O40)),"REVISAR","OK") | D9: Si dice REVISAR, hay un #DIV/0! o #REF!: casi siempre un supuesto en 0 o una fila borrada.
B10: Ninguna celda con error en Escenarios | C10: =IF(ISERROR(SUM('Escenarios'!C5:L120)),"REVISAR","OK") | D10: Si dice REVISAR, hay un #DIV/0! o #REF!: casi siempre un supuesto en 0 o una fila borrada.
B11: Ninguna celda con error en Seguimiento | C11: =IF(ISERROR(SUM('Seguimiento'!C5:Q80)),"REVISAR","OK") | D11: Si dice REVISAR, hay un #DIV/0! o #REF!: casi siempre un supuesto en 0 o una fila borrada.
B12: Los supuestos de tráfico son mayores a cero | C12: =IF(AND('Supuestos'!$C$10>0,'Supuestos'!$C$11>0,'Supuestos'!$C$12>0,'Supuestos'!$C$15>0),"OK","REVISAR") | D12: Con un 0 en el tráfico o en la conversión de la página no hay unidades y el modelo no dice nada.
B13: La curva de cobranza suma 100 % | C13: =IF(ABS('Supuestos'!$C$41+'Supuestos'!$C$42+'Supuestos'!$C$43-1)<0.001,"OK","REVISAR") | D13: Supuestos → cobranza mes 1 + mes 2 + mes 3 = 100 %.
B14: Comisiones + reembolsos menores al 60 % | C14: =IF(('Supuestos'!$C$34+'Supuestos'!$C$35+'Supuestos'!$C$36)<0.6,"OK","REVISAR") | D14: Si suman más, revisá los porcentajes.
B15: El escenario en uso es 1, 2 o 3 | C15: =IF(OR('Supuestos'!$C$6=1,'Supuestos'!$C$6=2,'Supuestos'!$C$6=3),"OK","REVISAR") | D15: Supuestos → celda 'Escenario en uso'.
B16: La inversión es mayor a cero | C16: =IF('Supuestos'!$C$8>0,"OK","REVISAR")
B17: La meta de ventas es alcanzable (hay conversión a venta) | C17: =IF('Modelo'!$C$27>0,"OK","REVISAR") | D17: Con conversión a venta en 0, la inversión para la meta dice 'inalcanzable con estos supuestos'.
B18: Las conversiones están entre 0 y 100 % | C18: =IF(AND('Supuestos'!$C$11>=0,'Supuestos'!$C$11<=1,'Supuestos'!$C$12>=0,'Supuestos'!$C$12<=1,'Supuestos'!$C$15>=0,'Supuestos'!$C$15<=1,'Supuestos'!$C$16>=0,'Supuestos'!$C$16<=1,'Supuestos'!$C$19>=0,'Supuestos'!$C$19<=1,'Supuestos'!$C$20>=0,'Supuestos'!$C$20<=1,'Supuestos'!$C$21>=0,'Supuestos'!$C$21<=1,'Supuestos'!$C$25>=0,'Supuestos'!$C$25<=1,'Supuestos'!$C$26>=0,'Supuestos'!$C$26<=1,'Supuestos'!$C$27>=0,'Supuestos'!$C$27<=1,'Supuestos'!$C$29>=0,'Supuestos'!$C$29<=1,'Supuestos'!$C$31>=0,'Supuestos'!$C$31<=1),"OK","REVISAR") | D18: Un 25 % se escribe 25 % (o 0,25), no 25.
B19: El margen de seguridad está entre 0 y 100 % | C19: =IF(AND('Supuestos'!$C$47>=0,'Supuestos'!$C$47<=1),"OK","REVISAR")
B20: El crecimiento mensual está entre −50 % y 100 % | C20: =IF(AND('Supuestos'!$C$49>=-0.5,'Supuestos'!$C$49<=1),"OK","REVISAR") | D20: Más de 100 % por mes no es realista para una proyección.
B21: La cadena es decreciente (cada etapa tiene menos gente que la anterior) | C21: =IF(AND('Modelo'!$C$15<='Modelo'!$C$11,'Modelo'!$C$17<='Modelo'!$C$11,'Modelo'!$C$21<='Modelo'!$C$17,'Modelo'!$C$22<='Modelo'!$C$18,'Modelo'!$C$26<='Modelo'!$C$23),"OK","REVISAR") | D21: Si falla, alguna conversión está por encima de 100 %.
B22: En vivo + replay no superan el 100 % de los registrados | C22: =IF(('Supuestos'!$C$20+'Supuestos'!$C$21)<=1,"OK","REVISAR") | D22: El replay se cuenta sin los que fueron en vivo.
B24: Estado general del modelo | C24: =IF(COUNTIF(C6:C22,"REVISAR")=0,"OK","REVISAR")
