Workbook
Name Autor_Jesus_Tassarolo: "Modelo financiero de embudos · creado por Jesús Tassarolo · TooAudience · youtube.com/@JesusTassaroloSinFiltro"

Sheet Inicio
B1: © Jesús Tassarolo · TooAudience · youtube.com/@JesusTassaroloSinFiltro · uso personal; no redistribuir modificado
B2: Modelo financiero · Embudo de webinar pago (evento pago)
B3: Anuncios → página de ventas de la entrada → entrada + bump → grupo de WhatsApp → evento en vivo y replay → oferta → programa superior
B5: Para qué sirve este modelo
B6: Es el modelo financiero de un embudo de webinar pago: anuncios que venden una entrada barata a un evento, un grupo de WhatsApp, el evento en vivo (con replay) donde se presenta la oferta principal, y un programa superior que se vende después. Con tus números (o con el ejemplo cargado) te dice cuánto vale cada entrada que comprás con publicidad, hasta cuánto podés pagar por entrada y por cada etapa siguiente, cuánto invertir para una meta de ventas, cuánta caja necesitás y qué palanca mejora más la ganancia.
B7: La unidad que comprás es la entrada vendida: acá los leads ya son compradores de un low ticket, no registros. Lo primero que se mira es qué parte de la pauta recupera la entrada (ROAS del front); después, escalón por escalón: costo por persona en el grupo, costo por asistente en vivo (mucho más alto que en gratuito porque pagaron), costo por solicitud y cierre, cada uno con su cantidad y su porcentaje.
B9: Cómo usarlo en 7 pasos
B10: 1. Andá a Supuestos y reemplazá el ejemplo por tus números. Si todavía no tenés datos, dejá el escenario en 1 (conservador) y usá Benchmarks como referencia.
B11: 2. Mirá Resumen: ganancia del lanzamiento, ROAS, el techo y el objetivo de costo por entrada, y el semáforo. Después Embudo: todos los pasos en orden con cuántos pasan, lo que pagás, lo que te queda y lo máximo que podrías pagar por cada uno.
B12: 3. Abrí Simulador para jugar: cada supuesto está en orden de embudo (inversión, CPM, CTR, visitas, conversión de la landing, asistencia, solicitudes, cierre, precios, costos) con tu número en amarillo al lado de la base. Cambiá uno y mirá cómo se mueven todos los demás contra la base; la columna Diferencia te dice cuánto. No toca Supuestos.
B13: 4. Abrí Escenarios para ver qué pasa si cambia el precio, la conversión o el costo en tablas de dos variables, y Sensibilidad para saber qué variable conviene trabajar primero.
B14: 5. Antes de invertir, mirá Proyección 12 meses: la caja necesaria es la plata que tenés que tener para no frenar la pauta mientras cobrás. Si da 0, el embudo se autofinancia.
... B47: Este modelo se comparte para que lo uses con tus números. Si lo compartís, dejá esta línea: es la forma de saber de dónde salió.

Sheet Resumen
B1: © Jesús Tassarolo · TooAudience · youtube.com/@JesusTassaroloSinFiltro · uso personal; no redistribuir modificado
B2: Resumen: lo que hay que mirar
B3: Todo sale de Modelo con los supuestos del escenario en uso. Cambiá Supuestos y esto se actualiza.
B5: Indicador | C5: Valor | D5: Qué significa
B6: Resultado del lanzamiento
B7: Ganancia del período | C7: ='Modelo'!$C$44 | D7: Cash neto menos costos y menos inversión.
B8: ROAS del front (qué parte de la pauta recupera la entrada) | C8: ='Modelo'!$C$14 | D8: Qué parte de la pauta recupera la entrada antes del evento. Cerca de 1 = el evento se paga solo.
B9: ROAS sobre cash neto | C9: ='Modelo'!$C$46 | D9: Total, sobre cash neto.
B10: Entradas vendidas | C10: ='Modelo'!$C$9 | D10: Entradas vendidas.
B11: Asistentes en vivo | C11: ='Modelo'!$C$18 | D11: Asistentes en vivo.
B12: Ventas de la oferta | C12: ='Modelo'!$C$27 | D12: Ventas de la oferta (vivo + replay).
B13: Unit economics
B14: Costo por entrada vendida | C14: ='Modelo'!$C$8 | D14: Costo por entrada vendida.
B15: Valor neto por entrada | C15: ='Modelo'!$C$50 | D15: Lo que vale una entrada en cash neto, con todo lo que viene después.
B16: Costo por persona en el grupo | C16: ='Modelo'!$C$17 | D16: Lo que te cuesta cada persona que entra al grupo.
B17: Costo por asistente en vivo | C17: ='Modelo'!$C$20 | D17: Lo que te cuesta cada asistente en vivo.
B18: Solicitudes (total) | C18: ='Modelo'!$C$24 | D18: Formularios de compra, aplicaciones o pedidos de hablar con un vendedor.
B19: Costo por solicitud | C19: ='Modelo'!$C$26 | D19: Lo que te cuesta cada solicitud.
B20: Costo por comprador de la oferta | C20: ='Modelo'!$C$29 | D20: Lo que te cuesta cada comprador de la oferta.
B21: Las dos caras de cada número
B22: Ganancia por visita | C22: ='Modelo'!$C$64 | D22: Lo que te queda por cada visita a la página de ventas. La métrica más valiosa del embudo.
B23: Ganancia por entrada | C23: ='Modelo'!$C$65 | D23: Lo que te queda por cada entrada vendida. Su par es el costo por entrada.
B24: Ganancia por cliente | C24: ='Modelo'!$C$68 | D24: Lo que te queda por cada comprador de la oferta. Su par es el costo por comprador.
B25: Order value (AOV) | C25: ='Modelo'!$C$34 | D25: Facturado por comprador de la oferta, con todo lo demás.
B26: Order value neto (AOV neto) | C26: ='Modelo'!$C$63 | D26: Lo mismo después de comisiones, reembolsos y costos por entrada.
B27: Hasta cuánto pagar
B28: Techo de costo por entrada (break-even) | C28: ='Modelo'!$C$51 | D28: Costo por entrada donde no ganás ni perdés.
B29: Objetivo de costo por entrada | C29: ='Modelo'!$C$52 | D29: A este costo o menos estás en verde.
B30: Techo de costo por visita a la página | C30: ='Modelo'!$C$53 | D30: Costo máximo por visita a la página de ventas.
B31: Techo de costo por solicitud | C31: ='Modelo'!$C$55 | D31: Costo máximo por solicitud.
B32: Techo de costo por comprador de la oferta | C32: ='Modelo'!$C$56 | D32: Costo máximo por comprador de la oferta.
B33: Semáforo del costo por entrada actual | C33: ='Modelo'!$C$59 | D33: Tu costo por entrada actual contra techo y objetivo.
B34: Cuánto invertir y cuánta caja
B35: Inversión necesaria para la meta de ventas de la oferta (al costo actual) | C35: ='Modelo'!$C$60 | D35: Para la meta de ventas de Supuestos, al costo actual.
B36: Caja que hay que tener (peor momento de la proyección) | C36: ='Proyección 12 meses'!$C$18 | D36: Si da 0, el embudo se autofinancia: cada mes cobra más de lo que invierte.
B37: Saldo mínimo de caja con tu caja inicial | C37: ='Proyección 12 meses'!$C$19 | D37: Si es negativo, la caja inicial no alcanza.
B38: Ganancia acumulada en 12 meses | C38: ='Proyección 12 meses'!$C$20 | D38: Con la inversión creciendo según el supuesto.
B40: Recomendación según el semáforo | C40: =IF('Modelo'!$C$59="VERDE","Sostener o subir un escalón (+25 %) y medir 7 días",IF('Modelo'!$C$59="AMARILLO","No subir. Si el costo está bien, el ROAS no llega al objetivo: mirá Sensibilidad. Si no, revisar en orden: CPM, creativo, página",IF('Modelo'!$C$59="ROJO","Bajar un escalón (−25 %) y arreglar antes de volver a subir","")))
B42: Modelo financiero de embudos · creado por Jesús Tassarolo · TooAudience · youtube.com/@JesusTassaroloSinFiltro · v1.2 · octubre 2026

Sheet Simulador
B1: © Jesús Tassarolo · TooAudience · youtube.com/@JesusTassaroloSinFiltro · uso personal; no redistribuir modificado
B2: Simulador: movés un número y ves cómo se mueve todo el embudo
B3: Amarillo = tu número: arranca igual a Supuestos; escribí encima para probar (CPM, CTR, conversiones, precios, costos). Al lado, la base. 'Con tus números' se recalcula al instante y se compara con el Modelo. Para volver a la base, borrá la celda amarilla y escribí =D seguido del número de fila (por ejemplo =D9).
B5: Paso / métrica | C5: Tu número (editable) | D5: Base (Supuestos) | E5: Con tus números | F5: Base (Modelo) | G5: Diferencia | H5: Cómo se calcula
B6: Tráfico y entradas
B7: Costo por visita a la página de ventas de la entrada | C7: ='Supuestos'!$C$10 | D7: ='Supuestos'!$C$10 | G7: =IF(C7<>D7,"← cambiado","") | H7: Supuesto. Escribí encima para probar; la base queda al lado.
B8: Inversión en publicidad por lanzamiento | C8: ='Supuestos'!$C$8 | D8: ='Supuestos'!$C$8 | G8: =IF(C8<>D8,"← cambiado","") | H8: Supuesto. Escribí encima para probar; la base queda al lado.
B9: Visitas a la página de ventas | E9: =IF($C$7=0,0,$C$8/$C$7) | F9: ='Modelo'!$C$7 | G9: =IF(AND(ISNUMBER(E9),ISNUMBER(F9)),E9-F9,"") | H9: Inversión ÷ costo por visita.
B10: % de visitas que compran la entrada | C10: ='Supuestos'!$C$13 | D10: ='Supuestos'!$C$13 | G10: =IF(C10<>D10,"← cambiado","") | H10: Supuesto. Escribí encima para probar; la base queda al lado.
B11: Costo por entrada vendida | E11: =IF($C$10=0,0,$C$7/$C$10) | F11: ='Modelo'!$C$8 | G11: =IF(AND(ISNUMBER(E11),ISNUMBER(F11)),E11-F11,"") | H11: Costo por visita ÷ % que compra la entrada.
B12: Entradas vendidas | E12: =IF($E$11=0,0,$C$8/$E$11) | F12: ='Modelo'!$C$9 | G12: =IF(AND(ISNUMBER(E12),ISNUMBER(F12)),E12-F12,"") | H12: Inversión ÷ costo por entrada.
B13: Precio promedio cobrado por entrada | C13: ='Supuestos'!$C$14 | D13: ='Supuestos'!$C$14 | G13: =IF(C13<>D13,"← cambiado","") | H13: Supuesto. Escribí encima para probar; la base queda al lado.
B14: Facturado: entradas | E14: =$E$12*$C$13 | F14: ='Modelo'!$C$10 | G14: =IF(AND(ISNUMBER(E14),ISNUMBER(F14)),E14-F14,"") | H14: Entradas × precio promedio.
B15: Bump: % de compradores de entrada que lo toman | C15: ='Supuestos'!$C$16 | D15: ='Supuestos'!$C$16 | G15: =IF(C15<>D15,"← cambiado","") | H15: Supuesto. Escribí encima para probar; la base queda al lado.
B16: Ventas: bump de la entrada | E16: =$E$12*$C$15 | F16: ='Modelo'!$C$11 | G16: =IF(AND(ISNUMBER(E16),ISNUMBER(F16)),E16-F16,"") | H16: Entradas × % que lo toma.
B17: Bump en el checkout de la entrada: precio | C17: ='Supuestos'!$C$15 | D17: ='Supuestos'!$C$15 | G17: =IF(C17<>D17,"← cambiado","") | H17: Supuesto. Escribí encima para probar; la base queda al lado.
B18: Facturado: bump de la entrada | E18: =$E$16*$C$17 | F18: ='Modelo'!$C$12 | G18: =IF(AND(ISNUMBER(E18),ISNUMBER(F18)),E18-F18,"") | H18: Ventas × precio.
B19: Facturado del front (entradas + bump) | E19: =$E$14+$E$18 | F19: ='Modelo'!$C$13 | G19: =IF(AND(ISNUMBER(E19),ISNUMBER(F19)),E19-F19,"") | H19: Lo que entra antes del evento.
B20: ROAS del front (qué parte de la pauta recupera la entrada) | E20: =IF($C$8=0,0,$E$19/$C$8) | F20: ='Modelo'!$C$14 | G20: =IF(AND(ISNUMBER(E20),ISNUMBER(F20)),E20-F20,"") | H20: Facturado del front ÷ inversión. Cerca de 1 = el evento se paga solo.
B21: Grupo y asistencia
B22: % que entra al grupo de WhatsApp | C22: ='Supuestos'!$C$19 | D22: ='Supuestos'!$C$19 | G22: =IF(C22<>D22,"← cambiado","") | H22: Supuesto. Escribí encima para probar; la base queda al lado.
B23: Personas en el grupo | E23: =$E$12*$C$22 | F23: ='Modelo'!$C$16 | G23: =IF(AND(ISNUMBER(E23),ISNUMBER(F23)),E23-F23,"") | H23: Entradas × % que entra.
B24: Costo por persona en el grupo | E24: =IF($E$23=0,0,$C$8/$E$23) | F24: ='Modelo'!$C$17 | G24: =IF(AND(ISNUMBER(E24),ISNUMBER(F24)),E24-F24,"") | H24: Inversión ÷ personas en el grupo.
B25: % que asiste en vivo | C25: ='Supuestos'!$C$20 | D25: ='Supuestos'!$C$20 | G25: =IF(C25<>D25,"← cambiado","") | H25: Supuesto. Escribí encima para probar; la base queda al lado.
B26: Asistentes en vivo | E26: =$E$12*$C$25 | F26: ='Modelo'!$C$18 | G26: =IF(AND(ISNUMBER(E26),ISNUMBER(F26)),E26-F26,"") | H26: Entradas × asistencia en vivo.
B27: % que ve el replay (sin contar los que fueron en vivo) | C27: ='Supuestos'!$C$21 | D27: ='Supuestos'!$C$21 | G27: =IF(C27<>D27,"← cambiado","") | H27: Supuesto. Escribí encima para probar; la base queda al lado.
B28: Vieron el replay | E28: =$E$12*$C$27 | F28: ='Modelo'!$C$19 | G28: =IF(AND(ISNUMBER(E28),ISNUMBER(F28)),E28-F28,"") | H28: Entradas × % que ve el replay.
B29: Costo por asistente en vivo | E29: =IF($E$26=0,0,$C$8/$E$26) | F29: ='Modelo'!$C$20 | G29: =IF(AND(ISNUMBER(E29),ISNUMBER(F29)),E29-F29,"") | H29: Inversión ÷ asistentes.
B30: Solicitudes (formulario de compra, aplicación o vendedor), oferta, programa y facturación
B31: % de asistentes en vivo que solicitan (formulario de compra, de aplicación o hablar con un vendedor) | C31: ='Supuestos'!$C$25 | D31: ='Supuestos'!$C$25 | G31: =IF(C31<>D31,"← cambiado","") | H31: Supuesto. Escribí encima para probar; la base queda al lado.
B32: Solicitudes: en vivo | E32: =$E$26*$C$31 | F32: ='Modelo'!$C$22 | G32: =IF(AND(ISNUMBER(E32),ISNUMBER(F32)),E32-F32,"") | H32: Asistentes en vivo × % que solicita.
B33: % de los que ven el replay que solicitan | C33: ='Supuestos'!$C$26 | D33: ='Supuestos'!$C$26 | G33: =IF(C33<>D33,"← cambiado","") | H33: Supuesto. Escribí encima para probar; la base queda al lado.
B34: Solicitudes: replay | E34: =$E$28*$C$33 | F34: ='Modelo'!$C$23 | G34: =IF(AND(ISNUMBER(E34),ISNUMBER(F34)),E34-F34,"") | H34: Replay × % que solicita.
B35: Solicitudes (total) | E35: =$E$32+$E$34 | F35: ='Modelo'!$C$24 | G35: =IF(AND(ISNUMBER(E35),ISNUMBER(F35)),E35-F35,"") | H35: En vivo + replay.
B36: % de compradores de entrada que solicitan | E36: =IF($E$12=0,0,$E$35/$E$12) | F36: ='Modelo'!$C$25 | G36: =IF(AND(ISNUMBER(E36),ISNUMBER(F36)),E36-F36,"") | H36: Solicitudes ÷ entradas.
B37: Costo por solicitud | E37: =IF($E$35=0,0,$C$8/$E$35) | F37: ='Modelo'!$C$26 | G37: =IF(AND(ISNUMBER(E37),ISNUMBER(F37)),E37-F37,"") | H37: Inversión ÷ solicitudes.
B38: % de solicitudes que terminan en compra | C38: ='Supuestos'!$C$27 | D38: ='Supuestos'!$C$27 | G38: =IF(C38<>D38,"← cambiado","") | H38: Supuesto. Escribí encima para probar; la base queda al lado.
B39: Ventas de la oferta | E39: =$E$35*$C$38 | F39: ='Modelo'!$C$27 | G39: =IF(AND(ISNUMBER(E39),ISNUMBER(F39)),E39-F39,"") | H39: Solicitudes × % que termina en compra.
B40: % de compradores de entrada que compran la oferta | E40: =IF($E$12=0,0,$E$39/$E$12) | F40: ='Modelo'!$C$28 | G40: =IF(AND(ISNUMBER(E40),ISNUMBER(F40)),E40-F40,"") | H40: Ventas ÷ entradas.
B41: Costo por comprador de la oferta | E41: =IF($E$39=0,0,$C$8/$E$39) | F41: ='Modelo'!$C$29 | G41: =IF(AND(ISNUMBER(E41),ISNUMBER(F41)),E41-F41,"") | H41: Inversión ÷ ventas de la oferta.
B42: Oferta principal: precio | C42: ='Supuestos'!$C$24 | D42: ='Supuestos'!$C$24 | G42: =IF(C42<>D42,"← cambiado","") | H42: Supuesto. Escribí encima para probar; la base queda al lado.
B43: Facturado: oferta | E43: =$E$39*$C$42 | F43: ='Modelo'!$C$30 | G43: =IF(AND(ISNUMBER(E43),ISNUMBER(F43)),E43-F43,"") | H43: Ventas × precio.
B44: Programa superior: % de compradores de la oferta que lo toman | C44: ='Supuestos'!$C$29 | D44: ='Supuestos'!$C$29 | G44: =IF(C44<>D44,"← cambiado","") | H44: Supuesto. Escribí encima para probar; la base queda al lado.
B45: Ventas: programa superior | E45: =$E$39*$C$44 | F45: ='Modelo'!$C$31 | G45: =IF(AND(ISNUMBER(E45),ISNUMBER(F45)),E45-F45,"") | H45: Compradores de la oferta × % que asciende.
B46: Programa superior: precio | C46: ='Supuestos'!$C$28 | D46: ='Supuestos'!$C$28 | G46: =IF(C46<>D46,"← cambiado","") | H46: Supuesto. Escribí encima para probar; la base queda al lado.
B47: Facturado: programa superior | E47: =$E$45*$C$46 | F47: ='Modelo'!$C$32 | G47: =IF(AND(ISNUMBER(E47),ISNUMBER(F47)),E47-F47,"") | H47: Ventas × precio.
B48: Facturado total | E48: =$E$19+$E$43+$E$47 | F48: ='Modelo'!$C$33 | G48: =IF(AND(ISNUMBER(E48),ISNUMBER(F48)),E48-F48,"") | H48: Front + oferta + programa.
B49: Facturado por comprador de la oferta | E49: =IF($E$39=0,0,$E$48/$E$39) | F49: ='Modelo'!$C$34 | G49: =IF(AND(ISNUMBER(E49),ISNUMBER(F49)),E49-F49,"") | H49: Facturado total ÷ ventas de la oferta.
B50: Ventas de la oferta por entrada (para la proyección) | E50: =IF($E$12=0,0,$E$39/$E$12) | F50: ='Modelo'!$C$35 | G50: =IF(AND(ISNUMBER(E50),ISNUMBER(F50)),E50-F50,"") | H50: Igual a '% que compra la oferta'.
B51: Facturado por entrada | E51: =IF($E$12=0,0,$E$48/$E$12) | F51: ='Modelo'!$C$36 | G51: =IF(AND(ISNUMBER(E51),ISNUMBER(F51)),E51-F51,"") | H51: Facturado total ÷ entradas.
B52: Cash, costos y ganancia del período
B53: % del facturado que entra en el mes 1 | C53: ='Supuestos'!$C$39 | D53: ='Supuestos'!$C$39 | G53: =IF(C53<>D53,"← cambiado","") | H53: Supuesto. Escribí encima para probar; la base queda al lado.
B54: % que entra en el mes 2 | C54: ='Supuestos'!$C$40 | D54: ='Supuestos'!$C$40 | G54: =IF(C54<>D54,"← cambiado","") | H54: Supuesto. Escribí encima para probar; la base queda al lado.
B55: % que entra en el mes 3 | C55: ='Supuestos'!$C$41 | D55: ='Supuestos'!$C$41 | G55: =IF(C55<>D55,"← cambiado","") | H55: Supuesto. Escribí encima para probar; la base queda al lado.
B56: Cash a cobrar (facturado × cobranza completa) | E56: =$E$48*($C$53+$C$54+$C$55) | F56: ='Modelo'!$C$38 | G56: =IF(AND(ISNUMBER(E56),ISNUMBER(F56)),E56-F56,"") | H56: Facturado × (mes 1 + mes 2 + mes 3). Si la cobranza suma 100 %, es igual al facturado.
B57: Cash que entra en el primer mes | E57: =$E$48*$C$53 | F57: ='Modelo'!$C$39 | G57: =IF(AND(ISNUMBER(E57),ISNUMBER(F57)),E57-F57,"") | H57: Facturado × % del mes 1.
B58: Comisión de la pasarela o plataforma de pago | C58: ='Supuestos'!$C$32 | D58: ='Supuestos'!$C$32 | G58: =IF(C58<>D58,"← cambiado","") | H58: Supuesto. Escribí encima para probar; la base queda al lado.
B59: Comisión del equipo de ventas | C59: ='Supuestos'!$C$33 | D59: ='Supuestos'!$C$33 | G59: =IF(C59<>D59,"← cambiado","") | H59: Supuesto. Escribí encima para probar; la base queda al lado.
B60: Comisiones (pasarela + ventas) | E60: =$E$56*($C$58+$C$59) | F60: ='Modelo'!$C$40 | G60: =IF(AND(ISNUMBER(E60),ISNUMBER(F60)),E60-F60,"") | H60: Cash × (pasarela + equipo de ventas).
B61: Reembolsos y contracargos | C61: ='Supuestos'!$C$34 | D61: ='Supuestos'!$C$34 | G61: =IF(C61<>D61,"← cambiado","") | H61: Supuesto. Escribí encima para probar; la base queda al lado.
B62: Reembolsos | E62: =$E$56*$C$61 | F62: ='Modelo'!$C$41 | G62: =IF(AND(ISNUMBER(E62),ISNUMBER(F62)),E62-F62,"") | H62: Cash × % de reembolsos.
B63: Cash neto | E63: =$E$56*(1-$C$58-$C$59-$C$61) | F63: ='Modelo'!$C$42 | G63: =IF(AND(ISNUMBER(E63),ISNUMBER(F63)),E63-F63,"") | H63: Cash − comisiones − reembolsos. La base de verdad.
B64: Costos por entrada (herramientas, WhatsApp, IA) | C64: ='Supuestos'!$C$35 | D64: ='Supuestos'!$C$35 | G64: =IF(C64<>D64,"← cambiado","") | H64: Supuesto. Escribí encima para probar; la base queda al lado.
B65: Costos por entrada (herramientas, WhatsApp, IA) | E65: =$E$12*$C$64 | F65: ='Modelo'!$C$43 | G65: =IF(AND(ISNUMBER(E65),ISNUMBER(F65)),E65-F65,"") | H65: Entradas × costo por entrada.
B66: Costos fijos por lanzamiento | C66: ='Supuestos'!$C$36 | D66: ='Supuestos'!$C$36 | G66: =IF(C66<>D66,"← cambiado","") | H66: Supuesto. Escribí encima para probar; la base queda al lado.
B67: Ganancia del período | E67: =$E$63-$E$65-$C$66-$C$8 | F67: ='Modelo'!$C$44 | G67: =IF(AND(ISNUMBER(E67),ISNUMBER(F67)),E67-F67,"") | H67: Cash neto − costos por unidad − fijos − inversión.
B68: ROAS sobre facturado | E68: =IF($C$8=0,0,$E$48/$C$8) | F68: ='Modelo'!$C$45 | G68: =IF(AND(ISNUMBER(E68),ISNUMBER(F68)),E68-F68,"") | H68: Facturado ÷ inversión. El número que más se infla: no decidas con este.
B69: ROAS sobre cash neto | E69: =IF($C$8=0,0,$E$63/$C$8) | F69: ='Modelo'!$C$46 | G69: =IF(AND(ISNUMBER(E69),ISNUMBER(F69)),E69-F69,"") | H69: Cash neto ÷ inversión. Con este se decide.
B70: Margen sobre cash | E70: =IF($E$56=0,0,$E$67/$E$56) | F70: ='Modelo'!$C$47 | G70: =IF(AND(ISNUMBER(E70),ISNUMBER(F70)),E70-F70,"") | H70: Ganancia ÷ cash.
B71: ROAS objetivo sobre cash neto | C71: ='Supuestos'!$C$44 | D71: ='Supuestos'!$C$44 | G71: =IF(C71<>D71,"← cambiado","") | H71: Supuesto. Escribí encima para probar; la base queda al lado.
B72: ¿Cumple el ROAS objetivo? | E72: =IF($E$69>=$C$71,"SÍ","NO") | F72: ='Modelo'!$C$48 | G72: =IF(E72=F72,"","≠ base") | H72: ROAS sobre cash neto contra el objetivo de Supuestos.
B73: Cuánto vale cada entrada y hasta cuánto pagar
B74: Valor neto por entrada | E74: =IF($E$12=0,0,($E$63-$E$65)/$E$12) | F74: ='Modelo'!$C$50 | G74: =IF(AND(ISNUMBER(E74),ISNUMBER(F74)),E74-F74,"") | H74: (Cash neto − costos por entrada) ÷ entradas.
B75: Techo de costo por entrada (break-even) | E75: =$E$74 | F75: ='Modelo'!$C$51 | G75: =IF(AND(ISNUMBER(E75),ISNUMBER(F75)),E75-F75,"") | H75: Igual al valor neto por entrada.
B76: Margen de seguridad | C76: ='Supuestos'!$C$45 | D76: ='Supuestos'!$C$45 | G76: =IF(C76<>D76,"← cambiado","") | H76: Supuesto. Escribí encima para probar; la base queda al lado.
B77: Objetivo de costo por entrada | E77: =$E$75/(1+$C$76) | F77: ='Modelo'!$C$52 | G77: =IF(AND(ISNUMBER(E77),ISNUMBER(F77)),E77-F77,"") | H77: Techo ÷ (1 + margen de seguridad).
B78: Techo de costo por visita a la página | E78: =$E$74*$C$10 | F78: ='Modelo'!$C$53 | G78: =IF(AND(ISNUMBER(E78),ISNUMBER(F78)),E78-F78,"") | H78: Valor por entrada × % que compra la entrada.
B79: Techo de costo por asistente en vivo | E79: =IF($C$25=0,0,$E$74/$C$25) | F79: ='Modelo'!$C$54 | G79: =IF(AND(ISNUMBER(E79),ISNUMBER(F79)),E79-F79,"") | H79: Valor por entrada ÷ asistencia.
B80: Techo de costo por solicitud | E80: =IF($E$35=0,0,$E$74*$E$12/$E$35) | F80: ='Modelo'!$C$55 | G80: =IF(AND(ISNUMBER(E80),ISNUMBER(F80)),E80-F80,"") | H80: Valor total ÷ solicitudes.
B81: Techo de costo por comprador de la oferta | E81: =IF($E$40=0,0,$E$74/$E$40) | F81: ='Modelo'!$C$56 | G81: =IF(AND(ISNUMBER(E81),ISNUMBER(F81)),E81-F81,"") | H81: Valor por entrada ÷ % que compra la oferta.
B82: Objetivo de costo por comprador de la oferta | E82: =$E$81/(1+$C$76) | F82: ='Modelo'!$C$57 | G82: =IF(AND(ISNUMBER(E82),ISNUMBER(F82)),E82-F82,"") | H82: Techo ÷ (1 + margen de seguridad).
B83: Semáforo y cuánto invertir
B84: Semáforo del costo por entrada actual | E84: =IF($E$11>$E$75,"ROJO",IF(AND($E$11<=$E$77,$E$69>=$C$71),"VERDE","AMARILLO")) | F84: ='Modelo'!$C$59 | G84: =IF(E84=F84,"","≠ base") | H84: Rojo: costo > techo. Verde: costo ≤ objetivo y ROAS sobre cash neto ≥ objetivo. Amarillo: el resto.
B85: Meta de ventas del producto principal | C85: ='Supuestos'!$C$46 | D85: ='Supuestos'!$C$46 | G85: =IF(C85<>D85,"← cambiado","") | H85: Supuesto. Escribí encima para probar; la base queda al lado.
B86: Inversión necesaria para la meta de ventas de la oferta (al costo actual) | E86: =IF($E$40=0,"inalcanzable con estos supuestos",$C$85/$E$40*$E$11) | F86: ='Modelo'!$C$60 | G86: =IF(AND(ISNUMBER(E86),ISNUMBER(F86)),E86-F86,"") | H86: Meta ÷ % que compra la oferta × costo por entrada.
B87: Inversión para la meta al costo objetivo (lo máximo que conviene pagar) | E87: =IF($E$40=0,"inalcanzable con estos supuestos",$C$85/$E$40*$E$77) | F87: ='Modelo'!$C$61 | G87: =IF(AND(ISNUMBER(E87),ISNUMBER(F87)),E87-F87,"") | H87: Lo mismo, al costo objetivo.
B88: Ganancia por paso (las dos caras de cada número)
B89: Cash neto por comprador (AOV neto) | E89: =IF($E$39=0,0,($E$63-$E$65)/$E$39) | F89: ='Modelo'!$C$63 | G89: =IF(AND(ISNUMBER(E89),ISNUMBER(F89)),E89-F89,"") | H89: Lo que deja cada comprador después de comisiones, reembolsos y costos por unidad. Su par es el CPA.
B90: Ganancia por visita | E90: =IF($E$9=0,0,$E$67/$E$9) | F90: ='Modelo'!$C$64 | G90: =IF(AND(ISNUMBER(E90),ISNUMBER(F90)),E90-F90,"") | H90: Ganancia del período ÷ visitas a la página de ventas. La métrica más valiosa: resume todo lo que pasa después. Su par es el costo por visita.
B91: Ganancia por entrada | E91: =IF($E$12=0,0,$E$67/$E$12) | F91: ='Modelo'!$C$65 | G91: =IF(AND(ISNUMBER(E91),ISNUMBER(F91)),E91-F91,"") | H91: Ganancia del período ÷ entradas. Su par es el costo por entrada.
B92: Ganancia por asistente en vivo | E92: =IF($E$26=0,0,$E$67/$E$26) | F92: ='Modelo'!$C$66 | G92: =IF(AND(ISNUMBER(E92),ISNUMBER(F92)),E92-F92,"") | H92: Ganancia del período ÷ asistente en vivos. Su par es el costo por asistente en vivo.
B93: Ganancia por solicitud | E93: =IF($E$35=0,0,$E$67/$E$35) | F93: ='Modelo'!$C$67 | G93: =IF(AND(ISNUMBER(E93),ISNUMBER(F93)),E93-F93,"") | H93: Ganancia del período ÷ solicituds. Su par es el costo por solicitud.
B94: Ganancia por cliente | E94: =IF($E$39=0,0,$E$67/$E$39) | F94: ='Modelo'!$C$68 | G94: =IF(AND(ISNUMBER(E94),ISNUMBER(F94)),E94-F94,"") | H94: Ganancia del período ÷ compradores de la oferta. Su par es el costo por comprador.
B96: Cómo se lee: cambiá una celda amarilla (por ejemplo el CPM, el CTR, la conversión de la landing, el show, el cierre o el precio) y mirá cómo se mueven la cantidad de cada paso, el costo por paso, el facturado, el cash neto, la ganancia, el ROAS, el techo y el semáforo.
B97: Una variable por vez: si cambiás tres cosas no sabés cuál movió el resultado. La columna Diferencia te muestra exactamente cuánto cambió cada número contra la base.
B98: El Simulador no modifica Supuestos ni Modelo: es tu mesa de pruebas. Cuando una prueba te convence, pasá ese número a Supuestos.

Sheet Embudo
B1: © Jesús Tassarolo · TooAudience · youtube.com/@JesusTassaroloSinFiltro · uso personal; no redistribuir modificado
B2: Embudo: todos los pasos, cuántos pasan y, por cada uno, qué pagás, qué te queda y hasta cuánto podrías pagar
B3: Cada fila es un paso del embudo en orden. '% que pasa' compara con el paso anterior (o con el que dice la nota). Tres números por paso: lo que pagás hoy por cada uno (inversión ÷ cantidad), lo que te queda por cada uno (ganancia ÷ cantidad) y lo máximo que podrías pagar (el techo: lo que cada uno genera en cash neto). Techo = costo + ganancia + fijos repartidos.
B5: Paso | C5: Cantidad | D5: % que pasa | E5: % acumulado | F5: Costo por paso (pagás hoy) | G5: Ganancia por paso (te queda) | H5: Techo por paso (máximo a pagar) | I5: Qué se paga acá / cómo se lee
B6: Visitas a la página de ventas de la entrada | C6: ='Modelo'!$C$7 | D6: — | E6: — | F6: =IF('Modelo'!$C$7=0,0,'Supuestos'!$C$8*1/'Modelo'!$C$7) | G6: =IF('Modelo'!$C$7=0,0,'Modelo'!$C$44*1/'Modelo'!$C$7) | H6: =IF('Modelo'!$C$7=0,0,'Modelo'!$C$50*'Modelo'!$C$9*1/'Modelo'!$C$7) | I6: Costo por visita.
B7: Compran la entrada | C7: ='Modelo'!$C$9 | D7: =IF('Modelo'!$C$7=0,0,'Modelo'!$C$9/'Modelo'!$C$7) | E7: =IF('Modelo'!$C$9=0,0,'Modelo'!$C$9/'Modelo'!$C$9) | F7: =IF('Modelo'!$C$9=0,0,'Supuestos'!$C$8*1/'Modelo'!$C$9) | G7: =IF('Modelo'!$C$9=0,0,'Modelo'!$C$44*1/'Modelo'!$C$9) | H7: =IF('Modelo'!$C$9=0,0,'Modelo'!$C$50*'Modelo'!$C$9*1/'Modelo'!$C$9) | I7: Costo por entrada. La unidad de este embudo: acá los leads ya son compradores.
B8: Toman el bump de la entrada | C8: ='Modelo'!$C$11 | D8: =IF('Modelo'!$C$9=0,0,'Modelo'!$C$11/'Modelo'!$C$9) | E8: =IF('Modelo'!$C$9=0,0,'Modelo'!$C$11/'Modelo'!$C$9) | F8: sin costo propio | G8: — | H8: — | I8: Sobre compradores de entrada. Suma al ROAS del front.
B9: Entran al grupo de WhatsApp | C9: ='Modelo'!$C$16 | D9: =IF('Modelo'!$C$9=0,0,'Modelo'!$C$16/'Modelo'!$C$9) | E9: =IF('Modelo'!$C$9=0,0,'Modelo'!$C$16/'Modelo'!$C$9) | F9: =IF('Modelo'!$C$16=0,0,'Supuestos'!$C$8*1/'Modelo'!$C$16) | G9: =IF('Modelo'!$C$16=0,0,'Modelo'!$C$44*1/'Modelo'!$C$16) | H9: =IF('Modelo'!$C$16=0,0,'Modelo'!$C$50*'Modelo'!$C$9*1/'Modelo'!$C$16) | I9: Costo por persona en el grupo.
B10: Asisten en vivo | C10: ='Modelo'!$C$18 | D10: =IF('Modelo'!$C$9=0,0,'Modelo'!$C$18/'Modelo'!$C$9) | E10: =IF('Modelo'!$C$9=0,0,'Modelo'!$C$18/'Modelo'!$C$9) | F10: =IF('Modelo'!$C$18=0,0,'Supuestos'!$C$8*1/'Modelo'!$C$18) | G10: =IF('Modelo'!$C$18=0,0,'Modelo'!$C$44*1/'Modelo'!$C$18) | H10: =IF('Modelo'!$C$18=0,0,'Modelo'!$C$50*'Modelo'!$C$9*1/'Modelo'!$C$18) | I10: Costo por asistente en vivo. Sobre compradores de entrada.
B11: Ven el replay | C11: ='Modelo'!$C$19 | D11: =IF('Modelo'!$C$9=0,0,'Modelo'!$C$19/'Modelo'!$C$9) | E11: =IF('Modelo'!$C$9=0,0,'Modelo'!$C$19/'Modelo'!$C$9) | F11: =IF('Modelo'!$C$19=0,0,'Supuestos'!$C$8*1/'Modelo'!$C$19) | G11: =IF('Modelo'!$C$19=0,0,'Modelo'!$C$44*1/'Modelo'!$C$19) | H11: =IF('Modelo'!$C$19=0,0,'Modelo'!$C$50*'Modelo'!$C$9*1/'Modelo'!$C$19) | I11: Sobre compradores de entrada.
B12: Solicitan, de los que estuvieron en vivo | C12: ='Modelo'!$C$22 | D12: =IF('Modelo'!$C$18=0,0,'Modelo'!$C$22/'Modelo'!$C$18) | E12: =IF('Modelo'!$C$9=0,0,'Modelo'!$C$22/'Modelo'!$C$9) | F12: =IF('Modelo'!$C$22=0,0,'Supuestos'!$C$8*1/'Modelo'!$C$22) | G12: =IF('Modelo'!$C$22=0,0,'Modelo'!$C$44*1/'Modelo'!$C$22) | H12: =IF('Modelo'!$C$22=0,0,'Modelo'!$C$50*'Modelo'!$C$9*1/'Modelo'!$C$22) | I12: Formulario de compra, aplicación o vendedor. Sobre asistentes en vivo.
B13: Solicitan, de los que vieron el replay | C13: ='Modelo'!$C$23 | D13: =IF('Modelo'!$C$19=0,0,'Modelo'!$C$23/'Modelo'!$C$19) | E13: =IF('Modelo'!$C$9=0,0,'Modelo'!$C$23/'Modelo'!$C$9) | F13: =IF('Modelo'!$C$23=0,0,'Supuestos'!$C$8*1/'Modelo'!$C$23) | G13: =IF('Modelo'!$C$23=0,0,'Modelo'!$C$44*1/'Modelo'!$C$23) | H13: =IF('Modelo'!$C$23=0,0,'Modelo'!$C$50*'Modelo'!$C$9*1/'Modelo'!$C$23) | I13: Sobre los que vieron el replay.
B14: Solicitudes (total) | C14: ='Modelo'!$C$24 | D14: =IF('Modelo'!$C$9=0,0,'Modelo'!$C$24/'Modelo'!$C$9) | E14: =IF('Modelo'!$C$9=0,0,'Modelo'!$C$24/'Modelo'!$C$9) | F14: =IF('Modelo'!$C$24=0,0,'Supuestos'!$C$8*1/'Modelo'!$C$24) | G14: =IF('Modelo'!$C$24=0,0,'Modelo'!$C$44*1/'Modelo'!$C$24) | H14: =IF('Modelo'!$C$24=0,0,'Modelo'!$C$50*'Modelo'!$C$9*1/'Modelo'!$C$24) | I14: Costo por solicitud. Sobre compradores de entrada.
B15: Compran la oferta | C15: ='Modelo'!$C$27 | D15: =IF('Modelo'!$C$24=0,0,'Modelo'!$C$27/'Modelo'!$C$24) | E15: =IF('Modelo'!$C$9=0,0,'Modelo'!$C$27/'Modelo'!$C$9) | F15: =IF('Modelo'!$C$27=0,0,'Supuestos'!$C$8*1/'Modelo'!$C$27) | G15: =IF('Modelo'!$C$27=0,0,'Modelo'!$C$44*1/'Modelo'!$C$27) | H15: =IF('Modelo'!$C$27=0,0,'Modelo'!$C$50*'Modelo'!$C$9*1/'Modelo'!$C$27) | I15: Costo por comprador de la oferta. Sobre solicitudes (cierre).
B16: Pasan al programa superior | C16: ='Modelo'!$C$31 | D16: =IF('Modelo'!$C$27=0,0,'Modelo'!$C$31/'Modelo'!$C$27) | E16: =IF('Modelo'!$C$9=0,0,'Modelo'!$C$31/'Modelo'!$C$9) | F16: sin costo propio | G16: — | H16: — | I16: Sobre compradores de la oferta.
B18: Comprobalo con la fila de la unidad: costo + ganancia + fijos repartidos = techo | F18: =F7 | G18: =G7 | H18: =F7+G7+'Supuestos'!$C$36/'Modelo'!$C$9 | I18: Techo = costo + ganancia + fijos ÷ unidades. Lo que falta entre (costo + ganancia) y el techo son los costos fijos repartidos entre las unidades.
B19: Cómo se lee
B20: Cantidad: cuántas acciones o personas hubo en ese paso con los supuestos del escenario en uso.
B21: % que pasa: de los que estaban en el paso anterior (o en el paso que indica la nota), cuántos llegan a este. % acumulado: cuántos llegan a este paso por cada 100 unidades que compra la pauta.
B22: Costo por paso: inversión ÷ cantidad. Es lo que te está costando hoy cada persona que llega a ese paso.
B23: Ganancia por paso: ganancia del período ÷ cantidad. Lo que te queda por cada persona de ese paso después de pagar la pauta, las comisiones, los reembolsos y los fijos. La ganancia por visita es la métrica más valiosa del embudo: resume todo lo que pasa después.
B24: Techo por paso: lo que cada persona de ese paso genera en cash neto (cash neto menos costos por unidad, dividido por la cantidad). Es lo máximo que podrías pagar por ese paso antes de que la ganancia llegue a cero, si lo demás se mantiene. Por eso siempre es mayor que la ganancia: techo = costo + ganancia + fijos repartidos.
B25: Los bumps, las OTOs y la ascensión no tienen costo propio: se pagan con el CPA del comprador principal y se miden por lo que suman al AOV.

Sheet Supuestos
B1: © Jesús Tassarolo · TooAudience · youtube.com/@JesusTassaroloSinFiltro · uso personal; no redistribuir modificado
B2: Supuestos
B3: Celdas amarillas = las editás vos. Celdas azules = se calculan solas. Cada fila dice en qué unidad va y de dónde sale el valor del ejemplo.
B5: Supuesto | C5: Valor en uso | D5: Conservador | E5: Base | F5: Optimista | G5: Unidad | H5: Nota / fuente del ejemplo
B6: Escenario en uso (1 = conservador · 2 = base · 3 = optimista) | C6: 2 | G6: 1 / 2 / 3 | H6: Cambia todas las filas que tienen tres valores. Si una fila no tiene tres valores, se usa el de 'Valor en uso'.
B7: 1. Inversión y tráfico
B8: Inversión en publicidad por lanzamiento | C8: 3000 | G8: USD / lanzamiento | H8: Un lanzamiento = una tanda de venta de entradas + evento + oferta.
B9: Lanzamientos por mes (para la proyección) | C9: 2 | G9: lanzamientos / mes | H9: Cuántos eventos como este hacés por mes. La proyección multiplica inversión, costos fijos y ventas por este número.
B10: Costo por visita a la página de ventas de la entrada | C10: =IF('Supuestos'!$C$6=1,D10,IF('Supuestos'!$C$6=2,E10,F10)) | D10: 0.5 | E10: 0.35 | F10: 0.25 | G10: USD / visita | H10: Lo que pagás por cada persona que llega a la página.
B12: 2. Entrada y bump
B13: % de visitas que compran la entrada | C13: =IF('Supuestos'!$C$6=1,D13,IF('Supuestos'!$C$6=2,E13,F13)) | D13: 0.015 | E13: 0.025 | F13: 0.035 | G13: % | H13: Página de ventas de un producto de 5 a 15 USD.
B14: Precio promedio cobrado por entrada | C14: 9 | G14: USD | H14: Si escalonás el precio (5 → 10 → 15), poné el promedio que cobrás.
B15: Bump en el checkout de la entrada: precio | C15: 27 | G15: USD | H15: Grabaciones, plantillas, acceso extendido.
B16: Bump: % de compradores de entrada que lo toman | C16: =IF('Supuestos'!$C$6=1,D16,IF('Supuestos'!$C$6=2,E16,F16)) | D16: 0.12 | E16: 0.2 | F16: 0.3 | G16: %
B18: 3. Grupo y asistencia (sobre compradores de entrada)
B19: % que entra al grupo de WhatsApp | C19: =IF('Supuestos'!$C$6=1,D19,IF('Supuestos'!$C$6=2,E19,F19)) | D19: 0.7 | E19: 0.85 | F19: 0.95 | G19: % | H19: Pagaron: entran casi todos.
B20: % que asiste en vivo | C20: =IF('Supuestos'!$C$6=1,D20,IF('Supuestos'!$C$6=2,E20,F20)) | D20: 0.4 | E20: 0.55 | F20: 0.65 | G20: % | H20: Mucho más alto que en gratuito.
B21: % que ve el replay (sin contar los que fueron en vivo) | C21: =IF('Supuestos'!$C$6=1,D21,IF('Supuestos'!$C$6=2,E21,F21)) | D21: 0.15 | E21: 0.25 | F21: 0.3 | G21: %
B23: 4. Oferta del evento y programa superior
B24: Oferta principal: precio | C24: 497 | G24: USD | H24: Lo que se presenta al final del evento.
B25: % de asistentes en vivo que solicitan (formulario de compra, de aplicación o hablar con un vendedor) | C25: =IF('Supuestos'!$C$6=1,D25,IF('Supuestos'!$C$6=2,E25,F25)) | D25: 0.1 | E25: 0.16 | F25: 0.22 | G25: % | H25: Público que pagó por estar: solicita más que en un webinar gratuito.
B26: % de los que ven el replay que solicitan | C26: =IF('Supuestos'!$C$6=1,D26,IF('Supuestos'!$C$6=2,E26,F26)) | D26: 0.02 | E26: 0.04 | F26: 0.06 | G26: %
B27: % de solicitudes que terminan en compra | C27: =IF('Supuestos'!$C$6=1,D27,IF('Supuestos'!$C$6=2,E27,F27)) | D27: 0.4 | E27: 0.5 | F27: 0.6 | G27: % | H27: Con compra directa en el formulario suele ser alto; con vendedor, 40 a 60 %.
B28: Programa superior: precio | C28: 1997 | G28: USD | H28: Por llamada o por ascenso.
B29: Programa superior: % de compradores de la oferta que lo toman | C29: =IF('Supuestos'!$C$6=1,D29,IF('Supuestos'!$C$6=2,E29,F29)) | D29: 0.05 | E29: 0.1 | F29: 0.15 | G29: %
B31: 5. Costos
B32: Comisión de la pasarela o plataforma de pago | C32: 0.08 | G32: % del cash | H32: Hotmart, Stripe, Mercado Pago: lo que se queda la plataforma.
B33: Comisión del equipo de ventas | C33: 0 | G33: % del cash | H33: Sobre el cash cobrado. Si el programa superior se vende por llamada, poné acá la comisión del closer.
B34: Reembolsos y contracargos | C34: 0.05 | G34: % del cash | H34: 5 % es normal en productos digitales. Más de 10 % es un problema de oferta o de expectativa.
B35: Costos por entrada (herramientas, WhatsApp, IA) | C35: 0.3 | G35: USD / entrada | H35: WhatsApp, soporte, plataforma del evento: lo que pagás por cada entrada.
B36: Costos fijos por lanzamiento | C36: 800 | G36: USD / lanzamiento | H36: Equipo, herramientas, edición: lo que pagás aunque no vendas.
B38: 6. Cobranza
B39: % del facturado que entra en el mes 1 | C39: 0.5 | G39: % | H39: Se aplica a todo el facturado como promedio ponderado: la entrada se cobra al contado, la oferta y el programa en cuotas. El ejemplo usa 50 / 25 / 25.
B40: % que entra en el mes 2 | C40: 0.25 | G40: % | H40: Cuotas o pagos diferidos.
B41: % que entra en el mes 3 | C41: 0.25 | G41: % | H41: Los tres deben sumar 100 %.
B43: 7. Objetivos y proyección
B44: ROAS objetivo sobre cash neto | C44: 2 | G44: x | H44: El retorno mínimo que querés por cada dólar invertido, después de comisiones y reembolsos. Entra en el semáforo: sin llegar a este ROAS no hay verde.
B45: Margen de seguridad | C45: 0.3 | G45: % | H45: Colchón entre el techo (donde no ganás ni perdés) y el objetivo. 30 % es el estándar que usamos.
B46: Meta de ventas del producto principal | C46: 25 | G46: ventas de la oferta / lanzamiento | H46: Para calcular cuánto invertir.
B47: Crecimiento de la inversión por mes (proyección) | C47: 0.1 | G47: % / mes | H47: Cuánto sube la inversión cada mes en la proyección. 10 % por mes es un ritmo prudente; más de 25 % suele encarecer el CPM.
B48: Caja inicial | C48: 4000 | G48: USD | H48: Con cuánta plata arrancás. La proyección te dice si alcanza.

Sheet Modelo
B1: © Jesús Tassarolo · TooAudience · youtube.com/@JesusTassaroloSinFiltro · uso personal; no redistribuir modificado
B2: Modelo: la cadena completa del embudo
B3: Cada fila es una etapa o un resultado. No se edita: todo sale de Supuestos. La columna de la derecha dice cómo se calcula.
B5: Etapa / resultado | C5: Valor | D5: Cómo se calcula
B6: Tráfico y entradas
B7: Visitas a la página de ventas | C7: =IF('Supuestos'!$C$10=0,0,'Supuestos'!$C$8/'Supuestos'!$C$10) | D7: Inversión ÷ costo por visita.
B8: Costo por entrada vendida | C8: =IF('Supuestos'!$C$13=0,0,'Supuestos'!$C$10/'Supuestos'!$C$13) | D8: Costo por visita ÷ % que compra la entrada.
B9: Entradas vendidas | C9: =IF('Modelo'!$C$8=0,0,'Supuestos'!$C$8/'Modelo'!$C$8) | D9: Inversión ÷ costo por entrada.
B10: Facturado: entradas | C10: ='Modelo'!$C$9*'Supuestos'!$C$14 | D10: Entradas × precio promedio.
B11: Ventas: bump de la entrada | C11: ='Modelo'!$C$9*'Supuestos'!$C$16 | D11: Entradas × % que lo toma.
B12: Facturado: bump de la entrada | C12: ='Modelo'!$C$11*'Supuestos'!$C$15 | D12: Ventas × precio.
B13: Facturado del front (entradas + bump) | C13: ='Modelo'!$C$10+'Modelo'!$C$12 | D13: Lo que entra antes del evento.
B14: ROAS del front (qué parte de la pauta recupera la entrada) | C14: =IF('Supuestos'!$C$8=0,0,'Modelo'!$C$13/'Supuestos'!$C$8) | D14: Facturado del front ÷ inversión. Cerca de 1 = el evento se paga solo.
B15: Grupo y asistencia
B16: Personas en el grupo | C16: ='Modelo'!$C$9*'Supuestos'!$C$19 | D16: Entradas × % que entra.
B17: Costo por persona en el grupo | C17: =IF('Modelo'!$C$16=0,0,'Supuestos'!$C$8/'Modelo'!$C$16) | D17: Inversión ÷ personas en el grupo.
B18: Asistentes en vivo | C18: ='Modelo'!$C$9*'Supuestos'!$C$20 | D18: Entradas × asistencia en vivo.
B19: Vieron el replay | C19: ='Modelo'!$C$9*'Supuestos'!$C$21 | D19: Entradas × % que ve el replay.
B20: Costo por asistente en vivo | C20: =IF('Modelo'!$C$18=0,0,'Supuestos'!$C$8/'Modelo'!$C$18) | D20: Inversión ÷ asistentes.
B21: Solicitudes (formulario de compra, aplicación o vendedor), oferta, programa y facturación
B22: Solicitudes: en vivo | C22: ='Modelo'!$C$18*'Supuestos'!$C$25 | D22: Asistentes en vivo × % que solicita.
B23: Solicitudes: replay | C23: ='Modelo'!$C$19*'Supuestos'!$C$26 | D23: Replay × % que solicita.
B24: Solicitudes (total) | C24: ='Modelo'!$C$22+'Modelo'!$C$23 | D24: En vivo + replay.
B25: % de compradores de entrada que solicitan | C25: =IF('Modelo'!$C$9=0,0,'Modelo'!$C$24/'Modelo'!$C$9) | D25: Solicitudes ÷ entradas.
B26: Costo por solicitud | C26: =IF('Modelo'!$C$24=0,0,'Supuestos'!$C$8/'Modelo'!$C$24) | D26: Inversión ÷ solicitudes.
B27: Ventas de la oferta | C27: ='Modelo'!$C$24*'Supuestos'!$C$27 | D27: Solicitudes × % que termina en compra.
B28: % de compradores de entrada que compran la oferta | C28: =IF('Modelo'!$C$9=0,0,'Modelo'!$C$27/'Modelo'!$C$9) | D28: Ventas ÷ entradas.
B29: Costo por comprador de la oferta | C29: =IF('Modelo'!$C$27=0,0,'Supuestos'!$C$8/'Modelo'!$C$27) | D29: Inversión ÷ ventas de la oferta.
B30: Facturado: oferta | C30: ='Modelo'!$C$27*'Supuestos'!$C$24 | D30: Ventas × precio.
B31: Ventas: programa superior | C31: ='Modelo'!$C$27*'Supuestos'!$C$29 | D31: Compradores de la oferta × % que asciende.
B32: Facturado: programa superior | C32: ='Modelo'!$C$31*'Supuestos'!$C$28 | D32: Ventas × precio.
B33: Facturado total | C33: ='Modelo'!$C$13+'Modelo'!$C$30+'Modelo'!$C$32 | D33: Front + oferta + programa.
B34: Facturado por comprador de la oferta | C34: =IF('Modelo'!$C$27=0,0,'Modelo'!$C$33/'Modelo'!$C$27) | D34: Facturado total ÷ ventas de la oferta.
B35: Ventas de la oferta por entrada (para la proyección) | C35: =IF('Modelo'!$C$9=0,0,'Modelo'!$C$27/'Modelo'!$C$9) | D35: Igual a '% que compra la oferta'.
B36: Facturado por entrada | C36: =IF('Modelo'!$C$9=0,0,'Modelo'!$C$33/'Modelo'!$C$9) | D36: Facturado total ÷ entradas.
B37: Cash, costos y ganancia del período
B38: Cash a cobrar (facturado × cobranza completa) | C38: ='Modelo'!$C$33*('Supuestos'!$C$39+'Supuestos'!$C$40+'Supuestos'!$C$41) | D38: Facturado × (mes 1 + mes 2 + mes 3). Si la cobranza suma 100 %, es igual al facturado.
B39: Cash que entra en el primer mes | C39: ='Modelo'!$C$33*'Supuestos'!$C$39 | D39: Facturado × % del mes 1.
B40: Comisiones (pasarela + ventas) | C40: ='Modelo'!$C$38*('Supuestos'!$C$32+'Supuestos'!$C$33) | D40: Cash × (pasarela + equipo de ventas).
B41: Reembolsos | C41: ='Modelo'!$C$38*'Supuestos'!$C$34 | D41: Cash × % de reembolsos.
B42: Cash neto | C42: ='Modelo'!$C$38*(1-'Supuestos'!$C$32-'Supuestos'!$C$33-'Supuestos'!$C$34) | D42: Cash − comisiones − reembolsos. La base de verdad.
B43: Costos por entrada (herramientas, WhatsApp, IA) | C43: ='Modelo'!$C$9*'Supuestos'!$C$35 | D43: Entradas × costo por entrada.
B44: Ganancia del período | C44: ='Modelo'!$C$42-'Modelo'!$C$43-'Supuestos'!$C$36-'Supuestos'!$C$8 | D44: Cash neto − costos por unidad − fijos − inversión.
B45: ROAS sobre facturado | C45: =IF('Supuestos'!$C$8=0,0,'Modelo'!$C$33/'Supuestos'!$C$8) | D45: Facturado ÷ inversión. El número que más se infla: no decidas con este.
B46: ROAS sobre cash neto | C46: =IF('Supuestos'!$C$8=0,0,'Modelo'!$C$42/'Supuestos'!$C$8) | D46: Cash neto ÷ inversión. Con este se decide.
B47: Margen sobre cash | C47: =IF('Modelo'!$C$38=0,0,'Modelo'!$C$44/'Modelo'!$C$38) | D47: Ganancia ÷ cash.
B48: ¿Cumple el ROAS objetivo? | C48: =IF('Modelo'!$C$46>='Supuestos'!$C$44,"SÍ","NO") | D48: ROAS sobre cash neto contra el objetivo de Supuestos.
B49: Cuánto vale cada entrada y hasta cuánto pagar
B50: Valor neto por entrada | C50: =IF('Modelo'!$C$9=0,0,('Modelo'!$C$42-'Modelo'!$C$43)/'Modelo'!$C$9) | D50: (Cash neto − costos por entrada) ÷ entradas.
B51: Techo de costo por entrada (break-even) | C51: ='Modelo'!$C$50 | D51: Igual al valor neto por entrada.
B52: Objetivo de costo por entrada | C52: ='Modelo'!$C$51/(1+'Supuestos'!$C$45) | D52: Techo ÷ (1 + margen de seguridad).
B53: Techo de costo por visita a la página | C53: ='Modelo'!$C$50*'Supuestos'!$C$13 | D53: Valor por entrada × % que compra la entrada.
B54: Techo de costo por asistente en vivo | C54: =IF('Supuestos'!$C$20=0,0,'Modelo'!$C$50/'Supuestos'!$C$20) | D54: Valor por entrada ÷ asistencia.
B55: Techo de costo por solicitud | C55: =IF('Modelo'!$C$24=0,0,'Modelo'!$C$50*'Modelo'!$C$9/'Modelo'!$C$24) | D55: Valor total ÷ solicitudes.
B56: Techo de costo por comprador de la oferta | C56: =IF('Modelo'!$C$28=0,0,'Modelo'!$C$50/'Modelo'!$C$28) | D56: Valor por entrada ÷ % que compra la oferta.
B57: Objetivo de costo por comprador de la oferta | C57: ='Modelo'!$C$56/(1+'Supuestos'!$C$45) | D57: Techo ÷ (1 + margen de seguridad).
B58: Semáforo y cuánto invertir
B59: Semáforo del costo por entrada actual | C59: =IF('Modelo'!$C$8>'Modelo'!$C$51,"ROJO",IF(AND('Modelo'!$C$8<='Modelo'!$C$52,'Modelo'!$C$46>='Supuestos'!$C$44),"VERDE","AMARILLO")) | D59: Rojo: costo > techo. Verde: costo ≤ objetivo y ROAS sobre cash neto ≥ objetivo. Amarillo: el resto.
B60: Inversión necesaria para la meta de ventas de la oferta (al costo actual) | C60: =IF('Modelo'!$C$28=0,"inalcanzable con estos supuestos",'Supuestos'!$C$46/'Modelo'!$C$28*'Modelo'!$C$8) | D60: Meta ÷ % que compra la oferta × costo por entrada.
B61: Inversión para la meta al costo objetivo (lo máximo que conviene pagar) | C61: =IF('Modelo'!$C$28=0,"inalcanzable con estos supuestos",'Supuestos'!$C$46/'Modelo'!$C$28*'Modelo'!$C$52) | D61: Lo mismo, al costo objetivo.
B62: Ganancia por paso (las dos caras de cada número: costo por X y ganancia por X)
B63: Cash neto por comprador (AOV neto) | C63: =IF('Modelo'!$C$27=0,0,('Modelo'!$C$42-'Modelo'!$C$43)/'Modelo'!$C$27) | D63: Lo que deja cada comprador del principal después de comisiones, reembolsos y costos por unidad. Su par es el CPA.
B64: Ganancia por visita | C64: =IF('Modelo'!$C$7=0,0,'Modelo'!$C$44/'Modelo'!$C$7) | D64: Ganancia del período ÷ visitas a la página de ventas. La métrica más valiosa: resume todo lo que pasa después. Su par es el costo por visita.
B65: Ganancia por entrada | C65: =IF('Modelo'!$C$9=0,0,'Modelo'!$C$44/'Modelo'!$C$9) | D65: Ganancia del período ÷ entradas. Su par es el costo por entrada.
B66: Ganancia por asistente en vivo | C66: =IF('Modelo'!$C$18=0,0,'Modelo'!$C$44/'Modelo'!$C$18) | D66: Ganancia del período ÷ asistente en vivos. Su par es el costo por asistente en vivo.
B67: Ganancia por solicitud | C67: =IF('Modelo'!$C$24=0,0,'Modelo'!$C$44/'Modelo'!$C$24) | D67: Ganancia del período ÷ solicituds. Su par es el costo por solicitud.
B68: Ganancia por cliente | C68: =IF('Modelo'!$C$27=0,0,'Modelo'!$C$44/'Modelo'!$C$27) | D68: Ganancia del período ÷ compradores de la oferta. Su par es el costo por comprador.

Sheet Escenarios
B1: © Jesús Tassarolo · TooAudience · youtube.com/@JesusTassaroloSinFiltro · uso personal; no redistribuir modificado
B2: Escenarios: qué pasa si cambian el precio, la conversión o el costo
B3: Las celdas amarillas de cada tabla (fila y columna) se pueden cambiar. Verde = ganancia, amarillo = cerca del cero, rojo = pérdida. Todo lo demás queda como en Supuestos.
B5: Umbral de 'cerca del cero' (inversión × margen de seguridad) | C5: ='Supuestos'!$C$8*'Supuestos'!$C$45
B7: Precio de la oferta × % de solicitudes que terminan en compra → ganancia del lanzamiento
B8: A más precio, menos cierre: la tabla muestra qué combinación gana.
B9: Precio ↓ / % solicitud → compra → | C9: 0.3 | D9: 0.4 | E9: 0.5 | F9: 0.6 | G9: 0.7
B10: 197 | C10: =(((((((IF((IF('Supuestos'!$C$13=0,0,'Supuestos'!$C$10/'Supuestos'!$C$13))=0,0,'Supuestos'!$C$8/(IF('Supuestos'!$C$13=0,0,'Supuestos'!$C$10/'Supuestos'!$C$13))))*'Supuestos'!$C$14)+(((IF((IF('Supuestos'!$C$13=0,0,'Supuestos'!$C$10/'Supuestos'!$C$13))=0,0,'Supuestos'!$C$8/(IF('Supuestos'!$C$13=0,0,'Supuestos'!$C$10/'Supuestos'!$C$13))))*'Supuestos'!$C$16)*'Supuestos'!$C$15))+((((((IF((IF('Supuestos'!$C$13=0,0,'Supuestos'!$C$10/'Supuestos'!$C$13))=0,0,'Supuestos'!$C$8/(IF('Supuestos'!$C$13=0,0,'Supuestos'!$C$10/'Supuestos'!$C$13))))*'Supuestos'!$C$20)*'Supuestos'!$C$25)+(((IF((IF('Supuestos'!$C$13=0,0,'Supuestos'!$C$10/'Supuestos'!$C$13))=0,0,'Supuestos'!$C$8/(IF('Supuestos'!$C$13=0,0,'Supuestos'!$C$10/'Supuestos'!$C$13))))*'Supuestos'!$C$21)*'Supuestos'!$C$26))*C$9)*$B10)+(((((((IF((IF('Supuestos'!$C$13=0,0,'Supuestos'!$C$10/'Supuestos'!$C$13))=0,0,'Supuestos'!$C$8/(IF('Supuestos'!$C$13=0,0,'Supuestos'!$C$10/'Supuestos'!$C$13))))*'Supuestos'!$C$20)*'Supuestos'!$C$25)+(((IF((IF('Supuestos'!$C$13=0,0,'Supuestos'!$C$10/'Supuestos'!$C$13))=0,0,'Supuestos'!$C$8/(IF('Supuestos'!$C$13=0,0,'Supuestos'!$C$10/'Supuestos'!$C$13))))*'Supuestos'!$C$21)*'Supuestos'!$C$26))*C$9)*'Supuestos'!$C$29)*'Supuestos'!$C$28))*('Supuestos'!$C$39+'Supuestos'!$C$40+'Supuestos'!$C$41))*(1-'Supuestos'!$C$32-'Supuestos'!$C$33-'Supuestos'!$C$34))-((IF((IF('Supuestos'!$C$13=0,0,'Supuestos'!$C$10/'Supuestos'!$C$13))=0,0,'Supuestos'!$C$8/(IF('Supuestos'!$C$13=0,0,'Supuestos'!$C$10/'Supuestos'!$C$13))))*'Supuestos'!$C$35)-'Supuestos'!$C$36-'Supuestos'!$C$8) | D10: =(((((((IF((IF('Supuestos'!$C$13=0,0,'Supuestos'!$C$10/'Supuestos'!$C$13))=0,0,'Supuestos'!$C$8/(IF('Supuestos'!$C$13=0,0,'Supuestos'!$C$10/'Supuestos'!$C$13))))*'Supuestos'!$C$14)+(((IF((IF('Supuestos'!$C$13=0,0,'Supuestos'!$C$10/'Supuestos'!$C$13))=0,0,'Supuestos'!$C$8/(IF('Supuestos'!$C$13=0,0,'Supuestos'!$C$10/'Supuestos'!$C$13))))*'Supuestos'!$C$16)*'Supuestos'!$C$15))+((((((IF((IF('Supuestos'!$C$13=0,0,'Supuestos'!$C$10/'Supuestos'!$C$13))=0,0,'Supuestos'!$C$8/(IF('Supuestos'!$C$13=0,0,'Supuestos'!$C$10/'Supuestos'!$C$13))))*'Supuestos'!$C$20)*'Supuestos'!$C$25)+(((IF((IF('Supuestos'!$C$13=0,0,'Supuestos'!$C$10/'Supuestos'!$C$13))=0,0,'Supuestos'!$C$8/(IF('Supuestos'!$C$13=0,0,'Supuestos'!$C$10/'Supuestos'!$C$13))))*'Supuestos'!$C$21)*'Supuestos'!$C$26))*D$9)*$B10)+(((((((IF((IF('Supuestos'!$C$13=0,0,'Supuestos'!$C$10/'Supuestos'!$C$13))=0,0,'Supuestos'!$C$8/(IF('Supuestos'!$C$13=0,0,'Supuestos'!$C$10/'Supuestos'!$C$13))))*'Supuestos'!$C$20)*'Supuestos'!$C$25)+(((IF((IF('Supuestos'!$C$13=0,0,'Supuestos'!$C$10/'Supuestos'!$C$13))=0,0,'Supuestos'!$C$8/(IF('Supuestos'!$C$13=0,0,'Supuestos'!$C$10/'Supuestos'!$C$13))))*'Supuestos'!$C$21)*'Supuestos'!$C$26))*D$9)*'Supuestos'!$C$29)*'Supuestos'!$C$28))*('Supuestos'!$C$39+'Supuestos'!$C$40+'Supuestos'!$C$41))*(1-'Supuestos'!$C$32-'Supuestos'!$C$33-'Supuestos'!$C$34))-((IF((IF('Supuestos'!$C$13=0,0,'Supuestos'!$C$10/'Supuestos'!$C$13))=0,0,'Supuestos'!$C$8/(IF('Supuestos'!$C$13=0,0,'Supuestos'!$C$10/'Supuestos'!$C$13))))*'Supuestos'!$C$35)-'Supuestos'!$C$36-'Supuestos'!$C$8) | E10: =(((((((IF((IF('Supuestos'!$C$13=0,0,'Supuestos'!$C$10/'Supuestos'!$C$13))=0,0,'Supuestos'!$C$8/(IF('Supuestos'!$C$13=0,0,'Supuestos'!$C$10/'Supuestos'!$C$13))))*'Supuestos'!$C$14)+(((IF((IF('Supuestos'!$C$13=0,0,'Supuestos'!$C$10/'Supuestos'!$C$13))=0,0,'Supuestos'!$C$8/(IF('Supuestos'!$C$13=0,0,'Supuestos'!$C$10/'Supuestos'!$C$13))))*'Supuestos'!$C$16)*'Supuestos'!$C$15))+((((((IF((IF('Supuestos'!$C$13=0,0,'Supuestos'!$C$10/'Supuestos'!$C$13))=0,0,'Supuestos'!$C$8/(IF('Supuestos'!$C$13=0,0,'Supuestos'!$C$10/'Supuestos'!$C$13))))*'Supuestos'!$C$20)*'Supuestos'!$C$25)+(((IF((IF('Supuestos'!$C$13=0,0,'Supuestos'!$C$10/'Supuestos'!$C$13))=0,0,'Supuestos'!$C$8/(IF('Supuestos'!$C$13=0,0,'Supuestos'!$C$10/'Supuestos'!$C$13))))*'Supuestos'!$C$21)*'Supuestos'!$C$26))*E$9)*$B10)+(((((((IF((IF('Supuestos'!$C$13=0,0,'Supuestos'!$C$10/'Supuestos'!$C$13))=0,0,'Supuestos'!$C$8/(IF('Supuestos'!$C$13=0,0,'Supuestos'!$C$10/'Supuestos'!$C$13))))*'Supuestos'!$C$20)*'Supuestos'!$C$25)+(((IF((IF('Supuestos'!$C$13=0,0,'Supuestos'!$C$10/'Supuestos'!$C$13))=0,0,'Supuestos'!$C$8/(IF('Supuestos'!$C$13=0,0,'Supuestos'!$C$10/'Supuestos'!$C$13))))*'Supuestos'!$C$21)*'Supuestos'!$C$26))*E$9)*'Supuestos'!$C$29)*'Supuestos'!$C$28))*('Supuestos'!$C$39+'Supuestos'!$C$40+'Supuestos'!$C$41))*(1-'Supuestos'!$C$32-'Supuestos'!$C$33-'Supuestos'!$C$34))-((IF((IF('Supuestos'!$C$13=0,0,'Supuestos'!$C$10/'Supuestos'!$C$13))=0,0,'Supuestos'!$C$8/(IF('Supuestos'!$C$13=0,0,'Supuestos'!$C$10/'Supuestos'!$C$13))))*'Supuestos'!$C$35)-'Supuestos'!$C$36-'Supuestos'!$C$8) | F10: =(((((((IF((IF('Supuestos'!$C$13=0,0,'Supuestos'!$C$10/'Supuestos'!$C$13))=0,0,'Supuestos'!$C$8/(IF('Supuestos'!$C$13=0,0,'Supuestos'!$C$10/'Supuestos'!$C$13))))*'Supuestos'!$C$14)+(((IF((IF('Supuestos'!$C$13=0,0,'Supuestos'!$C$10/'Supuestos'!$C$13))=0,0,'Supuestos'!$C$8/(IF('Supuestos'!$C$13=0,0,'Supuestos'!$C$10/'Supuestos'!$C$13))))*'Supuestos'!$C$16)*'Supuestos'!$C$15))+((((((IF((IF('Supuestos'!$C$13=0,0,'Supuestos'!$C$10/'Supuestos'!$C$13))=0,0,'Supuestos'!$C$8/(IF('Supuestos'!$C$13=0,0,'Supuestos'!$C$10/'Supuestos'!$C$13))))*'Supuestos'!$C$20)*'Supuestos'!$C$25)+(((IF((IF('Supuestos'!$C$13=0,0,'Supuestos'!$C$10/'Supuestos'!$C$13))=0,0,'Supuestos'!$C$8/(IF('Supuestos'!$C$13=0,0,'Supuestos'!$C$10/'Supuestos'!$C$13))))*'Supuestos'!$C$21)*'Supuestos'!$C$26))*F$9)*$B10)+(((((((IF((IF('Supuestos'!$C$13=0,0,'Supuestos'!$C$10/'Supuestos'!$C$13))=0,0,'Supuestos'!$C$8/(IF('Supuestos'!$C$13=0,0,'Supuestos'!$C$10/'Supuestos'!$C$13))))*'Supuestos'!$C$20)*'Supuestos'!$C$25)+(((IF((IF('Supuestos'!$C$13=0,0,'Supuestos'!$C$10/'Supuestos'!$C$13))=0,0,'Supuestos'!$C$8/(IF('Supuestos'!$C$13=0,0,'Supuestos'!$C$10/'Supuestos'!$C$13))))*'Supuestos'!$C$21)*'Supuestos'!$C$26))*F$9)*'Supuestos'!$C$29)*'Supuestos'!$C$28))*('Supuestos'!$C$39+'Supuestos'!$C$40+'Supuestos'!$C$41))*(1-'Supuestos'!$C$32-'Supuestos'!$C$33-'Supuestos'!$C$34))-((IF((IF('Supuestos'!$C$13=0,0,'Supuestos'!$C$10/'Supuestos'!$C$13))=0,0,'Supuestos'!$C$8/(IF('Supuestos'!$C$13=0,0,'Supuestos'!$C$10/'Supuestos'!$C$13))))*'Supuestos'!$C$35)-'Supuestos'!$C$36-'Supuestos'!$C$8) | G10: =(((((((IF((IF('Supuestos'!$C$13=0,0,'Supuestos'!$C$10/'Supuestos'!$C$13))=0,0,'Supuestos'!$C$8/(IF('Supuestos'!$C$13=0,0,'Supuestos'!$C$10/'Supuestos'!$C$13))))*'Supuestos'!$C$14)+(((IF((IF('Supuestos'!$C$13=0,0,'Supuestos'!$C$10/'Supuestos'!$C$13))=0,0,'Supuestos'!$C$8/(IF('Supuestos'!$C$13=0,0,'Supuestos'!$C$10/'Supuestos'!$C$13))))*'Supuestos'!$C$16)*'Supuestos'!$C$15))+((((((IF((IF('Supuestos'!$C$13=0,0,'Supuestos'!$C$10/'Supuestos'!$C$13))=0,0,'Supuestos'!$C$8/(IF('Supuestos'!$C$13=0,0,'Supuestos'!$C$10/'Supuestos'!$C$13))))*'Supuestos'!$C$20)*'Supuestos'!$C$25)+(((IF((IF('Supuestos'!$C$13=0,0,'Supuestos'!$C$10/'Supuestos'!$C$13))=0,0,'Supuestos'!$C$8/(IF('Supuestos'!$C$13=0,0,'Supuestos'!$C$10/'Supuestos'!$C$13))))*'Supuestos'!$C$21)*'Supuestos'!$C$26))*G$9)*$B10)+(((((((IF((IF('Supuestos'!$C$13=0,0,'Supuestos'!$C$10/'Supuestos'!$C$13))=0,0,'Supuestos'!$C$8/(IF('Supuestos'!$C$13=0,0,'Supuestos'!$C$10/'Supuestos'!$C$13))))*'Supuestos'!$C$20)*'Supuestos'!$C$25)+(((IF((IF('Supuestos'!$C$13=0,0,'Supuestos'!$C$10/'Supuestos'!$C$13))=0,0,'Supuestos'!$C$8/(IF('Supuestos'!$C$13=0,0,'Supuestos'!$C$10/'Supuestos'!$C$13))))*'Supuestos'!$C$21)*'Supuestos'!$C$26))*G$9)*'Supuestos'!$C$29)*'Supuestos'!$C$28))*('Supuestos'!$C$39+'Supuestos'!$C$40+'Supuestos'!$C$41))*(1-'Supuestos'!$C$32-'Supuestos'!$C$33-'Supuestos'!$C$34))-((IF((IF('Supuestos'!$C$13=0,0,'Supuestos'!$C$10/'Supuestos'!$C$13))=0,0,'Supuestos'!$C$8/(IF('Supuestos'!$C$13=0,0,'Supuestos'!$C$10/'Supuestos'!$C$13))))*'Supuestos'!$C$35)-'Supuestos'!$C$36-'Supuestos'!$C$8)
B11: 297 | C11: =(((((((IF((IF('Supuestos'!$C$13=0,0,'Supuestos'!$C$10/'Supuestos'!$C$13))=0,0,'Supuestos'!$C$8/(IF('Supuestos'!$C$13=0,0,'Supuestos'!$C$10/'Supuestos'!$C$13))))*'Supuestos'!$C$14)+(((IF((IF('Supuestos'!$C$13=0,0,'Supuestos'!$C$10/'Supuestos'!$C$13))=0,0,'Supuestos'!$C$8/(IF('Supuestos'!$C$13=0,0,'Supuestos'!$C$10/'Supuestos'!$C$13))))*'Supuestos'!$C$16)*'Supuestos'!$C$15))+((((((IF((IF('Supuestos'!$C$13=0,0,'Supuestos'!$C$10/'Supuestos'!$C$13))=0,0,'Supuestos'!$C$8/(IF('Supuestos'!$C$13=0,0,'Supuestos'!$C$10/'Supuestos'!$C$13))))*'Supuestos'!$C$20)*'Supuestos'!$C$25)+(((IF((IF('Supuestos'!$C$13=0,0,'Supuestos'!$C$10/'Supuestos'!$C$13))=0,0,'Supuestos'!$C$8/(IF('Supuestos'!$C$13=0,0,'Supuestos'!$C$10/'Supuestos'!$C$13))))*'Supuestos'!$C$21)*'Supuestos'!$C$26))*C$9)*$B11)+(((((((IF((IF('Supuestos'!$C$13=0,0,'Supuestos'!$C$10/'Supuestos'!$C$13))=0,0,'Supuestos'!$C$8/(IF('Supuestos'!$C$13=0,0,'Supuestos'!$C$10/'Supuestos'!$C$13))))*'Supuestos'!$C$20)*'Supuestos'!$C$25)+(((IF((IF('Supuestos'!$C$13=0,0,'Supuestos'!$C$10/'Supuestos'!$C$13))=0,0,'Supuestos'!$C$8/(IF('Supuestos'!$C$13=0,0,'Supuestos'!$C$10/'Supuestos'!$C$13))))*'Supuestos'!$C$21)*'Supuestos'!$C$26))*C$9)*'Supuestos'!$C$29)*'Supuestos'!$C$28))*('Supuestos'!$C$39+'Supuestos'!$C$40+'Supuestos'!$C$41))*(1-'Supuestos'!$C$32-'Supuestos'!$C$33-'Supuestos'!$C$34))-((IF((IF('Supuestos'!$C$13=0,0,'Supuestos'!$C$10/'Supuestos'!$C$13))=0,0,'Supuestos'!$C$8/(IF('Supuestos'!$C$13=0,0,'Supuestos'!$C$10/'Supuestos'!$C$13))))*'Supuestos'!$C$35)-'Supuestos'!$C$36-'Supuestos'!$C$8) | D11: =(((((((IF((IF('Supuestos'!$C$13=0,0,'Supuestos'!$C$10/'Supuestos'!$C$13))=0,0,'Supuestos'!$C$8/(IF('Supuestos'!$C$13=0,0,'Supuestos'!$C$10/'Supuestos'!$C$13))))*'Supuestos'!$C$14)+(((IF((IF('Supuestos'!$C$13=0,0,'Supuestos'!$C$10/'Supuestos'!$C$13))=0,0,'Supuestos'!$C$8/(IF('Supuestos'!$C$13=0,0,'Supuestos'!$C$10/'Supuestos'!$C$13))))*'Supuestos'!$C$16)*'Supuestos'!$C$15))+((((((IF((IF('Supuestos'!$C$13=0,0,'Supuestos'!$C$10/'Supuestos'!$C$13))=0,0,'Supuestos'!$C$8/(IF('Supuestos'!$C$13=0,0,'Supuestos'!$C$10/'Supuestos'!$C$13))))*'Supuestos'!$C$20)*'Supuestos'!$C$25)+(((IF((IF('Supuestos'!$C$13=0,0,'Supuestos'!$C$10/'Supuestos'!$C$13))=0,0,'Supuestos'!$C$8/(IF('Supuestos'!$C$13=0,0,'Supuestos'!$C$10/'Supuestos'!$C$13))))*'Supuestos'!$C$21)*'Supuestos'!$C$26))*D$9)*$B11)+(((((((IF((IF('Supuestos'!$C$13=0,0,'Supuestos'!$C$10/'Supuestos'!$C$13))=0,0,'Supuestos'!$C$8/(IF('Supuestos'!$C$13=0,0,'Supuestos'!$C$10/'Supuestos'!$C$13))))*'Supuestos'!$C$20)*'Supuestos'!$C$25)+(((IF((IF('Supuestos'!$C$13=0,0,'Supuestos'!$C$10/'Supuestos'!$C$13))=0,0,'Supuestos'!$C$8/(IF('Supuestos'!$C$13=0,0,'Supuestos'!$C$10/'Supuestos'!$C$13))))*'Supuestos'!$C$21)*'Supuestos'!$C$26))*D$9)*'Supuestos'!$C$29)*'Supuestos'!$C$28))*('Supuestos'!$C$39+'Supuestos'!$C$40+'Supuestos'!$C$41))*(1-'Supuestos'!$C$32-'Supuestos'!$C$33-'Supuestos'!$C$34))-((IF((IF('Supuestos'!$C$13=0,0,'Supuestos'!$C$10/'Supuestos'!$C$13))=0,0,'Supuestos'!$C$8/(IF('Supuestos'!$C$13=0,0,'Supuestos'!$C$10/'Supuestos'!$C$13))))*'Supuestos'!$C$35)-'Supuestos'!$C$36-'Supuestos'!$C$8) | E11: =(((((((IF((IF('Supuestos'!$C$13=0,0,'Supuestos'!$C$10/'Supuestos'!$C$13))=0,0,'Supuestos'!$C$8/(IF('Supuestos'!$C$13=0,0,'Supuestos'!$C$10/'Supuestos'!$C$13))))*'Supuestos'!$C$14)+(((IF((IF('Supuestos'!$C$13=0,0,'Supuestos'!$C$10/'Supuestos'!$C$13))=0,0,'Supuestos'!$C$8/(IF('Supuestos'!$C$13=0,0,'Supuestos'!$C$10/'Supuestos'!$C$13))))*'Supuestos'!$C$16)*'Supuestos'!$C$15))+((((((IF((IF('Supuestos'!$C$13=0,0,'Supuestos'!$C$10/'Supuestos'!$C$13))=0,0,'Supuestos'!$C$8/(IF('Supuestos'!$C$13=0,0,'Supuestos'!$C$10/'Supuestos'!$C$13))))*'Supuestos'!$C$20)*'Supuestos'!$C$25)+(((IF((IF('Supuestos'!$C$13=0,0,'Supuestos'!$C$10/'Supuestos'!$C$13))=0,0,'Supuestos'!$C$8/(IF('Supuestos'!$C$13=0,0,'Supuestos'!$C$10/'Supuestos'!$C$13))))*'Supuestos'!$C$21)*'Supuestos'!$C$26))*E$9)*$B11)+(((((((IF((IF('Supuestos'!$C$13=0,0,'Supuestos'!$C$10/'Supuestos'!$C$13))=0,0,'Supuestos'!$C$8/(IF('Supuestos'!$C$13=0,0,'Supuestos'!$C$10/'Supuestos'!$C$13))))*'Supuestos'!$C$20)*'Supuestos'!$C$25)+(((IF((IF('Supuestos'!$C$13=0,0,'Supuestos'!$C$10/'Supuestos'!$C$13))=0,0,'Supuestos'!$C$8/(IF('Supuestos'!$C$13=0,0,'Supuestos'!$C$10/'Supuestos'!$C$13))))*'Supuestos'!$C$21)*'Supuestos'!$C$26))*E$9)*'Supuestos'!$C$29)*'Supuestos'!$C$28))*('Supuestos'!$C$39+'Supuestos'!$C$40+'Supuestos'!$C$41))*(1-'Supuestos'!$C$32-'Supuestos'!$C$33-'Supuestos'!$C$34))-((IF((IF('Supuestos'!$C$13=0,0,'Supuestos'!$C$10/'Supuestos'!$C$13))=0,0,'Supuestos'!$C$8/(IF('Supuestos'!$C$13=0,0,'Supuestos'!$C$10/'Supuestos'!$C$13))))*'Supuestos'!$C$35)-'Supuestos'!$C$36-'Supuestos'!$C$8) | F11: =(((((((IF((IF('Supuestos'!$C$13=0,0,'Supuestos'!$C$10/'Supuestos'!$C$13))=0,0,'Supuestos'!$C$8/(IF('Supuestos'!$C$13=0,0,'Supuestos'!$C$10/'Supuestos'!$C$13))))*'Supuestos'!$C$14)+(((IF((IF('Supuestos'!$C$13=0,0,'Supuestos'!$C$10/'Supuestos'!$C$13))=0,0,'Supuestos'!$C$8/(IF('Supuestos'!$C$13=0,0,'Supuestos'!$C$10/'Supuestos'!$C$13))))*'Supuestos'!$C$16)*'Supuestos'!$C$15))+((((((IF((IF('Supuestos'!$C$13=0,0,'Supuestos'!$C$10/'Supuestos'!$C$13))=0,0,'Supuestos'!$C$8/(IF('Supuestos'!$C$13=0,0,'Supuestos'!$C$10/'Supuestos'!$C$13))))*'Supuestos'!$C$20)*'Supuestos'!$C$25)+(((IF((IF('Supuestos'!$C$13=0,0,'Supuestos'!$C$10/'Supuestos'!$C$13))=0,0,'Supuestos'!$C$8/(IF('Supuestos'!$C$13=0,0,'Supuestos'!$C$10/'Supuestos'!$C$13))))*'Supuestos'!$C$21)*'Supuestos'!$C$26))*F$9)*$B11)+(((((((IF((IF('Supuestos'!$C$13=0,0,'Supuestos'!$C$10/'Supuestos'!$C$13))=0,0,'Supuestos'!$C$8/(IF('Supuestos'!$C$13=0,0,'Supuestos'!$C$10/'Supuestos'!$C$13))))*'Supuestos'!$C$20)*'Supuestos'!$C$25)+(((IF((IF('Supuestos'!$C$13=0,0,'Supuestos'!$C$10/'Supuestos'!$C$13))=0,0,'Supuestos'!$C$8/(IF('Supuestos'!$C$13=0,0,'Supuestos'!$C$10/'Supuestos'!$C$13))))*'Supuestos'!$C$21)*'Supuestos'!$C$26))*F$9)*'Supuestos'!$C$29)*'Supuestos'!$C$28))*('Supuestos'!$C$39+'Supuestos'!$C$40+'Supuestos'!$C$41))*(1-'Supuestos'!$C$32-'Supuestos'!$C$33-'Supuestos'!$C$34))-((IF((IF('Supuestos'!$C$13=0,0,'Supuestos'!$C$10/'Supuestos'!$C$13))=0,0,'Supuestos'!$C$8/(IF('Supuestos'!$C$13=0,0,'Supuestos'!$C$10/'Supuestos'!$C$13))))*'Supuestos'!$C$35)-'Supuestos'!$C$36-'Supuestos'!$C$8) | G11: =(((((((IF((IF('Supuestos'!$C$13=0,0,'Supuestos'!$C$10/'Supuestos'!$C$13))=0,0,'Supuestos'!$C$8/(IF('Supuestos'!$C$13=0,0,'Supuestos'!$C$10/'Supuestos'!$C$13))))*'Supuestos'!$C$14)+(((IF((IF('Supuestos'!$C$13=0,0,'Supuestos'!$C$10/'Supuestos'!$C$13))=0,0,'Supuestos'!$C$8/(IF('Supuestos'!$C$13=0,0,'Supuestos'!$C$10/'Supuestos'!$C$13))))*'Supuestos'!$C$16)*'Supuestos'!$C$15))+((((((IF((IF('Supuestos'!$C$13=0,0,'Supuestos'!$C$10/'Supuestos'!$C$13))=0,0,'Supuestos'!$C$8/(IF('Supuestos'!$C$13=0,0,'Supuestos'!$C$10/'Supuestos'!$C$13))))*'Supuestos'!$C$20)*'Supuestos'!$C$25)+(((IF((IF('Supuestos'!$C$13=0,0,'Supuestos'!$C$10/'Supuestos'!$C$13))=0,0,'Supuestos'!$C$8/(IF('Supuestos'!$C$13=0,0,'Supuestos'!$C$10/'Supuestos'!$C$13))))*'Supuestos'!$C$21)*'Supuestos'!$C$26))*G$9)*$B11)+(((((((IF((IF('Supuestos'!$C$13=0,0,'Supuestos'!$C$10/'Supuestos'!$C$13))=0,0,'Supuestos'!$C$8/(IF('Supuestos'!$C$13=0,0,'Supuestos'!$C$10/'Supuestos'!$C$13))))*'Supuestos'!$C$20)*'Supuestos'!$C$25)+(((IF((IF('Supuestos'!$C$13=0,0,'Supuestos'!$C$10/'Supuestos'!$C$13))=0,0,'Supuestos'!$C$8/(IF('Supuestos'!$C$13=0,0,'Supuestos'!$C$10/'Supuestos'!$C$13))))*'Supuestos'!$C$21)*'Supuestos'!$C$26))*G$9)*'Supuestos'!$C$29)*'Supuestos'!$C$28))*('Supuestos'!$C$39+'Supuestos'!$C$40+'Supuestos'!$C$41))*(1-'Supuestos'!$C$32-'Supuestos'!$C$33-'Supuestos'!$C$34))-((IF((IF('Supuestos'!$C$13=0,0,'Supuestos'!$C$10/'Supuestos'!$C$13))=0,0,'Supuestos'!$C$8/(IF('Supuestos'!$C$13=0,0,'Supuestos'!$C$10/'Supuestos'!$C$13))))*'Supuestos'!$C$35)-'Supuestos'!$C$36-'Supuestos'!$C$8)
B12: 497 | C12: =(((((((IF((IF('Supuestos'!$C$13=0,0,'Supuestos'!$C$10/'Supuestos'!$C$13))=0,0,'Supuestos'!$C$8/(IF('Supuestos'!$C$13=0,0,'Supuestos'!$C$10/'Supuestos'!$C$13))))*'Supuestos'!$C$14)+(((IF((IF('Supuestos'!$C$13=0,0,'Supuestos'!$C$10/'Supuestos'!$C$13))=0,0,'Supuestos'!$C$8/(IF('Supuestos'!$C$13=0,0,'Supuestos'!$C$10/'Supuestos'!$C$13))))*'Supuestos'!$C$16)*'Supuestos'!$C$15))+((((((IF((IF('Supuestos'!$C$13=0,0,'Supuestos'!$C$10/'Supuestos'!$C$13))=0,0,'Supuestos'!$C$8/(IF('Supuestos'!$C$13=0,0,'Supuestos'!$C$10/'Supuestos'!$C$13))))*'Supuestos'!$C$20)*'Supuestos'!$C$25)+(((IF((IF('Supuestos'!$C$13=0,0,'Supuestos'!$C$10/'Supuestos'!$C$13))=0,0,'Supuestos'!$C$8/(IF('Supuestos'!$C$13=0,0,'Supuestos'!$C$10/'Supuestos'!$C$13))))*'Supuestos'!$C$21)*'Supuestos'!$C$26))*C$9)*$B12)+(((((((IF((IF('Supuestos'!$C$13=0,0,'Supuestos'!$C$10/'Supuestos'!$C$13))=0,0,'Supuestos'!$C$8/(IF('Supuestos'!$C$13=0,0,'Supuestos'!$C$10/'Supuestos'!$C$13))))*'Supuestos'!$C$20)*'Supuestos'!$C$25)+(((IF((IF('Supuestos'!$C$13=0,0,'Supuestos'!$C$10/'Supuestos'!$C$13))=0,0,'Supuestos'!$C$8/(IF('Supuestos'!$C$13=0,0,'Supuestos'!$C$10/'Supuestos'!$C$13))))*'Supuestos'!$C$21)*'Supuestos'!$C$26))*C$9)*'Supuestos'!$C$29)*'Supuestos'!$C$28))*('Supuestos'!$C$39+'Supuestos'!$C$40+'Supuestos'!$C$41))*(1-'Supuestos'!$C$32-'Supuestos'!$C$33-'Supuestos'!$C$34))-((IF((IF('Supuestos'!$C$13=0,0,'Supuestos'!$C$10/'Supuestos'!$C$13))=0,0,'Supuestos'!$C$8/(IF('Supuestos'!$C$13=0,0,'Supuestos'!$C$10/'Supuestos'!$C$13))))*'Supuestos'!$C$35)-'Supuestos'!$C$36-'Supuestos'!$C$8) | D12: =(((((((IF((IF('Supuestos'!$C$13=0,0,'Supuestos'!$C$10/'Supuestos'!$C$13))=0,0,'Supuestos'!$C$8/(IF('Supuestos'!$C$13=0,0,'Supuestos'!$C$10/'Supuestos'!$C$13))))*'Supuestos'!$C$14)+(((IF((IF('Supuestos'!$C$13=0,0,'Supuestos'!$C$10/'Supuestos'!$C$13))=0,0,'Supuestos'!$C$8/(IF('Supuestos'!$C$13=0,0,'Supuestos'!$C$10/'Supuestos'!$C$13))))*'Supuestos'!$C$16)*'Supuestos'!$C$15))+((((((IF((IF('Supuestos'!$C$13=0,0,'Supuestos'!$C$10/'Supuestos'!$C$13))=0,0,'Supuestos'!$C$8/(IF('Supuestos'!$C$13=0,0,'Supuestos'!$C$10/'Supuestos'!$C$13))))*'Supuestos'!$C$20)*'Supuestos'!$C$25)+(((IF((IF('Supuestos'!$C$13=0,0,'Supuestos'!$C$10/'Supuestos'!$C$13))=0,0,'Supuestos'!$C$8/(IF('Supuestos'!$C$13=0,0,'Supuestos'!$C$10/'Supuestos'!$C$13))))*'Supuestos'!$C$21)*'Supuestos'!$C$26))*D$9)*$B12)+(((((((IF((IF('Supuestos'!$C$13=0,0,'Supuestos'!$C$10/'Supuestos'!$C$13))=0,0,'Supuestos'!$C$8/(IF('Supuestos'!$C$13=0,0,'Supuestos'!$C$10/'Supuestos'!$C$13))))*'Supuestos'!$C$20)*'Supuestos'!$C$25)+(((IF((IF('Supuestos'!$C$13=0,0,'Supuestos'!$C$10/'Supuestos'!$C$13))=0,0,'Supuestos'!$C$8/(IF('Supuestos'!$C$13=0,0,'Supuestos'!$C$10/'Supuestos'!$C$13))))*'Supuestos'!$C$21)*'Supuestos'!$C$26))*D$9)*'Supuestos'!$C$29)*'Supuestos'!$C$28))*('Supuestos'!$C$39+'Supuestos'!$C$40+'Supuestos'!$C$41))*(1-'Supuestos'!$C$32-'Supuestos'!$C$33-'Supuestos'!$C$34))-((IF((IF('Supuestos'!$C$13=0,0,'Supuestos'!$C$10/'Supuestos'!$C$13))=0,0,'Supuestos'!$C$8/(IF('Supuestos'!$C$13=0,0,'Supuestos'!$C$10/'Supuestos'!$C$13))))*'Supuestos'!$C$35)-'Supuestos'!$C$36-'Supuestos'!$C$8) | E12: =(((((((IF((IF('Supuestos'!$C$13=0,0,'Supuestos'!$C$10/'Supuestos'!$C$13))=0,0,'Supuestos'!$C$8/(IF('Supuestos'!$C$13=0,0,'Supuestos'!$C$10/'Supuestos'!$C$13))))*'Supuestos'!$C$14)+(((IF((IF('Supuestos'!$C$13=0,0,'Supuestos'!$C$10/'Supuestos'!$C$13))=0,0,'Supuestos'!$C$8/(IF('Supuestos'!$C$13=0,0,'Supuestos'!$C$10/'Supuestos'!$C$13))))*'Supuestos'!$C$16)*'Supuestos'!$C$15))+((((((IF((IF('Supuestos'!$C$13=0,0,'Supuestos'!$C$10/'Supuestos'!$C$13))=0,0,'Supuestos'!$C$8/(IF('Supuestos'!$C$13=0,0,'Supuestos'!$C$10/'Supuestos'!$C$13))))*'Supuestos'!$C$20)*'Supuestos'!$C$25)+(((IF((IF('Supuestos'!$C$13=0,0,'Supuestos'!$C$10/'Supuestos'!$C$13))=0,0,'Supuestos'!$C$8/(IF('Supuestos'!$C$13=0,0,'Supuestos'!$C$10/'Supuestos'!$C$13))))*'Supuestos'!$C$21)*'Supuestos'!$C$26))*E$9)*$B12)+(((((((IF((IF('Supuestos'!$C$13=0,0,'Supuestos'!$C$10/'Supuestos'!$C$13))=0,0,'Supuestos'!$C$8/(IF('Supuestos'!$C$13=0,0,'Supuestos'!$C$10/'Supuestos'!$C$13))))*'Supuestos'!$C$20)*'Supuestos'!$C$25)+(((IF((IF('Supuestos'!$C$13=0,0,'Supuestos'!$C$10/'Supuestos'!$C$13))=0,0,'Supuestos'!$C$8/(IF('Supuestos'!$C$13=0,0,'Supuestos'!$C$10/'Supuestos'!$C$13))))*'Supuestos'!$C$21)*'Supuestos'!$C$26))*E$9)*'Supuestos'!$C$29)*'Supuestos'!$C$28))*('Supuestos'!$C$39+'Supuestos'!$C$40+'Supuestos'!$C$41))*(1-'Supuestos'!$C$32-'Supuestos'!$C$33-'Supuestos'!$C$34))-((IF((IF('Supuestos'!$C$13=0,0,'Supuestos'!$C$10/'Supuestos'!$C$13))=0,0,'Supuestos'!$C$8/(IF('Supuestos'!$C$13=0,0,'Supuestos'!$C$10/'Supuestos'!$C$13))))*'Supuestos'!$C$35)-'Supuestos'!$C$36-'Supuestos'!$C$8) | F12: =(((((((IF((IF('Supuestos'!$C$13=0,0,'Supuestos'!$C$10/'Supuestos'!$C$13))=0,0,'Supuestos'!$C$8/(IF('Supuestos'!$C$13=0,0,'Supuestos'!$C$10/'Supuestos'!$C$13))))*'Supuestos'!$C$14)+(((IF((IF('Supuestos'!$C$13=0,0,'Supuestos'!$C$10/'Supuestos'!$C$13))=0,0,'Supuestos'!$C$8/(IF('Supuestos'!$C$13=0,0,'Supuestos'!$C$10/'Supuestos'!$C$13))))*'Supuestos'!$C$16)*'Supuestos'!$C$15))+((((((IF((IF('Supuestos'!$C$13=0,0,'Supuestos'!$C$10/'Supuestos'!$C$13))=0,0,'Supuestos'!$C$8/(IF('Supuestos'!$C$13=0,0,'Supuestos'!$C$10/'Supuestos'!$C$13))))*'Supuestos'!$C$20)*'Supuestos'!$C$25)+(((IF((IF('Supuestos'!$C$13=0,0,'Supuestos'!$C$10/'Supuestos'!$C$13))=0,0,'Supuestos'!$C$8/(IF('Supuestos'!$C$13=0,0,'Supuestos'!$C$10/'Supuestos'!$C$13))))*'Supuestos'!$C$21)*'Supuestos'!$C$26))*F$9)*$B12)+(((((((IF((IF('Supuestos'!$C$13=0,0,'Supuestos'!$C$10/'Supuestos'!$C$13))=0,0,'Supuestos'!$C$8/(IF('Supuestos'!$C$13=0,0,'Supuestos'!$C$10/'Supuestos'!$C$13))))*'Supuestos'!$C$20)*'Supuestos'!$C$25)+(((IF((IF('Supuestos'!$C$13=0,0,'Supuestos'!$C$10/'Supuestos'!$C$13))=0,0,'Supuestos'!$C$8/(IF('Supuestos'!$C$13=0,0,'Supuestos'!$C$10/'Supuestos'!$C$13))))*'Supuestos'!$C$21)*'Supuestos'!$C$26))*F$9)*'Supuestos'!$C$29)*'Supuestos'!$C$28))*('Supuestos'!$C$39+'Supuestos'!$C$40+'Supuestos'!$C$41))*(1-'Supuestos'!$C$32-'Supuestos'!$C$33-'Supuestos'!$C$34))-((IF((IF('Supuestos'!$C$13=0,0,'Supuestos'!$C$10/'Supuestos'!$C$13))=0,0,'Supuestos'!$C$8/(IF('Supuestos'!$C$13=0,0,'Supuestos'!$C$10/'Supuestos'!$C$13))))*'Supuestos'!$C$35)-'Supuestos'!$C$36-'Supuestos'!$C$8) | G12: =(((((((IF((IF('Supuestos'!$C$13=0,0,'Supuestos'!$C$10/'Supuestos'!$C$13))=0,0,'Supuestos'!$C$8/(IF('Supuestos'!$C$13=0,0,'Supuestos'!$C$10/'Supuestos'!$C$13))))*'Supuestos'!$C$14)+(((IF((IF('Supuestos'!$C$13=0,0,'Supuestos'!$C$10/'Supuestos'!$C$13))=0,0,'Supuestos'!$C$8/(IF('Supuestos'!$C$13=0,0,'Supuestos'!$C$10/'Supuestos'!$C$13))))*'Supuestos'!$C$16)*'Supuestos'!$C$15))+((((((IF((IF('Supuestos'!$C$13=0,0,'Supuestos'!$C$10/'Supuestos'!$C$13))=0,0,'Supuestos'!$C$8/(IF('Supuestos'!$C$13=0,0,'Supuestos'!$C$10/'Supuestos'!$C$13))))*'Supuestos'!$C$20)*'Supuestos'!$C$25)+(((IF((IF('Supuestos'!$C$13=0,0,'Supuestos'!$C$10/'Supuestos'!$C$13))=0,0,'Supuestos'!$C$8/(IF('Supuestos'!$C$13=0,0,'Supuestos'!$C$10/'Supuestos'!$C$13))))*'Supuestos'!$C$21)*'Supuestos'!$C$26))*G$9)*$B12)+(((((((IF((IF('Supuestos'!$C$13=0,0,'Supuestos'!$C$10/'Supuestos'!$C$13))=0,0,'Supuestos'!$C$8/(IF('Supuestos'!$C$13=0,0,'Supuestos'!$C$10/'Supuestos'!$C$13))))*'Supuestos'!$C$20)*'Supuestos'!$C$25)+(((IF((IF('Supuestos'!$C$13=0,0,'Supuestos'!$C$10/'Supuestos'!$C$13))=0,0,'Supuestos'!$C$8/(IF('Supuestos'!$C$13=0,0,'Supuestos'!$C$10/'Supuestos'!$C$13))))*'Supuestos'!$C$21)*'Supuestos'!$C$26))*G$9)*'Supuestos'!$C$29)*'Supuestos'!$C$28))*('Supuestos'!$C$39+'Supuestos'!$C$40+'Supuestos'!$C$41))*(1-'Supuestos'!$C$32-'Supuestos'!$C$33-'Supuestos'!$C$34))-((IF((IF('Supuestos'!$C$13=0,0,'Supuestos'!$C$10/'Supuestos'!$C$13))=0,0,'Supuestos'!$C$8/(IF('Supuestos'!$C$13=0,0,'Supuestos'!$C$10/'Supuestos'!$C$13))))*'Supuestos'!$C$35)-'Supuestos'!$C$36-'Supuestos'!$C$8)
B13: 997 | C13: =(((((((IF((IF('Supuestos'!$C$13=0,0,'Supuestos'!$C$10/'Supuestos'!$C$13))=0,0,'Supuestos'!$C$8/(IF('Supuestos'!$C$13=0,0,'Supuestos'!$C$10/'Supuestos'!$C$13))))*'Supuestos'!$C$14)+(((IF((IF('Supuestos'!$C$13=0,0,'Supuestos'!$C$10/'Supuestos'!$C$13))=0,0,'Supuestos'!$C$8/(IF('Supuestos'!$C$13=0,0,'Supuestos'!$C$10/'Supuestos'!$C$13))))*'Supuestos'!$C$16)*'Supuestos'!$C$15))+((((((IF((IF('Supuestos'!$C$13=0,0,'Supuestos'!$C$10/'Supuestos'!$C$13))=0,0,'Supuestos'!$C$8/(IF('Supuestos'!$C$13=0,0,'Supuestos'!$C$10/'Supuestos'!$C$13))))*'Supuestos'!$C$20)*'Supuestos'!$C$25)+(((IF((IF('Supuestos'!$C$13=0,0,'Supuestos'!$C$10/'Supuestos'!$C$13))=0,0,'Supuestos'!$C$8/(IF('Supuestos'!$C$13=0,0,'Supuestos'!$C$10/'Supuestos'!$C$13))))*'Supuestos'!$C$21)*'Supuestos'!$C$26))*C$9)*$B13)+(((((((IF((IF('Supuestos'!$C$13=0,0,'Supuestos'!$C$10/'Supuestos'!$C$13))=0,0,'Supuestos'!$C$8/(IF('Supuestos'!$C$13=0,0,'Supuestos'!$C$10/'Supuestos'!$C$13))))*'Supuestos'!$C$20)*'Supuestos'!$C$25)+(((IF((IF('Supuestos'!$C$13=0,0,'Supuestos'!$C$10/'Supuestos'!$C$13))=0,0,'Supuestos'!$C$8/(IF('Supuestos'!$C$13=0,0,'Supuestos'!$C$10/'Supuestos'!$C$13))))*'Supuestos'!$C$21)*'Supuestos'!$C$26))*C$9)*'Supuestos'!$C$29)*'Supuestos'!$C$28))*('Supuestos'!$C$39+'Supuestos'!$C$40+'Supuestos'!$C$41))*(1-'Supuestos'!$C$32-'Supuestos'!$C$33-'Supuestos'!$C$34))-((IF((IF('Supuestos'!$C$13=0,0,'Supuestos'!$C$10/'Supuestos'!$C$13))=0,0,'Supuestos'!$C$8/(IF('Supuestos'!$C$13=0,0,'Supuestos'!$C$10/'Supuestos'!$C$13))))*'Supuestos'!$C$35)-'Supuestos'!$C$36-'Supuestos'!$C$8) | D13: =(((((((IF((IF('Supuestos'!$C$13=0,0,'Supuestos'!$C$10/'Supuestos'!$C$13))=0,0,'Supuestos'!$C$8/(IF('Supuestos'!$C$13=0,0,'Supuestos'!$C$10/'Supuestos'!$C$13))))*'Supuestos'!$C$14)+(((IF((IF('Supuestos'!$C$13=0,0,'Supuestos'!$C$10/'Supuestos'!$C$13))=0,0,'Supuestos'!$C$8/(IF('Supuestos'!$C$13=0,0,'Supuestos'!$C$10/'Supuestos'!$C$13))))*'Supuestos'!$C$16)*'Supuestos'!$C$15))+((((((IF((IF('Supuestos'!$C$13=0,0,'Supuestos'!$C$10/'Supuestos'!$C$13))=0,0,'Supuestos'!$C$8/(IF('Supuestos'!$C$13=0,0,'Supuestos'!$C$10/'Supuestos'!$C$13))))*'Supuestos'!$C$20)*'Supuestos'!$C$25)+(((IF((IF('Supuestos'!$C$13=0,0,'Supuestos'!$C$10/'Supuestos'!$C$13))=0,0,'Supuestos'!$C$8/(IF('Supuestos'!$C$13=0,0,'Supuestos'!$C$10/'Supuestos'!$C$13))))*'Supuestos'!$C$21)*'Supuestos'!$C$26))*D$9)*$B13)+(((((((IF((IF('Supuestos'!$C$13=0,0,'Supuestos'!$C$10/'Supuestos'!$C$13))=0,0,'Supuestos'!$C$8/(IF('Supuestos'!$C$13=0,0,'Supuestos'!$C$10/'Supuestos'!$C$13))))*'Supuestos'!$C$20)*'Supuestos'!$C$25)+(((IF((IF('Supuestos'!$C$13=0,0,'Supuestos'!$C$10/'Supuestos'!$C$13))=0,0,'Supuestos'!$C$8/(IF('Supuestos'!$C$13=0,0,'Supuestos'!$C$10/'Supuestos'!$C$13))))*'Supuestos'!$C$21)*'Supuestos'!$C$26))*D$9)*'Supuestos'!$C$29)*'Supuestos'!$C$28))*('Supuestos'!$C$39+'Supuestos'!$C$40+'Supuestos'!$C$41))*(1-'Supuestos'!$C$32-'Supuestos'!$C$33-'Supuestos'!$C$34))-((IF((IF('Supuestos'!$C$13=0,0,'Supuestos'!$C$10/'Supuestos'!$C$13))=0,0,'Supuestos'!$C$8/(IF('Supuestos'!$C$13=0,0,'Supuestos'!$C$10/'Supuestos'!$C$13))))*'Supuestos'!$C$35)-'Supuestos'!$C$36-'Supuestos'!$C$8) | E13: =(((((((IF((IF('Supuestos'!$C$13=0,0,'Supuestos'!$C$10/'Supuestos'!$C$13))=0,0,'Supuestos'!$C$8/(IF('Supuestos'!$C$13=0,0,'Supuestos'!$C$10/'Supuestos'!$C$13))))*'Supuestos'!$C$14)+(((IF((IF('Supuestos'!$C$13=0,0,'Supuestos'!$C$10/'Supuestos'!$C$13))=0,0,'Supuestos'!$C$8/(IF('Supuestos'!$C$13=0,0,'Supuestos'!$C$10/'Supuestos'!$C$13))))*'Supuestos'!$C$16)*'Supuestos'!$C$15))+((((((IF((IF('Supuestos'!$C$13=0,0,'Supuestos'!$C$10/'Supuestos'!$C$13))=0,0,'Supuestos'!$C$8/(IF('Supuestos'!$C$13=0,0,'Supuestos'!$C$10/'Supuestos'!$C$13))))*'Supuestos'!$C$20)*'Supuestos'!$C$25)+(((IF((IF('Supuestos'!$C$13=0,0,'Supuestos'!$C$10/'Supuestos'!$C$13))=0,0,'Supuestos'!$C$8/(IF('Supuestos'!$C$13=0,0,'Supuestos'!$C$10/'Supuestos'!$C$13))))*'Supuestos'!$C$21)*'Supuestos'!$C$26))*E$9)*$B13)+(((((((IF((IF('Supuestos'!$C$13=0,0,'Supuestos'!$C$10/'Supuestos'!$C$13))=0,0,'Supuestos'!$C$8/(IF('Supuestos'!$C$13=0,0,'Supuestos'!$C$10/'Supuestos'!$C$13))))*'Supuestos'!$C$20)*'Supuestos'!$C$25)+(((IF((IF('Supuestos'!$C$13=0,0,'Supuestos'!$C$10/'Supuestos'!$C$13))=0,0,'Supuestos'!$C$8/(IF('Supuestos'!$C$13=0,0,'Supuestos'!$C$10/'Supuestos'!$C$13))))*'Supuestos'!$C$21)*'Supuestos'!$C$26))*E$9)*'Supuestos'!$C$29)*'Supuestos'!$C$28))*('Supuestos'!$C$39+'Supuestos'!$C$40+'Supuestos'!$C$41))*(1-'Supuestos'!$C$32-'Supuestos'!$C$33-'Supuestos'!$C$34))-((IF((IF('Supuestos'!$C$13=0,0,'Supuestos'!$C$10/'Supuestos'!$C$13))=0,0,'Supuestos'!$C$8/(IF('Supuestos'!$C$13=0,0,'Supuestos'!$C$10/'Supuestos'!$C$13))))*'Supuestos'!$C$35)-'Supuestos'!$C$36-'Supuestos'!$C$8) | F13: =(((((((IF((IF('Supuestos'!$C$13=0,0,'Supuestos'!$C$10/'Supuestos'!$C$13))=0,0,'Supuestos'!$C$8/(IF('Supuestos'!$C$13=0,0,'Supuestos'!$C$10/'Supuestos'!$C$13))))*'Supuestos'!$C$14)+(((IF((IF('Supuestos'!$C$13=0,0,'Supuestos'!$C$10/'Supuestos'!$C$13))=0,0,'Supuestos'!$C$8/(IF('Supuestos'!$C$13=0,0,'Supuestos'!$C$10/'Supuestos'!$C$13))))*'Supuestos'!$C$16)*'Supuestos'!$C$15))+((((((IF((IF('Supuestos'!$C$13=0,0,'Supuestos'!$C$10/'Supuestos'!$C$13))=0,0,'Supuestos'!$C$8/(IF('Supuestos'!$C$13=0,0,'Supuestos'!$C$10/'Supuestos'!$C$13))))*'Supuestos'!$C$20)*'Supuestos'!$C$25)+(((IF((IF('Supuestos'!$C$13=0,0,'Supuestos'!$C$10/'Supuestos'!$C$13))=0,0,'Supuestos'!$C$8/(IF('Supuestos'!$C$13=0,0,'Supuestos'!$C$10/'Supuestos'!$C$13))))*'Supuestos'!$C$21)*'Supuestos'!$C$26))*F$9)*$B13)+(((((((IF((IF('Supuestos'!$C$13=0,0,'Supuestos'!$C$10/'Supuestos'!$C$13))=0,0,'Supuestos'!$C$8/(IF('Supuestos'!$C$13=0,0,'Supuestos'!$C$10/'Supuestos'!$C$13))))*'Supuestos'!$C$20)*'Supuestos'!$C$25)+(((IF((IF('Supuestos'!$C$13=0,0,'Supuestos'!$C$10/'Supuestos'!$C$13))=0,0,'Supuestos'!$C$8/(IF('Supuestos'!$C$13=0,0,'Supuestos'!$C$10/'Supuestos'!$C$13))))*'Supuestos'!$C$21)*'Supuestos'!$C$26))*F$9)*'Supuestos'!$C$29)*'Supuestos'!$C$28))*('Supuestos'!$C$39+'Supuestos'!$C$40+'Supuestos'!$C$41))*(1-'Supuestos'!$C$32-'Supuestos'!$C$33-'Supuestos'!$C$34))-((IF((IF('Supuestos'!$C$13=0,0,'Supuestos'!$C$10/'Supuestos'!$C$13))=0,0,'Supuestos'!$C$8/(IF('Supuestos'!$C$13=0,0,'Supuestos'!$C$10/'Supuestos'!$C$13))))*'Supuestos'!$C$35)-'Supuestos'!$C$36-'Supuestos'!$C$8) | G13: =(((((((IF((IF('Supuestos'!$C$13=0,0,'Supuestos'!$C$10/'Supuestos'!$C$13))=0,0,'Supuestos'!$C$8/(IF('Supuestos'!$C$13=0,0,'Supuestos'!$C$10/'Supuestos'!$C$13))))*'Supuestos'!$C$14)+(((IF((IF('Supuestos'!$C$13=0,0,'Supuestos'!$C$10/'Supuestos'!$C$13))=0,0,'Supuestos'!$C$8/(IF('Supuestos'!$C$13=0,0,'Supuestos'!$C$10/'Supuestos'!$C$13))))*'Supuestos'!$C$16)*'Supuestos'!$C$15))+((((((IF((IF('Supuestos'!$C$13=0,0,'Supuestos'!$C$10/'Supuestos'!$C$13))=0,0,'Supuestos'!$C$8/(IF('Supuestos'!$C$13=0,0,'Supuestos'!$C$10/'Supuestos'!$C$13))))*'Supuestos'!$C$20)*'Supuestos'!$C$25)+(((IF((IF('Supuestos'!$C$13=0,0,'Supuestos'!$C$10/'Supuestos'!$C$13))=0,0,'Supuestos'!$C$8/(IF('Supuestos'!$C$13=0,0,'Supuestos'!$C$10/'Supuestos'!$C$13))))*'Supuestos'!$C$21)*'Supuestos'!$C$26))*G$9)*$B13)+(((((((IF((IF('Supuestos'!$C$13=0,0,'Supuestos'!$C$10/'Supuestos'!$C$13))=0,0,'Supuestos'!$C$8/(IF('Supuestos'!$C$13=0,0,'Supuestos'!$C$10/'Supuestos'!$C$13))))*'Supuestos'!$C$20)*'Supuestos'!$C$25)+(((IF((IF('Supuestos'!$C$13=0,0,'Supuestos'!$C$10/'Supuestos'!$C$13))=0,0,'Supuestos'!$C$8/(IF('Supuestos'!$C$13=0,0,'Supuestos'!$C$10/'Supuestos'!$C$13))))*'Supuestos'!$C$21)*'Supuestos'!$C$26))*G$9)*'Supuestos'!$C$29)*'Supuestos'!$C$28))*('Supuestos'!$C$39+'Supuestos'!$C$40+'Supuestos'!$C$41))*(1-'Supuestos'!$C$32-'Supuestos'!$C$33-'Supuestos'!$C$34))-((IF((IF('Supuestos'!$C$13=0,0,'Supuestos'!$C$10/'Supuestos'!$C$13))=0,0,'Supuestos'!$C$8/(IF('Supuestos'!$C$13=0,0,'Supuestos'!$C$10/'Supuestos'!$C$13))))*'Supuestos'!$C$35)-'Supuestos'!$C$36-'Supuestos'!$C$8)
B14: 1997 | C14: =(((((((IF((IF('Supuestos'!$C$13=0,0,'Supuestos'!$C$10/'Supuestos'!$C$13))=0,0,'Supuestos'!$C$8/(IF('Supuestos'!$C$13=0,0,'Supuestos'!$C$10/'Supuestos'!$C$13))))*'Supuestos'!$C$14)+(((IF((IF('Supuestos'!$C$13=0,0,'Supuestos'!$C$10/'Supuestos'!$C$13))=0,0,'Supuestos'!$C$8/(IF('Supuestos'!$C$13=0,0,'Supuestos'!$C$10/'Supuestos'!$C$13))))*'Supuestos'!$C$16)*'Supuestos'!$C$15))+((((((IF((IF('Supuestos'!$C$13=0,0,'Supuestos'!$C$10/'Supuestos'!$C$13))=0,0,'Supuestos'!$C$8/(IF('Supuestos'!$C$13=0,0,'Supuestos'!$C$10/'Supuestos'!$C$13))))*'Supuestos'!$C$20)*'Supuestos'!$C$25)+(((IF((IF('Supuestos'!$C$13=0,0,'Supuestos'!$C$10/'Supuestos'!$C$13))=0,0,'Supuestos'!$C$8/(IF('Supuestos'!$C$13=0,0,'Supuestos'!$C$10/'Supuestos'!$C$13))))*'Supuestos'!$C$21)*'Supuestos'!$C$26))*C$9)*$B14)+(((((((IF((IF('Supuestos'!$C$13=0,0,'Supuestos'!$C$10/'Supuestos'!$C$13))=0,0,'Supuestos'!$C$8/(IF('Supuestos'!$C$13=0,0,'Supuestos'!$C$10/'Supuestos'!$C$13))))*'Supuestos'!$C$20)*'Supuestos'!$C$25)+(((IF((IF('Supuestos'!$C$13=0,0,'Supuestos'!$C$10/'Supuestos'!$C$13))=0,0,'Supuestos'!$C$8/(IF('Supuestos'!$C$13=0,0,'Supuestos'!$C$10/'Supuestos'!$C$13))))*'Supuestos'!$C$21)*'Supuestos'!$C$26))*C$9)*'Supuestos'!$C$29)*'Supuestos'!$C$28))*('Supuestos'!$C$39+'Supuestos'!$C$40+'Supuestos'!$C$41))*(1-'Supuestos'!$C$32-'Supuestos'!$C$33-'Supuestos'!$C$34))-((IF((IF('Supuestos'!$C$13=0,0,'Supuestos'!$C$10/'Supuestos'!$C$13))=0,0,'Supuestos'!$C$8/(IF('Supuestos'!$C$13=0,0,'Supuestos'!$C$10/'Supuestos'!$C$13))))*'Supuestos'!$C$35)-'Supuestos'!$C$36-'Supuestos'!$C$8) | D14: =(((((((IF((IF('Supuestos'!$C$13=0,0,'Supuestos'!$C$10/'Supuestos'!$C$13))=0,0,'Supuestos'!$C$8/(IF('Supuestos'!$C$13=0,0,'Supuestos'!$C$10/'Supuestos'!$C$13))))*'Supuestos'!$C$14)+(((IF((IF('Supuestos'!$C$13=0,0,'Supuestos'!$C$10/'Supuestos'!$C$13))=0,0,'Supuestos'!$C$8/(IF('Supuestos'!$C$13=0,0,'Supuestos'!$C$10/'Supuestos'!$C$13))))*'Supuestos'!$C$16)*'Supuestos'!$C$15))+((((((IF((IF('Supuestos'!$C$13=0,0,'Supuestos'!$C$10/'Supuestos'!$C$13))=0,0,'Supuestos'!$C$8/(IF('Supuestos'!$C$13=0,0,'Supuestos'!$C$10/'Supuestos'!$C$13))))*'Supuestos'!$C$20)*'Supuestos'!$C$25)+(((IF((IF('Supuestos'!$C$13=0,0,'Supuestos'!$C$10/'Supuestos'!$C$13))=0,0,'Supuestos'!$C$8/(IF('Supuestos'!$C$13=0,0,'Supuestos'!$C$10/'Supuestos'!$C$13))))*'Supuestos'!$C$21)*'Supuestos'!$C$26))*D$9)*$B14)+(((((((IF((IF('Supuestos'!$C$13=0,0,'Supuestos'!$C$10/'Supuestos'!$C$13))=0,0,'Supuestos'!$C$8/(IF('Supuestos'!$C$13=0,0,'Supuestos'!$C$10/'Supuestos'!$C$13))))*'Supuestos'!$C$20)*'Supuestos'!$C$25)+(((IF((IF('Supuestos'!$C$13=0,0,'Supuestos'!$C$10/'Supuestos'!$C$13))=0,0,'Supuestos'!$C$8/(IF('Supuestos'!$C$13=0,0,'Supuestos'!$C$10/'Supuestos'!$C$13))))*'Supuestos'!$C$21)*'Supuestos'!$C$26))*D$9)*'Supuestos'!$C$29)*'Supuestos'!$C$28))*('Supuestos'!$C$39+'Supuestos'!$C$40+'Supuestos'!$C$41))*(1-'Supuestos'!$C$32-'Supuestos'!$C$33-'Supuestos'!$C$34))-((IF((IF('Supuestos'!$C$13=0,0,'Supuestos'!$C$10/'Supuestos'!$C$13))=0,0,'Supuestos'!$C$8/(IF('Supuestos'!$C$13=0,0,'Supuestos'!$C$10/'Supuestos'!$C$13))))*'Supuestos'!$C$35)-'Supuestos'!$C$36-'Supuestos'!$C$8) | E14: =(((((((IF((IF('Supuestos'!$C$13=0,0,'Supuestos'!$C$10/'Supuestos'!$C$13))=0,0,'Supuestos'!$C$8/(IF('Supuestos'!$C$13=0,0,'Supuestos'!$C$10/'Supuestos'!$C$13))))*'Supuestos'!$C$14)+(((IF((IF('Supuestos'!$C$13=0,0,'Supuestos'!$C$10/'Supuestos'!$C$13))=0,0,'Supuestos'!$C$8/(IF('Supuestos'!$C$13=0,0,'Supuestos'!$C$10/'Supuestos'!$C$13))))*'Supuestos'!$C$16)*'Supuestos'!$C$15))+((((((IF((IF('Supuestos'!$C$13=0,0,'Supuestos'!$C$10/'Supuestos'!$C$13))=0,0,'Supuestos'!$C$8/(IF('Supuestos'!$C$13=0,0,'Supuestos'!$C$10/'Supuestos'!$C$13))))*'Supuestos'!$C$20)*'Supuestos'!$C$25)+(((IF((IF('Supuestos'!$C$13=0,0,'Supuestos'!$C$10/'Supuestos'!$C$13))=0,0,'Supuestos'!$C$8/(IF('Supuestos'!$C$13=0,0,'Supuestos'!$C$10/'Supuestos'!$C$13))))*'Supuestos'!$C$21)*'Supuestos'!$C$26))*E$9)*$B14)+(((((((IF((IF('Supuestos'!$C$13=0,0,'Supuestos'!$C$10/'Supuestos'!$C$13))=0,0,'Supuestos'!$C$8/(IF('Supuestos'!$C$13=0,0,'Supuestos'!$C$10/'Supuestos'!$C$13))))*'Supuestos'!$C$20)*'Supuestos'!$C$25)+(((IF((IF('Supuestos'!$C$13=0,0,'Supuestos'!$C$10/'Supuestos'!$C$13))=0,0,'Supuestos'!$C$8/(IF('Supuestos'!$C$13=0,0,'Supuestos'!$C$10/'Supuestos'!$C$13))))*'Supuestos'!$C$21)*'Supuestos'!$C$26))*E$9)*'Supuestos'!$C$29)*'Supuestos'!$C$28))*('Supuestos'!$C$39+'Supuestos'!$C$40+'Supuestos'!$C$41))*(1-'Supuestos'!$C$32-'Supuestos'!$C$33-'Supuestos'!$C$34))-((IF((IF('Supuestos'!$C$13=0,0,'Supuestos'!$C$10/'Supuestos'!$C$13))=0,0,'Supuestos'!$C$8/(IF('Supuestos'!$C$13=0,0,'Supuestos'!$C$10/'Supuestos'!$C$13))))*'Supuestos'!$C$35)-'Supuestos'!$C$36-'Supuestos'!$C$8) | F14: =(((((((IF((IF('Supuestos'!$C$13=0,0,'Supuestos'!$C$10/'Supuestos'!$C$13))=0,0,'Supuestos'!$C$8/(IF('Supuestos'!$C$13=0,0,'Supuestos'!$C$10/'Supuestos'!$C$13))))*'Supuestos'!$C$14)+(((IF((IF('Supuestos'!$C$13=0,0,'Supuestos'!$C$10/'Supuestos'!$C$13))=0,0,'Supuestos'!$C$8/(IF('Supuestos'!$C$13=0,0,'Supuestos'!$C$10/'Supuestos'!$C$13))))*'Supuestos'!$C$16)*'Supuestos'!$C$15))+((((((IF((IF('Supuestos'!$C$13=0,0,'Supuestos'!$C$10/'Supuestos'!$C$13))=0,0,'Supuestos'!$C$8/(IF('Supuestos'!$C$13=0,0,'Supuestos'!$C$10/'Supuestos'!$C$13))))*'Supuestos'!$C$20)*'Supuestos'!$C$25)+(((IF((IF('Supuestos'!$C$13=0,0,'Supuestos'!$C$10/'Supuestos'!$C$13))=0,0,'Supuestos'!$C$8/(IF('Supuestos'!$C$13=0,0,'Supuestos'!$C$10/'Supuestos'!$C$13))))*'Supuestos'!$C$21)*'Supuestos'!$C$26))*F$9)*$B14)+(((((((IF((IF('Supuestos'!$C$13=0,0,'Supuestos'!$C$10/'Supuestos'!$C$13))=0,0,'Supuestos'!$C$8/(IF('Supuestos'!$C$13=0,0,'Supuestos'!$C$10/'Supuestos'!$C$13))))*'Supuestos'!$C$20)*'Supuestos'!$C$25)+(((IF((IF('Supuestos'!$C$13=0,0,'Supuestos'!$C$10/'Supuestos'!$C$13))=0,0,'Supuestos'!$C$8/(IF('Supuestos'!$C$13=0,0,'Supuestos'!$C$10/'Supuestos'!$C$13))))*'Supuestos'!$C$21)*'Supuestos'!$C$26))*F$9)*'Supuestos'!$C$29)*'Supuestos'!$C$28))*('Supuestos'!$C$39+'Supuestos'!$C$40+'Supuestos'!$C$41))*(1-'Supuestos'!$C$32-'Supuestos'!$C$33-'Supuestos'!$C$34))-((IF((IF('Supuestos'!$C$13=0,0,'Supuestos'!$C$10/'Supuestos'!$C$13))=0,0,'Supuestos'!$C$8/(IF('Supuestos'!$C$13=0,0,'Supuestos'!$C$10/'Supuestos'!$C$13))))*'Supuestos'!$C$35)-'Supuestos'!$C$36-'Supuestos'!$C$8) | G14: =(((((((IF((IF('Supuestos'!$C$13=0,0,'Supuestos'!$C$10/'Supuestos'!$C$13))=0,0,'Supuestos'!$C$8/(IF('Supuestos'!$C$13=0,0,'Supuestos'!$C$10/'Supuestos'!$C$13))))*'Supuestos'!$C$14)+(((IF((IF('Supuestos'!$C$13=0,0,'Supuestos'!$C$10/'Supuestos'!$C$13))=0,0,'Supuestos'!$C$8/(IF('Supuestos'!$C$13=0,0,'Supuestos'!$C$10/'Supuestos'!$C$13))))*'Supuestos'!$C$16)*'Supuestos'!$C$15))+((((((IF((IF('Supuestos'!$C$13=0,0,'Supuestos'!$C$10/'Supuestos'!$C$13))=0,0,'Supuestos'!$C$8/(IF('Supuestos'!$C$13=0,0,'Supuestos'!$C$10/'Supuestos'!$C$13))))*'Supuestos'!$C$20)*'Supuestos'!$C$25)+(((IF((IF('Supuestos'!$C$13=0,0,'Supuestos'!$C$10/'Supuestos'!$C$13))=0,0,'Supuestos'!$C$8/(IF('Supuestos'!$C$13=0,0,'Supuestos'!$C$10/'Supuestos'!$C$13))))*'Supuestos'!$C$21)*'Supuestos'!$C$26))*G$9)*$B14)+(((((((IF((IF('Supuestos'!$C$13=0,0,'Supuestos'!$C$10/'Supuestos'!$C$13))=0,0,'Supuestos'!$C$8/(IF('Supuestos'!$C$13=0,0,'Supuestos'!$C$10/'Supuestos'!$C$13))))*'Supuestos'!$C$20)*'Supuestos'!$C$25)+(((IF((IF('Supuestos'!$C$13=0,0,'Supuestos'!$C$10/'Supuestos'!$C$13))=0,0,'Supuestos'!$C$8/(IF('Supuestos'!$C$13=0,0,'Supuestos'!$C$10/'Supuestos'!$C$13))))*'Supuestos'!$C$21)*'Supuestos'!$C$26))*G$9)*'Supuestos'!$C$29)*'Supuestos'!$C$28))*('Supuestos'!$C$39+'Supuestos'!$C$40+'Supuestos'!$C$41))*(1-'Supuestos'!$C$32-'Supuestos'!$C$33-'Supuestos'!$C$34))-((IF((IF('Supuestos'!$C$13=0,0,'Supuestos'!$C$10/'Supuestos'!$C$13))=0,0,'Supuestos'!$C$8/(IF('Supuestos'!$C$13=0,0,'Supuestos'!$C$10/'Supuestos'!$C$13))))*'Supuestos'!$C$35)-'Supuestos'!$C$36-'Supuestos'!$C$8)
B17: Costo por entrada × % de asistentes en vivo que solicitan → ganancia del lanzamiento
B18: Hasta cuánto pagar por cada entrada según lo que mueve el evento.
B19: Costo por entrada ↓ / % en vivo que solicita → | C19: 0.08 | D19: 0.12 | E19: 0.16 | F19: 0.2 | G19: 0.25
B20: 8 | C20: =(((((((IF($B20=0,0,'Supuestos'!$C$8/$B20))*'Supuestos'!$C$14)+(((IF($B20=0,0,'Supuestos'!$C$8/$B20))*'Supuestos'!$C$16)*'Supuestos'!$C$15))+((((((IF($B20=0,0,'Supuestos'!$C$8/$B20))*'Supuestos'!$C$20)*C$19)+(((IF($B20=0,0,'Supuestos'!$C$8/$B20))*'Supuestos'!$C$21)*'Supuestos'!$C$26))*'Supuestos'!$C$27)*'Supuestos'!$C$24)+(((((((IF($B20=0,0,'Supuestos'!$C$8/$B20))*'Supuestos'!$C$20)*C$19)+(((IF($B20=0,0,'Supuestos'!$C$8/$B20))*'Supuestos'!$C$21)*'Supuestos'!$C$26))*'Supuestos'!$C$27)*'Supuestos'!$C$29)*'Supuestos'!$C$28))*('Supuestos'!$C$39+'Supuestos'!$C$40+'Supuestos'!$C$41))*(1-'Supuestos'!$C$32-'Supuestos'!$C$33-'Supuestos'!$C$34))-((IF($B20=0,0,'Supuestos'!$C$8/$B20))*'Supuestos'!$C$35)-'Supuestos'!$C$36-'Supuestos'!$C$8) | D20: =(((((((IF($B20=0,0,'Supuestos'!$C$8/$B20))*'Supuestos'!$C$14)+(((IF($B20=0,0,'Supuestos'!$C$8/$B20))*'Supuestos'!$C$16)*'Supuestos'!$C$15))+((((((IF($B20=0,0,'Supuestos'!$C$8/$B20))*'Supuestos'!$C$20)*D$19)+(((IF($B20=0,0,'Supuestos'!$C$8/$B20))*'Supuestos'!$C$21)*'Supuestos'!$C$26))*'Supuestos'!$C$27)*'Supuestos'!$C$24)+(((((((IF($B20=0,0,'Supuestos'!$C$8/$B20))*'Supuestos'!$C$20)*D$19)+(((IF($B20=0,0,'Supuestos'!$C$8/$B20))*'Supuestos'!$C$21)*'Supuestos'!$C$26))*'Supuestos'!$C$27)*'Supuestos'!$C$29)*'Supuestos'!$C$28))*('Supuestos'!$C$39+'Supuestos'!$C$40+'Supuestos'!$C$41))*(1-'Supuestos'!$C$32-'Supuestos'!$C$33-'Supuestos'!$C$34))-((IF($B20=0,0,'Supuestos'!$C$8/$B20))*'Supuestos'!$C$35)-'Supuestos'!$C$36-'Supuestos'!$C$8) | E20: =(((((((IF($B20=0,0,'Supuestos'!$C$8/$B20))*'Supuestos'!$C$14)+(((IF($B20=0,0,'Supuestos'!$C$8/$B20))*'Supuestos'!$C$16)*'Supuestos'!$C$15))+((((((IF($B20=0,0,'Supuestos'!$C$8/$B20))*'Supuestos'!$C$20)*E$19)+(((IF($B20=0,0,'Supuestos'!$C$8/$B20))*'Supuestos'!$C$21)*'Supuestos'!$C$26))*'Supuestos'!$C$27)*'Supuestos'!$C$24)+(((((((IF($B20=0,0,'Supuestos'!$C$8/$B20))*'Supuestos'!$C$20)*E$19)+(((IF($B20=0,0,'Supuestos'!$C$8/$B20))*'Supuestos'!$C$21)*'Supuestos'!$C$26))*'Supuestos'!$C$27)*'Supuestos'!$C$29)*'Supuestos'!$C$28))*('Supuestos'!$C$39+'Supuestos'!$C$40+'Supuestos'!$C$41))*(1-'Supuestos'!$C$32-'Supuestos'!$C$33-'Supuestos'!$C$34))-((IF($B20=0,0,'Supuestos'!$C$8/$B20))*'Supuestos'!$C$35)-'Supuestos'!$C$36-'Supuestos'!$C$8) | F20: =(((((((IF($B20=0,0,'Supuestos'!$C$8/$B20))*'Supuestos'!$C$14)+(((IF($B20=0,0,'Supuestos'!$C$8/$B20))*'Supuestos'!$C$16)*'Supuestos'!$C$15))+((((((IF($B20=0,0,'Supuestos'!$C$8/$B20))*'Supuestos'!$C$20)*F$19)+(((IF($B20=0,0,'Supuestos'!$C$8/$B20))*'Supuestos'!$C$21)*'Supuestos'!$C$26))*'Supuestos'!$C$27)*'Supuestos'!$C$24)+(((((((IF($B20=0,0,'Supuestos'!$C$8/$B20))*'Supuestos'!$C$20)*F$19)+(((IF($B20=0,0,'Supuestos'!$C$8/$B20))*'Supuestos'!$C$21)*'Supuestos'!$C$26))*'Supuestos'!$C$27)*'Supuestos'!$C$29)*'Supuestos'!$C$28))*('Supuestos'!$C$39+'Supuestos'!$C$40+'Supuestos'!$C$41))*(1-'Supuestos'!$C$32-'Supuestos'!$C$33-'Supuestos'!$C$34))-((IF($B20=0,0,'Supuestos'!$C$8/$B20))*'Supuestos'!$C$35)-'Supuestos'!$C$36-'Supuestos'!$C$8) | G20: =(((((((IF($B20=0,0,'Supuestos'!$C$8/$B20))*'Supuestos'!$C$14)+(((IF($B20=0,0,'Supuestos'!$C$8/$B20))*'Supuestos'!$C$16)*'Supuestos'!$C$15))+((((((IF($B20=0,0,'Supuestos'!$C$8/$B20))*'Supuestos'!$C$20)*G$19)+(((IF($B20=0,0,'Supuestos'!$C$8/$B20))*'Supuestos'!$C$21)*'Supuestos'!$C$26))*'Supuestos'!$C$27)*'Supuestos'!$C$24)+(((((((IF($B20=0,0,'Supuestos'!$C$8/$B20))*'Supuestos'!$C$20)*G$19)+(((IF($B20=0,0,'Supuestos'!$C$8/$B20))*'Supuestos'!$C$21)*'Supuestos'!$C$26))*'Supuestos'!$C$27)*'Supuestos'!$C$29)*'Supuestos'!$C$28))*('Supuestos'!$C$39+'Supuestos'!$C$40+'Supuestos'!$C$41))*(1-'Supuestos'!$C$32-'Supuestos'!$C$33-'Supuestos'!$C$34))-((IF($B20=0,0,'Supuestos'!$C$8/$B20))*'Supuestos'!$C$35)-'Supuestos'!$C$36-'Supuestos'!$C$8)
B21: 12 | C21: =(((((((IF($B21=0,0,'Supuestos'!$C$8/$B21))*'Supuestos'!$C$14)+(((IF($B21=0,0,'Supuestos'!$C$8/$B21))*'Supuestos'!$C$16)*'Supuestos'!$C$15))+((((((IF($B21=0,0,'Supuestos'!$C$8/$B21))*'Supuestos'!$C$20)*C$19)+(((IF($B21=0,0,'Supuestos'!$C$8/$B21))*'Supuestos'!$C$21)*'Supuestos'!$C$26))*'Supuestos'!$C$27)*'Supuestos'!$C$24)+(((((((IF($B21=0,0,'Supuestos'!$C$8/$B21))*'Supuestos'!$C$20)*C$19)+(((IF($B21=0,0,'Supuestos'!$C$8/$B21))*'Supuestos'!$C$21)*'Supuestos'!$C$26))*'Supuestos'!$C$27)*'Supuestos'!$C$29)*'Supuestos'!$C$28))*('Supuestos'!$C$39+'Supuestos'!$C$40+'Supuestos'!$C$41))*(1-'Supuestos'!$C$32-'Supuestos'!$C$33-'Supuestos'!$C$34))-((IF($B21=0,0,'Supuestos'!$C$8/$B21))*'Supuestos'!$C$35)-'Supuestos'!$C$36-'Supuestos'!$C$8) | D21: =(((((((IF($B21=0,0,'Supuestos'!$C$8/$B21))*'Supuestos'!$C$14)+(((IF($B21=0,0,'Supuestos'!$C$8/$B21))*'Supuestos'!$C$16)*'Supuestos'!$C$15))+((((((IF($B21=0,0,'Supuestos'!$C$8/$B21))*'Supuestos'!$C$20)*D$19)+(((IF($B21=0,0,'Supuestos'!$C$8/$B21))*'Supuestos'!$C$21)*'Supuestos'!$C$26))*'Supuestos'!$C$27)*'Supuestos'!$C$24)+(((((((IF($B21=0,0,'Supuestos'!$C$8/$B21))*'Supuestos'!$C$20)*D$19)+(((IF($B21=0,0,'Supuestos'!$C$8/$B21))*'Supuestos'!$C$21)*'Supuestos'!$C$26))*'Supuestos'!$C$27)*'Supuestos'!$C$29)*'Supuestos'!$C$28))*('Supuestos'!$C$39+'Supuestos'!$C$40+'Supuestos'!$C$41))*(1-'Supuestos'!$C$32-'Supuestos'!$C$33-'Supuestos'!$C$34))-((IF($B21=0,0,'Supuestos'!$C$8/$B21))*'Supuestos'!$C$35)-'Supuestos'!$C$36-'Supuestos'!$C$8) | E21: =(((((((IF($B21=0,0,'Supuestos'!$C$8/$B21))*'Supuestos'!$C$14)+(((IF($B21=0,0,'Supuestos'!$C$8/$B21))*'Supuestos'!$C$16)*'Supuestos'!$C$15))+((((((IF($B21=0,0,'Supuestos'!$C$8/$B21))*'Supuestos'!$C$20)*E$19)+(((IF($B21=0,0,'Supuestos'!$C$8/$B21))*'Supuestos'!$C$21)*'Supuestos'!$C$26))*'Supuestos'!$C$27)*'Supuestos'!$C$24)+(((((((IF($B21=0,0,'Supuestos'!$C$8/$B21))*'Supuestos'!$C$20)*E$19)+(((IF($B21=0,0,'Supuestos'!$C$8/$B21))*'Supuestos'!$C$21)*'Supuestos'!$C$26))*'Supuestos'!$C$27)*'Supuestos'!$C$29)*'Supuestos'!$C$28))*('Supuestos'!$C$39+'Supuestos'!$C$40+'Supuestos'!$C$41))*(1-'Supuestos'!$C$32-'Supuestos'!$C$33-'Supuestos'!$C$34))-((IF($B21=0,0,'Supuestos'!$C$8/$B21))*'Supuestos'!$C$35)-'Supuestos'!$C$36-'Supuestos'!$C$8) | F21: =(((((((IF($B21=0,0,'Supuestos'!$C$8/$B21))*'Supuestos'!$C$14)+(((IF($B21=0,0,'Supuestos'!$C$8/$B21))*'Supuestos'!$C$16)*'Supuestos'!$C$15))+((((((IF($B21=0,0,'Supuestos'!$C$8/$B21))*'Supuestos'!$C$20)*F$19)+(((IF($B21=0,0,'Supuestos'!$C$8/$B21))*'Supuestos'!$C$21)*'Supuestos'!$C$26))*'Supuestos'!$C$27)*'Supuestos'!$C$24)+(((((((IF($B21=0,0,'Supuestos'!$C$8/$B21))*'Supuestos'!$C$20)*F$19)+(((IF($B21=0,0,'Supuestos'!$C$8/$B21))*'Supuestos'!$C$21)*'Supuestos'!$C$26))*'Supuestos'!$C$27)*'Supuestos'!$C$29)*'Supuestos'!$C$28))*('Supuestos'!$C$39+'Supuestos'!$C$40+'Supuestos'!$C$41))*(1-'Supuestos'!$C$32-'Supuestos'!$C$33-'Supuestos'!$C$34))-((IF($B21=0,0,'Supuestos'!$C$8/$B21))*'Supuestos'!$C$35)-'Supuestos'!$C$36-'Supuestos'!$C$8) | G21: =(((((((IF($B21=0,0,'Supuestos'!$C$8/$B21))*'Supuestos'!$C$14)+(((IF($B21=0,0,'Supuestos'!$C$8/$B21))*'Supuestos'!$C$16)*'Supuestos'!$C$15))+((((((IF($B21=0,0,'Supuestos'!$C$8/$B21))*'Supuestos'!$C$20)*G$19)+(((IF($B21=0,0,'Supuestos'!$C$8/$B21))*'Supuestos'!$C$21)*'Supuestos'!$C$26))*'Supuestos'!$C$27)*'Supuestos'!$C$24)+(((((((IF($B21=0,0,'Supuestos'!$C$8/$B21))*'Supuestos'!$C$20)*G$19)+(((IF($B21=0,0,'Supuestos'!$C$8/$B21))*'Supuestos'!$C$21)*'Supuestos'!$C$26))*'Supuestos'!$C$27)*'Supuestos'!$C$29)*'Supuestos'!$C$28))*('Supuestos'!$C$39+'Supuestos'!$C$40+'Supuestos'!$C$41))*(1-'Supuestos'!$C$32-'Supuestos'!$C$33-'Supuestos'!$C$34))-((IF($B21=0,0,'Supuestos'!$C$8/$B21))*'Supuestos'!$C$35)-'Supuestos'!$C$36-'Supuestos'!$C$8)
B22: 15 | C22: =(((((((IF($B22=0,0,'Supuestos'!$C$8/$B22))*'Supuestos'!$C$14)+(((IF($B22=0,0,'Supuestos'!$C$8/$B22))*'Supuestos'!$C$16)*'Supuestos'!$C$15))+((((((IF($B22=0,0,'Supuestos'!$C$8/$B22))*'Supuestos'!$C$20)*C$19)+(((IF($B22=0,0,'Supuestos'!$C$8/$B22))*'Supuestos'!$C$21)*'Supuestos'!$C$26))*'Supuestos'!$C$27)*'Supuestos'!$C$24)+(((((((IF($B22=0,0,'Supuestos'!$C$8/$B22))*'Supuestos'!$C$20)*C$19)+(((IF($B22=0,0,'Supuestos'!$C$8/$B22))*'Supuestos'!$C$21)*'Supuestos'!$C$26))*'Supuestos'!$C$27)*'Supuestos'!$C$29)*'Supuestos'!$C$28))*('Supuestos'!$C$39+'Supuestos'!$C$40+'Supuestos'!$C$41))*(1-'Supuestos'!$C$32-'Supuestos'!$C$33-'Supuestos'!$C$34))-((IF($B22=0,0,'Supuestos'!$C$8/$B22))*'Supuestos'!$C$35)-'Supuestos'!$C$36-'Supuestos'!$C$8) | D22: =(((((((IF($B22=0,0,'Supuestos'!$C$8/$B22))*'Supuestos'!$C$14)+(((IF($B22=0,0,'Supuestos'!$C$8/$B22))*'Supuestos'!$C$16)*'Supuestos'!$C$15))+((((((IF($B22=0,0,'Supuestos'!$C$8/$B22))*'Supuestos'!$C$20)*D$19)+(((IF($B22=0,0,'Supuestos'!$C$8/$B22))*'Supuestos'!$C$21)*'Supuestos'!$C$26))*'Supuestos'!$C$27)*'Supuestos'!$C$24)+(((((((IF($B22=0,0,'Supuestos'!$C$8/$B22))*'Supuestos'!$C$20)*D$19)+(((IF($B22=0,0,'Supuestos'!$C$8/$B22))*'Supuestos'!$C$21)*'Supuestos'!$C$26))*'Supuestos'!$C$27)*'Supuestos'!$C$29)*'Supuestos'!$C$28))*('Supuestos'!$C$39+'Supuestos'!$C$40+'Supuestos'!$C$41))*(1-'Supuestos'!$C$32-'Supuestos'!$C$33-'Supuestos'!$C$34))-((IF($B22=0,0,'Supuestos'!$C$8/$B22))*'Supuestos'!$C$35)-'Supuestos'!$C$36-'Supuestos'!$C$8) | E22: =(((((((IF($B22=0,0,'Supuestos'!$C$8/$B22))*'Supuestos'!$C$14)+(((IF($B22=0,0,'Supuestos'!$C$8/$B22))*'Supuestos'!$C$16)*'Supuestos'!$C$15))+((((((IF($B22=0,0,'Supuestos'!$C$8/$B22))*'Supuestos'!$C$20)*E$19)+(((IF($B22=0,0,'Supuestos'!$C$8/$B22))*'Supuestos'!$C$21)*'Supuestos'!$C$26))*'Supuestos'!$C$27)*'Supuestos'!$C$24)+(((((((IF($B22=0,0,'Supuestos'!$C$8/$B22))*'Supuestos'!$C$20)*E$19)+(((IF($B22=0,0,'Supuestos'!$C$8/$B22))*'Supuestos'!$C$21)*'Supuestos'!$C$26))*'Supuestos'!$C$27)*'Supuestos'!$C$29)*'Supuestos'!$C$28))*('Supuestos'!$C$39+'Supuestos'!$C$40+'Supuestos'!$C$41))*(1-'Supuestos'!$C$32-'Supuestos'!$C$33-'Supuestos'!$C$34))-((IF($B22=0,0,'Supuestos'!$C$8/$B22))*'Supuestos'!$C$35)-'Supuestos'!$C$36-'Supuestos'!$C$8) | F22: =(((((((IF($B22=0,0,'Supuestos'!$C$8/$B22))*'Supuestos'!$C$14)+(((IF($B22=0,0,'Supuestos'!$C$8/$B22))*'Supuestos'!$C$16)*'Supuestos'!$C$15))+((((((IF($B22=0,0,'Supuestos'!$C$8/$B22))*'Supuestos'!$C$20)*F$19)+(((IF($B22=0,0,'Supuestos'!$C$8/$B22))*'Supuestos'!$C$21)*'Supuestos'!$C$26))*'Supuestos'!$C$27)*'Supuestos'!$C$24)+(((((((IF($B22=0,0,'Supuestos'!$C$8/$B22))*'Supuestos'!$C$20)*F$19)+(((IF($B22=0,0,'Supuestos'!$C$8/$B22))*'Supuestos'!$C$21)*'Supuestos'!$C$26))*'Supuestos'!$C$27)*'Supuestos'!$C$29)*'Supuestos'!$C$28))*('Supuestos'!$C$39+'Supuestos'!$C$40+'Supuestos'!$C$41))*(1-'Supuestos'!$C$32-'Supuestos'!$C$33-'Supuestos'!$C$34))-((IF($B22=0,0,'Supuestos'!$C$8/$B22))*'Supuestos'!$C$35)-'Supuestos'!$C$36-'Supuestos'!$C$8) | G22: =(((((((IF($B22=0,0,'Supuestos'!$C$8/$B22))*'Supuestos'!$C$14)+(((IF($B22=0,0,'Supuestos'!$C$8/$B22))*'Supuestos'!$C$16)*'Supuestos'!$C$15))+((((((IF($B22=0,0,'Supuestos'!$C$8/$B22))*'Supuestos'!$C$20)*G$19)+(((IF($B22=0,0,'Supuestos'!$C$8/$B22))*'Supuestos'!$C$21)*'Supuestos'!$C$26))*'Supuestos'!$C$27)*'Supuestos'!$C$24)+(((((((IF($B22=0,0,'Supuestos'!$C$8/$B22))*'Supuestos'!$C$20)*G$19)+(((IF($B22=0,0,'Supuestos'!$C$8/$B22))*'Supuestos'!$C$21)*'Supuestos'!$C$26))*'Supuestos'!$C$27)*'Supuestos'!$C$29)*'Supuestos'!$C$28))*('Supuestos'!$C$39+'Supuestos'!$C$40+'Supuestos'!$C$41))*(1-'Supuestos'!$C$32-'Supuestos'!$C$33-'Supuestos'!$C$34))-((IF($B22=0,0,'Supuestos'!$C$8/$B22))*'Supuestos'!$C$35)-'Supuestos'!$C$36-'Supuestos'!$C$8)
B23: 20 | C23: =(((((((IF($B23=0,0,'Supuestos'!$C$8/$B23))*'Supuestos'!$C$14)+(((IF($B23=0,0,'Supuestos'!$C$8/$B23))*'Supuestos'!$C$16)*'Supuestos'!$C$15))+((((((IF($B23=0,0,'Supuestos'!$C$8/$B23))*'Supuestos'!$C$20)*C$19)+(((IF($B23=0,0,'Supuestos'!$C$8/$B23))*'Supuestos'!$C$21)*'Supuestos'!$C$26))*'Supuestos'!$C$27)*'Supuestos'!$C$24)+(((((((IF($B23=0,0,'Supuestos'!$C$8/$B23))*'Supuestos'!$C$20)*C$19)+(((IF($B23=0,0,'Supuestos'!$C$8/$B23))*'Supuestos'!$C$21)*'Supuestos'!$C$26))*'Supuestos'!$C$27)*'Supuestos'!$C$29)*'Supuestos'!$C$28))*('Supuestos'!$C$39+'Supuestos'!$C$40+'Supuestos'!$C$41))*(1-'Supuestos'!$C$32-'Supuestos'!$C$33-'Supuestos'!$C$34))-((IF($B23=0,0,'Supuestos'!$C$8/$B23))*'Supuestos'!$C$35)-'Supuestos'!$C$36-'Supuestos'!$C$8) | D23: =(((((((IF($B23=0,0,'Supuestos'!$C$8/$B23))*'Supuestos'!$C$14)+(((IF($B23=0,0,'Supuestos'!$C$8/$B23))*'Supuestos'!$C$16)*'Supuestos'!$C$15))+((((((IF($B23=0,0,'Supuestos'!$C$8/$B23))*'Supuestos'!$C$20)*D$19)+(((IF($B23=0,0,'Supuestos'!$C$8/$B23))*'Supuestos'!$C$21)*'Supuestos'!$C$26))*'Supuestos'!$C$27)*'Supuestos'!$C$24)+(((((((IF($B23=0,0,'Supuestos'!$C$8/$B23))*'Supuestos'!$C$20)*D$19)+(((IF($B23=0,0,'Supuestos'!$C$8/$B23))*'Supuestos'!$C$21)*'Supuestos'!$C$26))*'Supuestos'!$C$27)*'Supuestos'!$C$29)*'Supuestos'!$C$28))*('Supuestos'!$C$39+'Supuestos'!$C$40+'Supuestos'!$C$41))*(1-'Supuestos'!$C$32-'Supuestos'!$C$33-'Supuestos'!$C$34))-((IF($B23=0,0,'Supuestos'!$C$8/$B23))*'Supuestos'!$C$35)-'Supuestos'!$C$36-'Supuestos'!$C$8) | E23: =(((((((IF($B23=0,0,'Supuestos'!$C$8/$B23))*'Supuestos'!$C$14)+(((IF($B23=0,0,'Supuestos'!$C$8/$B23))*'Supuestos'!$C$16)*'Supuestos'!$C$15))+((((((IF($B23=0,0,'Supuestos'!$C$8/$B23))*'Supuestos'!$C$20)*E$19)+(((IF($B23=0,0,'Supuestos'!$C$8/$B23))*'Supuestos'!$C$21)*'Supuestos'!$C$26))*'Supuestos'!$C$27)*'Supuestos'!$C$24)+(((((((IF($B23=0,0,'Supuestos'!$C$8/$B23))*'Supuestos'!$C$20)*E$19)+(((IF($B23=0,0,'Supuestos'!$C$8/$B23))*'Supuestos'!$C$21)*'Supuestos'!$C$26))*'Supuestos'!$C$27)*'Supuestos'!$C$29)*'Supuestos'!$C$28))*('Supuestos'!$C$39+'Supuestos'!$C$40+'Supuestos'!$C$41))*(1-'Supuestos'!$C$32-'Supuestos'!$C$33-'Supuestos'!$C$34))-((IF($B23=0,0,'Supuestos'!$C$8/$B23))*'Supuestos'!$C$35)-'Supuestos'!$C$36-'Supuestos'!$C$8) | F23: =(((((((IF($B23=0,0,'Supuestos'!$C$8/$B23))*'Supuestos'!$C$14)+(((IF($B23=0,0,'Supuestos'!$C$8/$B23))*'Supuestos'!$C$16)*'Supuestos'!$C$15))+((((((IF($B23=0,0,'Supuestos'!$C$8/$B23))*'Supuestos'!$C$20)*F$19)+(((IF($B23=0,0,'Supuestos'!$C$8/$B23))*'Supuestos'!$C$21)*'Supuestos'!$C$26))*'Supuestos'!$C$27)*'Supuestos'!$C$24)+(((((((IF($B23=0,0,'Supuestos'!$C$8/$B23))*'Supuestos'!$C$20)*F$19)+(((IF($B23=0,0,'Supuestos'!$C$8/$B23))*'Supuestos'!$C$21)*'Supuestos'!$C$26))*'Supuestos'!$C$27)*'Supuestos'!$C$29)*'Supuestos'!$C$28))*('Supuestos'!$C$39+'Supuestos'!$C$40+'Supuestos'!$C$41))*(1-'Supuestos'!$C$32-'Supuestos'!$C$33-'Supuestos'!$C$34))-((IF($B23=0,0,'Supuestos'!$C$8/$B23))*'Supuestos'!$C$35)-'Supuestos'!$C$36-'Supuestos'!$C$8) | G23: =(((((((IF($B23=0,0,'Supuestos'!$C$8/$B23))*'Supuestos'!$C$14)+(((IF($B23=0,0,'Supuestos'!$C$8/$B23))*'Supuestos'!$C$16)*'Supuestos'!$C$15))+((((((IF($B23=0,0,'Supuestos'!$C$8/$B23))*'Supuestos'!$C$20)*G$19)+(((IF($B23=0,0,'Supuestos'!$C$8/$B23))*'Supuestos'!$C$21)*'Supuestos'!$C$26))*'Supuestos'!$C$27)*'Supuestos'!$C$24)+(((((((IF($B23=0,0,'Supuestos'!$C$8/$B23))*'Supuestos'!$C$20)*G$19)+(((IF($B23=0,0,'Supuestos'!$C$8/$B23))*'Supuestos'!$C$21)*'Supuestos'!$C$26))*'Supuestos'!$C$27)*'Supuestos'!$C$29)*'Supuestos'!$C$28))*('Supuestos'!$C$39+'Supuestos'!$C$40+'Supuestos'!$C$41))*(1-'Supuestos'!$C$32-'Supuestos'!$C$33-'Supuestos'!$C$34))-((IF($B23=0,0,'Supuestos'!$C$8/$B23))*'Supuestos'!$C$35)-'Supuestos'!$C$36-'Supuestos'!$C$8)
B24: 30 | C24: =(((((((IF($B24=0,0,'Supuestos'!$C$8/$B24))*'Supuestos'!$C$14)+(((IF($B24=0,0,'Supuestos'!$C$8/$B24))*'Supuestos'!$C$16)*'Supuestos'!$C$15))+((((((IF($B24=0,0,'Supuestos'!$C$8/$B24))*'Supuestos'!$C$20)*C$19)+(((IF($B24=0,0,'Supuestos'!$C$8/$B24))*'Supuestos'!$C$21)*'Supuestos'!$C$26))*'Supuestos'!$C$27)*'Supuestos'!$C$24)+(((((((IF($B24=0,0,'Supuestos'!$C$8/$B24))*'Supuestos'!$C$20)*C$19)+(((IF($B24=0,0,'Supuestos'!$C$8/$B24))*'Supuestos'!$C$21)*'Supuestos'!$C$26))*'Supuestos'!$C$27)*'Supuestos'!$C$29)*'Supuestos'!$C$28))*('Supuestos'!$C$39+'Supuestos'!$C$40+'Supuestos'!$C$41))*(1-'Supuestos'!$C$32-'Supuestos'!$C$33-'Supuestos'!$C$34))-((IF($B24=0,0,'Supuestos'!$C$8/$B24))*'Supuestos'!$C$35)-'Supuestos'!$C$36-'Supuestos'!$C$8) | D24: =(((((((IF($B24=0,0,'Supuestos'!$C$8/$B24))*'Supuestos'!$C$14)+(((IF($B24=0,0,'Supuestos'!$C$8/$B24))*'Supuestos'!$C$16)*'Supuestos'!$C$15))+((((((IF($B24=0,0,'Supuestos'!$C$8/$B24))*'Supuestos'!$C$20)*D$19)+(((IF($B24=0,0,'Supuestos'!$C$8/$B24))*'Supuestos'!$C$21)*'Supuestos'!$C$26))*'Supuestos'!$C$27)*'Supuestos'!$C$24)+(((((((IF($B24=0,0,'Supuestos'!$C$8/$B24))*'Supuestos'!$C$20)*D$19)+(((IF($B24=0,0,'Supuestos'!$C$8/$B24))*'Supuestos'!$C$21)*'Supuestos'!$C$26))*'Supuestos'!$C$27)*'Supuestos'!$C$29)*'Supuestos'!$C$28))*('Supuestos'!$C$39+'Supuestos'!$C$40+'Supuestos'!$C$41))*(1-'Supuestos'!$C$32-'Supuestos'!$C$33-'Supuestos'!$C$34))-((IF($B24=0,0,'Supuestos'!$C$8/$B24))*'Supuestos'!$C$35)-'Supuestos'!$C$36-'Supuestos'!$C$8) | E24: =(((((((IF($B24=0,0,'Supuestos'!$C$8/$B24))*'Supuestos'!$C$14)+(((IF($B24=0,0,'Supuestos'!$C$8/$B24))*'Supuestos'!$C$16)*'Supuestos'!$C$15))+((((((IF($B24=0,0,'Supuestos'!$C$8/$B24))*'Supuestos'!$C$20)*E$19)+(((IF($B24=0,0,'Supuestos'!$C$8/$B24))*'Supuestos'!$C$21)*'Supuestos'!$C$26))*'Supuestos'!$C$27)*'Supuestos'!$C$24)+(((((((IF($B24=0,0,'Supuestos'!$C$8/$B24))*'Supuestos'!$C$20)*E$19)+(((IF($B24=0,0,'Supuestos'!$C$8/$B24))*'Supuestos'!$C$21)*'Supuestos'!$C$26))*'Supuestos'!$C$27)*'Supuestos'!$C$29)*'Supuestos'!$C$28))*('Supuestos'!$C$39+'Supuestos'!$C$40+'Supuestos'!$C$41))*(1-'Supuestos'!$C$32-'Supuestos'!$C$33-'Supuestos'!$C$34))-((IF($B24=0,0,'Supuestos'!$C$8/$B24))*'Supuestos'!$C$35)-'Supuestos'!$C$36-'Supuestos'!$C$8) | F24: =(((((((IF($B24=0,0,'Supuestos'!$C$8/$B24))*'Supuestos'!$C$14)+(((IF($B24=0,0,'Supuestos'!$C$8/$B24))*'Supuestos'!$C$16)*'Supuestos'!$C$15))+((((((IF($B24=0,0,'Supuestos'!$C$8/$B24))*'Supuestos'!$C$20)*F$19)+(((IF($B24=0,0,'Supuestos'!$C$8/$B24))*'Supuestos'!$C$21)*'Supuestos'!$C$26))*'Supuestos'!$C$27)*'Supuestos'!$C$24)+(((((((IF($B24=0,0,'Supuestos'!$C$8/$B24))*'Supuestos'!$C$20)*F$19)+(((IF($B24=0,0,'Supuestos'!$C$8/$B24))*'Supuestos'!$C$21)*'Supuestos'!$C$26))*'Supuestos'!$C$27)*'Supuestos'!$C$29)*'Supuestos'!$C$28))*('Supuestos'!$C$39+'Supuestos'!$C$40+'Supuestos'!$C$41))*(1-'Supuestos'!$C$32-'Supuestos'!$C$33-'Supuestos'!$C$34))-((IF($B24=0,0,'Supuestos'!$C$8/$B24))*'Supuestos'!$C$35)-'Supuestos'!$C$36-'Supuestos'!$C$8) | G24: =(((((((IF($B24=0,0,'Supuestos'!$C$8/$B24))*'Supuestos'!$C$14)+(((IF($B24=0,0,'Supuestos'!$C$8/$B24))*'Supuestos'!$C$16)*'Supuestos'!$C$15))+((((((IF($B24=0,0,'Supuestos'!$C$8/$B24))*'Supuestos'!$C$20)*G$19)+(((IF($B24=0,0,'Supuestos'!$C$8/$B24))*'Supuestos'!$C$21)*'Supuestos'!$C$26))*'Supuestos'!$C$27)*'Supuestos'!$C$24)+(((((((IF($B24=0,0,'Supuestos'!$C$8/$B24))*'Supuestos'!$C$20)*G$19)+(((IF($B24=0,0,'Supuestos'!$C$8/$B24))*'Supuestos'!$C$21)*'Supuestos'!$C$26))*'Supuestos'!$C$27)*'Supuestos'!$C$29)*'Supuestos'!$C$28))*('Supuestos'!$C$39+'Supuestos'!$C$40+'Supuestos'!$C$41))*(1-'Supuestos'!$C$32-'Supuestos'!$C$33-'Supuestos'!$C$34))-((IF($B24=0,0,'Supuestos'!$C$8/$B24))*'Supuestos'!$C$35)-'Supuestos'!$C$36-'Supuestos'!$C$8)
B25: 40 | C25: =(((((((IF($B25=0,0,'Supuestos'!$C$8/$B25))*'Supuestos'!$C$14)+(((IF($B25=0,0,'Supuestos'!$C$8/$B25))*'Supuestos'!$C$16)*'Supuestos'!$C$15))+((((((IF($B25=0,0,'Supuestos'!$C$8/$B25))*'Supuestos'!$C$20)*C$19)+(((IF($B25=0,0,'Supuestos'!$C$8/$B25))*'Supuestos'!$C$21)*'Supuestos'!$C$26))*'Supuestos'!$C$27)*'Supuestos'!$C$24)+(((((((IF($B25=0,0,'Supuestos'!$C$8/$B25))*'Supuestos'!$C$20)*C$19)+(((IF($B25=0,0,'Supuestos'!$C$8/$B25))*'Supuestos'!$C$21)*'Supuestos'!$C$26))*'Supuestos'!$C$27)*'Supuestos'!$C$29)*'Supuestos'!$C$28))*('Supuestos'!$C$39+'Supuestos'!$C$40+'Supuestos'!$C$41))*(1-'Supuestos'!$C$32-'Supuestos'!$C$33-'Supuestos'!$C$34))-((IF($B25=0,0,'Supuestos'!$C$8/$B25))*'Supuestos'!$C$35)-'Supuestos'!$C$36-'Supuestos'!$C$8) | D25: =(((((((IF($B25=0,0,'Supuestos'!$C$8/$B25))*'Supuestos'!$C$14)+(((IF($B25=0,0,'Supuestos'!$C$8/$B25))*'Supuestos'!$C$16)*'Supuestos'!$C$15))+((((((IF($B25=0,0,'Supuestos'!$C$8/$B25))*'Supuestos'!$C$20)*D$19)+(((IF($B25=0,0,'Supuestos'!$C$8/$B25))*'Supuestos'!$C$21)*'Supuestos'!$C$26))*'Supuestos'!$C$27)*'Supuestos'!$C$24)+(((((((IF($B25=0,0,'Supuestos'!$C$8/$B25))*'Supuestos'!$C$20)*D$19)+(((IF($B25=0,0,'Supuestos'!$C$8/$B25))*'Supuestos'!$C$21)*'Supuestos'!$C$26))*'Supuestos'!$C$27)*'Supuestos'!$C$29)*'Supuestos'!$C$28))*('Supuestos'!$C$39+'Supuestos'!$C$40+'Supuestos'!$C$41))*(1-'Supuestos'!$C$32-'Supuestos'!$C$33-'Supuestos'!$C$34))-((IF($B25=0,0,'Supuestos'!$C$8/$B25))*'Supuestos'!$C$35)-'Supuestos'!$C$36-'Supuestos'!$C$8) | E25: =(((((((IF($B25=0,0,'Supuestos'!$C$8/$B25))*'Supuestos'!$C$14)+(((IF($B25=0,0,'Supuestos'!$C$8/$B25))*'Supuestos'!$C$16)*'Supuestos'!$C$15))+((((((IF($B25=0,0,'Supuestos'!$C$8/$B25))*'Supuestos'!$C$20)*E$19)+(((IF($B25=0,0,'Supuestos'!$C$8/$B25))*'Supuestos'!$C$21)*'Supuestos'!$C$26))*'Supuestos'!$C$27)*'Supuestos'!$C$24)+(((((((IF($B25=0,0,'Supuestos'!$C$8/$B25))*'Supuestos'!$C$20)*E$19)+(((IF($B25=0,0,'Supuestos'!$C$8/$B25))*'Supuestos'!$C$21)*'Supuestos'!$C$26))*'Supuestos'!$C$27)*'Supuestos'!$C$29)*'Supuestos'!$C$28))*('Supuestos'!$C$39+'Supuestos'!$C$40+'Supuestos'!$C$41))*(1-'Supuestos'!$C$32-'Supuestos'!$C$33-'Supuestos'!$C$34))-((IF($B25=0,0,'Supuestos'!$C$8/$B25))*'Supuestos'!$C$35)-'Supuestos'!$C$36-'Supuestos'!$C$8) | F25: =(((((((IF($B25=0,0,'Supuestos'!$C$8/$B25))*'Supuestos'!$C$14)+(((IF($B25=0,0,'Supuestos'!$C$8/$B25))*'Supuestos'!$C$16)*'Supuestos'!$C$15))+((((((IF($B25=0,0,'Supuestos'!$C$8/$B25))*'Supuestos'!$C$20)*F$19)+(((IF($B25=0,0,'Supuestos'!$C$8/$B25))*'Supuestos'!$C$21)*'Supuestos'!$C$26))*'Supuestos'!$C$27)*'Supuestos'!$C$24)+(((((((IF($B25=0,0,'Supuestos'!$C$8/$B25))*'Supuestos'!$C$20)*F$19)+(((IF($B25=0,0,'Supuestos'!$C$8/$B25))*'Supuestos'!$C$21)*'Supuestos'!$C$26))*'Supuestos'!$C$27)*'Supuestos'!$C$29)*'Supuestos'!$C$28))*('Supuestos'!$C$39+'Supuestos'!$C$40+'Supuestos'!$C$41))*(1-'Supuestos'!$C$32-'Supuestos'!$C$33-'Supuestos'!$C$34))-((IF($B25=0,0,'Supuestos'!$C$8/$B25))*'Supuestos'!$C$35)-'Supuestos'!$C$36-'Supuestos'!$C$8) | G25: =(((((((IF($B25=0,0,'Supuestos'!$C$8/$B25))*'Supuestos'!$C$14)+(((IF($B25=0,0,'Supuestos'!$C$8/$B25))*'Supuestos'!$C$16)*'Supuestos'!$C$15))+((((((IF($B25=0,0,'Supuestos'!$C$8/$B25))*'Supuestos'!$C$20)*G$19)+(((IF($B25=0,0,'Supuestos'!$C$8/$B25))*'Supuestos'!$C$21)*'Supuestos'!$C$26))*'Supuestos'!$C$27)*'Supuestos'!$C$24)+(((((((IF($B25=0,0,'Supuestos'!$C$8/$B25))*'Supuestos'!$C$20)*G$19)+(((IF($B25=0,0,'Supuestos'!$C$8/$B25))*'Supuestos'!$C$21)*'Supuestos'!$C$26))*'Supuestos'!$C$27)*'Supuestos'!$C$29)*'Supuestos'!$C$28))*('Supuestos'!$C$39+'Supuestos'!$C$40+'Supuestos'!$C$41))*(1-'Supuestos'!$C$32-'Supuestos'!$C$33-'Supuestos'!$C$34))-((IF($B25=0,0,'Supuestos'!$C$8/$B25))*'Supuestos'!$C$35)-'Supuestos'!$C$36-'Supuestos'!$C$8)
B28: Cuánto invertir para una facturación objetivo por lanzamiento, según el ROAS que querés
B29: Inversión = facturación ÷ ROAS. Debajo: cuántas entradas hacen falta y cuánto podés pagar por cada una.
B30: Facturación objetivo ↓ / ROAS objetivo → | C30: 1.5 | D30: 2 | E30: 2.5 | F30: 3 | G30: 4
B31: 5000 | C31: =$B31/C$30 | D31: =$B31/D$30 | E31: =$B31/E$30 | F31: =$B31/F$30 | G31: =$B31/G$30
B32: 10000 | C32: =$B32/C$30 | D32: =$B32/D$30 | E32: =$B32/E$30 | F32: =$B32/F$30 | G32: =$B32/G$30
B33: 20000 | C33: =$B33/C$30 | D33: =$B33/D$30 | E33: =$B33/E$30 | F33: =$B33/F$30 | G33: =$B33/G$30
B34: 30000 | C34: =$B34/C$30 | D34: =$B34/D$30 | E34: =$B34/E$30 | F34: =$B34/F$30 | G34: =$B34/G$30
B35: 50000 | C35: =$B35/C$30 | D35: =$B35/D$30 | E35: =$B35/E$30 | F35: =$B35/F$30 | G35: =$B35/G$30
B36: Cantidad de entradas necesaria para esa facturación
B37: =$B31 | C37: =IF('Modelo'!$C$36=0,"inalcanzable",$B31/'Modelo'!$C$36)
B38: =$B32 | C38: =IF('Modelo'!$C$36=0,"inalcanzable",$B32/'Modelo'!$C$36)
B39: =$B33 | C39: =IF('Modelo'!$C$36=0,"inalcanzable",$B33/'Modelo'!$C$36)
B40: =$B34 | C40: =IF('Modelo'!$C$36=0,"inalcanzable",$B34/'Modelo'!$C$36)
B41: =$B35 | C41: =IF('Modelo'!$C$36=0,"inalcanzable",$B35/'Modelo'!$C$36)
B43: Costo máximo por entrada para cumplir cada ROAS (sobre facturado)
C44: 1.5 | D44: 2 | E44: 2.5 | F44: 3 | G44: 4
B45: Costo máximo (facturado por unidad ÷ ROAS) | C45: =IF(C44=0,0,'Modelo'!$C$36/C44) | D45: =IF(D44=0,0,'Modelo'!$C$36/D44) | E45: =IF(E44=0,0,'Modelo'!$C$36/E44) | F45: =IF(F44=0,0,'Modelo'!$C$36/F44) | G45: =IF(G44=0,0,'Modelo'!$C$36/G44)
B46: Sobre cash neto, el techo real está en Modelo (ya descuenta comisiones y reembolsos).
B49: Guardarraíl: el ROAS mínimo que tiene que dar cada nivel de inversión para que subir valga la pena
B50: Parte de tu inversión y tu ROAS actuales. Cada dólar extra tiene que devolver al menos 1,3 neto. Si al subir un escalón el ROAS real queda por debajo del mínimo de esa fila, volvé al escalón anterior.
B51: Nivel de inversión | C51: Inversión del período | D51: ROAS mínimo (cash neto) | E51: Ganancia mínima
B52: actual | C52: ='Supuestos'!$C$8*1.0 | D52: =IF(C52=0,0,('Supuestos'!$C$8*'Modelo'!$C$46+1.3*(C52-'Supuestos'!$C$8))/C52) | E52: =C52*(D52-1)
B53: × 1.25 | C53: ='Supuestos'!$C$8*1.25 | D53: =IF(C53=0,0,('Supuestos'!$C$8*'Modelo'!$C$46+1.3*(C53-'Supuestos'!$C$8))/C53) | E53: =C53*(D53-1)
B54: × 1.5 | C54: ='Supuestos'!$C$8*1.5 | D54: =IF(C54=0,0,('Supuestos'!$C$8*'Modelo'!$C$46+1.3*(C54-'Supuestos'!$C$8))/C54) | E54: =C54*(D54-1)
B55: × 2 | C55: ='Supuestos'!$C$8*2.0 | D55: =IF(C55=0,0,('Supuestos'!$C$8*'Modelo'!$C$46+1.3*(C55-'Supuestos'!$C$8))/C55) | E55: =C55*(D55-1)
B56: × 3 | C56: ='Supuestos'!$C$8*3.0 | D56: =IF(C56=0,0,('Supuestos'!$C$8*'Modelo'!$C$46+1.3*(C56-'Supuestos'!$C$8))/C56) | E56: =C56*(D56-1)

Sheet Sensibilidad
B1: © Jesús Tassarolo · TooAudience · youtube.com/@JesusTassaroloSinFiltro · uso personal; no redistribuir modificado
B2: Sensibilidad: qué palanca mueve más la ganancia
B3: Cada fila mejora una sola variable un 10 % (o baja un costo un 10 %) y recalcula la ganancia del período. El ranking dice qué conviene trabajar primero.
B5: Palanca | C5: Cambio | D5: Ganancia nueva | E5: Diferencia | F5: Dif. % | G5: Ranking
B6: Ganancia del período con los supuestos actuales | D6: ='Modelo'!$C$44
B7: Costo por visita 10 % más barato | C7: −10 % | D7: =(((((((IF((IF('Supuestos'!$C$13=0,0,('Supuestos'!$C$10*0.9)/'Supuestos'!$C$13))=0,0,'Supuestos'!$C$8/(IF('Supuestos'!$C$13=0,0,('Supuestos'!$C$10*0.9)/'Supuestos'!$C$13))))*'Supuestos'!$C$14)+(((IF((IF('Supuestos'!$C$13=0,0,('Supuestos'!$C$10*0.9)/'Supuestos'!$C$13))=0,0,'Supuestos'!$C$8/(IF('Supuestos'!$C$13=0,0,('Supuestos'!$C$10*0.9)/'Supuestos'!$C$13))))*'Supuestos'!$C$16)*'Supuestos'!$C$15))+((((((IF((IF('Supuestos'!$C$13=0,0,('Supuestos'!$C$10*0.9)/'Supuestos'!$C$13))=0,0,'Supuestos'!$C$8/(IF('Supuestos'!$C$13=0,0,('Supuestos'!$C$10*0.9)/'Supuestos'!$C$13))))*'Supuestos'!$C$20)*'Supuestos'!$C$25)+(((IF((IF('Supuestos'!$C$13=0,0,('Supuestos'!$C$10*0.9)/'Supuestos'!$C$13))=0,0,'Supuestos'!$C$8/(IF('Supuestos'!$C$13=0,0,('Supuestos'!$C$10*0.9)/'Supuestos'!$C$13))))*'Supuestos'!$C$21)*'Supuestos'!$C$26))*'Supuestos'!$C$27)*'Supuestos'!$C$24)+(((((((IF((IF('Supuestos'!$C$13=0,0,('Supuestos'!$C$10*0.9)/'Supuestos'!$C$13))=0,0,'Supuestos'!$C$8/(IF('Supuestos'!$C$13=0,0,('Supuestos'!$C$10*0.9)/'Supuestos'!$C$13))))*'Supuestos'!$C$20)*'Supuestos'!$C$25)+(((IF((IF('Supuestos'!$C$13=0,0,('Supuestos'!$C$10*0.9)/'Supuestos'!$C$13))=0,0,'Supuestos'!$C$8/(IF('Supuestos'!$C$13=0,0,('Supuestos'!$C$10*0.9)/'Supuestos'!$C$13))))*'Supuestos'!$C$21)*'Supuestos'!$C$26))*'Supuestos'!$C$27)*'Supuestos'!$C$29)*'Supuestos'!$C$28))*('Supuestos'!$C$39+'Supuestos'!$C$40+'Supuestos'!$C$41))*(1-'Supuestos'!$C$32-'Supuestos'!$C$33-'Supuestos'!$C$34))-((IF((IF('Supuestos'!$C$13=0,0,('Supuestos'!$C$10*0.9)/'Supuestos'!$C$13))=0,0,'Supuestos'!$C$8/(IF('Supuestos'!$C$13=0,0,('Supuestos'!$C$10*0.9)/'Supuestos'!$C$13))))*'Supuestos'!$C$35)-'Supuestos'!$C$36-'Supuestos'!$C$8) | E7: =D7-$D$6 | F7: =IF($D$6=0,0,E7/ABS($D$6)) | G7: =RANK(E7,$E$7:$E$15)
B8: Página de la entrada 10 % más conversión | C8: +10 % | D8: =(((((((IF((IF(('Supuestos'!$C$13*1.1)=0,0,'Supuestos'!$C$10/('Supuestos'!$C$13*1.1)))=0,0,'Supuestos'!$C$8/(IF(('Supuestos'!$C$13*1.1)=0,0,'Supuestos'!$C$10/('Supuestos'!$C$13*1.1)))))*'Supuestos'!$C$14)+(((IF((IF(('Supuestos'!$C$13*1.1)=0,0,'Supuestos'!$C$10/('Supuestos'!$C$13*1.1)))=0,0,'Supuestos'!$C$8/(IF(('Supuestos'!$C$13*1.1)=0,0,'Supuestos'!$C$10/('Supuestos'!$C$13*1.1)))))*'Supuestos'!$C$16)*'Supuestos'!$C$15))+((((((IF((IF(('Supuestos'!$C$13*1.1)=0,0,'Supuestos'!$C$10/('Supuestos'!$C$13*1.1)))=0,0,'Supuestos'!$C$8/(IF(('Supuestos'!$C$13*1.1)=0,0,'Supuestos'!$C$10/('Supuestos'!$C$13*1.1)))))*'Supuestos'!$C$20)*'Supuestos'!$C$25)+(((IF((IF(('Supuestos'!$C$13*1.1)=0,0,'Supuestos'!$C$10/('Supuestos'!$C$13*1.1)))=0,0,'Supuestos'!$C$8/(IF(('Supuestos'!$C$13*1.1)=0,0,'Supuestos'!$C$10/('Supuestos'!$C$13*1.1)))))*'Supuestos'!$C$21)*'Supuestos'!$C$26))*'Supuestos'!$C$27)*'Supuestos'!$C$24)+(((((((IF((IF(('Supuestos'!$C$13*1.1)=0,0,'Supuestos'!$C$10/('Supuestos'!$C$13*1.1)))=0,0,'Supuestos'!$C$8/(IF(('Supuestos'!$C$13*1.1)=0,0,'Supuestos'!$C$10/('Supuestos'!$C$13*1.1)))))*'Supuestos'!$C$20)*'Supuestos'!$C$25)+(((IF((IF(('Supuestos'!$C$13*1.1)=0,0,'Supuestos'!$C$10/('Supuestos'!$C$13*1.1)))=0,0,'Supuestos'!$C$8/(IF(('Supuestos'!$C$13*1.1)=0,0,'Supuestos'!$C$10/('Supuestos'!$C$13*1.1)))))*'Supuestos'!$C$21)*'Supuestos'!$C$26))*'Supuestos'!$C$27)*'Supuestos'!$C$29)*'Supuestos'!$C$28))*('Supuestos'!$C$39+'Supuestos'!$C$40+'Supuestos'!$C$41))*(1-'Supuestos'!$C$32-'Supuestos'!$C$33-'Supuestos'!$C$34))-((IF((IF(('Supuestos'!$C$13*1.1)=0,0,'Supuestos'!$C$10/('Supuestos'!$C$13*1.1)))=0,0,'Supuestos'!$C$8/(IF(('Supuestos'!$C$13*1.1)=0,0,'Supuestos'!$C$10/('Supuestos'!$C$13*1.1)))))*'Supuestos'!$C$35)-'Supuestos'!$C$36-'Supuestos'!$C$8) | E8: =D8-$D$6 | F8: =IF($D$6=0,0,E8/ABS($D$6)) | G8: =RANK(E8,$E$7:$E$15)
B9: Precio de la entrada 10 % más alto (misma conversión) | C9: +10 % | D9: =(((((((IF((IF('Supuestos'!$C$13=0,0,'Supuestos'!$C$10/'Supuestos'!$C$13))=0,0,'Supuestos'!$C$8/(IF('Supuestos'!$C$13=0,0,'Supuestos'!$C$10/'Supuestos'!$C$13))))*('Supuestos'!$C$14*1.1))+(((IF((IF('Supuestos'!$C$13=0,0,'Supuestos'!$C$10/'Supuestos'!$C$13))=0,0,'Supuestos'!$C$8/(IF('Supuestos'!$C$13=0,0,'Supuestos'!$C$10/'Supuestos'!$C$13))))*'Supuestos'!$C$16)*'Supuestos'!$C$15))+((((((IF((IF('Supuestos'!$C$13=0,0,'Supuestos'!$C$10/'Supuestos'!$C$13))=0,0,'Supuestos'!$C$8/(IF('Supuestos'!$C$13=0,0,'Supuestos'!$C$10/'Supuestos'!$C$13))))*'Supuestos'!$C$20)*'Supuestos'!$C$25)+(((IF((IF('Supuestos'!$C$13=0,0,'Supuestos'!$C$10/'Supuestos'!$C$13))=0,0,'Supuestos'!$C$8/(IF('Supuestos'!$C$13=0,0,'Supuestos'!$C$10/'Supuestos'!$C$13))))*'Supuestos'!$C$21)*'Supuestos'!$C$26))*'Supuestos'!$C$27)*'Supuestos'!$C$24)+(((((((IF((IF('Supuestos'!$C$13=0,0,'Supuestos'!$C$10/'Supuestos'!$C$13))=0,0,'Supuestos'!$C$8/(IF('Supuestos'!$C$13=0,0,'Supuestos'!$C$10/'Supuestos'!$C$13))))*'Supuestos'!$C$20)*'Supuestos'!$C$25)+(((IF((IF('Supuestos'!$C$13=0,0,'Supuestos'!$C$10/'Supuestos'!$C$13))=0,0,'Supuestos'!$C$8/(IF('Supuestos'!$C$13=0,0,'Supuestos'!$C$10/'Supuestos'!$C$13))))*'Supuestos'!$C$21)*'Supuestos'!$C$26))*'Supuestos'!$C$27)*'Supuestos'!$C$29)*'Supuestos'!$C$28))*('Supuestos'!$C$39+'Supuestos'!$C$40+'Supuestos'!$C$41))*(1-'Supuestos'!$C$32-'Supuestos'!$C$33-'Supuestos'!$C$34))-((IF((IF('Supuestos'!$C$13=0,0,'Supuestos'!$C$10/'Supuestos'!$C$13))=0,0,'Supuestos'!$C$8/(IF('Supuestos'!$C$13=0,0,'Supuestos'!$C$10/'Supuestos'!$C$13))))*'Supuestos'!$C$35)-'Supuestos'!$C$36-'Supuestos'!$C$8) | E9: =D9-$D$6 | F9: =IF($D$6=0,0,E9/ABS($D$6)) | G9: =RANK(E9,$E$7:$E$15)
B10: Asistencia en vivo 10 % más alta | C10: +10 % | D10: =(((((((IF((IF('Supuestos'!$C$13=0,0,'Supuestos'!$C$10/'Supuestos'!$C$13))=0,0,'Supuestos'!$C$8/(IF('Supuestos'!$C$13=0,0,'Supuestos'!$C$10/'Supuestos'!$C$13))))*'Supuestos'!$C$14)+(((IF((IF('Supuestos'!$C$13=0,0,'Supuestos'!$C$10/'Supuestos'!$C$13))=0,0,'Supuestos'!$C$8/(IF('Supuestos'!$C$13=0,0,'Supuestos'!$C$10/'Supuestos'!$C$13))))*'Supuestos'!$C$16)*'Supuestos'!$C$15))+((((((IF((IF('Supuestos'!$C$13=0,0,'Supuestos'!$C$10/'Supuestos'!$C$13))=0,0,'Supuestos'!$C$8/(IF('Supuestos'!$C$13=0,0,'Supuestos'!$C$10/'Supuestos'!$C$13))))*('Supuestos'!$C$20*1.1))*'Supuestos'!$C$25)+(((IF((IF('Supuestos'!$C$13=0,0,'Supuestos'!$C$10/'Supuestos'!$C$13))=0,0,'Supuestos'!$C$8/(IF('Supuestos'!$C$13=0,0,'Supuestos'!$C$10/'Supuestos'!$C$13))))*'Supuestos'!$C$21)*'Supuestos'!$C$26))*'Supuestos'!$C$27)*'Supuestos'!$C$24)+(((((((IF((IF('Supuestos'!$C$13=0,0,'Supuestos'!$C$10/'Supuestos'!$C$13))=0,0,'Supuestos'!$C$8/(IF('Supuestos'!$C$13=0,0,'Supuestos'!$C$10/'Supuestos'!$C$13))))*('Supuestos'!$C$20*1.1))*'Supuestos'!$C$25)+(((IF((IF('Supuestos'!$C$13=0,0,'Supuestos'!$C$10/'Supuestos'!$C$13))=0,0,'Supuestos'!$C$8/(IF('Supuestos'!$C$13=0,0,'Supuestos'!$C$10/'Supuestos'!$C$13))))*'Supuestos'!$C$21)*'Supuestos'!$C$26))*'Supuestos'!$C$27)*'Supuestos'!$C$29)*'Supuestos'!$C$28))*('Supuestos'!$C$39+'Supuestos'!$C$40+'Supuestos'!$C$41))*(1-'Supuestos'!$C$32-'Supuestos'!$C$33-'Supuestos'!$C$34))-((IF((IF('Supuestos'!$C$13=0,0,'Supuestos'!$C$10/'Supuestos'!$C$13))=0,0,'Supuestos'!$C$8/(IF('Supuestos'!$C$13=0,0,'Supuestos'!$C$10/'Supuestos'!$C$13))))*'Supuestos'!$C$35)-'Supuestos'!$C$36-'Supuestos'!$C$8) | E10: =D10-$D$6 | F10: =IF($D$6=0,0,E10/ABS($D$6)) | G10: =RANK(E10,$E$7:$E$15)
B11: 10 % más asistentes en vivo que solicitan (oferta, pitch) | C11: +10 % | D11: =(((((((IF((IF('Supuestos'!$C$13=0,0,'Supuestos'!$C$10/'Supuestos'!$C$13))=0,0,'Supuestos'!$C$8/(IF('Supuestos'!$C$13=0,0,'Supuestos'!$C$10/'Supuestos'!$C$13))))*'Supuestos'!$C$14)+(((IF((IF('Supuestos'!$C$13=0,0,'Supuestos'!$C$10/'Supuestos'!$C$13))=0,0,'Supuestos'!$C$8/(IF('Supuestos'!$C$13=0,0,'Supuestos'!$C$10/'Supuestos'!$C$13))))*'Supuestos'!$C$16)*'Supuestos'!$C$15))+((((((IF((IF('Supuestos'!$C$13=0,0,'Supuestos'!$C$10/'Supuestos'!$C$13))=0,0,'Supuestos'!$C$8/(IF('Supuestos'!$C$13=0,0,'Supuestos'!$C$10/'Supuestos'!$C$13))))*'Supuestos'!$C$20)*('Supuestos'!$C$25*1.1))+(((IF((IF('Supuestos'!$C$13=0,0,'Supuestos'!$C$10/'Supuestos'!$C$13))=0,0,'Supuestos'!$C$8/(IF('Supuestos'!$C$13=0,0,'Supuestos'!$C$10/'Supuestos'!$C$13))))*'Supuestos'!$C$21)*'Supuestos'!$C$26))*'Supuestos'!$C$27)*'Supuestos'!$C$24)+(((((((IF((IF('Supuestos'!$C$13=0,0,'Supuestos'!$C$10/'Supuestos'!$C$13))=0,0,'Supuestos'!$C$8/(IF('Supuestos'!$C$13=0,0,'Supuestos'!$C$10/'Supuestos'!$C$13))))*'Supuestos'!$C$20)*('Supuestos'!$C$25*1.1))+(((IF((IF('Supuestos'!$C$13=0,0,'Supuestos'!$C$10/'Supuestos'!$C$13))=0,0,'Supuestos'!$C$8/(IF('Supuestos'!$C$13=0,0,'Supuestos'!$C$10/'Supuestos'!$C$13))))*'Supuestos'!$C$21)*'Supuestos'!$C$26))*'Supuestos'!$C$27)*'Supuestos'!$C$29)*'Supuestos'!$C$28))*('Supuestos'!$C$39+'Supuestos'!$C$40+'Supuestos'!$C$41))*(1-'Supuestos'!$C$32-'Supuestos'!$C$33-'Supuestos'!$C$34))-((IF((IF('Supuestos'!$C$13=0,0,'Supuestos'!$C$10/'Supuestos'!$C$13))=0,0,'Supuestos'!$C$8/(IF('Supuestos'!$C$13=0,0,'Supuestos'!$C$10/'Supuestos'!$C$13))))*'Supuestos'!$C$35)-'Supuestos'!$C$36-'Supuestos'!$C$8) | E11: =D11-$D$6 | F11: =IF($D$6=0,0,E11/ABS($D$6)) | G11: =RANK(E11,$E$7:$E$15)
B12: 10 % más solicitudes que terminan en compra (seguimiento, vendedor) | C12: +10 % | D12: =(((((((IF((IF('Supuestos'!$C$13=0,0,'Supuestos'!$C$10/'Supuestos'!$C$13))=0,0,'Supuestos'!$C$8/(IF('Supuestos'!$C$13=0,0,'Supuestos'!$C$10/'Supuestos'!$C$13))))*'Supuestos'!$C$14)+(((IF((IF('Supuestos'!$C$13=0,0,'Supuestos'!$C$10/'Supuestos'!$C$13))=0,0,'Supuestos'!$C$8/(IF('Supuestos'!$C$13=0,0,'Supuestos'!$C$10/'Supuestos'!$C$13))))*'Supuestos'!$C$16)*'Supuestos'!$C$15))+((((((IF((IF('Supuestos'!$C$13=0,0,'Supuestos'!$C$10/'Supuestos'!$C$13))=0,0,'Supuestos'!$C$8/(IF('Supuestos'!$C$13=0,0,'Supuestos'!$C$10/'Supuestos'!$C$13))))*'Supuestos'!$C$20)*'Supuestos'!$C$25)+(((IF((IF('Supuestos'!$C$13=0,0,'Supuestos'!$C$10/'Supuestos'!$C$13))=0,0,'Supuestos'!$C$8/(IF('Supuestos'!$C$13=0,0,'Supuestos'!$C$10/'Supuestos'!$C$13))))*'Supuestos'!$C$21)*'Supuestos'!$C$26))*('Supuestos'!$C$27*1.1))*'Supuestos'!$C$24)+(((((((IF((IF('Supuestos'!$C$13=0,0,'Supuestos'!$C$10/'Supuestos'!$C$13))=0,0,'Supuestos'!$C$8/(IF('Supuestos'!$C$13=0,0,'Supuestos'!$C$10/'Supuestos'!$C$13))))*'Supuestos'!$C$20)*'Supuestos'!$C$25)+(((IF((IF('Supuestos'!$C$13=0,0,'Supuestos'!$C$10/'Supuestos'!$C$13))=0,0,'Supuestos'!$C$8/(IF('Supuestos'!$C$13=0,0,'Supuestos'!$C$10/'Supuestos'!$C$13))))*'Supuestos'!$C$21)*'Supuestos'!$C$26))*('Supuestos'!$C$27*1.1))*'Supuestos'!$C$29)*'Supuestos'!$C$28))*('Supuestos'!$C$39+'Supuestos'!$C$40+'Supuestos'!$C$41))*(1-'Supuestos'!$C$32-'Supuestos'!$C$33-'Supuestos'!$C$34))-((IF((IF('Supuestos'!$C$13=0,0,'Supuestos'!$C$10/'Supuestos'!$C$13))=0,0,'Supuestos'!$C$8/(IF('Supuestos'!$C$13=0,0,'Supuestos'!$C$10/'Supuestos'!$C$13))))*'Supuestos'!$C$35)-'Supuestos'!$C$36-'Supuestos'!$C$8) | E12: =D12-$D$6 | F12: =IF($D$6=0,0,E12/ABS($D$6)) | G12: =RANK(E12,$E$7:$E$15)
B13: Precio de la oferta 10 % más alto (misma conversión) | C13: +10 % | D13: =(((((((IF((IF('Supuestos'!$C$13=0,0,'Supuestos'!$C$10/'Supuestos'!$C$13))=0,0,'Supuestos'!$C$8/(IF('Supuestos'!$C$13=0,0,'Supuestos'!$C$10/'Supuestos'!$C$13))))*'Supuestos'!$C$14)+(((IF((IF('Supuestos'!$C$13=0,0,'Supuestos'!$C$10/'Supuestos'!$C$13))=0,0,'Supuestos'!$C$8/(IF('Supuestos'!$C$13=0,0,'Supuestos'!$C$10/'Supuestos'!$C$13))))*'Supuestos'!$C$16)*'Supuestos'!$C$15))+((((((IF((IF('Supuestos'!$C$13=0,0,'Supuestos'!$C$10/'Supuestos'!$C$13))=0,0,'Supuestos'!$C$8/(IF('Supuestos'!$C$13=0,0,'Supuestos'!$C$10/'Supuestos'!$C$13))))*'Supuestos'!$C$20)*'Supuestos'!$C$25)+(((IF((IF('Supuestos'!$C$13=0,0,'Supuestos'!$C$10/'Supuestos'!$C$13))=0,0,'Supuestos'!$C$8/(IF('Supuestos'!$C$13=0,0,'Supuestos'!$C$10/'Supuestos'!$C$13))))*'Supuestos'!$C$21)*'Supuestos'!$C$26))*'Supuestos'!$C$27)*('Supuestos'!$C$24*1.1))+(((((((IF((IF('Supuestos'!$C$13=0,0,'Supuestos'!$C$10/'Supuestos'!$C$13))=0,0,'Supuestos'!$C$8/(IF('Supuestos'!$C$13=0,0,'Supuestos'!$C$10/'Supuestos'!$C$13))))*'Supuestos'!$C$20)*'Supuestos'!$C$25)+(((IF((IF('Supuestos'!$C$13=0,0,'Supuestos'!$C$10/'Supuestos'!$C$13))=0,0,'Supuestos'!$C$8/(IF('Supuestos'!$C$13=0,0,'Supuestos'!$C$10/'Supuestos'!$C$13))))*'Supuestos'!$C$21)*'Supuestos'!$C$26))*'Supuestos'!$C$27)*'Supuestos'!$C$29)*'Supuestos'!$C$28))*('Supuestos'!$C$39+'Supuestos'!$C$40+'Supuestos'!$C$41))*(1-'Supuestos'!$C$32-'Supuestos'!$C$33-'Supuestos'!$C$34))-((IF((IF('Supuestos'!$C$13=0,0,'Supuestos'!$C$10/'Supuestos'!$C$13))=0,0,'Supuestos'!$C$8/(IF('Supuestos'!$C$13=0,0,'Supuestos'!$C$10/'Supuestos'!$C$13))))*'Supuestos'!$C$35)-'Supuestos'!$C$36-'Supuestos'!$C$8) | E13: =D13-$D$6 | F13: =IF($D$6=0,0,E13/ABS($D$6)) | G13: =RANK(E13,$E$7:$E$15)
B14: Programa superior 10 % más tomado | C14: +10 % | D14: =(((((((IF((IF('Supuestos'!$C$13=0,0,'Supuestos'!$C$10/'Supuestos'!$C$13))=0,0,'Supuestos'!$C$8/(IF('Supuestos'!$C$13=0,0,'Supuestos'!$C$10/'Supuestos'!$C$13))))*'Supuestos'!$C$14)+(((IF((IF('Supuestos'!$C$13=0,0,'Supuestos'!$C$10/'Supuestos'!$C$13))=0,0,'Supuestos'!$C$8/(IF('Supuestos'!$C$13=0,0,'Supuestos'!$C$10/'Supuestos'!$C$13))))*'Supuestos'!$C$16)*'Supuestos'!$C$15))+((((((IF((IF('Supuestos'!$C$13=0,0,'Supuestos'!$C$10/'Supuestos'!$C$13))=0,0,'Supuestos'!$C$8/(IF('Supuestos'!$C$13=0,0,'Supuestos'!$C$10/'Supuestos'!$C$13))))*'Supuestos'!$C$20)*'Supuestos'!$C$25)+(((IF((IF('Supuestos'!$C$13=0,0,'Supuestos'!$C$10/'Supuestos'!$C$13))=0,0,'Supuestos'!$C$8/(IF('Supuestos'!$C$13=0,0,'Supuestos'!$C$10/'Supuestos'!$C$13))))*'Supuestos'!$C$21)*'Supuestos'!$C$26))*'Supuestos'!$C$27)*'Supuestos'!$C$24)+(((((((IF((IF('Supuestos'!$C$13=0,0,'Supuestos'!$C$10/'Supuestos'!$C$13))=0,0,'Supuestos'!$C$8/(IF('Supuestos'!$C$13=0,0,'Supuestos'!$C$10/'Supuestos'!$C$13))))*'Supuestos'!$C$20)*'Supuestos'!$C$25)+(((IF((IF('Supuestos'!$C$13=0,0,'Supuestos'!$C$10/'Supuestos'!$C$13))=0,0,'Supuestos'!$C$8/(IF('Supuestos'!$C$13=0,0,'Supuestos'!$C$10/'Supuestos'!$C$13))))*'Supuestos'!$C$21)*'Supuestos'!$C$26))*'Supuestos'!$C$27)*('Supuestos'!$C$29*1.1))*'Supuestos'!$C$28))*('Supuestos'!$C$39+'Supuestos'!$C$40+'Supuestos'!$C$41))*(1-'Supuestos'!$C$32-'Supuestos'!$C$33-'Supuestos'!$C$34))-((IF((IF('Supuestos'!$C$13=0,0,'Supuestos'!$C$10/'Supuestos'!$C$13))=0,0,'Supuestos'!$C$8/(IF('Supuestos'!$C$13=0,0,'Supuestos'!$C$10/'Supuestos'!$C$13))))*'Supuestos'!$C$35)-'Supuestos'!$C$36-'Supuestos'!$C$8) | E14: =D14-$D$6 | F14: =IF($D$6=0,0,E14/ABS($D$6)) | G14: =RANK(E14,$E$7:$E$15)
B15: Bump de la entrada 10 % más tomado | C15: +10 % | D15: =(((((((IF((IF('Supuestos'!$C$13=0,0,'Supuestos'!$C$10/'Supuestos'!$C$13))=0,0,'Supuestos'!$C$8/(IF('Supuestos'!$C$13=0,0,'Supuestos'!$C$10/'Supuestos'!$C$13))))*'Supuestos'!$C$14)+(((IF((IF('Supuestos'!$C$13=0,0,'Supuestos'!$C$10/'Supuestos'!$C$13))=0,0,'Supuestos'!$C$8/(IF('Supuestos'!$C$13=0,0,'Supuestos'!$C$10/'Supuestos'!$C$13))))*('Supuestos'!$C$16*1.1))*'Supuestos'!$C$15))+((((((IF((IF('Supuestos'!$C$13=0,0,'Supuestos'!$C$10/'Supuestos'!$C$13))=0,0,'Supuestos'!$C$8/(IF('Supuestos'!$C$13=0,0,'Supuestos'!$C$10/'Supuestos'!$C$13))))*'Supuestos'!$C$20)*'Supuestos'!$C$25)+(((IF((IF('Supuestos'!$C$13=0,0,'Supuestos'!$C$10/'Supuestos'!$C$13))=0,0,'Supuestos'!$C$8/(IF('Supuestos'!$C$13=0,0,'Supuestos'!$C$10/'Supuestos'!$C$13))))*'Supuestos'!$C$21)*'Supuestos'!$C$26))*'Supuestos'!$C$27)*'Supuestos'!$C$24)+(((((((IF((IF('Supuestos'!$C$13=0,0,'Supuestos'!$C$10/'Supuestos'!$C$13))=0,0,'Supuestos'!$C$8/(IF('Supuestos'!$C$13=0,0,'Supuestos'!$C$10/'Supuestos'!$C$13))))*'Supuestos'!$C$20)*'Supuestos'!$C$25)+(((IF((IF('Supuestos'!$C$13=0,0,'Supuestos'!$C$10/'Supuestos'!$C$13))=0,0,'Supuestos'!$C$8/(IF('Supuestos'!$C$13=0,0,'Supuestos'!$C$10/'Supuestos'!$C$13))))*'Supuestos'!$C$21)*'Supuestos'!$C$26))*'Supuestos'!$C$27)*'Supuestos'!$C$29)*'Supuestos'!$C$28))*('Supuestos'!$C$39+'Supuestos'!$C$40+'Supuestos'!$C$41))*(1-'Supuestos'!$C$32-'Supuestos'!$C$33-'Supuestos'!$C$34))-((IF((IF('Supuestos'!$C$13=0,0,'Supuestos'!$C$10/'Supuestos'!$C$13))=0,0,'Supuestos'!$C$8/(IF('Supuestos'!$C$13=0,0,'Supuestos'!$C$10/'Supuestos'!$C$13))))*'Supuestos'!$C$35)-'Supuestos'!$C$36-'Supuestos'!$C$8) | E15: =D15-$D$6 | F15: =IF($D$6=0,0,E15/ABS($D$6)) | G15: =RANK(E15,$E$7:$E$15)

Sheet Proyección 12 meses
B1: © Jesús Tassarolo · TooAudience · youtube.com/@JesusTassaroloSinFiltro · uso personal; no redistribuir modificado
B2: Proyección a 12 meses y caja
B3: La inversión crece cada mes según el supuesto de crecimiento. El cash entra según la curva de cobranza (mes 1 / 2 / 3). La ganancia acumulada muestra cuánto dinero hace falta para sostener la pauta. Cada mes multiplica inversión, costos fijos y ventas por los lanzamientos por mes de Supuestos.
B5: Concepto | C5: Mes 1 | D5: Mes 2 | E5: Mes 3 | F5: Mes 4 | G5: Mes 5 | H5: Mes 6 | I5: Mes 7 | J5: Mes 8 | K5: Mes 9 | L5: Mes 10 | M5: Mes 11 | N5: Mes 12 | O5: Total
B6: Inversión en publicidad del mes | C6: ='Supuestos'!$C$8*'Supuestos'!$C$9 | D6: =C6*(1+'Supuestos'!$C$47) | E6: =D6*(1+'Supuestos'!$C$47) | F6: =E6*(1+'Supuestos'!$C$47) | G6: =F6*(1+'Supuestos'!$C$47) | H6: =G6*(1+'Supuestos'!$C$47) | I6: =H6*(1+'Supuestos'!$C$47) | J6: =I6*(1+'Supuestos'!$C$47) | K6: =J6*(1+'Supuestos'!$C$47) | ... N6: =M6*(1+'Supuestos'!$C$47) | O6: =SUM(C6:N6)
B7: Entradas compradas | C7: =IF('Modelo'!$C$8=0,0,C6/'Modelo'!$C$8) | D7: =IF('Modelo'!$C$8=0,0,D6/'Modelo'!$C$8) | E7: =IF('Modelo'!$C$8=0,0,E6/'Modelo'!$C$8) | F7: =IF('Modelo'!$C$8=0,0,F6/'Modelo'!$C$8) | G7: =IF('Modelo'!$C$8=0,0,G6/'Modelo'!$C$8) | H7: =IF('Modelo'!$C$8=0,0,H6/'Modelo'!$C$8) | I7: =IF('Modelo'!$C$8=0,0,I6/'Modelo'!$C$8) | J7: =IF('Modelo'!$C$8=0,0,J6/'Modelo'!$C$8) | ... N7: =IF('Modelo'!$C$8=0,0,N6/'Modelo'!$C$8) | O7: =SUM(C7:N7)
B8: Ventas del producto principal | C8: =C7*'Modelo'!$C$35 | D8: =D7*'Modelo'!$C$35 | E8: =E7*'Modelo'!$C$35 | F8: =F7*'Modelo'!$C$35 | G8: =G7*'Modelo'!$C$35 | H8: =H7*'Modelo'!$C$35 | I8: =I7*'Modelo'!$C$35 | J8: =J7*'Modelo'!$C$35 | ... N8: =N7*'Modelo'!$C$35 | O8: =SUM(C8:N8)
B9: Facturado (todos los productos) | C9: =C7*'Modelo'!$C$36 | D9: =D7*'Modelo'!$C$36 | E9: =E7*'Modelo'!$C$36 | F9: =F7*'Modelo'!$C$36 | G9: =G7*'Modelo'!$C$36 | H9: =H7*'Modelo'!$C$36 | I9: =I7*'Modelo'!$C$36 | J9: =J7*'Modelo'!$C$36 | ... N9: =N7*'Modelo'!$C$36 | O9: =SUM(C9:N9)
B10: Cash cobrado en el mes | C10: =C9*'Supuestos'!$C$39 | D10: =D9*'Supuestos'!$C$39+C9*'Supuestos'!$C$40 | E10: =E9*'Supuestos'!$C$39+D9*'Supuestos'!$C$40+C9*'Supuestos'!$C$41 | F10: =F9*'Supuestos'!$C$39+E9*'Supuestos'!$C$40+D9*'Supuestos'!$C$41 | G10: =G9*'Supuestos'!$C$39+F9*'Supuestos'!$C$40+E9*'Supuestos'!$C$41 | H10: =H9*'Supuestos'!$C$39+G9*'Supuestos'!$C$40+F9*'Supuestos'!$C$41 | I10: =I9*'Supuestos'!$C$39+H9*'Supuestos'!$C$40+G9*'Supuestos'!$C$41 | J10: =J9*'Supuestos'!$C$39+I9*'Supuestos'!$C$40+H9*'Supuestos'!$C$41 | K10: =K9*'Supuestos'!$C$39+J9*'Supuestos'!$C$40+I9*'Supuestos'!$C$41 | L10: =L9*'Supuestos'!$C$39+K9*'Supuestos'!$C$40+J9*'Supuestos'!$C$41 | ... N10: =N9*'Supuestos'!$C$39+M9*'Supuestos'!$C$40+L9*'Supuestos'!$C$41 | O10: =SUM(C10:N10)
B11: Comisiones y reembolsos | C11: =C10*('Supuestos'!$C$32+'Supuestos'!$C$33+'Supuestos'!$C$34) | D11: =D10*('Supuestos'!$C$32+'Supuestos'!$C$33+'Supuestos'!$C$34) | E11: =E10*('Supuestos'!$C$32+'Supuestos'!$C$33+'Supuestos'!$C$34) | F11: =F10*('Supuestos'!$C$32+'Supuestos'!$C$33+'Supuestos'!$C$34) | G11: =G10*('Supuestos'!$C$32+'Supuestos'!$C$33+'Supuestos'!$C$34) | H11: =H10*('Supuestos'!$C$32+'Supuestos'!$C$33+'Supuestos'!$C$34) | I11: =I10*('Supuestos'!$C$32+'Supuestos'!$C$33+'Supuestos'!$C$34) | J11: =J10*('Supuestos'!$C$32+'Supuestos'!$C$33+'Supuestos'!$C$34) | ... N11: =N10*('Supuestos'!$C$32+'Supuestos'!$C$33+'Supuestos'!$C$34) | O11: =SUM(C11:N11)
B12: Costos por unidad (herramientas, WhatsApp, IA) | C12: =C7*'Supuestos'!$C$35 | D12: =D7*'Supuestos'!$C$35 | E12: =E7*'Supuestos'!$C$35 | F12: =F7*'Supuestos'!$C$35 | G12: =G7*'Supuestos'!$C$35 | H12: =H7*'Supuestos'!$C$35 | I12: =I7*'Supuestos'!$C$35 | J12: =J7*'Supuestos'!$C$35 | ... N12: =N7*'Supuestos'!$C$35 | O12: =SUM(C12:N12)
B13: Costos fijos del mes | C13: ='Supuestos'!$C$36*'Supuestos'!$C$9 | D13: ='Supuestos'!$C$36*'Supuestos'!$C$9 | E13: ='Supuestos'!$C$36*'Supuestos'!$C$9 | F13: ='Supuestos'!$C$36*'Supuestos'!$C$9 | G13: ='Supuestos'!$C$36*'Supuestos'!$C$9 | H13: ='Supuestos'!$C$36*'Supuestos'!$C$9 | I13: ='Supuestos'!$C$36*'Supuestos'!$C$9 | J13: ='Supuestos'!$C$36*'Supuestos'!$C$9 | ... N13: ='Supuestos'!$C$36*'Supuestos'!$C$9 | O13: =SUM(C13:N13)
B14: Ganancia de caja del mes | C14: =C10-C11-C12-C13-C6 | D14: =D10-D11-D12-D13-D6 | E14: =E10-E11-E12-E13-E6 | F14: =F10-F11-F12-F13-F6 | G14: =G10-G11-G12-G13-G6 | H14: =H10-H11-H12-H13-H6 | I14: =I10-I11-I12-I13-I6 | J14: =J10-J11-J12-J13-J6 | ... N14: =N10-N11-N12-N13-N6 | O14: =SUM(C14:N14)
B15: Ganancia de caja acumulada (desde cero) | C15: =C14 | D15: =C15+D14 | E15: =D15+E14 | F15: =E15+F14 | G15: =F15+G14 | H15: =G15+H14 | I15: =H15+I14 | J15: =I15+J14 | K15: =J15+K14 | ... N15: =M15+N14
B16: Saldo de caja (caja inicial + ganancia acumulada) | C16: ='Supuestos'!$C$48+C15 | D16: ='Supuestos'!$C$48+D15 | E16: ='Supuestos'!$C$48+E15 | F16: ='Supuestos'!$C$48+F15 | G16: ='Supuestos'!$C$48+G15 | H16: ='Supuestos'!$C$48+H15 | I16: ='Supuestos'!$C$48+I15 | J16: ='Supuestos'!$C$48+J15 | ... N16: ='Supuestos'!$C$48+N15
B18: Caja necesaria para no frenar la pauta (el peor momento de la ganancia acumulada) | C18: =MAX(0,-MIN(C15:N15))
B19: Saldo mínimo de caja con tu caja inicial | C19: =MIN(C16:N16)
B20: Ganancia de caja acumulada en 12 meses | C20: =O14

Sheet Seguimiento
B1: © Jesús Tassarolo · TooAudience · youtube.com/@JesusTassaroloSinFiltro · uso personal; no redistribuir modificado
B2: Seguimiento: una columna por lanzamiento
B3: Cargá los datos reales en las celdas amarillas. El semáforo compara tu costo real por entrada con el techo móvil (lo que rindieron tus últimas 4 columnas) y con el techo del modelo.
B5: Dato | C5: Lanzamiento 1 | D5: Lanzamiento 2 | E5: Lanzamiento 3 | F5: Lanzamiento 4 | G5: Lanzamiento 5 | H5: Lanzamiento 6 | I5: Lanzamiento 7 | J5: Lanzamiento 8 | K5: Lanzamiento 9 | L5: Lanzamiento 10 | M5: Lanzamiento 11 | N5: Lanzamiento 12 | O5: Promedio | P5: Máximo | Q5: Mínimo
B6: Datos que cargás
B7: Inversión en publicidad | C7: 3000 | D7: 3200 | E7: 3600 | O7: =IF(COUNT(C7:N7)=0,"",AVERAGE(C7:N7)) | P7: =IF(COUNT(C7:N7)=0,"",MAX(C7:N7)) | Q7: =IF(COUNT(C7:N7)=0,"",MIN(C7:N7))
B8: Visitas a la página de ventas | C8: 8600 | D8: 8900 | E8: 9700 | O8: =IF(COUNT(C8:N8)=0,"",AVERAGE(C8:N8)) | P8: =IF(COUNT(C8:N8)=0,"",MAX(C8:N8)) | Q8: =IF(COUNT(C8:N8)=0,"",MIN(C8:N8))
B9: Entradas vendidas | C9: 214 | D9: 220 | E9: 235 | O9: =IF(COUNT(C9:N9)=0,"",AVERAGE(C9:N9)) | P9: =IF(COUNT(C9:N9)=0,"",MAX(C9:N9)) | Q9: =IF(COUNT(C9:N9)=0,"",MIN(C9:N9))
B10: Bumps de la entrada | C10: 43 | D10: 40 | E10: 50 | O10: =IF(COUNT(C10:N10)=0,"",AVERAGE(C10:N10)) | P10: =IF(COUNT(C10:N10)=0,"",MAX(C10:N10)) | Q10: =IF(COUNT(C10:N10)=0,"",MIN(C10:N10))
B11: Entraron al grupo | C11: 182 | D11: 190 | E11: 200 | O11: =IF(COUNT(C11:N11)=0,"",AVERAGE(C11:N11)) | P11: =IF(COUNT(C11:N11)=0,"",MAX(C11:N11)) | Q11: =IF(COUNT(C11:N11)=0,"",MIN(C11:N11))
B12: Asistentes en vivo | C12: 118 | D12: 115 | E12: 135 | O12: =IF(COUNT(C12:N12)=0,"",AVERAGE(C12:N12)) | P12: =IF(COUNT(C12:N12)=0,"",MAX(C12:N12)) | Q12: =IF(COUNT(C12:N12)=0,"",MIN(C12:N12))
B13: Vieron el replay | C13: 54 | D13: 60 | E13: 58 | O13: =IF(COUNT(C13:N13)=0,"",AVERAGE(C13:N13)) | P13: =IF(COUNT(C13:N13)=0,"",MAX(C13:N13)) | Q13: =IF(COUNT(C13:N13)=0,"",MIN(C13:N13))
B14: Solicitudes (formulario de compra, aplicación o vendedor) | C14: 22 | D14: 19 | E14: 26 | O14: =IF(COUNT(C14:N14)=0,"",AVERAGE(C14:N14)) | P14: =IF(COUNT(C14:N14)=0,"",MAX(C14:N14)) | Q14: =IF(COUNT(C14:N14)=0,"",MIN(C14:N14))
B15: Ventas de la oferta | C15: 11 | D15: 9 | E15: 13 | O15: =IF(COUNT(C15:N15)=0,"",AVERAGE(C15:N15)) | P15: =IF(COUNT(C15:N15)=0,"",MAX(C15:N15)) | Q15: =IF(COUNT(C15:N15)=0,"",MIN(C15:N15))
B16: Ventas del programa superior | C16: 1 | D16: 1 | E16: 2 | O16: =IF(COUNT(C16:N16)=0,"",AVERAGE(C16:N16)) | P16: =IF(COUNT(C16:N16)=0,"",MAX(C16:N16)) | Q16: =IF(COUNT(C16:N16)=0,"",MIN(C16:N16))
B17: Facturado del lanzamiento (a precio de lista, con cuotas por cobrar) | C17: 10400 | D17: 9000 | E17: 12300 | O17: =IF(COUNT(C17:N17)=0,"",AVERAGE(C17:N17)) | P17: =IF(COUNT(C17:N17)=0,"",MAX(C17:N17)) | Q17: =IF(COUNT(C17:N17)=0,"",MIN(C17:N17))
B18: Cash cobrado hasta ahora de ese lanzamiento | C18: 6900 | D18: 6300 | E18: 8200 | O18: =IF(COUNT(C18:N18)=0,"",AVERAGE(C18:N18)) | P18: =IF(COUNT(C18:N18)=0,"",MAX(C18:N18)) | Q18: =IF(COUNT(C18:N18)=0,"",MIN(C18:N18))
B19: Lo que calcula el modelo
B20: Costo por entrada real | C20: =IF(COUNT(C7:C18)<12,"",IF(C9=0,0,C7/C9)) | D20: =IF(COUNT(D7:D18)<12,"",IF(D9=0,0,D7/D9)) | E20: =IF(COUNT(E7:E18)<12,"",IF(E9=0,0,E7/E9)) | F20: =IF(COUNT(F7:F18)<12,"",IF(F9=0,0,F7/F9)) | G20: =IF(COUNT(G7:G18)<12,"",IF(G9=0,0,G7/G9)) | H20: =IF(COUNT(H7:H18)<12,"",IF(H9=0,0,H7/H9)) | I20: =IF(COUNT(I7:I18)<12,"",IF(I9=0,0,I7/I9)) | J20: =IF(COUNT(J7:J18)<12,"",IF(J9=0,0,J7/J9)) | ... N20: =IF(COUNT(N7:N18)<12,"",IF(N9=0,0,N7/N9)) | O20: =IF(COUNT(C20:N20)=0,"",AVERAGE(C20:N20)) | P20: =IF(COUNT(C20:N20)=0,"",MAX(C20:N20)) | Q20: =IF(COUNT(C20:N20)=0,"",MIN(C20:N20))
B21: % visita → entrada | C21: =IF(COUNT(C7:C18)<12,"",IF(C8=0,0,C9/C8)) | D21: =IF(COUNT(D7:D18)<12,"",IF(D8=0,0,D9/D8)) | E21: =IF(COUNT(E7:E18)<12,"",IF(E8=0,0,E9/E8)) | F21: =IF(COUNT(F7:F18)<12,"",IF(F8=0,0,F9/F8)) | G21: =IF(COUNT(G7:G18)<12,"",IF(G8=0,0,G9/G8)) | H21: =IF(COUNT(H7:H18)<12,"",IF(H8=0,0,H9/H8)) | I21: =IF(COUNT(I7:I18)<12,"",IF(I8=0,0,I9/I8)) | J21: =IF(COUNT(J7:J18)<12,"",IF(J8=0,0,J9/J8)) | ... N21: =IF(COUNT(N7:N18)<12,"",IF(N8=0,0,N9/N8)) | O21: =IF(COUNT(C21:N21)=0,"",AVERAGE(C21:N21)) | P21: =IF(COUNT(C21:N21)=0,"",MAX(C21:N21)) | Q21: =IF(COUNT(C21:N21)=0,"",MIN(C21:N21))
B22: ROAS del front (entradas × precio + bumps × precio ÷ inversión) | C22: =IF(COUNT(C7:C18)<12,"",(C9*'Supuestos'!$C$14+C10*'Supuestos'!$C$15)/C7) | D22: =IF(COUNT(D7:D18)<12,"",(D9*'Supuestos'!$C$14+D10*'Supuestos'!$C$15)/D7) | E22: =IF(COUNT(E7:E18)<12,"",(E9*'Supuestos'!$C$14+E10*'Supuestos'!$C$15)/E7) | F22: =IF(COUNT(F7:F18)<12,"",(F9*'Supuestos'!$C$14+F10*'Supuestos'!$C$15)/F7) | G22: =IF(COUNT(G7:G18)<12,"",(G9*'Supuestos'!$C$14+G10*'Supuestos'!$C$15)/G7) | H22: =IF(COUNT(H7:H18)<12,"",(H9*'Supuestos'!$C$14+H10*'Supuestos'!$C$15)/H7) | I22: =IF(COUNT(I7:I18)<12,"",(I9*'Supuestos'!$C$14+I10*'Supuestos'!$C$15)/I7) | J22: =IF(COUNT(J7:J18)<12,"",(J9*'Supuestos'!$C$14+J10*'Supuestos'!$C$15)/J7) | ... N22: =IF(COUNT(N7:N18)<12,"",(N9*'Supuestos'!$C$14+N10*'Supuestos'!$C$15)/N7) | O22: =IF(COUNT(C22:N22)=0,"",AVERAGE(C22:N22)) | P22: =IF(COUNT(C22:N22)=0,"",MAX(C22:N22)) | Q22: =IF(COUNT(C22:N22)=0,"",MIN(C22:N22))
B23: % entrada → en vivo | C23: =IF(COUNT(C7:C18)<12,"",IF(C9=0,0,C12/C9)) | D23: =IF(COUNT(D7:D18)<12,"",IF(D9=0,0,D12/D9)) | E23: =IF(COUNT(E7:E18)<12,"",IF(E9=0,0,E12/E9)) | F23: =IF(COUNT(F7:F18)<12,"",IF(F9=0,0,F12/F9)) | G23: =IF(COUNT(G7:G18)<12,"",IF(G9=0,0,G12/G9)) | H23: =IF(COUNT(H7:H18)<12,"",IF(H9=0,0,H12/H9)) | I23: =IF(COUNT(I7:I18)<12,"",IF(I9=0,0,I12/I9)) | J23: =IF(COUNT(J7:J18)<12,"",IF(J9=0,0,J12/J9)) | ... N23: =IF(COUNT(N7:N18)<12,"",IF(N9=0,0,N12/N9)) | O23: =IF(COUNT(C23:N23)=0,"",AVERAGE(C23:N23)) | P23: =IF(COUNT(C23:N23)=0,"",MAX(C23:N23)) | Q23: =IF(COUNT(C23:N23)=0,"",MIN(C23:N23))
B24: Ventas ÷ asistentes en vivo | C24: =IF(COUNT(C7:C18)<12,"",IF(C12=0,0,C15/C12)) | D24: =IF(COUNT(D7:D18)<12,"",IF(D12=0,0,D15/D12)) | E24: =IF(COUNT(E7:E18)<12,"",IF(E12=0,0,E15/E12)) | F24: =IF(COUNT(F7:F18)<12,"",IF(F12=0,0,F15/F12)) | G24: =IF(COUNT(G7:G18)<12,"",IF(G12=0,0,G15/G12)) | H24: =IF(COUNT(H7:H18)<12,"",IF(H12=0,0,H15/H12)) | I24: =IF(COUNT(I7:I18)<12,"",IF(I12=0,0,I15/I12)) | J24: =IF(COUNT(J7:J18)<12,"",IF(J12=0,0,J15/J12)) | ... N24: =IF(COUNT(N7:N18)<12,"",IF(N12=0,0,N15/N12)) | O24: =IF(COUNT(C24:N24)=0,"",AVERAGE(C24:N24)) | P24: =IF(COUNT(C24:N24)=0,"",MAX(C24:N24)) | Q24: =IF(COUNT(C24:N24)=0,"",MIN(C24:N24))
B25: Costo por comprador de la oferta | C25: =IF(COUNT(C7:C18)<12,"",IF(C15=0,0,C7/C15)) | D25: =IF(COUNT(D7:D18)<12,"",IF(D15=0,0,D7/D15)) | E25: =IF(COUNT(E7:E18)<12,"",IF(E15=0,0,E7/E15)) | F25: =IF(COUNT(F7:F18)<12,"",IF(F15=0,0,F7/F15)) | G25: =IF(COUNT(G7:G18)<12,"",IF(G15=0,0,G7/G15)) | H25: =IF(COUNT(H7:H18)<12,"",IF(H15=0,0,H7/H15)) | I25: =IF(COUNT(I7:I18)<12,"",IF(I15=0,0,I7/I15)) | J25: =IF(COUNT(J7:J18)<12,"",IF(J15=0,0,J7/J15)) | ... N25: =IF(COUNT(N7:N18)<12,"",IF(N15=0,0,N7/N15)) | O25: =IF(COUNT(C25:N25)=0,"",AVERAGE(C25:N25)) | P25: =IF(COUNT(C25:N25)=0,"",MAX(C25:N25)) | Q25: =IF(COUNT(C25:N25)=0,"",MIN(C25:N25))
B26: Costo por persona en el grupo | C26: =IF(COUNT(C7:C18)<12,"",IF(C11=0,0,C7/C11)) | D26: =IF(COUNT(D7:D18)<12,"",IF(D11=0,0,D7/D11)) | E26: =IF(COUNT(E7:E18)<12,"",IF(E11=0,0,E7/E11)) | F26: =IF(COUNT(F7:F18)<12,"",IF(F11=0,0,F7/F11)) | G26: =IF(COUNT(G7:G18)<12,"",IF(G11=0,0,G7/G11)) | H26: =IF(COUNT(H7:H18)<12,"",IF(H11=0,0,H7/H11)) | I26: =IF(COUNT(I7:I18)<12,"",IF(I11=0,0,I7/I11)) | J26: =IF(COUNT(J7:J18)<12,"",IF(J11=0,0,J7/J11)) | ... N26: =IF(COUNT(N7:N18)<12,"",IF(N11=0,0,N7/N11)) | O26: =IF(COUNT(C26:N26)=0,"",AVERAGE(C26:N26)) | P26: =IF(COUNT(C26:N26)=0,"",MAX(C26:N26)) | Q26: =IF(COUNT(C26:N26)=0,"",MIN(C26:N26))
B27: % en vivo → solicitud | C27: =IF(COUNT(C7:C18)<12,"",IF(C12=0,0,C14/C12)) | D27: =IF(COUNT(D7:D18)<12,"",IF(D12=0,0,D14/D12)) | E27: =IF(COUNT(E7:E18)<12,"",IF(E12=0,0,E14/E12)) | F27: =IF(COUNT(F7:F18)<12,"",IF(F12=0,0,F14/F12)) | G27: =IF(COUNT(G7:G18)<12,"",IF(G12=0,0,G14/G12)) | H27: =IF(COUNT(H7:H18)<12,"",IF(H12=0,0,H14/H12)) | I27: =IF(COUNT(I7:I18)<12,"",IF(I12=0,0,I14/I12)) | J27: =IF(COUNT(J7:J18)<12,"",IF(J12=0,0,J14/J12)) | ... N27: =IF(COUNT(N7:N18)<12,"",IF(N12=0,0,N14/N12)) | O27: =IF(COUNT(C27:N27)=0,"",AVERAGE(C27:N27)) | P27: =IF(COUNT(C27:N27)=0,"",MAX(C27:N27)) | Q27: =IF(COUNT(C27:N27)=0,"",MIN(C27:N27))
B28: Costo por solicitud | C28: =IF(COUNT(C7:C18)<12,"",IF(C14=0,0,C7/C14)) | D28: =IF(COUNT(D7:D18)<12,"",IF(D14=0,0,D7/D14)) | E28: =IF(COUNT(E7:E18)<12,"",IF(E14=0,0,E7/E14)) | F28: =IF(COUNT(F7:F18)<12,"",IF(F14=0,0,F7/F14)) | G28: =IF(COUNT(G7:G18)<12,"",IF(G14=0,0,G7/G14)) | H28: =IF(COUNT(H7:H18)<12,"",IF(H14=0,0,H7/H14)) | I28: =IF(COUNT(I7:I18)<12,"",IF(I14=0,0,I7/I14)) | J28: =IF(COUNT(J7:J18)<12,"",IF(J14=0,0,J7/J14)) | ... N28: =IF(COUNT(N7:N18)<12,"",IF(N14=0,0,N7/N14)) | O28: =IF(COUNT(C28:N28)=0,"",AVERAGE(C28:N28)) | P28: =IF(COUNT(C28:N28)=0,"",MAX(C28:N28)) | Q28: =IF(COUNT(C28:N28)=0,"",MIN(C28:N28))
B29: % solicitud → compra | C29: =IF(COUNT(C7:C18)<12,"",IF(C14=0,0,C15/C14)) | D29: =IF(COUNT(D7:D18)<12,"",IF(D14=0,0,D15/D14)) | E29: =IF(COUNT(E7:E18)<12,"",IF(E14=0,0,E15/E14)) | F29: =IF(COUNT(F7:F18)<12,"",IF(F14=0,0,F15/F14)) | G29: =IF(COUNT(G7:G18)<12,"",IF(G14=0,0,G15/G14)) | H29: =IF(COUNT(H7:H18)<12,"",IF(H14=0,0,H15/H14)) | I29: =IF(COUNT(I7:I18)<12,"",IF(I14=0,0,I15/I14)) | J29: =IF(COUNT(J7:J18)<12,"",IF(J14=0,0,J15/J14)) | ... N29: =IF(COUNT(N7:N18)<12,"",IF(N14=0,0,N15/N14)) | O29: =IF(COUNT(C29:N29)=0,"",AVERAGE(C29:N29)) | P29: =IF(COUNT(C29:N29)=0,"",MAX(C29:N29)) | Q29: =IF(COUNT(C29:N29)=0,"",MIN(C29:N29))
B30: Valor neto por unidad real (sobre facturado, cobranza completa) | C30: =IF(COUNT(C7:C18)<12,"",IF(C9=0,0,(C17*(1-'Supuestos'!$C$32-'Supuestos'!$C$33-'Supuestos'!$C$34)-C9*'Supuestos'!$C$35)/C9)) | D30: =IF(COUNT(D7:D18)<12,"",IF(D9=0,0,(D17*(1-'Supuestos'!$C$32-'Supuestos'!$C$33-'Supuestos'!$C$34)-D9*'Supuestos'!$C$35)/D9)) | E30: =IF(COUNT(E7:E18)<12,"",IF(E9=0,0,(E17*(1-'Supuestos'!$C$32-'Supuestos'!$C$33-'Supuestos'!$C$34)-E9*'Supuestos'!$C$35)/E9)) | F30: =IF(COUNT(F7:F18)<12,"",IF(F9=0,0,(F17*(1-'Supuestos'!$C$32-'Supuestos'!$C$33-'Supuestos'!$C$34)-F9*'Supuestos'!$C$35)/F9)) | G30: =IF(COUNT(G7:G18)<12,"",IF(G9=0,0,(G17*(1-'Supuestos'!$C$32-'Supuestos'!$C$33-'Supuestos'!$C$34)-G9*'Supuestos'!$C$35)/G9)) | H30: =IF(COUNT(H7:H18)<12,"",IF(H9=0,0,(H17*(1-'Supuestos'!$C$32-'Supuestos'!$C$33-'Supuestos'!$C$34)-H9*'Supuestos'!$C$35)/H9)) | I30: =IF(COUNT(I7:I18)<12,"",IF(I9=0,0,(I17*(1-'Supuestos'!$C$32-'Supuestos'!$C$33-'Supuestos'!$C$34)-I9*'Supuestos'!$C$35)/I9)) | J30: =IF(COUNT(J7:J18)<12,"",IF(J9=0,0,(J17*(1-'Supuestos'!$C$32-'Supuestos'!$C$33-'Supuestos'!$C$34)-J9*'Supuestos'!$C$35)/J9)) | ... N30: =IF(COUNT(N7:N18)<12,"",IF(N9=0,0,(N17*(1-'Supuestos'!$C$32-'Supuestos'!$C$33-'Supuestos'!$C$34)-N9*'Supuestos'!$C$35)/N9)) | O30: =IF(COUNT(C30:N30)=0,"",AVERAGE(C30:N30)) | P30: =IF(COUNT(C30:N30)=0,"",MAX(C30:N30)) | Q30: =IF(COUNT(C30:N30)=0,"",MIN(C30:N30))
B31: Ganancia del período al completar la cobranza | C31: =IF(COUNT(C7:C18)<12,"",C17*(1-'Supuestos'!$C$32-'Supuestos'!$C$33-'Supuestos'!$C$34)-C9*'Supuestos'!$C$35-'Supuestos'!$C$36-C7) | D31: =IF(COUNT(D7:D18)<12,"",D17*(1-'Supuestos'!$C$32-'Supuestos'!$C$33-'Supuestos'!$C$34)-D9*'Supuestos'!$C$35-'Supuestos'!$C$36-D7) | E31: =IF(COUNT(E7:E18)<12,"",E17*(1-'Supuestos'!$C$32-'Supuestos'!$C$33-'Supuestos'!$C$34)-E9*'Supuestos'!$C$35-'Supuestos'!$C$36-E7) | F31: =IF(COUNT(F7:F18)<12,"",F17*(1-'Supuestos'!$C$32-'Supuestos'!$C$33-'Supuestos'!$C$34)-F9*'Supuestos'!$C$35-'Supuestos'!$C$36-F7) | G31: =IF(COUNT(G7:G18)<12,"",G17*(1-'Supuestos'!$C$32-'Supuestos'!$C$33-'Supuestos'!$C$34)-G9*'Supuestos'!$C$35-'Supuestos'!$C$36-G7) | H31: =IF(COUNT(H7:H18)<12,"",H17*(1-'Supuestos'!$C$32-'Supuestos'!$C$33-'Supuestos'!$C$34)-H9*'Supuestos'!$C$35-'Supuestos'!$C$36-H7) | I31: =IF(COUNT(I7:I18)<12,"",I17*(1-'Supuestos'!$C$32-'Supuestos'!$C$33-'Supuestos'!$C$34)-I9*'Supuestos'!$C$35-'Supuestos'!$C$36-I7) | J31: =IF(COUNT(J7:J18)<12,"",J17*(1-'Supuestos'!$C$32-'Supuestos'!$C$33-'Supuestos'!$C$34)-J9*'Supuestos'!$C$35-'Supuestos'!$C$36-J7) | ... N31: =IF(COUNT(N7:N18)<12,"",N17*(1-'Supuestos'!$C$32-'Supuestos'!$C$33-'Supuestos'!$C$34)-N9*'Supuestos'!$C$35-'Supuestos'!$C$36-N7) | O31: =IF(COUNT(C31:N31)=0,"",AVERAGE(C31:N31)) | P31: =IF(COUNT(C31:N31)=0,"",MAX(C31:N31)) | Q31: =IF(COUNT(C31:N31)=0,"",MIN(C31:N31))
B32: Ganancia de caja del período (con lo cobrado hasta ahora) | C32: =IF(COUNT(C7:C18)<12,"",C18*(1-'Supuestos'!$C$32-'Supuestos'!$C$33-'Supuestos'!$C$34)-C9*'Supuestos'!$C$35-'Supuestos'!$C$36-C7) | D32: =IF(COUNT(D7:D18)<12,"",D18*(1-'Supuestos'!$C$32-'Supuestos'!$C$33-'Supuestos'!$C$34)-D9*'Supuestos'!$C$35-'Supuestos'!$C$36-D7) | E32: =IF(COUNT(E7:E18)<12,"",E18*(1-'Supuestos'!$C$32-'Supuestos'!$C$33-'Supuestos'!$C$34)-E9*'Supuestos'!$C$35-'Supuestos'!$C$36-E7) | F32: =IF(COUNT(F7:F18)<12,"",F18*(1-'Supuestos'!$C$32-'Supuestos'!$C$33-'Supuestos'!$C$34)-F9*'Supuestos'!$C$35-'Supuestos'!$C$36-F7) | G32: =IF(COUNT(G7:G18)<12,"",G18*(1-'Supuestos'!$C$32-'Supuestos'!$C$33-'Supuestos'!$C$34)-G9*'Supuestos'!$C$35-'Supuestos'!$C$36-G7) | H32: =IF(COUNT(H7:H18)<12,"",H18*(1-'Supuestos'!$C$32-'Supuestos'!$C$33-'Supuestos'!$C$34)-H9*'Supuestos'!$C$35-'Supuestos'!$C$36-H7) | I32: =IF(COUNT(I7:I18)<12,"",I18*(1-'Supuestos'!$C$32-'Supuestos'!$C$33-'Supuestos'!$C$34)-I9*'Supuestos'!$C$35-'Supuestos'!$C$36-I7) | J32: =IF(COUNT(J7:J18)<12,"",J18*(1-'Supuestos'!$C$32-'Supuestos'!$C$33-'Supuestos'!$C$34)-J9*'Supuestos'!$C$35-'Supuestos'!$C$36-J7) | ... N32: =IF(COUNT(N7:N18)<12,"",N18*(1-'Supuestos'!$C$32-'Supuestos'!$C$33-'Supuestos'!$C$34)-N9*'Supuestos'!$C$35-'Supuestos'!$C$36-N7) | O32: =IF(COUNT(C32:N32)=0,"",AVERAGE(C32:N32)) | P32: =IF(COUNT(C32:N32)=0,"",MAX(C32:N32)) | Q32: =IF(COUNT(C32:N32)=0,"",MIN(C32:N32))
B33: Ganancia por unidad real (ganancia ÷ unidades) | C33: =IF(COUNT(C7:C18)<12,"",IF(C9=0,0,(C17*(1-'Supuestos'!$C$32-'Supuestos'!$C$33-'Supuestos'!$C$34)-C9*'Supuestos'!$C$35-'Supuestos'!$C$36-C7)/C9)) | D33: =IF(COUNT(D7:D18)<12,"",IF(D9=0,0,(D17*(1-'Supuestos'!$C$32-'Supuestos'!$C$33-'Supuestos'!$C$34)-D9*'Supuestos'!$C$35-'Supuestos'!$C$36-D7)/D9)) | E33: =IF(COUNT(E7:E18)<12,"",IF(E9=0,0,(E17*(1-'Supuestos'!$C$32-'Supuestos'!$C$33-'Supuestos'!$C$34)-E9*'Supuestos'!$C$35-'Supuestos'!$C$36-E7)/E9)) | F33: =IF(COUNT(F7:F18)<12,"",IF(F9=0,0,(F17*(1-'Supuestos'!$C$32-'Supuestos'!$C$33-'Supuestos'!$C$34)-F9*'Supuestos'!$C$35-'Supuestos'!$C$36-F7)/F9)) | G33: =IF(COUNT(G7:G18)<12,"",IF(G9=0,0,(G17*(1-'Supuestos'!$C$32-'Supuestos'!$C$33-'Supuestos'!$C$34)-G9*'Supuestos'!$C$35-'Supuestos'!$C$36-G7)/G9)) | H33: =IF(COUNT(H7:H18)<12,"",IF(H9=0,0,(H17*(1-'Supuestos'!$C$32-'Supuestos'!$C$33-'Supuestos'!$C$34)-H9*'Supuestos'!$C$35-'Supuestos'!$C$36-H7)/H9)) | I33: =IF(COUNT(I7:I18)<12,"",IF(I9=0,0,(I17*(1-'Supuestos'!$C$32-'Supuestos'!$C$33-'Supuestos'!$C$34)-I9*'Supuestos'!$C$35-'Supuestos'!$C$36-I7)/I9)) | J33: =IF(COUNT(J7:J18)<12,"",IF(J9=0,0,(J17*(1-'Supuestos'!$C$32-'Supuestos'!$C$33-'Supuestos'!$C$34)-J9*'Supuestos'!$C$35-'Supuestos'!$C$36-J7)/J9)) | ... N33: =IF(COUNT(N7:N18)<12,"",IF(N9=0,0,(N17*(1-'Supuestos'!$C$32-'Supuestos'!$C$33-'Supuestos'!$C$34)-N9*'Supuestos'!$C$35-'Supuestos'!$C$36-N7)/N9)) | O33: =IF(COUNT(C33:N33)=0,"",AVERAGE(C33:N33)) | P33: =IF(COUNT(C33:N33)=0,"",MAX(C33:N33)) | Q33: =IF(COUNT(C33:N33)=0,"",MIN(C33:N33))
B34: ROAS sobre cash neto (cobranza completa) | C34: =IF(COUNT(C7:C18)<12,"",IF(C7=0,0,C17*(1-'Supuestos'!$C$32-'Supuestos'!$C$33-'Supuestos'!$C$34)/C7)) | D34: =IF(COUNT(D7:D18)<12,"",IF(D7=0,0,D17*(1-'Supuestos'!$C$32-'Supuestos'!$C$33-'Supuestos'!$C$34)/D7)) | E34: =IF(COUNT(E7:E18)<12,"",IF(E7=0,0,E17*(1-'Supuestos'!$C$32-'Supuestos'!$C$33-'Supuestos'!$C$34)/E7)) | F34: =IF(COUNT(F7:F18)<12,"",IF(F7=0,0,F17*(1-'Supuestos'!$C$32-'Supuestos'!$C$33-'Supuestos'!$C$34)/F7)) | G34: =IF(COUNT(G7:G18)<12,"",IF(G7=0,0,G17*(1-'Supuestos'!$C$32-'Supuestos'!$C$33-'Supuestos'!$C$34)/G7)) | H34: =IF(COUNT(H7:H18)<12,"",IF(H7=0,0,H17*(1-'Supuestos'!$C$32-'Supuestos'!$C$33-'Supuestos'!$C$34)/H7)) | I34: =IF(COUNT(I7:I18)<12,"",IF(I7=0,0,I17*(1-'Supuestos'!$C$32-'Supuestos'!$C$33-'Supuestos'!$C$34)/I7)) | J34: =IF(COUNT(J7:J18)<12,"",IF(J7=0,0,J17*(1-'Supuestos'!$C$32-'Supuestos'!$C$33-'Supuestos'!$C$34)/J7)) | ... N34: =IF(COUNT(N7:N18)<12,"",IF(N7=0,0,N17*(1-'Supuestos'!$C$32-'Supuestos'!$C$33-'Supuestos'!$C$34)/N7)) | O34: =IF(COUNT(C34:N34)=0,"",AVERAGE(C34:N34)) | P34: =IF(COUNT(C34:N34)=0,"",MAX(C34:N34)) | Q34: =IF(COUNT(C34:N34)=0,"",MIN(C34:N34))
B35: ROAS de caja (cobrado hasta ahora) | C35: =IF(COUNT(C7:C18)<12,"",IF(C7=0,0,C18*(1-'Supuestos'!$C$32-'Supuestos'!$C$33-'Supuestos'!$C$34)/C7)) | D35: =IF(COUNT(D7:D18)<12,"",IF(D7=0,0,D18*(1-'Supuestos'!$C$32-'Supuestos'!$C$33-'Supuestos'!$C$34)/D7)) | E35: =IF(COUNT(E7:E18)<12,"",IF(E7=0,0,E18*(1-'Supuestos'!$C$32-'Supuestos'!$C$33-'Supuestos'!$C$34)/E7)) | F35: =IF(COUNT(F7:F18)<12,"",IF(F7=0,0,F18*(1-'Supuestos'!$C$32-'Supuestos'!$C$33-'Supuestos'!$C$34)/F7)) | G35: =IF(COUNT(G7:G18)<12,"",IF(G7=0,0,G18*(1-'Supuestos'!$C$32-'Supuestos'!$C$33-'Supuestos'!$C$34)/G7)) | H35: =IF(COUNT(H7:H18)<12,"",IF(H7=0,0,H18*(1-'Supuestos'!$C$32-'Supuestos'!$C$33-'Supuestos'!$C$34)/H7)) | I35: =IF(COUNT(I7:I18)<12,"",IF(I7=0,0,I18*(1-'Supuestos'!$C$32-'Supuestos'!$C$33-'Supuestos'!$C$34)/I7)) | J35: =IF(COUNT(J7:J18)<12,"",IF(J7=0,0,J18*(1-'Supuestos'!$C$32-'Supuestos'!$C$33-'Supuestos'!$C$34)/J7)) | ... N35: =IF(COUNT(N7:N18)<12,"",IF(N7=0,0,N18*(1-'Supuestos'!$C$32-'Supuestos'!$C$33-'Supuestos'!$C$34)/N7)) | O35: =IF(COUNT(C35:N35)=0,"",AVERAGE(C35:N35)) | P35: =IF(COUNT(C35:N35)=0,"",MAX(C35:N35)) | Q35: =IF(COUNT(C35:N35)=0,"",MIN(C35:N35))
B36: Techo móvil (mediana de tus últimas 4 columnas; al inicio, el del modelo) | C36: =IF(COUNT(C7:C18)<12,"",'Modelo'!$C$51) | D36: =IF(COUNT(D7:D18)<12,"",IF(COUNT(C30:C30)>0,MEDIAN(C30:C30),'Modelo'!$C$51)) | E36: =IF(COUNT(E7:E18)<12,"",IF(COUNT(C30:D30)>0,MEDIAN(C30:D30),'Modelo'!$C$51)) | F36: =IF(COUNT(F7:F18)<12,"",IF(COUNT(C30:E30)>0,MEDIAN(C30:E30),'Modelo'!$C$51)) | G36: =IF(COUNT(G7:G18)<12,"",IF(COUNT(C30:F30)>0,MEDIAN(C30:F30),'Modelo'!$C$51)) | H36: =IF(COUNT(H7:H18)<12,"",IF(COUNT(D30:G30)>0,MEDIAN(D30:G30),'Modelo'!$C$51)) | I36: =IF(COUNT(I7:I18)<12,"",IF(COUNT(E30:H30)>0,MEDIAN(E30:H30),'Modelo'!$C$51)) | J36: =IF(COUNT(J7:J18)<12,"",IF(COUNT(F30:I30)>0,MEDIAN(F30:I30),'Modelo'!$C$51)) | K36: =IF(COUNT(K7:K18)<12,"",IF(COUNT(G30:J30)>0,MEDIAN(G30:J30),'Modelo'!$C$51)) | L36: =IF(COUNT(L7:L18)<12,"",IF(COUNT(H30:K30)>0,MEDIAN(H30:K30),'Modelo'!$C$51)) | M36: =IF(COUNT(M7:M18)<12,"",IF(COUNT(I30:L30)>0,MEDIAN(I30:L30),'Modelo'!$C$51)) | N36: =IF(COUNT(N7:N18)<12,"",IF(COUNT(J30:M30)>0,MEDIAN(J30:M30),'Modelo'!$C$51)) | O36: =IF(COUNT(C36:N36)=0,"",AVERAGE(C36:N36)) | P36: =IF(COUNT(C36:N36)=0,"",MAX(C36:N36)) | Q36: =IF(COUNT(C36:N36)=0,"",MIN(C36:N36))
B37: Semáforo (costo por unidad contra el techo móvil, y ROAS contra el objetivo) | C37: =IF(COUNT(C7:C18)<12,"",IF(C20>C36,"ROJO",IF(AND(C20<=C36/(1+'Supuestos'!$C$45),C34>='Supuestos'!$C$44),"VERDE","AMARILLO"))) | D37: =IF(COUNT(D7:D18)<12,"",IF(D20>D36,"ROJO",IF(AND(D20<=D36/(1+'Supuestos'!$C$45),D34>='Supuestos'!$C$44),"VERDE","AMARILLO"))) | E37: =IF(COUNT(E7:E18)<12,"",IF(E20>E36,"ROJO",IF(AND(E20<=E36/(1+'Supuestos'!$C$45),E34>='Supuestos'!$C$44),"VERDE","AMARILLO"))) | F37: =IF(COUNT(F7:F18)<12,"",IF(F20>F36,"ROJO",IF(AND(F20<=F36/(1+'Supuestos'!$C$45),F34>='Supuestos'!$C$44),"VERDE","AMARILLO"))) | G37: =IF(COUNT(G7:G18)<12,"",IF(G20>G36,"ROJO",IF(AND(G20<=G36/(1+'Supuestos'!$C$45),G34>='Supuestos'!$C$44),"VERDE","AMARILLO"))) | H37: =IF(COUNT(H7:H18)<12,"",IF(H20>H36,"ROJO",IF(AND(H20<=H36/(1+'Supuestos'!$C$45),H34>='Supuestos'!$C$44),"VERDE","AMARILLO"))) | I37: =IF(COUNT(I7:I18)<12,"",IF(I20>I36,"ROJO",IF(AND(I20<=I36/(1+'Supuestos'!$C$45),I34>='Supuestos'!$C$44),"VERDE","AMARILLO"))) | J37: =IF(COUNT(J7:J18)<12,"",IF(J20>J36,"ROJO",IF(AND(J20<=J36/(1+'Supuestos'!$C$45),J34>='Supuestos'!$C$44),"VERDE","AMARILLO"))) | ... N37: =IF(COUNT(N7:N18)<12,"",IF(N20>N36,"ROJO",IF(AND(N20<=N36/(1+'Supuestos'!$C$45),N34>='Supuestos'!$C$44),"VERDE","AMARILLO")))

Sheet Benchmarks
B1: © Jesús Tassarolo · TooAudience · youtube.com/@JesusTassaroloSinFiltro · uso personal; no redistribuir modificado
B2: Benchmarks: contra qué comparar tus números
B3: Valores de referencia para tráfico frío en español. Son orden de magnitud, no objetivo: tus propios datos de Seguimiento mandan.
B5: Métrica | C5: Malo | D5: Aceptable | E5: Bueno | F5: Ganador | G5: Tu valor (Modelo) | H5: Fuente / nota
B6: ROAS del front (entradas + bump ÷ inversión) | C6: <0,5 | D6: 0,5 a 0,8 | E6: 0,8 a 1,2 | F6: >1,2 | G6: ='Modelo'!$C$14 | H6: Eventos pagos hispanos, 2025 a 2026. Cerca de 1 el evento se paga solo.
B7: % visitas → entrada | C7: <1 % | D7: 1 a 2 % | E7: 2 a 3,5 % | F7: >3,5 % | G7: ='Supuestos'!$C$13 | H7: Página de ventas de 5 a 15 USD.
B8: Costo por entrada (USD) | C8: >25 | D8: 15 a 25 | E8: 8 a 15 | F8: <8 | G8: ='Modelo'!$C$8 | H8: Depende del precio: compará contra tu precio de entrada.
B9: % entrada → en vivo | C9: <35 % | D9: 35 a 50 % | E9: 50 a 65 % | F9: >65 % | G9: ='Supuestos'!$C$20 | H9: Pagaron: asisten mucho más que en gratuito (10 a 20 %).
B10: Costo por persona en el grupo (USD) | C10: >30 | D10: 18 a 30 | E10: 10 a 18 | F10: <10 | G10: ='Modelo'!$C$17 | H10: Sobre compradores de entrada: casi todos entran.
B11: % asistentes en vivo que solicitan | C11: <8 % | D11: 8 a 14 % | E11: 14 a 22 % | F11: >22 % | G11: ='Supuestos'!$C$25 | H11: Público que pagó por estar: solicita más que en gratuito.
B12: Costo por solicitud (USD) | C12: >250 | D12: 150 a 250 | E12: 80 a 150 | F12: <80 | G12: ='Modelo'!$C$26 | H12: Oferta de 300 a 1.000.
B13: % solicitud → compra | C13: <35 % | D13: 35 a 50 % | E13: 50 a 65 % | F13: >65 % | G13: ='Supuestos'!$C$27 | H13: Con vendedor: 40 a 60 %. Compra directa en el formulario: más alto.
B14: % entrada → oferta (total) | C14: <3 % | D14: 3 a 6 % | E14: 6 a 10 % | F14: >10 % | G14: ='Modelo'!$C$28 | H14: Vivo + replay.
B15: ROAS total sobre cash neto | C15: <1,3 | D15: 1,3 a 2 | E15: 2 a 3 | F15: >3 | G15: ='Modelo'!$C$46 | H15: Por lanzamiento, cobranza completa.

Sheet Glosario
B1: © Jesús Tassarolo · TooAudience · youtube.com/@JesusTassaroloSinFiltro · uso personal; no redistribuir modificado
B2: Glosario
B3: Los términos que usa este modelo, en el orden del embudo.
B5: Término | C5: Qué es | D5: Dónde aparece
B6: CPM | C6: Costo por mil impresiones: lo que cobra la plataforma de anuncios por mostrar el aviso mil veces. | D6: Supuestos
B7: CTR | C7: Porcentaje de impresiones que terminan en clic al enlace. | D7: Supuestos
B8: Clic → visita | C8: Porcentaje de clics que llegan a cargar la página. Siempre menor a 100 % (cierran antes de que cargue). | D8: Supuestos
B9: Unidad de adquisición | C9: Lo que compra la publicidad en este embudo (visita, registro o entrada). Todo el modelo se mide por unidad. | D9: Modelo
B10: Costo por unidad | C10: Inversión dividida por unidades compradas: costo por visita, CPL (costo por lead o registro) o costo por entrada. | D10: Modelo, Seguimiento
B11: Conversión | C11: Porcentaje que pasa de una etapa a la siguiente. Las conversiones se multiplican: 15 % × 14 % × 44 % = 0,9 %. | D11: Supuestos, Modelo
B12: Show rate | C12: Porcentaje de registrados (o compradores) que asisten en vivo. El replay se cuenta aparte. | D12: Supuestos
B13: Bump | C13: Oferta extra en el mismo checkout, con una casilla. Se mide como % de los compradores. | D13: Supuestos
B14: OTO / upsell | C14: Oferta que aparece después de pagar (one-time offer). Downsell: la oferta más barata para quien rechaza la OTO. | D14: Supuestos
B15: Backend | C15: Producto de mayor valor que se vende después del primero, por ascenso o por llamada. | D15: Supuestos
B16: AOV | C16: Facturado promedio por comprador del producto principal, sumando toda la escalera. | D16: Modelo
... B43: Solicitud | C43: Lo que hace el asistente cuando se presenta la oferta: completa el formulario de compra, la aplicación, o pide hablar con un vendedor. Se mide en cantidad, costo por solicitud y % sobre asistentes en vivo. | D43: Modelo, Seguimiento

Sheet Chequeos
B1: © Jesús Tassarolo · TooAudience · youtube.com/@JesusTassaroloSinFiltro · uso personal; no redistribuir modificado
B2: Chequeos: el modelo se revisa solo
B3: Si alguna fila dice REVISAR, hay un supuesto fuera de rango o un dato inconsistente.
B5: Chequeo | C5: Estado | D5: Qué revisar
B6: Ninguna celda con error en Modelo | C6: =IF(ISERROR(SUM('Modelo'!C5:C160)),"REVISAR","OK") | D6: Si dice REVISAR, hay un #DIV/0! o #REF!: casi siempre un supuesto en 0 o una fila borrada.
B7: Ninguna celda con error en Simulador | C7: =IF(ISERROR(SUM('Simulador'!C5:G220)),"REVISAR","OK") | D7: Si dice REVISAR, hay un #DIV/0! o #REF!: casi siempre un supuesto en 0 o una fila borrada.
B8: Ninguna celda con error en Embudo | C8: =IF(ISERROR(SUM('Embudo'!C5:H60)),"REVISAR","OK") | D8: Si dice REVISAR, hay un #DIV/0! o #REF!: casi siempre un supuesto en 0 o una fila borrada.
B9: Ninguna celda con error en Resumen | C9: =IF(ISERROR(SUM('Resumen'!C5:C60)),"REVISAR","OK") | D9: Si dice REVISAR, hay un #DIV/0! o #REF!: casi siempre un supuesto en 0 o una fila borrada.
B10: Ninguna celda con error en Proyección 12 meses | C10: =IF(ISERROR(SUM('Proyección 12 meses'!C5:O40)),"REVISAR","OK") | D10: Si dice REVISAR, hay un #DIV/0! o #REF!: casi siempre un supuesto en 0 o una fila borrada.
B11: Ninguna celda con error en Escenarios | C11: =IF(ISERROR(SUM('Escenarios'!C5:L120)),"REVISAR","OK") | D11: Si dice REVISAR, hay un #DIV/0! o #REF!: casi siempre un supuesto en 0 o una fila borrada.
B12: Ninguna celda con error en Seguimiento | C12: =IF(ISERROR(SUM('Seguimiento'!C5:Q80)),"REVISAR","OK") | D12: Si dice REVISAR, hay un #DIV/0! o #REF!: casi siempre un supuesto en 0 o una fila borrada.
B13: Los supuestos de tráfico son mayores a cero | C13: =IF(AND('Supuestos'!$C$10>0,'Supuestos'!$C$13>0),"OK","REVISAR") | D13: Con un 0 en el tráfico o en la conversión de la página no hay unidades y el modelo no dice nada.
B14: La curva de cobranza suma 100 % | C14: =IF(ABS('Supuestos'!$C$39+'Supuestos'!$C$40+'Supuestos'!$C$41-1)<0.001,"OK","REVISAR") | D14: Supuestos → cobranza mes 1 + mes 2 + mes 3 = 100 %.
B15: Comisiones + reembolsos menores al 60 % | C15: =IF(('Supuestos'!$C$32+'Supuestos'!$C$33+'Supuestos'!$C$34)<0.6,"OK","REVISAR") | D15: Si suman más, revisá los porcentajes.
B16: El escenario en uso es 1, 2 o 3 | C16: =IF(OR('Supuestos'!$C$6=1,'Supuestos'!$C$6=2,'Supuestos'!$C$6=3),"OK","REVISAR") | D16: Supuestos → celda 'Escenario en uso'.
B17: La inversión es mayor a cero | C17: =IF('Supuestos'!$C$8>0,"OK","REVISAR")
B18: La meta de ventas es alcanzable (hay conversión a venta) | C18: =IF('Modelo'!$C$28>0,"OK","REVISAR") | D18: Con conversión a venta en 0, la inversión para la meta dice 'inalcanzable con estos supuestos'.
B19: Las conversiones están entre 0 y 100 % | C19: =IF(AND('Supuestos'!$C$13>=0,'Supuestos'!$C$13<=1,'Supuestos'!$C$16>=0,'Supuestos'!$C$16<=1,'Supuestos'!$C$19>=0,'Supuestos'!$C$19<=1,'Supuestos'!$C$20>=0,'Supuestos'!$C$20<=1,'Supuestos'!$C$21>=0,'Supuestos'!$C$21<=1,'Supuestos'!$C$25>=0,'Supuestos'!$C$25<=1,'Supuestos'!$C$26>=0,'Supuestos'!$C$26<=1,'Supuestos'!$C$27>=0,'Supuestos'!$C$27<=1,'Supuestos'!$C$29>=0,'Supuestos'!$C$29<=1),"OK","REVISAR") | D19: Un 25 % se escribe 25 % (o 0,25), no 25.
B20: El margen de seguridad está entre 0 y 100 % | C20: =IF(AND('Supuestos'!$C$45>=0,'Supuestos'!$C$45<=1),"OK","REVISAR")
B21: El crecimiento mensual está entre −50 % y 100 % | C21: =IF(AND('Supuestos'!$C$47>=-0.5,'Supuestos'!$C$47<=1),"OK","REVISAR") | D21: Más de 100 % por mes no es realista para una proyección.
B22: La cadena es decreciente (cada etapa tiene menos gente que la anterior) | C22: =IF(AND('Modelo'!$C$9<='Modelo'!$C$7,'Modelo'!$C$18<='Modelo'!$C$9,'Modelo'!$C$22<='Modelo'!$C$18,'Modelo'!$C$23<='Modelo'!$C$19,'Modelo'!$C$27<='Modelo'!$C$24),"OK","REVISAR") | D22: Si falla, alguna conversión está por encima de 100 %.
B23: En vivo + replay no superan el 100 % de los compradores | C23: =IF(('Supuestos'!$C$20+'Supuestos'!$C$21)<=1,"OK","REVISAR") | D23: El replay se cuenta sin los que fueron en vivo.
B25: Estado general del modelo | C25: =IF(COUNTIF(C6:C23,"REVISAR")=0,"OK","REVISAR")

Sheet Licencia
B2: Autoría y licencia
B4: Modelo financiero · Embudo de webinar pago (evento pago)
B5: Modelo financiero de embudos · creado por Jesús Tassarolo · TooAudience · youtube.com/@JesusTassaroloSinFiltro
B6: v1.2 · octubre 2026
B8: Licencia Creative Commons BY-NC-ND 4.0: podés usar este archivo con tus números y compartirlo tal cual, citando al autor. No podés venderlo, modificar su estructura para redistribuirlo ni quitar la línea de autoría.
B10: Este archivo, sus fórmulas, sus umbrales y su método son obra de Jesús Tassarolo (TooAudience). Si lo compartís, compartilo entero y con esta hoja.
B11: Canal: youtube.com/@JesusTassaroloSinFiltro
