Workbook
Name Autor_Jesus_Tassarolo: "Modelo financiero de embudos · creado por Jesús Tassarolo · TooAudience · youtube.com/@JesusTassaroloSinFiltro"

Sheet Inicio
B1: © Jesús Tassarolo · TooAudience · youtube.com/@JesusTassaroloSinFiltro · uso personal; no redistribuir modificado
B2: Métricas diarias · Embudo low-ticket con VSL, bumps y OTOs
B3: Las métricas diarias de todo el embudo, para saber cómo estás con tus propios números. Acompaña al modelo financiero del mismo embudo.
B5: Qué es
B6: Un registro diario de cada paso del embudo (anuncios, página, unidades, etapas, ventas, cash) que se convierte solo en un comparativo semanal y en un resumen con semáforo. El semáforo no usa números de mercado: compara cada semana con la mediana de tus 4 semanas anteriores, con una tolerancia del 25 % (la cambiás en Config).
B8: 1. Config
B9: Poné tus precios, comisiones, reembolsos, costos fijos por día y la fecha de inicio (un lunes). Todo lo demás se calcula con eso.
B11: 2. Diario (todos los días, 3 minutos)
B12: Una fila por día. Cargá las celdas amarillas con lo que hubo: inversión, impresiones, alcance, clics en el enlace, visitas y cada paso del embudo. Si un día no hubo evento, dejá vacío. Las celdas azules se calculan solas (CPM, CTR, costo por visita, CPL, conversiones, facturado, cash neto, ganancia, ROAS y la ganancia por visita).
B14: 3. Semanal (los lunes, 10 minutos)
B15: No se carga nada: suma Diario por semana y calcula las conversiones y los costos de la semana, el promedio, la mediana, la mejor y la peor. Abajo, el bloque «contra tu promedio» marca en verde, amarillo o rojo cada métrica clave contra la mediana de tus 4 semanas anteriores.
B17: 4. Resumen
... B36: Modelo financiero de embudos · creado por Jesús Tassarolo · TooAudience · youtube.com/@JesusTassaroloSinFiltro · v1.2 · octubre 2026

Sheet Config
B1: © Jesús Tassarolo · TooAudience · youtube.com/@JesusTassaroloSinFiltro · uso personal; no redistribuir modificado
B2: Config: tus precios, comisiones y la fecha de inicio
B3: Amarillo = podés cambiarlo. Todo lo demás del libro se calcula con esto.
B5: Dato | C5: Valor | D5: Nota
B6: Fecha de inicio del registro (un lunes) | C6: 46272 | D6: Desde este día se numeran las semanas en Diario y Semanal. Elegí un lunes.
B7: Precio del producto principal | C7: 37
B8: Precio del bump 1 | C8: 17
B9: Precio del bump 2 | C9: 17
B10: Precio de la OTO 1 | C10: 47
B11: Precio de la OTO 2 | C11: 17
B12: Precio de la OTO 3 | C12: 97
B13: Precio de la OTO 4 | C13: 27
B14: Precio del programa (ascensión) | C14: 297
B15: Comisión de la pasarela de pago | C15: 0.1 | D15: Lo que se queda la plataforma de cobro.
B16: Comisión del equipo de ventas | C16: 0 | D16: Si vendés por llamada: lo que cobra el closer sobre lo cobrado.
B17: Reembolsos y contracargos | C17: 0.05 | D17: Promedio histórico. 5 % es normal en productos digitales.
B18: Costos fijos por día (USD) | C18: 50 | D18: Equipo, herramientas, edición: lo que pagás aunque no vendas, dividido por 30.
B19: ROAS objetivo sobre cash neto | C19: 2 | D19: El retorno mínimo que querés por cada dólar, ya neto.
B20: Tolerancia del semáforo contra tu promedio | C20: 0.25 | D20: Igual o mejor que tu mediana = verde; hasta esta distancia peor = amarillo; más = rojo. 20 a 30 %.
A23: Modelo financiero de embudos · creado por Jesús Tassarolo · TooAudience · youtube.com/@JesusTassaroloSinFiltro · v1.2 · octubre 2026

Sheet Diario
A1: © Jesús Tassarolo · TooAudience · youtube.com/@JesusTassaroloSinFiltro · uso personal; no redistribuir modificado
A2: Diario: una fila por día. Amarillo = lo que cargás; azul = lo que calcula el libro
A3: Cargá cada día lo que hubo (vacío si no hubo). Los porcentajes de un solo día pueden ser raros en embudos con evento semanal: la lectura buena está en Semanal.
A5: Fecha | B5: Semana | C5: Inversión en publicidad (USD) | D5: Impresiones | E5: Alcance (personas únicas) | F5: Clics en el enlace | G5: Visitas a la página | H5: Inician el checkout | I5: Compran el producto principal | J5: Toman el bump 1 | K5: Toman el bump 2 | L5: Toman la OTO 1 | M5: Toman la OTO 2 | N5: Toman la OTO 3 | O5: Toman la OTO 4 | P5: Ascienden al programa | Q5: CPM | R5: Frecuencia | S5: CTR al enlace | T5: CPC (por clic en el enlace) | U5: % clic → visita | V5: Costo por visita | W5: Visitas por cada 1.000 impresiones | X5: % visita → checkout | Y5: % checkout → compra | Z5: % visita → compra | AA5: CPA (costo por comprador) | AB5: % toman el bump 1 | AC5: % toman el bump 2 | AD5: % toman la OTO 1 | AE5: % ascienden | AF5: Facturado (toda la escalera) | AG5: Order value (facturado por comprador) | AH5: Cash neto (después de comisiones y reembolsos) | AI5: Ganancia (cash neto − pauta − fijos) | AJ5: ROAS sobre cash neto | AK5: Ganancia por visita (la métrica más valiosa) | AL5: Margen por visita (ganancia por visita ÷ costo por visita) | AM5: Ganancia por comprador | AN5: AOV neto − CPA (lo que queda por comprador)
A6: =Config!$C$6+0 | B6: =INT((A6-Config!$C$6)/7)+1 | C6: 297 | D6: 69614 | E6: 39488 | F6: 1070 | G6: 965 | H6: 34 | I6: 8 | J6: 2 | K6: 1 | L6: 1 | M6: 0 | N6: 0 | O6: 0 | P6: 0 | Q6: =IF(COUNT(C6:P6)=0,"",IFERROR(C6/D6*1000,0)) | R6: =IF(COUNT(C6:P6)=0,"",IFERROR(D6/E6,0)) | S6: =IF(COUNT(C6:P6)=0,"",IFERROR(F6/D6,0)) | T6: =IF(COUNT(C6:P6)=0,"",IFERROR(C6/F6,0)) | U6: =IF(COUNT(C6:P6)=0,"",IFERROR(G6/F6,0)) | V6: =IF(COUNT(C6:P6)=0,"",IFERROR(C6/G6,0)) | W6: =IF(COUNT(C6:P6)=0,"",IFERROR(G6/D6*1000,0)) | X6: =IF(COUNT(C6:P6)=0,"",IFERROR(H6/G6,0)) | Y6: =IF(COUNT(C6:P6)=0,"",IFERROR(I6/H6,0)) | Z6: =IF(COUNT(C6:P6)=0,"",IFERROR(I6/G6,0)) | AA6: =IF(COUNT(C6:P6)=0,"",IFERROR(C6/I6,0)) | AB6: =IF(COUNT(C6:P6)=0,"",IFERROR(J6/I6,0)) | AC6: =IF(COUNT(C6:P6)=0,"",IFERROR(K6/I6,0)) | AD6: =IF(COUNT(C6:P6)=0,"",IFERROR(L6/I6,0)) | AE6: =IF(COUNT(C6:P6)=0,"",IFERROR(P6/I6,0)) | AF6: =IF(COUNT(C6:P6)=0,"",IFERROR(I6*Config!$C$7+J6*Config!$C$8+K6*Config!$C$9+L6*Config!$C$10+M6*Config!$C$11+N6*Config!$C$12+O6*Config!$C$13+P6*Config!$C$14,0)) | AG6: =IF(COUNT(C6:P6)=0,"",IFERROR(AF6/I6,0)) | AH6: =IF(COUNT(C6:P6)=0,"",IFERROR(AF6*(1-Config!$C$15-Config!$C$16-Config!$C$17),0)) | AI6: =IF(COUNT(C6:P6)=0,"",IFERROR(AH6-C6-Config!$C$18,0)) | AJ6: =IF(COUNT(C6:P6)=0,"",IFERROR(AH6/C6,0)) | AK6: =IF(COUNT(C6:P6)=0,"",IFERROR(AI6/G6,0)) | AL6: =IF(COUNT(C6:P6)=0,"",IFERROR(AK6/V6,0)) | AM6: =IF(COUNT(C6:P6)=0,"",IFERROR(AI6/I6,0)) | AN6: =IF(COUNT(C6:P6)=0,"",IFERROR(AH6/I6-AA6,0))
A7: =Config!$C$6+1 | B7: =INT((A7-Config!$C$6)/7)+1 | C7: 301 | D7: 69467 | E7: 40565 | F7: 972 | G7: 833 | H7: 26 | I7: 7 | J7: 2 | K7: 1 | L7: 1 | M7: 0 | N7: 0 | O7: 0 | P7: 0 | Q7: =IF(COUNT(C7:P7)=0,"",IFERROR(C7/D7*1000,0)) | R7: =IF(COUNT(C7:P7)=0,"",IFERROR(D7/E7,0)) | S7: =IF(COUNT(C7:P7)=0,"",IFERROR(F7/D7,0)) | T7: =IF(COUNT(C7:P7)=0,"",IFERROR(C7/F7,0)) | U7: =IF(COUNT(C7:P7)=0,"",IFERROR(G7/F7,0)) | V7: =IF(COUNT(C7:P7)=0,"",IFERROR(C7/G7,0)) | W7: =IF(COUNT(C7:P7)=0,"",IFERROR(G7/D7*1000,0)) | X7: =IF(COUNT(C7:P7)=0,"",IFERROR(H7/G7,0)) | Y7: =IF(COUNT(C7:P7)=0,"",IFERROR(I7/H7,0)) | Z7: =IF(COUNT(C7:P7)=0,"",IFERROR(I7/G7,0)) | AA7: =IF(COUNT(C7:P7)=0,"",IFERROR(C7/I7,0)) | AB7: =IF(COUNT(C7:P7)=0,"",IFERROR(J7/I7,0)) | AC7: =IF(COUNT(C7:P7)=0,"",IFERROR(K7/I7,0)) | AD7: =IF(COUNT(C7:P7)=0,"",IFERROR(L7/I7,0)) | AE7: =IF(COUNT(C7:P7)=0,"",IFERROR(P7/I7,0)) | AF7: =IF(COUNT(C7:P7)=0,"",IFERROR(I7*Config!$C$7+J7*Config!$C$8+K7*Config!$C$9+L7*Config!$C$10+M7*Config!$C$11+N7*Config!$C$12+O7*Config!$C$13+P7*Config!$C$14,0)) | AG7: =IF(COUNT(C7:P7)=0,"",IFERROR(AF7/I7,0)) | AH7: =IF(COUNT(C7:P7)=0,"",IFERROR(AF7*(1-Config!$C$15-Config!$C$16-Config!$C$17),0)) | AI7: =IF(COUNT(C7:P7)=0,"",IFERROR(AH7-C7-Config!$C$18,0)) | AJ7: =IF(COUNT(C7:P7)=0,"",IFERROR(AH7/C7,0)) | AK7: =IF(COUNT(C7:P7)=0,"",IFERROR(AI7/G7,0)) | AL7: =IF(COUNT(C7:P7)=0,"",IFERROR(AK7/V7,0)) | AM7: =IF(COUNT(C7:P7)=0,"",IFERROR(AI7/I7,0)) | AN7: =IF(COUNT(C7:P7)=0,"",IFERROR(AH7/I7-AA7,0))
A8: =Config!$C$6+2 | B8: =INT((A8-Config!$C$6)/7)+1 | C8: 314 | D8: 83978 | E8: 47042 | F8: 1447 | G8: 1350 | H8: 49 | I8: 12 | J8: 3 | K8: 2 | L8: 1 | M8: 1 | N8: 0 | O8: 0 | P8: 0 | Q8: =IF(COUNT(C8:P8)=0,"",IFERROR(C8/D8*1000,0)) | R8: =IF(COUNT(C8:P8)=0,"",IFERROR(D8/E8,0)) | S8: =IF(COUNT(C8:P8)=0,"",IFERROR(F8/D8,0)) | T8: =IF(COUNT(C8:P8)=0,"",IFERROR(C8/F8,0)) | U8: =IF(COUNT(C8:P8)=0,"",IFERROR(G8/F8,0)) | V8: =IF(COUNT(C8:P8)=0,"",IFERROR(C8/G8,0)) | W8: =IF(COUNT(C8:P8)=0,"",IFERROR(G8/D8*1000,0)) | X8: =IF(COUNT(C8:P8)=0,"",IFERROR(H8/G8,0)) | Y8: =IF(COUNT(C8:P8)=0,"",IFERROR(I8/H8,0)) | Z8: =IF(COUNT(C8:P8)=0,"",IFERROR(I8/G8,0)) | AA8: =IF(COUNT(C8:P8)=0,"",IFERROR(C8/I8,0)) | AB8: =IF(COUNT(C8:P8)=0,"",IFERROR(J8/I8,0)) | AC8: =IF(COUNT(C8:P8)=0,"",IFERROR(K8/I8,0)) | AD8: =IF(COUNT(C8:P8)=0,"",IFERROR(L8/I8,0)) | AE8: =IF(COUNT(C8:P8)=0,"",IFERROR(P8/I8,0)) | AF8: =IF(COUNT(C8:P8)=0,"",IFERROR(I8*Config!$C$7+J8*Config!$C$8+K8*Config!$C$9+L8*Config!$C$10+M8*Config!$C$11+N8*Config!$C$12+O8*Config!$C$13+P8*Config!$C$14,0)) | AG8: =IF(COUNT(C8:P8)=0,"",IFERROR(AF8/I8,0)) | AH8: =IF(COUNT(C8:P8)=0,"",IFERROR(AF8*(1-Config!$C$15-Config!$C$16-Config!$C$17),0)) | AI8: =IF(COUNT(C8:P8)=0,"",IFERROR(AH8-C8-Config!$C$18,0)) | AJ8: =IF(COUNT(C8:P8)=0,"",IFERROR(AH8/C8,0)) | AK8: =IF(COUNT(C8:P8)=0,"",IFERROR(AI8/G8,0)) | AL8: =IF(COUNT(C8:P8)=0,"",IFERROR(AK8/V8,0)) | AM8: =IF(COUNT(C8:P8)=0,"",IFERROR(AI8/I8,0)) | AN8: =IF(COUNT(C8:P8)=0,"",IFERROR(AH8/I8-AA8,0))
A9: =Config!$C$6+3 | B9: =INT((A9-Config!$C$6)/7)+1 | C9: 265 | D9: 62687 | E9: 43811 | F9: 899 | G9: 759 | H9: 24 | I9: 6 | J9: 2 | K9: 1 | L9: 1 | M9: 0 | N9: 0 | O9: 0 | P9: 0 | Q9: =IF(COUNT(C9:P9)=0,"",IFERROR(C9/D9*1000,0)) | R9: =IF(COUNT(C9:P9)=0,"",IFERROR(D9/E9,0)) | S9: =IF(COUNT(C9:P9)=0,"",IFERROR(F9/D9,0)) | T9: =IF(COUNT(C9:P9)=0,"",IFERROR(C9/F9,0)) | U9: =IF(COUNT(C9:P9)=0,"",IFERROR(G9/F9,0)) | V9: =IF(COUNT(C9:P9)=0,"",IFERROR(C9/G9,0)) | W9: =IF(COUNT(C9:P9)=0,"",IFERROR(G9/D9*1000,0)) | X9: =IF(COUNT(C9:P9)=0,"",IFERROR(H9/G9,0)) | Y9: =IF(COUNT(C9:P9)=0,"",IFERROR(I9/H9,0)) | Z9: =IF(COUNT(C9:P9)=0,"",IFERROR(I9/G9,0)) | AA9: =IF(COUNT(C9:P9)=0,"",IFERROR(C9/I9,0)) | AB9: =IF(COUNT(C9:P9)=0,"",IFERROR(J9/I9,0)) | AC9: =IF(COUNT(C9:P9)=0,"",IFERROR(K9/I9,0)) | AD9: =IF(COUNT(C9:P9)=0,"",IFERROR(L9/I9,0)) | AE9: =IF(COUNT(C9:P9)=0,"",IFERROR(P9/I9,0)) | AF9: =IF(COUNT(C9:P9)=0,"",IFERROR(I9*Config!$C$7+J9*Config!$C$8+K9*Config!$C$9+L9*Config!$C$10+M9*Config!$C$11+N9*Config!$C$12+O9*Config!$C$13+P9*Config!$C$14,0)) | AG9: =IF(COUNT(C9:P9)=0,"",IFERROR(AF9/I9,0)) | AH9: =IF(COUNT(C9:P9)=0,"",IFERROR(AF9*(1-Config!$C$15-Config!$C$16-Config!$C$17),0)) | AI9: =IF(COUNT(C9:P9)=0,"",IFERROR(AH9-C9-Config!$C$18,0)) | AJ9: =IF(COUNT(C9:P9)=0,"",IFERROR(AH9/C9,0)) | AK9: =IF(COUNT(C9:P9)=0,"",IFERROR(AI9/G9,0)) | AL9: =IF(COUNT(C9:P9)=0,"",IFERROR(AK9/V9,0)) | AM9: =IF(COUNT(C9:P9)=0,"",IFERROR(AI9/I9,0)) | AN9: =IF(COUNT(C9:P9)=0,"",IFERROR(AH9/I9-AA9,0))
A10: =Config!$C$6+4 | B10: =INT((A10-Config!$C$6)/7)+1 | C10: 296 | D10: 65062 | E10: 40478 | F10: 1042 | G10: 938 | H10: 34 | I10: 9 | J10: 2 | K10: 2 | L10: 1 | M10: 1 | N10: 0 | O10: 0 | P10: 0 | Q10: =IF(COUNT(C10:P10)=0,"",IFERROR(C10/D10*1000,0)) | R10: =IF(COUNT(C10:P10)=0,"",IFERROR(D10/E10,0)) | S10: =IF(COUNT(C10:P10)=0,"",IFERROR(F10/D10,0)) | T10: =IF(COUNT(C10:P10)=0,"",IFERROR(C10/F10,0)) | U10: =IF(COUNT(C10:P10)=0,"",IFERROR(G10/F10,0)) | V10: =IF(COUNT(C10:P10)=0,"",IFERROR(C10/G10,0)) | W10: =IF(COUNT(C10:P10)=0,"",IFERROR(G10/D10*1000,0)) | X10: =IF(COUNT(C10:P10)=0,"",IFERROR(H10/G10,0)) | Y10: =IF(COUNT(C10:P10)=0,"",IFERROR(I10/H10,0)) | Z10: =IF(COUNT(C10:P10)=0,"",IFERROR(I10/G10,0)) | AA10: =IF(COUNT(C10:P10)=0,"",IFERROR(C10/I10,0)) | AB10: =IF(COUNT(C10:P10)=0,"",IFERROR(J10/I10,0)) | AC10: =IF(COUNT(C10:P10)=0,"",IFERROR(K10/I10,0)) | AD10: =IF(COUNT(C10:P10)=0,"",IFERROR(L10/I10,0)) | AE10: =IF(COUNT(C10:P10)=0,"",IFERROR(P10/I10,0)) | AF10: =IF(COUNT(C10:P10)=0,"",IFERROR(I10*Config!$C$7+J10*Config!$C$8+K10*Config!$C$9+L10*Config!$C$10+M10*Config!$C$11+N10*Config!$C$12+O10*Config!$C$13+P10*Config!$C$14,0)) | AG10: =IF(COUNT(C10:P10)=0,"",IFERROR(AF10/I10,0)) | AH10: =IF(COUNT(C10:P10)=0,"",IFERROR(AF10*(1-Config!$C$15-Config!$C$16-Config!$C$17),0)) | AI10: =IF(COUNT(C10:P10)=0,"",IFERROR(AH10-C10-Config!$C$18,0)) | AJ10: =IF(COUNT(C10:P10)=0,"",IFERROR(AH10/C10,0)) | AK10: =IF(COUNT(C10:P10)=0,"",IFERROR(AI10/G10,0)) | AL10: =IF(COUNT(C10:P10)=0,"",IFERROR(AK10/V10,0)) | AM10: =IF(COUNT(C10:P10)=0,"",IFERROR(AI10/I10,0)) | AN10: =IF(COUNT(C10:P10)=0,"",IFERROR(AH10/I10-AA10,0))
A11: =Config!$C$6+5 | B11: =INT((A11-Config!$C$6)/7)+1 | C11: 284 | D11: 60410 | E11: 33742 | F11: 1013 | G11: 957 | H11: 32 | I11: 8 | J11: 2 | K11: 1 | L11: 1 | M11: 0 | N11: 0 | O11: 0 | P11: 0 | Q11: =IF(COUNT(C11:P11)=0,"",IFERROR(C11/D11*1000,0)) | R11: =IF(COUNT(C11:P11)=0,"",IFERROR(D11/E11,0)) | S11: =IF(COUNT(C11:P11)=0,"",IFERROR(F11/D11,0)) | T11: =IF(COUNT(C11:P11)=0,"",IFERROR(C11/F11,0)) | U11: =IF(COUNT(C11:P11)=0,"",IFERROR(G11/F11,0)) | V11: =IF(COUNT(C11:P11)=0,"",IFERROR(C11/G11,0)) | W11: =IF(COUNT(C11:P11)=0,"",IFERROR(G11/D11*1000,0)) | X11: =IF(COUNT(C11:P11)=0,"",IFERROR(H11/G11,0)) | Y11: =IF(COUNT(C11:P11)=0,"",IFERROR(I11/H11,0)) | Z11: =IF(COUNT(C11:P11)=0,"",IFERROR(I11/G11,0)) | AA11: =IF(COUNT(C11:P11)=0,"",IFERROR(C11/I11,0)) | AB11: =IF(COUNT(C11:P11)=0,"",IFERROR(J11/I11,0)) | AC11: =IF(COUNT(C11:P11)=0,"",IFERROR(K11/I11,0)) | AD11: =IF(COUNT(C11:P11)=0,"",IFERROR(L11/I11,0)) | AE11: =IF(COUNT(C11:P11)=0,"",IFERROR(P11/I11,0)) | AF11: =IF(COUNT(C11:P11)=0,"",IFERROR(I11*Config!$C$7+J11*Config!$C$8+K11*Config!$C$9+L11*Config!$C$10+M11*Config!$C$11+N11*Config!$C$12+O11*Config!$C$13+P11*Config!$C$14,0)) | AG11: =IF(COUNT(C11:P11)=0,"",IFERROR(AF11/I11,0)) | AH11: =IF(COUNT(C11:P11)=0,"",IFERROR(AF11*(1-Config!$C$15-Config!$C$16-Config!$C$17),0)) | AI11: =IF(COUNT(C11:P11)=0,"",IFERROR(AH11-C11-Config!$C$18,0)) | AJ11: =IF(COUNT(C11:P11)=0,"",IFERROR(AH11/C11,0)) | AK11: =IF(COUNT(C11:P11)=0,"",IFERROR(AI11/G11,0)) | AL11: =IF(COUNT(C11:P11)=0,"",IFERROR(AK11/V11,0)) | AM11: =IF(COUNT(C11:P11)=0,"",IFERROR(AI11/I11,0)) | AN11: =IF(COUNT(C11:P11)=0,"",IFERROR(AH11/I11-AA11,0))
A12: =Config!$C$6+6 | B12: =INT((A12-Config!$C$6)/7)+1 | C12: 285 | D12: 75611 | E12: 44418 | F12: 1144 | G12: 1115 | H12: 38 | I12: 11 | J12: 3 | K12: 2 | L12: 1 | M12: 1 | N12: 0 | O12: 0 | P12: 0 | Q12: =IF(COUNT(C12:P12)=0,"",IFERROR(C12/D12*1000,0)) | R12: =IF(COUNT(C12:P12)=0,"",IFERROR(D12/E12,0)) | S12: =IF(COUNT(C12:P12)=0,"",IFERROR(F12/D12,0)) | T12: =IF(COUNT(C12:P12)=0,"",IFERROR(C12/F12,0)) | U12: =IF(COUNT(C12:P12)=0,"",IFERROR(G12/F12,0)) | V12: =IF(COUNT(C12:P12)=0,"",IFERROR(C12/G12,0)) | W12: =IF(COUNT(C12:P12)=0,"",IFERROR(G12/D12*1000,0)) | X12: =IF(COUNT(C12:P12)=0,"",IFERROR(H12/G12,0)) | Y12: =IF(COUNT(C12:P12)=0,"",IFERROR(I12/H12,0)) | Z12: =IF(COUNT(C12:P12)=0,"",IFERROR(I12/G12,0)) | AA12: =IF(COUNT(C12:P12)=0,"",IFERROR(C12/I12,0)) | AB12: =IF(COUNT(C12:P12)=0,"",IFERROR(J12/I12,0)) | AC12: =IF(COUNT(C12:P12)=0,"",IFERROR(K12/I12,0)) | AD12: =IF(COUNT(C12:P12)=0,"",IFERROR(L12/I12,0)) | AE12: =IF(COUNT(C12:P12)=0,"",IFERROR(P12/I12,0)) | AF12: =IF(COUNT(C12:P12)=0,"",IFERROR(I12*Config!$C$7+J12*Config!$C$8+K12*Config!$C$9+L12*Config!$C$10+M12*Config!$C$11+N12*Config!$C$12+O12*Config!$C$13+P12*Config!$C$14,0)) | AG12: =IF(COUNT(C12:P12)=0,"",IFERROR(AF12/I12,0)) | AH12: =IF(COUNT(C12:P12)=0,"",IFERROR(AF12*(1-Config!$C$15-Config!$C$16-Config!$C$17),0)) | AI12: =IF(COUNT(C12:P12)=0,"",IFERROR(AH12-C12-Config!$C$18,0)) | AJ12: =IF(COUNT(C12:P12)=0,"",IFERROR(AH12/C12,0)) | AK12: =IF(COUNT(C12:P12)=0,"",IFERROR(AI12/G12,0)) | AL12: =IF(COUNT(C12:P12)=0,"",IFERROR(AK12/V12,0)) | AM12: =IF(COUNT(C12:P12)=0,"",IFERROR(AI12/I12,0)) | AN12: =IF(COUNT(C12:P12)=0,"",IFERROR(AH12/I12-AA12,0))
A13: =Config!$C$6+7 | B13: =INT((A13-Config!$C$6)/7)+1 | C13: 325 | D13: 87922 | E13: 59066 | F13: 1497 | G13: 1338 | H13: 52 | I13: 13 | J13: 3 | K13: 2 | L13: 1 | M13: 1 | N13: 0 | O13: 1 | P13: 0 | Q13: =IF(COUNT(C13:P13)=0,"",IFERROR(C13/D13*1000,0)) | R13: =IF(COUNT(C13:P13)=0,"",IFERROR(D13/E13,0)) | S13: =IF(COUNT(C13:P13)=0,"",IFERROR(F13/D13,0)) | T13: =IF(COUNT(C13:P13)=0,"",IFERROR(C13/F13,0)) | U13: =IF(COUNT(C13:P13)=0,"",IFERROR(G13/F13,0)) | V13: =IF(COUNT(C13:P13)=0,"",IFERROR(C13/G13,0)) | W13: =IF(COUNT(C13:P13)=0,"",IFERROR(G13/D13*1000,0)) | X13: =IF(COUNT(C13:P13)=0,"",IFERROR(H13/G13,0)) | Y13: =IF(COUNT(C13:P13)=0,"",IFERROR(I13/H13,0)) | Z13: =IF(COUNT(C13:P13)=0,"",IFERROR(I13/G13,0)) | AA13: =IF(COUNT(C13:P13)=0,"",IFERROR(C13/I13,0)) | AB13: =IF(COUNT(C13:P13)=0,"",IFERROR(J13/I13,0)) | AC13: =IF(COUNT(C13:P13)=0,"",IFERROR(K13/I13,0)) | AD13: =IF(COUNT(C13:P13)=0,"",IFERROR(L13/I13,0)) | AE13: =IF(COUNT(C13:P13)=0,"",IFERROR(P13/I13,0)) | AF13: =IF(COUNT(C13:P13)=0,"",IFERROR(I13*Config!$C$7+J13*Config!$C$8+K13*Config!$C$9+L13*Config!$C$10+M13*Config!$C$11+N13*Config!$C$12+O13*Config!$C$13+P13*Config!$C$14,0)) | AG13: =IF(COUNT(C13:P13)=0,"",IFERROR(AF13/I13,0)) | AH13: =IF(COUNT(C13:P13)=0,"",IFERROR(AF13*(1-Config!$C$15-Config!$C$16-Config!$C$17),0)) | AI13: =IF(COUNT(C13:P13)=0,"",IFERROR(AH13-C13-Config!$C$18,0)) | AJ13: =IF(COUNT(C13:P13)=0,"",IFERROR(AH13/C13,0)) | AK13: =IF(COUNT(C13:P13)=0,"",IFERROR(AI13/G13,0)) | AL13: =IF(COUNT(C13:P13)=0,"",IFERROR(AK13/V13,0)) | AM13: =IF(COUNT(C13:P13)=0,"",IFERROR(AI13/I13,0)) | AN13: =IF(COUNT(C13:P13)=0,"",IFERROR(AH13/I13-AA13,0))
A14: =Config!$C$6+8 | B14: =INT((A14-Config!$C$6)/7)+1 | C14: 269 | D14: 62177 | E14: 36426 | F14: 910 | G14: 738 | H14: 25 | I14: 7 | J14: 2 | K14: 1 | L14: 1 | M14: 0 | N14: 0 | O14: 0 | P14: 0 | Q14: =IF(COUNT(C14:P14)=0,"",IFERROR(C14/D14*1000,0)) | R14: =IF(COUNT(C14:P14)=0,"",IFERROR(D14/E14,0)) | S14: =IF(COUNT(C14:P14)=0,"",IFERROR(F14/D14,0)) | T14: =IF(COUNT(C14:P14)=0,"",IFERROR(C14/F14,0)) | U14: =IF(COUNT(C14:P14)=0,"",IFERROR(G14/F14,0)) | V14: =IF(COUNT(C14:P14)=0,"",IFERROR(C14/G14,0)) | W14: =IF(COUNT(C14:P14)=0,"",IFERROR(G14/D14*1000,0)) | X14: =IF(COUNT(C14:P14)=0,"",IFERROR(H14/G14,0)) | Y14: =IF(COUNT(C14:P14)=0,"",IFERROR(I14/H14,0)) | Z14: =IF(COUNT(C14:P14)=0,"",IFERROR(I14/G14,0)) | AA14: =IF(COUNT(C14:P14)=0,"",IFERROR(C14/I14,0)) | AB14: =IF(COUNT(C14:P14)=0,"",IFERROR(J14/I14,0)) | AC14: =IF(COUNT(C14:P14)=0,"",IFERROR(K14/I14,0)) | AD14: =IF(COUNT(C14:P14)=0,"",IFERROR(L14/I14,0)) | AE14: =IF(COUNT(C14:P14)=0,"",IFERROR(P14/I14,0)) | AF14: =IF(COUNT(C14:P14)=0,"",IFERROR(I14*Config!$C$7+J14*Config!$C$8+K14*Config!$C$9+L14*Config!$C$10+M14*Config!$C$11+N14*Config!$C$12+O14*Config!$C$13+P14*Config!$C$14,0)) | AG14: =IF(COUNT(C14:P14)=0,"",IFERROR(AF14/I14,0)) | AH14: =IF(COUNT(C14:P14)=0,"",IFERROR(AF14*(1-Config!$C$15-Config!$C$16-Config!$C$17),0)) | AI14: =IF(COUNT(C14:P14)=0,"",IFERROR(AH14-C14-Config!$C$18,0)) | AJ14: =IF(COUNT(C14:P14)=0,"",IFERROR(AH14/C14,0)) | AK14: =IF(COUNT(C14:P14)=0,"",IFERROR(AI14/G14,0)) | AL14: =IF(COUNT(C14:P14)=0,"",IFERROR(AK14/V14,0)) | AM14: =IF(COUNT(C14:P14)=0,"",IFERROR(AI14/I14,0)) | AN14: =IF(COUNT(C14:P14)=0,"",IFERROR(AH14/I14-AA14,0))
A15: =Config!$C$6+9 | B15: =INT((A15-Config!$C$6)/7)+1 | C15: 319 | D15: 83508 | E15: 55575 | F15: 1170 | G15: 942 | H15: 35 | I15: 8 | J15: 2 | K15: 2 | L15: 1 | M15: 1 | N15: 0 | O15: 0 | P15: 0 | Q15: =IF(COUNT(C15:P15)=0,"",IFERROR(C15/D15*1000,0)) | R15: =IF(COUNT(C15:P15)=0,"",IFERROR(D15/E15,0)) | S15: =IF(COUNT(C15:P15)=0,"",IFERROR(F15/D15,0)) | T15: =IF(COUNT(C15:P15)=0,"",IFERROR(C15/F15,0)) | U15: =IF(COUNT(C15:P15)=0,"",IFERROR(G15/F15,0)) | V15: =IF(COUNT(C15:P15)=0,"",IFERROR(C15/G15,0)) | W15: =IF(COUNT(C15:P15)=0,"",IFERROR(G15/D15*1000,0)) | X15: =IF(COUNT(C15:P15)=0,"",IFERROR(H15/G15,0)) | Y15: =IF(COUNT(C15:P15)=0,"",IFERROR(I15/H15,0)) | Z15: =IF(COUNT(C15:P15)=0,"",IFERROR(I15/G15,0)) | AA15: =IF(COUNT(C15:P15)=0,"",IFERROR(C15/I15,0)) | AB15: =IF(COUNT(C15:P15)=0,"",IFERROR(J15/I15,0)) | AC15: =IF(COUNT(C15:P15)=0,"",IFERROR(K15/I15,0)) | AD15: =IF(COUNT(C15:P15)=0,"",IFERROR(L15/I15,0)) | AE15: =IF(COUNT(C15:P15)=0,"",IFERROR(P15/I15,0)) | AF15: =IF(COUNT(C15:P15)=0,"",IFERROR(I15*Config!$C$7+J15*Config!$C$8+K15*Config!$C$9+L15*Config!$C$10+M15*Config!$C$11+N15*Config!$C$12+O15*Config!$C$13+P15*Config!$C$14,0)) | AG15: =IF(COUNT(C15:P15)=0,"",IFERROR(AF15/I15,0)) | AH15: =IF(COUNT(C15:P15)=0,"",IFERROR(AF15*(1-Config!$C$15-Config!$C$16-Config!$C$17),0)) | AI15: =IF(COUNT(C15:P15)=0,"",IFERROR(AH15-C15-Config!$C$18,0)) | AJ15: =IF(COUNT(C15:P15)=0,"",IFERROR(AH15/C15,0)) | AK15: =IF(COUNT(C15:P15)=0,"",IFERROR(AI15/G15,0)) | AL15: =IF(COUNT(C15:P15)=0,"",IFERROR(AK15/V15,0)) | AM15: =IF(COUNT(C15:P15)=0,"",IFERROR(AI15/I15,0)) | AN15: =IF(COUNT(C15:P15)=0,"",IFERROR(AH15/I15-AA15,0))
A16: =Config!$C$6+10 | B16: =INT((A16-Config!$C$6)/7)+1 | C16: 304 | D16: 73371 | E16: 49534 | F16: 1201 | G16: 985 | H16: 36 | I16: 8 | J16: 2 | K16: 2 | L16: 1 | M16: 1 | N16: 0 | O16: 0 | P16: 0 | Q16: =IF(COUNT(C16:P16)=0,"",IFERROR(C16/D16*1000,0)) | R16: =IF(COUNT(C16:P16)=0,"",IFERROR(D16/E16,0)) | S16: =IF(COUNT(C16:P16)=0,"",IFERROR(F16/D16,0)) | T16: =IF(COUNT(C16:P16)=0,"",IFERROR(C16/F16,0)) | U16: =IF(COUNT(C16:P16)=0,"",IFERROR(G16/F16,0)) | V16: =IF(COUNT(C16:P16)=0,"",IFERROR(C16/G16,0)) | W16: =IF(COUNT(C16:P16)=0,"",IFERROR(G16/D16*1000,0)) | X16: =IF(COUNT(C16:P16)=0,"",IFERROR(H16/G16,0)) | Y16: =IF(COUNT(C16:P16)=0,"",IFERROR(I16/H16,0)) | Z16: =IF(COUNT(C16:P16)=0,"",IFERROR(I16/G16,0)) | AA16: =IF(COUNT(C16:P16)=0,"",IFERROR(C16/I16,0)) | AB16: =IF(COUNT(C16:P16)=0,"",IFERROR(J16/I16,0)) | AC16: =IF(COUNT(C16:P16)=0,"",IFERROR(K16/I16,0)) | AD16: =IF(COUNT(C16:P16)=0,"",IFERROR(L16/I16,0)) | AE16: =IF(COUNT(C16:P16)=0,"",IFERROR(P16/I16,0)) | AF16: =IF(COUNT(C16:P16)=0,"",IFERROR(I16*Config!$C$7+J16*Config!$C$8+K16*Config!$C$9+L16*Config!$C$10+M16*Config!$C$11+N16*Config!$C$12+O16*Config!$C$13+P16*Config!$C$14,0)) | AG16: =IF(COUNT(C16:P16)=0,"",IFERROR(AF16/I16,0)) | AH16: =IF(COUNT(C16:P16)=0,"",IFERROR(AF16*(1-Config!$C$15-Config!$C$16-Config!$C$17),0)) | AI16: =IF(COUNT(C16:P16)=0,"",IFERROR(AH16-C16-Config!$C$18,0)) | AJ16: =IF(COUNT(C16:P16)=0,"",IFERROR(AH16/C16,0)) | AK16: =IF(COUNT(C16:P16)=0,"",IFERROR(AI16/G16,0)) | AL16: =IF(COUNT(C16:P16)=0,"",IFERROR(AK16/V16,0)) | AM16: =IF(COUNT(C16:P16)=0,"",IFERROR(AI16/I16,0)) | AN16: =IF(COUNT(C16:P16)=0,"",IFERROR(AH16/I16-AA16,0))
A17: =Config!$C$6+11 | B17: =INT((A17-Config!$C$6)/7)+1 | C17: 294 | D17: 75256 | E17: 49786 | F17: 1298 | G17: 1254 | H17: 42 | I17: 12 | J17: 3 | K17: 2 | L17: 1 | M17: 1 | N17: 0 | O17: 0 | P17: 0 | Q17: =IF(COUNT(C17:P17)=0,"",IFERROR(C17/D17*1000,0)) | R17: =IF(COUNT(C17:P17)=0,"",IFERROR(D17/E17,0)) | S17: =IF(COUNT(C17:P17)=0,"",IFERROR(F17/D17,0)) | T17: =IF(COUNT(C17:P17)=0,"",IFERROR(C17/F17,0)) | U17: =IF(COUNT(C17:P17)=0,"",IFERROR(G17/F17,0)) | V17: =IF(COUNT(C17:P17)=0,"",IFERROR(C17/G17,0)) | W17: =IF(COUNT(C17:P17)=0,"",IFERROR(G17/D17*1000,0)) | X17: =IF(COUNT(C17:P17)=0,"",IFERROR(H17/G17,0)) | Y17: =IF(COUNT(C17:P17)=0,"",IFERROR(I17/H17,0)) | Z17: =IF(COUNT(C17:P17)=0,"",IFERROR(I17/G17,0)) | AA17: =IF(COUNT(C17:P17)=0,"",IFERROR(C17/I17,0)) | AB17: =IF(COUNT(C17:P17)=0,"",IFERROR(J17/I17,0)) | AC17: =IF(COUNT(C17:P17)=0,"",IFERROR(K17/I17,0)) | AD17: =IF(COUNT(C17:P17)=0,"",IFERROR(L17/I17,0)) | AE17: =IF(COUNT(C17:P17)=0,"",IFERROR(P17/I17,0)) | AF17: =IF(COUNT(C17:P17)=0,"",IFERROR(I17*Config!$C$7+J17*Config!$C$8+K17*Config!$C$9+L17*Config!$C$10+M17*Config!$C$11+N17*Config!$C$12+O17*Config!$C$13+P17*Config!$C$14,0)) | AG17: =IF(COUNT(C17:P17)=0,"",IFERROR(AF17/I17,0)) | AH17: =IF(COUNT(C17:P17)=0,"",IFERROR(AF17*(1-Config!$C$15-Config!$C$16-Config!$C$17),0)) | AI17: =IF(COUNT(C17:P17)=0,"",IFERROR(AH17-C17-Config!$C$18,0)) | AJ17: =IF(COUNT(C17:P17)=0,"",IFERROR(AH17/C17,0)) | AK17: =IF(COUNT(C17:P17)=0,"",IFERROR(AI17/G17,0)) | AL17: =IF(COUNT(C17:P17)=0,"",IFERROR(AK17/V17,0)) | AM17: =IF(COUNT(C17:P17)=0,"",IFERROR(AI17/I17,0)) | AN17: =IF(COUNT(C17:P17)=0,"",IFERROR(AH17/I17-AA17,0))
A18: =Config!$C$6+12 | B18: =INT((A18-Config!$C$6)/7)+1 | C18: 279 | D18: 68200 | E18: 39284 | F18: 1093 | G18: 889 | H18: 35 | I18: 8 | J18: 2 | K18: 2 | L18: 1 | M18: 1 | N18: 0 | O18: 0 | P18: 0 | Q18: =IF(COUNT(C18:P18)=0,"",IFERROR(C18/D18*1000,0)) | R18: =IF(COUNT(C18:P18)=0,"",IFERROR(D18/E18,0)) | S18: =IF(COUNT(C18:P18)=0,"",IFERROR(F18/D18,0)) | T18: =IF(COUNT(C18:P18)=0,"",IFERROR(C18/F18,0)) | U18: =IF(COUNT(C18:P18)=0,"",IFERROR(G18/F18,0)) | V18: =IF(COUNT(C18:P18)=0,"",IFERROR(C18/G18,0)) | W18: =IF(COUNT(C18:P18)=0,"",IFERROR(G18/D18*1000,0)) | X18: =IF(COUNT(C18:P18)=0,"",IFERROR(H18/G18,0)) | Y18: =IF(COUNT(C18:P18)=0,"",IFERROR(I18/H18,0)) | Z18: =IF(COUNT(C18:P18)=0,"",IFERROR(I18/G18,0)) | AA18: =IF(COUNT(C18:P18)=0,"",IFERROR(C18/I18,0)) | AB18: =IF(COUNT(C18:P18)=0,"",IFERROR(J18/I18,0)) | AC18: =IF(COUNT(C18:P18)=0,"",IFERROR(K18/I18,0)) | AD18: =IF(COUNT(C18:P18)=0,"",IFERROR(L18/I18,0)) | AE18: =IF(COUNT(C18:P18)=0,"",IFERROR(P18/I18,0)) | AF18: =IF(COUNT(C18:P18)=0,"",IFERROR(I18*Config!$C$7+J18*Config!$C$8+K18*Config!$C$9+L18*Config!$C$10+M18*Config!$C$11+N18*Config!$C$12+O18*Config!$C$13+P18*Config!$C$14,0)) | AG18: =IF(COUNT(C18:P18)=0,"",IFERROR(AF18/I18,0)) | AH18: =IF(COUNT(C18:P18)=0,"",IFERROR(AF18*(1-Config!$C$15-Config!$C$16-Config!$C$17),0)) | AI18: =IF(COUNT(C18:P18)=0,"",IFERROR(AH18-C18-Config!$C$18,0)) | AJ18: =IF(COUNT(C18:P18)=0,"",IFERROR(AH18/C18,0)) | AK18: =IF(COUNT(C18:P18)=0,"",IFERROR(AI18/G18,0)) | AL18: =IF(COUNT(C18:P18)=0,"",IFERROR(AK18/V18,0)) | AM18: =IF(COUNT(C18:P18)=0,"",IFERROR(AI18/I18,0)) | AN18: =IF(COUNT(C18:P18)=0,"",IFERROR(AH18/I18-AA18,0))
A19: =Config!$C$6+13 | B19: =INT((A19-Config!$C$6)/7)+1 | C19: 283 | D19: 63152 | E19: 41159 | F19: 931 | G19: 752 | H19: 24 | I19: 6 | J19: 2 | K19: 1 | L19: 1 | M19: 0 | N19: 0 | O19: 0 | P19: 0 | Q19: =IF(COUNT(C19:P19)=0,"",IFERROR(C19/D19*1000,0)) | R19: =IF(COUNT(C19:P19)=0,"",IFERROR(D19/E19,0)) | S19: =IF(COUNT(C19:P19)=0,"",IFERROR(F19/D19,0)) | T19: =IF(COUNT(C19:P19)=0,"",IFERROR(C19/F19,0)) | U19: =IF(COUNT(C19:P19)=0,"",IFERROR(G19/F19,0)) | V19: =IF(COUNT(C19:P19)=0,"",IFERROR(C19/G19,0)) | W19: =IF(COUNT(C19:P19)=0,"",IFERROR(G19/D19*1000,0)) | X19: =IF(COUNT(C19:P19)=0,"",IFERROR(H19/G19,0)) | Y19: =IF(COUNT(C19:P19)=0,"",IFERROR(I19/H19,0)) | Z19: =IF(COUNT(C19:P19)=0,"",IFERROR(I19/G19,0)) | AA19: =IF(COUNT(C19:P19)=0,"",IFERROR(C19/I19,0)) | AB19: =IF(COUNT(C19:P19)=0,"",IFERROR(J19/I19,0)) | AC19: =IF(COUNT(C19:P19)=0,"",IFERROR(K19/I19,0)) | AD19: =IF(COUNT(C19:P19)=0,"",IFERROR(L19/I19,0)) | AE19: =IF(COUNT(C19:P19)=0,"",IFERROR(P19/I19,0)) | AF19: =IF(COUNT(C19:P19)=0,"",IFERROR(I19*Config!$C$7+J19*Config!$C$8+K19*Config!$C$9+L19*Config!$C$10+M19*Config!$C$11+N19*Config!$C$12+O19*Config!$C$13+P19*Config!$C$14,0)) | AG19: =IF(COUNT(C19:P19)=0,"",IFERROR(AF19/I19,0)) | AH19: =IF(COUNT(C19:P19)=0,"",IFERROR(AF19*(1-Config!$C$15-Config!$C$16-Config!$C$17),0)) | AI19: =IF(COUNT(C19:P19)=0,"",IFERROR(AH19-C19-Config!$C$18,0)) | AJ19: =IF(COUNT(C19:P19)=0,"",IFERROR(AH19/C19,0)) | AK19: =IF(COUNT(C19:P19)=0,"",IFERROR(AI19/G19,0)) | AL19: =IF(COUNT(C19:P19)=0,"",IFERROR(AK19/V19,0)) | AM19: =IF(COUNT(C19:P19)=0,"",IFERROR(AI19/I19,0)) | AN19: =IF(COUNT(C19:P19)=0,"",IFERROR(AH19/I19-AA19,0))
A20: =Config!$C$6+14 | B20: =INT((A20-Config!$C$6)/7)+1 | C20: 281 | D20: 65433 | E20: 42195 | F20: 1003 | G20: 1002 | H20: 35 | I20: 9 | J20: 2 | K20: 2 | L20: 1 | M20: 1 | N20: 0 | O20: 0 | P20: 0 | Q20: =IF(COUNT(C20:P20)=0,"",IFERROR(C20/D20*1000,0)) | R20: =IF(COUNT(C20:P20)=0,"",IFERROR(D20/E20,0)) | S20: =IF(COUNT(C20:P20)=0,"",IFERROR(F20/D20,0)) | T20: =IF(COUNT(C20:P20)=0,"",IFERROR(C20/F20,0)) | U20: =IF(COUNT(C20:P20)=0,"",IFERROR(G20/F20,0)) | V20: =IF(COUNT(C20:P20)=0,"",IFERROR(C20/G20,0)) | W20: =IF(COUNT(C20:P20)=0,"",IFERROR(G20/D20*1000,0)) | X20: =IF(COUNT(C20:P20)=0,"",IFERROR(H20/G20,0)) | Y20: =IF(COUNT(C20:P20)=0,"",IFERROR(I20/H20,0)) | Z20: =IF(COUNT(C20:P20)=0,"",IFERROR(I20/G20,0)) | AA20: =IF(COUNT(C20:P20)=0,"",IFERROR(C20/I20,0)) | AB20: =IF(COUNT(C20:P20)=0,"",IFERROR(J20/I20,0)) | AC20: =IF(COUNT(C20:P20)=0,"",IFERROR(K20/I20,0)) | AD20: =IF(COUNT(C20:P20)=0,"",IFERROR(L20/I20,0)) | AE20: =IF(COUNT(C20:P20)=0,"",IFERROR(P20/I20,0)) | AF20: =IF(COUNT(C20:P20)=0,"",IFERROR(I20*Config!$C$7+J20*Config!$C$8+K20*Config!$C$9+L20*Config!$C$10+M20*Config!$C$11+N20*Config!$C$12+O20*Config!$C$13+P20*Config!$C$14,0)) | AG20: =IF(COUNT(C20:P20)=0,"",IFERROR(AF20/I20,0)) | AH20: =IF(COUNT(C20:P20)=0,"",IFERROR(AF20*(1-Config!$C$15-Config!$C$16-Config!$C$17),0)) | AI20: =IF(COUNT(C20:P20)=0,"",IFERROR(AH20-C20-Config!$C$18,0)) | AJ20: =IF(COUNT(C20:P20)=0,"",IFERROR(AH20/C20,0)) | AK20: =IF(COUNT(C20:P20)=0,"",IFERROR(AI20/G20,0)) | AL20: =IF(COUNT(C20:P20)=0,"",IFERROR(AK20/V20,0)) | AM20: =IF(COUNT(C20:P20)=0,"",IFERROR(AI20/I20,0)) | AN20: =IF(COUNT(C20:P20)=0,"",IFERROR(AH20/I20-AA20,0))
A21: =Config!$C$6+15 | B21: =INT((A21-Config!$C$6)/7)+1 | C21: 326 | D21: 84115 | E21: 57331 | F21: 1432 | G21: 1387 | H21: 46 | I21: 11 | J21: 3 | K21: 2 | L21: 1 | M21: 1 | N21: 0 | O21: 0 | P21: 0 | Q21: =IF(COUNT(C21:P21)=0,"",IFERROR(C21/D21*1000,0)) | R21: =IF(COUNT(C21:P21)=0,"",IFERROR(D21/E21,0)) | S21: =IF(COUNT(C21:P21)=0,"",IFERROR(F21/D21,0)) | T21: =IF(COUNT(C21:P21)=0,"",IFERROR(C21/F21,0)) | U21: =IF(COUNT(C21:P21)=0,"",IFERROR(G21/F21,0)) | V21: =IF(COUNT(C21:P21)=0,"",IFERROR(C21/G21,0)) | W21: =IF(COUNT(C21:P21)=0,"",IFERROR(G21/D21*1000,0)) | X21: =IF(COUNT(C21:P21)=0,"",IFERROR(H21/G21,0)) | Y21: =IF(COUNT(C21:P21)=0,"",IFERROR(I21/H21,0)) | Z21: =IF(COUNT(C21:P21)=0,"",IFERROR(I21/G21,0)) | AA21: =IF(COUNT(C21:P21)=0,"",IFERROR(C21/I21,0)) | AB21: =IF(COUNT(C21:P21)=0,"",IFERROR(J21/I21,0)) | AC21: =IF(COUNT(C21:P21)=0,"",IFERROR(K21/I21,0)) | AD21: =IF(COUNT(C21:P21)=0,"",IFERROR(L21/I21,0)) | AE21: =IF(COUNT(C21:P21)=0,"",IFERROR(P21/I21,0)) | AF21: =IF(COUNT(C21:P21)=0,"",IFERROR(I21*Config!$C$7+J21*Config!$C$8+K21*Config!$C$9+L21*Config!$C$10+M21*Config!$C$11+N21*Config!$C$12+O21*Config!$C$13+P21*Config!$C$14,0)) | AG21: =IF(COUNT(C21:P21)=0,"",IFERROR(AF21/I21,0)) | AH21: =IF(COUNT(C21:P21)=0,"",IFERROR(AF21*(1-Config!$C$15-Config!$C$16-Config!$C$17),0)) | AI21: =IF(COUNT(C21:P21)=0,"",IFERROR(AH21-C21-Config!$C$18,0)) | AJ21: =IF(COUNT(C21:P21)=0,"",IFERROR(AH21/C21,0)) | AK21: =IF(COUNT(C21:P21)=0,"",IFERROR(AI21/G21,0)) | AL21: =IF(COUNT(C21:P21)=0,"",IFERROR(AK21/V21,0)) | AM21: =IF(COUNT(C21:P21)=0,"",IFERROR(AI21/I21,0)) | AN21: =IF(COUNT(C21:P21)=0,"",IFERROR(AH21/I21-AA21,0))
A22: =Config!$C$6+16 | B22: =INT((A22-Config!$C$6)/7)+1 | C22: 317 | D22: 68313 | E22: 46049 | F22: 1173 | G22: 1153 | H22: 41 | I22: 11 | J22: 3 | K22: 2 | L22: 1 | M22: 1 | N22: 0 | O22: 0 | P22: 0 | Q22: =IF(COUNT(C22:P22)=0,"",IFERROR(C22/D22*1000,0)) | R22: =IF(COUNT(C22:P22)=0,"",IFERROR(D22/E22,0)) | S22: =IF(COUNT(C22:P22)=0,"",IFERROR(F22/D22,0)) | T22: =IF(COUNT(C22:P22)=0,"",IFERROR(C22/F22,0)) | U22: =IF(COUNT(C22:P22)=0,"",IFERROR(G22/F22,0)) | V22: =IF(COUNT(C22:P22)=0,"",IFERROR(C22/G22,0)) | W22: =IF(COUNT(C22:P22)=0,"",IFERROR(G22/D22*1000,0)) | X22: =IF(COUNT(C22:P22)=0,"",IFERROR(H22/G22,0)) | Y22: =IF(COUNT(C22:P22)=0,"",IFERROR(I22/H22,0)) | Z22: =IF(COUNT(C22:P22)=0,"",IFERROR(I22/G22,0)) | AA22: =IF(COUNT(C22:P22)=0,"",IFERROR(C22/I22,0)) | AB22: =IF(COUNT(C22:P22)=0,"",IFERROR(J22/I22,0)) | AC22: =IF(COUNT(C22:P22)=0,"",IFERROR(K22/I22,0)) | AD22: =IF(COUNT(C22:P22)=0,"",IFERROR(L22/I22,0)) | AE22: =IF(COUNT(C22:P22)=0,"",IFERROR(P22/I22,0)) | AF22: =IF(COUNT(C22:P22)=0,"",IFERROR(I22*Config!$C$7+J22*Config!$C$8+K22*Config!$C$9+L22*Config!$C$10+M22*Config!$C$11+N22*Config!$C$12+O22*Config!$C$13+P22*Config!$C$14,0)) | AG22: =IF(COUNT(C22:P22)=0,"",IFERROR(AF22/I22,0)) | AH22: =IF(COUNT(C22:P22)=0,"",IFERROR(AF22*(1-Config!$C$15-Config!$C$16-Config!$C$17),0)) | AI22: =IF(COUNT(C22:P22)=0,"",IFERROR(AH22-C22-Config!$C$18,0)) | AJ22: =IF(COUNT(C22:P22)=0,"",IFERROR(AH22/C22,0)) | AK22: =IF(COUNT(C22:P22)=0,"",IFERROR(AI22/G22,0)) | AL22: =IF(COUNT(C22:P22)=0,"",IFERROR(AK22/V22,0)) | AM22: =IF(COUNT(C22:P22)=0,"",IFERROR(AI22/I22,0)) | AN22: =IF(COUNT(C22:P22)=0,"",IFERROR(AH22/I22-AA22,0))
A23: =Config!$C$6+17 | B23: =INT((A23-Config!$C$6)/7)+1 | C23: 271 | D23: 72684 | E23: 40887 | F23: 1056 | G23: 997 | H23: 33 | I23: 9 | J23: 2 | K23: 2 | L23: 1 | M23: 1 | N23: 0 | O23: 0 | P23: 0 | Q23: =IF(COUNT(C23:P23)=0,"",IFERROR(C23/D23*1000,0)) | R23: =IF(COUNT(C23:P23)=0,"",IFERROR(D23/E23,0)) | S23: =IF(COUNT(C23:P23)=0,"",IFERROR(F23/D23,0)) | T23: =IF(COUNT(C23:P23)=0,"",IFERROR(C23/F23,0)) | U23: =IF(COUNT(C23:P23)=0,"",IFERROR(G23/F23,0)) | V23: =IF(COUNT(C23:P23)=0,"",IFERROR(C23/G23,0)) | W23: =IF(COUNT(C23:P23)=0,"",IFERROR(G23/D23*1000,0)) | X23: =IF(COUNT(C23:P23)=0,"",IFERROR(H23/G23,0)) | Y23: =IF(COUNT(C23:P23)=0,"",IFERROR(I23/H23,0)) | Z23: =IF(COUNT(C23:P23)=0,"",IFERROR(I23/G23,0)) | AA23: =IF(COUNT(C23:P23)=0,"",IFERROR(C23/I23,0)) | AB23: =IF(COUNT(C23:P23)=0,"",IFERROR(J23/I23,0)) | AC23: =IF(COUNT(C23:P23)=0,"",IFERROR(K23/I23,0)) | AD23: =IF(COUNT(C23:P23)=0,"",IFERROR(L23/I23,0)) | AE23: =IF(COUNT(C23:P23)=0,"",IFERROR(P23/I23,0)) | AF23: =IF(COUNT(C23:P23)=0,"",IFERROR(I23*Config!$C$7+J23*Config!$C$8+K23*Config!$C$9+L23*Config!$C$10+M23*Config!$C$11+N23*Config!$C$12+O23*Config!$C$13+P23*Config!$C$14,0)) | AG23: =IF(COUNT(C23:P23)=0,"",IFERROR(AF23/I23,0)) | AH23: =IF(COUNT(C23:P23)=0,"",IFERROR(AF23*(1-Config!$C$15-Config!$C$16-Config!$C$17),0)) | AI23: =IF(COUNT(C23:P23)=0,"",IFERROR(AH23-C23-Config!$C$18,0)) | AJ23: =IF(COUNT(C23:P23)=0,"",IFERROR(AH23/C23,0)) | AK23: =IF(COUNT(C23:P23)=0,"",IFERROR(AI23/G23,0)) | AL23: =IF(COUNT(C23:P23)=0,"",IFERROR(AK23/V23,0)) | AM23: =IF(COUNT(C23:P23)=0,"",IFERROR(AI23/I23,0)) | AN23: =IF(COUNT(C23:P23)=0,"",IFERROR(AH23/I23-AA23,0))
A24: =Config!$C$6+18 | B24: =INT((A24-Config!$C$6)/7)+1 | C24: 307 | D24: 76894 | E24: 52119 | F24: 1255 | G24: 1013 | H24: 33 | I24: 9 | J24: 2 | K24: 2 | L24: 1 | M24: 1 | N24: 0 | O24: 0 | P24: 0 | Q24: =IF(COUNT(C24:P24)=0,"",IFERROR(C24/D24*1000,0)) | R24: =IF(COUNT(C24:P24)=0,"",IFERROR(D24/E24,0)) | S24: =IF(COUNT(C24:P24)=0,"",IFERROR(F24/D24,0)) | T24: =IF(COUNT(C24:P24)=0,"",IFERROR(C24/F24,0)) | U24: =IF(COUNT(C24:P24)=0,"",IFERROR(G24/F24,0)) | V24: =IF(COUNT(C24:P24)=0,"",IFERROR(C24/G24,0)) | W24: =IF(COUNT(C24:P24)=0,"",IFERROR(G24/D24*1000,0)) | X24: =IF(COUNT(C24:P24)=0,"",IFERROR(H24/G24,0)) | Y24: =IF(COUNT(C24:P24)=0,"",IFERROR(I24/H24,0)) | Z24: =IF(COUNT(C24:P24)=0,"",IFERROR(I24/G24,0)) | AA24: =IF(COUNT(C24:P24)=0,"",IFERROR(C24/I24,0)) | AB24: =IF(COUNT(C24:P24)=0,"",IFERROR(J24/I24,0)) | AC24: =IF(COUNT(C24:P24)=0,"",IFERROR(K24/I24,0)) | AD24: =IF(COUNT(C24:P24)=0,"",IFERROR(L24/I24,0)) | AE24: =IF(COUNT(C24:P24)=0,"",IFERROR(P24/I24,0)) | AF24: =IF(COUNT(C24:P24)=0,"",IFERROR(I24*Config!$C$7+J24*Config!$C$8+K24*Config!$C$9+L24*Config!$C$10+M24*Config!$C$11+N24*Config!$C$12+O24*Config!$C$13+P24*Config!$C$14,0)) | AG24: =IF(COUNT(C24:P24)=0,"",IFERROR(AF24/I24,0)) | AH24: =IF(COUNT(C24:P24)=0,"",IFERROR(AF24*(1-Config!$C$15-Config!$C$16-Config!$C$17),0)) | AI24: =IF(COUNT(C24:P24)=0,"",IFERROR(AH24-C24-Config!$C$18,0)) | AJ24: =IF(COUNT(C24:P24)=0,"",IFERROR(AH24/C24,0)) | AK24: =IF(COUNT(C24:P24)=0,"",IFERROR(AI24/G24,0)) | AL24: =IF(COUNT(C24:P24)=0,"",IFERROR(AK24/V24,0)) | AM24: =IF(COUNT(C24:P24)=0,"",IFERROR(AI24/I24,0)) | AN24: =IF(COUNT(C24:P24)=0,"",IFERROR(AH24/I24-AA24,0))
A25: =Config!$C$6+19 | B25: =INT((A25-Config!$C$6)/7)+1 | C25: 325 | D25: 75401 | E25: 49750 | F25: 1286 | G25: 1075 | H25: 33 | I25: 8 | J25: 2 | K25: 1 | L25: 1 | M25: 0 | N25: 0 | O25: 0 | P25: 0 | Q25: =IF(COUNT(C25:P25)=0,"",IFERROR(C25/D25*1000,0)) | R25: =IF(COUNT(C25:P25)=0,"",IFERROR(D25/E25,0)) | S25: =IF(COUNT(C25:P25)=0,"",IFERROR(F25/D25,0)) | T25: =IF(COUNT(C25:P25)=0,"",IFERROR(C25/F25,0)) | U25: =IF(COUNT(C25:P25)=0,"",IFERROR(G25/F25,0)) | V25: =IF(COUNT(C25:P25)=0,"",IFERROR(C25/G25,0)) | W25: =IF(COUNT(C25:P25)=0,"",IFERROR(G25/D25*1000,0)) | X25: =IF(COUNT(C25:P25)=0,"",IFERROR(H25/G25,0)) | Y25: =IF(COUNT(C25:P25)=0,"",IFERROR(I25/H25,0)) | Z25: =IF(COUNT(C25:P25)=0,"",IFERROR(I25/G25,0)) | AA25: =IF(COUNT(C25:P25)=0,"",IFERROR(C25/I25,0)) | AB25: =IF(COUNT(C25:P25)=0,"",IFERROR(J25/I25,0)) | AC25: =IF(COUNT(C25:P25)=0,"",IFERROR(K25/I25,0)) | AD25: =IF(COUNT(C25:P25)=0,"",IFERROR(L25/I25,0)) | AE25: =IF(COUNT(C25:P25)=0,"",IFERROR(P25/I25,0)) | AF25: =IF(COUNT(C25:P25)=0,"",IFERROR(I25*Config!$C$7+J25*Config!$C$8+K25*Config!$C$9+L25*Config!$C$10+M25*Config!$C$11+N25*Config!$C$12+O25*Config!$C$13+P25*Config!$C$14,0)) | AG25: =IF(COUNT(C25:P25)=0,"",IFERROR(AF25/I25,0)) | AH25: =IF(COUNT(C25:P25)=0,"",IFERROR(AF25*(1-Config!$C$15-Config!$C$16-Config!$C$17),0)) | AI25: =IF(COUNT(C25:P25)=0,"",IFERROR(AH25-C25-Config!$C$18,0)) | AJ25: =IF(COUNT(C25:P25)=0,"",IFERROR(AH25/C25,0)) | AK25: =IF(COUNT(C25:P25)=0,"",IFERROR(AI25/G25,0)) | AL25: =IF(COUNT(C25:P25)=0,"",IFERROR(AK25/V25,0)) | AM25: =IF(COUNT(C25:P25)=0,"",IFERROR(AI25/I25,0)) | AN25: =IF(COUNT(C25:P25)=0,"",IFERROR(AH25/I25-AA25,0))
A26: =Config!$C$6+20 | B26: =INT((A26-Config!$C$6)/7)+1 | C26: 296 | D26: 78812 | E26: 53407 | F26: 1183 | G26: 1083 | H26: 35 | I26: 9 | J26: 2 | K26: 2 | L26: 1 | M26: 1 | N26: 0 | O26: 0 | P26: 0 | Q26: =IF(COUNT(C26:P26)=0,"",IFERROR(C26/D26*1000,0)) | R26: =IF(COUNT(C26:P26)=0,"",IFERROR(D26/E26,0)) | S26: =IF(COUNT(C26:P26)=0,"",IFERROR(F26/D26,0)) | T26: =IF(COUNT(C26:P26)=0,"",IFERROR(C26/F26,0)) | U26: =IF(COUNT(C26:P26)=0,"",IFERROR(G26/F26,0)) | V26: =IF(COUNT(C26:P26)=0,"",IFERROR(C26/G26,0)) | W26: =IF(COUNT(C26:P26)=0,"",IFERROR(G26/D26*1000,0)) | X26: =IF(COUNT(C26:P26)=0,"",IFERROR(H26/G26,0)) | Y26: =IF(COUNT(C26:P26)=0,"",IFERROR(I26/H26,0)) | Z26: =IF(COUNT(C26:P26)=0,"",IFERROR(I26/G26,0)) | AA26: =IF(COUNT(C26:P26)=0,"",IFERROR(C26/I26,0)) | AB26: =IF(COUNT(C26:P26)=0,"",IFERROR(J26/I26,0)) | AC26: =IF(COUNT(C26:P26)=0,"",IFERROR(K26/I26,0)) | AD26: =IF(COUNT(C26:P26)=0,"",IFERROR(L26/I26,0)) | AE26: =IF(COUNT(C26:P26)=0,"",IFERROR(P26/I26,0)) | AF26: =IF(COUNT(C26:P26)=0,"",IFERROR(I26*Config!$C$7+J26*Config!$C$8+K26*Config!$C$9+L26*Config!$C$10+M26*Config!$C$11+N26*Config!$C$12+O26*Config!$C$13+P26*Config!$C$14,0)) | AG26: =IF(COUNT(C26:P26)=0,"",IFERROR(AF26/I26,0)) | AH26: =IF(COUNT(C26:P26)=0,"",IFERROR(AF26*(1-Config!$C$15-Config!$C$16-Config!$C$17),0)) | AI26: =IF(COUNT(C26:P26)=0,"",IFERROR(AH26-C26-Config!$C$18,0)) | AJ26: =IF(COUNT(C26:P26)=0,"",IFERROR(AH26/C26,0)) | AK26: =IF(COUNT(C26:P26)=0,"",IFERROR(AI26/G26,0)) | AL26: =IF(COUNT(C26:P26)=0,"",IFERROR(AK26/V26,0)) | AM26: =IF(COUNT(C26:P26)=0,"",IFERROR(AI26/I26,0)) | AN26: =IF(COUNT(C26:P26)=0,"",IFERROR(AH26/I26-AA26,0))
A27: =Config!$C$6+21 | B27: =INT((A27-Config!$C$6)/7)+1 | C27: 328 | D27: 70052 | E27: 42193 | F27: 1136 | G27: 1043 | H27: 33 | I27: 8 | J27: 2 | K27: 1 | L27: 1 | M27: 0 | N27: 0 | O27: 0 | P27: 0 | Q27: =IF(COUNT(C27:P27)=0,"",IFERROR(C27/D27*1000,0)) | R27: =IF(COUNT(C27:P27)=0,"",IFERROR(D27/E27,0)) | S27: =IF(COUNT(C27:P27)=0,"",IFERROR(F27/D27,0)) | T27: =IF(COUNT(C27:P27)=0,"",IFERROR(C27/F27,0)) | U27: =IF(COUNT(C27:P27)=0,"",IFERROR(G27/F27,0)) | V27: =IF(COUNT(C27:P27)=0,"",IFERROR(C27/G27,0)) | W27: =IF(COUNT(C27:P27)=0,"",IFERROR(G27/D27*1000,0)) | X27: =IF(COUNT(C27:P27)=0,"",IFERROR(H27/G27,0)) | Y27: =IF(COUNT(C27:P27)=0,"",IFERROR(I27/H27,0)) | Z27: =IF(COUNT(C27:P27)=0,"",IFERROR(I27/G27,0)) | AA27: =IF(COUNT(C27:P27)=0,"",IFERROR(C27/I27,0)) | AB27: =IF(COUNT(C27:P27)=0,"",IFERROR(J27/I27,0)) | AC27: =IF(COUNT(C27:P27)=0,"",IFERROR(K27/I27,0)) | AD27: =IF(COUNT(C27:P27)=0,"",IFERROR(L27/I27,0)) | AE27: =IF(COUNT(C27:P27)=0,"",IFERROR(P27/I27,0)) | AF27: =IF(COUNT(C27:P27)=0,"",IFERROR(I27*Config!$C$7+J27*Config!$C$8+K27*Config!$C$9+L27*Config!$C$10+M27*Config!$C$11+N27*Config!$C$12+O27*Config!$C$13+P27*Config!$C$14,0)) | AG27: =IF(COUNT(C27:P27)=0,"",IFERROR(AF27/I27,0)) | AH27: =IF(COUNT(C27:P27)=0,"",IFERROR(AF27*(1-Config!$C$15-Config!$C$16-Config!$C$17),0)) | AI27: =IF(COUNT(C27:P27)=0,"",IFERROR(AH27-C27-Config!$C$18,0)) | AJ27: =IF(COUNT(C27:P27)=0,"",IFERROR(AH27/C27,0)) | AK27: =IF(COUNT(C27:P27)=0,"",IFERROR(AI27/G27,0)) | AL27: =IF(COUNT(C27:P27)=0,"",IFERROR(AK27/V27,0)) | AM27: =IF(COUNT(C27:P27)=0,"",IFERROR(AI27/I27,0)) | AN27: =IF(COUNT(C27:P27)=0,"",IFERROR(AH27/I27-AA27,0))
A28: =Config!$C$6+22 | B28: =INT((A28-Config!$C$6)/7)+1 | C28: 265 | D28: 57503 | E28: 34286 | F28: 990 | G28: 789 | H28: 29 | I28: 7 | J28: 2 | K28: 1 | L28: 1 | M28: 0 | N28: 0 | O28: 0 | P28: 0 | Q28: =IF(COUNT(C28:P28)=0,"",IFERROR(C28/D28*1000,0)) | R28: =IF(COUNT(C28:P28)=0,"",IFERROR(D28/E28,0)) | S28: =IF(COUNT(C28:P28)=0,"",IFERROR(F28/D28,0)) | T28: =IF(COUNT(C28:P28)=0,"",IFERROR(C28/F28,0)) | U28: =IF(COUNT(C28:P28)=0,"",IFERROR(G28/F28,0)) | V28: =IF(COUNT(C28:P28)=0,"",IFERROR(C28/G28,0)) | W28: =IF(COUNT(C28:P28)=0,"",IFERROR(G28/D28*1000,0)) | X28: =IF(COUNT(C28:P28)=0,"",IFERROR(H28/G28,0)) | Y28: =IF(COUNT(C28:P28)=0,"",IFERROR(I28/H28,0)) | Z28: =IF(COUNT(C28:P28)=0,"",IFERROR(I28/G28,0)) | AA28: =IF(COUNT(C28:P28)=0,"",IFERROR(C28/I28,0)) | AB28: =IF(COUNT(C28:P28)=0,"",IFERROR(J28/I28,0)) | AC28: =IF(COUNT(C28:P28)=0,"",IFERROR(K28/I28,0)) | AD28: =IF(COUNT(C28:P28)=0,"",IFERROR(L28/I28,0)) | AE28: =IF(COUNT(C28:P28)=0,"",IFERROR(P28/I28,0)) | AF28: =IF(COUNT(C28:P28)=0,"",IFERROR(I28*Config!$C$7+J28*Config!$C$8+K28*Config!$C$9+L28*Config!$C$10+M28*Config!$C$11+N28*Config!$C$12+O28*Config!$C$13+P28*Config!$C$14,0)) | AG28: =IF(COUNT(C28:P28)=0,"",IFERROR(AF28/I28,0)) | AH28: =IF(COUNT(C28:P28)=0,"",IFERROR(AF28*(1-Config!$C$15-Config!$C$16-Config!$C$17),0)) | AI28: =IF(COUNT(C28:P28)=0,"",IFERROR(AH28-C28-Config!$C$18,0)) | AJ28: =IF(COUNT(C28:P28)=0,"",IFERROR(AH28/C28,0)) | AK28: =IF(COUNT(C28:P28)=0,"",IFERROR(AI28/G28,0)) | AL28: =IF(COUNT(C28:P28)=0,"",IFERROR(AK28/V28,0)) | AM28: =IF(COUNT(C28:P28)=0,"",IFERROR(AI28/I28,0)) | AN28: =IF(COUNT(C28:P28)=0,"",IFERROR(AH28/I28-AA28,0))
A29: =Config!$C$6+23 | B29: =INT((A29-Config!$C$6)/7)+1 | C29: 317 | D29: 78805 | E29: 43982 | F29: 1097 | G29: 998 | H29: 37 | I29: 11 | J29: 3 | K29: 2 | L29: 1 | M29: 1 | N29: 0 | O29: 0 | P29: 0 | Q29: =IF(COUNT(C29:P29)=0,"",IFERROR(C29/D29*1000,0)) | R29: =IF(COUNT(C29:P29)=0,"",IFERROR(D29/E29,0)) | S29: =IF(COUNT(C29:P29)=0,"",IFERROR(F29/D29,0)) | T29: =IF(COUNT(C29:P29)=0,"",IFERROR(C29/F29,0)) | U29: =IF(COUNT(C29:P29)=0,"",IFERROR(G29/F29,0)) | V29: =IF(COUNT(C29:P29)=0,"",IFERROR(C29/G29,0)) | W29: =IF(COUNT(C29:P29)=0,"",IFERROR(G29/D29*1000,0)) | X29: =IF(COUNT(C29:P29)=0,"",IFERROR(H29/G29,0)) | Y29: =IF(COUNT(C29:P29)=0,"",IFERROR(I29/H29,0)) | Z29: =IF(COUNT(C29:P29)=0,"",IFERROR(I29/G29,0)) | AA29: =IF(COUNT(C29:P29)=0,"",IFERROR(C29/I29,0)) | AB29: =IF(COUNT(C29:P29)=0,"",IFERROR(J29/I29,0)) | AC29: =IF(COUNT(C29:P29)=0,"",IFERROR(K29/I29,0)) | AD29: =IF(COUNT(C29:P29)=0,"",IFERROR(L29/I29,0)) | AE29: =IF(COUNT(C29:P29)=0,"",IFERROR(P29/I29,0)) | AF29: =IF(COUNT(C29:P29)=0,"",IFERROR(I29*Config!$C$7+J29*Config!$C$8+K29*Config!$C$9+L29*Config!$C$10+M29*Config!$C$11+N29*Config!$C$12+O29*Config!$C$13+P29*Config!$C$14,0)) | AG29: =IF(COUNT(C29:P29)=0,"",IFERROR(AF29/I29,0)) | AH29: =IF(COUNT(C29:P29)=0,"",IFERROR(AF29*(1-Config!$C$15-Config!$C$16-Config!$C$17),0)) | AI29: =IF(COUNT(C29:P29)=0,"",IFERROR(AH29-C29-Config!$C$18,0)) | AJ29: =IF(COUNT(C29:P29)=0,"",IFERROR(AH29/C29,0)) | AK29: =IF(COUNT(C29:P29)=0,"",IFERROR(AI29/G29,0)) | AL29: =IF(COUNT(C29:P29)=0,"",IFERROR(AK29/V29,0)) | AM29: =IF(COUNT(C29:P29)=0,"",IFERROR(AI29/I29,0)) | AN29: =IF(COUNT(C29:P29)=0,"",IFERROR(AH29/I29-AA29,0))
A30: =Config!$C$6+24 | B30: =INT((A30-Config!$C$6)/7)+1 | C30: 317 | D30: 71974 | E30: 42026 | F30: 1227 | G30: 1065 | H30: 39 | I30: 11 | J30: 3 | K30: 2 | L30: 1 | M30: 1 | N30: 0 | O30: 0 | P30: 0 | Q30: =IF(COUNT(C30:P30)=0,"",IFERROR(C30/D30*1000,0)) | R30: =IF(COUNT(C30:P30)=0,"",IFERROR(D30/E30,0)) | S30: =IF(COUNT(C30:P30)=0,"",IFERROR(F30/D30,0)) | T30: =IF(COUNT(C30:P30)=0,"",IFERROR(C30/F30,0)) | U30: =IF(COUNT(C30:P30)=0,"",IFERROR(G30/F30,0)) | V30: =IF(COUNT(C30:P30)=0,"",IFERROR(C30/G30,0)) | W30: =IF(COUNT(C30:P30)=0,"",IFERROR(G30/D30*1000,0)) | X30: =IF(COUNT(C30:P30)=0,"",IFERROR(H30/G30,0)) | Y30: =IF(COUNT(C30:P30)=0,"",IFERROR(I30/H30,0)) | Z30: =IF(COUNT(C30:P30)=0,"",IFERROR(I30/G30,0)) | AA30: =IF(COUNT(C30:P30)=0,"",IFERROR(C30/I30,0)) | AB30: =IF(COUNT(C30:P30)=0,"",IFERROR(J30/I30,0)) | AC30: =IF(COUNT(C30:P30)=0,"",IFERROR(K30/I30,0)) | AD30: =IF(COUNT(C30:P30)=0,"",IFERROR(L30/I30,0)) | AE30: =IF(COUNT(C30:P30)=0,"",IFERROR(P30/I30,0)) | AF30: =IF(COUNT(C30:P30)=0,"",IFERROR(I30*Config!$C$7+J30*Config!$C$8+K30*Config!$C$9+L30*Config!$C$10+M30*Config!$C$11+N30*Config!$C$12+O30*Config!$C$13+P30*Config!$C$14,0)) | AG30: =IF(COUNT(C30:P30)=0,"",IFERROR(AF30/I30,0)) | AH30: =IF(COUNT(C30:P30)=0,"",IFERROR(AF30*(1-Config!$C$15-Config!$C$16-Config!$C$17),0)) | AI30: =IF(COUNT(C30:P30)=0,"",IFERROR(AH30-C30-Config!$C$18,0)) | AJ30: =IF(COUNT(C30:P30)=0,"",IFERROR(AH30/C30,0)) | AK30: =IF(COUNT(C30:P30)=0,"",IFERROR(AI30/G30,0)) | AL30: =IF(COUNT(C30:P30)=0,"",IFERROR(AK30/V30,0)) | AM30: =IF(COUNT(C30:P30)=0,"",IFERROR(AI30/I30,0)) | AN30: =IF(COUNT(C30:P30)=0,"",IFERROR(AH30/I30-AA30,0))
A31: =Config!$C$6+25 | B31: =INT((A31-Config!$C$6)/7)+1 | C31: 327 | D31: 79368 | E31: 46372 | F31: 1338 | G31: 1225 | H31: 44 | I31: 11 | J31: 3 | K31: 2 | L31: 1 | M31: 1 | N31: 0 | O31: 0 | P31: 0 | Q31: =IF(COUNT(C31:P31)=0,"",IFERROR(C31/D31*1000,0)) | R31: =IF(COUNT(C31:P31)=0,"",IFERROR(D31/E31,0)) | S31: =IF(COUNT(C31:P31)=0,"",IFERROR(F31/D31,0)) | T31: =IF(COUNT(C31:P31)=0,"",IFERROR(C31/F31,0)) | U31: =IF(COUNT(C31:P31)=0,"",IFERROR(G31/F31,0)) | V31: =IF(COUNT(C31:P31)=0,"",IFERROR(C31/G31,0)) | W31: =IF(COUNT(C31:P31)=0,"",IFERROR(G31/D31*1000,0)) | X31: =IF(COUNT(C31:P31)=0,"",IFERROR(H31/G31,0)) | Y31: =IF(COUNT(C31:P31)=0,"",IFERROR(I31/H31,0)) | Z31: =IF(COUNT(C31:P31)=0,"",IFERROR(I31/G31,0)) | AA31: =IF(COUNT(C31:P31)=0,"",IFERROR(C31/I31,0)) | AB31: =IF(COUNT(C31:P31)=0,"",IFERROR(J31/I31,0)) | AC31: =IF(COUNT(C31:P31)=0,"",IFERROR(K31/I31,0)) | AD31: =IF(COUNT(C31:P31)=0,"",IFERROR(L31/I31,0)) | AE31: =IF(COUNT(C31:P31)=0,"",IFERROR(P31/I31,0)) | AF31: =IF(COUNT(C31:P31)=0,"",IFERROR(I31*Config!$C$7+J31*Config!$C$8+K31*Config!$C$9+L31*Config!$C$10+M31*Config!$C$11+N31*Config!$C$12+O31*Config!$C$13+P31*Config!$C$14,0)) | AG31: =IF(COUNT(C31:P31)=0,"",IFERROR(AF31/I31,0)) | AH31: =IF(COUNT(C31:P31)=0,"",IFERROR(AF31*(1-Config!$C$15-Config!$C$16-Config!$C$17),0)) | AI31: =IF(COUNT(C31:P31)=0,"",IFERROR(AH31-C31-Config!$C$18,0)) | AJ31: =IF(COUNT(C31:P31)=0,"",IFERROR(AH31/C31,0)) | AK31: =IF(COUNT(C31:P31)=0,"",IFERROR(AI31/G31,0)) | AL31: =IF(COUNT(C31:P31)=0,"",IFERROR(AK31/V31,0)) | AM31: =IF(COUNT(C31:P31)=0,"",IFERROR(AI31/I31,0)) | AN31: =IF(COUNT(C31:P31)=0,"",IFERROR(AH31/I31-AA31,0))
A32: =Config!$C$6+26 | B32: =INT((A32-Config!$C$6)/7)+1 | C32: 306 | D32: 70991 | E32: 49341 | F32: 1137 | G32: 1145 | H32: 44 | I32: 12 | J32: 3 | K32: 2 | L32: 1 | M32: 1 | N32: 0 | O32: 0 | P32: 0 | Q32: =IF(COUNT(C32:P32)=0,"",IFERROR(C32/D32*1000,0)) | R32: =IF(COUNT(C32:P32)=0,"",IFERROR(D32/E32,0)) | S32: =IF(COUNT(C32:P32)=0,"",IFERROR(F32/D32,0)) | T32: =IF(COUNT(C32:P32)=0,"",IFERROR(C32/F32,0)) | U32: =IF(COUNT(C32:P32)=0,"",IFERROR(G32/F32,0)) | V32: =IF(COUNT(C32:P32)=0,"",IFERROR(C32/G32,0)) | W32: =IF(COUNT(C32:P32)=0,"",IFERROR(G32/D32*1000,0)) | X32: =IF(COUNT(C32:P32)=0,"",IFERROR(H32/G32,0)) | Y32: =IF(COUNT(C32:P32)=0,"",IFERROR(I32/H32,0)) | Z32: =IF(COUNT(C32:P32)=0,"",IFERROR(I32/G32,0)) | AA32: =IF(COUNT(C32:P32)=0,"",IFERROR(C32/I32,0)) | AB32: =IF(COUNT(C32:P32)=0,"",IFERROR(J32/I32,0)) | AC32: =IF(COUNT(C32:P32)=0,"",IFERROR(K32/I32,0)) | AD32: =IF(COUNT(C32:P32)=0,"",IFERROR(L32/I32,0)) | AE32: =IF(COUNT(C32:P32)=0,"",IFERROR(P32/I32,0)) | AF32: =IF(COUNT(C32:P32)=0,"",IFERROR(I32*Config!$C$7+J32*Config!$C$8+K32*Config!$C$9+L32*Config!$C$10+M32*Config!$C$11+N32*Config!$C$12+O32*Config!$C$13+P32*Config!$C$14,0)) | AG32: =IF(COUNT(C32:P32)=0,"",IFERROR(AF32/I32,0)) | AH32: =IF(COUNT(C32:P32)=0,"",IFERROR(AF32*(1-Config!$C$15-Config!$C$16-Config!$C$17),0)) | AI32: =IF(COUNT(C32:P32)=0,"",IFERROR(AH32-C32-Config!$C$18,0)) | AJ32: =IF(COUNT(C32:P32)=0,"",IFERROR(AH32/C32,0)) | AK32: =IF(COUNT(C32:P32)=0,"",IFERROR(AI32/G32,0)) | AL32: =IF(COUNT(C32:P32)=0,"",IFERROR(AK32/V32,0)) | AM32: =IF(COUNT(C32:P32)=0,"",IFERROR(AI32/I32,0)) | AN32: =IF(COUNT(C32:P32)=0,"",IFERROR(AH32/I32-AA32,0))
A33: =Config!$C$6+27 | B33: =INT((A33-Config!$C$6)/7)+1 | C33: 292 | D33: 65804 | E33: 40344 | F33: 1005 | G33: 978 | H33: 31 | I33: 8 | J33: 2 | K33: 2 | L33: 1 | M33: 1 | N33: 0 | O33: 0 | P33: 0 | Q33: =IF(COUNT(C33:P33)=0,"",IFERROR(C33/D33*1000,0)) | R33: =IF(COUNT(C33:P33)=0,"",IFERROR(D33/E33,0)) | S33: =IF(COUNT(C33:P33)=0,"",IFERROR(F33/D33,0)) | T33: =IF(COUNT(C33:P33)=0,"",IFERROR(C33/F33,0)) | U33: =IF(COUNT(C33:P33)=0,"",IFERROR(G33/F33,0)) | V33: =IF(COUNT(C33:P33)=0,"",IFERROR(C33/G33,0)) | W33: =IF(COUNT(C33:P33)=0,"",IFERROR(G33/D33*1000,0)) | X33: =IF(COUNT(C33:P33)=0,"",IFERROR(H33/G33,0)) | Y33: =IF(COUNT(C33:P33)=0,"",IFERROR(I33/H33,0)) | Z33: =IF(COUNT(C33:P33)=0,"",IFERROR(I33/G33,0)) | AA33: =IF(COUNT(C33:P33)=0,"",IFERROR(C33/I33,0)) | AB33: =IF(COUNT(C33:P33)=0,"",IFERROR(J33/I33,0)) | AC33: =IF(COUNT(C33:P33)=0,"",IFERROR(K33/I33,0)) | AD33: =IF(COUNT(C33:P33)=0,"",IFERROR(L33/I33,0)) | AE33: =IF(COUNT(C33:P33)=0,"",IFERROR(P33/I33,0)) | AF33: =IF(COUNT(C33:P33)=0,"",IFERROR(I33*Config!$C$7+J33*Config!$C$8+K33*Config!$C$9+L33*Config!$C$10+M33*Config!$C$11+N33*Config!$C$12+O33*Config!$C$13+P33*Config!$C$14,0)) | AG33: =IF(COUNT(C33:P33)=0,"",IFERROR(AF33/I33,0)) | AH33: =IF(COUNT(C33:P33)=0,"",IFERROR(AF33*(1-Config!$C$15-Config!$C$16-Config!$C$17),0)) | AI33: =IF(COUNT(C33:P33)=0,"",IFERROR(AH33-C33-Config!$C$18,0)) | AJ33: =IF(COUNT(C33:P33)=0,"",IFERROR(AH33/C33,0)) | AK33: =IF(COUNT(C33:P33)=0,"",IFERROR(AI33/G33,0)) | AL33: =IF(COUNT(C33:P33)=0,"",IFERROR(AK33/V33,0)) | AM33: =IF(COUNT(C33:P33)=0,"",IFERROR(AI33/I33,0)) | AN33: =IF(COUNT(C33:P33)=0,"",IFERROR(AH33/I33-AA33,0))
A34: =Config!$C$6+28 | B34: =INT((A34-Config!$C$6)/7)+1 | Q34: =IF(COUNT(C34:P34)=0,"",IFERROR(C34/D34*1000,0)) | R34: =IF(COUNT(C34:P34)=0,"",IFERROR(D34/E34,0)) | S34: =IF(COUNT(C34:P34)=0,"",IFERROR(F34/D34,0)) | T34: =IF(COUNT(C34:P34)=0,"",IFERROR(C34/F34,0)) | U34: =IF(COUNT(C34:P34)=0,"",IFERROR(G34/F34,0)) | V34: =IF(COUNT(C34:P34)=0,"",IFERROR(C34/G34,0)) | W34: =IF(COUNT(C34:P34)=0,"",IFERROR(G34/D34*1000,0)) | X34: =IF(COUNT(C34:P34)=0,"",IFERROR(H34/G34,0)) | Y34: =IF(COUNT(C34:P34)=0,"",IFERROR(I34/H34,0)) | Z34: =IF(COUNT(C34:P34)=0,"",IFERROR(I34/G34,0)) | AA34: =IF(COUNT(C34:P34)=0,"",IFERROR(C34/I34,0)) | AB34: =IF(COUNT(C34:P34)=0,"",IFERROR(J34/I34,0)) | AC34: =IF(COUNT(C34:P34)=0,"",IFERROR(K34/I34,0)) | AD34: =IF(COUNT(C34:P34)=0,"",IFERROR(L34/I34,0)) | AE34: =IF(COUNT(C34:P34)=0,"",IFERROR(P34/I34,0)) | AF34: =IF(COUNT(C34:P34)=0,"",IFERROR(I34*Config!$C$7+J34*Config!$C$8+K34*Config!$C$9+L34*Config!$C$10+M34*Config!$C$11+N34*Config!$C$12+O34*Config!$C$13+P34*Config!$C$14,0)) | AG34: =IF(COUNT(C34:P34)=0,"",IFERROR(AF34/I34,0)) | AH34: =IF(COUNT(C34:P34)=0,"",IFERROR(AF34*(1-Config!$C$15-Config!$C$16-Config!$C$17),0)) | AI34: =IF(COUNT(C34:P34)=0,"",IFERROR(AH34-C34-Config!$C$18,0)) | AJ34: =IF(COUNT(C34:P34)=0,"",IFERROR(AH34/C34,0)) | AK34: =IF(COUNT(C34:P34)=0,"",IFERROR(AI34/G34,0)) | AL34: =IF(COUNT(C34:P34)=0,"",IFERROR(AK34/V34,0)) | AM34: =IF(COUNT(C34:P34)=0,"",IFERROR(AI34/I34,0)) | AN34: =IF(COUNT(C34:P34)=0,"",IFERROR(AH34/I34-AA34,0))
A35: =Config!$C$6+29 | B35: =INT((A35-Config!$C$6)/7)+1 | Q35: =IF(COUNT(C35:P35)=0,"",IFERROR(C35/D35*1000,0)) | R35: =IF(COUNT(C35:P35)=0,"",IFERROR(D35/E35,0)) | S35: =IF(COUNT(C35:P35)=0,"",IFERROR(F35/D35,0)) | T35: =IF(COUNT(C35:P35)=0,"",IFERROR(C35/F35,0)) | U35: =IF(COUNT(C35:P35)=0,"",IFERROR(G35/F35,0)) | V35: =IF(COUNT(C35:P35)=0,"",IFERROR(C35/G35,0)) | W35: =IF(COUNT(C35:P35)=0,"",IFERROR(G35/D35*1000,0)) | X35: =IF(COUNT(C35:P35)=0,"",IFERROR(H35/G35,0)) | Y35: =IF(COUNT(C35:P35)=0,"",IFERROR(I35/H35,0)) | Z35: =IF(COUNT(C35:P35)=0,"",IFERROR(I35/G35,0)) | AA35: =IF(COUNT(C35:P35)=0,"",IFERROR(C35/I35,0)) | AB35: =IF(COUNT(C35:P35)=0,"",IFERROR(J35/I35,0)) | AC35: =IF(COUNT(C35:P35)=0,"",IFERROR(K35/I35,0)) | AD35: =IF(COUNT(C35:P35)=0,"",IFERROR(L35/I35,0)) | AE35: =IF(COUNT(C35:P35)=0,"",IFERROR(P35/I35,0)) | AF35: =IF(COUNT(C35:P35)=0,"",IFERROR(I35*Config!$C$7+J35*Config!$C$8+K35*Config!$C$9+L35*Config!$C$10+M35*Config!$C$11+N35*Config!$C$12+O35*Config!$C$13+P35*Config!$C$14,0)) | AG35: =IF(COUNT(C35:P35)=0,"",IFERROR(AF35/I35,0)) | AH35: =IF(COUNT(C35:P35)=0,"",IFERROR(AF35*(1-Config!$C$15-Config!$C$16-Config!$C$17),0)) | AI35: =IF(COUNT(C35:P35)=0,"",IFERROR(AH35-C35-Config!$C$18,0)) | AJ35: =IF(COUNT(C35:P35)=0,"",IFERROR(AH35/C35,0)) | AK35: =IF(COUNT(C35:P35)=0,"",IFERROR(AI35/G35,0)) | AL35: =IF(COUNT(C35:P35)=0,"",IFERROR(AK35/V35,0)) | AM35: =IF(COUNT(C35:P35)=0,"",IFERROR(AI35/I35,0)) | AN35: =IF(COUNT(C35:P35)=0,"",IFERROR(AH35/I35-AA35,0))
A36: =Config!$C$6+30 | B36: =INT((A36-Config!$C$6)/7)+1 | Q36: =IF(COUNT(C36:P36)=0,"",IFERROR(C36/D36*1000,0)) | R36: =IF(COUNT(C36:P36)=0,"",IFERROR(D36/E36,0)) | S36: =IF(COUNT(C36:P36)=0,"",IFERROR(F36/D36,0)) | T36: =IF(COUNT(C36:P36)=0,"",IFERROR(C36/F36,0)) | U36: =IF(COUNT(C36:P36)=0,"",IFERROR(G36/F36,0)) | V36: =IF(COUNT(C36:P36)=0,"",IFERROR(C36/G36,0)) | W36: =IF(COUNT(C36:P36)=0,"",IFERROR(G36/D36*1000,0)) | X36: =IF(COUNT(C36:P36)=0,"",IFERROR(H36/G36,0)) | Y36: =IF(COUNT(C36:P36)=0,"",IFERROR(I36/H36,0)) | Z36: =IF(COUNT(C36:P36)=0,"",IFERROR(I36/G36,0)) | AA36: =IF(COUNT(C36:P36)=0,"",IFERROR(C36/I36,0)) | AB36: =IF(COUNT(C36:P36)=0,"",IFERROR(J36/I36,0)) | AC36: =IF(COUNT(C36:P36)=0,"",IFERROR(K36/I36,0)) | AD36: =IF(COUNT(C36:P36)=0,"",IFERROR(L36/I36,0)) | AE36: =IF(COUNT(C36:P36)=0,"",IFERROR(P36/I36,0)) | AF36: =IF(COUNT(C36:P36)=0,"",IFERROR(I36*Config!$C$7+J36*Config!$C$8+K36*Config!$C$9+L36*Config!$C$10+M36*Config!$C$11+N36*Config!$C$12+O36*Config!$C$13+P36*Config!$C$14,0)) | AG36: =IF(COUNT(C36:P36)=0,"",IFERROR(AF36/I36,0)) | AH36: =IF(COUNT(C36:P36)=0,"",IFERROR(AF36*(1-Config!$C$15-Config!$C$16-Config!$C$17),0)) | AI36: =IF(COUNT(C36:P36)=0,"",IFERROR(AH36-C36-Config!$C$18,0)) | AJ36: =IF(COUNT(C36:P36)=0,"",IFERROR(AH36/C36,0)) | AK36: =IF(COUNT(C36:P36)=0,"",IFERROR(AI36/G36,0)) | AL36: =IF(COUNT(C36:P36)=0,"",IFERROR(AK36/V36,0)) | AM36: =IF(COUNT(C36:P36)=0,"",IFERROR(AI36/I36,0)) | AN36: =IF(COUNT(C36:P36)=0,"",IFERROR(AH36/I36-AA36,0))
A37: =Config!$C$6+31 | B37: =INT((A37-Config!$C$6)/7)+1 | Q37: =IF(COUNT(C37:P37)=0,"",IFERROR(C37/D37*1000,0)) | R37: =IF(COUNT(C37:P37)=0,"",IFERROR(D37/E37,0)) | S37: =IF(COUNT(C37:P37)=0,"",IFERROR(F37/D37,0)) | T37: =IF(COUNT(C37:P37)=0,"",IFERROR(C37/F37,0)) | U37: =IF(COUNT(C37:P37)=0,"",IFERROR(G37/F37,0)) | V37: =IF(COUNT(C37:P37)=0,"",IFERROR(C37/G37,0)) | W37: =IF(COUNT(C37:P37)=0,"",IFERROR(G37/D37*1000,0)) | X37: =IF(COUNT(C37:P37)=0,"",IFERROR(H37/G37,0)) | Y37: =IF(COUNT(C37:P37)=0,"",IFERROR(I37/H37,0)) | Z37: =IF(COUNT(C37:P37)=0,"",IFERROR(I37/G37,0)) | AA37: =IF(COUNT(C37:P37)=0,"",IFERROR(C37/I37,0)) | AB37: =IF(COUNT(C37:P37)=0,"",IFERROR(J37/I37,0)) | AC37: =IF(COUNT(C37:P37)=0,"",IFERROR(K37/I37,0)) | AD37: =IF(COUNT(C37:P37)=0,"",IFERROR(L37/I37,0)) | AE37: =IF(COUNT(C37:P37)=0,"",IFERROR(P37/I37,0)) | AF37: =IF(COUNT(C37:P37)=0,"",IFERROR(I37*Config!$C$7+J37*Config!$C$8+K37*Config!$C$9+L37*Config!$C$10+M37*Config!$C$11+N37*Config!$C$12+O37*Config!$C$13+P37*Config!$C$14,0)) | AG37: =IF(COUNT(C37:P37)=0,"",IFERROR(AF37/I37,0)) | AH37: =IF(COUNT(C37:P37)=0,"",IFERROR(AF37*(1-Config!$C$15-Config!$C$16-Config!$C$17),0)) | AI37: =IF(COUNT(C37:P37)=0,"",IFERROR(AH37-C37-Config!$C$18,0)) | AJ37: =IF(COUNT(C37:P37)=0,"",IFERROR(AH37/C37,0)) | AK37: =IF(COUNT(C37:P37)=0,"",IFERROR(AI37/G37,0)) | AL37: =IF(COUNT(C37:P37)=0,"",IFERROR(AK37/V37,0)) | AM37: =IF(COUNT(C37:P37)=0,"",IFERROR(AI37/I37,0)) | AN37: =IF(COUNT(C37:P37)=0,"",IFERROR(AH37/I37-AA37,0))
A38: =Config!$C$6+32 | B38: =INT((A38-Config!$C$6)/7)+1 | Q38: =IF(COUNT(C38:P38)=0,"",IFERROR(C38/D38*1000,0)) | R38: =IF(COUNT(C38:P38)=0,"",IFERROR(D38/E38,0)) | S38: =IF(COUNT(C38:P38)=0,"",IFERROR(F38/D38,0)) | T38: =IF(COUNT(C38:P38)=0,"",IFERROR(C38/F38,0)) | U38: =IF(COUNT(C38:P38)=0,"",IFERROR(G38/F38,0)) | V38: =IF(COUNT(C38:P38)=0,"",IFERROR(C38/G38,0)) | W38: =IF(COUNT(C38:P38)=0,"",IFERROR(G38/D38*1000,0)) | X38: =IF(COUNT(C38:P38)=0,"",IFERROR(H38/G38,0)) | Y38: =IF(COUNT(C38:P38)=0,"",IFERROR(I38/H38,0)) | Z38: =IF(COUNT(C38:P38)=0,"",IFERROR(I38/G38,0)) | AA38: =IF(COUNT(C38:P38)=0,"",IFERROR(C38/I38,0)) | AB38: =IF(COUNT(C38:P38)=0,"",IFERROR(J38/I38,0)) | AC38: =IF(COUNT(C38:P38)=0,"",IFERROR(K38/I38,0)) | AD38: =IF(COUNT(C38:P38)=0,"",IFERROR(L38/I38,0)) | AE38: =IF(COUNT(C38:P38)=0,"",IFERROR(P38/I38,0)) | AF38: =IF(COUNT(C38:P38)=0,"",IFERROR(I38*Config!$C$7+J38*Config!$C$8+K38*Config!$C$9+L38*Config!$C$10+M38*Config!$C$11+N38*Config!$C$12+O38*Config!$C$13+P38*Config!$C$14,0)) | AG38: =IF(COUNT(C38:P38)=0,"",IFERROR(AF38/I38,0)) | AH38: =IF(COUNT(C38:P38)=0,"",IFERROR(AF38*(1-Config!$C$15-Config!$C$16-Config!$C$17),0)) | AI38: =IF(COUNT(C38:P38)=0,"",IFERROR(AH38-C38-Config!$C$18,0)) | AJ38: =IF(COUNT(C38:P38)=0,"",IFERROR(AH38/C38,0)) | AK38: =IF(COUNT(C38:P38)=0,"",IFERROR(AI38/G38,0)) | AL38: =IF(COUNT(C38:P38)=0,"",IFERROR(AK38/V38,0)) | AM38: =IF(COUNT(C38:P38)=0,"",IFERROR(AI38/I38,0)) | AN38: =IF(COUNT(C38:P38)=0,"",IFERROR(AH38/I38-AA38,0))
A39: =Config!$C$6+33 | B39: =INT((A39-Config!$C$6)/7)+1 | Q39: =IF(COUNT(C39:P39)=0,"",IFERROR(C39/D39*1000,0)) | R39: =IF(COUNT(C39:P39)=0,"",IFERROR(D39/E39,0)) | S39: =IF(COUNT(C39:P39)=0,"",IFERROR(F39/D39,0)) | T39: =IF(COUNT(C39:P39)=0,"",IFERROR(C39/F39,0)) | U39: =IF(COUNT(C39:P39)=0,"",IFERROR(G39/F39,0)) | V39: =IF(COUNT(C39:P39)=0,"",IFERROR(C39/G39,0)) | W39: =IF(COUNT(C39:P39)=0,"",IFERROR(G39/D39*1000,0)) | X39: =IF(COUNT(C39:P39)=0,"",IFERROR(H39/G39,0)) | Y39: =IF(COUNT(C39:P39)=0,"",IFERROR(I39/H39,0)) | Z39: =IF(COUNT(C39:P39)=0,"",IFERROR(I39/G39,0)) | AA39: =IF(COUNT(C39:P39)=0,"",IFERROR(C39/I39,0)) | AB39: =IF(COUNT(C39:P39)=0,"",IFERROR(J39/I39,0)) | AC39: =IF(COUNT(C39:P39)=0,"",IFERROR(K39/I39,0)) | AD39: =IF(COUNT(C39:P39)=0,"",IFERROR(L39/I39,0)) | AE39: =IF(COUNT(C39:P39)=0,"",IFERROR(P39/I39,0)) | AF39: =IF(COUNT(C39:P39)=0,"",IFERROR(I39*Config!$C$7+J39*Config!$C$8+K39*Config!$C$9+L39*Config!$C$10+M39*Config!$C$11+N39*Config!$C$12+O39*Config!$C$13+P39*Config!$C$14,0)) | AG39: =IF(COUNT(C39:P39)=0,"",IFERROR(AF39/I39,0)) | AH39: =IF(COUNT(C39:P39)=0,"",IFERROR(AF39*(1-Config!$C$15-Config!$C$16-Config!$C$17),0)) | AI39: =IF(COUNT(C39:P39)=0,"",IFERROR(AH39-C39-Config!$C$18,0)) | AJ39: =IF(COUNT(C39:P39)=0,"",IFERROR(AH39/C39,0)) | AK39: =IF(COUNT(C39:P39)=0,"",IFERROR(AI39/G39,0)) | AL39: =IF(COUNT(C39:P39)=0,"",IFERROR(AK39/V39,0)) | AM39: =IF(COUNT(C39:P39)=0,"",IFERROR(AI39/I39,0)) | AN39: =IF(COUNT(C39:P39)=0,"",IFERROR(AH39/I39-AA39,0))
A40: =Config!$C$6+34 | B40: =INT((A40-Config!$C$6)/7)+1 | Q40: =IF(COUNT(C40:P40)=0,"",IFERROR(C40/D40*1000,0)) | R40: =IF(COUNT(C40:P40)=0,"",IFERROR(D40/E40,0)) | S40: =IF(COUNT(C40:P40)=0,"",IFERROR(F40/D40,0)) | T40: =IF(COUNT(C40:P40)=0,"",IFERROR(C40/F40,0)) | U40: =IF(COUNT(C40:P40)=0,"",IFERROR(G40/F40,0)) | V40: =IF(COUNT(C40:P40)=0,"",IFERROR(C40/G40,0)) | W40: =IF(COUNT(C40:P40)=0,"",IFERROR(G40/D40*1000,0)) | X40: =IF(COUNT(C40:P40)=0,"",IFERROR(H40/G40,0)) | Y40: =IF(COUNT(C40:P40)=0,"",IFERROR(I40/H40,0)) | Z40: =IF(COUNT(C40:P40)=0,"",IFERROR(I40/G40,0)) | AA40: =IF(COUNT(C40:P40)=0,"",IFERROR(C40/I40,0)) | AB40: =IF(COUNT(C40:P40)=0,"",IFERROR(J40/I40,0)) | AC40: =IF(COUNT(C40:P40)=0,"",IFERROR(K40/I40,0)) | AD40: =IF(COUNT(C40:P40)=0,"",IFERROR(L40/I40,0)) | AE40: =IF(COUNT(C40:P40)=0,"",IFERROR(P40/I40,0)) | AF40: =IF(COUNT(C40:P40)=0,"",IFERROR(I40*Config!$C$7+J40*Config!$C$8+K40*Config!$C$9+L40*Config!$C$10+M40*Config!$C$11+N40*Config!$C$12+O40*Config!$C$13+P40*Config!$C$14,0)) | AG40: =IF(COUNT(C40:P40)=0,"",IFERROR(AF40/I40,0)) | AH40: =IF(COUNT(C40:P40)=0,"",IFERROR(AF40*(1-Config!$C$15-Config!$C$16-Config!$C$17),0)) | AI40: =IF(COUNT(C40:P40)=0,"",IFERROR(AH40-C40-Config!$C$18,0)) | AJ40: =IF(COUNT(C40:P40)=0,"",IFERROR(AH40/C40,0)) | AK40: =IF(COUNT(C40:P40)=0,"",IFERROR(AI40/G40,0)) | AL40: =IF(COUNT(C40:P40)=0,"",IFERROR(AK40/V40,0)) | AM40: =IF(COUNT(C40:P40)=0,"",IFERROR(AI40/I40,0)) | AN40: =IF(COUNT(C40:P40)=0,"",IFERROR(AH40/I40-AA40,0))
A41: =Config!$C$6+35 | B41: =INT((A41-Config!$C$6)/7)+1 | Q41: =IF(COUNT(C41:P41)=0,"",IFERROR(C41/D41*1000,0)) | R41: =IF(COUNT(C41:P41)=0,"",IFERROR(D41/E41,0)) | S41: =IF(COUNT(C41:P41)=0,"",IFERROR(F41/D41,0)) | T41: =IF(COUNT(C41:P41)=0,"",IFERROR(C41/F41,0)) | U41: =IF(COUNT(C41:P41)=0,"",IFERROR(G41/F41,0)) | V41: =IF(COUNT(C41:P41)=0,"",IFERROR(C41/G41,0)) | W41: =IF(COUNT(C41:P41)=0,"",IFERROR(G41/D41*1000,0)) | X41: =IF(COUNT(C41:P41)=0,"",IFERROR(H41/G41,0)) | Y41: =IF(COUNT(C41:P41)=0,"",IFERROR(I41/H41,0)) | Z41: =IF(COUNT(C41:P41)=0,"",IFERROR(I41/G41,0)) | AA41: =IF(COUNT(C41:P41)=0,"",IFERROR(C41/I41,0)) | AB41: =IF(COUNT(C41:P41)=0,"",IFERROR(J41/I41,0)) | AC41: =IF(COUNT(C41:P41)=0,"",IFERROR(K41/I41,0)) | AD41: =IF(COUNT(C41:P41)=0,"",IFERROR(L41/I41,0)) | AE41: =IF(COUNT(C41:P41)=0,"",IFERROR(P41/I41,0)) | AF41: =IF(COUNT(C41:P41)=0,"",IFERROR(I41*Config!$C$7+J41*Config!$C$8+K41*Config!$C$9+L41*Config!$C$10+M41*Config!$C$11+N41*Config!$C$12+O41*Config!$C$13+P41*Config!$C$14,0)) | AG41: =IF(COUNT(C41:P41)=0,"",IFERROR(AF41/I41,0)) | AH41: =IF(COUNT(C41:P41)=0,"",IFERROR(AF41*(1-Config!$C$15-Config!$C$16-Config!$C$17),0)) | AI41: =IF(COUNT(C41:P41)=0,"",IFERROR(AH41-C41-Config!$C$18,0)) | AJ41: =IF(COUNT(C41:P41)=0,"",IFERROR(AH41/C41,0)) | AK41: =IF(COUNT(C41:P41)=0,"",IFERROR(AI41/G41,0)) | AL41: =IF(COUNT(C41:P41)=0,"",IFERROR(AK41/V41,0)) | AM41: =IF(COUNT(C41:P41)=0,"",IFERROR(AI41/I41,0)) | AN41: =IF(COUNT(C41:P41)=0,"",IFERROR(AH41/I41-AA41,0))
A42: =Config!$C$6+36 | B42: =INT((A42-Config!$C$6)/7)+1 | Q42: =IF(COUNT(C42:P42)=0,"",IFERROR(C42/D42*1000,0)) | R42: =IF(COUNT(C42:P42)=0,"",IFERROR(D42/E42,0)) | S42: =IF(COUNT(C42:P42)=0,"",IFERROR(F42/D42,0)) | T42: =IF(COUNT(C42:P42)=0,"",IFERROR(C42/F42,0)) | U42: =IF(COUNT(C42:P42)=0,"",IFERROR(G42/F42,0)) | V42: =IF(COUNT(C42:P42)=0,"",IFERROR(C42/G42,0)) | W42: =IF(COUNT(C42:P42)=0,"",IFERROR(G42/D42*1000,0)) | X42: =IF(COUNT(C42:P42)=0,"",IFERROR(H42/G42,0)) | Y42: =IF(COUNT(C42:P42)=0,"",IFERROR(I42/H42,0)) | Z42: =IF(COUNT(C42:P42)=0,"",IFERROR(I42/G42,0)) | AA42: =IF(COUNT(C42:P42)=0,"",IFERROR(C42/I42,0)) | AB42: =IF(COUNT(C42:P42)=0,"",IFERROR(J42/I42,0)) | AC42: =IF(COUNT(C42:P42)=0,"",IFERROR(K42/I42,0)) | AD42: =IF(COUNT(C42:P42)=0,"",IFERROR(L42/I42,0)) | AE42: =IF(COUNT(C42:P42)=0,"",IFERROR(P42/I42,0)) | AF42: =IF(COUNT(C42:P42)=0,"",IFERROR(I42*Config!$C$7+J42*Config!$C$8+K42*Config!$C$9+L42*Config!$C$10+M42*Config!$C$11+N42*Config!$C$12+O42*Config!$C$13+P42*Config!$C$14,0)) | AG42: =IF(COUNT(C42:P42)=0,"",IFERROR(AF42/I42,0)) | AH42: =IF(COUNT(C42:P42)=0,"",IFERROR(AF42*(1-Config!$C$15-Config!$C$16-Config!$C$17),0)) | AI42: =IF(COUNT(C42:P42)=0,"",IFERROR(AH42-C42-Config!$C$18,0)) | AJ42: =IF(COUNT(C42:P42)=0,"",IFERROR(AH42/C42,0)) | AK42: =IF(COUNT(C42:P42)=0,"",IFERROR(AI42/G42,0)) | AL42: =IF(COUNT(C42:P42)=0,"",IFERROR(AK42/V42,0)) | AM42: =IF(COUNT(C42:P42)=0,"",IFERROR(AI42/I42,0)) | AN42: =IF(COUNT(C42:P42)=0,"",IFERROR(AH42/I42-AA42,0))
A43: =Config!$C$6+37 | B43: =INT((A43-Config!$C$6)/7)+1 | Q43: =IF(COUNT(C43:P43)=0,"",IFERROR(C43/D43*1000,0)) | R43: =IF(COUNT(C43:P43)=0,"",IFERROR(D43/E43,0)) | S43: =IF(COUNT(C43:P43)=0,"",IFERROR(F43/D43,0)) | T43: =IF(COUNT(C43:P43)=0,"",IFERROR(C43/F43,0)) | U43: =IF(COUNT(C43:P43)=0,"",IFERROR(G43/F43,0)) | V43: =IF(COUNT(C43:P43)=0,"",IFERROR(C43/G43,0)) | W43: =IF(COUNT(C43:P43)=0,"",IFERROR(G43/D43*1000,0)) | X43: =IF(COUNT(C43:P43)=0,"",IFERROR(H43/G43,0)) | Y43: =IF(COUNT(C43:P43)=0,"",IFERROR(I43/H43,0)) | Z43: =IF(COUNT(C43:P43)=0,"",IFERROR(I43/G43,0)) | AA43: =IF(COUNT(C43:P43)=0,"",IFERROR(C43/I43,0)) | AB43: =IF(COUNT(C43:P43)=0,"",IFERROR(J43/I43,0)) | AC43: =IF(COUNT(C43:P43)=0,"",IFERROR(K43/I43,0)) | AD43: =IF(COUNT(C43:P43)=0,"",IFERROR(L43/I43,0)) | AE43: =IF(COUNT(C43:P43)=0,"",IFERROR(P43/I43,0)) | AF43: =IF(COUNT(C43:P43)=0,"",IFERROR(I43*Config!$C$7+J43*Config!$C$8+K43*Config!$C$9+L43*Config!$C$10+M43*Config!$C$11+N43*Config!$C$12+O43*Config!$C$13+P43*Config!$C$14,0)) | AG43: =IF(COUNT(C43:P43)=0,"",IFERROR(AF43/I43,0)) | AH43: =IF(COUNT(C43:P43)=0,"",IFERROR(AF43*(1-Config!$C$15-Config!$C$16-Config!$C$17),0)) | AI43: =IF(COUNT(C43:P43)=0,"",IFERROR(AH43-C43-Config!$C$18,0)) | AJ43: =IF(COUNT(C43:P43)=0,"",IFERROR(AH43/C43,0)) | AK43: =IF(COUNT(C43:P43)=0,"",IFERROR(AI43/G43,0)) | AL43: =IF(COUNT(C43:P43)=0,"",IFERROR(AK43/V43,0)) | AM43: =IF(COUNT(C43:P43)=0,"",IFERROR(AI43/I43,0)) | AN43: =IF(COUNT(C43:P43)=0,"",IFERROR(AH43/I43-AA43,0))
A44: =Config!$C$6+38 | B44: =INT((A44-Config!$C$6)/7)+1 | Q44: =IF(COUNT(C44:P44)=0,"",IFERROR(C44/D44*1000,0)) | R44: =IF(COUNT(C44:P44)=0,"",IFERROR(D44/E44,0)) | S44: =IF(COUNT(C44:P44)=0,"",IFERROR(F44/D44,0)) | T44: =IF(COUNT(C44:P44)=0,"",IFERROR(C44/F44,0)) | U44: =IF(COUNT(C44:P44)=0,"",IFERROR(G44/F44,0)) | V44: =IF(COUNT(C44:P44)=0,"",IFERROR(C44/G44,0)) | W44: =IF(COUNT(C44:P44)=0,"",IFERROR(G44/D44*1000,0)) | X44: =IF(COUNT(C44:P44)=0,"",IFERROR(H44/G44,0)) | Y44: =IF(COUNT(C44:P44)=0,"",IFERROR(I44/H44,0)) | Z44: =IF(COUNT(C44:P44)=0,"",IFERROR(I44/G44,0)) | AA44: =IF(COUNT(C44:P44)=0,"",IFERROR(C44/I44,0)) | AB44: =IF(COUNT(C44:P44)=0,"",IFERROR(J44/I44,0)) | AC44: =IF(COUNT(C44:P44)=0,"",IFERROR(K44/I44,0)) | AD44: =IF(COUNT(C44:P44)=0,"",IFERROR(L44/I44,0)) | AE44: =IF(COUNT(C44:P44)=0,"",IFERROR(P44/I44,0)) | AF44: =IF(COUNT(C44:P44)=0,"",IFERROR(I44*Config!$C$7+J44*Config!$C$8+K44*Config!$C$9+L44*Config!$C$10+M44*Config!$C$11+N44*Config!$C$12+O44*Config!$C$13+P44*Config!$C$14,0)) | AG44: =IF(COUNT(C44:P44)=0,"",IFERROR(AF44/I44,0)) | AH44: =IF(COUNT(C44:P44)=0,"",IFERROR(AF44*(1-Config!$C$15-Config!$C$16-Config!$C$17),0)) | AI44: =IF(COUNT(C44:P44)=0,"",IFERROR(AH44-C44-Config!$C$18,0)) | AJ44: =IF(COUNT(C44:P44)=0,"",IFERROR(AH44/C44,0)) | AK44: =IF(COUNT(C44:P44)=0,"",IFERROR(AI44/G44,0)) | AL44: =IF(COUNT(C44:P44)=0,"",IFERROR(AK44/V44,0)) | AM44: =IF(COUNT(C44:P44)=0,"",IFERROR(AI44/I44,0)) | AN44: =IF(COUNT(C44:P44)=0,"",IFERROR(AH44/I44-AA44,0))
A45: =Config!$C$6+39 | B45: =INT((A45-Config!$C$6)/7)+1 | Q45: =IF(COUNT(C45:P45)=0,"",IFERROR(C45/D45*1000,0)) | R45: =IF(COUNT(C45:P45)=0,"",IFERROR(D45/E45,0)) | S45: =IF(COUNT(C45:P45)=0,"",IFERROR(F45/D45,0)) | T45: =IF(COUNT(C45:P45)=0,"",IFERROR(C45/F45,0)) | U45: =IF(COUNT(C45:P45)=0,"",IFERROR(G45/F45,0)) | V45: =IF(COUNT(C45:P45)=0,"",IFERROR(C45/G45,0)) | W45: =IF(COUNT(C45:P45)=0,"",IFERROR(G45/D45*1000,0)) | X45: =IF(COUNT(C45:P45)=0,"",IFERROR(H45/G45,0)) | Y45: =IF(COUNT(C45:P45)=0,"",IFERROR(I45/H45,0)) | Z45: =IF(COUNT(C45:P45)=0,"",IFERROR(I45/G45,0)) | AA45: =IF(COUNT(C45:P45)=0,"",IFERROR(C45/I45,0)) | AB45: =IF(COUNT(C45:P45)=0,"",IFERROR(J45/I45,0)) | AC45: =IF(COUNT(C45:P45)=0,"",IFERROR(K45/I45,0)) | AD45: =IF(COUNT(C45:P45)=0,"",IFERROR(L45/I45,0)) | AE45: =IF(COUNT(C45:P45)=0,"",IFERROR(P45/I45,0)) | AF45: =IF(COUNT(C45:P45)=0,"",IFERROR(I45*Config!$C$7+J45*Config!$C$8+K45*Config!$C$9+L45*Config!$C$10+M45*Config!$C$11+N45*Config!$C$12+O45*Config!$C$13+P45*Config!$C$14,0)) | AG45: =IF(COUNT(C45:P45)=0,"",IFERROR(AF45/I45,0)) | AH45: =IF(COUNT(C45:P45)=0,"",IFERROR(AF45*(1-Config!$C$15-Config!$C$16-Config!$C$17),0)) | AI45: =IF(COUNT(C45:P45)=0,"",IFERROR(AH45-C45-Config!$C$18,0)) | AJ45: =IF(COUNT(C45:P45)=0,"",IFERROR(AH45/C45,0)) | AK45: =IF(COUNT(C45:P45)=0,"",IFERROR(AI45/G45,0)) | AL45: =IF(COUNT(C45:P45)=0,"",IFERROR(AK45/V45,0)) | AM45: =IF(COUNT(C45:P45)=0,"",IFERROR(AI45/I45,0)) | AN45: =IF(COUNT(C45:P45)=0,"",IFERROR(AH45/I45-AA45,0))
A46: =Config!$C$6+40 | B46: =INT((A46-Config!$C$6)/7)+1 | Q46: =IF(COUNT(C46:P46)=0,"",IFERROR(C46/D46*1000,0)) | R46: =IF(COUNT(C46:P46)=0,"",IFERROR(D46/E46,0)) | S46: =IF(COUNT(C46:P46)=0,"",IFERROR(F46/D46,0)) | T46: =IF(COUNT(C46:P46)=0,"",IFERROR(C46/F46,0)) | U46: =IF(COUNT(C46:P46)=0,"",IFERROR(G46/F46,0)) | V46: =IF(COUNT(C46:P46)=0,"",IFERROR(C46/G46,0)) | W46: =IF(COUNT(C46:P46)=0,"",IFERROR(G46/D46*1000,0)) | X46: =IF(COUNT(C46:P46)=0,"",IFERROR(H46/G46,0)) | Y46: =IF(COUNT(C46:P46)=0,"",IFERROR(I46/H46,0)) | Z46: =IF(COUNT(C46:P46)=0,"",IFERROR(I46/G46,0)) | AA46: =IF(COUNT(C46:P46)=0,"",IFERROR(C46/I46,0)) | AB46: =IF(COUNT(C46:P46)=0,"",IFERROR(J46/I46,0)) | AC46: =IF(COUNT(C46:P46)=0,"",IFERROR(K46/I46,0)) | AD46: =IF(COUNT(C46:P46)=0,"",IFERROR(L46/I46,0)) | AE46: =IF(COUNT(C46:P46)=0,"",IFERROR(P46/I46,0)) | AF46: =IF(COUNT(C46:P46)=0,"",IFERROR(I46*Config!$C$7+J46*Config!$C$8+K46*Config!$C$9+L46*Config!$C$10+M46*Config!$C$11+N46*Config!$C$12+O46*Config!$C$13+P46*Config!$C$14,0)) | AG46: =IF(COUNT(C46:P46)=0,"",IFERROR(AF46/I46,0)) | AH46: =IF(COUNT(C46:P46)=0,"",IFERROR(AF46*(1-Config!$C$15-Config!$C$16-Config!$C$17),0)) | AI46: =IF(COUNT(C46:P46)=0,"",IFERROR(AH46-C46-Config!$C$18,0)) | AJ46: =IF(COUNT(C46:P46)=0,"",IFERROR(AH46/C46,0)) | AK46: =IF(COUNT(C46:P46)=0,"",IFERROR(AI46/G46,0)) | AL46: =IF(COUNT(C46:P46)=0,"",IFERROR(AK46/V46,0)) | AM46: =IF(COUNT(C46:P46)=0,"",IFERROR(AI46/I46,0)) | AN46: =IF(COUNT(C46:P46)=0,"",IFERROR(AH46/I46-AA46,0))
A47: =Config!$C$6+41 | B47: =INT((A47-Config!$C$6)/7)+1 | Q47: =IF(COUNT(C47:P47)=0,"",IFERROR(C47/D47*1000,0)) | R47: =IF(COUNT(C47:P47)=0,"",IFERROR(D47/E47,0)) | S47: =IF(COUNT(C47:P47)=0,"",IFERROR(F47/D47,0)) | T47: =IF(COUNT(C47:P47)=0,"",IFERROR(C47/F47,0)) | U47: =IF(COUNT(C47:P47)=0,"",IFERROR(G47/F47,0)) | V47: =IF(COUNT(C47:P47)=0,"",IFERROR(C47/G47,0)) | W47: =IF(COUNT(C47:P47)=0,"",IFERROR(G47/D47*1000,0)) | X47: =IF(COUNT(C47:P47)=0,"",IFERROR(H47/G47,0)) | Y47: =IF(COUNT(C47:P47)=0,"",IFERROR(I47/H47,0)) | Z47: =IF(COUNT(C47:P47)=0,"",IFERROR(I47/G47,0)) | AA47: =IF(COUNT(C47:P47)=0,"",IFERROR(C47/I47,0)) | AB47: =IF(COUNT(C47:P47)=0,"",IFERROR(J47/I47,0)) | AC47: =IF(COUNT(C47:P47)=0,"",IFERROR(K47/I47,0)) | AD47: =IF(COUNT(C47:P47)=0,"",IFERROR(L47/I47,0)) | AE47: =IF(COUNT(C47:P47)=0,"",IFERROR(P47/I47,0)) | AF47: =IF(COUNT(C47:P47)=0,"",IFERROR(I47*Config!$C$7+J47*Config!$C$8+K47*Config!$C$9+L47*Config!$C$10+M47*Config!$C$11+N47*Config!$C$12+O47*Config!$C$13+P47*Config!$C$14,0)) | AG47: =IF(COUNT(C47:P47)=0,"",IFERROR(AF47/I47,0)) | AH47: =IF(COUNT(C47:P47)=0,"",IFERROR(AF47*(1-Config!$C$15-Config!$C$16-Config!$C$17),0)) | AI47: =IF(COUNT(C47:P47)=0,"",IFERROR(AH47-C47-Config!$C$18,0)) | AJ47: =IF(COUNT(C47:P47)=0,"",IFERROR(AH47/C47,0)) | AK47: =IF(COUNT(C47:P47)=0,"",IFERROR(AI47/G47,0)) | AL47: =IF(COUNT(C47:P47)=0,"",IFERROR(AK47/V47,0)) | AM47: =IF(COUNT(C47:P47)=0,"",IFERROR(AI47/I47,0)) | AN47: =IF(COUNT(C47:P47)=0,"",IFERROR(AH47/I47-AA47,0))
A48: =Config!$C$6+42 | B48: =INT((A48-Config!$C$6)/7)+1 | Q48: =IF(COUNT(C48:P48)=0,"",IFERROR(C48/D48*1000,0)) | R48: =IF(COUNT(C48:P48)=0,"",IFERROR(D48/E48,0)) | S48: =IF(COUNT(C48:P48)=0,"",IFERROR(F48/D48,0)) | T48: =IF(COUNT(C48:P48)=0,"",IFERROR(C48/F48,0)) | U48: =IF(COUNT(C48:P48)=0,"",IFERROR(G48/F48,0)) | V48: =IF(COUNT(C48:P48)=0,"",IFERROR(C48/G48,0)) | W48: =IF(COUNT(C48:P48)=0,"",IFERROR(G48/D48*1000,0)) | X48: =IF(COUNT(C48:P48)=0,"",IFERROR(H48/G48,0)) | Y48: =IF(COUNT(C48:P48)=0,"",IFERROR(I48/H48,0)) | Z48: =IF(COUNT(C48:P48)=0,"",IFERROR(I48/G48,0)) | AA48: =IF(COUNT(C48:P48)=0,"",IFERROR(C48/I48,0)) | AB48: =IF(COUNT(C48:P48)=0,"",IFERROR(J48/I48,0)) | AC48: =IF(COUNT(C48:P48)=0,"",IFERROR(K48/I48,0)) | AD48: =IF(COUNT(C48:P48)=0,"",IFERROR(L48/I48,0)) | AE48: =IF(COUNT(C48:P48)=0,"",IFERROR(P48/I48,0)) | AF48: =IF(COUNT(C48:P48)=0,"",IFERROR(I48*Config!$C$7+J48*Config!$C$8+K48*Config!$C$9+L48*Config!$C$10+M48*Config!$C$11+N48*Config!$C$12+O48*Config!$C$13+P48*Config!$C$14,0)) | AG48: =IF(COUNT(C48:P48)=0,"",IFERROR(AF48/I48,0)) | AH48: =IF(COUNT(C48:P48)=0,"",IFERROR(AF48*(1-Config!$C$15-Config!$C$16-Config!$C$17),0)) | AI48: =IF(COUNT(C48:P48)=0,"",IFERROR(AH48-C48-Config!$C$18,0)) | AJ48: =IF(COUNT(C48:P48)=0,"",IFERROR(AH48/C48,0)) | AK48: =IF(COUNT(C48:P48)=0,"",IFERROR(AI48/G48,0)) | AL48: =IF(COUNT(C48:P48)=0,"",IFERROR(AK48/V48,0)) | AM48: =IF(COUNT(C48:P48)=0,"",IFERROR(AI48/I48,0)) | AN48: =IF(COUNT(C48:P48)=0,"",IFERROR(AH48/I48-AA48,0))
A49: =Config!$C$6+43 | B49: =INT((A49-Config!$C$6)/7)+1 | Q49: =IF(COUNT(C49:P49)=0,"",IFERROR(C49/D49*1000,0)) | R49: =IF(COUNT(C49:P49)=0,"",IFERROR(D49/E49,0)) | S49: =IF(COUNT(C49:P49)=0,"",IFERROR(F49/D49,0)) | T49: =IF(COUNT(C49:P49)=0,"",IFERROR(C49/F49,0)) | U49: =IF(COUNT(C49:P49)=0,"",IFERROR(G49/F49,0)) | V49: =IF(COUNT(C49:P49)=0,"",IFERROR(C49/G49,0)) | W49: =IF(COUNT(C49:P49)=0,"",IFERROR(G49/D49*1000,0)) | X49: =IF(COUNT(C49:P49)=0,"",IFERROR(H49/G49,0)) | Y49: =IF(COUNT(C49:P49)=0,"",IFERROR(I49/H49,0)) | Z49: =IF(COUNT(C49:P49)=0,"",IFERROR(I49/G49,0)) | AA49: =IF(COUNT(C49:P49)=0,"",IFERROR(C49/I49,0)) | AB49: =IF(COUNT(C49:P49)=0,"",IFERROR(J49/I49,0)) | AC49: =IF(COUNT(C49:P49)=0,"",IFERROR(K49/I49,0)) | AD49: =IF(COUNT(C49:P49)=0,"",IFERROR(L49/I49,0)) | AE49: =IF(COUNT(C49:P49)=0,"",IFERROR(P49/I49,0)) | AF49: =IF(COUNT(C49:P49)=0,"",IFERROR(I49*Config!$C$7+J49*Config!$C$8+K49*Config!$C$9+L49*Config!$C$10+M49*Config!$C$11+N49*Config!$C$12+O49*Config!$C$13+P49*Config!$C$14,0)) | AG49: =IF(COUNT(C49:P49)=0,"",IFERROR(AF49/I49,0)) | AH49: =IF(COUNT(C49:P49)=0,"",IFERROR(AF49*(1-Config!$C$15-Config!$C$16-Config!$C$17),0)) | AI49: =IF(COUNT(C49:P49)=0,"",IFERROR(AH49-C49-Config!$C$18,0)) | AJ49: =IF(COUNT(C49:P49)=0,"",IFERROR(AH49/C49,0)) | AK49: =IF(COUNT(C49:P49)=0,"",IFERROR(AI49/G49,0)) | AL49: =IF(COUNT(C49:P49)=0,"",IFERROR(AK49/V49,0)) | AM49: =IF(COUNT(C49:P49)=0,"",IFERROR(AI49/I49,0)) | AN49: =IF(COUNT(C49:P49)=0,"",IFERROR(AH49/I49-AA49,0))
A50: =Config!$C$6+44 | B50: =INT((A50-Config!$C$6)/7)+1 | Q50: =IF(COUNT(C50:P50)=0,"",IFERROR(C50/D50*1000,0)) | R50: =IF(COUNT(C50:P50)=0,"",IFERROR(D50/E50,0)) | S50: =IF(COUNT(C50:P50)=0,"",IFERROR(F50/D50,0)) | T50: =IF(COUNT(C50:P50)=0,"",IFERROR(C50/F50,0)) | U50: =IF(COUNT(C50:P50)=0,"",IFERROR(G50/F50,0)) | V50: =IF(COUNT(C50:P50)=0,"",IFERROR(C50/G50,0)) | W50: =IF(COUNT(C50:P50)=0,"",IFERROR(G50/D50*1000,0)) | X50: =IF(COUNT(C50:P50)=0,"",IFERROR(H50/G50,0)) | Y50: =IF(COUNT(C50:P50)=0,"",IFERROR(I50/H50,0)) | Z50: =IF(COUNT(C50:P50)=0,"",IFERROR(I50/G50,0)) | AA50: =IF(COUNT(C50:P50)=0,"",IFERROR(C50/I50,0)) | AB50: =IF(COUNT(C50:P50)=0,"",IFERROR(J50/I50,0)) | AC50: =IF(COUNT(C50:P50)=0,"",IFERROR(K50/I50,0)) | AD50: =IF(COUNT(C50:P50)=0,"",IFERROR(L50/I50,0)) | AE50: =IF(COUNT(C50:P50)=0,"",IFERROR(P50/I50,0)) | AF50: =IF(COUNT(C50:P50)=0,"",IFERROR(I50*Config!$C$7+J50*Config!$C$8+K50*Config!$C$9+L50*Config!$C$10+M50*Config!$C$11+N50*Config!$C$12+O50*Config!$C$13+P50*Config!$C$14,0)) | AG50: =IF(COUNT(C50:P50)=0,"",IFERROR(AF50/I50,0)) | AH50: =IF(COUNT(C50:P50)=0,"",IFERROR(AF50*(1-Config!$C$15-Config!$C$16-Config!$C$17),0)) | AI50: =IF(COUNT(C50:P50)=0,"",IFERROR(AH50-C50-Config!$C$18,0)) | AJ50: =IF(COUNT(C50:P50)=0,"",IFERROR(AH50/C50,0)) | AK50: =IF(COUNT(C50:P50)=0,"",IFERROR(AI50/G50,0)) | AL50: =IF(COUNT(C50:P50)=0,"",IFERROR(AK50/V50,0)) | AM50: =IF(COUNT(C50:P50)=0,"",IFERROR(AI50/I50,0)) | AN50: =IF(COUNT(C50:P50)=0,"",IFERROR(AH50/I50-AA50,0))
A51: =Config!$C$6+45 | B51: =INT((A51-Config!$C$6)/7)+1 | Q51: =IF(COUNT(C51:P51)=0,"",IFERROR(C51/D51*1000,0)) | R51: =IF(COUNT(C51:P51)=0,"",IFERROR(D51/E51,0)) | S51: =IF(COUNT(C51:P51)=0,"",IFERROR(F51/D51,0)) | T51: =IF(COUNT(C51:P51)=0,"",IFERROR(C51/F51,0)) | U51: =IF(COUNT(C51:P51)=0,"",IFERROR(G51/F51,0)) | V51: =IF(COUNT(C51:P51)=0,"",IFERROR(C51/G51,0)) | W51: =IF(COUNT(C51:P51)=0,"",IFERROR(G51/D51*1000,0)) | X51: =IF(COUNT(C51:P51)=0,"",IFERROR(H51/G51,0)) | Y51: =IF(COUNT(C51:P51)=0,"",IFERROR(I51/H51,0)) | Z51: =IF(COUNT(C51:P51)=0,"",IFERROR(I51/G51,0)) | AA51: =IF(COUNT(C51:P51)=0,"",IFERROR(C51/I51,0)) | AB51: =IF(COUNT(C51:P51)=0,"",IFERROR(J51/I51,0)) | AC51: =IF(COUNT(C51:P51)=0,"",IFERROR(K51/I51,0)) | AD51: =IF(COUNT(C51:P51)=0,"",IFERROR(L51/I51,0)) | AE51: =IF(COUNT(C51:P51)=0,"",IFERROR(P51/I51,0)) | AF51: =IF(COUNT(C51:P51)=0,"",IFERROR(I51*Config!$C$7+J51*Config!$C$8+K51*Config!$C$9+L51*Config!$C$10+M51*Config!$C$11+N51*Config!$C$12+O51*Config!$C$13+P51*Config!$C$14,0)) | AG51: =IF(COUNT(C51:P51)=0,"",IFERROR(AF51/I51,0)) | AH51: =IF(COUNT(C51:P51)=0,"",IFERROR(AF51*(1-Config!$C$15-Config!$C$16-Config!$C$17),0)) | AI51: =IF(COUNT(C51:P51)=0,"",IFERROR(AH51-C51-Config!$C$18,0)) | AJ51: =IF(COUNT(C51:P51)=0,"",IFERROR(AH51/C51,0)) | AK51: =IF(COUNT(C51:P51)=0,"",IFERROR(AI51/G51,0)) | AL51: =IF(COUNT(C51:P51)=0,"",IFERROR(AK51/V51,0)) | AM51: =IF(COUNT(C51:P51)=0,"",IFERROR(AI51/I51,0)) | AN51: =IF(COUNT(C51:P51)=0,"",IFERROR(AH51/I51-AA51,0))
A52: =Config!$C$6+46 | B52: =INT((A52-Config!$C$6)/7)+1 | Q52: =IF(COUNT(C52:P52)=0,"",IFERROR(C52/D52*1000,0)) | R52: =IF(COUNT(C52:P52)=0,"",IFERROR(D52/E52,0)) | S52: =IF(COUNT(C52:P52)=0,"",IFERROR(F52/D52,0)) | T52: =IF(COUNT(C52:P52)=0,"",IFERROR(C52/F52,0)) | U52: =IF(COUNT(C52:P52)=0,"",IFERROR(G52/F52,0)) | V52: =IF(COUNT(C52:P52)=0,"",IFERROR(C52/G52,0)) | W52: =IF(COUNT(C52:P52)=0,"",IFERROR(G52/D52*1000,0)) | X52: =IF(COUNT(C52:P52)=0,"",IFERROR(H52/G52,0)) | Y52: =IF(COUNT(C52:P52)=0,"",IFERROR(I52/H52,0)) | Z52: =IF(COUNT(C52:P52)=0,"",IFERROR(I52/G52,0)) | AA52: =IF(COUNT(C52:P52)=0,"",IFERROR(C52/I52,0)) | AB52: =IF(COUNT(C52:P52)=0,"",IFERROR(J52/I52,0)) | AC52: =IF(COUNT(C52:P52)=0,"",IFERROR(K52/I52,0)) | AD52: =IF(COUNT(C52:P52)=0,"",IFERROR(L52/I52,0)) | AE52: =IF(COUNT(C52:P52)=0,"",IFERROR(P52/I52,0)) | AF52: =IF(COUNT(C52:P52)=0,"",IFERROR(I52*Config!$C$7+J52*Config!$C$8+K52*Config!$C$9+L52*Config!$C$10+M52*Config!$C$11+N52*Config!$C$12+O52*Config!$C$13+P52*Config!$C$14,0)) | AG52: =IF(COUNT(C52:P52)=0,"",IFERROR(AF52/I52,0)) | AH52: =IF(COUNT(C52:P52)=0,"",IFERROR(AF52*(1-Config!$C$15-Config!$C$16-Config!$C$17),0)) | AI52: =IF(COUNT(C52:P52)=0,"",IFERROR(AH52-C52-Config!$C$18,0)) | AJ52: =IF(COUNT(C52:P52)=0,"",IFERROR(AH52/C52,0)) | AK52: =IF(COUNT(C52:P52)=0,"",IFERROR(AI52/G52,0)) | AL52: =IF(COUNT(C52:P52)=0,"",IFERROR(AK52/V52,0)) | AM52: =IF(COUNT(C52:P52)=0,"",IFERROR(AI52/I52,0)) | AN52: =IF(COUNT(C52:P52)=0,"",IFERROR(AH52/I52-AA52,0))
A53: =Config!$C$6+47 | B53: =INT((A53-Config!$C$6)/7)+1 | Q53: =IF(COUNT(C53:P53)=0,"",IFERROR(C53/D53*1000,0)) | R53: =IF(COUNT(C53:P53)=0,"",IFERROR(D53/E53,0)) | S53: =IF(COUNT(C53:P53)=0,"",IFERROR(F53/D53,0)) | T53: =IF(COUNT(C53:P53)=0,"",IFERROR(C53/F53,0)) | U53: =IF(COUNT(C53:P53)=0,"",IFERROR(G53/F53,0)) | V53: =IF(COUNT(C53:P53)=0,"",IFERROR(C53/G53,0)) | W53: =IF(COUNT(C53:P53)=0,"",IFERROR(G53/D53*1000,0)) | X53: =IF(COUNT(C53:P53)=0,"",IFERROR(H53/G53,0)) | Y53: =IF(COUNT(C53:P53)=0,"",IFERROR(I53/H53,0)) | Z53: =IF(COUNT(C53:P53)=0,"",IFERROR(I53/G53,0)) | AA53: =IF(COUNT(C53:P53)=0,"",IFERROR(C53/I53,0)) | AB53: =IF(COUNT(C53:P53)=0,"",IFERROR(J53/I53,0)) | AC53: =IF(COUNT(C53:P53)=0,"",IFERROR(K53/I53,0)) | AD53: =IF(COUNT(C53:P53)=0,"",IFERROR(L53/I53,0)) | AE53: =IF(COUNT(C53:P53)=0,"",IFERROR(P53/I53,0)) | AF53: =IF(COUNT(C53:P53)=0,"",IFERROR(I53*Config!$C$7+J53*Config!$C$8+K53*Config!$C$9+L53*Config!$C$10+M53*Config!$C$11+N53*Config!$C$12+O53*Config!$C$13+P53*Config!$C$14,0)) | AG53: =IF(COUNT(C53:P53)=0,"",IFERROR(AF53/I53,0)) | AH53: =IF(COUNT(C53:P53)=0,"",IFERROR(AF53*(1-Config!$C$15-Config!$C$16-Config!$C$17),0)) | AI53: =IF(COUNT(C53:P53)=0,"",IFERROR(AH53-C53-Config!$C$18,0)) | AJ53: =IF(COUNT(C53:P53)=0,"",IFERROR(AH53/C53,0)) | AK53: =IF(COUNT(C53:P53)=0,"",IFERROR(AI53/G53,0)) | AL53: =IF(COUNT(C53:P53)=0,"",IFERROR(AK53/V53,0)) | AM53: =IF(COUNT(C53:P53)=0,"",IFERROR(AI53/I53,0)) | AN53: =IF(COUNT(C53:P53)=0,"",IFERROR(AH53/I53-AA53,0))
A54: =Config!$C$6+48 | B54: =INT((A54-Config!$C$6)/7)+1 | Q54: =IF(COUNT(C54:P54)=0,"",IFERROR(C54/D54*1000,0)) | R54: =IF(COUNT(C54:P54)=0,"",IFERROR(D54/E54,0)) | S54: =IF(COUNT(C54:P54)=0,"",IFERROR(F54/D54,0)) | T54: =IF(COUNT(C54:P54)=0,"",IFERROR(C54/F54,0)) | U54: =IF(COUNT(C54:P54)=0,"",IFERROR(G54/F54,0)) | V54: =IF(COUNT(C54:P54)=0,"",IFERROR(C54/G54,0)) | W54: =IF(COUNT(C54:P54)=0,"",IFERROR(G54/D54*1000,0)) | X54: =IF(COUNT(C54:P54)=0,"",IFERROR(H54/G54,0)) | Y54: =IF(COUNT(C54:P54)=0,"",IFERROR(I54/H54,0)) | Z54: =IF(COUNT(C54:P54)=0,"",IFERROR(I54/G54,0)) | AA54: =IF(COUNT(C54:P54)=0,"",IFERROR(C54/I54,0)) | AB54: =IF(COUNT(C54:P54)=0,"",IFERROR(J54/I54,0)) | AC54: =IF(COUNT(C54:P54)=0,"",IFERROR(K54/I54,0)) | AD54: =IF(COUNT(C54:P54)=0,"",IFERROR(L54/I54,0)) | AE54: =IF(COUNT(C54:P54)=0,"",IFERROR(P54/I54,0)) | AF54: =IF(COUNT(C54:P54)=0,"",IFERROR(I54*Config!$C$7+J54*Config!$C$8+K54*Config!$C$9+L54*Config!$C$10+M54*Config!$C$11+N54*Config!$C$12+O54*Config!$C$13+P54*Config!$C$14,0)) | AG54: =IF(COUNT(C54:P54)=0,"",IFERROR(AF54/I54,0)) | AH54: =IF(COUNT(C54:P54)=0,"",IFERROR(AF54*(1-Config!$C$15-Config!$C$16-Config!$C$17),0)) | AI54: =IF(COUNT(C54:P54)=0,"",IFERROR(AH54-C54-Config!$C$18,0)) | AJ54: =IF(COUNT(C54:P54)=0,"",IFERROR(AH54/C54,0)) | AK54: =IF(COUNT(C54:P54)=0,"",IFERROR(AI54/G54,0)) | AL54: =IF(COUNT(C54:P54)=0,"",IFERROR(AK54/V54,0)) | AM54: =IF(COUNT(C54:P54)=0,"",IFERROR(AI54/I54,0)) | AN54: =IF(COUNT(C54:P54)=0,"",IFERROR(AH54/I54-AA54,0))
A55: =Config!$C$6+49 | B55: =INT((A55-Config!$C$6)/7)+1 | Q55: =IF(COUNT(C55:P55)=0,"",IFERROR(C55/D55*1000,0)) | R55: =IF(COUNT(C55:P55)=0,"",IFERROR(D55/E55,0)) | S55: =IF(COUNT(C55:P55)=0,"",IFERROR(F55/D55,0)) | T55: =IF(COUNT(C55:P55)=0,"",IFERROR(C55/F55,0)) | U55: =IF(COUNT(C55:P55)=0,"",IFERROR(G55/F55,0)) | V55: =IF(COUNT(C55:P55)=0,"",IFERROR(C55/G55,0)) | W55: =IF(COUNT(C55:P55)=0,"",IFERROR(G55/D55*1000,0)) | X55: =IF(COUNT(C55:P55)=0,"",IFERROR(H55/G55,0)) | Y55: =IF(COUNT(C55:P55)=0,"",IFERROR(I55/H55,0)) | Z55: =IF(COUNT(C55:P55)=0,"",IFERROR(I55/G55,0)) | AA55: =IF(COUNT(C55:P55)=0,"",IFERROR(C55/I55,0)) | AB55: =IF(COUNT(C55:P55)=0,"",IFERROR(J55/I55,0)) | AC55: =IF(COUNT(C55:P55)=0,"",IFERROR(K55/I55,0)) | AD55: =IF(COUNT(C55:P55)=0,"",IFERROR(L55/I55,0)) | AE55: =IF(COUNT(C55:P55)=0,"",IFERROR(P55/I55,0)) | AF55: =IF(COUNT(C55:P55)=0,"",IFERROR(I55*Config!$C$7+J55*Config!$C$8+K55*Config!$C$9+L55*Config!$C$10+M55*Config!$C$11+N55*Config!$C$12+O55*Config!$C$13+P55*Config!$C$14,0)) | AG55: =IF(COUNT(C55:P55)=0,"",IFERROR(AF55/I55,0)) | AH55: =IF(COUNT(C55:P55)=0,"",IFERROR(AF55*(1-Config!$C$15-Config!$C$16-Config!$C$17),0)) | AI55: =IF(COUNT(C55:P55)=0,"",IFERROR(AH55-C55-Config!$C$18,0)) | AJ55: =IF(COUNT(C55:P55)=0,"",IFERROR(AH55/C55,0)) | AK55: =IF(COUNT(C55:P55)=0,"",IFERROR(AI55/G55,0)) | AL55: =IF(COUNT(C55:P55)=0,"",IFERROR(AK55/V55,0)) | AM55: =IF(COUNT(C55:P55)=0,"",IFERROR(AI55/I55,0)) | AN55: =IF(COUNT(C55:P55)=0,"",IFERROR(AH55/I55-AA55,0))
A56: =Config!$C$6+50 | B56: =INT((A56-Config!$C$6)/7)+1 | Q56: =IF(COUNT(C56:P56)=0,"",IFERROR(C56/D56*1000,0)) | R56: =IF(COUNT(C56:P56)=0,"",IFERROR(D56/E56,0)) | S56: =IF(COUNT(C56:P56)=0,"",IFERROR(F56/D56,0)) | T56: =IF(COUNT(C56:P56)=0,"",IFERROR(C56/F56,0)) | U56: =IF(COUNT(C56:P56)=0,"",IFERROR(G56/F56,0)) | V56: =IF(COUNT(C56:P56)=0,"",IFERROR(C56/G56,0)) | W56: =IF(COUNT(C56:P56)=0,"",IFERROR(G56/D56*1000,0)) | X56: =IF(COUNT(C56:P56)=0,"",IFERROR(H56/G56,0)) | Y56: =IF(COUNT(C56:P56)=0,"",IFERROR(I56/H56,0)) | Z56: =IF(COUNT(C56:P56)=0,"",IFERROR(I56/G56,0)) | AA56: =IF(COUNT(C56:P56)=0,"",IFERROR(C56/I56,0)) | AB56: =IF(COUNT(C56:P56)=0,"",IFERROR(J56/I56,0)) | AC56: =IF(COUNT(C56:P56)=0,"",IFERROR(K56/I56,0)) | AD56: =IF(COUNT(C56:P56)=0,"",IFERROR(L56/I56,0)) | AE56: =IF(COUNT(C56:P56)=0,"",IFERROR(P56/I56,0)) | AF56: =IF(COUNT(C56:P56)=0,"",IFERROR(I56*Config!$C$7+J56*Config!$C$8+K56*Config!$C$9+L56*Config!$C$10+M56*Config!$C$11+N56*Config!$C$12+O56*Config!$C$13+P56*Config!$C$14,0)) | AG56: =IF(COUNT(C56:P56)=0,"",IFERROR(AF56/I56,0)) | AH56: =IF(COUNT(C56:P56)=0,"",IFERROR(AF56*(1-Config!$C$15-Config!$C$16-Config!$C$17),0)) | AI56: =IF(COUNT(C56:P56)=0,"",IFERROR(AH56-C56-Config!$C$18,0)) | AJ56: =IF(COUNT(C56:P56)=0,"",IFERROR(AH56/C56,0)) | AK56: =IF(COUNT(C56:P56)=0,"",IFERROR(AI56/G56,0)) | AL56: =IF(COUNT(C56:P56)=0,"",IFERROR(AK56/V56,0)) | AM56: =IF(COUNT(C56:P56)=0,"",IFERROR(AI56/I56,0)) | AN56: =IF(COUNT(C56:P56)=0,"",IFERROR(AH56/I56-AA56,0))
A57: =Config!$C$6+51 | B57: =INT((A57-Config!$C$6)/7)+1 | Q57: =IF(COUNT(C57:P57)=0,"",IFERROR(C57/D57*1000,0)) | R57: =IF(COUNT(C57:P57)=0,"",IFERROR(D57/E57,0)) | S57: =IF(COUNT(C57:P57)=0,"",IFERROR(F57/D57,0)) | T57: =IF(COUNT(C57:P57)=0,"",IFERROR(C57/F57,0)) | U57: =IF(COUNT(C57:P57)=0,"",IFERROR(G57/F57,0)) | V57: =IF(COUNT(C57:P57)=0,"",IFERROR(C57/G57,0)) | W57: =IF(COUNT(C57:P57)=0,"",IFERROR(G57/D57*1000,0)) | X57: =IF(COUNT(C57:P57)=0,"",IFERROR(H57/G57,0)) | Y57: =IF(COUNT(C57:P57)=0,"",IFERROR(I57/H57,0)) | Z57: =IF(COUNT(C57:P57)=0,"",IFERROR(I57/G57,0)) | AA57: =IF(COUNT(C57:P57)=0,"",IFERROR(C57/I57,0)) | AB57: =IF(COUNT(C57:P57)=0,"",IFERROR(J57/I57,0)) | AC57: =IF(COUNT(C57:P57)=0,"",IFERROR(K57/I57,0)) | AD57: =IF(COUNT(C57:P57)=0,"",IFERROR(L57/I57,0)) | AE57: =IF(COUNT(C57:P57)=0,"",IFERROR(P57/I57,0)) | AF57: =IF(COUNT(C57:P57)=0,"",IFERROR(I57*Config!$C$7+J57*Config!$C$8+K57*Config!$C$9+L57*Config!$C$10+M57*Config!$C$11+N57*Config!$C$12+O57*Config!$C$13+P57*Config!$C$14,0)) | AG57: =IF(COUNT(C57:P57)=0,"",IFERROR(AF57/I57,0)) | AH57: =IF(COUNT(C57:P57)=0,"",IFERROR(AF57*(1-Config!$C$15-Config!$C$16-Config!$C$17),0)) | AI57: =IF(COUNT(C57:P57)=0,"",IFERROR(AH57-C57-Config!$C$18,0)) | AJ57: =IF(COUNT(C57:P57)=0,"",IFERROR(AH57/C57,0)) | AK57: =IF(COUNT(C57:P57)=0,"",IFERROR(AI57/G57,0)) | AL57: =IF(COUNT(C57:P57)=0,"",IFERROR(AK57/V57,0)) | AM57: =IF(COUNT(C57:P57)=0,"",IFERROR(AI57/I57,0)) | AN57: =IF(COUNT(C57:P57)=0,"",IFERROR(AH57/I57-AA57,0))
A58: =Config!$C$6+52 | B58: =INT((A58-Config!$C$6)/7)+1 | Q58: =IF(COUNT(C58:P58)=0,"",IFERROR(C58/D58*1000,0)) | R58: =IF(COUNT(C58:P58)=0,"",IFERROR(D58/E58,0)) | S58: =IF(COUNT(C58:P58)=0,"",IFERROR(F58/D58,0)) | T58: =IF(COUNT(C58:P58)=0,"",IFERROR(C58/F58,0)) | U58: =IF(COUNT(C58:P58)=0,"",IFERROR(G58/F58,0)) | V58: =IF(COUNT(C58:P58)=0,"",IFERROR(C58/G58,0)) | W58: =IF(COUNT(C58:P58)=0,"",IFERROR(G58/D58*1000,0)) | X58: =IF(COUNT(C58:P58)=0,"",IFERROR(H58/G58,0)) | Y58: =IF(COUNT(C58:P58)=0,"",IFERROR(I58/H58,0)) | Z58: =IF(COUNT(C58:P58)=0,"",IFERROR(I58/G58,0)) | AA58: =IF(COUNT(C58:P58)=0,"",IFERROR(C58/I58,0)) | AB58: =IF(COUNT(C58:P58)=0,"",IFERROR(J58/I58,0)) | AC58: =IF(COUNT(C58:P58)=0,"",IFERROR(K58/I58,0)) | AD58: =IF(COUNT(C58:P58)=0,"",IFERROR(L58/I58,0)) | AE58: =IF(COUNT(C58:P58)=0,"",IFERROR(P58/I58,0)) | AF58: =IF(COUNT(C58:P58)=0,"",IFERROR(I58*Config!$C$7+J58*Config!$C$8+K58*Config!$C$9+L58*Config!$C$10+M58*Config!$C$11+N58*Config!$C$12+O58*Config!$C$13+P58*Config!$C$14,0)) | AG58: =IF(COUNT(C58:P58)=0,"",IFERROR(AF58/I58,0)) | AH58: =IF(COUNT(C58:P58)=0,"",IFERROR(AF58*(1-Config!$C$15-Config!$C$16-Config!$C$17),0)) | AI58: =IF(COUNT(C58:P58)=0,"",IFERROR(AH58-C58-Config!$C$18,0)) | AJ58: =IF(COUNT(C58:P58)=0,"",IFERROR(AH58/C58,0)) | AK58: =IF(COUNT(C58:P58)=0,"",IFERROR(AI58/G58,0)) | AL58: =IF(COUNT(C58:P58)=0,"",IFERROR(AK58/V58,0)) | AM58: =IF(COUNT(C58:P58)=0,"",IFERROR(AI58/I58,0)) | AN58: =IF(COUNT(C58:P58)=0,"",IFERROR(AH58/I58-AA58,0))
A59: =Config!$C$6+53 | B59: =INT((A59-Config!$C$6)/7)+1 | Q59: =IF(COUNT(C59:P59)=0,"",IFERROR(C59/D59*1000,0)) | R59: =IF(COUNT(C59:P59)=0,"",IFERROR(D59/E59,0)) | S59: =IF(COUNT(C59:P59)=0,"",IFERROR(F59/D59,0)) | T59: =IF(COUNT(C59:P59)=0,"",IFERROR(C59/F59,0)) | U59: =IF(COUNT(C59:P59)=0,"",IFERROR(G59/F59,0)) | V59: =IF(COUNT(C59:P59)=0,"",IFERROR(C59/G59,0)) | W59: =IF(COUNT(C59:P59)=0,"",IFERROR(G59/D59*1000,0)) | X59: =IF(COUNT(C59:P59)=0,"",IFERROR(H59/G59,0)) | Y59: =IF(COUNT(C59:P59)=0,"",IFERROR(I59/H59,0)) | Z59: =IF(COUNT(C59:P59)=0,"",IFERROR(I59/G59,0)) | AA59: =IF(COUNT(C59:P59)=0,"",IFERROR(C59/I59,0)) | AB59: =IF(COUNT(C59:P59)=0,"",IFERROR(J59/I59,0)) | AC59: =IF(COUNT(C59:P59)=0,"",IFERROR(K59/I59,0)) | AD59: =IF(COUNT(C59:P59)=0,"",IFERROR(L59/I59,0)) | AE59: =IF(COUNT(C59:P59)=0,"",IFERROR(P59/I59,0)) | AF59: =IF(COUNT(C59:P59)=0,"",IFERROR(I59*Config!$C$7+J59*Config!$C$8+K59*Config!$C$9+L59*Config!$C$10+M59*Config!$C$11+N59*Config!$C$12+O59*Config!$C$13+P59*Config!$C$14,0)) | AG59: =IF(COUNT(C59:P59)=0,"",IFERROR(AF59/I59,0)) | AH59: =IF(COUNT(C59:P59)=0,"",IFERROR(AF59*(1-Config!$C$15-Config!$C$16-Config!$C$17),0)) | AI59: =IF(COUNT(C59:P59)=0,"",IFERROR(AH59-C59-Config!$C$18,0)) | AJ59: =IF(COUNT(C59:P59)=0,"",IFERROR(AH59/C59,0)) | AK59: =IF(COUNT(C59:P59)=0,"",IFERROR(AI59/G59,0)) | AL59: =IF(COUNT(C59:P59)=0,"",IFERROR(AK59/V59,0)) | AM59: =IF(COUNT(C59:P59)=0,"",IFERROR(AI59/I59,0)) | AN59: =IF(COUNT(C59:P59)=0,"",IFERROR(AH59/I59-AA59,0))
A60: =Config!$C$6+54 | B60: =INT((A60-Config!$C$6)/7)+1 | Q60: =IF(COUNT(C60:P60)=0,"",IFERROR(C60/D60*1000,0)) | R60: =IF(COUNT(C60:P60)=0,"",IFERROR(D60/E60,0)) | S60: =IF(COUNT(C60:P60)=0,"",IFERROR(F60/D60,0)) | T60: =IF(COUNT(C60:P60)=0,"",IFERROR(C60/F60,0)) | U60: =IF(COUNT(C60:P60)=0,"",IFERROR(G60/F60,0)) | V60: =IF(COUNT(C60:P60)=0,"",IFERROR(C60/G60,0)) | W60: =IF(COUNT(C60:P60)=0,"",IFERROR(G60/D60*1000,0)) | X60: =IF(COUNT(C60:P60)=0,"",IFERROR(H60/G60,0)) | Y60: =IF(COUNT(C60:P60)=0,"",IFERROR(I60/H60,0)) | Z60: =IF(COUNT(C60:P60)=0,"",IFERROR(I60/G60,0)) | AA60: =IF(COUNT(C60:P60)=0,"",IFERROR(C60/I60,0)) | AB60: =IF(COUNT(C60:P60)=0,"",IFERROR(J60/I60,0)) | AC60: =IF(COUNT(C60:P60)=0,"",IFERROR(K60/I60,0)) | AD60: =IF(COUNT(C60:P60)=0,"",IFERROR(L60/I60,0)) | AE60: =IF(COUNT(C60:P60)=0,"",IFERROR(P60/I60,0)) | AF60: =IF(COUNT(C60:P60)=0,"",IFERROR(I60*Config!$C$7+J60*Config!$C$8+K60*Config!$C$9+L60*Config!$C$10+M60*Config!$C$11+N60*Config!$C$12+O60*Config!$C$13+P60*Config!$C$14,0)) | AG60: =IF(COUNT(C60:P60)=0,"",IFERROR(AF60/I60,0)) | AH60: =IF(COUNT(C60:P60)=0,"",IFERROR(AF60*(1-Config!$C$15-Config!$C$16-Config!$C$17),0)) | AI60: =IF(COUNT(C60:P60)=0,"",IFERROR(AH60-C60-Config!$C$18,0)) | AJ60: =IF(COUNT(C60:P60)=0,"",IFERROR(AH60/C60,0)) | AK60: =IF(COUNT(C60:P60)=0,"",IFERROR(AI60/G60,0)) | AL60: =IF(COUNT(C60:P60)=0,"",IFERROR(AK60/V60,0)) | AM60: =IF(COUNT(C60:P60)=0,"",IFERROR(AI60/I60,0)) | AN60: =IF(COUNT(C60:P60)=0,"",IFERROR(AH60/I60-AA60,0))
A61: =Config!$C$6+55 | B61: =INT((A61-Config!$C$6)/7)+1 | Q61: =IF(COUNT(C61:P61)=0,"",IFERROR(C61/D61*1000,0)) | R61: =IF(COUNT(C61:P61)=0,"",IFERROR(D61/E61,0)) | S61: =IF(COUNT(C61:P61)=0,"",IFERROR(F61/D61,0)) | T61: =IF(COUNT(C61:P61)=0,"",IFERROR(C61/F61,0)) | U61: =IF(COUNT(C61:P61)=0,"",IFERROR(G61/F61,0)) | V61: =IF(COUNT(C61:P61)=0,"",IFERROR(C61/G61,0)) | W61: =IF(COUNT(C61:P61)=0,"",IFERROR(G61/D61*1000,0)) | X61: =IF(COUNT(C61:P61)=0,"",IFERROR(H61/G61,0)) | Y61: =IF(COUNT(C61:P61)=0,"",IFERROR(I61/H61,0)) | Z61: =IF(COUNT(C61:P61)=0,"",IFERROR(I61/G61,0)) | AA61: =IF(COUNT(C61:P61)=0,"",IFERROR(C61/I61,0)) | AB61: =IF(COUNT(C61:P61)=0,"",IFERROR(J61/I61,0)) | AC61: =IF(COUNT(C61:P61)=0,"",IFERROR(K61/I61,0)) | AD61: =IF(COUNT(C61:P61)=0,"",IFERROR(L61/I61,0)) | AE61: =IF(COUNT(C61:P61)=0,"",IFERROR(P61/I61,0)) | AF61: =IF(COUNT(C61:P61)=0,"",IFERROR(I61*Config!$C$7+J61*Config!$C$8+K61*Config!$C$9+L61*Config!$C$10+M61*Config!$C$11+N61*Config!$C$12+O61*Config!$C$13+P61*Config!$C$14,0)) | AG61: =IF(COUNT(C61:P61)=0,"",IFERROR(AF61/I61,0)) | AH61: =IF(COUNT(C61:P61)=0,"",IFERROR(AF61*(1-Config!$C$15-Config!$C$16-Config!$C$17),0)) | AI61: =IF(COUNT(C61:P61)=0,"",IFERROR(AH61-C61-Config!$C$18,0)) | AJ61: =IF(COUNT(C61:P61)=0,"",IFERROR(AH61/C61,0)) | AK61: =IF(COUNT(C61:P61)=0,"",IFERROR(AI61/G61,0)) | AL61: =IF(COUNT(C61:P61)=0,"",IFERROR(AK61/V61,0)) | AM61: =IF(COUNT(C61:P61)=0,"",IFERROR(AI61/I61,0)) | AN61: =IF(COUNT(C61:P61)=0,"",IFERROR(AH61/I61-AA61,0))
A62: =Config!$C$6+56 | B62: =INT((A62-Config!$C$6)/7)+1 | Q62: =IF(COUNT(C62:P62)=0,"",IFERROR(C62/D62*1000,0)) | R62: =IF(COUNT(C62:P62)=0,"",IFERROR(D62/E62,0)) | S62: =IF(COUNT(C62:P62)=0,"",IFERROR(F62/D62,0)) | T62: =IF(COUNT(C62:P62)=0,"",IFERROR(C62/F62,0)) | U62: =IF(COUNT(C62:P62)=0,"",IFERROR(G62/F62,0)) | V62: =IF(COUNT(C62:P62)=0,"",IFERROR(C62/G62,0)) | W62: =IF(COUNT(C62:P62)=0,"",IFERROR(G62/D62*1000,0)) | X62: =IF(COUNT(C62:P62)=0,"",IFERROR(H62/G62,0)) | Y62: =IF(COUNT(C62:P62)=0,"",IFERROR(I62/H62,0)) | Z62: =IF(COUNT(C62:P62)=0,"",IFERROR(I62/G62,0)) | AA62: =IF(COUNT(C62:P62)=0,"",IFERROR(C62/I62,0)) | AB62: =IF(COUNT(C62:P62)=0,"",IFERROR(J62/I62,0)) | AC62: =IF(COUNT(C62:P62)=0,"",IFERROR(K62/I62,0)) | AD62: =IF(COUNT(C62:P62)=0,"",IFERROR(L62/I62,0)) | AE62: =IF(COUNT(C62:P62)=0,"",IFERROR(P62/I62,0)) | AF62: =IF(COUNT(C62:P62)=0,"",IFERROR(I62*Config!$C$7+J62*Config!$C$8+K62*Config!$C$9+L62*Config!$C$10+M62*Config!$C$11+N62*Config!$C$12+O62*Config!$C$13+P62*Config!$C$14,0)) | AG62: =IF(COUNT(C62:P62)=0,"",IFERROR(AF62/I62,0)) | AH62: =IF(COUNT(C62:P62)=0,"",IFERROR(AF62*(1-Config!$C$15-Config!$C$16-Config!$C$17),0)) | AI62: =IF(COUNT(C62:P62)=0,"",IFERROR(AH62-C62-Config!$C$18,0)) | AJ62: =IF(COUNT(C62:P62)=0,"",IFERROR(AH62/C62,0)) | AK62: =IF(COUNT(C62:P62)=0,"",IFERROR(AI62/G62,0)) | AL62: =IF(COUNT(C62:P62)=0,"",IFERROR(AK62/V62,0)) | AM62: =IF(COUNT(C62:P62)=0,"",IFERROR(AI62/I62,0)) | AN62: =IF(COUNT(C62:P62)=0,"",IFERROR(AH62/I62-AA62,0))
A63: =Config!$C$6+57 | B63: =INT((A63-Config!$C$6)/7)+1 | Q63: =IF(COUNT(C63:P63)=0,"",IFERROR(C63/D63*1000,0)) | R63: =IF(COUNT(C63:P63)=0,"",IFERROR(D63/E63,0)) | S63: =IF(COUNT(C63:P63)=0,"",IFERROR(F63/D63,0)) | T63: =IF(COUNT(C63:P63)=0,"",IFERROR(C63/F63,0)) | U63: =IF(COUNT(C63:P63)=0,"",IFERROR(G63/F63,0)) | V63: =IF(COUNT(C63:P63)=0,"",IFERROR(C63/G63,0)) | W63: =IF(COUNT(C63:P63)=0,"",IFERROR(G63/D63*1000,0)) | X63: =IF(COUNT(C63:P63)=0,"",IFERROR(H63/G63,0)) | Y63: =IF(COUNT(C63:P63)=0,"",IFERROR(I63/H63,0)) | Z63: =IF(COUNT(C63:P63)=0,"",IFERROR(I63/G63,0)) | AA63: =IF(COUNT(C63:P63)=0,"",IFERROR(C63/I63,0)) | AB63: =IF(COUNT(C63:P63)=0,"",IFERROR(J63/I63,0)) | AC63: =IF(COUNT(C63:P63)=0,"",IFERROR(K63/I63,0)) | AD63: =IF(COUNT(C63:P63)=0,"",IFERROR(L63/I63,0)) | AE63: =IF(COUNT(C63:P63)=0,"",IFERROR(P63/I63,0)) | AF63: =IF(COUNT(C63:P63)=0,"",IFERROR(I63*Config!$C$7+J63*Config!$C$8+K63*Config!$C$9+L63*Config!$C$10+M63*Config!$C$11+N63*Config!$C$12+O63*Config!$C$13+P63*Config!$C$14,0)) | AG63: =IF(COUNT(C63:P63)=0,"",IFERROR(AF63/I63,0)) | AH63: =IF(COUNT(C63:P63)=0,"",IFERROR(AF63*(1-Config!$C$15-Config!$C$16-Config!$C$17),0)) | AI63: =IF(COUNT(C63:P63)=0,"",IFERROR(AH63-C63-Config!$C$18,0)) | AJ63: =IF(COUNT(C63:P63)=0,"",IFERROR(AH63/C63,0)) | AK63: =IF(COUNT(C63:P63)=0,"",IFERROR(AI63/G63,0)) | AL63: =IF(COUNT(C63:P63)=0,"",IFERROR(AK63/V63,0)) | AM63: =IF(COUNT(C63:P63)=0,"",IFERROR(AI63/I63,0)) | AN63: =IF(COUNT(C63:P63)=0,"",IFERROR(AH63/I63-AA63,0))
A64: =Config!$C$6+58 | B64: =INT((A64-Config!$C$6)/7)+1 | Q64: =IF(COUNT(C64:P64)=0,"",IFERROR(C64/D64*1000,0)) | R64: =IF(COUNT(C64:P64)=0,"",IFERROR(D64/E64,0)) | S64: =IF(COUNT(C64:P64)=0,"",IFERROR(F64/D64,0)) | T64: =IF(COUNT(C64:P64)=0,"",IFERROR(C64/F64,0)) | U64: =IF(COUNT(C64:P64)=0,"",IFERROR(G64/F64,0)) | V64: =IF(COUNT(C64:P64)=0,"",IFERROR(C64/G64,0)) | W64: =IF(COUNT(C64:P64)=0,"",IFERROR(G64/D64*1000,0)) | X64: =IF(COUNT(C64:P64)=0,"",IFERROR(H64/G64,0)) | Y64: =IF(COUNT(C64:P64)=0,"",IFERROR(I64/H64,0)) | Z64: =IF(COUNT(C64:P64)=0,"",IFERROR(I64/G64,0)) | AA64: =IF(COUNT(C64:P64)=0,"",IFERROR(C64/I64,0)) | AB64: =IF(COUNT(C64:P64)=0,"",IFERROR(J64/I64,0)) | AC64: =IF(COUNT(C64:P64)=0,"",IFERROR(K64/I64,0)) | AD64: =IF(COUNT(C64:P64)=0,"",IFERROR(L64/I64,0)) | AE64: =IF(COUNT(C64:P64)=0,"",IFERROR(P64/I64,0)) | AF64: =IF(COUNT(C64:P64)=0,"",IFERROR(I64*Config!$C$7+J64*Config!$C$8+K64*Config!$C$9+L64*Config!$C$10+M64*Config!$C$11+N64*Config!$C$12+O64*Config!$C$13+P64*Config!$C$14,0)) | AG64: =IF(COUNT(C64:P64)=0,"",IFERROR(AF64/I64,0)) | AH64: =IF(COUNT(C64:P64)=0,"",IFERROR(AF64*(1-Config!$C$15-Config!$C$16-Config!$C$17),0)) | AI64: =IF(COUNT(C64:P64)=0,"",IFERROR(AH64-C64-Config!$C$18,0)) | AJ64: =IF(COUNT(C64:P64)=0,"",IFERROR(AH64/C64,0)) | AK64: =IF(COUNT(C64:P64)=0,"",IFERROR(AI64/G64,0)) | AL64: =IF(COUNT(C64:P64)=0,"",IFERROR(AK64/V64,0)) | AM64: =IF(COUNT(C64:P64)=0,"",IFERROR(AI64/I64,0)) | AN64: =IF(COUNT(C64:P64)=0,"",IFERROR(AH64/I64-AA64,0))
A65: =Config!$C$6+59 | B65: =INT((A65-Config!$C$6)/7)+1 | Q65: =IF(COUNT(C65:P65)=0,"",IFERROR(C65/D65*1000,0)) | R65: =IF(COUNT(C65:P65)=0,"",IFERROR(D65/E65,0)) | S65: =IF(COUNT(C65:P65)=0,"",IFERROR(F65/D65,0)) | T65: =IF(COUNT(C65:P65)=0,"",IFERROR(C65/F65,0)) | U65: =IF(COUNT(C65:P65)=0,"",IFERROR(G65/F65,0)) | V65: =IF(COUNT(C65:P65)=0,"",IFERROR(C65/G65,0)) | W65: =IF(COUNT(C65:P65)=0,"",IFERROR(G65/D65*1000,0)) | X65: =IF(COUNT(C65:P65)=0,"",IFERROR(H65/G65,0)) | Y65: =IF(COUNT(C65:P65)=0,"",IFERROR(I65/H65,0)) | Z65: =IF(COUNT(C65:P65)=0,"",IFERROR(I65/G65,0)) | AA65: =IF(COUNT(C65:P65)=0,"",IFERROR(C65/I65,0)) | AB65: =IF(COUNT(C65:P65)=0,"",IFERROR(J65/I65,0)) | AC65: =IF(COUNT(C65:P65)=0,"",IFERROR(K65/I65,0)) | AD65: =IF(COUNT(C65:P65)=0,"",IFERROR(L65/I65,0)) | AE65: =IF(COUNT(C65:P65)=0,"",IFERROR(P65/I65,0)) | AF65: =IF(COUNT(C65:P65)=0,"",IFERROR(I65*Config!$C$7+J65*Config!$C$8+K65*Config!$C$9+L65*Config!$C$10+M65*Config!$C$11+N65*Config!$C$12+O65*Config!$C$13+P65*Config!$C$14,0)) | AG65: =IF(COUNT(C65:P65)=0,"",IFERROR(AF65/I65,0)) | AH65: =IF(COUNT(C65:P65)=0,"",IFERROR(AF65*(1-Config!$C$15-Config!$C$16-Config!$C$17),0)) | AI65: =IF(COUNT(C65:P65)=0,"",IFERROR(AH65-C65-Config!$C$18,0)) | AJ65: =IF(COUNT(C65:P65)=0,"",IFERROR(AH65/C65,0)) | AK65: =IF(COUNT(C65:P65)=0,"",IFERROR(AI65/G65,0)) | AL65: =IF(COUNT(C65:P65)=0,"",IFERROR(AK65/V65,0)) | AM65: =IF(COUNT(C65:P65)=0,"",IFERROR(AI65/I65,0)) | AN65: =IF(COUNT(C65:P65)=0,"",IFERROR(AH65/I65-AA65,0))
A66: =Config!$C$6+60 | B66: =INT((A66-Config!$C$6)/7)+1 | Q66: =IF(COUNT(C66:P66)=0,"",IFERROR(C66/D66*1000,0)) | R66: =IF(COUNT(C66:P66)=0,"",IFERROR(D66/E66,0)) | S66: =IF(COUNT(C66:P66)=0,"",IFERROR(F66/D66,0)) | T66: =IF(COUNT(C66:P66)=0,"",IFERROR(C66/F66,0)) | U66: =IF(COUNT(C66:P66)=0,"",IFERROR(G66/F66,0)) | V66: =IF(COUNT(C66:P66)=0,"",IFERROR(C66/G66,0)) | W66: =IF(COUNT(C66:P66)=0,"",IFERROR(G66/D66*1000,0)) | X66: =IF(COUNT(C66:P66)=0,"",IFERROR(H66/G66,0)) | Y66: =IF(COUNT(C66:P66)=0,"",IFERROR(I66/H66,0)) | Z66: =IF(COUNT(C66:P66)=0,"",IFERROR(I66/G66,0)) | AA66: =IF(COUNT(C66:P66)=0,"",IFERROR(C66/I66,0)) | AB66: =IF(COUNT(C66:P66)=0,"",IFERROR(J66/I66,0)) | AC66: =IF(COUNT(C66:P66)=0,"",IFERROR(K66/I66,0)) | AD66: =IF(COUNT(C66:P66)=0,"",IFERROR(L66/I66,0)) | AE66: =IF(COUNT(C66:P66)=0,"",IFERROR(P66/I66,0)) | AF66: =IF(COUNT(C66:P66)=0,"",IFERROR(I66*Config!$C$7+J66*Config!$C$8+K66*Config!$C$9+L66*Config!$C$10+M66*Config!$C$11+N66*Config!$C$12+O66*Config!$C$13+P66*Config!$C$14,0)) | AG66: =IF(COUNT(C66:P66)=0,"",IFERROR(AF66/I66,0)) | AH66: =IF(COUNT(C66:P66)=0,"",IFERROR(AF66*(1-Config!$C$15-Config!$C$16-Config!$C$17),0)) | AI66: =IF(COUNT(C66:P66)=0,"",IFERROR(AH66-C66-Config!$C$18,0)) | AJ66: =IF(COUNT(C66:P66)=0,"",IFERROR(AH66/C66,0)) | AK66: =IF(COUNT(C66:P66)=0,"",IFERROR(AI66/G66,0)) | AL66: =IF(COUNT(C66:P66)=0,"",IFERROR(AK66/V66,0)) | AM66: =IF(COUNT(C66:P66)=0,"",IFERROR(AI66/I66,0)) | AN66: =IF(COUNT(C66:P66)=0,"",IFERROR(AH66/I66-AA66,0))
A67: =Config!$C$6+61 | B67: =INT((A67-Config!$C$6)/7)+1 | Q67: =IF(COUNT(C67:P67)=0,"",IFERROR(C67/D67*1000,0)) | R67: =IF(COUNT(C67:P67)=0,"",IFERROR(D67/E67,0)) | S67: =IF(COUNT(C67:P67)=0,"",IFERROR(F67/D67,0)) | T67: =IF(COUNT(C67:P67)=0,"",IFERROR(C67/F67,0)) | U67: =IF(COUNT(C67:P67)=0,"",IFERROR(G67/F67,0)) | V67: =IF(COUNT(C67:P67)=0,"",IFERROR(C67/G67,0)) | W67: =IF(COUNT(C67:P67)=0,"",IFERROR(G67/D67*1000,0)) | X67: =IF(COUNT(C67:P67)=0,"",IFERROR(H67/G67,0)) | Y67: =IF(COUNT(C67:P67)=0,"",IFERROR(I67/H67,0)) | Z67: =IF(COUNT(C67:P67)=0,"",IFERROR(I67/G67,0)) | AA67: =IF(COUNT(C67:P67)=0,"",IFERROR(C67/I67,0)) | AB67: =IF(COUNT(C67:P67)=0,"",IFERROR(J67/I67,0)) | AC67: =IF(COUNT(C67:P67)=0,"",IFERROR(K67/I67,0)) | AD67: =IF(COUNT(C67:P67)=0,"",IFERROR(L67/I67,0)) | AE67: =IF(COUNT(C67:P67)=0,"",IFERROR(P67/I67,0)) | AF67: =IF(COUNT(C67:P67)=0,"",IFERROR(I67*Config!$C$7+J67*Config!$C$8+K67*Config!$C$9+L67*Config!$C$10+M67*Config!$C$11+N67*Config!$C$12+O67*Config!$C$13+P67*Config!$C$14,0)) | AG67: =IF(COUNT(C67:P67)=0,"",IFERROR(AF67/I67,0)) | AH67: =IF(COUNT(C67:P67)=0,"",IFERROR(AF67*(1-Config!$C$15-Config!$C$16-Config!$C$17),0)) | AI67: =IF(COUNT(C67:P67)=0,"",IFERROR(AH67-C67-Config!$C$18,0)) | AJ67: =IF(COUNT(C67:P67)=0,"",IFERROR(AH67/C67,0)) | AK67: =IF(COUNT(C67:P67)=0,"",IFERROR(AI67/G67,0)) | AL67: =IF(COUNT(C67:P67)=0,"",IFERROR(AK67/V67,0)) | AM67: =IF(COUNT(C67:P67)=0,"",IFERROR(AI67/I67,0)) | AN67: =IF(COUNT(C67:P67)=0,"",IFERROR(AH67/I67-AA67,0))
A68: =Config!$C$6+62 | B68: =INT((A68-Config!$C$6)/7)+1 | Q68: =IF(COUNT(C68:P68)=0,"",IFERROR(C68/D68*1000,0)) | R68: =IF(COUNT(C68:P68)=0,"",IFERROR(D68/E68,0)) | S68: =IF(COUNT(C68:P68)=0,"",IFERROR(F68/D68,0)) | T68: =IF(COUNT(C68:P68)=0,"",IFERROR(C68/F68,0)) | U68: =IF(COUNT(C68:P68)=0,"",IFERROR(G68/F68,0)) | V68: =IF(COUNT(C68:P68)=0,"",IFERROR(C68/G68,0)) | W68: =IF(COUNT(C68:P68)=0,"",IFERROR(G68/D68*1000,0)) | X68: =IF(COUNT(C68:P68)=0,"",IFERROR(H68/G68,0)) | Y68: =IF(COUNT(C68:P68)=0,"",IFERROR(I68/H68,0)) | Z68: =IF(COUNT(C68:P68)=0,"",IFERROR(I68/G68,0)) | AA68: =IF(COUNT(C68:P68)=0,"",IFERROR(C68/I68,0)) | AB68: =IF(COUNT(C68:P68)=0,"",IFERROR(J68/I68,0)) | AC68: =IF(COUNT(C68:P68)=0,"",IFERROR(K68/I68,0)) | AD68: =IF(COUNT(C68:P68)=0,"",IFERROR(L68/I68,0)) | AE68: =IF(COUNT(C68:P68)=0,"",IFERROR(P68/I68,0)) | AF68: =IF(COUNT(C68:P68)=0,"",IFERROR(I68*Config!$C$7+J68*Config!$C$8+K68*Config!$C$9+L68*Config!$C$10+M68*Config!$C$11+N68*Config!$C$12+O68*Config!$C$13+P68*Config!$C$14,0)) | AG68: =IF(COUNT(C68:P68)=0,"",IFERROR(AF68/I68,0)) | AH68: =IF(COUNT(C68:P68)=0,"",IFERROR(AF68*(1-Config!$C$15-Config!$C$16-Config!$C$17),0)) | AI68: =IF(COUNT(C68:P68)=0,"",IFERROR(AH68-C68-Config!$C$18,0)) | AJ68: =IF(COUNT(C68:P68)=0,"",IFERROR(AH68/C68,0)) | AK68: =IF(COUNT(C68:P68)=0,"",IFERROR(AI68/G68,0)) | AL68: =IF(COUNT(C68:P68)=0,"",IFERROR(AK68/V68,0)) | AM68: =IF(COUNT(C68:P68)=0,"",IFERROR(AI68/I68,0)) | AN68: =IF(COUNT(C68:P68)=0,"",IFERROR(AH68/I68-AA68,0))
A69: =Config!$C$6+63 | B69: =INT((A69-Config!$C$6)/7)+1 | Q69: =IF(COUNT(C69:P69)=0,"",IFERROR(C69/D69*1000,0)) | R69: =IF(COUNT(C69:P69)=0,"",IFERROR(D69/E69,0)) | S69: =IF(COUNT(C69:P69)=0,"",IFERROR(F69/D69,0)) | T69: =IF(COUNT(C69:P69)=0,"",IFERROR(C69/F69,0)) | U69: =IF(COUNT(C69:P69)=0,"",IFERROR(G69/F69,0)) | V69: =IF(COUNT(C69:P69)=0,"",IFERROR(C69/G69,0)) | W69: =IF(COUNT(C69:P69)=0,"",IFERROR(G69/D69*1000,0)) | X69: =IF(COUNT(C69:P69)=0,"",IFERROR(H69/G69,0)) | Y69: =IF(COUNT(C69:P69)=0,"",IFERROR(I69/H69,0)) | Z69: =IF(COUNT(C69:P69)=0,"",IFERROR(I69/G69,0)) | AA69: =IF(COUNT(C69:P69)=0,"",IFERROR(C69/I69,0)) | AB69: =IF(COUNT(C69:P69)=0,"",IFERROR(J69/I69,0)) | AC69: =IF(COUNT(C69:P69)=0,"",IFERROR(K69/I69,0)) | AD69: =IF(COUNT(C69:P69)=0,"",IFERROR(L69/I69,0)) | AE69: =IF(COUNT(C69:P69)=0,"",IFERROR(P69/I69,0)) | AF69: =IF(COUNT(C69:P69)=0,"",IFERROR(I69*Config!$C$7+J69*Config!$C$8+K69*Config!$C$9+L69*Config!$C$10+M69*Config!$C$11+N69*Config!$C$12+O69*Config!$C$13+P69*Config!$C$14,0)) | AG69: =IF(COUNT(C69:P69)=0,"",IFERROR(AF69/I69,0)) | AH69: =IF(COUNT(C69:P69)=0,"",IFERROR(AF69*(1-Config!$C$15-Config!$C$16-Config!$C$17),0)) | AI69: =IF(COUNT(C69:P69)=0,"",IFERROR(AH69-C69-Config!$C$18,0)) | AJ69: =IF(COUNT(C69:P69)=0,"",IFERROR(AH69/C69,0)) | AK69: =IF(COUNT(C69:P69)=0,"",IFERROR(AI69/G69,0)) | AL69: =IF(COUNT(C69:P69)=0,"",IFERROR(AK69/V69,0)) | AM69: =IF(COUNT(C69:P69)=0,"",IFERROR(AI69/I69,0)) | AN69: =IF(COUNT(C69:P69)=0,"",IFERROR(AH69/I69-AA69,0))
A70: =Config!$C$6+64 | B70: =INT((A70-Config!$C$6)/7)+1 | Q70: =IF(COUNT(C70:P70)=0,"",IFERROR(C70/D70*1000,0)) | R70: =IF(COUNT(C70:P70)=0,"",IFERROR(D70/E70,0)) | S70: =IF(COUNT(C70:P70)=0,"",IFERROR(F70/D70,0)) | T70: =IF(COUNT(C70:P70)=0,"",IFERROR(C70/F70,0)) | U70: =IF(COUNT(C70:P70)=0,"",IFERROR(G70/F70,0)) | V70: =IF(COUNT(C70:P70)=0,"",IFERROR(C70/G70,0)) | W70: =IF(COUNT(C70:P70)=0,"",IFERROR(G70/D70*1000,0)) | X70: =IF(COUNT(C70:P70)=0,"",IFERROR(H70/G70,0)) | Y70: =IF(COUNT(C70:P70)=0,"",IFERROR(I70/H70,0)) | Z70: =IF(COUNT(C70:P70)=0,"",IFERROR(I70/G70,0)) | AA70: =IF(COUNT(C70:P70)=0,"",IFERROR(C70/I70,0)) | AB70: =IF(COUNT(C70:P70)=0,"",IFERROR(J70/I70,0)) | AC70: =IF(COUNT(C70:P70)=0,"",IFERROR(K70/I70,0)) | AD70: =IF(COUNT(C70:P70)=0,"",IFERROR(L70/I70,0)) | AE70: =IF(COUNT(C70:P70)=0,"",IFERROR(P70/I70,0)) | AF70: =IF(COUNT(C70:P70)=0,"",IFERROR(I70*Config!$C$7+J70*Config!$C$8+K70*Config!$C$9+L70*Config!$C$10+M70*Config!$C$11+N70*Config!$C$12+O70*Config!$C$13+P70*Config!$C$14,0)) | AG70: =IF(COUNT(C70:P70)=0,"",IFERROR(AF70/I70,0)) | AH70: =IF(COUNT(C70:P70)=0,"",IFERROR(AF70*(1-Config!$C$15-Config!$C$16-Config!$C$17),0)) | AI70: =IF(COUNT(C70:P70)=0,"",IFERROR(AH70-C70-Config!$C$18,0)) | AJ70: =IF(COUNT(C70:P70)=0,"",IFERROR(AH70/C70,0)) | AK70: =IF(COUNT(C70:P70)=0,"",IFERROR(AI70/G70,0)) | AL70: =IF(COUNT(C70:P70)=0,"",IFERROR(AK70/V70,0)) | AM70: =IF(COUNT(C70:P70)=0,"",IFERROR(AI70/I70,0)) | AN70: =IF(COUNT(C70:P70)=0,"",IFERROR(AH70/I70-AA70,0))
A71: =Config!$C$6+65 | B71: =INT((A71-Config!$C$6)/7)+1 | Q71: =IF(COUNT(C71:P71)=0,"",IFERROR(C71/D71*1000,0)) | R71: =IF(COUNT(C71:P71)=0,"",IFERROR(D71/E71,0)) | S71: =IF(COUNT(C71:P71)=0,"",IFERROR(F71/D71,0)) | T71: =IF(COUNT(C71:P71)=0,"",IFERROR(C71/F71,0)) | U71: =IF(COUNT(C71:P71)=0,"",IFERROR(G71/F71,0)) | V71: =IF(COUNT(C71:P71)=0,"",IFERROR(C71/G71,0)) | W71: =IF(COUNT(C71:P71)=0,"",IFERROR(G71/D71*1000,0)) | X71: =IF(COUNT(C71:P71)=0,"",IFERROR(H71/G71,0)) | Y71: =IF(COUNT(C71:P71)=0,"",IFERROR(I71/H71,0)) | Z71: =IF(COUNT(C71:P71)=0,"",IFERROR(I71/G71,0)) | AA71: =IF(COUNT(C71:P71)=0,"",IFERROR(C71/I71,0)) | AB71: =IF(COUNT(C71:P71)=0,"",IFERROR(J71/I71,0)) | AC71: =IF(COUNT(C71:P71)=0,"",IFERROR(K71/I71,0)) | AD71: =IF(COUNT(C71:P71)=0,"",IFERROR(L71/I71,0)) | AE71: =IF(COUNT(C71:P71)=0,"",IFERROR(P71/I71,0)) | AF71: =IF(COUNT(C71:P71)=0,"",IFERROR(I71*Config!$C$7+J71*Config!$C$8+K71*Config!$C$9+L71*Config!$C$10+M71*Config!$C$11+N71*Config!$C$12+O71*Config!$C$13+P71*Config!$C$14,0)) | AG71: =IF(COUNT(C71:P71)=0,"",IFERROR(AF71/I71,0)) | AH71: =IF(COUNT(C71:P71)=0,"",IFERROR(AF71*(1-Config!$C$15-Config!$C$16-Config!$C$17),0)) | AI71: =IF(COUNT(C71:P71)=0,"",IFERROR(AH71-C71-Config!$C$18,0)) | AJ71: =IF(COUNT(C71:P71)=0,"",IFERROR(AH71/C71,0)) | AK71: =IF(COUNT(C71:P71)=0,"",IFERROR(AI71/G71,0)) | AL71: =IF(COUNT(C71:P71)=0,"",IFERROR(AK71/V71,0)) | AM71: =IF(COUNT(C71:P71)=0,"",IFERROR(AI71/I71,0)) | AN71: =IF(COUNT(C71:P71)=0,"",IFERROR(AH71/I71-AA71,0))
A72: =Config!$C$6+66 | B72: =INT((A72-Config!$C$6)/7)+1 | Q72: =IF(COUNT(C72:P72)=0,"",IFERROR(C72/D72*1000,0)) | R72: =IF(COUNT(C72:P72)=0,"",IFERROR(D72/E72,0)) | S72: =IF(COUNT(C72:P72)=0,"",IFERROR(F72/D72,0)) | T72: =IF(COUNT(C72:P72)=0,"",IFERROR(C72/F72,0)) | U72: =IF(COUNT(C72:P72)=0,"",IFERROR(G72/F72,0)) | V72: =IF(COUNT(C72:P72)=0,"",IFERROR(C72/G72,0)) | W72: =IF(COUNT(C72:P72)=0,"",IFERROR(G72/D72*1000,0)) | X72: =IF(COUNT(C72:P72)=0,"",IFERROR(H72/G72,0)) | Y72: =IF(COUNT(C72:P72)=0,"",IFERROR(I72/H72,0)) | Z72: =IF(COUNT(C72:P72)=0,"",IFERROR(I72/G72,0)) | AA72: =IF(COUNT(C72:P72)=0,"",IFERROR(C72/I72,0)) | AB72: =IF(COUNT(C72:P72)=0,"",IFERROR(J72/I72,0)) | AC72: =IF(COUNT(C72:P72)=0,"",IFERROR(K72/I72,0)) | AD72: =IF(COUNT(C72:P72)=0,"",IFERROR(L72/I72,0)) | AE72: =IF(COUNT(C72:P72)=0,"",IFERROR(P72/I72,0)) | AF72: =IF(COUNT(C72:P72)=0,"",IFERROR(I72*Config!$C$7+J72*Config!$C$8+K72*Config!$C$9+L72*Config!$C$10+M72*Config!$C$11+N72*Config!$C$12+O72*Config!$C$13+P72*Config!$C$14,0)) | AG72: =IF(COUNT(C72:P72)=0,"",IFERROR(AF72/I72,0)) | AH72: =IF(COUNT(C72:P72)=0,"",IFERROR(AF72*(1-Config!$C$15-Config!$C$16-Config!$C$17),0)) | AI72: =IF(COUNT(C72:P72)=0,"",IFERROR(AH72-C72-Config!$C$18,0)) | AJ72: =IF(COUNT(C72:P72)=0,"",IFERROR(AH72/C72,0)) | AK72: =IF(COUNT(C72:P72)=0,"",IFERROR(AI72/G72,0)) | AL72: =IF(COUNT(C72:P72)=0,"",IFERROR(AK72/V72,0)) | AM72: =IF(COUNT(C72:P72)=0,"",IFERROR(AI72/I72,0)) | AN72: =IF(COUNT(C72:P72)=0,"",IFERROR(AH72/I72-AA72,0))
A73: =Config!$C$6+67 | B73: =INT((A73-Config!$C$6)/7)+1 | Q73: =IF(COUNT(C73:P73)=0,"",IFERROR(C73/D73*1000,0)) | R73: =IF(COUNT(C73:P73)=0,"",IFERROR(D73/E73,0)) | S73: =IF(COUNT(C73:P73)=0,"",IFERROR(F73/D73,0)) | T73: =IF(COUNT(C73:P73)=0,"",IFERROR(C73/F73,0)) | U73: =IF(COUNT(C73:P73)=0,"",IFERROR(G73/F73,0)) | V73: =IF(COUNT(C73:P73)=0,"",IFERROR(C73/G73,0)) | W73: =IF(COUNT(C73:P73)=0,"",IFERROR(G73/D73*1000,0)) | X73: =IF(COUNT(C73:P73)=0,"",IFERROR(H73/G73,0)) | Y73: =IF(COUNT(C73:P73)=0,"",IFERROR(I73/H73,0)) | Z73: =IF(COUNT(C73:P73)=0,"",IFERROR(I73/G73,0)) | AA73: =IF(COUNT(C73:P73)=0,"",IFERROR(C73/I73,0)) | AB73: =IF(COUNT(C73:P73)=0,"",IFERROR(J73/I73,0)) | AC73: =IF(COUNT(C73:P73)=0,"",IFERROR(K73/I73,0)) | AD73: =IF(COUNT(C73:P73)=0,"",IFERROR(L73/I73,0)) | AE73: =IF(COUNT(C73:P73)=0,"",IFERROR(P73/I73,0)) | AF73: =IF(COUNT(C73:P73)=0,"",IFERROR(I73*Config!$C$7+J73*Config!$C$8+K73*Config!$C$9+L73*Config!$C$10+M73*Config!$C$11+N73*Config!$C$12+O73*Config!$C$13+P73*Config!$C$14,0)) | AG73: =IF(COUNT(C73:P73)=0,"",IFERROR(AF73/I73,0)) | AH73: =IF(COUNT(C73:P73)=0,"",IFERROR(AF73*(1-Config!$C$15-Config!$C$16-Config!$C$17),0)) | AI73: =IF(COUNT(C73:P73)=0,"",IFERROR(AH73-C73-Config!$C$18,0)) | AJ73: =IF(COUNT(C73:P73)=0,"",IFERROR(AH73/C73,0)) | AK73: =IF(COUNT(C73:P73)=0,"",IFERROR(AI73/G73,0)) | AL73: =IF(COUNT(C73:P73)=0,"",IFERROR(AK73/V73,0)) | AM73: =IF(COUNT(C73:P73)=0,"",IFERROR(AI73/I73,0)) | AN73: =IF(COUNT(C73:P73)=0,"",IFERROR(AH73/I73-AA73,0))
A74: =Config!$C$6+68 | B74: =INT((A74-Config!$C$6)/7)+1 | Q74: =IF(COUNT(C74:P74)=0,"",IFERROR(C74/D74*1000,0)) | R74: =IF(COUNT(C74:P74)=0,"",IFERROR(D74/E74,0)) | S74: =IF(COUNT(C74:P74)=0,"",IFERROR(F74/D74,0)) | T74: =IF(COUNT(C74:P74)=0,"",IFERROR(C74/F74,0)) | U74: =IF(COUNT(C74:P74)=0,"",IFERROR(G74/F74,0)) | V74: =IF(COUNT(C74:P74)=0,"",IFERROR(C74/G74,0)) | W74: =IF(COUNT(C74:P74)=0,"",IFERROR(G74/D74*1000,0)) | X74: =IF(COUNT(C74:P74)=0,"",IFERROR(H74/G74,0)) | Y74: =IF(COUNT(C74:P74)=0,"",IFERROR(I74/H74,0)) | Z74: =IF(COUNT(C74:P74)=0,"",IFERROR(I74/G74,0)) | AA74: =IF(COUNT(C74:P74)=0,"",IFERROR(C74/I74,0)) | AB74: =IF(COUNT(C74:P74)=0,"",IFERROR(J74/I74,0)) | AC74: =IF(COUNT(C74:P74)=0,"",IFERROR(K74/I74,0)) | AD74: =IF(COUNT(C74:P74)=0,"",IFERROR(L74/I74,0)) | AE74: =IF(COUNT(C74:P74)=0,"",IFERROR(P74/I74,0)) | AF74: =IF(COUNT(C74:P74)=0,"",IFERROR(I74*Config!$C$7+J74*Config!$C$8+K74*Config!$C$9+L74*Config!$C$10+M74*Config!$C$11+N74*Config!$C$12+O74*Config!$C$13+P74*Config!$C$14,0)) | AG74: =IF(COUNT(C74:P74)=0,"",IFERROR(AF74/I74,0)) | AH74: =IF(COUNT(C74:P74)=0,"",IFERROR(AF74*(1-Config!$C$15-Config!$C$16-Config!$C$17),0)) | AI74: =IF(COUNT(C74:P74)=0,"",IFERROR(AH74-C74-Config!$C$18,0)) | AJ74: =IF(COUNT(C74:P74)=0,"",IFERROR(AH74/C74,0)) | AK74: =IF(COUNT(C74:P74)=0,"",IFERROR(AI74/G74,0)) | AL74: =IF(COUNT(C74:P74)=0,"",IFERROR(AK74/V74,0)) | AM74: =IF(COUNT(C74:P74)=0,"",IFERROR(AI74/I74,0)) | AN74: =IF(COUNT(C74:P74)=0,"",IFERROR(AH74/I74-AA74,0))
A75: =Config!$C$6+69 | B75: =INT((A75-Config!$C$6)/7)+1 | Q75: =IF(COUNT(C75:P75)=0,"",IFERROR(C75/D75*1000,0)) | R75: =IF(COUNT(C75:P75)=0,"",IFERROR(D75/E75,0)) | S75: =IF(COUNT(C75:P75)=0,"",IFERROR(F75/D75,0)) | T75: =IF(COUNT(C75:P75)=0,"",IFERROR(C75/F75,0)) | U75: =IF(COUNT(C75:P75)=0,"",IFERROR(G75/F75,0)) | V75: =IF(COUNT(C75:P75)=0,"",IFERROR(C75/G75,0)) | W75: =IF(COUNT(C75:P75)=0,"",IFERROR(G75/D75*1000,0)) | X75: =IF(COUNT(C75:P75)=0,"",IFERROR(H75/G75,0)) | Y75: =IF(COUNT(C75:P75)=0,"",IFERROR(I75/H75,0)) | Z75: =IF(COUNT(C75:P75)=0,"",IFERROR(I75/G75,0)) | AA75: =IF(COUNT(C75:P75)=0,"",IFERROR(C75/I75,0)) | AB75: =IF(COUNT(C75:P75)=0,"",IFERROR(J75/I75,0)) | AC75: =IF(COUNT(C75:P75)=0,"",IFERROR(K75/I75,0)) | AD75: =IF(COUNT(C75:P75)=0,"",IFERROR(L75/I75,0)) | AE75: =IF(COUNT(C75:P75)=0,"",IFERROR(P75/I75,0)) | AF75: =IF(COUNT(C75:P75)=0,"",IFERROR(I75*Config!$C$7+J75*Config!$C$8+K75*Config!$C$9+L75*Config!$C$10+M75*Config!$C$11+N75*Config!$C$12+O75*Config!$C$13+P75*Config!$C$14,0)) | AG75: =IF(COUNT(C75:P75)=0,"",IFERROR(AF75/I75,0)) | AH75: =IF(COUNT(C75:P75)=0,"",IFERROR(AF75*(1-Config!$C$15-Config!$C$16-Config!$C$17),0)) | AI75: =IF(COUNT(C75:P75)=0,"",IFERROR(AH75-C75-Config!$C$18,0)) | AJ75: =IF(COUNT(C75:P75)=0,"",IFERROR(AH75/C75,0)) | AK75: =IF(COUNT(C75:P75)=0,"",IFERROR(AI75/G75,0)) | AL75: =IF(COUNT(C75:P75)=0,"",IFERROR(AK75/V75,0)) | AM75: =IF(COUNT(C75:P75)=0,"",IFERROR(AI75/I75,0)) | AN75: =IF(COUNT(C75:P75)=0,"",IFERROR(AH75/I75-AA75,0))
A76: =Config!$C$6+70 | B76: =INT((A76-Config!$C$6)/7)+1 | Q76: =IF(COUNT(C76:P76)=0,"",IFERROR(C76/D76*1000,0)) | R76: =IF(COUNT(C76:P76)=0,"",IFERROR(D76/E76,0)) | S76: =IF(COUNT(C76:P76)=0,"",IFERROR(F76/D76,0)) | T76: =IF(COUNT(C76:P76)=0,"",IFERROR(C76/F76,0)) | U76: =IF(COUNT(C76:P76)=0,"",IFERROR(G76/F76,0)) | V76: =IF(COUNT(C76:P76)=0,"",IFERROR(C76/G76,0)) | W76: =IF(COUNT(C76:P76)=0,"",IFERROR(G76/D76*1000,0)) | X76: =IF(COUNT(C76:P76)=0,"",IFERROR(H76/G76,0)) | Y76: =IF(COUNT(C76:P76)=0,"",IFERROR(I76/H76,0)) | Z76: =IF(COUNT(C76:P76)=0,"",IFERROR(I76/G76,0)) | AA76: =IF(COUNT(C76:P76)=0,"",IFERROR(C76/I76,0)) | AB76: =IF(COUNT(C76:P76)=0,"",IFERROR(J76/I76,0)) | AC76: =IF(COUNT(C76:P76)=0,"",IFERROR(K76/I76,0)) | AD76: =IF(COUNT(C76:P76)=0,"",IFERROR(L76/I76,0)) | AE76: =IF(COUNT(C76:P76)=0,"",IFERROR(P76/I76,0)) | AF76: =IF(COUNT(C76:P76)=0,"",IFERROR(I76*Config!$C$7+J76*Config!$C$8+K76*Config!$C$9+L76*Config!$C$10+M76*Config!$C$11+N76*Config!$C$12+O76*Config!$C$13+P76*Config!$C$14,0)) | AG76: =IF(COUNT(C76:P76)=0,"",IFERROR(AF76/I76,0)) | AH76: =IF(COUNT(C76:P76)=0,"",IFERROR(AF76*(1-Config!$C$15-Config!$C$16-Config!$C$17),0)) | AI76: =IF(COUNT(C76:P76)=0,"",IFERROR(AH76-C76-Config!$C$18,0)) | AJ76: =IF(COUNT(C76:P76)=0,"",IFERROR(AH76/C76,0)) | AK76: =IF(COUNT(C76:P76)=0,"",IFERROR(AI76/G76,0)) | AL76: =IF(COUNT(C76:P76)=0,"",IFERROR(AK76/V76,0)) | AM76: =IF(COUNT(C76:P76)=0,"",IFERROR(AI76/I76,0)) | AN76: =IF(COUNT(C76:P76)=0,"",IFERROR(AH76/I76-AA76,0))
A77: =Config!$C$6+71 | B77: =INT((A77-Config!$C$6)/7)+1 | Q77: =IF(COUNT(C77:P77)=0,"",IFERROR(C77/D77*1000,0)) | R77: =IF(COUNT(C77:P77)=0,"",IFERROR(D77/E77,0)) | S77: =IF(COUNT(C77:P77)=0,"",IFERROR(F77/D77,0)) | T77: =IF(COUNT(C77:P77)=0,"",IFERROR(C77/F77,0)) | U77: =IF(COUNT(C77:P77)=0,"",IFERROR(G77/F77,0)) | V77: =IF(COUNT(C77:P77)=0,"",IFERROR(C77/G77,0)) | W77: =IF(COUNT(C77:P77)=0,"",IFERROR(G77/D77*1000,0)) | X77: =IF(COUNT(C77:P77)=0,"",IFERROR(H77/G77,0)) | Y77: =IF(COUNT(C77:P77)=0,"",IFERROR(I77/H77,0)) | Z77: =IF(COUNT(C77:P77)=0,"",IFERROR(I77/G77,0)) | AA77: =IF(COUNT(C77:P77)=0,"",IFERROR(C77/I77,0)) | AB77: =IF(COUNT(C77:P77)=0,"",IFERROR(J77/I77,0)) | AC77: =IF(COUNT(C77:P77)=0,"",IFERROR(K77/I77,0)) | AD77: =IF(COUNT(C77:P77)=0,"",IFERROR(L77/I77,0)) | AE77: =IF(COUNT(C77:P77)=0,"",IFERROR(P77/I77,0)) | AF77: =IF(COUNT(C77:P77)=0,"",IFERROR(I77*Config!$C$7+J77*Config!$C$8+K77*Config!$C$9+L77*Config!$C$10+M77*Config!$C$11+N77*Config!$C$12+O77*Config!$C$13+P77*Config!$C$14,0)) | AG77: =IF(COUNT(C77:P77)=0,"",IFERROR(AF77/I77,0)) | AH77: =IF(COUNT(C77:P77)=0,"",IFERROR(AF77*(1-Config!$C$15-Config!$C$16-Config!$C$17),0)) | AI77: =IF(COUNT(C77:P77)=0,"",IFERROR(AH77-C77-Config!$C$18,0)) | AJ77: =IF(COUNT(C77:P77)=0,"",IFERROR(AH77/C77,0)) | AK77: =IF(COUNT(C77:P77)=0,"",IFERROR(AI77/G77,0)) | AL77: =IF(COUNT(C77:P77)=0,"",IFERROR(AK77/V77,0)) | AM77: =IF(COUNT(C77:P77)=0,"",IFERROR(AI77/I77,0)) | AN77: =IF(COUNT(C77:P77)=0,"",IFERROR(AH77/I77-AA77,0))
A78: =Config!$C$6+72 | B78: =INT((A78-Config!$C$6)/7)+1 | Q78: =IF(COUNT(C78:P78)=0,"",IFERROR(C78/D78*1000,0)) | R78: =IF(COUNT(C78:P78)=0,"",IFERROR(D78/E78,0)) | S78: =IF(COUNT(C78:P78)=0,"",IFERROR(F78/D78,0)) | T78: =IF(COUNT(C78:P78)=0,"",IFERROR(C78/F78,0)) | U78: =IF(COUNT(C78:P78)=0,"",IFERROR(G78/F78,0)) | V78: =IF(COUNT(C78:P78)=0,"",IFERROR(C78/G78,0)) | W78: =IF(COUNT(C78:P78)=0,"",IFERROR(G78/D78*1000,0)) | X78: =IF(COUNT(C78:P78)=0,"",IFERROR(H78/G78,0)) | Y78: =IF(COUNT(C78:P78)=0,"",IFERROR(I78/H78,0)) | Z78: =IF(COUNT(C78:P78)=0,"",IFERROR(I78/G78,0)) | AA78: =IF(COUNT(C78:P78)=0,"",IFERROR(C78/I78,0)) | AB78: =IF(COUNT(C78:P78)=0,"",IFERROR(J78/I78,0)) | AC78: =IF(COUNT(C78:P78)=0,"",IFERROR(K78/I78,0)) | AD78: =IF(COUNT(C78:P78)=0,"",IFERROR(L78/I78,0)) | AE78: =IF(COUNT(C78:P78)=0,"",IFERROR(P78/I78,0)) | AF78: =IF(COUNT(C78:P78)=0,"",IFERROR(I78*Config!$C$7+J78*Config!$C$8+K78*Config!$C$9+L78*Config!$C$10+M78*Config!$C$11+N78*Config!$C$12+O78*Config!$C$13+P78*Config!$C$14,0)) | AG78: =IF(COUNT(C78:P78)=0,"",IFERROR(AF78/I78,0)) | AH78: =IF(COUNT(C78:P78)=0,"",IFERROR(AF78*(1-Config!$C$15-Config!$C$16-Config!$C$17),0)) | AI78: =IF(COUNT(C78:P78)=0,"",IFERROR(AH78-C78-Config!$C$18,0)) | AJ78: =IF(COUNT(C78:P78)=0,"",IFERROR(AH78/C78,0)) | AK78: =IF(COUNT(C78:P78)=0,"",IFERROR(AI78/G78,0)) | AL78: =IF(COUNT(C78:P78)=0,"",IFERROR(AK78/V78,0)) | AM78: =IF(COUNT(C78:P78)=0,"",IFERROR(AI78/I78,0)) | AN78: =IF(COUNT(C78:P78)=0,"",IFERROR(AH78/I78-AA78,0))
A79: =Config!$C$6+73 | B79: =INT((A79-Config!$C$6)/7)+1 | Q79: =IF(COUNT(C79:P79)=0,"",IFERROR(C79/D79*1000,0)) | R79: =IF(COUNT(C79:P79)=0,"",IFERROR(D79/E79,0)) | S79: =IF(COUNT(C79:P79)=0,"",IFERROR(F79/D79,0)) | T79: =IF(COUNT(C79:P79)=0,"",IFERROR(C79/F79,0)) | U79: =IF(COUNT(C79:P79)=0,"",IFERROR(G79/F79,0)) | V79: =IF(COUNT(C79:P79)=0,"",IFERROR(C79/G79,0)) | W79: =IF(COUNT(C79:P79)=0,"",IFERROR(G79/D79*1000,0)) | X79: =IF(COUNT(C79:P79)=0,"",IFERROR(H79/G79,0)) | Y79: =IF(COUNT(C79:P79)=0,"",IFERROR(I79/H79,0)) | Z79: =IF(COUNT(C79:P79)=0,"",IFERROR(I79/G79,0)) | AA79: =IF(COUNT(C79:P79)=0,"",IFERROR(C79/I79,0)) | AB79: =IF(COUNT(C79:P79)=0,"",IFERROR(J79/I79,0)) | AC79: =IF(COUNT(C79:P79)=0,"",IFERROR(K79/I79,0)) | AD79: =IF(COUNT(C79:P79)=0,"",IFERROR(L79/I79,0)) | AE79: =IF(COUNT(C79:P79)=0,"",IFERROR(P79/I79,0)) | AF79: =IF(COUNT(C79:P79)=0,"",IFERROR(I79*Config!$C$7+J79*Config!$C$8+K79*Config!$C$9+L79*Config!$C$10+M79*Config!$C$11+N79*Config!$C$12+O79*Config!$C$13+P79*Config!$C$14,0)) | AG79: =IF(COUNT(C79:P79)=0,"",IFERROR(AF79/I79,0)) | AH79: =IF(COUNT(C79:P79)=0,"",IFERROR(AF79*(1-Config!$C$15-Config!$C$16-Config!$C$17),0)) | AI79: =IF(COUNT(C79:P79)=0,"",IFERROR(AH79-C79-Config!$C$18,0)) | AJ79: =IF(COUNT(C79:P79)=0,"",IFERROR(AH79/C79,0)) | AK79: =IF(COUNT(C79:P79)=0,"",IFERROR(AI79/G79,0)) | AL79: =IF(COUNT(C79:P79)=0,"",IFERROR(AK79/V79,0)) | AM79: =IF(COUNT(C79:P79)=0,"",IFERROR(AI79/I79,0)) | AN79: =IF(COUNT(C79:P79)=0,"",IFERROR(AH79/I79-AA79,0))
A80: =Config!$C$6+74 | B80: =INT((A80-Config!$C$6)/7)+1 | Q80: =IF(COUNT(C80:P80)=0,"",IFERROR(C80/D80*1000,0)) | R80: =IF(COUNT(C80:P80)=0,"",IFERROR(D80/E80,0)) | S80: =IF(COUNT(C80:P80)=0,"",IFERROR(F80/D80,0)) | T80: =IF(COUNT(C80:P80)=0,"",IFERROR(C80/F80,0)) | U80: =IF(COUNT(C80:P80)=0,"",IFERROR(G80/F80,0)) | V80: =IF(COUNT(C80:P80)=0,"",IFERROR(C80/G80,0)) | W80: =IF(COUNT(C80:P80)=0,"",IFERROR(G80/D80*1000,0)) | X80: =IF(COUNT(C80:P80)=0,"",IFERROR(H80/G80,0)) | Y80: =IF(COUNT(C80:P80)=0,"",IFERROR(I80/H80,0)) | Z80: =IF(COUNT(C80:P80)=0,"",IFERROR(I80/G80,0)) | AA80: =IF(COUNT(C80:P80)=0,"",IFERROR(C80/I80,0)) | AB80: =IF(COUNT(C80:P80)=0,"",IFERROR(J80/I80,0)) | AC80: =IF(COUNT(C80:P80)=0,"",IFERROR(K80/I80,0)) | AD80: =IF(COUNT(C80:P80)=0,"",IFERROR(L80/I80,0)) | AE80: =IF(COUNT(C80:P80)=0,"",IFERROR(P80/I80,0)) | AF80: =IF(COUNT(C80:P80)=0,"",IFERROR(I80*Config!$C$7+J80*Config!$C$8+K80*Config!$C$9+L80*Config!$C$10+M80*Config!$C$11+N80*Config!$C$12+O80*Config!$C$13+P80*Config!$C$14,0)) | AG80: =IF(COUNT(C80:P80)=0,"",IFERROR(AF80/I80,0)) | AH80: =IF(COUNT(C80:P80)=0,"",IFERROR(AF80*(1-Config!$C$15-Config!$C$16-Config!$C$17),0)) | AI80: =IF(COUNT(C80:P80)=0,"",IFERROR(AH80-C80-Config!$C$18,0)) | AJ80: =IF(COUNT(C80:P80)=0,"",IFERROR(AH80/C80,0)) | AK80: =IF(COUNT(C80:P80)=0,"",IFERROR(AI80/G80,0)) | AL80: =IF(COUNT(C80:P80)=0,"",IFERROR(AK80/V80,0)) | AM80: =IF(COUNT(C80:P80)=0,"",IFERROR(AI80/I80,0)) | AN80: =IF(COUNT(C80:P80)=0,"",IFERROR(AH80/I80-AA80,0))
A81: =Config!$C$6+75 | B81: =INT((A81-Config!$C$6)/7)+1 | Q81: =IF(COUNT(C81:P81)=0,"",IFERROR(C81/D81*1000,0)) | R81: =IF(COUNT(C81:P81)=0,"",IFERROR(D81/E81,0)) | S81: =IF(COUNT(C81:P81)=0,"",IFERROR(F81/D81,0)) | T81: =IF(COUNT(C81:P81)=0,"",IFERROR(C81/F81,0)) | U81: =IF(COUNT(C81:P81)=0,"",IFERROR(G81/F81,0)) | V81: =IF(COUNT(C81:P81)=0,"",IFERROR(C81/G81,0)) | W81: =IF(COUNT(C81:P81)=0,"",IFERROR(G81/D81*1000,0)) | X81: =IF(COUNT(C81:P81)=0,"",IFERROR(H81/G81,0)) | Y81: =IF(COUNT(C81:P81)=0,"",IFERROR(I81/H81,0)) | Z81: =IF(COUNT(C81:P81)=0,"",IFERROR(I81/G81,0)) | AA81: =IF(COUNT(C81:P81)=0,"",IFERROR(C81/I81,0)) | AB81: =IF(COUNT(C81:P81)=0,"",IFERROR(J81/I81,0)) | AC81: =IF(COUNT(C81:P81)=0,"",IFERROR(K81/I81,0)) | AD81: =IF(COUNT(C81:P81)=0,"",IFERROR(L81/I81,0)) | AE81: =IF(COUNT(C81:P81)=0,"",IFERROR(P81/I81,0)) | AF81: =IF(COUNT(C81:P81)=0,"",IFERROR(I81*Config!$C$7+J81*Config!$C$8+K81*Config!$C$9+L81*Config!$C$10+M81*Config!$C$11+N81*Config!$C$12+O81*Config!$C$13+P81*Config!$C$14,0)) | AG81: =IF(COUNT(C81:P81)=0,"",IFERROR(AF81/I81,0)) | AH81: =IF(COUNT(C81:P81)=0,"",IFERROR(AF81*(1-Config!$C$15-Config!$C$16-Config!$C$17),0)) | AI81: =IF(COUNT(C81:P81)=0,"",IFERROR(AH81-C81-Config!$C$18,0)) | AJ81: =IF(COUNT(C81:P81)=0,"",IFERROR(AH81/C81,0)) | AK81: =IF(COUNT(C81:P81)=0,"",IFERROR(AI81/G81,0)) | AL81: =IF(COUNT(C81:P81)=0,"",IFERROR(AK81/V81,0)) | AM81: =IF(COUNT(C81:P81)=0,"",IFERROR(AI81/I81,0)) | AN81: =IF(COUNT(C81:P81)=0,"",IFERROR(AH81/I81-AA81,0))
A82: =Config!$C$6+76 | B82: =INT((A82-Config!$C$6)/7)+1 | Q82: =IF(COUNT(C82:P82)=0,"",IFERROR(C82/D82*1000,0)) | R82: =IF(COUNT(C82:P82)=0,"",IFERROR(D82/E82,0)) | S82: =IF(COUNT(C82:P82)=0,"",IFERROR(F82/D82,0)) | T82: =IF(COUNT(C82:P82)=0,"",IFERROR(C82/F82,0)) | U82: =IF(COUNT(C82:P82)=0,"",IFERROR(G82/F82,0)) | V82: =IF(COUNT(C82:P82)=0,"",IFERROR(C82/G82,0)) | W82: =IF(COUNT(C82:P82)=0,"",IFERROR(G82/D82*1000,0)) | X82: =IF(COUNT(C82:P82)=0,"",IFERROR(H82/G82,0)) | Y82: =IF(COUNT(C82:P82)=0,"",IFERROR(I82/H82,0)) | Z82: =IF(COUNT(C82:P82)=0,"",IFERROR(I82/G82,0)) | AA82: =IF(COUNT(C82:P82)=0,"",IFERROR(C82/I82,0)) | AB82: =IF(COUNT(C82:P82)=0,"",IFERROR(J82/I82,0)) | AC82: =IF(COUNT(C82:P82)=0,"",IFERROR(K82/I82,0)) | AD82: =IF(COUNT(C82:P82)=0,"",IFERROR(L82/I82,0)) | AE82: =IF(COUNT(C82:P82)=0,"",IFERROR(P82/I82,0)) | AF82: =IF(COUNT(C82:P82)=0,"",IFERROR(I82*Config!$C$7+J82*Config!$C$8+K82*Config!$C$9+L82*Config!$C$10+M82*Config!$C$11+N82*Config!$C$12+O82*Config!$C$13+P82*Config!$C$14,0)) | AG82: =IF(COUNT(C82:P82)=0,"",IFERROR(AF82/I82,0)) | AH82: =IF(COUNT(C82:P82)=0,"",IFERROR(AF82*(1-Config!$C$15-Config!$C$16-Config!$C$17),0)) | AI82: =IF(COUNT(C82:P82)=0,"",IFERROR(AH82-C82-Config!$C$18,0)) | AJ82: =IF(COUNT(C82:P82)=0,"",IFERROR(AH82/C82,0)) | AK82: =IF(COUNT(C82:P82)=0,"",IFERROR(AI82/G82,0)) | AL82: =IF(COUNT(C82:P82)=0,"",IFERROR(AK82/V82,0)) | AM82: =IF(COUNT(C82:P82)=0,"",IFERROR(AI82/I82,0)) | AN82: =IF(COUNT(C82:P82)=0,"",IFERROR(AH82/I82-AA82,0))
A83: =Config!$C$6+77 | B83: =INT((A83-Config!$C$6)/7)+1 | Q83: =IF(COUNT(C83:P83)=0,"",IFERROR(C83/D83*1000,0)) | R83: =IF(COUNT(C83:P83)=0,"",IFERROR(D83/E83,0)) | S83: =IF(COUNT(C83:P83)=0,"",IFERROR(F83/D83,0)) | T83: =IF(COUNT(C83:P83)=0,"",IFERROR(C83/F83,0)) | U83: =IF(COUNT(C83:P83)=0,"",IFERROR(G83/F83,0)) | V83: =IF(COUNT(C83:P83)=0,"",IFERROR(C83/G83,0)) | W83: =IF(COUNT(C83:P83)=0,"",IFERROR(G83/D83*1000,0)) | X83: =IF(COUNT(C83:P83)=0,"",IFERROR(H83/G83,0)) | Y83: =IF(COUNT(C83:P83)=0,"",IFERROR(I83/H83,0)) | Z83: =IF(COUNT(C83:P83)=0,"",IFERROR(I83/G83,0)) | AA83: =IF(COUNT(C83:P83)=0,"",IFERROR(C83/I83,0)) | AB83: =IF(COUNT(C83:P83)=0,"",IFERROR(J83/I83,0)) | AC83: =IF(COUNT(C83:P83)=0,"",IFERROR(K83/I83,0)) | AD83: =IF(COUNT(C83:P83)=0,"",IFERROR(L83/I83,0)) | AE83: =IF(COUNT(C83:P83)=0,"",IFERROR(P83/I83,0)) | AF83: =IF(COUNT(C83:P83)=0,"",IFERROR(I83*Config!$C$7+J83*Config!$C$8+K83*Config!$C$9+L83*Config!$C$10+M83*Config!$C$11+N83*Config!$C$12+O83*Config!$C$13+P83*Config!$C$14,0)) | AG83: =IF(COUNT(C83:P83)=0,"",IFERROR(AF83/I83,0)) | AH83: =IF(COUNT(C83:P83)=0,"",IFERROR(AF83*(1-Config!$C$15-Config!$C$16-Config!$C$17),0)) | AI83: =IF(COUNT(C83:P83)=0,"",IFERROR(AH83-C83-Config!$C$18,0)) | AJ83: =IF(COUNT(C83:P83)=0,"",IFERROR(AH83/C83,0)) | AK83: =IF(COUNT(C83:P83)=0,"",IFERROR(AI83/G83,0)) | AL83: =IF(COUNT(C83:P83)=0,"",IFERROR(AK83/V83,0)) | AM83: =IF(COUNT(C83:P83)=0,"",IFERROR(AI83/I83,0)) | AN83: =IF(COUNT(C83:P83)=0,"",IFERROR(AH83/I83-AA83,0))
A84: =Config!$C$6+78 | B84: =INT((A84-Config!$C$6)/7)+1 | Q84: =IF(COUNT(C84:P84)=0,"",IFERROR(C84/D84*1000,0)) | R84: =IF(COUNT(C84:P84)=0,"",IFERROR(D84/E84,0)) | S84: =IF(COUNT(C84:P84)=0,"",IFERROR(F84/D84,0)) | T84: =IF(COUNT(C84:P84)=0,"",IFERROR(C84/F84,0)) | U84: =IF(COUNT(C84:P84)=0,"",IFERROR(G84/F84,0)) | V84: =IF(COUNT(C84:P84)=0,"",IFERROR(C84/G84,0)) | W84: =IF(COUNT(C84:P84)=0,"",IFERROR(G84/D84*1000,0)) | X84: =IF(COUNT(C84:P84)=0,"",IFERROR(H84/G84,0)) | Y84: =IF(COUNT(C84:P84)=0,"",IFERROR(I84/H84,0)) | Z84: =IF(COUNT(C84:P84)=0,"",IFERROR(I84/G84,0)) | AA84: =IF(COUNT(C84:P84)=0,"",IFERROR(C84/I84,0)) | AB84: =IF(COUNT(C84:P84)=0,"",IFERROR(J84/I84,0)) | AC84: =IF(COUNT(C84:P84)=0,"",IFERROR(K84/I84,0)) | AD84: =IF(COUNT(C84:P84)=0,"",IFERROR(L84/I84,0)) | AE84: =IF(COUNT(C84:P84)=0,"",IFERROR(P84/I84,0)) | AF84: =IF(COUNT(C84:P84)=0,"",IFERROR(I84*Config!$C$7+J84*Config!$C$8+K84*Config!$C$9+L84*Config!$C$10+M84*Config!$C$11+N84*Config!$C$12+O84*Config!$C$13+P84*Config!$C$14,0)) | AG84: =IF(COUNT(C84:P84)=0,"",IFERROR(AF84/I84,0)) | AH84: =IF(COUNT(C84:P84)=0,"",IFERROR(AF84*(1-Config!$C$15-Config!$C$16-Config!$C$17),0)) | AI84: =IF(COUNT(C84:P84)=0,"",IFERROR(AH84-C84-Config!$C$18,0)) | AJ84: =IF(COUNT(C84:P84)=0,"",IFERROR(AH84/C84,0)) | AK84: =IF(COUNT(C84:P84)=0,"",IFERROR(AI84/G84,0)) | AL84: =IF(COUNT(C84:P84)=0,"",IFERROR(AK84/V84,0)) | AM84: =IF(COUNT(C84:P84)=0,"",IFERROR(AI84/I84,0)) | AN84: =IF(COUNT(C84:P84)=0,"",IFERROR(AH84/I84-AA84,0))
A85: =Config!$C$6+79 | B85: =INT((A85-Config!$C$6)/7)+1 | Q85: =IF(COUNT(C85:P85)=0,"",IFERROR(C85/D85*1000,0)) | R85: =IF(COUNT(C85:P85)=0,"",IFERROR(D85/E85,0)) | S85: =IF(COUNT(C85:P85)=0,"",IFERROR(F85/D85,0)) | T85: =IF(COUNT(C85:P85)=0,"",IFERROR(C85/F85,0)) | U85: =IF(COUNT(C85:P85)=0,"",IFERROR(G85/F85,0)) | V85: =IF(COUNT(C85:P85)=0,"",IFERROR(C85/G85,0)) | W85: =IF(COUNT(C85:P85)=0,"",IFERROR(G85/D85*1000,0)) | X85: =IF(COUNT(C85:P85)=0,"",IFERROR(H85/G85,0)) | Y85: =IF(COUNT(C85:P85)=0,"",IFERROR(I85/H85,0)) | Z85: =IF(COUNT(C85:P85)=0,"",IFERROR(I85/G85,0)) | AA85: =IF(COUNT(C85:P85)=0,"",IFERROR(C85/I85,0)) | AB85: =IF(COUNT(C85:P85)=0,"",IFERROR(J85/I85,0)) | AC85: =IF(COUNT(C85:P85)=0,"",IFERROR(K85/I85,0)) | AD85: =IF(COUNT(C85:P85)=0,"",IFERROR(L85/I85,0)) | AE85: =IF(COUNT(C85:P85)=0,"",IFERROR(P85/I85,0)) | AF85: =IF(COUNT(C85:P85)=0,"",IFERROR(I85*Config!$C$7+J85*Config!$C$8+K85*Config!$C$9+L85*Config!$C$10+M85*Config!$C$11+N85*Config!$C$12+O85*Config!$C$13+P85*Config!$C$14,0)) | AG85: =IF(COUNT(C85:P85)=0,"",IFERROR(AF85/I85,0)) | AH85: =IF(COUNT(C85:P85)=0,"",IFERROR(AF85*(1-Config!$C$15-Config!$C$16-Config!$C$17),0)) | AI85: =IF(COUNT(C85:P85)=0,"",IFERROR(AH85-C85-Config!$C$18,0)) | AJ85: =IF(COUNT(C85:P85)=0,"",IFERROR(AH85/C85,0)) | AK85: =IF(COUNT(C85:P85)=0,"",IFERROR(AI85/G85,0)) | AL85: =IF(COUNT(C85:P85)=0,"",IFERROR(AK85/V85,0)) | AM85: =IF(COUNT(C85:P85)=0,"",IFERROR(AI85/I85,0)) | AN85: =IF(COUNT(C85:P85)=0,"",IFERROR(AH85/I85-AA85,0))
A86: =Config!$C$6+80 | B86: =INT((A86-Config!$C$6)/7)+1 | Q86: =IF(COUNT(C86:P86)=0,"",IFERROR(C86/D86*1000,0)) | R86: =IF(COUNT(C86:P86)=0,"",IFERROR(D86/E86,0)) | S86: =IF(COUNT(C86:P86)=0,"",IFERROR(F86/D86,0)) | T86: =IF(COUNT(C86:P86)=0,"",IFERROR(C86/F86,0)) | U86: =IF(COUNT(C86:P86)=0,"",IFERROR(G86/F86,0)) | V86: =IF(COUNT(C86:P86)=0,"",IFERROR(C86/G86,0)) | W86: =IF(COUNT(C86:P86)=0,"",IFERROR(G86/D86*1000,0)) | X86: =IF(COUNT(C86:P86)=0,"",IFERROR(H86/G86,0)) | Y86: =IF(COUNT(C86:P86)=0,"",IFERROR(I86/H86,0)) | Z86: =IF(COUNT(C86:P86)=0,"",IFERROR(I86/G86,0)) | AA86: =IF(COUNT(C86:P86)=0,"",IFERROR(C86/I86,0)) | AB86: =IF(COUNT(C86:P86)=0,"",IFERROR(J86/I86,0)) | AC86: =IF(COUNT(C86:P86)=0,"",IFERROR(K86/I86,0)) | AD86: =IF(COUNT(C86:P86)=0,"",IFERROR(L86/I86,0)) | AE86: =IF(COUNT(C86:P86)=0,"",IFERROR(P86/I86,0)) | AF86: =IF(COUNT(C86:P86)=0,"",IFERROR(I86*Config!$C$7+J86*Config!$C$8+K86*Config!$C$9+L86*Config!$C$10+M86*Config!$C$11+N86*Config!$C$12+O86*Config!$C$13+P86*Config!$C$14,0)) | AG86: =IF(COUNT(C86:P86)=0,"",IFERROR(AF86/I86,0)) | AH86: =IF(COUNT(C86:P86)=0,"",IFERROR(AF86*(1-Config!$C$15-Config!$C$16-Config!$C$17),0)) | AI86: =IF(COUNT(C86:P86)=0,"",IFERROR(AH86-C86-Config!$C$18,0)) | AJ86: =IF(COUNT(C86:P86)=0,"",IFERROR(AH86/C86,0)) | AK86: =IF(COUNT(C86:P86)=0,"",IFERROR(AI86/G86,0)) | AL86: =IF(COUNT(C86:P86)=0,"",IFERROR(AK86/V86,0)) | AM86: =IF(COUNT(C86:P86)=0,"",IFERROR(AI86/I86,0)) | AN86: =IF(COUNT(C86:P86)=0,"",IFERROR(AH86/I86-AA86,0))
A87: =Config!$C$6+81 | B87: =INT((A87-Config!$C$6)/7)+1 | Q87: =IF(COUNT(C87:P87)=0,"",IFERROR(C87/D87*1000,0)) | R87: =IF(COUNT(C87:P87)=0,"",IFERROR(D87/E87,0)) | S87: =IF(COUNT(C87:P87)=0,"",IFERROR(F87/D87,0)) | T87: =IF(COUNT(C87:P87)=0,"",IFERROR(C87/F87,0)) | U87: =IF(COUNT(C87:P87)=0,"",IFERROR(G87/F87,0)) | V87: =IF(COUNT(C87:P87)=0,"",IFERROR(C87/G87,0)) | W87: =IF(COUNT(C87:P87)=0,"",IFERROR(G87/D87*1000,0)) | X87: =IF(COUNT(C87:P87)=0,"",IFERROR(H87/G87,0)) | Y87: =IF(COUNT(C87:P87)=0,"",IFERROR(I87/H87,0)) | Z87: =IF(COUNT(C87:P87)=0,"",IFERROR(I87/G87,0)) | AA87: =IF(COUNT(C87:P87)=0,"",IFERROR(C87/I87,0)) | AB87: =IF(COUNT(C87:P87)=0,"",IFERROR(J87/I87,0)) | AC87: =IF(COUNT(C87:P87)=0,"",IFERROR(K87/I87,0)) | AD87: =IF(COUNT(C87:P87)=0,"",IFERROR(L87/I87,0)) | AE87: =IF(COUNT(C87:P87)=0,"",IFERROR(P87/I87,0)) | AF87: =IF(COUNT(C87:P87)=0,"",IFERROR(I87*Config!$C$7+J87*Config!$C$8+K87*Config!$C$9+L87*Config!$C$10+M87*Config!$C$11+N87*Config!$C$12+O87*Config!$C$13+P87*Config!$C$14,0)) | AG87: =IF(COUNT(C87:P87)=0,"",IFERROR(AF87/I87,0)) | AH87: =IF(COUNT(C87:P87)=0,"",IFERROR(AF87*(1-Config!$C$15-Config!$C$16-Config!$C$17),0)) | AI87: =IF(COUNT(C87:P87)=0,"",IFERROR(AH87-C87-Config!$C$18,0)) | AJ87: =IF(COUNT(C87:P87)=0,"",IFERROR(AH87/C87,0)) | AK87: =IF(COUNT(C87:P87)=0,"",IFERROR(AI87/G87,0)) | AL87: =IF(COUNT(C87:P87)=0,"",IFERROR(AK87/V87,0)) | AM87: =IF(COUNT(C87:P87)=0,"",IFERROR(AI87/I87,0)) | AN87: =IF(COUNT(C87:P87)=0,"",IFERROR(AH87/I87-AA87,0))
A88: =Config!$C$6+82 | B88: =INT((A88-Config!$C$6)/7)+1 | Q88: =IF(COUNT(C88:P88)=0,"",IFERROR(C88/D88*1000,0)) | R88: =IF(COUNT(C88:P88)=0,"",IFERROR(D88/E88,0)) | S88: =IF(COUNT(C88:P88)=0,"",IFERROR(F88/D88,0)) | T88: =IF(COUNT(C88:P88)=0,"",IFERROR(C88/F88,0)) | U88: =IF(COUNT(C88:P88)=0,"",IFERROR(G88/F88,0)) | V88: =IF(COUNT(C88:P88)=0,"",IFERROR(C88/G88,0)) | W88: =IF(COUNT(C88:P88)=0,"",IFERROR(G88/D88*1000,0)) | X88: =IF(COUNT(C88:P88)=0,"",IFERROR(H88/G88,0)) | Y88: =IF(COUNT(C88:P88)=0,"",IFERROR(I88/H88,0)) | Z88: =IF(COUNT(C88:P88)=0,"",IFERROR(I88/G88,0)) | AA88: =IF(COUNT(C88:P88)=0,"",IFERROR(C88/I88,0)) | AB88: =IF(COUNT(C88:P88)=0,"",IFERROR(J88/I88,0)) | AC88: =IF(COUNT(C88:P88)=0,"",IFERROR(K88/I88,0)) | AD88: =IF(COUNT(C88:P88)=0,"",IFERROR(L88/I88,0)) | AE88: =IF(COUNT(C88:P88)=0,"",IFERROR(P88/I88,0)) | AF88: =IF(COUNT(C88:P88)=0,"",IFERROR(I88*Config!$C$7+J88*Config!$C$8+K88*Config!$C$9+L88*Config!$C$10+M88*Config!$C$11+N88*Config!$C$12+O88*Config!$C$13+P88*Config!$C$14,0)) | AG88: =IF(COUNT(C88:P88)=0,"",IFERROR(AF88/I88,0)) | AH88: =IF(COUNT(C88:P88)=0,"",IFERROR(AF88*(1-Config!$C$15-Config!$C$16-Config!$C$17),0)) | AI88: =IF(COUNT(C88:P88)=0,"",IFERROR(AH88-C88-Config!$C$18,0)) | AJ88: =IF(COUNT(C88:P88)=0,"",IFERROR(AH88/C88,0)) | AK88: =IF(COUNT(C88:P88)=0,"",IFERROR(AI88/G88,0)) | AL88: =IF(COUNT(C88:P88)=0,"",IFERROR(AK88/V88,0)) | AM88: =IF(COUNT(C88:P88)=0,"",IFERROR(AI88/I88,0)) | AN88: =IF(COUNT(C88:P88)=0,"",IFERROR(AH88/I88-AA88,0))
A89: =Config!$C$6+83 | B89: =INT((A89-Config!$C$6)/7)+1 | Q89: =IF(COUNT(C89:P89)=0,"",IFERROR(C89/D89*1000,0)) | R89: =IF(COUNT(C89:P89)=0,"",IFERROR(D89/E89,0)) | S89: =IF(COUNT(C89:P89)=0,"",IFERROR(F89/D89,0)) | T89: =IF(COUNT(C89:P89)=0,"",IFERROR(C89/F89,0)) | U89: =IF(COUNT(C89:P89)=0,"",IFERROR(G89/F89,0)) | V89: =IF(COUNT(C89:P89)=0,"",IFERROR(C89/G89,0)) | W89: =IF(COUNT(C89:P89)=0,"",IFERROR(G89/D89*1000,0)) | X89: =IF(COUNT(C89:P89)=0,"",IFERROR(H89/G89,0)) | Y89: =IF(COUNT(C89:P89)=0,"",IFERROR(I89/H89,0)) | Z89: =IF(COUNT(C89:P89)=0,"",IFERROR(I89/G89,0)) | AA89: =IF(COUNT(C89:P89)=0,"",IFERROR(C89/I89,0)) | AB89: =IF(COUNT(C89:P89)=0,"",IFERROR(J89/I89,0)) | AC89: =IF(COUNT(C89:P89)=0,"",IFERROR(K89/I89,0)) | AD89: =IF(COUNT(C89:P89)=0,"",IFERROR(L89/I89,0)) | AE89: =IF(COUNT(C89:P89)=0,"",IFERROR(P89/I89,0)) | AF89: =IF(COUNT(C89:P89)=0,"",IFERROR(I89*Config!$C$7+J89*Config!$C$8+K89*Config!$C$9+L89*Config!$C$10+M89*Config!$C$11+N89*Config!$C$12+O89*Config!$C$13+P89*Config!$C$14,0)) | AG89: =IF(COUNT(C89:P89)=0,"",IFERROR(AF89/I89,0)) | AH89: =IF(COUNT(C89:P89)=0,"",IFERROR(AF89*(1-Config!$C$15-Config!$C$16-Config!$C$17),0)) | AI89: =IF(COUNT(C89:P89)=0,"",IFERROR(AH89-C89-Config!$C$18,0)) | AJ89: =IF(COUNT(C89:P89)=0,"",IFERROR(AH89/C89,0)) | AK89: =IF(COUNT(C89:P89)=0,"",IFERROR(AI89/G89,0)) | AL89: =IF(COUNT(C89:P89)=0,"",IFERROR(AK89/V89,0)) | AM89: =IF(COUNT(C89:P89)=0,"",IFERROR(AI89/I89,0)) | AN89: =IF(COUNT(C89:P89)=0,"",IFERROR(AH89/I89-AA89,0))
A90: =Config!$C$6+84 | B90: =INT((A90-Config!$C$6)/7)+1 | Q90: =IF(COUNT(C90:P90)=0,"",IFERROR(C90/D90*1000,0)) | R90: =IF(COUNT(C90:P90)=0,"",IFERROR(D90/E90,0)) | S90: =IF(COUNT(C90:P90)=0,"",IFERROR(F90/D90,0)) | T90: =IF(COUNT(C90:P90)=0,"",IFERROR(C90/F90,0)) | U90: =IF(COUNT(C90:P90)=0,"",IFERROR(G90/F90,0)) | V90: =IF(COUNT(C90:P90)=0,"",IFERROR(C90/G90,0)) | W90: =IF(COUNT(C90:P90)=0,"",IFERROR(G90/D90*1000,0)) | X90: =IF(COUNT(C90:P90)=0,"",IFERROR(H90/G90,0)) | Y90: =IF(COUNT(C90:P90)=0,"",IFERROR(I90/H90,0)) | Z90: =IF(COUNT(C90:P90)=0,"",IFERROR(I90/G90,0)) | AA90: =IF(COUNT(C90:P90)=0,"",IFERROR(C90/I90,0)) | AB90: =IF(COUNT(C90:P90)=0,"",IFERROR(J90/I90,0)) | AC90: =IF(COUNT(C90:P90)=0,"",IFERROR(K90/I90,0)) | AD90: =IF(COUNT(C90:P90)=0,"",IFERROR(L90/I90,0)) | AE90: =IF(COUNT(C90:P90)=0,"",IFERROR(P90/I90,0)) | AF90: =IF(COUNT(C90:P90)=0,"",IFERROR(I90*Config!$C$7+J90*Config!$C$8+K90*Config!$C$9+L90*Config!$C$10+M90*Config!$C$11+N90*Config!$C$12+O90*Config!$C$13+P90*Config!$C$14,0)) | AG90: =IF(COUNT(C90:P90)=0,"",IFERROR(AF90/I90,0)) | AH90: =IF(COUNT(C90:P90)=0,"",IFERROR(AF90*(1-Config!$C$15-Config!$C$16-Config!$C$17),0)) | AI90: =IF(COUNT(C90:P90)=0,"",IFERROR(AH90-C90-Config!$C$18,0)) | AJ90: =IF(COUNT(C90:P90)=0,"",IFERROR(AH90/C90,0)) | AK90: =IF(COUNT(C90:P90)=0,"",IFERROR(AI90/G90,0)) | AL90: =IF(COUNT(C90:P90)=0,"",IFERROR(AK90/V90,0)) | AM90: =IF(COUNT(C90:P90)=0,"",IFERROR(AI90/I90,0)) | AN90: =IF(COUNT(C90:P90)=0,"",IFERROR(AH90/I90-AA90,0))
A91: =Config!$C$6+85 | B91: =INT((A91-Config!$C$6)/7)+1 | Q91: =IF(COUNT(C91:P91)=0,"",IFERROR(C91/D91*1000,0)) | R91: =IF(COUNT(C91:P91)=0,"",IFERROR(D91/E91,0)) | S91: =IF(COUNT(C91:P91)=0,"",IFERROR(F91/D91,0)) | T91: =IF(COUNT(C91:P91)=0,"",IFERROR(C91/F91,0)) | U91: =IF(COUNT(C91:P91)=0,"",IFERROR(G91/F91,0)) | V91: =IF(COUNT(C91:P91)=0,"",IFERROR(C91/G91,0)) | W91: =IF(COUNT(C91:P91)=0,"",IFERROR(G91/D91*1000,0)) | X91: =IF(COUNT(C91:P91)=0,"",IFERROR(H91/G91,0)) | Y91: =IF(COUNT(C91:P91)=0,"",IFERROR(I91/H91,0)) | Z91: =IF(COUNT(C91:P91)=0,"",IFERROR(I91/G91,0)) | AA91: =IF(COUNT(C91:P91)=0,"",IFERROR(C91/I91,0)) | AB91: =IF(COUNT(C91:P91)=0,"",IFERROR(J91/I91,0)) | AC91: =IF(COUNT(C91:P91)=0,"",IFERROR(K91/I91,0)) | AD91: =IF(COUNT(C91:P91)=0,"",IFERROR(L91/I91,0)) | AE91: =IF(COUNT(C91:P91)=0,"",IFERROR(P91/I91,0)) | AF91: =IF(COUNT(C91:P91)=0,"",IFERROR(I91*Config!$C$7+J91*Config!$C$8+K91*Config!$C$9+L91*Config!$C$10+M91*Config!$C$11+N91*Config!$C$12+O91*Config!$C$13+P91*Config!$C$14,0)) | AG91: =IF(COUNT(C91:P91)=0,"",IFERROR(AF91/I91,0)) | AH91: =IF(COUNT(C91:P91)=0,"",IFERROR(AF91*(1-Config!$C$15-Config!$C$16-Config!$C$17),0)) | AI91: =IF(COUNT(C91:P91)=0,"",IFERROR(AH91-C91-Config!$C$18,0)) | AJ91: =IF(COUNT(C91:P91)=0,"",IFERROR(AH91/C91,0)) | AK91: =IF(COUNT(C91:P91)=0,"",IFERROR(AI91/G91,0)) | AL91: =IF(COUNT(C91:P91)=0,"",IFERROR(AK91/V91,0)) | AM91: =IF(COUNT(C91:P91)=0,"",IFERROR(AI91/I91,0)) | AN91: =IF(COUNT(C91:P91)=0,"",IFERROR(AH91/I91-AA91,0))
A92: =Config!$C$6+86 | B92: =INT((A92-Config!$C$6)/7)+1 | Q92: =IF(COUNT(C92:P92)=0,"",IFERROR(C92/D92*1000,0)) | R92: =IF(COUNT(C92:P92)=0,"",IFERROR(D92/E92,0)) | S92: =IF(COUNT(C92:P92)=0,"",IFERROR(F92/D92,0)) | T92: =IF(COUNT(C92:P92)=0,"",IFERROR(C92/F92,0)) | U92: =IF(COUNT(C92:P92)=0,"",IFERROR(G92/F92,0)) | V92: =IF(COUNT(C92:P92)=0,"",IFERROR(C92/G92,0)) | W92: =IF(COUNT(C92:P92)=0,"",IFERROR(G92/D92*1000,0)) | X92: =IF(COUNT(C92:P92)=0,"",IFERROR(H92/G92,0)) | Y92: =IF(COUNT(C92:P92)=0,"",IFERROR(I92/H92,0)) | Z92: =IF(COUNT(C92:P92)=0,"",IFERROR(I92/G92,0)) | AA92: =IF(COUNT(C92:P92)=0,"",IFERROR(C92/I92,0)) | AB92: =IF(COUNT(C92:P92)=0,"",IFERROR(J92/I92,0)) | AC92: =IF(COUNT(C92:P92)=0,"",IFERROR(K92/I92,0)) | AD92: =IF(COUNT(C92:P92)=0,"",IFERROR(L92/I92,0)) | AE92: =IF(COUNT(C92:P92)=0,"",IFERROR(P92/I92,0)) | AF92: =IF(COUNT(C92:P92)=0,"",IFERROR(I92*Config!$C$7+J92*Config!$C$8+K92*Config!$C$9+L92*Config!$C$10+M92*Config!$C$11+N92*Config!$C$12+O92*Config!$C$13+P92*Config!$C$14,0)) | AG92: =IF(COUNT(C92:P92)=0,"",IFERROR(AF92/I92,0)) | AH92: =IF(COUNT(C92:P92)=0,"",IFERROR(AF92*(1-Config!$C$15-Config!$C$16-Config!$C$17),0)) | AI92: =IF(COUNT(C92:P92)=0,"",IFERROR(AH92-C92-Config!$C$18,0)) | AJ92: =IF(COUNT(C92:P92)=0,"",IFERROR(AH92/C92,0)) | AK92: =IF(COUNT(C92:P92)=0,"",IFERROR(AI92/G92,0)) | AL92: =IF(COUNT(C92:P92)=0,"",IFERROR(AK92/V92,0)) | AM92: =IF(COUNT(C92:P92)=0,"",IFERROR(AI92/I92,0)) | AN92: =IF(COUNT(C92:P92)=0,"",IFERROR(AH92/I92-AA92,0))
A93: =Config!$C$6+87 | B93: =INT((A93-Config!$C$6)/7)+1 | Q93: =IF(COUNT(C93:P93)=0,"",IFERROR(C93/D93*1000,0)) | R93: =IF(COUNT(C93:P93)=0,"",IFERROR(D93/E93,0)) | S93: =IF(COUNT(C93:P93)=0,"",IFERROR(F93/D93,0)) | T93: =IF(COUNT(C93:P93)=0,"",IFERROR(C93/F93,0)) | U93: =IF(COUNT(C93:P93)=0,"",IFERROR(G93/F93,0)) | V93: =IF(COUNT(C93:P93)=0,"",IFERROR(C93/G93,0)) | W93: =IF(COUNT(C93:P93)=0,"",IFERROR(G93/D93*1000,0)) | X93: =IF(COUNT(C93:P93)=0,"",IFERROR(H93/G93,0)) | Y93: =IF(COUNT(C93:P93)=0,"",IFERROR(I93/H93,0)) | Z93: =IF(COUNT(C93:P93)=0,"",IFERROR(I93/G93,0)) | AA93: =IF(COUNT(C93:P93)=0,"",IFERROR(C93/I93,0)) | AB93: =IF(COUNT(C93:P93)=0,"",IFERROR(J93/I93,0)) | AC93: =IF(COUNT(C93:P93)=0,"",IFERROR(K93/I93,0)) | AD93: =IF(COUNT(C93:P93)=0,"",IFERROR(L93/I93,0)) | AE93: =IF(COUNT(C93:P93)=0,"",IFERROR(P93/I93,0)) | AF93: =IF(COUNT(C93:P93)=0,"",IFERROR(I93*Config!$C$7+J93*Config!$C$8+K93*Config!$C$9+L93*Config!$C$10+M93*Config!$C$11+N93*Config!$C$12+O93*Config!$C$13+P93*Config!$C$14,0)) | AG93: =IF(COUNT(C93:P93)=0,"",IFERROR(AF93/I93,0)) | AH93: =IF(COUNT(C93:P93)=0,"",IFERROR(AF93*(1-Config!$C$15-Config!$C$16-Config!$C$17),0)) | AI93: =IF(COUNT(C93:P93)=0,"",IFERROR(AH93-C93-Config!$C$18,0)) | AJ93: =IF(COUNT(C93:P93)=0,"",IFERROR(AH93/C93,0)) | AK93: =IF(COUNT(C93:P93)=0,"",IFERROR(AI93/G93,0)) | AL93: =IF(COUNT(C93:P93)=0,"",IFERROR(AK93/V93,0)) | AM93: =IF(COUNT(C93:P93)=0,"",IFERROR(AI93/I93,0)) | AN93: =IF(COUNT(C93:P93)=0,"",IFERROR(AH93/I93-AA93,0))
A94: =Config!$C$6+88 | B94: =INT((A94-Config!$C$6)/7)+1 | Q94: =IF(COUNT(C94:P94)=0,"",IFERROR(C94/D94*1000,0)) | R94: =IF(COUNT(C94:P94)=0,"",IFERROR(D94/E94,0)) | S94: =IF(COUNT(C94:P94)=0,"",IFERROR(F94/D94,0)) | T94: =IF(COUNT(C94:P94)=0,"",IFERROR(C94/F94,0)) | U94: =IF(COUNT(C94:P94)=0,"",IFERROR(G94/F94,0)) | V94: =IF(COUNT(C94:P94)=0,"",IFERROR(C94/G94,0)) | W94: =IF(COUNT(C94:P94)=0,"",IFERROR(G94/D94*1000,0)) | X94: =IF(COUNT(C94:P94)=0,"",IFERROR(H94/G94,0)) | Y94: =IF(COUNT(C94:P94)=0,"",IFERROR(I94/H94,0)) | Z94: =IF(COUNT(C94:P94)=0,"",IFERROR(I94/G94,0)) | AA94: =IF(COUNT(C94:P94)=0,"",IFERROR(C94/I94,0)) | AB94: =IF(COUNT(C94:P94)=0,"",IFERROR(J94/I94,0)) | AC94: =IF(COUNT(C94:P94)=0,"",IFERROR(K94/I94,0)) | AD94: =IF(COUNT(C94:P94)=0,"",IFERROR(L94/I94,0)) | AE94: =IF(COUNT(C94:P94)=0,"",IFERROR(P94/I94,0)) | AF94: =IF(COUNT(C94:P94)=0,"",IFERROR(I94*Config!$C$7+J94*Config!$C$8+K94*Config!$C$9+L94*Config!$C$10+M94*Config!$C$11+N94*Config!$C$12+O94*Config!$C$13+P94*Config!$C$14,0)) | AG94: =IF(COUNT(C94:P94)=0,"",IFERROR(AF94/I94,0)) | AH94: =IF(COUNT(C94:P94)=0,"",IFERROR(AF94*(1-Config!$C$15-Config!$C$16-Config!$C$17),0)) | AI94: =IF(COUNT(C94:P94)=0,"",IFERROR(AH94-C94-Config!$C$18,0)) | AJ94: =IF(COUNT(C94:P94)=0,"",IFERROR(AH94/C94,0)) | AK94: =IF(COUNT(C94:P94)=0,"",IFERROR(AI94/G94,0)) | AL94: =IF(COUNT(C94:P94)=0,"",IFERROR(AK94/V94,0)) | AM94: =IF(COUNT(C94:P94)=0,"",IFERROR(AI94/I94,0)) | AN94: =IF(COUNT(C94:P94)=0,"",IFERROR(AH94/I94-AA94,0))
A95: =Config!$C$6+89 | B95: =INT((A95-Config!$C$6)/7)+1 | Q95: =IF(COUNT(C95:P95)=0,"",IFERROR(C95/D95*1000,0)) | R95: =IF(COUNT(C95:P95)=0,"",IFERROR(D95/E95,0)) | S95: =IF(COUNT(C95:P95)=0,"",IFERROR(F95/D95,0)) | T95: =IF(COUNT(C95:P95)=0,"",IFERROR(C95/F95,0)) | U95: =IF(COUNT(C95:P95)=0,"",IFERROR(G95/F95,0)) | V95: =IF(COUNT(C95:P95)=0,"",IFERROR(C95/G95,0)) | W95: =IF(COUNT(C95:P95)=0,"",IFERROR(G95/D95*1000,0)) | X95: =IF(COUNT(C95:P95)=0,"",IFERROR(H95/G95,0)) | Y95: =IF(COUNT(C95:P95)=0,"",IFERROR(I95/H95,0)) | Z95: =IF(COUNT(C95:P95)=0,"",IFERROR(I95/G95,0)) | AA95: =IF(COUNT(C95:P95)=0,"",IFERROR(C95/I95,0)) | AB95: =IF(COUNT(C95:P95)=0,"",IFERROR(J95/I95,0)) | AC95: =IF(COUNT(C95:P95)=0,"",IFERROR(K95/I95,0)) | AD95: =IF(COUNT(C95:P95)=0,"",IFERROR(L95/I95,0)) | AE95: =IF(COUNT(C95:P95)=0,"",IFERROR(P95/I95,0)) | AF95: =IF(COUNT(C95:P95)=0,"",IFERROR(I95*Config!$C$7+J95*Config!$C$8+K95*Config!$C$9+L95*Config!$C$10+M95*Config!$C$11+N95*Config!$C$12+O95*Config!$C$13+P95*Config!$C$14,0)) | AG95: =IF(COUNT(C95:P95)=0,"",IFERROR(AF95/I95,0)) | AH95: =IF(COUNT(C95:P95)=0,"",IFERROR(AF95*(1-Config!$C$15-Config!$C$16-Config!$C$17),0)) | AI95: =IF(COUNT(C95:P95)=0,"",IFERROR(AH95-C95-Config!$C$18,0)) | AJ95: =IF(COUNT(C95:P95)=0,"",IFERROR(AH95/C95,0)) | AK95: =IF(COUNT(C95:P95)=0,"",IFERROR(AI95/G95,0)) | AL95: =IF(COUNT(C95:P95)=0,"",IFERROR(AK95/V95,0)) | AM95: =IF(COUNT(C95:P95)=0,"",IFERROR(AI95/I95,0)) | AN95: =IF(COUNT(C95:P95)=0,"",IFERROR(AH95/I95-AA95,0))
A96: =Config!$C$6+90 | B96: =INT((A96-Config!$C$6)/7)+1 | Q96: =IF(COUNT(C96:P96)=0,"",IFERROR(C96/D96*1000,0)) | R96: =IF(COUNT(C96:P96)=0,"",IFERROR(D96/E96,0)) | S96: =IF(COUNT(C96:P96)=0,"",IFERROR(F96/D96,0)) | T96: =IF(COUNT(C96:P96)=0,"",IFERROR(C96/F96,0)) | U96: =IF(COUNT(C96:P96)=0,"",IFERROR(G96/F96,0)) | V96: =IF(COUNT(C96:P96)=0,"",IFERROR(C96/G96,0)) | W96: =IF(COUNT(C96:P96)=0,"",IFERROR(G96/D96*1000,0)) | X96: =IF(COUNT(C96:P96)=0,"",IFERROR(H96/G96,0)) | Y96: =IF(COUNT(C96:P96)=0,"",IFERROR(I96/H96,0)) | Z96: =IF(COUNT(C96:P96)=0,"",IFERROR(I96/G96,0)) | AA96: =IF(COUNT(C96:P96)=0,"",IFERROR(C96/I96,0)) | AB96: =IF(COUNT(C96:P96)=0,"",IFERROR(J96/I96,0)) | AC96: =IF(COUNT(C96:P96)=0,"",IFERROR(K96/I96,0)) | AD96: =IF(COUNT(C96:P96)=0,"",IFERROR(L96/I96,0)) | AE96: =IF(COUNT(C96:P96)=0,"",IFERROR(P96/I96,0)) | AF96: =IF(COUNT(C96:P96)=0,"",IFERROR(I96*Config!$C$7+J96*Config!$C$8+K96*Config!$C$9+L96*Config!$C$10+M96*Config!$C$11+N96*Config!$C$12+O96*Config!$C$13+P96*Config!$C$14,0)) | AG96: =IF(COUNT(C96:P96)=0,"",IFERROR(AF96/I96,0)) | AH96: =IF(COUNT(C96:P96)=0,"",IFERROR(AF96*(1-Config!$C$15-Config!$C$16-Config!$C$17),0)) | AI96: =IF(COUNT(C96:P96)=0,"",IFERROR(AH96-C96-Config!$C$18,0)) | AJ96: =IF(COUNT(C96:P96)=0,"",IFERROR(AH96/C96,0)) | AK96: =IF(COUNT(C96:P96)=0,"",IFERROR(AI96/G96,0)) | AL96: =IF(COUNT(C96:P96)=0,"",IFERROR(AK96/V96,0)) | AM96: =IF(COUNT(C96:P96)=0,"",IFERROR(AI96/I96,0)) | AN96: =IF(COUNT(C96:P96)=0,"",IFERROR(AH96/I96-AA96,0))
A97: =Config!$C$6+91 | B97: =INT((A97-Config!$C$6)/7)+1 | Q97: =IF(COUNT(C97:P97)=0,"",IFERROR(C97/D97*1000,0)) | R97: =IF(COUNT(C97:P97)=0,"",IFERROR(D97/E97,0)) | S97: =IF(COUNT(C97:P97)=0,"",IFERROR(F97/D97,0)) | T97: =IF(COUNT(C97:P97)=0,"",IFERROR(C97/F97,0)) | U97: =IF(COUNT(C97:P97)=0,"",IFERROR(G97/F97,0)) | V97: =IF(COUNT(C97:P97)=0,"",IFERROR(C97/G97,0)) | W97: =IF(COUNT(C97:P97)=0,"",IFERROR(G97/D97*1000,0)) | X97: =IF(COUNT(C97:P97)=0,"",IFERROR(H97/G97,0)) | Y97: =IF(COUNT(C97:P97)=0,"",IFERROR(I97/H97,0)) | Z97: =IF(COUNT(C97:P97)=0,"",IFERROR(I97/G97,0)) | AA97: =IF(COUNT(C97:P97)=0,"",IFERROR(C97/I97,0)) | AB97: =IF(COUNT(C97:P97)=0,"",IFERROR(J97/I97,0)) | AC97: =IF(COUNT(C97:P97)=0,"",IFERROR(K97/I97,0)) | AD97: =IF(COUNT(C97:P97)=0,"",IFERROR(L97/I97,0)) | AE97: =IF(COUNT(C97:P97)=0,"",IFERROR(P97/I97,0)) | AF97: =IF(COUNT(C97:P97)=0,"",IFERROR(I97*Config!$C$7+J97*Config!$C$8+K97*Config!$C$9+L97*Config!$C$10+M97*Config!$C$11+N97*Config!$C$12+O97*Config!$C$13+P97*Config!$C$14,0)) | AG97: =IF(COUNT(C97:P97)=0,"",IFERROR(AF97/I97,0)) | AH97: =IF(COUNT(C97:P97)=0,"",IFERROR(AF97*(1-Config!$C$15-Config!$C$16-Config!$C$17),0)) | AI97: =IF(COUNT(C97:P97)=0,"",IFERROR(AH97-C97-Config!$C$18,0)) | AJ97: =IF(COUNT(C97:P97)=0,"",IFERROR(AH97/C97,0)) | AK97: =IF(COUNT(C97:P97)=0,"",IFERROR(AI97/G97,0)) | AL97: =IF(COUNT(C97:P97)=0,"",IFERROR(AK97/V97,0)) | AM97: =IF(COUNT(C97:P97)=0,"",IFERROR(AI97/I97,0)) | AN97: =IF(COUNT(C97:P97)=0,"",IFERROR(AH97/I97-AA97,0))
A98: =Config!$C$6+92 | B98: =INT((A98-Config!$C$6)/7)+1 | Q98: =IF(COUNT(C98:P98)=0,"",IFERROR(C98/D98*1000,0)) | R98: =IF(COUNT(C98:P98)=0,"",IFERROR(D98/E98,0)) | S98: =IF(COUNT(C98:P98)=0,"",IFERROR(F98/D98,0)) | T98: =IF(COUNT(C98:P98)=0,"",IFERROR(C98/F98,0)) | U98: =IF(COUNT(C98:P98)=0,"",IFERROR(G98/F98,0)) | V98: =IF(COUNT(C98:P98)=0,"",IFERROR(C98/G98,0)) | W98: =IF(COUNT(C98:P98)=0,"",IFERROR(G98/D98*1000,0)) | X98: =IF(COUNT(C98:P98)=0,"",IFERROR(H98/G98,0)) | Y98: =IF(COUNT(C98:P98)=0,"",IFERROR(I98/H98,0)) | Z98: =IF(COUNT(C98:P98)=0,"",IFERROR(I98/G98,0)) | AA98: =IF(COUNT(C98:P98)=0,"",IFERROR(C98/I98,0)) | AB98: =IF(COUNT(C98:P98)=0,"",IFERROR(J98/I98,0)) | AC98: =IF(COUNT(C98:P98)=0,"",IFERROR(K98/I98,0)) | AD98: =IF(COUNT(C98:P98)=0,"",IFERROR(L98/I98,0)) | AE98: =IF(COUNT(C98:P98)=0,"",IFERROR(P98/I98,0)) | AF98: =IF(COUNT(C98:P98)=0,"",IFERROR(I98*Config!$C$7+J98*Config!$C$8+K98*Config!$C$9+L98*Config!$C$10+M98*Config!$C$11+N98*Config!$C$12+O98*Config!$C$13+P98*Config!$C$14,0)) | AG98: =IF(COUNT(C98:P98)=0,"",IFERROR(AF98/I98,0)) | AH98: =IF(COUNT(C98:P98)=0,"",IFERROR(AF98*(1-Config!$C$15-Config!$C$16-Config!$C$17),0)) | AI98: =IF(COUNT(C98:P98)=0,"",IFERROR(AH98-C98-Config!$C$18,0)) | AJ98: =IF(COUNT(C98:P98)=0,"",IFERROR(AH98/C98,0)) | AK98: =IF(COUNT(C98:P98)=0,"",IFERROR(AI98/G98,0)) | AL98: =IF(COUNT(C98:P98)=0,"",IFERROR(AK98/V98,0)) | AM98: =IF(COUNT(C98:P98)=0,"",IFERROR(AI98/I98,0)) | AN98: =IF(COUNT(C98:P98)=0,"",IFERROR(AH98/I98-AA98,0))
A99: =Config!$C$6+93 | B99: =INT((A99-Config!$C$6)/7)+1 | Q99: =IF(COUNT(C99:P99)=0,"",IFERROR(C99/D99*1000,0)) | R99: =IF(COUNT(C99:P99)=0,"",IFERROR(D99/E99,0)) | S99: =IF(COUNT(C99:P99)=0,"",IFERROR(F99/D99,0)) | T99: =IF(COUNT(C99:P99)=0,"",IFERROR(C99/F99,0)) | U99: =IF(COUNT(C99:P99)=0,"",IFERROR(G99/F99,0)) | V99: =IF(COUNT(C99:P99)=0,"",IFERROR(C99/G99,0)) | W99: =IF(COUNT(C99:P99)=0,"",IFERROR(G99/D99*1000,0)) | X99: =IF(COUNT(C99:P99)=0,"",IFERROR(H99/G99,0)) | Y99: =IF(COUNT(C99:P99)=0,"",IFERROR(I99/H99,0)) | Z99: =IF(COUNT(C99:P99)=0,"",IFERROR(I99/G99,0)) | AA99: =IF(COUNT(C99:P99)=0,"",IFERROR(C99/I99,0)) | AB99: =IF(COUNT(C99:P99)=0,"",IFERROR(J99/I99,0)) | AC99: =IF(COUNT(C99:P99)=0,"",IFERROR(K99/I99,0)) | AD99: =IF(COUNT(C99:P99)=0,"",IFERROR(L99/I99,0)) | AE99: =IF(COUNT(C99:P99)=0,"",IFERROR(P99/I99,0)) | AF99: =IF(COUNT(C99:P99)=0,"",IFERROR(I99*Config!$C$7+J99*Config!$C$8+K99*Config!$C$9+L99*Config!$C$10+M99*Config!$C$11+N99*Config!$C$12+O99*Config!$C$13+P99*Config!$C$14,0)) | AG99: =IF(COUNT(C99:P99)=0,"",IFERROR(AF99/I99,0)) | AH99: =IF(COUNT(C99:P99)=0,"",IFERROR(AF99*(1-Config!$C$15-Config!$C$16-Config!$C$17),0)) | AI99: =IF(COUNT(C99:P99)=0,"",IFERROR(AH99-C99-Config!$C$18,0)) | AJ99: =IF(COUNT(C99:P99)=0,"",IFERROR(AH99/C99,0)) | AK99: =IF(COUNT(C99:P99)=0,"",IFERROR(AI99/G99,0)) | AL99: =IF(COUNT(C99:P99)=0,"",IFERROR(AK99/V99,0)) | AM99: =IF(COUNT(C99:P99)=0,"",IFERROR(AI99/I99,0)) | AN99: =IF(COUNT(C99:P99)=0,"",IFERROR(AH99/I99-AA99,0))
A100: =Config!$C$6+94 | B100: =INT((A100-Config!$C$6)/7)+1 | Q100: =IF(COUNT(C100:P100)=0,"",IFERROR(C100/D100*1000,0)) | R100: =IF(COUNT(C100:P100)=0,"",IFERROR(D100/E100,0)) | S100: =IF(COUNT(C100:P100)=0,"",IFERROR(F100/D100,0)) | T100: =IF(COUNT(C100:P100)=0,"",IFERROR(C100/F100,0)) | U100: =IF(COUNT(C100:P100)=0,"",IFERROR(G100/F100,0)) | V100: =IF(COUNT(C100:P100)=0,"",IFERROR(C100/G100,0)) | W100: =IF(COUNT(C100:P100)=0,"",IFERROR(G100/D100*1000,0)) | X100: =IF(COUNT(C100:P100)=0,"",IFERROR(H100/G100,0)) | Y100: =IF(COUNT(C100:P100)=0,"",IFERROR(I100/H100,0)) | Z100: =IF(COUNT(C100:P100)=0,"",IFERROR(I100/G100,0)) | AA100: =IF(COUNT(C100:P100)=0,"",IFERROR(C100/I100,0)) | AB100: =IF(COUNT(C100:P100)=0,"",IFERROR(J100/I100,0)) | AC100: =IF(COUNT(C100:P100)=0,"",IFERROR(K100/I100,0)) | AD100: =IF(COUNT(C100:P100)=0,"",IFERROR(L100/I100,0)) | AE100: =IF(COUNT(C100:P100)=0,"",IFERROR(P100/I100,0)) | AF100: =IF(COUNT(C100:P100)=0,"",IFERROR(I100*Config!$C$7+J100*Config!$C$8+K100*Config!$C$9+L100*Config!$C$10+M100*Config!$C$11+N100*Config!$C$12+O100*Config!$C$13+P100*Config!$C$14,0)) | AG100: =IF(COUNT(C100:P100)=0,"",IFERROR(AF100/I100,0)) | AH100: =IF(COUNT(C100:P100)=0,"",IFERROR(AF100*(1-Config!$C$15-Config!$C$16-Config!$C$17),0)) | AI100: =IF(COUNT(C100:P100)=0,"",IFERROR(AH100-C100-Config!$C$18,0)) | AJ100: =IF(COUNT(C100:P100)=0,"",IFERROR(AH100/C100,0)) | AK100: =IF(COUNT(C100:P100)=0,"",IFERROR(AI100/G100,0)) | AL100: =IF(COUNT(C100:P100)=0,"",IFERROR(AK100/V100,0)) | AM100: =IF(COUNT(C100:P100)=0,"",IFERROR(AI100/I100,0)) | AN100: =IF(COUNT(C100:P100)=0,"",IFERROR(AH100/I100-AA100,0))
A101: =Config!$C$6+95 | B101: =INT((A101-Config!$C$6)/7)+1 | Q101: =IF(COUNT(C101:P101)=0,"",IFERROR(C101/D101*1000,0)) | R101: =IF(COUNT(C101:P101)=0,"",IFERROR(D101/E101,0)) | S101: =IF(COUNT(C101:P101)=0,"",IFERROR(F101/D101,0)) | T101: =IF(COUNT(C101:P101)=0,"",IFERROR(C101/F101,0)) | U101: =IF(COUNT(C101:P101)=0,"",IFERROR(G101/F101,0)) | V101: =IF(COUNT(C101:P101)=0,"",IFERROR(C101/G101,0)) | W101: =IF(COUNT(C101:P101)=0,"",IFERROR(G101/D101*1000,0)) | X101: =IF(COUNT(C101:P101)=0,"",IFERROR(H101/G101,0)) | Y101: =IF(COUNT(C101:P101)=0,"",IFERROR(I101/H101,0)) | Z101: =IF(COUNT(C101:P101)=0,"",IFERROR(I101/G101,0)) | AA101: =IF(COUNT(C101:P101)=0,"",IFERROR(C101/I101,0)) | AB101: =IF(COUNT(C101:P101)=0,"",IFERROR(J101/I101,0)) | AC101: =IF(COUNT(C101:P101)=0,"",IFERROR(K101/I101,0)) | AD101: =IF(COUNT(C101:P101)=0,"",IFERROR(L101/I101,0)) | AE101: =IF(COUNT(C101:P101)=0,"",IFERROR(P101/I101,0)) | AF101: =IF(COUNT(C101:P101)=0,"",IFERROR(I101*Config!$C$7+J101*Config!$C$8+K101*Config!$C$9+L101*Config!$C$10+M101*Config!$C$11+N101*Config!$C$12+O101*Config!$C$13+P101*Config!$C$14,0)) | AG101: =IF(COUNT(C101:P101)=0,"",IFERROR(AF101/I101,0)) | AH101: =IF(COUNT(C101:P101)=0,"",IFERROR(AF101*(1-Config!$C$15-Config!$C$16-Config!$C$17),0)) | AI101: =IF(COUNT(C101:P101)=0,"",IFERROR(AH101-C101-Config!$C$18,0)) | AJ101: =IF(COUNT(C101:P101)=0,"",IFERROR(AH101/C101,0)) | AK101: =IF(COUNT(C101:P101)=0,"",IFERROR(AI101/G101,0)) | AL101: =IF(COUNT(C101:P101)=0,"",IFERROR(AK101/V101,0)) | AM101: =IF(COUNT(C101:P101)=0,"",IFERROR(AI101/I101,0)) | AN101: =IF(COUNT(C101:P101)=0,"",IFERROR(AH101/I101-AA101,0))
...

Sheet Semanal
A1: © Jesús Tassarolo · TooAudience · youtube.com/@JesusTassaroloSinFiltro · uso personal; no redistribuir modificado
A2: Semanal: el comparativo semana a semana, calculado solo desde Diario
A3: Promedio, mediana, mejor y peor de tus semanas con datos. Abajo, el bloque «contra tu promedio»: cada semana contra la mediana de tus 4 semanas anteriores, con la tolerancia de Config. Ese es el umbral: tu promedio, no un número de mercado.
B4: Lunes de la semana | C4: =Config!$C$6+0 | D4: =Config!$C$6+7 | E4: =Config!$C$6+14 | F4: =Config!$C$6+21 | G4: =Config!$C$6+28 | H4: =Config!$C$6+35 | I4: =Config!$C$6+42 | J4: =Config!$C$6+49 | K4: =Config!$C$6+56 | L4: =Config!$C$6+63 | M4: =Config!$C$6+70 | N4: =Config!$C$6+77 | O4: =Config!$C$6+84 | P4: =Config!$C$6+91 | Q4: =Config!$C$6+98 | R4: =Config!$C$6+105 | S4: =Config!$C$6+112 | T4: =Config!$C$6+119 | U4: =Config!$C$6+126 | V4: =Config!$C$6+133 | W4: =Config!$C$6+140 | X4: =Config!$C$6+147 | Y4: =Config!$C$6+154 | Z4: =Config!$C$6+161 | AA4: =Config!$C$6+168 | AB4: =Config!$C$6+175
A5: Categoría | B5: Métrica | C5: 1 | D5: 2 | E5: 3 | F5: 4 | G5: 5 | H5: 6 | I5: 7 | J5: 8 | K5: 9 | L5: 10 | M5: 11 | N5: 12 | O5: 13 | P5: 14 | Q5: 15 | R5: 16 | S5: 17 | T5: 18 | U5: 19 | V5: 20 | W5: 21 | X5: 22 | Y5: 23 | Z5: 24 | AA5: 25 | AB5: 26 | AC5: Promedio | AD5: Mediana | AE5: Mejor | AF5: Peor
A6: Semana con datos (1 = sí) | C6: =IF(SUMIFS(Diario!$C$6:$C$371,Diario!$B$6:$B$371,C$5)+SUMIFS(Diario!$I$6:$I$371,Diario!$B$6:$B$371,C$5)>0,1,0) | D6: =IF(SUMIFS(Diario!$C$6:$C$371,Diario!$B$6:$B$371,D$5)+SUMIFS(Diario!$I$6:$I$371,Diario!$B$6:$B$371,D$5)>0,1,0) | E6: =IF(SUMIFS(Diario!$C$6:$C$371,Diario!$B$6:$B$371,E$5)+SUMIFS(Diario!$I$6:$I$371,Diario!$B$6:$B$371,E$5)>0,1,0) | F6: =IF(SUMIFS(Diario!$C$6:$C$371,Diario!$B$6:$B$371,F$5)+SUMIFS(Diario!$I$6:$I$371,Diario!$B$6:$B$371,F$5)>0,1,0) | G6: =IF(SUMIFS(Diario!$C$6:$C$371,Diario!$B$6:$B$371,G$5)+SUMIFS(Diario!$I$6:$I$371,Diario!$B$6:$B$371,G$5)>0,1,0) | H6: =IF(SUMIFS(Diario!$C$6:$C$371,Diario!$B$6:$B$371,H$5)+SUMIFS(Diario!$I$6:$I$371,Diario!$B$6:$B$371,H$5)>0,1,0) | I6: =IF(SUMIFS(Diario!$C$6:$C$371,Diario!$B$6:$B$371,I$5)+SUMIFS(Diario!$I$6:$I$371,Diario!$B$6:$B$371,I$5)>0,1,0) | J6: =IF(SUMIFS(Diario!$C$6:$C$371,Diario!$B$6:$B$371,J$5)+SUMIFS(Diario!$I$6:$I$371,Diario!$B$6:$B$371,J$5)>0,1,0) | ... AB6: =IF(SUMIFS(Diario!$C$6:$C$371,Diario!$B$6:$B$371,AB$5)+SUMIFS(Diario!$I$6:$I$371,Diario!$B$6:$B$371,AB$5)>0,1,0)
A7: Número de semana si tiene datos | C7: =IF(C6=1,C$5,0) | D7: =IF(D6=1,D$5,0) | E7: =IF(E6=1,E$5,0) | F7: =IF(F6=1,F$5,0) | G7: =IF(G6=1,G$5,0) | H7: =IF(H6=1,H$5,0) | I7: =IF(I6=1,I$5,0) | J7: =IF(J6=1,J$5,0) | ... AB7: =IF(AB6=1,AB$5,0)
A9: 1. Anuncios
A10: Anuncios | B10: Inversión en publicidad (USD) | C10: =IF(C6=0,"",SUMIFS(Diario!$C$6:$C$371,Diario!$B$6:$B$371,C$5)) | D10: =IF(D6=0,"",SUMIFS(Diario!$C$6:$C$371,Diario!$B$6:$B$371,D$5)) | E10: =IF(E6=0,"",SUMIFS(Diario!$C$6:$C$371,Diario!$B$6:$B$371,E$5)) | F10: =IF(F6=0,"",SUMIFS(Diario!$C$6:$C$371,Diario!$B$6:$B$371,F$5)) | G10: =IF(G6=0,"",SUMIFS(Diario!$C$6:$C$371,Diario!$B$6:$B$371,G$5)) | H10: =IF(H6=0,"",SUMIFS(Diario!$C$6:$C$371,Diario!$B$6:$B$371,H$5)) | I10: =IF(I6=0,"",SUMIFS(Diario!$C$6:$C$371,Diario!$B$6:$B$371,I$5)) | J10: =IF(J6=0,"",SUMIFS(Diario!$C$6:$C$371,Diario!$B$6:$B$371,J$5)) | ... AB10: =IF(AB6=0,"",SUMIFS(Diario!$C$6:$C$371,Diario!$B$6:$B$371,AB$5)) | AC10: =IFERROR(AVERAGE(C10:AB10),"") | AD10: =IFERROR(MEDIAN(C10:AB10),"") | AE10: =IFERROR(MAX(C10:AB10),"") | AF10: =IFERROR(MIN(C10:AB10),"")
A11: Anuncios | B11: Impresiones | C11: =IF(C6=0,"",SUMIFS(Diario!$D$6:$D$371,Diario!$B$6:$B$371,C$5)) | D11: =IF(D6=0,"",SUMIFS(Diario!$D$6:$D$371,Diario!$B$6:$B$371,D$5)) | E11: =IF(E6=0,"",SUMIFS(Diario!$D$6:$D$371,Diario!$B$6:$B$371,E$5)) | F11: =IF(F6=0,"",SUMIFS(Diario!$D$6:$D$371,Diario!$B$6:$B$371,F$5)) | G11: =IF(G6=0,"",SUMIFS(Diario!$D$6:$D$371,Diario!$B$6:$B$371,G$5)) | H11: =IF(H6=0,"",SUMIFS(Diario!$D$6:$D$371,Diario!$B$6:$B$371,H$5)) | I11: =IF(I6=0,"",SUMIFS(Diario!$D$6:$D$371,Diario!$B$6:$B$371,I$5)) | J11: =IF(J6=0,"",SUMIFS(Diario!$D$6:$D$371,Diario!$B$6:$B$371,J$5)) | ... AB11: =IF(AB6=0,"",SUMIFS(Diario!$D$6:$D$371,Diario!$B$6:$B$371,AB$5)) | AC11: =IFERROR(AVERAGE(C11:AB11),"") | AD11: =IFERROR(MEDIAN(C11:AB11),"") | AE11: =IFERROR(MAX(C11:AB11),"") | AF11: =IFERROR(MIN(C11:AB11),"")
A12: Anuncios | B12: Alcance (personas únicas) | C12: =IF(C6=0,"",SUMIFS(Diario!$E$6:$E$371,Diario!$B$6:$B$371,C$5)) | D12: =IF(D6=0,"",SUMIFS(Diario!$E$6:$E$371,Diario!$B$6:$B$371,D$5)) | E12: =IF(E6=0,"",SUMIFS(Diario!$E$6:$E$371,Diario!$B$6:$B$371,E$5)) | F12: =IF(F6=0,"",SUMIFS(Diario!$E$6:$E$371,Diario!$B$6:$B$371,F$5)) | G12: =IF(G6=0,"",SUMIFS(Diario!$E$6:$E$371,Diario!$B$6:$B$371,G$5)) | H12: =IF(H6=0,"",SUMIFS(Diario!$E$6:$E$371,Diario!$B$6:$B$371,H$5)) | I12: =IF(I6=0,"",SUMIFS(Diario!$E$6:$E$371,Diario!$B$6:$B$371,I$5)) | J12: =IF(J6=0,"",SUMIFS(Diario!$E$6:$E$371,Diario!$B$6:$B$371,J$5)) | ... AB12: =IF(AB6=0,"",SUMIFS(Diario!$E$6:$E$371,Diario!$B$6:$B$371,AB$5)) | AC12: =IFERROR(AVERAGE(C12:AB12),"") | AD12: =IFERROR(MEDIAN(C12:AB12),"") | AE12: =IFERROR(MAX(C12:AB12),"") | AF12: =IFERROR(MIN(C12:AB12),"")
A13: Anuncios | B13: Clics en el enlace | C13: =IF(C6=0,"",SUMIFS(Diario!$F$6:$F$371,Diario!$B$6:$B$371,C$5)) | D13: =IF(D6=0,"",SUMIFS(Diario!$F$6:$F$371,Diario!$B$6:$B$371,D$5)) | E13: =IF(E6=0,"",SUMIFS(Diario!$F$6:$F$371,Diario!$B$6:$B$371,E$5)) | F13: =IF(F6=0,"",SUMIFS(Diario!$F$6:$F$371,Diario!$B$6:$B$371,F$5)) | G13: =IF(G6=0,"",SUMIFS(Diario!$F$6:$F$371,Diario!$B$6:$B$371,G$5)) | H13: =IF(H6=0,"",SUMIFS(Diario!$F$6:$F$371,Diario!$B$6:$B$371,H$5)) | I13: =IF(I6=0,"",SUMIFS(Diario!$F$6:$F$371,Diario!$B$6:$B$371,I$5)) | J13: =IF(J6=0,"",SUMIFS(Diario!$F$6:$F$371,Diario!$B$6:$B$371,J$5)) | ... AB13: =IF(AB6=0,"",SUMIFS(Diario!$F$6:$F$371,Diario!$B$6:$B$371,AB$5)) | AC13: =IFERROR(AVERAGE(C13:AB13),"") | AD13: =IFERROR(MEDIAN(C13:AB13),"") | AE13: =IFERROR(MAX(C13:AB13),"") | AF13: =IFERROR(MIN(C13:AB13),"")
A14: Anuncios | B14: Visitas a la página | C14: =IF(C6=0,"",SUMIFS(Diario!$G$6:$G$371,Diario!$B$6:$B$371,C$5)) | D14: =IF(D6=0,"",SUMIFS(Diario!$G$6:$G$371,Diario!$B$6:$B$371,D$5)) | E14: =IF(E6=0,"",SUMIFS(Diario!$G$6:$G$371,Diario!$B$6:$B$371,E$5)) | F14: =IF(F6=0,"",SUMIFS(Diario!$G$6:$G$371,Diario!$B$6:$B$371,F$5)) | G14: =IF(G6=0,"",SUMIFS(Diario!$G$6:$G$371,Diario!$B$6:$B$371,G$5)) | H14: =IF(H6=0,"",SUMIFS(Diario!$G$6:$G$371,Diario!$B$6:$B$371,H$5)) | I14: =IF(I6=0,"",SUMIFS(Diario!$G$6:$G$371,Diario!$B$6:$B$371,I$5)) | J14: =IF(J6=0,"",SUMIFS(Diario!$G$6:$G$371,Diario!$B$6:$B$371,J$5)) | ... AB14: =IF(AB6=0,"",SUMIFS(Diario!$G$6:$G$371,Diario!$B$6:$B$371,AB$5)) | AC14: =IFERROR(AVERAGE(C14:AB14),"") | AD14: =IFERROR(MEDIAN(C14:AB14),"") | AE14: =IFERROR(MAX(C14:AB14),"") | AF14: =IFERROR(MIN(C14:AB14),"")
A15: Anuncios | B15: CPM | C15: =IF(C6=0,"",IFERROR(C10/C11*1000,0)) | D15: =IF(D6=0,"",IFERROR(D10/D11*1000,0)) | E15: =IF(E6=0,"",IFERROR(E10/E11*1000,0)) | F15: =IF(F6=0,"",IFERROR(F10/F11*1000,0)) | G15: =IF(G6=0,"",IFERROR(G10/G11*1000,0)) | H15: =IF(H6=0,"",IFERROR(H10/H11*1000,0)) | I15: =IF(I6=0,"",IFERROR(I10/I11*1000,0)) | J15: =IF(J6=0,"",IFERROR(J10/J11*1000,0)) | ... AB15: =IF(AB6=0,"",IFERROR(AB10/AB11*1000,0)) | AC15: =IFERROR(AVERAGE(C15:AB15),"") | AD15: =IFERROR(MEDIAN(C15:AB15),"") | AE15: =IFERROR(MIN(C15:AB15),"") | AF15: =IFERROR(MAX(C15:AB15),"")
A16: Anuncios | B16: Frecuencia | C16: =IF(C6=0,"",IFERROR(C11/C12,0)) | D16: =IF(D6=0,"",IFERROR(D11/D12,0)) | E16: =IF(E6=0,"",IFERROR(E11/E12,0)) | F16: =IF(F6=0,"",IFERROR(F11/F12,0)) | G16: =IF(G6=0,"",IFERROR(G11/G12,0)) | H16: =IF(H6=0,"",IFERROR(H11/H12,0)) | I16: =IF(I6=0,"",IFERROR(I11/I12,0)) | J16: =IF(J6=0,"",IFERROR(J11/J12,0)) | ... AB16: =IF(AB6=0,"",IFERROR(AB11/AB12,0)) | AC16: =IFERROR(AVERAGE(C16:AB16),"") | AD16: =IFERROR(MEDIAN(C16:AB16),"") | AE16: =IFERROR(MIN(C16:AB16),"") | AF16: =IFERROR(MAX(C16:AB16),"")
A17: Anuncios | B17: CTR al enlace | C17: =IF(C6=0,"",IFERROR(C13/C11,0)) | D17: =IF(D6=0,"",IFERROR(D13/D11,0)) | E17: =IF(E6=0,"",IFERROR(E13/E11,0)) | F17: =IF(F6=0,"",IFERROR(F13/F11,0)) | G17: =IF(G6=0,"",IFERROR(G13/G11,0)) | H17: =IF(H6=0,"",IFERROR(H13/H11,0)) | I17: =IF(I6=0,"",IFERROR(I13/I11,0)) | J17: =IF(J6=0,"",IFERROR(J13/J11,0)) | ... AB17: =IF(AB6=0,"",IFERROR(AB13/AB11,0)) | AC17: =IFERROR(AVERAGE(C17:AB17),"") | AD17: =IFERROR(MEDIAN(C17:AB17),"") | AE17: =IFERROR(MAX(C17:AB17),"") | AF17: =IFERROR(MIN(C17:AB17),"")
A18: Anuncios | B18: CPC (por clic en el enlace) | C18: =IF(C6=0,"",IFERROR(C10/C13,0)) | D18: =IF(D6=0,"",IFERROR(D10/D13,0)) | E18: =IF(E6=0,"",IFERROR(E10/E13,0)) | F18: =IF(F6=0,"",IFERROR(F10/F13,0)) | G18: =IF(G6=0,"",IFERROR(G10/G13,0)) | H18: =IF(H6=0,"",IFERROR(H10/H13,0)) | I18: =IF(I6=0,"",IFERROR(I10/I13,0)) | J18: =IF(J6=0,"",IFERROR(J10/J13,0)) | ... AB18: =IF(AB6=0,"",IFERROR(AB10/AB13,0)) | AC18: =IFERROR(AVERAGE(C18:AB18),"") | AD18: =IFERROR(MEDIAN(C18:AB18),"") | AE18: =IFERROR(MIN(C18:AB18),"") | AF18: =IFERROR(MAX(C18:AB18),"")
A19: Anuncios | B19: % clic → visita | C19: =IF(C6=0,"",IFERROR(C14/C13,0)) | D19: =IF(D6=0,"",IFERROR(D14/D13,0)) | E19: =IF(E6=0,"",IFERROR(E14/E13,0)) | F19: =IF(F6=0,"",IFERROR(F14/F13,0)) | G19: =IF(G6=0,"",IFERROR(G14/G13,0)) | H19: =IF(H6=0,"",IFERROR(H14/H13,0)) | I19: =IF(I6=0,"",IFERROR(I14/I13,0)) | J19: =IF(J6=0,"",IFERROR(J14/J13,0)) | ... AB19: =IF(AB6=0,"",IFERROR(AB14/AB13,0)) | AC19: =IFERROR(AVERAGE(C19:AB19),"") | AD19: =IFERROR(MEDIAN(C19:AB19),"") | AE19: =IFERROR(MAX(C19:AB19),"") | AF19: =IFERROR(MIN(C19:AB19),"")
A20: Anuncios | B20: Costo por visita | C20: =IF(C6=0,"",IFERROR(C10/C14,0)) | D20: =IF(D6=0,"",IFERROR(D10/D14,0)) | E20: =IF(E6=0,"",IFERROR(E10/E14,0)) | F20: =IF(F6=0,"",IFERROR(F10/F14,0)) | G20: =IF(G6=0,"",IFERROR(G10/G14,0)) | H20: =IF(H6=0,"",IFERROR(H10/H14,0)) | I20: =IF(I6=0,"",IFERROR(I10/I14,0)) | J20: =IF(J6=0,"",IFERROR(J10/J14,0)) | ... AB20: =IF(AB6=0,"",IFERROR(AB10/AB14,0)) | AC20: =IFERROR(AVERAGE(C20:AB20),"") | AD20: =IFERROR(MEDIAN(C20:AB20),"") | AE20: =IFERROR(MIN(C20:AB20),"") | AF20: =IFERROR(MAX(C20:AB20),"")
A21: Anuncios | B21: Visitas por cada 1.000 impresiones | C21: =IF(C6=0,"",IFERROR(C14/C11*1000,0)) | D21: =IF(D6=0,"",IFERROR(D14/D11*1000,0)) | E21: =IF(E6=0,"",IFERROR(E14/E11*1000,0)) | F21: =IF(F6=0,"",IFERROR(F14/F11*1000,0)) | G21: =IF(G6=0,"",IFERROR(G14/G11*1000,0)) | H21: =IF(H6=0,"",IFERROR(H14/H11*1000,0)) | I21: =IF(I6=0,"",IFERROR(I14/I11*1000,0)) | J21: =IF(J6=0,"",IFERROR(J14/J11*1000,0)) | ... AB21: =IF(AB6=0,"",IFERROR(AB14/AB11*1000,0)) | AC21: =IFERROR(AVERAGE(C21:AB21),"") | AD21: =IFERROR(MEDIAN(C21:AB21),"") | AE21: =IFERROR(MAX(C21:AB21),"") | AF21: =IFERROR(MIN(C21:AB21),"")
A23: 2. Página de ventas y compra
A24: Página de ventas y compra | B24: Inician el checkout | C24: =IF(C6=0,"",SUMIFS(Diario!$H$6:$H$371,Diario!$B$6:$B$371,C$5)) | D24: =IF(D6=0,"",SUMIFS(Diario!$H$6:$H$371,Diario!$B$6:$B$371,D$5)) | E24: =IF(E6=0,"",SUMIFS(Diario!$H$6:$H$371,Diario!$B$6:$B$371,E$5)) | F24: =IF(F6=0,"",SUMIFS(Diario!$H$6:$H$371,Diario!$B$6:$B$371,F$5)) | G24: =IF(G6=0,"",SUMIFS(Diario!$H$6:$H$371,Diario!$B$6:$B$371,G$5)) | H24: =IF(H6=0,"",SUMIFS(Diario!$H$6:$H$371,Diario!$B$6:$B$371,H$5)) | I24: =IF(I6=0,"",SUMIFS(Diario!$H$6:$H$371,Diario!$B$6:$B$371,I$5)) | J24: =IF(J6=0,"",SUMIFS(Diario!$H$6:$H$371,Diario!$B$6:$B$371,J$5)) | ... AB24: =IF(AB6=0,"",SUMIFS(Diario!$H$6:$H$371,Diario!$B$6:$B$371,AB$5)) | AC24: =IFERROR(AVERAGE(C24:AB24),"") | AD24: =IFERROR(MEDIAN(C24:AB24),"") | AE24: =IFERROR(MAX(C24:AB24),"") | AF24: =IFERROR(MIN(C24:AB24),"")
A25: Página de ventas y compra | B25: Compran el producto principal | C25: =IF(C6=0,"",SUMIFS(Diario!$I$6:$I$371,Diario!$B$6:$B$371,C$5)) | D25: =IF(D6=0,"",SUMIFS(Diario!$I$6:$I$371,Diario!$B$6:$B$371,D$5)) | E25: =IF(E6=0,"",SUMIFS(Diario!$I$6:$I$371,Diario!$B$6:$B$371,E$5)) | F25: =IF(F6=0,"",SUMIFS(Diario!$I$6:$I$371,Diario!$B$6:$B$371,F$5)) | G25: =IF(G6=0,"",SUMIFS(Diario!$I$6:$I$371,Diario!$B$6:$B$371,G$5)) | H25: =IF(H6=0,"",SUMIFS(Diario!$I$6:$I$371,Diario!$B$6:$B$371,H$5)) | I25: =IF(I6=0,"",SUMIFS(Diario!$I$6:$I$371,Diario!$B$6:$B$371,I$5)) | J25: =IF(J6=0,"",SUMIFS(Diario!$I$6:$I$371,Diario!$B$6:$B$371,J$5)) | ... AB25: =IF(AB6=0,"",SUMIFS(Diario!$I$6:$I$371,Diario!$B$6:$B$371,AB$5)) | AC25: =IFERROR(AVERAGE(C25:AB25),"") | AD25: =IFERROR(MEDIAN(C25:AB25),"") | AE25: =IFERROR(MAX(C25:AB25),"") | AF25: =IFERROR(MIN(C25:AB25),"")
A26: Página de ventas y compra | B26: % visita → checkout | C26: =IF(C6=0,"",IFERROR(C24/C14,0)) | D26: =IF(D6=0,"",IFERROR(D24/D14,0)) | E26: =IF(E6=0,"",IFERROR(E24/E14,0)) | F26: =IF(F6=0,"",IFERROR(F24/F14,0)) | G26: =IF(G6=0,"",IFERROR(G24/G14,0)) | H26: =IF(H6=0,"",IFERROR(H24/H14,0)) | I26: =IF(I6=0,"",IFERROR(I24/I14,0)) | J26: =IF(J6=0,"",IFERROR(J24/J14,0)) | ... AB26: =IF(AB6=0,"",IFERROR(AB24/AB14,0)) | AC26: =IFERROR(AVERAGE(C26:AB26),"") | AD26: =IFERROR(MEDIAN(C26:AB26),"") | AE26: =IFERROR(MAX(C26:AB26),"") | AF26: =IFERROR(MIN(C26:AB26),"")
A27: Página de ventas y compra | B27: % checkout → compra | C27: =IF(C6=0,"",IFERROR(C25/C24,0)) | D27: =IF(D6=0,"",IFERROR(D25/D24,0)) | E27: =IF(E6=0,"",IFERROR(E25/E24,0)) | F27: =IF(F6=0,"",IFERROR(F25/F24,0)) | G27: =IF(G6=0,"",IFERROR(G25/G24,0)) | H27: =IF(H6=0,"",IFERROR(H25/H24,0)) | I27: =IF(I6=0,"",IFERROR(I25/I24,0)) | J27: =IF(J6=0,"",IFERROR(J25/J24,0)) | ... AB27: =IF(AB6=0,"",IFERROR(AB25/AB24,0)) | AC27: =IFERROR(AVERAGE(C27:AB27),"") | AD27: =IFERROR(MEDIAN(C27:AB27),"") | AE27: =IFERROR(MAX(C27:AB27),"") | AF27: =IFERROR(MIN(C27:AB27),"")
A28: Página de ventas y compra | B28: % visita → compra | C28: =IF(C6=0,"",IFERROR(C25/C14,0)) | D28: =IF(D6=0,"",IFERROR(D25/D14,0)) | E28: =IF(E6=0,"",IFERROR(E25/E14,0)) | F28: =IF(F6=0,"",IFERROR(F25/F14,0)) | G28: =IF(G6=0,"",IFERROR(G25/G14,0)) | H28: =IF(H6=0,"",IFERROR(H25/H14,0)) | I28: =IF(I6=0,"",IFERROR(I25/I14,0)) | J28: =IF(J6=0,"",IFERROR(J25/J14,0)) | ... AB28: =IF(AB6=0,"",IFERROR(AB25/AB14,0)) | AC28: =IFERROR(AVERAGE(C28:AB28),"") | AD28: =IFERROR(MEDIAN(C28:AB28),"") | AE28: =IFERROR(MAX(C28:AB28),"") | AF28: =IFERROR(MIN(C28:AB28),"")
A29: Página de ventas y compra | B29: CPA (costo por comprador) | C29: =IF(C6=0,"",IFERROR(C10/C25,0)) | D29: =IF(D6=0,"",IFERROR(D10/D25,0)) | E29: =IF(E6=0,"",IFERROR(E10/E25,0)) | F29: =IF(F6=0,"",IFERROR(F10/F25,0)) | G29: =IF(G6=0,"",IFERROR(G10/G25,0)) | H29: =IF(H6=0,"",IFERROR(H10/H25,0)) | I29: =IF(I6=0,"",IFERROR(I10/I25,0)) | J29: =IF(J6=0,"",IFERROR(J10/J25,0)) | ... AB29: =IF(AB6=0,"",IFERROR(AB10/AB25,0)) | AC29: =IFERROR(AVERAGE(C29:AB29),"") | AD29: =IFERROR(MEDIAN(C29:AB29),"") | AE29: =IFERROR(MIN(C29:AB29),"") | AF29: =IFERROR(MAX(C29:AB29),"")
A31: 3. Escalera
A32: Escalera | B32: Toman el bump 1 | C32: =IF(C6=0,"",SUMIFS(Diario!$J$6:$J$371,Diario!$B$6:$B$371,C$5)) | D32: =IF(D6=0,"",SUMIFS(Diario!$J$6:$J$371,Diario!$B$6:$B$371,D$5)) | E32: =IF(E6=0,"",SUMIFS(Diario!$J$6:$J$371,Diario!$B$6:$B$371,E$5)) | F32: =IF(F6=0,"",SUMIFS(Diario!$J$6:$J$371,Diario!$B$6:$B$371,F$5)) | G32: =IF(G6=0,"",SUMIFS(Diario!$J$6:$J$371,Diario!$B$6:$B$371,G$5)) | H32: =IF(H6=0,"",SUMIFS(Diario!$J$6:$J$371,Diario!$B$6:$B$371,H$5)) | I32: =IF(I6=0,"",SUMIFS(Diario!$J$6:$J$371,Diario!$B$6:$B$371,I$5)) | J32: =IF(J6=0,"",SUMIFS(Diario!$J$6:$J$371,Diario!$B$6:$B$371,J$5)) | ... AB32: =IF(AB6=0,"",SUMIFS(Diario!$J$6:$J$371,Diario!$B$6:$B$371,AB$5)) | AC32: =IFERROR(AVERAGE(C32:AB32),"") | AD32: =IFERROR(MEDIAN(C32:AB32),"") | AE32: =IFERROR(MAX(C32:AB32),"") | AF32: =IFERROR(MIN(C32:AB32),"")
A33: Escalera | B33: Toman el bump 2 | C33: =IF(C6=0,"",SUMIFS(Diario!$K$6:$K$371,Diario!$B$6:$B$371,C$5)) | D33: =IF(D6=0,"",SUMIFS(Diario!$K$6:$K$371,Diario!$B$6:$B$371,D$5)) | E33: =IF(E6=0,"",SUMIFS(Diario!$K$6:$K$371,Diario!$B$6:$B$371,E$5)) | F33: =IF(F6=0,"",SUMIFS(Diario!$K$6:$K$371,Diario!$B$6:$B$371,F$5)) | G33: =IF(G6=0,"",SUMIFS(Diario!$K$6:$K$371,Diario!$B$6:$B$371,G$5)) | H33: =IF(H6=0,"",SUMIFS(Diario!$K$6:$K$371,Diario!$B$6:$B$371,H$5)) | I33: =IF(I6=0,"",SUMIFS(Diario!$K$6:$K$371,Diario!$B$6:$B$371,I$5)) | J33: =IF(J6=0,"",SUMIFS(Diario!$K$6:$K$371,Diario!$B$6:$B$371,J$5)) | ... AB33: =IF(AB6=0,"",SUMIFS(Diario!$K$6:$K$371,Diario!$B$6:$B$371,AB$5)) | AC33: =IFERROR(AVERAGE(C33:AB33),"") | AD33: =IFERROR(MEDIAN(C33:AB33),"") | AE33: =IFERROR(MAX(C33:AB33),"") | AF33: =IFERROR(MIN(C33:AB33),"")
A34: Escalera | B34: Toman la OTO 1 | C34: =IF(C6=0,"",SUMIFS(Diario!$L$6:$L$371,Diario!$B$6:$B$371,C$5)) | D34: =IF(D6=0,"",SUMIFS(Diario!$L$6:$L$371,Diario!$B$6:$B$371,D$5)) | E34: =IF(E6=0,"",SUMIFS(Diario!$L$6:$L$371,Diario!$B$6:$B$371,E$5)) | F34: =IF(F6=0,"",SUMIFS(Diario!$L$6:$L$371,Diario!$B$6:$B$371,F$5)) | G34: =IF(G6=0,"",SUMIFS(Diario!$L$6:$L$371,Diario!$B$6:$B$371,G$5)) | H34: =IF(H6=0,"",SUMIFS(Diario!$L$6:$L$371,Diario!$B$6:$B$371,H$5)) | I34: =IF(I6=0,"",SUMIFS(Diario!$L$6:$L$371,Diario!$B$6:$B$371,I$5)) | J34: =IF(J6=0,"",SUMIFS(Diario!$L$6:$L$371,Diario!$B$6:$B$371,J$5)) | ... AB34: =IF(AB6=0,"",SUMIFS(Diario!$L$6:$L$371,Diario!$B$6:$B$371,AB$5)) | AC34: =IFERROR(AVERAGE(C34:AB34),"") | AD34: =IFERROR(MEDIAN(C34:AB34),"") | AE34: =IFERROR(MAX(C34:AB34),"") | AF34: =IFERROR(MIN(C34:AB34),"")
A35: Escalera | B35: Toman la OTO 2 | C35: =IF(C6=0,"",SUMIFS(Diario!$M$6:$M$371,Diario!$B$6:$B$371,C$5)) | D35: =IF(D6=0,"",SUMIFS(Diario!$M$6:$M$371,Diario!$B$6:$B$371,D$5)) | E35: =IF(E6=0,"",SUMIFS(Diario!$M$6:$M$371,Diario!$B$6:$B$371,E$5)) | F35: =IF(F6=0,"",SUMIFS(Diario!$M$6:$M$371,Diario!$B$6:$B$371,F$5)) | G35: =IF(G6=0,"",SUMIFS(Diario!$M$6:$M$371,Diario!$B$6:$B$371,G$5)) | H35: =IF(H6=0,"",SUMIFS(Diario!$M$6:$M$371,Diario!$B$6:$B$371,H$5)) | I35: =IF(I6=0,"",SUMIFS(Diario!$M$6:$M$371,Diario!$B$6:$B$371,I$5)) | J35: =IF(J6=0,"",SUMIFS(Diario!$M$6:$M$371,Diario!$B$6:$B$371,J$5)) | ... AB35: =IF(AB6=0,"",SUMIFS(Diario!$M$6:$M$371,Diario!$B$6:$B$371,AB$5)) | AC35: =IFERROR(AVERAGE(C35:AB35),"") | AD35: =IFERROR(MEDIAN(C35:AB35),"") | AE35: =IFERROR(MAX(C35:AB35),"") | AF35: =IFERROR(MIN(C35:AB35),"")
A36: Escalera | B36: Toman la OTO 3 | C36: =IF(C6=0,"",SUMIFS(Diario!$N$6:$N$371,Diario!$B$6:$B$371,C$5)) | D36: =IF(D6=0,"",SUMIFS(Diario!$N$6:$N$371,Diario!$B$6:$B$371,D$5)) | E36: =IF(E6=0,"",SUMIFS(Diario!$N$6:$N$371,Diario!$B$6:$B$371,E$5)) | F36: =IF(F6=0,"",SUMIFS(Diario!$N$6:$N$371,Diario!$B$6:$B$371,F$5)) | G36: =IF(G6=0,"",SUMIFS(Diario!$N$6:$N$371,Diario!$B$6:$B$371,G$5)) | H36: =IF(H6=0,"",SUMIFS(Diario!$N$6:$N$371,Diario!$B$6:$B$371,H$5)) | I36: =IF(I6=0,"",SUMIFS(Diario!$N$6:$N$371,Diario!$B$6:$B$371,I$5)) | J36: =IF(J6=0,"",SUMIFS(Diario!$N$6:$N$371,Diario!$B$6:$B$371,J$5)) | ... AB36: =IF(AB6=0,"",SUMIFS(Diario!$N$6:$N$371,Diario!$B$6:$B$371,AB$5)) | AC36: =IFERROR(AVERAGE(C36:AB36),"") | AD36: =IFERROR(MEDIAN(C36:AB36),"") | AE36: =IFERROR(MAX(C36:AB36),"") | AF36: =IFERROR(MIN(C36:AB36),"")
A37: Escalera | B37: Toman la OTO 4 | C37: =IF(C6=0,"",SUMIFS(Diario!$O$6:$O$371,Diario!$B$6:$B$371,C$5)) | D37: =IF(D6=0,"",SUMIFS(Diario!$O$6:$O$371,Diario!$B$6:$B$371,D$5)) | E37: =IF(E6=0,"",SUMIFS(Diario!$O$6:$O$371,Diario!$B$6:$B$371,E$5)) | F37: =IF(F6=0,"",SUMIFS(Diario!$O$6:$O$371,Diario!$B$6:$B$371,F$5)) | G37: =IF(G6=0,"",SUMIFS(Diario!$O$6:$O$371,Diario!$B$6:$B$371,G$5)) | H37: =IF(H6=0,"",SUMIFS(Diario!$O$6:$O$371,Diario!$B$6:$B$371,H$5)) | I37: =IF(I6=0,"",SUMIFS(Diario!$O$6:$O$371,Diario!$B$6:$B$371,I$5)) | J37: =IF(J6=0,"",SUMIFS(Diario!$O$6:$O$371,Diario!$B$6:$B$371,J$5)) | ... AB37: =IF(AB6=0,"",SUMIFS(Diario!$O$6:$O$371,Diario!$B$6:$B$371,AB$5)) | AC37: =IFERROR(AVERAGE(C37:AB37),"") | AD37: =IFERROR(MEDIAN(C37:AB37),"") | AE37: =IFERROR(MAX(C37:AB37),"") | AF37: =IFERROR(MIN(C37:AB37),"")
A38: Escalera | B38: Ascienden al programa | C38: =IF(C6=0,"",SUMIFS(Diario!$P$6:$P$371,Diario!$B$6:$B$371,C$5)) | D38: =IF(D6=0,"",SUMIFS(Diario!$P$6:$P$371,Diario!$B$6:$B$371,D$5)) | E38: =IF(E6=0,"",SUMIFS(Diario!$P$6:$P$371,Diario!$B$6:$B$371,E$5)) | F38: =IF(F6=0,"",SUMIFS(Diario!$P$6:$P$371,Diario!$B$6:$B$371,F$5)) | G38: =IF(G6=0,"",SUMIFS(Diario!$P$6:$P$371,Diario!$B$6:$B$371,G$5)) | H38: =IF(H6=0,"",SUMIFS(Diario!$P$6:$P$371,Diario!$B$6:$B$371,H$5)) | I38: =IF(I6=0,"",SUMIFS(Diario!$P$6:$P$371,Diario!$B$6:$B$371,I$5)) | J38: =IF(J6=0,"",SUMIFS(Diario!$P$6:$P$371,Diario!$B$6:$B$371,J$5)) | ... AB38: =IF(AB6=0,"",SUMIFS(Diario!$P$6:$P$371,Diario!$B$6:$B$371,AB$5)) | AC38: =IFERROR(AVERAGE(C38:AB38),"") | AD38: =IFERROR(MEDIAN(C38:AB38),"") | AE38: =IFERROR(MAX(C38:AB38),"") | AF38: =IFERROR(MIN(C38:AB38),"")
A39: Escalera | B39: % toman el bump 1 | C39: =IF(C6=0,"",IFERROR(C32/C25,0)) | D39: =IF(D6=0,"",IFERROR(D32/D25,0)) | E39: =IF(E6=0,"",IFERROR(E32/E25,0)) | F39: =IF(F6=0,"",IFERROR(F32/F25,0)) | G39: =IF(G6=0,"",IFERROR(G32/G25,0)) | H39: =IF(H6=0,"",IFERROR(H32/H25,0)) | I39: =IF(I6=0,"",IFERROR(I32/I25,0)) | J39: =IF(J6=0,"",IFERROR(J32/J25,0)) | ... AB39: =IF(AB6=0,"",IFERROR(AB32/AB25,0)) | AC39: =IFERROR(AVERAGE(C39:AB39),"") | AD39: =IFERROR(MEDIAN(C39:AB39),"") | AE39: =IFERROR(MAX(C39:AB39),"") | AF39: =IFERROR(MIN(C39:AB39),"")
A40: Escalera | B40: % toman el bump 2 | C40: =IF(C6=0,"",IFERROR(C33/C25,0)) | D40: =IF(D6=0,"",IFERROR(D33/D25,0)) | E40: =IF(E6=0,"",IFERROR(E33/E25,0)) | F40: =IF(F6=0,"",IFERROR(F33/F25,0)) | G40: =IF(G6=0,"",IFERROR(G33/G25,0)) | H40: =IF(H6=0,"",IFERROR(H33/H25,0)) | I40: =IF(I6=0,"",IFERROR(I33/I25,0)) | J40: =IF(J6=0,"",IFERROR(J33/J25,0)) | ... AB40: =IF(AB6=0,"",IFERROR(AB33/AB25,0)) | AC40: =IFERROR(AVERAGE(C40:AB40),"") | AD40: =IFERROR(MEDIAN(C40:AB40),"") | AE40: =IFERROR(MAX(C40:AB40),"") | AF40: =IFERROR(MIN(C40:AB40),"")
A41: Escalera | B41: % toman la OTO 1 | C41: =IF(C6=0,"",IFERROR(C34/C25,0)) | D41: =IF(D6=0,"",IFERROR(D34/D25,0)) | E41: =IF(E6=0,"",IFERROR(E34/E25,0)) | F41: =IF(F6=0,"",IFERROR(F34/F25,0)) | G41: =IF(G6=0,"",IFERROR(G34/G25,0)) | H41: =IF(H6=0,"",IFERROR(H34/H25,0)) | I41: =IF(I6=0,"",IFERROR(I34/I25,0)) | J41: =IF(J6=0,"",IFERROR(J34/J25,0)) | ... AB41: =IF(AB6=0,"",IFERROR(AB34/AB25,0)) | AC41: =IFERROR(AVERAGE(C41:AB41),"") | AD41: =IFERROR(MEDIAN(C41:AB41),"") | AE41: =IFERROR(MAX(C41:AB41),"") | AF41: =IFERROR(MIN(C41:AB41),"")
A42: Escalera | B42: % ascienden | C42: =IF(C6=0,"",IFERROR(C38/C25,0)) | D42: =IF(D6=0,"",IFERROR(D38/D25,0)) | E42: =IF(E6=0,"",IFERROR(E38/E25,0)) | F42: =IF(F6=0,"",IFERROR(F38/F25,0)) | G42: =IF(G6=0,"",IFERROR(G38/G25,0)) | H42: =IF(H6=0,"",IFERROR(H38/H25,0)) | I42: =IF(I6=0,"",IFERROR(I38/I25,0)) | J42: =IF(J6=0,"",IFERROR(J38/J25,0)) | ... AB42: =IF(AB6=0,"",IFERROR(AB38/AB25,0)) | AC42: =IFERROR(AVERAGE(C42:AB42),"") | AD42: =IFERROR(MEDIAN(C42:AB42),"") | AE42: =IFERROR(MAX(C42:AB42),"") | AF42: =IFERROR(MIN(C42:AB42),"")
A43: Escalera | B43: Order value (facturado por comprador) | C43: =IF(C6=0,"",IFERROR(C46/C25,0)) | D43: =IF(D6=0,"",IFERROR(D46/D25,0)) | E43: =IF(E6=0,"",IFERROR(E46/E25,0)) | F43: =IF(F6=0,"",IFERROR(F46/F25,0)) | G43: =IF(G6=0,"",IFERROR(G46/G25,0)) | H43: =IF(H6=0,"",IFERROR(H46/H25,0)) | I43: =IF(I6=0,"",IFERROR(I46/I25,0)) | J43: =IF(J6=0,"",IFERROR(J46/J25,0)) | ... AB43: =IF(AB6=0,"",IFERROR(AB46/AB25,0)) | AC43: =IFERROR(AVERAGE(C43:AB43),"") | AD43: =IFERROR(MEDIAN(C43:AB43),"") | AE43: =IFERROR(MAX(C43:AB43),"") | AF43: =IFERROR(MIN(C43:AB43),"")
A45: 4. Resultado
A46: Resultado | B46: Facturado (toda la escalera) | C46: =IF(C6=0,"",IFERROR(C25*Config!$C$7+C32*Config!$C$8+C33*Config!$C$9+C34*Config!$C$10+C35*Config!$C$11+C36*Config!$C$12+C37*Config!$C$13+C38*Config!$C$14,0)) | D46: =IF(D6=0,"",IFERROR(D25*Config!$C$7+D32*Config!$C$8+D33*Config!$C$9+D34*Config!$C$10+D35*Config!$C$11+D36*Config!$C$12+D37*Config!$C$13+D38*Config!$C$14,0)) | E46: =IF(E6=0,"",IFERROR(E25*Config!$C$7+E32*Config!$C$8+E33*Config!$C$9+E34*Config!$C$10+E35*Config!$C$11+E36*Config!$C$12+E37*Config!$C$13+E38*Config!$C$14,0)) | F46: =IF(F6=0,"",IFERROR(F25*Config!$C$7+F32*Config!$C$8+F33*Config!$C$9+F34*Config!$C$10+F35*Config!$C$11+F36*Config!$C$12+F37*Config!$C$13+F38*Config!$C$14,0)) | G46: =IF(G6=0,"",IFERROR(G25*Config!$C$7+G32*Config!$C$8+G33*Config!$C$9+G34*Config!$C$10+G35*Config!$C$11+G36*Config!$C$12+G37*Config!$C$13+G38*Config!$C$14,0)) | H46: =IF(H6=0,"",IFERROR(H25*Config!$C$7+H32*Config!$C$8+H33*Config!$C$9+H34*Config!$C$10+H35*Config!$C$11+H36*Config!$C$12+H37*Config!$C$13+H38*Config!$C$14,0)) | I46: =IF(I6=0,"",IFERROR(I25*Config!$C$7+I32*Config!$C$8+I33*Config!$C$9+I34*Config!$C$10+I35*Config!$C$11+I36*Config!$C$12+I37*Config!$C$13+I38*Config!$C$14,0)) | J46: =IF(J6=0,"",IFERROR(J25*Config!$C$7+J32*Config!$C$8+J33*Config!$C$9+J34*Config!$C$10+J35*Config!$C$11+J36*Config!$C$12+J37*Config!$C$13+J38*Config!$C$14,0)) | ... AB46: =IF(AB6=0,"",IFERROR(AB25*Config!$C$7+AB32*Config!$C$8+AB33*Config!$C$9+AB34*Config!$C$10+AB35*Config!$C$11+AB36*Config!$C$12+AB37*Config!$C$13+AB38*Config!$C$14,0)) | AC46: =IFERROR(AVERAGE(C46:AB46),"") | AD46: =IFERROR(MEDIAN(C46:AB46),"") | AE46: =IFERROR(MAX(C46:AB46),"") | AF46: =IFERROR(MIN(C46:AB46),"")
A47: Resultado | B47: Cash neto (después de comisiones y reembolsos) | C47: =IF(C6=0,"",IFERROR(C46*(1-Config!$C$15-Config!$C$16-Config!$C$17),0)) | D47: =IF(D6=0,"",IFERROR(D46*(1-Config!$C$15-Config!$C$16-Config!$C$17),0)) | E47: =IF(E6=0,"",IFERROR(E46*(1-Config!$C$15-Config!$C$16-Config!$C$17),0)) | F47: =IF(F6=0,"",IFERROR(F46*(1-Config!$C$15-Config!$C$16-Config!$C$17),0)) | G47: =IF(G6=0,"",IFERROR(G46*(1-Config!$C$15-Config!$C$16-Config!$C$17),0)) | H47: =IF(H6=0,"",IFERROR(H46*(1-Config!$C$15-Config!$C$16-Config!$C$17),0)) | I47: =IF(I6=0,"",IFERROR(I46*(1-Config!$C$15-Config!$C$16-Config!$C$17),0)) | J47: =IF(J6=0,"",IFERROR(J46*(1-Config!$C$15-Config!$C$16-Config!$C$17),0)) | ... AB47: =IF(AB6=0,"",IFERROR(AB46*(1-Config!$C$15-Config!$C$16-Config!$C$17),0)) | AC47: =IFERROR(AVERAGE(C47:AB47),"") | AD47: =IFERROR(MEDIAN(C47:AB47),"") | AE47: =IFERROR(MAX(C47:AB47),"") | AF47: =IFERROR(MIN(C47:AB47),"")
A48: Resultado | B48: Ganancia (cash neto − pauta − fijos) | C48: =IF(C6=0,"",IFERROR(C47-C10-Config!$C$18*7,0)) | D48: =IF(D6=0,"",IFERROR(D47-D10-Config!$C$18*7,0)) | E48: =IF(E6=0,"",IFERROR(E47-E10-Config!$C$18*7,0)) | F48: =IF(F6=0,"",IFERROR(F47-F10-Config!$C$18*7,0)) | G48: =IF(G6=0,"",IFERROR(G47-G10-Config!$C$18*7,0)) | H48: =IF(H6=0,"",IFERROR(H47-H10-Config!$C$18*7,0)) | I48: =IF(I6=0,"",IFERROR(I47-I10-Config!$C$18*7,0)) | J48: =IF(J6=0,"",IFERROR(J47-J10-Config!$C$18*7,0)) | ... AB48: =IF(AB6=0,"",IFERROR(AB47-AB10-Config!$C$18*7,0)) | AC48: =IFERROR(AVERAGE(C48:AB48),"") | AD48: =IFERROR(MEDIAN(C48:AB48),"") | AE48: =IFERROR(MAX(C48:AB48),"") | AF48: =IFERROR(MIN(C48:AB48),"")
A49: Resultado | B49: ROAS sobre cash neto | C49: =IF(C6=0,"",IFERROR(C47/C10,0)) | D49: =IF(D6=0,"",IFERROR(D47/D10,0)) | E49: =IF(E6=0,"",IFERROR(E47/E10,0)) | F49: =IF(F6=0,"",IFERROR(F47/F10,0)) | G49: =IF(G6=0,"",IFERROR(G47/G10,0)) | H49: =IF(H6=0,"",IFERROR(H47/H10,0)) | I49: =IF(I6=0,"",IFERROR(I47/I10,0)) | J49: =IF(J6=0,"",IFERROR(J47/J10,0)) | ... AB49: =IF(AB6=0,"",IFERROR(AB47/AB10,0)) | AC49: =IFERROR(AVERAGE(C49:AB49),"") | AD49: =IFERROR(MEDIAN(C49:AB49),"") | AE49: =IFERROR(MAX(C49:AB49),"") | AF49: =IFERROR(MIN(C49:AB49),"")
A50: Resultado | B50: Ganancia por visita (la métrica más valiosa) | C50: =IF(C6=0,"",IFERROR(C48/C14,0)) | D50: =IF(D6=0,"",IFERROR(D48/D14,0)) | E50: =IF(E6=0,"",IFERROR(E48/E14,0)) | F50: =IF(F6=0,"",IFERROR(F48/F14,0)) | G50: =IF(G6=0,"",IFERROR(G48/G14,0)) | H50: =IF(H6=0,"",IFERROR(H48/H14,0)) | I50: =IF(I6=0,"",IFERROR(I48/I14,0)) | J50: =IF(J6=0,"",IFERROR(J48/J14,0)) | ... AB50: =IF(AB6=0,"",IFERROR(AB48/AB14,0)) | AC50: =IFERROR(AVERAGE(C50:AB50),"") | AD50: =IFERROR(MEDIAN(C50:AB50),"") | AE50: =IFERROR(MAX(C50:AB50),"") | AF50: =IFERROR(MIN(C50:AB50),"")
A51: Resultado | B51: Margen por visita (ganancia por visita ÷ costo por visita) | C51: =IF(C6=0,"",IFERROR(C50/C20,0)) | D51: =IF(D6=0,"",IFERROR(D50/D20,0)) | E51: =IF(E6=0,"",IFERROR(E50/E20,0)) | F51: =IF(F6=0,"",IFERROR(F50/F20,0)) | G51: =IF(G6=0,"",IFERROR(G50/G20,0)) | H51: =IF(H6=0,"",IFERROR(H50/H20,0)) | I51: =IF(I6=0,"",IFERROR(I50/I20,0)) | J51: =IF(J6=0,"",IFERROR(J50/J20,0)) | ... AB51: =IF(AB6=0,"",IFERROR(AB50/AB20,0)) | AC51: =IFERROR(AVERAGE(C51:AB51),"") | AD51: =IFERROR(MEDIAN(C51:AB51),"") | AE51: =IFERROR(MAX(C51:AB51),"") | AF51: =IFERROR(MIN(C51:AB51),"")
A52: Resultado | B52: Ganancia por comprador | C52: =IF(C6=0,"",IFERROR(C48/C25,0)) | D52: =IF(D6=0,"",IFERROR(D48/D25,0)) | E52: =IF(E6=0,"",IFERROR(E48/E25,0)) | F52: =IF(F6=0,"",IFERROR(F48/F25,0)) | G52: =IF(G6=0,"",IFERROR(G48/G25,0)) | H52: =IF(H6=0,"",IFERROR(H48/H25,0)) | I52: =IF(I6=0,"",IFERROR(I48/I25,0)) | J52: =IF(J6=0,"",IFERROR(J48/J25,0)) | ... AB52: =IF(AB6=0,"",IFERROR(AB48/AB25,0)) | AC52: =IFERROR(AVERAGE(C52:AB52),"") | AD52: =IFERROR(MEDIAN(C52:AB52),"") | AE52: =IFERROR(MAX(C52:AB52),"") | AF52: =IFERROR(MIN(C52:AB52),"")
A53: Resultado | B53: AOV neto − CPA (lo que queda por comprador) | C53: =IF(C6=0,"",IFERROR(C47/C25-C29,0)) | D53: =IF(D6=0,"",IFERROR(D47/D25-D29,0)) | E53: =IF(E6=0,"",IFERROR(E47/E25-E29,0)) | F53: =IF(F6=0,"",IFERROR(F47/F25-F29,0)) | G53: =IF(G6=0,"",IFERROR(G47/G25-G29,0)) | H53: =IF(H6=0,"",IFERROR(H47/H25-H29,0)) | I53: =IF(I6=0,"",IFERROR(I47/I25-I29,0)) | J53: =IF(J6=0,"",IFERROR(J47/J25-J29,0)) | ... AB53: =IF(AB6=0,"",IFERROR(AB47/AB25-AB29,0)) | AC53: =IFERROR(AVERAGE(C53:AB53),"") | AD53: =IFERROR(MEDIAN(C53:AB53),"") | AE53: =IFERROR(MAX(C53:AB53),"") | AF53: =IFERROR(MIN(C53:AB53),"")
A55: 6. Contra tu promedio: cada semana contra la mediana de tus 4 semanas anteriores (tolerancia en Config). Igual o mejor = VERDE · hasta la tolerancia peor = AMARILLO · más = ROJO
A56: Mediana 4 semanas anteriores | B56: Ganancia por visita (la métrica más valiosa) | D56: =IFERROR(MEDIAN(C50:C50),"") | E56: =IFERROR(MEDIAN(C50:D50),"") | F56: =IFERROR(MEDIAN(C50:E50),"") | G56: =IFERROR(MEDIAN(C50:F50),"") | H56: =IFERROR(MEDIAN(D50:G50),"") | I56: =IFERROR(MEDIAN(E50:H50),"") | J56: =IFERROR(MEDIAN(F50:I50),"") | K56: =IFERROR(MEDIAN(G50:J50),"") | L56: =IFERROR(MEDIAN(H50:K50),"") | M56: =IFERROR(MEDIAN(I50:L50),"") | N56: =IFERROR(MEDIAN(J50:M50),"") | ... AB56: =IFERROR(MEDIAN(X50:AA50),"")
A57: Semáforo | B57: Ganancia por visita (la métrica más valiosa) | C57: =IF(OR(C50="",C56=""),"",IF(C50<=0,"ROJO",IF(C50>=C56,"VERDE",IF(C50>=C56*(1-Config!$C$20),"AMARILLO","ROJO")))) | D57: =IF(OR(D50="",D56=""),"",IF(D50<=0,"ROJO",IF(D50>=D56,"VERDE",IF(D50>=D56*(1-Config!$C$20),"AMARILLO","ROJO")))) | E57: =IF(OR(E50="",E56=""),"",IF(E50<=0,"ROJO",IF(E50>=E56,"VERDE",IF(E50>=E56*(1-Config!$C$20),"AMARILLO","ROJO")))) | F57: =IF(OR(F50="",F56=""),"",IF(F50<=0,"ROJO",IF(F50>=F56,"VERDE",IF(F50>=F56*(1-Config!$C$20),"AMARILLO","ROJO")))) | G57: =IF(OR(G50="",G56=""),"",IF(G50<=0,"ROJO",IF(G50>=G56,"VERDE",IF(G50>=G56*(1-Config!$C$20),"AMARILLO","ROJO")))) | H57: =IF(OR(H50="",H56=""),"",IF(H50<=0,"ROJO",IF(H50>=H56,"VERDE",IF(H50>=H56*(1-Config!$C$20),"AMARILLO","ROJO")))) | I57: =IF(OR(I50="",I56=""),"",IF(I50<=0,"ROJO",IF(I50>=I56,"VERDE",IF(I50>=I56*(1-Config!$C$20),"AMARILLO","ROJO")))) | J57: =IF(OR(J50="",J56=""),"",IF(J50<=0,"ROJO",IF(J50>=J56,"VERDE",IF(J50>=J56*(1-Config!$C$20),"AMARILLO","ROJO")))) | ... AB57: =IF(OR(AB50="",AB56=""),"",IF(AB50<=0,"ROJO",IF(AB50>=AB56,"VERDE",IF(AB50>=AB56*(1-Config!$C$20),"AMARILLO","ROJO"))))
A58: Mediana 4 semanas anteriores | B58: Costo por visita | D58: =IFERROR(MEDIAN(C20:C20),"") | E58: =IFERROR(MEDIAN(C20:D20),"") | F58: =IFERROR(MEDIAN(C20:E20),"") | G58: =IFERROR(MEDIAN(C20:F20),"") | H58: =IFERROR(MEDIAN(D20:G20),"") | I58: =IFERROR(MEDIAN(E20:H20),"") | J58: =IFERROR(MEDIAN(F20:I20),"") | K58: =IFERROR(MEDIAN(G20:J20),"") | L58: =IFERROR(MEDIAN(H20:K20),"") | M58: =IFERROR(MEDIAN(I20:L20),"") | N58: =IFERROR(MEDIAN(J20:M20),"") | ... AB58: =IFERROR(MEDIAN(X20:AA20),"")
A59: Semáforo | B59: Costo por visita | C59: =IF(OR(C20="",C58=""),"",IF(C20<=C58,"VERDE",IF(C20<=C58*(1+Config!$C$20),"AMARILLO","ROJO"))) | D59: =IF(OR(D20="",D58=""),"",IF(D20<=D58,"VERDE",IF(D20<=D58*(1+Config!$C$20),"AMARILLO","ROJO"))) | E59: =IF(OR(E20="",E58=""),"",IF(E20<=E58,"VERDE",IF(E20<=E58*(1+Config!$C$20),"AMARILLO","ROJO"))) | F59: =IF(OR(F20="",F58=""),"",IF(F20<=F58,"VERDE",IF(F20<=F58*(1+Config!$C$20),"AMARILLO","ROJO"))) | G59: =IF(OR(G20="",G58=""),"",IF(G20<=G58,"VERDE",IF(G20<=G58*(1+Config!$C$20),"AMARILLO","ROJO"))) | H59: =IF(OR(H20="",H58=""),"",IF(H20<=H58,"VERDE",IF(H20<=H58*(1+Config!$C$20),"AMARILLO","ROJO"))) | I59: =IF(OR(I20="",I58=""),"",IF(I20<=I58,"VERDE",IF(I20<=I58*(1+Config!$C$20),"AMARILLO","ROJO"))) | J59: =IF(OR(J20="",J58=""),"",IF(J20<=J58,"VERDE",IF(J20<=J58*(1+Config!$C$20),"AMARILLO","ROJO"))) | ... AB59: =IF(OR(AB20="",AB58=""),"",IF(AB20<=AB58,"VERDE",IF(AB20<=AB58*(1+Config!$C$20),"AMARILLO","ROJO")))
A60: Mediana 4 semanas anteriores | B60: % visita → checkout | D60: =IFERROR(MEDIAN(C26:C26),"") | E60: =IFERROR(MEDIAN(C26:D26),"") | F60: =IFERROR(MEDIAN(C26:E26),"") | G60: =IFERROR(MEDIAN(C26:F26),"") | H60: =IFERROR(MEDIAN(D26:G26),"") | I60: =IFERROR(MEDIAN(E26:H26),"") | J60: =IFERROR(MEDIAN(F26:I26),"") | K60: =IFERROR(MEDIAN(G26:J26),"") | L60: =IFERROR(MEDIAN(H26:K26),"") | M60: =IFERROR(MEDIAN(I26:L26),"") | N60: =IFERROR(MEDIAN(J26:M26),"") | ... AB60: =IFERROR(MEDIAN(X26:AA26),"")
A61: Semáforo | B61: % visita → checkout | C61: =IF(OR(C26="",C60=""),"",IF(C26>=C60,"VERDE",IF(C26>=C60*(1-Config!$C$20),"AMARILLO","ROJO"))) | D61: =IF(OR(D26="",D60=""),"",IF(D26>=D60,"VERDE",IF(D26>=D60*(1-Config!$C$20),"AMARILLO","ROJO"))) | E61: =IF(OR(E26="",E60=""),"",IF(E26>=E60,"VERDE",IF(E26>=E60*(1-Config!$C$20),"AMARILLO","ROJO"))) | F61: =IF(OR(F26="",F60=""),"",IF(F26>=F60,"VERDE",IF(F26>=F60*(1-Config!$C$20),"AMARILLO","ROJO"))) | G61: =IF(OR(G26="",G60=""),"",IF(G26>=G60,"VERDE",IF(G26>=G60*(1-Config!$C$20),"AMARILLO","ROJO"))) | H61: =IF(OR(H26="",H60=""),"",IF(H26>=H60,"VERDE",IF(H26>=H60*(1-Config!$C$20),"AMARILLO","ROJO"))) | I61: =IF(OR(I26="",I60=""),"",IF(I26>=I60,"VERDE",IF(I26>=I60*(1-Config!$C$20),"AMARILLO","ROJO"))) | J61: =IF(OR(J26="",J60=""),"",IF(J26>=J60,"VERDE",IF(J26>=J60*(1-Config!$C$20),"AMARILLO","ROJO"))) | ... AB61: =IF(OR(AB26="",AB60=""),"",IF(AB26>=AB60,"VERDE",IF(AB26>=AB60*(1-Config!$C$20),"AMARILLO","ROJO")))
A62: Mediana 4 semanas anteriores | B62: % checkout → compra | D62: =IFERROR(MEDIAN(C27:C27),"") | E62: =IFERROR(MEDIAN(C27:D27),"") | F62: =IFERROR(MEDIAN(C27:E27),"") | G62: =IFERROR(MEDIAN(C27:F27),"") | H62: =IFERROR(MEDIAN(D27:G27),"") | I62: =IFERROR(MEDIAN(E27:H27),"") | J62: =IFERROR(MEDIAN(F27:I27),"") | K62: =IFERROR(MEDIAN(G27:J27),"") | L62: =IFERROR(MEDIAN(H27:K27),"") | M62: =IFERROR(MEDIAN(I27:L27),"") | N62: =IFERROR(MEDIAN(J27:M27),"") | ... AB62: =IFERROR(MEDIAN(X27:AA27),"")
A63: Semáforo | B63: % checkout → compra | C63: =IF(OR(C27="",C62=""),"",IF(C27>=C62,"VERDE",IF(C27>=C62*(1-Config!$C$20),"AMARILLO","ROJO"))) | D63: =IF(OR(D27="",D62=""),"",IF(D27>=D62,"VERDE",IF(D27>=D62*(1-Config!$C$20),"AMARILLO","ROJO"))) | E63: =IF(OR(E27="",E62=""),"",IF(E27>=E62,"VERDE",IF(E27>=E62*(1-Config!$C$20),"AMARILLO","ROJO"))) | F63: =IF(OR(F27="",F62=""),"",IF(F27>=F62,"VERDE",IF(F27>=F62*(1-Config!$C$20),"AMARILLO","ROJO"))) | G63: =IF(OR(G27="",G62=""),"",IF(G27>=G62,"VERDE",IF(G27>=G62*(1-Config!$C$20),"AMARILLO","ROJO"))) | H63: =IF(OR(H27="",H62=""),"",IF(H27>=H62,"VERDE",IF(H27>=H62*(1-Config!$C$20),"AMARILLO","ROJO"))) | I63: =IF(OR(I27="",I62=""),"",IF(I27>=I62,"VERDE",IF(I27>=I62*(1-Config!$C$20),"AMARILLO","ROJO"))) | J63: =IF(OR(J27="",J62=""),"",IF(J27>=J62,"VERDE",IF(J27>=J62*(1-Config!$C$20),"AMARILLO","ROJO"))) | ... AB63: =IF(OR(AB27="",AB62=""),"",IF(AB27>=AB62,"VERDE",IF(AB27>=AB62*(1-Config!$C$20),"AMARILLO","ROJO")))
A64: Mediana 4 semanas anteriores | B64: CPA (costo por comprador) | D64: =IFERROR(MEDIAN(C29:C29),"") | E64: =IFERROR(MEDIAN(C29:D29),"") | F64: =IFERROR(MEDIAN(C29:E29),"") | G64: =IFERROR(MEDIAN(C29:F29),"") | H64: =IFERROR(MEDIAN(D29:G29),"") | I64: =IFERROR(MEDIAN(E29:H29),"") | J64: =IFERROR(MEDIAN(F29:I29),"") | K64: =IFERROR(MEDIAN(G29:J29),"") | L64: =IFERROR(MEDIAN(H29:K29),"") | M64: =IFERROR(MEDIAN(I29:L29),"") | N64: =IFERROR(MEDIAN(J29:M29),"") | ... AB64: =IFERROR(MEDIAN(X29:AA29),"")
A65: Semáforo | B65: CPA (costo por comprador) | C65: =IF(OR(C29="",C64=""),"",IF(C29<=C64,"VERDE",IF(C29<=C64*(1+Config!$C$20),"AMARILLO","ROJO"))) | D65: =IF(OR(D29="",D64=""),"",IF(D29<=D64,"VERDE",IF(D29<=D64*(1+Config!$C$20),"AMARILLO","ROJO"))) | E65: =IF(OR(E29="",E64=""),"",IF(E29<=E64,"VERDE",IF(E29<=E64*(1+Config!$C$20),"AMARILLO","ROJO"))) | F65: =IF(OR(F29="",F64=""),"",IF(F29<=F64,"VERDE",IF(F29<=F64*(1+Config!$C$20),"AMARILLO","ROJO"))) | G65: =IF(OR(G29="",G64=""),"",IF(G29<=G64,"VERDE",IF(G29<=G64*(1+Config!$C$20),"AMARILLO","ROJO"))) | H65: =IF(OR(H29="",H64=""),"",IF(H29<=H64,"VERDE",IF(H29<=H64*(1+Config!$C$20),"AMARILLO","ROJO"))) | I65: =IF(OR(I29="",I64=""),"",IF(I29<=I64,"VERDE",IF(I29<=I64*(1+Config!$C$20),"AMARILLO","ROJO"))) | J65: =IF(OR(J29="",J64=""),"",IF(J29<=J64,"VERDE",IF(J29<=J64*(1+Config!$C$20),"AMARILLO","ROJO"))) | ... AB65: =IF(OR(AB29="",AB64=""),"",IF(AB29<=AB64,"VERDE",IF(AB29<=AB64*(1+Config!$C$20),"AMARILLO","ROJO")))
A66: Mediana 4 semanas anteriores | B66: Order value (facturado por comprador) | D66: =IFERROR(MEDIAN(C43:C43),"") | E66: =IFERROR(MEDIAN(C43:D43),"") | F66: =IFERROR(MEDIAN(C43:E43),"") | G66: =IFERROR(MEDIAN(C43:F43),"") | H66: =IFERROR(MEDIAN(D43:G43),"") | I66: =IFERROR(MEDIAN(E43:H43),"") | J66: =IFERROR(MEDIAN(F43:I43),"") | K66: =IFERROR(MEDIAN(G43:J43),"") | L66: =IFERROR(MEDIAN(H43:K43),"") | M66: =IFERROR(MEDIAN(I43:L43),"") | N66: =IFERROR(MEDIAN(J43:M43),"") | ... AB66: =IFERROR(MEDIAN(X43:AA43),"")
A67: Semáforo | B67: Order value (facturado por comprador) | C67: =IF(OR(C43="",C66=""),"",IF(C43>=C66,"VERDE",IF(C43>=C66*(1-Config!$C$20),"AMARILLO","ROJO"))) | D67: =IF(OR(D43="",D66=""),"",IF(D43>=D66,"VERDE",IF(D43>=D66*(1-Config!$C$20),"AMARILLO","ROJO"))) | E67: =IF(OR(E43="",E66=""),"",IF(E43>=E66,"VERDE",IF(E43>=E66*(1-Config!$C$20),"AMARILLO","ROJO"))) | F67: =IF(OR(F43="",F66=""),"",IF(F43>=F66,"VERDE",IF(F43>=F66*(1-Config!$C$20),"AMARILLO","ROJO"))) | G67: =IF(OR(G43="",G66=""),"",IF(G43>=G66,"VERDE",IF(G43>=G66*(1-Config!$C$20),"AMARILLO","ROJO"))) | H67: =IF(OR(H43="",H66=""),"",IF(H43>=H66,"VERDE",IF(H43>=H66*(1-Config!$C$20),"AMARILLO","ROJO"))) | I67: =IF(OR(I43="",I66=""),"",IF(I43>=I66,"VERDE",IF(I43>=I66*(1-Config!$C$20),"AMARILLO","ROJO"))) | J67: =IF(OR(J43="",J66=""),"",IF(J43>=J66,"VERDE",IF(J43>=J66*(1-Config!$C$20),"AMARILLO","ROJO"))) | ... AB67: =IF(OR(AB43="",AB66=""),"",IF(AB43>=AB66,"VERDE",IF(AB43>=AB66*(1-Config!$C$20),"AMARILLO","ROJO")))
A68: Mediana 4 semanas anteriores | B68: ROAS sobre cash neto | D68: =IFERROR(MEDIAN(C49:C49),"") | E68: =IFERROR(MEDIAN(C49:D49),"") | F68: =IFERROR(MEDIAN(C49:E49),"") | G68: =IFERROR(MEDIAN(C49:F49),"") | H68: =IFERROR(MEDIAN(D49:G49),"") | I68: =IFERROR(MEDIAN(E49:H49),"") | J68: =IFERROR(MEDIAN(F49:I49),"") | K68: =IFERROR(MEDIAN(G49:J49),"") | L68: =IFERROR(MEDIAN(H49:K49),"") | M68: =IFERROR(MEDIAN(I49:L49),"") | N68: =IFERROR(MEDIAN(J49:M49),"") | ... AB68: =IFERROR(MEDIAN(X49:AA49),"")
A69: Semáforo | B69: ROAS sobre cash neto | C69: =IF(OR(C49="",C68=""),"",IF(C49<=1,"ROJO",IF(C49>=C68,"VERDE",IF(C49>=C68*(1-Config!$C$20),"AMARILLO","ROJO")))) | D69: =IF(OR(D49="",D68=""),"",IF(D49<=1,"ROJO",IF(D49>=D68,"VERDE",IF(D49>=D68*(1-Config!$C$20),"AMARILLO","ROJO")))) | E69: =IF(OR(E49="",E68=""),"",IF(E49<=1,"ROJO",IF(E49>=E68,"VERDE",IF(E49>=E68*(1-Config!$C$20),"AMARILLO","ROJO")))) | F69: =IF(OR(F49="",F68=""),"",IF(F49<=1,"ROJO",IF(F49>=F68,"VERDE",IF(F49>=F68*(1-Config!$C$20),"AMARILLO","ROJO")))) | G69: =IF(OR(G49="",G68=""),"",IF(G49<=1,"ROJO",IF(G49>=G68,"VERDE",IF(G49>=G68*(1-Config!$C$20),"AMARILLO","ROJO")))) | H69: =IF(OR(H49="",H68=""),"",IF(H49<=1,"ROJO",IF(H49>=H68,"VERDE",IF(H49>=H68*(1-Config!$C$20),"AMARILLO","ROJO")))) | I69: =IF(OR(I49="",I68=""),"",IF(I49<=1,"ROJO",IF(I49>=I68,"VERDE",IF(I49>=I68*(1-Config!$C$20),"AMARILLO","ROJO")))) | J69: =IF(OR(J49="",J68=""),"",IF(J49<=1,"ROJO",IF(J49>=J68,"VERDE",IF(J49>=J68*(1-Config!$C$20),"AMARILLO","ROJO")))) | ... AB69: =IF(OR(AB49="",AB68=""),"",IF(AB49<=1,"ROJO",IF(AB49>=AB68,"VERDE",IF(AB49>=AB68*(1-Config!$C$20),"AMARILLO","ROJO"))))
A70: Mediana 4 semanas anteriores | B70: CPM | D70: =IFERROR(MEDIAN(C15:C15),"") | E70: =IFERROR(MEDIAN(C15:D15),"") | F70: =IFERROR(MEDIAN(C15:E15),"") | G70: =IFERROR(MEDIAN(C15:F15),"") | H70: =IFERROR(MEDIAN(D15:G15),"") | I70: =IFERROR(MEDIAN(E15:H15),"") | J70: =IFERROR(MEDIAN(F15:I15),"") | K70: =IFERROR(MEDIAN(G15:J15),"") | L70: =IFERROR(MEDIAN(H15:K15),"") | M70: =IFERROR(MEDIAN(I15:L15),"") | N70: =IFERROR(MEDIAN(J15:M15),"") | ... AB70: =IFERROR(MEDIAN(X15:AA15),"")
A71: Semáforo | B71: CPM | C71: =IF(OR(C15="",C70=""),"",IF(C15<=C70,"VERDE",IF(C15<=C70*(1+Config!$C$20),"AMARILLO","ROJO"))) | D71: =IF(OR(D15="",D70=""),"",IF(D15<=D70,"VERDE",IF(D15<=D70*(1+Config!$C$20),"AMARILLO","ROJO"))) | E71: =IF(OR(E15="",E70=""),"",IF(E15<=E70,"VERDE",IF(E15<=E70*(1+Config!$C$20),"AMARILLO","ROJO"))) | F71: =IF(OR(F15="",F70=""),"",IF(F15<=F70,"VERDE",IF(F15<=F70*(1+Config!$C$20),"AMARILLO","ROJO"))) | G71: =IF(OR(G15="",G70=""),"",IF(G15<=G70,"VERDE",IF(G15<=G70*(1+Config!$C$20),"AMARILLO","ROJO"))) | H71: =IF(OR(H15="",H70=""),"",IF(H15<=H70,"VERDE",IF(H15<=H70*(1+Config!$C$20),"AMARILLO","ROJO"))) | I71: =IF(OR(I15="",I70=""),"",IF(I15<=I70,"VERDE",IF(I15<=I70*(1+Config!$C$20),"AMARILLO","ROJO"))) | J71: =IF(OR(J15="",J70=""),"",IF(J15<=J70,"VERDE",IF(J15<=J70*(1+Config!$C$20),"AMARILLO","ROJO"))) | ... AB71: =IF(OR(AB15="",AB70=""),"",IF(AB15<=AB70,"VERDE",IF(AB15<=AB70*(1+Config!$C$20),"AMARILLO","ROJO")))
A72: Mediana 4 semanas anteriores | B72: CTR al enlace | D72: =IFERROR(MEDIAN(C17:C17),"") | E72: =IFERROR(MEDIAN(C17:D17),"") | F72: =IFERROR(MEDIAN(C17:E17),"") | G72: =IFERROR(MEDIAN(C17:F17),"") | H72: =IFERROR(MEDIAN(D17:G17),"") | I72: =IFERROR(MEDIAN(E17:H17),"") | J72: =IFERROR(MEDIAN(F17:I17),"") | K72: =IFERROR(MEDIAN(G17:J17),"") | L72: =IFERROR(MEDIAN(H17:K17),"") | M72: =IFERROR(MEDIAN(I17:L17),"") | N72: =IFERROR(MEDIAN(J17:M17),"") | ... AB72: =IFERROR(MEDIAN(X17:AA17),"")
A73: Semáforo | B73: CTR al enlace | C73: =IF(OR(C17="",C72=""),"",IF(C17>=C72,"VERDE",IF(C17>=C72*(1-Config!$C$20),"AMARILLO","ROJO"))) | D73: =IF(OR(D17="",D72=""),"",IF(D17>=D72,"VERDE",IF(D17>=D72*(1-Config!$C$20),"AMARILLO","ROJO"))) | E73: =IF(OR(E17="",E72=""),"",IF(E17>=E72,"VERDE",IF(E17>=E72*(1-Config!$C$20),"AMARILLO","ROJO"))) | F73: =IF(OR(F17="",F72=""),"",IF(F17>=F72,"VERDE",IF(F17>=F72*(1-Config!$C$20),"AMARILLO","ROJO"))) | G73: =IF(OR(G17="",G72=""),"",IF(G17>=G72,"VERDE",IF(G17>=G72*(1-Config!$C$20),"AMARILLO","ROJO"))) | H73: =IF(OR(H17="",H72=""),"",IF(H17>=H72,"VERDE",IF(H17>=H72*(1-Config!$C$20),"AMARILLO","ROJO"))) | I73: =IF(OR(I17="",I72=""),"",IF(I17>=I72,"VERDE",IF(I17>=I72*(1-Config!$C$20),"AMARILLO","ROJO"))) | J73: =IF(OR(J17="",J72=""),"",IF(J17>=J72,"VERDE",IF(J17>=J72*(1-Config!$C$20),"AMARILLO","ROJO"))) | ... AB73: =IF(OR(AB17="",AB72=""),"",IF(AB17>=AB72,"VERDE",IF(AB17>=AB72*(1-Config!$C$20),"AMARILLO","ROJO")))
A74: Mediana 4 semanas anteriores | B74: Frecuencia | D74: =IFERROR(MEDIAN(C16:C16),"") | E74: =IFERROR(MEDIAN(C16:D16),"") | F74: =IFERROR(MEDIAN(C16:E16),"") | G74: =IFERROR(MEDIAN(C16:F16),"") | H74: =IFERROR(MEDIAN(D16:G16),"") | I74: =IFERROR(MEDIAN(E16:H16),"") | J74: =IFERROR(MEDIAN(F16:I16),"") | K74: =IFERROR(MEDIAN(G16:J16),"") | L74: =IFERROR(MEDIAN(H16:K16),"") | M74: =IFERROR(MEDIAN(I16:L16),"") | N74: =IFERROR(MEDIAN(J16:M16),"") | ... AB74: =IFERROR(MEDIAN(X16:AA16),"")
A75: Semáforo | B75: Frecuencia | C75: =IF(OR(C16="",C74=""),"",IF(C16<=C74,"VERDE",IF(C16<=C74*(1+Config!$C$20),"AMARILLO","ROJO"))) | D75: =IF(OR(D16="",D74=""),"",IF(D16<=D74,"VERDE",IF(D16<=D74*(1+Config!$C$20),"AMARILLO","ROJO"))) | E75: =IF(OR(E16="",E74=""),"",IF(E16<=E74,"VERDE",IF(E16<=E74*(1+Config!$C$20),"AMARILLO","ROJO"))) | F75: =IF(OR(F16="",F74=""),"",IF(F16<=F74,"VERDE",IF(F16<=F74*(1+Config!$C$20),"AMARILLO","ROJO"))) | G75: =IF(OR(G16="",G74=""),"",IF(G16<=G74,"VERDE",IF(G16<=G74*(1+Config!$C$20),"AMARILLO","ROJO"))) | H75: =IF(OR(H16="",H74=""),"",IF(H16<=H74,"VERDE",IF(H16<=H74*(1+Config!$C$20),"AMARILLO","ROJO"))) | I75: =IF(OR(I16="",I74=""),"",IF(I16<=I74,"VERDE",IF(I16<=I74*(1+Config!$C$20),"AMARILLO","ROJO"))) | J75: =IF(OR(J16="",J74=""),"",IF(J16<=J74,"VERDE",IF(J16<=J74*(1+Config!$C$20),"AMARILLO","ROJO"))) | ... AB75: =IF(OR(AB16="",AB74=""),"",IF(AB16<=AB74,"VERDE",IF(AB16<=AB74*(1+Config!$C$20),"AMARILLO","ROJO")))
A77: Modelo financiero de embudos · creado por Jesús Tassarolo · TooAudience · youtube.com/@JesusTassaroloSinFiltro · v1.2 · octubre 2026

Sheet Resumen
A1: © Jesús Tassarolo · TooAudience · youtube.com/@JesusTassaroloSinFiltro · uso personal; no redistribuir modificado
A2: Resumen: la semana elegida contra la anterior, contra tu mediana y contra tu meta
A3: Las filas están en el orden en que miro un embudo. El semáforo compara con la mediana de tus 4 semanas anteriores, con la tolerancia de Config.
A4: Semana a mostrar | B4: =MAX(Semanal!$C$7:$AB$7) | C4: ← la última con datos; escribí otro número para ver otra semana
A6: KPI | B6: Esta semana | C6: Semana anterior | D6: Variación | E6: Mediana 4 semanas previas | F6: Semáforo contra tu promedio | G6: Mejor semana | H6: Meta (tu objetivo)
A7: Inversión en publicidad (USD) | B7: =IFERROR(INDEX(Semanal!$C$10:$AB$10,1,$B$4),"") | C7: =IF($B$4<=1,"",IFERROR(INDEX(Semanal!$C$10:$AB$10,1,$B$4-1),"")) | D7: =IFERROR(IF(OR(B7="",C7=""),"",(B7-C7)/C7),"") | G7: =Semanal!$AE$10
A8: Visitas a la página | B8: =IFERROR(INDEX(Semanal!$C$14:$AB$14,1,$B$4),"") | C8: =IF($B$4<=1,"",IFERROR(INDEX(Semanal!$C$14:$AB$14,1,$B$4-1),"")) | D8: =IFERROR(IF(OR(B8="",C8=""),"",(B8-C8)/C8),"") | G8: =Semanal!$AE$14
A9: Costo por visita | B9: =IFERROR(INDEX(Semanal!$C$20:$AB$20,1,$B$4),"") | C9: =IF($B$4<=1,"",IFERROR(INDEX(Semanal!$C$20:$AB$20,1,$B$4-1),"")) | D9: =IFERROR(IF(OR(B9="",C9=""),"",(B9-C9)/C9),"") | E9: =IFERROR(INDEX(Semanal!$C$58:$AB$58,1,$B$4),"") | F9: =IFERROR(INDEX(Semanal!$C$59:$AB$59,1,$B$4),"") | G9: =Semanal!$AE$20
A10: Compran el producto principal | B10: =IFERROR(INDEX(Semanal!$C$25:$AB$25,1,$B$4),"") | C10: =IF($B$4<=1,"",IFERROR(INDEX(Semanal!$C$25:$AB$25,1,$B$4-1),"")) | D10: =IFERROR(IF(OR(B10="",C10=""),"",(B10-C10)/C10),"") | G10: =Semanal!$AE$25
A11: CPA (costo por comprador) | B11: =IFERROR(INDEX(Semanal!$C$29:$AB$29,1,$B$4),"") | C11: =IF($B$4<=1,"",IFERROR(INDEX(Semanal!$C$29:$AB$29,1,$B$4-1),"")) | D11: =IFERROR(IF(OR(B11="",C11=""),"",(B11-C11)/C11),"") | E11: =IFERROR(INDEX(Semanal!$C$64:$AB$64,1,$B$4),"") | F11: =IFERROR(INDEX(Semanal!$C$65:$AB$65,1,$B$4),"") | G11: =Semanal!$AE$29
A12: % visita → checkout | B12: =IFERROR(INDEX(Semanal!$C$26:$AB$26,1,$B$4),"") | C12: =IF($B$4<=1,"",IFERROR(INDEX(Semanal!$C$26:$AB$26,1,$B$4-1),"")) | D12: =IFERROR(IF(OR(B12="",C12=""),"",(B12-C12)/C12),"") | E12: =IFERROR(INDEX(Semanal!$C$60:$AB$60,1,$B$4),"") | F12: =IFERROR(INDEX(Semanal!$C$61:$AB$61,1,$B$4),"") | G12: =Semanal!$AE$26
A13: % checkout → compra | B13: =IFERROR(INDEX(Semanal!$C$27:$AB$27,1,$B$4),"") | C13: =IF($B$4<=1,"",IFERROR(INDEX(Semanal!$C$27:$AB$27,1,$B$4-1),"")) | D13: =IFERROR(IF(OR(B13="",C13=""),"",(B13-C13)/C13),"") | E13: =IFERROR(INDEX(Semanal!$C$62:$AB$62,1,$B$4),"") | F13: =IFERROR(INDEX(Semanal!$C$63:$AB$63,1,$B$4),"") | G13: =Semanal!$AE$27
A14: Order value (facturado por comprador) | B14: =IFERROR(INDEX(Semanal!$C$43:$AB$43,1,$B$4),"") | C14: =IF($B$4<=1,"",IFERROR(INDEX(Semanal!$C$43:$AB$43,1,$B$4-1),"")) | D14: =IFERROR(IF(OR(B14="",C14=""),"",(B14-C14)/C14),"") | E14: =IFERROR(INDEX(Semanal!$C$66:$AB$66,1,$B$4),"") | F14: =IFERROR(INDEX(Semanal!$C$67:$AB$67,1,$B$4),"") | G14: =Semanal!$AE$43
