Workbook

Sheet Inicio
B2: Métricas diarias · Embudo de webinar gratuito
B3: Las métricas diarias de todo el embudo, para saber cómo estás con tus propios números. Acompaña al modelo financiero del mismo embudo.
B5: Qué es
B6: Un registro diario de cada paso del embudo (anuncios, página, unidades, etapas, ventas, cash) que se convierte solo en un comparativo semanal y en un resumen con semáforo. El semáforo no usa números de mercado: compara cada semana con la mediana de tus 4 semanas anteriores, con una tolerancia del 25 % (la cambiás en Config).
B8: 1. Config
B9: Poné tus precios, comisiones, reembolsos, costos fijos por día y la fecha de inicio (un lunes). Todo lo demás se calcula con eso.
B11: 2. Diario (todos los días, 3 minutos)
B12: Una fila por día. Cargá las celdas amarillas con lo que hubo: inversión, impresiones, alcance, clics en el enlace, visitas y cada paso del embudo. Si un día no hubo evento, dejá vacío. Las celdas azules se calculan solas (CPM, CTR, costo por visita, CPL, conversiones, facturado, cash neto, ganancia, ROAS y la ganancia por visita).
B14: 3. Semanal (los lunes, 10 minutos)
B15: No se carga nada: suma Diario por semana y calcula las conversiones y los costos de la semana, el promedio, la mediana, la mejor y la peor. Abajo, el bloque «contra tu promedio» marca en verde, amarillo o rojo cada métrica clave contra la mediana de tus 4 semanas anteriores.
B17: 4. Resumen
B18: La semana elegida (por defecto la última con datos) contra la anterior, contra tu mediana y contra la meta que vos escribas. Las filas van en el orden en que se mira un embudo: primero el tráfico y la ganancia por visita, después la página, después las etapas, después las ventas y la caja.
... B36: Modelo financiero de embudos · creado por Jesús Tassarolo · TooAudience · youtube.com/@JesusTassaroloSinFiltro · v1.2 · octubre 2026

Sheet Config
B2: Config: tus precios, comisiones y la fecha de inicio
B3: Amarillo = podés cambiarlo. Todo lo demás del libro se calcula con esto.
B5: Dato | C5: Valor | D5: Nota
B6: Fecha de inicio del registro (un lunes) | C6: 46272 | D6: Desde este día se numeran las semanas en Diario y Semanal. Elegí un lunes.
B7: Precio de la oferta del webinar | C7: 297
B8: Precio del bump | C8: 47
B9: Precio del programa superior | C9: 997
B10: Comisión de la pasarela de pago | C10: 0.1 | D10: Lo que se queda la plataforma de cobro.
B11: Comisión del equipo de ventas | C11: 0 | D11: Si vendés por llamada: lo que cobra el closer sobre lo cobrado.
B12: Reembolsos y contracargos | C12: 0.05 | D12: Promedio histórico. 5 % es normal en productos digitales.
B13: Costos fijos por día (USD) | C13: 170 | D13: Lo que pagás aunque no vendas, dividido por los días del período.
B14: ROAS objetivo sobre cash neto | C14: 2 | D14: El retorno mínimo que querés por cada dólar, ya neto.
B15: Tolerancia del semáforo contra tu promedio | C15: 0.25 | D15: Igual o mejor que tu mediana = verde; hasta esta distancia peor = amarillo; más = rojo. 20 a 30 %.
A18: Modelo financiero de embudos · creado por Jesús Tassarolo · TooAudience · youtube.com/@JesusTassaroloSinFiltro · v1.2 · octubre 2026

Sheet Diario
A2: Diario: una fila por día. Amarillo = lo que cargás; azul = lo que calcula el libro
A3: Cargá cada día lo que hubo (vacío si no hubo). Los porcentajes de un solo día pueden ser raros en embudos con evento semanal: la lectura buena está en Semanal.
A5: Fecha | B5: Semana | C5: Inversión en publicidad (USD) | D5: Impresiones | E5: Alcance (personas únicas) | F5: Clics en el enlace | G5: Visitas a la página | H5: Registros (leads) | I5: Registros calificados | J5: Entran al grupo de WhatsApp | K5: Asistentes en vivo | L5: Ven el replay | M5: Solicitudes (formulario de compra, aplicación o vendedor) | N5: Compran la oferta | O5: Toman el bump | P5: Pasan al programa superior | Q5: CPM | R5: Frecuencia | S5: CTR al enlace | T5: CPC (por clic en el enlace) | U5: % clic → visita | V5: Costo por visita | W5: Visitas por cada 1.000 impresiones | X5: % visita → registro (conversión de la landing) | Y5: CPL (costo por registro) | Z5: CPL calificado | AA5: CPL como % del CPM (el umbral depende del nicho) | AB5: Registros por cada 1.000 impresiones | AC5: % registro → grupo | AD5: Costo por persona en el grupo | AE5: % registro → en vivo | AF5: % registro → replay | AG5: Costo por asistente en vivo | AH5: % en vivo → solicitud | AI5: Costo por solicitud | AJ5: % solicitud → compra | AK5: % registro → compra | AL5: CPA (costo por comprador) | AM5: % toman el bump | AN5: % pasan al programa | AO5: Facturado (oferta + bump + programa) | AP5: Order value (facturado por comprador) | AQ5: Cash neto (después de comisiones y reembolsos) | AR5: Ganancia (cash neto − pauta − fijos) | AS5: ROAS sobre cash neto | AT5: Ganancia por visita (la métrica más valiosa) | AU5: Margen por visita (ganancia por visita ÷ costo por visita) | AV5: Ganancia por registro
A6: =Config!$C$6+0 | B6: =INT((A6-Config!$C$6)/7)+1 | C6: 847 | D6: 185605 | E6: 112303 | F6: 4050 | G6: 3652 | H6: 857 | I6: 514 | J6: 575 | Q6: =IF(COUNT(C6:P6)=0,"",IFERROR(C6/D6*1000,0)) | R6: =IF(COUNT(C6:P6)=0,"",IFERROR(D6/E6,0)) | S6: =IF(COUNT(C6:P6)=0,"",IFERROR(F6/D6,0)) | T6: =IF(COUNT(C6:P6)=0,"",IFERROR(C6/F6,0)) | U6: =IF(COUNT(C6:P6)=0,"",IFERROR(G6/F6,0)) | V6: =IF(COUNT(C6:P6)=0,"",IFERROR(C6/G6,0)) | W6: =IF(COUNT(C6:P6)=0,"",IFERROR(G6/D6*1000,0)) | X6: =IF(COUNT(C6:P6)=0,"",IFERROR(H6/G6,0)) | Y6: =IF(COUNT(C6:P6)=0,"",IFERROR(C6/H6,0)) | Z6: =IF(COUNT(C6:P6)=0,"",IFERROR(C6/I6,0)) | AA6: =IF(COUNT(C6:P6)=0,"",IFERROR(Y6/Q6,0)) | AB6: =IF(COUNT(C6:P6)=0,"",IFERROR(H6/D6*1000,0)) | AC6: =IF(COUNT(C6:P6)=0,"",IFERROR(J6/H6,0)) | AD6: =IF(COUNT(C6:P6)=0,"",IFERROR(C6/J6,0)) | AE6: =IF(COUNT(C6:P6)=0,"",IFERROR(K6/H6,0)) | AF6: =IF(COUNT(C6:P6)=0,"",IFERROR(L6/H6,0)) | AG6: =IF(COUNT(C6:P6)=0,"",IFERROR(C6/K6,0)) | AH6: =IF(COUNT(C6:P6)=0,"",IFERROR(M6/K6,0)) | AI6: =IF(COUNT(C6:P6)=0,"",IFERROR(C6/M6,0)) | AJ6: =IF(COUNT(C6:P6)=0,"",IFERROR(N6/M6,0)) | AK6: =IF(COUNT(C6:P6)=0,"",IFERROR(N6/H6,0)) | AL6: =IF(COUNT(C6:P6)=0,"",IFERROR(C6/N6,0)) | AM6: =IF(COUNT(C6:P6)=0,"",IFERROR(O6/N6,0)) | AN6: =IF(COUNT(C6:P6)=0,"",IFERROR(P6/N6,0)) | AO6: =IF(COUNT(C6:P6)=0,"",IFERROR(N6*Config!$C$7+O6*Config!$C$8+P6*Config!$C$9,0)) | AP6: =IF(COUNT(C6:P6)=0,"",IFERROR(AO6/N6,0)) | AQ6: =IF(COUNT(C6:P6)=0,"",IFERROR(AO6*(1-Config!$C$10-Config!$C$11-Config!$C$12),0)) | AR6: =IF(COUNT(C6:P6)=0,"",IFERROR(AQ6-C6-Config!$C$13,0)) | AS6: =IF(COUNT(C6:P6)=0,"",IFERROR(AQ6/C6,0)) | AT6: =IF(COUNT(C6:P6)=0,"",IFERROR(AR6/G6,0)) | AU6: =IF(COUNT(C6:P6)=0,"",IFERROR(AT6/V6,0)) | AV6: =IF(COUNT(C6:P6)=0,"",IFERROR(AR6/H6,0))
A7: =Config!$C$6+1 | B7: =INT((A7-Config!$C$6)/7)+1 | C7: 859 | D7: 185215 | E7: 115365 | F7: 3678 | G7: 3154 | H7: 654 | I7: 392 | J7: 438 | Q7: =IF(COUNT(C7:P7)=0,"",IFERROR(C7/D7*1000,0)) | R7: =IF(COUNT(C7:P7)=0,"",IFERROR(D7/E7,0)) | S7: =IF(COUNT(C7:P7)=0,"",IFERROR(F7/D7,0)) | T7: =IF(COUNT(C7:P7)=0,"",IFERROR(C7/F7,0)) | U7: =IF(COUNT(C7:P7)=0,"",IFERROR(G7/F7,0)) | V7: =IF(COUNT(C7:P7)=0,"",IFERROR(C7/G7,0)) | W7: =IF(COUNT(C7:P7)=0,"",IFERROR(G7/D7*1000,0)) | X7: =IF(COUNT(C7:P7)=0,"",IFERROR(H7/G7,0)) | Y7: =IF(COUNT(C7:P7)=0,"",IFERROR(C7/H7,0)) | Z7: =IF(COUNT(C7:P7)=0,"",IFERROR(C7/I7,0)) | AA7: =IF(COUNT(C7:P7)=0,"",IFERROR(Y7/Q7,0)) | AB7: =IF(COUNT(C7:P7)=0,"",IFERROR(H7/D7*1000,0)) | AC7: =IF(COUNT(C7:P7)=0,"",IFERROR(J7/H7,0)) | AD7: =IF(COUNT(C7:P7)=0,"",IFERROR(C7/J7,0)) | AE7: =IF(COUNT(C7:P7)=0,"",IFERROR(K7/H7,0)) | AF7: =IF(COUNT(C7:P7)=0,"",IFERROR(L7/H7,0)) | AG7: =IF(COUNT(C7:P7)=0,"",IFERROR(C7/K7,0)) | AH7: =IF(COUNT(C7:P7)=0,"",IFERROR(M7/K7,0)) | AI7: =IF(COUNT(C7:P7)=0,"",IFERROR(C7/M7,0)) | AJ7: =IF(COUNT(C7:P7)=0,"",IFERROR(N7/M7,0)) | AK7: =IF(COUNT(C7:P7)=0,"",IFERROR(N7/H7,0)) | AL7: =IF(COUNT(C7:P7)=0,"",IFERROR(C7/N7,0)) | AM7: =IF(COUNT(C7:P7)=0,"",IFERROR(O7/N7,0)) | AN7: =IF(COUNT(C7:P7)=0,"",IFERROR(P7/N7,0)) | AO7: =IF(COUNT(C7:P7)=0,"",IFERROR(N7*Config!$C$7+O7*Config!$C$8+P7*Config!$C$9,0)) | AP7: =IF(COUNT(C7:P7)=0,"",IFERROR(AO7/N7,0)) | AQ7: =IF(COUNT(C7:P7)=0,"",IFERROR(AO7*(1-Config!$C$10-Config!$C$11-Config!$C$12),0)) | AR7: =IF(COUNT(C7:P7)=0,"",IFERROR(AQ7-C7-Config!$C$13,0)) | AS7: =IF(COUNT(C7:P7)=0,"",IFERROR(AQ7/C7,0)) | AT7: =IF(COUNT(C7:P7)=0,"",IFERROR(AR7/G7,0)) | AU7: =IF(COUNT(C7:P7)=0,"",IFERROR(AT7/V7,0)) | AV7: =IF(COUNT(C7:P7)=0,"",IFERROR(AR7/H7,0))
A8: =Config!$C$6+2 | B8: =INT((A8-Config!$C$6)/7)+1 | C8: 897 | D8: 223904 | E8: 133787 | F8: 5475 | G8: 5110 | H8: 1208 | I8: 725 | J8: 809 | Q8: =IF(COUNT(C8:P8)=0,"",IFERROR(C8/D8*1000,0)) | R8: =IF(COUNT(C8:P8)=0,"",IFERROR(D8/E8,0)) | S8: =IF(COUNT(C8:P8)=0,"",IFERROR(F8/D8,0)) | T8: =IF(COUNT(C8:P8)=0,"",IFERROR(C8/F8,0)) | U8: =IF(COUNT(C8:P8)=0,"",IFERROR(G8/F8,0)) | V8: =IF(COUNT(C8:P8)=0,"",IFERROR(C8/G8,0)) | W8: =IF(COUNT(C8:P8)=0,"",IFERROR(G8/D8*1000,0)) | X8: =IF(COUNT(C8:P8)=0,"",IFERROR(H8/G8,0)) | Y8: =IF(COUNT(C8:P8)=0,"",IFERROR(C8/H8,0)) | Z8: =IF(COUNT(C8:P8)=0,"",IFERROR(C8/I8,0)) | AA8: =IF(COUNT(C8:P8)=0,"",IFERROR(Y8/Q8,0)) | AB8: =IF(COUNT(C8:P8)=0,"",IFERROR(H8/D8*1000,0)) | AC8: =IF(COUNT(C8:P8)=0,"",IFERROR(J8/H8,0)) | AD8: =IF(COUNT(C8:P8)=0,"",IFERROR(C8/J8,0)) | AE8: =IF(COUNT(C8:P8)=0,"",IFERROR(K8/H8,0)) | AF8: =IF(COUNT(C8:P8)=0,"",IFERROR(L8/H8,0)) | AG8: =IF(COUNT(C8:P8)=0,"",IFERROR(C8/K8,0)) | AH8: =IF(COUNT(C8:P8)=0,"",IFERROR(M8/K8,0)) | AI8: =IF(COUNT(C8:P8)=0,"",IFERROR(C8/M8,0)) | AJ8: =IF(COUNT(C8:P8)=0,"",IFERROR(N8/M8,0)) | AK8: =IF(COUNT(C8:P8)=0,"",IFERROR(N8/H8,0)) | AL8: =IF(COUNT(C8:P8)=0,"",IFERROR(C8/N8,0)) | AM8: =IF(COUNT(C8:P8)=0,"",IFERROR(O8/N8,0)) | AN8: =IF(COUNT(C8:P8)=0,"",IFERROR(P8/N8,0)) | AO8: =IF(COUNT(C8:P8)=0,"",IFERROR(N8*Config!$C$7+O8*Config!$C$8+P8*Config!$C$9,0)) | AP8: =IF(COUNT(C8:P8)=0,"",IFERROR(AO8/N8,0)) | AQ8: =IF(COUNT(C8:P8)=0,"",IFERROR(AO8*(1-Config!$C$10-Config!$C$11-Config!$C$12),0)) | AR8: =IF(COUNT(C8:P8)=0,"",IFERROR(AQ8-C8-Config!$C$13,0)) | AS8: =IF(COUNT(C8:P8)=0,"",IFERROR(AQ8/C8,0)) | AT8: =IF(COUNT(C8:P8)=0,"",IFERROR(AR8/G8,0)) | AU8: =IF(COUNT(C8:P8)=0,"",IFERROR(AT8/V8,0)) | AV8: =IF(COUNT(C8:P8)=0,"",IFERROR(AR8/H8,0))
A9: =Config!$C$6+3 | B9: =INT((A9-Config!$C$6)/7)+1 | C9: 757 | D9: 167138 | E9: 124596 | F9: 3404 | G9: 2874 | H9: 586 | I9: 352 | J9: 393 | K9: 888 | L9: 1195 | M9: 95 | N9: 38 | O9: 8 | P9: 0 | Q9: =IF(COUNT(C9:P9)=0,"",IFERROR(C9/D9*1000,0)) | R9: =IF(COUNT(C9:P9)=0,"",IFERROR(D9/E9,0)) | S9: =IF(COUNT(C9:P9)=0,"",IFERROR(F9/D9,0)) | T9: =IF(COUNT(C9:P9)=0,"",IFERROR(C9/F9,0)) | U9: =IF(COUNT(C9:P9)=0,"",IFERROR(G9/F9,0)) | V9: =IF(COUNT(C9:P9)=0,"",IFERROR(C9/G9,0)) | W9: =IF(COUNT(C9:P9)=0,"",IFERROR(G9/D9*1000,0)) | X9: =IF(COUNT(C9:P9)=0,"",IFERROR(H9/G9,0)) | Y9: =IF(COUNT(C9:P9)=0,"",IFERROR(C9/H9,0)) | Z9: =IF(COUNT(C9:P9)=0,"",IFERROR(C9/I9,0)) | AA9: =IF(COUNT(C9:P9)=0,"",IFERROR(Y9/Q9,0)) | AB9: =IF(COUNT(C9:P9)=0,"",IFERROR(H9/D9*1000,0)) | AC9: =IF(COUNT(C9:P9)=0,"",IFERROR(J9/H9,0)) | AD9: =IF(COUNT(C9:P9)=0,"",IFERROR(C9/J9,0)) | AE9: =IF(COUNT(C9:P9)=0,"",IFERROR(K9/H9,0)) | AF9: =IF(COUNT(C9:P9)=0,"",IFERROR(L9/H9,0)) | AG9: =IF(COUNT(C9:P9)=0,"",IFERROR(C9/K9,0)) | AH9: =IF(COUNT(C9:P9)=0,"",IFERROR(M9/K9,0)) | AI9: =IF(COUNT(C9:P9)=0,"",IFERROR(C9/M9,0)) | AJ9: =IF(COUNT(C9:P9)=0,"",IFERROR(N9/M9,0)) | AK9: =IF(COUNT(C9:P9)=0,"",IFERROR(N9/H9,0)) | AL9: =IF(COUNT(C9:P9)=0,"",IFERROR(C9/N9,0)) | AM9: =IF(COUNT(C9:P9)=0,"",IFERROR(O9/N9,0)) | AN9: =IF(COUNT(C9:P9)=0,"",IFERROR(P9/N9,0)) | AO9: =IF(COUNT(C9:P9)=0,"",IFERROR(N9*Config!$C$7+O9*Config!$C$8+P9*Config!$C$9,0)) | AP9: =IF(COUNT(C9:P9)=0,"",IFERROR(AO9/N9,0)) | AQ9: =IF(COUNT(C9:P9)=0,"",IFERROR(AO9*(1-Config!$C$10-Config!$C$11-Config!$C$12),0)) | AR9: =IF(COUNT(C9:P9)=0,"",IFERROR(AQ9-C9-Config!$C$13,0)) | AS9: =IF(COUNT(C9:P9)=0,"",IFERROR(AQ9/C9,0)) | AT9: =IF(COUNT(C9:P9)=0,"",IFERROR(AR9/G9,0)) | AU9: =IF(COUNT(C9:P9)=0,"",IFERROR(AT9/V9,0)) | AV9: =IF(COUNT(C9:P9)=0,"",IFERROR(AR9/H9,0))
A10: =Config!$C$6+4 | B10: =INT((A10-Config!$C$6)/7)+1 | C10: 861 | D10: 185087 | E10: 123398 | F10: 4231 | G10: 3769 | H10: 821 | I10: 492 | J10: 550 | L10: 1590 | M10: 110 | N10: 44 | O10: 9 | P10: 2 | Q10: =IF(COUNT(C10:P10)=0,"",IFERROR(C10/D10*1000,0)) | R10: =IF(COUNT(C10:P10)=0,"",IFERROR(D10/E10,0)) | S10: =IF(COUNT(C10:P10)=0,"",IFERROR(F10/D10,0)) | T10: =IF(COUNT(C10:P10)=0,"",IFERROR(C10/F10,0)) | U10: =IF(COUNT(C10:P10)=0,"",IFERROR(G10/F10,0)) | V10: =IF(COUNT(C10:P10)=0,"",IFERROR(C10/G10,0)) | W10: =IF(COUNT(C10:P10)=0,"",IFERROR(G10/D10*1000,0)) | X10: =IF(COUNT(C10:P10)=0,"",IFERROR(H10/G10,0)) | Y10: =IF(COUNT(C10:P10)=0,"",IFERROR(C10/H10,0)) | Z10: =IF(COUNT(C10:P10)=0,"",IFERROR(C10/I10,0)) | AA10: =IF(COUNT(C10:P10)=0,"",IFERROR(Y10/Q10,0)) | AB10: =IF(COUNT(C10:P10)=0,"",IFERROR(H10/D10*1000,0)) | AC10: =IF(COUNT(C10:P10)=0,"",IFERROR(J10/H10,0)) | AD10: =IF(COUNT(C10:P10)=0,"",IFERROR(C10/J10,0)) | AE10: =IF(COUNT(C10:P10)=0,"",IFERROR(K10/H10,0)) | AF10: =IF(COUNT(C10:P10)=0,"",IFERROR(L10/H10,0)) | AG10: =IF(COUNT(C10:P10)=0,"",IFERROR(C10/K10,0)) | AH10: =IF(COUNT(C10:P10)=0,"",IFERROR(M10/K10,0)) | AI10: =IF(COUNT(C10:P10)=0,"",IFERROR(C10/M10,0)) | AJ10: =IF(COUNT(C10:P10)=0,"",IFERROR(N10/M10,0)) | AK10: =IF(COUNT(C10:P10)=0,"",IFERROR(N10/H10,0)) | AL10: =IF(COUNT(C10:P10)=0,"",IFERROR(C10/N10,0)) | AM10: =IF(COUNT(C10:P10)=0,"",IFERROR(O10/N10,0)) | AN10: =IF(COUNT(C10:P10)=0,"",IFERROR(P10/N10,0)) | AO10: =IF(COUNT(C10:P10)=0,"",IFERROR(N10*Config!$C$7+O10*Config!$C$8+P10*Config!$C$9,0)) | AP10: =IF(COUNT(C10:P10)=0,"",IFERROR(AO10/N10,0)) | AQ10: =IF(COUNT(C10:P10)=0,"",IFERROR(AO10*(1-Config!$C$10-Config!$C$11-Config!$C$12),0)) | AR10: =IF(COUNT(C10:P10)=0,"",IFERROR(AQ10-C10-Config!$C$13,0)) | AS10: =IF(COUNT(C10:P10)=0,"",IFERROR(AQ10/C10,0)) | AT10: =IF(COUNT(C10:P10)=0,"",IFERROR(AR10/G10,0)) | AU10: =IF(COUNT(C10:P10)=0,"",IFERROR(AT10/V10,0)) | AV10: =IF(COUNT(C10:P10)=0,"",IFERROR(AR10/H10,0))
A11: =Config!$C$6+5 | B11: =INT((A11-Config!$C$6)/7)+1 | C11: 927 | D11: 196209 | E11: 136874 | F11: 4037 | G11: 3449 | H11: 711 | I11: 427 | J11: 477 | L11: 619 | M11: 33 | N11: 13 | O11: 3 | P11: 1 | Q11: =IF(COUNT(C11:P11)=0,"",IFERROR(C11/D11*1000,0)) | R11: =IF(COUNT(C11:P11)=0,"",IFERROR(D11/E11,0)) | S11: =IF(COUNT(C11:P11)=0,"",IFERROR(F11/D11,0)) | T11: =IF(COUNT(C11:P11)=0,"",IFERROR(C11/F11,0)) | U11: =IF(COUNT(C11:P11)=0,"",IFERROR(G11/F11,0)) | V11: =IF(COUNT(C11:P11)=0,"",IFERROR(C11/G11,0)) | W11: =IF(COUNT(C11:P11)=0,"",IFERROR(G11/D11*1000,0)) | X11: =IF(COUNT(C11:P11)=0,"",IFERROR(H11/G11,0)) | Y11: =IF(COUNT(C11:P11)=0,"",IFERROR(C11/H11,0)) | Z11: =IF(COUNT(C11:P11)=0,"",IFERROR(C11/I11,0)) | AA11: =IF(COUNT(C11:P11)=0,"",IFERROR(Y11/Q11,0)) | AB11: =IF(COUNT(C11:P11)=0,"",IFERROR(H11/D11*1000,0)) | AC11: =IF(COUNT(C11:P11)=0,"",IFERROR(J11/H11,0)) | AD11: =IF(COUNT(C11:P11)=0,"",IFERROR(C11/J11,0)) | AE11: =IF(COUNT(C11:P11)=0,"",IFERROR(K11/H11,0)) | AF11: =IF(COUNT(C11:P11)=0,"",IFERROR(L11/H11,0)) | AG11: =IF(COUNT(C11:P11)=0,"",IFERROR(C11/K11,0)) | AH11: =IF(COUNT(C11:P11)=0,"",IFERROR(M11/K11,0)) | AI11: =IF(COUNT(C11:P11)=0,"",IFERROR(C11/M11,0)) | AJ11: =IF(COUNT(C11:P11)=0,"",IFERROR(N11/M11,0)) | AK11: =IF(COUNT(C11:P11)=0,"",IFERROR(N11/H11,0)) | AL11: =IF(COUNT(C11:P11)=0,"",IFERROR(C11/N11,0)) | AM11: =IF(COUNT(C11:P11)=0,"",IFERROR(O11/N11,0)) | AN11: =IF(COUNT(C11:P11)=0,"",IFERROR(P11/N11,0)) | AO11: =IF(COUNT(C11:P11)=0,"",IFERROR(N11*Config!$C$7+O11*Config!$C$8+P11*Config!$C$9,0)) | AP11: =IF(COUNT(C11:P11)=0,"",IFERROR(AO11/N11,0)) | AQ11: =IF(COUNT(C11:P11)=0,"",IFERROR(AO11*(1-Config!$C$10-Config!$C$11-Config!$C$12),0)) | AR11: =IF(COUNT(C11:P11)=0,"",IFERROR(AQ11-C11-Config!$C$13,0)) | AS11: =IF(COUNT(C11:P11)=0,"",IFERROR(AQ11/C11,0)) | AT11: =IF(COUNT(C11:P11)=0,"",IFERROR(AR11/G11,0)) | AU11: =IF(COUNT(C11:P11)=0,"",IFERROR(AT11/V11,0)) | AV11: =IF(COUNT(C11:P11)=0,"",IFERROR(AR11/H11,0))
A12: =Config!$C$6+6 | B12: =INT((A12-Config!$C$6)/7)+1 | C12: 928 | D12: 212061 | E12: 127372 | F12: 5054 | G12: 4004 | H12: 857 | I12: 514 | J12: 574 | Q12: =IF(COUNT(C12:P12)=0,"",IFERROR(C12/D12*1000,0)) | R12: =IF(COUNT(C12:P12)=0,"",IFERROR(D12/E12,0)) | S12: =IF(COUNT(C12:P12)=0,"",IFERROR(F12/D12,0)) | T12: =IF(COUNT(C12:P12)=0,"",IFERROR(C12/F12,0)) | U12: =IF(COUNT(C12:P12)=0,"",IFERROR(G12/F12,0)) | V12: =IF(COUNT(C12:P12)=0,"",IFERROR(C12/G12,0)) | W12: =IF(COUNT(C12:P12)=0,"",IFERROR(G12/D12*1000,0)) | X12: =IF(COUNT(C12:P12)=0,"",IFERROR(H12/G12,0)) | Y12: =IF(COUNT(C12:P12)=0,"",IFERROR(C12/H12,0)) | Z12: =IF(COUNT(C12:P12)=0,"",IFERROR(C12/I12,0)) | AA12: =IF(COUNT(C12:P12)=0,"",IFERROR(Y12/Q12,0)) | AB12: =IF(COUNT(C12:P12)=0,"",IFERROR(H12/D12*1000,0)) | AC12: =IF(COUNT(C12:P12)=0,"",IFERROR(J12/H12,0)) | AD12: =IF(COUNT(C12:P12)=0,"",IFERROR(C12/J12,0)) | AE12: =IF(COUNT(C12:P12)=0,"",IFERROR(K12/H12,0)) | AF12: =IF(COUNT(C12:P12)=0,"",IFERROR(L12/H12,0)) | AG12: =IF(COUNT(C12:P12)=0,"",IFERROR(C12/K12,0)) | AH12: =IF(COUNT(C12:P12)=0,"",IFERROR(M12/K12,0)) | AI12: =IF(COUNT(C12:P12)=0,"",IFERROR(C12/M12,0)) | AJ12: =IF(COUNT(C12:P12)=0,"",IFERROR(N12/M12,0)) | AK12: =IF(COUNT(C12:P12)=0,"",IFERROR(N12/H12,0)) | AL12: =IF(COUNT(C12:P12)=0,"",IFERROR(C12/N12,0)) | AM12: =IF(COUNT(C12:P12)=0,"",IFERROR(O12/N12,0)) | AN12: =IF(COUNT(C12:P12)=0,"",IFERROR(P12/N12,0)) | AO12: =IF(COUNT(C12:P12)=0,"",IFERROR(N12*Config!$C$7+O12*Config!$C$8+P12*Config!$C$9,0)) | AP12: =IF(COUNT(C12:P12)=0,"",IFERROR(AO12/N12,0)) | AQ12: =IF(COUNT(C12:P12)=0,"",IFERROR(AO12*(1-Config!$C$10-Config!$C$11-Config!$C$12),0)) | AR12: =IF(COUNT(C12:P12)=0,"",IFERROR(AQ12-C12-Config!$C$13,0)) | AS12: =IF(COUNT(C12:P12)=0,"",IFERROR(AQ12/C12,0)) | AT12: =IF(COUNT(C12:P12)=0,"",IFERROR(AR12/G12,0)) | AU12: =IF(COUNT(C12:P12)=0,"",IFERROR(AT12/V12,0)) | AV12: =IF(COUNT(C12:P12)=0,"",IFERROR(AR12/H12,0))
A13: =Config!$C$6+7 | B13: =INT((A13-Config!$C$6)/7)+1 | C13: 851 | D13: 169528 | E13: 115871 | F13: 3347 | G13: 3106 | H13: 762 | I13: 457 | J13: 511 | Q13: =IF(COUNT(C13:P13)=0,"",IFERROR(C13/D13*1000,0)) | R13: =IF(COUNT(C13:P13)=0,"",IFERROR(D13/E13,0)) | S13: =IF(COUNT(C13:P13)=0,"",IFERROR(F13/D13,0)) | T13: =IF(COUNT(C13:P13)=0,"",IFERROR(C13/F13,0)) | U13: =IF(COUNT(C13:P13)=0,"",IFERROR(G13/F13,0)) | V13: =IF(COUNT(C13:P13)=0,"",IFERROR(C13/G13,0)) | W13: =IF(COUNT(C13:P13)=0,"",IFERROR(G13/D13*1000,0)) | X13: =IF(COUNT(C13:P13)=0,"",IFERROR(H13/G13,0)) | Y13: =IF(COUNT(C13:P13)=0,"",IFERROR(C13/H13,0)) | Z13: =IF(COUNT(C13:P13)=0,"",IFERROR(C13/I13,0)) | AA13: =IF(COUNT(C13:P13)=0,"",IFERROR(Y13/Q13,0)) | AB13: =IF(COUNT(C13:P13)=0,"",IFERROR(H13/D13*1000,0)) | AC13: =IF(COUNT(C13:P13)=0,"",IFERROR(J13/H13,0)) | AD13: =IF(COUNT(C13:P13)=0,"",IFERROR(C13/J13,0)) | AE13: =IF(COUNT(C13:P13)=0,"",IFERROR(K13/H13,0)) | AF13: =IF(COUNT(C13:P13)=0,"",IFERROR(L13/H13,0)) | AG13: =IF(COUNT(C13:P13)=0,"",IFERROR(C13/K13,0)) | AH13: =IF(COUNT(C13:P13)=0,"",IFERROR(M13/K13,0)) | AI13: =IF(COUNT(C13:P13)=0,"",IFERROR(C13/M13,0)) | AJ13: =IF(COUNT(C13:P13)=0,"",IFERROR(N13/M13,0)) | AK13: =IF(COUNT(C13:P13)=0,"",IFERROR(N13/H13,0)) | AL13: =IF(COUNT(C13:P13)=0,"",IFERROR(C13/N13,0)) | AM13: =IF(COUNT(C13:P13)=0,"",IFERROR(O13/N13,0)) | AN13: =IF(COUNT(C13:P13)=0,"",IFERROR(P13/N13,0)) | AO13: =IF(COUNT(C13:P13)=0,"",IFERROR(N13*Config!$C$7+O13*Config!$C$8+P13*Config!$C$9,0)) | AP13: =IF(COUNT(C13:P13)=0,"",IFERROR(AO13/N13,0)) | AQ13: =IF(COUNT(C13:P13)=0,"",IFERROR(AO13*(1-Config!$C$10-Config!$C$11-Config!$C$12),0)) | AR13: =IF(COUNT(C13:P13)=0,"",IFERROR(AQ13-C13-Config!$C$13,0)) | AS13: =IF(COUNT(C13:P13)=0,"",IFERROR(AQ13/C13,0)) | AT13: =IF(COUNT(C13:P13)=0,"",IFERROR(AR13/G13,0)) | AU13: =IF(COUNT(C13:P13)=0,"",IFERROR(AT13/V13,0)) | AV13: =IF(COUNT(C13:P13)=0,"",IFERROR(AR13/H13,0))
A14: =Config!$C$6+8 | B14: =INT((A14-Config!$C$6)/7)+1 | C14: 772 | D14: 178757 | E14: 107228 | F14: 4176 | G14: 3414 | H14: 737 | I14: 442 | J14: 494 | Q14: =IF(COUNT(C14:P14)=0,"",IFERROR(C14/D14*1000,0)) | R14: =IF(COUNT(C14:P14)=0,"",IFERROR(D14/E14,0)) | S14: =IF(COUNT(C14:P14)=0,"",IFERROR(F14/D14,0)) | T14: =IF(COUNT(C14:P14)=0,"",IFERROR(C14/F14,0)) | U14: =IF(COUNT(C14:P14)=0,"",IFERROR(G14/F14,0)) | V14: =IF(COUNT(C14:P14)=0,"",IFERROR(C14/G14,0)) | W14: =IF(COUNT(C14:P14)=0,"",IFERROR(G14/D14*1000,0)) | X14: =IF(COUNT(C14:P14)=0,"",IFERROR(H14/G14,0)) | Y14: =IF(COUNT(C14:P14)=0,"",IFERROR(C14/H14,0)) | Z14: =IF(COUNT(C14:P14)=0,"",IFERROR(C14/I14,0)) | AA14: =IF(COUNT(C14:P14)=0,"",IFERROR(Y14/Q14,0)) | AB14: =IF(COUNT(C14:P14)=0,"",IFERROR(H14/D14*1000,0)) | AC14: =IF(COUNT(C14:P14)=0,"",IFERROR(J14/H14,0)) | AD14: =IF(COUNT(C14:P14)=0,"",IFERROR(C14/J14,0)) | AE14: =IF(COUNT(C14:P14)=0,"",IFERROR(K14/H14,0)) | AF14: =IF(COUNT(C14:P14)=0,"",IFERROR(L14/H14,0)) | AG14: =IF(COUNT(C14:P14)=0,"",IFERROR(C14/K14,0)) | AH14: =IF(COUNT(C14:P14)=0,"",IFERROR(M14/K14,0)) | AI14: =IF(COUNT(C14:P14)=0,"",IFERROR(C14/M14,0)) | AJ14: =IF(COUNT(C14:P14)=0,"",IFERROR(N14/M14,0)) | AK14: =IF(COUNT(C14:P14)=0,"",IFERROR(N14/H14,0)) | AL14: =IF(COUNT(C14:P14)=0,"",IFERROR(C14/N14,0)) | AM14: =IF(COUNT(C14:P14)=0,"",IFERROR(O14/N14,0)) | AN14: =IF(COUNT(C14:P14)=0,"",IFERROR(P14/N14,0)) | AO14: =IF(COUNT(C14:P14)=0,"",IFERROR(N14*Config!$C$7+O14*Config!$C$8+P14*Config!$C$9,0)) | AP14: =IF(COUNT(C14:P14)=0,"",IFERROR(AO14/N14,0)) | AQ14: =IF(COUNT(C14:P14)=0,"",IFERROR(AO14*(1-Config!$C$10-Config!$C$11-Config!$C$12),0)) | AR14: =IF(COUNT(C14:P14)=0,"",IFERROR(AQ14-C14-Config!$C$13,0)) | AS14: =IF(COUNT(C14:P14)=0,"",IFERROR(AQ14/C14,0)) | AT14: =IF(COUNT(C14:P14)=0,"",IFERROR(AR14/G14,0)) | AU14: =IF(COUNT(C14:P14)=0,"",IFERROR(AT14/V14,0)) | AV14: =IF(COUNT(C14:P14)=0,"",IFERROR(AR14/H14,0))
A15: =Config!$C$6+9 | B15: =INT((A15-Config!$C$6)/7)+1 | C15: 766 | D15: 158995 | E15: 114884 | F15: 3548 | G15: 3153 | H15: 671 | I15: 403 | J15: 450 | Q15: =IF(COUNT(C15:P15)=0,"",IFERROR(C15/D15*1000,0)) | R15: =IF(COUNT(C15:P15)=0,"",IFERROR(D15/E15,0)) | S15: =IF(COUNT(C15:P15)=0,"",IFERROR(F15/D15,0)) | T15: =IF(COUNT(C15:P15)=0,"",IFERROR(C15/F15,0)) | U15: =IF(COUNT(C15:P15)=0,"",IFERROR(G15/F15,0)) | V15: =IF(COUNT(C15:P15)=0,"",IFERROR(C15/G15,0)) | W15: =IF(COUNT(C15:P15)=0,"",IFERROR(G15/D15*1000,0)) | X15: =IF(COUNT(C15:P15)=0,"",IFERROR(H15/G15,0)) | Y15: =IF(COUNT(C15:P15)=0,"",IFERROR(C15/H15,0)) | Z15: =IF(COUNT(C15:P15)=0,"",IFERROR(C15/I15,0)) | AA15: =IF(COUNT(C15:P15)=0,"",IFERROR(Y15/Q15,0)) | AB15: =IF(COUNT(C15:P15)=0,"",IFERROR(H15/D15*1000,0)) | AC15: =IF(COUNT(C15:P15)=0,"",IFERROR(J15/H15,0)) | AD15: =IF(COUNT(C15:P15)=0,"",IFERROR(C15/J15,0)) | AE15: =IF(COUNT(C15:P15)=0,"",IFERROR(K15/H15,0)) | AF15: =IF(COUNT(C15:P15)=0,"",IFERROR(L15/H15,0)) | AG15: =IF(COUNT(C15:P15)=0,"",IFERROR(C15/K15,0)) | AH15: =IF(COUNT(C15:P15)=0,"",IFERROR(M15/K15,0)) | AI15: =IF(COUNT(C15:P15)=0,"",IFERROR(C15/M15,0)) | AJ15: =IF(COUNT(C15:P15)=0,"",IFERROR(N15/M15,0)) | AK15: =IF(COUNT(C15:P15)=0,"",IFERROR(N15/H15,0)) | AL15: =IF(COUNT(C15:P15)=0,"",IFERROR(C15/N15,0)) | AM15: =IF(COUNT(C15:P15)=0,"",IFERROR(O15/N15,0)) | AN15: =IF(COUNT(C15:P15)=0,"",IFERROR(P15/N15,0)) | AO15: =IF(COUNT(C15:P15)=0,"",IFERROR(N15*Config!$C$7+O15*Config!$C$8+P15*Config!$C$9,0)) | AP15: =IF(COUNT(C15:P15)=0,"",IFERROR(AO15/N15,0)) | AQ15: =IF(COUNT(C15:P15)=0,"",IFERROR(AO15*(1-Config!$C$10-Config!$C$11-Config!$C$12),0)) | AR15: =IF(COUNT(C15:P15)=0,"",IFERROR(AQ15-C15-Config!$C$13,0)) | AS15: =IF(COUNT(C15:P15)=0,"",IFERROR(AQ15/C15,0)) | AT15: =IF(COUNT(C15:P15)=0,"",IFERROR(AR15/G15,0)) | AU15: =IF(COUNT(C15:P15)=0,"",IFERROR(AT15/V15,0)) | AV15: =IF(COUNT(C15:P15)=0,"",IFERROR(AR15/H15,0))
A16: =Config!$C$6+10 | B16: =INT((A16-Config!$C$6)/7)+1 | C16: 781 | D16: 167790 | E16: 123199 | F16: 3621 | G16: 3034 | H16: 659 | I16: 396 | J16: 442 | K16: 997 | L16: 1268 | M16: 96 | N16: 38 | O16: 8 | P16: 0 | Q16: =IF(COUNT(C16:P16)=0,"",IFERROR(C16/D16*1000,0)) | R16: =IF(COUNT(C16:P16)=0,"",IFERROR(D16/E16,0)) | S16: =IF(COUNT(C16:P16)=0,"",IFERROR(F16/D16,0)) | T16: =IF(COUNT(C16:P16)=0,"",IFERROR(C16/F16,0)) | U16: =IF(COUNT(C16:P16)=0,"",IFERROR(G16/F16,0)) | V16: =IF(COUNT(C16:P16)=0,"",IFERROR(C16/G16,0)) | W16: =IF(COUNT(C16:P16)=0,"",IFERROR(G16/D16*1000,0)) | X16: =IF(COUNT(C16:P16)=0,"",IFERROR(H16/G16,0)) | Y16: =IF(COUNT(C16:P16)=0,"",IFERROR(C16/H16,0)) | Z16: =IF(COUNT(C16:P16)=0,"",IFERROR(C16/I16,0)) | AA16: =IF(COUNT(C16:P16)=0,"",IFERROR(Y16/Q16,0)) | AB16: =IF(COUNT(C16:P16)=0,"",IFERROR(H16/D16*1000,0)) | AC16: =IF(COUNT(C16:P16)=0,"",IFERROR(J16/H16,0)) | AD16: =IF(COUNT(C16:P16)=0,"",IFERROR(C16/J16,0)) | AE16: =IF(COUNT(C16:P16)=0,"",IFERROR(K16/H16,0)) | AF16: =IF(COUNT(C16:P16)=0,"",IFERROR(L16/H16,0)) | AG16: =IF(COUNT(C16:P16)=0,"",IFERROR(C16/K16,0)) | AH16: =IF(COUNT(C16:P16)=0,"",IFERROR(M16/K16,0)) | AI16: =IF(COUNT(C16:P16)=0,"",IFERROR(C16/M16,0)) | AJ16: =IF(COUNT(C16:P16)=0,"",IFERROR(N16/M16,0)) | AK16: =IF(COUNT(C16:P16)=0,"",IFERROR(N16/H16,0)) | AL16: =IF(COUNT(C16:P16)=0,"",IFERROR(C16/N16,0)) | AM16: =IF(COUNT(C16:P16)=0,"",IFERROR(O16/N16,0)) | AN16: =IF(COUNT(C16:P16)=0,"",IFERROR(P16/N16,0)) | AO16: =IF(COUNT(C16:P16)=0,"",IFERROR(N16*Config!$C$7+O16*Config!$C$8+P16*Config!$C$9,0)) | AP16: =IF(COUNT(C16:P16)=0,"",IFERROR(AO16/N16,0)) | AQ16: =IF(COUNT(C16:P16)=0,"",IFERROR(AO16*(1-Config!$C$10-Config!$C$11-Config!$C$12),0)) | AR16: =IF(COUNT(C16:P16)=0,"",IFERROR(AQ16-C16-Config!$C$13,0)) | AS16: =IF(COUNT(C16:P16)=0,"",IFERROR(AQ16/C16,0)) | AT16: =IF(COUNT(C16:P16)=0,"",IFERROR(AR16/G16,0)) | AU16: =IF(COUNT(C16:P16)=0,"",IFERROR(AT16/V16,0)) | AV16: =IF(COUNT(C16:P16)=0,"",IFERROR(AR16/H16,0))
A17: =Config!$C$6+11 | B17: =INT((A17-Config!$C$6)/7)+1 | C17: 936 | D17: 223557 | E17: 152918 | F17: 5337 | G17: 4966 | H17: 1033 | I17: 620 | J17: 692 | L17: 1588 | M17: 87 | N17: 35 | O17: 7 | P17: 2 | Q17: =IF(COUNT(C17:P17)=0,"",IFERROR(C17/D17*1000,0)) | R17: =IF(COUNT(C17:P17)=0,"",IFERROR(D17/E17,0)) | S17: =IF(COUNT(C17:P17)=0,"",IFERROR(F17/D17,0)) | T17: =IF(COUNT(C17:P17)=0,"",IFERROR(C17/F17,0)) | U17: =IF(COUNT(C17:P17)=0,"",IFERROR(G17/F17,0)) | V17: =IF(COUNT(C17:P17)=0,"",IFERROR(C17/G17,0)) | W17: =IF(COUNT(C17:P17)=0,"",IFERROR(G17/D17*1000,0)) | X17: =IF(COUNT(C17:P17)=0,"",IFERROR(H17/G17,0)) | Y17: =IF(COUNT(C17:P17)=0,"",IFERROR(C17/H17,0)) | Z17: =IF(COUNT(C17:P17)=0,"",IFERROR(C17/I17,0)) | AA17: =IF(COUNT(C17:P17)=0,"",IFERROR(Y17/Q17,0)) | AB17: =IF(COUNT(C17:P17)=0,"",IFERROR(H17/D17*1000,0)) | AC17: =IF(COUNT(C17:P17)=0,"",IFERROR(J17/H17,0)) | AD17: =IF(COUNT(C17:P17)=0,"",IFERROR(C17/J17,0)) | AE17: =IF(COUNT(C17:P17)=0,"",IFERROR(K17/H17,0)) | AF17: =IF(COUNT(C17:P17)=0,"",IFERROR(L17/H17,0)) | AG17: =IF(COUNT(C17:P17)=0,"",IFERROR(C17/K17,0)) | AH17: =IF(COUNT(C17:P17)=0,"",IFERROR(M17/K17,0)) | AI17: =IF(COUNT(C17:P17)=0,"",IFERROR(C17/M17,0)) | AJ17: =IF(COUNT(C17:P17)=0,"",IFERROR(N17/M17,0)) | AK17: =IF(COUNT(C17:P17)=0,"",IFERROR(N17/H17,0)) | AL17: =IF(COUNT(C17:P17)=0,"",IFERROR(C17/N17,0)) | AM17: =IF(COUNT(C17:P17)=0,"",IFERROR(O17/N17,0)) | AN17: =IF(COUNT(C17:P17)=0,"",IFERROR(P17/N17,0)) | AO17: =IF(COUNT(C17:P17)=0,"",IFERROR(N17*Config!$C$7+O17*Config!$C$8+P17*Config!$C$9,0)) | AP17: =IF(COUNT(C17:P17)=0,"",IFERROR(AO17/N17,0)) | AQ17: =IF(COUNT(C17:P17)=0,"",IFERROR(AO17*(1-Config!$C$10-Config!$C$11-Config!$C$12),0)) | AR17: =IF(COUNT(C17:P17)=0,"",IFERROR(AQ17-C17-Config!$C$13,0)) | AS17: =IF(COUNT(C17:P17)=0,"",IFERROR(AQ17/C17,0)) | AT17: =IF(COUNT(C17:P17)=0,"",IFERROR(AR17/G17,0)) | AU17: =IF(COUNT(C17:P17)=0,"",IFERROR(AT17/V17,0)) | AV17: =IF(COUNT(C17:P17)=0,"",IFERROR(AR17/H17,0))
A18: =Config!$C$6+12 | B18: =INT((A18-Config!$C$6)/7)+1 | C18: 807 | D18: 168377 | E18: 117056 | F18: 3523 | G18: 2846 | H18: 590 | I18: 354 | J18: 395 | L18: 606 | M18: 31 | N18: 12 | O18: 2 | P18: 1 | Q18: =IF(COUNT(C18:P18)=0,"",IFERROR(C18/D18*1000,0)) | R18: =IF(COUNT(C18:P18)=0,"",IFERROR(D18/E18,0)) | S18: =IF(COUNT(C18:P18)=0,"",IFERROR(F18/D18,0)) | T18: =IF(COUNT(C18:P18)=0,"",IFERROR(C18/F18,0)) | U18: =IF(COUNT(C18:P18)=0,"",IFERROR(G18/F18,0)) | V18: =IF(COUNT(C18:P18)=0,"",IFERROR(C18/G18,0)) | W18: =IF(COUNT(C18:P18)=0,"",IFERROR(G18/D18*1000,0)) | X18: =IF(COUNT(C18:P18)=0,"",IFERROR(H18/G18,0)) | Y18: =IF(COUNT(C18:P18)=0,"",IFERROR(C18/H18,0)) | Z18: =IF(COUNT(C18:P18)=0,"",IFERROR(C18/I18,0)) | AA18: =IF(COUNT(C18:P18)=0,"",IFERROR(Y18/Q18,0)) | AB18: =IF(COUNT(C18:P18)=0,"",IFERROR(H18/D18*1000,0)) | AC18: =IF(COUNT(C18:P18)=0,"",IFERROR(J18/H18,0)) | AD18: =IF(COUNT(C18:P18)=0,"",IFERROR(C18/J18,0)) | AE18: =IF(COUNT(C18:P18)=0,"",IFERROR(K18/H18,0)) | AF18: =IF(COUNT(C18:P18)=0,"",IFERROR(L18/H18,0)) | AG18: =IF(COUNT(C18:P18)=0,"",IFERROR(C18/K18,0)) | AH18: =IF(COUNT(C18:P18)=0,"",IFERROR(M18/K18,0)) | AI18: =IF(COUNT(C18:P18)=0,"",IFERROR(C18/M18,0)) | AJ18: =IF(COUNT(C18:P18)=0,"",IFERROR(N18/M18,0)) | AK18: =IF(COUNT(C18:P18)=0,"",IFERROR(N18/H18,0)) | AL18: =IF(COUNT(C18:P18)=0,"",IFERROR(C18/N18,0)) | AM18: =IF(COUNT(C18:P18)=0,"",IFERROR(O18/N18,0)) | AN18: =IF(COUNT(C18:P18)=0,"",IFERROR(P18/N18,0)) | AO18: =IF(COUNT(C18:P18)=0,"",IFERROR(N18*Config!$C$7+O18*Config!$C$8+P18*Config!$C$9,0)) | AP18: =IF(COUNT(C18:P18)=0,"",IFERROR(AO18/N18,0)) | AQ18: =IF(COUNT(C18:P18)=0,"",IFERROR(AO18*(1-Config!$C$10-Config!$C$11-Config!$C$12),0)) | AR18: =IF(COUNT(C18:P18)=0,"",IFERROR(AQ18-C18-Config!$C$13,0)) | AS18: =IF(COUNT(C18:P18)=0,"",IFERROR(AQ18/C18,0)) | AT18: =IF(COUNT(C18:P18)=0,"",IFERROR(AR18/G18,0)) | AU18: =IF(COUNT(C18:P18)=0,"",IFERROR(AT18/V18,0)) | AV18: =IF(COUNT(C18:P18)=0,"",IFERROR(AR18/H18,0))
A19: =Config!$C$6+13 | B19: =INT((A19-Config!$C$6)/7)+1 | C19: 878 | D19: 201271 | E19: 135705 | F19: 4916 | G19: 4407 | H19: 1032 | I19: 619 | J19: 691 | Q19: =IF(COUNT(C19:P19)=0,"",IFERROR(C19/D19*1000,0)) | R19: =IF(COUNT(C19:P19)=0,"",IFERROR(D19/E19,0)) | S19: =IF(COUNT(C19:P19)=0,"",IFERROR(F19/D19,0)) | T19: =IF(COUNT(C19:P19)=0,"",IFERROR(C19/F19,0)) | U19: =IF(COUNT(C19:P19)=0,"",IFERROR(G19/F19,0)) | V19: =IF(COUNT(C19:P19)=0,"",IFERROR(C19/G19,0)) | W19: =IF(COUNT(C19:P19)=0,"",IFERROR(G19/D19*1000,0)) | X19: =IF(COUNT(C19:P19)=0,"",IFERROR(H19/G19,0)) | Y19: =IF(COUNT(C19:P19)=0,"",IFERROR(C19/H19,0)) | Z19: =IF(COUNT(C19:P19)=0,"",IFERROR(C19/I19,0)) | AA19: =IF(COUNT(C19:P19)=0,"",IFERROR(Y19/Q19,0)) | AB19: =IF(COUNT(C19:P19)=0,"",IFERROR(H19/D19*1000,0)) | AC19: =IF(COUNT(C19:P19)=0,"",IFERROR(J19/H19,0)) | AD19: =IF(COUNT(C19:P19)=0,"",IFERROR(C19/J19,0)) | AE19: =IF(COUNT(C19:P19)=0,"",IFERROR(K19/H19,0)) | AF19: =IF(COUNT(C19:P19)=0,"",IFERROR(L19/H19,0)) | AG19: =IF(COUNT(C19:P19)=0,"",IFERROR(C19/K19,0)) | AH19: =IF(COUNT(C19:P19)=0,"",IFERROR(M19/K19,0)) | AI19: =IF(COUNT(C19:P19)=0,"",IFERROR(C19/M19,0)) | AJ19: =IF(COUNT(C19:P19)=0,"",IFERROR(N19/M19,0)) | AK19: =IF(COUNT(C19:P19)=0,"",IFERROR(N19/H19,0)) | AL19: =IF(COUNT(C19:P19)=0,"",IFERROR(C19/N19,0)) | AM19: =IF(COUNT(C19:P19)=0,"",IFERROR(O19/N19,0)) | AN19: =IF(COUNT(C19:P19)=0,"",IFERROR(P19/N19,0)) | AO19: =IF(COUNT(C19:P19)=0,"",IFERROR(N19*Config!$C$7+O19*Config!$C$8+P19*Config!$C$9,0)) | AP19: =IF(COUNT(C19:P19)=0,"",IFERROR(AO19/N19,0)) | AQ19: =IF(COUNT(C19:P19)=0,"",IFERROR(AO19*(1-Config!$C$10-Config!$C$11-Config!$C$12),0)) | AR19: =IF(COUNT(C19:P19)=0,"",IFERROR(AQ19-C19-Config!$C$13,0)) | AS19: =IF(COUNT(C19:P19)=0,"",IFERROR(AQ19/C19,0)) | AT19: =IF(COUNT(C19:P19)=0,"",IFERROR(AR19/G19,0)) | AU19: =IF(COUNT(C19:P19)=0,"",IFERROR(AT19/V19,0)) | AV19: =IF(COUNT(C19:P19)=0,"",IFERROR(AR19/H19,0))
A20: =Config!$C$6+14 | B20: =INT((A20-Config!$C$6)/7)+1 | C20: 792 | D20: 191875 | E20: 116497 | F20: 4543 | G20: 3843 | H20: 818 | I20: 491 | J20: 548 | Q20: =IF(COUNT(C20:P20)=0,"",IFERROR(C20/D20*1000,0)) | R20: =IF(COUNT(C20:P20)=0,"",IFERROR(D20/E20,0)) | S20: =IF(COUNT(C20:P20)=0,"",IFERROR(F20/D20,0)) | T20: =IF(COUNT(C20:P20)=0,"",IFERROR(C20/F20,0)) | U20: =IF(COUNT(C20:P20)=0,"",IFERROR(G20/F20,0)) | V20: =IF(COUNT(C20:P20)=0,"",IFERROR(C20/G20,0)) | W20: =IF(COUNT(C20:P20)=0,"",IFERROR(G20/D20*1000,0)) | X20: =IF(COUNT(C20:P20)=0,"",IFERROR(H20/G20,0)) | Y20: =IF(COUNT(C20:P20)=0,"",IFERROR(C20/H20,0)) | Z20: =IF(COUNT(C20:P20)=0,"",IFERROR(C20/I20,0)) | AA20: =IF(COUNT(C20:P20)=0,"",IFERROR(Y20/Q20,0)) | AB20: =IF(COUNT(C20:P20)=0,"",IFERROR(H20/D20*1000,0)) | AC20: =IF(COUNT(C20:P20)=0,"",IFERROR(J20/H20,0)) | AD20: =IF(COUNT(C20:P20)=0,"",IFERROR(C20/J20,0)) | AE20: =IF(COUNT(C20:P20)=0,"",IFERROR(K20/H20,0)) | AF20: =IF(COUNT(C20:P20)=0,"",IFERROR(L20/H20,0)) | AG20: =IF(COUNT(C20:P20)=0,"",IFERROR(C20/K20,0)) | AH20: =IF(COUNT(C20:P20)=0,"",IFERROR(M20/K20,0)) | AI20: =IF(COUNT(C20:P20)=0,"",IFERROR(C20/M20,0)) | AJ20: =IF(COUNT(C20:P20)=0,"",IFERROR(N20/M20,0)) | AK20: =IF(COUNT(C20:P20)=0,"",IFERROR(N20/H20,0)) | AL20: =IF(COUNT(C20:P20)=0,"",IFERROR(C20/N20,0)) | AM20: =IF(COUNT(C20:P20)=0,"",IFERROR(O20/N20,0)) | AN20: =IF(COUNT(C20:P20)=0,"",IFERROR(P20/N20,0)) | AO20: =IF(COUNT(C20:P20)=0,"",IFERROR(N20*Config!$C$7+O20*Config!$C$8+P20*Config!$C$9,0)) | AP20: =IF(COUNT(C20:P20)=0,"",IFERROR(AO20/N20,0)) | AQ20: =IF(COUNT(C20:P20)=0,"",IFERROR(AO20*(1-Config!$C$10-Config!$C$11-Config!$C$12),0)) | AR20: =IF(COUNT(C20:P20)=0,"",IFERROR(AQ20-C20-Config!$C$13,0)) | AS20: =IF(COUNT(C20:P20)=0,"",IFERROR(AQ20/C20,0)) | AT20: =IF(COUNT(C20:P20)=0,"",IFERROR(AR20/G20,0)) | AU20: =IF(COUNT(C20:P20)=0,"",IFERROR(AT20/V20,0)) | AV20: =IF(COUNT(C20:P20)=0,"",IFERROR(AR20/H20,0))
A21: =Config!$C$6+15 | B21: =INT((A21-Config!$C$6)/7)+1 | C21: 948 | D21: 227112 | E21: 136646 | F21: 5455 | G21: 5031 | H21: 1135 | I21: 681 | J21: 761 | Q21: =IF(COUNT(C21:P21)=0,"",IFERROR(C21/D21*1000,0)) | R21: =IF(COUNT(C21:P21)=0,"",IFERROR(D21/E21,0)) | S21: =IF(COUNT(C21:P21)=0,"",IFERROR(F21/D21,0)) | T21: =IF(COUNT(C21:P21)=0,"",IFERROR(C21/F21,0)) | U21: =IF(COUNT(C21:P21)=0,"",IFERROR(G21/F21,0)) | V21: =IF(COUNT(C21:P21)=0,"",IFERROR(C21/G21,0)) | W21: =IF(COUNT(C21:P21)=0,"",IFERROR(G21/D21*1000,0)) | X21: =IF(COUNT(C21:P21)=0,"",IFERROR(H21/G21,0)) | Y21: =IF(COUNT(C21:P21)=0,"",IFERROR(C21/H21,0)) | Z21: =IF(COUNT(C21:P21)=0,"",IFERROR(C21/I21,0)) | AA21: =IF(COUNT(C21:P21)=0,"",IFERROR(Y21/Q21,0)) | AB21: =IF(COUNT(C21:P21)=0,"",IFERROR(H21/D21*1000,0)) | AC21: =IF(COUNT(C21:P21)=0,"",IFERROR(J21/H21,0)) | AD21: =IF(COUNT(C21:P21)=0,"",IFERROR(C21/J21,0)) | AE21: =IF(COUNT(C21:P21)=0,"",IFERROR(K21/H21,0)) | AF21: =IF(COUNT(C21:P21)=0,"",IFERROR(L21/H21,0)) | AG21: =IF(COUNT(C21:P21)=0,"",IFERROR(C21/K21,0)) | AH21: =IF(COUNT(C21:P21)=0,"",IFERROR(M21/K21,0)) | AI21: =IF(COUNT(C21:P21)=0,"",IFERROR(C21/M21,0)) | AJ21: =IF(COUNT(C21:P21)=0,"",IFERROR(N21/M21,0)) | AK21: =IF(COUNT(C21:P21)=0,"",IFERROR(N21/H21,0)) | AL21: =IF(COUNT(C21:P21)=0,"",IFERROR(C21/N21,0)) | AM21: =IF(COUNT(C21:P21)=0,"",IFERROR(O21/N21,0)) | AN21: =IF(COUNT(C21:P21)=0,"",IFERROR(P21/N21,0)) | AO21: =IF(COUNT(C21:P21)=0,"",IFERROR(N21*Config!$C$7+O21*Config!$C$8+P21*Config!$C$9,0)) | AP21: =IF(COUNT(C21:P21)=0,"",IFERROR(AO21/N21,0)) | AQ21: =IF(COUNT(C21:P21)=0,"",IFERROR(AO21*(1-Config!$C$10-Config!$C$11-Config!$C$12),0)) | AR21: =IF(COUNT(C21:P21)=0,"",IFERROR(AQ21-C21-Config!$C$13,0)) | AS21: =IF(COUNT(C21:P21)=0,"",IFERROR(AQ21/C21,0)) | AT21: =IF(COUNT(C21:P21)=0,"",IFERROR(AR21/G21,0)) | AU21: =IF(COUNT(C21:P21)=0,"",IFERROR(AT21/V21,0)) | AV21: =IF(COUNT(C21:P21)=0,"",IFERROR(AR21/H21,0))
A22: =Config!$C$6+16 | B22: =INT((A22-Config!$C$6)/7)+1 | C22: 762 | D22: 152433 | E22: 108430 | F22: 3518 | G22: 2982 | H22: 739 | I22: 443 | J22: 495 | Q22: =IF(COUNT(C22:P22)=0,"",IFERROR(C22/D22*1000,0)) | R22: =IF(COUNT(C22:P22)=0,"",IFERROR(D22/E22,0)) | S22: =IF(COUNT(C22:P22)=0,"",IFERROR(F22/D22,0)) | T22: =IF(COUNT(C22:P22)=0,"",IFERROR(C22/F22,0)) | U22: =IF(COUNT(C22:P22)=0,"",IFERROR(G22/F22,0)) | V22: =IF(COUNT(C22:P22)=0,"",IFERROR(C22/G22,0)) | W22: =IF(COUNT(C22:P22)=0,"",IFERROR(G22/D22*1000,0)) | X22: =IF(COUNT(C22:P22)=0,"",IFERROR(H22/G22,0)) | Y22: =IF(COUNT(C22:P22)=0,"",IFERROR(C22/H22,0)) | Z22: =IF(COUNT(C22:P22)=0,"",IFERROR(C22/I22,0)) | AA22: =IF(COUNT(C22:P22)=0,"",IFERROR(Y22/Q22,0)) | AB22: =IF(COUNT(C22:P22)=0,"",IFERROR(H22/D22*1000,0)) | AC22: =IF(COUNT(C22:P22)=0,"",IFERROR(J22/H22,0)) | AD22: =IF(COUNT(C22:P22)=0,"",IFERROR(C22/J22,0)) | AE22: =IF(COUNT(C22:P22)=0,"",IFERROR(K22/H22,0)) | AF22: =IF(COUNT(C22:P22)=0,"",IFERROR(L22/H22,0)) | AG22: =IF(COUNT(C22:P22)=0,"",IFERROR(C22/K22,0)) | AH22: =IF(COUNT(C22:P22)=0,"",IFERROR(M22/K22,0)) | AI22: =IF(COUNT(C22:P22)=0,"",IFERROR(C22/M22,0)) | AJ22: =IF(COUNT(C22:P22)=0,"",IFERROR(N22/M22,0)) | AK22: =IF(COUNT(C22:P22)=0,"",IFERROR(N22/H22,0)) | AL22: =IF(COUNT(C22:P22)=0,"",IFERROR(C22/N22,0)) | AM22: =IF(COUNT(C22:P22)=0,"",IFERROR(O22/N22,0)) | AN22: =IF(COUNT(C22:P22)=0,"",IFERROR(P22/N22,0)) | AO22: =IF(COUNT(C22:P22)=0,"",IFERROR(N22*Config!$C$7+O22*Config!$C$8+P22*Config!$C$9,0)) | AP22: =IF(COUNT(C22:P22)=0,"",IFERROR(AO22/N22,0)) | AQ22: =IF(COUNT(C22:P22)=0,"",IFERROR(AO22*(1-Config!$C$10-Config!$C$11-Config!$C$12),0)) | AR22: =IF(COUNT(C22:P22)=0,"",IFERROR(AQ22-C22-Config!$C$13,0)) | AS22: =IF(COUNT(C22:P22)=0,"",IFERROR(AQ22/C22,0)) | AT22: =IF(COUNT(C22:P22)=0,"",IFERROR(AR22/G22,0)) | AU22: =IF(COUNT(C22:P22)=0,"",IFERROR(AT22/V22,0)) | AV22: =IF(COUNT(C22:P22)=0,"",IFERROR(AR22/H22,0))
A23: =Config!$C$6+17 | B23: =INT((A23-Config!$C$6)/7)+1 | C23: 815 | D23: 196294 | E23: 124289 | F23: 3872 | G23: 3257 | H23: 760 | I23: 456 | J23: 509 | K23: 955 | L23: 1251 | M23: 91 | N23: 37 | O23: 7 | P23: 0 | Q23: =IF(COUNT(C23:P23)=0,"",IFERROR(C23/D23*1000,0)) | R23: =IF(COUNT(C23:P23)=0,"",IFERROR(D23/E23,0)) | S23: =IF(COUNT(C23:P23)=0,"",IFERROR(F23/D23,0)) | T23: =IF(COUNT(C23:P23)=0,"",IFERROR(C23/F23,0)) | U23: =IF(COUNT(C23:P23)=0,"",IFERROR(G23/F23,0)) | V23: =IF(COUNT(C23:P23)=0,"",IFERROR(C23/G23,0)) | W23: =IF(COUNT(C23:P23)=0,"",IFERROR(G23/D23*1000,0)) | X23: =IF(COUNT(C23:P23)=0,"",IFERROR(H23/G23,0)) | Y23: =IF(COUNT(C23:P23)=0,"",IFERROR(C23/H23,0)) | Z23: =IF(COUNT(C23:P23)=0,"",IFERROR(C23/I23,0)) | AA23: =IF(COUNT(C23:P23)=0,"",IFERROR(Y23/Q23,0)) | AB23: =IF(COUNT(C23:P23)=0,"",IFERROR(H23/D23*1000,0)) | AC23: =IF(COUNT(C23:P23)=0,"",IFERROR(J23/H23,0)) | AD23: =IF(COUNT(C23:P23)=0,"",IFERROR(C23/J23,0)) | AE23: =IF(COUNT(C23:P23)=0,"",IFERROR(K23/H23,0)) | AF23: =IF(COUNT(C23:P23)=0,"",IFERROR(L23/H23,0)) | AG23: =IF(COUNT(C23:P23)=0,"",IFERROR(C23/K23,0)) | AH23: =IF(COUNT(C23:P23)=0,"",IFERROR(M23/K23,0)) | AI23: =IF(COUNT(C23:P23)=0,"",IFERROR(C23/M23,0)) | AJ23: =IF(COUNT(C23:P23)=0,"",IFERROR(N23/M23,0)) | AK23: =IF(COUNT(C23:P23)=0,"",IFERROR(N23/H23,0)) | AL23: =IF(COUNT(C23:P23)=0,"",IFERROR(C23/N23,0)) | AM23: =IF(COUNT(C23:P23)=0,"",IFERROR(O23/N23,0)) | AN23: =IF(COUNT(C23:P23)=0,"",IFERROR(P23/N23,0)) | AO23: =IF(COUNT(C23:P23)=0,"",IFERROR(N23*Config!$C$7+O23*Config!$C$8+P23*Config!$C$9,0)) | AP23: =IF(COUNT(C23:P23)=0,"",IFERROR(AO23/N23,0)) | AQ23: =IF(COUNT(C23:P23)=0,"",IFERROR(AO23*(1-Config!$C$10-Config!$C$11-Config!$C$12),0)) | AR23: =IF(COUNT(C23:P23)=0,"",IFERROR(AQ23-C23-Config!$C$13,0)) | AS23: =IF(COUNT(C23:P23)=0,"",IFERROR(AQ23/C23,0)) | AT23: =IF(COUNT(C23:P23)=0,"",IFERROR(AR23/G23,0)) | AU23: =IF(COUNT(C23:P23)=0,"",IFERROR(AT23/V23,0)) | AV23: =IF(COUNT(C23:P23)=0,"",IFERROR(AR23/H23,0))
A24: =Config!$C$6+18 | B24: =INT((A24-Config!$C$6)/7)+1 | C24: 943 | D24: 225544 | E24: 170098 | F24: 4687 | G24: 4163 | H24: 857 | I24: 514 | J24: 574 | L24: 1442 | M24: 83 | N24: 33 | O24: 7 | P24: 2 | Q24: =IF(COUNT(C24:P24)=0,"",IFERROR(C24/D24*1000,0)) | R24: =IF(COUNT(C24:P24)=0,"",IFERROR(D24/E24,0)) | S24: =IF(COUNT(C24:P24)=0,"",IFERROR(F24/D24,0)) | T24: =IF(COUNT(C24:P24)=0,"",IFERROR(C24/F24,0)) | U24: =IF(COUNT(C24:P24)=0,"",IFERROR(G24/F24,0)) | V24: =IF(COUNT(C24:P24)=0,"",IFERROR(C24/G24,0)) | W24: =IF(COUNT(C24:P24)=0,"",IFERROR(G24/D24*1000,0)) | X24: =IF(COUNT(C24:P24)=0,"",IFERROR(H24/G24,0)) | Y24: =IF(COUNT(C24:P24)=0,"",IFERROR(C24/H24,0)) | Z24: =IF(COUNT(C24:P24)=0,"",IFERROR(C24/I24,0)) | AA24: =IF(COUNT(C24:P24)=0,"",IFERROR(Y24/Q24,0)) | AB24: =IF(COUNT(C24:P24)=0,"",IFERROR(H24/D24*1000,0)) | AC24: =IF(COUNT(C24:P24)=0,"",IFERROR(J24/H24,0)) | AD24: =IF(COUNT(C24:P24)=0,"",IFERROR(C24/J24,0)) | AE24: =IF(COUNT(C24:P24)=0,"",IFERROR(K24/H24,0)) | AF24: =IF(COUNT(C24:P24)=0,"",IFERROR(L24/H24,0)) | AG24: =IF(COUNT(C24:P24)=0,"",IFERROR(C24/K24,0)) | AH24: =IF(COUNT(C24:P24)=0,"",IFERROR(M24/K24,0)) | AI24: =IF(COUNT(C24:P24)=0,"",IFERROR(C24/M24,0)) | AJ24: =IF(COUNT(C24:P24)=0,"",IFERROR(N24/M24,0)) | AK24: =IF(COUNT(C24:P24)=0,"",IFERROR(N24/H24,0)) | AL24: =IF(COUNT(C24:P24)=0,"",IFERROR(C24/N24,0)) | AM24: =IF(COUNT(C24:P24)=0,"",IFERROR(O24/N24,0)) | AN24: =IF(COUNT(C24:P24)=0,"",IFERROR(P24/N24,0)) | AO24: =IF(COUNT(C24:P24)=0,"",IFERROR(N24*Config!$C$7+O24*Config!$C$8+P24*Config!$C$9,0)) | AP24: =IF(COUNT(C24:P24)=0,"",IFERROR(AO24/N24,0)) | AQ24: =IF(COUNT(C24:P24)=0,"",IFERROR(AO24*(1-Config!$C$10-Config!$C$11-Config!$C$12),0)) | AR24: =IF(COUNT(C24:P24)=0,"",IFERROR(AQ24-C24-Config!$C$13,0)) | AS24: =IF(COUNT(C24:P24)=0,"",IFERROR(AQ24/C24,0)) | AT24: =IF(COUNT(C24:P24)=0,"",IFERROR(AR24/G24,0)) | AU24: =IF(COUNT(C24:P24)=0,"",IFERROR(AT24/V24,0)) | AV24: =IF(COUNT(C24:P24)=0,"",IFERROR(AR24/H24,0))
A25: =Config!$C$6+19 | B25: =INT((A25-Config!$C$6)/7)+1 | C25: 872 | D25: 212536 | E25: 146539 | F25: 5114 | G25: 5134 | H25: 1225 | I25: 735 | J25: 821 | L25: 614 | M25: 35 | N25: 14 | O25: 3 | P25: 1 | Q25: =IF(COUNT(C25:P25)=0,"",IFERROR(C25/D25*1000,0)) | R25: =IF(COUNT(C25:P25)=0,"",IFERROR(D25/E25,0)) | S25: =IF(COUNT(C25:P25)=0,"",IFERROR(F25/D25,0)) | T25: =IF(COUNT(C25:P25)=0,"",IFERROR(C25/F25,0)) | U25: =IF(COUNT(C25:P25)=0,"",IFERROR(G25/F25,0)) | V25: =IF(COUNT(C25:P25)=0,"",IFERROR(C25/G25,0)) | W25: =IF(COUNT(C25:P25)=0,"",IFERROR(G25/D25*1000,0)) | X25: =IF(COUNT(C25:P25)=0,"",IFERROR(H25/G25,0)) | Y25: =IF(COUNT(C25:P25)=0,"",IFERROR(C25/H25,0)) | Z25: =IF(COUNT(C25:P25)=0,"",IFERROR(C25/I25,0)) | AA25: =IF(COUNT(C25:P25)=0,"",IFERROR(Y25/Q25,0)) | AB25: =IF(COUNT(C25:P25)=0,"",IFERROR(H25/D25*1000,0)) | AC25: =IF(COUNT(C25:P25)=0,"",IFERROR(J25/H25,0)) | AD25: =IF(COUNT(C25:P25)=0,"",IFERROR(C25/J25,0)) | AE25: =IF(COUNT(C25:P25)=0,"",IFERROR(K25/H25,0)) | AF25: =IF(COUNT(C25:P25)=0,"",IFERROR(L25/H25,0)) | AG25: =IF(COUNT(C25:P25)=0,"",IFERROR(C25/K25,0)) | AH25: =IF(COUNT(C25:P25)=0,"",IFERROR(M25/K25,0)) | AI25: =IF(COUNT(C25:P25)=0,"",IFERROR(C25/M25,0)) | AJ25: =IF(COUNT(C25:P25)=0,"",IFERROR(N25/M25,0)) | AK25: =IF(COUNT(C25:P25)=0,"",IFERROR(N25/H25,0)) | AL25: =IF(COUNT(C25:P25)=0,"",IFERROR(C25/N25,0)) | AM25: =IF(COUNT(C25:P25)=0,"",IFERROR(O25/N25,0)) | AN25: =IF(COUNT(C25:P25)=0,"",IFERROR(P25/N25,0)) | AO25: =IF(COUNT(C25:P25)=0,"",IFERROR(N25*Config!$C$7+O25*Config!$C$8+P25*Config!$C$9,0)) | AP25: =IF(COUNT(C25:P25)=0,"",IFERROR(AO25/N25,0)) | AQ25: =IF(COUNT(C25:P25)=0,"",IFERROR(AO25*(1-Config!$C$10-Config!$C$11-Config!$C$12),0)) | AR25: =IF(COUNT(C25:P25)=0,"",IFERROR(AQ25-C25-Config!$C$13,0)) | AS25: =IF(COUNT(C25:P25)=0,"",IFERROR(AQ25/C25,0)) | AT25: =IF(COUNT(C25:P25)=0,"",IFERROR(AR25/G25,0)) | AU25: =IF(COUNT(C25:P25)=0,"",IFERROR(AT25/V25,0)) | AV25: =IF(COUNT(C25:P25)=0,"",IFERROR(AR25/H25,0))
A26: =Config!$C$6+20 | B26: =INT((A26-Config!$C$6)/7)+1 | C26: 783 | D26: 195860 | E26: 147658 | F26: 4733 | G26: 4465 | H26: 1141 | I26: 685 | J26: 765 | Q26: =IF(COUNT(C26:P26)=0,"",IFERROR(C26/D26*1000,0)) | R26: =IF(COUNT(C26:P26)=0,"",IFERROR(D26/E26,0)) | S26: =IF(COUNT(C26:P26)=0,"",IFERROR(F26/D26,0)) | T26: =IF(COUNT(C26:P26)=0,"",IFERROR(C26/F26,0)) | U26: =IF(COUNT(C26:P26)=0,"",IFERROR(G26/F26,0)) | V26: =IF(COUNT(C26:P26)=0,"",IFERROR(C26/G26,0)) | W26: =IF(COUNT(C26:P26)=0,"",IFERROR(G26/D26*1000,0)) | X26: =IF(COUNT(C26:P26)=0,"",IFERROR(H26/G26,0)) | Y26: =IF(COUNT(C26:P26)=0,"",IFERROR(C26/H26,0)) | Z26: =IF(COUNT(C26:P26)=0,"",IFERROR(C26/I26,0)) | AA26: =IF(COUNT(C26:P26)=0,"",IFERROR(Y26/Q26,0)) | AB26: =IF(COUNT(C26:P26)=0,"",IFERROR(H26/D26*1000,0)) | AC26: =IF(COUNT(C26:P26)=0,"",IFERROR(J26/H26,0)) | AD26: =IF(COUNT(C26:P26)=0,"",IFERROR(C26/J26,0)) | AE26: =IF(COUNT(C26:P26)=0,"",IFERROR(K26/H26,0)) | AF26: =IF(COUNT(C26:P26)=0,"",IFERROR(L26/H26,0)) | AG26: =IF(COUNT(C26:P26)=0,"",IFERROR(C26/K26,0)) | AH26: =IF(COUNT(C26:P26)=0,"",IFERROR(M26/K26,0)) | AI26: =IF(COUNT(C26:P26)=0,"",IFERROR(C26/M26,0)) | AJ26: =IF(COUNT(C26:P26)=0,"",IFERROR(N26/M26,0)) | AK26: =IF(COUNT(C26:P26)=0,"",IFERROR(N26/H26,0)) | AL26: =IF(COUNT(C26:P26)=0,"",IFERROR(C26/N26,0)) | AM26: =IF(COUNT(C26:P26)=0,"",IFERROR(O26/N26,0)) | AN26: =IF(COUNT(C26:P26)=0,"",IFERROR(P26/N26,0)) | AO26: =IF(COUNT(C26:P26)=0,"",IFERROR(N26*Config!$C$7+O26*Config!$C$8+P26*Config!$C$9,0)) | AP26: =IF(COUNT(C26:P26)=0,"",IFERROR(AO26/N26,0)) | AQ26: =IF(COUNT(C26:P26)=0,"",IFERROR(AO26*(1-Config!$C$10-Config!$C$11-Config!$C$12),0)) | AR26: =IF(COUNT(C26:P26)=0,"",IFERROR(AQ26-C26-Config!$C$13,0)) | AS26: =IF(COUNT(C26:P26)=0,"",IFERROR(AQ26/C26,0)) | AT26: =IF(COUNT(C26:P26)=0,"",IFERROR(AR26/G26,0)) | AU26: =IF(COUNT(C26:P26)=0,"",IFERROR(AT26/V26,0)) | AV26: =IF(COUNT(C26:P26)=0,"",IFERROR(AR26/H26,0))
A27: =Config!$C$6+21 | B27: =INT((A27-Config!$C$6)/7)+1 | C27: 885 | D27: 197511 | E27: 124772 | F27: 4156 | G27: 4189 | H27: 865 | I27: 519 | J27: 580 | Q27: =IF(COUNT(C27:P27)=0,"",IFERROR(C27/D27*1000,0)) | R27: =IF(COUNT(C27:P27)=0,"",IFERROR(D27/E27,0)) | S27: =IF(COUNT(C27:P27)=0,"",IFERROR(F27/D27,0)) | T27: =IF(COUNT(C27:P27)=0,"",IFERROR(C27/F27,0)) | U27: =IF(COUNT(C27:P27)=0,"",IFERROR(G27/F27,0)) | V27: =IF(COUNT(C27:P27)=0,"",IFERROR(C27/G27,0)) | W27: =IF(COUNT(C27:P27)=0,"",IFERROR(G27/D27*1000,0)) | X27: =IF(COUNT(C27:P27)=0,"",IFERROR(H27/G27,0)) | Y27: =IF(COUNT(C27:P27)=0,"",IFERROR(C27/H27,0)) | Z27: =IF(COUNT(C27:P27)=0,"",IFERROR(C27/I27,0)) | AA27: =IF(COUNT(C27:P27)=0,"",IFERROR(Y27/Q27,0)) | AB27: =IF(COUNT(C27:P27)=0,"",IFERROR(H27/D27*1000,0)) | AC27: =IF(COUNT(C27:P27)=0,"",IFERROR(J27/H27,0)) | AD27: =IF(COUNT(C27:P27)=0,"",IFERROR(C27/J27,0)) | AE27: =IF(COUNT(C27:P27)=0,"",IFERROR(K27/H27,0)) | AF27: =IF(COUNT(C27:P27)=0,"",IFERROR(L27/H27,0)) | AG27: =IF(COUNT(C27:P27)=0,"",IFERROR(C27/K27,0)) | AH27: =IF(COUNT(C27:P27)=0,"",IFERROR(M27/K27,0)) | AI27: =IF(COUNT(C27:P27)=0,"",IFERROR(C27/M27,0)) | AJ27: =IF(COUNT(C27:P27)=0,"",IFERROR(N27/M27,0)) | AK27: =IF(COUNT(C27:P27)=0,"",IFERROR(N27/H27,0)) | AL27: =IF(COUNT(C27:P27)=0,"",IFERROR(C27/N27,0)) | AM27: =IF(COUNT(C27:P27)=0,"",IFERROR(O27/N27,0)) | AN27: =IF(COUNT(C27:P27)=0,"",IFERROR(P27/N27,0)) | AO27: =IF(COUNT(C27:P27)=0,"",IFERROR(N27*Config!$C$7+O27*Config!$C$8+P27*Config!$C$9,0)) | AP27: =IF(COUNT(C27:P27)=0,"",IFERROR(AO27/N27,0)) | AQ27: =IF(COUNT(C27:P27)=0,"",IFERROR(AO27*(1-Config!$C$10-Config!$C$11-Config!$C$12),0)) | AR27: =IF(COUNT(C27:P27)=0,"",IFERROR(AQ27-C27-Config!$C$13,0)) | AS27: =IF(COUNT(C27:P27)=0,"",IFERROR(AQ27/C27,0)) | AT27: =IF(COUNT(C27:P27)=0,"",IFERROR(AR27/G27,0)) | AU27: =IF(COUNT(C27:P27)=0,"",IFERROR(AT27/V27,0)) | AV27: =IF(COUNT(C27:P27)=0,"",IFERROR(AR27/H27,0))
A28: =Config!$C$6+22 | B28: =INT((A28-Config!$C$6)/7)+1 | C28: 906 | D28: 183639 | E28: 115835 | F28: 4238 | G28: 4082 | H28: 1032 | I28: 619 | J28: 692 | Q28: =IF(COUNT(C28:P28)=0,"",IFERROR(C28/D28*1000,0)) | R28: =IF(COUNT(C28:P28)=0,"",IFERROR(D28/E28,0)) | S28: =IF(COUNT(C28:P28)=0,"",IFERROR(F28/D28,0)) | T28: =IF(COUNT(C28:P28)=0,"",IFERROR(C28/F28,0)) | U28: =IF(COUNT(C28:P28)=0,"",IFERROR(G28/F28,0)) | V28: =IF(COUNT(C28:P28)=0,"",IFERROR(C28/G28,0)) | W28: =IF(COUNT(C28:P28)=0,"",IFERROR(G28/D28*1000,0)) | X28: =IF(COUNT(C28:P28)=0,"",IFERROR(H28/G28,0)) | Y28: =IF(COUNT(C28:P28)=0,"",IFERROR(C28/H28,0)) | Z28: =IF(COUNT(C28:P28)=0,"",IFERROR(C28/I28,0)) | AA28: =IF(COUNT(C28:P28)=0,"",IFERROR(Y28/Q28,0)) | AB28: =IF(COUNT(C28:P28)=0,"",IFERROR(H28/D28*1000,0)) | AC28: =IF(COUNT(C28:P28)=0,"",IFERROR(J28/H28,0)) | AD28: =IF(COUNT(C28:P28)=0,"",IFERROR(C28/J28,0)) | AE28: =IF(COUNT(C28:P28)=0,"",IFERROR(K28/H28,0)) | AF28: =IF(COUNT(C28:P28)=0,"",IFERROR(L28/H28,0)) | AG28: =IF(COUNT(C28:P28)=0,"",IFERROR(C28/K28,0)) | AH28: =IF(COUNT(C28:P28)=0,"",IFERROR(M28/K28,0)) | AI28: =IF(COUNT(C28:P28)=0,"",IFERROR(C28/M28,0)) | AJ28: =IF(COUNT(C28:P28)=0,"",IFERROR(N28/M28,0)) | AK28: =IF(COUNT(C28:P28)=0,"",IFERROR(N28/H28,0)) | AL28: =IF(COUNT(C28:P28)=0,"",IFERROR(C28/N28,0)) | AM28: =IF(COUNT(C28:P28)=0,"",IFERROR(O28/N28,0)) | AN28: =IF(COUNT(C28:P28)=0,"",IFERROR(P28/N28,0)) | AO28: =IF(COUNT(C28:P28)=0,"",IFERROR(N28*Config!$C$7+O28*Config!$C$8+P28*Config!$C$9,0)) | AP28: =IF(COUNT(C28:P28)=0,"",IFERROR(AO28/N28,0)) | AQ28: =IF(COUNT(C28:P28)=0,"",IFERROR(AO28*(1-Config!$C$10-Config!$C$11-Config!$C$12),0)) | AR28: =IF(COUNT(C28:P28)=0,"",IFERROR(AQ28-C28-Config!$C$13,0)) | AS28: =IF(COUNT(C28:P28)=0,"",IFERROR(AQ28/C28,0)) | AT28: =IF(COUNT(C28:P28)=0,"",IFERROR(AR28/G28,0)) | AU28: =IF(COUNT(C28:P28)=0,"",IFERROR(AT28/V28,0)) | AV28: =IF(COUNT(C28:P28)=0,"",IFERROR(AR28/H28,0))
A29: =Config!$C$6+23 | B29: =INT((A29-Config!$C$6)/7)+1 | C29: 895 | D29: 181451 | E29: 111075 | F29: 3913 | G29: 3767 | H29: 942 | I29: 565 | J29: 631 | Q29: =IF(COUNT(C29:P29)=0,"",IFERROR(C29/D29*1000,0)) | R29: =IF(COUNT(C29:P29)=0,"",IFERROR(D29/E29,0)) | S29: =IF(COUNT(C29:P29)=0,"",IFERROR(F29/D29,0)) | T29: =IF(COUNT(C29:P29)=0,"",IFERROR(C29/F29,0)) | U29: =IF(COUNT(C29:P29)=0,"",IFERROR(G29/F29,0)) | V29: =IF(COUNT(C29:P29)=0,"",IFERROR(C29/G29,0)) | W29: =IF(COUNT(C29:P29)=0,"",IFERROR(G29/D29*1000,0)) | X29: =IF(COUNT(C29:P29)=0,"",IFERROR(H29/G29,0)) | Y29: =IF(COUNT(C29:P29)=0,"",IFERROR(C29/H29,0)) | Z29: =IF(COUNT(C29:P29)=0,"",IFERROR(C29/I29,0)) | AA29: =IF(COUNT(C29:P29)=0,"",IFERROR(Y29/Q29,0)) | AB29: =IF(COUNT(C29:P29)=0,"",IFERROR(H29/D29*1000,0)) | AC29: =IF(COUNT(C29:P29)=0,"",IFERROR(J29/H29,0)) | AD29: =IF(COUNT(C29:P29)=0,"",IFERROR(C29/J29,0)) | AE29: =IF(COUNT(C29:P29)=0,"",IFERROR(K29/H29,0)) | AF29: =IF(COUNT(C29:P29)=0,"",IFERROR(L29/H29,0)) | AG29: =IF(COUNT(C29:P29)=0,"",IFERROR(C29/K29,0)) | AH29: =IF(COUNT(C29:P29)=0,"",IFERROR(M29/K29,0)) | AI29: =IF(COUNT(C29:P29)=0,"",IFERROR(C29/M29,0)) | AJ29: =IF(COUNT(C29:P29)=0,"",IFERROR(N29/M29,0)) | AK29: =IF(COUNT(C29:P29)=0,"",IFERROR(N29/H29,0)) | AL29: =IF(COUNT(C29:P29)=0,"",IFERROR(C29/N29,0)) | AM29: =IF(COUNT(C29:P29)=0,"",IFERROR(O29/N29,0)) | AN29: =IF(COUNT(C29:P29)=0,"",IFERROR(P29/N29,0)) | AO29: =IF(COUNT(C29:P29)=0,"",IFERROR(N29*Config!$C$7+O29*Config!$C$8+P29*Config!$C$9,0)) | AP29: =IF(COUNT(C29:P29)=0,"",IFERROR(AO29/N29,0)) | AQ29: =IF(COUNT(C29:P29)=0,"",IFERROR(AO29*(1-Config!$C$10-Config!$C$11-Config!$C$12),0)) | AR29: =IF(COUNT(C29:P29)=0,"",IFERROR(AQ29-C29-Config!$C$13,0)) | AS29: =IF(COUNT(C29:P29)=0,"",IFERROR(AQ29/C29,0)) | AT29: =IF(COUNT(C29:P29)=0,"",IFERROR(AR29/G29,0)) | AU29: =IF(COUNT(C29:P29)=0,"",IFERROR(AT29/V29,0)) | AV29: =IF(COUNT(C29:P29)=0,"",IFERROR(AR29/H29,0))
A30: =Config!$C$6+24 | B30: =INT((A30-Config!$C$6)/7)+1 | C30: 883 | D30: 201856 | E30: 131953 | F30: 4557 | G30: 3688 | H30: 877 | I30: 526 | J30: 587 | K30: 1011 | L30: 1271 | M30: 106 | N30: 42 | O30: 8 | P30: 0 | Q30: =IF(COUNT(C30:P30)=0,"",IFERROR(C30/D30*1000,0)) | R30: =IF(COUNT(C30:P30)=0,"",IFERROR(D30/E30,0)) | S30: =IF(COUNT(C30:P30)=0,"",IFERROR(F30/D30,0)) | T30: =IF(COUNT(C30:P30)=0,"",IFERROR(C30/F30,0)) | U30: =IF(COUNT(C30:P30)=0,"",IFERROR(G30/F30,0)) | V30: =IF(COUNT(C30:P30)=0,"",IFERROR(C30/G30,0)) | W30: =IF(COUNT(C30:P30)=0,"",IFERROR(G30/D30*1000,0)) | X30: =IF(COUNT(C30:P30)=0,"",IFERROR(H30/G30,0)) | Y30: =IF(COUNT(C30:P30)=0,"",IFERROR(C30/H30,0)) | Z30: =IF(COUNT(C30:P30)=0,"",IFERROR(C30/I30,0)) | AA30: =IF(COUNT(C30:P30)=0,"",IFERROR(Y30/Q30,0)) | AB30: =IF(COUNT(C30:P30)=0,"",IFERROR(H30/D30*1000,0)) | AC30: =IF(COUNT(C30:P30)=0,"",IFERROR(J30/H30,0)) | AD30: =IF(COUNT(C30:P30)=0,"",IFERROR(C30/J30,0)) | AE30: =IF(COUNT(C30:P30)=0,"",IFERROR(K30/H30,0)) | AF30: =IF(COUNT(C30:P30)=0,"",IFERROR(L30/H30,0)) | AG30: =IF(COUNT(C30:P30)=0,"",IFERROR(C30/K30,0)) | AH30: =IF(COUNT(C30:P30)=0,"",IFERROR(M30/K30,0)) | AI30: =IF(COUNT(C30:P30)=0,"",IFERROR(C30/M30,0)) | AJ30: =IF(COUNT(C30:P30)=0,"",IFERROR(N30/M30,0)) | AK30: =IF(COUNT(C30:P30)=0,"",IFERROR(N30/H30,0)) | AL30: =IF(COUNT(C30:P30)=0,"",IFERROR(C30/N30,0)) | AM30: =IF(COUNT(C30:P30)=0,"",IFERROR(O30/N30,0)) | AN30: =IF(COUNT(C30:P30)=0,"",IFERROR(P30/N30,0)) | AO30: =IF(COUNT(C30:P30)=0,"",IFERROR(N30*Config!$C$7+O30*Config!$C$8+P30*Config!$C$9,0)) | AP30: =IF(COUNT(C30:P30)=0,"",IFERROR(AO30/N30,0)) | AQ30: =IF(COUNT(C30:P30)=0,"",IFERROR(AO30*(1-Config!$C$10-Config!$C$11-Config!$C$12),0)) | AR30: =IF(COUNT(C30:P30)=0,"",IFERROR(AQ30-C30-Config!$C$13,0)) | AS30: =IF(COUNT(C30:P30)=0,"",IFERROR(AQ30/C30,0)) | AT30: =IF(COUNT(C30:P30)=0,"",IFERROR(AR30/G30,0)) | AU30: =IF(COUNT(C30:P30)=0,"",IFERROR(AT30/V30,0)) | AV30: =IF(COUNT(C30:P30)=0,"",IFERROR(AR30/H30,0))
A31: =Config!$C$6+25 | B31: =INT((A31-Config!$C$6)/7)+1 | C31: 834 | D31: 175448 | E31: 114736 | F31: 3805 | G31: 3702 | H31: 766 | I31: 460 | J31: 514 | L31: 1545 | M31: 80 | N31: 32 | O31: 6 | P31: 2 | Q31: =IF(COUNT(C31:P31)=0,"",IFERROR(C31/D31*1000,0)) | R31: =IF(COUNT(C31:P31)=0,"",IFERROR(D31/E31,0)) | S31: =IF(COUNT(C31:P31)=0,"",IFERROR(F31/D31,0)) | T31: =IF(COUNT(C31:P31)=0,"",IFERROR(C31/F31,0)) | U31: =IF(COUNT(C31:P31)=0,"",IFERROR(G31/F31,0)) | V31: =IF(COUNT(C31:P31)=0,"",IFERROR(C31/G31,0)) | W31: =IF(COUNT(C31:P31)=0,"",IFERROR(G31/D31*1000,0)) | X31: =IF(COUNT(C31:P31)=0,"",IFERROR(H31/G31,0)) | Y31: =IF(COUNT(C31:P31)=0,"",IFERROR(C31/H31,0)) | Z31: =IF(COUNT(C31:P31)=0,"",IFERROR(C31/I31,0)) | AA31: =IF(COUNT(C31:P31)=0,"",IFERROR(Y31/Q31,0)) | AB31: =IF(COUNT(C31:P31)=0,"",IFERROR(H31/D31*1000,0)) | AC31: =IF(COUNT(C31:P31)=0,"",IFERROR(J31/H31,0)) | AD31: =IF(COUNT(C31:P31)=0,"",IFERROR(C31/J31,0)) | AE31: =IF(COUNT(C31:P31)=0,"",IFERROR(K31/H31,0)) | AF31: =IF(COUNT(C31:P31)=0,"",IFERROR(L31/H31,0)) | AG31: =IF(COUNT(C31:P31)=0,"",IFERROR(C31/K31,0)) | AH31: =IF(COUNT(C31:P31)=0,"",IFERROR(M31/K31,0)) | AI31: =IF(COUNT(C31:P31)=0,"",IFERROR(C31/M31,0)) | AJ31: =IF(COUNT(C31:P31)=0,"",IFERROR(N31/M31,0)) | AK31: =IF(COUNT(C31:P31)=0,"",IFERROR(N31/H31,0)) | AL31: =IF(COUNT(C31:P31)=0,"",IFERROR(C31/N31,0)) | AM31: =IF(COUNT(C31:P31)=0,"",IFERROR(O31/N31,0)) | AN31: =IF(COUNT(C31:P31)=0,"",IFERROR(P31/N31,0)) | AO31: =IF(COUNT(C31:P31)=0,"",IFERROR(N31*Config!$C$7+O31*Config!$C$8+P31*Config!$C$9,0)) | AP31: =IF(COUNT(C31:P31)=0,"",IFERROR(AO31/N31,0)) | AQ31: =IF(COUNT(C31:P31)=0,"",IFERROR(AO31*(1-Config!$C$10-Config!$C$11-Config!$C$12),0)) | AR31: =IF(COUNT(C31:P31)=0,"",IFERROR(AQ31-C31-Config!$C$13,0)) | AS31: =IF(COUNT(C31:P31)=0,"",IFERROR(AQ31/C31,0)) | AT31: =IF(COUNT(C31:P31)=0,"",IFERROR(AR31/G31,0)) | AU31: =IF(COUNT(C31:P31)=0,"",IFERROR(AT31/V31,0)) | AV31: =IF(COUNT(C31:P31)=0,"",IFERROR(AR31/H31,0))
A32: =Config!$C$6+26 | B32: =INT((A32-Config!$C$6)/7)+1 | C32: 878 | D32: 195970 | E32: 139691 | F32: 4517 | G32: 4062 | H32: 960 | I32: 576 | J32: 643 | L32: 630 | M32: 32 | N32: 13 | O32: 3 | P32: 1 | Q32: =IF(COUNT(C32:P32)=0,"",IFERROR(C32/D32*1000,0)) | R32: =IF(COUNT(C32:P32)=0,"",IFERROR(D32/E32,0)) | S32: =IF(COUNT(C32:P32)=0,"",IFERROR(F32/D32,0)) | T32: =IF(COUNT(C32:P32)=0,"",IFERROR(C32/F32,0)) | U32: =IF(COUNT(C32:P32)=0,"",IFERROR(G32/F32,0)) | V32: =IF(COUNT(C32:P32)=0,"",IFERROR(C32/G32,0)) | W32: =IF(COUNT(C32:P32)=0,"",IFERROR(G32/D32*1000,0)) | X32: =IF(COUNT(C32:P32)=0,"",IFERROR(H32/G32,0)) | Y32: =IF(COUNT(C32:P32)=0,"",IFERROR(C32/H32,0)) | Z32: =IF(COUNT(C32:P32)=0,"",IFERROR(C32/I32,0)) | AA32: =IF(COUNT(C32:P32)=0,"",IFERROR(Y32/Q32,0)) | AB32: =IF(COUNT(C32:P32)=0,"",IFERROR(H32/D32*1000,0)) | AC32: =IF(COUNT(C32:P32)=0,"",IFERROR(J32/H32,0)) | AD32: =IF(COUNT(C32:P32)=0,"",IFERROR(C32/J32,0)) | AE32: =IF(COUNT(C32:P32)=0,"",IFERROR(K32/H32,0)) | AF32: =IF(COUNT(C32:P32)=0,"",IFERROR(L32/H32,0)) | AG32: =IF(COUNT(C32:P32)=0,"",IFERROR(C32/K32,0)) | AH32: =IF(COUNT(C32:P32)=0,"",IFERROR(M32/K32,0)) | AI32: =IF(COUNT(C32:P32)=0,"",IFERROR(C32/M32,0)) | AJ32: =IF(COUNT(C32:P32)=0,"",IFERROR(N32/M32,0)) | AK32: =IF(COUNT(C32:P32)=0,"",IFERROR(N32/H32,0)) | AL32: =IF(COUNT(C32:P32)=0,"",IFERROR(C32/N32,0)) | AM32: =IF(COUNT(C32:P32)=0,"",IFERROR(O32/N32,0)) | AN32: =IF(COUNT(C32:P32)=0,"",IFERROR(P32/N32,0)) | AO32: =IF(COUNT(C32:P32)=0,"",IFERROR(N32*Config!$C$7+O32*Config!$C$8+P32*Config!$C$9,0)) | AP32: =IF(COUNT(C32:P32)=0,"",IFERROR(AO32/N32,0)) | AQ32: =IF(COUNT(C32:P32)=0,"",IFERROR(AO32*(1-Config!$C$10-Config!$C$11-Config!$C$12),0)) | AR32: =IF(COUNT(C32:P32)=0,"",IFERROR(AQ32-C32-Config!$C$13,0)) | AS32: =IF(COUNT(C32:P32)=0,"",IFERROR(AQ32/C32,0)) | AT32: =IF(COUNT(C32:P32)=0,"",IFERROR(AR32/G32,0)) | AU32: =IF(COUNT(C32:P32)=0,"",IFERROR(AT32/V32,0)) | AV32: =IF(COUNT(C32:P32)=0,"",IFERROR(AR32/H32,0))
A33: =Config!$C$6+27 | B33: =INT((A33-Config!$C$6)/7)+1 | C33: 756 | D33: 176538 | E33: 112867 | F33: 3607 | G33: 2989 | H33: 754 | I33: 453 | J33: 505 | Q33: =IF(COUNT(C33:P33)=0,"",IFERROR(C33/D33*1000,0)) | R33: =IF(COUNT(C33:P33)=0,"",IFERROR(D33/E33,0)) | S33: =IF(COUNT(C33:P33)=0,"",IFERROR(F33/D33,0)) | T33: =IF(COUNT(C33:P33)=0,"",IFERROR(C33/F33,0)) | U33: =IF(COUNT(C33:P33)=0,"",IFERROR(G33/F33,0)) | V33: =IF(COUNT(C33:P33)=0,"",IFERROR(C33/G33,0)) | W33: =IF(COUNT(C33:P33)=0,"",IFERROR(G33/D33*1000,0)) | X33: =IF(COUNT(C33:P33)=0,"",IFERROR(H33/G33,0)) | Y33: =IF(COUNT(C33:P33)=0,"",IFERROR(C33/H33,0)) | Z33: =IF(COUNT(C33:P33)=0,"",IFERROR(C33/I33,0)) | AA33: =IF(COUNT(C33:P33)=0,"",IFERROR(Y33/Q33,0)) | AB33: =IF(COUNT(C33:P33)=0,"",IFERROR(H33/D33*1000,0)) | AC33: =IF(COUNT(C33:P33)=0,"",IFERROR(J33/H33,0)) | AD33: =IF(COUNT(C33:P33)=0,"",IFERROR(C33/J33,0)) | AE33: =IF(COUNT(C33:P33)=0,"",IFERROR(K33/H33,0)) | AF33: =IF(COUNT(C33:P33)=0,"",IFERROR(L33/H33,0)) | AG33: =IF(COUNT(C33:P33)=0,"",IFERROR(C33/K33,0)) | AH33: =IF(COUNT(C33:P33)=0,"",IFERROR(M33/K33,0)) | AI33: =IF(COUNT(C33:P33)=0,"",IFERROR(C33/M33,0)) | AJ33: =IF(COUNT(C33:P33)=0,"",IFERROR(N33/M33,0)) | AK33: =IF(COUNT(C33:P33)=0,"",IFERROR(N33/H33,0)) | AL33: =IF(COUNT(C33:P33)=0,"",IFERROR(C33/N33,0)) | AM33: =IF(COUNT(C33:P33)=0,"",IFERROR(O33/N33,0)) | AN33: =IF(COUNT(C33:P33)=0,"",IFERROR(P33/N33,0)) | AO33: =IF(COUNT(C33:P33)=0,"",IFERROR(N33*Config!$C$7+O33*Config!$C$8+P33*Config!$C$9,0)) | AP33: =IF(COUNT(C33:P33)=0,"",IFERROR(AO33/N33,0)) | AQ33: =IF(COUNT(C33:P33)=0,"",IFERROR(AO33*(1-Config!$C$10-Config!$C$11-Config!$C$12),0)) | AR33: =IF(COUNT(C33:P33)=0,"",IFERROR(AQ33-C33-Config!$C$13,0)) | AS33: =IF(COUNT(C33:P33)=0,"",IFERROR(AQ33/C33,0)) | AT33: =IF(COUNT(C33:P33)=0,"",IFERROR(AR33/G33,0)) | AU33: =IF(COUNT(C33:P33)=0,"",IFERROR(AT33/V33,0)) | AV33: =IF(COUNT(C33:P33)=0,"",IFERROR(AR33/H33,0))
A34: =Config!$C$6+28 | B34: =INT((A34-Config!$C$6)/7)+1 | Q34: =IF(COUNT(C34:P34)=0,"",IFERROR(C34/D34*1000,0)) | R34: =IF(COUNT(C34:P34)=0,"",IFERROR(D34/E34,0)) | S34: =IF(COUNT(C34:P34)=0,"",IFERROR(F34/D34,0)) | T34: =IF(COUNT(C34:P34)=0,"",IFERROR(C34/F34,0)) | U34: =IF(COUNT(C34:P34)=0,"",IFERROR(G34/F34,0)) | V34: =IF(COUNT(C34:P34)=0,"",IFERROR(C34/G34,0)) | W34: =IF(COUNT(C34:P34)=0,"",IFERROR(G34/D34*1000,0)) | X34: =IF(COUNT(C34:P34)=0,"",IFERROR(H34/G34,0)) | Y34: =IF(COUNT(C34:P34)=0,"",IFERROR(C34/H34,0)) | Z34: =IF(COUNT(C34:P34)=0,"",IFERROR(C34/I34,0)) | AA34: =IF(COUNT(C34:P34)=0,"",IFERROR(Y34/Q34,0)) | AB34: =IF(COUNT(C34:P34)=0,"",IFERROR(H34/D34*1000,0)) | AC34: =IF(COUNT(C34:P34)=0,"",IFERROR(J34/H34,0)) | AD34: =IF(COUNT(C34:P34)=0,"",IFERROR(C34/J34,0)) | AE34: =IF(COUNT(C34:P34)=0,"",IFERROR(K34/H34,0)) | AF34: =IF(COUNT(C34:P34)=0,"",IFERROR(L34/H34,0)) | AG34: =IF(COUNT(C34:P34)=0,"",IFERROR(C34/K34,0)) | AH34: =IF(COUNT(C34:P34)=0,"",IFERROR(M34/K34,0)) | AI34: =IF(COUNT(C34:P34)=0,"",IFERROR(C34/M34,0)) | AJ34: =IF(COUNT(C34:P34)=0,"",IFERROR(N34/M34,0)) | AK34: =IF(COUNT(C34:P34)=0,"",IFERROR(N34/H34,0)) | AL34: =IF(COUNT(C34:P34)=0,"",IFERROR(C34/N34,0)) | AM34: =IF(COUNT(C34:P34)=0,"",IFERROR(O34/N34,0)) | AN34: =IF(COUNT(C34:P34)=0,"",IFERROR(P34/N34,0)) | AO34: =IF(COUNT(C34:P34)=0,"",IFERROR(N34*Config!$C$7+O34*Config!$C$8+P34*Config!$C$9,0)) | AP34: =IF(COUNT(C34:P34)=0,"",IFERROR(AO34/N34,0)) | AQ34: =IF(COUNT(C34:P34)=0,"",IFERROR(AO34*(1-Config!$C$10-Config!$C$11-Config!$C$12),0)) | AR34: =IF(COUNT(C34:P34)=0,"",IFERROR(AQ34-C34-Config!$C$13,0)) | AS34: =IF(COUNT(C34:P34)=0,"",IFERROR(AQ34/C34,0)) | AT34: =IF(COUNT(C34:P34)=0,"",IFERROR(AR34/G34,0)) | AU34: =IF(COUNT(C34:P34)=0,"",IFERROR(AT34/V34,0)) | AV34: =IF(COUNT(C34:P34)=0,"",IFERROR(AR34/H34,0))
A35: =Config!$C$6+29 | B35: =INT((A35-Config!$C$6)/7)+1 | Q35: =IF(COUNT(C35:P35)=0,"",IFERROR(C35/D35*1000,0)) | R35: =IF(COUNT(C35:P35)=0,"",IFERROR(D35/E35,0)) | S35: =IF(COUNT(C35:P35)=0,"",IFERROR(F35/D35,0)) | T35: =IF(COUNT(C35:P35)=0,"",IFERROR(C35/F35,0)) | U35: =IF(COUNT(C35:P35)=0,"",IFERROR(G35/F35,0)) | V35: =IF(COUNT(C35:P35)=0,"",IFERROR(C35/G35,0)) | W35: =IF(COUNT(C35:P35)=0,"",IFERROR(G35/D35*1000,0)) | X35: =IF(COUNT(C35:P35)=0,"",IFERROR(H35/G35,0)) | Y35: =IF(COUNT(C35:P35)=0,"",IFERROR(C35/H35,0)) | Z35: =IF(COUNT(C35:P35)=0,"",IFERROR(C35/I35,0)) | AA35: =IF(COUNT(C35:P35)=0,"",IFERROR(Y35/Q35,0)) | AB35: =IF(COUNT(C35:P35)=0,"",IFERROR(H35/D35*1000,0)) | AC35: =IF(COUNT(C35:P35)=0,"",IFERROR(J35/H35,0)) | AD35: =IF(COUNT(C35:P35)=0,"",IFERROR(C35/J35,0)) | AE35: =IF(COUNT(C35:P35)=0,"",IFERROR(K35/H35,0)) | AF35: =IF(COUNT(C35:P35)=0,"",IFERROR(L35/H35,0)) | AG35: =IF(COUNT(C35:P35)=0,"",IFERROR(C35/K35,0)) | AH35: =IF(COUNT(C35:P35)=0,"",IFERROR(M35/K35,0)) | AI35: =IF(COUNT(C35:P35)=0,"",IFERROR(C35/M35,0)) | AJ35: =IF(COUNT(C35:P35)=0,"",IFERROR(N35/M35,0)) | AK35: =IF(COUNT(C35:P35)=0,"",IFERROR(N35/H35,0)) | AL35: =IF(COUNT(C35:P35)=0,"",IFERROR(C35/N35,0)) | AM35: =IF(COUNT(C35:P35)=0,"",IFERROR(O35/N35,0)) | AN35: =IF(COUNT(C35:P35)=0,"",IFERROR(P35/N35,0)) | AO35: =IF(COUNT(C35:P35)=0,"",IFERROR(N35*Config!$C$7+O35*Config!$C$8+P35*Config!$C$9,0)) | AP35: =IF(COUNT(C35:P35)=0,"",IFERROR(AO35/N35,0)) | AQ35: =IF(COUNT(C35:P35)=0,"",IFERROR(AO35*(1-Config!$C$10-Config!$C$11-Config!$C$12),0)) | AR35: =IF(COUNT(C35:P35)=0,"",IFERROR(AQ35-C35-Config!$C$13,0)) | AS35: =IF(COUNT(C35:P35)=0,"",IFERROR(AQ35/C35,0)) | AT35: =IF(COUNT(C35:P35)=0,"",IFERROR(AR35/G35,0)) | AU35: =IF(COUNT(C35:P35)=0,"",IFERROR(AT35/V35,0)) | AV35: =IF(COUNT(C35:P35)=0,"",IFERROR(AR35/H35,0))
A36: =Config!$C$6+30 | B36: =INT((A36-Config!$C$6)/7)+1 | Q36: =IF(COUNT(C36:P36)=0,"",IFERROR(C36/D36*1000,0)) | R36: =IF(COUNT(C36:P36)=0,"",IFERROR(D36/E36,0)) | S36: =IF(COUNT(C36:P36)=0,"",IFERROR(F36/D36,0)) | T36: =IF(COUNT(C36:P36)=0,"",IFERROR(C36/F36,0)) | U36: =IF(COUNT(C36:P36)=0,"",IFERROR(G36/F36,0)) | V36: =IF(COUNT(C36:P36)=0,"",IFERROR(C36/G36,0)) | W36: =IF(COUNT(C36:P36)=0,"",IFERROR(G36/D36*1000,0)) | X36: =IF(COUNT(C36:P36)=0,"",IFERROR(H36/G36,0)) | Y36: =IF(COUNT(C36:P36)=0,"",IFERROR(C36/H36,0)) | Z36: =IF(COUNT(C36:P36)=0,"",IFERROR(C36/I36,0)) | AA36: =IF(COUNT(C36:P36)=0,"",IFERROR(Y36/Q36,0)) | AB36: =IF(COUNT(C36:P36)=0,"",IFERROR(H36/D36*1000,0)) | AC36: =IF(COUNT(C36:P36)=0,"",IFERROR(J36/H36,0)) | AD36: =IF(COUNT(C36:P36)=0,"",IFERROR(C36/J36,0)) | AE36: =IF(COUNT(C36:P36)=0,"",IFERROR(K36/H36,0)) | AF36: =IF(COUNT(C36:P36)=0,"",IFERROR(L36/H36,0)) | AG36: =IF(COUNT(C36:P36)=0,"",IFERROR(C36/K36,0)) | AH36: =IF(COUNT(C36:P36)=0,"",IFERROR(M36/K36,0)) | AI36: =IF(COUNT(C36:P36)=0,"",IFERROR(C36/M36,0)) | AJ36: =IF(COUNT(C36:P36)=0,"",IFERROR(N36/M36,0)) | AK36: =IF(COUNT(C36:P36)=0,"",IFERROR(N36/H36,0)) | AL36: =IF(COUNT(C36:P36)=0,"",IFERROR(C36/N36,0)) | AM36: =IF(COUNT(C36:P36)=0,"",IFERROR(O36/N36,0)) | AN36: =IF(COUNT(C36:P36)=0,"",IFERROR(P36/N36,0)) | AO36: =IF(COUNT(C36:P36)=0,"",IFERROR(N36*Config!$C$7+O36*Config!$C$8+P36*Config!$C$9,0)) | AP36: =IF(COUNT(C36:P36)=0,"",IFERROR(AO36/N36,0)) | AQ36: =IF(COUNT(C36:P36)=0,"",IFERROR(AO36*(1-Config!$C$10-Config!$C$11-Config!$C$12),0)) | AR36: =IF(COUNT(C36:P36)=0,"",IFERROR(AQ36-C36-Config!$C$13,0)) | AS36: =IF(COUNT(C36:P36)=0,"",IFERROR(AQ36/C36,0)) | AT36: =IF(COUNT(C36:P36)=0,"",IFERROR(AR36/G36,0)) | AU36: =IF(COUNT(C36:P36)=0,"",IFERROR(AT36/V36,0)) | AV36: =IF(COUNT(C36:P36)=0,"",IFERROR(AR36/H36,0))
A37: =Config!$C$6+31 | B37: =INT((A37-Config!$C$6)/7)+1 | Q37: =IF(COUNT(C37:P37)=0,"",IFERROR(C37/D37*1000,0)) | R37: =IF(COUNT(C37:P37)=0,"",IFERROR(D37/E37,0)) | S37: =IF(COUNT(C37:P37)=0,"",IFERROR(F37/D37,0)) | T37: =IF(COUNT(C37:P37)=0,"",IFERROR(C37/F37,0)) | U37: =IF(COUNT(C37:P37)=0,"",IFERROR(G37/F37,0)) | V37: =IF(COUNT(C37:P37)=0,"",IFERROR(C37/G37,0)) | W37: =IF(COUNT(C37:P37)=0,"",IFERROR(G37/D37*1000,0)) | X37: =IF(COUNT(C37:P37)=0,"",IFERROR(H37/G37,0)) | Y37: =IF(COUNT(C37:P37)=0,"",IFERROR(C37/H37,0)) | Z37: =IF(COUNT(C37:P37)=0,"",IFERROR(C37/I37,0)) | AA37: =IF(COUNT(C37:P37)=0,"",IFERROR(Y37/Q37,0)) | AB37: =IF(COUNT(C37:P37)=0,"",IFERROR(H37/D37*1000,0)) | AC37: =IF(COUNT(C37:P37)=0,"",IFERROR(J37/H37,0)) | AD37: =IF(COUNT(C37:P37)=0,"",IFERROR(C37/J37,0)) | AE37: =IF(COUNT(C37:P37)=0,"",IFERROR(K37/H37,0)) | AF37: =IF(COUNT(C37:P37)=0,"",IFERROR(L37/H37,0)) | AG37: =IF(COUNT(C37:P37)=0,"",IFERROR(C37/K37,0)) | AH37: =IF(COUNT(C37:P37)=0,"",IFERROR(M37/K37,0)) | AI37: =IF(COUNT(C37:P37)=0,"",IFERROR(C37/M37,0)) | AJ37: =IF(COUNT(C37:P37)=0,"",IFERROR(N37/M37,0)) | AK37: =IF(COUNT(C37:P37)=0,"",IFERROR(N37/H37,0)) | AL37: =IF(COUNT(C37:P37)=0,"",IFERROR(C37/N37,0)) | AM37: =IF(COUNT(C37:P37)=0,"",IFERROR(O37/N37,0)) | AN37: =IF(COUNT(C37:P37)=0,"",IFERROR(P37/N37,0)) | AO37: =IF(COUNT(C37:P37)=0,"",IFERROR(N37*Config!$C$7+O37*Config!$C$8+P37*Config!$C$9,0)) | AP37: =IF(COUNT(C37:P37)=0,"",IFERROR(AO37/N37,0)) | AQ37: =IF(COUNT(C37:P37)=0,"",IFERROR(AO37*(1-Config!$C$10-Config!$C$11-Config!$C$12),0)) | AR37: =IF(COUNT(C37:P37)=0,"",IFERROR(AQ37-C37-Config!$C$13,0)) | AS37: =IF(COUNT(C37:P37)=0,"",IFERROR(AQ37/C37,0)) | AT37: =IF(COUNT(C37:P37)=0,"",IFERROR(AR37/G37,0)) | AU37: =IF(COUNT(C37:P37)=0,"",IFERROR(AT37/V37,0)) | AV37: =IF(COUNT(C37:P37)=0,"",IFERROR(AR37/H37,0))
A38: =Config!$C$6+32 | B38: =INT((A38-Config!$C$6)/7)+1 | Q38: =IF(COUNT(C38:P38)=0,"",IFERROR(C38/D38*1000,0)) | R38: =IF(COUNT(C38:P38)=0,"",IFERROR(D38/E38,0)) | S38: =IF(COUNT(C38:P38)=0,"",IFERROR(F38/D38,0)) | T38: =IF(COUNT(C38:P38)=0,"",IFERROR(C38/F38,0)) | U38: =IF(COUNT(C38:P38)=0,"",IFERROR(G38/F38,0)) | V38: =IF(COUNT(C38:P38)=0,"",IFERROR(C38/G38,0)) | W38: =IF(COUNT(C38:P38)=0,"",IFERROR(G38/D38*1000,0)) | X38: =IF(COUNT(C38:P38)=0,"",IFERROR(H38/G38,0)) | Y38: =IF(COUNT(C38:P38)=0,"",IFERROR(C38/H38,0)) | Z38: =IF(COUNT(C38:P38)=0,"",IFERROR(C38/I38,0)) | AA38: =IF(COUNT(C38:P38)=0,"",IFERROR(Y38/Q38,0)) | AB38: =IF(COUNT(C38:P38)=0,"",IFERROR(H38/D38*1000,0)) | AC38: =IF(COUNT(C38:P38)=0,"",IFERROR(J38/H38,0)) | AD38: =IF(COUNT(C38:P38)=0,"",IFERROR(C38/J38,0)) | AE38: =IF(COUNT(C38:P38)=0,"",IFERROR(K38/H38,0)) | AF38: =IF(COUNT(C38:P38)=0,"",IFERROR(L38/H38,0)) | AG38: =IF(COUNT(C38:P38)=0,"",IFERROR(C38/K38,0)) | AH38: =IF(COUNT(C38:P38)=0,"",IFERROR(M38/K38,0)) | AI38: =IF(COUNT(C38:P38)=0,"",IFERROR(C38/M38,0)) | AJ38: =IF(COUNT(C38:P38)=0,"",IFERROR(N38/M38,0)) | AK38: =IF(COUNT(C38:P38)=0,"",IFERROR(N38/H38,0)) | AL38: =IF(COUNT(C38:P38)=0,"",IFERROR(C38/N38,0)) | AM38: =IF(COUNT(C38:P38)=0,"",IFERROR(O38/N38,0)) | AN38: =IF(COUNT(C38:P38)=0,"",IFERROR(P38/N38,0)) | AO38: =IF(COUNT(C38:P38)=0,"",IFERROR(N38*Config!$C$7+O38*Config!$C$8+P38*Config!$C$9,0)) | AP38: =IF(COUNT(C38:P38)=0,"",IFERROR(AO38/N38,0)) | AQ38: =IF(COUNT(C38:P38)=0,"",IFERROR(AO38*(1-Config!$C$10-Config!$C$11-Config!$C$12),0)) | AR38: =IF(COUNT(C38:P38)=0,"",IFERROR(AQ38-C38-Config!$C$13,0)) | AS38: =IF(COUNT(C38:P38)=0,"",IFERROR(AQ38/C38,0)) | AT38: =IF(COUNT(C38:P38)=0,"",IFERROR(AR38/G38,0)) | AU38: =IF(COUNT(C38:P38)=0,"",IFERROR(AT38/V38,0)) | AV38: =IF(COUNT(C38:P38)=0,"",IFERROR(AR38/H38,0))
A39: =Config!$C$6+33 | B39: =INT((A39-Config!$C$6)/7)+1 | Q39: =IF(COUNT(C39:P39)=0,"",IFERROR(C39/D39*1000,0)) | R39: =IF(COUNT(C39:P39)=0,"",IFERROR(D39/E39,0)) | S39: =IF(COUNT(C39:P39)=0,"",IFERROR(F39/D39,0)) | T39: =IF(COUNT(C39:P39)=0,"",IFERROR(C39/F39,0)) | U39: =IF(COUNT(C39:P39)=0,"",IFERROR(G39/F39,0)) | V39: =IF(COUNT(C39:P39)=0,"",IFERROR(C39/G39,0)) | W39: =IF(COUNT(C39:P39)=0,"",IFERROR(G39/D39*1000,0)) | X39: =IF(COUNT(C39:P39)=0,"",IFERROR(H39/G39,0)) | Y39: =IF(COUNT(C39:P39)=0,"",IFERROR(C39/H39,0)) | Z39: =IF(COUNT(C39:P39)=0,"",IFERROR(C39/I39,0)) | AA39: =IF(COUNT(C39:P39)=0,"",IFERROR(Y39/Q39,0)) | AB39: =IF(COUNT(C39:P39)=0,"",IFERROR(H39/D39*1000,0)) | AC39: =IF(COUNT(C39:P39)=0,"",IFERROR(J39/H39,0)) | AD39: =IF(COUNT(C39:P39)=0,"",IFERROR(C39/J39,0)) | AE39: =IF(COUNT(C39:P39)=0,"",IFERROR(K39/H39,0)) | AF39: =IF(COUNT(C39:P39)=0,"",IFERROR(L39/H39,0)) | AG39: =IF(COUNT(C39:P39)=0,"",IFERROR(C39/K39,0)) | AH39: =IF(COUNT(C39:P39)=0,"",IFERROR(M39/K39,0)) | AI39: =IF(COUNT(C39:P39)=0,"",IFERROR(C39/M39,0)) | AJ39: =IF(COUNT(C39:P39)=0,"",IFERROR(N39/M39,0)) | AK39: =IF(COUNT(C39:P39)=0,"",IFERROR(N39/H39,0)) | AL39: =IF(COUNT(C39:P39)=0,"",IFERROR(C39/N39,0)) | AM39: =IF(COUNT(C39:P39)=0,"",IFERROR(O39/N39,0)) | AN39: =IF(COUNT(C39:P39)=0,"",IFERROR(P39/N39,0)) | AO39: =IF(COUNT(C39:P39)=0,"",IFERROR(N39*Config!$C$7+O39*Config!$C$8+P39*Config!$C$9,0)) | AP39: =IF(COUNT(C39:P39)=0,"",IFERROR(AO39/N39,0)) | AQ39: =IF(COUNT(C39:P39)=0,"",IFERROR(AO39*(1-Config!$C$10-Config!$C$11-Config!$C$12),0)) | AR39: =IF(COUNT(C39:P39)=0,"",IFERROR(AQ39-C39-Config!$C$13,0)) | AS39: =IF(COUNT(C39:P39)=0,"",IFERROR(AQ39/C39,0)) | AT39: =IF(COUNT(C39:P39)=0,"",IFERROR(AR39/G39,0)) | AU39: =IF(COUNT(C39:P39)=0,"",IFERROR(AT39/V39,0)) | AV39: =IF(COUNT(C39:P39)=0,"",IFERROR(AR39/H39,0))
A40: =Config!$C$6+34 | B40: =INT((A40-Config!$C$6)/7)+1 | Q40: =IF(COUNT(C40:P40)=0,"",IFERROR(C40/D40*1000,0)) | R40: =IF(COUNT(C40:P40)=0,"",IFERROR(D40/E40,0)) | S40: =IF(COUNT(C40:P40)=0,"",IFERROR(F40/D40,0)) | T40: =IF(COUNT(C40:P40)=0,"",IFERROR(C40/F40,0)) | U40: =IF(COUNT(C40:P40)=0,"",IFERROR(G40/F40,0)) | V40: =IF(COUNT(C40:P40)=0,"",IFERROR(C40/G40,0)) | W40: =IF(COUNT(C40:P40)=0,"",IFERROR(G40/D40*1000,0)) | X40: =IF(COUNT(C40:P40)=0,"",IFERROR(H40/G40,0)) | Y40: =IF(COUNT(C40:P40)=0,"",IFERROR(C40/H40,0)) | Z40: =IF(COUNT(C40:P40)=0,"",IFERROR(C40/I40,0)) | AA40: =IF(COUNT(C40:P40)=0,"",IFERROR(Y40/Q40,0)) | AB40: =IF(COUNT(C40:P40)=0,"",IFERROR(H40/D40*1000,0)) | AC40: =IF(COUNT(C40:P40)=0,"",IFERROR(J40/H40,0)) | AD40: =IF(COUNT(C40:P40)=0,"",IFERROR(C40/J40,0)) | AE40: =IF(COUNT(C40:P40)=0,"",IFERROR(K40/H40,0)) | AF40: =IF(COUNT(C40:P40)=0,"",IFERROR(L40/H40,0)) | AG40: =IF(COUNT(C40:P40)=0,"",IFERROR(C40/K40,0)) | AH40: =IF(COUNT(C40:P40)=0,"",IFERROR(M40/K40,0)) | AI40: =IF(COUNT(C40:P40)=0,"",IFERROR(C40/M40,0)) | AJ40: =IF(COUNT(C40:P40)=0,"",IFERROR(N40/M40,0)) | AK40: =IF(COUNT(C40:P40)=0,"",IFERROR(N40/H40,0)) | AL40: =IF(COUNT(C40:P40)=0,"",IFERROR(C40/N40,0)) | AM40: =IF(COUNT(C40:P40)=0,"",IFERROR(O40/N40,0)) | AN40: =IF(COUNT(C40:P40)=0,"",IFERROR(P40/N40,0)) | AO40: =IF(COUNT(C40:P40)=0,"",IFERROR(N40*Config!$C$7+O40*Config!$C$8+P40*Config!$C$9,0)) | AP40: =IF(COUNT(C40:P40)=0,"",IFERROR(AO40/N40,0)) | AQ40: =IF(COUNT(C40:P40)=0,"",IFERROR(AO40*(1-Config!$C$10-Config!$C$11-Config!$C$12),0)) | AR40: =IF(COUNT(C40:P40)=0,"",IFERROR(AQ40-C40-Config!$C$13,0)) | AS40: =IF(COUNT(C40:P40)=0,"",IFERROR(AQ40/C40,0)) | AT40: =IF(COUNT(C40:P40)=0,"",IFERROR(AR40/G40,0)) | AU40: =IF(COUNT(C40:P40)=0,"",IFERROR(AT40/V40,0)) | AV40: =IF(COUNT(C40:P40)=0,"",IFERROR(AR40/H40,0))
A41: =Config!$C$6+35 | B41: =INT((A41-Config!$C$6)/7)+1 | Q41: =IF(COUNT(C41:P41)=0,"",IFERROR(C41/D41*1000,0)) | R41: =IF(COUNT(C41:P41)=0,"",IFERROR(D41/E41,0)) | S41: =IF(COUNT(C41:P41)=0,"",IFERROR(F41/D41,0)) | T41: =IF(COUNT(C41:P41)=0,"",IFERROR(C41/F41,0)) | U41: =IF(COUNT(C41:P41)=0,"",IFERROR(G41/F41,0)) | V41: =IF(COUNT(C41:P41)=0,"",IFERROR(C41/G41,0)) | W41: =IF(COUNT(C41:P41)=0,"",IFERROR(G41/D41*1000,0)) | X41: =IF(COUNT(C41:P41)=0,"",IFERROR(H41/G41,0)) | Y41: =IF(COUNT(C41:P41)=0,"",IFERROR(C41/H41,0)) | Z41: =IF(COUNT(C41:P41)=0,"",IFERROR(C41/I41,0)) | AA41: =IF(COUNT(C41:P41)=0,"",IFERROR(Y41/Q41,0)) | AB41: =IF(COUNT(C41:P41)=0,"",IFERROR(H41/D41*1000,0)) | AC41: =IF(COUNT(C41:P41)=0,"",IFERROR(J41/H41,0)) | AD41: =IF(COUNT(C41:P41)=0,"",IFERROR(C41/J41,0)) | AE41: =IF(COUNT(C41:P41)=0,"",IFERROR(K41/H41,0)) | AF41: =IF(COUNT(C41:P41)=0,"",IFERROR(L41/H41,0)) | AG41: =IF(COUNT(C41:P41)=0,"",IFERROR(C41/K41,0)) | AH41: =IF(COUNT(C41:P41)=0,"",IFERROR(M41/K41,0)) | AI41: =IF(COUNT(C41:P41)=0,"",IFERROR(C41/M41,0)) | AJ41: =IF(COUNT(C41:P41)=0,"",IFERROR(N41/M41,0)) | AK41: =IF(COUNT(C41:P41)=0,"",IFERROR(N41/H41,0)) | AL41: =IF(COUNT(C41:P41)=0,"",IFERROR(C41/N41,0)) | AM41: =IF(COUNT(C41:P41)=0,"",IFERROR(O41/N41,0)) | AN41: =IF(COUNT(C41:P41)=0,"",IFERROR(P41/N41,0)) | AO41: =IF(COUNT(C41:P41)=0,"",IFERROR(N41*Config!$C$7+O41*Config!$C$8+P41*Config!$C$9,0)) | AP41: =IF(COUNT(C41:P41)=0,"",IFERROR(AO41/N41,0)) | AQ41: =IF(COUNT(C41:P41)=0,"",IFERROR(AO41*(1-Config!$C$10-Config!$C$11-Config!$C$12),0)) | AR41: =IF(COUNT(C41:P41)=0,"",IFERROR(AQ41-C41-Config!$C$13,0)) | AS41: =IF(COUNT(C41:P41)=0,"",IFERROR(AQ41/C41,0)) | AT41: =IF(COUNT(C41:P41)=0,"",IFERROR(AR41/G41,0)) | AU41: =IF(COUNT(C41:P41)=0,"",IFERROR(AT41/V41,0)) | AV41: =IF(COUNT(C41:P41)=0,"",IFERROR(AR41/H41,0))
A42: =Config!$C$6+36 | B42: =INT((A42-Config!$C$6)/7)+1 | Q42: =IF(COUNT(C42:P42)=0,"",IFERROR(C42/D42*1000,0)) | R42: =IF(COUNT(C42:P42)=0,"",IFERROR(D42/E42,0)) | S42: =IF(COUNT(C42:P42)=0,"",IFERROR(F42/D42,0)) | T42: =IF(COUNT(C42:P42)=0,"",IFERROR(C42/F42,0)) | U42: =IF(COUNT(C42:P42)=0,"",IFERROR(G42/F42,0)) | V42: =IF(COUNT(C42:P42)=0,"",IFERROR(C42/G42,0)) | W42: =IF(COUNT(C42:P42)=0,"",IFERROR(G42/D42*1000,0)) | X42: =IF(COUNT(C42:P42)=0,"",IFERROR(H42/G42,0)) | Y42: =IF(COUNT(C42:P42)=0,"",IFERROR(C42/H42,0)) | Z42: =IF(COUNT(C42:P42)=0,"",IFERROR(C42/I42,0)) | AA42: =IF(COUNT(C42:P42)=0,"",IFERROR(Y42/Q42,0)) | AB42: =IF(COUNT(C42:P42)=0,"",IFERROR(H42/D42*1000,0)) | AC42: =IF(COUNT(C42:P42)=0,"",IFERROR(J42/H42,0)) | AD42: =IF(COUNT(C42:P42)=0,"",IFERROR(C42/J42,0)) | AE42: =IF(COUNT(C42:P42)=0,"",IFERROR(K42/H42,0)) | AF42: =IF(COUNT(C42:P42)=0,"",IFERROR(L42/H42,0)) | AG42: =IF(COUNT(C42:P42)=0,"",IFERROR(C42/K42,0)) | AH42: =IF(COUNT(C42:P42)=0,"",IFERROR(M42/K42,0)) | AI42: =IF(COUNT(C42:P42)=0,"",IFERROR(C42/M42,0)) | AJ42: =IF(COUNT(C42:P42)=0,"",IFERROR(N42/M42,0)) | AK42: =IF(COUNT(C42:P42)=0,"",IFERROR(N42/H42,0)) | AL42: =IF(COUNT(C42:P42)=0,"",IFERROR(C42/N42,0)) | AM42: =IF(COUNT(C42:P42)=0,"",IFERROR(O42/N42,0)) | AN42: =IF(COUNT(C42:P42)=0,"",IFERROR(P42/N42,0)) | AO42: =IF(COUNT(C42:P42)=0,"",IFERROR(N42*Config!$C$7+O42*Config!$C$8+P42*Config!$C$9,0)) | AP42: =IF(COUNT(C42:P42)=0,"",IFERROR(AO42/N42,0)) | AQ42: =IF(COUNT(C42:P42)=0,"",IFERROR(AO42*(1-Config!$C$10-Config!$C$11-Config!$C$12),0)) | AR42: =IF(COUNT(C42:P42)=0,"",IFERROR(AQ42-C42-Config!$C$13,0)) | AS42: =IF(COUNT(C42:P42)=0,"",IFERROR(AQ42/C42,0)) | AT42: =IF(COUNT(C42:P42)=0,"",IFERROR(AR42/G42,0)) | AU42: =IF(COUNT(C42:P42)=0,"",IFERROR(AT42/V42,0)) | AV42: =IF(COUNT(C42:P42)=0,"",IFERROR(AR42/H42,0))
A43: =Config!$C$6+37 | B43: =INT((A43-Config!$C$6)/7)+1 | Q43: =IF(COUNT(C43:P43)=0,"",IFERROR(C43/D43*1000,0)) | R43: =IF(COUNT(C43:P43)=0,"",IFERROR(D43/E43,0)) | S43: =IF(COUNT(C43:P43)=0,"",IFERROR(F43/D43,0)) | T43: =IF(COUNT(C43:P43)=0,"",IFERROR(C43/F43,0)) | U43: =IF(COUNT(C43:P43)=0,"",IFERROR(G43/F43,0)) | V43: =IF(COUNT(C43:P43)=0,"",IFERROR(C43/G43,0)) | W43: =IF(COUNT(C43:P43)=0,"",IFERROR(G43/D43*1000,0)) | X43: =IF(COUNT(C43:P43)=0,"",IFERROR(H43/G43,0)) | Y43: =IF(COUNT(C43:P43)=0,"",IFERROR(C43/H43,0)) | Z43: =IF(COUNT(C43:P43)=0,"",IFERROR(C43/I43,0)) | AA43: =IF(COUNT(C43:P43)=0,"",IFERROR(Y43/Q43,0)) | AB43: =IF(COUNT(C43:P43)=0,"",IFERROR(H43/D43*1000,0)) | AC43: =IF(COUNT(C43:P43)=0,"",IFERROR(J43/H43,0)) | AD43: =IF(COUNT(C43:P43)=0,"",IFERROR(C43/J43,0)) | AE43: =IF(COUNT(C43:P43)=0,"",IFERROR(K43/H43,0)) | AF43: =IF(COUNT(C43:P43)=0,"",IFERROR(L43/H43,0)) | AG43: =IF(COUNT(C43:P43)=0,"",IFERROR(C43/K43,0)) | AH43: =IF(COUNT(C43:P43)=0,"",IFERROR(M43/K43,0)) | AI43: =IF(COUNT(C43:P43)=0,"",IFERROR(C43/M43,0)) | AJ43: =IF(COUNT(C43:P43)=0,"",IFERROR(N43/M43,0)) | AK43: =IF(COUNT(C43:P43)=0,"",IFERROR(N43/H43,0)) | AL43: =IF(COUNT(C43:P43)=0,"",IFERROR(C43/N43,0)) | AM43: =IF(COUNT(C43:P43)=0,"",IFERROR(O43/N43,0)) | AN43: =IF(COUNT(C43:P43)=0,"",IFERROR(P43/N43,0)) | AO43: =IF(COUNT(C43:P43)=0,"",IFERROR(N43*Config!$C$7+O43*Config!$C$8+P43*Config!$C$9,0)) | AP43: =IF(COUNT(C43:P43)=0,"",IFERROR(AO43/N43,0)) | AQ43: =IF(COUNT(C43:P43)=0,"",IFERROR(AO43*(1-Config!$C$10-Config!$C$11-Config!$C$12),0)) | AR43: =IF(COUNT(C43:P43)=0,"",IFERROR(AQ43-C43-Config!$C$13,0)) | AS43: =IF(COUNT(C43:P43)=0,"",IFERROR(AQ43/C43,0)) | AT43: =IF(COUNT(C43:P43)=0,"",IFERROR(AR43/G43,0)) | AU43: =IF(COUNT(C43:P43)=0,"",IFERROR(AT43/V43,0)) | AV43: =IF(COUNT(C43:P43)=0,"",IFERROR(AR43/H43,0))
A44: =Config!$C$6+38 | B44: =INT((A44-Config!$C$6)/7)+1 | Q44: =IF(COUNT(C44:P44)=0,"",IFERROR(C44/D44*1000,0)) | R44: =IF(COUNT(C44:P44)=0,"",IFERROR(D44/E44,0)) | S44: =IF(COUNT(C44:P44)=0,"",IFERROR(F44/D44,0)) | T44: =IF(COUNT(C44:P44)=0,"",IFERROR(C44/F44,0)) | U44: =IF(COUNT(C44:P44)=0,"",IFERROR(G44/F44,0)) | V44: =IF(COUNT(C44:P44)=0,"",IFERROR(C44/G44,0)) | W44: =IF(COUNT(C44:P44)=0,"",IFERROR(G44/D44*1000,0)) | X44: =IF(COUNT(C44:P44)=0,"",IFERROR(H44/G44,0)) | Y44: =IF(COUNT(C44:P44)=0,"",IFERROR(C44/H44,0)) | Z44: =IF(COUNT(C44:P44)=0,"",IFERROR(C44/I44,0)) | AA44: =IF(COUNT(C44:P44)=0,"",IFERROR(Y44/Q44,0)) | AB44: =IF(COUNT(C44:P44)=0,"",IFERROR(H44/D44*1000,0)) | AC44: =IF(COUNT(C44:P44)=0,"",IFERROR(J44/H44,0)) | AD44: =IF(COUNT(C44:P44)=0,"",IFERROR(C44/J44,0)) | AE44: =IF(COUNT(C44:P44)=0,"",IFERROR(K44/H44,0)) | AF44: =IF(COUNT(C44:P44)=0,"",IFERROR(L44/H44,0)) | AG44: =IF(COUNT(C44:P44)=0,"",IFERROR(C44/K44,0)) | AH44: =IF(COUNT(C44:P44)=0,"",IFERROR(M44/K44,0)) | AI44: =IF(COUNT(C44:P44)=0,"",IFERROR(C44/M44,0)) | AJ44: =IF(COUNT(C44:P44)=0,"",IFERROR(N44/M44,0)) | AK44: =IF(COUNT(C44:P44)=0,"",IFERROR(N44/H44,0)) | AL44: =IF(COUNT(C44:P44)=0,"",IFERROR(C44/N44,0)) | AM44: =IF(COUNT(C44:P44)=0,"",IFERROR(O44/N44,0)) | AN44: =IF(COUNT(C44:P44)=0,"",IFERROR(P44/N44,0)) | AO44: =IF(COUNT(C44:P44)=0,"",IFERROR(N44*Config!$C$7+O44*Config!$C$8+P44*Config!$C$9,0)) | AP44: =IF(COUNT(C44:P44)=0,"",IFERROR(AO44/N44,0)) | AQ44: =IF(COUNT(C44:P44)=0,"",IFERROR(AO44*(1-Config!$C$10-Config!$C$11-Config!$C$12),0)) | AR44: =IF(COUNT(C44:P44)=0,"",IFERROR(AQ44-C44-Config!$C$13,0)) | AS44: =IF(COUNT(C44:P44)=0,"",IFERROR(AQ44/C44,0)) | AT44: =IF(COUNT(C44:P44)=0,"",IFERROR(AR44/G44,0)) | AU44: =IF(COUNT(C44:P44)=0,"",IFERROR(AT44/V44,0)) | AV44: =IF(COUNT(C44:P44)=0,"",IFERROR(AR44/H44,0))
A45: =Config!$C$6+39 | B45: =INT((A45-Config!$C$6)/7)+1 | Q45: =IF(COUNT(C45:P45)=0,"",IFERROR(C45/D45*1000,0)) | R45: =IF(COUNT(C45:P45)=0,"",IFERROR(D45/E45,0)) | S45: =IF(COUNT(C45:P45)=0,"",IFERROR(F45/D45,0)) | T45: =IF(COUNT(C45:P45)=0,"",IFERROR(C45/F45,0)) | U45: =IF(COUNT(C45:P45)=0,"",IFERROR(G45/F45,0)) | V45: =IF(COUNT(C45:P45)=0,"",IFERROR(C45/G45,0)) | W45: =IF(COUNT(C45:P45)=0,"",IFERROR(G45/D45*1000,0)) | X45: =IF(COUNT(C45:P45)=0,"",IFERROR(H45/G45,0)) | Y45: =IF(COUNT(C45:P45)=0,"",IFERROR(C45/H45,0)) | Z45: =IF(COUNT(C45:P45)=0,"",IFERROR(C45/I45,0)) | AA45: =IF(COUNT(C45:P45)=0,"",IFERROR(Y45/Q45,0)) | AB45: =IF(COUNT(C45:P45)=0,"",IFERROR(H45/D45*1000,0)) | AC45: =IF(COUNT(C45:P45)=0,"",IFERROR(J45/H45,0)) | AD45: =IF(COUNT(C45:P45)=0,"",IFERROR(C45/J45,0)) | AE45: =IF(COUNT(C45:P45)=0,"",IFERROR(K45/H45,0)) | AF45: =IF(COUNT(C45:P45)=0,"",IFERROR(L45/H45,0)) | AG45: =IF(COUNT(C45:P45)=0,"",IFERROR(C45/K45,0)) | AH45: =IF(COUNT(C45:P45)=0,"",IFERROR(M45/K45,0)) | AI45: =IF(COUNT(C45:P45)=0,"",IFERROR(C45/M45,0)) | AJ45: =IF(COUNT(C45:P45)=0,"",IFERROR(N45/M45,0)) | AK45: =IF(COUNT(C45:P45)=0,"",IFERROR(N45/H45,0)) | AL45: =IF(COUNT(C45:P45)=0,"",IFERROR(C45/N45,0)) | AM45: =IF(COUNT(C45:P45)=0,"",IFERROR(O45/N45,0)) | AN45: =IF(COUNT(C45:P45)=0,"",IFERROR(P45/N45,0)) | AO45: =IF(COUNT(C45:P45)=0,"",IFERROR(N45*Config!$C$7+O45*Config!$C$8+P45*Config!$C$9,0)) | AP45: =IF(COUNT(C45:P45)=0,"",IFERROR(AO45/N45,0)) | AQ45: =IF(COUNT(C45:P45)=0,"",IFERROR(AO45*(1-Config!$C$10-Config!$C$11-Config!$C$12),0)) | AR45: =IF(COUNT(C45:P45)=0,"",IFERROR(AQ45-C45-Config!$C$13,0)) | AS45: =IF(COUNT(C45:P45)=0,"",IFERROR(AQ45/C45,0)) | AT45: =IF(COUNT(C45:P45)=0,"",IFERROR(AR45/G45,0)) | AU45: =IF(COUNT(C45:P45)=0,"",IFERROR(AT45/V45,0)) | AV45: =IF(COUNT(C45:P45)=0,"",IFERROR(AR45/H45,0))
A46: =Config!$C$6+40 | B46: =INT((A46-Config!$C$6)/7)+1 | Q46: =IF(COUNT(C46:P46)=0,"",IFERROR(C46/D46*1000,0)) | R46: =IF(COUNT(C46:P46)=0,"",IFERROR(D46/E46,0)) | S46: =IF(COUNT(C46:P46)=0,"",IFERROR(F46/D46,0)) | T46: =IF(COUNT(C46:P46)=0,"",IFERROR(C46/F46,0)) | U46: =IF(COUNT(C46:P46)=0,"",IFERROR(G46/F46,0)) | V46: =IF(COUNT(C46:P46)=0,"",IFERROR(C46/G46,0)) | W46: =IF(COUNT(C46:P46)=0,"",IFERROR(G46/D46*1000,0)) | X46: =IF(COUNT(C46:P46)=0,"",IFERROR(H46/G46,0)) | Y46: =IF(COUNT(C46:P46)=0,"",IFERROR(C46/H46,0)) | Z46: =IF(COUNT(C46:P46)=0,"",IFERROR(C46/I46,0)) | AA46: =IF(COUNT(C46:P46)=0,"",IFERROR(Y46/Q46,0)) | AB46: =IF(COUNT(C46:P46)=0,"",IFERROR(H46/D46*1000,0)) | AC46: =IF(COUNT(C46:P46)=0,"",IFERROR(J46/H46,0)) | AD46: =IF(COUNT(C46:P46)=0,"",IFERROR(C46/J46,0)) | AE46: =IF(COUNT(C46:P46)=0,"",IFERROR(K46/H46,0)) | AF46: =IF(COUNT(C46:P46)=0,"",IFERROR(L46/H46,0)) | AG46: =IF(COUNT(C46:P46)=0,"",IFERROR(C46/K46,0)) | AH46: =IF(COUNT(C46:P46)=0,"",IFERROR(M46/K46,0)) | AI46: =IF(COUNT(C46:P46)=0,"",IFERROR(C46/M46,0)) | AJ46: =IF(COUNT(C46:P46)=0,"",IFERROR(N46/M46,0)) | AK46: =IF(COUNT(C46:P46)=0,"",IFERROR(N46/H46,0)) | AL46: =IF(COUNT(C46:P46)=0,"",IFERROR(C46/N46,0)) | AM46: =IF(COUNT(C46:P46)=0,"",IFERROR(O46/N46,0)) | AN46: =IF(COUNT(C46:P46)=0,"",IFERROR(P46/N46,0)) | AO46: =IF(COUNT(C46:P46)=0,"",IFERROR(N46*Config!$C$7+O46*Config!$C$8+P46*Config!$C$9,0)) | AP46: =IF(COUNT(C46:P46)=0,"",IFERROR(AO46/N46,0)) | AQ46: =IF(COUNT(C46:P46)=0,"",IFERROR(AO46*(1-Config!$C$10-Config!$C$11-Config!$C$12),0)) | AR46: =IF(COUNT(C46:P46)=0,"",IFERROR(AQ46-C46-Config!$C$13,0)) | AS46: =IF(COUNT(C46:P46)=0,"",IFERROR(AQ46/C46,0)) | AT46: =IF(COUNT(C46:P46)=0,"",IFERROR(AR46/G46,0)) | AU46: =IF(COUNT(C46:P46)=0,"",IFERROR(AT46/V46,0)) | AV46: =IF(COUNT(C46:P46)=0,"",IFERROR(AR46/H46,0))
A47: =Config!$C$6+41 | B47: =INT((A47-Config!$C$6)/7)+1 | Q47: =IF(COUNT(C47:P47)=0,"",IFERROR(C47/D47*1000,0)) | R47: =IF(COUNT(C47:P47)=0,"",IFERROR(D47/E47,0)) | S47: =IF(COUNT(C47:P47)=0,"",IFERROR(F47/D47,0)) | T47: =IF(COUNT(C47:P47)=0,"",IFERROR(C47/F47,0)) | U47: =IF(COUNT(C47:P47)=0,"",IFERROR(G47/F47,0)) | V47: =IF(COUNT(C47:P47)=0,"",IFERROR(C47/G47,0)) | W47: =IF(COUNT(C47:P47)=0,"",IFERROR(G47/D47*1000,0)) | X47: =IF(COUNT(C47:P47)=0,"",IFERROR(H47/G47,0)) | Y47: =IF(COUNT(C47:P47)=0,"",IFERROR(C47/H47,0)) | Z47: =IF(COUNT(C47:P47)=0,"",IFERROR(C47/I47,0)) | AA47: =IF(COUNT(C47:P47)=0,"",IFERROR(Y47/Q47,0)) | AB47: =IF(COUNT(C47:P47)=0,"",IFERROR(H47/D47*1000,0)) | AC47: =IF(COUNT(C47:P47)=0,"",IFERROR(J47/H47,0)) | AD47: =IF(COUNT(C47:P47)=0,"",IFERROR(C47/J47,0)) | AE47: =IF(COUNT(C47:P47)=0,"",IFERROR(K47/H47,0)) | AF47: =IF(COUNT(C47:P47)=0,"",IFERROR(L47/H47,0)) | AG47: =IF(COUNT(C47:P47)=0,"",IFERROR(C47/K47,0)) | AH47: =IF(COUNT(C47:P47)=0,"",IFERROR(M47/K47,0)) | AI47: =IF(COUNT(C47:P47)=0,"",IFERROR(C47/M47,0)) | AJ47: =IF(COUNT(C47:P47)=0,"",IFERROR(N47/M47,0)) | AK47: =IF(COUNT(C47:P47)=0,"",IFERROR(N47/H47,0)) | AL47: =IF(COUNT(C47:P47)=0,"",IFERROR(C47/N47,0)) | AM47: =IF(COUNT(C47:P47)=0,"",IFERROR(O47/N47,0)) | AN47: =IF(COUNT(C47:P47)=0,"",IFERROR(P47/N47,0)) | AO47: =IF(COUNT(C47:P47)=0,"",IFERROR(N47*Config!$C$7+O47*Config!$C$8+P47*Config!$C$9,0)) | AP47: =IF(COUNT(C47:P47)=0,"",IFERROR(AO47/N47,0)) | AQ47: =IF(COUNT(C47:P47)=0,"",IFERROR(AO47*(1-Config!$C$10-Config!$C$11-Config!$C$12),0)) | AR47: =IF(COUNT(C47:P47)=0,"",IFERROR(AQ47-C47-Config!$C$13,0)) | AS47: =IF(COUNT(C47:P47)=0,"",IFERROR(AQ47/C47,0)) | AT47: =IF(COUNT(C47:P47)=0,"",IFERROR(AR47/G47,0)) | AU47: =IF(COUNT(C47:P47)=0,"",IFERROR(AT47/V47,0)) | AV47: =IF(COUNT(C47:P47)=0,"",IFERROR(AR47/H47,0))
A48: =Config!$C$6+42 | B48: =INT((A48-Config!$C$6)/7)+1 | Q48: =IF(COUNT(C48:P48)=0,"",IFERROR(C48/D48*1000,0)) | R48: =IF(COUNT(C48:P48)=0,"",IFERROR(D48/E48,0)) | S48: =IF(COUNT(C48:P48)=0,"",IFERROR(F48/D48,0)) | T48: =IF(COUNT(C48:P48)=0,"",IFERROR(C48/F48,0)) | U48: =IF(COUNT(C48:P48)=0,"",IFERROR(G48/F48,0)) | V48: =IF(COUNT(C48:P48)=0,"",IFERROR(C48/G48,0)) | W48: =IF(COUNT(C48:P48)=0,"",IFERROR(G48/D48*1000,0)) | X48: =IF(COUNT(C48:P48)=0,"",IFERROR(H48/G48,0)) | Y48: =IF(COUNT(C48:P48)=0,"",IFERROR(C48/H48,0)) | Z48: =IF(COUNT(C48:P48)=0,"",IFERROR(C48/I48,0)) | AA48: =IF(COUNT(C48:P48)=0,"",IFERROR(Y48/Q48,0)) | AB48: =IF(COUNT(C48:P48)=0,"",IFERROR(H48/D48*1000,0)) | AC48: =IF(COUNT(C48:P48)=0,"",IFERROR(J48/H48,0)) | AD48: =IF(COUNT(C48:P48)=0,"",IFERROR(C48/J48,0)) | AE48: =IF(COUNT(C48:P48)=0,"",IFERROR(K48/H48,0)) | AF48: =IF(COUNT(C48:P48)=0,"",IFERROR(L48/H48,0)) | AG48: =IF(COUNT(C48:P48)=0,"",IFERROR(C48/K48,0)) | AH48: =IF(COUNT(C48:P48)=0,"",IFERROR(M48/K48,0)) | AI48: =IF(COUNT(C48:P48)=0,"",IFERROR(C48/M48,0)) | AJ48: =IF(COUNT(C48:P48)=0,"",IFERROR(N48/M48,0)) | AK48: =IF(COUNT(C48:P48)=0,"",IFERROR(N48/H48,0)) | AL48: =IF(COUNT(C48:P48)=0,"",IFERROR(C48/N48,0)) | AM48: =IF(COUNT(C48:P48)=0,"",IFERROR(O48/N48,0)) | AN48: =IF(COUNT(C48:P48)=0,"",IFERROR(P48/N48,0)) | AO48: =IF(COUNT(C48:P48)=0,"",IFERROR(N48*Config!$C$7+O48*Config!$C$8+P48*Config!$C$9,0)) | AP48: =IF(COUNT(C48:P48)=0,"",IFERROR(AO48/N48,0)) | AQ48: =IF(COUNT(C48:P48)=0,"",IFERROR(AO48*(1-Config!$C$10-Config!$C$11-Config!$C$12),0)) | AR48: =IF(COUNT(C48:P48)=0,"",IFERROR(AQ48-C48-Config!$C$13,0)) | AS48: =IF(COUNT(C48:P48)=0,"",IFERROR(AQ48/C48,0)) | AT48: =IF(COUNT(C48:P48)=0,"",IFERROR(AR48/G48,0)) | AU48: =IF(COUNT(C48:P48)=0,"",IFERROR(AT48/V48,0)) | AV48: =IF(COUNT(C48:P48)=0,"",IFERROR(AR48/H48,0))
A49: =Config!$C$6+43 | B49: =INT((A49-Config!$C$6)/7)+1 | Q49: =IF(COUNT(C49:P49)=0,"",IFERROR(C49/D49*1000,0)) | R49: =IF(COUNT(C49:P49)=0,"",IFERROR(D49/E49,0)) | S49: =IF(COUNT(C49:P49)=0,"",IFERROR(F49/D49,0)) | T49: =IF(COUNT(C49:P49)=0,"",IFERROR(C49/F49,0)) | U49: =IF(COUNT(C49:P49)=0,"",IFERROR(G49/F49,0)) | V49: =IF(COUNT(C49:P49)=0,"",IFERROR(C49/G49,0)) | W49: =IF(COUNT(C49:P49)=0,"",IFERROR(G49/D49*1000,0)) | X49: =IF(COUNT(C49:P49)=0,"",IFERROR(H49/G49,0)) | Y49: =IF(COUNT(C49:P49)=0,"",IFERROR(C49/H49,0)) | Z49: =IF(COUNT(C49:P49)=0,"",IFERROR(C49/I49,0)) | AA49: =IF(COUNT(C49:P49)=0,"",IFERROR(Y49/Q49,0)) | AB49: =IF(COUNT(C49:P49)=0,"",IFERROR(H49/D49*1000,0)) | AC49: =IF(COUNT(C49:P49)=0,"",IFERROR(J49/H49,0)) | AD49: =IF(COUNT(C49:P49)=0,"",IFERROR(C49/J49,0)) | AE49: =IF(COUNT(C49:P49)=0,"",IFERROR(K49/H49,0)) | AF49: =IF(COUNT(C49:P49)=0,"",IFERROR(L49/H49,0)) | AG49: =IF(COUNT(C49:P49)=0,"",IFERROR(C49/K49,0)) | AH49: =IF(COUNT(C49:P49)=0,"",IFERROR(M49/K49,0)) | AI49: =IF(COUNT(C49:P49)=0,"",IFERROR(C49/M49,0)) | AJ49: =IF(COUNT(C49:P49)=0,"",IFERROR(N49/M49,0)) | AK49: =IF(COUNT(C49:P49)=0,"",IFERROR(N49/H49,0)) | AL49: =IF(COUNT(C49:P49)=0,"",IFERROR(C49/N49,0)) | AM49: =IF(COUNT(C49:P49)=0,"",IFERROR(O49/N49,0)) | AN49: =IF(COUNT(C49:P49)=0,"",IFERROR(P49/N49,0)) | AO49: =IF(COUNT(C49:P49)=0,"",IFERROR(N49*Config!$C$7+O49*Config!$C$8+P49*Config!$C$9,0)) | AP49: =IF(COUNT(C49:P49)=0,"",IFERROR(AO49/N49,0)) | AQ49: =IF(COUNT(C49:P49)=0,"",IFERROR(AO49*(1-Config!$C$10-Config!$C$11-Config!$C$12),0)) | AR49: =IF(COUNT(C49:P49)=0,"",IFERROR(AQ49-C49-Config!$C$13,0)) | AS49: =IF(COUNT(C49:P49)=0,"",IFERROR(AQ49/C49,0)) | AT49: =IF(COUNT(C49:P49)=0,"",IFERROR(AR49/G49,0)) | AU49: =IF(COUNT(C49:P49)=0,"",IFERROR(AT49/V49,0)) | AV49: =IF(COUNT(C49:P49)=0,"",IFERROR(AR49/H49,0))
A50: =Config!$C$6+44 | B50: =INT((A50-Config!$C$6)/7)+1 | Q50: =IF(COUNT(C50:P50)=0,"",IFERROR(C50/D50*1000,0)) | R50: =IF(COUNT(C50:P50)=0,"",IFERROR(D50/E50,0)) | S50: =IF(COUNT(C50:P50)=0,"",IFERROR(F50/D50,0)) | T50: =IF(COUNT(C50:P50)=0,"",IFERROR(C50/F50,0)) | U50: =IF(COUNT(C50:P50)=0,"",IFERROR(G50/F50,0)) | V50: =IF(COUNT(C50:P50)=0,"",IFERROR(C50/G50,0)) | W50: =IF(COUNT(C50:P50)=0,"",IFERROR(G50/D50*1000,0)) | X50: =IF(COUNT(C50:P50)=0,"",IFERROR(H50/G50,0)) | Y50: =IF(COUNT(C50:P50)=0,"",IFERROR(C50/H50,0)) | Z50: =IF(COUNT(C50:P50)=0,"",IFERROR(C50/I50,0)) | AA50: =IF(COUNT(C50:P50)=0,"",IFERROR(Y50/Q50,0)) | AB50: =IF(COUNT(C50:P50)=0,"",IFERROR(H50/D50*1000,0)) | AC50: =IF(COUNT(C50:P50)=0,"",IFERROR(J50/H50,0)) | AD50: =IF(COUNT(C50:P50)=0,"",IFERROR(C50/J50,0)) | AE50: =IF(COUNT(C50:P50)=0,"",IFERROR(K50/H50,0)) | AF50: =IF(COUNT(C50:P50)=0,"",IFERROR(L50/H50,0)) | AG50: =IF(COUNT(C50:P50)=0,"",IFERROR(C50/K50,0)) | AH50: =IF(COUNT(C50:P50)=0,"",IFERROR(M50/K50,0)) | AI50: =IF(COUNT(C50:P50)=0,"",IFERROR(C50/M50,0)) | AJ50: =IF(COUNT(C50:P50)=0,"",IFERROR(N50/M50,0)) | AK50: =IF(COUNT(C50:P50)=0,"",IFERROR(N50/H50,0)) | AL50: =IF(COUNT(C50:P50)=0,"",IFERROR(C50/N50,0)) | AM50: =IF(COUNT(C50:P50)=0,"",IFERROR(O50/N50,0)) | AN50: =IF(COUNT(C50:P50)=0,"",IFERROR(P50/N50,0)) | AO50: =IF(COUNT(C50:P50)=0,"",IFERROR(N50*Config!$C$7+O50*Config!$C$8+P50*Config!$C$9,0)) | AP50: =IF(COUNT(C50:P50)=0,"",IFERROR(AO50/N50,0)) | AQ50: =IF(COUNT(C50:P50)=0,"",IFERROR(AO50*(1-Config!$C$10-Config!$C$11-Config!$C$12),0)) | AR50: =IF(COUNT(C50:P50)=0,"",IFERROR(AQ50-C50-Config!$C$13,0)) | AS50: =IF(COUNT(C50:P50)=0,"",IFERROR(AQ50/C50,0)) | AT50: =IF(COUNT(C50:P50)=0,"",IFERROR(AR50/G50,0)) | AU50: =IF(COUNT(C50:P50)=0,"",IFERROR(AT50/V50,0)) | AV50: =IF(COUNT(C50:P50)=0,"",IFERROR(AR50/H50,0))
A51: =Config!$C$6+45 | B51: =INT((A51-Config!$C$6)/7)+1 | Q51: =IF(COUNT(C51:P51)=0,"",IFERROR(C51/D51*1000,0)) | R51: =IF(COUNT(C51:P51)=0,"",IFERROR(D51/E51,0)) | S51: =IF(COUNT(C51:P51)=0,"",IFERROR(F51/D51,0)) | T51: =IF(COUNT(C51:P51)=0,"",IFERROR(C51/F51,0)) | U51: =IF(COUNT(C51:P51)=0,"",IFERROR(G51/F51,0)) | V51: =IF(COUNT(C51:P51)=0,"",IFERROR(C51/G51,0)) | W51: =IF(COUNT(C51:P51)=0,"",IFERROR(G51/D51*1000,0)) | X51: =IF(COUNT(C51:P51)=0,"",IFERROR(H51/G51,0)) | Y51: =IF(COUNT(C51:P51)=0,"",IFERROR(C51/H51,0)) | Z51: =IF(COUNT(C51:P51)=0,"",IFERROR(C51/I51,0)) | AA51: =IF(COUNT(C51:P51)=0,"",IFERROR(Y51/Q51,0)) | AB51: =IF(COUNT(C51:P51)=0,"",IFERROR(H51/D51*1000,0)) | AC51: =IF(COUNT(C51:P51)=0,"",IFERROR(J51/H51,0)) | AD51: =IF(COUNT(C51:P51)=0,"",IFERROR(C51/J51,0)) | AE51: =IF(COUNT(C51:P51)=0,"",IFERROR(K51/H51,0)) | AF51: =IF(COUNT(C51:P51)=0,"",IFERROR(L51/H51,0)) | AG51: =IF(COUNT(C51:P51)=0,"",IFERROR(C51/K51,0)) | AH51: =IF(COUNT(C51:P51)=0,"",IFERROR(M51/K51,0)) | AI51: =IF(COUNT(C51:P51)=0,"",IFERROR(C51/M51,0)) | AJ51: =IF(COUNT(C51:P51)=0,"",IFERROR(N51/M51,0)) | AK51: =IF(COUNT(C51:P51)=0,"",IFERROR(N51/H51,0)) | AL51: =IF(COUNT(C51:P51)=0,"",IFERROR(C51/N51,0)) | AM51: =IF(COUNT(C51:P51)=0,"",IFERROR(O51/N51,0)) | AN51: =IF(COUNT(C51:P51)=0,"",IFERROR(P51/N51,0)) | AO51: =IF(COUNT(C51:P51)=0,"",IFERROR(N51*Config!$C$7+O51*Config!$C$8+P51*Config!$C$9,0)) | AP51: =IF(COUNT(C51:P51)=0,"",IFERROR(AO51/N51,0)) | AQ51: =IF(COUNT(C51:P51)=0,"",IFERROR(AO51*(1-Config!$C$10-Config!$C$11-Config!$C$12),0)) | AR51: =IF(COUNT(C51:P51)=0,"",IFERROR(AQ51-C51-Config!$C$13,0)) | AS51: =IF(COUNT(C51:P51)=0,"",IFERROR(AQ51/C51,0)) | AT51: =IF(COUNT(C51:P51)=0,"",IFERROR(AR51/G51,0)) | AU51: =IF(COUNT(C51:P51)=0,"",IFERROR(AT51/V51,0)) | AV51: =IF(COUNT(C51:P51)=0,"",IFERROR(AR51/H51,0))
A52: =Config!$C$6+46 | B52: =INT((A52-Config!$C$6)/7)+1 | Q52: =IF(COUNT(C52:P52)=0,"",IFERROR(C52/D52*1000,0)) | R52: =IF(COUNT(C52:P52)=0,"",IFERROR(D52/E52,0)) | S52: =IF(COUNT(C52:P52)=0,"",IFERROR(F52/D52,0)) | T52: =IF(COUNT(C52:P52)=0,"",IFERROR(C52/F52,0)) | U52: =IF(COUNT(C52:P52)=0,"",IFERROR(G52/F52,0)) | V52: =IF(COUNT(C52:P52)=0,"",IFERROR(C52/G52,0)) | W52: =IF(COUNT(C52:P52)=0,"",IFERROR(G52/D52*1000,0)) | X52: =IF(COUNT(C52:P52)=0,"",IFERROR(H52/G52,0)) | Y52: =IF(COUNT(C52:P52)=0,"",IFERROR(C52/H52,0)) | Z52: =IF(COUNT(C52:P52)=0,"",IFERROR(C52/I52,0)) | AA52: =IF(COUNT(C52:P52)=0,"",IFERROR(Y52/Q52,0)) | AB52: =IF(COUNT(C52:P52)=0,"",IFERROR(H52/D52*1000,0)) | AC52: =IF(COUNT(C52:P52)=0,"",IFERROR(J52/H52,0)) | AD52: =IF(COUNT(C52:P52)=0,"",IFERROR(C52/J52,0)) | AE52: =IF(COUNT(C52:P52)=0,"",IFERROR(K52/H52,0)) | AF52: =IF(COUNT(C52:P52)=0,"",IFERROR(L52/H52,0)) | AG52: =IF(COUNT(C52:P52)=0,"",IFERROR(C52/K52,0)) | AH52: =IF(COUNT(C52:P52)=0,"",IFERROR(M52/K52,0)) | AI52: =IF(COUNT(C52:P52)=0,"",IFERROR(C52/M52,0)) | AJ52: =IF(COUNT(C52:P52)=0,"",IFERROR(N52/M52,0)) | AK52: =IF(COUNT(C52:P52)=0,"",IFERROR(N52/H52,0)) | AL52: =IF(COUNT(C52:P52)=0,"",IFERROR(C52/N52,0)) | AM52: =IF(COUNT(C52:P52)=0,"",IFERROR(O52/N52,0)) | AN52: =IF(COUNT(C52:P52)=0,"",IFERROR(P52/N52,0)) | AO52: =IF(COUNT(C52:P52)=0,"",IFERROR(N52*Config!$C$7+O52*Config!$C$8+P52*Config!$C$9,0)) | AP52: =IF(COUNT(C52:P52)=0,"",IFERROR(AO52/N52,0)) | AQ52: =IF(COUNT(C52:P52)=0,"",IFERROR(AO52*(1-Config!$C$10-Config!$C$11-Config!$C$12),0)) | AR52: =IF(COUNT(C52:P52)=0,"",IFERROR(AQ52-C52-Config!$C$13,0)) | AS52: =IF(COUNT(C52:P52)=0,"",IFERROR(AQ52/C52,0)) | AT52: =IF(COUNT(C52:P52)=0,"",IFERROR(AR52/G52,0)) | AU52: =IF(COUNT(C52:P52)=0,"",IFERROR(AT52/V52,0)) | AV52: =IF(COUNT(C52:P52)=0,"",IFERROR(AR52/H52,0))
A53: =Config!$C$6+47 | B53: =INT((A53-Config!$C$6)/7)+1 | Q53: =IF(COUNT(C53:P53)=0,"",IFERROR(C53/D53*1000,0)) | R53: =IF(COUNT(C53:P53)=0,"",IFERROR(D53/E53,0)) | S53: =IF(COUNT(C53:P53)=0,"",IFERROR(F53/D53,0)) | T53: =IF(COUNT(C53:P53)=0,"",IFERROR(C53/F53,0)) | U53: =IF(COUNT(C53:P53)=0,"",IFERROR(G53/F53,0)) | V53: =IF(COUNT(C53:P53)=0,"",IFERROR(C53/G53,0)) | W53: =IF(COUNT(C53:P53)=0,"",IFERROR(G53/D53*1000,0)) | X53: =IF(COUNT(C53:P53)=0,"",IFERROR(H53/G53,0)) | Y53: =IF(COUNT(C53:P53)=0,"",IFERROR(C53/H53,0)) | Z53: =IF(COUNT(C53:P53)=0,"",IFERROR(C53/I53,0)) | AA53: =IF(COUNT(C53:P53)=0,"",IFERROR(Y53/Q53,0)) | AB53: =IF(COUNT(C53:P53)=0,"",IFERROR(H53/D53*1000,0)) | AC53: =IF(COUNT(C53:P53)=0,"",IFERROR(J53/H53,0)) | AD53: =IF(COUNT(C53:P53)=0,"",IFERROR(C53/J53,0)) | AE53: =IF(COUNT(C53:P53)=0,"",IFERROR(K53/H53,0)) | AF53: =IF(COUNT(C53:P53)=0,"",IFERROR(L53/H53,0)) | AG53: =IF(COUNT(C53:P53)=0,"",IFERROR(C53/K53,0)) | AH53: =IF(COUNT(C53:P53)=0,"",IFERROR(M53/K53,0)) | AI53: =IF(COUNT(C53:P53)=0,"",IFERROR(C53/M53,0)) | AJ53: =IF(COUNT(C53:P53)=0,"",IFERROR(N53/M53,0)) | AK53: =IF(COUNT(C53:P53)=0,"",IFERROR(N53/H53,0)) | AL53: =IF(COUNT(C53:P53)=0,"",IFERROR(C53/N53,0)) | AM53: =IF(COUNT(C53:P53)=0,"",IFERROR(O53/N53,0)) | AN53: =IF(COUNT(C53:P53)=0,"",IFERROR(P53/N53,0)) | AO53: =IF(COUNT(C53:P53)=0,"",IFERROR(N53*Config!$C$7+O53*Config!$C$8+P53*Config!$C$9,0)) | AP53: =IF(COUNT(C53:P53)=0,"",IFERROR(AO53/N53,0)) | AQ53: =IF(COUNT(C53:P53)=0,"",IFERROR(AO53*(1-Config!$C$10-Config!$C$11-Config!$C$12),0)) | AR53: =IF(COUNT(C53:P53)=0,"",IFERROR(AQ53-C53-Config!$C$13,0)) | AS53: =IF(COUNT(C53:P53)=0,"",IFERROR(AQ53/C53,0)) | AT53: =IF(COUNT(C53:P53)=0,"",IFERROR(AR53/G53,0)) | AU53: =IF(COUNT(C53:P53)=0,"",IFERROR(AT53/V53,0)) | AV53: =IF(COUNT(C53:P53)=0,"",IFERROR(AR53/H53,0))
A54: =Config!$C$6+48 | B54: =INT((A54-Config!$C$6)/7)+1 | Q54: =IF(COUNT(C54:P54)=0,"",IFERROR(C54/D54*1000,0)) | R54: =IF(COUNT(C54:P54)=0,"",IFERROR(D54/E54,0)) | S54: =IF(COUNT(C54:P54)=0,"",IFERROR(F54/D54,0)) | T54: =IF(COUNT(C54:P54)=0,"",IFERROR(C54/F54,0)) | U54: =IF(COUNT(C54:P54)=0,"",IFERROR(G54/F54,0)) | V54: =IF(COUNT(C54:P54)=0,"",IFERROR(C54/G54,0)) | W54: =IF(COUNT(C54:P54)=0,"",IFERROR(G54/D54*1000,0)) | X54: =IF(COUNT(C54:P54)=0,"",IFERROR(H54/G54,0)) | Y54: =IF(COUNT(C54:P54)=0,"",IFERROR(C54/H54,0)) | Z54: =IF(COUNT(C54:P54)=0,"",IFERROR(C54/I54,0)) | AA54: =IF(COUNT(C54:P54)=0,"",IFERROR(Y54/Q54,0)) | AB54: =IF(COUNT(C54:P54)=0,"",IFERROR(H54/D54*1000,0)) | AC54: =IF(COUNT(C54:P54)=0,"",IFERROR(J54/H54,0)) | AD54: =IF(COUNT(C54:P54)=0,"",IFERROR(C54/J54,0)) | AE54: =IF(COUNT(C54:P54)=0,"",IFERROR(K54/H54,0)) | AF54: =IF(COUNT(C54:P54)=0,"",IFERROR(L54/H54,0)) | AG54: =IF(COUNT(C54:P54)=0,"",IFERROR(C54/K54,0)) | AH54: =IF(COUNT(C54:P54)=0,"",IFERROR(M54/K54,0)) | AI54: =IF(COUNT(C54:P54)=0,"",IFERROR(C54/M54,0)) | AJ54: =IF(COUNT(C54:P54)=0,"",IFERROR(N54/M54,0)) | AK54: =IF(COUNT(C54:P54)=0,"",IFERROR(N54/H54,0)) | AL54: =IF(COUNT(C54:P54)=0,"",IFERROR(C54/N54,0)) | AM54: =IF(COUNT(C54:P54)=0,"",IFERROR(O54/N54,0)) | AN54: =IF(COUNT(C54:P54)=0,"",IFERROR(P54/N54,0)) | AO54: =IF(COUNT(C54:P54)=0,"",IFERROR(N54*Config!$C$7+O54*Config!$C$8+P54*Config!$C$9,0)) | AP54: =IF(COUNT(C54:P54)=0,"",IFERROR(AO54/N54,0)) | AQ54: =IF(COUNT(C54:P54)=0,"",IFERROR(AO54*(1-Config!$C$10-Config!$C$11-Config!$C$12),0)) | AR54: =IF(COUNT(C54:P54)=0,"",IFERROR(AQ54-C54-Config!$C$13,0)) | AS54: =IF(COUNT(C54:P54)=0,"",IFERROR(AQ54/C54,0)) | AT54: =IF(COUNT(C54:P54)=0,"",IFERROR(AR54/G54,0)) | AU54: =IF(COUNT(C54:P54)=0,"",IFERROR(AT54/V54,0)) | AV54: =IF(COUNT(C54:P54)=0,"",IFERROR(AR54/H54,0))
A55: =Config!$C$6+49 | B55: =INT((A55-Config!$C$6)/7)+1 | Q55: =IF(COUNT(C55:P55)=0,"",IFERROR(C55/D55*1000,0)) | R55: =IF(COUNT(C55:P55)=0,"",IFERROR(D55/E55,0)) | S55: =IF(COUNT(C55:P55)=0,"",IFERROR(F55/D55,0)) | T55: =IF(COUNT(C55:P55)=0,"",IFERROR(C55/F55,0)) | U55: =IF(COUNT(C55:P55)=0,"",IFERROR(G55/F55,0)) | V55: =IF(COUNT(C55:P55)=0,"",IFERROR(C55/G55,0)) | W55: =IF(COUNT(C55:P55)=0,"",IFERROR(G55/D55*1000,0)) | X55: =IF(COUNT(C55:P55)=0,"",IFERROR(H55/G55,0)) | Y55: =IF(COUNT(C55:P55)=0,"",IFERROR(C55/H55,0)) | Z55: =IF(COUNT(C55:P55)=0,"",IFERROR(C55/I55,0)) | AA55: =IF(COUNT(C55:P55)=0,"",IFERROR(Y55/Q55,0)) | AB55: =IF(COUNT(C55:P55)=0,"",IFERROR(H55/D55*1000,0)) | AC55: =IF(COUNT(C55:P55)=0,"",IFERROR(J55/H55,0)) | AD55: =IF(COUNT(C55:P55)=0,"",IFERROR(C55/J55,0)) | AE55: =IF(COUNT(C55:P55)=0,"",IFERROR(K55/H55,0)) | AF55: =IF(COUNT(C55:P55)=0,"",IFERROR(L55/H55,0)) | AG55: =IF(COUNT(C55:P55)=0,"",IFERROR(C55/K55,0)) | AH55: =IF(COUNT(C55:P55)=0,"",IFERROR(M55/K55,0)) | AI55: =IF(COUNT(C55:P55)=0,"",IFERROR(C55/M55,0)) | AJ55: =IF(COUNT(C55:P55)=0,"",IFERROR(N55/M55,0)) | AK55: =IF(COUNT(C55:P55)=0,"",IFERROR(N55/H55,0)) | AL55: =IF(COUNT(C55:P55)=0,"",IFERROR(C55/N55,0)) | AM55: =IF(COUNT(C55:P55)=0,"",IFERROR(O55/N55,0)) | AN55: =IF(COUNT(C55:P55)=0,"",IFERROR(P55/N55,0)) | AO55: =IF(COUNT(C55:P55)=0,"",IFERROR(N55*Config!$C$7+O55*Config!$C$8+P55*Config!$C$9,0)) | AP55: =IF(COUNT(C55:P55)=0,"",IFERROR(AO55/N55,0)) | AQ55: =IF(COUNT(C55:P55)=0,"",IFERROR(AO55*(1-Config!$C$10-Config!$C$11-Config!$C$12),0)) | AR55: =IF(COUNT(C55:P55)=0,"",IFERROR(AQ55-C55-Config!$C$13,0)) | AS55: =IF(COUNT(C55:P55)=0,"",IFERROR(AQ55/C55,0)) | AT55: =IF(COUNT(C55:P55)=0,"",IFERROR(AR55/G55,0)) | AU55: =IF(COUNT(C55:P55)=0,"",IFERROR(AT55/V55,0)) | AV55: =IF(COUNT(C55:P55)=0,"",IFERROR(AR55/H55,0))
A56: =Config!$C$6+50 | B56: =INT((A56-Config!$C$6)/7)+1 | Q56: =IF(COUNT(C56:P56)=0,"",IFERROR(C56/D56*1000,0)) | R56: =IF(COUNT(C56:P56)=0,"",IFERROR(D56/E56,0)) | S56: =IF(COUNT(C56:P56)=0,"",IFERROR(F56/D56,0)) | T56: =IF(COUNT(C56:P56)=0,"",IFERROR(C56/F56,0)) | U56: =IF(COUNT(C56:P56)=0,"",IFERROR(G56/F56,0)) | V56: =IF(COUNT(C56:P56)=0,"",IFERROR(C56/G56,0)) | W56: =IF(COUNT(C56:P56)=0,"",IFERROR(G56/D56*1000,0)) | X56: =IF(COUNT(C56:P56)=0,"",IFERROR(H56/G56,0)) | Y56: =IF(COUNT(C56:P56)=0,"",IFERROR(C56/H56,0)) | Z56: =IF(COUNT(C56:P56)=0,"",IFERROR(C56/I56,0)) | AA56: =IF(COUNT(C56:P56)=0,"",IFERROR(Y56/Q56,0)) | AB56: =IF(COUNT(C56:P56)=0,"",IFERROR(H56/D56*1000,0)) | AC56: =IF(COUNT(C56:P56)=0,"",IFERROR(J56/H56,0)) | AD56: =IF(COUNT(C56:P56)=0,"",IFERROR(C56/J56,0)) | AE56: =IF(COUNT(C56:P56)=0,"",IFERROR(K56/H56,0)) | AF56: =IF(COUNT(C56:P56)=0,"",IFERROR(L56/H56,0)) | AG56: =IF(COUNT(C56:P56)=0,"",IFERROR(C56/K56,0)) | AH56: =IF(COUNT(C56:P56)=0,"",IFERROR(M56/K56,0)) | AI56: =IF(COUNT(C56:P56)=0,"",IFERROR(C56/M56,0)) | AJ56: =IF(COUNT(C56:P56)=0,"",IFERROR(N56/M56,0)) | AK56: =IF(COUNT(C56:P56)=0,"",IFERROR(N56/H56,0)) | AL56: =IF(COUNT(C56:P56)=0,"",IFERROR(C56/N56,0)) | AM56: =IF(COUNT(C56:P56)=0,"",IFERROR(O56/N56,0)) | AN56: =IF(COUNT(C56:P56)=0,"",IFERROR(P56/N56,0)) | AO56: =IF(COUNT(C56:P56)=0,"",IFERROR(N56*Config!$C$7+O56*Config!$C$8+P56*Config!$C$9,0)) | AP56: =IF(COUNT(C56:P56)=0,"",IFERROR(AO56/N56,0)) | AQ56: =IF(COUNT(C56:P56)=0,"",IFERROR(AO56*(1-Config!$C$10-Config!$C$11-Config!$C$12),0)) | AR56: =IF(COUNT(C56:P56)=0,"",IFERROR(AQ56-C56-Config!$C$13,0)) | AS56: =IF(COUNT(C56:P56)=0,"",IFERROR(AQ56/C56,0)) | AT56: =IF(COUNT(C56:P56)=0,"",IFERROR(AR56/G56,0)) | AU56: =IF(COUNT(C56:P56)=0,"",IFERROR(AT56/V56,0)) | AV56: =IF(COUNT(C56:P56)=0,"",IFERROR(AR56/H56,0))
A57: =Config!$C$6+51 | B57: =INT((A57-Config!$C$6)/7)+1 | Q57: =IF(COUNT(C57:P57)=0,"",IFERROR(C57/D57*1000,0)) | R57: =IF(COUNT(C57:P57)=0,"",IFERROR(D57/E57,0)) | S57: =IF(COUNT(C57:P57)=0,"",IFERROR(F57/D57,0)) | T57: =IF(COUNT(C57:P57)=0,"",IFERROR(C57/F57,0)) | U57: =IF(COUNT(C57:P57)=0,"",IFERROR(G57/F57,0)) | V57: =IF(COUNT(C57:P57)=0,"",IFERROR(C57/G57,0)) | W57: =IF(COUNT(C57:P57)=0,"",IFERROR(G57/D57*1000,0)) | X57: =IF(COUNT(C57:P57)=0,"",IFERROR(H57/G57,0)) | Y57: =IF(COUNT(C57:P57)=0,"",IFERROR(C57/H57,0)) | Z57: =IF(COUNT(C57:P57)=0,"",IFERROR(C57/I57,0)) | AA57: =IF(COUNT(C57:P57)=0,"",IFERROR(Y57/Q57,0)) | AB57: =IF(COUNT(C57:P57)=0,"",IFERROR(H57/D57*1000,0)) | AC57: =IF(COUNT(C57:P57)=0,"",IFERROR(J57/H57,0)) | AD57: =IF(COUNT(C57:P57)=0,"",IFERROR(C57/J57,0)) | AE57: =IF(COUNT(C57:P57)=0,"",IFERROR(K57/H57,0)) | AF57: =IF(COUNT(C57:P57)=0,"",IFERROR(L57/H57,0)) | AG57: =IF(COUNT(C57:P57)=0,"",IFERROR(C57/K57,0)) | AH57: =IF(COUNT(C57:P57)=0,"",IFERROR(M57/K57,0)) | AI57: =IF(COUNT(C57:P57)=0,"",IFERROR(C57/M57,0)) | AJ57: =IF(COUNT(C57:P57)=0,"",IFERROR(N57/M57,0)) | AK57: =IF(COUNT(C57:P57)=0,"",IFERROR(N57/H57,0)) | AL57: =IF(COUNT(C57:P57)=0,"",IFERROR(C57/N57,0)) | AM57: =IF(COUNT(C57:P57)=0,"",IFERROR(O57/N57,0)) | AN57: =IF(COUNT(C57:P57)=0,"",IFERROR(P57/N57,0)) | AO57: =IF(COUNT(C57:P57)=0,"",IFERROR(N57*Config!$C$7+O57*Config!$C$8+P57*Config!$C$9,0)) | AP57: =IF(COUNT(C57:P57)=0,"",IFERROR(AO57/N57,0)) | AQ57: =IF(COUNT(C57:P57)=0,"",IFERROR(AO57*(1-Config!$C$10-Config!$C$11-Config!$C$12),0)) | AR57: =IF(COUNT(C57:P57)=0,"",IFERROR(AQ57-C57-Config!$C$13,0)) | AS57: =IF(COUNT(C57:P57)=0,"",IFERROR(AQ57/C57,0)) | AT57: =IF(COUNT(C57:P57)=0,"",IFERROR(AR57/G57,0)) | AU57: =IF(COUNT(C57:P57)=0,"",IFERROR(AT57/V57,0)) | AV57: =IF(COUNT(C57:P57)=0,"",IFERROR(AR57/H57,0))
A58: =Config!$C$6+52 | B58: =INT((A58-Config!$C$6)/7)+1 | Q58: =IF(COUNT(C58:P58)=0,"",IFERROR(C58/D58*1000,0)) | R58: =IF(COUNT(C58:P58)=0,"",IFERROR(D58/E58,0)) | S58: =IF(COUNT(C58:P58)=0,"",IFERROR(F58/D58,0)) | T58: =IF(COUNT(C58:P58)=0,"",IFERROR(C58/F58,0)) | U58: =IF(COUNT(C58:P58)=0,"",IFERROR(G58/F58,0)) | V58: =IF(COUNT(C58:P58)=0,"",IFERROR(C58/G58,0)) | W58: =IF(COUNT(C58:P58)=0,"",IFERROR(G58/D58*1000,0)) | X58: =IF(COUNT(C58:P58)=0,"",IFERROR(H58/G58,0)) | Y58: =IF(COUNT(C58:P58)=0,"",IFERROR(C58/H58,0)) | Z58: =IF(COUNT(C58:P58)=0,"",IFERROR(C58/I58,0)) | AA58: =IF(COUNT(C58:P58)=0,"",IFERROR(Y58/Q58,0)) | AB58: =IF(COUNT(C58:P58)=0,"",IFERROR(H58/D58*1000,0)) | AC58: =IF(COUNT(C58:P58)=0,"",IFERROR(J58/H58,0)) | AD58: =IF(COUNT(C58:P58)=0,"",IFERROR(C58/J58,0)) | AE58: =IF(COUNT(C58:P58)=0,"",IFERROR(K58/H58,0)) | AF58: =IF(COUNT(C58:P58)=0,"",IFERROR(L58/H58,0)) | AG58: =IF(COUNT(C58:P58)=0,"",IFERROR(C58/K58,0)) | AH58: =IF(COUNT(C58:P58)=0,"",IFERROR(M58/K58,0)) | AI58: =IF(COUNT(C58:P58)=0,"",IFERROR(C58/M58,0)) | AJ58: =IF(COUNT(C58:P58)=0,"",IFERROR(N58/M58,0)) | AK58: =IF(COUNT(C58:P58)=0,"",IFERROR(N58/H58,0)) | AL58: =IF(COUNT(C58:P58)=0,"",IFERROR(C58/N58,0)) | AM58: =IF(COUNT(C58:P58)=0,"",IFERROR(O58/N58,0)) | AN58: =IF(COUNT(C58:P58)=0,"",IFERROR(P58/N58,0)) | AO58: =IF(COUNT(C58:P58)=0,"",IFERROR(N58*Config!$C$7+O58*Config!$C$8+P58*Config!$C$9,0)) | AP58: =IF(COUNT(C58:P58)=0,"",IFERROR(AO58/N58,0)) | AQ58: =IF(COUNT(C58:P58)=0,"",IFERROR(AO58*(1-Config!$C$10-Config!$C$11-Config!$C$12),0)) | AR58: =IF(COUNT(C58:P58)=0,"",IFERROR(AQ58-C58-Config!$C$13,0)) | AS58: =IF(COUNT(C58:P58)=0,"",IFERROR(AQ58/C58,0)) | AT58: =IF(COUNT(C58:P58)=0,"",IFERROR(AR58/G58,0)) | AU58: =IF(COUNT(C58:P58)=0,"",IFERROR(AT58/V58,0)) | AV58: =IF(COUNT(C58:P58)=0,"",IFERROR(AR58/H58,0))
A59: =Config!$C$6+53 | B59: =INT((A59-Config!$C$6)/7)+1 | Q59: =IF(COUNT(C59:P59)=0,"",IFERROR(C59/D59*1000,0)) | R59: =IF(COUNT(C59:P59)=0,"",IFERROR(D59/E59,0)) | S59: =IF(COUNT(C59:P59)=0,"",IFERROR(F59/D59,0)) | T59: =IF(COUNT(C59:P59)=0,"",IFERROR(C59/F59,0)) | U59: =IF(COUNT(C59:P59)=0,"",IFERROR(G59/F59,0)) | V59: =IF(COUNT(C59:P59)=0,"",IFERROR(C59/G59,0)) | W59: =IF(COUNT(C59:P59)=0,"",IFERROR(G59/D59*1000,0)) | X59: =IF(COUNT(C59:P59)=0,"",IFERROR(H59/G59,0)) | Y59: =IF(COUNT(C59:P59)=0,"",IFERROR(C59/H59,0)) | Z59: =IF(COUNT(C59:P59)=0,"",IFERROR(C59/I59,0)) | AA59: =IF(COUNT(C59:P59)=0,"",IFERROR(Y59/Q59,0)) | AB59: =IF(COUNT(C59:P59)=0,"",IFERROR(H59/D59*1000,0)) | AC59: =IF(COUNT(C59:P59)=0,"",IFERROR(J59/H59,0)) | AD59: =IF(COUNT(C59:P59)=0,"",IFERROR(C59/J59,0)) | AE59: =IF(COUNT(C59:P59)=0,"",IFERROR(K59/H59,0)) | AF59: =IF(COUNT(C59:P59)=0,"",IFERROR(L59/H59,0)) | AG59: =IF(COUNT(C59:P59)=0,"",IFERROR(C59/K59,0)) | AH59: =IF(COUNT(C59:P59)=0,"",IFERROR(M59/K59,0)) | AI59: =IF(COUNT(C59:P59)=0,"",IFERROR(C59/M59,0)) | AJ59: =IF(COUNT(C59:P59)=0,"",IFERROR(N59/M59,0)) | AK59: =IF(COUNT(C59:P59)=0,"",IFERROR(N59/H59,0)) | AL59: =IF(COUNT(C59:P59)=0,"",IFERROR(C59/N59,0)) | AM59: =IF(COUNT(C59:P59)=0,"",IFERROR(O59/N59,0)) | AN59: =IF(COUNT(C59:P59)=0,"",IFERROR(P59/N59,0)) | AO59: =IF(COUNT(C59:P59)=0,"",IFERROR(N59*Config!$C$7+O59*Config!$C$8+P59*Config!$C$9,0)) | AP59: =IF(COUNT(C59:P59)=0,"",IFERROR(AO59/N59,0)) | AQ59: =IF(COUNT(C59:P59)=0,"",IFERROR(AO59*(1-Config!$C$10-Config!$C$11-Config!$C$12),0)) | AR59: =IF(COUNT(C59:P59)=0,"",IFERROR(AQ59-C59-Config!$C$13,0)) | AS59: =IF(COUNT(C59:P59)=0,"",IFERROR(AQ59/C59,0)) | AT59: =IF(COUNT(C59:P59)=0,"",IFERROR(AR59/G59,0)) | AU59: =IF(COUNT(C59:P59)=0,"",IFERROR(AT59/V59,0)) | AV59: =IF(COUNT(C59:P59)=0,"",IFERROR(AR59/H59,0))
A60: =Config!$C$6+54 | B60: =INT((A60-Config!$C$6)/7)+1 | Q60: =IF(COUNT(C60:P60)=0,"",IFERROR(C60/D60*1000,0)) | R60: =IF(COUNT(C60:P60)=0,"",IFERROR(D60/E60,0)) | S60: =IF(COUNT(C60:P60)=0,"",IFERROR(F60/D60,0)) | T60: =IF(COUNT(C60:P60)=0,"",IFERROR(C60/F60,0)) | U60: =IF(COUNT(C60:P60)=0,"",IFERROR(G60/F60,0)) | V60: =IF(COUNT(C60:P60)=0,"",IFERROR(C60/G60,0)) | W60: =IF(COUNT(C60:P60)=0,"",IFERROR(G60/D60*1000,0)) | X60: =IF(COUNT(C60:P60)=0,"",IFERROR(H60/G60,0)) | Y60: =IF(COUNT(C60:P60)=0,"",IFERROR(C60/H60,0)) | Z60: =IF(COUNT(C60:P60)=0,"",IFERROR(C60/I60,0)) | AA60: =IF(COUNT(C60:P60)=0,"",IFERROR(Y60/Q60,0)) | AB60: =IF(COUNT(C60:P60)=0,"",IFERROR(H60/D60*1000,0)) | AC60: =IF(COUNT(C60:P60)=0,"",IFERROR(J60/H60,0)) | AD60: =IF(COUNT(C60:P60)=0,"",IFERROR(C60/J60,0)) | AE60: =IF(COUNT(C60:P60)=0,"",IFERROR(K60/H60,0)) | AF60: =IF(COUNT(C60:P60)=0,"",IFERROR(L60/H60,0)) | AG60: =IF(COUNT(C60:P60)=0,"",IFERROR(C60/K60,0)) | AH60: =IF(COUNT(C60:P60)=0,"",IFERROR(M60/K60,0)) | AI60: =IF(COUNT(C60:P60)=0,"",IFERROR(C60/M60,0)) | AJ60: =IF(COUNT(C60:P60)=0,"",IFERROR(N60/M60,0)) | AK60: =IF(COUNT(C60:P60)=0,"",IFERROR(N60/H60,0)) | AL60: =IF(COUNT(C60:P60)=0,"",IFERROR(C60/N60,0)) | AM60: =IF(COUNT(C60:P60)=0,"",IFERROR(O60/N60,0)) | AN60: =IF(COUNT(C60:P60)=0,"",IFERROR(P60/N60,0)) | AO60: =IF(COUNT(C60:P60)=0,"",IFERROR(N60*Config!$C$7+O60*Config!$C$8+P60*Config!$C$9,0)) | AP60: =IF(COUNT(C60:P60)=0,"",IFERROR(AO60/N60,0)) | AQ60: =IF(COUNT(C60:P60)=0,"",IFERROR(AO60*(1-Config!$C$10-Config!$C$11-Config!$C$12),0)) | AR60: =IF(COUNT(C60:P60)=0,"",IFERROR(AQ60-C60-Config!$C$13,0)) | AS60: =IF(COUNT(C60:P60)=0,"",IFERROR(AQ60/C60,0)) | AT60: =IF(COUNT(C60:P60)=0,"",IFERROR(AR60/G60,0)) | AU60: =IF(COUNT(C60:P60)=0,"",IFERROR(AT60/V60,0)) | AV60: =IF(COUNT(C60:P60)=0,"",IFERROR(AR60/H60,0))
A61: =Config!$C$6+55 | B61: =INT((A61-Config!$C$6)/7)+1 | Q61: =IF(COUNT(C61:P61)=0,"",IFERROR(C61/D61*1000,0)) | R61: =IF(COUNT(C61:P61)=0,"",IFERROR(D61/E61,0)) | S61: =IF(COUNT(C61:P61)=0,"",IFERROR(F61/D61,0)) | T61: =IF(COUNT(C61:P61)=0,"",IFERROR(C61/F61,0)) | U61: =IF(COUNT(C61:P61)=0,"",IFERROR(G61/F61,0)) | V61: =IF(COUNT(C61:P61)=0,"",IFERROR(C61/G61,0)) | W61: =IF(COUNT(C61:P61)=0,"",IFERROR(G61/D61*1000,0)) | X61: =IF(COUNT(C61:P61)=0,"",IFERROR(H61/G61,0)) | Y61: =IF(COUNT(C61:P61)=0,"",IFERROR(C61/H61,0)) | Z61: =IF(COUNT(C61:P61)=0,"",IFERROR(C61/I61,0)) | AA61: =IF(COUNT(C61:P61)=0,"",IFERROR(Y61/Q61,0)) | AB61: =IF(COUNT(C61:P61)=0,"",IFERROR(H61/D61*1000,0)) | AC61: =IF(COUNT(C61:P61)=0,"",IFERROR(J61/H61,0)) | AD61: =IF(COUNT(C61:P61)=0,"",IFERROR(C61/J61,0)) | AE61: =IF(COUNT(C61:P61)=0,"",IFERROR(K61/H61,0)) | AF61: =IF(COUNT(C61:P61)=0,"",IFERROR(L61/H61,0)) | AG61: =IF(COUNT(C61:P61)=0,"",IFERROR(C61/K61,0)) | AH61: =IF(COUNT(C61:P61)=0,"",IFERROR(M61/K61,0)) | AI61: =IF(COUNT(C61:P61)=0,"",IFERROR(C61/M61,0)) | AJ61: =IF(COUNT(C61:P61)=0,"",IFERROR(N61/M61,0)) | AK61: =IF(COUNT(C61:P61)=0,"",IFERROR(N61/H61,0)) | AL61: =IF(COUNT(C61:P61)=0,"",IFERROR(C61/N61,0)) | AM61: =IF(COUNT(C61:P61)=0,"",IFERROR(O61/N61,0)) | AN61: =IF(COUNT(C61:P61)=0,"",IFERROR(P61/N61,0)) | AO61: =IF(COUNT(C61:P61)=0,"",IFERROR(N61*Config!$C$7+O61*Config!$C$8+P61*Config!$C$9,0)) | AP61: =IF(COUNT(C61:P61)=0,"",IFERROR(AO61/N61,0)) | AQ61: =IF(COUNT(C61:P61)=0,"",IFERROR(AO61*(1-Config!$C$10-Config!$C$11-Config!$C$12),0)) | AR61: =IF(COUNT(C61:P61)=0,"",IFERROR(AQ61-C61-Config!$C$13,0)) | AS61: =IF(COUNT(C61:P61)=0,"",IFERROR(AQ61/C61,0)) | AT61: =IF(COUNT(C61:P61)=0,"",IFERROR(AR61/G61,0)) | AU61: =IF(COUNT(C61:P61)=0,"",IFERROR(AT61/V61,0)) | AV61: =IF(COUNT(C61:P61)=0,"",IFERROR(AR61/H61,0))
A62: =Config!$C$6+56 | B62: =INT((A62-Config!$C$6)/7)+1 | Q62: =IF(COUNT(C62:P62)=0,"",IFERROR(C62/D62*1000,0)) | R62: =IF(COUNT(C62:P62)=0,"",IFERROR(D62/E62,0)) | S62: =IF(COUNT(C62:P62)=0,"",IFERROR(F62/D62,0)) | T62: =IF(COUNT(C62:P62)=0,"",IFERROR(C62/F62,0)) | U62: =IF(COUNT(C62:P62)=0,"",IFERROR(G62/F62,0)) | V62: =IF(COUNT(C62:P62)=0,"",IFERROR(C62/G62,0)) | W62: =IF(COUNT(C62:P62)=0,"",IFERROR(G62/D62*1000,0)) | X62: =IF(COUNT(C62:P62)=0,"",IFERROR(H62/G62,0)) | Y62: =IF(COUNT(C62:P62)=0,"",IFERROR(C62/H62,0)) | Z62: =IF(COUNT(C62:P62)=0,"",IFERROR(C62/I62,0)) | AA62: =IF(COUNT(C62:P62)=0,"",IFERROR(Y62/Q62,0)) | AB62: =IF(COUNT(C62:P62)=0,"",IFERROR(H62/D62*1000,0)) | AC62: =IF(COUNT(C62:P62)=0,"",IFERROR(J62/H62,0)) | AD62: =IF(COUNT(C62:P62)=0,"",IFERROR(C62/J62,0)) | AE62: =IF(COUNT(C62:P62)=0,"",IFERROR(K62/H62,0)) | AF62: =IF(COUNT(C62:P62)=0,"",IFERROR(L62/H62,0)) | AG62: =IF(COUNT(C62:P62)=0,"",IFERROR(C62/K62,0)) | AH62: =IF(COUNT(C62:P62)=0,"",IFERROR(M62/K62,0)) | AI62: =IF(COUNT(C62:P62)=0,"",IFERROR(C62/M62,0)) | AJ62: =IF(COUNT(C62:P62)=0,"",IFERROR(N62/M62,0)) | AK62: =IF(COUNT(C62:P62)=0,"",IFERROR(N62/H62,0)) | AL62: =IF(COUNT(C62:P62)=0,"",IFERROR(C62/N62,0)) | AM62: =IF(COUNT(C62:P62)=0,"",IFERROR(O62/N62,0)) | AN62: =IF(COUNT(C62:P62)=0,"",IFERROR(P62/N62,0)) | AO62: =IF(COUNT(C62:P62)=0,"",IFERROR(N62*Config!$C$7+O62*Config!$C$8+P62*Config!$C$9,0)) | AP62: =IF(COUNT(C62:P62)=0,"",IFERROR(AO62/N62,0)) | AQ62: =IF(COUNT(C62:P62)=0,"",IFERROR(AO62*(1-Config!$C$10-Config!$C$11-Config!$C$12),0)) | AR62: =IF(COUNT(C62:P62)=0,"",IFERROR(AQ62-C62-Config!$C$13,0)) | AS62: =IF(COUNT(C62:P62)=0,"",IFERROR(AQ62/C62,0)) | AT62: =IF(COUNT(C62:P62)=0,"",IFERROR(AR62/G62,0)) | AU62: =IF(COUNT(C62:P62)=0,"",IFERROR(AT62/V62,0)) | AV62: =IF(COUNT(C62:P62)=0,"",IFERROR(AR62/H62,0))
A63: =Config!$C$6+57 | B63: =INT((A63-Config!$C$6)/7)+1 | Q63: =IF(COUNT(C63:P63)=0,"",IFERROR(C63/D63*1000,0)) | R63: =IF(COUNT(C63:P63)=0,"",IFERROR(D63/E63,0)) | S63: =IF(COUNT(C63:P63)=0,"",IFERROR(F63/D63,0)) | T63: =IF(COUNT(C63:P63)=0,"",IFERROR(C63/F63,0)) | U63: =IF(COUNT(C63:P63)=0,"",IFERROR(G63/F63,0)) | V63: =IF(COUNT(C63:P63)=0,"",IFERROR(C63/G63,0)) | W63: =IF(COUNT(C63:P63)=0,"",IFERROR(G63/D63*1000,0)) | X63: =IF(COUNT(C63:P63)=0,"",IFERROR(H63/G63,0)) | Y63: =IF(COUNT(C63:P63)=0,"",IFERROR(C63/H63,0)) | Z63: =IF(COUNT(C63:P63)=0,"",IFERROR(C63/I63,0)) | AA63: =IF(COUNT(C63:P63)=0,"",IFERROR(Y63/Q63,0)) | AB63: =IF(COUNT(C63:P63)=0,"",IFERROR(H63/D63*1000,0)) | AC63: =IF(COUNT(C63:P63)=0,"",IFERROR(J63/H63,0)) | AD63: =IF(COUNT(C63:P63)=0,"",IFERROR(C63/J63,0)) | AE63: =IF(COUNT(C63:P63)=0,"",IFERROR(K63/H63,0)) | AF63: =IF(COUNT(C63:P63)=0,"",IFERROR(L63/H63,0)) | AG63: =IF(COUNT(C63:P63)=0,"",IFERROR(C63/K63,0)) | AH63: =IF(COUNT(C63:P63)=0,"",IFERROR(M63/K63,0)) | AI63: =IF(COUNT(C63:P63)=0,"",IFERROR(C63/M63,0)) | AJ63: =IF(COUNT(C63:P63)=0,"",IFERROR(N63/M63,0)) | AK63: =IF(COUNT(C63:P63)=0,"",IFERROR(N63/H63,0)) | AL63: =IF(COUNT(C63:P63)=0,"",IFERROR(C63/N63,0)) | AM63: =IF(COUNT(C63:P63)=0,"",IFERROR(O63/N63,0)) | AN63: =IF(COUNT(C63:P63)=0,"",IFERROR(P63/N63,0)) | AO63: =IF(COUNT(C63:P63)=0,"",IFERROR(N63*Config!$C$7+O63*Config!$C$8+P63*Config!$C$9,0)) | AP63: =IF(COUNT(C63:P63)=0,"",IFERROR(AO63/N63,0)) | AQ63: =IF(COUNT(C63:P63)=0,"",IFERROR(AO63*(1-Config!$C$10-Config!$C$11-Config!$C$12),0)) | AR63: =IF(COUNT(C63:P63)=0,"",IFERROR(AQ63-C63-Config!$C$13,0)) | AS63: =IF(COUNT(C63:P63)=0,"",IFERROR(AQ63/C63,0)) | AT63: =IF(COUNT(C63:P63)=0,"",IFERROR(AR63/G63,0)) | AU63: =IF(COUNT(C63:P63)=0,"",IFERROR(AT63/V63,0)) | AV63: =IF(COUNT(C63:P63)=0,"",IFERROR(AR63/H63,0))
A64: =Config!$C$6+58 | B64: =INT((A64-Config!$C$6)/7)+1 | Q64: =IF(COUNT(C64:P64)=0,"",IFERROR(C64/D64*1000,0)) | R64: =IF(COUNT(C64:P64)=0,"",IFERROR(D64/E64,0)) | S64: =IF(COUNT(C64:P64)=0,"",IFERROR(F64/D64,0)) | T64: =IF(COUNT(C64:P64)=0,"",IFERROR(C64/F64,0)) | U64: =IF(COUNT(C64:P64)=0,"",IFERROR(G64/F64,0)) | V64: =IF(COUNT(C64:P64)=0,"",IFERROR(C64/G64,0)) | W64: =IF(COUNT(C64:P64)=0,"",IFERROR(G64/D64*1000,0)) | X64: =IF(COUNT(C64:P64)=0,"",IFERROR(H64/G64,0)) | Y64: =IF(COUNT(C64:P64)=0,"",IFERROR(C64/H64,0)) | Z64: =IF(COUNT(C64:P64)=0,"",IFERROR(C64/I64,0)) | AA64: =IF(COUNT(C64:P64)=0,"",IFERROR(Y64/Q64,0)) | AB64: =IF(COUNT(C64:P64)=0,"",IFERROR(H64/D64*1000,0)) | AC64: =IF(COUNT(C64:P64)=0,"",IFERROR(J64/H64,0)) | AD64: =IF(COUNT(C64:P64)=0,"",IFERROR(C64/J64,0)) | AE64: =IF(COUNT(C64:P64)=0,"",IFERROR(K64/H64,0)) | AF64: =IF(COUNT(C64:P64)=0,"",IFERROR(L64/H64,0)) | AG64: =IF(COUNT(C64:P64)=0,"",IFERROR(C64/K64,0)) | AH64: =IF(COUNT(C64:P64)=0,"",IFERROR(M64/K64,0)) | AI64: =IF(COUNT(C64:P64)=0,"",IFERROR(C64/M64,0)) | AJ64: =IF(COUNT(C64:P64)=0,"",IFERROR(N64/M64,0)) | AK64: =IF(COUNT(C64:P64)=0,"",IFERROR(N64/H64,0)) | AL64: =IF(COUNT(C64:P64)=0,"",IFERROR(C64/N64,0)) | AM64: =IF(COUNT(C64:P64)=0,"",IFERROR(O64/N64,0)) | AN64: =IF(COUNT(C64:P64)=0,"",IFERROR(P64/N64,0)) | AO64: =IF(COUNT(C64:P64)=0,"",IFERROR(N64*Config!$C$7+O64*Config!$C$8+P64*Config!$C$9,0)) | AP64: =IF(COUNT(C64:P64)=0,"",IFERROR(AO64/N64,0)) | AQ64: =IF(COUNT(C64:P64)=0,"",IFERROR(AO64*(1-Config!$C$10-Config!$C$11-Config!$C$12),0)) | AR64: =IF(COUNT(C64:P64)=0,"",IFERROR(AQ64-C64-Config!$C$13,0)) | AS64: =IF(COUNT(C64:P64)=0,"",IFERROR(AQ64/C64,0)) | AT64: =IF(COUNT(C64:P64)=0,"",IFERROR(AR64/G64,0)) | AU64: =IF(COUNT(C64:P64)=0,"",IFERROR(AT64/V64,0)) | AV64: =IF(COUNT(C64:P64)=0,"",IFERROR(AR64/H64,0))
A65: =Config!$C$6+59 | B65: =INT((A65-Config!$C$6)/7)+1 | Q65: =IF(COUNT(C65:P65)=0,"",IFERROR(C65/D65*1000,0)) | R65: =IF(COUNT(C65:P65)=0,"",IFERROR(D65/E65,0)) | S65: =IF(COUNT(C65:P65)=0,"",IFERROR(F65/D65,0)) | T65: =IF(COUNT(C65:P65)=0,"",IFERROR(C65/F65,0)) | U65: =IF(COUNT(C65:P65)=0,"",IFERROR(G65/F65,0)) | V65: =IF(COUNT(C65:P65)=0,"",IFERROR(C65/G65,0)) | W65: =IF(COUNT(C65:P65)=0,"",IFERROR(G65/D65*1000,0)) | X65: =IF(COUNT(C65:P65)=0,"",IFERROR(H65/G65,0)) | Y65: =IF(COUNT(C65:P65)=0,"",IFERROR(C65/H65,0)) | Z65: =IF(COUNT(C65:P65)=0,"",IFERROR(C65/I65,0)) | AA65: =IF(COUNT(C65:P65)=0,"",IFERROR(Y65/Q65,0)) | AB65: =IF(COUNT(C65:P65)=0,"",IFERROR(H65/D65*1000,0)) | AC65: =IF(COUNT(C65:P65)=0,"",IFERROR(J65/H65,0)) | AD65: =IF(COUNT(C65:P65)=0,"",IFERROR(C65/J65,0)) | AE65: =IF(COUNT(C65:P65)=0,"",IFERROR(K65/H65,0)) | AF65: =IF(COUNT(C65:P65)=0,"",IFERROR(L65/H65,0)) | AG65: =IF(COUNT(C65:P65)=0,"",IFERROR(C65/K65,0)) | AH65: =IF(COUNT(C65:P65)=0,"",IFERROR(M65/K65,0)) | AI65: =IF(COUNT(C65:P65)=0,"",IFERROR(C65/M65,0)) | AJ65: =IF(COUNT(C65:P65)=0,"",IFERROR(N65/M65,0)) | AK65: =IF(COUNT(C65:P65)=0,"",IFERROR(N65/H65,0)) | AL65: =IF(COUNT(C65:P65)=0,"",IFERROR(C65/N65,0)) | AM65: =IF(COUNT(C65:P65)=0,"",IFERROR(O65/N65,0)) | AN65: =IF(COUNT(C65:P65)=0,"",IFERROR(P65/N65,0)) | AO65: =IF(COUNT(C65:P65)=0,"",IFERROR(N65*Config!$C$7+O65*Config!$C$8+P65*Config!$C$9,0)) | AP65: =IF(COUNT(C65:P65)=0,"",IFERROR(AO65/N65,0)) | AQ65: =IF(COUNT(C65:P65)=0,"",IFERROR(AO65*(1-Config!$C$10-Config!$C$11-Config!$C$12),0)) | AR65: =IF(COUNT(C65:P65)=0,"",IFERROR(AQ65-C65-Config!$C$13,0)) | AS65: =IF(COUNT(C65:P65)=0,"",IFERROR(AQ65/C65,0)) | AT65: =IF(COUNT(C65:P65)=0,"",IFERROR(AR65/G65,0)) | AU65: =IF(COUNT(C65:P65)=0,"",IFERROR(AT65/V65,0)) | AV65: =IF(COUNT(C65:P65)=0,"",IFERROR(AR65/H65,0))
A66: =Config!$C$6+60 | B66: =INT((A66-Config!$C$6)/7)+1 | Q66: =IF(COUNT(C66:P66)=0,"",IFERROR(C66/D66*1000,0)) | R66: =IF(COUNT(C66:P66)=0,"",IFERROR(D66/E66,0)) | S66: =IF(COUNT(C66:P66)=0,"",IFERROR(F66/D66,0)) | T66: =IF(COUNT(C66:P66)=0,"",IFERROR(C66/F66,0)) | U66: =IF(COUNT(C66:P66)=0,"",IFERROR(G66/F66,0)) | V66: =IF(COUNT(C66:P66)=0,"",IFERROR(C66/G66,0)) | W66: =IF(COUNT(C66:P66)=0,"",IFERROR(G66/D66*1000,0)) | X66: =IF(COUNT(C66:P66)=0,"",IFERROR(H66/G66,0)) | Y66: =IF(COUNT(C66:P66)=0,"",IFERROR(C66/H66,0)) | Z66: =IF(COUNT(C66:P66)=0,"",IFERROR(C66/I66,0)) | AA66: =IF(COUNT(C66:P66)=0,"",IFERROR(Y66/Q66,0)) | AB66: =IF(COUNT(C66:P66)=0,"",IFERROR(H66/D66*1000,0)) | AC66: =IF(COUNT(C66:P66)=0,"",IFERROR(J66/H66,0)) | AD66: =IF(COUNT(C66:P66)=0,"",IFERROR(C66/J66,0)) | AE66: =IF(COUNT(C66:P66)=0,"",IFERROR(K66/H66,0)) | AF66: =IF(COUNT(C66:P66)=0,"",IFERROR(L66/H66,0)) | AG66: =IF(COUNT(C66:P66)=0,"",IFERROR(C66/K66,0)) | AH66: =IF(COUNT(C66:P66)=0,"",IFERROR(M66/K66,0)) | AI66: =IF(COUNT(C66:P66)=0,"",IFERROR(C66/M66,0)) | AJ66: =IF(COUNT(C66:P66)=0,"",IFERROR(N66/M66,0)) | AK66: =IF(COUNT(C66:P66)=0,"",IFERROR(N66/H66,0)) | AL66: =IF(COUNT(C66:P66)=0,"",IFERROR(C66/N66,0)) | AM66: =IF(COUNT(C66:P66)=0,"",IFERROR(O66/N66,0)) | AN66: =IF(COUNT(C66:P66)=0,"",IFERROR(P66/N66,0)) | AO66: =IF(COUNT(C66:P66)=0,"",IFERROR(N66*Config!$C$7+O66*Config!$C$8+P66*Config!$C$9,0)) | AP66: =IF(COUNT(C66:P66)=0,"",IFERROR(AO66/N66,0)) | AQ66: =IF(COUNT(C66:P66)=0,"",IFERROR(AO66*(1-Config!$C$10-Config!$C$11-Config!$C$12),0)) | AR66: =IF(COUNT(C66:P66)=0,"",IFERROR(AQ66-C66-Config!$C$13,0)) | AS66: =IF(COUNT(C66:P66)=0,"",IFERROR(AQ66/C66,0)) | AT66: =IF(COUNT(C66:P66)=0,"",IFERROR(AR66/G66,0)) | AU66: =IF(COUNT(C66:P66)=0,"",IFERROR(AT66/V66,0)) | AV66: =IF(COUNT(C66:P66)=0,"",IFERROR(AR66/H66,0))
A67: =Config!$C$6+61 | B67: =INT((A67-Config!$C$6)/7)+1 | Q67: =IF(COUNT(C67:P67)=0,"",IFERROR(C67/D67*1000,0)) | R67: =IF(COUNT(C67:P67)=0,"",IFERROR(D67/E67,0)) | S67: =IF(COUNT(C67:P67)=0,"",IFERROR(F67/D67,0)) | T67: =IF(COUNT(C67:P67)=0,"",IFERROR(C67/F67,0)) | U67: =IF(COUNT(C67:P67)=0,"",IFERROR(G67/F67,0)) | V67: =IF(COUNT(C67:P67)=0,"",IFERROR(C67/G67,0)) | W67: =IF(COUNT(C67:P67)=0,"",IFERROR(G67/D67*1000,0)) | X67: =IF(COUNT(C67:P67)=0,"",IFERROR(H67/G67,0)) | Y67: =IF(COUNT(C67:P67)=0,"",IFERROR(C67/H67,0)) | Z67: =IF(COUNT(C67:P67)=0,"",IFERROR(C67/I67,0)) | AA67: =IF(COUNT(C67:P67)=0,"",IFERROR(Y67/Q67,0)) | AB67: =IF(COUNT(C67:P67)=0,"",IFERROR(H67/D67*1000,0)) | AC67: =IF(COUNT(C67:P67)=0,"",IFERROR(J67/H67,0)) | AD67: =IF(COUNT(C67:P67)=0,"",IFERROR(C67/J67,0)) | AE67: =IF(COUNT(C67:P67)=0,"",IFERROR(K67/H67,0)) | AF67: =IF(COUNT(C67:P67)=0,"",IFERROR(L67/H67,0)) | AG67: =IF(COUNT(C67:P67)=0,"",IFERROR(C67/K67,0)) | AH67: =IF(COUNT(C67:P67)=0,"",IFERROR(M67/K67,0)) | AI67: =IF(COUNT(C67:P67)=0,"",IFERROR(C67/M67,0)) | AJ67: =IF(COUNT(C67:P67)=0,"",IFERROR(N67/M67,0)) | AK67: =IF(COUNT(C67:P67)=0,"",IFERROR(N67/H67,0)) | AL67: =IF(COUNT(C67:P67)=0,"",IFERROR(C67/N67,0)) | AM67: =IF(COUNT(C67:P67)=0,"",IFERROR(O67/N67,0)) | AN67: =IF(COUNT(C67:P67)=0,"",IFERROR(P67/N67,0)) | AO67: =IF(COUNT(C67:P67)=0,"",IFERROR(N67*Config!$C$7+O67*Config!$C$8+P67*Config!$C$9,0)) | AP67: =IF(COUNT(C67:P67)=0,"",IFERROR(AO67/N67,0)) | AQ67: =IF(COUNT(C67:P67)=0,"",IFERROR(AO67*(1-Config!$C$10-Config!$C$11-Config!$C$12),0)) | AR67: =IF(COUNT(C67:P67)=0,"",IFERROR(AQ67-C67-Config!$C$13,0)) | AS67: =IF(COUNT(C67:P67)=0,"",IFERROR(AQ67/C67,0)) | AT67: =IF(COUNT(C67:P67)=0,"",IFERROR(AR67/G67,0)) | AU67: =IF(COUNT(C67:P67)=0,"",IFERROR(AT67/V67,0)) | AV67: =IF(COUNT(C67:P67)=0,"",IFERROR(AR67/H67,0))
A68: =Config!$C$6+62 | B68: =INT((A68-Config!$C$6)/7)+1 | Q68: =IF(COUNT(C68:P68)=0,"",IFERROR(C68/D68*1000,0)) | R68: =IF(COUNT(C68:P68)=0,"",IFERROR(D68/E68,0)) | S68: =IF(COUNT(C68:P68)=0,"",IFERROR(F68/D68,0)) | T68: =IF(COUNT(C68:P68)=0,"",IFERROR(C68/F68,0)) | U68: =IF(COUNT(C68:P68)=0,"",IFERROR(G68/F68,0)) | V68: =IF(COUNT(C68:P68)=0,"",IFERROR(C68/G68,0)) | W68: =IF(COUNT(C68:P68)=0,"",IFERROR(G68/D68*1000,0)) | X68: =IF(COUNT(C68:P68)=0,"",IFERROR(H68/G68,0)) | Y68: =IF(COUNT(C68:P68)=0,"",IFERROR(C68/H68,0)) | Z68: =IF(COUNT(C68:P68)=0,"",IFERROR(C68/I68,0)) | AA68: =IF(COUNT(C68:P68)=0,"",IFERROR(Y68/Q68,0)) | AB68: =IF(COUNT(C68:P68)=0,"",IFERROR(H68/D68*1000,0)) | AC68: =IF(COUNT(C68:P68)=0,"",IFERROR(J68/H68,0)) | AD68: =IF(COUNT(C68:P68)=0,"",IFERROR(C68/J68,0)) | AE68: =IF(COUNT(C68:P68)=0,"",IFERROR(K68/H68,0)) | AF68: =IF(COUNT(C68:P68)=0,"",IFERROR(L68/H68,0)) | AG68: =IF(COUNT(C68:P68)=0,"",IFERROR(C68/K68,0)) | AH68: =IF(COUNT(C68:P68)=0,"",IFERROR(M68/K68,0)) | AI68: =IF(COUNT(C68:P68)=0,"",IFERROR(C68/M68,0)) | AJ68: =IF(COUNT(C68:P68)=0,"",IFERROR(N68/M68,0)) | AK68: =IF(COUNT(C68:P68)=0,"",IFERROR(N68/H68,0)) | AL68: =IF(COUNT(C68:P68)=0,"",IFERROR(C68/N68,0)) | AM68: =IF(COUNT(C68:P68)=0,"",IFERROR(O68/N68,0)) | AN68: =IF(COUNT(C68:P68)=0,"",IFERROR(P68/N68,0)) | AO68: =IF(COUNT(C68:P68)=0,"",IFERROR(N68*Config!$C$7+O68*Config!$C$8+P68*Config!$C$9,0)) | AP68: =IF(COUNT(C68:P68)=0,"",IFERROR(AO68/N68,0)) | AQ68: =IF(COUNT(C68:P68)=0,"",IFERROR(AO68*(1-Config!$C$10-Config!$C$11-Config!$C$12),0)) | AR68: =IF(COUNT(C68:P68)=0,"",IFERROR(AQ68-C68-Config!$C$13,0)) | AS68: =IF(COUNT(C68:P68)=0,"",IFERROR(AQ68/C68,0)) | AT68: =IF(COUNT(C68:P68)=0,"",IFERROR(AR68/G68,0)) | AU68: =IF(COUNT(C68:P68)=0,"",IFERROR(AT68/V68,0)) | AV68: =IF(COUNT(C68:P68)=0,"",IFERROR(AR68/H68,0))
A69: =Config!$C$6+63 | B69: =INT((A69-Config!$C$6)/7)+1 | Q69: =IF(COUNT(C69:P69)=0,"",IFERROR(C69/D69*1000,0)) | R69: =IF(COUNT(C69:P69)=0,"",IFERROR(D69/E69,0)) | S69: =IF(COUNT(C69:P69)=0,"",IFERROR(F69/D69,0)) | T69: =IF(COUNT(C69:P69)=0,"",IFERROR(C69/F69,0)) | U69: =IF(COUNT(C69:P69)=0,"",IFERROR(G69/F69,0)) | V69: =IF(COUNT(C69:P69)=0,"",IFERROR(C69/G69,0)) | W69: =IF(COUNT(C69:P69)=0,"",IFERROR(G69/D69*1000,0)) | X69: =IF(COUNT(C69:P69)=0,"",IFERROR(H69/G69,0)) | Y69: =IF(COUNT(C69:P69)=0,"",IFERROR(C69/H69,0)) | Z69: =IF(COUNT(C69:P69)=0,"",IFERROR(C69/I69,0)) | AA69: =IF(COUNT(C69:P69)=0,"",IFERROR(Y69/Q69,0)) | AB69: =IF(COUNT(C69:P69)=0,"",IFERROR(H69/D69*1000,0)) | AC69: =IF(COUNT(C69:P69)=0,"",IFERROR(J69/H69,0)) | AD69: =IF(COUNT(C69:P69)=0,"",IFERROR(C69/J69,0)) | AE69: =IF(COUNT(C69:P69)=0,"",IFERROR(K69/H69,0)) | AF69: =IF(COUNT(C69:P69)=0,"",IFERROR(L69/H69,0)) | AG69: =IF(COUNT(C69:P69)=0,"",IFERROR(C69/K69,0)) | AH69: =IF(COUNT(C69:P69)=0,"",IFERROR(M69/K69,0)) | AI69: =IF(COUNT(C69:P69)=0,"",IFERROR(C69/M69,0)) | AJ69: =IF(COUNT(C69:P69)=0,"",IFERROR(N69/M69,0)) | AK69: =IF(COUNT(C69:P69)=0,"",IFERROR(N69/H69,0)) | AL69: =IF(COUNT(C69:P69)=0,"",IFERROR(C69/N69,0)) | AM69: =IF(COUNT(C69:P69)=0,"",IFERROR(O69/N69,0)) | AN69: =IF(COUNT(C69:P69)=0,"",IFERROR(P69/N69,0)) | AO69: =IF(COUNT(C69:P69)=0,"",IFERROR(N69*Config!$C$7+O69*Config!$C$8+P69*Config!$C$9,0)) | AP69: =IF(COUNT(C69:P69)=0,"",IFERROR(AO69/N69,0)) | AQ69: =IF(COUNT(C69:P69)=0,"",IFERROR(AO69*(1-Config!$C$10-Config!$C$11-Config!$C$12),0)) | AR69: =IF(COUNT(C69:P69)=0,"",IFERROR(AQ69-C69-Config!$C$13,0)) | AS69: =IF(COUNT(C69:P69)=0,"",IFERROR(AQ69/C69,0)) | AT69: =IF(COUNT(C69:P69)=0,"",IFERROR(AR69/G69,0)) | AU69: =IF(COUNT(C69:P69)=0,"",IFERROR(AT69/V69,0)) | AV69: =IF(COUNT(C69:P69)=0,"",IFERROR(AR69/H69,0))
A70: =Config!$C$6+64 | B70: =INT((A70-Config!$C$6)/7)+1 | Q70: =IF(COUNT(C70:P70)=0,"",IFERROR(C70/D70*1000,0)) | R70: =IF(COUNT(C70:P70)=0,"",IFERROR(D70/E70,0)) | S70: =IF(COUNT(C70:P70)=0,"",IFERROR(F70/D70,0)) | T70: =IF(COUNT(C70:P70)=0,"",IFERROR(C70/F70,0)) | U70: =IF(COUNT(C70:P70)=0,"",IFERROR(G70/F70,0)) | V70: =IF(COUNT(C70:P70)=0,"",IFERROR(C70/G70,0)) | W70: =IF(COUNT(C70:P70)=0,"",IFERROR(G70/D70*1000,0)) | X70: =IF(COUNT(C70:P70)=0,"",IFERROR(H70/G70,0)) | Y70: =IF(COUNT(C70:P70)=0,"",IFERROR(C70/H70,0)) | Z70: =IF(COUNT(C70:P70)=0,"",IFERROR(C70/I70,0)) | AA70: =IF(COUNT(C70:P70)=0,"",IFERROR(Y70/Q70,0)) | AB70: =IF(COUNT(C70:P70)=0,"",IFERROR(H70/D70*1000,0)) | AC70: =IF(COUNT(C70:P70)=0,"",IFERROR(J70/H70,0)) | AD70: =IF(COUNT(C70:P70)=0,"",IFERROR(C70/J70,0)) | AE70: =IF(COUNT(C70:P70)=0,"",IFERROR(K70/H70,0)) | AF70: =IF(COUNT(C70:P70)=0,"",IFERROR(L70/H70,0)) | AG70: =IF(COUNT(C70:P70)=0,"",IFERROR(C70/K70,0)) | AH70: =IF(COUNT(C70:P70)=0,"",IFERROR(M70/K70,0)) | AI70: =IF(COUNT(C70:P70)=0,"",IFERROR(C70/M70,0)) | AJ70: =IF(COUNT(C70:P70)=0,"",IFERROR(N70/M70,0)) | AK70: =IF(COUNT(C70:P70)=0,"",IFERROR(N70/H70,0)) | AL70: =IF(COUNT(C70:P70)=0,"",IFERROR(C70/N70,0)) | AM70: =IF(COUNT(C70:P70)=0,"",IFERROR(O70/N70,0)) | AN70: =IF(COUNT(C70:P70)=0,"",IFERROR(P70/N70,0)) | AO70: =IF(COUNT(C70:P70)=0,"",IFERROR(N70*Config!$C$7+O70*Config!$C$8+P70*Config!$C$9,0)) | AP70: =IF(COUNT(C70:P70)=0,"",IFERROR(AO70/N70,0)) | AQ70: =IF(COUNT(C70:P70)=0,"",IFERROR(AO70*(1-Config!$C$10-Config!$C$11-Config!$C$12),0)) | AR70: =IF(COUNT(C70:P70)=0,"",IFERROR(AQ70-C70-Config!$C$13,0)) | AS70: =IF(COUNT(C70:P70)=0,"",IFERROR(AQ70/C70,0)) | AT70: =IF(COUNT(C70:P70)=0,"",IFERROR(AR70/G70,0)) | AU70: =IF(COUNT(C70:P70)=0,"",IFERROR(AT70/V70,0)) | AV70: =IF(COUNT(C70:P70)=0,"",IFERROR(AR70/H70,0))
A71: =Config!$C$6+65 | B71: =INT((A71-Config!$C$6)/7)+1 | Q71: =IF(COUNT(C71:P71)=0,"",IFERROR(C71/D71*1000,0)) | R71: =IF(COUNT(C71:P71)=0,"",IFERROR(D71/E71,0)) | S71: =IF(COUNT(C71:P71)=0,"",IFERROR(F71/D71,0)) | T71: =IF(COUNT(C71:P71)=0,"",IFERROR(C71/F71,0)) | U71: =IF(COUNT(C71:P71)=0,"",IFERROR(G71/F71,0)) | V71: =IF(COUNT(C71:P71)=0,"",IFERROR(C71/G71,0)) | W71: =IF(COUNT(C71:P71)=0,"",IFERROR(G71/D71*1000,0)) | X71: =IF(COUNT(C71:P71)=0,"",IFERROR(H71/G71,0)) | Y71: =IF(COUNT(C71:P71)=0,"",IFERROR(C71/H71,0)) | Z71: =IF(COUNT(C71:P71)=0,"",IFERROR(C71/I71,0)) | AA71: =IF(COUNT(C71:P71)=0,"",IFERROR(Y71/Q71,0)) | AB71: =IF(COUNT(C71:P71)=0,"",IFERROR(H71/D71*1000,0)) | AC71: =IF(COUNT(C71:P71)=0,"",IFERROR(J71/H71,0)) | AD71: =IF(COUNT(C71:P71)=0,"",IFERROR(C71/J71,0)) | AE71: =IF(COUNT(C71:P71)=0,"",IFERROR(K71/H71,0)) | AF71: =IF(COUNT(C71:P71)=0,"",IFERROR(L71/H71,0)) | AG71: =IF(COUNT(C71:P71)=0,"",IFERROR(C71/K71,0)) | AH71: =IF(COUNT(C71:P71)=0,"",IFERROR(M71/K71,0)) | AI71: =IF(COUNT(C71:P71)=0,"",IFERROR(C71/M71,0)) | AJ71: =IF(COUNT(C71:P71)=0,"",IFERROR(N71/M71,0)) | AK71: =IF(COUNT(C71:P71)=0,"",IFERROR(N71/H71,0)) | AL71: =IF(COUNT(C71:P71)=0,"",IFERROR(C71/N71,0)) | AM71: =IF(COUNT(C71:P71)=0,"",IFERROR(O71/N71,0)) | AN71: =IF(COUNT(C71:P71)=0,"",IFERROR(P71/N71,0)) | AO71: =IF(COUNT(C71:P71)=0,"",IFERROR(N71*Config!$C$7+O71*Config!$C$8+P71*Config!$C$9,0)) | AP71: =IF(COUNT(C71:P71)=0,"",IFERROR(AO71/N71,0)) | AQ71: =IF(COUNT(C71:P71)=0,"",IFERROR(AO71*(1-Config!$C$10-Config!$C$11-Config!$C$12),0)) | AR71: =IF(COUNT(C71:P71)=0,"",IFERROR(AQ71-C71-Config!$C$13,0)) | AS71: =IF(COUNT(C71:P71)=0,"",IFERROR(AQ71/C71,0)) | AT71: =IF(COUNT(C71:P71)=0,"",IFERROR(AR71/G71,0)) | AU71: =IF(COUNT(C71:P71)=0,"",IFERROR(AT71/V71,0)) | AV71: =IF(COUNT(C71:P71)=0,"",IFERROR(AR71/H71,0))
A72: =Config!$C$6+66 | B72: =INT((A72-Config!$C$6)/7)+1 | Q72: =IF(COUNT(C72:P72)=0,"",IFERROR(C72/D72*1000,0)) | R72: =IF(COUNT(C72:P72)=0,"",IFERROR(D72/E72,0)) | S72: =IF(COUNT(C72:P72)=0,"",IFERROR(F72/D72,0)) | T72: =IF(COUNT(C72:P72)=0,"",IFERROR(C72/F72,0)) | U72: =IF(COUNT(C72:P72)=0,"",IFERROR(G72/F72,0)) | V72: =IF(COUNT(C72:P72)=0,"",IFERROR(C72/G72,0)) | W72: =IF(COUNT(C72:P72)=0,"",IFERROR(G72/D72*1000,0)) | X72: =IF(COUNT(C72:P72)=0,"",IFERROR(H72/G72,0)) | Y72: =IF(COUNT(C72:P72)=0,"",IFERROR(C72/H72,0)) | Z72: =IF(COUNT(C72:P72)=0,"",IFERROR(C72/I72,0)) | AA72: =IF(COUNT(C72:P72)=0,"",IFERROR(Y72/Q72,0)) | AB72: =IF(COUNT(C72:P72)=0,"",IFERROR(H72/D72*1000,0)) | AC72: =IF(COUNT(C72:P72)=0,"",IFERROR(J72/H72,0)) | AD72: =IF(COUNT(C72:P72)=0,"",IFERROR(C72/J72,0)) | AE72: =IF(COUNT(C72:P72)=0,"",IFERROR(K72/H72,0)) | AF72: =IF(COUNT(C72:P72)=0,"",IFERROR(L72/H72,0)) | AG72: =IF(COUNT(C72:P72)=0,"",IFERROR(C72/K72,0)) | AH72: =IF(COUNT(C72:P72)=0,"",IFERROR(M72/K72,0)) | AI72: =IF(COUNT(C72:P72)=0,"",IFERROR(C72/M72,0)) | AJ72: =IF(COUNT(C72:P72)=0,"",IFERROR(N72/M72,0)) | AK72: =IF(COUNT(C72:P72)=0,"",IFERROR(N72/H72,0)) | AL72: =IF(COUNT(C72:P72)=0,"",IFERROR(C72/N72,0)) | AM72: =IF(COUNT(C72:P72)=0,"",IFERROR(O72/N72,0)) | AN72: =IF(COUNT(C72:P72)=0,"",IFERROR(P72/N72,0)) | AO72: =IF(COUNT(C72:P72)=0,"",IFERROR(N72*Config!$C$7+O72*Config!$C$8+P72*Config!$C$9,0)) | AP72: =IF(COUNT(C72:P72)=0,"",IFERROR(AO72/N72,0)) | AQ72: =IF(COUNT(C72:P72)=0,"",IFERROR(AO72*(1-Config!$C$10-Config!$C$11-Config!$C$12),0)) | AR72: =IF(COUNT(C72:P72)=0,"",IFERROR(AQ72-C72-Config!$C$13,0)) | AS72: =IF(COUNT(C72:P72)=0,"",IFERROR(AQ72/C72,0)) | AT72: =IF(COUNT(C72:P72)=0,"",IFERROR(AR72/G72,0)) | AU72: =IF(COUNT(C72:P72)=0,"",IFERROR(AT72/V72,0)) | AV72: =IF(COUNT(C72:P72)=0,"",IFERROR(AR72/H72,0))
A73: =Config!$C$6+67 | B73: =INT((A73-Config!$C$6)/7)+1 | Q73: =IF(COUNT(C73:P73)=0,"",IFERROR(C73/D73*1000,0)) | R73: =IF(COUNT(C73:P73)=0,"",IFERROR(D73/E73,0)) | S73: =IF(COUNT(C73:P73)=0,"",IFERROR(F73/D73,0)) | T73: =IF(COUNT(C73:P73)=0,"",IFERROR(C73/F73,0)) | U73: =IF(COUNT(C73:P73)=0,"",IFERROR(G73/F73,0)) | V73: =IF(COUNT(C73:P73)=0,"",IFERROR(C73/G73,0)) | W73: =IF(COUNT(C73:P73)=0,"",IFERROR(G73/D73*1000,0)) | X73: =IF(COUNT(C73:P73)=0,"",IFERROR(H73/G73,0)) | Y73: =IF(COUNT(C73:P73)=0,"",IFERROR(C73/H73,0)) | Z73: =IF(COUNT(C73:P73)=0,"",IFERROR(C73/I73,0)) | AA73: =IF(COUNT(C73:P73)=0,"",IFERROR(Y73/Q73,0)) | AB73: =IF(COUNT(C73:P73)=0,"",IFERROR(H73/D73*1000,0)) | AC73: =IF(COUNT(C73:P73)=0,"",IFERROR(J73/H73,0)) | AD73: =IF(COUNT(C73:P73)=0,"",IFERROR(C73/J73,0)) | AE73: =IF(COUNT(C73:P73)=0,"",IFERROR(K73/H73,0)) | AF73: =IF(COUNT(C73:P73)=0,"",IFERROR(L73/H73,0)) | AG73: =IF(COUNT(C73:P73)=0,"",IFERROR(C73/K73,0)) | AH73: =IF(COUNT(C73:P73)=0,"",IFERROR(M73/K73,0)) | AI73: =IF(COUNT(C73:P73)=0,"",IFERROR(C73/M73,0)) | AJ73: =IF(COUNT(C73:P73)=0,"",IFERROR(N73/M73,0)) | AK73: =IF(COUNT(C73:P73)=0,"",IFERROR(N73/H73,0)) | AL73: =IF(COUNT(C73:P73)=0,"",IFERROR(C73/N73,0)) | AM73: =IF(COUNT(C73:P73)=0,"",IFERROR(O73/N73,0)) | AN73: =IF(COUNT(C73:P73)=0,"",IFERROR(P73/N73,0)) | AO73: =IF(COUNT(C73:P73)=0,"",IFERROR(N73*Config!$C$7+O73*Config!$C$8+P73*Config!$C$9,0)) | AP73: =IF(COUNT(C73:P73)=0,"",IFERROR(AO73/N73,0)) | AQ73: =IF(COUNT(C73:P73)=0,"",IFERROR(AO73*(1-Config!$C$10-Config!$C$11-Config!$C$12),0)) | AR73: =IF(COUNT(C73:P73)=0,"",IFERROR(AQ73-C73-Config!$C$13,0)) | AS73: =IF(COUNT(C73:P73)=0,"",IFERROR(AQ73/C73,0)) | AT73: =IF(COUNT(C73:P73)=0,"",IFERROR(AR73/G73,0)) | AU73: =IF(COUNT(C73:P73)=0,"",IFERROR(AT73/V73,0)) | AV73: =IF(COUNT(C73:P73)=0,"",IFERROR(AR73/H73,0))
A74: =Config!$C$6+68 | B74: =INT((A74-Config!$C$6)/7)+1 | Q74: =IF(COUNT(C74:P74)=0,"",IFERROR(C74/D74*1000,0)) | R74: =IF(COUNT(C74:P74)=0,"",IFERROR(D74/E74,0)) | S74: =IF(COUNT(C74:P74)=0,"",IFERROR(F74/D74,0)) | T74: =IF(COUNT(C74:P74)=0,"",IFERROR(C74/F74,0)) | U74: =IF(COUNT(C74:P74)=0,"",IFERROR(G74/F74,0)) | V74: =IF(COUNT(C74:P74)=0,"",IFERROR(C74/G74,0)) | W74: =IF(COUNT(C74:P74)=0,"",IFERROR(G74/D74*1000,0)) | X74: =IF(COUNT(C74:P74)=0,"",IFERROR(H74/G74,0)) | Y74: =IF(COUNT(C74:P74)=0,"",IFERROR(C74/H74,0)) | Z74: =IF(COUNT(C74:P74)=0,"",IFERROR(C74/I74,0)) | AA74: =IF(COUNT(C74:P74)=0,"",IFERROR(Y74/Q74,0)) | AB74: =IF(COUNT(C74:P74)=0,"",IFERROR(H74/D74*1000,0)) | AC74: =IF(COUNT(C74:P74)=0,"",IFERROR(J74/H74,0)) | AD74: =IF(COUNT(C74:P74)=0,"",IFERROR(C74/J74,0)) | AE74: =IF(COUNT(C74:P74)=0,"",IFERROR(K74/H74,0)) | AF74: =IF(COUNT(C74:P74)=0,"",IFERROR(L74/H74,0)) | AG74: =IF(COUNT(C74:P74)=0,"",IFERROR(C74/K74,0)) | AH74: =IF(COUNT(C74:P74)=0,"",IFERROR(M74/K74,0)) | AI74: =IF(COUNT(C74:P74)=0,"",IFERROR(C74/M74,0)) | AJ74: =IF(COUNT(C74:P74)=0,"",IFERROR(N74/M74,0)) | AK74: =IF(COUNT(C74:P74)=0,"",IFERROR(N74/H74,0)) | AL74: =IF(COUNT(C74:P74)=0,"",IFERROR(C74/N74,0)) | AM74: =IF(COUNT(C74:P74)=0,"",IFERROR(O74/N74,0)) | AN74: =IF(COUNT(C74:P74)=0,"",IFERROR(P74/N74,0)) | AO74: =IF(COUNT(C74:P74)=0,"",IFERROR(N74*Config!$C$7+O74*Config!$C$8+P74*Config!$C$9,0)) | AP74: =IF(COUNT(C74:P74)=0,"",IFERROR(AO74/N74,0)) | AQ74: =IF(COUNT(C74:P74)=0,"",IFERROR(AO74*(1-Config!$C$10-Config!$C$11-Config!$C$12),0)) | AR74: =IF(COUNT(C74:P74)=0,"",IFERROR(AQ74-C74-Config!$C$13,0)) | AS74: =IF(COUNT(C74:P74)=0,"",IFERROR(AQ74/C74,0)) | AT74: =IF(COUNT(C74:P74)=0,"",IFERROR(AR74/G74,0)) | AU74: =IF(COUNT(C74:P74)=0,"",IFERROR(AT74/V74,0)) | AV74: =IF(COUNT(C74:P74)=0,"",IFERROR(AR74/H74,0))
A75: =Config!$C$6+69 | B75: =INT((A75-Config!$C$6)/7)+1 | Q75: =IF(COUNT(C75:P75)=0,"",IFERROR(C75/D75*1000,0)) | R75: =IF(COUNT(C75:P75)=0,"",IFERROR(D75/E75,0)) | S75: =IF(COUNT(C75:P75)=0,"",IFERROR(F75/D75,0)) | T75: =IF(COUNT(C75:P75)=0,"",IFERROR(C75/F75,0)) | U75: =IF(COUNT(C75:P75)=0,"",IFERROR(G75/F75,0)) | V75: =IF(COUNT(C75:P75)=0,"",IFERROR(C75/G75,0)) | W75: =IF(COUNT(C75:P75)=0,"",IFERROR(G75/D75*1000,0)) | X75: =IF(COUNT(C75:P75)=0,"",IFERROR(H75/G75,0)) | Y75: =IF(COUNT(C75:P75)=0,"",IFERROR(C75/H75,0)) | Z75: =IF(COUNT(C75:P75)=0,"",IFERROR(C75/I75,0)) | AA75: =IF(COUNT(C75:P75)=0,"",IFERROR(Y75/Q75,0)) | AB75: =IF(COUNT(C75:P75)=0,"",IFERROR(H75/D75*1000,0)) | AC75: =IF(COUNT(C75:P75)=0,"",IFERROR(J75/H75,0)) | AD75: =IF(COUNT(C75:P75)=0,"",IFERROR(C75/J75,0)) | AE75: =IF(COUNT(C75:P75)=0,"",IFERROR(K75/H75,0)) | AF75: =IF(COUNT(C75:P75)=0,"",IFERROR(L75/H75,0)) | AG75: =IF(COUNT(C75:P75)=0,"",IFERROR(C75/K75,0)) | AH75: =IF(COUNT(C75:P75)=0,"",IFERROR(M75/K75,0)) | AI75: =IF(COUNT(C75:P75)=0,"",IFERROR(C75/M75,0)) | AJ75: =IF(COUNT(C75:P75)=0,"",IFERROR(N75/M75,0)) | AK75: =IF(COUNT(C75:P75)=0,"",IFERROR(N75/H75,0)) | AL75: =IF(COUNT(C75:P75)=0,"",IFERROR(C75/N75,0)) | AM75: =IF(COUNT(C75:P75)=0,"",IFERROR(O75/N75,0)) | AN75: =IF(COUNT(C75:P75)=0,"",IFERROR(P75/N75,0)) | AO75: =IF(COUNT(C75:P75)=0,"",IFERROR(N75*Config!$C$7+O75*Config!$C$8+P75*Config!$C$9,0)) | AP75: =IF(COUNT(C75:P75)=0,"",IFERROR(AO75/N75,0)) | AQ75: =IF(COUNT(C75:P75)=0,"",IFERROR(AO75*(1-Config!$C$10-Config!$C$11-Config!$C$12),0)) | AR75: =IF(COUNT(C75:P75)=0,"",IFERROR(AQ75-C75-Config!$C$13,0)) | AS75: =IF(COUNT(C75:P75)=0,"",IFERROR(AQ75/C75,0)) | AT75: =IF(COUNT(C75:P75)=0,"",IFERROR(AR75/G75,0)) | AU75: =IF(COUNT(C75:P75)=0,"",IFERROR(AT75/V75,0)) | AV75: =IF(COUNT(C75:P75)=0,"",IFERROR(AR75/H75,0))
A76: =Config!$C$6+70 | B76: =INT((A76-Config!$C$6)/7)+1 | Q76: =IF(COUNT(C76:P76)=0,"",IFERROR(C76/D76*1000,0)) | R76: =IF(COUNT(C76:P76)=0,"",IFERROR(D76/E76,0)) | S76: =IF(COUNT(C76:P76)=0,"",IFERROR(F76/D76,0)) | T76: =IF(COUNT(C76:P76)=0,"",IFERROR(C76/F76,0)) | U76: =IF(COUNT(C76:P76)=0,"",IFERROR(G76/F76,0)) | V76: =IF(COUNT(C76:P76)=0,"",IFERROR(C76/G76,0)) | W76: =IF(COUNT(C76:P76)=0,"",IFERROR(G76/D76*1000,0)) | X76: =IF(COUNT(C76:P76)=0,"",IFERROR(H76/G76,0)) | Y76: =IF(COUNT(C76:P76)=0,"",IFERROR(C76/H76,0)) | Z76: =IF(COUNT(C76:P76)=0,"",IFERROR(C76/I76,0)) | AA76: =IF(COUNT(C76:P76)=0,"",IFERROR(Y76/Q76,0)) | AB76: =IF(COUNT(C76:P76)=0,"",IFERROR(H76/D76*1000,0)) | AC76: =IF(COUNT(C76:P76)=0,"",IFERROR(J76/H76,0)) | AD76: =IF(COUNT(C76:P76)=0,"",IFERROR(C76/J76,0)) | AE76: =IF(COUNT(C76:P76)=0,"",IFERROR(K76/H76,0)) | AF76: =IF(COUNT(C76:P76)=0,"",IFERROR(L76/H76,0)) | AG76: =IF(COUNT(C76:P76)=0,"",IFERROR(C76/K76,0)) | AH76: =IF(COUNT(C76:P76)=0,"",IFERROR(M76/K76,0)) | AI76: =IF(COUNT(C76:P76)=0,"",IFERROR(C76/M76,0)) | AJ76: =IF(COUNT(C76:P76)=0,"",IFERROR(N76/M76,0)) | AK76: =IF(COUNT(C76:P76)=0,"",IFERROR(N76/H76,0)) | AL76: =IF(COUNT(C76:P76)=0,"",IFERROR(C76/N76,0)) | AM76: =IF(COUNT(C76:P76)=0,"",IFERROR(O76/N76,0)) | AN76: =IF(COUNT(C76:P76)=0,"",IFERROR(P76/N76,0)) | AO76: =IF(COUNT(C76:P76)=0,"",IFERROR(N76*Config!$C$7+O76*Config!$C$8+P76*Config!$C$9,0)) | AP76: =IF(COUNT(C76:P76)=0,"",IFERROR(AO76/N76,0)) | AQ76: =IF(COUNT(C76:P76)=0,"",IFERROR(AO76*(1-Config!$C$10-Config!$C$11-Config!$C$12),0)) | AR76: =IF(COUNT(C76:P76)=0,"",IFERROR(AQ76-C76-Config!$C$13,0)) | AS76: =IF(COUNT(C76:P76)=0,"",IFERROR(AQ76/C76,0)) | AT76: =IF(COUNT(C76:P76)=0,"",IFERROR(AR76/G76,0)) | AU76: =IF(COUNT(C76:P76)=0,"",IFERROR(AT76/V76,0)) | AV76: =IF(COUNT(C76:P76)=0,"",IFERROR(AR76/H76,0))
A77: =Config!$C$6+71 | B77: =INT((A77-Config!$C$6)/7)+1 | Q77: =IF(COUNT(C77:P77)=0,"",IFERROR(C77/D77*1000,0)) | R77: =IF(COUNT(C77:P77)=0,"",IFERROR(D77/E77,0)) | S77: =IF(COUNT(C77:P77)=0,"",IFERROR(F77/D77,0)) | T77: =IF(COUNT(C77:P77)=0,"",IFERROR(C77/F77,0)) | U77: =IF(COUNT(C77:P77)=0,"",IFERROR(G77/F77,0)) | V77: =IF(COUNT(C77:P77)=0,"",IFERROR(C77/G77,0)) | W77: =IF(COUNT(C77:P77)=0,"",IFERROR(G77/D77*1000,0)) | X77: =IF(COUNT(C77:P77)=0,"",IFERROR(H77/G77,0)) | Y77: =IF(COUNT(C77:P77)=0,"",IFERROR(C77/H77,0)) | Z77: =IF(COUNT(C77:P77)=0,"",IFERROR(C77/I77,0)) | AA77: =IF(COUNT(C77:P77)=0,"",IFERROR(Y77/Q77,0)) | AB77: =IF(COUNT(C77:P77)=0,"",IFERROR(H77/D77*1000,0)) | AC77: =IF(COUNT(C77:P77)=0,"",IFERROR(J77/H77,0)) | AD77: =IF(COUNT(C77:P77)=0,"",IFERROR(C77/J77,0)) | AE77: =IF(COUNT(C77:P77)=0,"",IFERROR(K77/H77,0)) | AF77: =IF(COUNT(C77:P77)=0,"",IFERROR(L77/H77,0)) | AG77: =IF(COUNT(C77:P77)=0,"",IFERROR(C77/K77,0)) | AH77: =IF(COUNT(C77:P77)=0,"",IFERROR(M77/K77,0)) | AI77: =IF(COUNT(C77:P77)=0,"",IFERROR(C77/M77,0)) | AJ77: =IF(COUNT(C77:P77)=0,"",IFERROR(N77/M77,0)) | AK77: =IF(COUNT(C77:P77)=0,"",IFERROR(N77/H77,0)) | AL77: =IF(COUNT(C77:P77)=0,"",IFERROR(C77/N77,0)) | AM77: =IF(COUNT(C77:P77)=0,"",IFERROR(O77/N77,0)) | AN77: =IF(COUNT(C77:P77)=0,"",IFERROR(P77/N77,0)) | AO77: =IF(COUNT(C77:P77)=0,"",IFERROR(N77*Config!$C$7+O77*Config!$C$8+P77*Config!$C$9,0)) | AP77: =IF(COUNT(C77:P77)=0,"",IFERROR(AO77/N77,0)) | AQ77: =IF(COUNT(C77:P77)=0,"",IFERROR(AO77*(1-Config!$C$10-Config!$C$11-Config!$C$12),0)) | AR77: =IF(COUNT(C77:P77)=0,"",IFERROR(AQ77-C77-Config!$C$13,0)) | AS77: =IF(COUNT(C77:P77)=0,"",IFERROR(AQ77/C77,0)) | AT77: =IF(COUNT(C77:P77)=0,"",IFERROR(AR77/G77,0)) | AU77: =IF(COUNT(C77:P77)=0,"",IFERROR(AT77/V77,0)) | AV77: =IF(COUNT(C77:P77)=0,"",IFERROR(AR77/H77,0))
A78: =Config!$C$6+72 | B78: =INT((A78-Config!$C$6)/7)+1 | Q78: =IF(COUNT(C78:P78)=0,"",IFERROR(C78/D78*1000,0)) | R78: =IF(COUNT(C78:P78)=0,"",IFERROR(D78/E78,0)) | S78: =IF(COUNT(C78:P78)=0,"",IFERROR(F78/D78,0)) | T78: =IF(COUNT(C78:P78)=0,"",IFERROR(C78/F78,0)) | U78: =IF(COUNT(C78:P78)=0,"",IFERROR(G78/F78,0)) | V78: =IF(COUNT(C78:P78)=0,"",IFERROR(C78/G78,0)) | W78: =IF(COUNT(C78:P78)=0,"",IFERROR(G78/D78*1000,0)) | X78: =IF(COUNT(C78:P78)=0,"",IFERROR(H78/G78,0)) | Y78: =IF(COUNT(C78:P78)=0,"",IFERROR(C78/H78,0)) | Z78: =IF(COUNT(C78:P78)=0,"",IFERROR(C78/I78,0)) | AA78: =IF(COUNT(C78:P78)=0,"",IFERROR(Y78/Q78,0)) | AB78: =IF(COUNT(C78:P78)=0,"",IFERROR(H78/D78*1000,0)) | AC78: =IF(COUNT(C78:P78)=0,"",IFERROR(J78/H78,0)) | AD78: =IF(COUNT(C78:P78)=0,"",IFERROR(C78/J78,0)) | AE78: =IF(COUNT(C78:P78)=0,"",IFERROR(K78/H78,0)) | AF78: =IF(COUNT(C78:P78)=0,"",IFERROR(L78/H78,0)) | AG78: =IF(COUNT(C78:P78)=0,"",IFERROR(C78/K78,0)) | AH78: =IF(COUNT(C78:P78)=0,"",IFERROR(M78/K78,0)) | AI78: =IF(COUNT(C78:P78)=0,"",IFERROR(C78/M78,0)) | AJ78: =IF(COUNT(C78:P78)=0,"",IFERROR(N78/M78,0)) | AK78: =IF(COUNT(C78:P78)=0,"",IFERROR(N78/H78,0)) | AL78: =IF(COUNT(C78:P78)=0,"",IFERROR(C78/N78,0)) | AM78: =IF(COUNT(C78:P78)=0,"",IFERROR(O78/N78,0)) | AN78: =IF(COUNT(C78:P78)=0,"",IFERROR(P78/N78,0)) | AO78: =IF(COUNT(C78:P78)=0,"",IFERROR(N78*Config!$C$7+O78*Config!$C$8+P78*Config!$C$9,0)) | AP78: =IF(COUNT(C78:P78)=0,"",IFERROR(AO78/N78,0)) | AQ78: =IF(COUNT(C78:P78)=0,"",IFERROR(AO78*(1-Config!$C$10-Config!$C$11-Config!$C$12),0)) | AR78: =IF(COUNT(C78:P78)=0,"",IFERROR(AQ78-C78-Config!$C$13,0)) | AS78: =IF(COUNT(C78:P78)=0,"",IFERROR(AQ78/C78,0)) | AT78: =IF(COUNT(C78:P78)=0,"",IFERROR(AR78/G78,0)) | AU78: =IF(COUNT(C78:P78)=0,"",IFERROR(AT78/V78,0)) | AV78: =IF(COUNT(C78:P78)=0,"",IFERROR(AR78/H78,0))
A79: =Config!$C$6+73 | B79: =INT((A79-Config!$C$6)/7)+1 | Q79: =IF(COUNT(C79:P79)=0,"",IFERROR(C79/D79*1000,0)) | R79: =IF(COUNT(C79:P79)=0,"",IFERROR(D79/E79,0)) | S79: =IF(COUNT(C79:P79)=0,"",IFERROR(F79/D79,0)) | T79: =IF(COUNT(C79:P79)=0,"",IFERROR(C79/F79,0)) | U79: =IF(COUNT(C79:P79)=0,"",IFERROR(G79/F79,0)) | V79: =IF(COUNT(C79:P79)=0,"",IFERROR(C79/G79,0)) | W79: =IF(COUNT(C79:P79)=0,"",IFERROR(G79/D79*1000,0)) | X79: =IF(COUNT(C79:P79)=0,"",IFERROR(H79/G79,0)) | Y79: =IF(COUNT(C79:P79)=0,"",IFERROR(C79/H79,0)) | Z79: =IF(COUNT(C79:P79)=0,"",IFERROR(C79/I79,0)) | AA79: =IF(COUNT(C79:P79)=0,"",IFERROR(Y79/Q79,0)) | AB79: =IF(COUNT(C79:P79)=0,"",IFERROR(H79/D79*1000,0)) | AC79: =IF(COUNT(C79:P79)=0,"",IFERROR(J79/H79,0)) | AD79: =IF(COUNT(C79:P79)=0,"",IFERROR(C79/J79,0)) | AE79: =IF(COUNT(C79:P79)=0,"",IFERROR(K79/H79,0)) | AF79: =IF(COUNT(C79:P79)=0,"",IFERROR(L79/H79,0)) | AG79: =IF(COUNT(C79:P79)=0,"",IFERROR(C79/K79,0)) | AH79: =IF(COUNT(C79:P79)=0,"",IFERROR(M79/K79,0)) | AI79: =IF(COUNT(C79:P79)=0,"",IFERROR(C79/M79,0)) | AJ79: =IF(COUNT(C79:P79)=0,"",IFERROR(N79/M79,0)) | AK79: =IF(COUNT(C79:P79)=0,"",IFERROR(N79/H79,0)) | AL79: =IF(COUNT(C79:P79)=0,"",IFERROR(C79/N79,0)) | AM79: =IF(COUNT(C79:P79)=0,"",IFERROR(O79/N79,0)) | AN79: =IF(COUNT(C79:P79)=0,"",IFERROR(P79/N79,0)) | AO79: =IF(COUNT(C79:P79)=0,"",IFERROR(N79*Config!$C$7+O79*Config!$C$8+P79*Config!$C$9,0)) | AP79: =IF(COUNT(C79:P79)=0,"",IFERROR(AO79/N79,0)) | AQ79: =IF(COUNT(C79:P79)=0,"",IFERROR(AO79*(1-Config!$C$10-Config!$C$11-Config!$C$12),0)) | AR79: =IF(COUNT(C79:P79)=0,"",IFERROR(AQ79-C79-Config!$C$13,0)) | AS79: =IF(COUNT(C79:P79)=0,"",IFERROR(AQ79/C79,0)) | AT79: =IF(COUNT(C79:P79)=0,"",IFERROR(AR79/G79,0)) | AU79: =IF(COUNT(C79:P79)=0,"",IFERROR(AT79/V79,0)) | AV79: =IF(COUNT(C79:P79)=0,"",IFERROR(AR79/H79,0))
A80: =Config!$C$6+74 | B80: =INT((A80-Config!$C$6)/7)+1 | Q80: =IF(COUNT(C80:P80)=0,"",IFERROR(C80/D80*1000,0)) | R80: =IF(COUNT(C80:P80)=0,"",IFERROR(D80/E80,0)) | S80: =IF(COUNT(C80:P80)=0,"",IFERROR(F80/D80,0)) | T80: =IF(COUNT(C80:P80)=0,"",IFERROR(C80/F80,0)) | U80: =IF(COUNT(C80:P80)=0,"",IFERROR(G80/F80,0)) | V80: =IF(COUNT(C80:P80)=0,"",IFERROR(C80/G80,0)) | W80: =IF(COUNT(C80:P80)=0,"",IFERROR(G80/D80*1000,0)) | X80: =IF(COUNT(C80:P80)=0,"",IFERROR(H80/G80,0)) | Y80: =IF(COUNT(C80:P80)=0,"",IFERROR(C80/H80,0)) | Z80: =IF(COUNT(C80:P80)=0,"",IFERROR(C80/I80,0)) | AA80: =IF(COUNT(C80:P80)=0,"",IFERROR(Y80/Q80,0)) | AB80: =IF(COUNT(C80:P80)=0,"",IFERROR(H80/D80*1000,0)) | AC80: =IF(COUNT(C80:P80)=0,"",IFERROR(J80/H80,0)) | AD80: =IF(COUNT(C80:P80)=0,"",IFERROR(C80/J80,0)) | AE80: =IF(COUNT(C80:P80)=0,"",IFERROR(K80/H80,0)) | AF80: =IF(COUNT(C80:P80)=0,"",IFERROR(L80/H80,0)) | AG80: =IF(COUNT(C80:P80)=0,"",IFERROR(C80/K80,0)) | AH80: =IF(COUNT(C80:P80)=0,"",IFERROR(M80/K80,0)) | AI80: =IF(COUNT(C80:P80)=0,"",IFERROR(C80/M80,0)) | AJ80: =IF(COUNT(C80:P80)=0,"",IFERROR(N80/M80,0)) | AK80: =IF(COUNT(C80:P80)=0,"",IFERROR(N80/H80,0)) | AL80: =IF(COUNT(C80:P80)=0,"",IFERROR(C80/N80,0)) | AM80: =IF(COUNT(C80:P80)=0,"",IFERROR(O80/N80,0)) | AN80: =IF(COUNT(C80:P80)=0,"",IFERROR(P80/N80,0)) | AO80: =IF(COUNT(C80:P80)=0,"",IFERROR(N80*Config!$C$7+O80*Config!$C$8+P80*Config!$C$9,0)) | AP80: =IF(COUNT(C80:P80)=0,"",IFERROR(AO80/N80,0)) | AQ80: =IF(COUNT(C80:P80)=0,"",IFERROR(AO80*(1-Config!$C$10-Config!$C$11-Config!$C$12),0)) | AR80: =IF(COUNT(C80:P80)=0,"",IFERROR(AQ80-C80-Config!$C$13,0)) | AS80: =IF(COUNT(C80:P80)=0,"",IFERROR(AQ80/C80,0)) | AT80: =IF(COUNT(C80:P80)=0,"",IFERROR(AR80/G80,0)) | AU80: =IF(COUNT(C80:P80)=0,"",IFERROR(AT80/V80,0)) | AV80: =IF(COUNT(C80:P80)=0,"",IFERROR(AR80/H80,0))
A81: =Config!$C$6+75 | B81: =INT((A81-Config!$C$6)/7)+1 | Q81: =IF(COUNT(C81:P81)=0,"",IFERROR(C81/D81*1000,0)) | R81: =IF(COUNT(C81:P81)=0,"",IFERROR(D81/E81,0)) | S81: =IF(COUNT(C81:P81)=0,"",IFERROR(F81/D81,0)) | T81: =IF(COUNT(C81:P81)=0,"",IFERROR(C81/F81,0)) | U81: =IF(COUNT(C81:P81)=0,"",IFERROR(G81/F81,0)) | V81: =IF(COUNT(C81:P81)=0,"",IFERROR(C81/G81,0)) | W81: =IF(COUNT(C81:P81)=0,"",IFERROR(G81/D81*1000,0)) | X81: =IF(COUNT(C81:P81)=0,"",IFERROR(H81/G81,0)) | Y81: =IF(COUNT(C81:P81)=0,"",IFERROR(C81/H81,0)) | Z81: =IF(COUNT(C81:P81)=0,"",IFERROR(C81/I81,0)) | AA81: =IF(COUNT(C81:P81)=0,"",IFERROR(Y81/Q81,0)) | AB81: =IF(COUNT(C81:P81)=0,"",IFERROR(H81/D81*1000,0)) | AC81: =IF(COUNT(C81:P81)=0,"",IFERROR(J81/H81,0)) | AD81: =IF(COUNT(C81:P81)=0,"",IFERROR(C81/J81,0)) | AE81: =IF(COUNT(C81:P81)=0,"",IFERROR(K81/H81,0)) | AF81: =IF(COUNT(C81:P81)=0,"",IFERROR(L81/H81,0)) | AG81: =IF(COUNT(C81:P81)=0,"",IFERROR(C81/K81,0)) | AH81: =IF(COUNT(C81:P81)=0,"",IFERROR(M81/K81,0)) | AI81: =IF(COUNT(C81:P81)=0,"",IFERROR(C81/M81,0)) | AJ81: =IF(COUNT(C81:P81)=0,"",IFERROR(N81/M81,0)) | AK81: =IF(COUNT(C81:P81)=0,"",IFERROR(N81/H81,0)) | AL81: =IF(COUNT(C81:P81)=0,"",IFERROR(C81/N81,0)) | AM81: =IF(COUNT(C81:P81)=0,"",IFERROR(O81/N81,0)) | AN81: =IF(COUNT(C81:P81)=0,"",IFERROR(P81/N81,0)) | AO81: =IF(COUNT(C81:P81)=0,"",IFERROR(N81*Config!$C$7+O81*Config!$C$8+P81*Config!$C$9,0)) | AP81: =IF(COUNT(C81:P81)=0,"",IFERROR(AO81/N81,0)) | AQ81: =IF(COUNT(C81:P81)=0,"",IFERROR(AO81*(1-Config!$C$10-Config!$C$11-Config!$C$12),0)) | AR81: =IF(COUNT(C81:P81)=0,"",IFERROR(AQ81-C81-Config!$C$13,0)) | AS81: =IF(COUNT(C81:P81)=0,"",IFERROR(AQ81/C81,0)) | AT81: =IF(COUNT(C81:P81)=0,"",IFERROR(AR81/G81,0)) | AU81: =IF(COUNT(C81:P81)=0,"",IFERROR(AT81/V81,0)) | AV81: =IF(COUNT(C81:P81)=0,"",IFERROR(AR81/H81,0))
A82: =Config!$C$6+76 | B82: =INT((A82-Config!$C$6)/7)+1 | Q82: =IF(COUNT(C82:P82)=0,"",IFERROR(C82/D82*1000,0)) | R82: =IF(COUNT(C82:P82)=0,"",IFERROR(D82/E82,0)) | S82: =IF(COUNT(C82:P82)=0,"",IFERROR(F82/D82,0)) | T82: =IF(COUNT(C82:P82)=0,"",IFERROR(C82/F82,0)) | U82: =IF(COUNT(C82:P82)=0,"",IFERROR(G82/F82,0)) | V82: =IF(COUNT(C82:P82)=0,"",IFERROR(C82/G82,0)) | W82: =IF(COUNT(C82:P82)=0,"",IFERROR(G82/D82*1000,0)) | X82: =IF(COUNT(C82:P82)=0,"",IFERROR(H82/G82,0)) | Y82: =IF(COUNT(C82:P82)=0,"",IFERROR(C82/H82,0)) | Z82: =IF(COUNT(C82:P82)=0,"",IFERROR(C82/I82,0)) | AA82: =IF(COUNT(C82:P82)=0,"",IFERROR(Y82/Q82,0)) | AB82: =IF(COUNT(C82:P82)=0,"",IFERROR(H82/D82*1000,0)) | AC82: =IF(COUNT(C82:P82)=0,"",IFERROR(J82/H82,0)) | AD82: =IF(COUNT(C82:P82)=0,"",IFERROR(C82/J82,0)) | AE82: =IF(COUNT(C82:P82)=0,"",IFERROR(K82/H82,0)) | AF82: =IF(COUNT(C82:P82)=0,"",IFERROR(L82/H82,0)) | AG82: =IF(COUNT(C82:P82)=0,"",IFERROR(C82/K82,0)) | AH82: =IF(COUNT(C82:P82)=0,"",IFERROR(M82/K82,0)) | AI82: =IF(COUNT(C82:P82)=0,"",IFERROR(C82/M82,0)) | AJ82: =IF(COUNT(C82:P82)=0,"",IFERROR(N82/M82,0)) | AK82: =IF(COUNT(C82:P82)=0,"",IFERROR(N82/H82,0)) | AL82: =IF(COUNT(C82:P82)=0,"",IFERROR(C82/N82,0)) | AM82: =IF(COUNT(C82:P82)=0,"",IFERROR(O82/N82,0)) | AN82: =IF(COUNT(C82:P82)=0,"",IFERROR(P82/N82,0)) | AO82: =IF(COUNT(C82:P82)=0,"",IFERROR(N82*Config!$C$7+O82*Config!$C$8+P82*Config!$C$9,0)) | AP82: =IF(COUNT(C82:P82)=0,"",IFERROR(AO82/N82,0)) | AQ82: =IF(COUNT(C82:P82)=0,"",IFERROR(AO82*(1-Config!$C$10-Config!$C$11-Config!$C$12),0)) | AR82: =IF(COUNT(C82:P82)=0,"",IFERROR(AQ82-C82-Config!$C$13,0)) | AS82: =IF(COUNT(C82:P82)=0,"",IFERROR(AQ82/C82,0)) | AT82: =IF(COUNT(C82:P82)=0,"",IFERROR(AR82/G82,0)) | AU82: =IF(COUNT(C82:P82)=0,"",IFERROR(AT82/V82,0)) | AV82: =IF(COUNT(C82:P82)=0,"",IFERROR(AR82/H82,0))
A83: =Config!$C$6+77 | B83: =INT((A83-Config!$C$6)/7)+1 | Q83: =IF(COUNT(C83:P83)=0,"",IFERROR(C83/D83*1000,0)) | R83: =IF(COUNT(C83:P83)=0,"",IFERROR(D83/E83,0)) | S83: =IF(COUNT(C83:P83)=0,"",IFERROR(F83/D83,0)) | T83: =IF(COUNT(C83:P83)=0,"",IFERROR(C83/F83,0)) | U83: =IF(COUNT(C83:P83)=0,"",IFERROR(G83/F83,0)) | V83: =IF(COUNT(C83:P83)=0,"",IFERROR(C83/G83,0)) | W83: =IF(COUNT(C83:P83)=0,"",IFERROR(G83/D83*1000,0)) | X83: =IF(COUNT(C83:P83)=0,"",IFERROR(H83/G83,0)) | Y83: =IF(COUNT(C83:P83)=0,"",IFERROR(C83/H83,0)) | Z83: =IF(COUNT(C83:P83)=0,"",IFERROR(C83/I83,0)) | AA83: =IF(COUNT(C83:P83)=0,"",IFERROR(Y83/Q83,0)) | AB83: =IF(COUNT(C83:P83)=0,"",IFERROR(H83/D83*1000,0)) | AC83: =IF(COUNT(C83:P83)=0,"",IFERROR(J83/H83,0)) | AD83: =IF(COUNT(C83:P83)=0,"",IFERROR(C83/J83,0)) | AE83: =IF(COUNT(C83:P83)=0,"",IFERROR(K83/H83,0)) | AF83: =IF(COUNT(C83:P83)=0,"",IFERROR(L83/H83,0)) | AG83: =IF(COUNT(C83:P83)=0,"",IFERROR(C83/K83,0)) | AH83: =IF(COUNT(C83:P83)=0,"",IFERROR(M83/K83,0)) | AI83: =IF(COUNT(C83:P83)=0,"",IFERROR(C83/M83,0)) | AJ83: =IF(COUNT(C83:P83)=0,"",IFERROR(N83/M83,0)) | AK83: =IF(COUNT(C83:P83)=0,"",IFERROR(N83/H83,0)) | AL83: =IF(COUNT(C83:P83)=0,"",IFERROR(C83/N83,0)) | AM83: =IF(COUNT(C83:P83)=0,"",IFERROR(O83/N83,0)) | AN83: =IF(COUNT(C83:P83)=0,"",IFERROR(P83/N83,0)) | AO83: =IF(COUNT(C83:P83)=0,"",IFERROR(N83*Config!$C$7+O83*Config!$C$8+P83*Config!$C$9,0)) | AP83: =IF(COUNT(C83:P83)=0,"",IFERROR(AO83/N83,0)) | AQ83: =IF(COUNT(C83:P83)=0,"",IFERROR(AO83*(1-Config!$C$10-Config!$C$11-Config!$C$12),0)) | AR83: =IF(COUNT(C83:P83)=0,"",IFERROR(AQ83-C83-Config!$C$13,0)) | AS83: =IF(COUNT(C83:P83)=0,"",IFERROR(AQ83/C83,0)) | AT83: =IF(COUNT(C83:P83)=0,"",IFERROR(AR83/G83,0)) | AU83: =IF(COUNT(C83:P83)=0,"",IFERROR(AT83/V83,0)) | AV83: =IF(COUNT(C83:P83)=0,"",IFERROR(AR83/H83,0))
A84: =Config!$C$6+78 | B84: =INT((A84-Config!$C$6)/7)+1 | Q84: =IF(COUNT(C84:P84)=0,"",IFERROR(C84/D84*1000,0)) | R84: =IF(COUNT(C84:P84)=0,"",IFERROR(D84/E84,0)) | S84: =IF(COUNT(C84:P84)=0,"",IFERROR(F84/D84,0)) | T84: =IF(COUNT(C84:P84)=0,"",IFERROR(C84/F84,0)) | U84: =IF(COUNT(C84:P84)=0,"",IFERROR(G84/F84,0)) | V84: =IF(COUNT(C84:P84)=0,"",IFERROR(C84/G84,0)) | W84: =IF(COUNT(C84:P84)=0,"",IFERROR(G84/D84*1000,0)) | X84: =IF(COUNT(C84:P84)=0,"",IFERROR(H84/G84,0)) | Y84: =IF(COUNT(C84:P84)=0,"",IFERROR(C84/H84,0)) | Z84: =IF(COUNT(C84:P84)=0,"",IFERROR(C84/I84,0)) | AA84: =IF(COUNT(C84:P84)=0,"",IFERROR(Y84/Q84,0)) | AB84: =IF(COUNT(C84:P84)=0,"",IFERROR(H84/D84*1000,0)) | AC84: =IF(COUNT(C84:P84)=0,"",IFERROR(J84/H84,0)) | AD84: =IF(COUNT(C84:P84)=0,"",IFERROR(C84/J84,0)) | AE84: =IF(COUNT(C84:P84)=0,"",IFERROR(K84/H84,0)) | AF84: =IF(COUNT(C84:P84)=0,"",IFERROR(L84/H84,0)) | AG84: =IF(COUNT(C84:P84)=0,"",IFERROR(C84/K84,0)) | AH84: =IF(COUNT(C84:P84)=0,"",IFERROR(M84/K84,0)) | AI84: =IF(COUNT(C84:P84)=0,"",IFERROR(C84/M84,0)) | AJ84: =IF(COUNT(C84:P84)=0,"",IFERROR(N84/M84,0)) | AK84: =IF(COUNT(C84:P84)=0,"",IFERROR(N84/H84,0)) | AL84: =IF(COUNT(C84:P84)=0,"",IFERROR(C84/N84,0)) | AM84: =IF(COUNT(C84:P84)=0,"",IFERROR(O84/N84,0)) | AN84: =IF(COUNT(C84:P84)=0,"",IFERROR(P84/N84,0)) | AO84: =IF(COUNT(C84:P84)=0,"",IFERROR(N84*Config!$C$7+O84*Config!$C$8+P84*Config!$C$9,0)) | AP84: =IF(COUNT(C84:P84)=0,"",IFERROR(AO84/N84,0)) | AQ84: =IF(COUNT(C84:P84)=0,"",IFERROR(AO84*(1-Config!$C$10-Config!$C$11-Config!$C$12),0)) | AR84: =IF(COUNT(C84:P84)=0,"",IFERROR(AQ84-C84-Config!$C$13,0)) | AS84: =IF(COUNT(C84:P84)=0,"",IFERROR(AQ84/C84,0)) | AT84: =IF(COUNT(C84:P84)=0,"",IFERROR(AR84/G84,0)) | AU84: =IF(COUNT(C84:P84)=0,"",IFERROR(AT84/V84,0)) | AV84: =IF(COUNT(C84:P84)=0,"",IFERROR(AR84/H84,0))
A85: =Config!$C$6+79 | B85: =INT((A85-Config!$C$6)/7)+1 | Q85: =IF(COUNT(C85:P85)=0,"",IFERROR(C85/D85*1000,0)) | R85: =IF(COUNT(C85:P85)=0,"",IFERROR(D85/E85,0)) | S85: =IF(COUNT(C85:P85)=0,"",IFERROR(F85/D85,0)) | T85: =IF(COUNT(C85:P85)=0,"",IFERROR(C85/F85,0)) | U85: =IF(COUNT(C85:P85)=0,"",IFERROR(G85/F85,0)) | V85: =IF(COUNT(C85:P85)=0,"",IFERROR(C85/G85,0)) | W85: =IF(COUNT(C85:P85)=0,"",IFERROR(G85/D85*1000,0)) | X85: =IF(COUNT(C85:P85)=0,"",IFERROR(H85/G85,0)) | Y85: =IF(COUNT(C85:P85)=0,"",IFERROR(C85/H85,0)) | Z85: =IF(COUNT(C85:P85)=0,"",IFERROR(C85/I85,0)) | AA85: =IF(COUNT(C85:P85)=0,"",IFERROR(Y85/Q85,0)) | AB85: =IF(COUNT(C85:P85)=0,"",IFERROR(H85/D85*1000,0)) | AC85: =IF(COUNT(C85:P85)=0,"",IFERROR(J85/H85,0)) | AD85: =IF(COUNT(C85:P85)=0,"",IFERROR(C85/J85,0)) | AE85: =IF(COUNT(C85:P85)=0,"",IFERROR(K85/H85,0)) | AF85: =IF(COUNT(C85:P85)=0,"",IFERROR(L85/H85,0)) | AG85: =IF(COUNT(C85:P85)=0,"",IFERROR(C85/K85,0)) | AH85: =IF(COUNT(C85:P85)=0,"",IFERROR(M85/K85,0)) | AI85: =IF(COUNT(C85:P85)=0,"",IFERROR(C85/M85,0)) | AJ85: =IF(COUNT(C85:P85)=0,"",IFERROR(N85/M85,0)) | AK85: =IF(COUNT(C85:P85)=0,"",IFERROR(N85/H85,0)) | AL85: =IF(COUNT(C85:P85)=0,"",IFERROR(C85/N85,0)) | AM85: =IF(COUNT(C85:P85)=0,"",IFERROR(O85/N85,0)) | AN85: =IF(COUNT(C85:P85)=0,"",IFERROR(P85/N85,0)) | AO85: =IF(COUNT(C85:P85)=0,"",IFERROR(N85*Config!$C$7+O85*Config!$C$8+P85*Config!$C$9,0)) | AP85: =IF(COUNT(C85:P85)=0,"",IFERROR(AO85/N85,0)) | AQ85: =IF(COUNT(C85:P85)=0,"",IFERROR(AO85*(1-Config!$C$10-Config!$C$11-Config!$C$12),0)) | AR85: =IF(COUNT(C85:P85)=0,"",IFERROR(AQ85-C85-Config!$C$13,0)) | AS85: =IF(COUNT(C85:P85)=0,"",IFERROR(AQ85/C85,0)) | AT85: =IF(COUNT(C85:P85)=0,"",IFERROR(AR85/G85,0)) | AU85: =IF(COUNT(C85:P85)=0,"",IFERROR(AT85/V85,0)) | AV85: =IF(COUNT(C85:P85)=0,"",IFERROR(AR85/H85,0))
A86: =Config!$C$6+80 | B86: =INT((A86-Config!$C$6)/7)+1 | Q86: =IF(COUNT(C86:P86)=0,"",IFERROR(C86/D86*1000,0)) | R86: =IF(COUNT(C86:P86)=0,"",IFERROR(D86/E86,0)) | S86: =IF(COUNT(C86:P86)=0,"",IFERROR(F86/D86,0)) | T86: =IF(COUNT(C86:P86)=0,"",IFERROR(C86/F86,0)) | U86: =IF(COUNT(C86:P86)=0,"",IFERROR(G86/F86,0)) | V86: =IF(COUNT(C86:P86)=0,"",IFERROR(C86/G86,0)) | W86: =IF(COUNT(C86:P86)=0,"",IFERROR(G86/D86*1000,0)) | X86: =IF(COUNT(C86:P86)=0,"",IFERROR(H86/G86,0)) | Y86: =IF(COUNT(C86:P86)=0,"",IFERROR(C86/H86,0)) | Z86: =IF(COUNT(C86:P86)=0,"",IFERROR(C86/I86,0)) | AA86: =IF(COUNT(C86:P86)=0,"",IFERROR(Y86/Q86,0)) | AB86: =IF(COUNT(C86:P86)=0,"",IFERROR(H86/D86*1000,0)) | AC86: =IF(COUNT(C86:P86)=0,"",IFERROR(J86/H86,0)) | AD86: =IF(COUNT(C86:P86)=0,"",IFERROR(C86/J86,0)) | AE86: =IF(COUNT(C86:P86)=0,"",IFERROR(K86/H86,0)) | AF86: =IF(COUNT(C86:P86)=0,"",IFERROR(L86/H86,0)) | AG86: =IF(COUNT(C86:P86)=0,"",IFERROR(C86/K86,0)) | AH86: =IF(COUNT(C86:P86)=0,"",IFERROR(M86/K86,0)) | AI86: =IF(COUNT(C86:P86)=0,"",IFERROR(C86/M86,0)) | AJ86: =IF(COUNT(C86:P86)=0,"",IFERROR(N86/M86,0)) | AK86: =IF(COUNT(C86:P86)=0,"",IFERROR(N86/H86,0)) | AL86: =IF(COUNT(C86:P86)=0,"",IFERROR(C86/N86,0)) | AM86: =IF(COUNT(C86:P86)=0,"",IFERROR(O86/N86,0)) | AN86: =IF(COUNT(C86:P86)=0,"",IFERROR(P86/N86,0)) | AO86: =IF(COUNT(C86:P86)=0,"",IFERROR(N86*Config!$C$7+O86*Config!$C$8+P86*Config!$C$9,0)) | AP86: =IF(COUNT(C86:P86)=0,"",IFERROR(AO86/N86,0)) | AQ86: =IF(COUNT(C86:P86)=0,"",IFERROR(AO86*(1-Config!$C$10-Config!$C$11-Config!$C$12),0)) | AR86: =IF(COUNT(C86:P86)=0,"",IFERROR(AQ86-C86-Config!$C$13,0)) | AS86: =IF(COUNT(C86:P86)=0,"",IFERROR(AQ86/C86,0)) | AT86: =IF(COUNT(C86:P86)=0,"",IFERROR(AR86/G86,0)) | AU86: =IF(COUNT(C86:P86)=0,"",IFERROR(AT86/V86,0)) | AV86: =IF(COUNT(C86:P86)=0,"",IFERROR(AR86/H86,0))
A87: =Config!$C$6+81 | B87: =INT((A87-Config!$C$6)/7)+1 | Q87: =IF(COUNT(C87:P87)=0,"",IFERROR(C87/D87*1000,0)) | R87: =IF(COUNT(C87:P87)=0,"",IFERROR(D87/E87,0)) | S87: =IF(COUNT(C87:P87)=0,"",IFERROR(F87/D87,0)) | T87: =IF(COUNT(C87:P87)=0,"",IFERROR(C87/F87,0)) | U87: =IF(COUNT(C87:P87)=0,"",IFERROR(G87/F87,0)) | V87: =IF(COUNT(C87:P87)=0,"",IFERROR(C87/G87,0)) | W87: =IF(COUNT(C87:P87)=0,"",IFERROR(G87/D87*1000,0)) | X87: =IF(COUNT(C87:P87)=0,"",IFERROR(H87/G87,0)) | Y87: =IF(COUNT(C87:P87)=0,"",IFERROR(C87/H87,0)) | Z87: =IF(COUNT(C87:P87)=0,"",IFERROR(C87/I87,0)) | AA87: =IF(COUNT(C87:P87)=0,"",IFERROR(Y87/Q87,0)) | AB87: =IF(COUNT(C87:P87)=0,"",IFERROR(H87/D87*1000,0)) | AC87: =IF(COUNT(C87:P87)=0,"",IFERROR(J87/H87,0)) | AD87: =IF(COUNT(C87:P87)=0,"",IFERROR(C87/J87,0)) | AE87: =IF(COUNT(C87:P87)=0,"",IFERROR(K87/H87,0)) | AF87: =IF(COUNT(C87:P87)=0,"",IFERROR(L87/H87,0)) | AG87: =IF(COUNT(C87:P87)=0,"",IFERROR(C87/K87,0)) | AH87: =IF(COUNT(C87:P87)=0,"",IFERROR(M87/K87,0)) | AI87: =IF(COUNT(C87:P87)=0,"",IFERROR(C87/M87,0)) | AJ87: =IF(COUNT(C87:P87)=0,"",IFERROR(N87/M87,0)) | AK87: =IF(COUNT(C87:P87)=0,"",IFERROR(N87/H87,0)) | AL87: =IF(COUNT(C87:P87)=0,"",IFERROR(C87/N87,0)) | AM87: =IF(COUNT(C87:P87)=0,"",IFERROR(O87/N87,0)) | AN87: =IF(COUNT(C87:P87)=0,"",IFERROR(P87/N87,0)) | AO87: =IF(COUNT(C87:P87)=0,"",IFERROR(N87*Config!$C$7+O87*Config!$C$8+P87*Config!$C$9,0)) | AP87: =IF(COUNT(C87:P87)=0,"",IFERROR(AO87/N87,0)) | AQ87: =IF(COUNT(C87:P87)=0,"",IFERROR(AO87*(1-Config!$C$10-Config!$C$11-Config!$C$12),0)) | AR87: =IF(COUNT(C87:P87)=0,"",IFERROR(AQ87-C87-Config!$C$13,0)) | AS87: =IF(COUNT(C87:P87)=0,"",IFERROR(AQ87/C87,0)) | AT87: =IF(COUNT(C87:P87)=0,"",IFERROR(AR87/G87,0)) | AU87: =IF(COUNT(C87:P87)=0,"",IFERROR(AT87/V87,0)) | AV87: =IF(COUNT(C87:P87)=0,"",IFERROR(AR87/H87,0))
A88: =Config!$C$6+82 | B88: =INT((A88-Config!$C$6)/7)+1 | Q88: =IF(COUNT(C88:P88)=0,"",IFERROR(C88/D88*1000,0)) | R88: =IF(COUNT(C88:P88)=0,"",IFERROR(D88/E88,0)) | S88: =IF(COUNT(C88:P88)=0,"",IFERROR(F88/D88,0)) | T88: =IF(COUNT(C88:P88)=0,"",IFERROR(C88/F88,0)) | U88: =IF(COUNT(C88:P88)=0,"",IFERROR(G88/F88,0)) | V88: =IF(COUNT(C88:P88)=0,"",IFERROR(C88/G88,0)) | W88: =IF(COUNT(C88:P88)=0,"",IFERROR(G88/D88*1000,0)) | X88: =IF(COUNT(C88:P88)=0,"",IFERROR(H88/G88,0)) | Y88: =IF(COUNT(C88:P88)=0,"",IFERROR(C88/H88,0)) | Z88: =IF(COUNT(C88:P88)=0,"",IFERROR(C88/I88,0)) | AA88: =IF(COUNT(C88:P88)=0,"",IFERROR(Y88/Q88,0)) | AB88: =IF(COUNT(C88:P88)=0,"",IFERROR(H88/D88*1000,0)) | AC88: =IF(COUNT(C88:P88)=0,"",IFERROR(J88/H88,0)) | AD88: =IF(COUNT(C88:P88)=0,"",IFERROR(C88/J88,0)) | AE88: =IF(COUNT(C88:P88)=0,"",IFERROR(K88/H88,0)) | AF88: =IF(COUNT(C88:P88)=0,"",IFERROR(L88/H88,0)) | AG88: =IF(COUNT(C88:P88)=0,"",IFERROR(C88/K88,0)) | AH88: =IF(COUNT(C88:P88)=0,"",IFERROR(M88/K88,0)) | AI88: =IF(COUNT(C88:P88)=0,"",IFERROR(C88/M88,0)) | AJ88: =IF(COUNT(C88:P88)=0,"",IFERROR(N88/M88,0)) | AK88: =IF(COUNT(C88:P88)=0,"",IFERROR(N88/H88,0)) | AL88: =IF(COUNT(C88:P88)=0,"",IFERROR(C88/N88,0)) | AM88: =IF(COUNT(C88:P88)=0,"",IFERROR(O88/N88,0)) | AN88: =IF(COUNT(C88:P88)=0,"",IFERROR(P88/N88,0)) | AO88: =IF(COUNT(C88:P88)=0,"",IFERROR(N88*Config!$C$7+O88*Config!$C$8+P88*Config!$C$9,0)) | AP88: =IF(COUNT(C88:P88)=0,"",IFERROR(AO88/N88,0)) | AQ88: =IF(COUNT(C88:P88)=0,"",IFERROR(AO88*(1-Config!$C$10-Config!$C$11-Config!$C$12),0)) | AR88: =IF(COUNT(C88:P88)=0,"",IFERROR(AQ88-C88-Config!$C$13,0)) | AS88: =IF(COUNT(C88:P88)=0,"",IFERROR(AQ88/C88,0)) | AT88: =IF(COUNT(C88:P88)=0,"",IFERROR(AR88/G88,0)) | AU88: =IF(COUNT(C88:P88)=0,"",IFERROR(AT88/V88,0)) | AV88: =IF(COUNT(C88:P88)=0,"",IFERROR(AR88/H88,0))
A89: =Config!$C$6+83 | B89: =INT((A89-Config!$C$6)/7)+1 | Q89: =IF(COUNT(C89:P89)=0,"",IFERROR(C89/D89*1000,0)) | R89: =IF(COUNT(C89:P89)=0,"",IFERROR(D89/E89,0)) | S89: =IF(COUNT(C89:P89)=0,"",IFERROR(F89/D89,0)) | T89: =IF(COUNT(C89:P89)=0,"",IFERROR(C89/F89,0)) | U89: =IF(COUNT(C89:P89)=0,"",IFERROR(G89/F89,0)) | V89: =IF(COUNT(C89:P89)=0,"",IFERROR(C89/G89,0)) | W89: =IF(COUNT(C89:P89)=0,"",IFERROR(G89/D89*1000,0)) | X89: =IF(COUNT(C89:P89)=0,"",IFERROR(H89/G89,0)) | Y89: =IF(COUNT(C89:P89)=0,"",IFERROR(C89/H89,0)) | Z89: =IF(COUNT(C89:P89)=0,"",IFERROR(C89/I89,0)) | AA89: =IF(COUNT(C89:P89)=0,"",IFERROR(Y89/Q89,0)) | AB89: =IF(COUNT(C89:P89)=0,"",IFERROR(H89/D89*1000,0)) | AC89: =IF(COUNT(C89:P89)=0,"",IFERROR(J89/H89,0)) | AD89: =IF(COUNT(C89:P89)=0,"",IFERROR(C89/J89,0)) | AE89: =IF(COUNT(C89:P89)=0,"",IFERROR(K89/H89,0)) | AF89: =IF(COUNT(C89:P89)=0,"",IFERROR(L89/H89,0)) | AG89: =IF(COUNT(C89:P89)=0,"",IFERROR(C89/K89,0)) | AH89: =IF(COUNT(C89:P89)=0,"",IFERROR(M89/K89,0)) | AI89: =IF(COUNT(C89:P89)=0,"",IFERROR(C89/M89,0)) | AJ89: =IF(COUNT(C89:P89)=0,"",IFERROR(N89/M89,0)) | AK89: =IF(COUNT(C89:P89)=0,"",IFERROR(N89/H89,0)) | AL89: =IF(COUNT(C89:P89)=0,"",IFERROR(C89/N89,0)) | AM89: =IF(COUNT(C89:P89)=0,"",IFERROR(O89/N89,0)) | AN89: =IF(COUNT(C89:P89)=0,"",IFERROR(P89/N89,0)) | AO89: =IF(COUNT(C89:P89)=0,"",IFERROR(N89*Config!$C$7+O89*Config!$C$8+P89*Config!$C$9,0)) | AP89: =IF(COUNT(C89:P89)=0,"",IFERROR(AO89/N89,0)) | AQ89: =IF(COUNT(C89:P89)=0,"",IFERROR(AO89*(1-Config!$C$10-Config!$C$11-Config!$C$12),0)) | AR89: =IF(COUNT(C89:P89)=0,"",IFERROR(AQ89-C89-Config!$C$13,0)) | AS89: =IF(COUNT(C89:P89)=0,"",IFERROR(AQ89/C89,0)) | AT89: =IF(COUNT(C89:P89)=0,"",IFERROR(AR89/G89,0)) | AU89: =IF(COUNT(C89:P89)=0,"",IFERROR(AT89/V89,0)) | AV89: =IF(COUNT(C89:P89)=0,"",IFERROR(AR89/H89,0))
A90: =Config!$C$6+84 | B90: =INT((A90-Config!$C$6)/7)+1 | Q90: =IF(COUNT(C90:P90)=0,"",IFERROR(C90/D90*1000,0)) | R90: =IF(COUNT(C90:P90)=0,"",IFERROR(D90/E90,0)) | S90: =IF(COUNT(C90:P90)=0,"",IFERROR(F90/D90,0)) | T90: =IF(COUNT(C90:P90)=0,"",IFERROR(C90/F90,0)) | U90: =IF(COUNT(C90:P90)=0,"",IFERROR(G90/F90,0)) | V90: =IF(COUNT(C90:P90)=0,"",IFERROR(C90/G90,0)) | W90: =IF(COUNT(C90:P90)=0,"",IFERROR(G90/D90*1000,0)) | X90: =IF(COUNT(C90:P90)=0,"",IFERROR(H90/G90,0)) | Y90: =IF(COUNT(C90:P90)=0,"",IFERROR(C90/H90,0)) | Z90: =IF(COUNT(C90:P90)=0,"",IFERROR(C90/I90,0)) | AA90: =IF(COUNT(C90:P90)=0,"",IFERROR(Y90/Q90,0)) | AB90: =IF(COUNT(C90:P90)=0,"",IFERROR(H90/D90*1000,0)) | AC90: =IF(COUNT(C90:P90)=0,"",IFERROR(J90/H90,0)) | AD90: =IF(COUNT(C90:P90)=0,"",IFERROR(C90/J90,0)) | AE90: =IF(COUNT(C90:P90)=0,"",IFERROR(K90/H90,0)) | AF90: =IF(COUNT(C90:P90)=0,"",IFERROR(L90/H90,0)) | AG90: =IF(COUNT(C90:P90)=0,"",IFERROR(C90/K90,0)) | AH90: =IF(COUNT(C90:P90)=0,"",IFERROR(M90/K90,0)) | AI90: =IF(COUNT(C90:P90)=0,"",IFERROR(C90/M90,0)) | AJ90: =IF(COUNT(C90:P90)=0,"",IFERROR(N90/M90,0)) | AK90: =IF(COUNT(C90:P90)=0,"",IFERROR(N90/H90,0)) | AL90: =IF(COUNT(C90:P90)=0,"",IFERROR(C90/N90,0)) | AM90: =IF(COUNT(C90:P90)=0,"",IFERROR(O90/N90,0)) | AN90: =IF(COUNT(C90:P90)=0,"",IFERROR(P90/N90,0)) | AO90: =IF(COUNT(C90:P90)=0,"",IFERROR(N90*Config!$C$7+O90*Config!$C$8+P90*Config!$C$9,0)) | AP90: =IF(COUNT(C90:P90)=0,"",IFERROR(AO90/N90,0)) | AQ90: =IF(COUNT(C90:P90)=0,"",IFERROR(AO90*(1-Config!$C$10-Config!$C$11-Config!$C$12),0)) | AR90: =IF(COUNT(C90:P90)=0,"",IFERROR(AQ90-C90-Config!$C$13,0)) | AS90: =IF(COUNT(C90:P90)=0,"",IFERROR(AQ90/C90,0)) | AT90: =IF(COUNT(C90:P90)=0,"",IFERROR(AR90/G90,0)) | AU90: =IF(COUNT(C90:P90)=0,"",IFERROR(AT90/V90,0)) | AV90: =IF(COUNT(C90:P90)=0,"",IFERROR(AR90/H90,0))
A91: =Config!$C$6+85 | B91: =INT((A91-Config!$C$6)/7)+1 | Q91: =IF(COUNT(C91:P91)=0,"",IFERROR(C91/D91*1000,0)) | R91: =IF(COUNT(C91:P91)=0,"",IFERROR(D91/E91,0)) | S91: =IF(COUNT(C91:P91)=0,"",IFERROR(F91/D91,0)) | T91: =IF(COUNT(C91:P91)=0,"",IFERROR(C91/F91,0)) | U91: =IF(COUNT(C91:P91)=0,"",IFERROR(G91/F91,0)) | V91: =IF(COUNT(C91:P91)=0,"",IFERROR(C91/G91,0)) | W91: =IF(COUNT(C91:P91)=0,"",IFERROR(G91/D91*1000,0)) | X91: =IF(COUNT(C91:P91)=0,"",IFERROR(H91/G91,0)) | Y91: =IF(COUNT(C91:P91)=0,"",IFERROR(C91/H91,0)) | Z91: =IF(COUNT(C91:P91)=0,"",IFERROR(C91/I91,0)) | AA91: =IF(COUNT(C91:P91)=0,"",IFERROR(Y91/Q91,0)) | AB91: =IF(COUNT(C91:P91)=0,"",IFERROR(H91/D91*1000,0)) | AC91: =IF(COUNT(C91:P91)=0,"",IFERROR(J91/H91,0)) | AD91: =IF(COUNT(C91:P91)=0,"",IFERROR(C91/J91,0)) | AE91: =IF(COUNT(C91:P91)=0,"",IFERROR(K91/H91,0)) | AF91: =IF(COUNT(C91:P91)=0,"",IFERROR(L91/H91,0)) | AG91: =IF(COUNT(C91:P91)=0,"",IFERROR(C91/K91,0)) | AH91: =IF(COUNT(C91:P91)=0,"",IFERROR(M91/K91,0)) | AI91: =IF(COUNT(C91:P91)=0,"",IFERROR(C91/M91,0)) | AJ91: =IF(COUNT(C91:P91)=0,"",IFERROR(N91/M91,0)) | AK91: =IF(COUNT(C91:P91)=0,"",IFERROR(N91/H91,0)) | AL91: =IF(COUNT(C91:P91)=0,"",IFERROR(C91/N91,0)) | AM91: =IF(COUNT(C91:P91)=0,"",IFERROR(O91/N91,0)) | AN91: =IF(COUNT(C91:P91)=0,"",IFERROR(P91/N91,0)) | AO91: =IF(COUNT(C91:P91)=0,"",IFERROR(N91*Config!$C$7+O91*Config!$C$8+P91*Config!$C$9,0)) | AP91: =IF(COUNT(C91:P91)=0,"",IFERROR(AO91/N91,0)) | AQ91: =IF(COUNT(C91:P91)=0,"",IFERROR(AO91*(1-Config!$C$10-Config!$C$11-Config!$C$12),0)) | AR91: =IF(COUNT(C91:P91)=0,"",IFERROR(AQ91-C91-Config!$C$13,0)) | AS91: =IF(COUNT(C91:P91)=0,"",IFERROR(AQ91/C91,0)) | AT91: =IF(COUNT(C91:P91)=0,"",IFERROR(AR91/G91,0)) | AU91: =IF(COUNT(C91:P91)=0,"",IFERROR(AT91/V91,0)) | AV91: =IF(COUNT(C91:P91)=0,"",IFERROR(AR91/H91,0))
A92: =Config!$C$6+86 | B92: =INT((A92-Config!$C$6)/7)+1 | Q92: =IF(COUNT(C92:P92)=0,"",IFERROR(C92/D92*1000,0)) | R92: =IF(COUNT(C92:P92)=0,"",IFERROR(D92/E92,0)) | S92: =IF(COUNT(C92:P92)=0,"",IFERROR(F92/D92,0)) | T92: =IF(COUNT(C92:P92)=0,"",IFERROR(C92/F92,0)) | U92: =IF(COUNT(C92:P92)=0,"",IFERROR(G92/F92,0)) | V92: =IF(COUNT(C92:P92)=0,"",IFERROR(C92/G92,0)) | W92: =IF(COUNT(C92:P92)=0,"",IFERROR(G92/D92*1000,0)) | X92: =IF(COUNT(C92:P92)=0,"",IFERROR(H92/G92,0)) | Y92: =IF(COUNT(C92:P92)=0,"",IFERROR(C92/H92,0)) | Z92: =IF(COUNT(C92:P92)=0,"",IFERROR(C92/I92,0)) | AA92: =IF(COUNT(C92:P92)=0,"",IFERROR(Y92/Q92,0)) | AB92: =IF(COUNT(C92:P92)=0,"",IFERROR(H92/D92*1000,0)) | AC92: =IF(COUNT(C92:P92)=0,"",IFERROR(J92/H92,0)) | AD92: =IF(COUNT(C92:P92)=0,"",IFERROR(C92/J92,0)) | AE92: =IF(COUNT(C92:P92)=0,"",IFERROR(K92/H92,0)) | AF92: =IF(COUNT(C92:P92)=0,"",IFERROR(L92/H92,0)) | AG92: =IF(COUNT(C92:P92)=0,"",IFERROR(C92/K92,0)) | AH92: =IF(COUNT(C92:P92)=0,"",IFERROR(M92/K92,0)) | AI92: =IF(COUNT(C92:P92)=0,"",IFERROR(C92/M92,0)) | AJ92: =IF(COUNT(C92:P92)=0,"",IFERROR(N92/M92,0)) | AK92: =IF(COUNT(C92:P92)=0,"",IFERROR(N92/H92,0)) | AL92: =IF(COUNT(C92:P92)=0,"",IFERROR(C92/N92,0)) | AM92: =IF(COUNT(C92:P92)=0,"",IFERROR(O92/N92,0)) | AN92: =IF(COUNT(C92:P92)=0,"",IFERROR(P92/N92,0)) | AO92: =IF(COUNT(C92:P92)=0,"",IFERROR(N92*Config!$C$7+O92*Config!$C$8+P92*Config!$C$9,0)) | AP92: =IF(COUNT(C92:P92)=0,"",IFERROR(AO92/N92,0)) | AQ92: =IF(COUNT(C92:P92)=0,"",IFERROR(AO92*(1-Config!$C$10-Config!$C$11-Config!$C$12),0)) | AR92: =IF(COUNT(C92:P92)=0,"",IFERROR(AQ92-C92-Config!$C$13,0)) | AS92: =IF(COUNT(C92:P92)=0,"",IFERROR(AQ92/C92,0)) | AT92: =IF(COUNT(C92:P92)=0,"",IFERROR(AR92/G92,0)) | AU92: =IF(COUNT(C92:P92)=0,"",IFERROR(AT92/V92,0)) | AV92: =IF(COUNT(C92:P92)=0,"",IFERROR(AR92/H92,0))
A93: =Config!$C$6+87 | B93: =INT((A93-Config!$C$6)/7)+1 | Q93: =IF(COUNT(C93:P93)=0,"",IFERROR(C93/D93*1000,0)) | R93: =IF(COUNT(C93:P93)=0,"",IFERROR(D93/E93,0)) | S93: =IF(COUNT(C93:P93)=0,"",IFERROR(F93/D93,0)) | T93: =IF(COUNT(C93:P93)=0,"",IFERROR(C93/F93,0)) | U93: =IF(COUNT(C93:P93)=0,"",IFERROR(G93/F93,0)) | V93: =IF(COUNT(C93:P93)=0,"",IFERROR(C93/G93,0)) | W93: =IF(COUNT(C93:P93)=0,"",IFERROR(G93/D93*1000,0)) | X93: =IF(COUNT(C93:P93)=0,"",IFERROR(H93/G93,0)) | Y93: =IF(COUNT(C93:P93)=0,"",IFERROR(C93/H93,0)) | Z93: =IF(COUNT(C93:P93)=0,"",IFERROR(C93/I93,0)) | AA93: =IF(COUNT(C93:P93)=0,"",IFERROR(Y93/Q93,0)) | AB93: =IF(COUNT(C93:P93)=0,"",IFERROR(H93/D93*1000,0)) | AC93: =IF(COUNT(C93:P93)=0,"",IFERROR(J93/H93,0)) | AD93: =IF(COUNT(C93:P93)=0,"",IFERROR(C93/J93,0)) | AE93: =IF(COUNT(C93:P93)=0,"",IFERROR(K93/H93,0)) | AF93: =IF(COUNT(C93:P93)=0,"",IFERROR(L93/H93,0)) | AG93: =IF(COUNT(C93:P93)=0,"",IFERROR(C93/K93,0)) | AH93: =IF(COUNT(C93:P93)=0,"",IFERROR(M93/K93,0)) | AI93: =IF(COUNT(C93:P93)=0,"",IFERROR(C93/M93,0)) | AJ93: =IF(COUNT(C93:P93)=0,"",IFERROR(N93/M93,0)) | AK93: =IF(COUNT(C93:P93)=0,"",IFERROR(N93/H93,0)) | AL93: =IF(COUNT(C93:P93)=0,"",IFERROR(C93/N93,0)) | AM93: =IF(COUNT(C93:P93)=0,"",IFERROR(O93/N93,0)) | AN93: =IF(COUNT(C93:P93)=0,"",IFERROR(P93/N93,0)) | AO93: =IF(COUNT(C93:P93)=0,"",IFERROR(N93*Config!$C$7+O93*Config!$C$8+P93*Config!$C$9,0)) | AP93: =IF(COUNT(C93:P93)=0,"",IFERROR(AO93/N93,0)) | AQ93: =IF(COUNT(C93:P93)=0,"",IFERROR(AO93*(1-Config!$C$10-Config!$C$11-Config!$C$12),0)) | AR93: =IF(COUNT(C93:P93)=0,"",IFERROR(AQ93-C93-Config!$C$13,0)) | AS93: =IF(COUNT(C93:P93)=0,"",IFERROR(AQ93/C93,0)) | AT93: =IF(COUNT(C93:P93)=0,"",IFERROR(AR93/G93,0)) | AU93: =IF(COUNT(C93:P93)=0,"",IFERROR(AT93/V93,0)) | AV93: =IF(COUNT(C93:P93)=0,"",IFERROR(AR93/H93,0))
A94: =Config!$C$6+88 | B94: =INT((A94-Config!$C$6)/7)+1 | Q94: =IF(COUNT(C94:P94)=0,"",IFERROR(C94/D94*1000,0)) | R94: =IF(COUNT(C94:P94)=0,"",IFERROR(D94/E94,0)) | S94: =IF(COUNT(C94:P94)=0,"",IFERROR(F94/D94,0)) | T94: =IF(COUNT(C94:P94)=0,"",IFERROR(C94/F94,0)) | U94: =IF(COUNT(C94:P94)=0,"",IFERROR(G94/F94,0)) | V94: =IF(COUNT(C94:P94)=0,"",IFERROR(C94/G94,0)) | W94: =IF(COUNT(C94:P94)=0,"",IFERROR(G94/D94*1000,0)) | X94: =IF(COUNT(C94:P94)=0,"",IFERROR(H94/G94,0)) | Y94: =IF(COUNT(C94:P94)=0,"",IFERROR(C94/H94,0)) | Z94: =IF(COUNT(C94:P94)=0,"",IFERROR(C94/I94,0)) | AA94: =IF(COUNT(C94:P94)=0,"",IFERROR(Y94/Q94,0)) | AB94: =IF(COUNT(C94:P94)=0,"",IFERROR(H94/D94*1000,0)) | AC94: =IF(COUNT(C94:P94)=0,"",IFERROR(J94/H94,0)) | AD94: =IF(COUNT(C94:P94)=0,"",IFERROR(C94/J94,0)) | AE94: =IF(COUNT(C94:P94)=0,"",IFERROR(K94/H94,0)) | AF94: =IF(COUNT(C94:P94)=0,"",IFERROR(L94/H94,0)) | AG94: =IF(COUNT(C94:P94)=0,"",IFERROR(C94/K94,0)) | AH94: =IF(COUNT(C94:P94)=0,"",IFERROR(M94/K94,0)) | AI94: =IF(COUNT(C94:P94)=0,"",IFERROR(C94/M94,0)) | AJ94: =IF(COUNT(C94:P94)=0,"",IFERROR(N94/M94,0)) | AK94: =IF(COUNT(C94:P94)=0,"",IFERROR(N94/H94,0)) | AL94: =IF(COUNT(C94:P94)=0,"",IFERROR(C94/N94,0)) | AM94: =IF(COUNT(C94:P94)=0,"",IFERROR(O94/N94,0)) | AN94: =IF(COUNT(C94:P94)=0,"",IFERROR(P94/N94,0)) | AO94: =IF(COUNT(C94:P94)=0,"",IFERROR(N94*Config!$C$7+O94*Config!$C$8+P94*Config!$C$9,0)) | AP94: =IF(COUNT(C94:P94)=0,"",IFERROR(AO94/N94,0)) | AQ94: =IF(COUNT(C94:P94)=0,"",IFERROR(AO94*(1-Config!$C$10-Config!$C$11-Config!$C$12),0)) | AR94: =IF(COUNT(C94:P94)=0,"",IFERROR(AQ94-C94-Config!$C$13,0)) | AS94: =IF(COUNT(C94:P94)=0,"",IFERROR(AQ94/C94,0)) | AT94: =IF(COUNT(C94:P94)=0,"",IFERROR(AR94/G94,0)) | AU94: =IF(COUNT(C94:P94)=0,"",IFERROR(AT94/V94,0)) | AV94: =IF(COUNT(C94:P94)=0,"",IFERROR(AR94/H94,0))
A95: =Config!$C$6+89 | B95: =INT((A95-Config!$C$6)/7)+1 | Q95: =IF(COUNT(C95:P95)=0,"",IFERROR(C95/D95*1000,0)) | R95: =IF(COUNT(C95:P95)=0,"",IFERROR(D95/E95,0)) | S95: =IF(COUNT(C95:P95)=0,"",IFERROR(F95/D95,0)) | T95: =IF(COUNT(C95:P95)=0,"",IFERROR(C95/F95,0)) | U95: =IF(COUNT(C95:P95)=0,"",IFERROR(G95/F95,0)) | V95: =IF(COUNT(C95:P95)=0,"",IFERROR(C95/G95,0)) | W95: =IF(COUNT(C95:P95)=0,"",IFERROR(G95/D95*1000,0)) | X95: =IF(COUNT(C95:P95)=0,"",IFERROR(H95/G95,0)) | Y95: =IF(COUNT(C95:P95)=0,"",IFERROR(C95/H95,0)) | Z95: =IF(COUNT(C95:P95)=0,"",IFERROR(C95/I95,0)) | AA95: =IF(COUNT(C95:P95)=0,"",IFERROR(Y95/Q95,0)) | AB95: =IF(COUNT(C95:P95)=0,"",IFERROR(H95/D95*1000,0)) | AC95: =IF(COUNT(C95:P95)=0,"",IFERROR(J95/H95,0)) | AD95: =IF(COUNT(C95:P95)=0,"",IFERROR(C95/J95,0)) | AE95: =IF(COUNT(C95:P95)=0,"",IFERROR(K95/H95,0)) | AF95: =IF(COUNT(C95:P95)=0,"",IFERROR(L95/H95,0)) | AG95: =IF(COUNT(C95:P95)=0,"",IFERROR(C95/K95,0)) | AH95: =IF(COUNT(C95:P95)=0,"",IFERROR(M95/K95,0)) | AI95: =IF(COUNT(C95:P95)=0,"",IFERROR(C95/M95,0)) | AJ95: =IF(COUNT(C95:P95)=0,"",IFERROR(N95/M95,0)) | AK95: =IF(COUNT(C95:P95)=0,"",IFERROR(N95/H95,0)) | AL95: =IF(COUNT(C95:P95)=0,"",IFERROR(C95/N95,0)) | AM95: =IF(COUNT(C95:P95)=0,"",IFERROR(O95/N95,0)) | AN95: =IF(COUNT(C95:P95)=0,"",IFERROR(P95/N95,0)) | AO95: =IF(COUNT(C95:P95)=0,"",IFERROR(N95*Config!$C$7+O95*Config!$C$8+P95*Config!$C$9,0)) | AP95: =IF(COUNT(C95:P95)=0,"",IFERROR(AO95/N95,0)) | AQ95: =IF(COUNT(C95:P95)=0,"",IFERROR(AO95*(1-Config!$C$10-Config!$C$11-Config!$C$12),0)) | AR95: =IF(COUNT(C95:P95)=0,"",IFERROR(AQ95-C95-Config!$C$13,0)) | AS95: =IF(COUNT(C95:P95)=0,"",IFERROR(AQ95/C95,0)) | AT95: =IF(COUNT(C95:P95)=0,"",IFERROR(AR95/G95,0)) | AU95: =IF(COUNT(C95:P95)=0,"",IFERROR(AT95/V95,0)) | AV95: =IF(COUNT(C95:P95)=0,"",IFERROR(AR95/H95,0))
A96: =Config!$C$6+90 | B96: =INT((A96-Config!$C$6)/7)+1 | Q96: =IF(COUNT(C96:P96)=0,"",IFERROR(C96/D96*1000,0)) | R96: =IF(COUNT(C96:P96)=0,"",IFERROR(D96/E96,0)) | S96: =IF(COUNT(C96:P96)=0,"",IFERROR(F96/D96,0)) | T96: =IF(COUNT(C96:P96)=0,"",IFERROR(C96/F96,0)) | U96: =IF(COUNT(C96:P96)=0,"",IFERROR(G96/F96,0)) | V96: =IF(COUNT(C96:P96)=0,"",IFERROR(C96/G96,0)) | W96: =IF(COUNT(C96:P96)=0,"",IFERROR(G96/D96*1000,0)) | X96: =IF(COUNT(C96:P96)=0,"",IFERROR(H96/G96,0)) | Y96: =IF(COUNT(C96:P96)=0,"",IFERROR(C96/H96,0)) | Z96: =IF(COUNT(C96:P96)=0,"",IFERROR(C96/I96,0)) | AA96: =IF(COUNT(C96:P96)=0,"",IFERROR(Y96/Q96,0)) | AB96: =IF(COUNT(C96:P96)=0,"",IFERROR(H96/D96*1000,0)) | AC96: =IF(COUNT(C96:P96)=0,"",IFERROR(J96/H96,0)) | AD96: =IF(COUNT(C96:P96)=0,"",IFERROR(C96/J96,0)) | AE96: =IF(COUNT(C96:P96)=0,"",IFERROR(K96/H96,0)) | AF96: =IF(COUNT(C96:P96)=0,"",IFERROR(L96/H96,0)) | AG96: =IF(COUNT(C96:P96)=0,"",IFERROR(C96/K96,0)) | AH96: =IF(COUNT(C96:P96)=0,"",IFERROR(M96/K96,0)) | AI96: =IF(COUNT(C96:P96)=0,"",IFERROR(C96/M96,0)) | AJ96: =IF(COUNT(C96:P96)=0,"",IFERROR(N96/M96,0)) | AK96: =IF(COUNT(C96:P96)=0,"",IFERROR(N96/H96,0)) | AL96: =IF(COUNT(C96:P96)=0,"",IFERROR(C96/N96,0)) | AM96: =IF(COUNT(C96:P96)=0,"",IFERROR(O96/N96,0)) | AN96: =IF(COUNT(C96:P96)=0,"",IFERROR(P96/N96,0)) | AO96: =IF(COUNT(C96:P96)=0,"",IFERROR(N96*Config!$C$7+O96*Config!$C$8+P96*Config!$C$9,0)) | AP96: =IF(COUNT(C96:P96)=0,"",IFERROR(AO96/N96,0)) | AQ96: =IF(COUNT(C96:P96)=0,"",IFERROR(AO96*(1-Config!$C$10-Config!$C$11-Config!$C$12),0)) | AR96: =IF(COUNT(C96:P96)=0,"",IFERROR(AQ96-C96-Config!$C$13,0)) | AS96: =IF(COUNT(C96:P96)=0,"",IFERROR(AQ96/C96,0)) | AT96: =IF(COUNT(C96:P96)=0,"",IFERROR(AR96/G96,0)) | AU96: =IF(COUNT(C96:P96)=0,"",IFERROR(AT96/V96,0)) | AV96: =IF(COUNT(C96:P96)=0,"",IFERROR(AR96/H96,0))
A97: =Config!$C$6+91 | B97: =INT((A97-Config!$C$6)/7)+1 | Q97: =IF(COUNT(C97:P97)=0,"",IFERROR(C97/D97*1000,0)) | R97: =IF(COUNT(C97:P97)=0,"",IFERROR(D97/E97,0)) | S97: =IF(COUNT(C97:P97)=0,"",IFERROR(F97/D97,0)) | T97: =IF(COUNT(C97:P97)=0,"",IFERROR(C97/F97,0)) | U97: =IF(COUNT(C97:P97)=0,"",IFERROR(G97/F97,0)) | V97: =IF(COUNT(C97:P97)=0,"",IFERROR(C97/G97,0)) | W97: =IF(COUNT(C97:P97)=0,"",IFERROR(G97/D97*1000,0)) | X97: =IF(COUNT(C97:P97)=0,"",IFERROR(H97/G97,0)) | Y97: =IF(COUNT(C97:P97)=0,"",IFERROR(C97/H97,0)) | Z97: =IF(COUNT(C97:P97)=0,"",IFERROR(C97/I97,0)) | AA97: =IF(COUNT(C97:P97)=0,"",IFERROR(Y97/Q97,0)) | AB97: =IF(COUNT(C97:P97)=0,"",IFERROR(H97/D97*1000,0)) | AC97: =IF(COUNT(C97:P97)=0,"",IFERROR(J97/H97,0)) | AD97: =IF(COUNT(C97:P97)=0,"",IFERROR(C97/J97,0)) | AE97: =IF(COUNT(C97:P97)=0,"",IFERROR(K97/H97,0)) | AF97: =IF(COUNT(C97:P97)=0,"",IFERROR(L97/H97,0)) | AG97: =IF(COUNT(C97:P97)=0,"",IFERROR(C97/K97,0)) | AH97: =IF(COUNT(C97:P97)=0,"",IFERROR(M97/K97,0)) | AI97: =IF(COUNT(C97:P97)=0,"",IFERROR(C97/M97,0)) | AJ97: =IF(COUNT(C97:P97)=0,"",IFERROR(N97/M97,0)) | AK97: =IF(COUNT(C97:P97)=0,"",IFERROR(N97/H97,0)) | AL97: =IF(COUNT(C97:P97)=0,"",IFERROR(C97/N97,0)) | AM97: =IF(COUNT(C97:P97)=0,"",IFERROR(O97/N97,0)) | AN97: =IF(COUNT(C97:P97)=0,"",IFERROR(P97/N97,0)) | AO97: =IF(COUNT(C97:P97)=0,"",IFERROR(N97*Config!$C$7+O97*Config!$C$8+P97*Config!$C$9,0)) | AP97: =IF(COUNT(C97:P97)=0,"",IFERROR(AO97/N97,0)) | AQ97: =IF(COUNT(C97:P97)=0,"",IFERROR(AO97*(1-Config!$C$10-Config!$C$11-Config!$C$12),0)) | AR97: =IF(COUNT(C97:P97)=0,"",IFERROR(AQ97-C97-Config!$C$13,0)) | AS97: =IF(COUNT(C97:P97)=0,"",IFERROR(AQ97/C97,0)) | AT97: =IF(COUNT(C97:P97)=0,"",IFERROR(AR97/G97,0)) | AU97: =IF(COUNT(C97:P97)=0,"",IFERROR(AT97/V97,0)) | AV97: =IF(COUNT(C97:P97)=0,"",IFERROR(AR97/H97,0))
A98: =Config!$C$6+92 | B98: =INT((A98-Config!$C$6)/7)+1 | Q98: =IF(COUNT(C98:P98)=0,"",IFERROR(C98/D98*1000,0)) | R98: =IF(COUNT(C98:P98)=0,"",IFERROR(D98/E98,0)) | S98: =IF(COUNT(C98:P98)=0,"",IFERROR(F98/D98,0)) | T98: =IF(COUNT(C98:P98)=0,"",IFERROR(C98/F98,0)) | U98: =IF(COUNT(C98:P98)=0,"",IFERROR(G98/F98,0)) | V98: =IF(COUNT(C98:P98)=0,"",IFERROR(C98/G98,0)) | W98: =IF(COUNT(C98:P98)=0,"",IFERROR(G98/D98*1000,0)) | X98: =IF(COUNT(C98:P98)=0,"",IFERROR(H98/G98,0)) | Y98: =IF(COUNT(C98:P98)=0,"",IFERROR(C98/H98,0)) | Z98: =IF(COUNT(C98:P98)=0,"",IFERROR(C98/I98,0)) | AA98: =IF(COUNT(C98:P98)=0,"",IFERROR(Y98/Q98,0)) | AB98: =IF(COUNT(C98:P98)=0,"",IFERROR(H98/D98*1000,0)) | AC98: =IF(COUNT(C98:P98)=0,"",IFERROR(J98/H98,0)) | AD98: =IF(COUNT(C98:P98)=0,"",IFERROR(C98/J98,0)) | AE98: =IF(COUNT(C98:P98)=0,"",IFERROR(K98/H98,0)) | AF98: =IF(COUNT(C98:P98)=0,"",IFERROR(L98/H98,0)) | AG98: =IF(COUNT(C98:P98)=0,"",IFERROR(C98/K98,0)) | AH98: =IF(COUNT(C98:P98)=0,"",IFERROR(M98/K98,0)) | AI98: =IF(COUNT(C98:P98)=0,"",IFERROR(C98/M98,0)) | AJ98: =IF(COUNT(C98:P98)=0,"",IFERROR(N98/M98,0)) | AK98: =IF(COUNT(C98:P98)=0,"",IFERROR(N98/H98,0)) | AL98: =IF(COUNT(C98:P98)=0,"",IFERROR(C98/N98,0)) | AM98: =IF(COUNT(C98:P98)=0,"",IFERROR(O98/N98,0)) | AN98: =IF(COUNT(C98:P98)=0,"",IFERROR(P98/N98,0)) | AO98: =IF(COUNT(C98:P98)=0,"",IFERROR(N98*Config!$C$7+O98*Config!$C$8+P98*Config!$C$9,0)) | AP98: =IF(COUNT(C98:P98)=0,"",IFERROR(AO98/N98,0)) | AQ98: =IF(COUNT(C98:P98)=0,"",IFERROR(AO98*(1-Config!$C$10-Config!$C$11-Config!$C$12),0)) | AR98: =IF(COUNT(C98:P98)=0,"",IFERROR(AQ98-C98-Config!$C$13,0)) | AS98: =IF(COUNT(C98:P98)=0,"",IFERROR(AQ98/C98,0)) | AT98: =IF(COUNT(C98:P98)=0,"",IFERROR(AR98/G98,0)) | AU98: =IF(COUNT(C98:P98)=0,"",IFERROR(AT98/V98,0)) | AV98: =IF(COUNT(C98:P98)=0,"",IFERROR(AR98/H98,0))
A99: =Config!$C$6+93 | B99: =INT((A99-Config!$C$6)/7)+1 | Q99: =IF(COUNT(C99:P99)=0,"",IFERROR(C99/D99*1000,0)) | R99: =IF(COUNT(C99:P99)=0,"",IFERROR(D99/E99,0)) | S99: =IF(COUNT(C99:P99)=0,"",IFERROR(F99/D99,0)) | T99: =IF(COUNT(C99:P99)=0,"",IFERROR(C99/F99,0)) | U99: =IF(COUNT(C99:P99)=0,"",IFERROR(G99/F99,0)) | V99: =IF(COUNT(C99:P99)=0,"",IFERROR(C99/G99,0)) | W99: =IF(COUNT(C99:P99)=0,"",IFERROR(G99/D99*1000,0)) | X99: =IF(COUNT(C99:P99)=0,"",IFERROR(H99/G99,0)) | Y99: =IF(COUNT(C99:P99)=0,"",IFERROR(C99/H99,0)) | Z99: =IF(COUNT(C99:P99)=0,"",IFERROR(C99/I99,0)) | AA99: =IF(COUNT(C99:P99)=0,"",IFERROR(Y99/Q99,0)) | AB99: =IF(COUNT(C99:P99)=0,"",IFERROR(H99/D99*1000,0)) | AC99: =IF(COUNT(C99:P99)=0,"",IFERROR(J99/H99,0)) | AD99: =IF(COUNT(C99:P99)=0,"",IFERROR(C99/J99,0)) | AE99: =IF(COUNT(C99:P99)=0,"",IFERROR(K99/H99,0)) | AF99: =IF(COUNT(C99:P99)=0,"",IFERROR(L99/H99,0)) | AG99: =IF(COUNT(C99:P99)=0,"",IFERROR(C99/K99,0)) | AH99: =IF(COUNT(C99:P99)=0,"",IFERROR(M99/K99,0)) | AI99: =IF(COUNT(C99:P99)=0,"",IFERROR(C99/M99,0)) | AJ99: =IF(COUNT(C99:P99)=0,"",IFERROR(N99/M99,0)) | AK99: =IF(COUNT(C99:P99)=0,"",IFERROR(N99/H99,0)) | AL99: =IF(COUNT(C99:P99)=0,"",IFERROR(C99/N99,0)) | AM99: =IF(COUNT(C99:P99)=0,"",IFERROR(O99/N99,0)) | AN99: =IF(COUNT(C99:P99)=0,"",IFERROR(P99/N99,0)) | AO99: =IF(COUNT(C99:P99)=0,"",IFERROR(N99*Config!$C$7+O99*Config!$C$8+P99*Config!$C$9,0)) | AP99: =IF(COUNT(C99:P99)=0,"",IFERROR(AO99/N99,0)) | AQ99: =IF(COUNT(C99:P99)=0,"",IFERROR(AO99*(1-Config!$C$10-Config!$C$11-Config!$C$12),0)) | AR99: =IF(COUNT(C99:P99)=0,"",IFERROR(AQ99-C99-Config!$C$13,0)) | AS99: =IF(COUNT(C99:P99)=0,"",IFERROR(AQ99/C99,0)) | AT99: =IF(COUNT(C99:P99)=0,"",IFERROR(AR99/G99,0)) | AU99: =IF(COUNT(C99:P99)=0,"",IFERROR(AT99/V99,0)) | AV99: =IF(COUNT(C99:P99)=0,"",IFERROR(AR99/H99,0))
A100: =Config!$C$6+94 | B100: =INT((A100-Config!$C$6)/7)+1 | Q100: =IF(COUNT(C100:P100)=0,"",IFERROR(C100/D100*1000,0)) | R100: =IF(COUNT(C100:P100)=0,"",IFERROR(D100/E100,0)) | S100: =IF(COUNT(C100:P100)=0,"",IFERROR(F100/D100,0)) | T100: =IF(COUNT(C100:P100)=0,"",IFERROR(C100/F100,0)) | U100: =IF(COUNT(C100:P100)=0,"",IFERROR(G100/F100,0)) | V100: =IF(COUNT(C100:P100)=0,"",IFERROR(C100/G100,0)) | W100: =IF(COUNT(C100:P100)=0,"",IFERROR(G100/D100*1000,0)) | X100: =IF(COUNT(C100:P100)=0,"",IFERROR(H100/G100,0)) | Y100: =IF(COUNT(C100:P100)=0,"",IFERROR(C100/H100,0)) | Z100: =IF(COUNT(C100:P100)=0,"",IFERROR(C100/I100,0)) | AA100: =IF(COUNT(C100:P100)=0,"",IFERROR(Y100/Q100,0)) | AB100: =IF(COUNT(C100:P100)=0,"",IFERROR(H100/D100*1000,0)) | AC100: =IF(COUNT(C100:P100)=0,"",IFERROR(J100/H100,0)) | AD100: =IF(COUNT(C100:P100)=0,"",IFERROR(C100/J100,0)) | AE100: =IF(COUNT(C100:P100)=0,"",IFERROR(K100/H100,0)) | AF100: =IF(COUNT(C100:P100)=0,"",IFERROR(L100/H100,0)) | AG100: =IF(COUNT(C100:P100)=0,"",IFERROR(C100/K100,0)) | AH100: =IF(COUNT(C100:P100)=0,"",IFERROR(M100/K100,0)) | AI100: =IF(COUNT(C100:P100)=0,"",IFERROR(C100/M100,0)) | AJ100: =IF(COUNT(C100:P100)=0,"",IFERROR(N100/M100,0)) | AK100: =IF(COUNT(C100:P100)=0,"",IFERROR(N100/H100,0)) | AL100: =IF(COUNT(C100:P100)=0,"",IFERROR(C100/N100,0)) | AM100: =IF(COUNT(C100:P100)=0,"",IFERROR(O100/N100,0)) | AN100: =IF(COUNT(C100:P100)=0,"",IFERROR(P100/N100,0)) | AO100: =IF(COUNT(C100:P100)=0,"",IFERROR(N100*Config!$C$7+O100*Config!$C$8+P100*Config!$C$9,0)) | AP100: =IF(COUNT(C100:P100)=0,"",IFERROR(AO100/N100,0)) | AQ100: =IF(COUNT(C100:P100)=0,"",IFERROR(AO100*(1-Config!$C$10-Config!$C$11-Config!$C$12),0)) | AR100: =IF(COUNT(C100:P100)=0,"",IFERROR(AQ100-C100-Config!$C$13,0)) | AS100: =IF(COUNT(C100:P100)=0,"",IFERROR(AQ100/C100,0)) | AT100: =IF(COUNT(C100:P100)=0,"",IFERROR(AR100/G100,0)) | AU100: =IF(COUNT(C100:P100)=0,"",IFERROR(AT100/V100,0)) | AV100: =IF(COUNT(C100:P100)=0,"",IFERROR(AR100/H100,0))
A101: =Config!$C$6+95 | B101: =INT((A101-Config!$C$6)/7)+1 | Q101: =IF(COUNT(C101:P101)=0,"",IFERROR(C101/D101*1000,0)) | R101: =IF(COUNT(C101:P101)=0,"",IFERROR(D101/E101,0)) | S101: =IF(COUNT(C101:P101)=0,"",IFERROR(F101/D101,0)) | T101: =IF(COUNT(C101:P101)=0,"",IFERROR(C101/F101,0)) | U101: =IF(COUNT(C101:P101)=0,"",IFERROR(G101/F101,0)) | V101: =IF(COUNT(C101:P101)=0,"",IFERROR(C101/G101,0)) | W101: =IF(COUNT(C101:P101)=0,"",IFERROR(G101/D101*1000,0)) | X101: =IF(COUNT(C101:P101)=0,"",IFERROR(H101/G101,0)) | Y101: =IF(COUNT(C101:P101)=0,"",IFERROR(C101/H101,0)) | Z101: =IF(COUNT(C101:P101)=0,"",IFERROR(C101/I101,0)) | AA101: =IF(COUNT(C101:P101)=0,"",IFERROR(Y101/Q101,0)) | AB101: =IF(COUNT(C101:P101)=0,"",IFERROR(H101/D101*1000,0)) | AC101: =IF(COUNT(C101:P101)=0,"",IFERROR(J101/H101,0)) | AD101: =IF(COUNT(C101:P101)=0,"",IFERROR(C101/J101,0)) | AE101: =IF(COUNT(C101:P101)=0,"",IFERROR(K101/H101,0)) | AF101: =IF(COUNT(C101:P101)=0,"",IFERROR(L101/H101,0)) | AG101: =IF(COUNT(C101:P101)=0,"",IFERROR(C101/K101,0)) | AH101: =IF(COUNT(C101:P101)=0,"",IFERROR(M101/K101,0)) | AI101: =IF(COUNT(C101:P101)=0,"",IFERROR(C101/M101,0)) | AJ101: =IF(COUNT(C101:P101)=0,"",IFERROR(N101/M101,0)) | AK101: =IF(COUNT(C101:P101)=0,"",IFERROR(N101/H101,0)) | AL101: =IF(COUNT(C101:P101)=0,"",IFERROR(C101/N101,0)) | AM101: =IF(COUNT(C101:P101)=0,"",IFERROR(O101/N101,0)) | AN101: =IF(COUNT(C101:P101)=0,"",IFERROR(P101/N101,0)) | AO101: =IF(COUNT(C101:P101)=0,"",IFERROR(N101*Config!$C$7+O101*Config!$C$8+P101*Config!$C$9,0)) | AP101: =IF(COUNT(C101:P101)=0,"",IFERROR(AO101/N101,0)) | AQ101: =IF(COUNT(C101:P101)=0,"",IFERROR(AO101*(1-Config!$C$10-Config!$C$11-Config!$C$12),0)) | AR101: =IF(COUNT(C101:P101)=0,"",IFERROR(AQ101-C101-Config!$C$13,0)) | AS101: =IF(COUNT(C101:P101)=0,"",IFERROR(AQ101/C101,0)) | AT101: =IF(COUNT(C101:P101)=0,"",IFERROR(AR101/G101,0)) | AU101: =IF(COUNT(C101:P101)=0,"",IFERROR(AT101/V101,0)) | AV101: =IF(COUNT(C101:P101)=0,"",IFERROR(AR101/H101,0))
A102: =Config!$C$6+96 | B102: =INT((A102-Config!$C$6)/7)+1 | Q102: =IF(COUNT(C102:P102)=0,"",IFERROR(C102/D102*1000,0)) | R102: =IF(COUNT(C102:P102)=0,"",IFERROR(D102/E102,0)) | S102: =IF(COUNT(C102:P102)=0,"",IFERROR(F102/D102,0)) | T102: =IF(COUNT(C102:P102)=0,"",IFERROR(C102/F102,0)) | U102: =IF(COUNT(C102:P102)=0,"",IFERROR(G102/F102,0)) | V102: =IF(COUNT(C102:P102)=0,"",IFERROR(C102/G102,0)) | W102: =IF(COUNT(C102:P102)=0,"",IFERROR(G102/D102*1000,0)) | X102: =IF(COUNT(C102:P102)=0,"",IFERROR(H102/G102,0)) | Y102: =IF(COUNT(C102:P102)=0,"",IFERROR(C102/H102,0)) | Z102: =IF(COUNT(C102:P102)=0,"",IFERROR(C102/I102,0)) | AA102: =IF(COUNT(C102:P102)=0,"",IFERROR(Y102/Q102,0)) | AB102: =IF(COUNT(C102:P102)=0,"",IFERROR(H102/D102*1000,0)) | AC102: =IF(COUNT(C102:P102)=0,"",IFERROR(J102/H102,0)) | AD102: =IF(COUNT(C102:P102)=0,"",IFERROR(C102/J102,0)) | AE102: =IF(COUNT(C102:P102)=0,"",IFERROR(K102/H102,0)) | AF102: =IF(COUNT(C102:P102)=0,"",IFERROR(L102/H102,0)) | AG102: =IF(COUNT(C102:P102)=0,"",IFERROR(C102/K102,0)) | AH102: =IF(COUNT(C102:P102)=0,"",IFERROR(M102/K102,0)) | AI102: =IF(COUNT(C102:P102)=0,"",IFERROR(C102/M102,0)) | AJ102: =IF(COUNT(C102:P102)=0,"",IFERROR(N102/M102,0)) | AK102: =IF(COUNT(C102:P102)=0,"",IFERROR(N102/H102,0)) | AL102: =IF(COUNT(C102:P102)=0,"",IFERROR(C102/N102,0)) | AM102: =IF(COUNT(C102:P102)=0,"",IFERROR(O102/N102,0)) | AN102: =IF(COUNT(C102:P102)=0,"",IFERROR(P102/N102,0)) | AO102: =IF(COUNT(C102:P102)=0,"",IFERROR(N102*Config!$C$7+O102*Config!$C$8+P102*Config!$C$9,0)) | AP102: =IF(COUNT(C102:P102)=0,"",IFERROR(AO102/N102,0)) | AQ102: =IF(COUNT(C102:P102)=0,"",IFERROR(AO102*(1-Config!$C$10-Config!$C$11-Config!$C$12),0)) | AR102: =IF(COUNT(C102:P102)=0,"",IFERROR(AQ102-C102-Config!$C$13,0)) | AS102: =IF(COUNT(C102:P102)=0,"",IFERROR(AQ102/C102,0)) | AT102: =IF(COUNT(C102:P102)=0,"",IFERROR(AR102/G102,0)) | AU102: =IF(COUNT(C102:P102)=0,"",IFERROR(AT102/V102,0)) | AV102: =IF(COUNT(C102:P102)=0,"",IFERROR(AR102/H102,0))
...

Sheet Semanal
A2: Semanal: el comparativo semana a semana, calculado solo desde Diario
A3: Promedio, mediana, mejor y peor de tus semanas con datos. Abajo, el bloque «contra tu promedio»: cada semana contra la mediana de tus 4 semanas anteriores, con la tolerancia de Config. Ese es el umbral: tu promedio, no un número de mercado.
B4: Lunes de la semana | C4: =Config!$C$6+0 | D4: =Config!$C$6+7 | E4: =Config!$C$6+14 | F4: =Config!$C$6+21 | G4: =Config!$C$6+28 | H4: =Config!$C$6+35 | I4: =Config!$C$6+42 | J4: =Config!$C$6+49 | K4: =Config!$C$6+56 | L4: =Config!$C$6+63 | M4: =Config!$C$6+70 | N4: =Config!$C$6+77 | O4: =Config!$C$6+84 | P4: =Config!$C$6+91 | Q4: =Config!$C$6+98 | R4: =Config!$C$6+105 | S4: =Config!$C$6+112 | T4: =Config!$C$6+119 | U4: =Config!$C$6+126 | V4: =Config!$C$6+133 | W4: =Config!$C$6+140 | X4: =Config!$C$6+147 | Y4: =Config!$C$6+154 | Z4: =Config!$C$6+161 | AA4: =Config!$C$6+168 | AB4: =Config!$C$6+175
A5: Categoría | B5: Métrica | C5: 1 | D5: 2 | E5: 3 | F5: 4 | G5: 5 | H5: 6 | I5: 7 | J5: 8 | K5: 9 | L5: 10 | M5: 11 | N5: 12 | O5: 13 | P5: 14 | Q5: 15 | R5: 16 | S5: 17 | T5: 18 | U5: 19 | V5: 20 | W5: 21 | X5: 22 | Y5: 23 | Z5: 24 | AA5: 25 | AB5: 26 | AC5: Promedio | AD5: Mediana | AE5: Mejor | AF5: Peor
A6: Semana con datos (1 = sí) | C6: =IF(SUMIFS(Diario!$C$6:$C$371,Diario!$B$6:$B$371,C$5)+SUMIFS(Diario!$H$6:$H$371,Diario!$B$6:$B$371,C$5)>0,1,0) | D6: =IF(SUMIFS(Diario!$C$6:$C$371,Diario!$B$6:$B$371,D$5)+SUMIFS(Diario!$H$6:$H$371,Diario!$B$6:$B$371,D$5)>0,1,0) | E6: =IF(SUMIFS(Diario!$C$6:$C$371,Diario!$B$6:$B$371,E$5)+SUMIFS(Diario!$H$6:$H$371,Diario!$B$6:$B$371,E$5)>0,1,0) | F6: =IF(SUMIFS(Diario!$C$6:$C$371,Diario!$B$6:$B$371,F$5)+SUMIFS(Diario!$H$6:$H$371,Diario!$B$6:$B$371,F$5)>0,1,0) | G6: =IF(SUMIFS(Diario!$C$6:$C$371,Diario!$B$6:$B$371,G$5)+SUMIFS(Diario!$H$6:$H$371,Diario!$B$6:$B$371,G$5)>0,1,0) | H6: =IF(SUMIFS(Diario!$C$6:$C$371,Diario!$B$6:$B$371,H$5)+SUMIFS(Diario!$H$6:$H$371,Diario!$B$6:$B$371,H$5)>0,1,0) | I6: =IF(SUMIFS(Diario!$C$6:$C$371,Diario!$B$6:$B$371,I$5)+SUMIFS(Diario!$H$6:$H$371,Diario!$B$6:$B$371,I$5)>0,1,0) | J6: =IF(SUMIFS(Diario!$C$6:$C$371,Diario!$B$6:$B$371,J$5)+SUMIFS(Diario!$H$6:$H$371,Diario!$B$6:$B$371,J$5)>0,1,0) | ... AB6: =IF(SUMIFS(Diario!$C$6:$C$371,Diario!$B$6:$B$371,AB$5)+SUMIFS(Diario!$H$6:$H$371,Diario!$B$6:$B$371,AB$5)>0,1,0)
A7: Número de semana si tiene datos | C7: =IF(C6=1,C$5,0) | D7: =IF(D6=1,D$5,0) | E7: =IF(E6=1,E$5,0) | F7: =IF(F6=1,F$5,0) | G7: =IF(G6=1,G$5,0) | H7: =IF(H6=1,H$5,0) | I7: =IF(I6=1,I$5,0) | J7: =IF(J6=1,J$5,0) | ... AB7: =IF(AB6=1,AB$5,0)
A9: 1. Anuncios
A10: Anuncios | B10: Inversión en publicidad (USD) | C10: =IF(C6=0,"",SUMIFS(Diario!$C$6:$C$371,Diario!$B$6:$B$371,C$5)) | D10: =IF(D6=0,"",SUMIFS(Diario!$C$6:$C$371,Diario!$B$6:$B$371,D$5)) | E10: =IF(E6=0,"",SUMIFS(Diario!$C$6:$C$371,Diario!$B$6:$B$371,E$5)) | F10: =IF(F6=0,"",SUMIFS(Diario!$C$6:$C$371,Diario!$B$6:$B$371,F$5)) | G10: =IF(G6=0,"",SUMIFS(Diario!$C$6:$C$371,Diario!$B$6:$B$371,G$5)) | H10: =IF(H6=0,"",SUMIFS(Diario!$C$6:$C$371,Diario!$B$6:$B$371,H$5)) | I10: =IF(I6=0,"",SUMIFS(Diario!$C$6:$C$371,Diario!$B$6:$B$371,I$5)) | J10: =IF(J6=0,"",SUMIFS(Diario!$C$6:$C$371,Diario!$B$6:$B$371,J$5)) | ... AB10: =IF(AB6=0,"",SUMIFS(Diario!$C$6:$C$371,Diario!$B$6:$B$371,AB$5)) | AC10: =IFERROR(AVERAGE(C10:AB10),"") | AD10: =IFERROR(MEDIAN(C10:AB10),"") | AE10: =IFERROR(MAX(C10:AB10),"") | AF10: =IFERROR(MIN(C10:AB10),"")
A11: Anuncios | B11: Impresiones | C11: =IF(C6=0,"",SUMIFS(Diario!$D$6:$D$371,Diario!$B$6:$B$371,C$5)) | D11: =IF(D6=0,"",SUMIFS(Diario!$D$6:$D$371,Diario!$B$6:$B$371,D$5)) | E11: =IF(E6=0,"",SUMIFS(Diario!$D$6:$D$371,Diario!$B$6:$B$371,E$5)) | F11: =IF(F6=0,"",SUMIFS(Diario!$D$6:$D$371,Diario!$B$6:$B$371,F$5)) | G11: =IF(G6=0,"",SUMIFS(Diario!$D$6:$D$371,Diario!$B$6:$B$371,G$5)) | H11: =IF(H6=0,"",SUMIFS(Diario!$D$6:$D$371,Diario!$B$6:$B$371,H$5)) | I11: =IF(I6=0,"",SUMIFS(Diario!$D$6:$D$371,Diario!$B$6:$B$371,I$5)) | J11: =IF(J6=0,"",SUMIFS(Diario!$D$6:$D$371,Diario!$B$6:$B$371,J$5)) | ... AB11: =IF(AB6=0,"",SUMIFS(Diario!$D$6:$D$371,Diario!$B$6:$B$371,AB$5)) | AC11: =IFERROR(AVERAGE(C11:AB11),"") | AD11: =IFERROR(MEDIAN(C11:AB11),"") | AE11: =IFERROR(MAX(C11:AB11),"") | AF11: =IFERROR(MIN(C11:AB11),"")
A12: Anuncios | B12: Alcance (personas únicas) | C12: =IF(C6=0,"",SUMIFS(Diario!$E$6:$E$371,Diario!$B$6:$B$371,C$5)) | D12: =IF(D6=0,"",SUMIFS(Diario!$E$6:$E$371,Diario!$B$6:$B$371,D$5)) | E12: =IF(E6=0,"",SUMIFS(Diario!$E$6:$E$371,Diario!$B$6:$B$371,E$5)) | F12: =IF(F6=0,"",SUMIFS(Diario!$E$6:$E$371,Diario!$B$6:$B$371,F$5)) | G12: =IF(G6=0,"",SUMIFS(Diario!$E$6:$E$371,Diario!$B$6:$B$371,G$5)) | H12: =IF(H6=0,"",SUMIFS(Diario!$E$6:$E$371,Diario!$B$6:$B$371,H$5)) | I12: =IF(I6=0,"",SUMIFS(Diario!$E$6:$E$371,Diario!$B$6:$B$371,I$5)) | J12: =IF(J6=0,"",SUMIFS(Diario!$E$6:$E$371,Diario!$B$6:$B$371,J$5)) | ... AB12: =IF(AB6=0,"",SUMIFS(Diario!$E$6:$E$371,Diario!$B$6:$B$371,AB$5)) | AC12: =IFERROR(AVERAGE(C12:AB12),"") | AD12: =IFERROR(MEDIAN(C12:AB12),"") | AE12: =IFERROR(MAX(C12:AB12),"") | AF12: =IFERROR(MIN(C12:AB12),"")
A13: Anuncios | B13: Clics en el enlace | C13: =IF(C6=0,"",SUMIFS(Diario!$F$6:$F$371,Diario!$B$6:$B$371,C$5)) | D13: =IF(D6=0,"",SUMIFS(Diario!$F$6:$F$371,Diario!$B$6:$B$371,D$5)) | E13: =IF(E6=0,"",SUMIFS(Diario!$F$6:$F$371,Diario!$B$6:$B$371,E$5)) | F13: =IF(F6=0,"",SUMIFS(Diario!$F$6:$F$371,Diario!$B$6:$B$371,F$5)) | G13: =IF(G6=0,"",SUMIFS(Diario!$F$6:$F$371,Diario!$B$6:$B$371,G$5)) | H13: =IF(H6=0,"",SUMIFS(Diario!$F$6:$F$371,Diario!$B$6:$B$371,H$5)) | I13: =IF(I6=0,"",SUMIFS(Diario!$F$6:$F$371,Diario!$B$6:$B$371,I$5)) | J13: =IF(J6=0,"",SUMIFS(Diario!$F$6:$F$371,Diario!$B$6:$B$371,J$5)) | ... AB13: =IF(AB6=0,"",SUMIFS(Diario!$F$6:$F$371,Diario!$B$6:$B$371,AB$5)) | AC13: =IFERROR(AVERAGE(C13:AB13),"") | AD13: =IFERROR(MEDIAN(C13:AB13),"") | AE13: =IFERROR(MAX(C13:AB13),"") | AF13: =IFERROR(MIN(C13:AB13),"")
A14: Anuncios | B14: Visitas a la página | C14: =IF(C6=0,"",SUMIFS(Diario!$G$6:$G$371,Diario!$B$6:$B$371,C$5)) | D14: =IF(D6=0,"",SUMIFS(Diario!$G$6:$G$371,Diario!$B$6:$B$371,D$5)) | E14: =IF(E6=0,"",SUMIFS(Diario!$G$6:$G$371,Diario!$B$6:$B$371,E$5)) | F14: =IF(F6=0,"",SUMIFS(Diario!$G$6:$G$371,Diario!$B$6:$B$371,F$5)) | G14: =IF(G6=0,"",SUMIFS(Diario!$G$6:$G$371,Diario!$B$6:$B$371,G$5)) | H14: =IF(H6=0,"",SUMIFS(Diario!$G$6:$G$371,Diario!$B$6:$B$371,H$5)) | I14: =IF(I6=0,"",SUMIFS(Diario!$G$6:$G$371,Diario!$B$6:$B$371,I$5)) | J14: =IF(J6=0,"",SUMIFS(Diario!$G$6:$G$371,Diario!$B$6:$B$371,J$5)) | ... AB14: =IF(AB6=0,"",SUMIFS(Diario!$G$6:$G$371,Diario!$B$6:$B$371,AB$5)) | AC14: =IFERROR(AVERAGE(C14:AB14),"") | AD14: =IFERROR(MEDIAN(C14:AB14),"") | AE14: =IFERROR(MAX(C14:AB14),"") | AF14: =IFERROR(MIN(C14:AB14),"")
A15: Anuncios | B15: CPM | C15: =IF(C6=0,"",IFERROR(C10/C11*1000,0)) | D15: =IF(D6=0,"",IFERROR(D10/D11*1000,0)) | E15: =IF(E6=0,"",IFERROR(E10/E11*1000,0)) | F15: =IF(F6=0,"",IFERROR(F10/F11*1000,0)) | G15: =IF(G6=0,"",IFERROR(G10/G11*1000,0)) | H15: =IF(H6=0,"",IFERROR(H10/H11*1000,0)) | I15: =IF(I6=0,"",IFERROR(I10/I11*1000,0)) | J15: =IF(J6=0,"",IFERROR(J10/J11*1000,0)) | ... AB15: =IF(AB6=0,"",IFERROR(AB10/AB11*1000,0)) | AC15: =IFERROR(AVERAGE(C15:AB15),"") | AD15: =IFERROR(MEDIAN(C15:AB15),"") | AE15: =IFERROR(MIN(C15:AB15),"") | AF15: =IFERROR(MAX(C15:AB15),"")
A16: Anuncios | B16: Frecuencia | C16: =IF(C6=0,"",IFERROR(C11/C12,0)) | D16: =IF(D6=0,"",IFERROR(D11/D12,0)) | E16: =IF(E6=0,"",IFERROR(E11/E12,0)) | F16: =IF(F6=0,"",IFERROR(F11/F12,0)) | G16: =IF(G6=0,"",IFERROR(G11/G12,0)) | H16: =IF(H6=0,"",IFERROR(H11/H12,0)) | I16: =IF(I6=0,"",IFERROR(I11/I12,0)) | J16: =IF(J6=0,"",IFERROR(J11/J12,0)) | ... AB16: =IF(AB6=0,"",IFERROR(AB11/AB12,0)) | AC16: =IFERROR(AVERAGE(C16:AB16),"") | AD16: =IFERROR(MEDIAN(C16:AB16),"") | AE16: =IFERROR(MIN(C16:AB16),"") | AF16: =IFERROR(MAX(C16:AB16),"")
A17: Anuncios | B17: CTR al enlace | C17: =IF(C6=0,"",IFERROR(C13/C11,0)) | D17: =IF(D6=0,"",IFERROR(D13/D11,0)) | E17: =IF(E6=0,"",IFERROR(E13/E11,0)) | F17: =IF(F6=0,"",IFERROR(F13/F11,0)) | G17: =IF(G6=0,"",IFERROR(G13/G11,0)) | H17: =IF(H6=0,"",IFERROR(H13/H11,0)) | I17: =IF(I6=0,"",IFERROR(I13/I11,0)) | J17: =IF(J6=0,"",IFERROR(J13/J11,0)) | ... AB17: =IF(AB6=0,"",IFERROR(AB13/AB11,0)) | AC17: =IFERROR(AVERAGE(C17:AB17),"") | AD17: =IFERROR(MEDIAN(C17:AB17),"") | AE17: =IFERROR(MAX(C17:AB17),"") | AF17: =IFERROR(MIN(C17:AB17),"")
A18: Anuncios | B18: CPC (por clic en el enlace) | C18: =IF(C6=0,"",IFERROR(C10/C13,0)) | D18: =IF(D6=0,"",IFERROR(D10/D13,0)) | E18: =IF(E6=0,"",IFERROR(E10/E13,0)) | F18: =IF(F6=0,"",IFERROR(F10/F13,0)) | G18: =IF(G6=0,"",IFERROR(G10/G13,0)) | H18: =IF(H6=0,"",IFERROR(H10/H13,0)) | I18: =IF(I6=0,"",IFERROR(I10/I13,0)) | J18: =IF(J6=0,"",IFERROR(J10/J13,0)) | ... AB18: =IF(AB6=0,"",IFERROR(AB10/AB13,0)) | AC18: =IFERROR(AVERAGE(C18:AB18),"") | AD18: =IFERROR(MEDIAN(C18:AB18),"") | AE18: =IFERROR(MIN(C18:AB18),"") | AF18: =IFERROR(MAX(C18:AB18),"")
A19: Anuncios | B19: % clic → visita | C19: =IF(C6=0,"",IFERROR(C14/C13,0)) | D19: =IF(D6=0,"",IFERROR(D14/D13,0)) | E19: =IF(E6=0,"",IFERROR(E14/E13,0)) | F19: =IF(F6=0,"",IFERROR(F14/F13,0)) | G19: =IF(G6=0,"",IFERROR(G14/G13,0)) | H19: =IF(H6=0,"",IFERROR(H14/H13,0)) | I19: =IF(I6=0,"",IFERROR(I14/I13,0)) | J19: =IF(J6=0,"",IFERROR(J14/J13,0)) | ... AB19: =IF(AB6=0,"",IFERROR(AB14/AB13,0)) | AC19: =IFERROR(AVERAGE(C19:AB19),"") | AD19: =IFERROR(MEDIAN(C19:AB19),"") | AE19: =IFERROR(MAX(C19:AB19),"") | AF19: =IFERROR(MIN(C19:AB19),"")
A20: Anuncios | B20: Costo por visita | C20: =IF(C6=0,"",IFERROR(C10/C14,0)) | D20: =IF(D6=0,"",IFERROR(D10/D14,0)) | E20: =IF(E6=0,"",IFERROR(E10/E14,0)) | F20: =IF(F6=0,"",IFERROR(F10/F14,0)) | G20: =IF(G6=0,"",IFERROR(G10/G14,0)) | H20: =IF(H6=0,"",IFERROR(H10/H14,0)) | I20: =IF(I6=0,"",IFERROR(I10/I14,0)) | J20: =IF(J6=0,"",IFERROR(J10/J14,0)) | ... AB20: =IF(AB6=0,"",IFERROR(AB10/AB14,0)) | AC20: =IFERROR(AVERAGE(C20:AB20),"") | AD20: =IFERROR(MEDIAN(C20:AB20),"") | AE20: =IFERROR(MIN(C20:AB20),"") | AF20: =IFERROR(MAX(C20:AB20),"")
A21: Anuncios | B21: Visitas por cada 1.000 impresiones | C21: =IF(C6=0,"",IFERROR(C14/C11*1000,0)) | D21: =IF(D6=0,"",IFERROR(D14/D11*1000,0)) | E21: =IF(E6=0,"",IFERROR(E14/E11*1000,0)) | F21: =IF(F6=0,"",IFERROR(F14/F11*1000,0)) | G21: =IF(G6=0,"",IFERROR(G14/G11*1000,0)) | H21: =IF(H6=0,"",IFERROR(H14/H11*1000,0)) | I21: =IF(I6=0,"",IFERROR(I14/I11*1000,0)) | J21: =IF(J6=0,"",IFERROR(J14/J11*1000,0)) | ... AB21: =IF(AB6=0,"",IFERROR(AB14/AB11*1000,0)) | AC21: =IFERROR(AVERAGE(C21:AB21),"") | AD21: =IFERROR(MEDIAN(C21:AB21),"") | AE21: =IFERROR(MAX(C21:AB21),"") | AF21: =IFERROR(MIN(C21:AB21),"")
A23: 2. Landing y registros
A24: Landing y registros | B24: Registros (leads) | C24: =IF(C6=0,"",SUMIFS(Diario!$H$6:$H$371,Diario!$B$6:$B$371,C$5)) | D24: =IF(D6=0,"",SUMIFS(Diario!$H$6:$H$371,Diario!$B$6:$B$371,D$5)) | E24: =IF(E6=0,"",SUMIFS(Diario!$H$6:$H$371,Diario!$B$6:$B$371,E$5)) | F24: =IF(F6=0,"",SUMIFS(Diario!$H$6:$H$371,Diario!$B$6:$B$371,F$5)) | G24: =IF(G6=0,"",SUMIFS(Diario!$H$6:$H$371,Diario!$B$6:$B$371,G$5)) | H24: =IF(H6=0,"",SUMIFS(Diario!$H$6:$H$371,Diario!$B$6:$B$371,H$5)) | I24: =IF(I6=0,"",SUMIFS(Diario!$H$6:$H$371,Diario!$B$6:$B$371,I$5)) | J24: =IF(J6=0,"",SUMIFS(Diario!$H$6:$H$371,Diario!$B$6:$B$371,J$5)) | ... AB24: =IF(AB6=0,"",SUMIFS(Diario!$H$6:$H$371,Diario!$B$6:$B$371,AB$5)) | AC24: =IFERROR(AVERAGE(C24:AB24),"") | AD24: =IFERROR(MEDIAN(C24:AB24),"") | AE24: =IFERROR(MAX(C24:AB24),"") | AF24: =IFERROR(MIN(C24:AB24),"")
A25: Landing y registros | B25: Registros calificados | C25: =IF(C6=0,"",SUMIFS(Diario!$I$6:$I$371,Diario!$B$6:$B$371,C$5)) | D25: =IF(D6=0,"",SUMIFS(Diario!$I$6:$I$371,Diario!$B$6:$B$371,D$5)) | E25: =IF(E6=0,"",SUMIFS(Diario!$I$6:$I$371,Diario!$B$6:$B$371,E$5)) | F25: =IF(F6=0,"",SUMIFS(Diario!$I$6:$I$371,Diario!$B$6:$B$371,F$5)) | G25: =IF(G6=0,"",SUMIFS(Diario!$I$6:$I$371,Diario!$B$6:$B$371,G$5)) | H25: =IF(H6=0,"",SUMIFS(Diario!$I$6:$I$371,Diario!$B$6:$B$371,H$5)) | I25: =IF(I6=0,"",SUMIFS(Diario!$I$6:$I$371,Diario!$B$6:$B$371,I$5)) | J25: =IF(J6=0,"",SUMIFS(Diario!$I$6:$I$371,Diario!$B$6:$B$371,J$5)) | ... AB25: =IF(AB6=0,"",SUMIFS(Diario!$I$6:$I$371,Diario!$B$6:$B$371,AB$5)) | AC25: =IFERROR(AVERAGE(C25:AB25),"") | AD25: =IFERROR(MEDIAN(C25:AB25),"") | AE25: =IFERROR(MAX(C25:AB25),"") | AF25: =IFERROR(MIN(C25:AB25),"")
A26: Landing y registros | B26: % visita → registro (conversión de la landing) | C26: =IF(C6=0,"",IFERROR(C24/C14,0)) | D26: =IF(D6=0,"",IFERROR(D24/D14,0)) | E26: =IF(E6=0,"",IFERROR(E24/E14,0)) | F26: =IF(F6=0,"",IFERROR(F24/F14,0)) | G26: =IF(G6=0,"",IFERROR(G24/G14,0)) | H26: =IF(H6=0,"",IFERROR(H24/H14,0)) | I26: =IF(I6=0,"",IFERROR(I24/I14,0)) | J26: =IF(J6=0,"",IFERROR(J24/J14,0)) | ... AB26: =IF(AB6=0,"",IFERROR(AB24/AB14,0)) | AC26: =IFERROR(AVERAGE(C26:AB26),"") | AD26: =IFERROR(MEDIAN(C26:AB26),"") | AE26: =IFERROR(MAX(C26:AB26),"") | AF26: =IFERROR(MIN(C26:AB26),"")
A27: Landing y registros | B27: CPL (costo por registro) | C27: =IF(C6=0,"",IFERROR(C10/C24,0)) | D27: =IF(D6=0,"",IFERROR(D10/D24,0)) | E27: =IF(E6=0,"",IFERROR(E10/E24,0)) | F27: =IF(F6=0,"",IFERROR(F10/F24,0)) | G27: =IF(G6=0,"",IFERROR(G10/G24,0)) | H27: =IF(H6=0,"",IFERROR(H10/H24,0)) | I27: =IF(I6=0,"",IFERROR(I10/I24,0)) | J27: =IF(J6=0,"",IFERROR(J10/J24,0)) | ... AB27: =IF(AB6=0,"",IFERROR(AB10/AB24,0)) | AC27: =IFERROR(AVERAGE(C27:AB27),"") | AD27: =IFERROR(MEDIAN(C27:AB27),"") | AE27: =IFERROR(MIN(C27:AB27),"") | AF27: =IFERROR(MAX(C27:AB27),"")
A28: Landing y registros | B28: CPL calificado | C28: =IF(C6=0,"",IFERROR(C10/C25,0)) | D28: =IF(D6=0,"",IFERROR(D10/D25,0)) | E28: =IF(E6=0,"",IFERROR(E10/E25,0)) | F28: =IF(F6=0,"",IFERROR(F10/F25,0)) | G28: =IF(G6=0,"",IFERROR(G10/G25,0)) | H28: =IF(H6=0,"",IFERROR(H10/H25,0)) | I28: =IF(I6=0,"",IFERROR(I10/I25,0)) | J28: =IF(J6=0,"",IFERROR(J10/J25,0)) | ... AB28: =IF(AB6=0,"",IFERROR(AB10/AB25,0)) | AC28: =IFERROR(AVERAGE(C28:AB28),"") | AD28: =IFERROR(MEDIAN(C28:AB28),"") | AE28: =IFERROR(MIN(C28:AB28),"") | AF28: =IFERROR(MAX(C28:AB28),"")
A29: Landing y registros | B29: CPL como % del CPM (el umbral depende del nicho) | C29: =IF(C6=0,"",IFERROR(C27/C15,0)) | D29: =IF(D6=0,"",IFERROR(D27/D15,0)) | E29: =IF(E6=0,"",IFERROR(E27/E15,0)) | F29: =IF(F6=0,"",IFERROR(F27/F15,0)) | G29: =IF(G6=0,"",IFERROR(G27/G15,0)) | H29: =IF(H6=0,"",IFERROR(H27/H15,0)) | I29: =IF(I6=0,"",IFERROR(I27/I15,0)) | J29: =IF(J6=0,"",IFERROR(J27/J15,0)) | ... AB29: =IF(AB6=0,"",IFERROR(AB27/AB15,0)) | AC29: =IFERROR(AVERAGE(C29:AB29),"") | AD29: =IFERROR(MEDIAN(C29:AB29),"") | AE29: =IFERROR(MIN(C29:AB29),"") | AF29: =IFERROR(MAX(C29:AB29),"")
