Workbook
Name Autor_Jesus_Tassarolo: "Modelo financiero de embudos · creado por Jesús Tassarolo · TooAudience · youtube.com/@JesusTassaroloSinFiltro"

Sheet Inicio
B1: © Jesús Tassarolo · TooAudience · youtube.com/@JesusTassaroloSinFiltro · uso personal; no redistribuir modificado
B2: Métricas diarias · Embudo de llamada (high ticket)
B3: Las métricas diarias de todo el embudo, para saber cómo estás con tus propios números. Acompaña al modelo financiero del mismo embudo.
B5: Qué es
B6: Un registro diario de cada paso del embudo (anuncios, página, unidades, etapas, ventas, cash) que se convierte solo en un comparativo semanal y en un resumen con semáforo. El semáforo no usa números de mercado: compara cada semana con la mediana de tus 4 semanas anteriores, con una tolerancia del 25 % (la cambiás en Config).
B8: 1. Config
B9: Poné tus precios, comisiones, reembolsos, costos fijos por día y la fecha de inicio (un lunes). Todo lo demás se calcula con eso.
B11: 2. Diario (todos los días, 3 minutos)
B12: Una fila por día. Cargá las celdas amarillas con lo que hubo: inversión, impresiones, alcance, clics en el enlace, visitas y cada paso del embudo. Si un día no hubo evento, dejá vacío. Las celdas azules se calculan solas (CPM, CTR, costo por visita, CPL, conversiones, facturado, cash neto, ganancia, ROAS y la ganancia por visita).
B14: 3. Semanal (los lunes, 10 minutos)
B15: No se carga nada: suma Diario por semana y calcula las conversiones y los costos de la semana, el promedio, la mediana, la mejor y la peor. Abajo, el bloque «contra tu promedio» marca en verde, amarillo o rojo cada métrica clave contra la mediana de tus 4 semanas anteriores.
B17: 4. Resumen
... B36: Modelo financiero de embudos · creado por Jesús Tassarolo · TooAudience · youtube.com/@JesusTassaroloSinFiltro · v1.2 · octubre 2026

Sheet Config
B1: © Jesús Tassarolo · TooAudience · youtube.com/@JesusTassaroloSinFiltro · uso personal; no redistribuir modificado
B2: Config: tus precios, comisiones y la fecha de inicio
B3: Amarillo = podés cambiarlo. Todo lo demás del libro se calcula con esto.
B5: Dato | C5: Valor | D5: Nota
B6: Fecha de inicio del registro (un lunes) | C6: 46272 | D6: Desde este día se numeran las semanas en Diario y Semanal. Elegí un lunes.
B7: Precio del programa (ticket) | C7: 1500 | D7: A precio de lista; las cuotas van en el cash cobrado.
B8: Precio del downsell | C8: 497
B9: % del facturado que entra el primer mes (si no cargás el cash cobrado) | C9: 0.6 | D9: Se usa solo cuando la columna de cash cobrado está vacía.
B10: Comisión de la pasarela de pago | C10: 0.05
B11: Comisión del equipo de ventas | C11: 0.1 | D11: Sobre lo cobrado.
B12: Reembolsos y contracargos | C12: 0.05
B13: Costos fijos por día (USD) | C13: 83 | D13: 2.500 por mes ÷ 30.
B14: ROAS objetivo sobre cash neto | C14: 2.5 | D14: En llamada, 2,5 a 3 por la varianza.
B15: Tolerancia del semáforo contra tu promedio | C15: 0.25 | D15: Igual o mejor que tu mediana = verde; hasta esta distancia peor = amarillo; más = rojo. 20 a 30 %.
A18: Modelo financiero de embudos · creado por Jesús Tassarolo · TooAudience · youtube.com/@JesusTassaroloSinFiltro · v1.2 · octubre 2026

Sheet Diario
A1: © Jesús Tassarolo · TooAudience · youtube.com/@JesusTassaroloSinFiltro · uso personal; no redistribuir modificado
A2: Diario: una fila por día. Amarillo = lo que cargás; azul = lo que calcula el libro
A3: Cargá cada día lo que hubo (vacío si no hubo). Los porcentajes de un solo día pueden ser raros en embudos con evento semanal: la lectura buena está en Semanal.
A5: Fecha | B5: Semana | C5: Inversión en publicidad (USD) | D5: Impresiones | E5: Alcance (personas únicas) | F5: Clics en el enlace | G5: Visitas a la página | H5: Leads | I5: Completan la aplicación | J5: Califican | K5: Agendan la llamada | L5: Llamadas realizadas (show) | M5: Compran el programa | N5: Toman el downsell | O5: Cash cobrado ese día (USD) | P5: CPM | Q5: Frecuencia | R5: CTR al enlace | S5: CPC (por clic en el enlace) | T5: % clic → visita | U5: Costo por visita | V5: Visitas por cada 1.000 impresiones | W5: % visita → lead (conversión de la página) | X5: CPL (costo por lead) | Y5: CPL como % del CPM (el umbral depende del nicho) | Z5: Leads por cada 1.000 impresiones | AA5: % lead → aplicación | AB5: % aplicación → calificado | AC5: % calificado → agenda | AD5: Costo por agenda | AE5: % agenda → llamada (show) | AF5: % llamada → venta (cierre) | AG5: % lead → venta | AH5: CAC (costo por venta) | AI5: Facturado a precio de lista | AJ5: Cash cobrado (real, o estimado con el % del primer mes) | AK5: Cash neto (después de comisiones, closers y reembolsos) | AL5: Ganancia de caja (cash neto − pauta − fijos) | AM5: ROAS sobre cash neto | AN5: ROAS sobre facturado (no decidas con este) | AO5: Ganancia por visita (la métrica más valiosa) | AP5: Margen por visita (ganancia por visita ÷ costo por visita) | AQ5: Ganancia por lead
A6: =Config!$C$6+0 | B6: =INT((A6-Config!$C$6)/7)+1 | C6: 148 | D6: 14619 | E6: 9477 | F6: 217 | G6: 185 | H6: 53 | I6: 4 | J6: 3 | K6: 2 | L6: 1 | M6: 0 | N6: 0 | O6: 0 | P6: =IF(COUNT(C6:O6)=0,"",IFERROR(C6/D6*1000,0)) | Q6: =IF(COUNT(C6:O6)=0,"",IFERROR(D6/E6,0)) | R6: =IF(COUNT(C6:O6)=0,"",IFERROR(F6/D6,0)) | S6: =IF(COUNT(C6:O6)=0,"",IFERROR(C6/F6,0)) | T6: =IF(COUNT(C6:O6)=0,"",IFERROR(G6/F6,0)) | U6: =IF(COUNT(C6:O6)=0,"",IFERROR(C6/G6,0)) | V6: =IF(COUNT(C6:O6)=0,"",IFERROR(G6/D6*1000,0)) | W6: =IF(COUNT(C6:O6)=0,"",IFERROR(H6/G6,0)) | X6: =IF(COUNT(C6:O6)=0,"",IFERROR(C6/H6,0)) | Y6: =IF(COUNT(C6:O6)=0,"",IFERROR(X6/P6,0)) | Z6: =IF(COUNT(C6:O6)=0,"",IFERROR(H6/D6*1000,0)) | AA6: =IF(COUNT(C6:O6)=0,"",IFERROR(I6/H6,0)) | AB6: =IF(COUNT(C6:O6)=0,"",IFERROR(J6/I6,0)) | AC6: =IF(COUNT(C6:O6)=0,"",IFERROR(K6/J6,0)) | AD6: =IF(COUNT(C6:O6)=0,"",IFERROR(C6/K6,0)) | AE6: =IF(COUNT(C6:O6)=0,"",IFERROR(L6/K6,0)) | AF6: =IF(COUNT(C6:O6)=0,"",IFERROR(M6/L6,0)) | AG6: =IF(COUNT(C6:O6)=0,"",IFERROR(M6/H6,0)) | AH6: =IF(COUNT(C6:O6)=0,"",IFERROR(C6/M6,0)) | AI6: =IF(COUNT(C6:O6)=0,"",IFERROR(M6*Config!$C$7+N6*Config!$C$8,0)) | AJ6: =IF(COUNT(C6:O6)=0,"",IFERROR(IF(O6>0,O6,AI6*Config!$C$9),0)) | AK6: =IF(COUNT(C6:O6)=0,"",IFERROR(AJ6*(1-Config!$C$10-Config!$C$11-Config!$C$12),0)) | AL6: =IF(COUNT(C6:O6)=0,"",IFERROR(AK6-C6-Config!$C$13,0)) | AM6: =IF(COUNT(C6:O6)=0,"",IFERROR(AK6/C6,0)) | AN6: =IF(COUNT(C6:O6)=0,"",IFERROR(AI6/C6,0)) | AO6: =IF(COUNT(C6:O6)=0,"",IFERROR(AL6/G6,0)) | AP6: =IF(COUNT(C6:O6)=0,"",IFERROR(AO6/U6,0)) | AQ6: =IF(COUNT(C6:O6)=0,"",IFERROR(AL6/H6,0))
A7: =Config!$C$6+1 | B7: =INT((A7-Config!$C$6)/7)+1 | C7: 135 | D7: 14209 | E7: 11255 | F7: 229 | G7: 204 | H7: 51 | I7: 7 | J7: 4 | K7: 2 | L7: 2 | M7: 0 | N7: 0 | O7: 0 | P7: =IF(COUNT(C7:O7)=0,"",IFERROR(C7/D7*1000,0)) | Q7: =IF(COUNT(C7:O7)=0,"",IFERROR(D7/E7,0)) | R7: =IF(COUNT(C7:O7)=0,"",IFERROR(F7/D7,0)) | S7: =IF(COUNT(C7:O7)=0,"",IFERROR(C7/F7,0)) | T7: =IF(COUNT(C7:O7)=0,"",IFERROR(G7/F7,0)) | U7: =IF(COUNT(C7:O7)=0,"",IFERROR(C7/G7,0)) | V7: =IF(COUNT(C7:O7)=0,"",IFERROR(G7/D7*1000,0)) | W7: =IF(COUNT(C7:O7)=0,"",IFERROR(H7/G7,0)) | X7: =IF(COUNT(C7:O7)=0,"",IFERROR(C7/H7,0)) | Y7: =IF(COUNT(C7:O7)=0,"",IFERROR(X7/P7,0)) | Z7: =IF(COUNT(C7:O7)=0,"",IFERROR(H7/D7*1000,0)) | AA7: =IF(COUNT(C7:O7)=0,"",IFERROR(I7/H7,0)) | AB7: =IF(COUNT(C7:O7)=0,"",IFERROR(J7/I7,0)) | AC7: =IF(COUNT(C7:O7)=0,"",IFERROR(K7/J7,0)) | AD7: =IF(COUNT(C7:O7)=0,"",IFERROR(C7/K7,0)) | AE7: =IF(COUNT(C7:O7)=0,"",IFERROR(L7/K7,0)) | AF7: =IF(COUNT(C7:O7)=0,"",IFERROR(M7/L7,0)) | AG7: =IF(COUNT(C7:O7)=0,"",IFERROR(M7/H7,0)) | AH7: =IF(COUNT(C7:O7)=0,"",IFERROR(C7/M7,0)) | AI7: =IF(COUNT(C7:O7)=0,"",IFERROR(M7*Config!$C$7+N7*Config!$C$8,0)) | AJ7: =IF(COUNT(C7:O7)=0,"",IFERROR(IF(O7>0,O7,AI7*Config!$C$9),0)) | AK7: =IF(COUNT(C7:O7)=0,"",IFERROR(AJ7*(1-Config!$C$10-Config!$C$11-Config!$C$12),0)) | AL7: =IF(COUNT(C7:O7)=0,"",IFERROR(AK7-C7-Config!$C$13,0)) | AM7: =IF(COUNT(C7:O7)=0,"",IFERROR(AK7/C7,0)) | AN7: =IF(COUNT(C7:O7)=0,"",IFERROR(AI7/C7,0)) | AO7: =IF(COUNT(C7:O7)=0,"",IFERROR(AL7/G7,0)) | AP7: =IF(COUNT(C7:O7)=0,"",IFERROR(AO7/U7,0)) | AQ7: =IF(COUNT(C7:O7)=0,"",IFERROR(AL7/H7,0))
A8: =Config!$C$6+2 | B8: =INT((A8-Config!$C$6)/7)+1 | C8: 138 | D8: 15581 | E8: 11054 | F8: 209 | G8: 164 | H8: 43 | I8: 3 | J8: 2 | K8: 1 | L8: 1 | M8: 0 | N8: 0 | O8: 0 | P8: =IF(COUNT(C8:O8)=0,"",IFERROR(C8/D8*1000,0)) | Q8: =IF(COUNT(C8:O8)=0,"",IFERROR(D8/E8,0)) | R8: =IF(COUNT(C8:O8)=0,"",IFERROR(F8/D8,0)) | S8: =IF(COUNT(C8:O8)=0,"",IFERROR(C8/F8,0)) | T8: =IF(COUNT(C8:O8)=0,"",IFERROR(G8/F8,0)) | U8: =IF(COUNT(C8:O8)=0,"",IFERROR(C8/G8,0)) | V8: =IF(COUNT(C8:O8)=0,"",IFERROR(G8/D8*1000,0)) | W8: =IF(COUNT(C8:O8)=0,"",IFERROR(H8/G8,0)) | X8: =IF(COUNT(C8:O8)=0,"",IFERROR(C8/H8,0)) | Y8: =IF(COUNT(C8:O8)=0,"",IFERROR(X8/P8,0)) | Z8: =IF(COUNT(C8:O8)=0,"",IFERROR(H8/D8*1000,0)) | AA8: =IF(COUNT(C8:O8)=0,"",IFERROR(I8/H8,0)) | AB8: =IF(COUNT(C8:O8)=0,"",IFERROR(J8/I8,0)) | AC8: =IF(COUNT(C8:O8)=0,"",IFERROR(K8/J8,0)) | AD8: =IF(COUNT(C8:O8)=0,"",IFERROR(C8/K8,0)) | AE8: =IF(COUNT(C8:O8)=0,"",IFERROR(L8/K8,0)) | AF8: =IF(COUNT(C8:O8)=0,"",IFERROR(M8/L8,0)) | AG8: =IF(COUNT(C8:O8)=0,"",IFERROR(M8/H8,0)) | AH8: =IF(COUNT(C8:O8)=0,"",IFERROR(C8/M8,0)) | AI8: =IF(COUNT(C8:O8)=0,"",IFERROR(M8*Config!$C$7+N8*Config!$C$8,0)) | AJ8: =IF(COUNT(C8:O8)=0,"",IFERROR(IF(O8>0,O8,AI8*Config!$C$9),0)) | AK8: =IF(COUNT(C8:O8)=0,"",IFERROR(AJ8*(1-Config!$C$10-Config!$C$11-Config!$C$12),0)) | AL8: =IF(COUNT(C8:O8)=0,"",IFERROR(AK8-C8-Config!$C$13,0)) | AM8: =IF(COUNT(C8:O8)=0,"",IFERROR(AK8/C8,0)) | AN8: =IF(COUNT(C8:O8)=0,"",IFERROR(AI8/C8,0)) | AO8: =IF(COUNT(C8:O8)=0,"",IFERROR(AL8/G8,0)) | AP8: =IF(COUNT(C8:O8)=0,"",IFERROR(AO8/U8,0)) | AQ8: =IF(COUNT(C8:O8)=0,"",IFERROR(AL8/H8,0))
A9: =Config!$C$6+3 | B9: =INT((A9-Config!$C$6)/7)+1 | C9: 151 | D9: 14578 | E9: 10413 | F9: 227 | G9: 191 | H9: 51 | I9: 7 | J9: 4 | K9: 2 | L9: 2 | M9: 0 | N9: 0 | O9: 0 | P9: =IF(COUNT(C9:O9)=0,"",IFERROR(C9/D9*1000,0)) | Q9: =IF(COUNT(C9:O9)=0,"",IFERROR(D9/E9,0)) | R9: =IF(COUNT(C9:O9)=0,"",IFERROR(F9/D9,0)) | S9: =IF(COUNT(C9:O9)=0,"",IFERROR(C9/F9,0)) | T9: =IF(COUNT(C9:O9)=0,"",IFERROR(G9/F9,0)) | U9: =IF(COUNT(C9:O9)=0,"",IFERROR(C9/G9,0)) | V9: =IF(COUNT(C9:O9)=0,"",IFERROR(G9/D9*1000,0)) | W9: =IF(COUNT(C9:O9)=0,"",IFERROR(H9/G9,0)) | X9: =IF(COUNT(C9:O9)=0,"",IFERROR(C9/H9,0)) | Y9: =IF(COUNT(C9:O9)=0,"",IFERROR(X9/P9,0)) | Z9: =IF(COUNT(C9:O9)=0,"",IFERROR(H9/D9*1000,0)) | AA9: =IF(COUNT(C9:O9)=0,"",IFERROR(I9/H9,0)) | AB9: =IF(COUNT(C9:O9)=0,"",IFERROR(J9/I9,0)) | AC9: =IF(COUNT(C9:O9)=0,"",IFERROR(K9/J9,0)) | AD9: =IF(COUNT(C9:O9)=0,"",IFERROR(C9/K9,0)) | AE9: =IF(COUNT(C9:O9)=0,"",IFERROR(L9/K9,0)) | AF9: =IF(COUNT(C9:O9)=0,"",IFERROR(M9/L9,0)) | AG9: =IF(COUNT(C9:O9)=0,"",IFERROR(M9/H9,0)) | AH9: =IF(COUNT(C9:O9)=0,"",IFERROR(C9/M9,0)) | AI9: =IF(COUNT(C9:O9)=0,"",IFERROR(M9*Config!$C$7+N9*Config!$C$8,0)) | AJ9: =IF(COUNT(C9:O9)=0,"",IFERROR(IF(O9>0,O9,AI9*Config!$C$9),0)) | AK9: =IF(COUNT(C9:O9)=0,"",IFERROR(AJ9*(1-Config!$C$10-Config!$C$11-Config!$C$12),0)) | AL9: =IF(COUNT(C9:O9)=0,"",IFERROR(AK9-C9-Config!$C$13,0)) | AM9: =IF(COUNT(C9:O9)=0,"",IFERROR(AK9/C9,0)) | AN9: =IF(COUNT(C9:O9)=0,"",IFERROR(AI9/C9,0)) | AO9: =IF(COUNT(C9:O9)=0,"",IFERROR(AL9/G9,0)) | AP9: =IF(COUNT(C9:O9)=0,"",IFERROR(AO9/U9,0)) | AQ9: =IF(COUNT(C9:O9)=0,"",IFERROR(AL9/H9,0))
A10: =Config!$C$6+4 | B10: =INT((A10-Config!$C$6)/7)+1 | C10: 143 | D10: 15330 | E10: 11534 | F10: 206 | G10: 186 | H10: 51 | I10: 6 | J10: 4 | K10: 2 | L10: 2 | M10: 0 | N10: 0 | O10: 0 | P10: =IF(COUNT(C10:O10)=0,"",IFERROR(C10/D10*1000,0)) | Q10: =IF(COUNT(C10:O10)=0,"",IFERROR(D10/E10,0)) | R10: =IF(COUNT(C10:O10)=0,"",IFERROR(F10/D10,0)) | S10: =IF(COUNT(C10:O10)=0,"",IFERROR(C10/F10,0)) | T10: =IF(COUNT(C10:O10)=0,"",IFERROR(G10/F10,0)) | U10: =IF(COUNT(C10:O10)=0,"",IFERROR(C10/G10,0)) | V10: =IF(COUNT(C10:O10)=0,"",IFERROR(G10/D10*1000,0)) | W10: =IF(COUNT(C10:O10)=0,"",IFERROR(H10/G10,0)) | X10: =IF(COUNT(C10:O10)=0,"",IFERROR(C10/H10,0)) | Y10: =IF(COUNT(C10:O10)=0,"",IFERROR(X10/P10,0)) | Z10: =IF(COUNT(C10:O10)=0,"",IFERROR(H10/D10*1000,0)) | AA10: =IF(COUNT(C10:O10)=0,"",IFERROR(I10/H10,0)) | AB10: =IF(COUNT(C10:O10)=0,"",IFERROR(J10/I10,0)) | AC10: =IF(COUNT(C10:O10)=0,"",IFERROR(K10/J10,0)) | AD10: =IF(COUNT(C10:O10)=0,"",IFERROR(C10/K10,0)) | AE10: =IF(COUNT(C10:O10)=0,"",IFERROR(L10/K10,0)) | AF10: =IF(COUNT(C10:O10)=0,"",IFERROR(M10/L10,0)) | AG10: =IF(COUNT(C10:O10)=0,"",IFERROR(M10/H10,0)) | AH10: =IF(COUNT(C10:O10)=0,"",IFERROR(C10/M10,0)) | AI10: =IF(COUNT(C10:O10)=0,"",IFERROR(M10*Config!$C$7+N10*Config!$C$8,0)) | AJ10: =IF(COUNT(C10:O10)=0,"",IFERROR(IF(O10>0,O10,AI10*Config!$C$9),0)) | AK10: =IF(COUNT(C10:O10)=0,"",IFERROR(AJ10*(1-Config!$C$10-Config!$C$11-Config!$C$12),0)) | AL10: =IF(COUNT(C10:O10)=0,"",IFERROR(AK10-C10-Config!$C$13,0)) | AM10: =IF(COUNT(C10:O10)=0,"",IFERROR(AK10/C10,0)) | AN10: =IF(COUNT(C10:O10)=0,"",IFERROR(AI10/C10,0)) | AO10: =IF(COUNT(C10:O10)=0,"",IFERROR(AL10/G10,0)) | AP10: =IF(COUNT(C10:O10)=0,"",IFERROR(AO10/U10,0)) | AQ10: =IF(COUNT(C10:O10)=0,"",IFERROR(AL10/H10,0))
A11: =Config!$C$6+5 | B11: =INT((A11-Config!$C$6)/7)+1 | C11: 132 | D11: 14191 | E11: 9228 | F11: 211 | G11: 200 | H11: 55 | I11: 4 | J11: 2 | K11: 1 | L11: 1 | M11: 0 | N11: 0 | O11: 300 | P11: =IF(COUNT(C11:O11)=0,"",IFERROR(C11/D11*1000,0)) | Q11: =IF(COUNT(C11:O11)=0,"",IFERROR(D11/E11,0)) | R11: =IF(COUNT(C11:O11)=0,"",IFERROR(F11/D11,0)) | S11: =IF(COUNT(C11:O11)=0,"",IFERROR(C11/F11,0)) | T11: =IF(COUNT(C11:O11)=0,"",IFERROR(G11/F11,0)) | U11: =IF(COUNT(C11:O11)=0,"",IFERROR(C11/G11,0)) | V11: =IF(COUNT(C11:O11)=0,"",IFERROR(G11/D11*1000,0)) | W11: =IF(COUNT(C11:O11)=0,"",IFERROR(H11/G11,0)) | X11: =IF(COUNT(C11:O11)=0,"",IFERROR(C11/H11,0)) | Y11: =IF(COUNT(C11:O11)=0,"",IFERROR(X11/P11,0)) | Z11: =IF(COUNT(C11:O11)=0,"",IFERROR(H11/D11*1000,0)) | AA11: =IF(COUNT(C11:O11)=0,"",IFERROR(I11/H11,0)) | AB11: =IF(COUNT(C11:O11)=0,"",IFERROR(J11/I11,0)) | AC11: =IF(COUNT(C11:O11)=0,"",IFERROR(K11/J11,0)) | AD11: =IF(COUNT(C11:O11)=0,"",IFERROR(C11/K11,0)) | AE11: =IF(COUNT(C11:O11)=0,"",IFERROR(L11/K11,0)) | AF11: =IF(COUNT(C11:O11)=0,"",IFERROR(M11/L11,0)) | AG11: =IF(COUNT(C11:O11)=0,"",IFERROR(M11/H11,0)) | AH11: =IF(COUNT(C11:O11)=0,"",IFERROR(C11/M11,0)) | AI11: =IF(COUNT(C11:O11)=0,"",IFERROR(M11*Config!$C$7+N11*Config!$C$8,0)) | AJ11: =IF(COUNT(C11:O11)=0,"",IFERROR(IF(O11>0,O11,AI11*Config!$C$9),0)) | AK11: =IF(COUNT(C11:O11)=0,"",IFERROR(AJ11*(1-Config!$C$10-Config!$C$11-Config!$C$12),0)) | AL11: =IF(COUNT(C11:O11)=0,"",IFERROR(AK11-C11-Config!$C$13,0)) | AM11: =IF(COUNT(C11:O11)=0,"",IFERROR(AK11/C11,0)) | AN11: =IF(COUNT(C11:O11)=0,"",IFERROR(AI11/C11,0)) | AO11: =IF(COUNT(C11:O11)=0,"",IFERROR(AL11/G11,0)) | AP11: =IF(COUNT(C11:O11)=0,"",IFERROR(AO11/U11,0)) | AQ11: =IF(COUNT(C11:O11)=0,"",IFERROR(AL11/H11,0))
A12: =Config!$C$6+6 | B12: =INT((A12-Config!$C$6)/7)+1 | C12: 135 | D12: 14079 | E12: 9049 | F12: 224 | G12: 173 | H12: 46 | I12: 3 | J12: 2 | K12: 1 | L12: 1 | M12: 1 | N12: 0 | O12: 900 | P12: =IF(COUNT(C12:O12)=0,"",IFERROR(C12/D12*1000,0)) | Q12: =IF(COUNT(C12:O12)=0,"",IFERROR(D12/E12,0)) | R12: =IF(COUNT(C12:O12)=0,"",IFERROR(F12/D12,0)) | S12: =IF(COUNT(C12:O12)=0,"",IFERROR(C12/F12,0)) | T12: =IF(COUNT(C12:O12)=0,"",IFERROR(G12/F12,0)) | U12: =IF(COUNT(C12:O12)=0,"",IFERROR(C12/G12,0)) | V12: =IF(COUNT(C12:O12)=0,"",IFERROR(G12/D12*1000,0)) | W12: =IF(COUNT(C12:O12)=0,"",IFERROR(H12/G12,0)) | X12: =IF(COUNT(C12:O12)=0,"",IFERROR(C12/H12,0)) | Y12: =IF(COUNT(C12:O12)=0,"",IFERROR(X12/P12,0)) | Z12: =IF(COUNT(C12:O12)=0,"",IFERROR(H12/D12*1000,0)) | AA12: =IF(COUNT(C12:O12)=0,"",IFERROR(I12/H12,0)) | AB12: =IF(COUNT(C12:O12)=0,"",IFERROR(J12/I12,0)) | AC12: =IF(COUNT(C12:O12)=0,"",IFERROR(K12/J12,0)) | AD12: =IF(COUNT(C12:O12)=0,"",IFERROR(C12/K12,0)) | AE12: =IF(COUNT(C12:O12)=0,"",IFERROR(L12/K12,0)) | AF12: =IF(COUNT(C12:O12)=0,"",IFERROR(M12/L12,0)) | AG12: =IF(COUNT(C12:O12)=0,"",IFERROR(M12/H12,0)) | AH12: =IF(COUNT(C12:O12)=0,"",IFERROR(C12/M12,0)) | AI12: =IF(COUNT(C12:O12)=0,"",IFERROR(M12*Config!$C$7+N12*Config!$C$8,0)) | AJ12: =IF(COUNT(C12:O12)=0,"",IFERROR(IF(O12>0,O12,AI12*Config!$C$9),0)) | AK12: =IF(COUNT(C12:O12)=0,"",IFERROR(AJ12*(1-Config!$C$10-Config!$C$11-Config!$C$12),0)) | AL12: =IF(COUNT(C12:O12)=0,"",IFERROR(AK12-C12-Config!$C$13,0)) | AM12: =IF(COUNT(C12:O12)=0,"",IFERROR(AK12/C12,0)) | AN12: =IF(COUNT(C12:O12)=0,"",IFERROR(AI12/C12,0)) | AO12: =IF(COUNT(C12:O12)=0,"",IFERROR(AL12/G12,0)) | AP12: =IF(COUNT(C12:O12)=0,"",IFERROR(AO12/U12,0)) | AQ12: =IF(COUNT(C12:O12)=0,"",IFERROR(AL12/H12,0))
A13: =Config!$C$6+7 | B13: =INT((A13-Config!$C$6)/7)+1 | C13: 138 | D13: 13645 | E13: 9871 | F13: 189 | G13: 170 | H13: 43 | I13: 5 | J13: 3 | K13: 2 | L13: 1 | M13: 1 | N13: 0 | O13: 900 | P13: =IF(COUNT(C13:O13)=0,"",IFERROR(C13/D13*1000,0)) | Q13: =IF(COUNT(C13:O13)=0,"",IFERROR(D13/E13,0)) | R13: =IF(COUNT(C13:O13)=0,"",IFERROR(F13/D13,0)) | S13: =IF(COUNT(C13:O13)=0,"",IFERROR(C13/F13,0)) | T13: =IF(COUNT(C13:O13)=0,"",IFERROR(G13/F13,0)) | U13: =IF(COUNT(C13:O13)=0,"",IFERROR(C13/G13,0)) | V13: =IF(COUNT(C13:O13)=0,"",IFERROR(G13/D13*1000,0)) | W13: =IF(COUNT(C13:O13)=0,"",IFERROR(H13/G13,0)) | X13: =IF(COUNT(C13:O13)=0,"",IFERROR(C13/H13,0)) | Y13: =IF(COUNT(C13:O13)=0,"",IFERROR(X13/P13,0)) | Z13: =IF(COUNT(C13:O13)=0,"",IFERROR(H13/D13*1000,0)) | AA13: =IF(COUNT(C13:O13)=0,"",IFERROR(I13/H13,0)) | AB13: =IF(COUNT(C13:O13)=0,"",IFERROR(J13/I13,0)) | AC13: =IF(COUNT(C13:O13)=0,"",IFERROR(K13/J13,0)) | AD13: =IF(COUNT(C13:O13)=0,"",IFERROR(C13/K13,0)) | AE13: =IF(COUNT(C13:O13)=0,"",IFERROR(L13/K13,0)) | AF13: =IF(COUNT(C13:O13)=0,"",IFERROR(M13/L13,0)) | AG13: =IF(COUNT(C13:O13)=0,"",IFERROR(M13/H13,0)) | AH13: =IF(COUNT(C13:O13)=0,"",IFERROR(C13/M13,0)) | AI13: =IF(COUNT(C13:O13)=0,"",IFERROR(M13*Config!$C$7+N13*Config!$C$8,0)) | AJ13: =IF(COUNT(C13:O13)=0,"",IFERROR(IF(O13>0,O13,AI13*Config!$C$9),0)) | AK13: =IF(COUNT(C13:O13)=0,"",IFERROR(AJ13*(1-Config!$C$10-Config!$C$11-Config!$C$12),0)) | AL13: =IF(COUNT(C13:O13)=0,"",IFERROR(AK13-C13-Config!$C$13,0)) | AM13: =IF(COUNT(C13:O13)=0,"",IFERROR(AK13/C13,0)) | AN13: =IF(COUNT(C13:O13)=0,"",IFERROR(AI13/C13,0)) | AO13: =IF(COUNT(C13:O13)=0,"",IFERROR(AL13/G13,0)) | AP13: =IF(COUNT(C13:O13)=0,"",IFERROR(AO13/U13,0)) | AQ13: =IF(COUNT(C13:O13)=0,"",IFERROR(AL13/H13,0))
A14: =Config!$C$6+8 | B14: =INT((A14-Config!$C$6)/7)+1 | C14: 140 | D14: 14783 | E14: 9487 | F14: 238 | G14: 193 | H14: 59 | I14: 5 | J14: 3 | K14: 2 | L14: 1 | M14: 0 | N14: 0 | O14: 0 | P14: =IF(COUNT(C14:O14)=0,"",IFERROR(C14/D14*1000,0)) | Q14: =IF(COUNT(C14:O14)=0,"",IFERROR(D14/E14,0)) | R14: =IF(COUNT(C14:O14)=0,"",IFERROR(F14/D14,0)) | S14: =IF(COUNT(C14:O14)=0,"",IFERROR(C14/F14,0)) | T14: =IF(COUNT(C14:O14)=0,"",IFERROR(G14/F14,0)) | U14: =IF(COUNT(C14:O14)=0,"",IFERROR(C14/G14,0)) | V14: =IF(COUNT(C14:O14)=0,"",IFERROR(G14/D14*1000,0)) | W14: =IF(COUNT(C14:O14)=0,"",IFERROR(H14/G14,0)) | X14: =IF(COUNT(C14:O14)=0,"",IFERROR(C14/H14,0)) | Y14: =IF(COUNT(C14:O14)=0,"",IFERROR(X14/P14,0)) | Z14: =IF(COUNT(C14:O14)=0,"",IFERROR(H14/D14*1000,0)) | AA14: =IF(COUNT(C14:O14)=0,"",IFERROR(I14/H14,0)) | AB14: =IF(COUNT(C14:O14)=0,"",IFERROR(J14/I14,0)) | AC14: =IF(COUNT(C14:O14)=0,"",IFERROR(K14/J14,0)) | AD14: =IF(COUNT(C14:O14)=0,"",IFERROR(C14/K14,0)) | AE14: =IF(COUNT(C14:O14)=0,"",IFERROR(L14/K14,0)) | AF14: =IF(COUNT(C14:O14)=0,"",IFERROR(M14/L14,0)) | AG14: =IF(COUNT(C14:O14)=0,"",IFERROR(M14/H14,0)) | AH14: =IF(COUNT(C14:O14)=0,"",IFERROR(C14/M14,0)) | AI14: =IF(COUNT(C14:O14)=0,"",IFERROR(M14*Config!$C$7+N14*Config!$C$8,0)) | AJ14: =IF(COUNT(C14:O14)=0,"",IFERROR(IF(O14>0,O14,AI14*Config!$C$9),0)) | AK14: =IF(COUNT(C14:O14)=0,"",IFERROR(AJ14*(1-Config!$C$10-Config!$C$11-Config!$C$12),0)) | AL14: =IF(COUNT(C14:O14)=0,"",IFERROR(AK14-C14-Config!$C$13,0)) | AM14: =IF(COUNT(C14:O14)=0,"",IFERROR(AK14/C14,0)) | AN14: =IF(COUNT(C14:O14)=0,"",IFERROR(AI14/C14,0)) | AO14: =IF(COUNT(C14:O14)=0,"",IFERROR(AL14/G14,0)) | AP14: =IF(COUNT(C14:O14)=0,"",IFERROR(AO14/U14,0)) | AQ14: =IF(COUNT(C14:O14)=0,"",IFERROR(AL14/H14,0))
A15: =Config!$C$6+9 | B15: =INT((A15-Config!$C$6)/7)+1 | C15: 136 | D15: 12136 | E15: 9309 | F15: 171 | G15: 155 | H15: 42 | I15: 4 | J15: 2 | K15: 1 | L15: 1 | M15: 1 | N15: 0 | O15: 1200 | P15: =IF(COUNT(C15:O15)=0,"",IFERROR(C15/D15*1000,0)) | Q15: =IF(COUNT(C15:O15)=0,"",IFERROR(D15/E15,0)) | R15: =IF(COUNT(C15:O15)=0,"",IFERROR(F15/D15,0)) | S15: =IF(COUNT(C15:O15)=0,"",IFERROR(C15/F15,0)) | T15: =IF(COUNT(C15:O15)=0,"",IFERROR(G15/F15,0)) | U15: =IF(COUNT(C15:O15)=0,"",IFERROR(C15/G15,0)) | V15: =IF(COUNT(C15:O15)=0,"",IFERROR(G15/D15*1000,0)) | W15: =IF(COUNT(C15:O15)=0,"",IFERROR(H15/G15,0)) | X15: =IF(COUNT(C15:O15)=0,"",IFERROR(C15/H15,0)) | Y15: =IF(COUNT(C15:O15)=0,"",IFERROR(X15/P15,0)) | Z15: =IF(COUNT(C15:O15)=0,"",IFERROR(H15/D15*1000,0)) | AA15: =IF(COUNT(C15:O15)=0,"",IFERROR(I15/H15,0)) | AB15: =IF(COUNT(C15:O15)=0,"",IFERROR(J15/I15,0)) | AC15: =IF(COUNT(C15:O15)=0,"",IFERROR(K15/J15,0)) | AD15: =IF(COUNT(C15:O15)=0,"",IFERROR(C15/K15,0)) | AE15: =IF(COUNT(C15:O15)=0,"",IFERROR(L15/K15,0)) | AF15: =IF(COUNT(C15:O15)=0,"",IFERROR(M15/L15,0)) | AG15: =IF(COUNT(C15:O15)=0,"",IFERROR(M15/H15,0)) | AH15: =IF(COUNT(C15:O15)=0,"",IFERROR(C15/M15,0)) | AI15: =IF(COUNT(C15:O15)=0,"",IFERROR(M15*Config!$C$7+N15*Config!$C$8,0)) | AJ15: =IF(COUNT(C15:O15)=0,"",IFERROR(IF(O15>0,O15,AI15*Config!$C$9),0)) | AK15: =IF(COUNT(C15:O15)=0,"",IFERROR(AJ15*(1-Config!$C$10-Config!$C$11-Config!$C$12),0)) | AL15: =IF(COUNT(C15:O15)=0,"",IFERROR(AK15-C15-Config!$C$13,0)) | AM15: =IF(COUNT(C15:O15)=0,"",IFERROR(AK15/C15,0)) | AN15: =IF(COUNT(C15:O15)=0,"",IFERROR(AI15/C15,0)) | AO15: =IF(COUNT(C15:O15)=0,"",IFERROR(AL15/G15,0)) | AP15: =IF(COUNT(C15:O15)=0,"",IFERROR(AO15/U15,0)) | AQ15: =IF(COUNT(C15:O15)=0,"",IFERROR(AL15/H15,0))
A16: =Config!$C$6+10 | B16: =INT((A16-Config!$C$6)/7)+1 | C16: 153 | D16: 16303 | E16: 11369 | F16: 237 | G16: 199 | H16: 62 | I16: 6 | J16: 4 | K16: 2 | L16: 2 | M16: 0 | N16: 0 | O16: 300 | P16: =IF(COUNT(C16:O16)=0,"",IFERROR(C16/D16*1000,0)) | Q16: =IF(COUNT(C16:O16)=0,"",IFERROR(D16/E16,0)) | R16: =IF(COUNT(C16:O16)=0,"",IFERROR(F16/D16,0)) | S16: =IF(COUNT(C16:O16)=0,"",IFERROR(C16/F16,0)) | T16: =IF(COUNT(C16:O16)=0,"",IFERROR(G16/F16,0)) | U16: =IF(COUNT(C16:O16)=0,"",IFERROR(C16/G16,0)) | V16: =IF(COUNT(C16:O16)=0,"",IFERROR(G16/D16*1000,0)) | W16: =IF(COUNT(C16:O16)=0,"",IFERROR(H16/G16,0)) | X16: =IF(COUNT(C16:O16)=0,"",IFERROR(C16/H16,0)) | Y16: =IF(COUNT(C16:O16)=0,"",IFERROR(X16/P16,0)) | Z16: =IF(COUNT(C16:O16)=0,"",IFERROR(H16/D16*1000,0)) | AA16: =IF(COUNT(C16:O16)=0,"",IFERROR(I16/H16,0)) | AB16: =IF(COUNT(C16:O16)=0,"",IFERROR(J16/I16,0)) | AC16: =IF(COUNT(C16:O16)=0,"",IFERROR(K16/J16,0)) | AD16: =IF(COUNT(C16:O16)=0,"",IFERROR(C16/K16,0)) | AE16: =IF(COUNT(C16:O16)=0,"",IFERROR(L16/K16,0)) | AF16: =IF(COUNT(C16:O16)=0,"",IFERROR(M16/L16,0)) | AG16: =IF(COUNT(C16:O16)=0,"",IFERROR(M16/H16,0)) | AH16: =IF(COUNT(C16:O16)=0,"",IFERROR(C16/M16,0)) | AI16: =IF(COUNT(C16:O16)=0,"",IFERROR(M16*Config!$C$7+N16*Config!$C$8,0)) | AJ16: =IF(COUNT(C16:O16)=0,"",IFERROR(IF(O16>0,O16,AI16*Config!$C$9),0)) | AK16: =IF(COUNT(C16:O16)=0,"",IFERROR(AJ16*(1-Config!$C$10-Config!$C$11-Config!$C$12),0)) | AL16: =IF(COUNT(C16:O16)=0,"",IFERROR(AK16-C16-Config!$C$13,0)) | AM16: =IF(COUNT(C16:O16)=0,"",IFERROR(AK16/C16,0)) | AN16: =IF(COUNT(C16:O16)=0,"",IFERROR(AI16/C16,0)) | AO16: =IF(COUNT(C16:O16)=0,"",IFERROR(AL16/G16,0)) | AP16: =IF(COUNT(C16:O16)=0,"",IFERROR(AO16/U16,0)) | AQ16: =IF(COUNT(C16:O16)=0,"",IFERROR(AL16/H16,0))
A17: =Config!$C$6+11 | B17: =INT((A17-Config!$C$6)/7)+1 | C17: 138 | D17: 12527 | E17: 8314 | F17: 177 | G17: 139 | H17: 41 | I17: 5 | J17: 3 | K17: 2 | L17: 1 | M17: 1 | N17: 0 | O17: 900 | P17: =IF(COUNT(C17:O17)=0,"",IFERROR(C17/D17*1000,0)) | Q17: =IF(COUNT(C17:O17)=0,"",IFERROR(D17/E17,0)) | R17: =IF(COUNT(C17:O17)=0,"",IFERROR(F17/D17,0)) | S17: =IF(COUNT(C17:O17)=0,"",IFERROR(C17/F17,0)) | T17: =IF(COUNT(C17:O17)=0,"",IFERROR(G17/F17,0)) | U17: =IF(COUNT(C17:O17)=0,"",IFERROR(C17/G17,0)) | V17: =IF(COUNT(C17:O17)=0,"",IFERROR(G17/D17*1000,0)) | W17: =IF(COUNT(C17:O17)=0,"",IFERROR(H17/G17,0)) | X17: =IF(COUNT(C17:O17)=0,"",IFERROR(C17/H17,0)) | Y17: =IF(COUNT(C17:O17)=0,"",IFERROR(X17/P17,0)) | Z17: =IF(COUNT(C17:O17)=0,"",IFERROR(H17/D17*1000,0)) | AA17: =IF(COUNT(C17:O17)=0,"",IFERROR(I17/H17,0)) | AB17: =IF(COUNT(C17:O17)=0,"",IFERROR(J17/I17,0)) | AC17: =IF(COUNT(C17:O17)=0,"",IFERROR(K17/J17,0)) | AD17: =IF(COUNT(C17:O17)=0,"",IFERROR(C17/K17,0)) | AE17: =IF(COUNT(C17:O17)=0,"",IFERROR(L17/K17,0)) | AF17: =IF(COUNT(C17:O17)=0,"",IFERROR(M17/L17,0)) | AG17: =IF(COUNT(C17:O17)=0,"",IFERROR(M17/H17,0)) | AH17: =IF(COUNT(C17:O17)=0,"",IFERROR(C17/M17,0)) | AI17: =IF(COUNT(C17:O17)=0,"",IFERROR(M17*Config!$C$7+N17*Config!$C$8,0)) | AJ17: =IF(COUNT(C17:O17)=0,"",IFERROR(IF(O17>0,O17,AI17*Config!$C$9),0)) | AK17: =IF(COUNT(C17:O17)=0,"",IFERROR(AJ17*(1-Config!$C$10-Config!$C$11-Config!$C$12),0)) | AL17: =IF(COUNT(C17:O17)=0,"",IFERROR(AK17-C17-Config!$C$13,0)) | AM17: =IF(COUNT(C17:O17)=0,"",IFERROR(AK17/C17,0)) | AN17: =IF(COUNT(C17:O17)=0,"",IFERROR(AI17/C17,0)) | AO17: =IF(COUNT(C17:O17)=0,"",IFERROR(AL17/G17,0)) | AP17: =IF(COUNT(C17:O17)=0,"",IFERROR(AO17/U17,0)) | AQ17: =IF(COUNT(C17:O17)=0,"",IFERROR(AL17/H17,0))
A18: =Config!$C$6+12 | B18: =INT((A18-Config!$C$6)/7)+1 | C18: 164 | D18: 15979 | E18: 11633 | F18: 217 | G18: 164 | H18: 51 | I18: 4 | J18: 3 | K18: 2 | L18: 1 | M18: 0 | N18: 0 | O18: 0 | P18: =IF(COUNT(C18:O18)=0,"",IFERROR(C18/D18*1000,0)) | Q18: =IF(COUNT(C18:O18)=0,"",IFERROR(D18/E18,0)) | R18: =IF(COUNT(C18:O18)=0,"",IFERROR(F18/D18,0)) | S18: =IF(COUNT(C18:O18)=0,"",IFERROR(C18/F18,0)) | T18: =IF(COUNT(C18:O18)=0,"",IFERROR(G18/F18,0)) | U18: =IF(COUNT(C18:O18)=0,"",IFERROR(C18/G18,0)) | V18: =IF(COUNT(C18:O18)=0,"",IFERROR(G18/D18*1000,0)) | W18: =IF(COUNT(C18:O18)=0,"",IFERROR(H18/G18,0)) | X18: =IF(COUNT(C18:O18)=0,"",IFERROR(C18/H18,0)) | Y18: =IF(COUNT(C18:O18)=0,"",IFERROR(X18/P18,0)) | Z18: =IF(COUNT(C18:O18)=0,"",IFERROR(H18/D18*1000,0)) | AA18: =IF(COUNT(C18:O18)=0,"",IFERROR(I18/H18,0)) | AB18: =IF(COUNT(C18:O18)=0,"",IFERROR(J18/I18,0)) | AC18: =IF(COUNT(C18:O18)=0,"",IFERROR(K18/J18,0)) | AD18: =IF(COUNT(C18:O18)=0,"",IFERROR(C18/K18,0)) | AE18: =IF(COUNT(C18:O18)=0,"",IFERROR(L18/K18,0)) | AF18: =IF(COUNT(C18:O18)=0,"",IFERROR(M18/L18,0)) | AG18: =IF(COUNT(C18:O18)=0,"",IFERROR(M18/H18,0)) | AH18: =IF(COUNT(C18:O18)=0,"",IFERROR(C18/M18,0)) | AI18: =IF(COUNT(C18:O18)=0,"",IFERROR(M18*Config!$C$7+N18*Config!$C$8,0)) | AJ18: =IF(COUNT(C18:O18)=0,"",IFERROR(IF(O18>0,O18,AI18*Config!$C$9),0)) | AK18: =IF(COUNT(C18:O18)=0,"",IFERROR(AJ18*(1-Config!$C$10-Config!$C$11-Config!$C$12),0)) | AL18: =IF(COUNT(C18:O18)=0,"",IFERROR(AK18-C18-Config!$C$13,0)) | AM18: =IF(COUNT(C18:O18)=0,"",IFERROR(AK18/C18,0)) | AN18: =IF(COUNT(C18:O18)=0,"",IFERROR(AI18/C18,0)) | AO18: =IF(COUNT(C18:O18)=0,"",IFERROR(AL18/G18,0)) | AP18: =IF(COUNT(C18:O18)=0,"",IFERROR(AO18/U18,0)) | AQ18: =IF(COUNT(C18:O18)=0,"",IFERROR(AL18/H18,0))
A19: =Config!$C$6+13 | B19: =INT((A19-Config!$C$6)/7)+1 | C19: 153 | D19: 16148 | E19: 12509 | F19: 255 | G19: 194 | H19: 51 | I19: 5 | J19: 3 | K19: 2 | L19: 1 | M19: 0 | N19: 0 | O19: 300 | P19: =IF(COUNT(C19:O19)=0,"",IFERROR(C19/D19*1000,0)) | Q19: =IF(COUNT(C19:O19)=0,"",IFERROR(D19/E19,0)) | R19: =IF(COUNT(C19:O19)=0,"",IFERROR(F19/D19,0)) | S19: =IF(COUNT(C19:O19)=0,"",IFERROR(C19/F19,0)) | T19: =IF(COUNT(C19:O19)=0,"",IFERROR(G19/F19,0)) | U19: =IF(COUNT(C19:O19)=0,"",IFERROR(C19/G19,0)) | V19: =IF(COUNT(C19:O19)=0,"",IFERROR(G19/D19*1000,0)) | W19: =IF(COUNT(C19:O19)=0,"",IFERROR(H19/G19,0)) | X19: =IF(COUNT(C19:O19)=0,"",IFERROR(C19/H19,0)) | Y19: =IF(COUNT(C19:O19)=0,"",IFERROR(X19/P19,0)) | Z19: =IF(COUNT(C19:O19)=0,"",IFERROR(H19/D19*1000,0)) | AA19: =IF(COUNT(C19:O19)=0,"",IFERROR(I19/H19,0)) | AB19: =IF(COUNT(C19:O19)=0,"",IFERROR(J19/I19,0)) | AC19: =IF(COUNT(C19:O19)=0,"",IFERROR(K19/J19,0)) | AD19: =IF(COUNT(C19:O19)=0,"",IFERROR(C19/K19,0)) | AE19: =IF(COUNT(C19:O19)=0,"",IFERROR(L19/K19,0)) | AF19: =IF(COUNT(C19:O19)=0,"",IFERROR(M19/L19,0)) | AG19: =IF(COUNT(C19:O19)=0,"",IFERROR(M19/H19,0)) | AH19: =IF(COUNT(C19:O19)=0,"",IFERROR(C19/M19,0)) | AI19: =IF(COUNT(C19:O19)=0,"",IFERROR(M19*Config!$C$7+N19*Config!$C$8,0)) | AJ19: =IF(COUNT(C19:O19)=0,"",IFERROR(IF(O19>0,O19,AI19*Config!$C$9),0)) | AK19: =IF(COUNT(C19:O19)=0,"",IFERROR(AJ19*(1-Config!$C$10-Config!$C$11-Config!$C$12),0)) | AL19: =IF(COUNT(C19:O19)=0,"",IFERROR(AK19-C19-Config!$C$13,0)) | AM19: =IF(COUNT(C19:O19)=0,"",IFERROR(AK19/C19,0)) | AN19: =IF(COUNT(C19:O19)=0,"",IFERROR(AI19/C19,0)) | AO19: =IF(COUNT(C19:O19)=0,"",IFERROR(AL19/G19,0)) | AP19: =IF(COUNT(C19:O19)=0,"",IFERROR(AO19/U19,0)) | AQ19: =IF(COUNT(C19:O19)=0,"",IFERROR(AL19/H19,0))
A20: =Config!$C$6+14 | B20: =INT((A20-Config!$C$6)/7)+1 | C20: 165 | D20: 17765 | E20: 14354 | F20: 252 | G20: 211 | H20: 53 | I20: 4 | J20: 3 | K20: 2 | L20: 1 | M20: 0 | N20: 0 | O20: 300 | P20: =IF(COUNT(C20:O20)=0,"",IFERROR(C20/D20*1000,0)) | Q20: =IF(COUNT(C20:O20)=0,"",IFERROR(D20/E20,0)) | R20: =IF(COUNT(C20:O20)=0,"",IFERROR(F20/D20,0)) | S20: =IF(COUNT(C20:O20)=0,"",IFERROR(C20/F20,0)) | T20: =IF(COUNT(C20:O20)=0,"",IFERROR(G20/F20,0)) | U20: =IF(COUNT(C20:O20)=0,"",IFERROR(C20/G20,0)) | V20: =IF(COUNT(C20:O20)=0,"",IFERROR(G20/D20*1000,0)) | W20: =IF(COUNT(C20:O20)=0,"",IFERROR(H20/G20,0)) | X20: =IF(COUNT(C20:O20)=0,"",IFERROR(C20/H20,0)) | Y20: =IF(COUNT(C20:O20)=0,"",IFERROR(X20/P20,0)) | Z20: =IF(COUNT(C20:O20)=0,"",IFERROR(H20/D20*1000,0)) | AA20: =IF(COUNT(C20:O20)=0,"",IFERROR(I20/H20,0)) | AB20: =IF(COUNT(C20:O20)=0,"",IFERROR(J20/I20,0)) | AC20: =IF(COUNT(C20:O20)=0,"",IFERROR(K20/J20,0)) | AD20: =IF(COUNT(C20:O20)=0,"",IFERROR(C20/K20,0)) | AE20: =IF(COUNT(C20:O20)=0,"",IFERROR(L20/K20,0)) | AF20: =IF(COUNT(C20:O20)=0,"",IFERROR(M20/L20,0)) | AG20: =IF(COUNT(C20:O20)=0,"",IFERROR(M20/H20,0)) | AH20: =IF(COUNT(C20:O20)=0,"",IFERROR(C20/M20,0)) | AI20: =IF(COUNT(C20:O20)=0,"",IFERROR(M20*Config!$C$7+N20*Config!$C$8,0)) | AJ20: =IF(COUNT(C20:O20)=0,"",IFERROR(IF(O20>0,O20,AI20*Config!$C$9),0)) | AK20: =IF(COUNT(C20:O20)=0,"",IFERROR(AJ20*(1-Config!$C$10-Config!$C$11-Config!$C$12),0)) | AL20: =IF(COUNT(C20:O20)=0,"",IFERROR(AK20-C20-Config!$C$13,0)) | AM20: =IF(COUNT(C20:O20)=0,"",IFERROR(AK20/C20,0)) | AN20: =IF(COUNT(C20:O20)=0,"",IFERROR(AI20/C20,0)) | AO20: =IF(COUNT(C20:O20)=0,"",IFERROR(AL20/G20,0)) | AP20: =IF(COUNT(C20:O20)=0,"",IFERROR(AO20/U20,0)) | AQ20: =IF(COUNT(C20:O20)=0,"",IFERROR(AL20/H20,0))
A21: =Config!$C$6+15 | B21: =INT((A21-Config!$C$6)/7)+1 | C21: 145 | D21: 13260 | E21: 8492 | F21: 206 | G21: 183 | H21: 52 | I21: 4 | J21: 2 | K21: 1 | L21: 1 | M21: 1 | N21: 0 | O21: 1200 | P21: =IF(COUNT(C21:O21)=0,"",IFERROR(C21/D21*1000,0)) | Q21: =IF(COUNT(C21:O21)=0,"",IFERROR(D21/E21,0)) | R21: =IF(COUNT(C21:O21)=0,"",IFERROR(F21/D21,0)) | S21: =IF(COUNT(C21:O21)=0,"",IFERROR(C21/F21,0)) | T21: =IF(COUNT(C21:O21)=0,"",IFERROR(G21/F21,0)) | U21: =IF(COUNT(C21:O21)=0,"",IFERROR(C21/G21,0)) | V21: =IF(COUNT(C21:O21)=0,"",IFERROR(G21/D21*1000,0)) | W21: =IF(COUNT(C21:O21)=0,"",IFERROR(H21/G21,0)) | X21: =IF(COUNT(C21:O21)=0,"",IFERROR(C21/H21,0)) | Y21: =IF(COUNT(C21:O21)=0,"",IFERROR(X21/P21,0)) | Z21: =IF(COUNT(C21:O21)=0,"",IFERROR(H21/D21*1000,0)) | AA21: =IF(COUNT(C21:O21)=0,"",IFERROR(I21/H21,0)) | AB21: =IF(COUNT(C21:O21)=0,"",IFERROR(J21/I21,0)) | AC21: =IF(COUNT(C21:O21)=0,"",IFERROR(K21/J21,0)) | AD21: =IF(COUNT(C21:O21)=0,"",IFERROR(C21/K21,0)) | AE21: =IF(COUNT(C21:O21)=0,"",IFERROR(L21/K21,0)) | AF21: =IF(COUNT(C21:O21)=0,"",IFERROR(M21/L21,0)) | AG21: =IF(COUNT(C21:O21)=0,"",IFERROR(M21/H21,0)) | AH21: =IF(COUNT(C21:O21)=0,"",IFERROR(C21/M21,0)) | AI21: =IF(COUNT(C21:O21)=0,"",IFERROR(M21*Config!$C$7+N21*Config!$C$8,0)) | AJ21: =IF(COUNT(C21:O21)=0,"",IFERROR(IF(O21>0,O21,AI21*Config!$C$9),0)) | AK21: =IF(COUNT(C21:O21)=0,"",IFERROR(AJ21*(1-Config!$C$10-Config!$C$11-Config!$C$12),0)) | AL21: =IF(COUNT(C21:O21)=0,"",IFERROR(AK21-C21-Config!$C$13,0)) | AM21: =IF(COUNT(C21:O21)=0,"",IFERROR(AK21/C21,0)) | AN21: =IF(COUNT(C21:O21)=0,"",IFERROR(AI21/C21,0)) | AO21: =IF(COUNT(C21:O21)=0,"",IFERROR(AL21/G21,0)) | AP21: =IF(COUNT(C21:O21)=0,"",IFERROR(AO21/U21,0)) | AQ21: =IF(COUNT(C21:O21)=0,"",IFERROR(AL21/H21,0))
A22: =Config!$C$6+16 | B22: =INT((A22-Config!$C$6)/7)+1 | C22: 165 | D22: 15719 | E22: 10105 | F22: 209 | G22: 183 | H22: 51 | I22: 6 | J22: 3 | K22: 2 | L22: 1 | M22: 1 | N22: 0 | O22: 900 | P22: =IF(COUNT(C22:O22)=0,"",IFERROR(C22/D22*1000,0)) | Q22: =IF(COUNT(C22:O22)=0,"",IFERROR(D22/E22,0)) | R22: =IF(COUNT(C22:O22)=0,"",IFERROR(F22/D22,0)) | S22: =IF(COUNT(C22:O22)=0,"",IFERROR(C22/F22,0)) | T22: =IF(COUNT(C22:O22)=0,"",IFERROR(G22/F22,0)) | U22: =IF(COUNT(C22:O22)=0,"",IFERROR(C22/G22,0)) | V22: =IF(COUNT(C22:O22)=0,"",IFERROR(G22/D22*1000,0)) | W22: =IF(COUNT(C22:O22)=0,"",IFERROR(H22/G22,0)) | X22: =IF(COUNT(C22:O22)=0,"",IFERROR(C22/H22,0)) | Y22: =IF(COUNT(C22:O22)=0,"",IFERROR(X22/P22,0)) | Z22: =IF(COUNT(C22:O22)=0,"",IFERROR(H22/D22*1000,0)) | AA22: =IF(COUNT(C22:O22)=0,"",IFERROR(I22/H22,0)) | AB22: =IF(COUNT(C22:O22)=0,"",IFERROR(J22/I22,0)) | AC22: =IF(COUNT(C22:O22)=0,"",IFERROR(K22/J22,0)) | AD22: =IF(COUNT(C22:O22)=0,"",IFERROR(C22/K22,0)) | AE22: =IF(COUNT(C22:O22)=0,"",IFERROR(L22/K22,0)) | AF22: =IF(COUNT(C22:O22)=0,"",IFERROR(M22/L22,0)) | AG22: =IF(COUNT(C22:O22)=0,"",IFERROR(M22/H22,0)) | AH22: =IF(COUNT(C22:O22)=0,"",IFERROR(C22/M22,0)) | AI22: =IF(COUNT(C22:O22)=0,"",IFERROR(M22*Config!$C$7+N22*Config!$C$8,0)) | AJ22: =IF(COUNT(C22:O22)=0,"",IFERROR(IF(O22>0,O22,AI22*Config!$C$9),0)) | AK22: =IF(COUNT(C22:O22)=0,"",IFERROR(AJ22*(1-Config!$C$10-Config!$C$11-Config!$C$12),0)) | AL22: =IF(COUNT(C22:O22)=0,"",IFERROR(AK22-C22-Config!$C$13,0)) | AM22: =IF(COUNT(C22:O22)=0,"",IFERROR(AK22/C22,0)) | AN22: =IF(COUNT(C22:O22)=0,"",IFERROR(AI22/C22,0)) | AO22: =IF(COUNT(C22:O22)=0,"",IFERROR(AL22/G22,0)) | AP22: =IF(COUNT(C22:O22)=0,"",IFERROR(AO22/U22,0)) | AQ22: =IF(COUNT(C22:O22)=0,"",IFERROR(AL22/H22,0))
A23: =Config!$C$6+17 | B23: =INT((A23-Config!$C$6)/7)+1 | C23: 135 | D23: 13324 | E23: 9005 | F23: 219 | G23: 197 | H23: 58 | I23: 7 | J23: 4 | K23: 2 | L23: 2 | M23: 0 | N23: 0 | O23: 0 | P23: =IF(COUNT(C23:O23)=0,"",IFERROR(C23/D23*1000,0)) | Q23: =IF(COUNT(C23:O23)=0,"",IFERROR(D23/E23,0)) | R23: =IF(COUNT(C23:O23)=0,"",IFERROR(F23/D23,0)) | S23: =IF(COUNT(C23:O23)=0,"",IFERROR(C23/F23,0)) | T23: =IF(COUNT(C23:O23)=0,"",IFERROR(G23/F23,0)) | U23: =IF(COUNT(C23:O23)=0,"",IFERROR(C23/G23,0)) | V23: =IF(COUNT(C23:O23)=0,"",IFERROR(G23/D23*1000,0)) | W23: =IF(COUNT(C23:O23)=0,"",IFERROR(H23/G23,0)) | X23: =IF(COUNT(C23:O23)=0,"",IFERROR(C23/H23,0)) | Y23: =IF(COUNT(C23:O23)=0,"",IFERROR(X23/P23,0)) | Z23: =IF(COUNT(C23:O23)=0,"",IFERROR(H23/D23*1000,0)) | AA23: =IF(COUNT(C23:O23)=0,"",IFERROR(I23/H23,0)) | AB23: =IF(COUNT(C23:O23)=0,"",IFERROR(J23/I23,0)) | AC23: =IF(COUNT(C23:O23)=0,"",IFERROR(K23/J23,0)) | AD23: =IF(COUNT(C23:O23)=0,"",IFERROR(C23/K23,0)) | AE23: =IF(COUNT(C23:O23)=0,"",IFERROR(L23/K23,0)) | AF23: =IF(COUNT(C23:O23)=0,"",IFERROR(M23/L23,0)) | AG23: =IF(COUNT(C23:O23)=0,"",IFERROR(M23/H23,0)) | AH23: =IF(COUNT(C23:O23)=0,"",IFERROR(C23/M23,0)) | AI23: =IF(COUNT(C23:O23)=0,"",IFERROR(M23*Config!$C$7+N23*Config!$C$8,0)) | AJ23: =IF(COUNT(C23:O23)=0,"",IFERROR(IF(O23>0,O23,AI23*Config!$C$9),0)) | AK23: =IF(COUNT(C23:O23)=0,"",IFERROR(AJ23*(1-Config!$C$10-Config!$C$11-Config!$C$12),0)) | AL23: =IF(COUNT(C23:O23)=0,"",IFERROR(AK23-C23-Config!$C$13,0)) | AM23: =IF(COUNT(C23:O23)=0,"",IFERROR(AK23/C23,0)) | AN23: =IF(COUNT(C23:O23)=0,"",IFERROR(AI23/C23,0)) | AO23: =IF(COUNT(C23:O23)=0,"",IFERROR(AL23/G23,0)) | AP23: =IF(COUNT(C23:O23)=0,"",IFERROR(AO23/U23,0)) | AQ23: =IF(COUNT(C23:O23)=0,"",IFERROR(AL23/H23,0))
A24: =Config!$C$6+18 | B24: =INT((A24-Config!$C$6)/7)+1 | C24: 164 | D24: 15098 | E24: 11003 | F24: 242 | G24: 224 | H24: 64 | I24: 7 | J24: 4 | K24: 2 | L24: 2 | M24: 0 | N24: 0 | O24: 0 | P24: =IF(COUNT(C24:O24)=0,"",IFERROR(C24/D24*1000,0)) | Q24: =IF(COUNT(C24:O24)=0,"",IFERROR(D24/E24,0)) | R24: =IF(COUNT(C24:O24)=0,"",IFERROR(F24/D24,0)) | S24: =IF(COUNT(C24:O24)=0,"",IFERROR(C24/F24,0)) | T24: =IF(COUNT(C24:O24)=0,"",IFERROR(G24/F24,0)) | U24: =IF(COUNT(C24:O24)=0,"",IFERROR(C24/G24,0)) | V24: =IF(COUNT(C24:O24)=0,"",IFERROR(G24/D24*1000,0)) | W24: =IF(COUNT(C24:O24)=0,"",IFERROR(H24/G24,0)) | X24: =IF(COUNT(C24:O24)=0,"",IFERROR(C24/H24,0)) | Y24: =IF(COUNT(C24:O24)=0,"",IFERROR(X24/P24,0)) | Z24: =IF(COUNT(C24:O24)=0,"",IFERROR(H24/D24*1000,0)) | AA24: =IF(COUNT(C24:O24)=0,"",IFERROR(I24/H24,0)) | AB24: =IF(COUNT(C24:O24)=0,"",IFERROR(J24/I24,0)) | AC24: =IF(COUNT(C24:O24)=0,"",IFERROR(K24/J24,0)) | AD24: =IF(COUNT(C24:O24)=0,"",IFERROR(C24/K24,0)) | AE24: =IF(COUNT(C24:O24)=0,"",IFERROR(L24/K24,0)) | AF24: =IF(COUNT(C24:O24)=0,"",IFERROR(M24/L24,0)) | AG24: =IF(COUNT(C24:O24)=0,"",IFERROR(M24/H24,0)) | AH24: =IF(COUNT(C24:O24)=0,"",IFERROR(C24/M24,0)) | AI24: =IF(COUNT(C24:O24)=0,"",IFERROR(M24*Config!$C$7+N24*Config!$C$8,0)) | AJ24: =IF(COUNT(C24:O24)=0,"",IFERROR(IF(O24>0,O24,AI24*Config!$C$9),0)) | AK24: =IF(COUNT(C24:O24)=0,"",IFERROR(AJ24*(1-Config!$C$10-Config!$C$11-Config!$C$12),0)) | AL24: =IF(COUNT(C24:O24)=0,"",IFERROR(AK24-C24-Config!$C$13,0)) | AM24: =IF(COUNT(C24:O24)=0,"",IFERROR(AK24/C24,0)) | AN24: =IF(COUNT(C24:O24)=0,"",IFERROR(AI24/C24,0)) | AO24: =IF(COUNT(C24:O24)=0,"",IFERROR(AL24/G24,0)) | AP24: =IF(COUNT(C24:O24)=0,"",IFERROR(AO24/U24,0)) | AQ24: =IF(COUNT(C24:O24)=0,"",IFERROR(AL24/H24,0))
A25: =Config!$C$6+19 | B25: =INT((A25-Config!$C$6)/7)+1 | C25: 135 | D25: 13052 | E25: 8336 | F25: 214 | G25: 192 | H25: 52 | I25: 6 | J25: 4 | K25: 2 | L25: 2 | M25: 0 | N25: 0 | O25: 0 | P25: =IF(COUNT(C25:O25)=0,"",IFERROR(C25/D25*1000,0)) | Q25: =IF(COUNT(C25:O25)=0,"",IFERROR(D25/E25,0)) | R25: =IF(COUNT(C25:O25)=0,"",IFERROR(F25/D25,0)) | S25: =IF(COUNT(C25:O25)=0,"",IFERROR(C25/F25,0)) | T25: =IF(COUNT(C25:O25)=0,"",IFERROR(G25/F25,0)) | U25: =IF(COUNT(C25:O25)=0,"",IFERROR(C25/G25,0)) | V25: =IF(COUNT(C25:O25)=0,"",IFERROR(G25/D25*1000,0)) | W25: =IF(COUNT(C25:O25)=0,"",IFERROR(H25/G25,0)) | X25: =IF(COUNT(C25:O25)=0,"",IFERROR(C25/H25,0)) | Y25: =IF(COUNT(C25:O25)=0,"",IFERROR(X25/P25,0)) | Z25: =IF(COUNT(C25:O25)=0,"",IFERROR(H25/D25*1000,0)) | AA25: =IF(COUNT(C25:O25)=0,"",IFERROR(I25/H25,0)) | AB25: =IF(COUNT(C25:O25)=0,"",IFERROR(J25/I25,0)) | AC25: =IF(COUNT(C25:O25)=0,"",IFERROR(K25/J25,0)) | AD25: =IF(COUNT(C25:O25)=0,"",IFERROR(C25/K25,0)) | AE25: =IF(COUNT(C25:O25)=0,"",IFERROR(L25/K25,0)) | AF25: =IF(COUNT(C25:O25)=0,"",IFERROR(M25/L25,0)) | AG25: =IF(COUNT(C25:O25)=0,"",IFERROR(M25/H25,0)) | AH25: =IF(COUNT(C25:O25)=0,"",IFERROR(C25/M25,0)) | AI25: =IF(COUNT(C25:O25)=0,"",IFERROR(M25*Config!$C$7+N25*Config!$C$8,0)) | AJ25: =IF(COUNT(C25:O25)=0,"",IFERROR(IF(O25>0,O25,AI25*Config!$C$9),0)) | AK25: =IF(COUNT(C25:O25)=0,"",IFERROR(AJ25*(1-Config!$C$10-Config!$C$11-Config!$C$12),0)) | AL25: =IF(COUNT(C25:O25)=0,"",IFERROR(AK25-C25-Config!$C$13,0)) | AM25: =IF(COUNT(C25:O25)=0,"",IFERROR(AK25/C25,0)) | AN25: =IF(COUNT(C25:O25)=0,"",IFERROR(AI25/C25,0)) | AO25: =IF(COUNT(C25:O25)=0,"",IFERROR(AL25/G25,0)) | AP25: =IF(COUNT(C25:O25)=0,"",IFERROR(AO25/U25,0)) | AQ25: =IF(COUNT(C25:O25)=0,"",IFERROR(AL25/H25,0))
A26: =Config!$C$6+20 | B26: =INT((A26-Config!$C$6)/7)+1 | C26: 135 | D26: 12737 | E26: 10255 | F26: 196 | G26: 166 | H26: 43 | I26: 5 | J26: 3 | K26: 2 | L26: 1 | M26: 0 | N26: 0 | O26: 0 | P26: =IF(COUNT(C26:O26)=0,"",IFERROR(C26/D26*1000,0)) | Q26: =IF(COUNT(C26:O26)=0,"",IFERROR(D26/E26,0)) | R26: =IF(COUNT(C26:O26)=0,"",IFERROR(F26/D26,0)) | S26: =IF(COUNT(C26:O26)=0,"",IFERROR(C26/F26,0)) | T26: =IF(COUNT(C26:O26)=0,"",IFERROR(G26/F26,0)) | U26: =IF(COUNT(C26:O26)=0,"",IFERROR(C26/G26,0)) | V26: =IF(COUNT(C26:O26)=0,"",IFERROR(G26/D26*1000,0)) | W26: =IF(COUNT(C26:O26)=0,"",IFERROR(H26/G26,0)) | X26: =IF(COUNT(C26:O26)=0,"",IFERROR(C26/H26,0)) | Y26: =IF(COUNT(C26:O26)=0,"",IFERROR(X26/P26,0)) | Z26: =IF(COUNT(C26:O26)=0,"",IFERROR(H26/D26*1000,0)) | AA26: =IF(COUNT(C26:O26)=0,"",IFERROR(I26/H26,0)) | AB26: =IF(COUNT(C26:O26)=0,"",IFERROR(J26/I26,0)) | AC26: =IF(COUNT(C26:O26)=0,"",IFERROR(K26/J26,0)) | AD26: =IF(COUNT(C26:O26)=0,"",IFERROR(C26/K26,0)) | AE26: =IF(COUNT(C26:O26)=0,"",IFERROR(L26/K26,0)) | AF26: =IF(COUNT(C26:O26)=0,"",IFERROR(M26/L26,0)) | AG26: =IF(COUNT(C26:O26)=0,"",IFERROR(M26/H26,0)) | AH26: =IF(COUNT(C26:O26)=0,"",IFERROR(C26/M26,0)) | AI26: =IF(COUNT(C26:O26)=0,"",IFERROR(M26*Config!$C$7+N26*Config!$C$8,0)) | AJ26: =IF(COUNT(C26:O26)=0,"",IFERROR(IF(O26>0,O26,AI26*Config!$C$9),0)) | AK26: =IF(COUNT(C26:O26)=0,"",IFERROR(AJ26*(1-Config!$C$10-Config!$C$11-Config!$C$12),0)) | AL26: =IF(COUNT(C26:O26)=0,"",IFERROR(AK26-C26-Config!$C$13,0)) | AM26: =IF(COUNT(C26:O26)=0,"",IFERROR(AK26/C26,0)) | AN26: =IF(COUNT(C26:O26)=0,"",IFERROR(AI26/C26,0)) | AO26: =IF(COUNT(C26:O26)=0,"",IFERROR(AL26/G26,0)) | AP26: =IF(COUNT(C26:O26)=0,"",IFERROR(AO26/U26,0)) | AQ26: =IF(COUNT(C26:O26)=0,"",IFERROR(AL26/H26,0))
A27: =Config!$C$6+21 | B27: =INT((A27-Config!$C$6)/7)+1 | C27: 141 | D27: 15997 | E27: 12000 | F27: 250 | G27: 198 | H27: 51 | I27: 6 | J27: 4 | K27: 2 | L27: 2 | M27: 0 | N27: 0 | O27: 0 | P27: =IF(COUNT(C27:O27)=0,"",IFERROR(C27/D27*1000,0)) | Q27: =IF(COUNT(C27:O27)=0,"",IFERROR(D27/E27,0)) | R27: =IF(COUNT(C27:O27)=0,"",IFERROR(F27/D27,0)) | S27: =IF(COUNT(C27:O27)=0,"",IFERROR(C27/F27,0)) | T27: =IF(COUNT(C27:O27)=0,"",IFERROR(G27/F27,0)) | U27: =IF(COUNT(C27:O27)=0,"",IFERROR(C27/G27,0)) | V27: =IF(COUNT(C27:O27)=0,"",IFERROR(G27/D27*1000,0)) | W27: =IF(COUNT(C27:O27)=0,"",IFERROR(H27/G27,0)) | X27: =IF(COUNT(C27:O27)=0,"",IFERROR(C27/H27,0)) | Y27: =IF(COUNT(C27:O27)=0,"",IFERROR(X27/P27,0)) | Z27: =IF(COUNT(C27:O27)=0,"",IFERROR(H27/D27*1000,0)) | AA27: =IF(COUNT(C27:O27)=0,"",IFERROR(I27/H27,0)) | AB27: =IF(COUNT(C27:O27)=0,"",IFERROR(J27/I27,0)) | AC27: =IF(COUNT(C27:O27)=0,"",IFERROR(K27/J27,0)) | AD27: =IF(COUNT(C27:O27)=0,"",IFERROR(C27/K27,0)) | AE27: =IF(COUNT(C27:O27)=0,"",IFERROR(L27/K27,0)) | AF27: =IF(COUNT(C27:O27)=0,"",IFERROR(M27/L27,0)) | AG27: =IF(COUNT(C27:O27)=0,"",IFERROR(M27/H27,0)) | AH27: =IF(COUNT(C27:O27)=0,"",IFERROR(C27/M27,0)) | AI27: =IF(COUNT(C27:O27)=0,"",IFERROR(M27*Config!$C$7+N27*Config!$C$8,0)) | AJ27: =IF(COUNT(C27:O27)=0,"",IFERROR(IF(O27>0,O27,AI27*Config!$C$9),0)) | AK27: =IF(COUNT(C27:O27)=0,"",IFERROR(AJ27*(1-Config!$C$10-Config!$C$11-Config!$C$12),0)) | AL27: =IF(COUNT(C27:O27)=0,"",IFERROR(AK27-C27-Config!$C$13,0)) | AM27: =IF(COUNT(C27:O27)=0,"",IFERROR(AK27/C27,0)) | AN27: =IF(COUNT(C27:O27)=0,"",IFERROR(AI27/C27,0)) | AO27: =IF(COUNT(C27:O27)=0,"",IFERROR(AL27/G27,0)) | AP27: =IF(COUNT(C27:O27)=0,"",IFERROR(AO27/U27,0)) | AQ27: =IF(COUNT(C27:O27)=0,"",IFERROR(AL27/H27,0))
A28: =Config!$C$6+22 | B28: =INT((A28-Config!$C$6)/7)+1 | C28: 144 | D28: 13827 | E28: 10646 | F28: 204 | G28: 186 | H28: 57 | I28: 7 | J28: 4 | K28: 3 | L28: 2 | M28: 0 | N28: 0 | O28: 0 | P28: =IF(COUNT(C28:O28)=0,"",IFERROR(C28/D28*1000,0)) | Q28: =IF(COUNT(C28:O28)=0,"",IFERROR(D28/E28,0)) | R28: =IF(COUNT(C28:O28)=0,"",IFERROR(F28/D28,0)) | S28: =IF(COUNT(C28:O28)=0,"",IFERROR(C28/F28,0)) | T28: =IF(COUNT(C28:O28)=0,"",IFERROR(G28/F28,0)) | U28: =IF(COUNT(C28:O28)=0,"",IFERROR(C28/G28,0)) | V28: =IF(COUNT(C28:O28)=0,"",IFERROR(G28/D28*1000,0)) | W28: =IF(COUNT(C28:O28)=0,"",IFERROR(H28/G28,0)) | X28: =IF(COUNT(C28:O28)=0,"",IFERROR(C28/H28,0)) | Y28: =IF(COUNT(C28:O28)=0,"",IFERROR(X28/P28,0)) | Z28: =IF(COUNT(C28:O28)=0,"",IFERROR(H28/D28*1000,0)) | AA28: =IF(COUNT(C28:O28)=0,"",IFERROR(I28/H28,0)) | AB28: =IF(COUNT(C28:O28)=0,"",IFERROR(J28/I28,0)) | AC28: =IF(COUNT(C28:O28)=0,"",IFERROR(K28/J28,0)) | AD28: =IF(COUNT(C28:O28)=0,"",IFERROR(C28/K28,0)) | AE28: =IF(COUNT(C28:O28)=0,"",IFERROR(L28/K28,0)) | AF28: =IF(COUNT(C28:O28)=0,"",IFERROR(M28/L28,0)) | AG28: =IF(COUNT(C28:O28)=0,"",IFERROR(M28/H28,0)) | AH28: =IF(COUNT(C28:O28)=0,"",IFERROR(C28/M28,0)) | AI28: =IF(COUNT(C28:O28)=0,"",IFERROR(M28*Config!$C$7+N28*Config!$C$8,0)) | AJ28: =IF(COUNT(C28:O28)=0,"",IFERROR(IF(O28>0,O28,AI28*Config!$C$9),0)) | AK28: =IF(COUNT(C28:O28)=0,"",IFERROR(AJ28*(1-Config!$C$10-Config!$C$11-Config!$C$12),0)) | AL28: =IF(COUNT(C28:O28)=0,"",IFERROR(AK28-C28-Config!$C$13,0)) | AM28: =IF(COUNT(C28:O28)=0,"",IFERROR(AK28/C28,0)) | AN28: =IF(COUNT(C28:O28)=0,"",IFERROR(AI28/C28,0)) | AO28: =IF(COUNT(C28:O28)=0,"",IFERROR(AL28/G28,0)) | AP28: =IF(COUNT(C28:O28)=0,"",IFERROR(AO28/U28,0)) | AQ28: =IF(COUNT(C28:O28)=0,"",IFERROR(AL28/H28,0))
A29: =Config!$C$6+23 | B29: =INT((A29-Config!$C$6)/7)+1 | C29: 137 | D29: 13702 | E29: 9055 | F29: 223 | G29: 199 | H29: 62 | I29: 5 | J29: 3 | K29: 2 | L29: 1 | M29: 1 | N29: 0 | O29: 900 | P29: =IF(COUNT(C29:O29)=0,"",IFERROR(C29/D29*1000,0)) | Q29: =IF(COUNT(C29:O29)=0,"",IFERROR(D29/E29,0)) | R29: =IF(COUNT(C29:O29)=0,"",IFERROR(F29/D29,0)) | S29: =IF(COUNT(C29:O29)=0,"",IFERROR(C29/F29,0)) | T29: =IF(COUNT(C29:O29)=0,"",IFERROR(G29/F29,0)) | U29: =IF(COUNT(C29:O29)=0,"",IFERROR(C29/G29,0)) | V29: =IF(COUNT(C29:O29)=0,"",IFERROR(G29/D29*1000,0)) | W29: =IF(COUNT(C29:O29)=0,"",IFERROR(H29/G29,0)) | X29: =IF(COUNT(C29:O29)=0,"",IFERROR(C29/H29,0)) | Y29: =IF(COUNT(C29:O29)=0,"",IFERROR(X29/P29,0)) | Z29: =IF(COUNT(C29:O29)=0,"",IFERROR(H29/D29*1000,0)) | AA29: =IF(COUNT(C29:O29)=0,"",IFERROR(I29/H29,0)) | AB29: =IF(COUNT(C29:O29)=0,"",IFERROR(J29/I29,0)) | AC29: =IF(COUNT(C29:O29)=0,"",IFERROR(K29/J29,0)) | AD29: =IF(COUNT(C29:O29)=0,"",IFERROR(C29/K29,0)) | AE29: =IF(COUNT(C29:O29)=0,"",IFERROR(L29/K29,0)) | AF29: =IF(COUNT(C29:O29)=0,"",IFERROR(M29/L29,0)) | AG29: =IF(COUNT(C29:O29)=0,"",IFERROR(M29/H29,0)) | AH29: =IF(COUNT(C29:O29)=0,"",IFERROR(C29/M29,0)) | AI29: =IF(COUNT(C29:O29)=0,"",IFERROR(M29*Config!$C$7+N29*Config!$C$8,0)) | AJ29: =IF(COUNT(C29:O29)=0,"",IFERROR(IF(O29>0,O29,AI29*Config!$C$9),0)) | AK29: =IF(COUNT(C29:O29)=0,"",IFERROR(AJ29*(1-Config!$C$10-Config!$C$11-Config!$C$12),0)) | AL29: =IF(COUNT(C29:O29)=0,"",IFERROR(AK29-C29-Config!$C$13,0)) | AM29: =IF(COUNT(C29:O29)=0,"",IFERROR(AK29/C29,0)) | AN29: =IF(COUNT(C29:O29)=0,"",IFERROR(AI29/C29,0)) | AO29: =IF(COUNT(C29:O29)=0,"",IFERROR(AL29/G29,0)) | AP29: =IF(COUNT(C29:O29)=0,"",IFERROR(AO29/U29,0)) | AQ29: =IF(COUNT(C29:O29)=0,"",IFERROR(AL29/H29,0))
A30: =Config!$C$6+24 | B30: =INT((A30-Config!$C$6)/7)+1 | C30: 142 | D30: 15236 | E30: 11112 | F30: 235 | G30: 200 | H30: 53 | I30: 6 | J30: 4 | K30: 2 | L30: 2 | M30: 0 | N30: 0 | O30: 300 | P30: =IF(COUNT(C30:O30)=0,"",IFERROR(C30/D30*1000,0)) | Q30: =IF(COUNT(C30:O30)=0,"",IFERROR(D30/E30,0)) | R30: =IF(COUNT(C30:O30)=0,"",IFERROR(F30/D30,0)) | S30: =IF(COUNT(C30:O30)=0,"",IFERROR(C30/F30,0)) | T30: =IF(COUNT(C30:O30)=0,"",IFERROR(G30/F30,0)) | U30: =IF(COUNT(C30:O30)=0,"",IFERROR(C30/G30,0)) | V30: =IF(COUNT(C30:O30)=0,"",IFERROR(G30/D30*1000,0)) | W30: =IF(COUNT(C30:O30)=0,"",IFERROR(H30/G30,0)) | X30: =IF(COUNT(C30:O30)=0,"",IFERROR(C30/H30,0)) | Y30: =IF(COUNT(C30:O30)=0,"",IFERROR(X30/P30,0)) | Z30: =IF(COUNT(C30:O30)=0,"",IFERROR(H30/D30*1000,0)) | AA30: =IF(COUNT(C30:O30)=0,"",IFERROR(I30/H30,0)) | AB30: =IF(COUNT(C30:O30)=0,"",IFERROR(J30/I30,0)) | AC30: =IF(COUNT(C30:O30)=0,"",IFERROR(K30/J30,0)) | AD30: =IF(COUNT(C30:O30)=0,"",IFERROR(C30/K30,0)) | AE30: =IF(COUNT(C30:O30)=0,"",IFERROR(L30/K30,0)) | AF30: =IF(COUNT(C30:O30)=0,"",IFERROR(M30/L30,0)) | AG30: =IF(COUNT(C30:O30)=0,"",IFERROR(M30/H30,0)) | AH30: =IF(COUNT(C30:O30)=0,"",IFERROR(C30/M30,0)) | AI30: =IF(COUNT(C30:O30)=0,"",IFERROR(M30*Config!$C$7+N30*Config!$C$8,0)) | AJ30: =IF(COUNT(C30:O30)=0,"",IFERROR(IF(O30>0,O30,AI30*Config!$C$9),0)) | AK30: =IF(COUNT(C30:O30)=0,"",IFERROR(AJ30*(1-Config!$C$10-Config!$C$11-Config!$C$12),0)) | AL30: =IF(COUNT(C30:O30)=0,"",IFERROR(AK30-C30-Config!$C$13,0)) | AM30: =IF(COUNT(C30:O30)=0,"",IFERROR(AK30/C30,0)) | AN30: =IF(COUNT(C30:O30)=0,"",IFERROR(AI30/C30,0)) | AO30: =IF(COUNT(C30:O30)=0,"",IFERROR(AL30/G30,0)) | AP30: =IF(COUNT(C30:O30)=0,"",IFERROR(AO30/U30,0)) | AQ30: =IF(COUNT(C30:O30)=0,"",IFERROR(AL30/H30,0))
A31: =Config!$C$6+25 | B31: =INT((A31-Config!$C$6)/7)+1 | C31: 133 | D31: 12220 | E31: 9808 | F31: 192 | G31: 166 | H31: 44 | I31: 5 | J31: 3 | K31: 2 | L31: 1 | M31: 1 | N31: 0 | O31: 1200 | P31: =IF(COUNT(C31:O31)=0,"",IFERROR(C31/D31*1000,0)) | Q31: =IF(COUNT(C31:O31)=0,"",IFERROR(D31/E31,0)) | R31: =IF(COUNT(C31:O31)=0,"",IFERROR(F31/D31,0)) | S31: =IF(COUNT(C31:O31)=0,"",IFERROR(C31/F31,0)) | T31: =IF(COUNT(C31:O31)=0,"",IFERROR(G31/F31,0)) | U31: =IF(COUNT(C31:O31)=0,"",IFERROR(C31/G31,0)) | V31: =IF(COUNT(C31:O31)=0,"",IFERROR(G31/D31*1000,0)) | W31: =IF(COUNT(C31:O31)=0,"",IFERROR(H31/G31,0)) | X31: =IF(COUNT(C31:O31)=0,"",IFERROR(C31/H31,0)) | Y31: =IF(COUNT(C31:O31)=0,"",IFERROR(X31/P31,0)) | Z31: =IF(COUNT(C31:O31)=0,"",IFERROR(H31/D31*1000,0)) | AA31: =IF(COUNT(C31:O31)=0,"",IFERROR(I31/H31,0)) | AB31: =IF(COUNT(C31:O31)=0,"",IFERROR(J31/I31,0)) | AC31: =IF(COUNT(C31:O31)=0,"",IFERROR(K31/J31,0)) | AD31: =IF(COUNT(C31:O31)=0,"",IFERROR(C31/K31,0)) | AE31: =IF(COUNT(C31:O31)=0,"",IFERROR(L31/K31,0)) | AF31: =IF(COUNT(C31:O31)=0,"",IFERROR(M31/L31,0)) | AG31: =IF(COUNT(C31:O31)=0,"",IFERROR(M31/H31,0)) | AH31: =IF(COUNT(C31:O31)=0,"",IFERROR(C31/M31,0)) | AI31: =IF(COUNT(C31:O31)=0,"",IFERROR(M31*Config!$C$7+N31*Config!$C$8,0)) | AJ31: =IF(COUNT(C31:O31)=0,"",IFERROR(IF(O31>0,O31,AI31*Config!$C$9),0)) | AK31: =IF(COUNT(C31:O31)=0,"",IFERROR(AJ31*(1-Config!$C$10-Config!$C$11-Config!$C$12),0)) | AL31: =IF(COUNT(C31:O31)=0,"",IFERROR(AK31-C31-Config!$C$13,0)) | AM31: =IF(COUNT(C31:O31)=0,"",IFERROR(AK31/C31,0)) | AN31: =IF(COUNT(C31:O31)=0,"",IFERROR(AI31/C31,0)) | AO31: =IF(COUNT(C31:O31)=0,"",IFERROR(AL31/G31,0)) | AP31: =IF(COUNT(C31:O31)=0,"",IFERROR(AO31/U31,0)) | AQ31: =IF(COUNT(C31:O31)=0,"",IFERROR(AL31/H31,0))
A32: =Config!$C$6+26 | B32: =INT((A32-Config!$C$6)/7)+1 | C32: 148 | D32: 16748 | E32: 11086 | F32: 235 | G32: 183 | H32: 46 | I32: 5 | J32: 3 | K32: 2 | L32: 1 | M32: 0 | N32: 0 | O32: 0 | P32: =IF(COUNT(C32:O32)=0,"",IFERROR(C32/D32*1000,0)) | Q32: =IF(COUNT(C32:O32)=0,"",IFERROR(D32/E32,0)) | R32: =IF(COUNT(C32:O32)=0,"",IFERROR(F32/D32,0)) | S32: =IF(COUNT(C32:O32)=0,"",IFERROR(C32/F32,0)) | T32: =IF(COUNT(C32:O32)=0,"",IFERROR(G32/F32,0)) | U32: =IF(COUNT(C32:O32)=0,"",IFERROR(C32/G32,0)) | V32: =IF(COUNT(C32:O32)=0,"",IFERROR(G32/D32*1000,0)) | W32: =IF(COUNT(C32:O32)=0,"",IFERROR(H32/G32,0)) | X32: =IF(COUNT(C32:O32)=0,"",IFERROR(C32/H32,0)) | Y32: =IF(COUNT(C32:O32)=0,"",IFERROR(X32/P32,0)) | Z32: =IF(COUNT(C32:O32)=0,"",IFERROR(H32/D32*1000,0)) | AA32: =IF(COUNT(C32:O32)=0,"",IFERROR(I32/H32,0)) | AB32: =IF(COUNT(C32:O32)=0,"",IFERROR(J32/I32,0)) | AC32: =IF(COUNT(C32:O32)=0,"",IFERROR(K32/J32,0)) | AD32: =IF(COUNT(C32:O32)=0,"",IFERROR(C32/K32,0)) | AE32: =IF(COUNT(C32:O32)=0,"",IFERROR(L32/K32,0)) | AF32: =IF(COUNT(C32:O32)=0,"",IFERROR(M32/L32,0)) | AG32: =IF(COUNT(C32:O32)=0,"",IFERROR(M32/H32,0)) | AH32: =IF(COUNT(C32:O32)=0,"",IFERROR(C32/M32,0)) | AI32: =IF(COUNT(C32:O32)=0,"",IFERROR(M32*Config!$C$7+N32*Config!$C$8,0)) | AJ32: =IF(COUNT(C32:O32)=0,"",IFERROR(IF(O32>0,O32,AI32*Config!$C$9),0)) | AK32: =IF(COUNT(C32:O32)=0,"",IFERROR(AJ32*(1-Config!$C$10-Config!$C$11-Config!$C$12),0)) | AL32: =IF(COUNT(C32:O32)=0,"",IFERROR(AK32-C32-Config!$C$13,0)) | AM32: =IF(COUNT(C32:O32)=0,"",IFERROR(AK32/C32,0)) | AN32: =IF(COUNT(C32:O32)=0,"",IFERROR(AI32/C32,0)) | AO32: =IF(COUNT(C32:O32)=0,"",IFERROR(AL32/G32,0)) | AP32: =IF(COUNT(C32:O32)=0,"",IFERROR(AO32/U32,0)) | AQ32: =IF(COUNT(C32:O32)=0,"",IFERROR(AL32/H32,0))
A33: =Config!$C$6+27 | B33: =INT((A33-Config!$C$6)/7)+1 | C33: 161 | D33: 14510 | E33: 9925 | F33: 202 | G33: 171 | H33: 44 | I33: 3 | J33: 2 | K33: 1 | L33: 1 | M33: 0 | N33: 0 | O33: 300 | P33: =IF(COUNT(C33:O33)=0,"",IFERROR(C33/D33*1000,0)) | Q33: =IF(COUNT(C33:O33)=0,"",IFERROR(D33/E33,0)) | R33: =IF(COUNT(C33:O33)=0,"",IFERROR(F33/D33,0)) | S33: =IF(COUNT(C33:O33)=0,"",IFERROR(C33/F33,0)) | T33: =IF(COUNT(C33:O33)=0,"",IFERROR(G33/F33,0)) | U33: =IF(COUNT(C33:O33)=0,"",IFERROR(C33/G33,0)) | V33: =IF(COUNT(C33:O33)=0,"",IFERROR(G33/D33*1000,0)) | W33: =IF(COUNT(C33:O33)=0,"",IFERROR(H33/G33,0)) | X33: =IF(COUNT(C33:O33)=0,"",IFERROR(C33/H33,0)) | Y33: =IF(COUNT(C33:O33)=0,"",IFERROR(X33/P33,0)) | Z33: =IF(COUNT(C33:O33)=0,"",IFERROR(H33/D33*1000,0)) | AA33: =IF(COUNT(C33:O33)=0,"",IFERROR(I33/H33,0)) | AB33: =IF(COUNT(C33:O33)=0,"",IFERROR(J33/I33,0)) | AC33: =IF(COUNT(C33:O33)=0,"",IFERROR(K33/J33,0)) | AD33: =IF(COUNT(C33:O33)=0,"",IFERROR(C33/K33,0)) | AE33: =IF(COUNT(C33:O33)=0,"",IFERROR(L33/K33,0)) | AF33: =IF(COUNT(C33:O33)=0,"",IFERROR(M33/L33,0)) | AG33: =IF(COUNT(C33:O33)=0,"",IFERROR(M33/H33,0)) | AH33: =IF(COUNT(C33:O33)=0,"",IFERROR(C33/M33,0)) | AI33: =IF(COUNT(C33:O33)=0,"",IFERROR(M33*Config!$C$7+N33*Config!$C$8,0)) | AJ33: =IF(COUNT(C33:O33)=0,"",IFERROR(IF(O33>0,O33,AI33*Config!$C$9),0)) | AK33: =IF(COUNT(C33:O33)=0,"",IFERROR(AJ33*(1-Config!$C$10-Config!$C$11-Config!$C$12),0)) | AL33: =IF(COUNT(C33:O33)=0,"",IFERROR(AK33-C33-Config!$C$13,0)) | AM33: =IF(COUNT(C33:O33)=0,"",IFERROR(AK33/C33,0)) | AN33: =IF(COUNT(C33:O33)=0,"",IFERROR(AI33/C33,0)) | AO33: =IF(COUNT(C33:O33)=0,"",IFERROR(AL33/G33,0)) | AP33: =IF(COUNT(C33:O33)=0,"",IFERROR(AO33/U33,0)) | AQ33: =IF(COUNT(C33:O33)=0,"",IFERROR(AL33/H33,0))
A34: =Config!$C$6+28 | B34: =INT((A34-Config!$C$6)/7)+1 | P34: =IF(COUNT(C34:O34)=0,"",IFERROR(C34/D34*1000,0)) | Q34: =IF(COUNT(C34:O34)=0,"",IFERROR(D34/E34,0)) | R34: =IF(COUNT(C34:O34)=0,"",IFERROR(F34/D34,0)) | S34: =IF(COUNT(C34:O34)=0,"",IFERROR(C34/F34,0)) | T34: =IF(COUNT(C34:O34)=0,"",IFERROR(G34/F34,0)) | U34: =IF(COUNT(C34:O34)=0,"",IFERROR(C34/G34,0)) | V34: =IF(COUNT(C34:O34)=0,"",IFERROR(G34/D34*1000,0)) | W34: =IF(COUNT(C34:O34)=0,"",IFERROR(H34/G34,0)) | X34: =IF(COUNT(C34:O34)=0,"",IFERROR(C34/H34,0)) | Y34: =IF(COUNT(C34:O34)=0,"",IFERROR(X34/P34,0)) | Z34: =IF(COUNT(C34:O34)=0,"",IFERROR(H34/D34*1000,0)) | AA34: =IF(COUNT(C34:O34)=0,"",IFERROR(I34/H34,0)) | AB34: =IF(COUNT(C34:O34)=0,"",IFERROR(J34/I34,0)) | AC34: =IF(COUNT(C34:O34)=0,"",IFERROR(K34/J34,0)) | AD34: =IF(COUNT(C34:O34)=0,"",IFERROR(C34/K34,0)) | AE34: =IF(COUNT(C34:O34)=0,"",IFERROR(L34/K34,0)) | AF34: =IF(COUNT(C34:O34)=0,"",IFERROR(M34/L34,0)) | AG34: =IF(COUNT(C34:O34)=0,"",IFERROR(M34/H34,0)) | AH34: =IF(COUNT(C34:O34)=0,"",IFERROR(C34/M34,0)) | AI34: =IF(COUNT(C34:O34)=0,"",IFERROR(M34*Config!$C$7+N34*Config!$C$8,0)) | AJ34: =IF(COUNT(C34:O34)=0,"",IFERROR(IF(O34>0,O34,AI34*Config!$C$9),0)) | AK34: =IF(COUNT(C34:O34)=0,"",IFERROR(AJ34*(1-Config!$C$10-Config!$C$11-Config!$C$12),0)) | AL34: =IF(COUNT(C34:O34)=0,"",IFERROR(AK34-C34-Config!$C$13,0)) | AM34: =IF(COUNT(C34:O34)=0,"",IFERROR(AK34/C34,0)) | AN34: =IF(COUNT(C34:O34)=0,"",IFERROR(AI34/C34,0)) | AO34: =IF(COUNT(C34:O34)=0,"",IFERROR(AL34/G34,0)) | AP34: =IF(COUNT(C34:O34)=0,"",IFERROR(AO34/U34,0)) | AQ34: =IF(COUNT(C34:O34)=0,"",IFERROR(AL34/H34,0))
A35: =Config!$C$6+29 | B35: =INT((A35-Config!$C$6)/7)+1 | P35: =IF(COUNT(C35:O35)=0,"",IFERROR(C35/D35*1000,0)) | Q35: =IF(COUNT(C35:O35)=0,"",IFERROR(D35/E35,0)) | R35: =IF(COUNT(C35:O35)=0,"",IFERROR(F35/D35,0)) | S35: =IF(COUNT(C35:O35)=0,"",IFERROR(C35/F35,0)) | T35: =IF(COUNT(C35:O35)=0,"",IFERROR(G35/F35,0)) | U35: =IF(COUNT(C35:O35)=0,"",IFERROR(C35/G35,0)) | V35: =IF(COUNT(C35:O35)=0,"",IFERROR(G35/D35*1000,0)) | W35: =IF(COUNT(C35:O35)=0,"",IFERROR(H35/G35,0)) | X35: =IF(COUNT(C35:O35)=0,"",IFERROR(C35/H35,0)) | Y35: =IF(COUNT(C35:O35)=0,"",IFERROR(X35/P35,0)) | Z35: =IF(COUNT(C35:O35)=0,"",IFERROR(H35/D35*1000,0)) | AA35: =IF(COUNT(C35:O35)=0,"",IFERROR(I35/H35,0)) | AB35: =IF(COUNT(C35:O35)=0,"",IFERROR(J35/I35,0)) | AC35: =IF(COUNT(C35:O35)=0,"",IFERROR(K35/J35,0)) | AD35: =IF(COUNT(C35:O35)=0,"",IFERROR(C35/K35,0)) | AE35: =IF(COUNT(C35:O35)=0,"",IFERROR(L35/K35,0)) | AF35: =IF(COUNT(C35:O35)=0,"",IFERROR(M35/L35,0)) | AG35: =IF(COUNT(C35:O35)=0,"",IFERROR(M35/H35,0)) | AH35: =IF(COUNT(C35:O35)=0,"",IFERROR(C35/M35,0)) | AI35: =IF(COUNT(C35:O35)=0,"",IFERROR(M35*Config!$C$7+N35*Config!$C$8,0)) | AJ35: =IF(COUNT(C35:O35)=0,"",IFERROR(IF(O35>0,O35,AI35*Config!$C$9),0)) | AK35: =IF(COUNT(C35:O35)=0,"",IFERROR(AJ35*(1-Config!$C$10-Config!$C$11-Config!$C$12),0)) | AL35: =IF(COUNT(C35:O35)=0,"",IFERROR(AK35-C35-Config!$C$13,0)) | AM35: =IF(COUNT(C35:O35)=0,"",IFERROR(AK35/C35,0)) | AN35: =IF(COUNT(C35:O35)=0,"",IFERROR(AI35/C35,0)) | AO35: =IF(COUNT(C35:O35)=0,"",IFERROR(AL35/G35,0)) | AP35: =IF(COUNT(C35:O35)=0,"",IFERROR(AO35/U35,0)) | AQ35: =IF(COUNT(C35:O35)=0,"",IFERROR(AL35/H35,0))
A36: =Config!$C$6+30 | B36: =INT((A36-Config!$C$6)/7)+1 | P36: =IF(COUNT(C36:O36)=0,"",IFERROR(C36/D36*1000,0)) | Q36: =IF(COUNT(C36:O36)=0,"",IFERROR(D36/E36,0)) | R36: =IF(COUNT(C36:O36)=0,"",IFERROR(F36/D36,0)) | S36: =IF(COUNT(C36:O36)=0,"",IFERROR(C36/F36,0)) | T36: =IF(COUNT(C36:O36)=0,"",IFERROR(G36/F36,0)) | U36: =IF(COUNT(C36:O36)=0,"",IFERROR(C36/G36,0)) | V36: =IF(COUNT(C36:O36)=0,"",IFERROR(G36/D36*1000,0)) | W36: =IF(COUNT(C36:O36)=0,"",IFERROR(H36/G36,0)) | X36: =IF(COUNT(C36:O36)=0,"",IFERROR(C36/H36,0)) | Y36: =IF(COUNT(C36:O36)=0,"",IFERROR(X36/P36,0)) | Z36: =IF(COUNT(C36:O36)=0,"",IFERROR(H36/D36*1000,0)) | AA36: =IF(COUNT(C36:O36)=0,"",IFERROR(I36/H36,0)) | AB36: =IF(COUNT(C36:O36)=0,"",IFERROR(J36/I36,0)) | AC36: =IF(COUNT(C36:O36)=0,"",IFERROR(K36/J36,0)) | AD36: =IF(COUNT(C36:O36)=0,"",IFERROR(C36/K36,0)) | AE36: =IF(COUNT(C36:O36)=0,"",IFERROR(L36/K36,0)) | AF36: =IF(COUNT(C36:O36)=0,"",IFERROR(M36/L36,0)) | AG36: =IF(COUNT(C36:O36)=0,"",IFERROR(M36/H36,0)) | AH36: =IF(COUNT(C36:O36)=0,"",IFERROR(C36/M36,0)) | AI36: =IF(COUNT(C36:O36)=0,"",IFERROR(M36*Config!$C$7+N36*Config!$C$8,0)) | AJ36: =IF(COUNT(C36:O36)=0,"",IFERROR(IF(O36>0,O36,AI36*Config!$C$9),0)) | AK36: =IF(COUNT(C36:O36)=0,"",IFERROR(AJ36*(1-Config!$C$10-Config!$C$11-Config!$C$12),0)) | AL36: =IF(COUNT(C36:O36)=0,"",IFERROR(AK36-C36-Config!$C$13,0)) | AM36: =IF(COUNT(C36:O36)=0,"",IFERROR(AK36/C36,0)) | AN36: =IF(COUNT(C36:O36)=0,"",IFERROR(AI36/C36,0)) | AO36: =IF(COUNT(C36:O36)=0,"",IFERROR(AL36/G36,0)) | AP36: =IF(COUNT(C36:O36)=0,"",IFERROR(AO36/U36,0)) | AQ36: =IF(COUNT(C36:O36)=0,"",IFERROR(AL36/H36,0))
A37: =Config!$C$6+31 | B37: =INT((A37-Config!$C$6)/7)+1 | P37: =IF(COUNT(C37:O37)=0,"",IFERROR(C37/D37*1000,0)) | Q37: =IF(COUNT(C37:O37)=0,"",IFERROR(D37/E37,0)) | R37: =IF(COUNT(C37:O37)=0,"",IFERROR(F37/D37,0)) | S37: =IF(COUNT(C37:O37)=0,"",IFERROR(C37/F37,0)) | T37: =IF(COUNT(C37:O37)=0,"",IFERROR(G37/F37,0)) | U37: =IF(COUNT(C37:O37)=0,"",IFERROR(C37/G37,0)) | V37: =IF(COUNT(C37:O37)=0,"",IFERROR(G37/D37*1000,0)) | W37: =IF(COUNT(C37:O37)=0,"",IFERROR(H37/G37,0)) | X37: =IF(COUNT(C37:O37)=0,"",IFERROR(C37/H37,0)) | Y37: =IF(COUNT(C37:O37)=0,"",IFERROR(X37/P37,0)) | Z37: =IF(COUNT(C37:O37)=0,"",IFERROR(H37/D37*1000,0)) | AA37: =IF(COUNT(C37:O37)=0,"",IFERROR(I37/H37,0)) | AB37: =IF(COUNT(C37:O37)=0,"",IFERROR(J37/I37,0)) | AC37: =IF(COUNT(C37:O37)=0,"",IFERROR(K37/J37,0)) | AD37: =IF(COUNT(C37:O37)=0,"",IFERROR(C37/K37,0)) | AE37: =IF(COUNT(C37:O37)=0,"",IFERROR(L37/K37,0)) | AF37: =IF(COUNT(C37:O37)=0,"",IFERROR(M37/L37,0)) | AG37: =IF(COUNT(C37:O37)=0,"",IFERROR(M37/H37,0)) | AH37: =IF(COUNT(C37:O37)=0,"",IFERROR(C37/M37,0)) | AI37: =IF(COUNT(C37:O37)=0,"",IFERROR(M37*Config!$C$7+N37*Config!$C$8,0)) | AJ37: =IF(COUNT(C37:O37)=0,"",IFERROR(IF(O37>0,O37,AI37*Config!$C$9),0)) | AK37: =IF(COUNT(C37:O37)=0,"",IFERROR(AJ37*(1-Config!$C$10-Config!$C$11-Config!$C$12),0)) | AL37: =IF(COUNT(C37:O37)=0,"",IFERROR(AK37-C37-Config!$C$13,0)) | AM37: =IF(COUNT(C37:O37)=0,"",IFERROR(AK37/C37,0)) | AN37: =IF(COUNT(C37:O37)=0,"",IFERROR(AI37/C37,0)) | AO37: =IF(COUNT(C37:O37)=0,"",IFERROR(AL37/G37,0)) | AP37: =IF(COUNT(C37:O37)=0,"",IFERROR(AO37/U37,0)) | AQ37: =IF(COUNT(C37:O37)=0,"",IFERROR(AL37/H37,0))
A38: =Config!$C$6+32 | B38: =INT((A38-Config!$C$6)/7)+1 | P38: =IF(COUNT(C38:O38)=0,"",IFERROR(C38/D38*1000,0)) | Q38: =IF(COUNT(C38:O38)=0,"",IFERROR(D38/E38,0)) | R38: =IF(COUNT(C38:O38)=0,"",IFERROR(F38/D38,0)) | S38: =IF(COUNT(C38:O38)=0,"",IFERROR(C38/F38,0)) | T38: =IF(COUNT(C38:O38)=0,"",IFERROR(G38/F38,0)) | U38: =IF(COUNT(C38:O38)=0,"",IFERROR(C38/G38,0)) | V38: =IF(COUNT(C38:O38)=0,"",IFERROR(G38/D38*1000,0)) | W38: =IF(COUNT(C38:O38)=0,"",IFERROR(H38/G38,0)) | X38: =IF(COUNT(C38:O38)=0,"",IFERROR(C38/H38,0)) | Y38: =IF(COUNT(C38:O38)=0,"",IFERROR(X38/P38,0)) | Z38: =IF(COUNT(C38:O38)=0,"",IFERROR(H38/D38*1000,0)) | AA38: =IF(COUNT(C38:O38)=0,"",IFERROR(I38/H38,0)) | AB38: =IF(COUNT(C38:O38)=0,"",IFERROR(J38/I38,0)) | AC38: =IF(COUNT(C38:O38)=0,"",IFERROR(K38/J38,0)) | AD38: =IF(COUNT(C38:O38)=0,"",IFERROR(C38/K38,0)) | AE38: =IF(COUNT(C38:O38)=0,"",IFERROR(L38/K38,0)) | AF38: =IF(COUNT(C38:O38)=0,"",IFERROR(M38/L38,0)) | AG38: =IF(COUNT(C38:O38)=0,"",IFERROR(M38/H38,0)) | AH38: =IF(COUNT(C38:O38)=0,"",IFERROR(C38/M38,0)) | AI38: =IF(COUNT(C38:O38)=0,"",IFERROR(M38*Config!$C$7+N38*Config!$C$8,0)) | AJ38: =IF(COUNT(C38:O38)=0,"",IFERROR(IF(O38>0,O38,AI38*Config!$C$9),0)) | AK38: =IF(COUNT(C38:O38)=0,"",IFERROR(AJ38*(1-Config!$C$10-Config!$C$11-Config!$C$12),0)) | AL38: =IF(COUNT(C38:O38)=0,"",IFERROR(AK38-C38-Config!$C$13,0)) | AM38: =IF(COUNT(C38:O38)=0,"",IFERROR(AK38/C38,0)) | AN38: =IF(COUNT(C38:O38)=0,"",IFERROR(AI38/C38,0)) | AO38: =IF(COUNT(C38:O38)=0,"",IFERROR(AL38/G38,0)) | AP38: =IF(COUNT(C38:O38)=0,"",IFERROR(AO38/U38,0)) | AQ38: =IF(COUNT(C38:O38)=0,"",IFERROR(AL38/H38,0))
A39: =Config!$C$6+33 | B39: =INT((A39-Config!$C$6)/7)+1 | P39: =IF(COUNT(C39:O39)=0,"",IFERROR(C39/D39*1000,0)) | Q39: =IF(COUNT(C39:O39)=0,"",IFERROR(D39/E39,0)) | R39: =IF(COUNT(C39:O39)=0,"",IFERROR(F39/D39,0)) | S39: =IF(COUNT(C39:O39)=0,"",IFERROR(C39/F39,0)) | T39: =IF(COUNT(C39:O39)=0,"",IFERROR(G39/F39,0)) | U39: =IF(COUNT(C39:O39)=0,"",IFERROR(C39/G39,0)) | V39: =IF(COUNT(C39:O39)=0,"",IFERROR(G39/D39*1000,0)) | W39: =IF(COUNT(C39:O39)=0,"",IFERROR(H39/G39,0)) | X39: =IF(COUNT(C39:O39)=0,"",IFERROR(C39/H39,0)) | Y39: =IF(COUNT(C39:O39)=0,"",IFERROR(X39/P39,0)) | Z39: =IF(COUNT(C39:O39)=0,"",IFERROR(H39/D39*1000,0)) | AA39: =IF(COUNT(C39:O39)=0,"",IFERROR(I39/H39,0)) | AB39: =IF(COUNT(C39:O39)=0,"",IFERROR(J39/I39,0)) | AC39: =IF(COUNT(C39:O39)=0,"",IFERROR(K39/J39,0)) | AD39: =IF(COUNT(C39:O39)=0,"",IFERROR(C39/K39,0)) | AE39: =IF(COUNT(C39:O39)=0,"",IFERROR(L39/K39,0)) | AF39: =IF(COUNT(C39:O39)=0,"",IFERROR(M39/L39,0)) | AG39: =IF(COUNT(C39:O39)=0,"",IFERROR(M39/H39,0)) | AH39: =IF(COUNT(C39:O39)=0,"",IFERROR(C39/M39,0)) | AI39: =IF(COUNT(C39:O39)=0,"",IFERROR(M39*Config!$C$7+N39*Config!$C$8,0)) | AJ39: =IF(COUNT(C39:O39)=0,"",IFERROR(IF(O39>0,O39,AI39*Config!$C$9),0)) | AK39: =IF(COUNT(C39:O39)=0,"",IFERROR(AJ39*(1-Config!$C$10-Config!$C$11-Config!$C$12),0)) | AL39: =IF(COUNT(C39:O39)=0,"",IFERROR(AK39-C39-Config!$C$13,0)) | AM39: =IF(COUNT(C39:O39)=0,"",IFERROR(AK39/C39,0)) | AN39: =IF(COUNT(C39:O39)=0,"",IFERROR(AI39/C39,0)) | AO39: =IF(COUNT(C39:O39)=0,"",IFERROR(AL39/G39,0)) | AP39: =IF(COUNT(C39:O39)=0,"",IFERROR(AO39/U39,0)) | AQ39: =IF(COUNT(C39:O39)=0,"",IFERROR(AL39/H39,0))
A40: =Config!$C$6+34 | B40: =INT((A40-Config!$C$6)/7)+1 | P40: =IF(COUNT(C40:O40)=0,"",IFERROR(C40/D40*1000,0)) | Q40: =IF(COUNT(C40:O40)=0,"",IFERROR(D40/E40,0)) | R40: =IF(COUNT(C40:O40)=0,"",IFERROR(F40/D40,0)) | S40: =IF(COUNT(C40:O40)=0,"",IFERROR(C40/F40,0)) | T40: =IF(COUNT(C40:O40)=0,"",IFERROR(G40/F40,0)) | U40: =IF(COUNT(C40:O40)=0,"",IFERROR(C40/G40,0)) | V40: =IF(COUNT(C40:O40)=0,"",IFERROR(G40/D40*1000,0)) | W40: =IF(COUNT(C40:O40)=0,"",IFERROR(H40/G40,0)) | X40: =IF(COUNT(C40:O40)=0,"",IFERROR(C40/H40,0)) | Y40: =IF(COUNT(C40:O40)=0,"",IFERROR(X40/P40,0)) | Z40: =IF(COUNT(C40:O40)=0,"",IFERROR(H40/D40*1000,0)) | AA40: =IF(COUNT(C40:O40)=0,"",IFERROR(I40/H40,0)) | AB40: =IF(COUNT(C40:O40)=0,"",IFERROR(J40/I40,0)) | AC40: =IF(COUNT(C40:O40)=0,"",IFERROR(K40/J40,0)) | AD40: =IF(COUNT(C40:O40)=0,"",IFERROR(C40/K40,0)) | AE40: =IF(COUNT(C40:O40)=0,"",IFERROR(L40/K40,0)) | AF40: =IF(COUNT(C40:O40)=0,"",IFERROR(M40/L40,0)) | AG40: =IF(COUNT(C40:O40)=0,"",IFERROR(M40/H40,0)) | AH40: =IF(COUNT(C40:O40)=0,"",IFERROR(C40/M40,0)) | AI40: =IF(COUNT(C40:O40)=0,"",IFERROR(M40*Config!$C$7+N40*Config!$C$8,0)) | AJ40: =IF(COUNT(C40:O40)=0,"",IFERROR(IF(O40>0,O40,AI40*Config!$C$9),0)) | AK40: =IF(COUNT(C40:O40)=0,"",IFERROR(AJ40*(1-Config!$C$10-Config!$C$11-Config!$C$12),0)) | AL40: =IF(COUNT(C40:O40)=0,"",IFERROR(AK40-C40-Config!$C$13,0)) | AM40: =IF(COUNT(C40:O40)=0,"",IFERROR(AK40/C40,0)) | AN40: =IF(COUNT(C40:O40)=0,"",IFERROR(AI40/C40,0)) | AO40: =IF(COUNT(C40:O40)=0,"",IFERROR(AL40/G40,0)) | AP40: =IF(COUNT(C40:O40)=0,"",IFERROR(AO40/U40,0)) | AQ40: =IF(COUNT(C40:O40)=0,"",IFERROR(AL40/H40,0))
A41: =Config!$C$6+35 | B41: =INT((A41-Config!$C$6)/7)+1 | P41: =IF(COUNT(C41:O41)=0,"",IFERROR(C41/D41*1000,0)) | Q41: =IF(COUNT(C41:O41)=0,"",IFERROR(D41/E41,0)) | R41: =IF(COUNT(C41:O41)=0,"",IFERROR(F41/D41,0)) | S41: =IF(COUNT(C41:O41)=0,"",IFERROR(C41/F41,0)) | T41: =IF(COUNT(C41:O41)=0,"",IFERROR(G41/F41,0)) | U41: =IF(COUNT(C41:O41)=0,"",IFERROR(C41/G41,0)) | V41: =IF(COUNT(C41:O41)=0,"",IFERROR(G41/D41*1000,0)) | W41: =IF(COUNT(C41:O41)=0,"",IFERROR(H41/G41,0)) | X41: =IF(COUNT(C41:O41)=0,"",IFERROR(C41/H41,0)) | Y41: =IF(COUNT(C41:O41)=0,"",IFERROR(X41/P41,0)) | Z41: =IF(COUNT(C41:O41)=0,"",IFERROR(H41/D41*1000,0)) | AA41: =IF(COUNT(C41:O41)=0,"",IFERROR(I41/H41,0)) | AB41: =IF(COUNT(C41:O41)=0,"",IFERROR(J41/I41,0)) | AC41: =IF(COUNT(C41:O41)=0,"",IFERROR(K41/J41,0)) | AD41: =IF(COUNT(C41:O41)=0,"",IFERROR(C41/K41,0)) | AE41: =IF(COUNT(C41:O41)=0,"",IFERROR(L41/K41,0)) | AF41: =IF(COUNT(C41:O41)=0,"",IFERROR(M41/L41,0)) | AG41: =IF(COUNT(C41:O41)=0,"",IFERROR(M41/H41,0)) | AH41: =IF(COUNT(C41:O41)=0,"",IFERROR(C41/M41,0)) | AI41: =IF(COUNT(C41:O41)=0,"",IFERROR(M41*Config!$C$7+N41*Config!$C$8,0)) | AJ41: =IF(COUNT(C41:O41)=0,"",IFERROR(IF(O41>0,O41,AI41*Config!$C$9),0)) | AK41: =IF(COUNT(C41:O41)=0,"",IFERROR(AJ41*(1-Config!$C$10-Config!$C$11-Config!$C$12),0)) | AL41: =IF(COUNT(C41:O41)=0,"",IFERROR(AK41-C41-Config!$C$13,0)) | AM41: =IF(COUNT(C41:O41)=0,"",IFERROR(AK41/C41,0)) | AN41: =IF(COUNT(C41:O41)=0,"",IFERROR(AI41/C41,0)) | AO41: =IF(COUNT(C41:O41)=0,"",IFERROR(AL41/G41,0)) | AP41: =IF(COUNT(C41:O41)=0,"",IFERROR(AO41/U41,0)) | AQ41: =IF(COUNT(C41:O41)=0,"",IFERROR(AL41/H41,0))
A42: =Config!$C$6+36 | B42: =INT((A42-Config!$C$6)/7)+1 | P42: =IF(COUNT(C42:O42)=0,"",IFERROR(C42/D42*1000,0)) | Q42: =IF(COUNT(C42:O42)=0,"",IFERROR(D42/E42,0)) | R42: =IF(COUNT(C42:O42)=0,"",IFERROR(F42/D42,0)) | S42: =IF(COUNT(C42:O42)=0,"",IFERROR(C42/F42,0)) | T42: =IF(COUNT(C42:O42)=0,"",IFERROR(G42/F42,0)) | U42: =IF(COUNT(C42:O42)=0,"",IFERROR(C42/G42,0)) | V42: =IF(COUNT(C42:O42)=0,"",IFERROR(G42/D42*1000,0)) | W42: =IF(COUNT(C42:O42)=0,"",IFERROR(H42/G42,0)) | X42: =IF(COUNT(C42:O42)=0,"",IFERROR(C42/H42,0)) | Y42: =IF(COUNT(C42:O42)=0,"",IFERROR(X42/P42,0)) | Z42: =IF(COUNT(C42:O42)=0,"",IFERROR(H42/D42*1000,0)) | AA42: =IF(COUNT(C42:O42)=0,"",IFERROR(I42/H42,0)) | AB42: =IF(COUNT(C42:O42)=0,"",IFERROR(J42/I42,0)) | AC42: =IF(COUNT(C42:O42)=0,"",IFERROR(K42/J42,0)) | AD42: =IF(COUNT(C42:O42)=0,"",IFERROR(C42/K42,0)) | AE42: =IF(COUNT(C42:O42)=0,"",IFERROR(L42/K42,0)) | AF42: =IF(COUNT(C42:O42)=0,"",IFERROR(M42/L42,0)) | AG42: =IF(COUNT(C42:O42)=0,"",IFERROR(M42/H42,0)) | AH42: =IF(COUNT(C42:O42)=0,"",IFERROR(C42/M42,0)) | AI42: =IF(COUNT(C42:O42)=0,"",IFERROR(M42*Config!$C$7+N42*Config!$C$8,0)) | AJ42: =IF(COUNT(C42:O42)=0,"",IFERROR(IF(O42>0,O42,AI42*Config!$C$9),0)) | AK42: =IF(COUNT(C42:O42)=0,"",IFERROR(AJ42*(1-Config!$C$10-Config!$C$11-Config!$C$12),0)) | AL42: =IF(COUNT(C42:O42)=0,"",IFERROR(AK42-C42-Config!$C$13,0)) | AM42: =IF(COUNT(C42:O42)=0,"",IFERROR(AK42/C42,0)) | AN42: =IF(COUNT(C42:O42)=0,"",IFERROR(AI42/C42,0)) | AO42: =IF(COUNT(C42:O42)=0,"",IFERROR(AL42/G42,0)) | AP42: =IF(COUNT(C42:O42)=0,"",IFERROR(AO42/U42,0)) | AQ42: =IF(COUNT(C42:O42)=0,"",IFERROR(AL42/H42,0))
A43: =Config!$C$6+37 | B43: =INT((A43-Config!$C$6)/7)+1 | P43: =IF(COUNT(C43:O43)=0,"",IFERROR(C43/D43*1000,0)) | Q43: =IF(COUNT(C43:O43)=0,"",IFERROR(D43/E43,0)) | R43: =IF(COUNT(C43:O43)=0,"",IFERROR(F43/D43,0)) | S43: =IF(COUNT(C43:O43)=0,"",IFERROR(C43/F43,0)) | T43: =IF(COUNT(C43:O43)=0,"",IFERROR(G43/F43,0)) | U43: =IF(COUNT(C43:O43)=0,"",IFERROR(C43/G43,0)) | V43: =IF(COUNT(C43:O43)=0,"",IFERROR(G43/D43*1000,0)) | W43: =IF(COUNT(C43:O43)=0,"",IFERROR(H43/G43,0)) | X43: =IF(COUNT(C43:O43)=0,"",IFERROR(C43/H43,0)) | Y43: =IF(COUNT(C43:O43)=0,"",IFERROR(X43/P43,0)) | Z43: =IF(COUNT(C43:O43)=0,"",IFERROR(H43/D43*1000,0)) | AA43: =IF(COUNT(C43:O43)=0,"",IFERROR(I43/H43,0)) | AB43: =IF(COUNT(C43:O43)=0,"",IFERROR(J43/I43,0)) | AC43: =IF(COUNT(C43:O43)=0,"",IFERROR(K43/J43,0)) | AD43: =IF(COUNT(C43:O43)=0,"",IFERROR(C43/K43,0)) | AE43: =IF(COUNT(C43:O43)=0,"",IFERROR(L43/K43,0)) | AF43: =IF(COUNT(C43:O43)=0,"",IFERROR(M43/L43,0)) | AG43: =IF(COUNT(C43:O43)=0,"",IFERROR(M43/H43,0)) | AH43: =IF(COUNT(C43:O43)=0,"",IFERROR(C43/M43,0)) | AI43: =IF(COUNT(C43:O43)=0,"",IFERROR(M43*Config!$C$7+N43*Config!$C$8,0)) | AJ43: =IF(COUNT(C43:O43)=0,"",IFERROR(IF(O43>0,O43,AI43*Config!$C$9),0)) | AK43: =IF(COUNT(C43:O43)=0,"",IFERROR(AJ43*(1-Config!$C$10-Config!$C$11-Config!$C$12),0)) | AL43: =IF(COUNT(C43:O43)=0,"",IFERROR(AK43-C43-Config!$C$13,0)) | AM43: =IF(COUNT(C43:O43)=0,"",IFERROR(AK43/C43,0)) | AN43: =IF(COUNT(C43:O43)=0,"",IFERROR(AI43/C43,0)) | AO43: =IF(COUNT(C43:O43)=0,"",IFERROR(AL43/G43,0)) | AP43: =IF(COUNT(C43:O43)=0,"",IFERROR(AO43/U43,0)) | AQ43: =IF(COUNT(C43:O43)=0,"",IFERROR(AL43/H43,0))
A44: =Config!$C$6+38 | B44: =INT((A44-Config!$C$6)/7)+1 | P44: =IF(COUNT(C44:O44)=0,"",IFERROR(C44/D44*1000,0)) | Q44: =IF(COUNT(C44:O44)=0,"",IFERROR(D44/E44,0)) | R44: =IF(COUNT(C44:O44)=0,"",IFERROR(F44/D44,0)) | S44: =IF(COUNT(C44:O44)=0,"",IFERROR(C44/F44,0)) | T44: =IF(COUNT(C44:O44)=0,"",IFERROR(G44/F44,0)) | U44: =IF(COUNT(C44:O44)=0,"",IFERROR(C44/G44,0)) | V44: =IF(COUNT(C44:O44)=0,"",IFERROR(G44/D44*1000,0)) | W44: =IF(COUNT(C44:O44)=0,"",IFERROR(H44/G44,0)) | X44: =IF(COUNT(C44:O44)=0,"",IFERROR(C44/H44,0)) | Y44: =IF(COUNT(C44:O44)=0,"",IFERROR(X44/P44,0)) | Z44: =IF(COUNT(C44:O44)=0,"",IFERROR(H44/D44*1000,0)) | AA44: =IF(COUNT(C44:O44)=0,"",IFERROR(I44/H44,0)) | AB44: =IF(COUNT(C44:O44)=0,"",IFERROR(J44/I44,0)) | AC44: =IF(COUNT(C44:O44)=0,"",IFERROR(K44/J44,0)) | AD44: =IF(COUNT(C44:O44)=0,"",IFERROR(C44/K44,0)) | AE44: =IF(COUNT(C44:O44)=0,"",IFERROR(L44/K44,0)) | AF44: =IF(COUNT(C44:O44)=0,"",IFERROR(M44/L44,0)) | AG44: =IF(COUNT(C44:O44)=0,"",IFERROR(M44/H44,0)) | AH44: =IF(COUNT(C44:O44)=0,"",IFERROR(C44/M44,0)) | AI44: =IF(COUNT(C44:O44)=0,"",IFERROR(M44*Config!$C$7+N44*Config!$C$8,0)) | AJ44: =IF(COUNT(C44:O44)=0,"",IFERROR(IF(O44>0,O44,AI44*Config!$C$9),0)) | AK44: =IF(COUNT(C44:O44)=0,"",IFERROR(AJ44*(1-Config!$C$10-Config!$C$11-Config!$C$12),0)) | AL44: =IF(COUNT(C44:O44)=0,"",IFERROR(AK44-C44-Config!$C$13,0)) | AM44: =IF(COUNT(C44:O44)=0,"",IFERROR(AK44/C44,0)) | AN44: =IF(COUNT(C44:O44)=0,"",IFERROR(AI44/C44,0)) | AO44: =IF(COUNT(C44:O44)=0,"",IFERROR(AL44/G44,0)) | AP44: =IF(COUNT(C44:O44)=0,"",IFERROR(AO44/U44,0)) | AQ44: =IF(COUNT(C44:O44)=0,"",IFERROR(AL44/H44,0))
A45: =Config!$C$6+39 | B45: =INT((A45-Config!$C$6)/7)+1 | P45: =IF(COUNT(C45:O45)=0,"",IFERROR(C45/D45*1000,0)) | Q45: =IF(COUNT(C45:O45)=0,"",IFERROR(D45/E45,0)) | R45: =IF(COUNT(C45:O45)=0,"",IFERROR(F45/D45,0)) | S45: =IF(COUNT(C45:O45)=0,"",IFERROR(C45/F45,0)) | T45: =IF(COUNT(C45:O45)=0,"",IFERROR(G45/F45,0)) | U45: =IF(COUNT(C45:O45)=0,"",IFERROR(C45/G45,0)) | V45: =IF(COUNT(C45:O45)=0,"",IFERROR(G45/D45*1000,0)) | W45: =IF(COUNT(C45:O45)=0,"",IFERROR(H45/G45,0)) | X45: =IF(COUNT(C45:O45)=0,"",IFERROR(C45/H45,0)) | Y45: =IF(COUNT(C45:O45)=0,"",IFERROR(X45/P45,0)) | Z45: =IF(COUNT(C45:O45)=0,"",IFERROR(H45/D45*1000,0)) | AA45: =IF(COUNT(C45:O45)=0,"",IFERROR(I45/H45,0)) | AB45: =IF(COUNT(C45:O45)=0,"",IFERROR(J45/I45,0)) | AC45: =IF(COUNT(C45:O45)=0,"",IFERROR(K45/J45,0)) | AD45: =IF(COUNT(C45:O45)=0,"",IFERROR(C45/K45,0)) | AE45: =IF(COUNT(C45:O45)=0,"",IFERROR(L45/K45,0)) | AF45: =IF(COUNT(C45:O45)=0,"",IFERROR(M45/L45,0)) | AG45: =IF(COUNT(C45:O45)=0,"",IFERROR(M45/H45,0)) | AH45: =IF(COUNT(C45:O45)=0,"",IFERROR(C45/M45,0)) | AI45: =IF(COUNT(C45:O45)=0,"",IFERROR(M45*Config!$C$7+N45*Config!$C$8,0)) | AJ45: =IF(COUNT(C45:O45)=0,"",IFERROR(IF(O45>0,O45,AI45*Config!$C$9),0)) | AK45: =IF(COUNT(C45:O45)=0,"",IFERROR(AJ45*(1-Config!$C$10-Config!$C$11-Config!$C$12),0)) | AL45: =IF(COUNT(C45:O45)=0,"",IFERROR(AK45-C45-Config!$C$13,0)) | AM45: =IF(COUNT(C45:O45)=0,"",IFERROR(AK45/C45,0)) | AN45: =IF(COUNT(C45:O45)=0,"",IFERROR(AI45/C45,0)) | AO45: =IF(COUNT(C45:O45)=0,"",IFERROR(AL45/G45,0)) | AP45: =IF(COUNT(C45:O45)=0,"",IFERROR(AO45/U45,0)) | AQ45: =IF(COUNT(C45:O45)=0,"",IFERROR(AL45/H45,0))
A46: =Config!$C$6+40 | B46: =INT((A46-Config!$C$6)/7)+1 | P46: =IF(COUNT(C46:O46)=0,"",IFERROR(C46/D46*1000,0)) | Q46: =IF(COUNT(C46:O46)=0,"",IFERROR(D46/E46,0)) | R46: =IF(COUNT(C46:O46)=0,"",IFERROR(F46/D46,0)) | S46: =IF(COUNT(C46:O46)=0,"",IFERROR(C46/F46,0)) | T46: =IF(COUNT(C46:O46)=0,"",IFERROR(G46/F46,0)) | U46: =IF(COUNT(C46:O46)=0,"",IFERROR(C46/G46,0)) | V46: =IF(COUNT(C46:O46)=0,"",IFERROR(G46/D46*1000,0)) | W46: =IF(COUNT(C46:O46)=0,"",IFERROR(H46/G46,0)) | X46: =IF(COUNT(C46:O46)=0,"",IFERROR(C46/H46,0)) | Y46: =IF(COUNT(C46:O46)=0,"",IFERROR(X46/P46,0)) | Z46: =IF(COUNT(C46:O46)=0,"",IFERROR(H46/D46*1000,0)) | AA46: =IF(COUNT(C46:O46)=0,"",IFERROR(I46/H46,0)) | AB46: =IF(COUNT(C46:O46)=0,"",IFERROR(J46/I46,0)) | AC46: =IF(COUNT(C46:O46)=0,"",IFERROR(K46/J46,0)) | AD46: =IF(COUNT(C46:O46)=0,"",IFERROR(C46/K46,0)) | AE46: =IF(COUNT(C46:O46)=0,"",IFERROR(L46/K46,0)) | AF46: =IF(COUNT(C46:O46)=0,"",IFERROR(M46/L46,0)) | AG46: =IF(COUNT(C46:O46)=0,"",IFERROR(M46/H46,0)) | AH46: =IF(COUNT(C46:O46)=0,"",IFERROR(C46/M46,0)) | AI46: =IF(COUNT(C46:O46)=0,"",IFERROR(M46*Config!$C$7+N46*Config!$C$8,0)) | AJ46: =IF(COUNT(C46:O46)=0,"",IFERROR(IF(O46>0,O46,AI46*Config!$C$9),0)) | AK46: =IF(COUNT(C46:O46)=0,"",IFERROR(AJ46*(1-Config!$C$10-Config!$C$11-Config!$C$12),0)) | AL46: =IF(COUNT(C46:O46)=0,"",IFERROR(AK46-C46-Config!$C$13,0)) | AM46: =IF(COUNT(C46:O46)=0,"",IFERROR(AK46/C46,0)) | AN46: =IF(COUNT(C46:O46)=0,"",IFERROR(AI46/C46,0)) | AO46: =IF(COUNT(C46:O46)=0,"",IFERROR(AL46/G46,0)) | AP46: =IF(COUNT(C46:O46)=0,"",IFERROR(AO46/U46,0)) | AQ46: =IF(COUNT(C46:O46)=0,"",IFERROR(AL46/H46,0))
A47: =Config!$C$6+41 | B47: =INT((A47-Config!$C$6)/7)+1 | P47: =IF(COUNT(C47:O47)=0,"",IFERROR(C47/D47*1000,0)) | Q47: =IF(COUNT(C47:O47)=0,"",IFERROR(D47/E47,0)) | R47: =IF(COUNT(C47:O47)=0,"",IFERROR(F47/D47,0)) | S47: =IF(COUNT(C47:O47)=0,"",IFERROR(C47/F47,0)) | T47: =IF(COUNT(C47:O47)=0,"",IFERROR(G47/F47,0)) | U47: =IF(COUNT(C47:O47)=0,"",IFERROR(C47/G47,0)) | V47: =IF(COUNT(C47:O47)=0,"",IFERROR(G47/D47*1000,0)) | W47: =IF(COUNT(C47:O47)=0,"",IFERROR(H47/G47,0)) | X47: =IF(COUNT(C47:O47)=0,"",IFERROR(C47/H47,0)) | Y47: =IF(COUNT(C47:O47)=0,"",IFERROR(X47/P47,0)) | Z47: =IF(COUNT(C47:O47)=0,"",IFERROR(H47/D47*1000,0)) | AA47: =IF(COUNT(C47:O47)=0,"",IFERROR(I47/H47,0)) | AB47: =IF(COUNT(C47:O47)=0,"",IFERROR(J47/I47,0)) | AC47: =IF(COUNT(C47:O47)=0,"",IFERROR(K47/J47,0)) | AD47: =IF(COUNT(C47:O47)=0,"",IFERROR(C47/K47,0)) | AE47: =IF(COUNT(C47:O47)=0,"",IFERROR(L47/K47,0)) | AF47: =IF(COUNT(C47:O47)=0,"",IFERROR(M47/L47,0)) | AG47: =IF(COUNT(C47:O47)=0,"",IFERROR(M47/H47,0)) | AH47: =IF(COUNT(C47:O47)=0,"",IFERROR(C47/M47,0)) | AI47: =IF(COUNT(C47:O47)=0,"",IFERROR(M47*Config!$C$7+N47*Config!$C$8,0)) | AJ47: =IF(COUNT(C47:O47)=0,"",IFERROR(IF(O47>0,O47,AI47*Config!$C$9),0)) | AK47: =IF(COUNT(C47:O47)=0,"",IFERROR(AJ47*(1-Config!$C$10-Config!$C$11-Config!$C$12),0)) | AL47: =IF(COUNT(C47:O47)=0,"",IFERROR(AK47-C47-Config!$C$13,0)) | AM47: =IF(COUNT(C47:O47)=0,"",IFERROR(AK47/C47,0)) | AN47: =IF(COUNT(C47:O47)=0,"",IFERROR(AI47/C47,0)) | AO47: =IF(COUNT(C47:O47)=0,"",IFERROR(AL47/G47,0)) | AP47: =IF(COUNT(C47:O47)=0,"",IFERROR(AO47/U47,0)) | AQ47: =IF(COUNT(C47:O47)=0,"",IFERROR(AL47/H47,0))
A48: =Config!$C$6+42 | B48: =INT((A48-Config!$C$6)/7)+1 | P48: =IF(COUNT(C48:O48)=0,"",IFERROR(C48/D48*1000,0)) | Q48: =IF(COUNT(C48:O48)=0,"",IFERROR(D48/E48,0)) | R48: =IF(COUNT(C48:O48)=0,"",IFERROR(F48/D48,0)) | S48: =IF(COUNT(C48:O48)=0,"",IFERROR(C48/F48,0)) | T48: =IF(COUNT(C48:O48)=0,"",IFERROR(G48/F48,0)) | U48: =IF(COUNT(C48:O48)=0,"",IFERROR(C48/G48,0)) | V48: =IF(COUNT(C48:O48)=0,"",IFERROR(G48/D48*1000,0)) | W48: =IF(COUNT(C48:O48)=0,"",IFERROR(H48/G48,0)) | X48: =IF(COUNT(C48:O48)=0,"",IFERROR(C48/H48,0)) | Y48: =IF(COUNT(C48:O48)=0,"",IFERROR(X48/P48,0)) | Z48: =IF(COUNT(C48:O48)=0,"",IFERROR(H48/D48*1000,0)) | AA48: =IF(COUNT(C48:O48)=0,"",IFERROR(I48/H48,0)) | AB48: =IF(COUNT(C48:O48)=0,"",IFERROR(J48/I48,0)) | AC48: =IF(COUNT(C48:O48)=0,"",IFERROR(K48/J48,0)) | AD48: =IF(COUNT(C48:O48)=0,"",IFERROR(C48/K48,0)) | AE48: =IF(COUNT(C48:O48)=0,"",IFERROR(L48/K48,0)) | AF48: =IF(COUNT(C48:O48)=0,"",IFERROR(M48/L48,0)) | AG48: =IF(COUNT(C48:O48)=0,"",IFERROR(M48/H48,0)) | AH48: =IF(COUNT(C48:O48)=0,"",IFERROR(C48/M48,0)) | AI48: =IF(COUNT(C48:O48)=0,"",IFERROR(M48*Config!$C$7+N48*Config!$C$8,0)) | AJ48: =IF(COUNT(C48:O48)=0,"",IFERROR(IF(O48>0,O48,AI48*Config!$C$9),0)) | AK48: =IF(COUNT(C48:O48)=0,"",IFERROR(AJ48*(1-Config!$C$10-Config!$C$11-Config!$C$12),0)) | AL48: =IF(COUNT(C48:O48)=0,"",IFERROR(AK48-C48-Config!$C$13,0)) | AM48: =IF(COUNT(C48:O48)=0,"",IFERROR(AK48/C48,0)) | AN48: =IF(COUNT(C48:O48)=0,"",IFERROR(AI48/C48,0)) | AO48: =IF(COUNT(C48:O48)=0,"",IFERROR(AL48/G48,0)) | AP48: =IF(COUNT(C48:O48)=0,"",IFERROR(AO48/U48,0)) | AQ48: =IF(COUNT(C48:O48)=0,"",IFERROR(AL48/H48,0))
A49: =Config!$C$6+43 | B49: =INT((A49-Config!$C$6)/7)+1 | P49: =IF(COUNT(C49:O49)=0,"",IFERROR(C49/D49*1000,0)) | Q49: =IF(COUNT(C49:O49)=0,"",IFERROR(D49/E49,0)) | R49: =IF(COUNT(C49:O49)=0,"",IFERROR(F49/D49,0)) | S49: =IF(COUNT(C49:O49)=0,"",IFERROR(C49/F49,0)) | T49: =IF(COUNT(C49:O49)=0,"",IFERROR(G49/F49,0)) | U49: =IF(COUNT(C49:O49)=0,"",IFERROR(C49/G49,0)) | V49: =IF(COUNT(C49:O49)=0,"",IFERROR(G49/D49*1000,0)) | W49: =IF(COUNT(C49:O49)=0,"",IFERROR(H49/G49,0)) | X49: =IF(COUNT(C49:O49)=0,"",IFERROR(C49/H49,0)) | Y49: =IF(COUNT(C49:O49)=0,"",IFERROR(X49/P49,0)) | Z49: =IF(COUNT(C49:O49)=0,"",IFERROR(H49/D49*1000,0)) | AA49: =IF(COUNT(C49:O49)=0,"",IFERROR(I49/H49,0)) | AB49: =IF(COUNT(C49:O49)=0,"",IFERROR(J49/I49,0)) | AC49: =IF(COUNT(C49:O49)=0,"",IFERROR(K49/J49,0)) | AD49: =IF(COUNT(C49:O49)=0,"",IFERROR(C49/K49,0)) | AE49: =IF(COUNT(C49:O49)=0,"",IFERROR(L49/K49,0)) | AF49: =IF(COUNT(C49:O49)=0,"",IFERROR(M49/L49,0)) | AG49: =IF(COUNT(C49:O49)=0,"",IFERROR(M49/H49,0)) | AH49: =IF(COUNT(C49:O49)=0,"",IFERROR(C49/M49,0)) | AI49: =IF(COUNT(C49:O49)=0,"",IFERROR(M49*Config!$C$7+N49*Config!$C$8,0)) | AJ49: =IF(COUNT(C49:O49)=0,"",IFERROR(IF(O49>0,O49,AI49*Config!$C$9),0)) | AK49: =IF(COUNT(C49:O49)=0,"",IFERROR(AJ49*(1-Config!$C$10-Config!$C$11-Config!$C$12),0)) | AL49: =IF(COUNT(C49:O49)=0,"",IFERROR(AK49-C49-Config!$C$13,0)) | AM49: =IF(COUNT(C49:O49)=0,"",IFERROR(AK49/C49,0)) | AN49: =IF(COUNT(C49:O49)=0,"",IFERROR(AI49/C49,0)) | AO49: =IF(COUNT(C49:O49)=0,"",IFERROR(AL49/G49,0)) | AP49: =IF(COUNT(C49:O49)=0,"",IFERROR(AO49/U49,0)) | AQ49: =IF(COUNT(C49:O49)=0,"",IFERROR(AL49/H49,0))
A50: =Config!$C$6+44 | B50: =INT((A50-Config!$C$6)/7)+1 | P50: =IF(COUNT(C50:O50)=0,"",IFERROR(C50/D50*1000,0)) | Q50: =IF(COUNT(C50:O50)=0,"",IFERROR(D50/E50,0)) | R50: =IF(COUNT(C50:O50)=0,"",IFERROR(F50/D50,0)) | S50: =IF(COUNT(C50:O50)=0,"",IFERROR(C50/F50,0)) | T50: =IF(COUNT(C50:O50)=0,"",IFERROR(G50/F50,0)) | U50: =IF(COUNT(C50:O50)=0,"",IFERROR(C50/G50,0)) | V50: =IF(COUNT(C50:O50)=0,"",IFERROR(G50/D50*1000,0)) | W50: =IF(COUNT(C50:O50)=0,"",IFERROR(H50/G50,0)) | X50: =IF(COUNT(C50:O50)=0,"",IFERROR(C50/H50,0)) | Y50: =IF(COUNT(C50:O50)=0,"",IFERROR(X50/P50,0)) | Z50: =IF(COUNT(C50:O50)=0,"",IFERROR(H50/D50*1000,0)) | AA50: =IF(COUNT(C50:O50)=0,"",IFERROR(I50/H50,0)) | AB50: =IF(COUNT(C50:O50)=0,"",IFERROR(J50/I50,0)) | AC50: =IF(COUNT(C50:O50)=0,"",IFERROR(K50/J50,0)) | AD50: =IF(COUNT(C50:O50)=0,"",IFERROR(C50/K50,0)) | AE50: =IF(COUNT(C50:O50)=0,"",IFERROR(L50/K50,0)) | AF50: =IF(COUNT(C50:O50)=0,"",IFERROR(M50/L50,0)) | AG50: =IF(COUNT(C50:O50)=0,"",IFERROR(M50/H50,0)) | AH50: =IF(COUNT(C50:O50)=0,"",IFERROR(C50/M50,0)) | AI50: =IF(COUNT(C50:O50)=0,"",IFERROR(M50*Config!$C$7+N50*Config!$C$8,0)) | AJ50: =IF(COUNT(C50:O50)=0,"",IFERROR(IF(O50>0,O50,AI50*Config!$C$9),0)) | AK50: =IF(COUNT(C50:O50)=0,"",IFERROR(AJ50*(1-Config!$C$10-Config!$C$11-Config!$C$12),0)) | AL50: =IF(COUNT(C50:O50)=0,"",IFERROR(AK50-C50-Config!$C$13,0)) | AM50: =IF(COUNT(C50:O50)=0,"",IFERROR(AK50/C50,0)) | AN50: =IF(COUNT(C50:O50)=0,"",IFERROR(AI50/C50,0)) | AO50: =IF(COUNT(C50:O50)=0,"",IFERROR(AL50/G50,0)) | AP50: =IF(COUNT(C50:O50)=0,"",IFERROR(AO50/U50,0)) | AQ50: =IF(COUNT(C50:O50)=0,"",IFERROR(AL50/H50,0))
A51: =Config!$C$6+45 | B51: =INT((A51-Config!$C$6)/7)+1 | P51: =IF(COUNT(C51:O51)=0,"",IFERROR(C51/D51*1000,0)) | Q51: =IF(COUNT(C51:O51)=0,"",IFERROR(D51/E51,0)) | R51: =IF(COUNT(C51:O51)=0,"",IFERROR(F51/D51,0)) | S51: =IF(COUNT(C51:O51)=0,"",IFERROR(C51/F51,0)) | T51: =IF(COUNT(C51:O51)=0,"",IFERROR(G51/F51,0)) | U51: =IF(COUNT(C51:O51)=0,"",IFERROR(C51/G51,0)) | V51: =IF(COUNT(C51:O51)=0,"",IFERROR(G51/D51*1000,0)) | W51: =IF(COUNT(C51:O51)=0,"",IFERROR(H51/G51,0)) | X51: =IF(COUNT(C51:O51)=0,"",IFERROR(C51/H51,0)) | Y51: =IF(COUNT(C51:O51)=0,"",IFERROR(X51/P51,0)) | Z51: =IF(COUNT(C51:O51)=0,"",IFERROR(H51/D51*1000,0)) | AA51: =IF(COUNT(C51:O51)=0,"",IFERROR(I51/H51,0)) | AB51: =IF(COUNT(C51:O51)=0,"",IFERROR(J51/I51,0)) | AC51: =IF(COUNT(C51:O51)=0,"",IFERROR(K51/J51,0)) | AD51: =IF(COUNT(C51:O51)=0,"",IFERROR(C51/K51,0)) | AE51: =IF(COUNT(C51:O51)=0,"",IFERROR(L51/K51,0)) | AF51: =IF(COUNT(C51:O51)=0,"",IFERROR(M51/L51,0)) | AG51: =IF(COUNT(C51:O51)=0,"",IFERROR(M51/H51,0)) | AH51: =IF(COUNT(C51:O51)=0,"",IFERROR(C51/M51,0)) | AI51: =IF(COUNT(C51:O51)=0,"",IFERROR(M51*Config!$C$7+N51*Config!$C$8,0)) | AJ51: =IF(COUNT(C51:O51)=0,"",IFERROR(IF(O51>0,O51,AI51*Config!$C$9),0)) | AK51: =IF(COUNT(C51:O51)=0,"",IFERROR(AJ51*(1-Config!$C$10-Config!$C$11-Config!$C$12),0)) | AL51: =IF(COUNT(C51:O51)=0,"",IFERROR(AK51-C51-Config!$C$13,0)) | AM51: =IF(COUNT(C51:O51)=0,"",IFERROR(AK51/C51,0)) | AN51: =IF(COUNT(C51:O51)=0,"",IFERROR(AI51/C51,0)) | AO51: =IF(COUNT(C51:O51)=0,"",IFERROR(AL51/G51,0)) | AP51: =IF(COUNT(C51:O51)=0,"",IFERROR(AO51/U51,0)) | AQ51: =IF(COUNT(C51:O51)=0,"",IFERROR(AL51/H51,0))
A52: =Config!$C$6+46 | B52: =INT((A52-Config!$C$6)/7)+1 | P52: =IF(COUNT(C52:O52)=0,"",IFERROR(C52/D52*1000,0)) | Q52: =IF(COUNT(C52:O52)=0,"",IFERROR(D52/E52,0)) | R52: =IF(COUNT(C52:O52)=0,"",IFERROR(F52/D52,0)) | S52: =IF(COUNT(C52:O52)=0,"",IFERROR(C52/F52,0)) | T52: =IF(COUNT(C52:O52)=0,"",IFERROR(G52/F52,0)) | U52: =IF(COUNT(C52:O52)=0,"",IFERROR(C52/G52,0)) | V52: =IF(COUNT(C52:O52)=0,"",IFERROR(G52/D52*1000,0)) | W52: =IF(COUNT(C52:O52)=0,"",IFERROR(H52/G52,0)) | X52: =IF(COUNT(C52:O52)=0,"",IFERROR(C52/H52,0)) | Y52: =IF(COUNT(C52:O52)=0,"",IFERROR(X52/P52,0)) | Z52: =IF(COUNT(C52:O52)=0,"",IFERROR(H52/D52*1000,0)) | AA52: =IF(COUNT(C52:O52)=0,"",IFERROR(I52/H52,0)) | AB52: =IF(COUNT(C52:O52)=0,"",IFERROR(J52/I52,0)) | AC52: =IF(COUNT(C52:O52)=0,"",IFERROR(K52/J52,0)) | AD52: =IF(COUNT(C52:O52)=0,"",IFERROR(C52/K52,0)) | AE52: =IF(COUNT(C52:O52)=0,"",IFERROR(L52/K52,0)) | AF52: =IF(COUNT(C52:O52)=0,"",IFERROR(M52/L52,0)) | AG52: =IF(COUNT(C52:O52)=0,"",IFERROR(M52/H52,0)) | AH52: =IF(COUNT(C52:O52)=0,"",IFERROR(C52/M52,0)) | AI52: =IF(COUNT(C52:O52)=0,"",IFERROR(M52*Config!$C$7+N52*Config!$C$8,0)) | AJ52: =IF(COUNT(C52:O52)=0,"",IFERROR(IF(O52>0,O52,AI52*Config!$C$9),0)) | AK52: =IF(COUNT(C52:O52)=0,"",IFERROR(AJ52*(1-Config!$C$10-Config!$C$11-Config!$C$12),0)) | AL52: =IF(COUNT(C52:O52)=0,"",IFERROR(AK52-C52-Config!$C$13,0)) | AM52: =IF(COUNT(C52:O52)=0,"",IFERROR(AK52/C52,0)) | AN52: =IF(COUNT(C52:O52)=0,"",IFERROR(AI52/C52,0)) | AO52: =IF(COUNT(C52:O52)=0,"",IFERROR(AL52/G52,0)) | AP52: =IF(COUNT(C52:O52)=0,"",IFERROR(AO52/U52,0)) | AQ52: =IF(COUNT(C52:O52)=0,"",IFERROR(AL52/H52,0))
A53: =Config!$C$6+47 | B53: =INT((A53-Config!$C$6)/7)+1 | P53: =IF(COUNT(C53:O53)=0,"",IFERROR(C53/D53*1000,0)) | Q53: =IF(COUNT(C53:O53)=0,"",IFERROR(D53/E53,0)) | R53: =IF(COUNT(C53:O53)=0,"",IFERROR(F53/D53,0)) | S53: =IF(COUNT(C53:O53)=0,"",IFERROR(C53/F53,0)) | T53: =IF(COUNT(C53:O53)=0,"",IFERROR(G53/F53,0)) | U53: =IF(COUNT(C53:O53)=0,"",IFERROR(C53/G53,0)) | V53: =IF(COUNT(C53:O53)=0,"",IFERROR(G53/D53*1000,0)) | W53: =IF(COUNT(C53:O53)=0,"",IFERROR(H53/G53,0)) | X53: =IF(COUNT(C53:O53)=0,"",IFERROR(C53/H53,0)) | Y53: =IF(COUNT(C53:O53)=0,"",IFERROR(X53/P53,0)) | Z53: =IF(COUNT(C53:O53)=0,"",IFERROR(H53/D53*1000,0)) | AA53: =IF(COUNT(C53:O53)=0,"",IFERROR(I53/H53,0)) | AB53: =IF(COUNT(C53:O53)=0,"",IFERROR(J53/I53,0)) | AC53: =IF(COUNT(C53:O53)=0,"",IFERROR(K53/J53,0)) | AD53: =IF(COUNT(C53:O53)=0,"",IFERROR(C53/K53,0)) | AE53: =IF(COUNT(C53:O53)=0,"",IFERROR(L53/K53,0)) | AF53: =IF(COUNT(C53:O53)=0,"",IFERROR(M53/L53,0)) | AG53: =IF(COUNT(C53:O53)=0,"",IFERROR(M53/H53,0)) | AH53: =IF(COUNT(C53:O53)=0,"",IFERROR(C53/M53,0)) | AI53: =IF(COUNT(C53:O53)=0,"",IFERROR(M53*Config!$C$7+N53*Config!$C$8,0)) | AJ53: =IF(COUNT(C53:O53)=0,"",IFERROR(IF(O53>0,O53,AI53*Config!$C$9),0)) | AK53: =IF(COUNT(C53:O53)=0,"",IFERROR(AJ53*(1-Config!$C$10-Config!$C$11-Config!$C$12),0)) | AL53: =IF(COUNT(C53:O53)=0,"",IFERROR(AK53-C53-Config!$C$13,0)) | AM53: =IF(COUNT(C53:O53)=0,"",IFERROR(AK53/C53,0)) | AN53: =IF(COUNT(C53:O53)=0,"",IFERROR(AI53/C53,0)) | AO53: =IF(COUNT(C53:O53)=0,"",IFERROR(AL53/G53,0)) | AP53: =IF(COUNT(C53:O53)=0,"",IFERROR(AO53/U53,0)) | AQ53: =IF(COUNT(C53:O53)=0,"",IFERROR(AL53/H53,0))
A54: =Config!$C$6+48 | B54: =INT((A54-Config!$C$6)/7)+1 | P54: =IF(COUNT(C54:O54)=0,"",IFERROR(C54/D54*1000,0)) | Q54: =IF(COUNT(C54:O54)=0,"",IFERROR(D54/E54,0)) | R54: =IF(COUNT(C54:O54)=0,"",IFERROR(F54/D54,0)) | S54: =IF(COUNT(C54:O54)=0,"",IFERROR(C54/F54,0)) | T54: =IF(COUNT(C54:O54)=0,"",IFERROR(G54/F54,0)) | U54: =IF(COUNT(C54:O54)=0,"",IFERROR(C54/G54,0)) | V54: =IF(COUNT(C54:O54)=0,"",IFERROR(G54/D54*1000,0)) | W54: =IF(COUNT(C54:O54)=0,"",IFERROR(H54/G54,0)) | X54: =IF(COUNT(C54:O54)=0,"",IFERROR(C54/H54,0)) | Y54: =IF(COUNT(C54:O54)=0,"",IFERROR(X54/P54,0)) | Z54: =IF(COUNT(C54:O54)=0,"",IFERROR(H54/D54*1000,0)) | AA54: =IF(COUNT(C54:O54)=0,"",IFERROR(I54/H54,0)) | AB54: =IF(COUNT(C54:O54)=0,"",IFERROR(J54/I54,0)) | AC54: =IF(COUNT(C54:O54)=0,"",IFERROR(K54/J54,0)) | AD54: =IF(COUNT(C54:O54)=0,"",IFERROR(C54/K54,0)) | AE54: =IF(COUNT(C54:O54)=0,"",IFERROR(L54/K54,0)) | AF54: =IF(COUNT(C54:O54)=0,"",IFERROR(M54/L54,0)) | AG54: =IF(COUNT(C54:O54)=0,"",IFERROR(M54/H54,0)) | AH54: =IF(COUNT(C54:O54)=0,"",IFERROR(C54/M54,0)) | AI54: =IF(COUNT(C54:O54)=0,"",IFERROR(M54*Config!$C$7+N54*Config!$C$8,0)) | AJ54: =IF(COUNT(C54:O54)=0,"",IFERROR(IF(O54>0,O54,AI54*Config!$C$9),0)) | AK54: =IF(COUNT(C54:O54)=0,"",IFERROR(AJ54*(1-Config!$C$10-Config!$C$11-Config!$C$12),0)) | AL54: =IF(COUNT(C54:O54)=0,"",IFERROR(AK54-C54-Config!$C$13,0)) | AM54: =IF(COUNT(C54:O54)=0,"",IFERROR(AK54/C54,0)) | AN54: =IF(COUNT(C54:O54)=0,"",IFERROR(AI54/C54,0)) | AO54: =IF(COUNT(C54:O54)=0,"",IFERROR(AL54/G54,0)) | AP54: =IF(COUNT(C54:O54)=0,"",IFERROR(AO54/U54,0)) | AQ54: =IF(COUNT(C54:O54)=0,"",IFERROR(AL54/H54,0))
A55: =Config!$C$6+49 | B55: =INT((A55-Config!$C$6)/7)+1 | P55: =IF(COUNT(C55:O55)=0,"",IFERROR(C55/D55*1000,0)) | Q55: =IF(COUNT(C55:O55)=0,"",IFERROR(D55/E55,0)) | R55: =IF(COUNT(C55:O55)=0,"",IFERROR(F55/D55,0)) | S55: =IF(COUNT(C55:O55)=0,"",IFERROR(C55/F55,0)) | T55: =IF(COUNT(C55:O55)=0,"",IFERROR(G55/F55,0)) | U55: =IF(COUNT(C55:O55)=0,"",IFERROR(C55/G55,0)) | V55: =IF(COUNT(C55:O55)=0,"",IFERROR(G55/D55*1000,0)) | W55: =IF(COUNT(C55:O55)=0,"",IFERROR(H55/G55,0)) | X55: =IF(COUNT(C55:O55)=0,"",IFERROR(C55/H55,0)) | Y55: =IF(COUNT(C55:O55)=0,"",IFERROR(X55/P55,0)) | Z55: =IF(COUNT(C55:O55)=0,"",IFERROR(H55/D55*1000,0)) | AA55: =IF(COUNT(C55:O55)=0,"",IFERROR(I55/H55,0)) | AB55: =IF(COUNT(C55:O55)=0,"",IFERROR(J55/I55,0)) | AC55: =IF(COUNT(C55:O55)=0,"",IFERROR(K55/J55,0)) | AD55: =IF(COUNT(C55:O55)=0,"",IFERROR(C55/K55,0)) | AE55: =IF(COUNT(C55:O55)=0,"",IFERROR(L55/K55,0)) | AF55: =IF(COUNT(C55:O55)=0,"",IFERROR(M55/L55,0)) | AG55: =IF(COUNT(C55:O55)=0,"",IFERROR(M55/H55,0)) | AH55: =IF(COUNT(C55:O55)=0,"",IFERROR(C55/M55,0)) | AI55: =IF(COUNT(C55:O55)=0,"",IFERROR(M55*Config!$C$7+N55*Config!$C$8,0)) | AJ55: =IF(COUNT(C55:O55)=0,"",IFERROR(IF(O55>0,O55,AI55*Config!$C$9),0)) | AK55: =IF(COUNT(C55:O55)=0,"",IFERROR(AJ55*(1-Config!$C$10-Config!$C$11-Config!$C$12),0)) | AL55: =IF(COUNT(C55:O55)=0,"",IFERROR(AK55-C55-Config!$C$13,0)) | AM55: =IF(COUNT(C55:O55)=0,"",IFERROR(AK55/C55,0)) | AN55: =IF(COUNT(C55:O55)=0,"",IFERROR(AI55/C55,0)) | AO55: =IF(COUNT(C55:O55)=0,"",IFERROR(AL55/G55,0)) | AP55: =IF(COUNT(C55:O55)=0,"",IFERROR(AO55/U55,0)) | AQ55: =IF(COUNT(C55:O55)=0,"",IFERROR(AL55/H55,0))
A56: =Config!$C$6+50 | B56: =INT((A56-Config!$C$6)/7)+1 | P56: =IF(COUNT(C56:O56)=0,"",IFERROR(C56/D56*1000,0)) | Q56: =IF(COUNT(C56:O56)=0,"",IFERROR(D56/E56,0)) | R56: =IF(COUNT(C56:O56)=0,"",IFERROR(F56/D56,0)) | S56: =IF(COUNT(C56:O56)=0,"",IFERROR(C56/F56,0)) | T56: =IF(COUNT(C56:O56)=0,"",IFERROR(G56/F56,0)) | U56: =IF(COUNT(C56:O56)=0,"",IFERROR(C56/G56,0)) | V56: =IF(COUNT(C56:O56)=0,"",IFERROR(G56/D56*1000,0)) | W56: =IF(COUNT(C56:O56)=0,"",IFERROR(H56/G56,0)) | X56: =IF(COUNT(C56:O56)=0,"",IFERROR(C56/H56,0)) | Y56: =IF(COUNT(C56:O56)=0,"",IFERROR(X56/P56,0)) | Z56: =IF(COUNT(C56:O56)=0,"",IFERROR(H56/D56*1000,0)) | AA56: =IF(COUNT(C56:O56)=0,"",IFERROR(I56/H56,0)) | AB56: =IF(COUNT(C56:O56)=0,"",IFERROR(J56/I56,0)) | AC56: =IF(COUNT(C56:O56)=0,"",IFERROR(K56/J56,0)) | AD56: =IF(COUNT(C56:O56)=0,"",IFERROR(C56/K56,0)) | AE56: =IF(COUNT(C56:O56)=0,"",IFERROR(L56/K56,0)) | AF56: =IF(COUNT(C56:O56)=0,"",IFERROR(M56/L56,0)) | AG56: =IF(COUNT(C56:O56)=0,"",IFERROR(M56/H56,0)) | AH56: =IF(COUNT(C56:O56)=0,"",IFERROR(C56/M56,0)) | AI56: =IF(COUNT(C56:O56)=0,"",IFERROR(M56*Config!$C$7+N56*Config!$C$8,0)) | AJ56: =IF(COUNT(C56:O56)=0,"",IFERROR(IF(O56>0,O56,AI56*Config!$C$9),0)) | AK56: =IF(COUNT(C56:O56)=0,"",IFERROR(AJ56*(1-Config!$C$10-Config!$C$11-Config!$C$12),0)) | AL56: =IF(COUNT(C56:O56)=0,"",IFERROR(AK56-C56-Config!$C$13,0)) | AM56: =IF(COUNT(C56:O56)=0,"",IFERROR(AK56/C56,0)) | AN56: =IF(COUNT(C56:O56)=0,"",IFERROR(AI56/C56,0)) | AO56: =IF(COUNT(C56:O56)=0,"",IFERROR(AL56/G56,0)) | AP56: =IF(COUNT(C56:O56)=0,"",IFERROR(AO56/U56,0)) | AQ56: =IF(COUNT(C56:O56)=0,"",IFERROR(AL56/H56,0))
A57: =Config!$C$6+51 | B57: =INT((A57-Config!$C$6)/7)+1 | P57: =IF(COUNT(C57:O57)=0,"",IFERROR(C57/D57*1000,0)) | Q57: =IF(COUNT(C57:O57)=0,"",IFERROR(D57/E57,0)) | R57: =IF(COUNT(C57:O57)=0,"",IFERROR(F57/D57,0)) | S57: =IF(COUNT(C57:O57)=0,"",IFERROR(C57/F57,0)) | T57: =IF(COUNT(C57:O57)=0,"",IFERROR(G57/F57,0)) | U57: =IF(COUNT(C57:O57)=0,"",IFERROR(C57/G57,0)) | V57: =IF(COUNT(C57:O57)=0,"",IFERROR(G57/D57*1000,0)) | W57: =IF(COUNT(C57:O57)=0,"",IFERROR(H57/G57,0)) | X57: =IF(COUNT(C57:O57)=0,"",IFERROR(C57/H57,0)) | Y57: =IF(COUNT(C57:O57)=0,"",IFERROR(X57/P57,0)) | Z57: =IF(COUNT(C57:O57)=0,"",IFERROR(H57/D57*1000,0)) | AA57: =IF(COUNT(C57:O57)=0,"",IFERROR(I57/H57,0)) | AB57: =IF(COUNT(C57:O57)=0,"",IFERROR(J57/I57,0)) | AC57: =IF(COUNT(C57:O57)=0,"",IFERROR(K57/J57,0)) | AD57: =IF(COUNT(C57:O57)=0,"",IFERROR(C57/K57,0)) | AE57: =IF(COUNT(C57:O57)=0,"",IFERROR(L57/K57,0)) | AF57: =IF(COUNT(C57:O57)=0,"",IFERROR(M57/L57,0)) | AG57: =IF(COUNT(C57:O57)=0,"",IFERROR(M57/H57,0)) | AH57: =IF(COUNT(C57:O57)=0,"",IFERROR(C57/M57,0)) | AI57: =IF(COUNT(C57:O57)=0,"",IFERROR(M57*Config!$C$7+N57*Config!$C$8,0)) | AJ57: =IF(COUNT(C57:O57)=0,"",IFERROR(IF(O57>0,O57,AI57*Config!$C$9),0)) | AK57: =IF(COUNT(C57:O57)=0,"",IFERROR(AJ57*(1-Config!$C$10-Config!$C$11-Config!$C$12),0)) | AL57: =IF(COUNT(C57:O57)=0,"",IFERROR(AK57-C57-Config!$C$13,0)) | AM57: =IF(COUNT(C57:O57)=0,"",IFERROR(AK57/C57,0)) | AN57: =IF(COUNT(C57:O57)=0,"",IFERROR(AI57/C57,0)) | AO57: =IF(COUNT(C57:O57)=0,"",IFERROR(AL57/G57,0)) | AP57: =IF(COUNT(C57:O57)=0,"",IFERROR(AO57/U57,0)) | AQ57: =IF(COUNT(C57:O57)=0,"",IFERROR(AL57/H57,0))
A58: =Config!$C$6+52 | B58: =INT((A58-Config!$C$6)/7)+1 | P58: =IF(COUNT(C58:O58)=0,"",IFERROR(C58/D58*1000,0)) | Q58: =IF(COUNT(C58:O58)=0,"",IFERROR(D58/E58,0)) | R58: =IF(COUNT(C58:O58)=0,"",IFERROR(F58/D58,0)) | S58: =IF(COUNT(C58:O58)=0,"",IFERROR(C58/F58,0)) | T58: =IF(COUNT(C58:O58)=0,"",IFERROR(G58/F58,0)) | U58: =IF(COUNT(C58:O58)=0,"",IFERROR(C58/G58,0)) | V58: =IF(COUNT(C58:O58)=0,"",IFERROR(G58/D58*1000,0)) | W58: =IF(COUNT(C58:O58)=0,"",IFERROR(H58/G58,0)) | X58: =IF(COUNT(C58:O58)=0,"",IFERROR(C58/H58,0)) | Y58: =IF(COUNT(C58:O58)=0,"",IFERROR(X58/P58,0)) | Z58: =IF(COUNT(C58:O58)=0,"",IFERROR(H58/D58*1000,0)) | AA58: =IF(COUNT(C58:O58)=0,"",IFERROR(I58/H58,0)) | AB58: =IF(COUNT(C58:O58)=0,"",IFERROR(J58/I58,0)) | AC58: =IF(COUNT(C58:O58)=0,"",IFERROR(K58/J58,0)) | AD58: =IF(COUNT(C58:O58)=0,"",IFERROR(C58/K58,0)) | AE58: =IF(COUNT(C58:O58)=0,"",IFERROR(L58/K58,0)) | AF58: =IF(COUNT(C58:O58)=0,"",IFERROR(M58/L58,0)) | AG58: =IF(COUNT(C58:O58)=0,"",IFERROR(M58/H58,0)) | AH58: =IF(COUNT(C58:O58)=0,"",IFERROR(C58/M58,0)) | AI58: =IF(COUNT(C58:O58)=0,"",IFERROR(M58*Config!$C$7+N58*Config!$C$8,0)) | AJ58: =IF(COUNT(C58:O58)=0,"",IFERROR(IF(O58>0,O58,AI58*Config!$C$9),0)) | AK58: =IF(COUNT(C58:O58)=0,"",IFERROR(AJ58*(1-Config!$C$10-Config!$C$11-Config!$C$12),0)) | AL58: =IF(COUNT(C58:O58)=0,"",IFERROR(AK58-C58-Config!$C$13,0)) | AM58: =IF(COUNT(C58:O58)=0,"",IFERROR(AK58/C58,0)) | AN58: =IF(COUNT(C58:O58)=0,"",IFERROR(AI58/C58,0)) | AO58: =IF(COUNT(C58:O58)=0,"",IFERROR(AL58/G58,0)) | AP58: =IF(COUNT(C58:O58)=0,"",IFERROR(AO58/U58,0)) | AQ58: =IF(COUNT(C58:O58)=0,"",IFERROR(AL58/H58,0))
A59: =Config!$C$6+53 | B59: =INT((A59-Config!$C$6)/7)+1 | P59: =IF(COUNT(C59:O59)=0,"",IFERROR(C59/D59*1000,0)) | Q59: =IF(COUNT(C59:O59)=0,"",IFERROR(D59/E59,0)) | R59: =IF(COUNT(C59:O59)=0,"",IFERROR(F59/D59,0)) | S59: =IF(COUNT(C59:O59)=0,"",IFERROR(C59/F59,0)) | T59: =IF(COUNT(C59:O59)=0,"",IFERROR(G59/F59,0)) | U59: =IF(COUNT(C59:O59)=0,"",IFERROR(C59/G59,0)) | V59: =IF(COUNT(C59:O59)=0,"",IFERROR(G59/D59*1000,0)) | W59: =IF(COUNT(C59:O59)=0,"",IFERROR(H59/G59,0)) | X59: =IF(COUNT(C59:O59)=0,"",IFERROR(C59/H59,0)) | Y59: =IF(COUNT(C59:O59)=0,"",IFERROR(X59/P59,0)) | Z59: =IF(COUNT(C59:O59)=0,"",IFERROR(H59/D59*1000,0)) | AA59: =IF(COUNT(C59:O59)=0,"",IFERROR(I59/H59,0)) | AB59: =IF(COUNT(C59:O59)=0,"",IFERROR(J59/I59,0)) | AC59: =IF(COUNT(C59:O59)=0,"",IFERROR(K59/J59,0)) | AD59: =IF(COUNT(C59:O59)=0,"",IFERROR(C59/K59,0)) | AE59: =IF(COUNT(C59:O59)=0,"",IFERROR(L59/K59,0)) | AF59: =IF(COUNT(C59:O59)=0,"",IFERROR(M59/L59,0)) | AG59: =IF(COUNT(C59:O59)=0,"",IFERROR(M59/H59,0)) | AH59: =IF(COUNT(C59:O59)=0,"",IFERROR(C59/M59,0)) | AI59: =IF(COUNT(C59:O59)=0,"",IFERROR(M59*Config!$C$7+N59*Config!$C$8,0)) | AJ59: =IF(COUNT(C59:O59)=0,"",IFERROR(IF(O59>0,O59,AI59*Config!$C$9),0)) | AK59: =IF(COUNT(C59:O59)=0,"",IFERROR(AJ59*(1-Config!$C$10-Config!$C$11-Config!$C$12),0)) | AL59: =IF(COUNT(C59:O59)=0,"",IFERROR(AK59-C59-Config!$C$13,0)) | AM59: =IF(COUNT(C59:O59)=0,"",IFERROR(AK59/C59,0)) | AN59: =IF(COUNT(C59:O59)=0,"",IFERROR(AI59/C59,0)) | AO59: =IF(COUNT(C59:O59)=0,"",IFERROR(AL59/G59,0)) | AP59: =IF(COUNT(C59:O59)=0,"",IFERROR(AO59/U59,0)) | AQ59: =IF(COUNT(C59:O59)=0,"",IFERROR(AL59/H59,0))
A60: =Config!$C$6+54 | B60: =INT((A60-Config!$C$6)/7)+1 | P60: =IF(COUNT(C60:O60)=0,"",IFERROR(C60/D60*1000,0)) | Q60: =IF(COUNT(C60:O60)=0,"",IFERROR(D60/E60,0)) | R60: =IF(COUNT(C60:O60)=0,"",IFERROR(F60/D60,0)) | S60: =IF(COUNT(C60:O60)=0,"",IFERROR(C60/F60,0)) | T60: =IF(COUNT(C60:O60)=0,"",IFERROR(G60/F60,0)) | U60: =IF(COUNT(C60:O60)=0,"",IFERROR(C60/G60,0)) | V60: =IF(COUNT(C60:O60)=0,"",IFERROR(G60/D60*1000,0)) | W60: =IF(COUNT(C60:O60)=0,"",IFERROR(H60/G60,0)) | X60: =IF(COUNT(C60:O60)=0,"",IFERROR(C60/H60,0)) | Y60: =IF(COUNT(C60:O60)=0,"",IFERROR(X60/P60,0)) | Z60: =IF(COUNT(C60:O60)=0,"",IFERROR(H60/D60*1000,0)) | AA60: =IF(COUNT(C60:O60)=0,"",IFERROR(I60/H60,0)) | AB60: =IF(COUNT(C60:O60)=0,"",IFERROR(J60/I60,0)) | AC60: =IF(COUNT(C60:O60)=0,"",IFERROR(K60/J60,0)) | AD60: =IF(COUNT(C60:O60)=0,"",IFERROR(C60/K60,0)) | AE60: =IF(COUNT(C60:O60)=0,"",IFERROR(L60/K60,0)) | AF60: =IF(COUNT(C60:O60)=0,"",IFERROR(M60/L60,0)) | AG60: =IF(COUNT(C60:O60)=0,"",IFERROR(M60/H60,0)) | AH60: =IF(COUNT(C60:O60)=0,"",IFERROR(C60/M60,0)) | AI60: =IF(COUNT(C60:O60)=0,"",IFERROR(M60*Config!$C$7+N60*Config!$C$8,0)) | AJ60: =IF(COUNT(C60:O60)=0,"",IFERROR(IF(O60>0,O60,AI60*Config!$C$9),0)) | AK60: =IF(COUNT(C60:O60)=0,"",IFERROR(AJ60*(1-Config!$C$10-Config!$C$11-Config!$C$12),0)) | AL60: =IF(COUNT(C60:O60)=0,"",IFERROR(AK60-C60-Config!$C$13,0)) | AM60: =IF(COUNT(C60:O60)=0,"",IFERROR(AK60/C60,0)) | AN60: =IF(COUNT(C60:O60)=0,"",IFERROR(AI60/C60,0)) | AO60: =IF(COUNT(C60:O60)=0,"",IFERROR(AL60/G60,0)) | AP60: =IF(COUNT(C60:O60)=0,"",IFERROR(AO60/U60,0)) | AQ60: =IF(COUNT(C60:O60)=0,"",IFERROR(AL60/H60,0))
A61: =Config!$C$6+55 | B61: =INT((A61-Config!$C$6)/7)+1 | P61: =IF(COUNT(C61:O61)=0,"",IFERROR(C61/D61*1000,0)) | Q61: =IF(COUNT(C61:O61)=0,"",IFERROR(D61/E61,0)) | R61: =IF(COUNT(C61:O61)=0,"",IFERROR(F61/D61,0)) | S61: =IF(COUNT(C61:O61)=0,"",IFERROR(C61/F61,0)) | T61: =IF(COUNT(C61:O61)=0,"",IFERROR(G61/F61,0)) | U61: =IF(COUNT(C61:O61)=0,"",IFERROR(C61/G61,0)) | V61: =IF(COUNT(C61:O61)=0,"",IFERROR(G61/D61*1000,0)) | W61: =IF(COUNT(C61:O61)=0,"",IFERROR(H61/G61,0)) | X61: =IF(COUNT(C61:O61)=0,"",IFERROR(C61/H61,0)) | Y61: =IF(COUNT(C61:O61)=0,"",IFERROR(X61/P61,0)) | Z61: =IF(COUNT(C61:O61)=0,"",IFERROR(H61/D61*1000,0)) | AA61: =IF(COUNT(C61:O61)=0,"",IFERROR(I61/H61,0)) | AB61: =IF(COUNT(C61:O61)=0,"",IFERROR(J61/I61,0)) | AC61: =IF(COUNT(C61:O61)=0,"",IFERROR(K61/J61,0)) | AD61: =IF(COUNT(C61:O61)=0,"",IFERROR(C61/K61,0)) | AE61: =IF(COUNT(C61:O61)=0,"",IFERROR(L61/K61,0)) | AF61: =IF(COUNT(C61:O61)=0,"",IFERROR(M61/L61,0)) | AG61: =IF(COUNT(C61:O61)=0,"",IFERROR(M61/H61,0)) | AH61: =IF(COUNT(C61:O61)=0,"",IFERROR(C61/M61,0)) | AI61: =IF(COUNT(C61:O61)=0,"",IFERROR(M61*Config!$C$7+N61*Config!$C$8,0)) | AJ61: =IF(COUNT(C61:O61)=0,"",IFERROR(IF(O61>0,O61,AI61*Config!$C$9),0)) | AK61: =IF(COUNT(C61:O61)=0,"",IFERROR(AJ61*(1-Config!$C$10-Config!$C$11-Config!$C$12),0)) | AL61: =IF(COUNT(C61:O61)=0,"",IFERROR(AK61-C61-Config!$C$13,0)) | AM61: =IF(COUNT(C61:O61)=0,"",IFERROR(AK61/C61,0)) | AN61: =IF(COUNT(C61:O61)=0,"",IFERROR(AI61/C61,0)) | AO61: =IF(COUNT(C61:O61)=0,"",IFERROR(AL61/G61,0)) | AP61: =IF(COUNT(C61:O61)=0,"",IFERROR(AO61/U61,0)) | AQ61: =IF(COUNT(C61:O61)=0,"",IFERROR(AL61/H61,0))
A62: =Config!$C$6+56 | B62: =INT((A62-Config!$C$6)/7)+1 | P62: =IF(COUNT(C62:O62)=0,"",IFERROR(C62/D62*1000,0)) | Q62: =IF(COUNT(C62:O62)=0,"",IFERROR(D62/E62,0)) | R62: =IF(COUNT(C62:O62)=0,"",IFERROR(F62/D62,0)) | S62: =IF(COUNT(C62:O62)=0,"",IFERROR(C62/F62,0)) | T62: =IF(COUNT(C62:O62)=0,"",IFERROR(G62/F62,0)) | U62: =IF(COUNT(C62:O62)=0,"",IFERROR(C62/G62,0)) | V62: =IF(COUNT(C62:O62)=0,"",IFERROR(G62/D62*1000,0)) | W62: =IF(COUNT(C62:O62)=0,"",IFERROR(H62/G62,0)) | X62: =IF(COUNT(C62:O62)=0,"",IFERROR(C62/H62,0)) | Y62: =IF(COUNT(C62:O62)=0,"",IFERROR(X62/P62,0)) | Z62: =IF(COUNT(C62:O62)=0,"",IFERROR(H62/D62*1000,0)) | AA62: =IF(COUNT(C62:O62)=0,"",IFERROR(I62/H62,0)) | AB62: =IF(COUNT(C62:O62)=0,"",IFERROR(J62/I62,0)) | AC62: =IF(COUNT(C62:O62)=0,"",IFERROR(K62/J62,0)) | AD62: =IF(COUNT(C62:O62)=0,"",IFERROR(C62/K62,0)) | AE62: =IF(COUNT(C62:O62)=0,"",IFERROR(L62/K62,0)) | AF62: =IF(COUNT(C62:O62)=0,"",IFERROR(M62/L62,0)) | AG62: =IF(COUNT(C62:O62)=0,"",IFERROR(M62/H62,0)) | AH62: =IF(COUNT(C62:O62)=0,"",IFERROR(C62/M62,0)) | AI62: =IF(COUNT(C62:O62)=0,"",IFERROR(M62*Config!$C$7+N62*Config!$C$8,0)) | AJ62: =IF(COUNT(C62:O62)=0,"",IFERROR(IF(O62>0,O62,AI62*Config!$C$9),0)) | AK62: =IF(COUNT(C62:O62)=0,"",IFERROR(AJ62*(1-Config!$C$10-Config!$C$11-Config!$C$12),0)) | AL62: =IF(COUNT(C62:O62)=0,"",IFERROR(AK62-C62-Config!$C$13,0)) | AM62: =IF(COUNT(C62:O62)=0,"",IFERROR(AK62/C62,0)) | AN62: =IF(COUNT(C62:O62)=0,"",IFERROR(AI62/C62,0)) | AO62: =IF(COUNT(C62:O62)=0,"",IFERROR(AL62/G62,0)) | AP62: =IF(COUNT(C62:O62)=0,"",IFERROR(AO62/U62,0)) | AQ62: =IF(COUNT(C62:O62)=0,"",IFERROR(AL62/H62,0))
A63: =Config!$C$6+57 | B63: =INT((A63-Config!$C$6)/7)+1 | P63: =IF(COUNT(C63:O63)=0,"",IFERROR(C63/D63*1000,0)) | Q63: =IF(COUNT(C63:O63)=0,"",IFERROR(D63/E63,0)) | R63: =IF(COUNT(C63:O63)=0,"",IFERROR(F63/D63,0)) | S63: =IF(COUNT(C63:O63)=0,"",IFERROR(C63/F63,0)) | T63: =IF(COUNT(C63:O63)=0,"",IFERROR(G63/F63,0)) | U63: =IF(COUNT(C63:O63)=0,"",IFERROR(C63/G63,0)) | V63: =IF(COUNT(C63:O63)=0,"",IFERROR(G63/D63*1000,0)) | W63: =IF(COUNT(C63:O63)=0,"",IFERROR(H63/G63,0)) | X63: =IF(COUNT(C63:O63)=0,"",IFERROR(C63/H63,0)) | Y63: =IF(COUNT(C63:O63)=0,"",IFERROR(X63/P63,0)) | Z63: =IF(COUNT(C63:O63)=0,"",IFERROR(H63/D63*1000,0)) | AA63: =IF(COUNT(C63:O63)=0,"",IFERROR(I63/H63,0)) | AB63: =IF(COUNT(C63:O63)=0,"",IFERROR(J63/I63,0)) | AC63: =IF(COUNT(C63:O63)=0,"",IFERROR(K63/J63,0)) | AD63: =IF(COUNT(C63:O63)=0,"",IFERROR(C63/K63,0)) | AE63: =IF(COUNT(C63:O63)=0,"",IFERROR(L63/K63,0)) | AF63: =IF(COUNT(C63:O63)=0,"",IFERROR(M63/L63,0)) | AG63: =IF(COUNT(C63:O63)=0,"",IFERROR(M63/H63,0)) | AH63: =IF(COUNT(C63:O63)=0,"",IFERROR(C63/M63,0)) | AI63: =IF(COUNT(C63:O63)=0,"",IFERROR(M63*Config!$C$7+N63*Config!$C$8,0)) | AJ63: =IF(COUNT(C63:O63)=0,"",IFERROR(IF(O63>0,O63,AI63*Config!$C$9),0)) | AK63: =IF(COUNT(C63:O63)=0,"",IFERROR(AJ63*(1-Config!$C$10-Config!$C$11-Config!$C$12),0)) | AL63: =IF(COUNT(C63:O63)=0,"",IFERROR(AK63-C63-Config!$C$13,0)) | AM63: =IF(COUNT(C63:O63)=0,"",IFERROR(AK63/C63,0)) | AN63: =IF(COUNT(C63:O63)=0,"",IFERROR(AI63/C63,0)) | AO63: =IF(COUNT(C63:O63)=0,"",IFERROR(AL63/G63,0)) | AP63: =IF(COUNT(C63:O63)=0,"",IFERROR(AO63/U63,0)) | AQ63: =IF(COUNT(C63:O63)=0,"",IFERROR(AL63/H63,0))
A64: =Config!$C$6+58 | B64: =INT((A64-Config!$C$6)/7)+1 | P64: =IF(COUNT(C64:O64)=0,"",IFERROR(C64/D64*1000,0)) | Q64: =IF(COUNT(C64:O64)=0,"",IFERROR(D64/E64,0)) | R64: =IF(COUNT(C64:O64)=0,"",IFERROR(F64/D64,0)) | S64: =IF(COUNT(C64:O64)=0,"",IFERROR(C64/F64,0)) | T64: =IF(COUNT(C64:O64)=0,"",IFERROR(G64/F64,0)) | U64: =IF(COUNT(C64:O64)=0,"",IFERROR(C64/G64,0)) | V64: =IF(COUNT(C64:O64)=0,"",IFERROR(G64/D64*1000,0)) | W64: =IF(COUNT(C64:O64)=0,"",IFERROR(H64/G64,0)) | X64: =IF(COUNT(C64:O64)=0,"",IFERROR(C64/H64,0)) | Y64: =IF(COUNT(C64:O64)=0,"",IFERROR(X64/P64,0)) | Z64: =IF(COUNT(C64:O64)=0,"",IFERROR(H64/D64*1000,0)) | AA64: =IF(COUNT(C64:O64)=0,"",IFERROR(I64/H64,0)) | AB64: =IF(COUNT(C64:O64)=0,"",IFERROR(J64/I64,0)) | AC64: =IF(COUNT(C64:O64)=0,"",IFERROR(K64/J64,0)) | AD64: =IF(COUNT(C64:O64)=0,"",IFERROR(C64/K64,0)) | AE64: =IF(COUNT(C64:O64)=0,"",IFERROR(L64/K64,0)) | AF64: =IF(COUNT(C64:O64)=0,"",IFERROR(M64/L64,0)) | AG64: =IF(COUNT(C64:O64)=0,"",IFERROR(M64/H64,0)) | AH64: =IF(COUNT(C64:O64)=0,"",IFERROR(C64/M64,0)) | AI64: =IF(COUNT(C64:O64)=0,"",IFERROR(M64*Config!$C$7+N64*Config!$C$8,0)) | AJ64: =IF(COUNT(C64:O64)=0,"",IFERROR(IF(O64>0,O64,AI64*Config!$C$9),0)) | AK64: =IF(COUNT(C64:O64)=0,"",IFERROR(AJ64*(1-Config!$C$10-Config!$C$11-Config!$C$12),0)) | AL64: =IF(COUNT(C64:O64)=0,"",IFERROR(AK64-C64-Config!$C$13,0)) | AM64: =IF(COUNT(C64:O64)=0,"",IFERROR(AK64/C64,0)) | AN64: =IF(COUNT(C64:O64)=0,"",IFERROR(AI64/C64,0)) | AO64: =IF(COUNT(C64:O64)=0,"",IFERROR(AL64/G64,0)) | AP64: =IF(COUNT(C64:O64)=0,"",IFERROR(AO64/U64,0)) | AQ64: =IF(COUNT(C64:O64)=0,"",IFERROR(AL64/H64,0))
A65: =Config!$C$6+59 | B65: =INT((A65-Config!$C$6)/7)+1 | P65: =IF(COUNT(C65:O65)=0,"",IFERROR(C65/D65*1000,0)) | Q65: =IF(COUNT(C65:O65)=0,"",IFERROR(D65/E65,0)) | R65: =IF(COUNT(C65:O65)=0,"",IFERROR(F65/D65,0)) | S65: =IF(COUNT(C65:O65)=0,"",IFERROR(C65/F65,0)) | T65: =IF(COUNT(C65:O65)=0,"",IFERROR(G65/F65,0)) | U65: =IF(COUNT(C65:O65)=0,"",IFERROR(C65/G65,0)) | V65: =IF(COUNT(C65:O65)=0,"",IFERROR(G65/D65*1000,0)) | W65: =IF(COUNT(C65:O65)=0,"",IFERROR(H65/G65,0)) | X65: =IF(COUNT(C65:O65)=0,"",IFERROR(C65/H65,0)) | Y65: =IF(COUNT(C65:O65)=0,"",IFERROR(X65/P65,0)) | Z65: =IF(COUNT(C65:O65)=0,"",IFERROR(H65/D65*1000,0)) | AA65: =IF(COUNT(C65:O65)=0,"",IFERROR(I65/H65,0)) | AB65: =IF(COUNT(C65:O65)=0,"",IFERROR(J65/I65,0)) | AC65: =IF(COUNT(C65:O65)=0,"",IFERROR(K65/J65,0)) | AD65: =IF(COUNT(C65:O65)=0,"",IFERROR(C65/K65,0)) | AE65: =IF(COUNT(C65:O65)=0,"",IFERROR(L65/K65,0)) | AF65: =IF(COUNT(C65:O65)=0,"",IFERROR(M65/L65,0)) | AG65: =IF(COUNT(C65:O65)=0,"",IFERROR(M65/H65,0)) | AH65: =IF(COUNT(C65:O65)=0,"",IFERROR(C65/M65,0)) | AI65: =IF(COUNT(C65:O65)=0,"",IFERROR(M65*Config!$C$7+N65*Config!$C$8,0)) | AJ65: =IF(COUNT(C65:O65)=0,"",IFERROR(IF(O65>0,O65,AI65*Config!$C$9),0)) | AK65: =IF(COUNT(C65:O65)=0,"",IFERROR(AJ65*(1-Config!$C$10-Config!$C$11-Config!$C$12),0)) | AL65: =IF(COUNT(C65:O65)=0,"",IFERROR(AK65-C65-Config!$C$13,0)) | AM65: =IF(COUNT(C65:O65)=0,"",IFERROR(AK65/C65,0)) | AN65: =IF(COUNT(C65:O65)=0,"",IFERROR(AI65/C65,0)) | AO65: =IF(COUNT(C65:O65)=0,"",IFERROR(AL65/G65,0)) | AP65: =IF(COUNT(C65:O65)=0,"",IFERROR(AO65/U65,0)) | AQ65: =IF(COUNT(C65:O65)=0,"",IFERROR(AL65/H65,0))
A66: =Config!$C$6+60 | B66: =INT((A66-Config!$C$6)/7)+1 | P66: =IF(COUNT(C66:O66)=0,"",IFERROR(C66/D66*1000,0)) | Q66: =IF(COUNT(C66:O66)=0,"",IFERROR(D66/E66,0)) | R66: =IF(COUNT(C66:O66)=0,"",IFERROR(F66/D66,0)) | S66: =IF(COUNT(C66:O66)=0,"",IFERROR(C66/F66,0)) | T66: =IF(COUNT(C66:O66)=0,"",IFERROR(G66/F66,0)) | U66: =IF(COUNT(C66:O66)=0,"",IFERROR(C66/G66,0)) | V66: =IF(COUNT(C66:O66)=0,"",IFERROR(G66/D66*1000,0)) | W66: =IF(COUNT(C66:O66)=0,"",IFERROR(H66/G66,0)) | X66: =IF(COUNT(C66:O66)=0,"",IFERROR(C66/H66,0)) | Y66: =IF(COUNT(C66:O66)=0,"",IFERROR(X66/P66,0)) | Z66: =IF(COUNT(C66:O66)=0,"",IFERROR(H66/D66*1000,0)) | AA66: =IF(COUNT(C66:O66)=0,"",IFERROR(I66/H66,0)) | AB66: =IF(COUNT(C66:O66)=0,"",IFERROR(J66/I66,0)) | AC66: =IF(COUNT(C66:O66)=0,"",IFERROR(K66/J66,0)) | AD66: =IF(COUNT(C66:O66)=0,"",IFERROR(C66/K66,0)) | AE66: =IF(COUNT(C66:O66)=0,"",IFERROR(L66/K66,0)) | AF66: =IF(COUNT(C66:O66)=0,"",IFERROR(M66/L66,0)) | AG66: =IF(COUNT(C66:O66)=0,"",IFERROR(M66/H66,0)) | AH66: =IF(COUNT(C66:O66)=0,"",IFERROR(C66/M66,0)) | AI66: =IF(COUNT(C66:O66)=0,"",IFERROR(M66*Config!$C$7+N66*Config!$C$8,0)) | AJ66: =IF(COUNT(C66:O66)=0,"",IFERROR(IF(O66>0,O66,AI66*Config!$C$9),0)) | AK66: =IF(COUNT(C66:O66)=0,"",IFERROR(AJ66*(1-Config!$C$10-Config!$C$11-Config!$C$12),0)) | AL66: =IF(COUNT(C66:O66)=0,"",IFERROR(AK66-C66-Config!$C$13,0)) | AM66: =IF(COUNT(C66:O66)=0,"",IFERROR(AK66/C66,0)) | AN66: =IF(COUNT(C66:O66)=0,"",IFERROR(AI66/C66,0)) | AO66: =IF(COUNT(C66:O66)=0,"",IFERROR(AL66/G66,0)) | AP66: =IF(COUNT(C66:O66)=0,"",IFERROR(AO66/U66,0)) | AQ66: =IF(COUNT(C66:O66)=0,"",IFERROR(AL66/H66,0))
A67: =Config!$C$6+61 | B67: =INT((A67-Config!$C$6)/7)+1 | P67: =IF(COUNT(C67:O67)=0,"",IFERROR(C67/D67*1000,0)) | Q67: =IF(COUNT(C67:O67)=0,"",IFERROR(D67/E67,0)) | R67: =IF(COUNT(C67:O67)=0,"",IFERROR(F67/D67,0)) | S67: =IF(COUNT(C67:O67)=0,"",IFERROR(C67/F67,0)) | T67: =IF(COUNT(C67:O67)=0,"",IFERROR(G67/F67,0)) | U67: =IF(COUNT(C67:O67)=0,"",IFERROR(C67/G67,0)) | V67: =IF(COUNT(C67:O67)=0,"",IFERROR(G67/D67*1000,0)) | W67: =IF(COUNT(C67:O67)=0,"",IFERROR(H67/G67,0)) | X67: =IF(COUNT(C67:O67)=0,"",IFERROR(C67/H67,0)) | Y67: =IF(COUNT(C67:O67)=0,"",IFERROR(X67/P67,0)) | Z67: =IF(COUNT(C67:O67)=0,"",IFERROR(H67/D67*1000,0)) | AA67: =IF(COUNT(C67:O67)=0,"",IFERROR(I67/H67,0)) | AB67: =IF(COUNT(C67:O67)=0,"",IFERROR(J67/I67,0)) | AC67: =IF(COUNT(C67:O67)=0,"",IFERROR(K67/J67,0)) | AD67: =IF(COUNT(C67:O67)=0,"",IFERROR(C67/K67,0)) | AE67: =IF(COUNT(C67:O67)=0,"",IFERROR(L67/K67,0)) | AF67: =IF(COUNT(C67:O67)=0,"",IFERROR(M67/L67,0)) | AG67: =IF(COUNT(C67:O67)=0,"",IFERROR(M67/H67,0)) | AH67: =IF(COUNT(C67:O67)=0,"",IFERROR(C67/M67,0)) | AI67: =IF(COUNT(C67:O67)=0,"",IFERROR(M67*Config!$C$7+N67*Config!$C$8,0)) | AJ67: =IF(COUNT(C67:O67)=0,"",IFERROR(IF(O67>0,O67,AI67*Config!$C$9),0)) | AK67: =IF(COUNT(C67:O67)=0,"",IFERROR(AJ67*(1-Config!$C$10-Config!$C$11-Config!$C$12),0)) | AL67: =IF(COUNT(C67:O67)=0,"",IFERROR(AK67-C67-Config!$C$13,0)) | AM67: =IF(COUNT(C67:O67)=0,"",IFERROR(AK67/C67,0)) | AN67: =IF(COUNT(C67:O67)=0,"",IFERROR(AI67/C67,0)) | AO67: =IF(COUNT(C67:O67)=0,"",IFERROR(AL67/G67,0)) | AP67: =IF(COUNT(C67:O67)=0,"",IFERROR(AO67/U67,0)) | AQ67: =IF(COUNT(C67:O67)=0,"",IFERROR(AL67/H67,0))
A68: =Config!$C$6+62 | B68: =INT((A68-Config!$C$6)/7)+1 | P68: =IF(COUNT(C68:O68)=0,"",IFERROR(C68/D68*1000,0)) | Q68: =IF(COUNT(C68:O68)=0,"",IFERROR(D68/E68,0)) | R68: =IF(COUNT(C68:O68)=0,"",IFERROR(F68/D68,0)) | S68: =IF(COUNT(C68:O68)=0,"",IFERROR(C68/F68,0)) | T68: =IF(COUNT(C68:O68)=0,"",IFERROR(G68/F68,0)) | U68: =IF(COUNT(C68:O68)=0,"",IFERROR(C68/G68,0)) | V68: =IF(COUNT(C68:O68)=0,"",IFERROR(G68/D68*1000,0)) | W68: =IF(COUNT(C68:O68)=0,"",IFERROR(H68/G68,0)) | X68: =IF(COUNT(C68:O68)=0,"",IFERROR(C68/H68,0)) | Y68: =IF(COUNT(C68:O68)=0,"",IFERROR(X68/P68,0)) | Z68: =IF(COUNT(C68:O68)=0,"",IFERROR(H68/D68*1000,0)) | AA68: =IF(COUNT(C68:O68)=0,"",IFERROR(I68/H68,0)) | AB68: =IF(COUNT(C68:O68)=0,"",IFERROR(J68/I68,0)) | AC68: =IF(COUNT(C68:O68)=0,"",IFERROR(K68/J68,0)) | AD68: =IF(COUNT(C68:O68)=0,"",IFERROR(C68/K68,0)) | AE68: =IF(COUNT(C68:O68)=0,"",IFERROR(L68/K68,0)) | AF68: =IF(COUNT(C68:O68)=0,"",IFERROR(M68/L68,0)) | AG68: =IF(COUNT(C68:O68)=0,"",IFERROR(M68/H68,0)) | AH68: =IF(COUNT(C68:O68)=0,"",IFERROR(C68/M68,0)) | AI68: =IF(COUNT(C68:O68)=0,"",IFERROR(M68*Config!$C$7+N68*Config!$C$8,0)) | AJ68: =IF(COUNT(C68:O68)=0,"",IFERROR(IF(O68>0,O68,AI68*Config!$C$9),0)) | AK68: =IF(COUNT(C68:O68)=0,"",IFERROR(AJ68*(1-Config!$C$10-Config!$C$11-Config!$C$12),0)) | AL68: =IF(COUNT(C68:O68)=0,"",IFERROR(AK68-C68-Config!$C$13,0)) | AM68: =IF(COUNT(C68:O68)=0,"",IFERROR(AK68/C68,0)) | AN68: =IF(COUNT(C68:O68)=0,"",IFERROR(AI68/C68,0)) | AO68: =IF(COUNT(C68:O68)=0,"",IFERROR(AL68/G68,0)) | AP68: =IF(COUNT(C68:O68)=0,"",IFERROR(AO68/U68,0)) | AQ68: =IF(COUNT(C68:O68)=0,"",IFERROR(AL68/H68,0))
A69: =Config!$C$6+63 | B69: =INT((A69-Config!$C$6)/7)+1 | P69: =IF(COUNT(C69:O69)=0,"",IFERROR(C69/D69*1000,0)) | Q69: =IF(COUNT(C69:O69)=0,"",IFERROR(D69/E69,0)) | R69: =IF(COUNT(C69:O69)=0,"",IFERROR(F69/D69,0)) | S69: =IF(COUNT(C69:O69)=0,"",IFERROR(C69/F69,0)) | T69: =IF(COUNT(C69:O69)=0,"",IFERROR(G69/F69,0)) | U69: =IF(COUNT(C69:O69)=0,"",IFERROR(C69/G69,0)) | V69: =IF(COUNT(C69:O69)=0,"",IFERROR(G69/D69*1000,0)) | W69: =IF(COUNT(C69:O69)=0,"",IFERROR(H69/G69,0)) | X69: =IF(COUNT(C69:O69)=0,"",IFERROR(C69/H69,0)) | Y69: =IF(COUNT(C69:O69)=0,"",IFERROR(X69/P69,0)) | Z69: =IF(COUNT(C69:O69)=0,"",IFERROR(H69/D69*1000,0)) | AA69: =IF(COUNT(C69:O69)=0,"",IFERROR(I69/H69,0)) | AB69: =IF(COUNT(C69:O69)=0,"",IFERROR(J69/I69,0)) | AC69: =IF(COUNT(C69:O69)=0,"",IFERROR(K69/J69,0)) | AD69: =IF(COUNT(C69:O69)=0,"",IFERROR(C69/K69,0)) | AE69: =IF(COUNT(C69:O69)=0,"",IFERROR(L69/K69,0)) | AF69: =IF(COUNT(C69:O69)=0,"",IFERROR(M69/L69,0)) | AG69: =IF(COUNT(C69:O69)=0,"",IFERROR(M69/H69,0)) | AH69: =IF(COUNT(C69:O69)=0,"",IFERROR(C69/M69,0)) | AI69: =IF(COUNT(C69:O69)=0,"",IFERROR(M69*Config!$C$7+N69*Config!$C$8,0)) | AJ69: =IF(COUNT(C69:O69)=0,"",IFERROR(IF(O69>0,O69,AI69*Config!$C$9),0)) | AK69: =IF(COUNT(C69:O69)=0,"",IFERROR(AJ69*(1-Config!$C$10-Config!$C$11-Config!$C$12),0)) | AL69: =IF(COUNT(C69:O69)=0,"",IFERROR(AK69-C69-Config!$C$13,0)) | AM69: =IF(COUNT(C69:O69)=0,"",IFERROR(AK69/C69,0)) | AN69: =IF(COUNT(C69:O69)=0,"",IFERROR(AI69/C69,0)) | AO69: =IF(COUNT(C69:O69)=0,"",IFERROR(AL69/G69,0)) | AP69: =IF(COUNT(C69:O69)=0,"",IFERROR(AO69/U69,0)) | AQ69: =IF(COUNT(C69:O69)=0,"",IFERROR(AL69/H69,0))
A70: =Config!$C$6+64 | B70: =INT((A70-Config!$C$6)/7)+1 | P70: =IF(COUNT(C70:O70)=0,"",IFERROR(C70/D70*1000,0)) | Q70: =IF(COUNT(C70:O70)=0,"",IFERROR(D70/E70,0)) | R70: =IF(COUNT(C70:O70)=0,"",IFERROR(F70/D70,0)) | S70: =IF(COUNT(C70:O70)=0,"",IFERROR(C70/F70,0)) | T70: =IF(COUNT(C70:O70)=0,"",IFERROR(G70/F70,0)) | U70: =IF(COUNT(C70:O70)=0,"",IFERROR(C70/G70,0)) | V70: =IF(COUNT(C70:O70)=0,"",IFERROR(G70/D70*1000,0)) | W70: =IF(COUNT(C70:O70)=0,"",IFERROR(H70/G70,0)) | X70: =IF(COUNT(C70:O70)=0,"",IFERROR(C70/H70,0)) | Y70: =IF(COUNT(C70:O70)=0,"",IFERROR(X70/P70,0)) | Z70: =IF(COUNT(C70:O70)=0,"",IFERROR(H70/D70*1000,0)) | AA70: =IF(COUNT(C70:O70)=0,"",IFERROR(I70/H70,0)) | AB70: =IF(COUNT(C70:O70)=0,"",IFERROR(J70/I70,0)) | AC70: =IF(COUNT(C70:O70)=0,"",IFERROR(K70/J70,0)) | AD70: =IF(COUNT(C70:O70)=0,"",IFERROR(C70/K70,0)) | AE70: =IF(COUNT(C70:O70)=0,"",IFERROR(L70/K70,0)) | AF70: =IF(COUNT(C70:O70)=0,"",IFERROR(M70/L70,0)) | AG70: =IF(COUNT(C70:O70)=0,"",IFERROR(M70/H70,0)) | AH70: =IF(COUNT(C70:O70)=0,"",IFERROR(C70/M70,0)) | AI70: =IF(COUNT(C70:O70)=0,"",IFERROR(M70*Config!$C$7+N70*Config!$C$8,0)) | AJ70: =IF(COUNT(C70:O70)=0,"",IFERROR(IF(O70>0,O70,AI70*Config!$C$9),0)) | AK70: =IF(COUNT(C70:O70)=0,"",IFERROR(AJ70*(1-Config!$C$10-Config!$C$11-Config!$C$12),0)) | AL70: =IF(COUNT(C70:O70)=0,"",IFERROR(AK70-C70-Config!$C$13,0)) | AM70: =IF(COUNT(C70:O70)=0,"",IFERROR(AK70/C70,0)) | AN70: =IF(COUNT(C70:O70)=0,"",IFERROR(AI70/C70,0)) | AO70: =IF(COUNT(C70:O70)=0,"",IFERROR(AL70/G70,0)) | AP70: =IF(COUNT(C70:O70)=0,"",IFERROR(AO70/U70,0)) | AQ70: =IF(COUNT(C70:O70)=0,"",IFERROR(AL70/H70,0))
A71: =Config!$C$6+65 | B71: =INT((A71-Config!$C$6)/7)+1 | P71: =IF(COUNT(C71:O71)=0,"",IFERROR(C71/D71*1000,0)) | Q71: =IF(COUNT(C71:O71)=0,"",IFERROR(D71/E71,0)) | R71: =IF(COUNT(C71:O71)=0,"",IFERROR(F71/D71,0)) | S71: =IF(COUNT(C71:O71)=0,"",IFERROR(C71/F71,0)) | T71: =IF(COUNT(C71:O71)=0,"",IFERROR(G71/F71,0)) | U71: =IF(COUNT(C71:O71)=0,"",IFERROR(C71/G71,0)) | V71: =IF(COUNT(C71:O71)=0,"",IFERROR(G71/D71*1000,0)) | W71: =IF(COUNT(C71:O71)=0,"",IFERROR(H71/G71,0)) | X71: =IF(COUNT(C71:O71)=0,"",IFERROR(C71/H71,0)) | Y71: =IF(COUNT(C71:O71)=0,"",IFERROR(X71/P71,0)) | Z71: =IF(COUNT(C71:O71)=0,"",IFERROR(H71/D71*1000,0)) | AA71: =IF(COUNT(C71:O71)=0,"",IFERROR(I71/H71,0)) | AB71: =IF(COUNT(C71:O71)=0,"",IFERROR(J71/I71,0)) | AC71: =IF(COUNT(C71:O71)=0,"",IFERROR(K71/J71,0)) | AD71: =IF(COUNT(C71:O71)=0,"",IFERROR(C71/K71,0)) | AE71: =IF(COUNT(C71:O71)=0,"",IFERROR(L71/K71,0)) | AF71: =IF(COUNT(C71:O71)=0,"",IFERROR(M71/L71,0)) | AG71: =IF(COUNT(C71:O71)=0,"",IFERROR(M71/H71,0)) | AH71: =IF(COUNT(C71:O71)=0,"",IFERROR(C71/M71,0)) | AI71: =IF(COUNT(C71:O71)=0,"",IFERROR(M71*Config!$C$7+N71*Config!$C$8,0)) | AJ71: =IF(COUNT(C71:O71)=0,"",IFERROR(IF(O71>0,O71,AI71*Config!$C$9),0)) | AK71: =IF(COUNT(C71:O71)=0,"",IFERROR(AJ71*(1-Config!$C$10-Config!$C$11-Config!$C$12),0)) | AL71: =IF(COUNT(C71:O71)=0,"",IFERROR(AK71-C71-Config!$C$13,0)) | AM71: =IF(COUNT(C71:O71)=0,"",IFERROR(AK71/C71,0)) | AN71: =IF(COUNT(C71:O71)=0,"",IFERROR(AI71/C71,0)) | AO71: =IF(COUNT(C71:O71)=0,"",IFERROR(AL71/G71,0)) | AP71: =IF(COUNT(C71:O71)=0,"",IFERROR(AO71/U71,0)) | AQ71: =IF(COUNT(C71:O71)=0,"",IFERROR(AL71/H71,0))
A72: =Config!$C$6+66 | B72: =INT((A72-Config!$C$6)/7)+1 | P72: =IF(COUNT(C72:O72)=0,"",IFERROR(C72/D72*1000,0)) | Q72: =IF(COUNT(C72:O72)=0,"",IFERROR(D72/E72,0)) | R72: =IF(COUNT(C72:O72)=0,"",IFERROR(F72/D72,0)) | S72: =IF(COUNT(C72:O72)=0,"",IFERROR(C72/F72,0)) | T72: =IF(COUNT(C72:O72)=0,"",IFERROR(G72/F72,0)) | U72: =IF(COUNT(C72:O72)=0,"",IFERROR(C72/G72,0)) | V72: =IF(COUNT(C72:O72)=0,"",IFERROR(G72/D72*1000,0)) | W72: =IF(COUNT(C72:O72)=0,"",IFERROR(H72/G72,0)) | X72: =IF(COUNT(C72:O72)=0,"",IFERROR(C72/H72,0)) | Y72: =IF(COUNT(C72:O72)=0,"",IFERROR(X72/P72,0)) | Z72: =IF(COUNT(C72:O72)=0,"",IFERROR(H72/D72*1000,0)) | AA72: =IF(COUNT(C72:O72)=0,"",IFERROR(I72/H72,0)) | AB72: =IF(COUNT(C72:O72)=0,"",IFERROR(J72/I72,0)) | AC72: =IF(COUNT(C72:O72)=0,"",IFERROR(K72/J72,0)) | AD72: =IF(COUNT(C72:O72)=0,"",IFERROR(C72/K72,0)) | AE72: =IF(COUNT(C72:O72)=0,"",IFERROR(L72/K72,0)) | AF72: =IF(COUNT(C72:O72)=0,"",IFERROR(M72/L72,0)) | AG72: =IF(COUNT(C72:O72)=0,"",IFERROR(M72/H72,0)) | AH72: =IF(COUNT(C72:O72)=0,"",IFERROR(C72/M72,0)) | AI72: =IF(COUNT(C72:O72)=0,"",IFERROR(M72*Config!$C$7+N72*Config!$C$8,0)) | AJ72: =IF(COUNT(C72:O72)=0,"",IFERROR(IF(O72>0,O72,AI72*Config!$C$9),0)) | AK72: =IF(COUNT(C72:O72)=0,"",IFERROR(AJ72*(1-Config!$C$10-Config!$C$11-Config!$C$12),0)) | AL72: =IF(COUNT(C72:O72)=0,"",IFERROR(AK72-C72-Config!$C$13,0)) | AM72: =IF(COUNT(C72:O72)=0,"",IFERROR(AK72/C72,0)) | AN72: =IF(COUNT(C72:O72)=0,"",IFERROR(AI72/C72,0)) | AO72: =IF(COUNT(C72:O72)=0,"",IFERROR(AL72/G72,0)) | AP72: =IF(COUNT(C72:O72)=0,"",IFERROR(AO72/U72,0)) | AQ72: =IF(COUNT(C72:O72)=0,"",IFERROR(AL72/H72,0))
A73: =Config!$C$6+67 | B73: =INT((A73-Config!$C$6)/7)+1 | P73: =IF(COUNT(C73:O73)=0,"",IFERROR(C73/D73*1000,0)) | Q73: =IF(COUNT(C73:O73)=0,"",IFERROR(D73/E73,0)) | R73: =IF(COUNT(C73:O73)=0,"",IFERROR(F73/D73,0)) | S73: =IF(COUNT(C73:O73)=0,"",IFERROR(C73/F73,0)) | T73: =IF(COUNT(C73:O73)=0,"",IFERROR(G73/F73,0)) | U73: =IF(COUNT(C73:O73)=0,"",IFERROR(C73/G73,0)) | V73: =IF(COUNT(C73:O73)=0,"",IFERROR(G73/D73*1000,0)) | W73: =IF(COUNT(C73:O73)=0,"",IFERROR(H73/G73,0)) | X73: =IF(COUNT(C73:O73)=0,"",IFERROR(C73/H73,0)) | Y73: =IF(COUNT(C73:O73)=0,"",IFERROR(X73/P73,0)) | Z73: =IF(COUNT(C73:O73)=0,"",IFERROR(H73/D73*1000,0)) | AA73: =IF(COUNT(C73:O73)=0,"",IFERROR(I73/H73,0)) | AB73: =IF(COUNT(C73:O73)=0,"",IFERROR(J73/I73,0)) | AC73: =IF(COUNT(C73:O73)=0,"",IFERROR(K73/J73,0)) | AD73: =IF(COUNT(C73:O73)=0,"",IFERROR(C73/K73,0)) | AE73: =IF(COUNT(C73:O73)=0,"",IFERROR(L73/K73,0)) | AF73: =IF(COUNT(C73:O73)=0,"",IFERROR(M73/L73,0)) | AG73: =IF(COUNT(C73:O73)=0,"",IFERROR(M73/H73,0)) | AH73: =IF(COUNT(C73:O73)=0,"",IFERROR(C73/M73,0)) | AI73: =IF(COUNT(C73:O73)=0,"",IFERROR(M73*Config!$C$7+N73*Config!$C$8,0)) | AJ73: =IF(COUNT(C73:O73)=0,"",IFERROR(IF(O73>0,O73,AI73*Config!$C$9),0)) | AK73: =IF(COUNT(C73:O73)=0,"",IFERROR(AJ73*(1-Config!$C$10-Config!$C$11-Config!$C$12),0)) | AL73: =IF(COUNT(C73:O73)=0,"",IFERROR(AK73-C73-Config!$C$13,0)) | AM73: =IF(COUNT(C73:O73)=0,"",IFERROR(AK73/C73,0)) | AN73: =IF(COUNT(C73:O73)=0,"",IFERROR(AI73/C73,0)) | AO73: =IF(COUNT(C73:O73)=0,"",IFERROR(AL73/G73,0)) | AP73: =IF(COUNT(C73:O73)=0,"",IFERROR(AO73/U73,0)) | AQ73: =IF(COUNT(C73:O73)=0,"",IFERROR(AL73/H73,0))
A74: =Config!$C$6+68 | B74: =INT((A74-Config!$C$6)/7)+1 | P74: =IF(COUNT(C74:O74)=0,"",IFERROR(C74/D74*1000,0)) | Q74: =IF(COUNT(C74:O74)=0,"",IFERROR(D74/E74,0)) | R74: =IF(COUNT(C74:O74)=0,"",IFERROR(F74/D74,0)) | S74: =IF(COUNT(C74:O74)=0,"",IFERROR(C74/F74,0)) | T74: =IF(COUNT(C74:O74)=0,"",IFERROR(G74/F74,0)) | U74: =IF(COUNT(C74:O74)=0,"",IFERROR(C74/G74,0)) | V74: =IF(COUNT(C74:O74)=0,"",IFERROR(G74/D74*1000,0)) | W74: =IF(COUNT(C74:O74)=0,"",IFERROR(H74/G74,0)) | X74: =IF(COUNT(C74:O74)=0,"",IFERROR(C74/H74,0)) | Y74: =IF(COUNT(C74:O74)=0,"",IFERROR(X74/P74,0)) | Z74: =IF(COUNT(C74:O74)=0,"",IFERROR(H74/D74*1000,0)) | AA74: =IF(COUNT(C74:O74)=0,"",IFERROR(I74/H74,0)) | AB74: =IF(COUNT(C74:O74)=0,"",IFERROR(J74/I74,0)) | AC74: =IF(COUNT(C74:O74)=0,"",IFERROR(K74/J74,0)) | AD74: =IF(COUNT(C74:O74)=0,"",IFERROR(C74/K74,0)) | AE74: =IF(COUNT(C74:O74)=0,"",IFERROR(L74/K74,0)) | AF74: =IF(COUNT(C74:O74)=0,"",IFERROR(M74/L74,0)) | AG74: =IF(COUNT(C74:O74)=0,"",IFERROR(M74/H74,0)) | AH74: =IF(COUNT(C74:O74)=0,"",IFERROR(C74/M74,0)) | AI74: =IF(COUNT(C74:O74)=0,"",IFERROR(M74*Config!$C$7+N74*Config!$C$8,0)) | AJ74: =IF(COUNT(C74:O74)=0,"",IFERROR(IF(O74>0,O74,AI74*Config!$C$9),0)) | AK74: =IF(COUNT(C74:O74)=0,"",IFERROR(AJ74*(1-Config!$C$10-Config!$C$11-Config!$C$12),0)) | AL74: =IF(COUNT(C74:O74)=0,"",IFERROR(AK74-C74-Config!$C$13,0)) | AM74: =IF(COUNT(C74:O74)=0,"",IFERROR(AK74/C74,0)) | AN74: =IF(COUNT(C74:O74)=0,"",IFERROR(AI74/C74,0)) | AO74: =IF(COUNT(C74:O74)=0,"",IFERROR(AL74/G74,0)) | AP74: =IF(COUNT(C74:O74)=0,"",IFERROR(AO74/U74,0)) | AQ74: =IF(COUNT(C74:O74)=0,"",IFERROR(AL74/H74,0))
A75: =Config!$C$6+69 | B75: =INT((A75-Config!$C$6)/7)+1 | P75: =IF(COUNT(C75:O75)=0,"",IFERROR(C75/D75*1000,0)) | Q75: =IF(COUNT(C75:O75)=0,"",IFERROR(D75/E75,0)) | R75: =IF(COUNT(C75:O75)=0,"",IFERROR(F75/D75,0)) | S75: =IF(COUNT(C75:O75)=0,"",IFERROR(C75/F75,0)) | T75: =IF(COUNT(C75:O75)=0,"",IFERROR(G75/F75,0)) | U75: =IF(COUNT(C75:O75)=0,"",IFERROR(C75/G75,0)) | V75: =IF(COUNT(C75:O75)=0,"",IFERROR(G75/D75*1000,0)) | W75: =IF(COUNT(C75:O75)=0,"",IFERROR(H75/G75,0)) | X75: =IF(COUNT(C75:O75)=0,"",IFERROR(C75/H75,0)) | Y75: =IF(COUNT(C75:O75)=0,"",IFERROR(X75/P75,0)) | Z75: =IF(COUNT(C75:O75)=0,"",IFERROR(H75/D75*1000,0)) | AA75: =IF(COUNT(C75:O75)=0,"",IFERROR(I75/H75,0)) | AB75: =IF(COUNT(C75:O75)=0,"",IFERROR(J75/I75,0)) | AC75: =IF(COUNT(C75:O75)=0,"",IFERROR(K75/J75,0)) | AD75: =IF(COUNT(C75:O75)=0,"",IFERROR(C75/K75,0)) | AE75: =IF(COUNT(C75:O75)=0,"",IFERROR(L75/K75,0)) | AF75: =IF(COUNT(C75:O75)=0,"",IFERROR(M75/L75,0)) | AG75: =IF(COUNT(C75:O75)=0,"",IFERROR(M75/H75,0)) | AH75: =IF(COUNT(C75:O75)=0,"",IFERROR(C75/M75,0)) | AI75: =IF(COUNT(C75:O75)=0,"",IFERROR(M75*Config!$C$7+N75*Config!$C$8,0)) | AJ75: =IF(COUNT(C75:O75)=0,"",IFERROR(IF(O75>0,O75,AI75*Config!$C$9),0)) | AK75: =IF(COUNT(C75:O75)=0,"",IFERROR(AJ75*(1-Config!$C$10-Config!$C$11-Config!$C$12),0)) | AL75: =IF(COUNT(C75:O75)=0,"",IFERROR(AK75-C75-Config!$C$13,0)) | AM75: =IF(COUNT(C75:O75)=0,"",IFERROR(AK75/C75,0)) | AN75: =IF(COUNT(C75:O75)=0,"",IFERROR(AI75/C75,0)) | AO75: =IF(COUNT(C75:O75)=0,"",IFERROR(AL75/G75,0)) | AP75: =IF(COUNT(C75:O75)=0,"",IFERROR(AO75/U75,0)) | AQ75: =IF(COUNT(C75:O75)=0,"",IFERROR(AL75/H75,0))
A76: =Config!$C$6+70 | B76: =INT((A76-Config!$C$6)/7)+1 | P76: =IF(COUNT(C76:O76)=0,"",IFERROR(C76/D76*1000,0)) | Q76: =IF(COUNT(C76:O76)=0,"",IFERROR(D76/E76,0)) | R76: =IF(COUNT(C76:O76)=0,"",IFERROR(F76/D76,0)) | S76: =IF(COUNT(C76:O76)=0,"",IFERROR(C76/F76,0)) | T76: =IF(COUNT(C76:O76)=0,"",IFERROR(G76/F76,0)) | U76: =IF(COUNT(C76:O76)=0,"",IFERROR(C76/G76,0)) | V76: =IF(COUNT(C76:O76)=0,"",IFERROR(G76/D76*1000,0)) | W76: =IF(COUNT(C76:O76)=0,"",IFERROR(H76/G76,0)) | X76: =IF(COUNT(C76:O76)=0,"",IFERROR(C76/H76,0)) | Y76: =IF(COUNT(C76:O76)=0,"",IFERROR(X76/P76,0)) | Z76: =IF(COUNT(C76:O76)=0,"",IFERROR(H76/D76*1000,0)) | AA76: =IF(COUNT(C76:O76)=0,"",IFERROR(I76/H76,0)) | AB76: =IF(COUNT(C76:O76)=0,"",IFERROR(J76/I76,0)) | AC76: =IF(COUNT(C76:O76)=0,"",IFERROR(K76/J76,0)) | AD76: =IF(COUNT(C76:O76)=0,"",IFERROR(C76/K76,0)) | AE76: =IF(COUNT(C76:O76)=0,"",IFERROR(L76/K76,0)) | AF76: =IF(COUNT(C76:O76)=0,"",IFERROR(M76/L76,0)) | AG76: =IF(COUNT(C76:O76)=0,"",IFERROR(M76/H76,0)) | AH76: =IF(COUNT(C76:O76)=0,"",IFERROR(C76/M76,0)) | AI76: =IF(COUNT(C76:O76)=0,"",IFERROR(M76*Config!$C$7+N76*Config!$C$8,0)) | AJ76: =IF(COUNT(C76:O76)=0,"",IFERROR(IF(O76>0,O76,AI76*Config!$C$9),0)) | AK76: =IF(COUNT(C76:O76)=0,"",IFERROR(AJ76*(1-Config!$C$10-Config!$C$11-Config!$C$12),0)) | AL76: =IF(COUNT(C76:O76)=0,"",IFERROR(AK76-C76-Config!$C$13,0)) | AM76: =IF(COUNT(C76:O76)=0,"",IFERROR(AK76/C76,0)) | AN76: =IF(COUNT(C76:O76)=0,"",IFERROR(AI76/C76,0)) | AO76: =IF(COUNT(C76:O76)=0,"",IFERROR(AL76/G76,0)) | AP76: =IF(COUNT(C76:O76)=0,"",IFERROR(AO76/U76,0)) | AQ76: =IF(COUNT(C76:O76)=0,"",IFERROR(AL76/H76,0))
A77: =Config!$C$6+71 | B77: =INT((A77-Config!$C$6)/7)+1 | P77: =IF(COUNT(C77:O77)=0,"",IFERROR(C77/D77*1000,0)) | Q77: =IF(COUNT(C77:O77)=0,"",IFERROR(D77/E77,0)) | R77: =IF(COUNT(C77:O77)=0,"",IFERROR(F77/D77,0)) | S77: =IF(COUNT(C77:O77)=0,"",IFERROR(C77/F77,0)) | T77: =IF(COUNT(C77:O77)=0,"",IFERROR(G77/F77,0)) | U77: =IF(COUNT(C77:O77)=0,"",IFERROR(C77/G77,0)) | V77: =IF(COUNT(C77:O77)=0,"",IFERROR(G77/D77*1000,0)) | W77: =IF(COUNT(C77:O77)=0,"",IFERROR(H77/G77,0)) | X77: =IF(COUNT(C77:O77)=0,"",IFERROR(C77/H77,0)) | Y77: =IF(COUNT(C77:O77)=0,"",IFERROR(X77/P77,0)) | Z77: =IF(COUNT(C77:O77)=0,"",IFERROR(H77/D77*1000,0)) | AA77: =IF(COUNT(C77:O77)=0,"",IFERROR(I77/H77,0)) | AB77: =IF(COUNT(C77:O77)=0,"",IFERROR(J77/I77,0)) | AC77: =IF(COUNT(C77:O77)=0,"",IFERROR(K77/J77,0)) | AD77: =IF(COUNT(C77:O77)=0,"",IFERROR(C77/K77,0)) | AE77: =IF(COUNT(C77:O77)=0,"",IFERROR(L77/K77,0)) | AF77: =IF(COUNT(C77:O77)=0,"",IFERROR(M77/L77,0)) | AG77: =IF(COUNT(C77:O77)=0,"",IFERROR(M77/H77,0)) | AH77: =IF(COUNT(C77:O77)=0,"",IFERROR(C77/M77,0)) | AI77: =IF(COUNT(C77:O77)=0,"",IFERROR(M77*Config!$C$7+N77*Config!$C$8,0)) | AJ77: =IF(COUNT(C77:O77)=0,"",IFERROR(IF(O77>0,O77,AI77*Config!$C$9),0)) | AK77: =IF(COUNT(C77:O77)=0,"",IFERROR(AJ77*(1-Config!$C$10-Config!$C$11-Config!$C$12),0)) | AL77: =IF(COUNT(C77:O77)=0,"",IFERROR(AK77-C77-Config!$C$13,0)) | AM77: =IF(COUNT(C77:O77)=0,"",IFERROR(AK77/C77,0)) | AN77: =IF(COUNT(C77:O77)=0,"",IFERROR(AI77/C77,0)) | AO77: =IF(COUNT(C77:O77)=0,"",IFERROR(AL77/G77,0)) | AP77: =IF(COUNT(C77:O77)=0,"",IFERROR(AO77/U77,0)) | AQ77: =IF(COUNT(C77:O77)=0,"",IFERROR(AL77/H77,0))
A78: =Config!$C$6+72 | B78: =INT((A78-Config!$C$6)/7)+1 | P78: =IF(COUNT(C78:O78)=0,"",IFERROR(C78/D78*1000,0)) | Q78: =IF(COUNT(C78:O78)=0,"",IFERROR(D78/E78,0)) | R78: =IF(COUNT(C78:O78)=0,"",IFERROR(F78/D78,0)) | S78: =IF(COUNT(C78:O78)=0,"",IFERROR(C78/F78,0)) | T78: =IF(COUNT(C78:O78)=0,"",IFERROR(G78/F78,0)) | U78: =IF(COUNT(C78:O78)=0,"",IFERROR(C78/G78,0)) | V78: =IF(COUNT(C78:O78)=0,"",IFERROR(G78/D78*1000,0)) | W78: =IF(COUNT(C78:O78)=0,"",IFERROR(H78/G78,0)) | X78: =IF(COUNT(C78:O78)=0,"",IFERROR(C78/H78,0)) | Y78: =IF(COUNT(C78:O78)=0,"",IFERROR(X78/P78,0)) | Z78: =IF(COUNT(C78:O78)=0,"",IFERROR(H78/D78*1000,0)) | AA78: =IF(COUNT(C78:O78)=0,"",IFERROR(I78/H78,0)) | AB78: =IF(COUNT(C78:O78)=0,"",IFERROR(J78/I78,0)) | AC78: =IF(COUNT(C78:O78)=0,"",IFERROR(K78/J78,0)) | AD78: =IF(COUNT(C78:O78)=0,"",IFERROR(C78/K78,0)) | AE78: =IF(COUNT(C78:O78)=0,"",IFERROR(L78/K78,0)) | AF78: =IF(COUNT(C78:O78)=0,"",IFERROR(M78/L78,0)) | AG78: =IF(COUNT(C78:O78)=0,"",IFERROR(M78/H78,0)) | AH78: =IF(COUNT(C78:O78)=0,"",IFERROR(C78/M78,0)) | AI78: =IF(COUNT(C78:O78)=0,"",IFERROR(M78*Config!$C$7+N78*Config!$C$8,0)) | AJ78: =IF(COUNT(C78:O78)=0,"",IFERROR(IF(O78>0,O78,AI78*Config!$C$9),0)) | AK78: =IF(COUNT(C78:O78)=0,"",IFERROR(AJ78*(1-Config!$C$10-Config!$C$11-Config!$C$12),0)) | AL78: =IF(COUNT(C78:O78)=0,"",IFERROR(AK78-C78-Config!$C$13,0)) | AM78: =IF(COUNT(C78:O78)=0,"",IFERROR(AK78/C78,0)) | AN78: =IF(COUNT(C78:O78)=0,"",IFERROR(AI78/C78,0)) | AO78: =IF(COUNT(C78:O78)=0,"",IFERROR(AL78/G78,0)) | AP78: =IF(COUNT(C78:O78)=0,"",IFERROR(AO78/U78,0)) | AQ78: =IF(COUNT(C78:O78)=0,"",IFERROR(AL78/H78,0))
A79: =Config!$C$6+73 | B79: =INT((A79-Config!$C$6)/7)+1 | P79: =IF(COUNT(C79:O79)=0,"",IFERROR(C79/D79*1000,0)) | Q79: =IF(COUNT(C79:O79)=0,"",IFERROR(D79/E79,0)) | R79: =IF(COUNT(C79:O79)=0,"",IFERROR(F79/D79,0)) | S79: =IF(COUNT(C79:O79)=0,"",IFERROR(C79/F79,0)) | T79: =IF(COUNT(C79:O79)=0,"",IFERROR(G79/F79,0)) | U79: =IF(COUNT(C79:O79)=0,"",IFERROR(C79/G79,0)) | V79: =IF(COUNT(C79:O79)=0,"",IFERROR(G79/D79*1000,0)) | W79: =IF(COUNT(C79:O79)=0,"",IFERROR(H79/G79,0)) | X79: =IF(COUNT(C79:O79)=0,"",IFERROR(C79/H79,0)) | Y79: =IF(COUNT(C79:O79)=0,"",IFERROR(X79/P79,0)) | Z79: =IF(COUNT(C79:O79)=0,"",IFERROR(H79/D79*1000,0)) | AA79: =IF(COUNT(C79:O79)=0,"",IFERROR(I79/H79,0)) | AB79: =IF(COUNT(C79:O79)=0,"",IFERROR(J79/I79,0)) | AC79: =IF(COUNT(C79:O79)=0,"",IFERROR(K79/J79,0)) | AD79: =IF(COUNT(C79:O79)=0,"",IFERROR(C79/K79,0)) | AE79: =IF(COUNT(C79:O79)=0,"",IFERROR(L79/K79,0)) | AF79: =IF(COUNT(C79:O79)=0,"",IFERROR(M79/L79,0)) | AG79: =IF(COUNT(C79:O79)=0,"",IFERROR(M79/H79,0)) | AH79: =IF(COUNT(C79:O79)=0,"",IFERROR(C79/M79,0)) | AI79: =IF(COUNT(C79:O79)=0,"",IFERROR(M79*Config!$C$7+N79*Config!$C$8,0)) | AJ79: =IF(COUNT(C79:O79)=0,"",IFERROR(IF(O79>0,O79,AI79*Config!$C$9),0)) | AK79: =IF(COUNT(C79:O79)=0,"",IFERROR(AJ79*(1-Config!$C$10-Config!$C$11-Config!$C$12),0)) | AL79: =IF(COUNT(C79:O79)=0,"",IFERROR(AK79-C79-Config!$C$13,0)) | AM79: =IF(COUNT(C79:O79)=0,"",IFERROR(AK79/C79,0)) | AN79: =IF(COUNT(C79:O79)=0,"",IFERROR(AI79/C79,0)) | AO79: =IF(COUNT(C79:O79)=0,"",IFERROR(AL79/G79,0)) | AP79: =IF(COUNT(C79:O79)=0,"",IFERROR(AO79/U79,0)) | AQ79: =IF(COUNT(C79:O79)=0,"",IFERROR(AL79/H79,0))
A80: =Config!$C$6+74 | B80: =INT((A80-Config!$C$6)/7)+1 | P80: =IF(COUNT(C80:O80)=0,"",IFERROR(C80/D80*1000,0)) | Q80: =IF(COUNT(C80:O80)=0,"",IFERROR(D80/E80,0)) | R80: =IF(COUNT(C80:O80)=0,"",IFERROR(F80/D80,0)) | S80: =IF(COUNT(C80:O80)=0,"",IFERROR(C80/F80,0)) | T80: =IF(COUNT(C80:O80)=0,"",IFERROR(G80/F80,0)) | U80: =IF(COUNT(C80:O80)=0,"",IFERROR(C80/G80,0)) | V80: =IF(COUNT(C80:O80)=0,"",IFERROR(G80/D80*1000,0)) | W80: =IF(COUNT(C80:O80)=0,"",IFERROR(H80/G80,0)) | X80: =IF(COUNT(C80:O80)=0,"",IFERROR(C80/H80,0)) | Y80: =IF(COUNT(C80:O80)=0,"",IFERROR(X80/P80,0)) | Z80: =IF(COUNT(C80:O80)=0,"",IFERROR(H80/D80*1000,0)) | AA80: =IF(COUNT(C80:O80)=0,"",IFERROR(I80/H80,0)) | AB80: =IF(COUNT(C80:O80)=0,"",IFERROR(J80/I80,0)) | AC80: =IF(COUNT(C80:O80)=0,"",IFERROR(K80/J80,0)) | AD80: =IF(COUNT(C80:O80)=0,"",IFERROR(C80/K80,0)) | AE80: =IF(COUNT(C80:O80)=0,"",IFERROR(L80/K80,0)) | AF80: =IF(COUNT(C80:O80)=0,"",IFERROR(M80/L80,0)) | AG80: =IF(COUNT(C80:O80)=0,"",IFERROR(M80/H80,0)) | AH80: =IF(COUNT(C80:O80)=0,"",IFERROR(C80/M80,0)) | AI80: =IF(COUNT(C80:O80)=0,"",IFERROR(M80*Config!$C$7+N80*Config!$C$8,0)) | AJ80: =IF(COUNT(C80:O80)=0,"",IFERROR(IF(O80>0,O80,AI80*Config!$C$9),0)) | AK80: =IF(COUNT(C80:O80)=0,"",IFERROR(AJ80*(1-Config!$C$10-Config!$C$11-Config!$C$12),0)) | AL80: =IF(COUNT(C80:O80)=0,"",IFERROR(AK80-C80-Config!$C$13,0)) | AM80: =IF(COUNT(C80:O80)=0,"",IFERROR(AK80/C80,0)) | AN80: =IF(COUNT(C80:O80)=0,"",IFERROR(AI80/C80,0)) | AO80: =IF(COUNT(C80:O80)=0,"",IFERROR(AL80/G80,0)) | AP80: =IF(COUNT(C80:O80)=0,"",IFERROR(AO80/U80,0)) | AQ80: =IF(COUNT(C80:O80)=0,"",IFERROR(AL80/H80,0))
A81: =Config!$C$6+75 | B81: =INT((A81-Config!$C$6)/7)+1 | P81: =IF(COUNT(C81:O81)=0,"",IFERROR(C81/D81*1000,0)) | Q81: =IF(COUNT(C81:O81)=0,"",IFERROR(D81/E81,0)) | R81: =IF(COUNT(C81:O81)=0,"",IFERROR(F81/D81,0)) | S81: =IF(COUNT(C81:O81)=0,"",IFERROR(C81/F81,0)) | T81: =IF(COUNT(C81:O81)=0,"",IFERROR(G81/F81,0)) | U81: =IF(COUNT(C81:O81)=0,"",IFERROR(C81/G81,0)) | V81: =IF(COUNT(C81:O81)=0,"",IFERROR(G81/D81*1000,0)) | W81: =IF(COUNT(C81:O81)=0,"",IFERROR(H81/G81,0)) | X81: =IF(COUNT(C81:O81)=0,"",IFERROR(C81/H81,0)) | Y81: =IF(COUNT(C81:O81)=0,"",IFERROR(X81/P81,0)) | Z81: =IF(COUNT(C81:O81)=0,"",IFERROR(H81/D81*1000,0)) | AA81: =IF(COUNT(C81:O81)=0,"",IFERROR(I81/H81,0)) | AB81: =IF(COUNT(C81:O81)=0,"",IFERROR(J81/I81,0)) | AC81: =IF(COUNT(C81:O81)=0,"",IFERROR(K81/J81,0)) | AD81: =IF(COUNT(C81:O81)=0,"",IFERROR(C81/K81,0)) | AE81: =IF(COUNT(C81:O81)=0,"",IFERROR(L81/K81,0)) | AF81: =IF(COUNT(C81:O81)=0,"",IFERROR(M81/L81,0)) | AG81: =IF(COUNT(C81:O81)=0,"",IFERROR(M81/H81,0)) | AH81: =IF(COUNT(C81:O81)=0,"",IFERROR(C81/M81,0)) | AI81: =IF(COUNT(C81:O81)=0,"",IFERROR(M81*Config!$C$7+N81*Config!$C$8,0)) | AJ81: =IF(COUNT(C81:O81)=0,"",IFERROR(IF(O81>0,O81,AI81*Config!$C$9),0)) | AK81: =IF(COUNT(C81:O81)=0,"",IFERROR(AJ81*(1-Config!$C$10-Config!$C$11-Config!$C$12),0)) | AL81: =IF(COUNT(C81:O81)=0,"",IFERROR(AK81-C81-Config!$C$13,0)) | AM81: =IF(COUNT(C81:O81)=0,"",IFERROR(AK81/C81,0)) | AN81: =IF(COUNT(C81:O81)=0,"",IFERROR(AI81/C81,0)) | AO81: =IF(COUNT(C81:O81)=0,"",IFERROR(AL81/G81,0)) | AP81: =IF(COUNT(C81:O81)=0,"",IFERROR(AO81/U81,0)) | AQ81: =IF(COUNT(C81:O81)=0,"",IFERROR(AL81/H81,0))
A82: =Config!$C$6+76 | B82: =INT((A82-Config!$C$6)/7)+1 | P82: =IF(COUNT(C82:O82)=0,"",IFERROR(C82/D82*1000,0)) | Q82: =IF(COUNT(C82:O82)=0,"",IFERROR(D82/E82,0)) | R82: =IF(COUNT(C82:O82)=0,"",IFERROR(F82/D82,0)) | S82: =IF(COUNT(C82:O82)=0,"",IFERROR(C82/F82,0)) | T82: =IF(COUNT(C82:O82)=0,"",IFERROR(G82/F82,0)) | U82: =IF(COUNT(C82:O82)=0,"",IFERROR(C82/G82,0)) | V82: =IF(COUNT(C82:O82)=0,"",IFERROR(G82/D82*1000,0)) | W82: =IF(COUNT(C82:O82)=0,"",IFERROR(H82/G82,0)) | X82: =IF(COUNT(C82:O82)=0,"",IFERROR(C82/H82,0)) | Y82: =IF(COUNT(C82:O82)=0,"",IFERROR(X82/P82,0)) | Z82: =IF(COUNT(C82:O82)=0,"",IFERROR(H82/D82*1000,0)) | AA82: =IF(COUNT(C82:O82)=0,"",IFERROR(I82/H82,0)) | AB82: =IF(COUNT(C82:O82)=0,"",IFERROR(J82/I82,0)) | AC82: =IF(COUNT(C82:O82)=0,"",IFERROR(K82/J82,0)) | AD82: =IF(COUNT(C82:O82)=0,"",IFERROR(C82/K82,0)) | AE82: =IF(COUNT(C82:O82)=0,"",IFERROR(L82/K82,0)) | AF82: =IF(COUNT(C82:O82)=0,"",IFERROR(M82/L82,0)) | AG82: =IF(COUNT(C82:O82)=0,"",IFERROR(M82/H82,0)) | AH82: =IF(COUNT(C82:O82)=0,"",IFERROR(C82/M82,0)) | AI82: =IF(COUNT(C82:O82)=0,"",IFERROR(M82*Config!$C$7+N82*Config!$C$8,0)) | AJ82: =IF(COUNT(C82:O82)=0,"",IFERROR(IF(O82>0,O82,AI82*Config!$C$9),0)) | AK82: =IF(COUNT(C82:O82)=0,"",IFERROR(AJ82*(1-Config!$C$10-Config!$C$11-Config!$C$12),0)) | AL82: =IF(COUNT(C82:O82)=0,"",IFERROR(AK82-C82-Config!$C$13,0)) | AM82: =IF(COUNT(C82:O82)=0,"",IFERROR(AK82/C82,0)) | AN82: =IF(COUNT(C82:O82)=0,"",IFERROR(AI82/C82,0)) | AO82: =IF(COUNT(C82:O82)=0,"",IFERROR(AL82/G82,0)) | AP82: =IF(COUNT(C82:O82)=0,"",IFERROR(AO82/U82,0)) | AQ82: =IF(COUNT(C82:O82)=0,"",IFERROR(AL82/H82,0))
A83: =Config!$C$6+77 | B83: =INT((A83-Config!$C$6)/7)+1 | P83: =IF(COUNT(C83:O83)=0,"",IFERROR(C83/D83*1000,0)) | Q83: =IF(COUNT(C83:O83)=0,"",IFERROR(D83/E83,0)) | R83: =IF(COUNT(C83:O83)=0,"",IFERROR(F83/D83,0)) | S83: =IF(COUNT(C83:O83)=0,"",IFERROR(C83/F83,0)) | T83: =IF(COUNT(C83:O83)=0,"",IFERROR(G83/F83,0)) | U83: =IF(COUNT(C83:O83)=0,"",IFERROR(C83/G83,0)) | V83: =IF(COUNT(C83:O83)=0,"",IFERROR(G83/D83*1000,0)) | W83: =IF(COUNT(C83:O83)=0,"",IFERROR(H83/G83,0)) | X83: =IF(COUNT(C83:O83)=0,"",IFERROR(C83/H83,0)) | Y83: =IF(COUNT(C83:O83)=0,"",IFERROR(X83/P83,0)) | Z83: =IF(COUNT(C83:O83)=0,"",IFERROR(H83/D83*1000,0)) | AA83: =IF(COUNT(C83:O83)=0,"",IFERROR(I83/H83,0)) | AB83: =IF(COUNT(C83:O83)=0,"",IFERROR(J83/I83,0)) | AC83: =IF(COUNT(C83:O83)=0,"",IFERROR(K83/J83,0)) | AD83: =IF(COUNT(C83:O83)=0,"",IFERROR(C83/K83,0)) | AE83: =IF(COUNT(C83:O83)=0,"",IFERROR(L83/K83,0)) | AF83: =IF(COUNT(C83:O83)=0,"",IFERROR(M83/L83,0)) | AG83: =IF(COUNT(C83:O83)=0,"",IFERROR(M83/H83,0)) | AH83: =IF(COUNT(C83:O83)=0,"",IFERROR(C83/M83,0)) | AI83: =IF(COUNT(C83:O83)=0,"",IFERROR(M83*Config!$C$7+N83*Config!$C$8,0)) | AJ83: =IF(COUNT(C83:O83)=0,"",IFERROR(IF(O83>0,O83,AI83*Config!$C$9),0)) | AK83: =IF(COUNT(C83:O83)=0,"",IFERROR(AJ83*(1-Config!$C$10-Config!$C$11-Config!$C$12),0)) | AL83: =IF(COUNT(C83:O83)=0,"",IFERROR(AK83-C83-Config!$C$13,0)) | AM83: =IF(COUNT(C83:O83)=0,"",IFERROR(AK83/C83,0)) | AN83: =IF(COUNT(C83:O83)=0,"",IFERROR(AI83/C83,0)) | AO83: =IF(COUNT(C83:O83)=0,"",IFERROR(AL83/G83,0)) | AP83: =IF(COUNT(C83:O83)=0,"",IFERROR(AO83/U83,0)) | AQ83: =IF(COUNT(C83:O83)=0,"",IFERROR(AL83/H83,0))
A84: =Config!$C$6+78 | B84: =INT((A84-Config!$C$6)/7)+1 | P84: =IF(COUNT(C84:O84)=0,"",IFERROR(C84/D84*1000,0)) | Q84: =IF(COUNT(C84:O84)=0,"",IFERROR(D84/E84,0)) | R84: =IF(COUNT(C84:O84)=0,"",IFERROR(F84/D84,0)) | S84: =IF(COUNT(C84:O84)=0,"",IFERROR(C84/F84,0)) | T84: =IF(COUNT(C84:O84)=0,"",IFERROR(G84/F84,0)) | U84: =IF(COUNT(C84:O84)=0,"",IFERROR(C84/G84,0)) | V84: =IF(COUNT(C84:O84)=0,"",IFERROR(G84/D84*1000,0)) | W84: =IF(COUNT(C84:O84)=0,"",IFERROR(H84/G84,0)) | X84: =IF(COUNT(C84:O84)=0,"",IFERROR(C84/H84,0)) | Y84: =IF(COUNT(C84:O84)=0,"",IFERROR(X84/P84,0)) | Z84: =IF(COUNT(C84:O84)=0,"",IFERROR(H84/D84*1000,0)) | AA84: =IF(COUNT(C84:O84)=0,"",IFERROR(I84/H84,0)) | AB84: =IF(COUNT(C84:O84)=0,"",IFERROR(J84/I84,0)) | AC84: =IF(COUNT(C84:O84)=0,"",IFERROR(K84/J84,0)) | AD84: =IF(COUNT(C84:O84)=0,"",IFERROR(C84/K84,0)) | AE84: =IF(COUNT(C84:O84)=0,"",IFERROR(L84/K84,0)) | AF84: =IF(COUNT(C84:O84)=0,"",IFERROR(M84/L84,0)) | AG84: =IF(COUNT(C84:O84)=0,"",IFERROR(M84/H84,0)) | AH84: =IF(COUNT(C84:O84)=0,"",IFERROR(C84/M84,0)) | AI84: =IF(COUNT(C84:O84)=0,"",IFERROR(M84*Config!$C$7+N84*Config!$C$8,0)) | AJ84: =IF(COUNT(C84:O84)=0,"",IFERROR(IF(O84>0,O84,AI84*Config!$C$9),0)) | AK84: =IF(COUNT(C84:O84)=0,"",IFERROR(AJ84*(1-Config!$C$10-Config!$C$11-Config!$C$12),0)) | AL84: =IF(COUNT(C84:O84)=0,"",IFERROR(AK84-C84-Config!$C$13,0)) | AM84: =IF(COUNT(C84:O84)=0,"",IFERROR(AK84/C84,0)) | AN84: =IF(COUNT(C84:O84)=0,"",IFERROR(AI84/C84,0)) | AO84: =IF(COUNT(C84:O84)=0,"",IFERROR(AL84/G84,0)) | AP84: =IF(COUNT(C84:O84)=0,"",IFERROR(AO84/U84,0)) | AQ84: =IF(COUNT(C84:O84)=0,"",IFERROR(AL84/H84,0))
A85: =Config!$C$6+79 | B85: =INT((A85-Config!$C$6)/7)+1 | P85: =IF(COUNT(C85:O85)=0,"",IFERROR(C85/D85*1000,0)) | Q85: =IF(COUNT(C85:O85)=0,"",IFERROR(D85/E85,0)) | R85: =IF(COUNT(C85:O85)=0,"",IFERROR(F85/D85,0)) | S85: =IF(COUNT(C85:O85)=0,"",IFERROR(C85/F85,0)) | T85: =IF(COUNT(C85:O85)=0,"",IFERROR(G85/F85,0)) | U85: =IF(COUNT(C85:O85)=0,"",IFERROR(C85/G85,0)) | V85: =IF(COUNT(C85:O85)=0,"",IFERROR(G85/D85*1000,0)) | W85: =IF(COUNT(C85:O85)=0,"",IFERROR(H85/G85,0)) | X85: =IF(COUNT(C85:O85)=0,"",IFERROR(C85/H85,0)) | Y85: =IF(COUNT(C85:O85)=0,"",IFERROR(X85/P85,0)) | Z85: =IF(COUNT(C85:O85)=0,"",IFERROR(H85/D85*1000,0)) | AA85: =IF(COUNT(C85:O85)=0,"",IFERROR(I85/H85,0)) | AB85: =IF(COUNT(C85:O85)=0,"",IFERROR(J85/I85,0)) | AC85: =IF(COUNT(C85:O85)=0,"",IFERROR(K85/J85,0)) | AD85: =IF(COUNT(C85:O85)=0,"",IFERROR(C85/K85,0)) | AE85: =IF(COUNT(C85:O85)=0,"",IFERROR(L85/K85,0)) | AF85: =IF(COUNT(C85:O85)=0,"",IFERROR(M85/L85,0)) | AG85: =IF(COUNT(C85:O85)=0,"",IFERROR(M85/H85,0)) | AH85: =IF(COUNT(C85:O85)=0,"",IFERROR(C85/M85,0)) | AI85: =IF(COUNT(C85:O85)=0,"",IFERROR(M85*Config!$C$7+N85*Config!$C$8,0)) | AJ85: =IF(COUNT(C85:O85)=0,"",IFERROR(IF(O85>0,O85,AI85*Config!$C$9),0)) | AK85: =IF(COUNT(C85:O85)=0,"",IFERROR(AJ85*(1-Config!$C$10-Config!$C$11-Config!$C$12),0)) | AL85: =IF(COUNT(C85:O85)=0,"",IFERROR(AK85-C85-Config!$C$13,0)) | AM85: =IF(COUNT(C85:O85)=0,"",IFERROR(AK85/C85,0)) | AN85: =IF(COUNT(C85:O85)=0,"",IFERROR(AI85/C85,0)) | AO85: =IF(COUNT(C85:O85)=0,"",IFERROR(AL85/G85,0)) | AP85: =IF(COUNT(C85:O85)=0,"",IFERROR(AO85/U85,0)) | AQ85: =IF(COUNT(C85:O85)=0,"",IFERROR(AL85/H85,0))
A86: =Config!$C$6+80 | B86: =INT((A86-Config!$C$6)/7)+1 | P86: =IF(COUNT(C86:O86)=0,"",IFERROR(C86/D86*1000,0)) | Q86: =IF(COUNT(C86:O86)=0,"",IFERROR(D86/E86,0)) | R86: =IF(COUNT(C86:O86)=0,"",IFERROR(F86/D86,0)) | S86: =IF(COUNT(C86:O86)=0,"",IFERROR(C86/F86,0)) | T86: =IF(COUNT(C86:O86)=0,"",IFERROR(G86/F86,0)) | U86: =IF(COUNT(C86:O86)=0,"",IFERROR(C86/G86,0)) | V86: =IF(COUNT(C86:O86)=0,"",IFERROR(G86/D86*1000,0)) | W86: =IF(COUNT(C86:O86)=0,"",IFERROR(H86/G86,0)) | X86: =IF(COUNT(C86:O86)=0,"",IFERROR(C86/H86,0)) | Y86: =IF(COUNT(C86:O86)=0,"",IFERROR(X86/P86,0)) | Z86: =IF(COUNT(C86:O86)=0,"",IFERROR(H86/D86*1000,0)) | AA86: =IF(COUNT(C86:O86)=0,"",IFERROR(I86/H86,0)) | AB86: =IF(COUNT(C86:O86)=0,"",IFERROR(J86/I86,0)) | AC86: =IF(COUNT(C86:O86)=0,"",IFERROR(K86/J86,0)) | AD86: =IF(COUNT(C86:O86)=0,"",IFERROR(C86/K86,0)) | AE86: =IF(COUNT(C86:O86)=0,"",IFERROR(L86/K86,0)) | AF86: =IF(COUNT(C86:O86)=0,"",IFERROR(M86/L86,0)) | AG86: =IF(COUNT(C86:O86)=0,"",IFERROR(M86/H86,0)) | AH86: =IF(COUNT(C86:O86)=0,"",IFERROR(C86/M86,0)) | AI86: =IF(COUNT(C86:O86)=0,"",IFERROR(M86*Config!$C$7+N86*Config!$C$8,0)) | AJ86: =IF(COUNT(C86:O86)=0,"",IFERROR(IF(O86>0,O86,AI86*Config!$C$9),0)) | AK86: =IF(COUNT(C86:O86)=0,"",IFERROR(AJ86*(1-Config!$C$10-Config!$C$11-Config!$C$12),0)) | AL86: =IF(COUNT(C86:O86)=0,"",IFERROR(AK86-C86-Config!$C$13,0)) | AM86: =IF(COUNT(C86:O86)=0,"",IFERROR(AK86/C86,0)) | AN86: =IF(COUNT(C86:O86)=0,"",IFERROR(AI86/C86,0)) | AO86: =IF(COUNT(C86:O86)=0,"",IFERROR(AL86/G86,0)) | AP86: =IF(COUNT(C86:O86)=0,"",IFERROR(AO86/U86,0)) | AQ86: =IF(COUNT(C86:O86)=0,"",IFERROR(AL86/H86,0))
A87: =Config!$C$6+81 | B87: =INT((A87-Config!$C$6)/7)+1 | P87: =IF(COUNT(C87:O87)=0,"",IFERROR(C87/D87*1000,0)) | Q87: =IF(COUNT(C87:O87)=0,"",IFERROR(D87/E87,0)) | R87: =IF(COUNT(C87:O87)=0,"",IFERROR(F87/D87,0)) | S87: =IF(COUNT(C87:O87)=0,"",IFERROR(C87/F87,0)) | T87: =IF(COUNT(C87:O87)=0,"",IFERROR(G87/F87,0)) | U87: =IF(COUNT(C87:O87)=0,"",IFERROR(C87/G87,0)) | V87: =IF(COUNT(C87:O87)=0,"",IFERROR(G87/D87*1000,0)) | W87: =IF(COUNT(C87:O87)=0,"",IFERROR(H87/G87,0)) | X87: =IF(COUNT(C87:O87)=0,"",IFERROR(C87/H87,0)) | Y87: =IF(COUNT(C87:O87)=0,"",IFERROR(X87/P87,0)) | Z87: =IF(COUNT(C87:O87)=0,"",IFERROR(H87/D87*1000,0)) | AA87: =IF(COUNT(C87:O87)=0,"",IFERROR(I87/H87,0)) | AB87: =IF(COUNT(C87:O87)=0,"",IFERROR(J87/I87,0)) | AC87: =IF(COUNT(C87:O87)=0,"",IFERROR(K87/J87,0)) | AD87: =IF(COUNT(C87:O87)=0,"",IFERROR(C87/K87,0)) | AE87: =IF(COUNT(C87:O87)=0,"",IFERROR(L87/K87,0)) | AF87: =IF(COUNT(C87:O87)=0,"",IFERROR(M87/L87,0)) | AG87: =IF(COUNT(C87:O87)=0,"",IFERROR(M87/H87,0)) | AH87: =IF(COUNT(C87:O87)=0,"",IFERROR(C87/M87,0)) | AI87: =IF(COUNT(C87:O87)=0,"",IFERROR(M87*Config!$C$7+N87*Config!$C$8,0)) | AJ87: =IF(COUNT(C87:O87)=0,"",IFERROR(IF(O87>0,O87,AI87*Config!$C$9),0)) | AK87: =IF(COUNT(C87:O87)=0,"",IFERROR(AJ87*(1-Config!$C$10-Config!$C$11-Config!$C$12),0)) | AL87: =IF(COUNT(C87:O87)=0,"",IFERROR(AK87-C87-Config!$C$13,0)) | AM87: =IF(COUNT(C87:O87)=0,"",IFERROR(AK87/C87,0)) | AN87: =IF(COUNT(C87:O87)=0,"",IFERROR(AI87/C87,0)) | AO87: =IF(COUNT(C87:O87)=0,"",IFERROR(AL87/G87,0)) | AP87: =IF(COUNT(C87:O87)=0,"",IFERROR(AO87/U87,0)) | AQ87: =IF(COUNT(C87:O87)=0,"",IFERROR(AL87/H87,0))
A88: =Config!$C$6+82 | B88: =INT((A88-Config!$C$6)/7)+1 | P88: =IF(COUNT(C88:O88)=0,"",IFERROR(C88/D88*1000,0)) | Q88: =IF(COUNT(C88:O88)=0,"",IFERROR(D88/E88,0)) | R88: =IF(COUNT(C88:O88)=0,"",IFERROR(F88/D88,0)) | S88: =IF(COUNT(C88:O88)=0,"",IFERROR(C88/F88,0)) | T88: =IF(COUNT(C88:O88)=0,"",IFERROR(G88/F88,0)) | U88: =IF(COUNT(C88:O88)=0,"",IFERROR(C88/G88,0)) | V88: =IF(COUNT(C88:O88)=0,"",IFERROR(G88/D88*1000,0)) | W88: =IF(COUNT(C88:O88)=0,"",IFERROR(H88/G88,0)) | X88: =IF(COUNT(C88:O88)=0,"",IFERROR(C88/H88,0)) | Y88: =IF(COUNT(C88:O88)=0,"",IFERROR(X88/P88,0)) | Z88: =IF(COUNT(C88:O88)=0,"",IFERROR(H88/D88*1000,0)) | AA88: =IF(COUNT(C88:O88)=0,"",IFERROR(I88/H88,0)) | AB88: =IF(COUNT(C88:O88)=0,"",IFERROR(J88/I88,0)) | AC88: =IF(COUNT(C88:O88)=0,"",IFERROR(K88/J88,0)) | AD88: =IF(COUNT(C88:O88)=0,"",IFERROR(C88/K88,0)) | AE88: =IF(COUNT(C88:O88)=0,"",IFERROR(L88/K88,0)) | AF88: =IF(COUNT(C88:O88)=0,"",IFERROR(M88/L88,0)) | AG88: =IF(COUNT(C88:O88)=0,"",IFERROR(M88/H88,0)) | AH88: =IF(COUNT(C88:O88)=0,"",IFERROR(C88/M88,0)) | AI88: =IF(COUNT(C88:O88)=0,"",IFERROR(M88*Config!$C$7+N88*Config!$C$8,0)) | AJ88: =IF(COUNT(C88:O88)=0,"",IFERROR(IF(O88>0,O88,AI88*Config!$C$9),0)) | AK88: =IF(COUNT(C88:O88)=0,"",IFERROR(AJ88*(1-Config!$C$10-Config!$C$11-Config!$C$12),0)) | AL88: =IF(COUNT(C88:O88)=0,"",IFERROR(AK88-C88-Config!$C$13,0)) | AM88: =IF(COUNT(C88:O88)=0,"",IFERROR(AK88/C88,0)) | AN88: =IF(COUNT(C88:O88)=0,"",IFERROR(AI88/C88,0)) | AO88: =IF(COUNT(C88:O88)=0,"",IFERROR(AL88/G88,0)) | AP88: =IF(COUNT(C88:O88)=0,"",IFERROR(AO88/U88,0)) | AQ88: =IF(COUNT(C88:O88)=0,"",IFERROR(AL88/H88,0))
A89: =Config!$C$6+83 | B89: =INT((A89-Config!$C$6)/7)+1 | P89: =IF(COUNT(C89:O89)=0,"",IFERROR(C89/D89*1000,0)) | Q89: =IF(COUNT(C89:O89)=0,"",IFERROR(D89/E89,0)) | R89: =IF(COUNT(C89:O89)=0,"",IFERROR(F89/D89,0)) | S89: =IF(COUNT(C89:O89)=0,"",IFERROR(C89/F89,0)) | T89: =IF(COUNT(C89:O89)=0,"",IFERROR(G89/F89,0)) | U89: =IF(COUNT(C89:O89)=0,"",IFERROR(C89/G89,0)) | V89: =IF(COUNT(C89:O89)=0,"",IFERROR(G89/D89*1000,0)) | W89: =IF(COUNT(C89:O89)=0,"",IFERROR(H89/G89,0)) | X89: =IF(COUNT(C89:O89)=0,"",IFERROR(C89/H89,0)) | Y89: =IF(COUNT(C89:O89)=0,"",IFERROR(X89/P89,0)) | Z89: =IF(COUNT(C89:O89)=0,"",IFERROR(H89/D89*1000,0)) | AA89: =IF(COUNT(C89:O89)=0,"",IFERROR(I89/H89,0)) | AB89: =IF(COUNT(C89:O89)=0,"",IFERROR(J89/I89,0)) | AC89: =IF(COUNT(C89:O89)=0,"",IFERROR(K89/J89,0)) | AD89: =IF(COUNT(C89:O89)=0,"",IFERROR(C89/K89,0)) | AE89: =IF(COUNT(C89:O89)=0,"",IFERROR(L89/K89,0)) | AF89: =IF(COUNT(C89:O89)=0,"",IFERROR(M89/L89,0)) | AG89: =IF(COUNT(C89:O89)=0,"",IFERROR(M89/H89,0)) | AH89: =IF(COUNT(C89:O89)=0,"",IFERROR(C89/M89,0)) | AI89: =IF(COUNT(C89:O89)=0,"",IFERROR(M89*Config!$C$7+N89*Config!$C$8,0)) | AJ89: =IF(COUNT(C89:O89)=0,"",IFERROR(IF(O89>0,O89,AI89*Config!$C$9),0)) | AK89: =IF(COUNT(C89:O89)=0,"",IFERROR(AJ89*(1-Config!$C$10-Config!$C$11-Config!$C$12),0)) | AL89: =IF(COUNT(C89:O89)=0,"",IFERROR(AK89-C89-Config!$C$13,0)) | AM89: =IF(COUNT(C89:O89)=0,"",IFERROR(AK89/C89,0)) | AN89: =IF(COUNT(C89:O89)=0,"",IFERROR(AI89/C89,0)) | AO89: =IF(COUNT(C89:O89)=0,"",IFERROR(AL89/G89,0)) | AP89: =IF(COUNT(C89:O89)=0,"",IFERROR(AO89/U89,0)) | AQ89: =IF(COUNT(C89:O89)=0,"",IFERROR(AL89/H89,0))
A90: =Config!$C$6+84 | B90: =INT((A90-Config!$C$6)/7)+1 | P90: =IF(COUNT(C90:O90)=0,"",IFERROR(C90/D90*1000,0)) | Q90: =IF(COUNT(C90:O90)=0,"",IFERROR(D90/E90,0)) | R90: =IF(COUNT(C90:O90)=0,"",IFERROR(F90/D90,0)) | S90: =IF(COUNT(C90:O90)=0,"",IFERROR(C90/F90,0)) | T90: =IF(COUNT(C90:O90)=0,"",IFERROR(G90/F90,0)) | U90: =IF(COUNT(C90:O90)=0,"",IFERROR(C90/G90,0)) | V90: =IF(COUNT(C90:O90)=0,"",IFERROR(G90/D90*1000,0)) | W90: =IF(COUNT(C90:O90)=0,"",IFERROR(H90/G90,0)) | X90: =IF(COUNT(C90:O90)=0,"",IFERROR(C90/H90,0)) | Y90: =IF(COUNT(C90:O90)=0,"",IFERROR(X90/P90,0)) | Z90: =IF(COUNT(C90:O90)=0,"",IFERROR(H90/D90*1000,0)) | AA90: =IF(COUNT(C90:O90)=0,"",IFERROR(I90/H90,0)) | AB90: =IF(COUNT(C90:O90)=0,"",IFERROR(J90/I90,0)) | AC90: =IF(COUNT(C90:O90)=0,"",IFERROR(K90/J90,0)) | AD90: =IF(COUNT(C90:O90)=0,"",IFERROR(C90/K90,0)) | AE90: =IF(COUNT(C90:O90)=0,"",IFERROR(L90/K90,0)) | AF90: =IF(COUNT(C90:O90)=0,"",IFERROR(M90/L90,0)) | AG90: =IF(COUNT(C90:O90)=0,"",IFERROR(M90/H90,0)) | AH90: =IF(COUNT(C90:O90)=0,"",IFERROR(C90/M90,0)) | AI90: =IF(COUNT(C90:O90)=0,"",IFERROR(M90*Config!$C$7+N90*Config!$C$8,0)) | AJ90: =IF(COUNT(C90:O90)=0,"",IFERROR(IF(O90>0,O90,AI90*Config!$C$9),0)) | AK90: =IF(COUNT(C90:O90)=0,"",IFERROR(AJ90*(1-Config!$C$10-Config!$C$11-Config!$C$12),0)) | AL90: =IF(COUNT(C90:O90)=0,"",IFERROR(AK90-C90-Config!$C$13,0)) | AM90: =IF(COUNT(C90:O90)=0,"",IFERROR(AK90/C90,0)) | AN90: =IF(COUNT(C90:O90)=0,"",IFERROR(AI90/C90,0)) | AO90: =IF(COUNT(C90:O90)=0,"",IFERROR(AL90/G90,0)) | AP90: =IF(COUNT(C90:O90)=0,"",IFERROR(AO90/U90,0)) | AQ90: =IF(COUNT(C90:O90)=0,"",IFERROR(AL90/H90,0))
A91: =Config!$C$6+85 | B91: =INT((A91-Config!$C$6)/7)+1 | P91: =IF(COUNT(C91:O91)=0,"",IFERROR(C91/D91*1000,0)) | Q91: =IF(COUNT(C91:O91)=0,"",IFERROR(D91/E91,0)) | R91: =IF(COUNT(C91:O91)=0,"",IFERROR(F91/D91,0)) | S91: =IF(COUNT(C91:O91)=0,"",IFERROR(C91/F91,0)) | T91: =IF(COUNT(C91:O91)=0,"",IFERROR(G91/F91,0)) | U91: =IF(COUNT(C91:O91)=0,"",IFERROR(C91/G91,0)) | V91: =IF(COUNT(C91:O91)=0,"",IFERROR(G91/D91*1000,0)) | W91: =IF(COUNT(C91:O91)=0,"",IFERROR(H91/G91,0)) | X91: =IF(COUNT(C91:O91)=0,"",IFERROR(C91/H91,0)) | Y91: =IF(COUNT(C91:O91)=0,"",IFERROR(X91/P91,0)) | Z91: =IF(COUNT(C91:O91)=0,"",IFERROR(H91/D91*1000,0)) | AA91: =IF(COUNT(C91:O91)=0,"",IFERROR(I91/H91,0)) | AB91: =IF(COUNT(C91:O91)=0,"",IFERROR(J91/I91,0)) | AC91: =IF(COUNT(C91:O91)=0,"",IFERROR(K91/J91,0)) | AD91: =IF(COUNT(C91:O91)=0,"",IFERROR(C91/K91,0)) | AE91: =IF(COUNT(C91:O91)=0,"",IFERROR(L91/K91,0)) | AF91: =IF(COUNT(C91:O91)=0,"",IFERROR(M91/L91,0)) | AG91: =IF(COUNT(C91:O91)=0,"",IFERROR(M91/H91,0)) | AH91: =IF(COUNT(C91:O91)=0,"",IFERROR(C91/M91,0)) | AI91: =IF(COUNT(C91:O91)=0,"",IFERROR(M91*Config!$C$7+N91*Config!$C$8,0)) | AJ91: =IF(COUNT(C91:O91)=0,"",IFERROR(IF(O91>0,O91,AI91*Config!$C$9),0)) | AK91: =IF(COUNT(C91:O91)=0,"",IFERROR(AJ91*(1-Config!$C$10-Config!$C$11-Config!$C$12),0)) | AL91: =IF(COUNT(C91:O91)=0,"",IFERROR(AK91-C91-Config!$C$13,0)) | AM91: =IF(COUNT(C91:O91)=0,"",IFERROR(AK91/C91,0)) | AN91: =IF(COUNT(C91:O91)=0,"",IFERROR(AI91/C91,0)) | AO91: =IF(COUNT(C91:O91)=0,"",IFERROR(AL91/G91,0)) | AP91: =IF(COUNT(C91:O91)=0,"",IFERROR(AO91/U91,0)) | AQ91: =IF(COUNT(C91:O91)=0,"",IFERROR(AL91/H91,0))
A92: =Config!$C$6+86 | B92: =INT((A92-Config!$C$6)/7)+1 | P92: =IF(COUNT(C92:O92)=0,"",IFERROR(C92/D92*1000,0)) | Q92: =IF(COUNT(C92:O92)=0,"",IFERROR(D92/E92,0)) | R92: =IF(COUNT(C92:O92)=0,"",IFERROR(F92/D92,0)) | S92: =IF(COUNT(C92:O92)=0,"",IFERROR(C92/F92,0)) | T92: =IF(COUNT(C92:O92)=0,"",IFERROR(G92/F92,0)) | U92: =IF(COUNT(C92:O92)=0,"",IFERROR(C92/G92,0)) | V92: =IF(COUNT(C92:O92)=0,"",IFERROR(G92/D92*1000,0)) | W92: =IF(COUNT(C92:O92)=0,"",IFERROR(H92/G92,0)) | X92: =IF(COUNT(C92:O92)=0,"",IFERROR(C92/H92,0)) | Y92: =IF(COUNT(C92:O92)=0,"",IFERROR(X92/P92,0)) | Z92: =IF(COUNT(C92:O92)=0,"",IFERROR(H92/D92*1000,0)) | AA92: =IF(COUNT(C92:O92)=0,"",IFERROR(I92/H92,0)) | AB92: =IF(COUNT(C92:O92)=0,"",IFERROR(J92/I92,0)) | AC92: =IF(COUNT(C92:O92)=0,"",IFERROR(K92/J92,0)) | AD92: =IF(COUNT(C92:O92)=0,"",IFERROR(C92/K92,0)) | AE92: =IF(COUNT(C92:O92)=0,"",IFERROR(L92/K92,0)) | AF92: =IF(COUNT(C92:O92)=0,"",IFERROR(M92/L92,0)) | AG92: =IF(COUNT(C92:O92)=0,"",IFERROR(M92/H92,0)) | AH92: =IF(COUNT(C92:O92)=0,"",IFERROR(C92/M92,0)) | AI92: =IF(COUNT(C92:O92)=0,"",IFERROR(M92*Config!$C$7+N92*Config!$C$8,0)) | AJ92: =IF(COUNT(C92:O92)=0,"",IFERROR(IF(O92>0,O92,AI92*Config!$C$9),0)) | AK92: =IF(COUNT(C92:O92)=0,"",IFERROR(AJ92*(1-Config!$C$10-Config!$C$11-Config!$C$12),0)) | AL92: =IF(COUNT(C92:O92)=0,"",IFERROR(AK92-C92-Config!$C$13,0)) | AM92: =IF(COUNT(C92:O92)=0,"",IFERROR(AK92/C92,0)) | AN92: =IF(COUNT(C92:O92)=0,"",IFERROR(AI92/C92,0)) | AO92: =IF(COUNT(C92:O92)=0,"",IFERROR(AL92/G92,0)) | AP92: =IF(COUNT(C92:O92)=0,"",IFERROR(AO92/U92,0)) | AQ92: =IF(COUNT(C92:O92)=0,"",IFERROR(AL92/H92,0))
A93: =Config!$C$6+87 | B93: =INT((A93-Config!$C$6)/7)+1 | P93: =IF(COUNT(C93:O93)=0,"",IFERROR(C93/D93*1000,0)) | Q93: =IF(COUNT(C93:O93)=0,"",IFERROR(D93/E93,0)) | R93: =IF(COUNT(C93:O93)=0,"",IFERROR(F93/D93,0)) | S93: =IF(COUNT(C93:O93)=0,"",IFERROR(C93/F93,0)) | T93: =IF(COUNT(C93:O93)=0,"",IFERROR(G93/F93,0)) | U93: =IF(COUNT(C93:O93)=0,"",IFERROR(C93/G93,0)) | V93: =IF(COUNT(C93:O93)=0,"",IFERROR(G93/D93*1000,0)) | W93: =IF(COUNT(C93:O93)=0,"",IFERROR(H93/G93,0)) | X93: =IF(COUNT(C93:O93)=0,"",IFERROR(C93/H93,0)) | Y93: =IF(COUNT(C93:O93)=0,"",IFERROR(X93/P93,0)) | Z93: =IF(COUNT(C93:O93)=0,"",IFERROR(H93/D93*1000,0)) | AA93: =IF(COUNT(C93:O93)=0,"",IFERROR(I93/H93,0)) | AB93: =IF(COUNT(C93:O93)=0,"",IFERROR(J93/I93,0)) | AC93: =IF(COUNT(C93:O93)=0,"",IFERROR(K93/J93,0)) | AD93: =IF(COUNT(C93:O93)=0,"",IFERROR(C93/K93,0)) | AE93: =IF(COUNT(C93:O93)=0,"",IFERROR(L93/K93,0)) | AF93: =IF(COUNT(C93:O93)=0,"",IFERROR(M93/L93,0)) | AG93: =IF(COUNT(C93:O93)=0,"",IFERROR(M93/H93,0)) | AH93: =IF(COUNT(C93:O93)=0,"",IFERROR(C93/M93,0)) | AI93: =IF(COUNT(C93:O93)=0,"",IFERROR(M93*Config!$C$7+N93*Config!$C$8,0)) | AJ93: =IF(COUNT(C93:O93)=0,"",IFERROR(IF(O93>0,O93,AI93*Config!$C$9),0)) | AK93: =IF(COUNT(C93:O93)=0,"",IFERROR(AJ93*(1-Config!$C$10-Config!$C$11-Config!$C$12),0)) | AL93: =IF(COUNT(C93:O93)=0,"",IFERROR(AK93-C93-Config!$C$13,0)) | AM93: =IF(COUNT(C93:O93)=0,"",IFERROR(AK93/C93,0)) | AN93: =IF(COUNT(C93:O93)=0,"",IFERROR(AI93/C93,0)) | AO93: =IF(COUNT(C93:O93)=0,"",IFERROR(AL93/G93,0)) | AP93: =IF(COUNT(C93:O93)=0,"",IFERROR(AO93/U93,0)) | AQ93: =IF(COUNT(C93:O93)=0,"",IFERROR(AL93/H93,0))
A94: =Config!$C$6+88 | B94: =INT((A94-Config!$C$6)/7)+1 | P94: =IF(COUNT(C94:O94)=0,"",IFERROR(C94/D94*1000,0)) | Q94: =IF(COUNT(C94:O94)=0,"",IFERROR(D94/E94,0)) | R94: =IF(COUNT(C94:O94)=0,"",IFERROR(F94/D94,0)) | S94: =IF(COUNT(C94:O94)=0,"",IFERROR(C94/F94,0)) | T94: =IF(COUNT(C94:O94)=0,"",IFERROR(G94/F94,0)) | U94: =IF(COUNT(C94:O94)=0,"",IFERROR(C94/G94,0)) | V94: =IF(COUNT(C94:O94)=0,"",IFERROR(G94/D94*1000,0)) | W94: =IF(COUNT(C94:O94)=0,"",IFERROR(H94/G94,0)) | X94: =IF(COUNT(C94:O94)=0,"",IFERROR(C94/H94,0)) | Y94: =IF(COUNT(C94:O94)=0,"",IFERROR(X94/P94,0)) | Z94: =IF(COUNT(C94:O94)=0,"",IFERROR(H94/D94*1000,0)) | AA94: =IF(COUNT(C94:O94)=0,"",IFERROR(I94/H94,0)) | AB94: =IF(COUNT(C94:O94)=0,"",IFERROR(J94/I94,0)) | AC94: =IF(COUNT(C94:O94)=0,"",IFERROR(K94/J94,0)) | AD94: =IF(COUNT(C94:O94)=0,"",IFERROR(C94/K94,0)) | AE94: =IF(COUNT(C94:O94)=0,"",IFERROR(L94/K94,0)) | AF94: =IF(COUNT(C94:O94)=0,"",IFERROR(M94/L94,0)) | AG94: =IF(COUNT(C94:O94)=0,"",IFERROR(M94/H94,0)) | AH94: =IF(COUNT(C94:O94)=0,"",IFERROR(C94/M94,0)) | AI94: =IF(COUNT(C94:O94)=0,"",IFERROR(M94*Config!$C$7+N94*Config!$C$8,0)) | AJ94: =IF(COUNT(C94:O94)=0,"",IFERROR(IF(O94>0,O94,AI94*Config!$C$9),0)) | AK94: =IF(COUNT(C94:O94)=0,"",IFERROR(AJ94*(1-Config!$C$10-Config!$C$11-Config!$C$12),0)) | AL94: =IF(COUNT(C94:O94)=0,"",IFERROR(AK94-C94-Config!$C$13,0)) | AM94: =IF(COUNT(C94:O94)=0,"",IFERROR(AK94/C94,0)) | AN94: =IF(COUNT(C94:O94)=0,"",IFERROR(AI94/C94,0)) | AO94: =IF(COUNT(C94:O94)=0,"",IFERROR(AL94/G94,0)) | AP94: =IF(COUNT(C94:O94)=0,"",IFERROR(AO94/U94,0)) | AQ94: =IF(COUNT(C94:O94)=0,"",IFERROR(AL94/H94,0))
A95: =Config!$C$6+89 | B95: =INT((A95-Config!$C$6)/7)+1 | P95: =IF(COUNT(C95:O95)=0,"",IFERROR(C95/D95*1000,0)) | Q95: =IF(COUNT(C95:O95)=0,"",IFERROR(D95/E95,0)) | R95: =IF(COUNT(C95:O95)=0,"",IFERROR(F95/D95,0)) | S95: =IF(COUNT(C95:O95)=0,"",IFERROR(C95/F95,0)) | T95: =IF(COUNT(C95:O95)=0,"",IFERROR(G95/F95,0)) | U95: =IF(COUNT(C95:O95)=0,"",IFERROR(C95/G95,0)) | V95: =IF(COUNT(C95:O95)=0,"",IFERROR(G95/D95*1000,0)) | W95: =IF(COUNT(C95:O95)=0,"",IFERROR(H95/G95,0)) | X95: =IF(COUNT(C95:O95)=0,"",IFERROR(C95/H95,0)) | Y95: =IF(COUNT(C95:O95)=0,"",IFERROR(X95/P95,0)) | Z95: =IF(COUNT(C95:O95)=0,"",IFERROR(H95/D95*1000,0)) | AA95: =IF(COUNT(C95:O95)=0,"",IFERROR(I95/H95,0)) | AB95: =IF(COUNT(C95:O95)=0,"",IFERROR(J95/I95,0)) | AC95: =IF(COUNT(C95:O95)=0,"",IFERROR(K95/J95,0)) | AD95: =IF(COUNT(C95:O95)=0,"",IFERROR(C95/K95,0)) | AE95: =IF(COUNT(C95:O95)=0,"",IFERROR(L95/K95,0)) | AF95: =IF(COUNT(C95:O95)=0,"",IFERROR(M95/L95,0)) | AG95: =IF(COUNT(C95:O95)=0,"",IFERROR(M95/H95,0)) | AH95: =IF(COUNT(C95:O95)=0,"",IFERROR(C95/M95,0)) | AI95: =IF(COUNT(C95:O95)=0,"",IFERROR(M95*Config!$C$7+N95*Config!$C$8,0)) | AJ95: =IF(COUNT(C95:O95)=0,"",IFERROR(IF(O95>0,O95,AI95*Config!$C$9),0)) | AK95: =IF(COUNT(C95:O95)=0,"",IFERROR(AJ95*(1-Config!$C$10-Config!$C$11-Config!$C$12),0)) | AL95: =IF(COUNT(C95:O95)=0,"",IFERROR(AK95-C95-Config!$C$13,0)) | AM95: =IF(COUNT(C95:O95)=0,"",IFERROR(AK95/C95,0)) | AN95: =IF(COUNT(C95:O95)=0,"",IFERROR(AI95/C95,0)) | AO95: =IF(COUNT(C95:O95)=0,"",IFERROR(AL95/G95,0)) | AP95: =IF(COUNT(C95:O95)=0,"",IFERROR(AO95/U95,0)) | AQ95: =IF(COUNT(C95:O95)=0,"",IFERROR(AL95/H95,0))
A96: =Config!$C$6+90 | B96: =INT((A96-Config!$C$6)/7)+1 | P96: =IF(COUNT(C96:O96)=0,"",IFERROR(C96/D96*1000,0)) | Q96: =IF(COUNT(C96:O96)=0,"",IFERROR(D96/E96,0)) | R96: =IF(COUNT(C96:O96)=0,"",IFERROR(F96/D96,0)) | S96: =IF(COUNT(C96:O96)=0,"",IFERROR(C96/F96,0)) | T96: =IF(COUNT(C96:O96)=0,"",IFERROR(G96/F96,0)) | U96: =IF(COUNT(C96:O96)=0,"",IFERROR(C96/G96,0)) | V96: =IF(COUNT(C96:O96)=0,"",IFERROR(G96/D96*1000,0)) | W96: =IF(COUNT(C96:O96)=0,"",IFERROR(H96/G96,0)) | X96: =IF(COUNT(C96:O96)=0,"",IFERROR(C96/H96,0)) | Y96: =IF(COUNT(C96:O96)=0,"",IFERROR(X96/P96,0)) | Z96: =IF(COUNT(C96:O96)=0,"",IFERROR(H96/D96*1000,0)) | AA96: =IF(COUNT(C96:O96)=0,"",IFERROR(I96/H96,0)) | AB96: =IF(COUNT(C96:O96)=0,"",IFERROR(J96/I96,0)) | AC96: =IF(COUNT(C96:O96)=0,"",IFERROR(K96/J96,0)) | AD96: =IF(COUNT(C96:O96)=0,"",IFERROR(C96/K96,0)) | AE96: =IF(COUNT(C96:O96)=0,"",IFERROR(L96/K96,0)) | AF96: =IF(COUNT(C96:O96)=0,"",IFERROR(M96/L96,0)) | AG96: =IF(COUNT(C96:O96)=0,"",IFERROR(M96/H96,0)) | AH96: =IF(COUNT(C96:O96)=0,"",IFERROR(C96/M96,0)) | AI96: =IF(COUNT(C96:O96)=0,"",IFERROR(M96*Config!$C$7+N96*Config!$C$8,0)) | AJ96: =IF(COUNT(C96:O96)=0,"",IFERROR(IF(O96>0,O96,AI96*Config!$C$9),0)) | AK96: =IF(COUNT(C96:O96)=0,"",IFERROR(AJ96*(1-Config!$C$10-Config!$C$11-Config!$C$12),0)) | AL96: =IF(COUNT(C96:O96)=0,"",IFERROR(AK96-C96-Config!$C$13,0)) | AM96: =IF(COUNT(C96:O96)=0,"",IFERROR(AK96/C96,0)) | AN96: =IF(COUNT(C96:O96)=0,"",IFERROR(AI96/C96,0)) | AO96: =IF(COUNT(C96:O96)=0,"",IFERROR(AL96/G96,0)) | AP96: =IF(COUNT(C96:O96)=0,"",IFERROR(AO96/U96,0)) | AQ96: =IF(COUNT(C96:O96)=0,"",IFERROR(AL96/H96,0))
A97: =Config!$C$6+91 | B97: =INT((A97-Config!$C$6)/7)+1 | P97: =IF(COUNT(C97:O97)=0,"",IFERROR(C97/D97*1000,0)) | Q97: =IF(COUNT(C97:O97)=0,"",IFERROR(D97/E97,0)) | R97: =IF(COUNT(C97:O97)=0,"",IFERROR(F97/D97,0)) | S97: =IF(COUNT(C97:O97)=0,"",IFERROR(C97/F97,0)) | T97: =IF(COUNT(C97:O97)=0,"",IFERROR(G97/F97,0)) | U97: =IF(COUNT(C97:O97)=0,"",IFERROR(C97/G97,0)) | V97: =IF(COUNT(C97:O97)=0,"",IFERROR(G97/D97*1000,0)) | W97: =IF(COUNT(C97:O97)=0,"",IFERROR(H97/G97,0)) | X97: =IF(COUNT(C97:O97)=0,"",IFERROR(C97/H97,0)) | Y97: =IF(COUNT(C97:O97)=0,"",IFERROR(X97/P97,0)) | Z97: =IF(COUNT(C97:O97)=0,"",IFERROR(H97/D97*1000,0)) | AA97: =IF(COUNT(C97:O97)=0,"",IFERROR(I97/H97,0)) | AB97: =IF(COUNT(C97:O97)=0,"",IFERROR(J97/I97,0)) | AC97: =IF(COUNT(C97:O97)=0,"",IFERROR(K97/J97,0)) | AD97: =IF(COUNT(C97:O97)=0,"",IFERROR(C97/K97,0)) | AE97: =IF(COUNT(C97:O97)=0,"",IFERROR(L97/K97,0)) | AF97: =IF(COUNT(C97:O97)=0,"",IFERROR(M97/L97,0)) | AG97: =IF(COUNT(C97:O97)=0,"",IFERROR(M97/H97,0)) | AH97: =IF(COUNT(C97:O97)=0,"",IFERROR(C97/M97,0)) | AI97: =IF(COUNT(C97:O97)=0,"",IFERROR(M97*Config!$C$7+N97*Config!$C$8,0)) | AJ97: =IF(COUNT(C97:O97)=0,"",IFERROR(IF(O97>0,O97,AI97*Config!$C$9),0)) | AK97: =IF(COUNT(C97:O97)=0,"",IFERROR(AJ97*(1-Config!$C$10-Config!$C$11-Config!$C$12),0)) | AL97: =IF(COUNT(C97:O97)=0,"",IFERROR(AK97-C97-Config!$C$13,0)) | AM97: =IF(COUNT(C97:O97)=0,"",IFERROR(AK97/C97,0)) | AN97: =IF(COUNT(C97:O97)=0,"",IFERROR(AI97/C97,0)) | AO97: =IF(COUNT(C97:O97)=0,"",IFERROR(AL97/G97,0)) | AP97: =IF(COUNT(C97:O97)=0,"",IFERROR(AO97/U97,0)) | AQ97: =IF(COUNT(C97:O97)=0,"",IFERROR(AL97/H97,0))
A98: =Config!$C$6+92 | B98: =INT((A98-Config!$C$6)/7)+1 | P98: =IF(COUNT(C98:O98)=0,"",IFERROR(C98/D98*1000,0)) | Q98: =IF(COUNT(C98:O98)=0,"",IFERROR(D98/E98,0)) | R98: =IF(COUNT(C98:O98)=0,"",IFERROR(F98/D98,0)) | S98: =IF(COUNT(C98:O98)=0,"",IFERROR(C98/F98,0)) | T98: =IF(COUNT(C98:O98)=0,"",IFERROR(G98/F98,0)) | U98: =IF(COUNT(C98:O98)=0,"",IFERROR(C98/G98,0)) | V98: =IF(COUNT(C98:O98)=0,"",IFERROR(G98/D98*1000,0)) | W98: =IF(COUNT(C98:O98)=0,"",IFERROR(H98/G98,0)) | X98: =IF(COUNT(C98:O98)=0,"",IFERROR(C98/H98,0)) | Y98: =IF(COUNT(C98:O98)=0,"",IFERROR(X98/P98,0)) | Z98: =IF(COUNT(C98:O98)=0,"",IFERROR(H98/D98*1000,0)) | AA98: =IF(COUNT(C98:O98)=0,"",IFERROR(I98/H98,0)) | AB98: =IF(COUNT(C98:O98)=0,"",IFERROR(J98/I98,0)) | AC98: =IF(COUNT(C98:O98)=0,"",IFERROR(K98/J98,0)) | AD98: =IF(COUNT(C98:O98)=0,"",IFERROR(C98/K98,0)) | AE98: =IF(COUNT(C98:O98)=0,"",IFERROR(L98/K98,0)) | AF98: =IF(COUNT(C98:O98)=0,"",IFERROR(M98/L98,0)) | AG98: =IF(COUNT(C98:O98)=0,"",IFERROR(M98/H98,0)) | AH98: =IF(COUNT(C98:O98)=0,"",IFERROR(C98/M98,0)) | AI98: =IF(COUNT(C98:O98)=0,"",IFERROR(M98*Config!$C$7+N98*Config!$C$8,0)) | AJ98: =IF(COUNT(C98:O98)=0,"",IFERROR(IF(O98>0,O98,AI98*Config!$C$9),0)) | AK98: =IF(COUNT(C98:O98)=0,"",IFERROR(AJ98*(1-Config!$C$10-Config!$C$11-Config!$C$12),0)) | AL98: =IF(COUNT(C98:O98)=0,"",IFERROR(AK98-C98-Config!$C$13,0)) | AM98: =IF(COUNT(C98:O98)=0,"",IFERROR(AK98/C98,0)) | AN98: =IF(COUNT(C98:O98)=0,"",IFERROR(AI98/C98,0)) | AO98: =IF(COUNT(C98:O98)=0,"",IFERROR(AL98/G98,0)) | AP98: =IF(COUNT(C98:O98)=0,"",IFERROR(AO98/U98,0)) | AQ98: =IF(COUNT(C98:O98)=0,"",IFERROR(AL98/H98,0))
A99: =Config!$C$6+93 | B99: =INT((A99-Config!$C$6)/7)+1 | P99: =IF(COUNT(C99:O99)=0,"",IFERROR(C99/D99*1000,0)) | Q99: =IF(COUNT(C99:O99)=0,"",IFERROR(D99/E99,0)) | R99: =IF(COUNT(C99:O99)=0,"",IFERROR(F99/D99,0)) | S99: =IF(COUNT(C99:O99)=0,"",IFERROR(C99/F99,0)) | T99: =IF(COUNT(C99:O99)=0,"",IFERROR(G99/F99,0)) | U99: =IF(COUNT(C99:O99)=0,"",IFERROR(C99/G99,0)) | V99: =IF(COUNT(C99:O99)=0,"",IFERROR(G99/D99*1000,0)) | W99: =IF(COUNT(C99:O99)=0,"",IFERROR(H99/G99,0)) | X99: =IF(COUNT(C99:O99)=0,"",IFERROR(C99/H99,0)) | Y99: =IF(COUNT(C99:O99)=0,"",IFERROR(X99/P99,0)) | Z99: =IF(COUNT(C99:O99)=0,"",IFERROR(H99/D99*1000,0)) | AA99: =IF(COUNT(C99:O99)=0,"",IFERROR(I99/H99,0)) | AB99: =IF(COUNT(C99:O99)=0,"",IFERROR(J99/I99,0)) | AC99: =IF(COUNT(C99:O99)=0,"",IFERROR(K99/J99,0)) | AD99: =IF(COUNT(C99:O99)=0,"",IFERROR(C99/K99,0)) | AE99: =IF(COUNT(C99:O99)=0,"",IFERROR(L99/K99,0)) | AF99: =IF(COUNT(C99:O99)=0,"",IFERROR(M99/L99,0)) | AG99: =IF(COUNT(C99:O99)=0,"",IFERROR(M99/H99,0)) | AH99: =IF(COUNT(C99:O99)=0,"",IFERROR(C99/M99,0)) | AI99: =IF(COUNT(C99:O99)=0,"",IFERROR(M99*Config!$C$7+N99*Config!$C$8,0)) | AJ99: =IF(COUNT(C99:O99)=0,"",IFERROR(IF(O99>0,O99,AI99*Config!$C$9),0)) | AK99: =IF(COUNT(C99:O99)=0,"",IFERROR(AJ99*(1-Config!$C$10-Config!$C$11-Config!$C$12),0)) | AL99: =IF(COUNT(C99:O99)=0,"",IFERROR(AK99-C99-Config!$C$13,0)) | AM99: =IF(COUNT(C99:O99)=0,"",IFERROR(AK99/C99,0)) | AN99: =IF(COUNT(C99:O99)=0,"",IFERROR(AI99/C99,0)) | AO99: =IF(COUNT(C99:O99)=0,"",IFERROR(AL99/G99,0)) | AP99: =IF(COUNT(C99:O99)=0,"",IFERROR(AO99/U99,0)) | AQ99: =IF(COUNT(C99:O99)=0,"",IFERROR(AL99/H99,0))
A100: =Config!$C$6+94 | B100: =INT((A100-Config!$C$6)/7)+1 | P100: =IF(COUNT(C100:O100)=0,"",IFERROR(C100/D100*1000,0)) | Q100: =IF(COUNT(C100:O100)=0,"",IFERROR(D100/E100,0)) | R100: =IF(COUNT(C100:O100)=0,"",IFERROR(F100/D100,0)) | S100: =IF(COUNT(C100:O100)=0,"",IFERROR(C100/F100,0)) | T100: =IF(COUNT(C100:O100)=0,"",IFERROR(G100/F100,0)) | U100: =IF(COUNT(C100:O100)=0,"",IFERROR(C100/G100,0)) | V100: =IF(COUNT(C100:O100)=0,"",IFERROR(G100/D100*1000,0)) | W100: =IF(COUNT(C100:O100)=0,"",IFERROR(H100/G100,0)) | X100: =IF(COUNT(C100:O100)=0,"",IFERROR(C100/H100,0)) | Y100: =IF(COUNT(C100:O100)=0,"",IFERROR(X100/P100,0)) | Z100: =IF(COUNT(C100:O100)=0,"",IFERROR(H100/D100*1000,0)) | AA100: =IF(COUNT(C100:O100)=0,"",IFERROR(I100/H100,0)) | AB100: =IF(COUNT(C100:O100)=0,"",IFERROR(J100/I100,0)) | AC100: =IF(COUNT(C100:O100)=0,"",IFERROR(K100/J100,0)) | AD100: =IF(COUNT(C100:O100)=0,"",IFERROR(C100/K100,0)) | AE100: =IF(COUNT(C100:O100)=0,"",IFERROR(L100/K100,0)) | AF100: =IF(COUNT(C100:O100)=0,"",IFERROR(M100/L100,0)) | AG100: =IF(COUNT(C100:O100)=0,"",IFERROR(M100/H100,0)) | AH100: =IF(COUNT(C100:O100)=0,"",IFERROR(C100/M100,0)) | AI100: =IF(COUNT(C100:O100)=0,"",IFERROR(M100*Config!$C$7+N100*Config!$C$8,0)) | AJ100: =IF(COUNT(C100:O100)=0,"",IFERROR(IF(O100>0,O100,AI100*Config!$C$9),0)) | AK100: =IF(COUNT(C100:O100)=0,"",IFERROR(AJ100*(1-Config!$C$10-Config!$C$11-Config!$C$12),0)) | AL100: =IF(COUNT(C100:O100)=0,"",IFERROR(AK100-C100-Config!$C$13,0)) | AM100: =IF(COUNT(C100:O100)=0,"",IFERROR(AK100/C100,0)) | AN100: =IF(COUNT(C100:O100)=0,"",IFERROR(AI100/C100,0)) | AO100: =IF(COUNT(C100:O100)=0,"",IFERROR(AL100/G100,0)) | AP100: =IF(COUNT(C100:O100)=0,"",IFERROR(AO100/U100,0)) | AQ100: =IF(COUNT(C100:O100)=0,"",IFERROR(AL100/H100,0))
A101: =Config!$C$6+95 | B101: =INT((A101-Config!$C$6)/7)+1 | P101: =IF(COUNT(C101:O101)=0,"",IFERROR(C101/D101*1000,0)) | Q101: =IF(COUNT(C101:O101)=0,"",IFERROR(D101/E101,0)) | R101: =IF(COUNT(C101:O101)=0,"",IFERROR(F101/D101,0)) | S101: =IF(COUNT(C101:O101)=0,"",IFERROR(C101/F101,0)) | T101: =IF(COUNT(C101:O101)=0,"",IFERROR(G101/F101,0)) | U101: =IF(COUNT(C101:O101)=0,"",IFERROR(C101/G101,0)) | V101: =IF(COUNT(C101:O101)=0,"",IFERROR(G101/D101*1000,0)) | W101: =IF(COUNT(C101:O101)=0,"",IFERROR(H101/G101,0)) | X101: =IF(COUNT(C101:O101)=0,"",IFERROR(C101/H101,0)) | Y101: =IF(COUNT(C101:O101)=0,"",IFERROR(X101/P101,0)) | Z101: =IF(COUNT(C101:O101)=0,"",IFERROR(H101/D101*1000,0)) | AA101: =IF(COUNT(C101:O101)=0,"",IFERROR(I101/H101,0)) | AB101: =IF(COUNT(C101:O101)=0,"",IFERROR(J101/I101,0)) | AC101: =IF(COUNT(C101:O101)=0,"",IFERROR(K101/J101,0)) | AD101: =IF(COUNT(C101:O101)=0,"",IFERROR(C101/K101,0)) | AE101: =IF(COUNT(C101:O101)=0,"",IFERROR(L101/K101,0)) | AF101: =IF(COUNT(C101:O101)=0,"",IFERROR(M101/L101,0)) | AG101: =IF(COUNT(C101:O101)=0,"",IFERROR(M101/H101,0)) | AH101: =IF(COUNT(C101:O101)=0,"",IFERROR(C101/M101,0)) | AI101: =IF(COUNT(C101:O101)=0,"",IFERROR(M101*Config!$C$7+N101*Config!$C$8,0)) | AJ101: =IF(COUNT(C101:O101)=0,"",IFERROR(IF(O101>0,O101,AI101*Config!$C$9),0)) | AK101: =IF(COUNT(C101:O101)=0,"",IFERROR(AJ101*(1-Config!$C$10-Config!$C$11-Config!$C$12),0)) | AL101: =IF(COUNT(C101:O101)=0,"",IFERROR(AK101-C101-Config!$C$13,0)) | AM101: =IF(COUNT(C101:O101)=0,"",IFERROR(AK101/C101,0)) | AN101: =IF(COUNT(C101:O101)=0,"",IFERROR(AI101/C101,0)) | AO101: =IF(COUNT(C101:O101)=0,"",IFERROR(AL101/G101,0)) | AP101: =IF(COUNT(C101:O101)=0,"",IFERROR(AO101/U101,0)) | AQ101: =IF(COUNT(C101:O101)=0,"",IFERROR(AL101/H101,0))
...

Sheet Semanal
A1: © Jesús Tassarolo · TooAudience · youtube.com/@JesusTassaroloSinFiltro · uso personal; no redistribuir modificado
A2: Semanal: el comparativo semana a semana, calculado solo desde Diario
A3: Promedio, mediana, mejor y peor de tus semanas con datos. Abajo, el bloque «contra tu promedio»: cada semana contra la mediana de tus 4 semanas anteriores, con la tolerancia de Config. Ese es el umbral: tu promedio, no un número de mercado.
B4: Lunes de la semana | C4: =Config!$C$6+0 | D4: =Config!$C$6+7 | E4: =Config!$C$6+14 | F4: =Config!$C$6+21 | G4: =Config!$C$6+28 | H4: =Config!$C$6+35 | I4: =Config!$C$6+42 | J4: =Config!$C$6+49 | K4: =Config!$C$6+56 | L4: =Config!$C$6+63 | M4: =Config!$C$6+70 | N4: =Config!$C$6+77 | O4: =Config!$C$6+84 | P4: =Config!$C$6+91 | Q4: =Config!$C$6+98 | R4: =Config!$C$6+105 | S4: =Config!$C$6+112 | T4: =Config!$C$6+119 | U4: =Config!$C$6+126 | V4: =Config!$C$6+133 | W4: =Config!$C$6+140 | X4: =Config!$C$6+147 | Y4: =Config!$C$6+154 | Z4: =Config!$C$6+161 | AA4: =Config!$C$6+168 | AB4: =Config!$C$6+175
A5: Categoría | B5: Métrica | C5: 1 | D5: 2 | E5: 3 | F5: 4 | G5: 5 | H5: 6 | I5: 7 | J5: 8 | K5: 9 | L5: 10 | M5: 11 | N5: 12 | O5: 13 | P5: 14 | Q5: 15 | R5: 16 | S5: 17 | T5: 18 | U5: 19 | V5: 20 | W5: 21 | X5: 22 | Y5: 23 | Z5: 24 | AA5: 25 | AB5: 26 | AC5: Promedio | AD5: Mediana | AE5: Mejor | AF5: Peor
A6: Semana con datos (1 = sí) | C6: =IF(SUMIFS(Diario!$C$6:$C$371,Diario!$B$6:$B$371,C$5)+SUMIFS(Diario!$H$6:$H$371,Diario!$B$6:$B$371,C$5)>0,1,0) | D6: =IF(SUMIFS(Diario!$C$6:$C$371,Diario!$B$6:$B$371,D$5)+SUMIFS(Diario!$H$6:$H$371,Diario!$B$6:$B$371,D$5)>0,1,0) | E6: =IF(SUMIFS(Diario!$C$6:$C$371,Diario!$B$6:$B$371,E$5)+SUMIFS(Diario!$H$6:$H$371,Diario!$B$6:$B$371,E$5)>0,1,0) | F6: =IF(SUMIFS(Diario!$C$6:$C$371,Diario!$B$6:$B$371,F$5)+SUMIFS(Diario!$H$6:$H$371,Diario!$B$6:$B$371,F$5)>0,1,0) | G6: =IF(SUMIFS(Diario!$C$6:$C$371,Diario!$B$6:$B$371,G$5)+SUMIFS(Diario!$H$6:$H$371,Diario!$B$6:$B$371,G$5)>0,1,0) | H6: =IF(SUMIFS(Diario!$C$6:$C$371,Diario!$B$6:$B$371,H$5)+SUMIFS(Diario!$H$6:$H$371,Diario!$B$6:$B$371,H$5)>0,1,0) | I6: =IF(SUMIFS(Diario!$C$6:$C$371,Diario!$B$6:$B$371,I$5)+SUMIFS(Diario!$H$6:$H$371,Diario!$B$6:$B$371,I$5)>0,1,0) | J6: =IF(SUMIFS(Diario!$C$6:$C$371,Diario!$B$6:$B$371,J$5)+SUMIFS(Diario!$H$6:$H$371,Diario!$B$6:$B$371,J$5)>0,1,0) | ... AB6: =IF(SUMIFS(Diario!$C$6:$C$371,Diario!$B$6:$B$371,AB$5)+SUMIFS(Diario!$H$6:$H$371,Diario!$B$6:$B$371,AB$5)>0,1,0)
A7: Número de semana si tiene datos | C7: =IF(C6=1,C$5,0) | D7: =IF(D6=1,D$5,0) | E7: =IF(E6=1,E$5,0) | F7: =IF(F6=1,F$5,0) | G7: =IF(G6=1,G$5,0) | H7: =IF(H6=1,H$5,0) | I7: =IF(I6=1,I$5,0) | J7: =IF(J6=1,J$5,0) | ... AB7: =IF(AB6=1,AB$5,0)
A9: 1. Anuncios
A10: Anuncios | B10: Inversión en publicidad (USD) | C10: =IF(C6=0,"",SUMIFS(Diario!$C$6:$C$371,Diario!$B$6:$B$371,C$5)) | D10: =IF(D6=0,"",SUMIFS(Diario!$C$6:$C$371,Diario!$B$6:$B$371,D$5)) | E10: =IF(E6=0,"",SUMIFS(Diario!$C$6:$C$371,Diario!$B$6:$B$371,E$5)) | F10: =IF(F6=0,"",SUMIFS(Diario!$C$6:$C$371,Diario!$B$6:$B$371,F$5)) | G10: =IF(G6=0,"",SUMIFS(Diario!$C$6:$C$371,Diario!$B$6:$B$371,G$5)) | H10: =IF(H6=0,"",SUMIFS(Diario!$C$6:$C$371,Diario!$B$6:$B$371,H$5)) | I10: =IF(I6=0,"",SUMIFS(Diario!$C$6:$C$371,Diario!$B$6:$B$371,I$5)) | J10: =IF(J6=0,"",SUMIFS(Diario!$C$6:$C$371,Diario!$B$6:$B$371,J$5)) | ... AB10: =IF(AB6=0,"",SUMIFS(Diario!$C$6:$C$371,Diario!$B$6:$B$371,AB$5)) | AC10: =IFERROR(AVERAGE(C10:AB10),"") | AD10: =IFERROR(MEDIAN(C10:AB10),"") | AE10: =IFERROR(MAX(C10:AB10),"") | AF10: =IFERROR(MIN(C10:AB10),"")
A11: Anuncios | B11: Impresiones | C11: =IF(C6=0,"",SUMIFS(Diario!$D$6:$D$371,Diario!$B$6:$B$371,C$5)) | D11: =IF(D6=0,"",SUMIFS(Diario!$D$6:$D$371,Diario!$B$6:$B$371,D$5)) | E11: =IF(E6=0,"",SUMIFS(Diario!$D$6:$D$371,Diario!$B$6:$B$371,E$5)) | F11: =IF(F6=0,"",SUMIFS(Diario!$D$6:$D$371,Diario!$B$6:$B$371,F$5)) | G11: =IF(G6=0,"",SUMIFS(Diario!$D$6:$D$371,Diario!$B$6:$B$371,G$5)) | H11: =IF(H6=0,"",SUMIFS(Diario!$D$6:$D$371,Diario!$B$6:$B$371,H$5)) | I11: =IF(I6=0,"",SUMIFS(Diario!$D$6:$D$371,Diario!$B$6:$B$371,I$5)) | J11: =IF(J6=0,"",SUMIFS(Diario!$D$6:$D$371,Diario!$B$6:$B$371,J$5)) | ... AB11: =IF(AB6=0,"",SUMIFS(Diario!$D$6:$D$371,Diario!$B$6:$B$371,AB$5)) | AC11: =IFERROR(AVERAGE(C11:AB11),"") | AD11: =IFERROR(MEDIAN(C11:AB11),"") | AE11: =IFERROR(MAX(C11:AB11),"") | AF11: =IFERROR(MIN(C11:AB11),"")
A12: Anuncios | B12: Alcance (personas únicas) | C12: =IF(C6=0,"",SUMIFS(Diario!$E$6:$E$371,Diario!$B$6:$B$371,C$5)) | D12: =IF(D6=0,"",SUMIFS(Diario!$E$6:$E$371,Diario!$B$6:$B$371,D$5)) | E12: =IF(E6=0,"",SUMIFS(Diario!$E$6:$E$371,Diario!$B$6:$B$371,E$5)) | F12: =IF(F6=0,"",SUMIFS(Diario!$E$6:$E$371,Diario!$B$6:$B$371,F$5)) | G12: =IF(G6=0,"",SUMIFS(Diario!$E$6:$E$371,Diario!$B$6:$B$371,G$5)) | H12: =IF(H6=0,"",SUMIFS(Diario!$E$6:$E$371,Diario!$B$6:$B$371,H$5)) | I12: =IF(I6=0,"",SUMIFS(Diario!$E$6:$E$371,Diario!$B$6:$B$371,I$5)) | J12: =IF(J6=0,"",SUMIFS(Diario!$E$6:$E$371,Diario!$B$6:$B$371,J$5)) | ... AB12: =IF(AB6=0,"",SUMIFS(Diario!$E$6:$E$371,Diario!$B$6:$B$371,AB$5)) | AC12: =IFERROR(AVERAGE(C12:AB12),"") | AD12: =IFERROR(MEDIAN(C12:AB12),"") | AE12: =IFERROR(MAX(C12:AB12),"") | AF12: =IFERROR(MIN(C12:AB12),"")
A13: Anuncios | B13: Clics en el enlace | C13: =IF(C6=0,"",SUMIFS(Diario!$F$6:$F$371,Diario!$B$6:$B$371,C$5)) | D13: =IF(D6=0,"",SUMIFS(Diario!$F$6:$F$371,Diario!$B$6:$B$371,D$5)) | E13: =IF(E6=0,"",SUMIFS(Diario!$F$6:$F$371,Diario!$B$6:$B$371,E$5)) | F13: =IF(F6=0,"",SUMIFS(Diario!$F$6:$F$371,Diario!$B$6:$B$371,F$5)) | G13: =IF(G6=0,"",SUMIFS(Diario!$F$6:$F$371,Diario!$B$6:$B$371,G$5)) | H13: =IF(H6=0,"",SUMIFS(Diario!$F$6:$F$371,Diario!$B$6:$B$371,H$5)) | I13: =IF(I6=0,"",SUMIFS(Diario!$F$6:$F$371,Diario!$B$6:$B$371,I$5)) | J13: =IF(J6=0,"",SUMIFS(Diario!$F$6:$F$371,Diario!$B$6:$B$371,J$5)) | ... AB13: =IF(AB6=0,"",SUMIFS(Diario!$F$6:$F$371,Diario!$B$6:$B$371,AB$5)) | AC13: =IFERROR(AVERAGE(C13:AB13),"") | AD13: =IFERROR(MEDIAN(C13:AB13),"") | AE13: =IFERROR(MAX(C13:AB13),"") | AF13: =IFERROR(MIN(C13:AB13),"")
A14: Anuncios | B14: Visitas a la página | C14: =IF(C6=0,"",SUMIFS(Diario!$G$6:$G$371,Diario!$B$6:$B$371,C$5)) | D14: =IF(D6=0,"",SUMIFS(Diario!$G$6:$G$371,Diario!$B$6:$B$371,D$5)) | E14: =IF(E6=0,"",SUMIFS(Diario!$G$6:$G$371,Diario!$B$6:$B$371,E$5)) | F14: =IF(F6=0,"",SUMIFS(Diario!$G$6:$G$371,Diario!$B$6:$B$371,F$5)) | G14: =IF(G6=0,"",SUMIFS(Diario!$G$6:$G$371,Diario!$B$6:$B$371,G$5)) | H14: =IF(H6=0,"",SUMIFS(Diario!$G$6:$G$371,Diario!$B$6:$B$371,H$5)) | I14: =IF(I6=0,"",SUMIFS(Diario!$G$6:$G$371,Diario!$B$6:$B$371,I$5)) | J14: =IF(J6=0,"",SUMIFS(Diario!$G$6:$G$371,Diario!$B$6:$B$371,J$5)) | ... AB14: =IF(AB6=0,"",SUMIFS(Diario!$G$6:$G$371,Diario!$B$6:$B$371,AB$5)) | AC14: =IFERROR(AVERAGE(C14:AB14),"") | AD14: =IFERROR(MEDIAN(C14:AB14),"") | AE14: =IFERROR(MAX(C14:AB14),"") | AF14: =IFERROR(MIN(C14:AB14),"")
A15: Anuncios | B15: CPM | C15: =IF(C6=0,"",IFERROR(C10/C11*1000,0)) | D15: =IF(D6=0,"",IFERROR(D10/D11*1000,0)) | E15: =IF(E6=0,"",IFERROR(E10/E11*1000,0)) | F15: =IF(F6=0,"",IFERROR(F10/F11*1000,0)) | G15: =IF(G6=0,"",IFERROR(G10/G11*1000,0)) | H15: =IF(H6=0,"",IFERROR(H10/H11*1000,0)) | I15: =IF(I6=0,"",IFERROR(I10/I11*1000,0)) | J15: =IF(J6=0,"",IFERROR(J10/J11*1000,0)) | ... AB15: =IF(AB6=0,"",IFERROR(AB10/AB11*1000,0)) | AC15: =IFERROR(AVERAGE(C15:AB15),"") | AD15: =IFERROR(MEDIAN(C15:AB15),"") | AE15: =IFERROR(MIN(C15:AB15),"") | AF15: =IFERROR(MAX(C15:AB15),"")
A16: Anuncios | B16: Frecuencia | C16: =IF(C6=0,"",IFERROR(C11/C12,0)) | D16: =IF(D6=0,"",IFERROR(D11/D12,0)) | E16: =IF(E6=0,"",IFERROR(E11/E12,0)) | F16: =IF(F6=0,"",IFERROR(F11/F12,0)) | G16: =IF(G6=0,"",IFERROR(G11/G12,0)) | H16: =IF(H6=0,"",IFERROR(H11/H12,0)) | I16: =IF(I6=0,"",IFERROR(I11/I12,0)) | J16: =IF(J6=0,"",IFERROR(J11/J12,0)) | ... AB16: =IF(AB6=0,"",IFERROR(AB11/AB12,0)) | AC16: =IFERROR(AVERAGE(C16:AB16),"") | AD16: =IFERROR(MEDIAN(C16:AB16),"") | AE16: =IFERROR(MIN(C16:AB16),"") | AF16: =IFERROR(MAX(C16:AB16),"")
A17: Anuncios | B17: CTR al enlace | C17: =IF(C6=0,"",IFERROR(C13/C11,0)) | D17: =IF(D6=0,"",IFERROR(D13/D11,0)) | E17: =IF(E6=0,"",IFERROR(E13/E11,0)) | F17: =IF(F6=0,"",IFERROR(F13/F11,0)) | G17: =IF(G6=0,"",IFERROR(G13/G11,0)) | H17: =IF(H6=0,"",IFERROR(H13/H11,0)) | I17: =IF(I6=0,"",IFERROR(I13/I11,0)) | J17: =IF(J6=0,"",IFERROR(J13/J11,0)) | ... AB17: =IF(AB6=0,"",IFERROR(AB13/AB11,0)) | AC17: =IFERROR(AVERAGE(C17:AB17),"") | AD17: =IFERROR(MEDIAN(C17:AB17),"") | AE17: =IFERROR(MAX(C17:AB17),"") | AF17: =IFERROR(MIN(C17:AB17),"")
A18: Anuncios | B18: CPC (por clic en el enlace) | C18: =IF(C6=0,"",IFERROR(C10/C13,0)) | D18: =IF(D6=0,"",IFERROR(D10/D13,0)) | E18: =IF(E6=0,"",IFERROR(E10/E13,0)) | F18: =IF(F6=0,"",IFERROR(F10/F13,0)) | G18: =IF(G6=0,"",IFERROR(G10/G13,0)) | H18: =IF(H6=0,"",IFERROR(H10/H13,0)) | I18: =IF(I6=0,"",IFERROR(I10/I13,0)) | J18: =IF(J6=0,"",IFERROR(J10/J13,0)) | ... AB18: =IF(AB6=0,"",IFERROR(AB10/AB13,0)) | AC18: =IFERROR(AVERAGE(C18:AB18),"") | AD18: =IFERROR(MEDIAN(C18:AB18),"") | AE18: =IFERROR(MIN(C18:AB18),"") | AF18: =IFERROR(MAX(C18:AB18),"")
A19: Anuncios | B19: % clic → visita | C19: =IF(C6=0,"",IFERROR(C14/C13,0)) | D19: =IF(D6=0,"",IFERROR(D14/D13,0)) | E19: =IF(E6=0,"",IFERROR(E14/E13,0)) | F19: =IF(F6=0,"",IFERROR(F14/F13,0)) | G19: =IF(G6=0,"",IFERROR(G14/G13,0)) | H19: =IF(H6=0,"",IFERROR(H14/H13,0)) | I19: =IF(I6=0,"",IFERROR(I14/I13,0)) | J19: =IF(J6=0,"",IFERROR(J14/J13,0)) | ... AB19: =IF(AB6=0,"",IFERROR(AB14/AB13,0)) | AC19: =IFERROR(AVERAGE(C19:AB19),"") | AD19: =IFERROR(MEDIAN(C19:AB19),"") | AE19: =IFERROR(MAX(C19:AB19),"") | AF19: =IFERROR(MIN(C19:AB19),"")
A20: Anuncios | B20: Costo por visita | C20: =IF(C6=0,"",IFERROR(C10/C14,0)) | D20: =IF(D6=0,"",IFERROR(D10/D14,0)) | E20: =IF(E6=0,"",IFERROR(E10/E14,0)) | F20: =IF(F6=0,"",IFERROR(F10/F14,0)) | G20: =IF(G6=0,"",IFERROR(G10/G14,0)) | H20: =IF(H6=0,"",IFERROR(H10/H14,0)) | I20: =IF(I6=0,"",IFERROR(I10/I14,0)) | J20: =IF(J6=0,"",IFERROR(J10/J14,0)) | ... AB20: =IF(AB6=0,"",IFERROR(AB10/AB14,0)) | AC20: =IFERROR(AVERAGE(C20:AB20),"") | AD20: =IFERROR(MEDIAN(C20:AB20),"") | AE20: =IFERROR(MIN(C20:AB20),"") | AF20: =IFERROR(MAX(C20:AB20),"")
A21: Anuncios | B21: Visitas por cada 1.000 impresiones | C21: =IF(C6=0,"",IFERROR(C14/C11*1000,0)) | D21: =IF(D6=0,"",IFERROR(D14/D11*1000,0)) | E21: =IF(E6=0,"",IFERROR(E14/E11*1000,0)) | F21: =IF(F6=0,"",IFERROR(F14/F11*1000,0)) | G21: =IF(G6=0,"",IFERROR(G14/G11*1000,0)) | H21: =IF(H6=0,"",IFERROR(H14/H11*1000,0)) | I21: =IF(I6=0,"",IFERROR(I14/I11*1000,0)) | J21: =IF(J6=0,"",IFERROR(J14/J11*1000,0)) | ... AB21: =IF(AB6=0,"",IFERROR(AB14/AB11*1000,0)) | AC21: =IFERROR(AVERAGE(C21:AB21),"") | AD21: =IFERROR(MEDIAN(C21:AB21),"") | AE21: =IFERROR(MAX(C21:AB21),"") | AF21: =IFERROR(MIN(C21:AB21),"")
A23: 2. Página y leads
A24: Página y leads | B24: Leads | C24: =IF(C6=0,"",SUMIFS(Diario!$H$6:$H$371,Diario!$B$6:$B$371,C$5)) | D24: =IF(D6=0,"",SUMIFS(Diario!$H$6:$H$371,Diario!$B$6:$B$371,D$5)) | E24: =IF(E6=0,"",SUMIFS(Diario!$H$6:$H$371,Diario!$B$6:$B$371,E$5)) | F24: =IF(F6=0,"",SUMIFS(Diario!$H$6:$H$371,Diario!$B$6:$B$371,F$5)) | G24: =IF(G6=0,"",SUMIFS(Diario!$H$6:$H$371,Diario!$B$6:$B$371,G$5)) | H24: =IF(H6=0,"",SUMIFS(Diario!$H$6:$H$371,Diario!$B$6:$B$371,H$5)) | I24: =IF(I6=0,"",SUMIFS(Diario!$H$6:$H$371,Diario!$B$6:$B$371,I$5)) | J24: =IF(J6=0,"",SUMIFS(Diario!$H$6:$H$371,Diario!$B$6:$B$371,J$5)) | ... AB24: =IF(AB6=0,"",SUMIFS(Diario!$H$6:$H$371,Diario!$B$6:$B$371,AB$5)) | AC24: =IFERROR(AVERAGE(C24:AB24),"") | AD24: =IFERROR(MEDIAN(C24:AB24),"") | AE24: =IFERROR(MAX(C24:AB24),"") | AF24: =IFERROR(MIN(C24:AB24),"")
A25: Página y leads | B25: % visita → lead (conversión de la página) | C25: =IF(C6=0,"",IFERROR(C24/C14,0)) | D25: =IF(D6=0,"",IFERROR(D24/D14,0)) | E25: =IF(E6=0,"",IFERROR(E24/E14,0)) | F25: =IF(F6=0,"",IFERROR(F24/F14,0)) | G25: =IF(G6=0,"",IFERROR(G24/G14,0)) | H25: =IF(H6=0,"",IFERROR(H24/H14,0)) | I25: =IF(I6=0,"",IFERROR(I24/I14,0)) | J25: =IF(J6=0,"",IFERROR(J24/J14,0)) | ... AB25: =IF(AB6=0,"",IFERROR(AB24/AB14,0)) | AC25: =IFERROR(AVERAGE(C25:AB25),"") | AD25: =IFERROR(MEDIAN(C25:AB25),"") | AE25: =IFERROR(MAX(C25:AB25),"") | AF25: =IFERROR(MIN(C25:AB25),"")
A26: Página y leads | B26: CPL (costo por lead) | C26: =IF(C6=0,"",IFERROR(C10/C24,0)) | D26: =IF(D6=0,"",IFERROR(D10/D24,0)) | E26: =IF(E6=0,"",IFERROR(E10/E24,0)) | F26: =IF(F6=0,"",IFERROR(F10/F24,0)) | G26: =IF(G6=0,"",IFERROR(G10/G24,0)) | H26: =IF(H6=0,"",IFERROR(H10/H24,0)) | I26: =IF(I6=0,"",IFERROR(I10/I24,0)) | J26: =IF(J6=0,"",IFERROR(J10/J24,0)) | ... AB26: =IF(AB6=0,"",IFERROR(AB10/AB24,0)) | AC26: =IFERROR(AVERAGE(C26:AB26),"") | AD26: =IFERROR(MEDIAN(C26:AB26),"") | AE26: =IFERROR(MIN(C26:AB26),"") | AF26: =IFERROR(MAX(C26:AB26),"")
A27: Página y leads | B27: CPL como % del CPM (el umbral depende del nicho) | C27: =IF(C6=0,"",IFERROR(C26/C15,0)) | D27: =IF(D6=0,"",IFERROR(D26/D15,0)) | E27: =IF(E6=0,"",IFERROR(E26/E15,0)) | F27: =IF(F6=0,"",IFERROR(F26/F15,0)) | G27: =IF(G6=0,"",IFERROR(G26/G15,0)) | H27: =IF(H6=0,"",IFERROR(H26/H15,0)) | I27: =IF(I6=0,"",IFERROR(I26/I15,0)) | J27: =IF(J6=0,"",IFERROR(J26/J15,0)) | ... AB27: =IF(AB6=0,"",IFERROR(AB26/AB15,0)) | AC27: =IFERROR(AVERAGE(C27:AB27),"") | AD27: =IFERROR(MEDIAN(C27:AB27),"") | AE27: =IFERROR(MIN(C27:AB27),"") | AF27: =IFERROR(MAX(C27:AB27),"")
A28: Página y leads | B28: Leads por cada 1.000 impresiones | C28: =IF(C6=0,"",IFERROR(C24/C11*1000,0)) | D28: =IF(D6=0,"",IFERROR(D24/D11*1000,0)) | E28: =IF(E6=0,"",IFERROR(E24/E11*1000,0)) | F28: =IF(F6=0,"",IFERROR(F24/F11*1000,0)) | G28: =IF(G6=0,"",IFERROR(G24/G11*1000,0)) | H28: =IF(H6=0,"",IFERROR(H24/H11*1000,0)) | I28: =IF(I6=0,"",IFERROR(I24/I11*1000,0)) | J28: =IF(J6=0,"",IFERROR(J24/J11*1000,0)) | ... AB28: =IF(AB6=0,"",IFERROR(AB24/AB11*1000,0)) | AC28: =IFERROR(AVERAGE(C28:AB28),"") | AD28: =IFERROR(MEDIAN(C28:AB28),"") | AE28: =IFERROR(MAX(C28:AB28),"") | AF28: =IFERROR(MIN(C28:AB28),"")
A30: 3. Aplicación, agenda y llamada
A31: Aplicación, agenda y llamada | B31: Completan la aplicación | C31: =IF(C6=0,"",SUMIFS(Diario!$I$6:$I$371,Diario!$B$6:$B$371,C$5)) | D31: =IF(D6=0,"",SUMIFS(Diario!$I$6:$I$371,Diario!$B$6:$B$371,D$5)) | E31: =IF(E6=0,"",SUMIFS(Diario!$I$6:$I$371,Diario!$B$6:$B$371,E$5)) | F31: =IF(F6=0,"",SUMIFS(Diario!$I$6:$I$371,Diario!$B$6:$B$371,F$5)) | G31: =IF(G6=0,"",SUMIFS(Diario!$I$6:$I$371,Diario!$B$6:$B$371,G$5)) | H31: =IF(H6=0,"",SUMIFS(Diario!$I$6:$I$371,Diario!$B$6:$B$371,H$5)) | I31: =IF(I6=0,"",SUMIFS(Diario!$I$6:$I$371,Diario!$B$6:$B$371,I$5)) | J31: =IF(J6=0,"",SUMIFS(Diario!$I$6:$I$371,Diario!$B$6:$B$371,J$5)) | ... AB31: =IF(AB6=0,"",SUMIFS(Diario!$I$6:$I$371,Diario!$B$6:$B$371,AB$5)) | AC31: =IFERROR(AVERAGE(C31:AB31),"") | AD31: =IFERROR(MEDIAN(C31:AB31),"") | AE31: =IFERROR(MAX(C31:AB31),"") | AF31: =IFERROR(MIN(C31:AB31),"")
A32: Aplicación, agenda y llamada | B32: Califican | C32: =IF(C6=0,"",SUMIFS(Diario!$J$6:$J$371,Diario!$B$6:$B$371,C$5)) | D32: =IF(D6=0,"",SUMIFS(Diario!$J$6:$J$371,Diario!$B$6:$B$371,D$5)) | E32: =IF(E6=0,"",SUMIFS(Diario!$J$6:$J$371,Diario!$B$6:$B$371,E$5)) | F32: =IF(F6=0,"",SUMIFS(Diario!$J$6:$J$371,Diario!$B$6:$B$371,F$5)) | G32: =IF(G6=0,"",SUMIFS(Diario!$J$6:$J$371,Diario!$B$6:$B$371,G$5)) | H32: =IF(H6=0,"",SUMIFS(Diario!$J$6:$J$371,Diario!$B$6:$B$371,H$5)) | I32: =IF(I6=0,"",SUMIFS(Diario!$J$6:$J$371,Diario!$B$6:$B$371,I$5)) | J32: =IF(J6=0,"",SUMIFS(Diario!$J$6:$J$371,Diario!$B$6:$B$371,J$5)) | ... AB32: =IF(AB6=0,"",SUMIFS(Diario!$J$6:$J$371,Diario!$B$6:$B$371,AB$5)) | AC32: =IFERROR(AVERAGE(C32:AB32),"") | AD32: =IFERROR(MEDIAN(C32:AB32),"") | AE32: =IFERROR(MAX(C32:AB32),"") | AF32: =IFERROR(MIN(C32:AB32),"")
A33: Aplicación, agenda y llamada | B33: Agendan la llamada | C33: =IF(C6=0,"",SUMIFS(Diario!$K$6:$K$371,Diario!$B$6:$B$371,C$5)) | D33: =IF(D6=0,"",SUMIFS(Diario!$K$6:$K$371,Diario!$B$6:$B$371,D$5)) | E33: =IF(E6=0,"",SUMIFS(Diario!$K$6:$K$371,Diario!$B$6:$B$371,E$5)) | F33: =IF(F6=0,"",SUMIFS(Diario!$K$6:$K$371,Diario!$B$6:$B$371,F$5)) | G33: =IF(G6=0,"",SUMIFS(Diario!$K$6:$K$371,Diario!$B$6:$B$371,G$5)) | H33: =IF(H6=0,"",SUMIFS(Diario!$K$6:$K$371,Diario!$B$6:$B$371,H$5)) | I33: =IF(I6=0,"",SUMIFS(Diario!$K$6:$K$371,Diario!$B$6:$B$371,I$5)) | J33: =IF(J6=0,"",SUMIFS(Diario!$K$6:$K$371,Diario!$B$6:$B$371,J$5)) | ... AB33: =IF(AB6=0,"",SUMIFS(Diario!$K$6:$K$371,Diario!$B$6:$B$371,AB$5)) | AC33: =IFERROR(AVERAGE(C33:AB33),"") | AD33: =IFERROR(MEDIAN(C33:AB33),"") | AE33: =IFERROR(MAX(C33:AB33),"") | AF33: =IFERROR(MIN(C33:AB33),"")
A34: Aplicación, agenda y llamada | B34: Llamadas realizadas (show) | C34: =IF(C6=0,"",SUMIFS(Diario!$L$6:$L$371,Diario!$B$6:$B$371,C$5)) | D34: =IF(D6=0,"",SUMIFS(Diario!$L$6:$L$371,Diario!$B$6:$B$371,D$5)) | E34: =IF(E6=0,"",SUMIFS(Diario!$L$6:$L$371,Diario!$B$6:$B$371,E$5)) | F34: =IF(F6=0,"",SUMIFS(Diario!$L$6:$L$371,Diario!$B$6:$B$371,F$5)) | G34: =IF(G6=0,"",SUMIFS(Diario!$L$6:$L$371,Diario!$B$6:$B$371,G$5)) | H34: =IF(H6=0,"",SUMIFS(Diario!$L$6:$L$371,Diario!$B$6:$B$371,H$5)) | I34: =IF(I6=0,"",SUMIFS(Diario!$L$6:$L$371,Diario!$B$6:$B$371,I$5)) | J34: =IF(J6=0,"",SUMIFS(Diario!$L$6:$L$371,Diario!$B$6:$B$371,J$5)) | ... AB34: =IF(AB6=0,"",SUMIFS(Diario!$L$6:$L$371,Diario!$B$6:$B$371,AB$5)) | AC34: =IFERROR(AVERAGE(C34:AB34),"") | AD34: =IFERROR(MEDIAN(C34:AB34),"") | AE34: =IFERROR(MAX(C34:AB34),"") | AF34: =IFERROR(MIN(C34:AB34),"")
A35: Aplicación, agenda y llamada | B35: % lead → aplicación | C35: =IF(C6=0,"",IFERROR(C31/C24,0)) | D35: =IF(D6=0,"",IFERROR(D31/D24,0)) | E35: =IF(E6=0,"",IFERROR(E31/E24,0)) | F35: =IF(F6=0,"",IFERROR(F31/F24,0)) | G35: =IF(G6=0,"",IFERROR(G31/G24,0)) | H35: =IF(H6=0,"",IFERROR(H31/H24,0)) | I35: =IF(I6=0,"",IFERROR(I31/I24,0)) | J35: =IF(J6=0,"",IFERROR(J31/J24,0)) | ... AB35: =IF(AB6=0,"",IFERROR(AB31/AB24,0)) | AC35: =IFERROR(AVERAGE(C35:AB35),"") | AD35: =IFERROR(MEDIAN(C35:AB35),"") | AE35: =IFERROR(MAX(C35:AB35),"") | AF35: =IFERROR(MIN(C35:AB35),"")
A36: Aplicación, agenda y llamada | B36: % aplicación → calificado | C36: =IF(C6=0,"",IFERROR(C32/C31,0)) | D36: =IF(D6=0,"",IFERROR(D32/D31,0)) | E36: =IF(E6=0,"",IFERROR(E32/E31,0)) | F36: =IF(F6=0,"",IFERROR(F32/F31,0)) | G36: =IF(G6=0,"",IFERROR(G32/G31,0)) | H36: =IF(H6=0,"",IFERROR(H32/H31,0)) | I36: =IF(I6=0,"",IFERROR(I32/I31,0)) | J36: =IF(J6=0,"",IFERROR(J32/J31,0)) | ... AB36: =IF(AB6=0,"",IFERROR(AB32/AB31,0)) | AC36: =IFERROR(AVERAGE(C36:AB36),"") | AD36: =IFERROR(MEDIAN(C36:AB36),"") | AE36: =IFERROR(MAX(C36:AB36),"") | AF36: =IFERROR(MIN(C36:AB36),"")
A37: Aplicación, agenda y llamada | B37: % calificado → agenda | C37: =IF(C6=0,"",IFERROR(C33/C32,0)) | D37: =IF(D6=0,"",IFERROR(D33/D32,0)) | E37: =IF(E6=0,"",IFERROR(E33/E32,0)) | F37: =IF(F6=0,"",IFERROR(F33/F32,0)) | G37: =IF(G6=0,"",IFERROR(G33/G32,0)) | H37: =IF(H6=0,"",IFERROR(H33/H32,0)) | I37: =IF(I6=0,"",IFERROR(I33/I32,0)) | J37: =IF(J6=0,"",IFERROR(J33/J32,0)) | ... AB37: =IF(AB6=0,"",IFERROR(AB33/AB32,0)) | AC37: =IFERROR(AVERAGE(C37:AB37),"") | AD37: =IFERROR(MEDIAN(C37:AB37),"") | AE37: =IFERROR(MAX(C37:AB37),"") | AF37: =IFERROR(MIN(C37:AB37),"")
A38: Aplicación, agenda y llamada | B38: Costo por agenda | C38: =IF(C6=0,"",IFERROR(C10/C33,0)) | D38: =IF(D6=0,"",IFERROR(D10/D33,0)) | E38: =IF(E6=0,"",IFERROR(E10/E33,0)) | F38: =IF(F6=0,"",IFERROR(F10/F33,0)) | G38: =IF(G6=0,"",IFERROR(G10/G33,0)) | H38: =IF(H6=0,"",IFERROR(H10/H33,0)) | I38: =IF(I6=0,"",IFERROR(I10/I33,0)) | J38: =IF(J6=0,"",IFERROR(J10/J33,0)) | ... AB38: =IF(AB6=0,"",IFERROR(AB10/AB33,0)) | AC38: =IFERROR(AVERAGE(C38:AB38),"") | AD38: =IFERROR(MEDIAN(C38:AB38),"") | AE38: =IFERROR(MIN(C38:AB38),"") | AF38: =IFERROR(MAX(C38:AB38),"")
A39: Aplicación, agenda y llamada | B39: % agenda → llamada (show) | C39: =IF(C6=0,"",IFERROR(C34/C33,0)) | D39: =IF(D6=0,"",IFERROR(D34/D33,0)) | E39: =IF(E6=0,"",IFERROR(E34/E33,0)) | F39: =IF(F6=0,"",IFERROR(F34/F33,0)) | G39: =IF(G6=0,"",IFERROR(G34/G33,0)) | H39: =IF(H6=0,"",IFERROR(H34/H33,0)) | I39: =IF(I6=0,"",IFERROR(I34/I33,0)) | J39: =IF(J6=0,"",IFERROR(J34/J33,0)) | ... AB39: =IF(AB6=0,"",IFERROR(AB34/AB33,0)) | AC39: =IFERROR(AVERAGE(C39:AB39),"") | AD39: =IFERROR(MEDIAN(C39:AB39),"") | AE39: =IFERROR(MAX(C39:AB39),"") | AF39: =IFERROR(MIN(C39:AB39),"")
A41: 4. Ventas y cobranza
A42: Ventas y cobranza | B42: Compran el programa | C42: =IF(C6=0,"",SUMIFS(Diario!$M$6:$M$371,Diario!$B$6:$B$371,C$5)) | D42: =IF(D6=0,"",SUMIFS(Diario!$M$6:$M$371,Diario!$B$6:$B$371,D$5)) | E42: =IF(E6=0,"",SUMIFS(Diario!$M$6:$M$371,Diario!$B$6:$B$371,E$5)) | F42: =IF(F6=0,"",SUMIFS(Diario!$M$6:$M$371,Diario!$B$6:$B$371,F$5)) | G42: =IF(G6=0,"",SUMIFS(Diario!$M$6:$M$371,Diario!$B$6:$B$371,G$5)) | H42: =IF(H6=0,"",SUMIFS(Diario!$M$6:$M$371,Diario!$B$6:$B$371,H$5)) | I42: =IF(I6=0,"",SUMIFS(Diario!$M$6:$M$371,Diario!$B$6:$B$371,I$5)) | J42: =IF(J6=0,"",SUMIFS(Diario!$M$6:$M$371,Diario!$B$6:$B$371,J$5)) | ... AB42: =IF(AB6=0,"",SUMIFS(Diario!$M$6:$M$371,Diario!$B$6:$B$371,AB$5)) | AC42: =IFERROR(AVERAGE(C42:AB42),"") | AD42: =IFERROR(MEDIAN(C42:AB42),"") | AE42: =IFERROR(MAX(C42:AB42),"") | AF42: =IFERROR(MIN(C42:AB42),"")
A43: Ventas y cobranza | B43: Toman el downsell | C43: =IF(C6=0,"",SUMIFS(Diario!$N$6:$N$371,Diario!$B$6:$B$371,C$5)) | D43: =IF(D6=0,"",SUMIFS(Diario!$N$6:$N$371,Diario!$B$6:$B$371,D$5)) | E43: =IF(E6=0,"",SUMIFS(Diario!$N$6:$N$371,Diario!$B$6:$B$371,E$5)) | F43: =IF(F6=0,"",SUMIFS(Diario!$N$6:$N$371,Diario!$B$6:$B$371,F$5)) | G43: =IF(G6=0,"",SUMIFS(Diario!$N$6:$N$371,Diario!$B$6:$B$371,G$5)) | H43: =IF(H6=0,"",SUMIFS(Diario!$N$6:$N$371,Diario!$B$6:$B$371,H$5)) | I43: =IF(I6=0,"",SUMIFS(Diario!$N$6:$N$371,Diario!$B$6:$B$371,I$5)) | J43: =IF(J6=0,"",SUMIFS(Diario!$N$6:$N$371,Diario!$B$6:$B$371,J$5)) | ... AB43: =IF(AB6=0,"",SUMIFS(Diario!$N$6:$N$371,Diario!$B$6:$B$371,AB$5)) | AC43: =IFERROR(AVERAGE(C43:AB43),"") | AD43: =IFERROR(MEDIAN(C43:AB43),"") | AE43: =IFERROR(MAX(C43:AB43),"") | AF43: =IFERROR(MIN(C43:AB43),"")
A44: Ventas y cobranza | B44: % llamada → venta (cierre) | C44: =IF(C6=0,"",IFERROR(C42/C34,0)) | D44: =IF(D6=0,"",IFERROR(D42/D34,0)) | E44: =IF(E6=0,"",IFERROR(E42/E34,0)) | F44: =IF(F6=0,"",IFERROR(F42/F34,0)) | G44: =IF(G6=0,"",IFERROR(G42/G34,0)) | H44: =IF(H6=0,"",IFERROR(H42/H34,0)) | I44: =IF(I6=0,"",IFERROR(I42/I34,0)) | J44: =IF(J6=0,"",IFERROR(J42/J34,0)) | ... AB44: =IF(AB6=0,"",IFERROR(AB42/AB34,0)) | AC44: =IFERROR(AVERAGE(C44:AB44),"") | AD44: =IFERROR(MEDIAN(C44:AB44),"") | AE44: =IFERROR(MAX(C44:AB44),"") | AF44: =IFERROR(MIN(C44:AB44),"")
A45: Ventas y cobranza | B45: % lead → venta | C45: =IF(C6=0,"",IFERROR(C42/C24,0)) | D45: =IF(D6=0,"",IFERROR(D42/D24,0)) | E45: =IF(E6=0,"",IFERROR(E42/E24,0)) | F45: =IF(F6=0,"",IFERROR(F42/F24,0)) | G45: =IF(G6=0,"",IFERROR(G42/G24,0)) | H45: =IF(H6=0,"",IFERROR(H42/H24,0)) | I45: =IF(I6=0,"",IFERROR(I42/I24,0)) | J45: =IF(J6=0,"",IFERROR(J42/J24,0)) | ... AB45: =IF(AB6=0,"",IFERROR(AB42/AB24,0)) | AC45: =IFERROR(AVERAGE(C45:AB45),"") | AD45: =IFERROR(MEDIAN(C45:AB45),"") | AE45: =IFERROR(MAX(C45:AB45),"") | AF45: =IFERROR(MIN(C45:AB45),"")
A46: Ventas y cobranza | B46: CAC (costo por venta) | C46: =IF(C6=0,"",IFERROR(C10/C42,0)) | D46: =IF(D6=0,"",IFERROR(D10/D42,0)) | E46: =IF(E6=0,"",IFERROR(E10/E42,0)) | F46: =IF(F6=0,"",IFERROR(F10/F42,0)) | G46: =IF(G6=0,"",IFERROR(G10/G42,0)) | H46: =IF(H6=0,"",IFERROR(H10/H42,0)) | I46: =IF(I6=0,"",IFERROR(I10/I42,0)) | J46: =IF(J6=0,"",IFERROR(J10/J42,0)) | ... AB46: =IF(AB6=0,"",IFERROR(AB10/AB42,0)) | AC46: =IFERROR(AVERAGE(C46:AB46),"") | AD46: =IFERROR(MEDIAN(C46:AB46),"") | AE46: =IFERROR(MIN(C46:AB46),"") | AF46: =IFERROR(MAX(C46:AB46),"")
A47: Ventas y cobranza | B47: Facturado a precio de lista | C47: =IF(C6=0,"",IFERROR(C42*Config!$C$7+C43*Config!$C$8,0)) | D47: =IF(D6=0,"",IFERROR(D42*Config!$C$7+D43*Config!$C$8,0)) | E47: =IF(E6=0,"",IFERROR(E42*Config!$C$7+E43*Config!$C$8,0)) | F47: =IF(F6=0,"",IFERROR(F42*Config!$C$7+F43*Config!$C$8,0)) | G47: =IF(G6=0,"",IFERROR(G42*Config!$C$7+G43*Config!$C$8,0)) | H47: =IF(H6=0,"",IFERROR(H42*Config!$C$7+H43*Config!$C$8,0)) | I47: =IF(I6=0,"",IFERROR(I42*Config!$C$7+I43*Config!$C$8,0)) | J47: =IF(J6=0,"",IFERROR(J42*Config!$C$7+J43*Config!$C$8,0)) | ... AB47: =IF(AB6=0,"",IFERROR(AB42*Config!$C$7+AB43*Config!$C$8,0)) | AC47: =IFERROR(AVERAGE(C47:AB47),"") | AD47: =IFERROR(MEDIAN(C47:AB47),"") | AE47: =IFERROR(MAX(C47:AB47),"") | AF47: =IFERROR(MIN(C47:AB47),"")
A48: Ventas y cobranza | B48: Cash cobrado ese día (USD) | C48: =IF(C6=0,"",SUMIFS(Diario!$O$6:$O$371,Diario!$B$6:$B$371,C$5)) | D48: =IF(D6=0,"",SUMIFS(Diario!$O$6:$O$371,Diario!$B$6:$B$371,D$5)) | E48: =IF(E6=0,"",SUMIFS(Diario!$O$6:$O$371,Diario!$B$6:$B$371,E$5)) | F48: =IF(F6=0,"",SUMIFS(Diario!$O$6:$O$371,Diario!$B$6:$B$371,F$5)) | G48: =IF(G6=0,"",SUMIFS(Diario!$O$6:$O$371,Diario!$B$6:$B$371,G$5)) | H48: =IF(H6=0,"",SUMIFS(Diario!$O$6:$O$371,Diario!$B$6:$B$371,H$5)) | I48: =IF(I6=0,"",SUMIFS(Diario!$O$6:$O$371,Diario!$B$6:$B$371,I$5)) | J48: =IF(J6=0,"",SUMIFS(Diario!$O$6:$O$371,Diario!$B$6:$B$371,J$5)) | ... AB48: =IF(AB6=0,"",SUMIFS(Diario!$O$6:$O$371,Diario!$B$6:$B$371,AB$5)) | AC48: =IFERROR(AVERAGE(C48:AB48),"") | AD48: =IFERROR(MEDIAN(C48:AB48),"") | AE48: =IFERROR(MAX(C48:AB48),"") | AF48: =IFERROR(MIN(C48:AB48),"")
A49: Ventas y cobranza | B49: Cash cobrado (real, o estimado con el % del primer mes) | C49: =IF(C6=0,"",IFERROR(IF(C48>0,C48,C47*Config!$C$9),0)) | D49: =IF(D6=0,"",IFERROR(IF(D48>0,D48,D47*Config!$C$9),0)) | E49: =IF(E6=0,"",IFERROR(IF(E48>0,E48,E47*Config!$C$9),0)) | F49: =IF(F6=0,"",IFERROR(IF(F48>0,F48,F47*Config!$C$9),0)) | G49: =IF(G6=0,"",IFERROR(IF(G48>0,G48,G47*Config!$C$9),0)) | H49: =IF(H6=0,"",IFERROR(IF(H48>0,H48,H47*Config!$C$9),0)) | I49: =IF(I6=0,"",IFERROR(IF(I48>0,I48,I47*Config!$C$9),0)) | J49: =IF(J6=0,"",IFERROR(IF(J48>0,J48,J47*Config!$C$9),0)) | ... AB49: =IF(AB6=0,"",IFERROR(IF(AB48>0,AB48,AB47*Config!$C$9),0)) | AC49: =IFERROR(AVERAGE(C49:AB49),"") | AD49: =IFERROR(MEDIAN(C49:AB49),"") | AE49: =IFERROR(MAX(C49:AB49),"") | AF49: =IFERROR(MIN(C49:AB49),"")
A51: 5. Resultado
A52: Resultado | B52: Cash neto (después de comisiones, closers y reembolsos) | C52: =IF(C6=0,"",IFERROR(C49*(1-Config!$C$10-Config!$C$11-Config!$C$12),0)) | D52: =IF(D6=0,"",IFERROR(D49*(1-Config!$C$10-Config!$C$11-Config!$C$12),0)) | E52: =IF(E6=0,"",IFERROR(E49*(1-Config!$C$10-Config!$C$11-Config!$C$12),0)) | F52: =IF(F6=0,"",IFERROR(F49*(1-Config!$C$10-Config!$C$11-Config!$C$12),0)) | G52: =IF(G6=0,"",IFERROR(G49*(1-Config!$C$10-Config!$C$11-Config!$C$12),0)) | H52: =IF(H6=0,"",IFERROR(H49*(1-Config!$C$10-Config!$C$11-Config!$C$12),0)) | I52: =IF(I6=0,"",IFERROR(I49*(1-Config!$C$10-Config!$C$11-Config!$C$12),0)) | J52: =IF(J6=0,"",IFERROR(J49*(1-Config!$C$10-Config!$C$11-Config!$C$12),0)) | ... AB52: =IF(AB6=0,"",IFERROR(AB49*(1-Config!$C$10-Config!$C$11-Config!$C$12),0)) | AC52: =IFERROR(AVERAGE(C52:AB52),"") | AD52: =IFERROR(MEDIAN(C52:AB52),"") | AE52: =IFERROR(MAX(C52:AB52),"") | AF52: =IFERROR(MIN(C52:AB52),"")
A53: Resultado | B53: Ganancia de caja (cash neto − pauta − fijos) | C53: =IF(C6=0,"",IFERROR(C52-C10-Config!$C$13*7,0)) | D53: =IF(D6=0,"",IFERROR(D52-D10-Config!$C$13*7,0)) | E53: =IF(E6=0,"",IFERROR(E52-E10-Config!$C$13*7,0)) | F53: =IF(F6=0,"",IFERROR(F52-F10-Config!$C$13*7,0)) | G53: =IF(G6=0,"",IFERROR(G52-G10-Config!$C$13*7,0)) | H53: =IF(H6=0,"",IFERROR(H52-H10-Config!$C$13*7,0)) | I53: =IF(I6=0,"",IFERROR(I52-I10-Config!$C$13*7,0)) | J53: =IF(J6=0,"",IFERROR(J52-J10-Config!$C$13*7,0)) | ... AB53: =IF(AB6=0,"",IFERROR(AB52-AB10-Config!$C$13*7,0)) | AC53: =IFERROR(AVERAGE(C53:AB53),"") | AD53: =IFERROR(MEDIAN(C53:AB53),"") | AE53: =IFERROR(MAX(C53:AB53),"") | AF53: =IFERROR(MIN(C53:AB53),"")
A54: Resultado | B54: ROAS sobre cash neto | C54: =IF(C6=0,"",IFERROR(C52/C10,0)) | D54: =IF(D6=0,"",IFERROR(D52/D10,0)) | E54: =IF(E6=0,"",IFERROR(E52/E10,0)) | F54: =IF(F6=0,"",IFERROR(F52/F10,0)) | G54: =IF(G6=0,"",IFERROR(G52/G10,0)) | H54: =IF(H6=0,"",IFERROR(H52/H10,0)) | I54: =IF(I6=0,"",IFERROR(I52/I10,0)) | J54: =IF(J6=0,"",IFERROR(J52/J10,0)) | ... AB54: =IF(AB6=0,"",IFERROR(AB52/AB10,0)) | AC54: =IFERROR(AVERAGE(C54:AB54),"") | AD54: =IFERROR(MEDIAN(C54:AB54),"") | AE54: =IFERROR(MAX(C54:AB54),"") | AF54: =IFERROR(MIN(C54:AB54),"")
A55: Resultado | B55: ROAS sobre facturado (no decidas con este) | C55: =IF(C6=0,"",IFERROR(C47/C10,0)) | D55: =IF(D6=0,"",IFERROR(D47/D10,0)) | E55: =IF(E6=0,"",IFERROR(E47/E10,0)) | F55: =IF(F6=0,"",IFERROR(F47/F10,0)) | G55: =IF(G6=0,"",IFERROR(G47/G10,0)) | H55: =IF(H6=0,"",IFERROR(H47/H10,0)) | I55: =IF(I6=0,"",IFERROR(I47/I10,0)) | J55: =IF(J6=0,"",IFERROR(J47/J10,0)) | ... AB55: =IF(AB6=0,"",IFERROR(AB47/AB10,0)) | AC55: =IFERROR(AVERAGE(C55:AB55),"") | AD55: =IFERROR(MEDIAN(C55:AB55),"") | AE55: =IFERROR(MAX(C55:AB55),"") | AF55: =IFERROR(MIN(C55:AB55),"")
A56: Resultado | B56: Ganancia por visita (la métrica más valiosa) | C56: =IF(C6=0,"",IFERROR(C53/C14,0)) | D56: =IF(D6=0,"",IFERROR(D53/D14,0)) | E56: =IF(E6=0,"",IFERROR(E53/E14,0)) | F56: =IF(F6=0,"",IFERROR(F53/F14,0)) | G56: =IF(G6=0,"",IFERROR(G53/G14,0)) | H56: =IF(H6=0,"",IFERROR(H53/H14,0)) | I56: =IF(I6=0,"",IFERROR(I53/I14,0)) | J56: =IF(J6=0,"",IFERROR(J53/J14,0)) | ... AB56: =IF(AB6=0,"",IFERROR(AB53/AB14,0)) | AC56: =IFERROR(AVERAGE(C56:AB56),"") | AD56: =IFERROR(MEDIAN(C56:AB56),"") | AE56: =IFERROR(MAX(C56:AB56),"") | AF56: =IFERROR(MIN(C56:AB56),"")
A57: Resultado | B57: Margen por visita (ganancia por visita ÷ costo por visita) | C57: =IF(C6=0,"",IFERROR(C56/C20,0)) | D57: =IF(D6=0,"",IFERROR(D56/D20,0)) | E57: =IF(E6=0,"",IFERROR(E56/E20,0)) | F57: =IF(F6=0,"",IFERROR(F56/F20,0)) | G57: =IF(G6=0,"",IFERROR(G56/G20,0)) | H57: =IF(H6=0,"",IFERROR(H56/H20,0)) | I57: =IF(I6=0,"",IFERROR(I56/I20,0)) | J57: =IF(J6=0,"",IFERROR(J56/J20,0)) | ... AB57: =IF(AB6=0,"",IFERROR(AB56/AB20,0)) | AC57: =IFERROR(AVERAGE(C57:AB57),"") | AD57: =IFERROR(MEDIAN(C57:AB57),"") | AE57: =IFERROR(MAX(C57:AB57),"") | AF57: =IFERROR(MIN(C57:AB57),"")
A58: Resultado | B58: Ganancia por lead | C58: =IF(C6=0,"",IFERROR(C53/C24,0)) | D58: =IF(D6=0,"",IFERROR(D53/D24,0)) | E58: =IF(E6=0,"",IFERROR(E53/E24,0)) | F58: =IF(F6=0,"",IFERROR(F53/F24,0)) | G58: =IF(G6=0,"",IFERROR(G53/G24,0)) | H58: =IF(H6=0,"",IFERROR(H53/H24,0)) | I58: =IF(I6=0,"",IFERROR(I53/I24,0)) | J58: =IF(J6=0,"",IFERROR(J53/J24,0)) | ... AB58: =IF(AB6=0,"",IFERROR(AB53/AB24,0)) | AC58: =IFERROR(AVERAGE(C58:AB58),"") | AD58: =IFERROR(MEDIAN(C58:AB58),"") | AE58: =IFERROR(MAX(C58:AB58),"") | AF58: =IFERROR(MIN(C58:AB58),"")
A60: 6. Contra tu promedio: cada semana contra la mediana de tus 4 semanas anteriores (tolerancia en Config). Igual o mejor = VERDE · hasta la tolerancia peor = AMARILLO · más = ROJO
A61: Mediana 4 semanas anteriores | B61: Ganancia por visita (la métrica más valiosa) | D61: =IFERROR(MEDIAN(C56:C56),"") | E61: =IFERROR(MEDIAN(C56:D56),"") | F61: =IFERROR(MEDIAN(C56:E56),"") | G61: =IFERROR(MEDIAN(C56:F56),"") | H61: =IFERROR(MEDIAN(D56:G56),"") | I61: =IFERROR(MEDIAN(E56:H56),"") | J61: =IFERROR(MEDIAN(F56:I56),"") | K61: =IFERROR(MEDIAN(G56:J56),"") | L61: =IFERROR(MEDIAN(H56:K56),"") | M61: =IFERROR(MEDIAN(I56:L56),"") | N61: =IFERROR(MEDIAN(J56:M56),"") | ... AB61: =IFERROR(MEDIAN(X56:AA56),"")
A62: Semáforo | B62: Ganancia por visita (la métrica más valiosa) | C62: =IF(OR(C56="",C61=""),"",IF(C56<=0,"ROJO",IF(C56>=C61,"VERDE",IF(C56>=C61*(1-Config!$C$15),"AMARILLO","ROJO")))) | D62: =IF(OR(D56="",D61=""),"",IF(D56<=0,"ROJO",IF(D56>=D61,"VERDE",IF(D56>=D61*(1-Config!$C$15),"AMARILLO","ROJO")))) | E62: =IF(OR(E56="",E61=""),"",IF(E56<=0,"ROJO",IF(E56>=E61,"VERDE",IF(E56>=E61*(1-Config!$C$15),"AMARILLO","ROJO")))) | F62: =IF(OR(F56="",F61=""),"",IF(F56<=0,"ROJO",IF(F56>=F61,"VERDE",IF(F56>=F61*(1-Config!$C$15),"AMARILLO","ROJO")))) | G62: =IF(OR(G56="",G61=""),"",IF(G56<=0,"ROJO",IF(G56>=G61,"VERDE",IF(G56>=G61*(1-Config!$C$15),"AMARILLO","ROJO")))) | H62: =IF(OR(H56="",H61=""),"",IF(H56<=0,"ROJO",IF(H56>=H61,"VERDE",IF(H56>=H61*(1-Config!$C$15),"AMARILLO","ROJO")))) | I62: =IF(OR(I56="",I61=""),"",IF(I56<=0,"ROJO",IF(I56>=I61,"VERDE",IF(I56>=I61*(1-Config!$C$15),"AMARILLO","ROJO")))) | J62: =IF(OR(J56="",J61=""),"",IF(J56<=0,"ROJO",IF(J56>=J61,"VERDE",IF(J56>=J61*(1-Config!$C$15),"AMARILLO","ROJO")))) | ... AB62: =IF(OR(AB56="",AB61=""),"",IF(AB56<=0,"ROJO",IF(AB56>=AB61,"VERDE",IF(AB56>=AB61*(1-Config!$C$15),"AMARILLO","ROJO"))))
A63: Mediana 4 semanas anteriores | B63: Costo por visita | D63: =IFERROR(MEDIAN(C20:C20),"") | E63: =IFERROR(MEDIAN(C20:D20),"") | F63: =IFERROR(MEDIAN(C20:E20),"") | G63: =IFERROR(MEDIAN(C20:F20),"") | H63: =IFERROR(MEDIAN(D20:G20),"") | I63: =IFERROR(MEDIAN(E20:H20),"") | J63: =IFERROR(MEDIAN(F20:I20),"") | K63: =IFERROR(MEDIAN(G20:J20),"") | L63: =IFERROR(MEDIAN(H20:K20),"") | M63: =IFERROR(MEDIAN(I20:L20),"") | N63: =IFERROR(MEDIAN(J20:M20),"") | ... AB63: =IFERROR(MEDIAN(X20:AA20),"")
A64: Semáforo | B64: Costo por visita | C64: =IF(OR(C20="",C63=""),"",IF(C20<=C63,"VERDE",IF(C20<=C63*(1+Config!$C$15),"AMARILLO","ROJO"))) | D64: =IF(OR(D20="",D63=""),"",IF(D20<=D63,"VERDE",IF(D20<=D63*(1+Config!$C$15),"AMARILLO","ROJO"))) | E64: =IF(OR(E20="",E63=""),"",IF(E20<=E63,"VERDE",IF(E20<=E63*(1+Config!$C$15),"AMARILLO","ROJO"))) | F64: =IF(OR(F20="",F63=""),"",IF(F20<=F63,"VERDE",IF(F20<=F63*(1+Config!$C$15),"AMARILLO","ROJO"))) | G64: =IF(OR(G20="",G63=""),"",IF(G20<=G63,"VERDE",IF(G20<=G63*(1+Config!$C$15),"AMARILLO","ROJO"))) | H64: =IF(OR(H20="",H63=""),"",IF(H20<=H63,"VERDE",IF(H20<=H63*(1+Config!$C$15),"AMARILLO","ROJO"))) | I64: =IF(OR(I20="",I63=""),"",IF(I20<=I63,"VERDE",IF(I20<=I63*(1+Config!$C$15),"AMARILLO","ROJO"))) | J64: =IF(OR(J20="",J63=""),"",IF(J20<=J63,"VERDE",IF(J20<=J63*(1+Config!$C$15),"AMARILLO","ROJO"))) | ... AB64: =IF(OR(AB20="",AB63=""),"",IF(AB20<=AB63,"VERDE",IF(AB20<=AB63*(1+Config!$C$15),"AMARILLO","ROJO")))
A65: Mediana 4 semanas anteriores | B65: CPL (costo por lead) | D65: =IFERROR(MEDIAN(C26:C26),"") | E65: =IFERROR(MEDIAN(C26:D26),"") | F65: =IFERROR(MEDIAN(C26:E26),"") | G65: =IFERROR(MEDIAN(C26:F26),"") | H65: =IFERROR(MEDIAN(D26:G26),"") | I65: =IFERROR(MEDIAN(E26:H26),"") | J65: =IFERROR(MEDIAN(F26:I26),"") | K65: =IFERROR(MEDIAN(G26:J26),"") | L65: =IFERROR(MEDIAN(H26:K26),"") | M65: =IFERROR(MEDIAN(I26:L26),"") | N65: =IFERROR(MEDIAN(J26:M26),"") | ... AB65: =IFERROR(MEDIAN(X26:AA26),"")
A66: Semáforo | B66: CPL (costo por lead) | C66: =IF(OR(C26="",C65=""),"",IF(C26<=C65,"VERDE",IF(C26<=C65*(1+Config!$C$15),"AMARILLO","ROJO"))) | D66: =IF(OR(D26="",D65=""),"",IF(D26<=D65,"VERDE",IF(D26<=D65*(1+Config!$C$15),"AMARILLO","ROJO"))) | E66: =IF(OR(E26="",E65=""),"",IF(E26<=E65,"VERDE",IF(E26<=E65*(1+Config!$C$15),"AMARILLO","ROJO"))) | F66: =IF(OR(F26="",F65=""),"",IF(F26<=F65,"VERDE",IF(F26<=F65*(1+Config!$C$15),"AMARILLO","ROJO"))) | G66: =IF(OR(G26="",G65=""),"",IF(G26<=G65,"VERDE",IF(G26<=G65*(1+Config!$C$15),"AMARILLO","ROJO"))) | H66: =IF(OR(H26="",H65=""),"",IF(H26<=H65,"VERDE",IF(H26<=H65*(1+Config!$C$15),"AMARILLO","ROJO"))) | I66: =IF(OR(I26="",I65=""),"",IF(I26<=I65,"VERDE",IF(I26<=I65*(1+Config!$C$15),"AMARILLO","ROJO"))) | J66: =IF(OR(J26="",J65=""),"",IF(J26<=J65,"VERDE",IF(J26<=J65*(1+Config!$C$15),"AMARILLO","ROJO"))) | ... AB66: =IF(OR(AB26="",AB65=""),"",IF(AB26<=AB65,"VERDE",IF(AB26<=AB65*(1+Config!$C$15),"AMARILLO","ROJO")))
A67: Mediana 4 semanas anteriores | B67: CPL como % del CPM (el umbral depende del nicho) | D67: =IFERROR(MEDIAN(C27:C27),"") | E67: =IFERROR(MEDIAN(C27:D27),"") | F67: =IFERROR(MEDIAN(C27:E27),"") | G67: =IFERROR(MEDIAN(C27:F27),"") | H67: =IFERROR(MEDIAN(D27:G27),"") | I67: =IFERROR(MEDIAN(E27:H27),"") | J67: =IFERROR(MEDIAN(F27:I27),"") | K67: =IFERROR(MEDIAN(G27:J27),"") | L67: =IFERROR(MEDIAN(H27:K27),"") | M67: =IFERROR(MEDIAN(I27:L27),"") | N67: =IFERROR(MEDIAN(J27:M27),"") | ... AB67: =IFERROR(MEDIAN(X27:AA27),"")
